Workbook
Name circ: [1]Cover!$K$6
Name Circ: Cover!$K$6
Name Date: [2]WACC!$H$1
Name Days: #REF!
Name GVKey: ""
Name IQ_CH: 110000
Name IQ_CQ: 5000
Name IQ_CY: 10000
Name IQ_DAILY: 500000
Name IQ_FH: 100000
Name IQ_FQ: 500
Name IQ_FY: 1000
Name IQ_LTM: 2000
Name IQ_MONTH: 15000
Name IQ_NTM: 6000
Name IQ_WEEK: 50000
Name IQ_YTD: 3000
Name List: '[2]Input Tab'!$AD$15:$AD$19
Name SPSet: "current"
Name SPWS_WBID: "D37EBD5C-BA90-4B94-B2F1-78539D014FA9"

Sheet _CIQHiddenCacheSheet
A1: 26 | B1: BAABTAVMT0NBTAFI/////wFQZwAAAB9DSVEuTllTRTpULklRX0NPTVBBTllfTkFNRV9MT05HAQAAAIeHAQADAAAAEkFUJlQgSW5jLiAoTllTRTpUKQCSY69ibxHZCDz/0GJvEdkIL0NJUS5OWVNFOlQuSVFfVE9UQUxfUkVWLkZZMjAxNi4yMDIxLTA1LTA3Li4uVVNEAQAAAIeHAQACAAAABjE2Mzc4NgEIAAAABQAAAAExAQAAAAoxOTQ2MjQ2ODc1AwAAAAMxNjACAAAAAjI4BAAAAAEwBwAAAAg1LzcvMjAyMQgAAAAKMTIvMzEvMjAxNgkAAAABMJCKr2JvEdkI/A/SYm8R2QgvQ0lRLk5ZU0U6VC5JUV9UT1RBTF9SRVYuRlkyMDE3LjIwMjEtMDUtMDcuLi5VU0QBAAAAh4cBAAIAAAAGMTYwNTQ2AQgAAAAFAAAAATEBAAAACjIwMTYwNTg4MjYDAAAAAzE2MAIAAAACMjgEAAAAATAHAAAACDUvNy8yMDIxCAAAAAoxMi8zMS8yMDE3CQAAAAEwkIqvYm8R2QgF6dFibxHZCC9DSVEuTllTRTpULklRX1RPVEFMX1JFVi5GWTIwMTguMjAyMS0wNS0wNy4uLlVTRAEAAACHhwEAAgAAAAYxNzA3NTYBCAAAAAUAAAABMQEAAAAKMjA4MjI1MjQyOAMAAAADMTYwAgAAAAIyOAQAAAABMAcAAAAINS83LzIwMjEIAAAACjEyLzMxLzIwMTgJAAAAATCQiq9ibxHZCB6b0WJvEdkIL0NJUS5OWVNFOlQuSVFfVE9UQUxfUkVWLkZZMjAxOS4yMDIxLTA1LTA3Li4uVVNEAQAAAIeHAQACAAAABjE4MTE5MwEIAAAABQAAAAExAQAAAAoyMDgy | C1: MjUyNDM0AwAAAAMxNjACAAAAAjI4BAAAAAEwBwAAAAg1LzcvMjAyMQgAAAAKMTIvMzEvMjAxOQkAAAABMJCKr2JvEdkIF3TRYm8R2QgvQ0lRLk5ZU0U6VC5JUV9UT1RBTF9SRVYuRlkyMDIwLjIwMjEtMDUtMDcuLi5VU0QBAAAAh4cBAAIAAAAGMTcxNzYwAQgAAAAFAAAAATEBAAAACjIwODIyNTI0MjcDAAAAAzE2MAIAAAACMjgEAAAAATAHAAAACDUvNy8yMDIxCAAAAAoxMi8zMS8yMDIwCQAAAAEwkIqvYm8R2QgsJtFibxHZCC9DSVEuTllTRTpULklRX1RPVEFMX1JFVi5JUV9MVE0uMjAyMS0wNS0wNy4uLlVTRAEAAACHhwEAAgAAAAYxNzI5MjABCAAAAAUAAAABMQEAAAAKMjA5MDc3Mzc3NgMAAAADMTYwAgAAAAIyOAQAAAABMAcAAAAINS83LzIwMjEIAAAACTMvMzEvMjAyMQkAAAABMJCKr2JvEdkIQ9jQYm8R2QguQ0lRLk5ZU0U6VC5JUV9PUEVSX0lOQy5GWTIwMTYuMjAyMS0wNS0wNy4uLlVTRAEAAACHhwEAAgAAAAUyNDkwNQEIAAAABQAAAAExAQAAAAoxOTQ2MjQ2ODc1AwAAAAMxNjACAAAAAjIxBAAAAAEwBwAAAAg1LzcvMjAyMQgAAAAKMTIvMzEvMjAxNgkAAAABMJCKr2JvEdkI4TbSYm8R2QguQ0lRLk5ZU0U6VC5JUV9PUEVSX0lOQy5GWTIwMTcuMjAyMS0wNS0wNy4uLlVTRAEAAACHhwEAAgAAAAUyMzk5NQEIAAAABQAAAAExAQAAAAoyMDE2MDU4ODI2AwAAAAMxNjACAAAAAjIxBAAAAAEwBwAA | D1: AAg1LzcvMjAyMQgAAAAKMTIvMzEvMjAxNwkAAAABMJCKr2JvEdkIBenRYm8R2QguQ0lRLk5ZU0U6VC5JUV9PUEVSX0lOQy5GWTIwMTguMjAyMS0wNS0wNy4uLlVTRAEAAACHhwEAAgAAAAUzMTYxOAEIAAAABQAAAAExAQAAAAoyMDgyMjUyNDI4AwAAAAMxNjACAAAAAjIxBAAAAAEwBwAAAAg1LzcvMjAyMQgAAAAKMTIvMzEvMjAxOAkAAAABMJCKr2JvEdkIBcLRYm8R2QguQ0lRLk5ZU0U6VC5JUV9PUEVSX0lOQy5GWTIwMTkuMjAyMS0wNS0wNy4uLlVTRAEAAACHhwEAAgAAAAUyNzc0MQEIAAAABQAAAAExAQAAAAoyMDgyMjUyNDM0AwAAAAMxNjACAAAAAjIxBAAAAAEwBwAAAAg1LzcvMjAyMQgAAAAKMTIvMzEvMjAxOQkAAAABMJCKr2JvEdkIF3TRYm8R2QguQ0lRLk5ZU0U6VC5JUV9PUEVSX0lOQy5GWTIwMjAuMjAyMS0wNS0wNy4uLlVTRAEAAACHhwEAAgAAAAUyNTY1NgEIAAAABQAAAAExAQAAAAoyMDgyMjUyNDI3AwAAAAMxNjACAAAAAjIxBAAAAAEwBwAAAAg1LzcvMjAyMQgAAAAKMTIvMzEvMjAyMAkAAAABMJCKr2JvEdkIHk3RYm8R2QguQ0lRLk5ZU0U6VC5JUV9PUEVSX0lOQy5JUV9MVE0uMjAyMS0wNS0wNy4uLlVTRAEAAACHhwEAAgAAAAUyNTcwOAEIAAAABQAAAAExAQAAAAoyMDkwNzczNzc2AwAAAAMxNjACAAAAAjIxBAAAAAEwBwAAAAg1LzcvMjAyMQgAAAAJMy8zMS8yMDIxCQAAAAEwkIqv | E1: Ym8R2Qg8/9BibxHZCCxDSVEuTllTRTpULklRX0VCSVREQS5GWTIwMTYuMjAyMS0wNS0wNy4uLlVTRAEAAACHhwEAAgAAAAU0ODM5MAEIAAAABQAAAAExAQAAAAoxOTQ2MjQ2ODc1AwAAAAMxNjACAAAABDQwNTEEAAAAATAHAAAACDUvNy8yMDIxCAAAAAoxMi8zMS8yMDE2CQAAAAEwkIqvYm8R2QjhNtJibxHZCCxDSVEuTllTRTpULklRX0VCSVREQS5GWTIwMTcuMjAyMS0wNS0wNy4uLlVTRAEAAACHhwEAAgAAAAU0NTU3MgEIAAAABQAAAAExAQAAAAoyMDE2MDU4ODI2AwAAAAMxNjACAAAABDQwNTEEAAAAATAHAAAACDUvNy8yMDIxCAAAAAoxMi8zMS8yMDE3CQAAAAEwkIqvYm8R2Qj8D9JibxHZCCxDSVEuTllTRTpULklRX0VCSVREQS5GWTIwMTguMjAyMS0wNS0wNy4uLlVTRAEAAACHhwEAAgAAAAU1Njk1NgEIAAAABQAAAAExAQAAAAoyMDgyMjUyNDI4AwAAAAMxNjACAAAABDQwNTEEAAAAATAHAAAACDUvNy8yMDIxCAAAAAoxMi8zMS8yMDE4CQAAAAEwkIqvYm8R2Qgem9FibxHZCCxDSVEuTllTRTpULklRX0VCSVREQS5GWTIwMTkuMjAyMS0wNS0wNy4uLlVTRAEAAACHhwEAAgAAAAU1MjY0NQEIAAAABQAAAAExAQAAAAoyMDgyMjUyNDM0AwAAAAMxNjACAAAABDQwNTEEAAAAATAHAAAACDUvNy8yMDIxCAAAAAoxMi8zMS8yMDE5CQAAAAEwkIqvYm8R2QgXdNFibxHZCCxDSVEuTllTRTpULklRX0VCSVRE | F1: QS5GWTIwMjAuMjAyMS0wNS0wNy4uLlVTRAEAAACHhwEAAgAAAAU1MDY4OQEIAAAABQAAAAExAQAAAAoyMDgyMjUyNDI3AwAAAAMxNjACAAAABDQwNTEEAAAAATAHAAAACDUvNy8yMDIxCAAAAAoxMi8zMS8yMDIwCQAAAAEwkIqvYm8R2QgsJtFibxHZCCxDSVEuTllTRTpULklRX0VCSVREQS5JUV9MVE0uMjAyMS0wNS0wNy4uLlVTRAEAAACHhwEAAgAAAAU0OTMyOAEIAAAABQAAAAExAQAAAAoyMDkwNzczNzc2AwAAAAMxNjACAAAABDQwNTEEAAAAATAHAAAACDUvNy8yMDIxCAAAAAkzLzMxLzIwMjEJAAAAATCQiq9ibxHZCDz/0GJvEdkIMENJUS5OWVNFOlQuSVFfTklfQ09NUEFOWS5GWTIwMTYuMjAyMS0wNS0wNy4uLlVTRAEAAACHhwEAAgAAAAUxMzMzMwEIAAAABQAAAAExAQAAAAoxOTQ2MjQ2ODc1AwAAAAMxNjACAAAABTQxNTcxBAAAAAEwBwAAAAg1LzcvMjAyMQgAAAAKMTIvMzEvMjAxNgkAAAABMJCKr2JvEdkI4TbSYm8R2QgwQ0lRLk5ZU0U6VC5JUV9OSV9DT01QQU5ZLkZZMjAxNy4yMDIxLTA1LTA3Li4uVVNEAQAAAIeHAQACAAAABTI5ODQ3AQgAAAAFAAAAATEBAAAACjIwMTYwNTg4MjYDAAAAAzE2MAIAAAAFNDE1NzEEAAAAATAHAAAACDUvNy8yMDIxCAAAAAoxMi8zMS8yMDE3CQAAAAEwkIqvYm8R2QgF6dFibxHZCDBDSVEuTllTRTpULklRX05JX0NPTVBBTlkuRlkyMDE4LjIwMjEtMDUtMDcu | G1: Li5VU0QBAAAAh4cBAAIAAAAFMTk5NTMBCAAAAAUAAAABMQEAAAAKMjA4MjI1MjQyOAMAAAADMTYwAgAAAAU0MTU3MQQAAAABMAcAAAAINS83LzIwMjEIAAAACjEyLzMxLzIwMTgJAAAAATCQiq9ibxHZCB6b0WJvEdkIMENJUS5OWVNFOlQuSVFfTklfQ09NUEFOWS5GWTIwMTkuMjAyMS0wNS0wNy4uLlVTRAEAAACHhwEAAgAAAAUxNDk3NQEIAAAABQAAAAExAQAAAAoyMDgyMjUyNDM0AwAAAAMxNjACAAAABTQxNTcxBAAAAAEwBwAAAAg1LzcvMjAyMQgAAAAKMTIvMzEvMjAxOQkAAAABMJCKr2JvEdkIF3TRYm8R2QgwQ0lRLk5ZU0U6VC5JUV9OSV9DT01QQU5ZLkZZMjAyMC4yMDIxLTA1LTA3Li4uVVNEAQAAAIeHAQACAAAABS0zODIxAQgAAAAFAAAAATEBAAAACjIwODIyNTI0MjcDAAAAAzE2MAIAAAAFNDE1NzEEAAAAATAHAAAACDUvNy8yMDIxCAAAAAoxMi8zMS8yMDIwCQAAAAEwkIqvYm8R2QgeTdFibxHZCDBDSVEuTllTRTpULklRX05JX0NPTVBBTlkuSVFfTFRNLjIwMjEtMDUtMDcuLi5VU0QBAAAAh4cBAAIAAAAELTg0MgEIAAAABQAAAAExAQAAAAoyMDkwNzczNzc2AwAAAAMxNjACAAAABTQxNTcxBAAAAAEwBwAAAAg1LzcvMjAyMQgAAAAJMy8zMS8yMDIxCQAAAAEwkIqvYm8R2Qg8/9BibxHZCChDSVEuTllTRTpULklRX05JLkZZMjAxNi4yMDIxLTA1LTA3Li4uVVNEAQAAAIeHAQACAAAABTEyOTc2 | H1: AQgAAAAFAAAAATEBAAAACjE5NDYyNDY4NzUDAAAAAzE2MAIAAAACMTUEAAAAATAHAAAACDUvNy8yMDIxCAAAAAoxMi8zMS8yMDE2CQAAAAEwkIqvYm8R2QjhNtJibxHZCChDSVEuTllTRTpULklRX05JLkZZMjAxNy4yMDIxLTA1LTA3Li4uVVNEAQAAAIeHAQACAAAABTI5NDUwAQgAAAAFAAAAATEBAAAACjIwMTYwNTg4MjYDAAAAAzE2MAIAAAACMTUEAAAAATAHAAAACDUvNy8yMDIxCAAAAAoxMi8zMS8yMDE3CQAAAAEwkIqvYm8R2QgFwtFibxHZCChDSVEuTllTRTpULklRX05JLkZZMjAxOC4yMDIxLTA1LTA3Li4uVVNEAQAAAIeHAQACAAAABTE5MzcwAQgAAAAFAAAAATEBAAAACjIwODIyNTI0MjgDAAAAAzE2MAIAAAACMTUEAAAAATAHAAAACDUvNy8yMDIxCAAAAAoxMi8zMS8yMDE4CQAAAAEwkIqvYm8R2Qgem9FibxHZCChDSVEuTllTRTpULklRX05JLkZZMjAxOS4yMDIxLTA1LTA3Li4uVVNEAQAAAIeHAQACAAAABTEzOTAzAQgAAAAFAAAAATEBAAAACjIwODIyNTI0MzQDAAAAAzE2MAIAAAACMTUEAAAAATAHAAAACDUvNy8yMDIxCAAAAAoxMi8zMS8yMDE5CQAAAAEwkIqvYm8R2QgXdNFibxHZCChDSVEuTllTRTpULklRX05JLkZZMjAyMC4yMDIxLTA1LTA3Li4uVVNEAQAAAIeHAQACAAAABS01MTc2AQgAAAAFAAAAATEBAAAACjIwODIyNTI0MjcDAAAAAzE2MAIAAAACMTUEAAAAATAHAAAACDUvNy8y | I1: MDIxCAAAAAoxMi8zMS8yMDIwCQAAAAEwkIqvYm8R2QgsJtFibxHZCChDSVEuTllTRTpULklRX05JLklRX0xUTS4yMDIxLTA1LTA3Li4uVVNEAQAAAIeHAQACAAAABS0yMjM2AQgAAAAFAAAAATEBAAAACjIwOTA3NzM3NzYDAAAAAzE2MAIAAAACMTUEAAAAATAHAAAACDUvNy8yMDIxCAAAAAkzLzMxLzIwMjEJAAAAATCQiq9ibxHZCEPY0GJvEdkIK0NJUS5OWVNFOlQuSVFfQ0FQRVguRlkyMDE2LjIwMjEtMDUtMDcuLi5VU0QBAAAAh4cBAAIAAAAGLTIyNDA4AQgAAAAFAAAAATEBAAAACjE5NDYyNDY4NzUDAAAAAzE2MAIAAAAEMjAyMQQAAAABMAcAAAAINS83LzIwMjEIAAAACjEyLzMxLzIwMTYJAAAAATCQiq9ibxHZCOE20mJvEdkIK0NJUS5OWVNFOlQuSVFfQ0FQRVguRlkyMDE3LjIwMjEtMDUtMDcuLi5VU0QBAAAAh4cBAAIAAAAGLTIxNTUwAQgAAAAFAAAAATEBAAAACjIwMTYwNTg4MjYDAAAAAzE2MAIAAAAEMjAyMQQAAAABMAcAAAAINS83LzIwMjEIAAAACjEyLzMxLzIwMTcJAAAAATCQiq9ibxHZCAXp0WJvEdkIK0NJUS5OWVNFOlQuSVFfQ0FQRVguRlkyMDE4LjIwMjEtMDUtMDcuLi5VU0QBAAAAh4cBAAIAAAAGLTIxMjUxAQgAAAAFAAAAATEBAAAACjIwODIyNTI0MjgDAAAAAzE2MAIAAAAEMjAyMQQAAAABMAcAAAAINS83LzIwMjEIAAAACjEyLzMxLzIwMTgJAAAAATCQiq9ibxHZCAXC0WJvEdkI | J1: K0NJUS5OWVNFOlQuSVFfQ0FQRVguRlkyMDE5LjIwMjEtMDUtMDcuLi5VU0QBAAAAh4cBAAIAAAAGLTE5NjM1AQgAAAAFAAAAATEBAAAACjIwODIyNTI0MzQDAAAAAzE2MAIAAAAEMjAyMQQAAAABMAcAAAAINS83LzIwMjEIAAAACjEyLzMxLzIwMTkJAAAAATCQiq9ibxHZCBd00WJvEdkIK0NJUS5OWVNFOlQuSVFfQ0FQRVguRlkyMDIwLjIwMjEtMDUtMDcuLi5VU0QBAAAAh4cBAAIAAAAGLTE1Njc1AQgAAAAFAAAAATEBAAAACjIwODIyNTI0MjcDAAAAAzE2MAIAAAAEMjAyMQQAAAABMAcAAAAINS83LzIwMjEIAAAACjEyLzMxLzIwMjAJAAAAATCQiq9ibxHZCB5N0WJvEdkIK0NJUS5OWVNFOlQuSVFfQ0FQRVguSVFfTFRNLjIwMjEtMDUtMDcuLi5VU0QBAAAAh4cBAAIAAAAGLTE0NzQyAQgAAAAFAAAAATEBAAAACjIwOTA3NzM3NzYDAAAAAzE2MAIAAAAEMjAyMQQAAAABMAcAAAAINS83LzIwMjEIAAAACTMvMzEvMjAyMQkAAAABMJCKr2JvEdkILCbRYm8R2QgzQ0lRLk5ZU0U6VC5JUV9TQUxFX0lOVEFOX0NGLkZZMjAxNi4yMDIxLTA1LTA3Li4uVVNEAQAAAIeHAQADAAAAAACQiq9ibxHZCOE20mJvEdkIM0NJUS5OWVNFOlQuSVFfU0FMRV9JTlRBTl9DRi5GWTIwMTcuMjAyMS0wNS0wNy4uLlVTRAEAAACHhwEAAwAAAAAAkIqvYm8R2Qj8D9JibxHZCDNDSVEuTllTRTpULklRX1NBTEVfSU5UQU5fQ0YuRlky | K1: MDE4LjIwMjEtMDUtMDcuLi5VU0QBAAAAh4cBAAMAAAAAAJCKr2JvEdkIHpvRYm8R2QgzQ0lRLk5ZU0U6VC5JUV9TQUxFX0lOVEFOX0NGLkZZMjAxOS4yMDIxLTA1LTA3Li4uVVNEAQAAAIeHAQADAAAAAACQiq9ibxHZCBd00WJvEdkIM0NJUS5OWVNFOlQuSVFfU0FMRV9JTlRBTl9DRi5GWTIwMjAuMjAyMS0wNS0wNy4uLlVTRAEAAACHhwEAAwAAAAAAkIqvYm8R2QgsJtFibxHZCDNDSVEuTllTRTpULklRX1NBTEVfSU5UQU5fQ0YuSVFfTFRNLjIwMjEtMDUtMDcuLi5VU0QBAAAAh4cBAAMAAAAAAJCKr2JvEdkIPP/QYm8R2QgxQ0lRLk5ZU0U6VC5JUV9TQUxFX1BQRV9DRi5GWTIwMTYuMjAyMS0wNS0wNy4uLlVTRAEAAACHhwEAAgAAAAM2NDYBCAAAAAUAAAABMQEAAAAKMTk0NjI0Njg3NQMAAAADMTYwAgAAAAQyMDQyBAAAAAEwBwAAAAg1LzcvMjAyMQgAAAAKMTIvMzEvMjAxNgkAAAABMJCKr2JvEdkI4TbSYm8R2QgxQ0lRLk5ZU0U6VC5JUV9TQUxFX1BQRV9DRi5GWTIwMTcuMjAyMS0wNS0wNy4uLlVTRAEAAACHhwEAAgAAAAI1OQEIAAAABQAAAAExAQAAAAoyMDE2MDU4ODI2AwAAAAMxNjACAAAABDIwNDIEAAAAATAHAAAACDUvNy8yMDIxCAAAAAoxMi8zMS8yMDE3CQAAAAEwkIqvYm8R2QgF6dFibxHZCDFDSVEuTllTRTpULklRX1NBTEVfUFBFX0NGLkZZMjAxOC4yMDIxLTA1LTA3Li4uVVNEAQAAAIeH | L1: AQACAAAABDIxNDgBCAAAAAUAAAABMQEAAAAKMjA4MjI1MjQyOAMAAAADMTYwAgAAAAQyMDQyBAAAAAEwBwAAAAg1LzcvMjAyMQgAAAAKMTIvMzEvMjAxOAkAAAABMJCKr2JvEdkIHpvRYm8R2QgxQ0lRLk5ZU0U6VC5JUV9TQUxFX1BQRV9DRi5GWTIwMTkuMjAyMS0wNS0wNy4uLlVTRAEAAACHhwEAAgAAAAQ0Njg0AQgAAAAFAAAAATEBAAAACjIwODIyNTI0MzQDAAAAAzE2MAIAAAAEMjA0MgQAAAABMAcAAAAINS83LzIwMjEIAAAACjEyLzMxLzIwMTkJAAAAATCQiq9ibxHZCBd00WJvEdkIMUNJUS5OWVNFOlQuSVFfU0FMRV9QUEVfQ0YuRlkyMDIwLjIwMjEtMDUtMDcuLi5VU0QBAAAAh4cBAAIAAAAEMzY0MQEIAAAABQAAAAExAQAAAAoyMDgyMjUyNDI3AwAAAAMxNjACAAAABDIwNDIEAAAAATAHAAAACDUvNy8yMDIxCAAAAAoxMi8zMS8yMDIwCQAAAAEwkIqvYm8R2QgeTdFibxHZCDFDSVEuTllTRTpULklRX1NBTEVfUFBFX0NGLklRX0xUTS4yMDIxLTA1LTA3Li4uVVNEAQAAAIeHAQACAAAABDM1NzQBCAAAAAUAAAABMQEAAAAKMjA5MDc3Mzc3NgMAAAADMTYwAgAAAAQyMDQyBAAAAAEwBwAAAAg1LzcvMjAyMQgAAAAJMy8zMS8yMDIxCQAAAAEwkIqvYm8R2Qg8/9BibxHZCDBDSVEuTllTRTpULklRX1RPVEFMX0RFQlQuRlkyMDE2LjIwMjEtMDUtMDcuLi5VU0QBAAAAh4cBAAIAAAAGMTI3Mzk0AQgAAAAF | M1: AAAAATEBAAAACjE5NDYyNDY4NzUDAAAAAzE2MAIAAAAENDE3MwQAAAABMAcAAAAINS83LzIwMjEIAAAACjEyLzMxLzIwMTYJAAAAATCQiq9ibxHZCOE20mJvEdkIMENJUS5OWVNFOlQuSVFfVE9UQUxfREVCVC5GWTIwMTcuMjAyMS0wNS0wNy4uLlVTRAEAAACHhwEAAgAAAAYxNjU2NjcBCAAAAAUAAAABMQEAAAAKMjAxNjA1ODgyNgMAAAADMTYwAgAAAAQ0MTczBAAAAAEwBwAAAAg1LzcvMjAyMQgAAAAKMTIvMzEvMjAxNwkAAAABMJCKr2JvEdkIBenRYm8R2QgwQ0lRLk5ZU0U6VC5JUV9UT1RBTF9ERUJULkZZMjAxOC4yMDIxLTA1LTA3Li4uVVNEAQAAAIeHAQACAAAABjE3OTEwNwEIAAAABQAAAAExAQAAAAoyMDgyMjUyNDI4AwAAAAMxNjACAAAABDQxNzMEAAAAATAHAAAACDUvNy8yMDIxCAAAAAoxMi8zMS8yMDE4CQAAAAEwkIqvYm8R2Qgem9FibxHZCDBDSVEuTllTRTpULklRX1RPVEFMX0RFQlQuRlkyMDE5LjIwMjEtMDUtMDcuLi5VU0QBAAAAh4cBAAIAAAAGMTg4NDAyAQgAAAAFAAAAATEBAAAACjIwODIyNTI0MzQDAAAAAzE2MAIAAAAENDE3MwQAAAABMAcAAAAINS83LzIwMjEIAAAACjEyLzMxLzIwMTkJAAAAATCQiq9ibxHZCBd00WJvEdkIMENJUS5OWVNFOlQuSVFfVE9UQUxfREVCVC5GWTIwMjAuMjAyMS0wNS0wNy4uLlVTRAEAAACHhwEAAgAAAAYxODI5ODQBCAAAAAUAAAABMQEAAAAKMjA4 | N1: MjI1MjQyNwMAAAADMTYwAgAAAAQ0MTczBAAAAAEwBwAAAAg1LzcvMjAyMQgAAAAKMTIvMzEvMjAyMAkAAAABMJCKr2JvEdkIHk3RYm8R2QgwQ0lRLk5ZU0U6VC5JUV9UT1RBTF9ERUJULklRX0xUTS4yMDIxLTA1LTA3Li4uVVNEAQAAAIeHAQACAAAABjIwMTk2NQEIAAAABQAAAAExAQAAAAoyMDkwNzczNzc2AwAAAAMxNjACAAAABDQxNzMEAAAAATAHAAAACDUvNy8yMDIxCAAAAAkzLzMxLzIwMjEJAAAAATCQiq9ibxHZCEPY0GJvEdkIL0NJUS5OWVNFOlQuSVFfQ0FTSF9PUEVSLkZZMjAxNi4yMDIxLTA1LTA3Li4uVVNEAQAAAIeHAQACAAAABTM4NDQyAQgAAAAFAAAAATEBAAAACjE5NDYyNDY4NzUDAAAAAzE2MAIAAAAEMjAwNgQAAAABMAcAAAAINS83LzIwMjEIAAAACjEyLzMxLzIwMTYJAAAAATCQiq9ibxHZCPwP0mJvEdkIL0NJUS5OWVNFOlQuSVFfQ0FTSF9PUEVSLkZZMjAxNy4yMDIxLTA1LTA3Li4uVVNEAQAAAIeHAQACAAAABTM4MDEwAQgAAAAFAAAAATEBAAAACjIwMTYwNTg4MjYDAAAAAzE2MAIAAAAEMjAwNgQAAAABMAcAAAAINS83LzIwMjEIAAAACjEyLzMxLzIwMTcJAAAAATCQiq9ibxHZCAXC0WJvEdkIL0NJUS5OWVNFOlQuSVFfQ0FTSF9PUEVSLkZZMjAxOC4yMDIxLTA1LTA3Li4uVVNEAQAAAIeHAQACAAAABTQzNjAyAQgAAAAFAAAAATEBAAAACjIwODIyNTI0MjgDAAAAAzE2MAIAAAAE | O1: MjAwNgQAAAABMAcAAAAINS83LzIwMjEIAAAACjEyLzMxLzIwMTgJAAAAATCQiq9ibxHZCAXC0WJvEdkIL0NJUS5OWVNFOlQuSVFfQ0FTSF9PUEVSLkZZMjAxOS4yMDIxLTA1LTA3Li4uVVNEAQAAAIeHAQACAAAABTQ4NjY4AQgAAAAFAAAAATEBAAAACjIwODIyNTI0MzQDAAAAAzE2MAIAAAAEMjAwNgQAAAABMAcAAAAINS83LzIwMjEIAAAACjEyLzMxLzIwMTkJAAAAATCQiq9ibxHZCBd00WJvEdkIL0NJUS5OWVNFOlQuSVFfQ0FTSF9PUEVSLkZZMjAyMC4yMDIxLTA1LTA3Li4uVVNEAQAAAIeHAQACAAAABTQzMTMwAQgAAAAFAAAAATEBAAAACjIwODIyNTI0MjcDAAAAAzE2MAIAAAAEMjAwNgQAAAABMAcAAAAINS83LzIwMjEIAAAACjEyLzMxLzIwMjAJAAAAATCQiq9ibxHZCCwm0WJvEdkIL0NJUS5OWVNFOlQuSVFfQ0FTSF9PUEVSLklRX0xUTS4yMDIxLTA1LTA3Li4uVVNEAQAAAIeHAQACAAAABTQ0MTkxAQgAAAAFAAAAATEBAAAACjIwOTA3NzM3NzYDAAAAAzE2MAIAAAAEMjAwNgQAAAABMAcAAAAINS83LzIwMjEIAAAACTMvMzEvMjAyMQkAAAABMJCKr2JvEdkILCbRYm8R2QgxQ0lRLk5ZU0U6VC5JUV9DQVNIX0lOVkVTVC5GWTIwMTYuMjAyMS0wNS0wNy4uLlVTRAEAAACHhwEAAgAAAAYtMjMzMTgBCAAAAAUAAAABMQEAAAAKMTk0NjI0Njg3NQMAAAADMTYwAgAAAAQyMDA1BAAAAAEwBwAAAAg1Lzcv | P1: MjAyMQgAAAAKMTIvMzEvMjAxNgkAAAABMJCKr2JvEdkI/A/SYm8R2QgxQ0lRLk5ZU0U6VC5JUV9DQVNIX0lOVkVTVC5GWTIwMTcuMjAyMS0wNS0wNy4uLlVTRAEAAACHhwEAAgAAAAYtMTg5NDMBCAAAAAUAAAABMQEAAAAKMjAxNjA1ODgyNgMAAAADMTYwAgAAAAQyMDA1BAAAAAEwBwAAAAg1LzcvMjAyMQgAAAAKMTIvMzEvMjAxNwkAAAABMJCKr2JvEdkIBenRYm8R2QgxQ0lRLk5ZU0U6VC5JUV9DQVNIX0lOVkVTVC5GWTIwMTguMjAyMS0wNS0wNy4uLlVTRAEAAACHhwEAAgAAAAYtNjMxNDUBCAAAAAUAAAABMQEAAAAKMjA4MjI1MjQyOAMAAAADMTYwAgAAAAQyMDA1BAAAAAEwBwAAAAg1LzcvMjAyMQgAAAAKMTIvMzEvMjAxOAkAAAABMJCKr2JvEdkIBcLRYm8R2QgxQ0lRLk5ZU0U6VC5JUV9DQVNIX0lOVkVTVC5GWTIwMTkuMjAyMS0wNS0wNy4uLlVTRAEAAACHhwEAAgAAAAYtMTY2OTABCAAAAAUAAAABMQEAAAAKMjA4MjI1MjQzNAMAAAADMTYwAgAAAAQyMDA1BAAAAAEwBwAAAAg1LzcvMjAyMQgAAAAKMTIvMzEvMjAxOQkAAAABMJCKr2JvEdkIF3TRYm8R2QgxQ0lRLk5ZU0U6VC5JUV9DQVNIX0lOVkVTVC5GWTIwMjAuMjAyMS0wNS0wNy4uLlVTRAEAAACHhwEAAgAAAAYtMTM1NDgBCAAAAAUAAAABMQEAAAAKMjA4MjI1MjQyNwMAAAADMTYwAgAAAAQyMDA1BAAAAAEwBwAAAAg1LzcvMjAyMQgAAAAK | Q1: MTIvMzEvMjAyMAkAAAABMJCKr2JvEdkILCbRYm8R2QgxQ0lRLk5ZU0U6VC5JUV9DQVNIX0lOVkVTVC5JUV9MVE0uMjAyMS0wNS0wNy4uLlVTRAEAAACHhwEAAgAAAAYtMzUzNzgBCAAAAAUAAAABMQEAAAAKMjA5MDc3Mzc3NgMAAAADMTYwAgAAAAQyMDA1BAAAAAEwBwAAAAg1LzcvMjAyMQgAAAAJMy8zMS8yMDIxCQAAAAEwkIqvYm8R2Qg8/9BibxHZCDBDSVEuTllTRTpULklRX0NBU0hfRklOQU4uRlkyMDE2LjIwMjEtMDUtMDcuLi5VU0QBAAAAh4cBAAIAAAAGLTE0NDYyAQgAAAAFAAAAATEBAAAACjE5NDYyNDY4NzUDAAAAAzE2MAIAAAAEMjAwNAQAAAABMAcAAAAINS83LzIwMjEIAAAACjEyLzMxLzIwMTYJAAAAATCQiq9ibxHZCOE20mJvEdkIMENJUS5OWVNFOlQuSVFfQ0FTSF9GSU5BTi5GWTIwMTcuMjAyMS0wNS0wNy4uLlVTRAEAAACHhwEAAgAAAAUyNTkzMAEIAAAABQAAAAExAQAAAAoyMDE2MDU4ODI2AwAAAAMxNjACAAAABDIwMDQEAAAAATAHAAAACDUvNy8yMDIxCAAAAAoxMi8zMS8yMDE3CQAAAAEwkIqvYm8R2QgF6dFibxHZCDBDSVEuTllTRTpULklRX0NBU0hfRklOQU4uRlkyMDE4LjIwMjEtMDUtMDcuLi5VU0QBAAAAh4cBAAIAAAAGLTI1OTg5AQgAAAAFAAAAATEBAAAACjIwODIyNTI0MjgDAAAAAzE2MAIAAAAEMjAwNAQAAAABMAcAAAAINS83LzIwMjEIAAAACjEyLzMxLzIwMTgJAAAA | R1: ATCQiq9ibxHZCB6b0WJvEdkIMENJUS5OWVNFOlQuSVFfQ0FTSF9GSU5BTi5GWTIwMTkuMjAyMS0wNS0wNy4uLlVTRAEAAACHhwEAAgAAAAYtMjUwODMBCAAAAAUAAAABMQEAAAAKMjA4MjI1MjQzNAMAAAADMTYwAgAAAAQyMDA0BAAAAAEwBwAAAAg1LzcvMjAyMQgAAAAKMTIvMzEvMjAxOQkAAAABMJCKr2JvEdkIF3TRYm8R2QgwQ0lRLk5ZU0U6VC5JUV9DQVNIX0ZJTkFOLkZZMjAyMC4yMDIxLTA1LTA3Li4uVVNEAQAAAIeHAQACAAAABi0zMjAwNwEIAAAABQAAAAExAQAAAAoyMDgyMjUyNDI3AwAAAAMxNjACAAAABDIwMDQEAAAAATAHAAAACDUvNy8yMDIxCAAAAAoxMi8zMS8yMDIwCQAAAAEwkIqvYm8R2QgeTdFibxHZCDBDSVEuTllTRTpULklRX0NBU0hfRklOQU4uSVFfTFRNLjIwMjEtMDUtMDcuLi5VU0QBAAAAh4cBAAIAAAAFLTc0MjUBCAAAAAUAAAABMQEAAAAKMjA5MDc3Mzc3NgMAAAADMTYwAgAAAAQyMDA0BAAAAAEwBwAAAAg1LzcvMjAyMQgAAAAJMy8zMS8yMDIxCQAAAAEwkIqvYm8R2Qg8/9BibxHZCDRDSVEuTllTRTpULklRX0NBU0hfU1RfSU5WRVNULkZZMjAxNi4yMDIxLTA1LTA3Li4uVVNEAQAAAIeHAQACAAAABDU3ODgBCAAAAAUAAAABMQEAAAAKMTk0NjI0Njg3NQMAAAADMTYwAgAAAAQxMDAyBAAAAAEwBwAAAAg1LzcvMjAyMQgAAAAKMTIvMzEvMjAxNgkAAAABMJCKr2JvEdkI4TbS | S1: Ym8R2Qg0Q0lRLk5ZU0U6VC5JUV9DQVNIX1NUX0lOVkVTVC5GWTIwMTcuMjAyMS0wNS0wNy4uLlVTRAEAAACHhwEAAgAAAAU1MDQ5OAEIAAAABQAAAAExAQAAAAoyMDE2MDU4ODI2AwAAAAMxNjACAAAABDEwMDIEAAAAATAHAAAACDUvNy8yMDIxCAAAAAoxMi8zMS8yMDE3CQAAAAEwkIqvYm8R2Qj8D9JibxHZCDRDSVEuTllTRTpULklRX0NBU0hfU1RfSU5WRVNULkZZMjAxOC4yMDIxLTA1LTA3Li4uVVNEAQAAAIeHAQACAAAABDUyMDQBCAAAAAUAAAABMQEAAAAKMjA4MjI1MjQyOAMAAAADMTYwAgAAAAQxMDAyBAAAAAEwBwAAAAg1LzcvMjAyMQgAAAAKMTIvMzEvMjAxOAkAAAABMJCKr2JvEdkIHpvRYm8R2Qg0Q0lRLk5ZU0U6VC5JUV9DQVNIX1NUX0lOVkVTVC5GWTIwMTkuMjAyMS0wNS0wNy4uLlVTRAEAAACHhwEAAgAAAAUxMjEzMAEIAAAABQAAAAExAQAAAAoyMDgyMjUyNDM0AwAAAAMxNjACAAAABDEwMDIEAAAAATAHAAAACDUvNy8yMDIxCAAAAAoxMi8zMS8yMDE5CQAAAAEwkIqvYm8R2QgXdNFibxHZCDRDSVEuTllTRTpULklRX0NBU0hfU1RfSU5WRVNULkZZMjAyMC4yMDIxLTA1LTA3Li4uVVNEAQAAAIeHAQACAAAABDk3NjkBCAAAAAUAAAABMQEAAAAKMjA4MjI1MjQyNwMAAAADMTYwAgAAAAQxMDAyBAAAAAEwBwAAAAg1LzcvMjAyMQgAAAAKMTIvMzEvMjAyMAkAAAABMJCKr2JvEdkIHk3RYm8R | T1: 2Qg0Q0lRLk5ZU0U6VC5JUV9DQVNIX1NUX0lOVkVTVC5JUV9MVE0uMjAyMS0wNS0wNy4uLlVTRAEAAACHhwEAAgAAAAUxMTM0MgEIAAAABQAAAAExAQAAAAoyMDkwNzczNzc2AwAAAAMxNjACAAAABDEwMDIEAAAAATAHAAAACDUvNy8yMDIxCAAAAAkzLzMxLzIwMjEJAAAAATCQiq9ibxHZCEPY0GJvEdkINUNJUS5OWVNFOlQuSVFfT1RIRVJfTFRfQVNTRVRTLkZZMjAxNi4yMDIxLTA1LTA3Li4uVVNEAQAAAIeHAQACAAAABTE2ODEyAQgAAAAFAAAAATEBAAAACjE5NDYyNDY4NzUDAAAAAzE2MAIAAAAEMTA2MAQAAAABMAcAAAAINS83LzIwMjEIAAAACjEyLzMxLzIwMTYJAAAAATCQiq9ibxHZCPwP0mJvEdkINUNJUS5OWVNFOlQuSVFfT1RIRVJfTFRfQVNTRVRTLkZZMjAxNy4yMDIxLTA1LTA3Li4uVVNEAQAAAIeHAQACAAAABTE4NDI3AQgAAAAFAAAAATEBAAAACjIwMTYwNTg4MjYDAAAAAzE2MAIAAAAEMTA2MAQAAAABMAcAAAAINS83LzIwMjEIAAAACjEyLzMxLzIwMTcJAAAAATCQiq9ibxHZCAXC0WJvEdkINUNJUS5OWVNFOlQuSVFfT1RIRVJfTFRfQVNTRVRTLkZZMjAxOC4yMDIxLTA1LTA3Li4uVVNEAQAAAIeHAQACAAAABTIyOTk5AQgAAAAFAAAAATEBAAAACjIwODIyNTI0MjgDAAAAAzE2MAIAAAAEMTA2MAQAAAABMAcAAAAINS83LzIwMjEIAAAACjEyLzMxLzIwMTgJAAAAATCQiq9ibxHZCB6b0WJv | U1: EdkINUNJUS5OWVNFOlQuSVFfT1RIRVJfTFRfQVNTRVRTLkZZMjAxOS4yMDIxLTA1LTA3Li4uVVNEAQAAAIeHAQACAAAABTI1NzQ3AQgAAAAFAAAAATEBAAAACjIwODIyNTI0MzQDAAAAAzE2MAIAAAAEMTA2MAQAAAABMAcAAAAINS83LzIwMjEIAAAACjEyLzMxLzIwMTkJAAAAATCQiq9ibxHZCBd00WJvEdkINUNJUS5OWVNFOlQuSVFfT1RIRVJfTFRfQVNTRVRTLkZZMjAyMC4yMDIxLTA1LTA3Li4uVVNEAQAAAIeHAQACAAAABTI4MDg3AQgAAAAFAAAAATEBAAAACjIwODIyNTI0MjcDAAAAAzE2MAIAAAAEMTA2MAQAAAABMAcAAAAINS83LzIwMjEIAAAACjEyLzMxLzIwMjAJAAAAATCQiq9ibxHZCB5N0WJvEdkINUNJUS5OWVNFOlQuSVFfT1RIRVJfTFRfQVNTRVRTLklRX0xUTS4yMDIxLTA1LTA3Li4uVVNEAQAAAIeHAQACAAAABTYwNTI4AQgAAAAFAAAAATEBAAAACjIwOTA3NzM3NzYDAAAAAzE2MAIAAAAEMTA2MAQAAAABMAcAAAAINS83LzIwMjEIAAAACTMvMzEvMjAyMQkAAAABMJCKr2JvEdkIPP/QYm8R2QgvQ0lRLk5ZU0U6VC5JUV9MVF9JTlZFU1QuRlkyMDE2LjIwMjEtMDUtMDcuLi5VU0QBAAAAh4cBAAIAAAAEMTY3NAEIAAAABQAAAAExAQAAAAoxOTQ2MjQ2ODc1AwAAAAMxNjACAAAABDEwNTQEAAAAATAHAAAACDUvNy8yMDIxCAAAAAoxMi8zMS8yMDE2CQAAAAEwkIqvYm8R2QjhNtJibxHZCC9D | V1: SVEuTllTRTpULklRX0xUX0lOVkVTVC5GWTIwMTcuMjAyMS0wNS0wNy4uLlVTRAEAAACHhwEAAgAAAAQxNTc3AQgAAAAFAAAAATEBAAAACjIwMTYwNTg4MjYDAAAAAzE2MAIAAAAEMTA1NAQAAAABMAcAAAAINS83LzIwMjEIAAAACjEyLzMxLzIwMTcJAAAAATCQiq9ibxHZCAXp0WJvEdkIL0NJUS5OWVNFOlQuSVFfTFRfSU5WRVNULkZZMjAxOC4yMDIxLTA1LTA3Li4uVVNEAQAAAIeHAQACAAAABDYyNDUBCAAAAAUAAAABMQEAAAAKMjA4MjI1MjQyOAMAAAADMTYwAgAAAAQxMDU0BAAAAAEwBwAAAAg1LzcvMjAyMQgAAAAKMTIvMzEvMjAxOAkAAAABMJCKr2JvEdkIBcLRYm8R2QgvQ0lRLk5ZU0U6VC5JUV9MVF9JTlZFU1QuRlkyMDE5LjIwMjEtMDUtMDcuLi5VU0QBAAAAh4cBAAIAAAAEMzcwNgEIAAAABQAAAAExAQAAAAoyMDgyMjUyNDM0AwAAAAMxNjACAAAABDEwNTQEAAAAATAHAAAACDUvNy8yMDIxCAAAAAoxMi8zMS8yMDE5CQAAAAEwkIqvYm8R2QgXdNFibxHZCC9DSVEuTllTRTpULklRX0xUX0lOVkVTVC5GWTIwMjAuMjAyMS0wNS0wNy4uLlVTRAEAAACHhwEAAgAAAAQzMjMwAQgAAAAFAAAAATEBAAAACjIwODIyNTI0MjcDAAAAAzE2MAIAAAAEMTA1NAQAAAABMAcAAAAINS83LzIwMjEIAAAACjEyLzMxLzIwMjAJAAAAATCQiq9ibxHZCCwm0WJvEdkIL0NJUS5OWVNFOlQuSVFfTFRfSU5WRVNULklR | W1: X0xUTS4yMDIxLTA1LTA3Li4uVVNEAQAAAIeHAQACAAAABDE4MDUBCAAAAAUAAAABMQEAAAAKMjA5MDc3Mzc3NgMAAAADMTYwAgAAAAQxMDU0BAAAAAEwBwAAAAg1LzcvMjAyMQgAAAAJMy8zMS8yMDIxCQAAAAEwkIqvYm8R2Qg8/9BibxHZCDlDSVEuTllTRTpULklRX1RPVEFMX0NPTU1PTl9FUVVJVFkuRlkyMDE2LjIwMjEtMDUtMDcuLi5VU0QBAAAAh4cBAAIAAAAGMTIzMTM1AQgAAAAFAAAAATEBAAAACjE5NDYyNDY4NzUDAAAAAzE2MAIAAAAEMTAwNgQAAAABMAcAAAAINS83LzIwMjEIAAAACjEyLzMxLzIwMTYJAAAAATCQiq9ibxHZCPwP0mJvEdkIOUNJUS5OWVNFOlQuSVFfVE9UQUxfQ09NTU9OX0VRVUlUWS5GWTIwMTcuMjAyMS0wNS0wNy4uLlVTRAEAAACHhwEAAgAAAAYxNDA4NjEBCAAAAAUAAAABMQEAAAAKMjAxNjA1ODgyNgMAAAADMTYwAgAAAAQxMDA2BAAAAAEwBwAAAAg1LzcvMjAyMQgAAAAKMTIvMzEvMjAxNwkAAAABMJCKr2JvEdkIBenRYm8R2Qg5Q0lRLk5ZU0U6VC5JUV9UT1RBTF9DT01NT05fRVFVSVRZLkZZMjAxOC4yMDIxLTA1LTA3Li4uVVNEAQAAAIeHAQACAAAABjE4NDA4OQEIAAAABQAAAAExAQAAAAoyMDgyMjUyNDI4AwAAAAMxNjACAAAABDEwMDYEAAAAATAHAAAACDUvNy8yMDIxCAAAAAoxMi8zMS8yMDE4CQAAAAEwkIqvYm8R2Qgem9FibxHZCDlDSVEuTllTRTpULklRX1RP | X1: VEFMX0NPTU1PTl9FUVVJVFkuRlkyMDE5LjIwMjEtMDUtMDcuLi5VU0QBAAAAh4cBAAIAAAAGMTg0MjIxAQgAAAAFAAAAATEBAAAACjIwODIyNTI0MzQDAAAAAzE2MAIAAAAEMTAwNgQAAAABMAcAAAAINS83LzIwMjEIAAAACjEyLzMxLzIwMTkJAAAAATCQiq9ibxHZCBd00WJvEdkIOUNJUS5OWVNFOlQuSVFfVE9UQUxfQ09NTU9OX0VRVUlUWS5GWTIwMjAuMjAyMS0wNS0wNy4uLlVTRAEAAACHhwEAAgAAAAYxNjE2NzMBCAAAAAUAAAABMQEAAAAKMjA4MjI1MjQyNwMAAAADMTYwAgAAAAQxMDA2BAAAAAEwBwAAAAg1LzcvMjAyMQgAAAAKMTIvMzEvMjAyMAkAAAABMJCKr2JvEdkIHk3RYm8R2Qg5Q0lRLk5ZU0U6VC5JUV9UT1RBTF9DT01NT05fRVFVSVRZLklRX0xUTS4yMDIxLTA1LTA3Li4uVVNEAQAAAIeHAQACAAAABjE2NTQ4OAEIAAAABQAAAAExAQAAAAoyMDkwNzczNzc2AwAAAAMxNjACAAAABDEwMDYEAAAAATAHAAAACDUvNy8yMDIxCAAAAAkzLzMxLzIwMjEJAAAAATCQiq9ibxHZCDz/0GJvEdkIMkNJUS5OWVNFOlQuSVFfVE9UQUxfRVFVSVRZLkZZMjAxNi4yMDIxLTA1LTA3Li4uVVNEAQAAAIeHAQACAAAABjEyNDExMAEIAAAABQAAAAExAQAAAAoxOTQ2MjQ2ODc1AwAAAAMxNjACAAAABDEyNzUEAAAAATAHAAAACDUvNy8yMDIxCAAAAAoxMi8zMS8yMDE2CQAAAAEwkIqvYm8R2QjhNtJibxHZCDJD | Y1: SVEuTllTRTpULklRX1RPVEFMX0VRVUlUWS5GWTIwMTcuMjAyMS0wNS0wNy4uLlVTRAEAAACHhwEAAgAAAAYxNDIwMDcBCAAAAAUAAAABMQEAAAAKMjAxNjA1ODgyNgMAAAADMTYwAgAAAAQxMjc1BAAAAAEwBwAAAAg1LzcvMjAyMQgAAAAKMTIvMzEvMjAxNwkAAAABMJCKr2JvEdkI/A/SYm8R2QgyQ0lRLk5ZU0U6VC5JUV9UT1RBTF9FUVVJVFkuRlkyMDE4LjIwMjEtMDUtMDcuLi5VU0QBAAAAh4cBAAIAAAAGMTkzODg0AQgAAAAFAAAAATEBAAAACjIwODIyNTI0MjgDAAAAAzE2MAIAAAAEMTI3NQQAAAABMAcAAAAINS83LzIwMjEIAAAACjEyLzMxLzIwMTgJAAAAATCQiq9ibxHZCAXC0WJvEdkIMkNJUS5OWVNFOlQuSVFfVE9UQUxfRVFVSVRZLkZZMjAxOS4yMDIxLTA1LTA3Li4uVVNEAQAAAIeHAQACAAAABjIwMTkzNAEIAAAABQAAAAExAQAAAAoyMDgyMjUyNDM0AwAAAAMxNjACAAAABDEyNzUEAAAAATAHAAAACDUvNy8yMDIxCAAAAAoxMi8zMS8yMDE5CQAAAAEwkIqvYm8R2QgXdNFibxHZCDJDSVEuTllTRTpULklRX1RPVEFMX0VRVUlUWS5GWTIwMjAuMjAyMS0wNS0wNy4uLlVTRAEAAACHhwEAAgAAAAYxNzkyNDABCAAAAAUAAAABMQEAAAAKMjA4MjI1MjQyNwMAAAADMTYwAgAAAAQxMjc1BAAAAAEwBwAAAAg1LzcvMjAyMQgAAAAKMTIvMzEvMjAyMAkAAAABMJCKr2JvEdkILCbRYm8R2QgyQ0lRLk5Z | Z1: U0U6VC5JUV9UT1RBTF9FUVVJVFkuSVFfTFRNLjIwMjEtMDUtMDcuLi5VU0QBAAAAh4cBAAIAAAAGMTgzMDc5AQgAAAAFAAAAATEBAAAACjIwOTA3NzM3NzYDAAAAAzE2MAIAAAAEMTI3NQQAAAABMAcAAAAINS83LzIwMjEIAAAACTMvMzEvMjAyMQkAAAABMJCKr2JvEdkIPP/QYm8R2Qg=

Sheet Cover
B2: 배당 수익률 계산기 | K2: ='Data_ AT&T 데이터'!D4 -> AT&T Inc. (NYSE:T)
D6: Latest update: | F6: =TODAY() -> 45831
C29: © 2021 Wall Street Training Asia Inc.
C30: No portion of this report may be reproduced, reused, or otherwise distributed in any form without prior written consent.
C31: For more information, please visit/contatct Wall Street Training Asia Inc. through www.wallstreettraining.co.kr
C33: © 2021 (주)월스트릿트레이닝아시아.
C34: 이 파일은 대한민국 및 미국 저작권법의 보호를 받는 저작물 입니다.
C35: 파일의 원 저자로부터 서면에 의한 허락없이 이 파일의 일부나 전체를 어떠한 형태로도 가공/배포할 수 없습니다.
C36: 이를 위반시에는 형사/민사상의 법적 책임을 질수 있으며, 특별한 문의가 있는경우 www.wallstreettraining.co.kr에 있는 정보로 연락주시기 바랍니다.

Sheet 현황판
A2: =""&'Data_ AT&T 데이터'!D4&" – 현황판" -> AT&T Inc. (NYSE:T) – 현황판
C5: 회사 소개
C6: 회사명: | E6: AT&T | F6: 티커: | G6: NYSE: T
C7: 주식가격: | E7: 28.63 | F7: 배당수익률: | G7: 0.07324377
C8: 배당주기: | E8: 분기 (1,4,7,10월) | F8: 배당 성장률: | G8: 0.020981007
C10: 비즈니스Quality
C11: 5년 매출성장: | E11: 0.048631745 | F11: 영업이익 성장: | G11: 0.073599172
C12: EPS 성장성: | E12: -0.010755189 | F12: 배당 커버율(CF): | G12: 0.7307024
E14: 업계평균 | F14: AT&T | G14: 평가
C15: 차입금 부담 (낮을수록 긍정적)
C16: 순차입금/EBIT: | E16: 5.9728995 | F16: 5.9769122 | G16: 산업 평균 수준
C17: 순차입금/FCF: | E17: 6.0242855 | F17: 6.0796841 | G17: 산업 평균 수준
C18: 가치평가 (낮을수록 긍정적)
C19: EV/EBIT: | E19: 12.746605 | F19: 13.559603 | G19: 조금 높음
C20: EV/FCF: | E20: 15.395395 | F20: 13.792758 | G20: 조금 낮음

Sheet IBPE_배당 수익률 계산기 (교재)
A2: 배당 수익률 계산기
D3: 2020 | E3: 2021 | F3: 2022 | G3: 2023 | H3: 2024 | I3: 2025 | J3: 2026 | K3: 2027 | L3: 2028 | M3: 2029 | N3: 2030
C5: 주식가격 | D5: =+현황판!E7 -> 28.63 | G5: 시가총액 (십억달러) | J5: =+D5*J6 -> 203990.05
C6: 주당 배당금 | D6: =+D5*현황판!G7 -> 2.0969691 | G6: 주식수 (백만주) | J6: 7125.0453
C7: 배당 성장률 | D7: =+현황판!G8 -> 0.020981007
B10: 시나리오 0. 손쉬운 계산
B12: x | C12: PV | D12: 29.01
C13: 요구수익률 | D13: 0.1
C14: 투자기간 | D14: 5
C15: 주식 배당금 | D15: =+D6 -> 2.0969691
C16: 매각 예정가격 | D16: =+D5 -> 28.63
C18: PV 함수 풀이
D19: 2020 | E19: =+D19+1 -> 2021 | F19: =+E19+1 -> 2022 | G19: =+F19+1 -> 2023 | H19: =+G19+1 -> 2024 | I19: =+H19+1 -> 2025 | J19: =+I19 -> 2025
C20: 투자기간 | D20: 0 | E20: =+D20+1 -> 1 | F20: =+E20+1 -> 2 | G20: =+F20+1 -> 3 | H20: =+G20+1 -> 4 | I20: =+H20+1 -> 5 | J20: =+I20 -> 5
C21: 주당 배당금 | E21: =+$D$15 -> 2.0969691 | F21: =+$D$15 -> 2.0969691 | G21: =+$D$15 -> 2.0969691 | H21: =+$D$15 -> 2.0969691 | I21: =+$D$15 -> 2.0969691
C22: 매각 예정가격 | J22: =+D16 -> 28.63
C23: 할인계수 | E23: 1.07 | F23: 1.14 | G23: 1.23 | H23: 1.31 | I23: 1.4 | J23: 1.4
C24: 현재가치 | E24: =+E21/E23 -> 1.9597842 | F24: =+F21/F23 -> 1.8394466 | G24: =+G21/G23 -> 1.704853 | H24: =+H21/H23 -> 1.6007398 | I24: =+I21/I23 -> 1.4978351 | J24: =+J22/J23 -> 20.45
I25: ∑현재가치: | J25: =SUM(E24:J24) -> 29.052659 | K25: =J25=D12 -> FALSE
B27: x | C27: PV
C28: 요구수익률 | D28: 0.1
C29: 투자기간 | D29: 5
C30: 주식 배당금 | D30: =+D21 -> 0
C31: 매각 예정가격 | D31: =+D20 -> 0
D33: * 증권을 발행한 사람의 기준
B35: x | C35: FV | D35: =FV(D36,D37,-D38,-D39,0) -> 58.911108 | G35: 투자기간 | H35: 1 | I35: =+H35+1 -> 2 | J35: =+I35+1 -> 3 | K35: =+J35+1 -> 4 | L35: 5 | M35: 5
C36: 요구수익률 | D36: 0.1 | G36: 주당 배당금 | H36: =E21 -> 2.0969691 | I36: =F21 -> 2.0969691 | J36: =G21 -> 2.0969691 | K36: =H21 -> 2.0969691 | L36: =I21 -> 2.0969691
C37: 투자기간 | D37: 5 | G37: 매각가격 | M37: =+D5 -> 28.63
C38: 쿠폰 수익 | D38: =D6 -> 2.0969691 | G38: 할증계수 | H38: =1.1^(COUNTA(I35:$L$35)) -> 1.4641 | I38: =1.1^(COUNTA(J35:$L$35)) -> 1.331 | J38: =1.1^(COUNTA(K35:$L$35)) -> 1.21 | K38: =1.1^(COUNTA(L35:$L$35)) -> 1.1 | L38: 1 | M38: 1
C39: 만기 상환금액 | D39: =+D5 -> 28.63 | G39: 현재가치 | H39: =+H36*H38 -> 3.0701725 | I39: =+I36*I38 -> 2.7910659 | J39: =+J36*J38 -> 2.5373327 | K39: =+K36*K38 -> 2.306666 | L39: =+L36*L38 -> 2.0969691 | M39: =+M37*M38 -> 28.63
L40: ∑현재가치: | M40: =SUM(H39:M39) -> 41.432206 | N40: =M40=D35 -> FALSE
D41: * 증권을 구매한 사람의 기준
B43: x | C43: NPV | D43: 0.38 | E43: =+D12=D43-D49 -> TRUE
C44: 요구수익률 | D44: 0.1
C46: 성장률 미포함
D47: 2020 | E47: =+D47+1 -> 2021 | F47: =+E47+1 -> 2022 | G47: =+F47+1 -> 2023 | H47: =+G47+1 -> 2024 | I47: =+H47+1 -> 2025 | J47: =+I47 -> 2025
C48: 투자기간 | D48: 0 | E48: 1 | F48: =+E48+1 -> 2 | G48: =+F48+1 -> 3 | H48: =+G48+1 -> 4 | I48: =+H48+1 -> 5
C49: 매입 가격 | D49: =-D5 -> -28.63
C50: 주당 배당금 | E50: =+E21 -> 2.0969691 | F50: =+F21 -> 2.0969691 | G50: =+G21 -> 2.0969691 | H50: =+H21 -> 2.0969691 | I50: =+I21+J22 -> 30.726969 | J50: <- 매각 예정가격 포함
C52: 성장률 포함
C53: NPV w/ 성장률 | D53: =NPV(D54,E59:I59,-D55) -> 26.195521
C54: 요구수익률 | D54: 0.1
C55: 성장률 포함 | D55: =+D7 -> 0.020981007
D56: 2020 | E56: =+D56+1 -> 2021 | F56: =+E56+1 -> 2022 | G56: =+F56+1 -> 2023 | H56: =+G56+1 -> 2024 | I56: =+H56+1 -> 2025 | J56: =+I56 -> 2025
C57: 투자기간 | D57: 0 | E57: 1 | F57: =+E57+1 -> 2 | G57: =+F57+1 -> 3 | H57: =+G57+1 -> 4 | I57: =+H57+1 -> 5
C58: 매입 가격 | D58: =-D5 -> -28.63
C59: 주당 배당금 | E59: =+E50*(1+$D$7) -> 2.1409657 | F59: =+E59*(1+$D$55) -> 2.1858853 | G59: =+F59*(1+$D$55) -> 2.2317473 | H59: =+G59*(1+$D$55) -> 2.2785717 | I59: =+H59*(1+$D$55)+J22 -> 30.956378 | J59: <- 매각 예정가격 포함
C62: NPV함수는 기본적으로 기말에 투자가 발생한 것으로 간주함, 첫 변수 부터 할인이 들어가는 것임
B64: x | C64: IRR | D64: =IRR(D68:I68) -> 0.07324377
D66: 2020 | E66: =+D66+1 -> 2021 | F66: =+E66+1 -> 2022 | G66: =+F66+1 -> 2023 | H66: =+G66+1 -> 2024 | I66: =+H66+1 -> 2025 | J66: =+I66 -> 2025
C67: 투자기간 | D67: 0 | E67: 1 | F67: =+E67+1 -> 2 | G67: =+F67+1 -> 3 | H67: =+G67+1 -> 4 | I67: =+H67+1 -> 5
C68: 현금 유입/(유출) | D68: =+D49 -> -28.63 | E68: =+E50 -> 2.0969691 | F68: =+F50 -> 2.0969691 | G68: =+G50 -> 2.0969691 | H68: =+H50 -> 2.0969691 | I68: =+I50 -> 30.726969
C71: 동일한지 Check <- goal check | D71: =D64-D44 -> -0.02675623
B74: x | C74: XNPV | D74: =XNPV(D75,D78:K78,D77:K77) -> -1.2708692
C75: 요구수익률 | D75: 0.1
C77: 현금 유입/(유출) 시점 | D77: 43816 | E77: 43920 | F77: =+E77+365 -> 44285 | G77: =+F77+365 -> 44650 | H77: =+G77+365 -> 45015 | I77: =+H77+365 -> 45380 | J77: =+I77+365 -> 45745 | K77: =+J77+90 -> 45835
C78: 현금 유입/(유출) | D78: =-D5 -> -28.63 | E78: =+$D$6*(1+$D$7) -> 2.1409657 | F78: =E78*(1+$D$7) -> 2.1858853 | G78: =F78*(1+$D$7) -> 2.2317473 | H78: =G78*(1+$D$7) -> 2.2785717 | I78: =H78*(1+$D$7) -> 2.3263784 | J78: =I78*(1+$D$7) -> 2.3751881 | K78: =+J22 -> 28.63
B86: x | C86: XIRR | D86: =XIRR(D89:K89,D88:K88) -> 0.088744757
C88: 현금 유입/(유출) 시점 | D88: =+D77 -> 43816 | E88: =+E77 -> 43920 | F88: =+F77 -> 44285 | G88: =+G77 -> 44650 | H88: =+H77 -> 45015 | I88: =+I77 -> 45380 | J88: =+J77 -> 45745 | K88: =+K77 -> 45835
C89: 현금 유입/(유출) | D89: =+D78 -> -28.63 | E89: =+E78 -> 2.1409657 | F89: =+F78 -> 2.1858853 | G89: =+G78 -> 2.2317473 | H89: =+H78 -> 2.2785717 | I89: =+I78 -> 2.3263784 | J89: =+J78 -> 2.3751881 | K89: =+K78 -> 28.63
C92: 만약 IRR을 요구수익률로 포함시킨다면?
B94: 시나리오 1. 현상유지: 영업상황 유지 & 배당 현상유지 & 가치평가 평균 회귀
D96: =YEAR(Cover!F6)-1 -> 2024 | E96: =+D96+1 -> 2025 | F96: =+E96+1 -> 2026 | G96: =+F96+1 -> 2027 | H96: =+G96+1 -> 2028 | I96: =+H96+1 -> 2029 | J96: =+I96+1 -> 2030 | K96: =+J96+1 -> 2031 | L96: =+K96+1 -> 2032 | ... N96: =+M96+1 -> 2034
C97: 연차 | D97: 작년 | E97: 1 | F97: =E97+1 -> 2 | G97: =F97+1 -> 3 | H97: =G97+1 -> 4 | I97: =H97+1 -> 5 | J97: =I97+1 -> 6 | K97: =J97+1 -> 7 | L97: =K97+1 -> 8 | M97: =L97+1 -> 9 | N97: =M97+1 -> 10
C98: 주당 배당금 | D98: =+D6 -> 2.0969691 | E98: =D98*(1+E99) -> 2.1409657 | F98: =E98*(1+F99) -> 2.1858853 | G98: =F98*(1+G99) -> 2.2317473 | H98: =G98*(1+H99) -> 2.2763823 | I98: =H98*(1+I99) -> 2.3219099 | J98: =I98*(1+J99) -> 2.3683481 | K98: =J98*(1+K99) -> 2.4157151 | L98: =K98*(1+L99) -> 2.4640294 | ... N98: =M98*(1+N99) -> 2.5635762
C99: 연도별 변화율 | E99: =+$D$7 -> 0.020981007 | F99: =+E99 -> 0.020981007 | G99: =+F99 -> 0.020981007 | H99: =$N$103 -> 0.02 | I99: =$N$103 -> 0.02 | J99: =$N$103 -> 0.02 | K99: =$N$103 -> 0.02 | L99: =$N$103 -> 0.02 | M99: =$N$103 -> 0.02 | N99: =$N$103 -> 0.02
C100: 배당수익률 | E100: =+E98/$D$5 -> 0.074780498 | F100: =+F98/$D$5 -> 0.076349468 | G100: =+G98/$D$5 -> 0.077951357 | H100: =+H98/$D$5 -> 0.079510384 | I100: =+I98/$D$5 -> 0.081100592 | J100: =+J98/$D$5 -> 0.082722603 | K100: =+K98/$D$5 -> 0.084377056 | L100: =+L98/$D$5 -> 0.086064597 | ... N100: =+N98/$D$5 -> 0.089541606
C101: 총 배당금 | E101: =+$J$6*E98 -> 15254.477 | F101: =+$J$6*F98 -> 15574.532 | G101: =+$J$6*G98 -> 15901.301 | H101: =+$J$6*H98 -> 16219.327 | I101: =+$J$6*I98 -> 16543.713 | J101: =+$J$6*J98 -> 16874.588 | K101: =+$J$6*K98 -> 17212.079 | L101: =+$J$6*L98 -> 17556.321 | ... N101: =+$J$6*N98 -> 18265.596
M103: 3년차 이후의 장기 성장율: | N103: 0.02
M104: 작년 대비 10년후 성장율: | N104: =N98/D98-1 -> 0.22251499
D106: =+D96 -> 2024 | E106: =+D106+1 -> 2025 | F106: =+E106+1 -> 2026 | G106: =+F106+1 -> 2027 | H106: =+G106+1 -> 2028 | I106: =+H106+1 -> 2029 | J106: =+I106+1 -> 2030 | K106: =+J106+1 -> 2031 | L106: =+K106+1 -> 2032 | ... N106: =+M106+1 -> 2034
C107: 차입금 | D107: =+'Data_ AT&T 데이터'!I33 -> 179447 | E107: =+D107+E108 -> 167416.33 | F107: =+E107+F108 -> 155385.67 | G107: =+F107+G108 -> 143355 | H107: =+G107+H108 -> 131324.33 | I107: =+H107+I108 -> 119293.67 | J107: =+I107+J108 -> 107263 | K107: =+J107+K108 -> 95232.333 | L107: =+K107+L108 -> 83201.667 | ... N107: =+M107+N108 -> 59140.333
C108: 연간 차입금 상환금액 | D108: -12030.667 | E108: =+D108 -> -12030.667 | F108: =+E108 -> -12030.667 | G108: =+F108 -> -12030.667 | H108: =+G108 -> -12030.667 | I108: =+H108 -> -12030.667 | J108: =+I108 -> -12030.667 | K108: =+J108 -> -12030.667 | L108: =+K108 -> -12030.667 | ... N108: =+M108 -> -12030.667
C110: =+현황판!C20 -> EV/FCF: | D110: =+D112/D111 -> 13.792758 | M110: 업계평균 EV/FCF: | N110: =+현황판!E20 -> 15.395395
C111: 자유현금흐름 | D111: 29253 | E111: =+D111*(1+E99) -> 29866.757 | F111: =+E111*(1+F99) -> 30493.392 | G111: =+F111*(1+G99) -> 31133.174 | H111: =+G111*(1+H99) -> 31755.838 | I111: =+H111*(1+I99) -> 32390.954 | J111: =+I111*(1+J99) -> 33038.773 | K111: =+J111*(1+K99) -> 33699.549 | L111: =+K111*(1+L99) -> 34373.54 | ... N111: =+M111*(1+N99) -> 35762.231
C112: 기업가치 | D112: 403479.56 | N112: =+N111*N110 -> 550573.66
C114: NOA | D114: =+D115-J5 -> 20042.514 | N114: =+D114 -> 20042.514
C115: 주주가치 | D115: =+D112-D107 -> 224032.56 | N115: =+N112-N107 -> 491433.33
C116: 주당가치 | D116: =(D115-D114)/$J$6 -> 28.63 | N116: =(N115-N114)/$J$6 -> 66.159694
C119: 10년 동안의 주식가격 상승 | D119: =+N116/D116-1 -> 1.310852 | E119: =+(N116/D116)^(0.1)-1 -> 0.087369667 | F119: <--- 연평균 수익률 (IRR)
C120: 10년후 배당수익률 | D120: =+N98/D5 -> 0.089541606 | E120: =+SUM(E100:N100) -> 0.82018405 | F120: <--- 원금 회수율
C121: 10년후 총 수익률 | D121: =+D119+E120 -> 2.1310361 | E121: =+(1+D121)^(0.1)-1 -> 0.120905 | F121: <--- 연평균 수익률 (IRR)
B124: 시나리오 2. 채무부담으로 조정기간: 영업상황 약간 하락 & 배당 반토막 이후 정상화 & 가치평가 평균 회귀
D126: =+$D$96 -> 2024 | E126: =+D126+1 -> 2025 | F126: =+E126+1 -> 2026 | G126: =+F126+1 -> 2027 | H126: =+G126+1 -> 2028 | I126: =+H126+1 -> 2029 | J126: =+I126+1 -> 2030 | K126: =+J126+1 -> 2031 | L126: =+K126+1 -> 2032 | ... N126: =+M126+1 -> 2034
C127: 연차 | D127: 작년 | E127: 1 | F127: =E127+1 -> 2 | G127: =F127+1 -> 3 | H127: =G127+1 -> 4 | I127: =H127+1 -> 5 | J127: =I127+1 -> 6 | K127: =J127+1 -> 7 | L127: =K127+1 -> 8 | M127: =L127+1 -> 9 | N127: =M127+1 -> 10
C128: 주당 배당금 | D128: =+$D$6 -> 2.0969691 | E128: =D128*(1+E129) -> 1.0484846 | F128: =E128*(1+F129) -> 1.0799391 | G128: =F128*(1+G129) -> 1.1123373 | H128: =G128*(1+H129) -> 1.2458178 | I128: =H128*(1+I129) -> 1.3953159 | J128: =I128*(1+J129) -> 1.5627538 | K128: =J128*(1+K129) -> 1.7502842 | L128: =K128*(1+L129) -> 1.9603183 | ... N128: =M128*(1+N129) -> 2.4590233
C129: 연도별 변화율 | E129: -0.5 | F129: 0.03 | G129: 0.03 | H129: =$N133 -> 0.12 | I129: =$N133 -> 0.12 | J129: =$N133 -> 0.12 | K129: =$N133 -> 0.12 | L129: =$N133 -> 0.12 | M129: =$N133 -> 0.12 | N129: =$N133 -> 0.12
C130: 배당수익률 | E130: =+E128/$D$5 -> 0.036621885 | F130: =+F128/$D$5 -> 0.037720542 | G130: =+G128/$D$5 -> 0.038852158 | H130: =+H128/$D$5 -> 0.043514417 | I130: =+I128/$D$5 -> 0.048736147 | J130: =+J128/$D$5 -> 0.054584484 | K130: =+K128/$D$5 -> 0.061134622 | L130: =+L128/$D$5 -> 0.068470777 | ... N130: =+N128/$D$5 -> 0.085889743
C131: 총 배당금 | E131: =+$J$6*E128 -> 7470.5 | F131: =+$J$6*F128 -> 7694.615 | G131: =+$J$6*G128 -> 7925.4535 | H131: =+$J$6*H128 -> 8876.5079 | I131: =+$J$6*I128 -> 9941.6888 | J131: =+$J$6*J128 -> 11134.691 | K131: =+$J$6*K128 -> 12470.854 | L131: =+$J$6*L128 -> 13967.357 | ... N131: =+$J$6*N128 -> 17520.653
M133: 3년차 이후의 장기 성장율: | N133: 0.12
M134: 작년 대비 10년후 성장율: | N134: =N128/D128-1 -> 0.17265595
D136: =+D126 -> 2024 | E136: =+D136+1 -> 2025 | F136: =+E136+1 -> 2026 | G136: =+F136+1 -> 2027 | H136: =+G136+1 -> 2028 | I136: =+H136+1 -> 2029 | J136: =+I136+1 -> 2030 | K136: =+J136+1 -> 2031 | L136: =+K136+1 -> 2032 | ... N136: =+M136+1 -> 2034
C137: 차입금 | D137: =+D107 -> 179447 | E137: =+D137+E138 -> 159632.36 | F137: =+E137+F138 -> 139721.77 | G137: =+F137+G138 -> 119715.26 | H137: =+G137+H138 -> 107684.59 | I137: =+H137+I138 -> 87869.948 | J137: =+I137+J138 -> 67959.365 | K137: =+J137+K138 -> 47952.851 | L137: =+K137+L138 -> 35922.184 | ... N137: =+M137+N138 -> 16107.54
C138: 연간 차입금 상환금액 | D138: =+D108 -> -12030.667 | E138: =+$D$138-(E101-E131) -> -19814.644 | F138: =+$D$138-(F101-F131) -> -19910.583 | G138: =+$D$138-(G101-G131) -> -20006.514 | H138: =+D138 -> -12030.667 | I138: =+E138 -> -19814.644 | J138: =+F138 -> -19910.583 | K138: =+G138 -> -20006.514 | L138: =+H138 -> -12030.667 | M138: =+I138 -> -19814.644 | N138: 0
C140: =+$C$110 -> EV/FCF: | D140: =+D145/D144 -> 19.521599 | M140: 업계평균 EV/FCF: | N140: =+$N$110 -> 15.395395
C141: 자유현금흐름 (추정) | D141: =+D111 -> 29253 | E141: =+E111 -> 29866.757 | F141: =+F111 -> 30493.392 | G141: =+G111 -> 31133.174 | H141: =+H111 -> 31755.838 | I141: =+I111 -> 32390.954 | J141: =+J111 -> 33038.773 | K141: =+K111 -> 33699.549 | ... N141: =+N111 -> 35762.231
C142: ="Discount ("&O142&" 이내)" -> Discount (0.3 이내) | D142: =ABS(RAND())*$O$142 -> 0.27566158 | E142: =ABS(RAND())*$O$142 -> 0.22221089 | F142: =ABS(RAND())*$O$142 -> 0.2120352 | G142: =ABS(RAND())*$O$142 -> 0.19556995 | H142: =ABS(RAND())*$O$142 -> 0.28601275 | I142: =ABS(RAND())*$O$142 -> 0.14433488 | J142: =ABS(RAND())*$O$142 -> 0.14810289 | K142: =ABS(RAND())*$O$142 -> 0.11265673 | ... N142: =ABS(RAND())*$O$142 -> 0.28978502 | O142: 0.3
C143: =C142&" 값 붙여넣기" -> Discount (0.3 이내) 값 붙여넣기 | D143: 0.29346164 | E143: 0.28670019 | F143: 0.079243708 | G143: 0.022314943 | H143: 0.062482168 | I143: 0.080364891 | J143: 0.11951367 | K143: 0.27881105 | L143: 0.10315382 | M143: 0.20433481 | N143: 0.15241477
C144: 자유현금흐름 (시나리오 2.) | D144: =+D141*(1-D143) -> 20668.367 | E144: =+E141*(1-E143) -> 21303.952 | F144: =+F141*(1-F143) -> 28076.983 | G144: =+G141*(1-G143) -> 30438.439 | H144: =+H141*(1-H143) -> 29771.664 | I144: =+I141*(1-I143) -> 29787.859 | J144: =+J141*(1-J143) -> 29090.188 | K144: =+K141*(1-K143) -> 24303.742 | ... N144: =+N141*(1-N143) -> 30311.539
C145: 기업가치 | D145: =+D112 -> 403479.56 | N145: =+N144*N140 -> 466658.1
...

Sheet IBPE_배당 수익률 계산기 (정답)
A2: 배당 수익률 계산기 (정답)
D3: 2020 | E3: 2021 | F3: 2022 | G3: 2023 | H3: 2024 | I3: 2025 | J3: 2026 | K3: 2027 | L3: 2028 | M3: 2029 | N3: 2030
C5: 주식가격 | D5: =+현황판!E7 -> 28.63 | G5: 시가총액 (십억달러) | J5: =+D5*J6 -> 203990.05
C6: 주당 배당금 | D6: =+D5*현황판!G7 -> 2.0969691 | G6: 주식수 (백만주) | J6: 7125.0453
C7: 배당 성장률 | D7: =+현황판!G8 -> 0.020981007
B10: 시나리오 0. 손쉬운 계산
B12: x | C12: PV | D12: =PV(D13,D14,-D15,-D16,0) -> 25.72614
C13: 요구수익률 | D13: 0.1
C14: 투자기간 | D14: 5
C15: 주식 배당금 | D15: =+D6 -> 2.0969691
C16: 매각 예정가격 | D16: =+D5 -> 28.63
C18: PV 함수 풀이
D19: 2020 | E19: =+D19+1 -> 2021 | F19: =+E19+1 -> 2022 | G19: =+F19+1 -> 2023 | H19: =+G19+1 -> 2024 | I19: =+H19+1 -> 2025 | J19: =+I19 -> 2025
C20: 투자기간 | D20: 0 | E20: =+D20+1 -> 1 | F20: =+E20+1 -> 2 | G20: =+F20+1 -> 3 | H20: =+G20+1 -> 4 | I20: =+H20+1 -> 5 | J20: =+I20 -> 5
C21: 주당 배당금 | E21: =+$D$15 -> 2.0969691 | F21: =+$D$15 -> 2.0969691 | G21: =+$D$15 -> 2.0969691 | H21: =+$D$15 -> 2.0969691 | I21: =+$D$15 -> 2.0969691
C22: 매각 예정가격 | J22: =+D16 -> 28.63
C23: 할인계수 | E23: =(1+$D$13)^(COUNTA($E$21:E21)) -> 1.1 | F23: =(1+$D$13)^(COUNTA($E$21:F21)) -> 1.21 | G23: =(1+$D$13)^(COUNTA($E$21:G21)) -> 1.331 | H23: =(1+$D$13)^(COUNTA($E$21:H21)) -> 1.4641 | I23: =(1+$D$13)^(COUNTA($E$20:I20)) -> 1.61051 | J23: =+I23 -> 1.61051
C24: 현재가치 | E24: =+E21/E23 -> 1.9063356 | F24: =+F21/F23 -> 1.7330323 | G24: =+G21/G23 -> 1.5754839 | H24: =+H21/H23 -> 1.4322581 | I24: =+I21/I23 -> 1.3020528 | J24: =+J22/J23 -> 17.776977
I25: ∑현재가치: | J25: =SUM(E24:J24) -> 25.72614 | K25: =J25=D12 -> TRUE
B27: x | C27: PV | D27: =PV(D28,D29,-D30,-D31,0) -> 25.72614
C28: 요구수익률 | D28: =10% -> 0.1
C29: 투자기간 | D29: =5 -> 5 | G29: =SUM(H29:M29) -> -2.6398724 | H29: =+D49/E23 -> -26.027273 | I29: =+E50/F23 -> 1.7330323 | J29: =+F50/G23 -> 1.5754839 | K29: =+G50/H23 -> 1.4322581 | L29: =+H50/I23 -> 1.3020528 | M29: =+I50/(J23*1.1) -> 17.344573
C30: 주식 배당금 | D30: =+D6 -> 2.0969691 | G30: =G29=D43 -> FALSE
C31: 매각 예정가격 | D31: =+D5 -> 28.63
D33: * 증권을 발행한 사람의 기준
B35: x | C35: FV | D35: =FV(D36,D37,-D38,-D39,0) -> 58.911108 | G35: 투자기간 | H35: 1 | I35: =+H35+1 -> 2 | J35: =+I35+1 -> 3 | K35: =+J35+1 -> 4 | L35: 5 | M35: 5
C36: 요구수익률 | D36: 0.1 | G36: 주당 배당금 | H36: =E21 -> 2.0969691 | I36: =F21 -> 2.0969691 | J36: =G21 -> 2.0969691 | K36: =H21 -> 2.0969691 | L36: =I21 -> 2.0969691
C37: 투자기간 | D37: 5 | G37: 매각가격 | M37: =+D5 -> 28.63
C38: 쿠폰 수익 | D38: =D6 -> 2.0969691 | G38: 할증계수 | H38: =1.1^(COUNTA(I35:$L$35)) -> 1.4641 | I38: =1.1^(COUNTA(J35:$L$35)) -> 1.331 | J38: =1.1^(COUNTA(K35:$L$35)) -> 1.21 | K38: =1.1^(COUNTA(L35:$L$35)) -> 1.1 | L38: 1 | M38: 1
C39: 만기 상환금액 | D39: =+D5 -> 28.63 | G39: 현재가치 | H39: =+H36*H38 -> 3.0701725 | I39: =+I36*I38 -> 2.7910659 | J39: =+J36*J38 -> 2.5373327 | K39: =+K36*K38 -> 2.306666 | L39: =+L36*L38 -> 2.0969691 | M39: =+M37*M38 -> 28.63
L40: ∑현재가치: | M40: =SUM(H39:M39) -> 41.432206 | N40: =M40=D35 -> FALSE
D41: * 증권을 구매한 사람의 기준
E42: =+D27+D49 -> -2.9038597
B43: x | C43: NPV | D43: =NPV(D44,E50:I50)+D49 -> -2.9038597 | F43: =NPV(D44,D49:I50) -> -2.6398724
C44: 요구수익률 | D44: 0.1
C46: 성장률 미포함
D47: 2020 | E47: =+D47+1 -> 2021 | F47: =+E47+1 -> 2022 | G47: =+F47+1 -> 2023 | H47: =+G47+1 -> 2024 | I47: =+H47+1 -> 2025
C48: 투자기간 | D48: 0 | E48: 1 | F48: =+E48+1 -> 2 | G48: =+F48+1 -> 3 | H48: =+G48+1 -> 4 | I48: =+H48+1 -> 5
C49: 매입 가격 | D49: =-D5 -> -28.63
C50: 주당 배당금 | E50: =E21 -> 2.0969691 | F50: =F21 -> 2.0969691 | G50: =G21 -> 2.0969691 | H50: =H21 -> 2.0969691 | I50: =I21+J22 -> 30.726969 | J50: <- 매각 예정가격 포함
C52: 성장률 포함
C53: NPV w/ 성장률 | D53: =NPV(D54,E59:I59)+D58 -> -2.4226355
C54: 요구수익률 | D54: 0.1
C55: 성장률 포함 | D55: =+D7 -> 0.020981007
D56: 2020 | E56: =+D56+1 -> 2021 | F56: =+E56+1 -> 2022 | G56: =+F56+1 -> 2023 | H56: =+G56+1 -> 2024 | I56: =+H56+1 -> 2025 | J56: =+I56 -> 2025
C57: 투자기간 | D57: 0 | E57: 1 | F57: =+E57+1 -> 2 | G57: =+F57+1 -> 3 | H57: =+G57+1 -> 4 | I57: =+H57+1 -> 5
C58: 매입 가격 | D58: =-D5 -> -28.63
C59: 주당 배당금 | E59: =+E50*(1+$D$55) -> 2.1409657 | F59: =+E59*(1+$D$55) -> 2.1858853 | G59: =+F59*(1+$D$55) -> 2.2317473 | H59: =+G59*(1+$D$55) -> 2.2785717 | I59: =+H59*(1+$D$55)+J22 -> 30.956378 | J59: <- 매각 예정가격 포함
C62: NPV함수는 기본적으로 기말에 투자가 발생한 것으로 간주함, 첫 변수 부터 할인이 들어가는 것임
B64: x | C64: IRR | D64: =IRR(D68:I68) -> 0.07324377
D66: 2020 | E66: =+D66+1 -> 2021 | F66: =+E66+1 -> 2022 | G66: =+F66+1 -> 2023 | H66: =+G66+1 -> 2024 | I66: =+H66+1 -> 2025 | J66: =+I66 -> 2025
C67: 투자기간 | D67: 0 | E67: 1 | F67: =+E67+1 -> 2 | G67: =+F67+1 -> 3 | H67: =+G67+1 -> 4 | I67: =+H67+1 -> 5
C68: 현금 유입/(유출) | D68: =+D49 -> -28.63 | E68: =+E50 -> 2.0969691 | F68: =+F50 -> 2.0969691 | G68: =+G50 -> 2.0969691 | H68: =+H50 -> 2.0969691 | I68: =+I50 -> 30.726969
C71: 동일한지 Check <- goal check | D71: =K64-D44 -> -0.1
J72: =XNPV(D75,D78:K78,D77:K77) -> -1.2708692
B74: x | C74: XNPV | D74: =XNPV(D75,D78:K78,D77:K77) -> -1.2708692
C75: 요구수익률 | D75: 0.1
C77: 현금 유입/(유출) 시점 | D77: 43816 | E77: 43920 | F77: =+E77+365 -> 44285 | G77: =+F77+365 -> 44650 | H77: =+G77+365 -> 45015 | I77: =+H77+365 -> 45380 | J77: =+I77+365 -> 45745 | K77: =+J77+90 -> 45835
C78: 현금 유입/(유출) | D78: =-D5 -> -28.63 | E78: =+$D$6*(1+$D$7) -> 2.1409657 | F78: =E78*(1+$D$7) -> 2.1858853 | G78: =F78*(1+$D$7) -> 2.2317473 | H78: =G78*(1+$D$7) -> 2.2785717 | I78: =H78*(1+$D$7) -> 2.3263784 | J78: =I78*(1+$D$7) -> 2.3751881 | K78: =+J22 -> 28.63
B80: x | C80: XNPV TEST | D80: =XNPV(D81,D84:I84,D83:I83) -> -2.4212175 | F80: NPV w/ 성장률 | H80: =+D53 -> -2.4226355
C81: 요구수익률 | D81: 0.1
C83: 현금 유입/(유출) 시점 | D83: 44197 | E83: 44561 | F83: =+E83+365 -> 44926 | G83: =+F83+365 -> 45291 | H83: 45657 | I83: =+H83+365 -> 46022
C84: 현금 유입/(유출) | D84: =+D78 -> -28.63 | E84: =+E59 -> 2.1409657 | F84: =+F59 -> 2.1858853 | G84: =+G59 -> 2.2317473 | H84: =+H59 -> 2.2785717 | I84: =+I59 -> 30.956378
B86: x | C86: XIRR | D86: =XIRR(D89:K89,D88:K88) -> 0.088744757
C88: 현금 유입/(유출) 시점 | D88: =+D77 -> 43816 | E88: =+E77 -> 43920 | F88: =+F77 -> 44285 | G88: =+G77 -> 44650 | H88: =+H77 -> 45015 | I88: =+I77 -> 45380 | J88: =+J77 -> 45745 | K88: =+K77 -> 45835
C89: 현금 유입/(유출) | D89: =+D78 -> -28.63 | E89: =+E78 -> 2.1409657 | F89: =+F78 -> 2.1858853 | G89: =+G78 -> 2.2317473 | H89: =+H78 -> 2.2785717 | I89: =+I78 -> 2.3263784 | J89: =+J78 -> 2.3751881 | K89: =+K78 -> 28.63
C92: 만약 IRR을 요구수익률로 포함시킨다면?
B94: 시나리오 1. 현상유지: 영업상황 유지 & 배당 현상유지 & 가치평가 평균 회귀
D96: =YEAR(Cover!F6)-1 -> 2024 | E96: =+D96+1 -> 2025 | F96: =+E96+1 -> 2026 | G96: =+F96+1 -> 2027 | H96: =+G96+1 -> 2028 | I96: =+H96+1 -> 2029 | J96: =+I96+1 -> 2030 | K96: =+J96+1 -> 2031 | L96: =+K96+1 -> 2032 | ... N96: =+M96+1 -> 2034
C97: 연차 | D97: 작년 | E97: 1 | F97: =E97+1 -> 2 | G97: =F97+1 -> 3 | H97: =G97+1 -> 4 | I97: =H97+1 -> 5 | J97: =I97+1 -> 6 | K97: =J97+1 -> 7 | L97: =K97+1 -> 8 | M97: =L97+1 -> 9 | N97: =M97+1 -> 10
C98: 주당 배당금 | D98: =+D6 -> 2.0969691 | E98: =D98*(1+E99) -> 2.1409657 | F98: =E98*(1+F99) -> 2.1858853 | G98: =F98*(1+G99) -> 2.2317473 | H98: =G98*(1+H99) -> 2.2763823 | I98: =H98*(1+I99) -> 2.3219099 | J98: =I98*(1+J99) -> 2.3683481 | K98: =J98*(1+K99) -> 2.4157151 | L98: =K98*(1+L99) -> 2.4640294 | ... N98: =M98*(1+N99) -> 2.5635762
C99: 연도별 변화율 | E99: =+$D$7 -> 0.020981007 | F99: =+E99 -> 0.020981007 | G99: =+F99 -> 0.020981007 | H99: =$N$103 -> 0.02 | I99: =$N$103 -> 0.02 | J99: =$N$103 -> 0.02 | K99: =$N$103 -> 0.02 | L99: =$N$103 -> 0.02 | M99: =$N$103 -> 0.02 | N99: =$N$103 -> 0.02
C100: 배당수익률 | E100: =+E98/$D$5 -> 0.074780498 | F100: =+F98/$D$5 -> 0.076349468 | G100: =+G98/$D$5 -> 0.077951357 | H100: =+H98/$D$5 -> 0.079510384 | I100: =+I98/$D$5 -> 0.081100592 | J100: =+J98/$D$5 -> 0.082722603 | K100: =+K98/$D$5 -> 0.084377056 | L100: =+L98/$D$5 -> 0.086064597 | ... N100: =+N98/$D$5 -> 0.089541606
C101: 총 배당금 | E101: =+$J$6*E98 -> 15254.477 | F101: =+$J$6*F98 -> 15574.532 | G101: =+$J$6*G98 -> 15901.301 | H101: =+$J$6*H98 -> 16219.327 | I101: =+$J$6*I98 -> 16543.713 | J101: =+$J$6*J98 -> 16874.588 | K101: =+$J$6*K98 -> 17212.079 | L101: =+$J$6*L98 -> 17556.321 | ... N101: =+$J$6*N98 -> 18265.596
M103: 3년차 이후의 장기 성장율: | N103: 0.02
M104: 작년 대비 10년후 성장율: | N104: =N98/D98-1 -> 0.22251499
D106: =+D96 -> 2024 | E106: =+D106+1 -> 2025 | F106: =+E106+1 -> 2026 | G106: =+F106+1 -> 2027 | H106: =+G106+1 -> 2028 | I106: =+H106+1 -> 2029 | J106: =+I106+1 -> 2030 | K106: =+J106+1 -> 2031 | L106: =+K106+1 -> 2032 | ... N106: =+M106+1 -> 2034
C107: 차입금 | D107: =+'Data_ AT&T 데이터'!I33 -> 179447 | E107: =+D107+E108 -> 167416.33 | F107: =+E107+F108 -> 155385.67 | G107: =+F107+G108 -> 143355 | H107: =+G107+H108 -> 131324.33 | I107: =+H107+I108 -> 119293.67 | J107: =+I107+J108 -> 107263 | K107: =+J107+K108 -> 95232.333 | L107: =+K107+L108 -> 83201.667 | ... N107: =+M107+N108 -> 59140.333
C108: 연간 차입금 상환금액 | D108: -12030.667 | E108: =+D108 -> -12030.667 | F108: =+E108 -> -12030.667 | G108: =+F108 -> -12030.667 | H108: =+G108 -> -12030.667 | I108: =+H108 -> -12030.667 | J108: =+I108 -> -12030.667 | K108: =+J108 -> -12030.667 | L108: =+K108 -> -12030.667 | ... N108: =+M108 -> -12030.667
C110: =+현황판!C20 -> EV/FCF: | D110: =+D112/D111 -> 13.792758 | M110: 업계평균 EV/FCF: | N110: =+현황판!E20 -> 15.395395
C111: 자유현금흐름 | D111: 29253 | E111: =+D111*(1+E99) -> 29866.757 | F111: =+E111*(1+F99) -> 30493.392 | G111: =+F111*(1+G99) -> 31133.174 | H111: =+G111*(1+H99) -> 31755.838 | I111: =+H111*(1+I99) -> 32390.954 | J111: =+I111*(1+J99) -> 33038.773 | K111: =+J111*(1+K99) -> 33699.549 | L111: =+K111*(1+L99) -> 34373.54 | ... N111: =+M111*(1+N99) -> 35762.231
C112: 기업가치 | D112: 403479.56 | N112: =+N111*N110 -> 550573.66
C114: NOA | D114: =+D115-J5 -> 20042.514 | N114: =+D114 -> 20042.514
C115: 주주가치 | D115: =+D112-D107 -> 224032.56 | N115: =+N112-N107 -> 491433.33
C116: 주당가치 | D116: =(D115-D114)/$J$6 -> 28.63 | N116: =(N115-N114)/$J$6 -> 66.159694
C119: 10년 동안의 주식가격 상승 | D119: =+N116/D116-1 -> 1.310852 | E119: =+(N116/D116)^(0.1)-1 -> 0.087369667 | F119: <--- 연평균 수익률 (IRR) | K119: =+D119/D121 -> 0.61512428
C120: 10년후 배당수익률 | D120: =+N98/D5 -> 0.089541606 | E120: =+SUM(E100:N100) -> 0.82018405 | F120: <--- 원금 회수율 | K120: =+E120/D121 -> 0.38487572
C121: 10년후 총 수익률 | D121: =+D119+E120 -> 2.1310361 | E121: =+(1+D121)^(0.1)-1 -> 0.120905 | F121: <--- 연평균 수익률 (IRR)
B124: 시나리오 2. 채무부담으로 조정기간: 영업상황 약간 하락 & 배당 반토막 이후 정상화 & 가치평가 평균 회귀
D126: =+$D$96 -> 2024 | E126: =+D126+1 -> 2025 | F126: =+E126+1 -> 2026 | G126: =+F126+1 -> 2027 | H126: =+G126+1 -> 2028 | I126: =+H126+1 -> 2029 | J126: =+I126+1 -> 2030 | K126: =+J126+1 -> 2031 | L126: =+K126+1 -> 2032 | ... N126: =+M126+1 -> 2034
C127: 연차 | D127: 작년 | E127: 1 | F127: =E127+1 -> 2 | G127: =F127+1 -> 3 | H127: =G127+1 -> 4 | I127: =H127+1 -> 5 | J127: =I127+1 -> 6 | K127: =J127+1 -> 7 | L127: =K127+1 -> 8 | M127: =L127+1 -> 9 | N127: =M127+1 -> 10
C128: 주당 배당금 | D128: =+$D$6 -> 2.0969691 | E128: =D128*(1+E129) -> 1.0484846 | F128: =E128*(1+F129) -> 1.0799391 | G128: =F128*(1+G129) -> 1.1123373 | H128: =G128*(1+H129) -> 1.2458178 | I128: =H128*(1+I129) -> 1.3953159 | J128: =I128*(1+J129) -> 1.5627538 | K128: =J128*(1+K129) -> 1.7502842 | L128: =K128*(1+L129) -> 1.9603183 | ... N128: =M128*(1+N129) -> 2.4590233
C129: 연도별 변화율 | E129: -0.5 | F129: 0.03 | G129: 0.03 | H129: =$N133 -> 0.12 | I129: =$N133 -> 0.12 | J129: =$N133 -> 0.12 | K129: =$N133 -> 0.12 | L129: =$N133 -> 0.12 | M129: =$N133 -> 0.12 | N129: =$N133 -> 0.12
C130: 배당수익률 | E130: =+E128/$D$5 -> 0.036621885 | F130: =+F128/$D$5 -> 0.037720542 | G130: =+G128/$D$5 -> 0.038852158 | H130: =+H128/$D$5 -> 0.043514417 | I130: =+I128/$D$5 -> 0.048736147 | J130: =+J128/$D$5 -> 0.054584484 | K130: =+K128/$D$5 -> 0.061134622 | L130: =+L128/$D$5 -> 0.068470777 | ... N130: =+N128/$D$5 -> 0.085889743
C131: 총 배당금 | E131: =+$J$6*E128 -> 7470.5 | F131: =+$J$6*F128 -> 7694.615 | G131: =+$J$6*G128 -> 7925.4535 | H131: =+$J$6*H128 -> 8876.5079 | I131: =+$J$6*I128 -> 9941.6888 | J131: =+$J$6*J128 -> 11134.691 | K131: =+$J$6*K128 -> 12470.854 | L131: =+$J$6*L128 -> 13967.357 | ... N131: =+$J$6*N128 -> 17520.653
M133: 3년차 이후의 장기 성장율: | N133: 0.12
M134: 작년 대비 10년후 성장율: | N134: =N128/D128-1 -> 0.17265595
D136: =+D126 -> 2024 | E136: =+D136+1 -> 2025 | F136: =+E136+1 -> 2026 | G136: =+F136+1 -> 2027 | H136: =+G136+1 -> 2028 | I136: =+H136+1 -> 2029 | J136: =+I136+1 -> 2030 | K136: =+J136+1 -> 2031 | L136: =+K136+1 -> 2032 | ... N136: =+M136+1 -> 2034
C137: 차입금 | D137: =+D107 -> 179447 | E137: =+D137+E138 -> 159632.36 | F137: =+E137+F138 -> 139721.77 | G137: =+F137+G138 -> 119715.26 | H137: =+G137+H138 -> 107684.59 | I137: =+H137+I138 -> 87869.948 | J137: =+I137+J138 -> 67959.365 | K137: =+J137+K138 -> 47952.851 | L137: =+K137+L138 -> 35922.184 | ... N137: =+M137+N138 -> 16107.54
C138: 연간 차입금 상환금액 | D138: =+D108 -> -12030.667 | E138: =+$D$138-(E101-E131) -> -19814.644 | F138: =+$D$138-(F101-F131) -> -19910.583 | G138: =+$D$138-(G101-G131) -> -20006.514 | H138: =+D138 -> -12030.667 | I138: =+E138 -> -19814.644 | J138: =+F138 -> -19910.583 | K138: =+G138 -> -20006.514 | L138: =+H138 -> -12030.667 | M138: =+I138 -> -19814.644 | N138: 0
...

Sheet Data_ AT&T 데이터
A2: ="Data from S&P Capital IQ - "&'Data_ AT&T 데이터'!D4 -> Data from S&P Capital IQ - AT&T Inc. (NYSE:T)
C3: CIQ Ticker: | D3: NYSE:T | F3: Tax rate: | G3: 0.21
D4: AT&T Inc. (NYSE:T) | F4: Currency: | G4: USD
F5: Date: | G5: 44228
A7: x | B7: 가치평가에 필요한 주요 재무 항목들
D9: 2016 | E9: 2017 | F9: 2018 | G9: 2019 | H9: 2020 | I9: 2020 Latest LTM | K9: CIQ Formula | L9: Used Values
C10: Revenue | D10: 163786 | E10: 160546 | F10: 170756 | G10: 181193 | H10: 171760 | I10: 171760 | K10: IQ_TOTAL_REV
C11: EBIT | D11: 24905 | E11: 23995 | F11: 31618 | G11: 27741 | H11: 25285 | I11: 25285 | K11: IQ_OPER_INC
C12: EBITDA | D12: 48390 | E12: 45572 | F12: 56956 | G12: 52645 | H12: 53801 | I12: 53801 | K12: IQ_EBITDA | L12: =+AVERAGE(D12:I12) -> 51860.833
C13: D&A | D13: 23485 | E13: 21577 | F13: 25338 | G13: 24904 | H13: 28516 | I13: 28516
C14: Net Income to Company | D14: 13333 | E14: 29847 | F14: 19953 | G14: 14975 | H14: -3821 | I14: -3821 | K14: IQ_NI_COMPANY
C15: Net Income | D15: 12976 | E15: 29450 | F15: 19370 | G15: 13903 | H15: -5176 | I15: -5176 | K15: IQ_NI | L15: =+AVERAGE(D15:I15) -> 10891.167
C17: EBIT Margin | D17: 0.15205817 | E17: 0.14945872 | F17: 0.1851648 | G17: 0.15310194 | H17: 0.14721122 | I17: 0.14721122
C18: EBITDA Margin | D18: 0.2954465 | E18: 0.28385634 | F18: 0.33355197 | G18: 0.29054654 | H18: 0.31323358 | I18: 0.31323358
C19: NI Margin | D19: 0.081405004 | E19: 0.18590933 | F19: 0.11685095 | G19: 0.082646681 | H19: -0.022246157 | I19: -0.022246157
C21: Capex | D21: -22408 | E21: -21550 | F21: -21251 | G21: -19635 | H21: -15675 | I21: -15675 | K21: IQ_CAPEX
C22: Increase in Intangibles | D22: 0 | E22: 0 | F22: 0 | G22: 0 | H22: 0 | I22: 0 | K22: IQ_SALE_INTAN_CF
C23: Asset Sale | D23: 646 | E23: 59 | F23: 2148 | G23: 4684 | H23: 3641 | I23: 3641 | K23: IQ_SALE_PPE_CF
C25: Unlevered FCF | D25: 21397.95 | E25: 19042.05 | F25: 31213.22 | G25: 31868.39 | H25: 36457.15 | I25: 36457.15 | L25: =+AVERAGE(D25:I25) -> 29405.985
C26: Levered FCF | D26: 1959.6 | E26: 12969.3 | F26: 7694.3 | G26: 4687.6 | H26: -6638.7 | I26: -6638.7 | L26: =+AVERAGE(D26:I26) -> 2338.9
C28: CFO | D28: 38442 | E28: 38010 | F28: 43602 | G28: 48668 | H28: 43130 | I28: 43130 | K28: IQ_CASH_OPER
C29: CFI | D29: -23318 | E29: -18943 | F29: -63145 | G29: -16690 | H29: -13548 | I29: -13548 | K29: IQ_CASH_INVEST
C30: CFF | D30: -14462 | E30: 25930 | F30: -25989 | G30: -25083 | H30: -32007 | I30: -32007 | K30: IQ_CASH_FINAN
C32: Cash | D32: 5788 | E32: 50498 | F32: 5204 | G32: 12186 | H32: 9740 | I32: 9740 | K32: IQ_cash_st_invest
C33: Total Debt | D33: 127394 | E33: 165667 | F33: 179107 | G33: 191684 | H33: 179447 | I33: 179447 | K33: IQ_TOTAL_DEBT
C34: Mandatory Debt Repayment | D34: =+D33/$K$34 -> 8492.9333 | E34: =+E33/$K$34 -> 11044.467 | F34: =+F33/$K$34 -> 11940.467 | G34: =+G33/$K$34 -> 12778.933 | H34: =+H33/$K$34 -> 11963.133 | I34: =+I33/$K$34 -> 11963.133 | K34: 15
C35: Other LT Assets | D35: 16812 | E35: 18427 | F35: 22999 | G35: 24368 | H35: 38369 | I35: 38369 | K35: IQ_OTHER_LT_ASSETS
C36: LT Investments | D36: 1674 | E36: 1577 | F36: 6245 | G36: 5085 | H36: 1780 | I36: 1780 | K36: IQ_LT_INVEST
C37: Total Common Equity | D37: 123135 | E37: 140861 | F37: 184089 | G37: 184221 | H37: 161673 | I37: 161673 | K37: IQ_TOTAL_COMMON_EQUITY
C38: Total Equity | D38: 124110 | E38: 142007 | F38: 193884 | G38: 201934 | H38: 179240 | I38: 179240 | K38: IQ_TOTAL_EQUITY
C40: ROE | D40: =+D15/D37 -> 0.10538027 | E40: =+E15/E37 -> 0.20907135 | F40: =+F15/F37 -> 0.10522084 | G40: =+G15/G37 -> 0.075469138 | H40: =+H15/H37 -> -0.032015241 | I40: =+I15/I37 -> -0.032015241 | L40: =+AVERAGE(D40:I40) -> 0.071851855
C41: ROE adj. | D41: =+D15/(D37-D32) -> 0.11057803 | E41: =+E15/(E37-E32) -> 0.32590773 | F41: =+F15/(F37-F32) -> 0.10828186 | G41: =+G15/(G37-G32) -> 0.08081495 | H41: =+H15/(H37-H32) -> -0.034067648 | I41: =+I15/(I37-I32) -> -0.034067648 | L41: =+AVERAGE(D41:I41) -> 0.092907878
A44: x | B44: Graphs
C46: 손익계산서 그래프
C65: 현금흐름표 그래프
C84: ROE와 adjusted ROE 그래프
C103: FCF
A123: x | B123: x | C123: x

Sheet Data_CIQ 다운로드
A2: Data from S&P Capital IQ
C3: CIQ Ticker: | D3: NYSE:T | F3: Tax rate: | G3: 0.21
D4: AT&T Inc. (NYSE:T) | F4: Currency: | G4: USD
F5: Date: | G5: 44323
A7: x | B7: 가치평가에 필요한 주요 재무 항목들
D9: 2016 | E9: 2017 | F9: 2018 | G9: 2019 | H9: 2020 | I9: 2021 Latest LTM | K9: CIQ Formula | L9: Used Values
C10: Revenue | D10: 163786 | E10: 160546 | F10: 170756 | G10: 181193 | H10: 171760 | I10: 172920 | K10: IQ_TOTAL_REV
C11: EBIT | D11: 24905 | E11: 23995 | F11: 31618 | G11: 27741 | H11: 25656 | I11: 25708 | K11: IQ_OPER_INC
C12: EBITDA | D12: 48390 | E12: 45572 | F12: 56956 | G12: 52645 | H12: 50689 | I12: 49328 | K12: IQ_EBITDA | L12: 50596.667
C13: D&A | D13: 23485 | E13: 21577 | F13: 25338 | G13: 24904 | H13: 25033 | I13: 23620
C14: Net Income to Company | D14: 13333 | E14: 29847 | F14: 19953 | G14: 14975 | H14: -3821 | I14: -842 | K14: IQ_NI_COMPANY
C15: Net Income | D15: 12976 | E15: 29450 | F15: 19370 | G15: 13903 | H15: -5176 | I15: -2236 | K15: IQ_NI | L15: 11381.167
C17: EBIT Margin | D17: 0.15205817 | E17: 0.14945872 | F17: 0.1851648 | G17: 0.15310194 | H17: 0.14937122 | I17: 0.14866991
C18: EBITDA Margin | D18: 0.2954465 | E18: 0.28385634 | F18: 0.33355197 | G18: 0.29054654 | H18: 0.29511528 | I18: 0.28526486
C19: NI Margin | D19: 0.081405004 | E19: 0.18590933 | F19: 0.11685095 | G19: 0.082646681 | H19: -0.022246157 | I19: -0.0048693037
C21: Capex | D21: -22408 | E21: -21550 | F21: -21251 | G21: -19635 | H21: -15675 | I21: -14742 | K21: IQ_CAPEX
C22: Increase in Intangibles | D22: 0 | E22: 0 | F22: 0 | G22: 0 | H22: 0 | I22: 0 | K22: IQ_SALE_INTAN_CF
C23: Asset Sale | D23: 646 | E23: 59 | F23: 2148 | G23: 4684 | H23: 3641 | I23: 3574 | K23: IQ_SALE_PPE_CF
C25: Unlevered FCF | D25: 21397.95 | E25: 19042.05 | F25: 31213.22 | G25: 31868.39 | H25: 33267.24 | I25: 32761.32 | L25: 28258.362
C26: Levered FCF | D26: 1959.6 | E26: 12969.3 | F26: 7694.3 | G26: 5015.8 | H26: -10475.4 | I26: -9980.5 | L26: 1197.1833
C28: CFO | D28: 38442 | E28: 38010 | F28: 43602 | G28: 48668 | H28: 43130 | I28: 44191 | K28: IQ_CASH_OPER
C29: CFI | D29: -23318 | E29: -18943 | F29: -63145 | G29: -16690 | H29: -13548 | I29: -35378 | K29: IQ_CASH_INVEST
C30: CFF | D30: -14462 | E30: 25930 | F30: -25989 | G30: -25083 | H30: -32007 | I30: -7425 | K30: IQ_CASH_FINAN
C32: Cash | D32: 5788 | E32: 50498 | F32: 5204 | G32: 12130 | H32: 9769 | I32: 11342 | K32: IQ_cash_st_invest
C33: Total Debt | D33: 127394 | E33: 165667 | F33: 179107 | G33: 188402 | H33: 182984 | I33: 201965 | K33: IQ_TOTAL_DEBT
C34: Mandatory Debt Repayment | D34: 12739.4 | E34: 16566.7 | F34: 17910.7 | G34: 18840.2 | H34: 18298.4 | I34: 20196.5 | K34: 10
C35: Other LT Assets | D35: 16812 | E35: 18427 | F35: 22999 | G35: 25747 | H35: 28087 | I35: 60528 | K35: IQ_OTHER_LT_ASSETS
C36: LT Investments | D36: 1674 | E36: 1577 | F36: 6245 | G36: 3706 | H36: 3230 | I36: 1805 | K36: IQ_LT_INVEST
C37: Total Common Equity | D37: 123135 | E37: 140861 | F37: 184089 | G37: 184221 | H37: 161673 | I37: 165488 | K37: IQ_TOTAL_COMMON_EQUITY
C38: Total Equity | D38: 124110 | E38: 142007 | F38: 193884 | G38: 201934 | H38: 179240 | I38: 183079 | K38: IQ_TOTAL_EQUITY
C40: ROE | D40: 0.10538027 | E40: 0.20907135 | F40: 0.10522084 | G40: 0.075469138 | H40: -0.032015241 | I40: -0.013511554 | L40: 0.074935803
C41: ROE adj. | D41: 0.11057803 | E41: 0.32590773 | F41: 0.10828186 | G41: 0.080788653 | H41: -0.034074152 | I41: -0.014505728 | L41: 0.096162731
A44: x | B44: Graphs
C46: 손익계산서 그래프
C65: 현금흐름표 그래프
C84: ROE와 adjusted ROE 그래프
C103: FCF
A123: x | B123: x | C123: x

Sheet CR
B2: © 2016 홍성현, (주)월스트릿트레이닝아시아.
B3: No portion of this report may be reproduced, reused, or otherwise distributed in any form without prior written consent.
B4: For more information, please visit/contatct (주)월스트릿트레이닝아시아 through www.wallstreettraining.co.kr
B5: 이 파일은 대한민국 및 미국 저작권법의 보호를 받는 저작물 입니다.
B6: 파일의 원 저자로부터 서면에 의한 허락없이 이 파일의 일부나 전체를 어떠한 형태로도 가공/배포할 수 없습니다.
B7: 이를 위반시에는 형사/민사상의 법적 책임을 질수 있으며, 특별한 문의가 있는경우
B8: www.wallstreettraining.co.kr에 있는 정보로 연락주시기 바랍니다.
