Workbook
Name Ccy: WACC!$E$1
Name circ: [1]Cover!$K$6
Name Circ: Cover!$K$6
Name Conv: WACC!$AP$24
Name Date: WACC!$H$1
Name Days: #REF!
Name Days: 'Working Capital'!$H$30
Name Fil: WACC!$AQ$27
Name GVKey: ""
Name img_1675017080: SHAK_10K!#REF!
Name IQ_CH: 110000
Name IQ_CQ: 5000
Name IQ_CY: 10000
Name IQ_DAILY: 500000
Name IQ_FH: 100000
Name IQ_FQ: 500
Name IQ_FY: 1000
Name IQ_LTM: 2000
Name IQ_MONTH: 15000
Name IQ_NTM: 6000
Name IQ_WEEK: 50000
Name IQ_YTD: 3000
Name List: 'Input Tab'!$AD$15:$AD$19
Name SPSet: "current"
Name SPWS_WBID: "D37EBD5C-BA90-4B94-B2F1-78539D014FA9"

Sheet _CIQHiddenCacheSheet
A1: 26 | B1: AwABTAVMT0NBTAFI/////wFQuQAAACNDSVEuS1IuSVFfRlhfUkFURS5ERUMyMDEzLjgvMjUvMjAxNwEAAADIS5MGAgAAAAsxMDU3LjEwOTA5MQCqPkp9LevVCPiMZn0t69UIMENJUS5ORExTLklRX1BSRUZfRVFVSVRZLjUwMC4yMDE4LTA3LTEwLkxGUi4uVVNELgEAAAD5n3sAAwAAAAAAFPwQcS/r1Qh2NzSKL+vVCCRDSVEuQ01HLklRX01BUktFVENBUC4yMDE4LTA3LTEwLlVTRC4BAAAATmcAAAIAAAALMTI2MjQuMDE5MzIBBgAAAAUAAAABMQEAAAAKMTg4NDk2MzMzMAMAAAADMTYwAgAAAAYxMDAwNTQEAAAAATAHAAAACTcvMTAvMjAxOBT8EHEv69UIdjc0ii/r1QgjQ0lRLktSLklRX0ZYX1JBVEUuU0VQMjAxNS44LzI1LzIwMTcBAAAAyEuTBgIAAAALMTE4NS4yNDA5MDkAqj5KfS3r1QgHZmZ9LevVCCtDSVEuTllTRTpTSEFLLklRX0VCVC4uMjAxOC0wNy0xMC5MRlIuLlVTRC5IAQAAAJ0Tpg0CAAAABjE2MC45NQEIAAAABQAAAAExAQAAAAoxODg3MjkwNTQxAwAAAAMxNjACAAAAAzEzOQQAAAABMAcAAAAJNy8xMC8yMDE4CAAAAAkzLzI4LzIwMTgJAAAAATBOt2twL+vVCFRmdLcv69UII0NJUS5LUi5JUV9GWF9SQVRFLk5PVjIwMTUuOC8yNS8yMDE3AQAAAMhLkwYCAAAACzExNTIuOTM4MDk1AKo+Sn0t69UIB2ZmfS3r1QgwQ0lRLlpPRVMuSVFfUFJFRl9FUVVJVFkuNTAwLjIwMTgtMDctMTAuTEZSLi5V | C1: U0QuAQAAANTGTwIDAAAAAAAU/BBxL+vVCG5eNIov69UIMUNJUS5IQUJULklRX1BSRUZfRVFVSVRZLjUwMC4yMDE4LTA3LTEwLkxGUi4uVVNELkgBAAAAI9YREAMAAAAAAIIe/FQv69UIVoU0ii/r1QgmQ0lRLk5ZU0U6TUNELklRX0NPTVBBTllfVElDS0VSX05PX0VYQ0gBAAAA4CACAAMAAAADTUNEAKFSM1Qv69UIghA0ii/r1QgtQ0lRQVZHLk5ETFMuSVFfRUZGRUNUX1RBWF9SQVRFLjk5Ni4yMDE4LTA3LTEwAQAAAPmfewACAAAABzQwLjA0NjEAgh78VC/r1QhuXjSKL+vVCB1DSVEuTllTRTpTSEFLLklRX1FVSUNLX0NPTVAuNgEAAACdE6YNAwAAAAhOWVNFOk1DRABOt2twL+vVCIIQNIov69UIL0NJUS5DTUcuSVFfVE9UQUxfREVCVC41MDAuMjAxOC0wNy0xMC5MRlIuLlVTRC5IAQAAAE5nAAACAAAAATABCAAAAAUAAAABMQEAAAAKMTg4NDk2MzMzMAMAAAADMTYwAgAAAAQ0MTczBAAAAAEwBwAAAAk3LzEwLzIwMTgIAAAACTMvMzEvMjAxOAkAAAABMIIe/FQv69UIUqw0ii/r1QgmQ0lRLktSLklRX0ZYX1JBVEVfRkMuU0VQMjAxOS44LzI0LzIwMTcBAAAAxDGUBgIAAAAKMTExNS41NzgzOQCqPkp9LevVCAE/Zn0t69UIKkNJUS5OWVNFOlNIQUsuSVFfRUJULi4yMDE4LTA3LTEwLkxGUi4uVVNELgEAAACdE6YNAgAAAAYxNjAuOTUBCAAAAAUAAAABMQEAAAAKMTg4NzI5MDU0MQMAAAADMTYwAgAAAAMxMzkE | D1: AAAAATAHAAAACTcvMTAvMjAxOAgAAAAJMy8yOC8yMDE4CQAAAAEwFPwQcS/r1QhUZnS3L+vVCCZDSVEuS1IuSVFfRlhfUkFURV9GQy5NQVkyMDIwLjgvMjQvMjAxNwEAAADEMZQGAgAAAAoxMTMyLjExMzQyAKo+Sn0t69UIAT9mfS3r1QgvQ0lRLk1DRC5JUV9UT1RBTF9ERUJULjUwMC4yMDE4LTA3LTEwLkxGUi4uVVNELkgBAAAA4CACAAIAAAAFMzA4ODgBCAAAAAUAAAABMQEAAAAKMTg4NzY2NTU5NgMAAAADMTYwAgAAAAQ0MTczBAAAAAEwBwAAAAk3LzEwLzIwMTgIAAAACTMvMzEvMjAxOAkAAAABMIIe/FQv69UIVEQkiy/r1Qg+Q0lRUkFOR0UuTllTRTpTSEFLLklRX0ZJWEVEX0lOQ09NRV9MSVNULjEuNTAwLi4uLi5GSVhFRCBJTkNPTUUDAAAAnROmDQAAAABOt2twL+vVCGw/dLcv69UIF0NJUS5NQ0QuSVFfQ09NUEFOWV9OQU1FAQAAAOAgAgADAAAAFk1jRG9uYWxkJ3MgQ29ycG9yYXRpb24Agh78VC/r1Qh2NzSKL+vVCBhDSVEuTkRMUy5JUV9DT01QQU5ZX05BTUUBAAAA+Z97AAMAAAARTm9vZGxlcyAmIENvbXBhbnkAgh78VC/r1QhuXjSKL+vVCCZDSVEuS1IuSVFfRlhfUkFURV9GQy5BUFIyMDIwLjgvMjQvMjAxNwEAAADEMZQGAgAAAAoxMTI4Ljg0NjM5AKo+Sn0t69UIAT9mfS3r1QgmQ0lRLkhBQlQuSVFfTUFSS0VUQ0FQLjIwMTgtMDctMTAuVVNELkgBAAAAI9YREAIAAAAKMjE1LjI5NTUyOAEG | E1: AAAABQAAAAExAQAAAAoxODg2NDUxNTgyAwAAAAMxNjACAAAABjEwMDA1NAQAAAABMAcAAAAJNy8xMC8yMDE4gh78VC/r1QhWhTSKL+vVCDFDSVEuWk9FUy5JUV9QUkVGX0VRVUlUWS41MDAuMjAxOC0wNy0xMC5MRlIuLlVTRC5IAQAAANTGTwIDAAAAAACCHvxUL+vVCFaFNIov69UII0NJUS5LUi5JUV9GWF9SQVRFLkRFQzIwMTUuOC8yNS8yMDE3AQAAAMhLkwYCAAAACzExNzIuMjEzMDQzAKo+Sn0t69UI+IxmfS3r1QgrQ0lRLk5ZU0U6U0hBSy5JUV9NQVJLRVRDQVAuMjAxOC0wNy0xMC5VU0QuSAEAAACdE6YNAgAAAAsxNzcxLjU5MTI3NgEGAAAABQAAAAExAQAAAAoxODg3MjkwMTI1AwAAAAMxNjACAAAABjEwMDA1NAQAAAABMAcAAAAJNy8xMC8yMDE4TrdrcC/r1QhUZnS3L+vVCBxDSVEuTllTRTpTSEFLLklRX1FVSUNLX0NPTVAuAQAAAJ0Tpg0DAAAACU5ZU0U6Wk9FUwAU/BBxL+vVCBT8EHEv69UII0NJUS5LUi5JUV9GWF9SQVRFLkpVTDIwMTMuOC8yNS8yMDE3AQAAAMhLkwYCAAAACzExMjYuNTc4MjYxAKo+Sn0t69UI+IxmfS3r1QgsQ0lRQVZHLk1DRC5JUV9FRkZFQ1RfVEFYX1JBVEUuOTk2LjIwMTgtMDctMTABAAAA4CACAAIAAAAIMzMuODkzODgAgh78VC/r1QhuXjSKL+vVCC9DSVEuTllTRTpTSEFLLklRX1BFUklPRERBVEUuMTAwMC4yMDE4LTA3LTEwLkxGUgEAAACdE6YNBQAAAAoyMDE3LTEy | F1: LTI3AE63a3Av69UIVGZ0ty/r1QgjQ0lRLktSLklRX0ZYX1JBVEUuTUFZMjAxMy44LzI1LzIwMTcBAAAAyEuTBgIAAAALMTExMC40OTU2NTIAvhdKfS3r1Qj4jGZ9LevVCCNDSVEuS1IuSVFfRlhfUkFURS5KVU4yMDEzLjgvMjUvMjAxNwEAAADIS5MGAgAAAAcxMTM0LjU0AKo+Sn0t69UI+IxmfS3r1QgjQ0lRLktSLklRX0ZYX1JBVEUuSkFOMjAxNS44LzI1LzIwMTcBAAAAyEuTBgIAAAALMTA4OS42NDA5MDkAqj5KfS3r1QgHZmZ9LevVCCZDSVEuS1IuSVFfRlhfUkFURV9GQy5KQU4yMDE5LjgvMjQvMjAxNwEAAADEMZQGAgAAAAoxMTAxLjYwMjY3AKo+Sn0t69UIAT9mfS3r1QguQ0lRLk5ZU0U6U0hBSy5JUV9JTkNfVEFYLi4yMDE4LTA3LTEwLkxGUi4uVVNELgEAAACdE6YNAgAAAAcxNTAuOTQ5AQgAAAAFAAAAATEBAAAACjE4ODcyOTA1NDEDAAAAAzE2MAIAAAACNzUEAAAAATAHAAAACTcvMTAvMjAxOAgAAAAJMy8yOC8yMDE4CQAAAAEwFPwQcS/r1QhUZnS3L+vVCDBDSVEuQ01HLklRX1BSRUZfRVFVSVRZLjUwMC4yMDE4LTA3LTEwLkxGUi4uVVNELkgBAAAATmcAAAMAAAAAAIIe/FQv69UIUqw0ii/r1QgjQ0lRLktSLklRX0ZYX1JBVEUuU0VQMjAxMy44LzI1LzIwMTcBAAAAyEuTBgIAAAAKMTA4Ni42NzYxOQC+F0p9LevVCPiMZn0t69UIOUNJUS5OWVNFOlNIQUsuSVFfU1BfSVNTVUVSX1JBVElORy4y | G1: MDE4LTA3LTEwLkxUX0xDLlJBVElORwEAAACdE6YNAwAAAAAATrdrcC/r1QhUZnS3L+vVCB1DSVEuTllTRTpTSEFLLklRX1FVSUNLX0NPTVAuNAEAAACdE6YNAwAAAA1OYXNkYXFHTTpIQUJUAE63a3Av69UIghA0ii/r1QgdQ0lRLk5ZU0U6U0hBSy5JUV9RVUlDS19DT01QLjIBAAAAnROmDQMAAAAITllTRTpDTUcATrdrcC/r1QiCEDSKL+vVCCVDSVFQQy5eU1BYLklRX0xBU1RTQUxFUFJJQ0UuLTFZLjQwMTc4AQAAAJu4KAACAAAAEDIzLjQ1MzgxNzQxOTA1ODQATrdrcC/r1Qg8tHS3L+vVCC9DSVEuWk9FUy5JUV9UT1RBTF9ERUJULjUwMC4yMDE4LTA3LTEwLkxGUi4uVVNELgEAAADUxk8CAgAAAAY0Ny42MzQBCAAAAAUAAAABMQEAAAAKMTg5MDY1MzA5OAMAAAADMTYwAgAAAAQ0MTczBAAAAAEwBwAAAAk3LzEwLzIwMTgIAAAACTQvMTYvMjAxOAkAAAABMBT8EHEv69UIdjc0ii/r1QgdQ0lRLi5JUV9SQVRFX0xFVkVMLjIwMTgtMDctMTAFAAAAAAAAAAgAAAAUKEludmFsaWQgSWRlbnRpZmllcikU/BBxL+vVCIIQNIov69UIJkNJUS5LUi5JUV9GWF9SQVRFX0ZDLkFQUjIwMTkuOC8yNC8yMDE3AQAAAMQxlAYCAAAACjExMTEuMzM4NTYAqj5KfS3r1QgBP2Z9LevVCCZDSVEuS1IuSVFfRlhfUkFURV9GQy5KVU4yMDIwLjgvMjQvMjAxNwEAAADEMZQGAgAAAAoxMTMyLjIyNjQ0AKo+Sn0t69UIAT9mfS3r1Qge | H1: Q0lRLkNNRy5JUV9CRVRBXzVZUi4yMDE4LTA3LTEwAQAAAE5nAAACAAAAETAuNDEzMzAxODc0MzM1OTYxAIIe/FQv69UIdjc0ii/r1QglQ0lRUEMuXlNQWC5JUV9MQVNUU0FMRVBSSUNFLi0xWS4zOTgxMwEAAACbuCgAAgAAABEtMzguNDg1MjU2MzYwNzMzOQBOt2twL+vVCDy0dLcv69UILkNJUS5OWVNFOlNIQUsuSVFfUEVSSU9EREFURS41MDAuMjAxOC0wNy0xMC5MRlIBAAAAnROmDQUAAAAKMjAxOC0wMy0yOABOt2twL+vVCFRmdLcv69UIL0NJUS5XRU4uSVFfVE9UQUxfREVCVC41MDAuMjAxOC0wNy0xMC5MRlIuLlVTRC5IAQAAAAVcAAACAAAACDI4MDguMDIxAQgAAAAFAAAAATEBAAAACjE4ODgwNTUxODADAAAAAzE2MAIAAAAENDE3MwQAAAABMAcAAAAJNy8xMC8yMDE4CAAAAAg0LzEvMjAxOAkAAAABMIIe/FQv69UIVoU0ii/r1QgcQ0lRLklRVDM2MTgzODM5LklRX1JBVEVfTkFNRQEAAAAdHygCAwAAADJVbml0ZWQgU3RhdGVzIFRyZWFzdXJ5IENvbnN0YW50IE1hdHVyaXR5IC0gMTAgWWVhcgBOt2twL+vVCFRmdLcv69UIJUNJUVBDLl5TUFguSVFfTEFTVFNBTEVQUklDRS4tMVkuNDMxMDABAAAAm7goAAIAAAAQMTkuNDIwMTY1MjU4NzMxOQBOt2twL+vVCFCNdLcv69UIJkNJUS5LUi5JUV9GWF9SQVRFX0ZDLk1BUjIwMTkuOC8yNC8yMDE3AQAAAMQxlAYCAAAACTExMDguMjMwOQCqPkp9LevVCAE/ | I1: Zn0t69UIJUNJUS5DTUcuSVFfTUFSS0VUQ0FQLjIwMTgtMDctMTAuVVNELkgBAAAATmcAAAIAAAALMTI2MjQuMDE5MzIBBgAAAAUAAAABMQEAAAAKMTg4NDk2MzMzMAMAAAADMTYwAgAAAAYxMDAwNTQEAAAAATAHAAAACTcvMTAvMjAxOIIe/FQv69UIVoU0ii/r1QgjQ0lRLktSLklRX0ZYX1JBVEUuSkFOMjAxMy44LzI1LzIwMTcBAAAAyEuTBgIAAAALMTA2NS45ODY5NTcAvhdKfS3r1Qj4jGZ9LevVCCBDSVEuTllTRTpTSEFLLklRX0lORFVTVFJZX1NFQ1RPUgEAAACdE6YNAwAAABZDb25zdW1lciBEaXNjcmV0aW9uYXJ5AE63a3Av69UIVGZ0ty/r1QgRQ0lRLi5JUV9SQVRFX05BTUUFAAAAAAAAAAgAAAAUKEludmFsaWQgSWRlbnRpZmllcikU/BBxL+vVCIIQNIov69UIL0NJUS5XRU4uSVFfUFJFRl9FUVVJVFkuNTAwLjIwMTgtMDctMTAuTEZSLi5VU0QuAQAAAAVcAAADAAAAAAAU/BBxL+vVCG5eNIov69UILENJUS5OWVNFOlNIQUsuSVFfUEVSSU9EREFURS4xMDAwLjIwMTgtMDctMTAuAQAAAJ0Tpg0FAAAACjIwMTctMTItMjcAFPwQcS/r1QhsP3S3L+vVCCVDSVEuTUNELklRX01BUktFVENBUC4yMDE4LTA3LTEwLlVTRC5IAQAAAOAgAgACAAAADTEyNjExNS4xOTM2NjcBBgAAAAUAAAABMQEAAAAKMTg4NzY2NTU5NgMAAAADMTYwAgAAAAYxMDAwNTQEAAAAATAHAAAACTcvMTAvMjAxOIIe/FQv69UIVEQk | J1: iy/r1QhCQ0lRLlVTRC5JUV9GVUxMX0NVUlZFX0FOTlVBTC5DT05TVU1FUkRJU0NSRVRJT05BUlkuMC41WS4yMDE4LTA3LTEwAQAAAAAAAAACAAAACTAuMDM4MjYyOQCVeTNUL+vVCFaFNIov69UII0NJUS5LUi5JUV9GWF9SQVRFLk1BWTIwMTUuOC8yNS8yMDE3AQAAAMhLkwYCAAAACzEwODkuMjgwOTUyAKo+Sn0t69UIB2ZmfS3r1QguQ0lRLk1DRC5JUV9UT1RBTF9ERUJULjUwMC4yMDE4LTA3LTEwLkxGUi4uVVNELgEAAADgIAIAAgAAAAUzMDg4OAEIAAAABQAAAAExAQAAAAoxODg3NjY1NTk2AwAAAAMxNjACAAAABDQxNzMEAAAAATAHAAAACTcvMTAvMjAxOAgAAAAJMy8zMS8yMDE4CQAAAAEwBOAdiy/r1QgE4B2LL+vVCCRDSVEuTllTRTpTSEFLLklRX0JFVEFfNVlSLjIwMTgtMDctMTABAAAAnROmDQIAAAAQMS4zNDc2NDIyNjAzNTM5NABOt2twL+vVCFRmdLcv69UIJkNJUS5LUi5JUV9GWF9SQVRFX0ZDLkZFQjIwMTkuOC8yNC8yMDE3AQAAAMQxlAYCAAAACjExMDUuMDkwNjIAqj5KfS3r1QgBP2Z9LevVCCNDSVEuS1IuSVFfRlhfUkFURS5KVUwyMDE2LjgvMjUvMjAxNwEAAADIS5MGAgAAAAsxMTQ0LjMzMzMzMwCqPkp9LevVCAdmZn0t69UIH0NJUS5LUi5JUV9GWF9SQVRFX0ZDLi44LzI0LzIwMTcBAAAARJe+BgMAAAAAAKo+Sn0t69UIqj5KfS3r1QgXQ0lRLkNNRy5JUV9DT01QQU5ZX05BTUUBAAAA | K1: TmcAAAMAAAAcQ2hpcG90bGUgTWV4aWNhbiBHcmlsbCwgSW5jLgCCHvxUL+vVCG5eNIov69UIJkNJUS5LUi5JUV9GWF9SQVRFX0ZDLkpVTjIwMTkuOC8yNC8yMDE3AQAAAMQxlAYCAAAACjExMTUuMTY0NjcAqj5KfS3r1QgBP2Z9LevVCCpDSVEuTkFTREFRR1M6V0VOLklRX0NPTVBBTllfVElDS0VSX05PX0VYQ0gBAAAABVwAAAMAAAADV0VOAKFSM1Qv69UIghA0ii/r1QgmQ0lRLktSLklRX0ZYX1JBVEVfRkMuRkVCMjAyMC44LzI0LzIwMTcBAAAAxDGUBgIAAAAKMTExMS4xODA4MwCqPkp9LevVCAE/Zn0t69UII0NJUS5LUi5JUV9GWF9SQVRFLk1BWTIwMTcuOC8yNS8yMDE3AQAAAMhLkwYCAAAACzExMjYuMzA4Njk2AKo+Sn0t69UIB2ZmfS3r1QgjQ0lRLktSLklRX0ZYX1JBVEUuSlVMMjAxNy44LzI1LzIwMTcBAAAAyEuTBgIAAAALMTEzMy45MzgwOTUAqj5KfS3r1QgBP2Z9LevVCDBDSVEuSEFCVC5JUV9UT1RBTF9ERUJULjUwMC4yMDE4LTA3LTEwLkxGUi4uVVNELkgBAAAAI9YREAIAAAAGMTcuMjIxAQgAAAAFAAAAATEBAAAACjE4ODY0NTE1ODIDAAAAAzE2MAIAAAAENDE3MwQAAAABMAcAAAAJNy8xMC8yMDE4CAAAAAkzLzI3LzIwMTgJAAAAATCCHvxUL+vVCFaFNIov69UII0NJUS5LUi5JUV9GWF9SQVRFLkpVTDIwMTQuOC8yNS8yMDE3AQAAAMhLkwYCAAAACzEwMTkuOTM0NzgzAKo+Sn0t69UI+Ixm | L1: fS3r1QgvQ0lRLkhBQlQuSVFfVE9UQUxfREVCVC41MDAuMjAxOC0wNy0xMC5MRlIuLlVTRC4BAAAAI9YREAIAAAAGMTcuMjIxAQgAAAAFAAAAATEBAAAACjE4ODY0NTE1ODIDAAAAAzE2MAIAAAAENDE3MwQAAAABMAcAAAAJNy8xMC8yMDE4CAAAAAkzLzI3LzIwMTgJAAAAATAU/BBxL+vVCHY3NIov69UII0NJUS5LUi5JUV9GWF9SQVRFLk1BUjIwMTUuOC8yNS8yMDE3AQAAAMhLkwYCAAAACzExMTIuNTY4MTgyAKo+Sn0t69UIB2ZmfS3r1QgjQ0lRLktSLklRX0ZYX1JBVEUuTUFZMjAxNi44LzI1LzIwMTcBAAAAyEuTBgIAAAALMTE2OC40NTkwOTEAqj5KfS3r1QgHZmZ9LevVCCtDSVEuTllTRTpTSEFLLklRX1BFUklPRERBVEUuNTAwLjIwMTgtMDctMTAuAQAAAJ0Tpg0FAAAACjIwMTgtMDMtMjgAFPwQcS/r1QhUZnS3L+vVCDBDSVEuTUNELklRX1BSRUZfRVFVSVRZLjUwMC4yMDE4LTA3LTEwLkxGUi4uVVNELkgBAAAA4CACAAMAAAAAAIIe/FQv69UIVEQkiy/r1QgsQ0lRLlVTRC5JUV9GVUxMX0NVUlZFX0FOTlVBTC4uLjVZLjIwMTgtMDctMTABAAAAAAAAAAIAAAAJMC4wMzg3OTU3AKFSM1Qv69UIghA0ii/r1QgjQ0lRLktSLklRX0ZYX1JBVEUuQVVHMjAxNS44LzI1LzIwMTcBAAAAyEuTBgIAAAALMTE3OS42MzMzMzMAqj5KfS3r1QgHZmZ9LevVCCNDSVEuS1IuSVFfRlhfUkFURS5KVUwyMDE1LjgvMjUv | M1: MjAxNwEAAADIS5MGAgAAAAsxMTQzLjAxNzM5MQCqPkp9LevVCAdmZn0t69UII0NJUS5LUi5JUV9GWF9SQVRFLkZFQjIwMTMuOC8yNS8yMDE3AQAAAMhLkwYCAAAACDEwODcuMDk1AL4XSn0t69UI+IxmfS3r1QgtQ0lRQVZHLkhBQlQuSVFfRUZGRUNUX1RBWF9SQVRFLjk5Ni4yMDE4LTA3LTEwAQAAACPWERACAAAACTM4Ljk0Njg3NQCCHvxUL+vVCHY3NIov69UIMENJUS5IQUJULklRX1BSRUZfRVFVSVRZLjUwMC4yMDE4LTA3LTEwLkxGUi4uVVNELgEAAAAj1hEQAwAAAAAAFPwQcS/r1QhuXjSKL+vVCBhDSVEuXlNQWC5JUV9DT01QQU5ZX05BTUUBAAAAm7goAAMAAAAHUyZQIDUwMABOt2twL+vVCIIQNIov69UIL0NJUS5NQ0QuSVFfUFJFRl9FUVVJVFkuNTAwLjIwMTgtMDctMTAuTEZSLi5VU0QuAQAAAOAgAgADAAAAAAAE4B2LL+vVCATgHYsv69UIGENJUS5IQUJULklRX0NPTVBBTllfTkFNRQEAAAAj1hEQAwAAABtUaGUgSGFiaXQgUmVzdGF1cmFudHMsIEluYy4Agh78VC/r1QhuXjSKL+vVCCNDSVEuS1IuSVFfRlhfUkFURS5BVUcyMDE0LjgvMjUvMjAxNwEAAADIS5MGAgAAAAsxMDI1LjQ5MDQ3NgCqPkp9LevVCPiMZn0t69UIGENJUS5aT0VTLklRX0NPTVBBTllfTkFNRQEAAADUxk8CAwAAABNab2UncyBLaXRjaGVuLCBJbmMuAIIe/FQv69UIdjc0ii/r1QglQ0lRUEMuXlNQWC5JUV9MQVNUU0FMRVBS | N1: SUNFLi0xWS40MTYzOQEAAACbuCgAAgAAABAyOS42MDExODUwNzE2NTkxAE63a3Av69UIUI10ty/r1QgjQ0lRLktSLklRX0ZYX1JBVEUuT0NUMjAxMy44LzI1LzIwMTcBAAAAyEuTBgIAAAALMTA2Ny41MTczOTEAqj5KfS3r1Qj4jGZ9LevVCCZDSVEuS1IuSVFfRlhfUkFURV9GQy5KQU4yMDIwLjgvMjQvMjAxNwEAAADEMZQGAgAAAAkxMTA4LjQ3ODMAqj5KfS3r1QgBP2Z9LevVCCNDSVEuS1IuSVFfRlhfUkFURS5BUFIyMDE2LjgvMjUvMjAxNwEAAADIS5MGAgAAAAsxMTQ3LjU5MDQ3NgCqPkp9LevVCAdmZn0t69UILENJUUFWRy5XRU4uSVFfRUZGRUNUX1RBWF9SQVRFLjk5Ni4yMDE4LTA3LTEwAQAAAAVcAAACAAAACTM1LjE4MTUyNQCCHvxUL+vVCG5eNIov69UII0NJUS5LUi5JUV9GWF9SQVRFLk9DVDIwMTYuOC8yNS8yMDE3AQAAAMhLkwYCAAAACzExMjMuNjg1NzE0AKo+Sn0t69UIB2ZmfS3r1QgmQ0lRLktSLklRX0ZYX1JBVEVfRkMuQVVHMjAxOS44LzI0LzIwMTcBAAAAxDGUBgIAAAAKMTExNi44Mjc2OQCqPkp9LevVCAE/Zn0t69UII0NJUS5LUi5JUV9GWF9SQVRFLkZFQjIwMTQuOC8yNS8yMDE3AQAAAMhLkwYCAAAABjEwNzEuNACqPkp9LevVCPiMZn0t69UIJkNJUS5LUi5JUV9GWF9SQVRFX0ZDLk5PVjIwMTguOC8yNC8yMDE3AQAAAMQxlAYCAAAACjEwOTMuMTE1NDQAqj5KfS3r1QgBP2Z9LevV | O1: CCVDSVEuTkRMUy5JUV9NQVJLRVRDQVAuMjAxOC0wNy0xMC5VU0QuAQAAAPmfewACAAAACjQ4OS44MTA0MjYBBgAAAAUAAAABMQEAAAAKMTg4ODc0NzA4MwMAAAADMTYwAgAAAAYxMDAwNTQEAAAAATAHAAAACTcvMTAvMjAxOBT8EHEv69UIdjc0ii/r1QgdQ0lRLk5ZU0U6U0hBSy5JUV9RVUlDS19DT01QLjUBAAAAnROmDQMAAAAMTmFzZGFxR1M6V0VOAE63a3Av69UIghA0ii/r1QgmQ0lRLktSLklRX0ZYX1JBVEVfRkMuT0NUMjAxOS44LzI0LzIwMTcBAAAAxDGUBgIAAAAKMTExMC4yMjYxNACqPkp9LevVCAE/Zn0t69UII0NJUS5LUi5JUV9GWF9SQVRFLkFQUjIwMTcuOC8yNS8yMDE3AQAAAMhLkwYCAAAACDExMzIuNzI1AKo+Sn0t69UIB2ZmfS3r1QgdQ0lRLk5ZU0U6U0hBSy5JUV9RVUlDS19DT01QLjMBAAAAnROmDQMAAAANTmFzZGFxR1M6TkRMUwBOt2twL+vVCIIQNIov69UIJkNJUS5ORExTLklRX01BUktFVENBUC4yMDE4LTA3LTEwLlVTRC5IAQAAAPmfewACAAAACjQ4OS44MTA0MjYBBgAAAAUAAAABMQEAAAAKMTg4ODc0NzA4MwMAAAADMTYwAgAAAAYxMDAwNTQEAAAAATAHAAAACTcvMTAvMjAxOIIe/FQv69UIVoU0ii/r1QgjQ0lRLktSLklRX0ZYX1JBVEUuU0VQMjAxNC44LzI1LzIwMTcBAAAAyEuTBgIAAAALMTAzMS4xMDQ1NDUAvhdKfS3r1Qj4jGZ9LevVCCNDSVEuS1IuSVFfRlhfUkFURS5O | P1: T1YyMDE0LjgvMjUvMjAxNwEAAADIS5MGAgAAAAkxMDk1LjQ0MDUAqj5KfS3r1Qj4jGZ9LevVCCNDSVEuS1IuSVFfRlhfUkFURS5ERUMyMDE2LjgvMjUvMjAxNwEAAADIS5MGAgAAAAsxMTgyLjA1NDU0NQCqPkp9LevVCAdmZn0t69UIHUNJUS5OWVNFOlNIQUsuSVFfQ09NUEFOWV9OQU1FAQAAAJ0Tpg0DAAAAEFNoYWtlIFNoYWNrIEluYy4AYicwGi3r1Qj9vj1SL+vVCB5DSVEuTUNELklRX0JFVEFfNVlSLjIwMTgtMDctMTABAAAA4CACAAIAAAARMC42ODE0MzUwMDM5OTcxOTkAgh78VC/r1QhuXjSKL+vVCCNDSVEuS1IuSVFfRlhfUkFURS5KVU4yMDE2LjgvMjUvMjAxNwEAAADIS5MGAgAAAAsxMTcxLjM3MjcyNwCqPkp9LevVCAdmZn0t69UII0NJUS5LUi5JUV9GWF9SQVRFLkFVRzIwMTMuOC8yNS8yMDE3AQAAAMhLkwYCAAAACzExMTYuOTU0NTQ1AKo+Sn0t69UI+IxmfS3r1QgiQ0lRLk5ZU0U6U0hBSy5JUV9DT01QQU5ZX05BTUVfTE9ORwEAAACdE6YNAwAAABxTaGFrZSBTaGFjayBJbmMuIChOWVNFOlNIQUspAE63a3Av69UIe+kzii/r1QglQ0lRLkhBQlQuSVFfTUFSS0VUQ0FQLjIwMTgtMDctMTAuVVNELgEAAAAj1hEQAgAAAAoyMTUuMjk1NTI4AQYAAAAFAAAAATEBAAAACjE4ODY0NTE1ODIDAAAAAzE2MAIAAAAGMTAwMDU0BAAAAAEwBwAAAAk3LzEwLzIwMTgU/BBxL+vVCG5eNIov69UII0NJUS5L | Q1: Ui5JUV9GWF9SQVRFLk1BUjIwMTMuOC8yNS8yMDE3AQAAAMhLkwYCAAAACzExMDEuNjA0NzYyAKo+Sn0t69UI+IxmfS3r1QgjQ0lRLktSLklRX0ZYX1JBVEUuU0VQMjAxNi44LzI1LzIwMTcBAAAAyEuTBgIAAAALMTEwNy45OTA5MDkAqj5KfS3r1QgHZmZ9LevVCCNDSVEuS1IuSVFfRlhfUkFURS5OT1YyMDE2LjgvMjUvMjAxNwEAAADIS5MGAgAAAAcxMTYxLjM1AKo+Sn0t69UIB2ZmfS3r1QgjQ0lRLktSLklRX0ZYX1JBVEUuREVDMjAxNC44LzI1LzIwMTcBAAAAyEuTBgIAAAALMTEwMy45OTU2NTIAqj5KfS3r1Qj4jGZ9LevVCCNDSVEuS1IuSVFfRlhfUkFURS5KVU4yMDE3LjgvMjUvMjAxNwEAAADIS5MGAgAAAAsxMTI5LjYyMjcyNwCqPkp9LevVCAdmZn0t69UIMENJUS5XRU4uSVFfUFJFRl9FUVVJVFkuNTAwLjIwMTgtMDctMTAuTEZSLi5VU0QuSAEAAAAFXAAAAwAAAAAAgh78VC/r1QhWhTSKL+vVCCZDSVEuS1IuSVFfRlhfUkFURV9GQy5ERUMyMDE4LjgvMjQvMjAxNwEAAADEMZQGAgAAAAoxMDk1Ljg4MzE0AKo+Sn0t69UIB2ZmfS3r1QgjQ0lRLktSLklRX0ZYX1JBVEUuSlVOMjAxNC44LzI1LzIwMTcBAAAAyEuTBgIAAAALMTAxOS43OTUyMzgAqj5KfS3r1Qj4jGZ9LevVCC9DSVEuQ01HLklRX1BSRUZfRVFVSVRZLjUwMC4yMDE4LTA3LTEwLkxGUi4uVVNELgEAAABOZwAAAwAAAAAAFPwQcS/r1Qh2 | R1: NzSKL+vVCCpDSVEuTllTRTpTSEFLLklRX01BUktFVENBUC4yMDE4LTA3LTEwLlVTRC4BAAAAnROmDQIAAAALMTc3MS41OTEyNzYBBgAAAAUAAAABMQEAAAAKMTg4NzI5MDEyNQMAAAADMTYwAgAAAAYxMDAwNTQEAAAAATAHAAAACTcvMTAvMjAxOBT8EHEv69UIVGZ0ty/r1QgmQ0lRLktSLklRX0ZYX1JBVEVfRkMuSlVMMjAxOS44LzI0LzIwMTcBAAAAxDGUBgIAAAAKMTExNi45MzU1OQCqPkp9LevVCAE/Zn0t69UII0NJUS5LUi5JUV9GWF9SQVRFLkpVTjIwMTUuOC8yNS8yMDE3AQAAAMhLkwYCAAAACzExMTIuMTk1NDU1AKo+Sn0t69UI+IxmfS3r1QgoQ0lRLklRVDM2MTgzODM5LklRX1JBVEVfTEVWRUwuMjAxOC0wNy0xMAEAAAAdHygCAgAAAAQyLjg3AE63a3Av69UIVoU0ii/r1QglQ0lRUEMuXlNQWC5JUV9MQVNUU0FMRVBSSUNFLi0xWS40MjAwNAEAAACbuCgAAgAAABAxMS4zOTA5NzY1NTI5MjQ2AE63a3Av69UIUI10ty/r1QgdQ0lRLk5ZU0U6U0hBSy5JUV9RVUlDS19DT01QLjEBAAAAnROmDQMAAAAJTllTRTpaT0VTAE63a3Av69UIghA0ii/r1QgvQ0lRUkFOR0UuTllTRTpTSEFLLklRX0JPTkRfTElTVC4xLjUwMC4uLi4uQk9ORFMDAAAAnROmDQAAAABOt2twL+vVCGw/dLcv69UIJUNJUVBDLl5TUFguSVFfTEFTVFNBTEVQUklDRS4tMVkuNDEyNzQBAAAAm7goAAIAAAAQMTMuNDA1MDk5MzU1NDA2 | S1: OABOt2twL+vVCFCNdLcv69UIHkNJUS4zNjAyLklRX0VWX09WRVJfTFRNX0VCSVREQQUAAAAAAAAACAAAABQoSW52YWxpZCBJZGVudGlmaWVyKU63a3Av69UIYwV6cC/r1QgwQ0lRLlpPRVMuSVFfVE9UQUxfREVCVC41MDAuMjAxOC0wNy0xMC5MRlIuLlVTRC5IAQAAANTGTwICAAAABjQ3LjYzNAEIAAAABQAAAAExAQAAAAoxODkwNjUzMDk4AwAAAAMxNjACAAAABDQxNzMEAAAAATAHAAAACTcvMTAvMjAxOAgAAAAJNC8xNi8yMDE4CQAAAAEwgh78VC/r1QhSrDSKL+vVCCVDSVFQQy5eU1BYLklRX0xBU1RTQUxFUFJJQ0UuLTFZLjQwOTA4AQAAAJu4KAACAAAAFC0wLjAwMjQ3OTQ1MDgwNzg3OTc5AE63a3Av69UIPLR0ty/r1QgXQ0lRLldFTi5JUV9DT01QQU5ZX05BTUUBAAAABVwAAAMAAAATVGhlIFdlbmR5J3MgQ29tcGFueQCCHvxUL+vVCG5eNIov69UIJkNJUS5LUi5JUV9GWF9SQVRFX0ZDLk1BWTIwMTkuOC8yNC8yMDE3AQAAAMQxlAYCAAAACjExMTMuNTQ0NzgAqj5KfS3r1QgBP2Z9LevVCB5DSVEuV0VOLklRX0JFVEFfNVlSLjIwMTgtMDctMTABAAAABVwAAAIAAAARMC41NjA1NzAxMzUxNjI1OTQAgh78VC/r1QhuXjSKL+vVCCVDSVEuV0VOLklRX01BUktFVENBUC4yMDE4LTA3LTEwLlVTRC5IAQAAAAVcAAACAAAACjQxODguNjI3NTEBBgAAAAUAAAABMQEAAAAKMTg4ODA1NTE4MAMAAAADMTYwAgAA | T1: AAYxMDAwNTQEAAAAATAHAAAACTcvMTAvMjAxOIIe/FQv69UIVoU0ii/r1QgmQ0lRLktSLklRX0ZYX1JBVEVfRkMuU0VQMjAxOC44LzI0LzIwMTcBAAAAxDGUBgIAAAAKMTA5NC4wNDczOQCqPkp9LevVCAdmZn0t69UIM0NJUS5OWVNFOlNIQUsuSVFfUFJFRl9FUVVJVFkuLjIwMTgtMDctMTAuTEZSLi5VU0QuSAEAAACdE6YNAwAAAAAATrdrcC/r1QhUZnS3L+vVCCNDSVEuS1IuSVFfRlhfUkFURS5BUFIyMDEzLjgvMjUvMjAxNwEAAADIS5MGAgAAAAsxMTIxLjgzMTgxOACqPkp9LevVCPiMZn0t69UIJUNJUVBDLl5TUFguSVFfTEFTVFNBTEVQUklDRS4tMVkuNDIzNjkBAAAAm7goAAIAAAASLTAuNzI2ODY4NjYzMTIxMzI2AE63a3Av69UIUI10ty/r1QgvQ0lRLk5ZU0U6U0hBSy5JUV9JTkNfVEFYLi4yMDE4LTA3LTEwLkxGUi4uVVNELkgBAAAAnROmDQIAAAAHMTUwLjk0OQEIAAAABQAAAAExAQAAAAoxODg3MjkwNTQxAwAAAAMxNjACAAAAAjc1BAAAAAEwBwAAAAk3LzEwLzIwMTgIAAAACTMvMjgvMjAxOAkAAAABME63a3Av69UIVGZ0ty/r1QgfQ0lRLlpPRVMuSVFfQkVUQV81WVIuMjAxOC0wNy0xMAEAAADUxk8CAgAAABEwLjE0Nzk3NDYyODU4Nzg0NgCCHvxUL+vVCG5eNIov69UII0NJUS5LUi5JUV9GWF9SQVRFLk1BUjIwMTcuOC8yNS8yMDE3AQAAAMhLkwYCAAAACzExMzUuMTA4Njk2AKo+Sn0t69UI | U1: B2ZmfS3r1QgjQ0lRLktSLklRX0ZYX1JBVEUuSkFOMjAxNC44LzI1LzIwMTcBAAAAyEuTBgIAAAAKMTA2NS43NjA4NwCqPkp9LevVCPiMZn0t69UIJkNJUS5LUi5JUV9GWF9SQVRFX0ZDLkpVTDIwMjAuOC8yNC8yMDE3AQAAAMQxlAYCAAAACjExMjEuNTM2NzcAqj5KfS3r1QgBP2Z9LevVCCNDSVEuS1IuSVFfRlhfUkFURS5NQVkyMDE0LjgvMjUvMjAxNwEAAADIS5MGAgAAAAsxMDI1Ljk5MDkwOQCqPkp9LevVCPiMZn0t69UIJkNJUS5aT0VTLklRX01BUktFVENBUC4yMDE4LTA3LTEwLlVTRC5IAQAAANTGTwICAAAACjE5NS42NDAxNTYBBgAAAAUAAAABMQEAAAAKMTg5MDY1MzA5OAMAAAADMTYwAgAAAAYxMDAwNTQEAAAAATAHAAAACTcvMTAvMjAxOIIe/FQv69UIUqw0ii/r1QgwQ0lRLk5ETFMuSVFfVE9UQUxfREVCVC41MDAuMjAxOC0wNy0xMC5MRlIuLlVTRC5IAQAAAPmfewACAAAABjYyLjg3MQEIAAAABQAAAAExAQAAAAoxODg4NzQ3MDgzAwAAAAMxNjACAAAABDQxNzMEAAAAATAHAAAACTcvMTAvMjAxOAgAAAAINC8zLzIwMTgJAAAAATCCHvxUL+vVCFaFNIov69UIJUNJUS5aT0VTLklRX01BUktFVENBUC4yMDE4LTA3LTEwLlVTRC4BAAAA1MZPAgIAAAAKMTk1LjY0MDE1NgEGAAAABQAAAAExAQAAAAoxODkwNjUzMDk4AwAAAAMxNjACAAAABjEwMDA1NAQAAAABMAcAAAAJNy8xMC8yMDE4FPwQcS/r | V1: 1Qh2NzSKL+vVCCZDSVEuS1IuSVFfRlhfUkFURV9GQy5NQVIyMDIwLjgvMjQvMjAxNwEAAADEMZQGAgAAAAoxMTE1Ljc0MjYzAKo+Sn0t69UIAT9mfS3r1QgmQ0lRLktSLklRX0ZYX1JBVEVfRkMuT0NUMjAxOC44LzI0LzIwMTcBAAAAxDGUBgIAAAAKMTA5MS40MTU3MwCqPkp9LevVCAdmZn0t69UIJkNJUS5LUi5JUV9GWF9SQVRFX0ZDLkFVRzIwMTguOC8yNC8yMDE3AQAAAMQxlAYCAAAACjEwOTIuMDM5MjMAqj5KfS3r1QgBP2Z9LevVCCNDSVEuS1IuSVFfRlhfUkFURS5NQVIyMDE2LjgvMjUvMjAxNwEAAADIS5MGAgAAAAsxMTkwLjUxNzM5MQCqPkp9LevVCAdmZn0t69UIJkNJUS5LUi5JUV9GWF9SQVRFX0ZDLk5PVjIwMTkuOC8yNC8yMDE3AQAAAMQxlAYCAAAACjExMDguOTEzNDEAqj5KfS3r1QgBP2Z9LevVCCNDSVEuS1IuSVFfRlhfUkFURS5OT1YyMDEzLjgvMjUvMjAxNwEAAADIS5MGAgAAAAsxMDYyLjcwOTUyNACqPkp9LevVCPiMZn0t69UII0NJUS5LUi5JUV9GWF9SQVRFLkpBTjIwMTYuOC8yNS8yMDE3AQAAAMhLkwYCAAAACzEyMDAuMzQyODU3AKo+Sn0t69UIB2ZmfS3r1QgjQ0lRLktSLklRX0ZYX1JBVEUuQVVHMjAxNi44LzI1LzIwMTcBAAAAyEuTBgIAAAALMTExMS4xMDg2OTYAqj5KfS3r1QgHZmZ9LevVCCxDSVFBVkcuQ01HLklRX0VGRkVDVF9UQVhfUkFURS45OTYuMjAxOC0wNy0xMAEA | W1: AABOZwAAAgAAAAgzOC4yOTUzNgCCHvxUL+vVCG5eNIov69UII0NJUS5LUi5JUV9GWF9SQVRFLkFQUjIwMTQuOC8yNS8yMDE3AQAAAMhLkwYCAAAACzEwNDQuNTU4MTgyAKo+Sn0t69UI+IxmfS3r1QgjQ0lRLktSLklRX0ZYX1JBVEUuT0NUMjAxNC44LzI1LzIwMTcBAAAAyEuTBgIAAAALMTA2MC42ODY5NTcAqj5KfS3r1Qj4jGZ9LevVCCVDSVFQQy5eU1BYLklRX0xBU1RTQUxFUFJJQ0UuLTFZLjQwNTQzAQAAAJu4KAACAAAADzEyLjc4MjA3OTAzNDM4OABOt2twL+vVCDy0dLcv69UII0NJUS5LUi5JUV9GWF9SQVRFLk1BUjIwMTQuOC8yNS8yMDE3AQAAAMhLkwYCAAAACzEwNzAuNzM4MDk1AKo+Sn0t69UI+IxmfS3r1QgfQ0lRLkhBQlQuSVFfQkVUQV81WVIuMjAxOC0wNy0xMAEAAAAj1hEQAgAAABEwLjUyMzI4OTkwNzM4MjQ5NgCCHvxUL+vVCG5eNIov69UII0NJUS5LUi5JUV9GWF9SQVRFLkpBTjIwMTcuOC8yNS8yMDE3AQAAAMhLkwYCAAAACzExODYuMDI3MjczAKo+Sn0t69UIB2ZmfS3r1QgcQ0lRLktSLklRX0ZYX1JBVEUuLjgvMjUvMjAxNwEAAABEl74GAwAAAAAAqj5KfS3r1QiqPkp9LevVCCNDSVEuS1IuSVFfRlhfUkFURS5GRUIyMDE2LjgvMjUvMjAxNwEAAADIS5MGAgAAAAsxMjE0LjgzODA5NQCqPkp9LevVCAdmZn0t69UIMkNJUS5OWVNFOlNIQUsuSVFfUFJFRl9FUVVJVFkuLjIwMTgtMDct | X1: MTAuTEZSLi5VU0QuAQAAAJ0Tpg0DAAAAAAAU/BBxL+vVCFRmdLcv69UIJENJUS5XRU4uSVFfTUFSS0VUQ0FQLjIwMTgtMDctMTAuVVNELgEAAAAFXAAAAgAAAAo0MTg4LjYyNzUxAQYAAAAFAAAAATEBAAAACjE4ODgwNTUxODADAAAAAzE2MAIAAAAGMTAwMDU0BAAAAAEwBwAAAAk3LzEwLzIwMTgU/BBxL+vVCG5eNIov69UILkNJUS5XRU4uSVFfVE9UQUxfREVCVC41MDAuMjAxOC0wNy0xMC5MRlIuLlVTRC4BAAAABVwAAAIAAAAIMjgwOC4wMjEBCAAAAAUAAAABMQEAAAAKMTg4ODA1NTE4MAMAAAADMTYwAgAAAAQ0MTczBAAAAAEwBwAAAAk3LzEwLzIwMTgIAAAACDQvMS8yMDE4CQAAAAEwFPwQcS/r1QhuXjSKL+vVCB9DSVEuTkRMUy5JUV9CRVRBXzVZUi4yMDE4LTA3LTEwAQAAAPmfewACAAAAES0wLjYyNzcyNzE0MTM4Nzg4AIIe/FQv69UIbl40ii/r1QgmQ0lRLk5ZU0U6Q01HLklRX0NPTVBBTllfVElDS0VSX05PX0VYQ0gBAAAATmcAAAMAAAADQ01HAKFSM1Qv69UIghA0ii/r1QglQ0lRUEMuXlNQWC5JUV9MQVNUU0FMRVBSSUNFLi0xWS40MjczNQEAAACbuCgAAgAAABA5LjUzNTAyMTQ4NzU1ODU3AE63a3Av69UIUI10ty/r1QgjQ0lRLktSLklRX0ZYX1JBVEUuQVBSMjAxNS44LzI1LzIwMTcBAAAAyEuTBgIAAAALMTA4OC42NjM2MzYAqj5KfS3r1QgHZmZ9LevVCCNDSVEuS1IuSVFfRlhfUkFURS5P | Y1: Q1QyMDE1LjgvMjUvMjAxNwEAAADIS5MGAgAAAAsxMTQ5LjIxODE4MgCqPkp9LevVCPiMZn0t69UIMUNJUS5ORExTLklRX1BSRUZfRVFVSVRZLjUwMC4yMDE4LTA3LTEwLkxGUi4uVVNELkgBAAAA+Z97AAMAAAAAAIIe/FQv69UIVoU0ii/r1QgjQ0lRLktSLklRX0ZYX1JBVEUuRkVCMjAxNy44LzI1LzIwMTcBAAAAyEuTBgIAAAAGMTE0NC42AKo+Sn0t69UIB2ZmfS3r1QgmQ0lRLktSLklRX0ZYX1JBVEVfRkMuREVDMjAxOS44LzI0LzIwMTcBAAAAxDGUBgIAAAAKMTEwOC42Nzg2OQCqPkp9LevVCAE/Zn0t69UIJ0NJUS5OWVNFOlpPRVMuSVFfQ09NUEFOWV9USUNLRVJfTk9fRVhDSAEAAADUxk8CAwAAAARaT0VTAKFSM1Qv69UIghA0ii/r1QgrQ0lRLk5BU0RBUUdTOk5ETFMuSVFfQ09NUEFOWV9USUNLRVJfTk9fRVhDSAEAAAD5n3sAAwAAAARORExTAKFSM1Qv69UIghA0ii/r1QgjQ0lRLktSLklRX0ZYX1JBVEUuRkVCMjAxNS44LzI1LzIwMTcBAAAAyEuTBgIAAAAHMTEwMC42NgCqPkp9LevVCAdmZn0t69UIL0NJUS5ORExTLklRX1RPVEFMX0RFQlQuNTAwLjIwMTgtMDctMTAuTEZSLi5VU0QuAQAAAPmfewACAAAABjYyLjg3MQEIAAAABQAAAAExAQAAAAoxODg4NzQ3MDgzAwAAAAMxNjACAAAABDQxNzMEAAAAATAHAAAACTcvMTAvMjAxOAgAAAAINC8zLzIwMTgJAAAAATAU/BBxL+vVCG5eNIov69UIJENJ | Z1: US5NQ0QuSVFfTUFSS0VUQ0FQLjIwMTgtMDctMTAuVVNELgEAAADgIAIAAgAAAA0xMjYxMTUuMTkzNjY3AQYAAAAFAAAAATEBAAAACjE4ODc2NjU1OTYDAAAAAzE2MAIAAAAGMTAwMDU0BAAAAAEwBwAAAAk3LzEwLzIwMTgE4B2LL+vVCATgHYsv69UILkNJUS5DTUcuSVFfVE9UQUxfREVCVC41MDAuMjAxOC0wNy0xMC5MRlIuLlVTRC4BAAAATmcAAAIAAAABMAEIAAAABQAAAAExAQAAAAoxODg0OTYzMzMwAwAAAAMxNjACAAAABDQxNzMEAAAAATAHAAAACTcvMTAvMjAxOAgAAAAJMy8zMS8yMDE4CQAAAAEwFPwQcS/r1Qh2NzSKL+vVCC1DSVFBVkcuWk9FUy5JUV9FRkZFQ1RfVEFYX1JBVEUuOTk2LjIwMTgtMDctMTABAAAA1MZPAgIAAAAIMzcuNTMwMjUAgh78VC/r1QhuXjSKL+vVCCtDSVEuTkFTREFRR006SEFCVC5JUV9DT01QQU5ZX1RJQ0tFUl9OT19FWENIAQAAACPWERADAAAABEhBQlQAoVIzVC/r1QiCEDSKL+vVCA==

Sheet Cover
B2: Shake Shack - 3 Statement Model with DCF
D6: Company name: | F6: Shake Shack | I6: Circ switch: | K6: 1
D7: Ticker: | F7: SHAK
D9: Latest update: | F9: =TODAY() -> 45835 | I9: Enterprise value: | K9: =+DCF!J47 -> 0
D10: Created by: | F10: Wall Street Training | I10: Equity value: | K10: =+DCF!J51 -> 0
I11: Target price per share: | K11: =+DCF!J55 -> 0
I12: Share price: | K12: 43.2
K13: (units in USD '000 except per share number)
C29: © 2021 Wall Street Training Asia Inc.
C30: No portion of this report may be reproduced, reused, or otherwise distributed in any form without prior written consent.
C31: For more information, please visit/contatct Wall Street Training Asia Inc. through www.wallstreettraining.co.kr
C33: © 2021 (주)월스트릿트레이닝아시아.
C34: 이 파일은 대한민국 및 미국 저작권법의 보호를 받는 저작물 입니다.
C35: 파일의 원 저자로부터 서면에 의한 허락없이 이 파일의 일부나 전체를 어떠한 형태로도 가공/배포할 수 없습니다.
C36: 이를 위반시에는 형사/민사상의 법적 책임을 질수 있으며, 특별한 문의가 있는경우 www.wallstreettraining.co.kr에 있는 정보로 연락주시기 바랍니다.

Sheet Operations
B2: Shake Shack, Inc (SHAK)
B3: Operations Analysis & Assumptions
B4: (units in USD '000)
H7: Historical Year Ending December 31, | K7: Projected year Ending December 31,
F8: 2013 | G8: =F8+1 -> 2014 | H8: =G8+1 -> 2015 | I8: =H8+1 -> 2016 | J8: =I8+1 -> 2017 | K8: =J8+1 -> 2018 | L8: =K8+1 -> 2019 | M8: =L8+1 -> 2020 | N8: =M8+1 -> 2021 | ... T8: =S8+1 -> 2027
A10: x | B10: Store
B11: Store Count (stores)
C12: Domestic Company Operated | F12: 21 | G12: 31 | H12: 44 | I12: 64 | J12: 90 | K12: =J12+K19 -> 123 | L12: =K12+L19 -> 163 | M12: =L12+M19 -> 200 | N12: =M12+N19 -> 225 | O12: =N12+O19 -> 250 | P12: =O12+P19+P23 -> 270 | Q12: =P12+Q19+Q23 -> 290 | R12: =Q12+R19+R23 -> 305 | S12: =R12+S19+S23 -> 315 | T12: =S12+T19+T23 -> 320
C13: Domestic Licensed | F13: 4 | G13: 5 | H13: 5 | I13: 7 | J13: 10 | K13: =J13+K20 -> 13 | L13: =K13+L20 -> 16 | M13: =L13+M20 -> 19 | N13: =M13+N20 -> 22 | O13: =N13+O20 -> 24 | P13: =O13+P20 -> 26 | Q13: =P13+Q20 -> 28 | R13: =Q13+R20 -> 29 | ... T13: =S13+T20 -> 31
C14: International Licensed | F14: 15 | G14: 27 | H14: 35 | I14: 43 | J14: 59 | K14: =J14+K21 -> 73 | L14: =K14+L21 -> 93 | M14: =L14+M21 -> 120 | N14: =M14+N21 -> 145 | O14: =N14+O21 -> 165 | P14: =O14+P21 -> 180 | Q14: =P14+Q21 -> 195 | R14: =Q14+R21 -> 210 | ... T14: =S14+T21 -> 230
B15: Total Stores | F15: =SUM(F12:F14) -> 40 | G15: =SUM(G12:G14) -> 63 | H15: =SUM(H12:H14) -> 84 | I15: =SUM(I12:I14) -> 114 | J15: =SUM(J12:J14) -> 159 | K15: =SUM(K12:K14) -> 209 | L15: =SUM(L12:L14) -> 272 | M15: =SUM(M12:M14) -> 339 | ... T15: =SUM(T12:T14) -> 581
C16: Comp Store Base | F16: 8 | G16: 13 | H16: 21 | I16: 29 | J16: 43 | K16: 64 | L16: 90 | M16: 123 | N16: 163 | O16: 200 | P16: =N12 -> 225 | Q16: =O12 -> 250 | R16: =P12 -> 270 | S16: =Q12 -> 290 | T16: =R12 -> 305
B18: New Store Openings (net)
C19: Domestic Company Operated | G19: =G12-F12 -> 10 | H19: =H12-G12 -> 13 | I19: =I12-H12 -> 20 | J19: =J12-I12 -> 26 | K19: 33 | L19: 40 | M19: 37 | N19: 25 | O19: 25 | P19: 20 | Q19: 20 | R19: 15 | S19: 10 | T19: 5
C20: Domestic Licensed | G20: =G13-F13 -> 1 | H20: =H13-G13 -> 0 | I20: =I13-H13 -> 2 | J20: =J13-I13 -> 3 | K20: 3 | L20: 3 | M20: 3 | N20: 3 | O20: 2 | P20: 2 | Q20: 2 | R20: 1 | S20: 1 | T20: 1
C21: International Licensed | G21: =G14-F14 -> 12 | H21: =H14-G14 -> 8 | I21: =I14-H14 -> 8 | J21: =J14-I14 -> 16 | K21: 14 | L21: 20 | M21: 27 | N21: 25 | O21: 20 | P21: 15 | Q21: 15 | R21: 15 | S21: 10 | T21: 10
B23: Closures (implied) | G23: 0 | H23: =H16-F12 -> 0 | I23: =I16-G12 -> -2 | J23: =J16-H12 -> -1 | K23: 0 | L23: 0 | M23: 0 | N23: 0 | O23: 0 | P23: 0 | Q23: 0 | R23: 0 | S23: 0 | T23: 0
B24: New Domestic Company Store Openings (gross) | G24: =G19+ABS(G23) -> 10 | H24: =H19+ABS(H23) -> 13 | I24: =I19+ABS(I23) -> 22 | J24: =J19+ABS(J23) -> 27 | K24: =K19+ABS(K23) -> 33 | L24: =L19+ABS(L23) -> 40 | M24: =M19+ABS(M23) -> 37 | N24: =N19+ABS(N23) -> 25 | O24: =O19+ABS(O23) -> 25 | P24: =+P19-P23 -> 20 | Q24: =+Q19-Q23 -> 20 | R24: =+R19-R23 -> 15 | S24: =+S19-S23 -> 10 | T24: =+T19-T23 -> 5
A26: x | B26: Revenue
B27: System-wide Revenue | F27: 139903 | G27: 217442 | H27: 295257 | I27: 402791 | J27: 532137 | K27: =K42/2*(J15+K15) -> 675451.2 | L27: =L42/2*(K15+L15) -> 854531.99 | M27: =M42/2*(L15+M15) -> 1063939.5 | N27: =N42/2*(M15+N15) -> 1269105.6 | O27: =O42/2*(N15+O15) -> 1439397.4 | P27: =P28+P31 -> 0 | Q27: =Q28+Q31 -> 0 | R27: =R28+R31 -> 0 | S27: =S28+S31 -> 0 | T27: =T28+T31 -> 0
B28: Licensed Location Revenue | F28: 61316 | G28: 105400 | H28: 112038 | I28: 143441 | J28: 185749 | K28: =K41/2*(J13+J14+K13+K14) -> 234683.72 | L28: =L41/2*(K13+K14+L13+L14) -> 292294.78 | M28: =M41/2*(L13+L14+M13+M14) -> 371739.01 | N28: =N41/2*(M13+M14+N13+N14) -> 458677.97 | O28: =O41/2*(N13+N14+O13+O14) -> 533625.35 | P28: =P41*(SUM(P13:P14)+SUM(O13:O14))/2 -> 0 | Q28: =Q41*(SUM(Q13:Q14)+SUM(P13:P14))/2 -> 0 | R28: =R41*(SUM(R13:R14)+SUM(Q13:Q14))/2 -> 0 | S28: =S41*(SUM(S13:S14)+SUM(R13:R14))/2 -> 0 | T28: =T41*(SUM(T13:T14)+SUM(S13:S14))/2 -> 0
B30: Corporate Revenue | F30: =+F31+F32 -> 82456 | G30: =+G31+G32 -> 118530 | H30: =+H31+H32 -> 190592 | I30: =+I31+I32 -> 268475 | J30: =+J31+J32 -> 358810 | K30: =K31+K32 -> 456021.93 | L30: =L31+L32 -> 581236.37 | M30: =M31+M32 -> 716363.54 | N30: =N31+N32 -> 840241.65 | O30: =O31+O32 -> 940457.65 | P30: =SUM(P31:P32) -> 0 | Q30: =SUM(Q31:Q32) -> 0 | R30: =SUM(R31:R32) -> 0 | S30: =SUM(S31:S32) -> 0 | T30: =SUM(T31:T32) -> 0
B31: Company Operated Stores Revenue | F31: 78587 | G31: 112042 | H31: 183219 | I31: 259350 | J31: 346388 | K31: =K40/2*(J12+K12) -> 440767.48 | L31: =L40/2*(K12+L12) -> 562237.21 | M31: =M40/2*(L12+M12) -> 692200.5 | N31: =N40/2*(M12+N12) -> 810427.58 | O31: =O40/2*(N12+O12) -> 905772.01 | P31: =P40*AVERAGE(O12:P12) -> 0 | Q31: =Q40*AVERAGE(P12:Q12) -> 0 | R31: =R40*AVERAGE(Q12:R12) -> 0 | S31: =S40*AVERAGE(R12:S12) -> 0 | T31: =T40*AVERAGE(S12:T12) -> 0
B32: Licensing Revenue | F32: 3869 | G32: 6488 | H32: 7373 | I32: 9125 | J32: 12422 | K32: =K28*K33 -> 15254.442 | L32: =L28*L33 -> 18999.161 | M32: =M28*M33 -> 24163.035 | N32: =N28*N33 -> 29814.068 | O32: =O28*O33 -> 34685.648 | P32: =P33*P28 -> 0 | Q32: =Q33*Q28 -> 0 | R32: =R33*R28 -> 0 | S32: =S33*S28 -> 0 | T32: =T33*T28 -> 0
C33: Royalty Rate | F33: =F32/F28 -> 0.063099354 | G33: =G32/G28 -> 0.061555977 | H33: =H32/H28 -> 0.065808029 | I33: =I32/I28 -> 0.063615005 | J33: =J32/J28 -> 0.066875192 | K33: 0.065 | L33: 0.065 | M33: 0.065 | N33: 0.065 | O33: 0.065 | P33: 0.065 | Q33: 0.065 | R33: 0.065 | S33: 0.065 | T33: 0.065
B35: Avg Unit Volume (Reported)
C36: Domestic Company Operated | F36: 5017 | G36: 4611 | H36: 4976 | I36: 4981 | J36: 4598
C37: International Licensed | F37: 6077 | G37: 4588 | H37: 3413 | I37: 3334 | J37: 3176
B39: Avg Unit Volume (Implied)
C40: Domestic Company Operated | G40: =G31/(F12+G12)*2 -> 4309.3077 | H40: =H31/(G12+H12)*2 -> 4885.84 | I40: =I31/(H12+I12)*2 -> 4802.7778 | J40: =J31/(I12+J12)*2 -> 4498.5455 | K40: =J40*(1+K45) -> 4138.6618 | L40: =K40*(1+L45) -> 3931.7287 | M40: =L40*(1+M45) -> 3813.7769 | N40: =M40*(1+N45) -> 3813.7769 | O40: =N40*(1+O45) -> 3813.7769
C41: Licensed (total) | G41: =G28/(F13+F14+G13+G14)*2 -> 4133.3333 | H41: =H28/(G13+G14+H13+H14)*2 -> 3112.1667 | I41: =I28/(H13+H14+I13+I14)*2 -> 3187.5778 | J41: =J28/(I13+I14+J13+J14)*2 -> 3121.8319 | K41: =J41*(1+K46) -> 3028.177 | L41: =K41*(1+L46) -> 2997.8952 | M41: =L41*(1+M46) -> 2997.8952 | N41: =M41*(1+N46) -> 2997.8952 | O41: =N41*(1+O46) -> 2997.8952
C42: Systemwide | G42: =G27/(F15+G15)*2 -> 4222.1748 | H42: =H27/(G15+H15)*2 -> 4017.102 | I42: =I27/(H15+I15)*2 -> 4068.596 | J42: =J27/(I15+J15)*2 -> 3898.4396 | K42: =J42*(1+K47) -> 3670.9304 | L42: =K42*(1+L47) -> 3553.1476 | M42: =L42*(1+M47) -> 3482.617 | N42: =M42*(1+N47) -> 3472.245 | O42: =N42*(1+O47) -> 3464.2536
B44: Avg Unit Volume (% yoy)
C45: Domestic Company Operated | H45: =(H40-G40)/G40 -> 0.13378769 | I45: =(I40-H40)/H40 -> -0.017000602 | J45: =(J40-I40)/I40 -> -0.063345076 | K45: -0.08 | L45: -0.05 | M45: -0.03 | N45: 0 | O45: 0 | P45: 0 | Q45: 0 | R45: 0 | S45: 0 | T45: 0
C46: Licensed (total) | H46: =(H41-G41)/G41 -> -0.24705645 | I46: =(I41-H41)/H41 -> 0.024231064 | J46: =(J41-I41)/I41 -> -0.020625644 | K46: -0.03 | L46: -0.01 | M46: 0 | N46: 0 | O46: 0 | P46: 0 | Q46: 0 | R46: 0 | S46: 0 | T46: 0 | U46: << add f/x conversion
C47: Systemwide | H47: =(H42-G42)/G42 -> -0.0485704 | I47: =(I42-H42)/H42 -> 0.012818673 | J47: =(J42-I42)/I42 -> -0.041821897 | K47: -0.058359025 | L47: -0.032085288 | M47: -0.019850154 | N47: -0.0029782301 | O47: -0.0023015233 | P47: =P42/O42-1 -> -1 | Q47: =Q42/P42-1 -> #DIV/0! | R47: =R42/Q42-1 -> #DIV/0! | S47: =S42/R42-1 -> #DIV/0! | T47: =T42/S42-1 -> #DIV/0!
B49: Same Shack Sales (% yoy) - Actual | G49: 0.041 | H49: 0.133 | I49: =(1+3.1%)*(1+1.1%)-1 -> 0.042341 | J49: =(1-3.2%)*(1+2%)-1 -> -0.01264
B51: Company Operated Stores Revenue
C52: Existing Shack Sales (Respt. Yr) | F52: =55600+2300 -> 57900 | G52: =F31+2300 -> 80887 | H52: =G31+10100 -> 122142 | I52: =H31+5200 -> 188419 | J52: =I31-2300 -> 257050
C53: New Shack Contribution (Respt. Yr) | F53: =F31-F52 -> 20687 | G53: =G31-G52 -> 31155 | H53: =H31-H52 -> 61077 | I53: =I31-I52 -> 70931 | J53: =J31-J52 -> 89338
B55: Shack-by-Shack Revenue
C56: 2013-Prior Shacks | H56: =F31*(1+G49)*(1+H49) -> 92689.673 | I56: =H56*(1+I49) -> 96614.246 | J56: =I56*(1+J$49) -> 95393.042
C57: 2014 Shacks | H57: =H31-H56-H58 -> 29452.327 | I57: =H57*(1+I49) -> 30699.368 | J57: =I57*(1+J$49) -> 30311.328
C58: 2015 Shacks | H58: =H53 -> 61077 | I58: =I31-SUM(I56:I57)-I59 -> 61105.386 | J58: =I58*(1+J$49) -> 60333.014
C59: 2016 Shacks | I59: =I53 -> 70931 | J59: =J31-J60-SUM(J56:J58) -> 71012.616
C60: 2017 Shacks | J60: =J53 -> 89338
B62: Shack-by-Shack Unit Volume
C63: 2013-Prior Shacks | H63: =H56/$F$12 -> 4413.7939 | I63: =I56/$F$12 -> 4600.6784 | J63: =J56/$F$12 -> 4542.5258
C64: 2014 Shacks | H64: =H57/$G$19 -> 2945.2327 | I64: =I57/$G$19 -> 3069.9368 | J64: =J57/$G$19 -> 3031.1328
C65: 2015 Shacks | H65: =H58/$H$19 -> 4698.2308 | I65: =I58/$H$19 -> 4700.4143 | J65: =J58/$H$19 -> 4641.001
C66: 2016 Shacks | I66: =I59/$I$19 -> 3546.55 | J66: =J59/$I$19 -> 3550.6308
C67: 2017 Shacks | J67: =J60/$J$19 -> 3436.0769
A69: x | B69: Operating Expenses
B70: Store-Level Operating Costs | F70: 58168 | G70: 85181 | H70: 130345 | I70: 186058 | J70: 254079 | K70: =SUM(K71:K74) -> 335068.2 | L70: =SUM(L71:L74) -> 436523.53 | M70: =SUM(M71:M74) -> 544456.84 | N70: =SUM(N71:N74) -> 633375.71 | O70: =SUM(O71:O74) -> 707890.5 | P70: =SUM(P71:P74) -> 774953.82 | Q70: =SUM(Q71:Q74) -> 834565.65 | R70: =SUM(R71:R74) -> 886726 | ... T70: =SUM(T71:T74) -> 946337.83
C71: Food & Paper Costs | F71: 23865 | G71: 34925 | H71: 54079 | I71: 73752 | J71: 98337 | K71: =K77*(K$12+J$12)/2 -> 125130.64 | L71: =L77*(L$12+K$12)/2 -> 159615 | M71: =M77*(M$12+L$12)/2 -> 196510.62 | N71: =N77*(N$12+M$12)/2 -> 230074.42 | O71: =O77*(O$12+N$12)/2 -> 257142 | P71: =P77*AVERAGE(O$12:P$12) -> 281502.82 | Q71: =Q77*AVERAGE(P$12:Q$12) -> 303156.88 | R71: =R77*AVERAGE(Q$12:R$12) -> 322104.18 | S71: =S77*AVERAGE(R$12:S$12) -> 335637.97 | T71: =T77*AVERAGE(S$12:T$12) -> 343758.25
C72: Labor & Related | F72: 20096 | G72: 29312 | H72: 44752 | I72: 65540 | J72: 91740 | K72: =K78*(K$12+J$12)/2 -> 123080.53 | L72: =L78*(L$12+K$12)/2 -> 161957.8 | M72: =M78*(M$12+L$12)/2 -> 203506.2 | N72: =N78*(N$12+M$12)/2 -> 235882.19 | O72: =O78*(O$12+N$12)/2 -> 263633.03 | P72: =P78*AVERAGE(O$12:P$12) -> 288608.79 | Q72: =Q78*AVERAGE(P$12:Q$12) -> 310809.47 | R72: =R78*AVERAGE(Q$12:R$12) -> 330235.06 | S72: =S78*AVERAGE(R$12:S$12) -> 344110.48 | T72: =T78*AVERAGE(S$12:T$12) -> 352435.74
C73: Occupancy & Related | F73: 6892 | G73: 9735 | H73: 15207 | I73: 21820 | J73: 28197 | K73: =K79*(K$12+J$12)/2 -> 37829.754 | L73: =L79*(L$12+K$12)/2 -> 49778.984 | M73: =M79*(M$12+L$12)/2 -> 62549.208 | N73: =N79*(N$12+M$12)/2 -> 72500.218 | O73: =O79*(O$12+N$12)/2 -> 81029.655 | P73: =P79*AVERAGE(O$12:P$12) -> 88706.149 | Q73: =Q79*AVERAGE(P$12:Q$12) -> 95529.699 | R73: =R79*AVERAGE(Q$12:R$12) -> 101500.31 | S73: =S79*AVERAGE(R$12:S$12) -> 105765.02 | T73: =T79*AVERAGE(S$12:T$12) -> 108323.86
C74: Other | F74: =F70-SUM(F71:F73) -> 7315 | G74: =G70-SUM(G71:G73) -> 11209 | H74: =H70-SUM(H71:H73) -> 16307 | I74: =I70-SUM(I71:I73) -> 24946 | J74: =J70-SUM(J71:J73) -> 35805 | K74: =K80*(K$12+J$12)/2 -> 49027.275 | L74: =L80*(L$12+K$12)/2 -> 65171.75 | M74: =M80*(M$12+L$12)/2 -> 81890.81 | N74: =N80*(N$12+M$12)/2 -> 94918.893 | O74: =O80*(O$12+N$12)/2 -> 106085.82 | P74: =P80*AVERAGE(O$12:P$12) -> 116136.06 | Q74: =Q80*AVERAGE(P$12:Q$12) -> 125069.6 | R74: =R80*AVERAGE(Q$12:R$12) -> 132886.45 | S74: =S80*AVERAGE(R$12:S$12) -> 138469.91 | T74: =T80*AVERAGE(S$12:T$12) -> 141819.99
B76: Store-Level Operating Costs per Store
C77: Food & Paper Costs | G77: =G71/(F$12+G$12)*2 -> 1343.2692 | H77: =H71/(G$12+H$12)*2 -> 1442.1067 | I77: =I71/(H$12+I$12)*2 -> 1365.7778 | J77: =J71/(I$12+J$12)*2 -> 1277.1039 | K77: =J77*(1+K83) -> 1174.9356 | L77: =K77*(1+L83) -> 1116.1888 | M77: =L77*(1+M83) -> 1082.7031 | N77: =M77*(1+N83) -> 1082.7031 | O77: =N77*(1+O83) -> 1082.7031 | P77: =O77*(1+P83) -> 1082.7031 | Q77: =P77*(1+Q83) -> 1082.7031 | R77: =Q77*(1+R83) -> 1082.7031 | ... T77: =S77*(1+T83) -> 1082.7031
C78: Labor & Related | G78: =G72/(F$12+G$12)*2 -> 1127.3846 | H78: =H72/(G$12+H$12)*2 -> 1193.3867 | I78: =I72/(H$12+I$12)*2 -> 1213.7037 | J78: =J72/(I$12+J$12)*2 -> 1191.4286 | K78: =J78*(1+K84) -> 1155.6857 | L78: =K78*(1+L84) -> 1132.572 | M78: =L78*(1+M84) -> 1121.2463 | N78: =M78*(1+N84) -> 1110.0338 | O78: =N78*(1+O84) -> 1110.0338 | P78: =O78*(1+P84) -> 1110.0338 | Q78: =P78*(1+Q84) -> 1110.0338 | R78: =Q78*(1+R84) -> 1110.0338 | ... T78: =S78*(1+T84) -> 1110.0338
C79: Occupancy & Related | G79: =G73/(F$12+G$12)*2 -> 374.42308 | H79: =H73/(G$12+H$12)*2 -> 405.52 | I79: =I73/(H$12+I$12)*2 -> 404.07407 | J79: =J73/(I$12+J$12)*2 -> 366.19481 | K79: =J79*(1+K85) -> 355.20896 | L79: =K79*(1+L85) -> 348.10478 | M79: =L79*(1+M85) -> 344.62373 | N79: =M79*(1+N85) -> 341.1775 | O79: =N79*(1+O85) -> 341.1775 | P79: =O79*(1+P85) -> 341.1775 | Q79: =P79*(1+Q85) -> 341.1775 | R79: =Q79*(1+R85) -> 341.1775 | ... T79: =S79*(1+T85) -> 341.1775
C80: Other | G80: =G74/(F$12+G$12)*2 -> 431.11538 | H80: =H74/(G$12+H$12)*2 -> 434.85333 | I80: =I74/(H$12+I$12)*2 -> 461.96296 | J80: =J74/(I$12+J$12)*2 -> 465 | K80: =J80*(1+K86) -> 460.35 | L80: =K80*(1+L86) -> 455.7465 | M80: =L80*(1+M86) -> 451.18904 | N80: =M80*(1+N86) -> 446.67714 | O80: =N80*(1+O86) -> 446.67714 | P80: =O80*(1+P86) -> 446.67714 | Q80: =P80*(1+Q86) -> 446.67714 | R80: =Q80*(1+R86) -> 446.67714 | ... T80: =S80*(1+T86) -> 446.67714
B82: Store-Level Operating Costs yoy % Changes
C83: Food & Paper Costs | H83: =(H77-G77)/G77 -> 0.073579766 | I83: =(I77-H77)/H77 -> -0.05292874 | J83: =(J77-I77)/I77 -> -0.064925556 | K83: =K45 -> -0.08 | L83: =L45 -> -0.05 | M83: =M45 -> -0.03 | N83: =N45 -> 0 | O83: =O45 -> 0 | P83: =+P45 -> 0 | Q83: =+Q45 -> 0 | R83: =+R45 -> 0 | S83: =+S45 -> 0 | T83: =+T45 -> 0 | U83: <<in-line w/ volume
C84: Labor & Related | H84: =(H78-G78)/G78 -> 0.058544396 | I84: =(I78-H78)/H78 -> 0.017024689 | J84: =(J78-I78)/I78 -> -0.018353023 | K84: -0.03 | L84: -0.02 | M84: -0.01 | N84: -0.01 | O84: =+O83/2 -> 0 | P84: =+P83/2 -> 0 | Q84: =+Q83/2 -> 0 | R84: =+R83/2 -> 0 | S84: =+S83/2 -> 0 | T84: =+T83/2 -> 0
C85: Occupancy & Related | H85: =(H79-G79)/G79 -> 0.083052902 | I85: =(I79-H79)/H79 -> -0.0035656094 | J85: =(J79-I79)/I79 -> -0.093743379 | K85: -0.03 | L85: -0.02 | M85: -0.01 | N85: -0.01 | O85: =+O83/2 -> 0 | P85: =+P83/2 -> 0 | Q85: =+Q83/2 -> 0 | R85: =+R83/2 -> 0 | S85: =+S83/2 -> 0 | T85: =+T83/2 -> 0 | U85: <<reduce NYC footage
C86: Other | H86: =(H80-G80)/G80 -> 0.0086704137 | I86: =(I80-H80)/H80 -> 0.062342007 | J86: =(J80-I80)/I80 -> 0.0065742003 | K86: -0.01 | L86: -0.01 | M86: -0.01 | N86: -0.01 | O86: 0 | P86: 0 | Q86: 0 | R86: 0 | S86: 0 | T86: 0
B88: Other Operating Costs
C89: General & Admin | F89: 12453 | G89: 18187 | H89: 37825 | I89: 30556 | J89: 39003 | K89: =K90+K91 -> 48275.987 | L89: =L90+L91 -> 60030.59 | M89: =M90+M91 -> 72607.114 | N89: =N90+N91 -> 84047.927 | O89: =O90+O91 -> 93274.389 | P89: =+SUM(P90:P91) -> 5623 | Q89: =+SUM(Q90:Q91) -> 5623 | R89: =+SUM(R90:R91) -> 5623 | S89: =+SUM(S90:S91) -> 5623 | T89: =+SUM(T90:T91) -> 5623
D90: Stock Based Compensation | F90: =SCF!C24 -> 93 | G90: =SCF!D24 -> 165 | H90: =SCF!E24 -> 16681 | I90: =SCF!F24 -> 5354 | J90: =SCF!G24 -> 5623 | K90: 5623 | L90: 5623 | M90: 5623 | N90: 5623 | O90: 5623 | P90: =+O90 -> 5623 | Q90: =+P90 -> 5623 | R90: =+Q90 -> 5623 | S90: =+R90 -> 5623 | T90: =+S90 -> 5623 | U90: FY 2017 flat
D91: G&A Excluding SBC | F91: =F89-F90 -> 12360 | G91: =G89-G90 -> 18022 | H91: =H89-H90 -> 21144 | I91: =I89-I90 -> 25202 | J91: =J89-J90 -> 33380 | K91: =K31*K97 -> 42652.987 | L91: =L31*L97 -> 54407.59 | M91: =M31*M97 -> 66984.114 | N91: =N31*N97 -> 78424.927 | O91: =O31*O97 -> 87651.389 | P91: =P97*P31 -> 0 | Q91: =Q97*Q31 -> 0 | R91: =R97*R31 -> 0 | S91: =S97*S31 -> 0 | T91: =T97*T31 -> 0
C92: Store Opening Costs | F92: 2334 | G92: 6105 | H92: 5430 | I92: 9520 | J92: 9603 | K92: =K98*K24 -> 10747 | L92: =L98*L24 -> 11826.667 | M92: =M98*M24 -> 9829.6667 | N92: =N98*N24 -> 5891.6667 | O92: =O98*O24 -> 5141.6667 | P92: =P98*P19 -> #VALUE! | Q92: =Q98*Q19 -> #VALUE! | R92: =R98*R19 -> #VALUE! | S92: =S98*S19 -> #VALUE! | T92: =T98*T19 -> #VALUE!
C93: Depreciation | F93: 3541 | G93: 5809 | H93: 10222 | I93: 14502 | J93: 21704 | K93: 29216.938 | L93: 36370.255 | M93: 42532.247 | N93: 45546.708 | O93: 46155.145 | P93: =+'PP&E'!P18 -> 0 | Q93: =+'PP&E'!Q18 -> 0 | R93: =+'PP&E'!R18 -> 0 | S93: =+'PP&E'!S18 -> 0 | T93: =+'PP&E'!T18 -> 0
C94: Loss on PP&E Disposal | F94: 25 | G94: 105 | H94: 17 | I94: 34 | J94: 608 | K94: =K100 -> 50 | L94: =L100 -> 50 | M94: =M100 -> 50 | N94: =N100 -> 50 | O94: =O100 -> 50 | P94: =P100 -> 50 | Q94: =Q100 -> 50 | R94: =R100 -> 50 | ... T94: =T100 -> 50
C95: SG&A | F95: =F89+F92 -> 14787 | G95: =G89+G92 -> 24292 | H95: =H89+H92 -> 43255 | I95: =I89+I92 -> 40076 | J95: =J89+J92 -> 48606 | K95: =K89+K92 -> 59022.987 | L95: =L89+L92 -> 71857.257 | M95: =M89+M92 -> 82436.781 | ... O95: =O89+O92 -> 98416.055
B96: Other Operating Costs Analysis & Assumptions
C97: G&A as % of Co. Operated Store Rev. | F97: =F91/F31 -> 0.15727792 | G97: =G91/G31 -> 0.1608504 | H97: =H91/H31 -> 0.11540288 | I97: =I91/I31 -> 0.097173703 | J97: =J91/J31 -> 0.096365925 | K97: 0.096769814 | L97: 0.096769814 | M97: 0.096769814 | N97: 0.096769814 | O97: 0.096769814 | P97: =+O97 -> 0.096769814 | Q97: =+P97 -> 0.096769814 | R97: =+Q97 -> 0.096769814 | S97: =+R97 -> 0.096769814 | T97: =+S97 -> 0.096769814 | U97: 직전 2개년 avg flat
C98: Store Opening Costs per New Store | G98: =G92/G24 -> 610.5 | H98: =H92/H24 -> 417.69231 | I98: =I92/I24 -> 432.72727 | J98: =J92/J24 -> 355.66667 | K98: =J98-30 -> 325.66667 | L98: =K98-30 -> 295.66667 | M98: =L98-30 -> 265.66667 | N98: =M98-30 -> 235.66667 | O98: =N98-30 -> 205.66667 | P98: =MAX(O98+$U$98,200) -> #VALUE! | Q98: =MAX(P98+$U$98,200) -> #VALUE! | R98: =MAX(Q98+$U$98,200) -> #VALUE! | S98: =MAX(R98+$U$98,200) -> #VALUE! | T98: =MAX(S98+$U$98,200) -> #VALUE! | U98: 직전년 대비 30씩 감소
C99: D&A / Existing Store
C100: Loss on PP&E Disposal (amount) | G100: =G94 -> 105 | H100: =H94 -> 17 | I100: =I94 -> 34 | J100: =J94 -> 608 | K100: 50 | L100: 50 | M100: 50 | N100: 50 | O100: 50 | P100: 50 | Q100: 50 | R100: 50 | S100: 50 | T100: 50 | U100: 50 고정
A103: x | B103: Operating Profit
B104: Store-Level EBIT | F104: =F31-F70 -> 20419 | G104: =G31-G70 -> 26861 | H104: =H31-H70 -> 52874 | I104: =I31-I70 -> 73292 | J104: =J31-J70 -> 92309 | K104: =K31-K70 -> 105699.29 | L104: =L31-L70 -> 125713.68 | M104: =M31-M70 -> 147743.66 | ... O104: =O31-O70 -> 197881.5 | P104: =+P31-P70 -> -774953.82 | Q104: =+Q31-Q70 -> -834565.65 | R104: =+R31-R70 -> -886726 | S104: =+S31-S70 -> -923983.4 | T104: =+T31-T70 -> -946337.83
C105: Margin % | F105: =F104/F31 -> 0.25982669 | G105: =G104/G31 -> 0.23974045 | H105: =H104/H31 -> 0.28858361 | I105: =I104/I31 -> 0.2825988 | J105: =J104/J31 -> 0.26649018 | K105: =K104/K31 -> 0.23980736 | L105: =L104/L31 -> 0.22359545 | M105: =M104/M31 -> 0.21344056 | ... O105: =O104/O31 -> 0.21846723 | P105: =+P104/P31 -> #DIV/0! | Q105: =+Q104/Q31 -> #DIV/0! | R105: =+R104/R31 -> #DIV/0! | S105: =+S104/S31 -> #DIV/0! | T105: =+T104/T31 -> #DIV/0!
B107: Adjusted EBITDA | F107: 12722 | G107: 14862 | H107: 37011 | I107: 50234 | J107: 64664 | P107: =+'Income Statement'!P21+'Income Statement'!P19 -> 0 | Q107: =+'Income Statement'!Q21+'Income Statement'!Q19 -> 0 | R107: =+'Income Statement'!R21+'Income Statement'!R19 -> 0 | S107: =+'Income Statement'!S21+'Income Statement'!S19 -> 0 | T107: =+'Income Statement'!T21+'Income Statement'!T19 -> 0
C108: Margin % | F108: =F107/F31 -> 0.16188428 | G108: =G107/G31 -> 0.13264669 | H108: =H107/H31 -> 0.20200416 | I108: =I107/I31 -> 0.19369192 | J108: =J107/J31 -> 0.18668083 | K108: =K107/K31 -> 0 | L108: =L107/L31 -> 0 | M108: =M107/M31 -> 0 | ... O108: =O107/O31 -> 0 | P108: =+O107/O30 -> 0 | Q108: =+P107/P30 -> #DIV/0! | R108: =+Q107/Q30 -> #DIV/0! | S108: =+R107/R30 -> #DIV/0! | T108: =+S107/S30 -> #DIV/0!
B110: Corporate EBIT | F110: 5935 | G110: 3143 | H110: 6753 | I110: 27805 | J110: 33813 | K110: =K104-SUM(K89,K92,K93,K94)+K32 -> 32663.801 | L110: =L104-SUM(L89,L92:L94)+L32 -> 36435.328 | M110: =M104-SUM(M89,M92:M94)+M32 -> 46887.671 | N110: =N104-SUM(N89,N92:N94)+N32 -> 71329.635 | O110: =O104-SUM(O89,O92:O94)+O32 -> 87945.948 | P110: =P104-SUM(P89,P92:P94)+P32 -> #VALUE! | Q110: =Q104-SUM(Q89,Q92:Q94)+Q32 -> #VALUE! | R110: =R104-SUM(R89,R92:R94)+R32 -> #VALUE! | S110: =S104-SUM(S89,S92:S94)+S32 -> #VALUE! | T110: =T104-SUM(T89,T92:T94)+T32 -> #VALUE!
C111: Margin % | F111: =F110/F31 -> 0.075521397 | G111: =G110/G31 -> 0.028051981 | H111: =H110/H31 -> 0.036857531 | I111: =I110/I31 -> 0.10721033 | J111: =J110/J31 -> 0.097615968 | K111: =K110/K31 -> 0.07410665 | L111: =L110/L31 -> 0.064804192 | M111: =M110/M31 -> 0.067737124 | ... O111: =O110/O31 -> 0.097095017 | P111: =+P110/P30 -> #VALUE! | Q111: =+Q110/Q30 -> #VALUE! | R111: =+R110/R30 -> #VALUE! | S111: =+S110/S30 -> #VALUE! | T111: =+T110/T30 -> #VALUE!
E112: Other Operating Costs | F112: =F89+F92+F93+F94 -> 18353 | G112: =G89+G92+G93+G94 -> 30206 | H112: =H89+H92+H93+H94 -> 53494 | I112: =I89+I92+I93+I94 -> 54612 | J112: =J89+J92+J93+J94 -> 70918 | K112: =K89+K92+K93+K94 -> 88289.926 | L112: =L89+L92+L93+L94 -> 108277.51 | M112: =M89+M92+M93+M94 -> 125019.03 | ... O112: =O89+O92+O93+O94 -> 144621.2
A113: x | F113: =F104-F112+F32 -> 5935 | G113: =G104-G112+G32 -> 3143 | H113: =H104-H112+H32 -> 6753 | I113: =I104-I112+I32 -> 27805 | J113: =J104-J112+J32 -> 33813 | K113: =K104-K112+K32 -> 32663.801 | L113: =L104-L112+L32 -> 36435.328 | M113: =M104-M112+M32 -> 46887.671 | ... O113: =O104-O112+O32 -> 87945.948

Sheet Income Statement
B2: Shake Shack, Inc (SHAK)
B3: Income Statement
B4: (units in USD '000)
H7: Historical Year Ending December 31, | K7: Projected year Ending December 31, | V7: CAGR
F8: 2013 | G8: =F8+1 -> 2014 | H8: =G8+1 -> 2015 | I8: =H8+1 -> 2016 | J8: =I8+1 -> 2017 | K8: =J8+1 -> 2018 | L8: =K8+1 -> 2019 | M8: =L8+1 -> 2020 | N8: =M8+1 -> 2021 | ... T8: =S8+1 -> 2027 | V8: 2017-2022
A10: x | B10: Total Revenue | F10: =Operations!F30 -> 82456 | G10: =Operations!G30 -> 118530 | H10: =Operations!H30 -> 190592 | I10: =Operations!I30 -> 268475 | J10: =Operations!J30 -> 358810 | K10: =Operations!K30 -> 456021.93 | L10: =Operations!L30 -> 581236.37 | M10: =Operations!M30 -> 716363.54 | ... O10: =Operations!O30 -> 940457.65 | V10: =(O10/J10)^(1/COLUMNS(F10:J10))-1 -> 0.21253684
C11: Domestic Company Operated | F11: =Operations!F31 -> 78587 | G11: =Operations!G31 -> 112042 | H11: =Operations!H31 -> 183219 | I11: =Operations!I31 -> 259350 | J11: =Operations!J31 -> 346388 | K11: =Operations!K31 -> 440767.48 | L11: =Operations!L31 -> 562237.21 | M11: =Operations!M31 -> 692200.5 | ... O11: =Operations!O31 -> 905772.01
C12: Licensing | F12: =Operations!F32 -> 3869 | G12: =Operations!G32 -> 6488 | H12: =Operations!H32 -> 7373 | I12: =Operations!I32 -> 9125 | J12: =Operations!J32 -> 12422 | K12: =Operations!K32 -> 15254.442 | L12: =Operations!L32 -> 18999.161 | M12: =Operations!M32 -> 24163.035 | ... O12: =Operations!O32 -> 34685.648
B14: Store Level Costs | F14: =Operations!F70 -> 58168 | G14: =Operations!G70 -> 85181 | H14: =Operations!H70 -> 130345 | I14: =Operations!I70 -> 186058 | J14: =Operations!J70 -> 254079 | K14: =Operations!K70 -> 335068.2 | L14: =Operations!L70 -> 436523.53 | M14: =Operations!M70 -> 544456.84 | ... O14: =Operations!O70 -> 707890.5
A15: x | B15: Gross Profit | F15: =F10-F14 -> 24288 | G15: =G10-G14 -> 33349 | H15: =H10-H14 -> 60247 | I15: =I10-I14 -> 82417 | J15: =J10-J14 -> 104731 | K15: =K10-K14 -> 120953.73 | L15: =L10-L14 -> 144712.84 | M15: =M10-M14 -> 171906.7 | ... O15: =O10-O14 -> 232567.15 | V15: =(O15/J15)^(1/COLUMNS(F15:J15))-1 -> 0.17299085
C16: Gross Profit Margin % | F16: =F15/F10 -> 0.2945571 | G16: =G15/G10 -> 0.28135493 | H16: =H15/H10 -> 0.31610456 | I16: =I15/I10 -> 0.30698203 | J16: =J15/J10 -> 0.29188428 | K16: =K15/K10 -> 0.26523665 | L16: =L15/L10 -> 0.24897417 | M16: =M15/M10 -> 0.23997131 | ... O16: =O15/O10 -> 0.24729146
B18: SG&A | F18: =Operations!F89+Operations!F92 -> 14787 | G18: =Operations!G89+Operations!G92 -> 24292 | H18: =Operations!H89+Operations!H92 -> 43255 | I18: =Operations!I89+Operations!I92 -> 40076 | J18: =Operations!J89+Operations!J92 -> 48606 | K18: =Operations!K89+Operations!K92 -> 59022.987 | L18: =Operations!L89+Operations!L92 -> 71857.257 | M18: =Operations!M89+Operations!M92 -> 82436.781 | ... O18: =Operations!O89+Operations!O92 -> 98416.055
B19: Depreciation | F19: =Operations!F93 -> 3541 | G19: =Operations!G93 -> 5809 | H19: =Operations!H93 -> 10222 | I19: =Operations!I93 -> 14502 | J19: =Operations!J93 -> 21704 | K19: =Operations!K93 -> 29216.938 | L19: =Operations!L93 -> 36370.255 | M19: =Operations!M93 -> 42532.247 | ... O19: =Operations!O93 -> 46155.145
B20: Other Operating Costs | F20: =Operations!F94 -> 25 | G20: =Operations!G94 -> 105 | H20: =Operations!H94 -> 17 | I20: =Operations!I94 -> 34 | J20: =Operations!J94 -> 608 | K20: =Operations!K94 -> 50 | L20: =Operations!L94 -> 50 | M20: =Operations!M94 -> 50 | ... O20: =Operations!O94 -> 50
A21: x | B21: EBIT | F21: =Operations!F110 -> 5935 | G21: =Operations!G110 -> 3143 | H21: =Operations!H110 -> 6753 | I21: =Operations!I110 -> 27805 | J21: =Operations!J110 -> 33813 | K21: =Operations!K110 -> 32663.801 | L21: =Operations!L110 -> 36435.328 | M21: =Operations!M110 -> 46887.671 | ... O21: =Operations!O110 -> 87945.948 | V21: =(O21/J21)^(1/COLUMNS(F21:J21))-1 -> 0.2106718
C22: EBIT Margin % | H22: =H21/H10 -> 0.035431708 | I22: =I21/I10 -> 0.10356644 | J22: =J21/J10 -> 0.094236504 | K22: =K21/K10 -> 0.0716277 | L22: =L21/L10 -> 0.062685906 | M22: =M21/M10 -> 0.065452342 | N22: =N21/N10 -> 0.084891811 | O22: =O21/O10 -> 0.093513991
B24: Other Income | F24: 0 | G24: 0 | H24: 7 | I24: 1065 | J24: 128123 | K24: 0 | L24: 0 | M24: 0 | N24: 0 | O24: 0 | P24: 0 | Q24: 0 | R24: 0 | S24: 0 | T24: 0 | U24: 0 고정.
B25: Interest Expense/(Income) | F25: 52 | G25: 363 | H25: 332 | I25: 374 | J25: 1643 | K25: =IF(Circ=0,0,'Debt&Interest'!K55+'Debt&Interest'!K59) -> 1209.1954 | L25: =IF(Circ=0,0,'Debt&Interest'!L55+'Debt&Interest'!L59) -> 1268.3362 | M25: =IF(Circ=0,0,'Debt&Interest'!M55+'Debt&Interest'!M59) -> 1024.0566 | N25: =IF(Circ=0,0,'Debt&Interest'!N55+'Debt&Interest'!N59) -> -107.95514 | O25: =IF(Circ=0,0,'Debt&Interest'!O55+'Debt&Interest'!O59) -> -2032.4278
B26: Pre-tax Income | F26: =F21+F24-F25 -> 5883 | G26: =G21+G24-G25 -> 2780 | H26: =H21+H24-H25 -> 6428 | I26: =I21+I24-I25 -> 28496 | J26: =J21+J24-J25 -> 160293 | K26: =K21+K24-K25 -> 31454.606 | L26: =L21+L24-L25 -> 35166.992 | M26: =M21+M24-M25 -> 45863.614 | ... O26: =O21+O24-O25 -> 89978.376
B28: Income Tax | F28: 460 | G28: 662 | H28: 3304 | I28: 6350 | J28: 151409 | K28: =K26*K29 -> 6605.4673 | L28: =L26*L29 -> 7385.0683 | M28: =M26*M29 -> 9631.359 | N28: =N26*N29 -> 15001.894 | O28: =O26*O29 -> 18895.459
C29: Tax Rate % | F29: =F28/F26 -> 0.078191399 | G29: =G28/G26 -> 0.2381295 | H29: =H28/H26 -> 0.51400124 | I29: =I28/I26 -> 0.22283829 | J29: =J28/J26 -> 0.94457649 | K29: 0.21 | L29: 0.21 | M29: 0.21 | N29: 0.21 | O29: 0.21 | P29: 0.21 | Q29: 0.21 | R29: 0.21 | S29: 0.21 | T29: 0.21 | U29: 21% 고정.
A30: x | B30: Net Income | F30: =F26-F28 -> 5423 | G30: =G26-G28 -> 2118 | H30: =H26-H28 -> 3124 | I30: =I26-I28 -> 22146 | J30: =J26-J28 -> 8884 | K30: =K26-K28 -> 24849.139 | L30: =L26-L28 -> 27781.924 | M30: =M26-M28 -> 36232.255 | ... O30: =O26-O28 -> 71082.917 | V30: =(O30/J30)^(1/COLUMNS(F30:J30))-1 -> 0.51576313
C31: Net Income Margin % | F31: =F30/F10 -> 0.06576841 | G31: =G30/G10 -> 0.017868894 | H31: =H30/H10 -> 0.016391034 | I31: =I30/I10 -> 0.082488127 | J31: =J30/J10 -> 0.024759622 | K31: =K30/K10 -> 0.054491105 | L31: =L30/L10 -> 0.047797979 | M31: =M30/M10 -> 0.050578029 | ... O31: =O30/O10 -> 0.075583326
B33: Non-Controlling Interests | F33: 0 | G33: 0 | H33: 11900 | I33: 9700 | J33: 9204 | K33: 0 | L33: 0 | M33: 0 | N33: 0 | O33: 0 | P33: 0 | Q33: 0 | R33: 0 | S33: 0 | T33: 0
A34: x | B34: Net Income to Common | F34: =F30-F33 -> 5423 | G34: =G30-G33 -> 2118 | H34: =H30-H33 -> -8776 | I34: =I30-I33 -> 12446 | J34: =J30-J33 -> -320 | K34: =K30-K33 -> 24849.139 | L34: =L30-L33 -> 27781.924 | M34: =M30-M33 -> 36232.255 | ... O34: =O30-O33 -> 71082.917
B36: Diluted Shares Outstanding (in '000 shares) | H36: 20982.881 | I36: 25470.089 | J36: 27078.149 | K36: =Shares!K20 -> 37777.325 | L36: =Shares!L20 -> 37787.325 | M36: =Shares!M20 -> 37794.825 | N36: =Shares!N20 -> 37799.825 | O36: =Shares!O20 -> 37804.825
B37: Diluted Earnings Per Shares (EPS) | H37: =H30/H36 -> 0.14888327 | I37: =I30/I36 -> 0.86949048 | J37: =J30/J36 -> 0.32808742 | K37: =K30/K36 -> 0.65777921 | L37: =L30/L36 -> 0.73521806 | M37: =M30/M36 -> 0.95865653 | N37: =N30/N36 -> 1.4930148 | O37: =O30/O36 -> 1.8802605 | V37: =(O37/J37)^(1/COLUMNS(F37:J37))-1 -> 0.41790028
B39: S&P Capital IQ Consensus GAAP EPS | K39: 0.51 | L39: 0.82 | M39: 1.22 | N39: 1.57
B40: S&P Capital IQ Consensus Adjusted EPS | K40: 0.54 | L40: 0.76 | M40: 0.98 | N40: 1.57

Sheet Balance Sheet
B2: Shake Shack, Inc (SHAK)
B3: Balance Sheet
B4: (units in USD '000)
H7: Historical Year Ending December 31, | K7: Projected year Ending December 31,
F8: 2013 | G8: =F8+1 -> 2014 | H8: =G8+1 -> 2015 | I8: =H8+1 -> 2016 | J8: =I8+1 -> 2017 | K8: =J8+1 -> 2018 | L8: =K8+1 -> 2019 | M8: =L8+1 -> 2020 | N8: =M8+1 -> 2021 | ... T8: =S8+1 -> 2027
A10: x | B10: Cash & Cash Equivalents | G10: 2677 | H10: 70849 | I10: 73647 | J10: 84543 | K10: ='Cash Flow'!K41 -> 71330.965 | L10: ='Cash Flow'!L41 -> 59011.741 | M10: ='Cash Flow'!M41 -> 70073.327 | N10: ='Cash Flow'!N41 -> 128772.68 | O10: ='Cash Flow'!O41 -> 203231.14
B11: Accounts Receivable | G11: 3278 | H11: 4217 | I11: 6006 | J11: 5641 | K11: ='Working Capital'!K14 -> 7496.2508 | L11: ='Working Capital'!L14 -> 9554.5704 | M11: ='Working Capital'!M14 -> 11775.839 | N11: ='Working Capital'!N14 -> 13812.192 | O11: ='Working Capital'!O14 -> 15459.578
B12: Inventories | G12: 529 | H12: 543 | I12: 806 | J12: 1258 | K12: ='Working Capital'!K15 -> 1468.7921 | L12: ='Working Capital'!L15 -> 1913.5278 | M12: ='Working Capital'!M15 -> 2386.6601 | N12: ='Working Capital'!N15 -> 2776.4415 | O12: ='Working Capital'!O15 -> 3103.0817
B13: Prepaid Expenses & Other | G13: 1441 | H13: 3325 | I13: 3485 | J13: 1757 | K13: ='Working Capital'!K16 -> 3648.1754 | L13: ='Working Capital'!L16 -> 4649.891 | M13: ='Working Capital'!M16 -> 5730.9083 | N13: ='Working Capital'!N16 -> 6721.9332 | O13: ='Working Capital'!O16 -> 7523.6612
C14: Total Current Assets | G14: =SUM(G10:G13) -> 7925 | H14: =SUM(H10:H13) -> 78934 | I14: =SUM(I10:I13) -> 83944 | J14: =SUM(J10:J13) -> 93199 | K14: =SUM(K10:K13) -> 83944.184 | L14: =SUM(L10:L13) -> 75129.73 | M14: =SUM(M10:M13) -> 89966.734 | N14: =SUM(N10:N13) -> 152083.25 | O14: =SUM(O10:O13) -> 229317.46
B16: PP&E | G16: 70124 | H16: 93041 | I16: 136264 | J16: 187095 | K16: ='PP&E'!K30 -> 233778.06 | L16: ='PP&E'!L30 -> 285407.81 | M16: ='PP&E'!M30 -> 320575.56 | N16: ='PP&E'!N30 -> 325028.85 | O16: ='PP&E'!O30 -> 326373.71
B17: Deferred Income Taxes | G17: 161 | H17: 201957 | I17: 313207 | J17: 185914 | K17: ='Other LT Items'!K11 -> 185914 | L17: ='Other LT Items'!L11 -> 185914 | M17: ='Other LT Items'!M11 -> 185914 | N17: ='Other LT Items'!N11 -> 185914 | O17: ='Other LT Items'!O11 -> 185914
B18: Goodwill | G18: 0 | H18: 0 | I18: 0 | J18: 0 | K18: ='Other LT Items'!K12 -> 0
B19: Other Long-term Assets | G19: 4752 | H19: 5615 | I19: 4779 | J19: 4398 | K19: ='Other LT Items'!K13 -> 3898 | L19: ='Other LT Items'!L13 -> 3398 | M19: ='Other LT Items'!M13 -> 2898 | N19: ='Other LT Items'!N13 -> 2398 | O19: ='Other LT Items'!O13 -> 1898
A20: x | C20: Total Assets | G20: =SUM(G16:G19)+G14 -> 82962 | H20: =SUM(H16:H19)+H14 -> 379547 | I20: =SUM(I16:I19)+I14 -> 538194 | J20: =SUM(J16:J19)+J14 -> 470606 | K20: =SUM(K16:K19)+K14 -> 507534.25 | L20: =SUM(L16:L19)+L14 -> 549849.54 | M20: =SUM(M16:M19)+M14 -> 599354.29 | N20: =SUM(N16:N19)+N14 -> 665424.1 | O20: =SUM(O16:O19)+O14 -> 743503.17
B22: Accounts Payable | G22: 6440 | H22: 6786 | I22: 6921 | J22: 8210 | K22: ='Working Capital'!K19 -> 10097.946 | L22: ='Working Capital'!L19 -> 13155.504 | M22: ='Working Capital'!M19 -> 16408.288 | N22: ='Working Capital'!N19 -> 19088.035 | O22: ='Working Capital'!O19 -> 21333.686
B23: Accrued Expenses | G23: 5578 | H23: 6801 | I23: 8538 | J23: 11649 | K23: ='Working Capital'!K20 -> 15078.069 | L23: ='Working Capital'!L20 -> 19643.559 | M23: ='Working Capital'!M20 -> 24500.558 | N23: ='Working Capital'!N20 -> 28501.907 | O23: ='Working Capital'!O20 -> 31855.073
B24: Accrued Wages & Related | G24: 2410 | H24: 5804 | I24: 6084 | J24: 6228 | K24: ='Working Capital'!K21 -> 8376.7049 | L24: ='Working Capital'!L21 -> 10913.088 | M24: ='Working Capital'!M21 -> 13611.421 | N24: ='Working Capital'!N21 -> 15834.393 | O24: ='Working Capital'!O21 -> 17697.263
B25: Other Current Liabilities | G25: 1749 | H25: 4614 | I25: 10173 | J25: 7937 | K25: ='Working Capital'!K22 -> 11727.387 | L25: ='Working Capital'!L22 -> 15278.323 | M25: ='Working Capital'!M22 -> 19055.989 | N25: ='Working Capital'!N22 -> 22168.15 | O25: ='Working Capital'!O22 -> 24776.168
C26: Total Current Liabilities | G26: =SUM(G22:G25) -> 16177 | H26: =SUM(H22:H25) -> 24005 | I26: =SUM(I22:I25) -> 31716 | J26: =SUM(J22:J25) -> 34024 | K26: =SUM(K22:K25) -> 45280.106 | L26: =SUM(L22:L25) -> 58990.474 | M26: =SUM(M22:M25) -> 73576.256 | N26: =SUM(N22:N25) -> 85592.485 | O26: =SUM(O22:O25) -> 95662.189
B28: Revolver | G28: 32000 | H28: 0 | I28: 0 | J28: 0 | K28: ='Debt&Interest'!K43 -> 0 | L28: ='Debt&Interest'!L43 -> 0 | M28: ='Debt&Interest'!M43 -> 0 | N28: ='Debt&Interest'!N43 -> 0 | O28: ='Debt&Interest'!O43 -> 0
B29: Capital Leases | G29: 313 | H29: 313 | I29: 2007 | J29: 14518 | K29: ='Debt&Interest'!K47 -> 14018 | L29: ='Debt&Interest'!L47 -> 13018 | M29: ='Debt&Interest'!M47 -> 12018 | N29: ='Debt&Interest'!N47 -> 11018 | O29: ='Debt&Interest'!O47 -> 10018
B30: Long-term Debt | G30: 17853 | H30: 22927 | I30: 31107 | J30: 36596 | K30: ='Debt&Interest'!K51 -> 35096 | L30: ='Debt&Interest'!L51 -> 32096 | M30: ='Debt&Interest'!M51 -> 29096 | N30: ='Debt&Interest'!N51 -> 26096 | O30: ='Debt&Interest'!O51 -> 23096
B31: Other Long-term Liabilities | G31: 4019 | H31: 175283 | I31: =267902+4109 -> 272011 | J31: =158436+2553 -> 160989 | K31: ='Other LT Items'!K19 -> 159989 | L31: ='Other LT Items'!L19 -> 158989 | M31: ='Other LT Items'!M19 -> 157989 | N31: ='Other LT Items'!N19 -> 156989 | O31: ='Other LT Items'!O19 -> 155989
A32: x | C32: Total Liabilites | G32: =SUM(G28:G31)+G26 -> 70362 | H32: =SUM(H28:H31)+H26 -> 222528 | I32: =SUM(I28:I31)+I26 -> 336841 | J32: =SUM(J28:J31)+J26 -> 246127 | K32: =SUM(K28:K31)+K26 -> 254383.11 | L32: =SUM(L28:L31)+L26 -> 263093.47 | M32: =SUM(M28:M31)+M26 -> 272679.26 | N32: =SUM(N28:N31)+N26 -> 279695.49 | O32: =SUM(O28:O31)+O26 -> 284765.19
B34: Common Equity | G34: =G36-G35 -> 12600 | H34: =H36-H35 -> 100615 | I34: =I36-I35 -> 152188 | J34: =J36-J35 -> 169492 | K34: =K36-K35 -> 200164.14 | L34: =L36-L35 -> 234724.33 | M34: =M36-M35 -> 275645.29 | N34: =N36-N35 -> 335507.87 | O34: =O36-O35 -> 408431.95
B35: Non-Controlling Interests | H35: 56404 | I35: 49165 | J35: 54987 | K35: 54987 | L35: 54987 | M35: 54987 | N35: 54987 | O35: 54987 | U35: 직전년 고정
A36: x | C36: Total Equity | G36: 12600 | H36: 157019 | I36: 201353 | J36: 224479 | K36: =Equity!K17 -> 255151.14 | L36: =Equity!L17 -> 289711.33 | M36: =Equity!M17 -> 330632.29 | N36: =Equity!N17 -> 390494.87 | O36: =Equity!O17 -> 463418.95
A38: x | C38: Total Liabilities & Equity | G38: =G36+G32 -> 82962 | H38: =H36+H32 -> 379547 | I38: =I36+I32 -> 538194 | J38: =J36+J32 -> 470606 | K38: =K36+K32 -> 509534.25 | L38: =L36+L32 -> 552804.8 | M38: =M36+M32 -> 603311.54 | N38: =N36+N32 -> 670190.36 | O38: =O36+O32 -> 748184.14
C39: Check | G39: =BS!D66 -> 82962 | H39: =BS!E66 -> 379547 | I39: =BS!F66 -> 538194 | J39: =BS!G66 -> 470606
F90: =SCF!C24 -> 93 | G90: =SCF!D24 -> 165 | H90: =SCF!E24 -> 16681 | I90: =SCF!F24 -> 5354 | J90: =SCF!G24 -> 5623 | K90: 5623 | L90: 5623 | M90: 5623 | N90: 5623 | O90: 5623 | U90: FY 2017 flat
F91: =F89-F90 -> -93 | G91: =G89-G90 -> -165 | H91: =H89-H90 -> -16681 | I91: =I89-I90 -> -5354 | J91: =J89-J90 -> -5623

Sheet Cash Flow
B2: Shake Shack, Inc (SHAK)
B3: Cash Flow Statement
B4: (units in USD '000)
H7: Historical Year Ending December 31, | K7: Projected year Ending December 31,
F8: 2013 | G8: =F8+1 -> 2014 | H8: =G8+1 -> 2015 | I8: =H8+1 -> 2016 | J8: =I8+1 -> 2017 | K8: =J8+1 -> 2018 | L8: =K8+1 -> 2019 | M8: =L8+1 -> 2020 | N8: =M8+1 -> 2021 | ... T8: =S8+1 -> 2027
A10: x | B10: Operating
C11: Net Income | K11: ='Income Statement'!K30 -> 24849.139 | L11: ='Income Statement'!L30 -> 27781.924 | M11: ='Income Statement'!M30 -> 36232.255 | N11: ='Income Statement'!N30 -> 56435.696 | O11: ='Income Statement'!O30 -> 71082.917
C12: Depreciation | K12: =Operations!K93 -> 29216.938 | L12: =Operations!L93 -> 36370.255 | M12: =Operations!M93 -> 42532.247 | N12: =Operations!N93 -> 45546.708 | O12: =Operations!O93 -> 46155.145
C13: Amortization | K13: 0 | L13: 0 | M13: 0 | N13: 0 | O13: 0 | P13: 0 | Q13: 0 | R13: 0 | S13: 0 | T13: 0
C14: Stock-based Compensation Expense | K14: =Operations!K90 -> 5623 | L14: =Operations!L90 -> 5623 | M14: =Operations!M90 -> 5623 | N14: =Operations!N90 -> 5623 | O14: =Operations!O90 -> 5623
C15: Change in Working Capital | K15: ='Working Capital'!K27 -> 7298.8881 | L15: ='Working Capital'!L27 -> 10205.597 | M15: ='Working Capital'!M27 -> 10810.364 | N15: ='Working Capital'!N27 -> 8599.0702 | O15: ='Working Capital'!O27 -> 7293.9496
C16: Change in Other LT Assets & Liabilities | K16: ='Other LT Items'!K23 -> -500 | L16: ='Other LT Items'!L23 -> -500 | M16: ='Other LT Items'!M23 -> -500 | N16: ='Other LT Items'!N23 -> -500 | O16: ='Other LT Items'!O23 -> -500
D17: Cash Flow from Operations | K17: =SUM(K11:K16) -> 66487.965 | L17: =SUM(L11:L16) -> 79480.776 | M17: =SUM(M11:M16) -> 94697.867 | N17: =SUM(N11:N16) -> 115704.47 | O17: =SUM(O11:O16) -> 129655.01
A19: x | B19: Investing
C20: Capital Expenditures | K20: =-'PP&E'!K12 -> -75900 | L20: =-'PP&E'!L12 -> -88000 | M20: =-'PP&E'!M12 -> -77700 | N20: =-'PP&E'!N12 -> -50000 | O20: =-'PP&E'!O12 -> -47500
C21: Asset Sales | K21: 0 | L21: 0 | M21: 0 | N21: 0 | O21: 0
C22: Additions to Intangibles | K22: 0 | L22: 0 | M22: 0 | N22: 0 | O22: 0 | P22: 0 | Q22: 0 | R22: 0 | S22: 0 | T22: 0
D23: Cash Flow from Investing | K23: =SUM(K20:K22) -> -75900 | L23: =SUM(L20:L22) -> -88000 | M23: =SUM(M20:M22) -> -77700 | N23: =SUM(N20:N22) -> -50000 | O23: =SUM(O20:O22) -> -47500
A25: x | B25: Cash Flow Available for Financing | K25: =K17+K23 -> -9412.0346 | L25: =L17+L23 -> -8519.2241 | M25: =M17+M23 -> 16997.867 | N25: =N17+N23 -> 65704.475 | O25: =O17+O23 -> 82155.011
A27: x | B27: Financing
C28: Issuance/(Repayment) of Revolver | K28: ='Debt&Interest'!K27 -> 0 | L28: ='Debt&Interest'!L27 -> 0 | M28: ='Debt&Interest'!M27 -> 0 | N28: ='Debt&Interest'!N27 -> 0 | O28: ='Debt&Interest'!O27 -> 0
C29: Increase in Capital Leases | K29: ='Debt&Interest'!K19 -> 1000 | L29: ='Debt&Interest'!L19 -> 1000 | M29: ='Debt&Interest'!M19 -> 1000 | N29: ='Debt&Interest'!N19 -> 1000 | O29: ='Debt&Interest'!O19 -> 1000
C30: Repayment of Capital Leases | K30: ='Debt&Interest'!K20 -> -2000 | L30: ='Debt&Interest'!L20 -> -2000 | M30: ='Debt&Interest'!M20 -> -2000 | N30: ='Debt&Interest'!N20 -> -2000 | O30: ='Debt&Interest'!O20 -> -2000
C31: Increase in Long-term Debt | K31: ='Debt&Interest'!K21 -> 3000 | L31: ='Debt&Interest'!L21 -> 3000 | M31: ='Debt&Interest'!M21 -> 3000 | N31: ='Debt&Interest'!N21 -> 3000 | O31: ='Debt&Interest'!O21 -> 3000
C32: Repayment of Long-term Debt | K32: ='Debt&Interest'!K22 -> -6000 | L32: ='Debt&Interest'!L22 -> -6000 | M32: ='Debt&Interest'!M22 -> -6000 | N32: ='Debt&Interest'!N22 -> -6000 | O32: ='Debt&Interest'!O22 -> -6000
C33: Repurchase of Equity | K33: =Equity!K13 -> 0 | L33: =Equity!L13 -> 0 | M33: =Equity!M13 -> -284.21789 | N33: =Equity!N13 -> -387.59722 | O33: =Equity!O13 -> -422.69152
C34: Dividends Paid Out | K34: =Equity!K14 -> 0 | L34: =Equity!L14 -> 0 | M34: =Equity!M14 -> -1852.063 | N34: =Equity!N14 -> -2817.5206 | O34: =Equity!O14 -> -3473.865
C35: Proceeds from Options | K35: =Equity!K15 -> 200 | L35: =Equity!L15 -> 200 | M35: =Equity!M15 -> 200 | N35: =Equity!N15 -> 200 | O35: =Equity!O15 -> 200
C36: Change in Non-Controlling Interest | K36: =Equity!K16 -> 0 | L36: =Equity!L16 -> 0 | M36: =Equity!M16 -> 0 | N36: =Equity!N16 -> 0 | O36: =Equity!O16 -> 0
D37: Cash Flow from Financing | K37: =SUM(K28:K36) -> -3800 | L37: =SUM(L28:L36) -> -3800 | M37: =SUM(M28:M36) -> -5936.2809 | N37: =SUM(N28:N36) -> -7005.1178 | O37: =SUM(O28:O36) -> -7696.5565
B39: Net Change in Cash | K39: =K25+K37 -> -13212.035 | L39: =L25+L37 -> -12319.224 | M39: =M25+M37 -> 11061.586 | N39: =N25+N37 -> 58699.357 | O39: =O25+O37 -> 74458.455
C40: Beginning Cash Balance | K40: ='Balance Sheet'!J10 -> 84543 | L40: ='Balance Sheet'!K10 -> 71330.965 | M40: ='Balance Sheet'!L10 -> 59011.741 | N40: ='Balance Sheet'!M10 -> 70073.327 | O40: ='Balance Sheet'!N10 -> 128772.68
C41: Ending Cash Balance | K41: =SUM(K39:K40) -> 71330.965 | L41: =SUM(L39:L40) -> 59011.741 | M41: =SUM(M39:M40) -> 70073.327 | N41: =SUM(N39:N40) -> 128772.68 | O41: =SUM(O39:O40) -> 203231.14
A42: x

Sheet Working Capital
B2: Shake Shack, Inc (SHAK)
B3: Working Capital
B4: (units in USD '000)
H7: Historical Year Ending December 31, | K7: Projected year Ending December 31,
F8: 2013 | G8: =F8+1 -> 2014 | H8: =G8+1 -> 2015 | I8: =H8+1 -> 2016 | J8: =I8+1 -> 2017 | K8: =J8+1 -> 2018 | L8: =K8+1 -> 2019 | M8: =L8+1 -> 2020 | N8: =M8+1 -> 2021 | ... T8: =S8+1 -> 2027
A10: x | B10: Total Revenue | G10: =Operations!G30 -> 118530 | H10: =Operations!H30 -> 190592 | I10: =Operations!I30 -> 268475 | J10: =Operations!J30 -> 358810 | K10: =Operations!K30 -> 456021.93 | L10: =Operations!L30 -> 581236.37 | M10: =Operations!M30 -> 716363.54 | N10: =Operations!N30 -> 840241.65 | O10: =Operations!O30 -> 940457.65
B11: Cost of Goods Sold | G11: =Operations!G70 -> 85181 | H11: =Operations!H70 -> 130345 | I11: =Operations!I70 -> 186058 | J11: =Operations!J70 -> 254079 | K11: =Operations!K70 -> 335068.2 | L11: =Operations!L70 -> 436523.53 | M11: =Operations!M70 -> 544456.84 | N11: =Operations!N70 -> 633375.71 | O11: =Operations!O70 -> 707890.5
A13: x | B13: Working Capital Balances
C14: Accounts Receivable | G14: ='Balance Sheet'!G11 -> 3278 | H14: ='Balance Sheet'!H11 -> 4217 | I14: ='Balance Sheet'!I11 -> 6006 | J14: ='Balance Sheet'!J11 -> 5641 | K14: =K10/365*K32 -> 7496.2508 | L14: =L10/365*L32 -> 9554.5704 | M14: =M10/365*M32 -> 11775.839 | N14: =N10/365*N32 -> 13812.192 | O14: =O10/365*O32 -> 15459.578
C15: Inventories | G15: ='Balance Sheet'!G12 -> 529 | H15: ='Balance Sheet'!H12 -> 543 | I15: ='Balance Sheet'!I12 -> 806 | J15: ='Balance Sheet'!J12 -> 1258 | K15: =K11/365*K33 -> 1468.7921 | L15: =L11/365*L33 -> 1913.5278 | M15: =M11/365*M33 -> 2386.6601 | N15: =N11/365*N33 -> 2776.4415 | O15: =O11/365*O33 -> 3103.0817
C16: Prepaid Expenses & Other | G16: ='Balance Sheet'!G13 -> 1441 | H16: ='Balance Sheet'!H13 -> 3325 | I16: ='Balance Sheet'!I13 -> 3485 | J16: ='Balance Sheet'!J13 -> 1757 | K16: =K10*K34 -> 3648.1754 | L16: =L10*L34 -> 4649.891 | M16: =M10*M34 -> 5730.9083 | N16: =N10*N34 -> 6721.9332 | O16: =O10*O34 -> 7523.6612
D17: Total Non-cash Current Assets | G17: =SUM(G14:G16) -> 5248 | H17: =SUM(H14:H16) -> 8085 | I17: =SUM(I14:I16) -> 10297 | J17: =SUM(J14:J16) -> 8656 | K17: =SUM(K14:K16) -> 12613.218 | L17: =SUM(L14:L16) -> 16117.989 | M17: =SUM(M14:M16) -> 19893.407 | N17: =SUM(N14:N16) -> 23310.566 | O17: =SUM(O14:O16) -> 26086.321
C19: Accounts Payable | G19: ='Balance Sheet'!G22 -> 6440 | H19: ='Balance Sheet'!H22 -> 6786 | I19: ='Balance Sheet'!I22 -> 6921 | J19: ='Balance Sheet'!J22 -> 8210 | K19: =K11/365*K36 -> 10097.946 | L19: =L11/365*L36 -> 13155.504 | M19: =M11/365*M36 -> 16408.288 | N19: =N11/365*N36 -> 19088.035 | O19: =O11/365*O36 -> 21333.686
C20: Accrued Expenses | G20: ='Balance Sheet'!G23 -> 5578 | H20: ='Balance Sheet'!H23 -> 6801 | I20: ='Balance Sheet'!I23 -> 8538 | J20: ='Balance Sheet'!J23 -> 11649 | K20: =K$11*K37 -> 15078.069 | L20: =L$11*L37 -> 19643.559 | M20: =M$11*M37 -> 24500.558 | N20: =N$11*N37 -> 28501.907 | O20: =O$11*O37 -> 31855.073
C21: Accrued Wages & Related | G21: ='Balance Sheet'!G24 -> 2410 | H21: ='Balance Sheet'!H24 -> 5804 | I21: ='Balance Sheet'!I24 -> 6084 | J21: ='Balance Sheet'!J24 -> 6228 | K21: =K$11*K38 -> 8376.7049 | L21: =L$11*L38 -> 10913.088 | M21: =M$11*M38 -> 13611.421 | N21: =N$11*N38 -> 15834.393 | O21: =O$11*O38 -> 17697.263
C22: Other Current Liabilities | G22: ='Balance Sheet'!G25 -> 1749 | H22: ='Balance Sheet'!H25 -> 4614 | I22: ='Balance Sheet'!I25 -> 10173 | J22: ='Balance Sheet'!J25 -> 7937 | K22: =K$11*K39 -> 11727.387 | L22: =L$11*L39 -> 15278.323 | M22: =M$11*M39 -> 19055.989 | N22: =N$11*N39 -> 22168.15 | O22: =O$11*O39 -> 24776.168
D23: Total Non-debt Current Liabilities | G23: =SUM(G19:G22) -> 16177 | H23: =SUM(H19:H22) -> 24005 | I23: =SUM(I19:I22) -> 31716 | J23: =SUM(J19:J22) -> 34024 | K23: =SUM(K19:K22) -> 45280.106 | L23: =SUM(L19:L22) -> 58990.474 | M23: =SUM(M19:M22) -> 73576.256 | N23: =SUM(N19:N22) -> 85592.485 | O23: =SUM(O19:O22) -> 95662.189
B25: Net Working Capital / (Deficit) | G25: =G17-G23 -> -10929 | H25: =H17-H23 -> -15920 | I25: =I17-I23 -> -21419 | J25: =J17-J23 -> -25368 | K25: =K17-K23 -> -32666.888 | L25: =L17-L23 -> -42872.485 | M25: =M17-M23 -> -53682.849 | N25: =N17-N23 -> -62281.919 | O25: =O17-O23 -> -69575.869
A27: x | B27: (Increase) / Decrease in Net Working Capital | H27: =G25-H25 -> 4991 | I27: =H25-I25 -> 5499 | J27: =I25-J25 -> 3949 | K27: =J25-K25 -> 7298.8881 | L27: =K25-L25 -> 10205.597 | M27: =L25-M25 -> 10810.364 | N27: =M25-N25 -> 8599.0702 | O27: =N25-O25 -> 7293.9496
B29: Ratios & Assumptions
C30: Numbers of days in a period | H30: 365
C32: Accounts Receivable (Collection Period in Days) | G32: =G14/G10*Days -> 10.094238 | H32: =H14/H10*Days -> 8.0759161 | I32: =I14/I10*Days -> 8.1653413 | J32: =J14/J10*Days -> 5.7383155 | K32: 6 | L32: 6 | M32: 6 | N32: 6 | O32: 6 | P32: 6 | Q32: 6 | R32: 6 | S32: 6 | T32: 6 | U32: 6 고정
C33: Inventories (Days Outstanding) | G33: =G15/G11*Days -> 2.2667614 | H33: =H15/H11*Days -> 1.5205416 | I33: =I15/I11*Days -> 1.5811736 | J33: =J15/J11*Days -> 1.8071938 | K33: 1.6 | L33: 1.6 | M33: 1.6 | N33: 1.6 | O33: 1.6 | P33: 1.6 | Q33: 1.6 | R33: 1.6 | S33: 1.6 | T33: 1.6 | U33: 1.6 고정
C34: Other Current Assets (% of Revenue) | G34: =G16/G10 -> 0.01215726 | H34: =H16/H10 -> 0.017445643 | I34: =I16/I10 -> 0.012980724 | J34: =J16/J10 -> 0.004896742 | K34: 0.008 | L34: 0.008 | M34: 0.008 | N34: 0.008 | O34: 0.008 | P34: 0.008 | Q34: 0.008 | R34: 0.008 | S34: 0.008 | T34: 0.008 | U34: 0.8% 고정
C36: Accounts Payable (Days Outstanding) | G36: =G19/G11*Days -> 27.595356 | H36: =H19/H11*Days -> 19.00257 | I36: =I19/I11*Days -> 13.577298 | J36: =J19/J11*Days -> 11.794166 | K36: 11 | L36: 11 | M36: 11 | N36: 11 | O36: 11 | P36: 11 | Q36: 11 | R36: 11 | S36: 11 | T36: 11 | U36: 11고정
C37: Accrued Expenses (% of COGS) | G37: =G20/G$11 -> 0.065484087 | H37: =H20/H$11 -> 0.052176915 | I37: =I20/I$11 -> 0.045888916 | J37: =J20/J$11 -> 0.045847945 | K37: 0.045 | L37: 0.045 | M37: 0.045 | N37: 0.045 | O37: 0.045 | P37: 0.045 | Q37: 0.045 | R37: 0.045 | S37: 0.045 | T37: 0.045 | U37: 4.5% 고정
C38: Accrued Wages & Related (% of COGS) | G38: =G21/G$11 -> 0.028292694 | H38: =H21/H$11 -> 0.044527983 | I38: =I21/I$11 -> 0.032699481 | J38: =J21/J$11 -> 0.024512061 | K38: 0.025 | L38: 0.025 | M38: 0.025 | N38: 0.025 | O38: 0.025 | P38: 0.025 | Q38: 0.025 | R38: 0.025 | S38: 0.025 | T38: 0.025 | U38: 2.5% 고정
C39: Other Current Liabilities (% of COGS) | G39: =G22/G$11 -> 0.020532748 | H39: =H22/H$11 -> 0.035398366 | I39: =I22/I$11 -> 0.054676499 | J39: =J22/J$11 -> 0.031238316 | K39: 0.035 | L39: 0.035 | M39: 0.035 | N39: 0.035 | O39: 0.035 | P39: 0.035 | Q39: 0.035 | R39: 0.035 | S39: 0.035 | T39: 0.035 | U39: 3.5% 고정
A40: x

Sheet PP&E
B2: Shake Shack, Inc (SHAK)
B3: PP&E and Depreciation Schedule
B4: (units in USD '000)
H7: Historical Year Ending December 31, | K7: Projected year Ending December 31,
F8: 2013 | G8: =F8+1 -> 2014 | H8: =G8+1 -> 2015 | I8: =H8+1 -> 2016 | J8: =I8+1 -> 2017 | K8: =J8+1 -> 2018 | L8: =K8+1 -> 2019 | M8: =L8+1 -> 2020 | N8: =M8+1 -> 2021 | ... T8: =S8+1 -> 2027
A10: x | B10: Total Revenue | F10: ='Working Capital'!F10 -> 0 | G10: ='Working Capital'!G10 -> 118530 | H10: ='Working Capital'!H10 -> 190592 | I10: ='Working Capital'!I10 -> 268475 | J10: ='Working Capital'!J10 -> 358810 | K10: ='Working Capital'!K10 -> 456021.93 | L10: ='Working Capital'!L10 -> 581236.37 | M10: ='Working Capital'!M10 -> 716363.54 | ... O10: ='Working Capital'!O10 -> 940457.65
A12: x | B12: Capital Expenditure | F12: =ABS(SCF!C33) -> 16194 | G12: =ABS(SCF!D33) -> 28515 | H12: =ABS(SCF!E33) -> 32117 | I12: =ABS(SCF!F33) -> 54433 | J12: =ABS(SCF!G33) -> 61533 | K12: =K15*K16 -> 75900 | L12: =L15*L16 -> 88000 | M12: =M15*M16 -> 77700 | N12: =N15*N16 -> 50000 | O12: =O15*O16 -> 47500
C13: Capex as % of Revenue | G13: =G12/G10 -> 0.24057201 | H13: =H12/H10 -> 0.16851179 | I13: =I12/I10 -> 0.20274886 | J13: =J12/J10 -> 0.17149188 | K13: =K12/K10 -> 0.16643937 | L13: =L12/L10 -> 0.1514014 | M13: =M12/M10 -> 0.10846448 | N13: =N12/N10 -> 0.059506691 | O13: =O12/O10 -> 0.050507325
C15: New Store Openings (gross) | G15: =Operations!G24 -> 10 | H15: =Operations!H24 -> 13 | I15: =Operations!I24 -> 22 | J15: =Operations!J24 -> 27 | K15: =Operations!K24 -> 33 | L15: =Operations!L24 -> 40 | M15: =Operations!M24 -> 37 | N15: =Operations!N24 -> 25 | O15: =Operations!O24 -> 25 | U15: Step
C16: Capex / New Stores Opened | G16: =G12/G15 -> 2851.5 | H16: =H12/H15 -> 2470.5385 | I16: =I12/I15 -> 2474.2273 | J16: =J12/J15 -> 2279 | K16: 2300 | L16: 2200 | M16: 2100 | N16: 2000 | O16: 1900 | U16: -100
A18: x | B18: Depreciation Expense | F18: ='Income Statement'!F19 -> 3541 | G18: ='Income Statement'!G19 -> 5809 | H18: ='Income Statement'!H19 -> 10222 | I18: ='Income Statement'!I19 -> 14502 | J18: ='Income Statement'!J19 -> 21704 | K18: ='Income Statement'!K19 -> 29216.938 | L18: ='Income Statement'!L19 -> 36370.255 | M18: ='Income Statement'!M19 -> 42532.247 | ... O18: ='Income Statement'!O19 -> 46155.145
C19: Capex / Depreciation | F19: =F12/F18 -> 4.5732844 | G19: =G12/G18 -> 4.9087623 | H19: =H12/H18 -> 3.1419487 | I19: =I12/I18 -> 3.7534823 | J19: =J12/J18 -> 2.8350995 | K19: =K12/K18 -> 2.5978081 | L19: =L12/L18 -> 2.4195596 | M19: =M12/M18 -> 1.8268492 | ... O19: =O12/O18 -> 1.0291377 | U19: Step
C20: Depreciation / Existing Store | G20: =G18/(Operations!G12+Operations!F12)*2 -> 223.42308 | H20: =H18/(Operations!H12+Operations!G12)*2 -> 272.58667 | I20: =I18/(Operations!I12+Operations!H12)*2 -> 268.55556 | J20: =J18/(Operations!J12+Operations!I12)*2 -> 281.87013 | K20: =AVERAGE(H20:J20) -> 274.33745 | L20: =K20-20 -> 254.33745 | M20: =L20-20 -> 234.33745 | N20: =M20-20 -> 214.33745 | O20: =N20-20 -> 194.33745 | U20: -20 | V20: 직전 3개년 avg로 계산 후, 20씩 감소 가정
C22: Depreciation as % of Net PP&E | G22: =G18/'Balance Sheet'!G16 -> 0.082838971 | H22: =H18/'Balance Sheet'!H16 -> 0.10986554 | I22: =I18/'Balance Sheet'!I16 -> 0.10642576 | J22: =J18/'Balance Sheet'!J16 -> 0.11600524 | K22: =K18/K30 -> 0.12497725 | L22: =L18/L30 -> 0.12743259 | M22: =M18/M30 -> 0.13267464 | N22: =N18/N30 -> 0.14013128 | O22: =O18/O30 -> 0.14141809
C23: Implied Useful Life (Years) | G23: ='Balance Sheet'!G16/G18 -> 12.071613 | H23: ='Balance Sheet'!H16/H18 -> 9.1020348 | I23: ='Balance Sheet'!I16/I18 -> 9.3962212 | J23: ='Balance Sheet'!J16/J18 -> 8.6203004 | K23: =K30/K18 -> 8.0014565 | L23: =L30/L18 -> 7.8472863 | M23: =M30/M18 -> 7.5372354 | N23: =N30/N18 -> 7.1361655 | O23: =O30/O18 -> 7.0712314
A25: x | B25: PP&E BASE Table
C26: Beginning Net PP&E | K26: =J30 -> 187095 | L26: =K30 -> 233778.06 | M26: =L30 -> 285407.81 | N26: =M30 -> 320575.56 | O26: =N30 -> 325028.85
D27: Capital Expenditure | K27: =K12 -> 75900 | L27: =L12 -> 88000 | M27: =M12 -> 77700 | N27: =N12 -> 50000 | O27: =O12 -> 47500
D28: (Depreciation Expense) | K28: =-K18 -> -29216.938 | L28: =-L18 -> -36370.255 | M28: =-M18 -> -42532.247 | N28: =-N18 -> -45546.708 | O28: =-O18 -> -46155.145
D29: (Asset Sales) | K29: 0 | L29: 0 | M29: 0 | N29: 0 | O29: 0 | P29: 0 | Q29: 0 | R29: 0 | S29: 0 | T29: 0
A30: x | C30: Ending Net PP&E | G30: ='Balance Sheet'!G16 -> 70124 | H30: ='Balance Sheet'!H16 -> 93041 | I30: ='Balance Sheet'!I16 -> 136264 | J30: ='Balance Sheet'!J16 -> 187095 | K30: =SUM(K26:K29) -> 233778.06 | L30: =SUM(L26:L29) -> 285407.81 | M30: =SUM(M26:M29) -> 320575.56 | N30: =SUM(N26:N29) -> 325028.85 | O30: =SUM(O26:O29) -> 326373.71

Sheet Other LT Items
B2: Shake Shack, Inc (SHAK)
B3: Other Long-term Items
B4: (units in USD '000)
H7: Historical Year Ending December 31, | K7: Projected year Ending December 31,
F8: 2013 | G8: =F8+1 -> 2014 | H8: =G8+1 -> 2015 | I8: =H8+1 -> 2016 | J8: =I8+1 -> 2017 | K8: =J8+1 -> 2018 | L8: =K8+1 -> 2019 | M8: =L8+1 -> 2020 | N8: =M8+1 -> 2021 | ... T8: =S8+1 -> 2027
B10: Assets
C11: Deferred Income Taxes | G11: ='Balance Sheet'!G17 -> 161 | H11: ='Balance Sheet'!H17 -> 201957 | I11: ='Balance Sheet'!I17 -> 313207 | J11: ='Balance Sheet'!J17 -> 185914 | K11: 185914 | L11: 185914 | M11: 185914 | N11: 185914 | O11: 185914 | U11: 직전년 flat.
C12: Goodwill | G12: ='Balance Sheet'!G18 -> 0 | H12: ='Balance Sheet'!H18 -> 0 | I12: ='Balance Sheet'!I18 -> 0 | J12: ='Balance Sheet'!J18 -> 0 | U12: Step
C13: Other Long-term Assets | G13: ='Balance Sheet'!G19 -> 4752 | H13: ='Balance Sheet'!H19 -> 5615 | I13: ='Balance Sheet'!I19 -> 4779 | J13: ='Balance Sheet'!J19 -> 4398 | K13: =J13-500 -> 3898 | L13: =K13-500 -> 3398 | M13: =L13-500 -> 2898 | N13: =M13-500 -> 2398 | O13: =N13-500 -> 1898 | U13: -500 | V13: 직전년 대비 500씩 감소.
D14: Total Other Long-term Assets | G14: =SUM(G11:G13) -> 4913 | H14: =SUM(H11:H13) -> 207572 | I14: =SUM(I11:I13) -> 317986 | J14: =SUM(J11:J13) -> 190312 | K14: =K11+K13 -> 189812 | L14: =L11+L13 -> 189312 | M14: =M11+M13 -> 188812 | N14: =N11+N13 -> 188312 | O14: =O11+O13 -> 187812
D16: (Increase)/Decrease in Other LT Assets | H16: =G14-H14 -> -202659 | I16: =H14-I14 -> -110414 | J16: =I14-J14 -> 127674 | K16: =J14-K14 -> 500 | L16: =K14-L14 -> 500 | M16: =L14-M14 -> 500 | N16: =M14-N14 -> 500 | O16: =N14-O14 -> 500
B18: Liabilities | U18: Step
C19: Other Long-term Liabilities | G19: ='Balance Sheet'!G31 -> 4019 | H19: ='Balance Sheet'!H31 -> 175283 | I19: ='Balance Sheet'!I31 -> 272011 | J19: ='Balance Sheet'!J31 -> 160989 | K19: =J19-1000 -> 159989 | L19: =K19-1000 -> 158989 | M19: =L19-1000 -> 157989 | N19: =M19-1000 -> 156989 | O19: =N19-1000 -> 155989 | U19: -1000 | V19: 직전년 대비 1000씩 감소
D21: Increase/(Decrease) in Other LT Liabilities | H21: =G19-H19 -> -171264 | I21: =H19-I19 -> -96728 | J21: =I19-J19 -> 111022 | K21: =K19-J19 -> -1000 | L21: =L19-K19 -> -1000 | M21: =M19-L19 -> -1000 | N21: =N19-M19 -> -1000 | O21: =O19-N19 -> -1000
A23: x | B23: Change in Other Long-term Assets and Liabilities | H23: =-H16+H21 -> 31395 | I23: =I16-I21 -> -13686 | J23: =J16-J21 -> 16652 | K23: =K16+K21 -> -500 | L23: =L16+L21 -> -500 | M23: =M16+M21 -> -500 | N23: =N16+N21 -> -500 | O23: =O16+O21 -> -500

Sheet Equity
B2: Shake Shack, Inc (SHAK)
B3: Equity
B4: (units in USD '000)
H7: Historical Year Ending December 31, | K7: Projected year Ending December 31,
F8: 2013 | G8: =F8+1 -> 2014 | H8: =G8+1 -> 2015 | I8: =H8+1 -> 2016 | J8: =I8+1 -> 2017 | K8: =J8+1 -> 2018 | L8: =K8+1 -> 2019 | M8: =L8+1 -> 2020 | N8: =M8+1 -> 2021 | ... T8: =S8+1 -> 2027
A10: x | B10: Beginning equity balance | K10: 224479 | L10: 256106.4 | M10: 290713.31 | N10: 331441.29 | O10: 390409.59
C11: Net income | K11: ='Income Statement'!K30 -> 24849.139 | L11: ='Income Statement'!L30 -> 27781.924 | M11: ='Income Statement'!M30 -> 36232.255 | N11: ='Income Statement'!N30 -> 56435.696 | O11: ='Income Statement'!O30 -> 71082.917
C12: Stock-based compensation expense | G12: =Operations!G90 -> 165 | H12: =Operations!H90 -> 16681 | I12: =Operations!I90 -> 5354 | J12: =Operations!J90 -> 5623 | K12: =Operations!K90 -> 5623 | L12: =Operations!L90 -> 5623 | M12: =Operations!M90 -> 5623 | N12: =Operations!N90 -> 5623 | O12: =Operations!O90 -> 5623
C13: Repurchase of equity | K13: 0 | L13: 0 | M13: -284.21789 | N13: -387.59722 | O13: -422.69152
C14: Dividends paid | K14: 0 | L14: 0 | M14: -1852.063 | N14: -2817.5206 | O14: -3473.865
C15: Option proceeds | K15: 200 | L15: 200 | M15: 200 | N15: 200 | O15: 200
C16: Inc/(Dec) in Non-Controlling Interest | K16: 0 | L16: 0 | M16: 0 | N16: 0 | O16: 0
A17: x | B17: Ending equity balance | G17: ='Balance Sheet'!G36 -> 12600 | H17: ='Balance Sheet'!H36 -> 157019 | I17: ='Balance Sheet'!I36 -> 201353 | J17: ='Balance Sheet'!J36 -> 224479 | K17: =SUM(K10:K16) -> 255151.14 | L17: =SUM(L10:L16) -> 289711.33 | M17: =SUM(M10:M16) -> 330632.29 | N17: =SUM(N10:N16) -> 390494.87 | O17: =SUM(O10:O16) -> 463418.95
A19: x | B19: Share repurchase
C20: Projected EPS | H20: ='Income Statement'!H37 -> 0.14888327 | I20: ='Income Statement'!I37 -> 0.86949048 | J20: ='Income Statement'!J37 -> 0.32808742 | K20: ='Income Statement'!K37 -> 0.65777921 | L20: ='Income Statement'!L37 -> 0.73521806 | M20: ='Income Statement'!M37 -> 0.95865653 | N20: ='Income Statement'!N37 -> 1.4930148 | O20: ='Income Statement'!O37 -> 1.8802605 | U20: Step
C21: Assumed P/E Multiple | H21: =H22/H20 -> 240.25533 | I21: =I22/I20 -> 35.825579 | J21: =J22/J20 -> 118.87076 | K21: 70 | L21: =K21-6 -> 64 | M21: =L21-6 -> 58 | N21: =M21-6 -> 52 | O21: =N21-6 -> 46 | U21: -6 | V21: 직전년 대비 6씩 감소
C22: Projected share price | H22: ='Historical Capitalization'!H18 -> 35.77 | I22: ='Historical Capitalization'!L18 -> 31.15 | J22: ='Historical Capitalization'!P18 -> 39 | K22: =K21*K20 -> 46.044545 | L22: =L21*L20 -> 47.053956 | M22: =M21*M20 -> 55.602079 | N22: =N21*N20 -> 77.636768 | O22: =O21*O20 -> 86.491981
C23: Shares repurchased (in thounsands) | K23: 0 | L23: 0 | M23: 5 | N23: 5 | O23: 5 | P23: 5 | Q23: 5 | R23: 5 | S23: 5 | T23: 5 | U23: 19년까지 0, '20년부터 5로 고정
C24: $ amount repurchased | K24: =K22*K23 -> 0 | L24: =L22*L23 -> 0 | M24: =M22*M23 -> 278.01039 | N24: =N22*N23 -> 388.18384 | O24: =O22*O23 -> 432.45991
A26: x | B26: Dividend
C27: Total dividends paid | G27: 0 | H27: 0 | I27: 0 | J27: 0 | K27: =K28*K29 -> 0 | L27: =L28*L29 -> 0 | M27: =M28*M29 -> 1811.6128 | N27: =N28*N29 -> 2821.7848 | O27: =O28*O29 -> 3554.1459
C28: Net income | G28: ='Income Statement'!G30 -> 2118 | H28: ='Income Statement'!H30 -> 3124 | I28: ='Income Statement'!I30 -> 22146 | J28: ='Income Statement'!J30 -> 8884 | K28: ='Income Statement'!K30 -> 24849.139 | L28: ='Income Statement'!L30 -> 27781.924 | M28: ='Income Statement'!M30 -> 36232.255 | N28: ='Income Statement'!N30 -> 56435.696 | O28: ='Income Statement'!O30 -> 71082.917
C29: Divident payout ratio | G29: =G27/G28 -> 0 | H29: =H27/H28 -> 0 | I29: =I27/I28 -> 0 | J29: =J27/J28 -> 0 | K29: 0 | L29: 0 | M29: 0.05 | N29: 0.05 | O29: 0.05 | P29: 0.05 | Q29: 0.1 | R29: 0.1 | S29: 0.1 | T29: 0.1
A31: x | B31: New shares from exercised options
C32: New shares issued from options (in thounsands) | K32: 10 | L32: 10 | M32: 10 | N32: 10 | O32: 10 | P32: 10 | Q32: 10 | R32: 10 | S32: 10 | T32: 10 | U32: 10 고정
C33: Average strike price per share | K33: 20 | L33: 20 | M33: 20 | N33: 20 | O33: 20 | P33: 20 | Q33: 20 | R33: 20 | S33: 20 | T33: 20 | U33: $20 고정
C34: Option proceeds | K34: =K32*K33 -> 200 | L34: =L32*L33 -> 200 | M34: =M32*M33 -> 200 | N34: =N32*N33 -> 200 | O34: =O32*O33 -> 200
A35: x

Sheet Shares
B2: Shake Shack, Inc (SHAK)
B3: Shares
B4: (units in '000 shares)
H7: Historical Year Ending December 31, | K7: Projected year Ending December 31,
F8: 2013 | G8: =F8+1 -> 2014 | H8: =G8+1 -> 2015 | I8: =H8+1 -> 2016 | J8: =I8+1 -> 2017 | K8: =J8+1 -> 2018 | L8: =K8+1 -> 2019 | M8: =L8+1 -> 2020 | N8: =M8+1 -> 2021 | ... T8: =S8+1 -> 2027
A10: x | B10: Beginning balance | K10: =J13 -> 27078.149 | L10: =K13 -> 27088.149 | M10: =L13 -> 27098.149 | N10: =M13 -> 27103.149 | O10: =N13 -> 27108.149 | P10: =+O13 -> 27113.149 | Q10: =+P13 -> 27118.149 | R10: =+Q13 -> 27123.149 | S10: =+R13 -> 27128.149 | T10: =+S13 -> 27133.149
C11: Shares issued from options | K11: 10 | L11: 10 | M11: 10 | N11: 10 | O11: 10 | P11: =+Equity!P32 -> 10 | Q11: =+Equity!Q32 -> 10 | R11: =+Equity!R32 -> 10 | S11: =+Equity!S32 -> 10 | T11: =+Equity!T32 -> 10
C12: Shares repurchsed | K12: 0 | L12: 0 | M12: -5 | N12: -5 | O12: -5 | P12: =-Equity!P23 -> -5 | Q12: =-Equity!Q23 -> -5 | R12: =-Equity!R23 -> -5 | S12: =-Equity!S23 -> -5 | T12: =-Equity!T23 -> -5
B13: Ending balance | J13: ='Income Statement'!J36 -> 27078.149 | K13: =SUM(K10:K12) -> 27088.149 | L13: =SUM(L10:L12) -> 27098.149 | M13: =SUM(M10:M12) -> 27103.149 | N13: =SUM(N10:N12) -> 27108.149 | O13: =SUM(O10:O12) -> 27113.149 | P13: =+SUM(P10:P12) -> 27118.149 | Q13: =+SUM(Q10:Q12) -> 27123.149 | R13: =+SUM(R10:R12) -> 27128.149 | S13: =+SUM(S10:S12) -> 27133.149 | T13: =+SUM(T10:T12) -> 27138.149
B15: Average basic shares | J15: =J13 -> 27078.149 | K15: =AVERAGE(K10,K13) -> 27083.149 | L15: =AVERAGE(L10,L13) -> 27093.149 | M15: =AVERAGE(M10,M13) -> 27100.649 | N15: =AVERAGE(N10,N13) -> 27105.649 | O15: =AVERAGE(O10,O13) -> 27110.649 | P15: =+AVERAGE(O13:P13) -> 27115.649 | Q15: =+AVERAGE(P13:Q13) -> 27120.649 | R15: =+AVERAGE(Q13:R13) -> 27125.649 | S15: =+AVERAGE(R13:S13) -> 27130.649 | T15: =+AVERAGE(S13:T13) -> 27135.649
C16: Assumed exchange of LLC Interests for shares of Class A common stock | J16: 10250 | K16: 10250 | L16: 10250 | M16: 10250 | N16: 10250 | O16: 10250 | P16: =+O16 -> 10250 | Q16: =+P16 -> 10250 | R16: =+Q16 -> 10250 | S16: =+R16 -> 10250 | T16: =+S16 -> 10250
C17: Effects of options (unexercised) | J17: =SHAK_10K!I58/1000 -> 274.85773 | K17: 274.85773 | L17: 274.85773 | M17: 274.85773 | N17: 274.85773 | O17: 274.85773 | P17: =+O17 -> 274.85773 | Q17: =+P17 -> 274.85773 | R17: =+Q17 -> 274.85773 | S17: =+R17 -> 274.85773 | T17: =+S17 -> 274.85773
C18: Restricted Stock Units | J18: =SHAK_10K!I97/1000 -> 44.476 | K18: 44.476 | L18: 44.476 | M18: 44.476 | N18: 44.476 | O18: 44.476 | P18: =+O18 -> 44.476 | Q18: =+P18 -> 44.476 | R18: =+Q18 -> 44.476 | S18: =+R18 -> 44.476 | T18: =+S18 -> 44.476
C19: Performance Stock Units | J19: =SHAK_10K!D90/1000 -> 124.842 | K19: 124.842 | L19: 124.842 | M19: 124.842 | N19: 124.842 | O19: 124.842 | P19: =+O19 -> 124.842 | Q19: =+P19 -> 124.842 | R19: =+Q19 -> 124.842 | S19: =+R19 -> 124.842 | T19: =+S19 -> 124.842
B20: Average diluted shares | H20: ='Income Statement'!H36 -> 20982.881 | I20: ='Income Statement'!I36 -> 25470.089 | J20: =SUM(J15:J19) -> 37772.325 | K20: =SUM(K15:K19) -> 37777.325 | L20: =SUM(L15:L19) -> 37787.325 | M20: =SUM(M15:M19) -> 37794.825 | N20: =SUM(N15:N19) -> 37799.825 | O20: =SUM(O15:O19) -> 37804.825 | P20: =+SUM(P15:P19) -> 37809.825 | Q20: =+SUM(Q15:Q19) -> 37814.825 | R20: =+SUM(R15:R19) -> 37819.825 | S20: =+SUM(S15:S19) -> 37824.825 | T20: =+SUM(T15:T19) -> 37829.825

Sheet Debt&Interest
B2: Shake Shack, Inc (SHAK)
B3: Debt & Interest Expense
B4: (units in USD '000)
H7: Historical Year Ending December 31, | K7: Projected year Ending December 31,
F8: 2013 | G8: =F8+1 -> 2014 | H8: =G8+1 -> 2015 | I8: =H8+1 -> 2016 | J8: =I8+1 -> 2017 | K8: =J8+1 -> 2018 | L8: =K8+1 -> 2019 | M8: =L8+1 -> 2020 | N8: =M8+1 -> 2021 | ... T8: =S8+1 -> 2027
B10: Cash flow Available for Financing Activities | K10: ='Cash Flow'!K25 -> -9412.0346 | L10: ='Cash Flow'!L25 -> -8519.2241 | M10: ='Cash Flow'!M25 -> 16997.867 | N10: ='Cash Flow'!N25 -> 65704.475 | O10: ='Cash Flow'!O25 -> 82155.011
C11: Repurchase of Equity | K11: =Equity!K13 -> 0 | L11: =Equity!L13 -> 0 | M11: =Equity!M13 -> -284.21789 | N11: =Equity!N13 -> -387.59722 | O11: =Equity!O13 -> -422.69152
C12: Dividends Paid | K12: =Equity!K14 -> 0 | L12: =Equity!L14 -> 0 | M12: =Equity!M14 -> -1852.063 | N12: =Equity!N14 -> -2817.5206 | O12: =Equity!O14 -> -3473.865
C13: Option Proceeds | K13: =Equity!K15 -> 200 | L13: =Equity!L15 -> 200 | M13: =Equity!M15 -> 200 | N13: =Equity!N15 -> 200 | O13: =Equity!O15 -> 200
C14: =+'Cash Flow'!C36 -> Change in Non-Controlling Interest | K14: =Equity!K16 -> 0 | L14: =Equity!L16 -> 0 | M14: =Equity!M16 -> 0 | N14: =Equity!N16 -> 0 | O14: =Equity!O16 -> 0
C15: Plus: Beginning Cash Balance | K15: ='Balance Sheet'!J10 -> 84543 | L15: ='Balance Sheet'!K10 -> 71330.965 | M15: ='Balance Sheet'!L10 -> 59011.741 | N15: ='Balance Sheet'!M10 -> 70073.327 | O15: ='Balance Sheet'!N10 -> 128772.68
C16: Less: Minimum Cash Balance | K16: -30000 | L16: -30000 | M16: -30000 | N16: -30000 | O16: -30000 | P16: -30000 | Q16: -30000 | R16: -30000 | S16: -30000 | T16: -30000 | U16: 현금 loss가 3만씩 있다고 가정
A17: x | B17: Cash Available for Debt Repayment | K17: =SUM(K10:K16) -> 45330.965 | L17: =SUM(L10:L16) -> 33011.741 | M17: =SUM(M10:M16) -> 44073.327 | N17: =SUM(N10:N16) -> 102772.68 | O17: =SUM(O10:O16) -> 177231.14
C19: Capital Lease Increase | K19: =K32 -> 1000 | L19: =L32 -> 1000 | M19: =M32 -> 1000 | N19: =N32 -> 1000 | O19: =O32 -> 1000 | P19: =P32 -> 1000 | Q19: =Q32 -> 1000 | R19: =R32 -> 1000 | ... T19: =T32 -> 1000
C20: Capital Lease (Paydown) | K20: =K33 -> -2000 | L20: =L33 -> -2000 | M20: =M33 -> -2000 | N20: =N33 -> -2000 | O20: =O33 -> -2000 | P20: =P33 -> -2000 | Q20: =Q33 -> -2000 | R20: =R33 -> -2000 | ... T20: =T33 -> -2000
C21: Long-term Debt Issuance | K21: =K38 -> 3000 | L21: =L38 -> 3000 | M21: =M38 -> 3000 | N21: =N38 -> 3000 | O21: =O38 -> 3000 | P21: =P38 -> 3000 | Q21: =Q38 -> 3000 | R21: =R38 -> 3000 | ... T21: =T38 -> 3000
C22: Long-term Debt (Repayment) | K22: =K39 -> -6000 | L22: =L39 -> -6000 | M22: =M39 -> -6000 | N22: =N39 -> -6000 | O22: =O39 -> -6000 | P22: =P39 -> -6000 | Q22: =Q39 -> -6000 | R22: =R39 -> -6000 | ... T22: =T39 -> -6000
B23: Excess Cash Available for Revolver | K23: =SUM(K19:K22)+K17 -> 41330.965 | L23: =SUM(L19:L22)+L17 -> 29011.741 | M23: =SUM(M19:M22)+M17 -> 40073.327 | N23: =SUM(N19:N22)+N17 -> 98772.684 | O23: =SUM(O19:O22)+O17 -> 173231.14 | P23: =SUM(P19:P22)+P17 -> -4000 | Q23: =SUM(Q19:Q22)+Q17 -> -4000 | R23: =SUM(R19:R22)+R17 -> -4000 | ... T23: =SUM(T19:T22)+T17 -> -4000
A25: x | B25: Revolver
C26: Beginning Balance | K26: =J28 -> 0 | L26: =K28 -> 0 | M26: =L28 -> 0 | N26: =M28 -> 0 | O26: =N28 -> 0
C27: Issuance/(Repayment) of Revolver - Cash Sweep | K27: =-MIN(K26,K23) -> 0 | L27: =-MIN(L26,L23) -> 0 | M27: =-MIN(M26,M23) -> 0 | N27: =-MIN(N26,N23) -> 0 | O27: =-MIN(O26,O23) -> 0
C28: Ending Balance | H28: ='Balance Sheet'!I28 -> 0 | I28: ='Balance Sheet'!J28 -> 0 | J28: ='Balance Sheet'!K28 -> 0 | K28: =SUM(K26:K27) -> 0 | L28: =SUM(L26:L27) -> 0 | M28: =SUM(M26:M27) -> 0 | N28: =SUM(N26:N27) -> 0 | O28: =SUM(O26:O27) -> 0
A30: x | B30: Capital Lease
C31: Beginning Balance | K31: =J34 -> 14518 | L31: =K34 -> 13518 | M31: =L34 -> 12518 | N31: =M34 -> 11518 | O31: =N34 -> 10518
C32: Issuance | K32: 1000 | L32: 1000 | M32: 1000 | N32: 1000 | O32: 1000 | P32: 1000 | Q32: 1000 | R32: 1000 | S32: 1000 | T32: 1000
C33: (Repayment) | K33: -2000 | L33: -2000 | M33: -2000 | N33: -2000 | O33: -2000 | P33: -2000 | Q33: -2000 | R33: -2000 | S33: -2000 | T33: -2000
C34: Ending Balance | H34: ='Balance Sheet'!H29 -> 313 | I34: ='Balance Sheet'!I29 -> 2007 | J34: ='Balance Sheet'!J29 -> 14518 | K34: =SUM(K31:K33) -> 13518 | L34: =SUM(L31:L33) -> 12518 | M34: =SUM(M31:M33) -> 11518 | N34: =SUM(N31:N33) -> 10518 | O34: =SUM(O31:O33) -> 9518
A36: x | B36: Long-term Debt
C37: Beginning Balance | K37: =J40 -> 36596 | L37: =K40 -> 33596 | M37: =L40 -> 30596 | N37: =M40 -> 27596 | O37: =N40 -> 24596
C38: Issuance | K38: 3000 | L38: 3000 | M38: 3000 | N38: 3000 | O38: 3000 | P38: 3000 | Q38: 3000 | R38: 3000 | S38: 3000 | T38: 3000
C39: (Repayment) | K39: -6000 | L39: -6000 | M39: -6000 | N39: -6000 | O39: -6000 | P39: -6000 | Q39: -6000 | R39: -6000 | S39: -6000 | T39: -6000
C40: Ending Balance | H40: ='Balance Sheet'!H30 -> 22927 | I40: ='Balance Sheet'!I30 -> 31107 | J40: ='Balance Sheet'!J30 -> 36596 | K40: =SUM(K37:K39) -> 33596 | L40: =SUM(L37:L39) -> 30596 | M40: =SUM(M37:M39) -> 27596 | N40: =SUM(N37:N39) -> 24596 | O40: =SUM(O37:O39) -> 21596
B43: Revolver Interest Expense | H43: Average balance | K43: =AVERAGE(J28:K28) -> 0 | L43: =AVERAGE(K28:L28) -> 0 | M43: =AVERAGE(L28:M28) -> 0 | N43: =AVERAGE(M28:N28) -> 0 | O43: =AVERAGE(N28:O28) -> 0
H44: Interest rate | J44: 0.033 | K44: 0.033 | L44: 0.033 | M44: 0.033 | N44: 0.033 | O44: 0.033 | U44: 3.3% 고정
H45: Interest expense | K45: =K43*K44 -> 0 | L45: =L43*L44 -> 0 | M45: =M43*M44 -> 0 | N45: =N43*N44 -> 0 | O45: =O43*O44 -> 0
B47: Capital Lease Interest Expense | H47: Average balance | K47: =AVERAGE(J34:K34) -> 14018 | L47: =AVERAGE(K34:L34) -> 13018 | M47: =AVERAGE(L34:M34) -> 12018 | N47: =AVERAGE(M34:N34) -> 11018 | O47: =AVERAGE(N34:O34) -> 10018
H48: Interest rate | K48: 0.05 | L48: 0.05 | M48: 0.05 | N48: 0.05 | O48: 0.05 | P48: 0.05 | Q48: 0.05 | R48: 0.05 | S48: 0.05 | T48: 0.05 | U48: 5% 고정
H49: Interest expense | K49: =K47*K48 -> 700.9 | L49: =L47*L48 -> 650.9 | M49: =M47*M48 -> 600.9 | N49: =N47*N48 -> 550.9 | O49: =O47*O48 -> 500.9
B51: Long-term debt Interest Expense | H51: Average balance | K51: =AVERAGE(J40:K40) -> 35096 | L51: =AVERAGE(K40:L40) -> 32096 | M51: =AVERAGE(L40:M40) -> 29096 | N51: =AVERAGE(M40:N40) -> 26096 | O51: =AVERAGE(N40:O40) -> 23096
H52: Interest rate | K52: 0.07 | L52: 0.07 | M52: 0.07 | N52: 0.07 | O52: 0.07 | P52: 0.07 | Q52: 0.07 | R52: 0.07 | S52: 0.07 | T52: 0.07 | U52: 7% 고정
H53: Interest expense | K53: =K51*K52 -> 2456.72 | L53: =L51*L52 -> 2246.72 | M53: =M51*M52 -> 2036.72 | N53: =N51*N52 -> 1826.72 | O53: =O51*O52 -> 1616.72
A55: x | H55: Total Interest Expense | K55: =SUM(K45,K49,K53) -> 3157.62 | L55: =SUM(L45,L49,L53) -> 2897.62 | M55: =SUM(M45,M49,M53) -> 2637.62 | N55: =SUM(N45,N49,N53) -> 2377.62 | O55: =SUM(O45,O49,O53) -> 2117.62
B57: Cash Interest (Income) | H57: Average balance | K57: =AVERAGE('Balance Sheet'!J10:K10) -> 77936.983 | L57: =AVERAGE('Balance Sheet'!K10:L10) -> 65171.353 | M57: =AVERAGE('Balance Sheet'!L10:M10) -> 64542.534 | N57: =AVERAGE('Balance Sheet'!M10:N10) -> 99423.006 | O57: =AVERAGE('Balance Sheet'!N10:O10) -> 166001.91
H58: Interest rate | K58: 0.025 | L58: 0.025 | M58: 0.025 | N58: 0.025 | O58: 0.025 | P58: 0.025 | Q58: 0.025 | R58: 0.025 | S58: 0.025 | T58: 0.025 | U58: 2.5% 고정
A59: x | H59: Interest (income) | K59: =K57*-K58 -> -1948.4246 | L59: =L57*-L58 -> -1629.2838 | M59: =M57*-M58 -> -1613.5634 | N59: =N57*-N58 -> -2485.5751 | O59: =O57*-O58 -> -4150.0478

Sheet DCF
B2: Shake Shack, Inc (SHAK)
B3: Discounted Cash Flow Analysis
B4: (units in USD '000)
H7: Historical Year Ending December 31, | K7: Projected year Ending December 31,
F8: 2013 | G8: =F8+1 -> 2014 | H8: =G8+1 -> 2015 | I8: =H8+1 -> 2016 | J8: =I8+1 -> 2017 | K8: =J8+1 -> 2018 | L8: =K8+1 -> 2019 | M8: =L8+1 -> 2020 | N8: =M8+1 -> 2021 | ... T8: =S8+1 -> 2027
A10: x | B10: Sales | H10: ='Income Statement'!H10 -> 190592 | I10: ='Income Statement'!I10 -> 268475 | J10: ='Income Statement'!J10 -> 358810 | K10: ='Income Statement'!K10 -> 456021.93 | L10: ='Income Statement'!L10 -> 581236.37 | M10: ='Income Statement'!M10 -> 716363.54 | N10: ='Income Statement'!N10 -> 840241.65 | O10: ='Income Statement'!O10 -> 940457.65
B12: EBITDA | K12: =Operations!K107 -> 0 | L12: =Operations!L107 -> 0 | M12: =Operations!M107 -> 0 | N12: =Operations!N107 -> 0 | O12: =Operations!O107 -> 0
A13: x | B13: EBIT | H13: ='Income Statement'!H21 -> 6753 | I13: ='Income Statement'!I21 -> 27805 | J13: ='Income Statement'!J21 -> 33813 | K13: ='Income Statement'!K21 -> 32663.801 | L13: ='Income Statement'!L21 -> 36435.328 | M13: ='Income Statement'!M21 -> 46887.671 | N13: ='Income Statement'!N21 -> 71329.635 | O13: ='Income Statement'!O21 -> 87945.948
C14: Less: Taxes@ | E14: 0.21 | I14: =I13*$E$14 -> 5839.05 | J14: =J13*$E$14 -> 7100.73 | K14: =K13*$E$14 -> 6859.3983 | L14: =L13*$E$14 -> 7651.4189 | M14: =M13*$E$14 -> 9846.4109 | N14: =N13*$E$14 -> 14979.223 | O14: =O13*$E$14 -> 18468.649
C15: Tax-effected EBIT ("NOPLAT") | I15: =I13-I14 -> 21965.95 | J15: =J13-J14 -> 26712.27 | K15: =K13-K14 -> 25804.403 | L15: =L13-L14 -> 28783.909 | M15: =M13-M14 -> 37041.26 | N15: =N13-N14 -> 56350.412 | O15: =O13-O14 -> 69477.299
C17: Plus: Depreciation | K17: ='PP&E'!K18 -> 29216.938 | L17: ='PP&E'!L18 -> 36370.255 | M17: ='PP&E'!M18 -> 42532.247 | N17: ='PP&E'!N18 -> 45546.708 | O17: ='PP&E'!O18 -> 46155.145
C18: Plus: Amortization | K18: ='Cash Flow'!K13 -> 0 | L18: ='Cash Flow'!L13 -> 0 | M18: ='Cash Flow'!M13 -> 0 | N18: ='Cash Flow'!N13 -> 0 | O18: ='Cash Flow'!O13 -> 0
C19: Less: Capital Expenditures | K19: =-'PP&E'!K12 -> -75900 | L19: =-'PP&E'!L12 -> -88000 | M19: =-'PP&E'!M12 -> -77700 | N19: =-'PP&E'!N12 -> -50000 | O19: =-'PP&E'!O12 -> -47500
C20: Plus: Asset Sale | K20: ='Cash Flow'!K21 -> 0 | L20: ='Cash Flow'!L21 -> 0 | M20: ='Cash Flow'!M21 -> 0 | N20: ='Cash Flow'!N21 -> 0 | O20: ='Cash Flow'!O21 -> 0
C21: Less: Additions to Intangibles | K21: =-'Cash Flow'!K22 -> 0 | L21: =-'Cash Flow'!L22 -> 0 | M21: =-'Cash Flow'!M22 -> 0 | N21: =-'Cash Flow'!N22 -> 0 | O21: =-'Cash Flow'!O22 -> 0
C22: +/- Changes in Net Working Capital | K22: {='Working Capital'!K27:O27} -> 7298.8881 | L22: 10205.597 | M22: 10810.364 | N22: 8599.0702 | O22: 7293.9496
C23: +/- Changes in Other Assets & Liabilities | K23: ='Other LT Items'!K23 -> -500 | L23: ='Other LT Items'!L23 -> -500 | M23: ='Other LT Items'!M23 -> -500 | N23: ='Other LT Items'!N23 -> -500 | O23: ='Other LT Items'!O23 -> -500
A24: x | B24: Unlevered Free Cash Flow | K24: =SUM(K17:K23)+K15 -> -14079.77 | L24: =SUM(L17:L23)+L15 -> -13140.239 | M24: =SUM(M17:M23)+M15 -> 12183.871 | N24: =SUM(N17:N23)+N15 -> 59996.19 | O24: =SUM(O17:O23)+O15 -> 74926.393 | P24: =$O$31 -> 50561.55 | Q24: =$O$31 -> 50561.55 | R24: =$O$31 -> 50561.55 | S24: =$O$31 -> 50561.55 | T24: =$O$31 -> 50561.55
C25: Unlevered Free Cash Flow yoy Growth Rate | N25: =(N24-M24)/M24 -> 3.9242304 | O25: =(O24-N24)/N24 -> 0.24885252
B27: Weighted Average Cost of Capital (WACC) | H27: =+WACC!O47 -> 0.081839639
B28: Year Count | K28: 1 | L28: 2 | M28: 3 | N28: 4 | O28: 5 | P28: 6 | Q28: 7 | R28: 8 | S28: 9 | T28: 10
B29: Discount Factor | K29: =1*(1+$H$27)^K28 -> 1.0818396 | L29: =1*(1+$H$27)^L28 -> 1.170377 | M29: =1*(1+$H$27)^M28 -> 1.2661602 | N29: =1*(1+$H$27)^N28 -> 1.3697823 | O29: =1*(1+$H$27)^O28 -> 1.4818848 | P29: =1*(1+$H$27)^P28 -> 1.6031617 | Q29: =1*(1+$H$27)^Q28 -> 1.7343639 | R29: =1*(1+$H$27)^R28 -> 1.8763036 | ... T29: =1*(1+$H$27)^T28 -> 2.1959826
B31: Present Value of Respective FCF | K31: =K24/K29 -> -13014.656 | L31: =L24/L29 -> -11227.355 | M31: =M24/M29 -> 9622.6931 | N31: =N24/N29 -> 43799.799 | O31: =O24/O29 -> 50561.55 | P31: =P24/P29 -> 31538.645 | Q31: =Q24/Q29 -> 29152.792 | R31: =R24/R29 -> 26947.424 | ... T31: =T24/T29 -> 23024.567
A32: x | B32: NPV of FCF | J32: =403993 -> 403993
A34: x | B34: Terminal Value Calculation
E36: Perpetuity Growth Method | L36: EBITDA Multiple Method
E38: Terminal Growth Rate of FCF (after 2027) | J38: 0.03 | L38: EV/EBITDA Exit Multiple | O38: ='Trading Multiples'!H25 -> 13.39548
E39: Terminal Value | J39: =O31*(1+J38)/(H27-J38) -> 1004605.7 | L39: Terminal Value
E40: Present Value of the Terminal Value | L40: Present Value of the Terminal Value
A43: x | B43: DCF Result Summary
C45: NPV of FCF from 2016-2027
C46: NPV of Terminal Value
C47: Enterprise Value
C49: Cash
C50: Debt
C51: Equity Value
C53: Diluted Share Count (in '000)
A55: x | C55: Value Per Share
B60: Sensitivity Analyses

Sheet SHAK_10K
B2: Shake Shack, Inc (SHAK)
B3: Company Published Data & Information
A5: x | B5: SEC Edgar Shake Shack
B6: https://www.sec.gov/cgi-bin/browse-edgar?company=shake+shack&match=&CIK=&filenum=&State=&Country=&SIC=&owner=exclude&Find=Find+Companies&action=getcompany
B8: Shake Shack FY2017 10-K
B9: https://www.sec.gov/Archives/edgar/data/1620533/000162053318000015/shak-20171227_10k.htm
B11: Shake Shack FY2017 10-K Interactive Data
B12: https://www.sec.gov/cgi-bin/viewer?action=view&cik=1620533&accession_number=0001620533-18-000015&xbrl_type=v
A16: x | B16: FY 2018 Guidance
C18: Current Outlook
B19: Total revenue (inclusive of licensing revenue) | C19: $444 to $448 million
B20: Licensing revenue | C20: $12 to $13 million
B21: Same-Shack sales growth (%)(1) | C21: 0
B22: Domestic company-operated Shack openings | C22: 32 to 35
B23: Licensed Shack openings, net | C23: 16 to 18
B24: Average annual sales volume for domestic company-operated Shacks | C24: $4.1 to $4.2 million
B25: Shack-level operating profit margin (%) | C25: 24.5% to 25.5%
B26: General and administrative expenses(2) | C26: $49 to $51 million
B27: Depreciation expense | C27: $32 million
B28: Pre-opening costs | C28: $12 to $13 million
B29: Interest expense | C29: $2 to $2.2 million
B30: Adjusted pro forma effective tax rate (%) | C30: 26% to 27%
B32: By the end of fiscal 2020, we are targeting: ▪ At least 200 domestic company-operated Shacks and at least 120 globally licensed Shacks (more than double the system-wide Shack count as of December 27, 2017); and ▪ Over $700 million in total revenue.
A35: x | B35: Stock Options
B36: The following table summarizes information about stock options outstanding and exercisable as December 27, 2017:
D38: Options Outstanding | I38: Options Exercisable
D39: Number Outstanding at December 27, 2017 | E39: Weighted Average Remaining Contractual Life (Years) | F39: Weighted Average Exercise Price | I39: Number Exercisable at December 27, 2017 | J39: Weighted Average Remaining Contractual Life (Years) | K39: Weighted Average Exercise Price
B40: Exercise Price
B41: 21 | D41: 1700665 | E41: 7.1 | F41: $ | G41: 21 | I41: 529720 | J41: 7.1 | K41: $ | L41: 21
B43: 34.62 | D43: 12418 | E43: 8.4 | F43: $ | G43: 34.62 | I43: 12418 | J43: 8.4 | K43: $ | L43: 34.62
B45: 36.41 | D45: 1108 | E45: 8.9 | F45: $ | G45: 36.41 | I45: 1108 | J45: 8.9 | K45: $ | L45: 36.41
B47: 38.91 | D47: 5150 | E47: 9.5 | F47: $ | G47: 38.91 | I47: — | J47: — | K47: $ | L47: —
D50: Exercise Price | E50: Shares | F50: Current P | G50: Exercisable | I50: Shares | J50: $ inflow
D51: =+B41 -> 21 | E51: =+I41 -> 529720 | F51: =+Cover!K12 -> 43.2 | G51: =+IF(D51<$F$51,1,0) -> 1 | I51: =+E51*G51 -> 529720 | J51: =+D51*I51 -> 11124120
D52: =+B43 -> 34.62 | E52: =+I43 -> 12418 | G52: =+IF(D52<$F$51,1,0) -> 1 | I52: =+E52*G52 -> 12418 | J52: =+D52*I52 -> 429911.16
D53: =+B45 -> 36.41 | E53: =+I45 -> 1108 | G53: =+IF(D53<$F$51,1,0) -> 1 | I53: =+E53*G53 -> 1108 | J53: =+D53*I53 -> 40342.28
D54: =+B47 -> 38.91 | E54: 0 | G54: =+IF(D54<$F$51,1,0) -> 1 | I54: =+E54*G54 -> 0 | J54: =+D54*I54 -> 0
G55: 총 발행주식수 | H55: Gross Issuance | I55: =+SUM(I51:I54) -> 543246 | J55: =+SUM(J51:J54) -> 11594373
G57: 재매입 주식수 | H57: Shares Buyback | I57: =-J55/F51 -> -268388.27
G58: 순 발행주식수 | H58: Net Issuance | I58: =+I55+I57 -> 274857.73
A60: x | B60: Performance Stock Unit
B61: A summary of performance stock unit activity for fiscal years 2017 and 2016 is as follows:
C63: PSU | D63: Performance | G63: Weighted
D64: Stock | G64: Average
D65: Units | G65: Grant Date Fair Value
B66: Outstanding as of December 30, 2015 | D66: — | G66: $ | H66: —
C68: Granted | D68: 63600 | G68: 38.41
C70: Performance achievement(1) | D70: — | G70: —
C72: Vested | D72: — | G72: —
C74: Forfeited | D74: (2,000 | E74: ) | G74: 38.43
C76: Expired | D76: — | G76: —
B78: Outstanding as of December 28, 2016 | D78: 61600 | G78: $ | H78: 38.41
C80: Granted | D80: 87596 | G80: 37.9
C82: Performance achievement(1) | D82: 9545 | G82: 38.4
C84: Vested | D84: (22,703 | E84: ) | G84: 38.4
C86: Forfeited | D86: (11,196 | E86: ) | G86: 38.28
C88: Expired | D88: — | G88: —
B90: Outstanding as of December 27, 2017 | D90: 124842 | G90: $ | H90: 38.06
B93: -1 | C93: Represents incremental awards earned based on the achievement of performance conditions.
A95: x | B95: Share count
B96: In fiscal 2017, 44,476 restricted stock units were granted with a weighted average grant date fair value of $38.98. As of December 27, 2017, there were 44,476 restricted stock units outstanding, of which none were vested. No restricted stock units were granted in fiscal 2016 and 2015. As of December 27, 2017, total unrecognized compensation expense related to unvested restricted stock units was $1,453, which is expected to be recognized over a weighted-average period of 2.5 years.
I97: 44476
B98: As of February 14, 2018, there were 27,078,149 shares of Class A common stock outstanding and 9,701,815 shares of Class B common stock outstanding.
B99: 27078149
A102: x | B102: Adjusted EBITDA
B104: (in thousands) | E104: 2017 | I104: 2016 | M104: 2015 | Q104: 2014(1) | U104: 2013
B106: Net income | E106: $ | F106: 8884 | I106: $ | J106: 22146 | M106: $ | N106: 3124 | Q106: $ | R106: 2118 | U106: $ | V106: 5423
B108: Depreciation expense | E108: 21704 | I108: 14502 | M108: 10222 | Q108: 5809 | U108: 3541
B110: Interest expense, net | E110: 1565 | I110: 285 | M110: 325 | Q110: 363 | U110: 52
B112: Income tax expense | E112: 151409 | I112: 6350 | M112: 3304 | Q112: 662 | U112: 460
B114: EBITDA | E114: 183562 | I114: 43283 | M114: 16975 | Q114: 8952 | U114: 9476
B117: Equity-based compensation | E117: 5623 | I117: 5354 | M117: 4314 | Q117: 165 | U117: 93
B119: Deferred compensation | E119: — | I119: — | M119: — | Q119: — | U119: 2054
B121: Deferred rent | E121: 983 | I121: 2251 | M121: 1482 | Q121: 2830 | U121: 975
B123: Loss on disposal of property and equipment | E123: 608 | I123: 34 | M123: 17 | Q123: 105 | U123: 25
B125: Non-recurring compensation expenses related to the IPO(2) | E125: — | I125: — | M125: 12818 | Q125: — | U125: —
B127: IPO-related expenses | E127: — | I127: — | M127: 635 | Q127: 2675 | U127: —
B129: Legal settlement | E129: — | I129: — | M129: 770 | Q129: — | U129: —
B131: Executive transition costs(3) | E131: 664 | I131: — | M131: — | Q131: — | U131: —
B133: Project Concrete(4) | E133: 181 | I133: — | M133: — | Q133: — | U133: —
B135: Home Office relocation expenses(5) | E135: 264 | I135: — | M135: — | Q135: — | U135: —
B137: Other income related to adjustment of liabilities under tax receivable agreement | E137: (1,362 | G137: ) | I137: (688 | K137: ) | M137: — | Q137: — | U137: —
B139: Other income related to adjustment of liabilities under tax receivable agreement resulting from the enactment of the TCJA | E139: (125,859 | G139: ) | I139: — | M139: — | Q139: — | U139: —
B141: Other non-cash items | E141: — | I141: — | M141: — | Q141: 135 | U141: 99
B143: ADJUSTED EBITDA | E143: $ | F143: 64664 | I143: $ | J143: 50234 | M143: $ | N143: 37011 | Q143: $ | R143: 14862 | U143: $ | V143: 12722
A150: x | B150: Operating Leases
B152: Less than | F152: 1 ~ 3 | J152: 3 ~ 5 | N152: More Than
B153: 1 Year | F153: Years | J153: Years | N153: 5 Years
B154: Operating lease obligations(1) | C154: $ | D154: 271811 | G154: $ | H154: 24123 | K154: $ | L154: 51862 | O154: $ | P154: 52582 | S154: $ | T154: 143244
B156: Deemed landlord financing obligations(1) | C156: 49989 | G156: 3679 | K156: 9309 | O156: 9563 | S156: 27438
B158: Liabilities under tax receivable agreement(2) | C158: 159373 | G158: 937 | K158: 17008 | O158: 17714 | S158: 123714
B160: Purchase obligations | C160: 167063 | G160: 82561 | K160: 11468 | O160: 13504 | S160: 59530
B162: Deferred compensation(3) | C162: 2450 | G162: 2450 | K162: — | O162: — | S162: —
B164: TOTAL | C164: $ | D164: 650686 | G164: $ | H164: 113750 | K164: $ | L164: 89647 | O164: $ | P164: 93363 | S164: $ | T164: 353926
A170: x | B170: Store Count for FY 2017
E172: Licensed | H172: Total
B173: Company
B174: Operated
B175: Arizona | C175: 3 | F175: — | I175: 3
B177: California | C177: 7 | F177: 1 | I177: 8
...

Sheet Capital IQ>>>>>
A1: >>>>>>>>>>>>>>>>>>>>>>>>>>>>>>>

Sheet Key Stats
A5: Shake Shack Inc. (NYSE:SHAK) > Financials > Key Stats
A7: In Thousands of the trading currency, except per share items. | B7: Currency: | C7: Trading Currency | E7: Conversion: | F7: Historical
B8: Order: | C8: Latest on Right | E8: Units: | F8: Thousands (k)
B9: Decimals: | C9: Capital IQ (Default) | E9: Dilution: | F9: Basic
A12: Key Financials¹
A13: For the Fiscal Period Ending | B13: 12 months Dec-26-2012A | C13: 12 months Dec-25-2013A | D13: 12 months Dec-31-2014A | E13: 12 months Dec-30-2015A | F13: 12 months Dec-28-2016A | G13: 12 months Dec-27-2017A | H13: LTM² 12 months Mar-28-2018A | I13: 12 months† Dec-31-2018E
A14: Currency | B14: USD | C14: USD | D14: USD | E14: USD | F14: USD | G14: USD | H14: USD | I14: USD
A16: Total Revenue | B16: 57038 | C16: 82456 | D16: 118530 | E16: 190592 | F16: 268475 | G16: 358810 | H16: 381177 | I16: 452403.1
A17: Growth Over Prior Year | B17: NA | C17: 0.445632 | D17: 0.437493 | E17: 0.607964 | F17: 0.408637 | G17: 0.336474 | H17: 0.309621 | I17: 0.26084306
A19: Gross Profit | B19: 20775 | C19: 31603 | D19: 44540 | E19: 76554 | F19: 107363 | G19: 140536 | H19: 150895 | I19: -
A20: Margin % | B20: 0.36423 | C20: 0.383271 | D20: 0.375769 | E20: 0.401664 | F20: 0.399899 | G20: 0.391672 | H20: 0.395865 | I20: 0.2535
A22: EBITDA | B22: 6848 | C22: 11555 | D22: 9057 | E22: 30580 | F22: 42341 | G22: 56789 | H22: 60600 | I22: 63724.59
A23: Margin % | B23: 0.12006 | C23: 0.140135 | D23: 0.076411 | E23: 0.160447 | F23: 0.157709 | G23: 0.15827 | H23: 0.158981 | I23: 0.14085799
A25: EBIT | B25: 4686 | C25: 8014 | D25: 3248 | E25: 20358 | F25: 27839 | G25: 35085 | H25: 37146 | I25: 28796.41
A26: Margin % | B26: 0.082155 | C26: 0.097191 | D26: 0.027402 | E26: 0.106814 | F26: 0.103693 | G26: 0.097781 | H26: 0.09745 | I26: 0.063652106
A28: Earnings from Cont. Ops. | B28: 4133 | C28: 5423 | D28: 2118 | E28: 3124 | F28: 22146 | G28: 8884 | H28: 10001 | I28: -
A29: Margin % | B29: 0.07246 | C29: 0.065768 | D29: 0.017868 | E29: 0.016391 | F29: 0.082488 | G29: 0.024759 | H29: 0.026237 | I29: -
A31: Net Income | B31: 4133 | C31: 5423 | D31: 2118 | E31: -8776 | F31: 12446 | G31: -320 | H31: 921 | I31: 20156.63
A32: Margin % | B32: 0.07246 | C32: 0.065768 | D32: 0.017868 | E32: -0.046046 | F32: 0.046358 | G32: -0.000891 | H32: 0.002416 | I32: 0.04455458
A34: Diluted EPS Excl. Extra Items³ | B34: NA | C34: 0.18 | D34: 0.070314 | E34: -0.65 | F34: 0.53 | G34: -0.01 | H34: 0.035029 | I34: 0.54317
A35: Growth Over Prior Year | B35: NA | C35: NA | D35: -0.609367 | E35: NM | F35: NM | G35: NM | H35: -0.93489 | I35: -0.047070175
A38: Currency | B38: USD | C38: USD | D38: USD | E38: USD | F38: USD | G38: USD | H38: USD | I38: USD
A39: Exchange Rate | B39: 1 | C39: 1 | D39: 1 | E39: 1 | F39: 1 | G39: 1 | H39: 1 | I39: 1
A40: Conversion Method | B40: H | C40: H | D40: H | E40: H | F40: H | G40: H | H40: H | I40: S
A42: ¹All results are taken from the most recently filed statement for each period. When there has been more than one, earlier filings can be viewed on the individual statement pages.
A43: ²Growth rates for the LTM period are calculated against the LTM period ending 12 months before.
A44: ³All forward period figures are consensus mean estimates provided by the brokers and may not be on a comparable basis as financials.
A45: †Growth rates for forward periods are calculated against prior period estimates or actual pro forma results as disclosed on the Estimates Consensus page.
A46: Growth Rates are calculated in originally reported currency only and will not reflect any currency conversion selected above.
A48: Latest Capitalization (Thousands of USD)
A49: Currency | B49: USD
A50: Share Price | B50: 65.26
A51: Shares Out. | B51: 27811.48
A53: Market Capitalization | B53: 1814977.2
A54: - Cash & Short Term Investments | B54: 87752
A55: + Total Debt | B55: 17030
A56: + Pref. Equity | B56: -
A57: + Total Minority Interest | B57: 50991
A58: = Total Enterprise Value (TEV) | B58: 1795246.2
A60: Implied Shares Outstanding | B60: 36981.716
A61: Implied Market Capitalization | B61: 2413426.8
A62: Book Value of Common Equity | B62: 182142
A63: + Pref. Equity | B63: -
A64: + Total Minority Interest | B64: 50991
A65: + Total Debt | B65: 17030
A66: = Total Capital | B66: 250163
A68: **For companies that have multiple share classes that publicly trade, we are incorporating the different prices to calculate our company level market capitalization. Please click on the value to see the detailed calculation. Prices shown on this page are the close price of the company’s primary stock class. Shares shown on this page are total company as-reported share values.
A69: *Includes number of shares outstanding + shares held by non-controlling interest holders without accounting for dilutive securities
A71: Note: Striped area represents the impact of negative Net Liability on Market Cap.
A72: Total Liability includes Total Debt, Minority Interest and Pref. Equity.
A73: Net Liability includes Total Liability, net of Cash and Short Term Investments.
A74: TEV includes Market Cap and Net Liability.
A75: Total Capital includes Common Equity and Total Liability.
A77: Valuation Multiples based on Current Capitalization
A78: For the Fiscal Period Ending | B78: 12 months Dec-27-2017A | C78: LTM 12 months Mar-28-2018A | D78: 12 months Dec-31-2018E | E78: 12 months Dec-31-2019E | F78: 12 months Dec-31-2020E
A79: TEV/Total Revenue | B79: 5.016413 | C79: 4.709744 | D79: 3.9682447 | E79: 3.0784031 | F79: 2.495006
A81: TEV/EBITDA | B81: 31.695208 | C81: 29.624524 | D81: 28.171953 | E81: 21.256002 | F81: 16.575428
A83: TEV/EBIT | B83: 51.302242 | C83: 48.329461 | D83: 62.342708 | E83: 44.707488 | F83: 34.712742
A85: P/Diluted EPS Before Extra | B85: NM | C85: NM | D85: 120.14655 | E85: 85.995151 | F85: 66.712327
A87: P/BV | B87: 10.213953 | C87: 9.898728 | D87: 12.647287 | E87: 10.813587 | F87: 8.8910082
A89: Price/Tang BV | B89: 10.268113 | C89: 9.898728 | D89: - | E89: - | F89: -

Sheet IS
A5: Shake Shack Inc. (NYSE:SHAK) > Financials > Income Statement
A7: In Thousands of the reported currency, except per share items. | B7: Template: | C7: Standard | E7: Restatement: | F7: Latest Filings
B8: Period Type: | C8: Annual | E8: Order: | F8: Latest on Right
B9: Currency: | C9: Reported Currency | E9: Conversion: | F9: Historical
B10: Units: | C10: Thousands (k) | E10: Decimals: | F10: Capital IQ (Default)
B11: Source: | C11: Capital IQ & Proprietary Data
A14: Income Statement
A15: For the Fiscal Period Ending | B15: 12 months Dec-26-2012 | C15: Reclassified 12 months Dec-25-2013 | D15: 12 months Dec-31-2014 | E15: Reclassified 12 months Dec-30-2015 | F15: 12 months Dec-28-2016 | G15: 12 months Dec-27-2017 | H15: LTM 12 months Mar-28-2018
A16: Currency | B16: USD | C16: USD | D16: USD | E16: USD | F16: USD | G16: USD | H16: USD
A18: Revenue | B18: 57038 | C18: 82456 | D18: 118530 | E18: 190592 | F18: 268475 | G18: 358810 | H18: 381177
A19: Other Revenue | B19: - | C19: - | D19: - | E19: - | F19: - | G19: - | H19: -
A20: Total Revenue | B20: 57038 | C20: 82456 | D20: 118530 | E20: 190592 | F20: 268475 | G20: 358810 | H20: 381177
A22: Cost Of Goods Sold | B22: 36263 | C22: 50853 | D22: 73990 | E22: 114038 | F22: 161112 | G22: 218274 | H22: 230282
A23: Gross Profit | B23: 20775 | C23: 31603 | D23: 44540 | E23: 76554 | F23: 107363 | G23: 140536 | H23: 150895
A25: Selling General & Admin Exp. | B25: 6988 | C25: 10399 | D25: 18187 | E25: 24237 | F25: 30556 | G25: 38339 | H25: 42179
A26: Pre-Opening Costs | B26: 1858 | C26: 2334 | D26: 6105 | E26: 5430 | F26: 9520 | G26: 9603 | H26: 9217
A27: R & D Exp. | B27: - | C27: - | D27: - | E27: - | F27: - | G27: - | H27: -
A28: Depreciation & Amort. | B28: 2162 | C28: 3541 | D28: 5809 | E28: 10222 | F28: 14502 | G28: 21704 | H28: 23454
A29: Other Operating Expense/(Income) | B29: 5081 | C29: 7315 | D29: 11191 | E29: 16307 | F29: 24946 | G29: 35805 | H29: 38899
A31: Other Operating Exp., Total | B31: 16089 | C31: 23589 | D31: 41292 | E31: 56196 | F31: 79524 | G31: 105451 | H31: 113749
A33: Operating Income | B33: 4686 | C33: 8014 | D33: 3248 | E33: 20358 | F33: 27839 | G33: 35085 | H33: 37146
A35: Interest Expense | B35: -156 | C35: -52 | D35: -365 | E35: -332 | F35: -374 | G35: -1643 | H35: -1905
A36: Interest and Invest. Income | B36: - | C36: - | D36: - | E36: 7 | F36: 384 | G36: 907 | H36: 991
A37: Net Interest Exp. | B37: -156 | C37: -52 | D37: -365 | E37: -325 | F37: 10 | G37: -736 | H37: -914
A39: Other Non-Operating Inc. (Exp.) | B39: - | C39: - | D39: 2 | E39: - | F39: - | G39: - | H39: -
A40: EBT Excl. Unusual Items | B40: 4530 | C40: 7962 | D40: 2885 | E40: 20033 | F40: 27849 | G40: 34349 | H40: 36232
A42: Impairment of Goodwill | B42: - | C42: - | D42: - | E42: - | F42: - | G42: - | H42: -
A43: Gain (Loss) On Sale Of Invest. | B43: - | C43: - | D43: - | E43: - | F43: -7 | G43: -5 | H43: -56
A44: Gain (Loss) On Sale Of Assets | B44: - | C44: -25 | D44: -105 | E44: -17 | F44: -34 | G44: -608 | H44: -785
A45: Legal Settlements | B45: - | C45: - | D45: - | E45: -770 | F45: - | G45: - | H45: -
A46: Other Unusual Items | B46: - | C46: -2054 | D46: - | E46: -12818 | F46: 688 | G46: 126557 | H46: 125559
A47: EBT Incl. Unusual Items | B47: 4530 | C47: 5883 | D47: 2780 | E47: 6428 | F47: 28496 | G47: 160293 | H47: 160950
A49: Income Tax Expense | B49: 397 | C49: 460 | D49: 662 | E49: 3304 | F49: 6350 | G49: 151409 | H49: 150949
A50: Earnings from Cont. Ops. | B50: 4133 | C50: 5423 | D50: 2118 | E50: 3124 | F50: 22146 | G50: 8884 | H50: 10001
A52: Earnings of Discontinued Ops. | B52: - | C52: - | D52: - | E52: - | F52: - | G52: - | H52: -
A53: Extraord. Item & Account. Change | B53: - | C53: - | D53: - | E53: - | F53: - | G53: - | H53: -
A54: Net Income to Company | B54: 4133 | C54: 5423 | D54: 2118 | E54: 3124 | F54: 22146 | G54: 8884 | H54: 10001
A56: Minority Int. in Earnings | B56: - | C56: - | D56: - | E56: -11900 | F56: -9700 | G56: -9204 | H56: -9080
A57: Net Income | B57: 4133 | C57: 5423 | D57: 2118 | E57: -8776 | F57: 12446 | G57: -320 | H57: 921
A59: Pref. Dividends and Other Adj. | B59: - | C59: - | D59: - | E59: - | F59: - | G59: - | H59: -
A61: NI to Common Incl Extra Items | B61: 4133 | C61: 5423 | D61: 2118 | E61: -8776 | F61: 12446 | G61: -320 | H61: 921
A62: NI to Common Excl. Extra Items | B62: 4133 | C62: 5423 | D62: 2118 | E62: -8776 | F62: 12446 | G62: -320 | H62: 921
A64: Per Share Items
A65: Basic EPS | B65: NA | C65: 0.18 | D65: 0.07 | E65: -0.65 | F65: 0.54 | G65: -0.01 | H65: 0.04
A66: Basic EPS Excl. Extra Items | B66: NA | C66: 0.181165 | D66: 0.070654 | E66: -0.65 | F66: 0.542167 | G66: -0.01 | H66: 0.035029
A67: Weighted Avg. Basic Shares Out. | B67: NA | C67: 29934 | D67: 29977 | E67: 13588 | F67: 22956 | G67: 25876 | H67: 26291.75
A69: Diluted EPS | B69: NA | C69: 0.18 | D69: 0.07 | E69: -0.65 | F69: 0.53 | G69: -0.01 | H69: 0.04
A70: Diluted EPS Excl. Extra Items | B70: NA | C70: 0.18 | D70: 0.070314 | E70: -0.65 | F70: 0.53 | G70: -0.01 | H70: 0.035029
A71: Weighted Avg. Diluted Shares Out. | B71: NA | C71: 30018 | D71: 30122 | E71: 13588 | F71: 23449 | G71: 25876 | H71: 26342.75
A73: Normalized Basic EPS | B73: NA | C73: 0.17 | D73: 0.06 | E73: 0.05 | F73: 0.34 | G73: 0.47 | H73: 0.52
A74: Normalized Diluted EPS | B74: NA | C74: 0.165775 | D74: 0.05986 | E74: 0.045674 | F74: 0.328612 | G74: 0.473957 | H74: 0.514942
A76: Dividends per Share | B76: NA | C76: NA | D76: NA | E76: NA | F76: NA | G76: NA | H76: NA
A77: Payout Ratio % | B77: NA | C77: NA | D77: 12.780925 | E77: NA | F77: NA | G77: NA | H77: NA
A79: Supplemental Items
A80: EBITDA | B80: 6848 | C80: 11555 | D80: 9057 | E80: 30580 | F80: 42341 | G80: 56789 | H80: 60600
A81: EBITA | B81: 4686 | C81: 8014 | D81: 3248 | E81: 20358 | F81: 27839 | G81: 35085 | H81: 37146
A82: EBIT | B82: 4686 | C82: 8014 | D82: 3248 | E82: 20358 | F82: 27839 | G82: 35085 | H82: 37146
A83: EBITDAR | B83: 11722 | C83: 18663 | D83: 20267 | E83: 45817 | F83: 64165 | G83: 82950 | H83: NA
A84: As Reported Total Revenue* | B84: 57038 | C84: 82456 | D84: 118530 | E84: 190592 | F84: 268475 | G84: 358810 | H84: 381177
A85: Effective Tax Rate % | B85: 0.087637 | C85: 0.078191 | D85: 0.238129 | E85: 0.514001 | F85: 0.222838 | G85: 0.944576 | H85: 0.937862
A86: Current Domestic Taxes | B86: 308 | C86: 266 | D86: 194 | E86: 3605 | F86: 6206 | G86: 4133 | H86: 4133
A87: Current Foreign Taxes | B87: 123 | C87: 187 | D87: 561 | E87: 433 | F87: 667 | G87: 942 | H87: 942
A88: Total Current Taxes | B88: 431 | C88: 453 | D88: 755 | E88: 4038 | F88: 6873 | G88: 5075 | H88: 5075
A89: Deferred Domestic Taxes | B89: -34 | C89: 7 | D89: -93 | E89: -734 | F89: -523 | G89: 146334 | H89: 146334
A90: Total Deferred Taxes | B90: -34 | C90: 7 | D90: -93 | E90: -734 | F90: -523 | G90: 146334 | H90: 146334
A92: Normalized Net Income | B92: 2831.25 | C92: 4976.25 | D92: 1803.125 | E92: 620.625 | F92: 7705.625 | G92: 12264.125 | H92: 13565
A93: Interest Capitalized | B93: NA | C93: NA | D93: NA | E93: 108 | F93: NA | G93: 164 | H93: NA
A94: Interest on Long Term Debt | B94: NA | C94: NA | D94: 365 | E94: 440 | F94: 374 | G94: 1806 | H94: NA
A95: Filing Date | B95: 42090 | C95: 42459 | D95: 42807 | E95: 43157 | F95: 43157 | G95: 43157 | H95: 43227
A96: Restatement Type | B96: NC | C96: RC | D96: NC | E96: RC | F96: NC | G96: O | H96: O
A97: Calculation Type | B97: REP | C97: REP | D97: REP | E97: REP | F97: REP | G97: REP | H97: LTM
A99: Supplemental Operating Expense Items
A100: Advertising Exp. | B100: 564 | C100: 794 | D100: 87 | E100: 149 | F100: 147 | G100: 357 | H100: NA
A101: General and Administrative Exp. | B101: 6928 | C101: 10163 | D101: 18149 | E101: 24237 | F101: 30556 | G101: 38339 | H101: 40680
A102: Net Rental Exp. | B102: 4874 | C102: 7108 | D102: 11210 | E102: 15237 | F102: 21824 | G102: 26161 | H102: NA
A103: Imputed Oper. Lease Interest Exp. | B103: - | C103: - | D103: 2006.5 | E103: 3287.779 | F103: 56290.73 | G103: 45770.867 | H103: -
A104: Imputed Oper. Lease Depreciation | B104: - | C104: - | D104: 9203.5 | E104: 11949.221 | F104: -34466.7 | G104: -19609.9 | H104: -
A106: Stock-Based Comp., G&A Exp. | B106: 450 | C106: 93 | D106: - | E106: 12367 | F106: - | G106: - | H106: -
A107: Stock-Based Comp., Unallocated | B107: - | C107: - | D107: 165 | E107: 4314 | F107: 5354 | G107: 5623 | H107: 5811
A108: Stock-Based Comp., Total | B108: 450 | C108: 93 | D108: 165 | E108: 16681 | F108: 5354 | G108: 5623 | H108: 5811
A110: * Occasionally, certain items classified as Revenue by the company will be re-classified as other income if it is deemed to be non-recurring and unrelated to the core business of the firm. This field shows Total Revenue exactly as reported by the firm on its consolidated statement of income.
A111: Note: For multiple class companies, per share items are primary class equivalent, and for foreign companies listed as primary ADRs, per share items are ADR-equivalent.

Sheet BS
A5: Shake Shack Inc. (NYSE:SHAK) > Financials > Balance Sheet
A7: In Thousands of the reported currency, except per share items. | B7: Template: | C7: Standard | E7: Restatement: | F7: Latest Filings
B8: Period Type: | C8: Annual | E8: Order: | F8: Latest on Right
B9: Currency: | C9: Reported Currency | E9: Conversion: | F9: Historical
B10: Units: | C10: Thousands (k) | E10: Decimals: | F10: Capital IQ (Default)
B11: Source: | C11: Capital IQ & Proprietary Data
A14: Balance Sheet
A15: Balance Sheet as of: | B15: 41269 | C15: 41633 | D15: Reclassified Dec-31-2014 | E15: 42368 | F15: 42732 | G15: 43096 | H15: 43187
A16: Currency | B16: USD | C16: USD | D16: USD | E16: USD | F16: USD | G16: USD | H16: USD
A17: ASSETS
A18: Cash And Equivalents | B18: 16033 | C18: 13076 | D18: 2677 | E18: 70849 | F18: 11607 | G18: 21507 | H18: 26624
A19: Short Term Investments | B19: - | C19: - | D19: - | E19: 275 | F19: 62040 | G19: 63036 | H19: 61128
A20: Total Cash & ST Investments | B20: 16033 | C20: 13076 | D20: 2677 | E20: 71124 | F20: 73647 | G20: 84543 | H20: 87752
A22: Accounts Receivable | B22: 1553 | C22: 1107 | D22: 1482 | E22: 2692 | F22: 2878 | G22: 3458 | H22: 5057
A23: Other Receivables | B23: - | C23: 420 | D23: 1796 | E23: 1525 | F23: 3139 | G23: 2201 | H23: -
A24: Total Receivables | B24: 1553 | C24: 1527 | D24: 3278 | E24: 4217 | F24: 6017 | G24: 5659 | H24: 5057
A26: Inventory | B26: 243 | C26: 331 | D26: 529 | E26: 543 | F26: 806 | G26: 1258 | H26: 1175
A27: Prepaid Exp. | B27: 155 | C27: 273 | D27: 1441 | E27: 3050 | F27: 3474 | G27: 1739 | H27: 1665
A28: Other Current Assets | B28: - | C28: - | D28: - | E28: - | F28: - | G28: - | H28: -
A29: Total Current Assets | B29: 17984 | C29: 15207 | D29: 7925 | E29: 78934 | F29: 83944 | G29: 93199 | H29: 95649
A31: Gross Property, Plant & Equipment | B31: 29891 | C31: 46271 | D31: 83467 | E31: 116560 | F31: 173385 | G31: 245350 | H31: 263819
A32: Accumulated Depreciation | B32: -4816 | C32: -8333 | D32: -13343 | E32: -23519 | F32: -37121 | G32: -58255 | H32: -63941
A33: Net Property, Plant & Equipment | B33: 25075 | C33: 37938 | D33: 70124 | E33: 93041 | F33: 136264 | G33: 187095 | H33: 199878
A35: Other Intangibles | B35: - | C35: - | D35: 701 | E35: 701 | F35: 701 | G35: 894 | H35: -
A36: Deferred Tax Assets, LT | B36: 74 | C36: 67 | D36: 161 | E36: 201957 | F36: 313207 | G36: 185914 | H36: 200622
A37: Deferred Charges, LT | B37: 246 | C37: - | D37: - | E37: - | F37: - | G37: - | H37: -
A38: Other Long-Term Assets | B38: 689 | C38: 2007 | D38: 4051 | E38: 4914 | F38: 4078 | G38: 3504 | H38: 4145
A39: Total Assets | B39: 44068 | C39: 55219 | D39: 82962 | E39: 379547 | F39: 538194 | G39: 470606 | H39: 500294
A41: LIABILITIES
A42: Accounts Payable | B42: 1174 | C42: 2393 | D42: 6440 | E42: 6786 | F42: 6921 | G42: 8210 | H42: 6738
A43: Accrued Exp. | B43: 3531 | C43: 3483 | D43: 8724 | E43: 13678 | F43: 15946 | G43: 19690 | H43: 21757
A44: Short-term Borrowings | B44: - | C44: - | D44: 32000 | E44: - | F44: - | G44: - | H44: -
A45: Unearned Revenue, Current | B45: 628 | C45: - | D45: 625 | E45: 833 | F45: 1153 | G45: 1472 | H45: 1310
A46: Other Current Liabilities | B46: 234 | C46: 1329 | D46: 388 | E46: 2708 | F46: 7696 | G46: 4652 | H46: 3652
A47: Total Current Liabilities | B47: 5567 | C47: 7205 | D47: 48177 | E47: 24005 | F47: 31716 | G47: 34024 | H47: 33457
A49: Long-Term Debt | B49: - | C49: 313 | D49: 313 | E49: 313 | F49: - | G49: - | H49: -
A50: Capital Leases | B50: - | C50: - | D50: - | E50: - | F50: 2007 | G50: 14518 | H50: 17030
A51: Unearned Revenue, Non-Current | B51: 1725 | C51: - | D51: - | E51: - | F51: - | G51: - | H51: -
A52: Other Non-Current Liabilities | B52: 4905 | C52: 10314 | D52: 21872 | E52: 198210 | F52: 303118 | G52: 197585 | H52: 216674
A53: Total Liabilities | B53: 12197 | C53: 17832 | D53: 70362 | E53: 222528 | F53: 336841 | G53: 246127 | H53: 267161
A55: Common Stock | B55: 31871 | C55: 37387 | D55: 12600 | E55: 36 | F55: 36 | G55: 37 | H55: 37
A56: Additional Paid In Capital | B56: - | C56: - | D56: - | E56: 96311 | F56: 135448 | G56: 153105 | H56: 163372
A57: Retained Earnings | B57: - | C57: - | D57: - | E57: 4273 | F57: 16719 | G57: 16399 | H57: 18733
A58: Treasury Stock | B58: - | C58: - | D58: - | E58: - | F58: - | G58: - | H58: -
A59: Comprehensive Inc. and Other | B59: - | C59: - | D59: - | E59: -5 | F59: -15 | G59: -49 | H59: -
A60: Total Common Equity | B60: 31871 | C60: 37387 | D60: 12600 | E60: 100615 | F60: 152188 | G60: 169492 | H60: 182142
A62: Minority Interest | B62: - | C62: - | D62: - | E62: 56404 | F62: 49165 | G62: 54987 | H62: 50991
A64: Total Equity | B64: 31871 | C64: 37387 | D64: 12600 | E64: 157019 | F64: 201353 | G64: 224479 | H64: 233133
A66: Total Liabilities And Equity | B66: 44068 | C66: 55219 | D66: 82962 | E66: 379547 | F66: 538194 | G66: 470606 | H66: 500294
A68: Supplemental Items
A69: Total Shares Out. on Filing Date | B69: NA | C69: 29934 | D69: 12058.147 | E69: 20982.881 | F69: 25151.384 | G69: 27078.149 | H69: 27647.588
A70: Total Shares Out. on Balance Sheet Date | B70: NA | C70: 29934 | D70: 12058.147 | E70: 19789.259 | F70: 25151.384 | G70: 26527.477 | H70: 27627.553
A71: Book Value/Share | B71: NA | C71: NA | D71: 1.04 | E71: 5.08 | F71: 6.05 | G71: 6.39 | H71: 6.59
A72: Tangible Book Value | B72: 31871 | C72: 37387 | D72: 11899 | E72: 99914 | F72: 151487 | G72: 168598 | H72: 182142
A73: Tangible Book Value/Share | B73: NA | C73: NA | D73: 0.99 | E73: 5.05 | F73: 6.02 | G73: 6.36 | H73: 6.59
A74: Total Debt | B74: 0 | C74: 313 | D74: 32313 | E74: 313 | F74: 2007 | G74: 14518 | H74: 17030
A75: Net Debt | B75: -16033 | C75: -12763 | D75: 29636 | E75: -70811 | F75: -71640 | G75: -70025 | H75: -70722
A76: Debt Equivalent Oper. Leases | B76: 38992 | C76: 56864 | D76: 89680 | E76: 121896 | F76: 174592 | G76: 209288 | H76: NA
A77: Total Minority Interest | B77: NA | C77: NA | D77: NA | E77: 56404 | F77: 49165 | G77: 54987 | H77: 50991
A78: Inventory Method | B78: NA | C78: FIFO | D78: FIFO | E78: FIFO | F78: FIFO | G78: FIFO | H78: NA
A79: Finished Goods Inventory | B79: 243 | C79: 331 | D79: 529 | E79: 543 | F79: 806 | G79: 1258 | H79: 1175
A80: Machinery | B80: 7372 | C80: 11591 | D80: 18886 | E80: 27065 | F80: 39246 | G80: 54457 | H80: 56588
A81: Construction in Progress | B81: 1663 | C81: 2277 | D81: 6309 | E81: 6591 | F81: 13510 | G81: 16458 | H81: 22860
A82: Leasehold Improvements | B82: 20856 | C82: 32403 | D82: 58272 | E82: 82904 | F82: 120629 | G82: 166963 | H82: 173422
A83: Full Time Employees | B83: NA | C83: 1590 | D83: 1680 | E83: 2215 | F83: 3521 | G83: 4440 | H83: NA
A84: Filing Date | B84: 42090 | C84: 42459 | D84: 42807 | E84: 43157 | F84: 43157 | G84: 43157 | H84: 43227
A85: Restatement Type | B85: NC | C85: NC | D85: RC | E85: NC | F85: NC | G85: O | H85: O
A86: Calculation Type | B86: RUP | C86: RUP | D86: RUP | E86: RUP | F86: REP | G86: REP | H86: REP
A89: Note: For multiple class companies, total share counts are primary class equivalent, and for foreign companies listed as primary ADRs, total share counts are ADR-equivalent.

Sheet SCF
A5: Shake Shack Inc. (NYSE:SHAK) > Financials > Cash Flow
A7: In Thousands of the reported currency, except per share items. | B7: Template: | C7: Standard | E7: Restatement: | F7: Latest Filings
B8: Period Type: | C8: Annual | E8: Order: | F8: Latest on Right
B9: Currency: | C9: Reported Currency | E9: Conversion: | F9: Historical
B10: Units: | C10: Thousands (k) | E10: Decimals: | F10: Capital IQ (Default)
B11: Source: | C11: Capital IQ & Proprietary Data
A14: Cash Flow
A15: For the Fiscal Period Ending | B15: 12 months Dec-26-2012 | C15: 12 months Dec-25-2013 | D15: 12 months Dec-31-2014 | E15: 12 months Dec-30-2015 | F15: 12 months Dec-28-2016 | G15: 12 months Dec-27-2017 | H15: LTM 12 months Mar-28-2018
A16: Currency | B16: USD | C16: USD | D16: USD | E16: USD | F16: USD | G16: USD | H16: USD
A18: Net Income | B18: 4133 | C18: 5423 | D18: 2118 | E18: -8776 | F18: 12446 | G18: -320 | H18: 921
A19: Depreciation & Amort. | B19: 2162 | C19: 3541 | D19: 5809 | E19: 10222 | F19: 14502 | G19: 21704 | H19: 23454
A20: Depreciation & Amort., Total | B20: 2162 | C20: 3541 | D20: 5809 | E20: 10222 | F20: 14502 | G20: 21704 | H20: 23454
A22: (Gain) Loss From Sale Of Assets | B22: - | C22: 25 | D22: 105 | E22: 17 | F22: 34 | G22: 608 | H22: 1457
A23: (Gain) Loss On Sale Of Invest. | B23: - | C23: - | D23: - | E23: - | F23: 18 | G23: 5 | H23: 56
A24: Stock-Based Compensation | B24: 450 | C24: 93 | D24: 165 | E24: 16681 | F24: 5354 | G24: 5623 | H24: 5811
A25: Tax Benefit from Stock Options | B25: - | C25: - | D25: - | E25: - | F25: -33 | G25: - | H25: -
A26: Other Operating Activities | B26: 62 | C26: 44 | D26: 99 | E26: 11439 | F26: 8793 | G26: 28634 | H26: 29215
A27: Change in Acc. Receivable | B27: -1076 | C27: 26 | D27: -1751 | E27: 775 | F27: 2974 | G27: 6421 | H27: 7220
A28: Change In Inventories | B28: -35 | C28: -88 | D28: -198 | E28: -14 | F28: -263 | G28: -452 | H28: -272
A29: Change in Acc. Payable | B29: -210 | C29: 1219 | D29: 1210 | E29: 201 | F29: 839 | G29: 1235 | H29: 835
A30: Change in Other Net Operating Assets | B30: 6192 | C30: 2641 | D30: 6027 | E30: 10713 | F30: 9621 | G30: 7420 | H30: 11635
A31: Cash from Ops. | B31: 11678 | C31: 12924 | D31: 13584 | E31: 41258 | F31: 54285 | G31: 70878 | H31: 80332
A33: Capital Expenditure | B33: -11036 | C33: -16194 | D33: -28515 | E33: -32117 | F33: -54433 | G33: -61533 | H33: -66119
A34: Cash Acquisitions | B34: - | C34: - | D34: - | E34: - | F34: - | G34: - | H34: -
A35: Divestitures | B35: - | C35: - | D35: - | E35: - | F35: - | G35: - | H35: -
A36: Invest. in Marketable & Equity Securt. | B36: - | C36: - | D36: - | E36: -2397 | F36: -60328 | G36: -410 | H36: -3373
A37: Net (Inc.) Dec. in Loans Originated/Sold | B37: - | C37: - | D37: - | E37: - | F37: - | G37: - | H37: -
A38: Other Investing Activities | B38: - | C38: - | D38: - | E38: - | F38: - | G38: - | H38: -
A39: Cash from Investing | B39: -11036 | C39: -16194 | D39: -28515 | E39: -34514 | F39: -114761 | G39: -61943 | H39: -69492
A41: Short Term Debt Issued | B41: - | C41: - | D41: 32000 | E41: 4000 | F41: - | G41: - | H41: -
A42: Long-Term Debt Issued | B42: - | C42: 313 | D42: - | E42: - | F42: 65 | G42: 1183 | H42: -
A43: Total Debt Issued | B43: - | C43: 313 | D43: 32000 | E43: 4000 | F43: 65 | G43: 1183 | H43: 1411
A44: Short Term Debt Repaid | B44: -1925 | C44: - | D44: - | E44: -36000 | F44: - | G44: - | H44: -
A45: Long-Term Debt Repaid | B45: - | C45: - | D45: - | E45: - | F45: -313 | G45: -266 | H45: -
A46: Total Debt Repaid | B46: -1925 | C46: - | D46: - | E46: -36000 | F46: -313 | G46: -266 | H46: -309
A48: Issuance of Common Stock | B48: - | C48: - | D48: - | E48: 109292 | F48: 3194 | G48: 7585 | H48: 4765
A50: Common Dividends Paid | B50: - | C50: - | D50: -27070 | E50: - | F50: - | G50: - | H50: -
A51: Total Dividends Paid | B51: - | C51: - | D51: -27070 | E51: - | F51: - | G51: - | H51: -
A53: Special Dividend Paid | B53: - | C53: - | D53: - | E53: -11125 | F53: - | G53: - | H53: -
A54: Other Financing Activities | B54: -246 | C54: - | D54: -398 | E54: -4739 | F54: -1712 | G54: -7537 | H54: -5794
A55: Cash from Financing | B55: -2171 | C55: 313 | D55: 4532 | E55: 61428 | F55: 1234 | G55: 965 | H55: 73
A57: Net Change in Cash | B57: -1529 | C57: -2957 | D57: -10399 | E57: 68172 | F57: -59242 | G57: 9900 | H57: 10913
A59: Supplemental Items
A60: Cash Interest Paid | B60: 59 | C60: 19 | D60: 123 | E60: 92 | F60: 54 | G60: 1106 | H60: 1650
A61: Cash Taxes Paid | B61: 198 | C61: 639 | D61: 836 | E61: 416 | F61: 1823 | G61: 2261 | H61: 2022
A62: Levered Free Cash Flow | B62: NA | C62: -6125.8 | D62: -14884.1 | E62: 12568.25 | F62: -12187.4 | G62: -9355.8 | H62: -7835.4
A63: Unlevered Free Cash Flow | B63: NA | C63: -6093.3 | D63: -14656 | E63: 12775.75 | F63: -11953.6 | G63: -8328.9 | H63: -6644.8
A64: Change in Net Working Capital | B64: NA | C64: -1458 | D64: -5855 | E64: -5266 | F64: -5224 | G64: -3949 | H64: -6993
A65: Net Debt Issued | B65: -1925 | C65: 313 | D65: 32000 | E65: -32000 | F65: -248 | G65: 917 | H65: 1102
A66: Filing Date | B66: 42090 | C66: 42459 | D66: 42807 | E66: 43157 | F66: 43157 | G66: 43157 | H66: 43227
A67: Restatement Type | B67: NC | C67: NC | D67: NC | E67: NC | F67: NC | G67: O | H67: O
A68: Calculation Type | B68: REP | C68: REP | D68: REP | E68: REP | F68: REP | G68: REP | H68: LTM

Sheet Multiples
A5: Shake Shack Inc. (NYSE:SHAK) > Financials > Multiples
B7: View: | C7: Data | E7: Frequency: | F7: Quarterly
B8: Order: | C8: Latest on Right | E8: Decimals: | F8: Capital IQ (Default)
B9: Dilution: | C9: Basic
A12: Multiples Detail In Thousands of the reported currency, except per share items.
A14: For Quarter Ending | C14: 42094 | D14: 42185 | E14: 42277 | F14: 42369 | G14: 42460 | H14: 42551 | I14: 42643 | J14: 42734 | K14: 42825 | L14: 42916 | M14: 43007 | N14: 43098 | O14: 43188 | P14: 43280 | Q14: 43286
A15: TEV/LTM Total Revenue | B15: Average | C15: 4.5920169 | D15: 6.4147764 | E15: 4.6529703 | F15: 3.8995765 | G15: 3.5788121 | H15: 3.9002068 | I15: 3.8914554 | J15: 3.5294064 | K15: 3.3175419 | L15: 3.179591 | M15: 2.7095607 | N15: 3.0098018 | O15: 3.1255771 | P15: 4.0317018 | Q15: 4.707798
B16: High | C16: 5.341654 | D16: 8.221554 | E16: 6.070497 | F16: 4.583484 | G16: 4.407273 | H16: 4.200808 | I16: 4.427036 | J16: 3.785779 | K16: 3.89203 | L16: 3.422233 | M16: 3.089457 | N16: 3.560216 | O16: 3.605442 | P16: 4.998674 | Q16: 4.730173
B17: Low | C17: 4.112146 | D17: 5.032968 | E17: 3.894621 | F17: 3.205442 | G17: 2.802777 | H17: 3.441574 | I17: 3.549253 | J17: 3.160664 | K17: 2.820066 | L17: 2.846347 | M17: 2.444294 | N17: 2.640984 | O17: 2.660946 | P17: 3.032596 | Q17: 4.683477
B18: Close | C18: 5.341654 | D18: 5.032968 | E18: 4.313762 | F18: 3.563747 | G18: 4.034529 | H18: 3.871844 | I18: 3.609934 | J18: 3.521668 | K18: 3.084916 | L18: 3.035469 | M18: 2.674861 | N18: 3.302894 | O18: 3.099761 | P18: 4.776869 | Q18: 4.709744
A20: TEV/NTM Total Revenues | B20: Average | C20: 3.282823 | D20: 4.65507 | E20: 3.42962 | F20: 2.993161 | G20: 2.77707 | H20: 3.061841 | I20: 2.984795 | J20: 2.645538 | K20: 2.477775 | L20: 2.431864 | M20: 2.142041 | N20: 2.387029 | O20: 2.471681 | P20: 3.187265 | Q20: 3.703628
B21: High | C21: 3.843232 | D21: 5.914375 | E21: 4.428971 | F21: 3.403685 | G21: 3.398954 | H21: 3.303067 | I21: 3.425858 | J21: 2.810505 | K21: 2.906166 | L21: 2.639768 | M21: 2.385114 | N21: 2.809796 | O21: 2.831571 | P21: 3.93246 | Q21: 3.721231
B22: Low | C22: 2.915662 | D22: 3.673351 | E22: 2.888873 | F22: 2.516771 | G22: 2.16026 | H22: 2.739853 | I22: 2.692183 | J22: 2.46761 | K22: 2.122488 | L22: 2.190586 | M22: 1.960621 | N22: 2.11839 | O22: 2.123115 | P22: 2.422784 | Q22: 3.684495
B23: Close | C23: 3.843232 | D23: 3.673351 | E23: 3.20339 | F23: 2.783149 | G23: 3.173475 | H23: 3.030613 | I23: 2.735721 | J23: 2.618232 | K23: 2.322907 | L23: 2.343434 | M23: 2.145563 | N23: 2.601676 | O23: 2.476327 | P23: 3.757966 | Q23: 3.705159
A25: TEV/LTM EBITDA | B25: Average | C25: 68.171592 | D25: 81.73159 | E25: 50.497727 | F25: 32.647252 | G25: 30.209722 | H25: 39.541643 | I25: 35.78185 | J25: 31.373139 | K25: 26.808763 | L25: 20.462761 | M25: 17.363572 | N25: 18.894772 | O25: 19.661783 | P25: 25.418746 | Q25: 29.612286
B26: High | C26: 75.912815 | D26: 107.59643 | E26: 75.306764 | F26: 63.408795 | G26: 46.934615 | H26: 45.076034 | I26: 42.569036 | J26: 33.779166 | K26: 34.72721 | L26: 22.179291 | M26: 20.022587 | N26: 22.205992 | O26: 22.48808 | P26: 31.441908 | Q26: 29.753026
B27: Low | C27: 59.476699 | D27: 62.435835 | E27: 37.549667 | F27: 23.241189 | G27: 20.321651 | H27: 33.961824 | I27: 23.889054 | J27: 19.265884 | K27: 17.948705 | L27: 18.9199 | M27: 15.546426 | N27: 16.797434 | O27: 17.285883 | P27: 19.160854 | Q27: 29.459307
B28: Close | C28: 69.90684 | D28: 62.435835 | E28: 41.590772 | F28: 25.839097 | G28: 43.291809 | H28: 37.230475 | I28: 32.268376 | J28: 31.422601 | K28: 19.56078 | L28: 19.672696 | M28: 17.012899 | N28: 20.60101 | O28: 19.585224 | P28: 30.046744 | Q28: 29.624524
A30: TEV/NTM EBITDA | B30: Average | C30: 44.680719 | D30: 50.854473 | E30: 27.714753 | F30: 18.505282 | G30: 16.007642 | H30: 17.091267 | I30: 17.064819 | J30: 16.205422 | K30: 15.314615 | L30: 15.340442 | M30: 13.502986 | N30: 15.349637 | O30: 16.947151 | P30: 22.820652 | Q30: 26.088413
B31: High | C31: 53.117953 | D31: 70.176033 | E31: 44.689006 | F31: 21.711974 | G31: 19.586761 | H31: 19.577387 | I31: 18.507376 | J31: 17.301015 | K31: 18.042113 | L31: 16.774 | M31: 15.236244 | N31: 18.232993 | O31: 18.637584 | P31: 27.70031 | Q31: 26.212405
B32: Low | C32: 37.136917 | D32: 37.05106 | E32: 17.859625 | F32: 15.20392 | G32: 12.044182 | H32: 14.632727 | I32: 15.500358 | J32: 14.72473 | K32: 12.949983 | L32: 13.183291 | M32: 12.239779 | N32: 13.266446 | O32: 15.084662 | P32: 17.718349 | Q32: 25.953639
B33: Close | C33: 45.594307 | D33: 37.05106 | E33: 20.4343 | F33: 17.002105 | G33: 18.73261 | H33: 16.277924 | I33: 16.662061 | J33: 16.09403 | K33: 14.402864 | L33: 14.925387 | M33: 13.436618 | N33: 17.068031 | O33: 17.741877 | P33: 26.471171 | Q33: 26.099195
A35: TEV/LTM EBIT | B35: Average | C35: 239.00043 | D35: 224.53681 | E35: 119.51355 | F35: 57.583151 | G35: 57.882573 | H35: 87.369022 | I35: 71.182187 | J35: 60.052131 | K35: 48.463105 | L35: 31.658971 | M35: 27.178493 | N35: 29.852133 | O35: 31.454084 | P35: 41.363488 | Q35: 48.309496
B36: High | C36: 299.48391 | D36: 289.97035 | E36: 206.58451 | F36: 87.883652 | G36: 114.17288 | H36: 106.18575 | I36: 88.220587 | J36: 64.640158 | K36: 66.454343 | L36: 34.626712 | M36: 31.259625 | N36: 35.200334 | O36: 35.647492 | P36: 51.294342 | Q36: 48.539099
B37: Low | C37: 158.77541 | D37: 171.27647 | E37: 74.675417 | F37: 37.188379 | G37: 32.516806 | H37: 68.582609 | I37: 34.772543 | J37: 28.573143 | K37: 27.196285 | L37: 28.799803 | M37: 24.38143 | N37: 26.343383 | O37: 27.73813 | P37: 31.013988 | Q37: 48.059927
B38: Close | C38: 194.93419 | D38: 171.27647 | E38: 82.712005 | F38: 41.345307 | G38: 101.98264 | H38: 77.156889 | I38: 62.117982 | J38: 60.13061 | K38: 29.750457 | L38: 30.713369 | M38: 26.681297 | N38: 32.65616 | O38: 31.700879 | P38: 49.018272 | Q38: 48.329461
A40: TEV/NTM EBIT | B40: Average | C40: 206.90287 | D40: 160.71917 | E40: 50.014569 | F40: 27.974848 | G40: 25.819448 | H40: 28.95267 | I40: 27.372298 | J40: 24.736699 | K40: 25.023587 | L40: 27.07057 | M40: 24.130115 | N40: 27.477397 | O40: 35.364779 | P40: 51.922721 | Q40: 58.601424
B41: High | C41: 265.58977 | D41: 294.89218 | E41: 89.263634 | F41: 34.188531 | G41: 31.623796 | H41: 32.625659 | I41: 31.771771 | J41: 26.776601 | K41: 28.054917 | L41: 29.631066 | M41: 27.009599 | N41: 32.607244 | O41: 43.279175 | P41: 62.222167 | Q41: 58.879943
B42: Low | C42: 163.17377 | D42: 73.475835 | E42: 28.30333 | F42: 22.435779 | G42: 19.516553 | H42: 25.242523 | I42: 24.567678 | J42: 21.970841 | K42: 22.970474 | L42: 23.579131 | M42: 22.018304 | N42: 23.925798 | O42: 27.477712 | P42: 41.47774 | Q42: 58.298687
B43: Close | C43: 200.33421 | D43: 73.475835 | E43: 32.176655 | F43: 25.034636 | G43: 31.385409 | H43: 27.409924 | I43: 24.945035 | J43: 24.908561 | K43: 25.294434 | L43: 26.408948 | M43: 24.2327 | N43: 30.79836 | O43: 42.401713 | P43: 59.4612 | Q43: 58.625644
A45: P/LTM EPS | B45: Average | C45: 282.13624 | D45: 281.96002 | E45: NM | F45: NM | G45: NM | H45: 108.01606 | I45: 99.896446 | J45: 80.80118 | K45: 72.168455 | L45: 66.836142 | M45: 58.430773 | N45: 64.264724 | O45: 69.255478 | P45: NM | Q45: NM
B46: High | C46: 284.94489 | D46: 287.39297 | E46: NM | F46: NM | G46: NM | H46: 114.51817 | I46: 124.09866 | J46: 85.000444 | K46: 86.620673 | L46: 72.95661 | M46: 65.967646 | N46: 75.350989 | O46: 76.290851 | P46: NM | Q46: NM
B47: Low | C47: 278.96702 | D47: 274.64019 | E47: NM | F47: NM | G47: NM | H47: 99.863903 | I47: 84.136869 | J47: 73.029242 | K47: 57.962264 | L47: 61.226415 | M47: 53.334262 | N47: 57.203611 | O47: 61.917447 | P47: NM | Q47: NM
B48: Close | C48: 284.94489 | D48: NM | E48: NM | F48: NM | G48: NM | H48: 108.72809 | I48: 85.543262 | J48: 78.584383 | K48: 63.018867 | L48: 64.833798 | M48: 57.91822 | N48: 70.0035 | O48: NM | P48: NM | Q48: NM
A50: P/NTM EPS | B50: Average | C50: NM | D50: NM | E50: 184.67867 | F50: 134.04883 | G50: 94.346649 | H50: 87.05593 | I50: 75.400747 | J50: 66.011461 | K50: 65.602059 | L50: 71.202832 | M50: 63.191911 | N50: 73.031589 | O50: 78.518067 | P50: 101.61299 | Q50: 113.33102
B51: High | C51: NM | D51: NM | E51: 262.17973 | F51: 180.77201 | G51: 109.17837 | H51: 102.14768 | I51: 90.07799 | J51: 71.122696 | K51: 73.245451 | L51: 77.969805 | M51: 70.753589 | N51: 84.869502 | O51: 86.848077 | P51: 120.25712 | Q51: 113.86379
B52: Low | C52: NM | D52: NM | E52: 160.14984 | F52: 102.30378 | G52: 83.560209 | H52: 72.929381 | I52: 66.110896 | J52: 60.759956 | K52: 60.440317 | L52: 62.727273 | M52: 58.020478 | N52: 62.50238 | O52: 67.401658 | P52: 83.290741 | Q52: 112.75191
B53: Close | C53: NM | D53: NM | E53: 170.99567 | F53: 106.0809 | G53: 99.197278 | H53: 78.869885 | I53: 67.215975 | J53: 65.863084 | K53: 66.305362 | L53: 69.53748 | M53: 63.235014 | N53: 79.484821 | O53: 85.110298 | P53: 114.97568 | Q53: 113.37735
A55: P/LTM Normalized EPS | B55: Average | C55: NM | D55: NM | E55: NM | F55: NM | G55: NM | H55: NM | I55: 172.57906 | J55: 101.41542 | K55: 93.53979 | L55: 100.02532 | M55: 82.597564 | N55: 86.309919 | O55: 88.887639 | P55: 110.45309 | Q55: 126.68093
B56: High | C56: NM | D56: NM | E56: NM | F56: NM | G56: NM | H56: NM | I56: 172.57906 | J56: 101.41542 | K56: 104.16336 | L56: 108.07075 | M56: 97.717986 | N56: 100.08416 | O56: 101.33252 | P56: 134.4229 | Q56: 127.27647
B57: Low | C57: NM | D57: NM | E57: NM | F57: NM | G57: NM | H57: NM | I57: 172.57906 | J57: 101.41542 | K57: 88.543272 | L57: 91.211527 | M57: 73.140999 | N57: 77.269273 | O57: 81.083305 | P57: 85.957164 | Q57: 126.03361
B58: Close | C58: NM | D58: NM | E58: NM | F58: NM | G58: NM | H58: NM | I58: NM | J58: NM | K58: 96.267751 | L58: 96.038415 | M58: 79.427301 | N58: 92.98141 | O58: 87.834972 | P58: 128.51933 | Q58: 126.73272
A60: P/BV | B60: Average | C60: 17.476413 | D60: 33.469235 | E60: 5.8961511 | F60: 4.9232516 | G60: 4.2660061 | H60: 7.0483578 | I60: 6.8971724 | J60: 6.1870538 | K60: 5.9095897 | L60: 5.7791228 | M60: 5.0993396 | N60: 5.8031141 | O60: 6.2861893 | P60: 8.4918022 | Q60: 9.8946833
B61: High | C61: 47.89767 | D61: 74.990238 | E61: 7.839743 | F61: 5.78918 | G61: 7.34021 | H61: 7.558528 | I61: 7.959893 | J61: 6.629844 | K61: 6.811129 | L61: 6.263132 | M61: 5.663148 | N61: 6.879869 | O61: 6.965683 | P61: 10.499386 | Q61: 9.941199
B62: Low | C62: 13.307511 | D62: 6.595496 | E62: 4.812153 | F62: 4.42266 | G62: 3.696552 | H62: 6.405436 | I62: 6.196133 | J62: 5.70553 | K62: 5.076948 | L62: 5.362857 | M62: 4.697165 | N62: 5.03794 | O62: 5.517211 | P62: 6.376286 | Q62: 9.844123
B63: Close | C63: 47.89767 | D63: 6.595496 | E63: 5.081222 | F63: 4.585948 | G63: 7.34021 | H63: 6.973999 | I63: 6.299705 | J63: 6.179222 | K63: 5.519859 | L63: 5.56581 | M63: 5.100876 | N63: 6.39162 | O63: 6.515581 | P63: 10.038275 | Q63: 9.898728
A65: P/Tangible BV | B65: Average | C65: 17.476413 | D65: 33.469235 | E65: 5.8961511 | F65: 4.9232516 | G65: 4.2676596 | H65: 7.072734 | I65: 6.8971724 | J65: 6.1870538 | K65: 5.9155447 | L65: 5.7884586 | M65: 5.0993396 | N65: 5.8031141 | O65: 6.2995176 | P65: 8.506236 | Q65: 9.8946833
B66: High | C66: 47.89767 | D66: 74.990238 | E66: 7.839743 | F66: 5.78918 | G66: 7.391709 | H66: 7.611558 | I66: 7.959893 | J66: 6.629844 | K66: 6.811129 | L66: 6.263132 | M66: 5.663148 | N66: 6.879869 | O66: 6.965683 | P66: 10.499386 | Q66: 9.941199
B67: Low | C67: 13.307511 | D67: 6.595496 | E67: 4.812153 | F67: 4.42266 | G67: 3.696552 | H67: 6.405436 | I67: 6.196133 | J67: 5.70553 | K67: 5.100441 | L67: 5.387673 | M67: 4.697165 | N67: 5.03794 | O67: 5.517211 | P67: 6.410097 | Q67: 9.844123
B68: Close | C68: 47.89767 | D68: 6.595496 | E68: 5.081222 | F68: 4.585948 | G68: 7.391709 | H68: 6.973999 | I68: 6.299705 | J68: 6.179222 | K68: 5.545401 | L68: 5.56581 | M68: 5.100876 | N68: 6.39162 | O68: 6.550131 | P68: 10.038275 | Q68: 9.898728
A70: P/NTM CFPS | B70: Average | C70: - | D70: - | E70: - | F70: - | G70: - | H70: 29.350754 | I70: 28.887022 | J70: 26.019428 | K70: 25.0354 | L70: - | M70: - | N70: - | O70: - | P70: - | Q70: -
B71: High | C71: - | D71: - | E71: - | F71: - | G71: - | H71: 30.089069 | I71: 33.804878 | J71: 28.131868 | K71: 28.901099 | L71: - | M71: - | N71: - | O71: - | P71: - | Q71: -
B72: Low | C72: - | D72: - | E72: - | F72: - | G72: - | H72: 27.40081 | I72: 25.735849 | J72: 23.787879 | K72: 21.787234 | L72: - | M72: - | N72: - | O72: - | P72: - | Q72: -
B73: Close | C73: - | D73: - | E73: - | F73: - | G73: - | H73: 29.497976 | I73: 26.166038 | J73: 26.21978 | K73: 23.687943 | L73: - | M73: - | N73: - | O73: - | P73: - | Q73: -
A75: TEV/LTM Unlevered FCF | B75: Average | C75: NM | D75: - | E75: NM | F75: NM | G75: 167.65506 | H75: 168.94388 | I75: NM | J75: NM | K75: NM | L75: NM | M75: NM | N75: NM | O75: NM | P75: NM | Q75: NM
B76: High | C76: NM | D76: - | E76: NM | F76: NM | G76: 171.27723 | H76: 178.33623 | I76: NM | J76: NM | K76: NM | L76: NM | M76: NM | N76: NM | O76: NM | P76: NM | Q76: NM
B77: Low | C77: NM | D77: - | E77: NM | F77: NM | G77: 164.03289 | H77: 158.78526 | I77: NM | J77: NM | K77: NM | L77: NM | M77: NM | N77: NM | O77: NM | P77: NM | Q77: NM
B78: Close | C78: NM | D78: - | E78: NM | F78: NM | G78: 171.27723 | H78: NM | I78: NM | J78: NM | K78: NM | L78: NM | M78: NM | N78: NM | O78: NM | P78: NM | Q78: NM
A80: Market Cap/LTM Levered FCF | B80: Average | C80: NM | D80: - | E80: NM | F80: NM | G80: 178.89694 | H80: 180.24684 | I80: NM | J80: NM | K80: NM | L80: NM | M80: NM | N80: NM | O80: NM | P80: NM | Q80: NM
B81: High | C81: NM | D81: - | E81: NM | F81: NM | G81: 182.69076 | H81: 190.08428 | I81: NM | J81: NM | K81: NM | L81: NM | M81: NM | N81: NM | O81: NM | P81: NM | Q81: NM
B82: Low | C82: NM | D82: - | E82: NM | F82: NM | G82: 175.10312 | H82: 169.60682 | I82: NM | J82: NM | K82: NM | L82: NM | M82: NM | N82: NM | O82: NM | P82: NM | Q82: NM
B83: Close | C83: NM | D83: - | E83: NM | F83: NM | G83: 182.69076 | H83: NM | I83: NM | J83: NM | K83: NM | L83: NM | M83: NM | N83: NM | O83: NM | P83: NM | Q83: NM
A85: Average multiples are calculated using positive close values on each trading day within the frequency periods selected. Negative values are excluded from the calculation. When the Multiples are not meaningful, due to negative values, then they will not be displayed in the chart.
A87: When a mismatch exists between the currency of the equity listing and the reported financial results such results are translated into the currency of the listing at the exchange rate applicable on the financial period end date.
A91: Historical Equity Pricing Data supplied by Interactive Data Pricing and Reference Data LLC

Sheet Historical Capitalization
A5: Shake Shack Inc. (NYSE:SHAK) > Financials > Historical Capitalization
A7: In Thousands of the trading currency, except per share items. | B7: Frequency: | C7: Quarterly | E7: Order: | F7: Latest on Right
B8: Currency: | C8: Trading Currency | E8: Conversion: | F8: Historical
B9: Units: | C9: Thousands (k) | E9: Decimals: | F9: Capital IQ (Default)
B10: Dilution: | C10: Basic
A13: Historical Capitalization
A14: Balance Sheet as of: | B14: 41633 | C14: 41906 | D14: 42004 | E14: 42095 | F14: 42186 | G14: 42277 | H14: 42368 | I14: 42459 | J14: 42550 | K14: 42641 | L14: 42732 | M14: 42823 | N14: 42914 | O14: 43005 | P14: 43096 | Q14: 43187
A15: Pricing as of* | D15: 42090 | E15: 42139 | F15: 42226 | G15: 42314 | H15: 42459 | I15: 42506 | J15: 42593 | K15: 42684 | L15: 42807 | M15: 42860 | N15: 42951 | O15: 43041 | P15: 43157 | Q15: 43227
A16: Currency | B16: USD | C16: USD | D16: USD | E16: USD | F16: USD | G16: USD | H16: USD | I16: USD | J16: USD | K16: USD | L16: USD | M16: USD | N16: USD | O16: USD | P16: USD | Q16: USD
A17: Capitalization Detail
A18: Share Price | B18: - | C18: - | D18: 49 | E18: 69.39 | F18: 70.64 | G18: 49.99 | H18: 35.77 | I18: 35.75 | J18: 38.34 | K18: 36.81 | L18: 31.15 | M18: 36.17 | N18: 31.35 | O18: 35.9 | P18: 39 | Q18: 57.1
A19: Shares Out. | B19: - | C19: - | D19: 12058.147 | E19: 12058.147 | F19: 12058.147 | G19: 15213.42 | H19: 20982.881 | I19: 22313.896 | J19: 23953.852 | K19: 24921.902 | L19: 25470.089 | M19: 25757.064 | N19: 25964.866 | O19: 26195.741 | P19: 27078.149 | Q19: 27647.588
A21: Market Capitalization | B21: - | C21: - | D21: 590849.2 | E21: 836714.82 | F21: 851787.5 | G21: 760518.86 | H21: 750557.65 | I21: 797721.78 | J21: 918390.69 | K21: 917375.21 | L21: 793393.27 | M21: 931633 | N21: 813998.55 | O21: 940427.1 | P21: 1056047.8 | Q21: 1578677.3
A22: - Cash & Short Term Investments | B22: 13076 | C22: 6107 | D22: 2677 | E22: 60834 | F22: 64919 | G22: 69821 | H22: 70849 | I22: 65855 | J22: 68371 | K22: 73575 | L22: 73647 | M22: 73551 | N22: 85542 | O22: 90186 | P22: 84543 | Q22: 87752
A23: + Total Debt | B23: 313 | C23: 5313 | D23: 32313 | E23: 313 | F23: 313 | G23: 313 | H23: 313 | I23: 313 | J23: 0 | K23: 0 | L23: 2007 | M23: 8016 | N23: 11166 | O23: 13162 | P23: 14518 | Q23: 17030
A24: + Pref. Equity | B24: - | C24: - | D24: - | E24: - | F24: - | G24: - | H24: - | I24: - | J24: - | K24: - | L24: - | M24: - | N24: - | O24: - | P24: - | Q24: -
A25: + Total Minority Interest | B25: - | C25: - | D25: - | E25: -1157 | F25: 2870 | G25: 6758 | H25: 56404 | I25: 54063 | J25: 50155 | K25: 48952 | L25: 49165 | M25: 50527 | N25: 52011 | O25: 54959 | P25: 54987 | Q25: 50991
A26: = Total Enterprise Value (TEV) | B26: - | C26: - | D26: 620485.2 | E26: 775036.82 | F26: 790051.5 | G26: 697768.86 | H26: 736425.65 | I26: 786242.78 | J26: 900174.69 | K26: 892752.21 | L26: 770918.27 | M26: 916625 | N26: 791633.55 | O26: 918362.1 | P26: 1041009.8 | Q26: 1558946.3
A28: Implied Shares Outstanding*** | B28: - | C28: - | D28: 36250 | E28: 36250 | F28: 36250 | G28: 39405.273 | H28: 37443.622 | I28: 36896.782 | J28: 36937.448 | K28: 36675.98 | L28: 36723.681 | M28: 36636.656 | N28: 36735.858 | O28: 36730.533 | P28: 36779.964 | Q28: 36852.824
A29: Implied Market Capitalization*** | B29: - | C29: - | D29: 1776250 | E29: 2515387.5 | F29: 2560700 | G29: 1969869.6 | H29: 1339358.4 | I29: 1319060 | J29: 1416181.8 | K29: 1350042.8 | L29: 1143942.7 | M29: 1325147.8 | N29: 1151669.1 | O29: 1318626.1 | P29: 1434418.6 | Q29: 2104296.2
A30: Book Value of Common Equity | B30: 37387 | C30: 35837 | D30: 12600 | E30: 110188 | F30: 112484 | G30: 131369 | H30: 100615 | I30: 113355 | J30: 128474 | K30: 142470 | L30: 152188 | M30: 160944 | N30: 168987 | O30: 176819 | P30: 169492 | Q30: 182142
A31: + Pref. Equity | B31: - | C31: - | D31: - | E31: - | F31: - | G31: - | H31: - | I31: - | J31: - | K31: - | L31: - | M31: - | N31: - | O31: - | P31: - | Q31: -
A32: + Total Minority Interest | B32: - | C32: - | D32: - | E32: -1157 | F32: 2870 | G32: 6758 | H32: 56404 | I32: 54063 | J32: 50155 | K32: 48952 | L32: 49165 | M32: 50527 | N32: 52011 | O32: 54959 | P32: 54987 | Q32: 50991
A33: + Total Debt | B33: 313 | C33: 5313 | D33: 32313 | E33: 313 | F33: 313 | G33: 313 | H33: 313 | I33: 313 | J33: 0 | K33: 0 | L33: 2007 | M33: 8016 | N33: 11166 | O33: 13162 | P33: 14518 | Q33: 17030
A34: = Total Capital | B34: 37700 | C34: 41150 | D34: 44913 | E34: 109344 | F34: 115667 | G34: 138440 | H34: 157332 | I34: 167731 | J34: 178629 | K34: 191422 | L34: 203360 | M34: 219487 | N34: 232164 | O34: 244940 | P34: 238997 | Q34: 250163
A37: * Pricing as of the filing date of the balance sheet period end date. For TEV calculation purposes on this page Capital IQ only uses balance sheet components from the original filing that is publicly available as of a given pricing date and does not use restated balance sheet data from a later filing. In the cases where a company did not disclose balance sheet values for a particular period, TEV is calculated using balance sheet components from the last reported balance sheet as of this date. The table above is organized along period end dates.
A38: ** For companies that have multiple share classes that publicly trade, we are incorporating the different prices to calculate our company level market capitalization. Please click on the value to see the detailed calculation. Prices shown on this page are the close price of the company’s primary stock class. Shares shown on this page are total company as-reported share values.
A39: *** Includes number of shares outstanding + shares held by non-controlling interest holders without accounting for dilutive securities.
A41: Historical Equity Pricing Data supplied by Interactive Data Pricing and Reference Data LLC

Sheet Capital Structure Summary
A5: Shake Shack Inc. (NYSE:SHAK) > Financials > Capital Structure Summary
A7: In Thousands of the reported currency, except ratios and % of Total values. | B7: Restatement: | C7: Latest Filings | E7: Period Type: | F7: Annual
B8: Currency: | C8: Reported Currency | E8: Conversion: | F8: Historical
B9: Units: | C9: Thousands (k) | E9: Decimals: | F9: Capital IQ (Default)
B10: Order: | C10: Latest on Right
A13: Capital Structure Data
A14: For the Fiscal Period Ending | B14: 12 months Dec-26-2012 | D14: 12 months Dec-25-2013 | F14: 12 months Dec-31-2014 | H14: 12 months Dec-30-2015 | J14: 12 months Dec-28-2016 | L14: 12 months Dec-27-2017 | N14: 3 months Mar-28-2018
A15: Currency | B15: USD | D15: USD | F15: USD | H15: USD | J15: USD | L15: USD | N15: USD
A16: Units | B16: Thousands | C16: % of Total | D16: Thousands | E16: % of Total | F16: Thousands | G16: % of Total | H16: Thousands | I16: % of Total | J16: Thousands | K16: % of Total | L16: Thousands | M16: % of Total | N16: Thousands | O16: % of Total
A18: Total Debt | B18: 0 | C18: 0 | D18: 313 | E18: 0.0083023873 | F18: 32313 | G18: 0.71945762 | H18: 313 | I18: 0.0019894236 | J18: 2007 | K18: 0.0098691975 | L18: 14518 | M18: 0.060745532 | N18: 17030 | O18: 0.068075615
A19: Total Common Equity | B19: 31871 | C19: 1 | D19: 37387 | E19: 0.99169761 | F19: 12600 | G19: 0.28054238 | H19: 100615 | I19: 0.63950754 | J19: 152188 | K19: 0.74836743 | L19: 169492 | M19: 0.70918045 | N19: 182142 | O19: 0.72809328
A20: Total Minority Interest | B20: - | C20: - | D20: - | E20: - | F20: - | G20: - | H20: 56404 | I20: 0.35850304 | J20: 49165 | K20: 0.24176338 | L20: 54987 | M20: 0.23007402 | N20: 50991 | O20: 0.2038311
A21: Total Capital | B21: 31871 | C21: 1 | D21: 37700 | E21: 1 | F21: 44913 | G21: 1 | H21: 157332 | I21: 1 | J21: 203360 | K21: 1 | L21: 238997 | M21: 1 | N21: 250163 | O21: 1
A25: Debt Summary Data
A26: For the Fiscal Period Ending | B26: 12 months Dec-26-2012 | D26: 12 months Dec-25-2013 | F26: 12 months Dec-31-2014 | H26: 12 months Dec-30-2015 | J26: 12 months Dec-28-2016 | L26: 12 months Dec-27-2017 | N26: 3 months Mar-28-2018
A27: Currency | B27: USD | D27: USD | F27: USD | H27: USD | J27: USD | L27: USD | N27: USD
A28: Units | B28: Thousands | C28: % of Total | D28: Thousands | E28: % of Total | F28: Thousands | G28: % of Total | H28: Thousands | I28: % of Total | J28: Thousands | K28: % of Total | L28: Thousands | M28: % of Total | N28: Thousands | O28: % of Total
A30: Total Revolving Credit | B30: 0 | C30: - | D30: 0 | E30: 0 | F30: 32000 | G30: 0.990313 | H30: 0 | I30: 0 | J30: 0 | K30: 0 | L30: 0 | M30: 0 | N30: 0 | O30: 0
A31: Total Senior Bonds and Notes | B31: - | C31: - | D31: 313 | E31: 1 | F31: 313 | G31: 0.009686 | H31: 313 | I31: 1 | J31: - | K31: - | L31: - | M31: - | N31: - | O31: -
A32: Total Capital Leases | B32: - | C32: - | D32: - | E32: - | F32: - | G32: - | H32: - | I32: - | J32: 2007 | K32: 1 | L32: 14518 | M32: 1 | N32: 17030 | O32: 1
A33: Total Principal Due | B33: 0 | C33: - | D33: 313 | E33: 1 | F33: 32313 | G33: 1 | H33: 313 | I33: 1 | J33: 2007 | K33: 1 | L33: 14518 | M33: 1 | N33: 17030 | O33: 1
A35: Total Debt Outstanding | B35: 0 | C35: 1 | D35: 313 | E35: 1 | F35: 32313 | G35: 1 | H35: 313 | I35: 1 | J35: 2007 | K35: 1 | L35: 14518 | M35: 1 | N35: 17030 | O35: 1
A37: Available Credit
A38: Undrawn Revolving Credit | B38: - | C38: - | D38: - | E38: - | F38: - | G38: - | H38: - | I38: - | J38: - | K38: - | L38: 19317 | M38: - | N38: 19317 | O38: -
A39: Total Undrawn Credit | B39: - | C39: - | D39: - | E39: - | F39: - | G39: - | H39: - | I39: - | J39: - | K39: - | L39: 19317 | M39: - | N39: 19317 | O39: -
A41: Additional Totals
A42: Total Cash & ST Investments | B42: 16033 | C42: - | D42: 13076 | E42: - | F42: 2677 | G42: - | H42: 71124 | I42: - | J42: 73647 | K42: - | L42: 84543 | M42: - | N42: 87752 | O42: -
A43: Net Debt | B43: -16033 | C43: - | D43: -12763 | E43: - | F43: 29636 | G43: - | H43: -70811 | I43: - | J43: -71640 | K43: - | L43: -70025 | M43: - | N43: -70722 | O43: -
A44: Total Senior Debt | B44: 0 | C44: - | D44: 313 | E44: 1 | F44: 32313 | G44: 1 | H44: 313 | I44: 1 | J44: 2007 | K44: 1 | L44: 14518 | M44: 1 | N44: 17030 | O44: 1
A45: Total Convertible Debt | B45: 0 | C45: - | D45: 0 | E45: 0 | F45: 32000 | G45: 0.990313 | H45: 0 | I45: 0 | J45: 0 | K45: 0 | L45: 0 | M45: 0 | N45: 0 | O45: 0
A46: Total Short-Term Borrowings | B46: - | C46: - | D46: - | E46: - | F46: 32000 | G46: 0.990313 | H46: - | I46: - | J46: - | K46: - | L46: - | M46: - | N46: - | O46: -
A47: Long-Term Debt (Incl. Cap. Leases) | B47: - | C47: - | D47: 313 | E47: 1 | F47: 313 | G47: 0.009686 | H47: 313 | I47: 1 | J47: 2007 | K47: 1 | L47: 14518 | M47: 1 | N47: 17030 | O47: 1
A48: Total Bank Debt | B48: 0 | C48: - | D48: 0 | E48: 0 | F48: 32000 | G48: 0.990313 | H48: 0 | I48: 0 | J48: 0 | K48: 0 | L48: 0 | M48: 0 | N48: 0 | O48: 0
A49: Total Secured Debt | B49: 0 | C49: - | D49: 0 | E49: 0 | F49: 32000 | G49: 0.990313 | H49: 0 | I49: 0 | J49: 2007 | K49: 1 | L49: 14518 | M49: 1 | N49: 17030 | O49: 1
A50: Senior Secured Loans | B50: 0 | C50: - | D50: 0 | E50: 0 | F50: 32000 | G50: 0.990313 | H50: 0 | I50: 0 | J50: 0 | K50: 0 | L50: 0 | M50: 0 | N50: 0 | O50: 0
A51: Total Senior Secured Debt | B51: 0 | C51: - | D51: 0 | E51: 0 | F51: 32000 | G51: 0.990313 | H51: 0 | I51: 0 | J51: 2007 | K51: 1 | L51: 14518 | M51: 1 | N51: 17030 | O51: 1
A52: Total Unsecured Debt | B52: - | C52: - | D52: 313 | E52: 1 | F52: 313 | G52: 0.009686 | H52: 313 | I52: 1 | J52: - | K52: - | L52: - | M52: - | N52: - | O52: -
A53: Senior Unsecured Bonds and Notes | B53: - | C53: - | D53: 313 | E53: 1 | F53: 313 | G53: 0.009686 | H53: 313 | I53: 1 | J53: - | K53: - | L53: - | M53: - | N53: - | O53: -
A54: Fixed Rate Debt | B54: - | C54: - | D54: 313 | E54: 1 | F54: 313 | G54: 0.009686 | H54: 313 | I54: 1 | J54: - | K54: - | L54: - | M54: - | N54: - | O54: -
A55: Variable Rate Debt | B55: 0 | C55: - | D55: 0 | E55: 0 | F55: 32000 | G55: 0.990313 | H55: 0 | I55: 0 | J55: 0 | K55: 0 | L55: 0 | M55: 0 | N55: 0 | O55: 0
A57: Credit Ratios
A58: Net Debt/EBITDA | B58: NM | C58: - | D58: NM | E58: - | F58: 3.272165 | G58: - | H58: NM | I58: - | J58: NM | K58: - | L58: NM | M58: - | N58: NM | O58: -
A59: Total Debt/EBITDA | B59: - | C59: - | D59: 0.027087 | E59: - | F59: 3.567737 | G59: - | H59: 0.010235 | I59: - | J59: 0.0474 | K59: - | L59: 0.255648 | M59: - | N59: 0.299824 | O59: -
A60: Total Senior Debt/EBITDA | B60: NM | C60: - | D60: 0.027087 | E60: - | F60: 3.567737 | G60: - | H60: 0.010235 | I60: - | J60: 0.0474 | K60: - | L60: 0.255648 | M60: - | N60: 0.299824 | O60: -
A61: Total Senior Secured/EBITDA | B61: NM | C61: - | D61: NM | E61: - | F61: 3.533178 | G61: - | H61: NM | I61: - | J61: 0.0474 | K61: - | L61: 0.255648 | M61: - | N61: 0.299824 | O61: -
A62: Net Debt/(EBITDA-CAPEX) | B62: NM | C62: - | D62: NM | E62: - | F62: NM | G62: - | H62: NM | I62: - | J62: NM | K62: - | L62: NM | M62: - | N62: NM | O62: -
A63: Total Debt/(EBITDA-CAPEX) | B63: - | C63: - | D63: NM | E63: - | F63: NM | G63: - | H63: NM | I63: - | J63: NM | K63: - | L63: NM | M63: - | N63: NM | O63: -
A64: Total Senior Debt/(EBITDA-CAPEX) | B64: NM | C64: - | D64: NM | E64: - | F64: NM | G64: - | H64: NM | I64: - | J64: NM | K64: - | L64: NM | M64: - | N64: NM | O64: -
A65: Total Senior Secured/(EBITDA-CAPEX) | B65: NM | C65: - | D65: NM | E65: - | F65: NM | G65: - | H65: NM | I65: - | J65: NM | K65: - | L65: NM | M65: - | N65: NM | O65: -
A67: Fixed Payment Schedule
A68: LT Debt (Incl. Cap. Leases) Due, After 5 Yrs | B68: - | C68: - | D68: - | E68: - | F68: 313 | G68: 0.0096865039 | H68: 313 | I68: 1 | J68: - | K68: - | L68: - | M68: - | N68: - | O68: -
A70: Cap. Lease Payment Due +1 | B70: - | C70: - | D70: - | E70: - | F70: - | G70: - | H70: - | I70: - | J70: 67.499 | K70: - | L70: 1068.47 | M70: - | N70: - | O70: -
A71: Cap. Lease Payment Due +2 | B71: - | C71: - | D71: - | E71: - | F71: - | G71: - | H71: - | I71: - | J71: 163.675 | K71: - | L71: 1340.016 | M71: - | N71: - | O71: -
A72: Cap. Lease Payment Due +3 | B72: - | C72: - | D72: - | E72: - | F72: - | G72: - | H72: - | I72: - | J72: 178.013 | K72: - | L72: 1363.54 | M72: - | N72: - | O72: -
A73: Cap. Lease Payment Due +4 | B73: - | C73: - | D73: - | E73: - | F73: - | G73: - | H73: - | I73: - | J73: 181.101 | K73: - | L73: 1378.642 | M73: - | N73: - | O73: -
A74: Cap. Lease Payment Due +5 | B74: - | C74: - | D74: - | E74: - | F74: - | G74: - | H74: - | I74: - | J74: 184.189 | K74: - | L74: 1398.681 | M74: - | N74: - | O74: -
A75: Cap. Lease Payment Due, Next 5 Yrs | B75: - | C75: - | D75: - | E75: - | F75: - | G75: - | H75: - | I75: - | J75: 774.477 | K75: - | L75: 6549.349 | M75: - | N75: - | O75: -
A76: Cap. Lease Payment Due, After 5 Yrs | B76: - | C76: - | D76: - | E76: - | F76: - | G76: - | H76: - | I76: - | J76: 1232.523 | K76: - | L76: 7968.651 | M76: - | N76: 17030 | O76: -
A77: Cap. Lease Payment Due (incl. Interest) +1 | B77: - | C77: - | D77: - | E77: - | F77: - | G77: - | H77: - | I77: - | J77: - | K77: - | L77: 3679 | M77: - | N77: - | O77: -
A79: Operating Lease Commitment Due +1 | B79: - | C79: - | D79: 6464 | E79: - | F79: 10690 | G79: - | H79: 14199 | I79: - | J79: 20688 | K79: - | L79: 24123 | M79: - | N79: - | O79: -
A80: Operating Lease Commitment Due +2 | B80: - | C80: - | D80: 10349 | E80: - | F80: 13152 | G80: - | H80: 15664 | I80: - | J80: 21872 | K80: - | L80: 26045 | M80: - | N80: - | O80: -
A81: Operating Lease Commitment Due +3 | B81: - | C81: - | D81: 12729 | E81: - | F81: 14059 | G81: - | H81: 16329 | I81: - | J81: 22173 | K81: - | L81: 25817 | M81: - | N81: - | O81: -
A82: Operating Lease Commitment Due +4 | B82: - | C82: - | D82: 13595 | E82: - | F82: 14440 | G82: - | H82: 16507 | I82: - | J82: 21766 | K82: - | L82: 26076 | M82: - | N82: - | O82: -
A83: Operating Lease Commitment Due +5 | B83: - | C83: - | D83: 13973 | E83: - | F83: 14603 | G83: - | H83: 15982 | I83: - | J83: 21965 | K83: - | L83: 26506 | M83: - | N83: - | O83: -
A84: Operating Lease Commitment Due, Next 5 Yrs | B84: - | C84: - | D84: 57110 | E84: - | F84: 66944 | G84: - | H84: 78681 | I84: - | J84: 108464 | K84: - | L84: 128567 | M84: - | N84: - | O84: -
A85: Operating Lease Commitment Due, After 5 Yrs | B85: - | C85: - | D85: 109105 | E85: - | F85: 99093 | G85: - | H85: 97415 | I85: - | J85: 123372 | K85: - | L85: 143244 | M85: - | N85: - | O85: -
A87: Contractual Obligations Due +1 | B87: - | C87: - | D87: - | E87: - | F87: 42785 | G87: - | H87: 20888 | I87: - | J87: 37072 | K87: - | L87: 85948 | M87: - | N87: - | O87: -
A88: Contractual Obligations Due + 2 | B88: - | C88: - | D88: - | E88: - | F88: 891 | G88: - | H88: 13740 | I88: - | J88: 30780 | K88: - | L88: 14238 | M88: - | N88: - | O88: -
A89: Contractual Obligations Due + 3 | B89: - | C89: - | D89: - | E89: - | F89: 891 | G89: - | H89: 13740 | I89: - | J89: 30780 | K89: - | L89: 14238 | M89: - | N89: - | O89: -
A90: Contractual Obligations Due + 4 | B90: - | C90: - | D90: 1225 | E90: - | F90: 1225 | G90: - | H90: 12849 | I90: - | J90: 15824.5 | K90: - | L90: 15609 | M90: - | N90: - | O90: -
A91: Contractual Obligations Due + 5 | B91: - | C91: - | D91: 1225 | E91: - | F91: 1225 | G91: - | H91: 12849 | I91: - | J91: 15824.5 | K91: - | L91: 15609 | M91: - | N91: - | O91: -
A92: Contractual Obligations Due, Next 5 Yrs | B92: - | C92: - | D92: 2450 | E92: - | F92: 47017 | G92: - | H92: 74066 | I92: - | J92: 130281 | K92: - | L92: 145642 | M92: - | N92: - | O92: -
A93: Contractual Obligations Due, After 5 Yrs | B93: - | C93: - | D93: - | E93: - | F93: - | G93: - | H93: 175157 | I93: - | J93: 234837 | K93: - | L93: 183244 | M93: - | N93: - | O93: -
A94: Total Contractual Obligations | B94: - | C94: - | D94: 2450 | E94: - | F94: 47017 | G94: - | H94: 249223 | I94: - | J94: 365118 | K94: - | L94: 328886 | M94: - | N94: - | O94: -
A96: Interest Rate Data
A97: Filing Date | B97: 42090 | C97: - | D97: 42459 | E97: - | F97: 42807 | G97: - | H97: 43157 | I97: - | J97: 43157 | K97: - | L97: 43157 | M97: - | N97: 43227 | O97: -

Sheet Capital Structure Details
A5: Shake Shack Inc. (NYSE:SHAK) > Financials > Capital Structure Details
A7: Principal Due in Thousands of the reported currency. | B7: Period Type: | C7: Annual | E7: Source: | F7: A 2017 filed Feb-26-2018
B8: Currency: | C8: Reported Currency | E8: Conversion: | F8: Historical
B9: Units: | C9: Thousands (k) | E9: Decimals: | F9: Capital IQ (Default)
A12: FY 2017 (Dec-27-2017) Capital Structure As Reported Details
A13: Description | B13: Type | C13: Principal Due (USD) | D13: Coupon/Base Rate | E13: Floating Rate | F13: Maturity | G13: Seniority | H13: Secured | I13: Convertible | J13: Repayment Currency
A14: Deemed Landlord Financing Lease | B14: Capital Lease | C14: 14518 | D14: NA | E14: NA | F14: - | G14: Senior | H14: Yes | I14: No | J14: USD
A15: Revolving Credit Facility | B15: Revolving Credit | C15: - | D15: 0.033 | E15: Benchmark | F15: 43865 | G15: Senior | H15: Yes | I15: Exchangeable | J15: USD
A20: FY 2016 (Dec-28-2016) Capital Structure As Reported Details
A21: Description | B21: Type | C21: Principal Due (USD) | D21: Coupon/Base Rate | E21: Floating Rate | F21: Maturity | G21: Seniority | H21: Secured | I21: Convertible | J21: Repayment Currency
A22: Deemed Landlord Financing Lease | B22: Capital Lease | C22: 2007 | D22: NA | E22: NA | F22: - | G22: Senior | H22: Yes | I22: No | J22: USD
A23: Revolving Credit Facility | B23: Revolving Credit | C23: - | D23: 3.300% | E23: Benchmark | F23: 43865 | G23: Senior | H23: Yes | I23: Exchangeable | J23: USD

Sheet Ratios
A5: Shake Shack Inc. (NYSE:SHAK) > Financials > Ratios
B7: Restatement: | C7: Latest Filings | E7: Period Type: | F7: Annual
B8: Order: | C8: Latest on Right | E8: Decimals: | F8: Capital IQ (Default)
B9: Source: | C9: Capital IQ & Proprietary Data
A12: Ratios
A13: For the Fiscal Period Ending | B13: 12 months Dec-26-2012 | C13: 12 months Dec-25-2013 | D13: 12 months Dec-31-2014 | E13: 12 months Dec-30-2015 | F13: 12 months Dec-28-2016 | G13: 12 months Dec-27-2017 | H13: LTM 12 months Mar-28-2018
A14: Profitability
A15: Return on Assets % | B15: NA | C15: 0.100894 | D15: 0.029381 | E15: 0.05502 | F15: 0.037917 | G15: 0.043473 | H15: 0.043981
A16: Return on Capital % | B16: NA | C16: 0.143989 | D16: 0.049144 | E16: 0.125825 | F16: 0.096477 | G16: 0.099142 | H16: 0.098866
A17: Return on Equity % | B17: NA | C17: 0.156602 | D17: 0.084742 | E17: 0.036835 | F17: 0.123592 | G17: 0.041725 | H17: 0.044988
A18: Return on Common Equity % | B18: NA | C18: 0.156602 | D18: 0.084742 | E18: -0.155032 | F18: 0.098464 | G18: -0.001989 | H18: 0.005368
A20: Margin Analysis
A21: Gross Margin % | B21: 0.36423 | C21: 0.383271 | D21: 0.375769 | E21: 0.401664 | F21: 0.399899 | G21: 0.391672 | H21: 0.395865
A22: SG&A Margin % | B22: 0.122514 | C22: 0.126115 | D22: 0.153437 | E22: 0.127166 | F22: 0.113813 | G22: 0.10685 | H22: 0.110654
A23: EBITDA Margin % | B23: 0.12006 | C23: 0.140135 | D23: 0.076411 | E23: 0.160447 | F23: 0.157709 | G23: 0.15827 | H23: 0.158981
A24: EBITA Margin % | B24: 0.082155 | C24: 0.097191 | D24: 0.027402 | E24: 0.106814 | F24: 0.103693 | G24: 0.097781 | H24: 0.09745
A25: EBIT Margin % | B25: 0.082155 | C25: 0.097191 | D25: 0.027402 | E25: 0.106814 | F25: 0.103693 | G25: 0.097781 | H25: 0.09745
A26: Earnings from Cont. Ops Margin % | B26: 0.07246 | C26: 0.065768 | D26: 0.017868 | E26: 0.016391 | F26: 0.082488 | G26: 0.024759 | H26: 0.026237
A27: Net Income Margin % | B27: 0.07246 | C27: 0.065768 | D27: 0.017868 | E27: -0.046046 | F27: 0.046358 | G27: -0.000891 | H27: 0.002416
A28: Net Income Avail. for Common Margin % | B28: 0.07246 | C28: 0.065768 | D28: 0.017868 | E28: -0.046046 | F28: 0.046358 | G28: -0.000891 | H28: 0.002416
A29: Normalized Net Income Margin % | B29: 0.049637 | C29: 0.06035 | D29: 0.015212 | E29: 0.003256 | F29: 0.028701 | G29: 0.034179 | H29: 0.035587
A30: Levered Free Cash Flow Margin % | B30: NA | C30: -0.074291 | D30: -0.125572 | E30: 0.065943 | F30: -0.045394 | G30: -0.026074 | H30: -0.020555
A31: Unlevered Free Cash Flow Margin % | B31: NA | C31: -0.073896 | D31: -0.123648 | E31: 0.067031 | F31: -0.044524 | G31: -0.023212 | H31: -0.017432
A33: Asset Turnover
A34: Total Asset Turnover | B34: NA | C34: 1.660962 | D34: 1.715575 | E34: 0.824165 | F34: 0.585077 | G34: 0.71136 | H34: 0.722116
A35: Fixed Asset Turnover | B35: NA | C35: 2.61711 | D35: 2.19374 | E35: 2.336187 | F35: 2.341641 | G35: 2.219267 | H35: 2.215713
A36: Accounts Receivable Turnover | B36: NA | C36: 61.996992 | D36: 91.56431 | E36: 91.32343 | F36: 96.400359 | G36: 113.26073 | H36: 75.294222
A37: Inventory Turnover | B37: NA | C37: 177.18815 | D37: 172.06977 | E37: 212.75746 | F37: 238.86138 | G37: 211.50581 | H37: 221.63811
A39: Short Term Liquidity
A40: Current Ratio | B40: 3.230465 | C40: 2.110617 | D40: 0.164497 | E40: 3.288231 | F40: 2.646739 | G40: 2.739213 | H40: 2.858863
A41: Quick Ratio | B41: 3.158972 | C41: 2.026786 | D41: 0.123606 | E41: 3.138554 | F41: 2.511792 | G41: 2.651128 | H41: 2.773978
A42: Cash from Ops. to Curr. Liab. | B42: 2.097718 | C42: 1.793754 | D42: 0.28196 | E42: 1.718725 | F42: 1.711596 | G42: 2.083176 | H42: 2.401052
A43: Avg. Days Sales Out. | B43: NA | C43: 5.870956 | D43: 4.051691 | E43: 3.9858 | F43: 3.775772 | G43: 3.213756 | H43: 4.834284
A44: Avg. Days Inventory Out. | B44: NA | C44: 2.054052 | D44: 2.155881 | E44: 1.7108 | F44: 1.523704 | G44: 1.720992 | H44: 1.642004
A45: Avg. Days Payable Out. | B45: NA | C45: 12.744004 | D45: 22.086001 | E45: 21.105448 | F45: 15.458716 | G45: 12.590032 | H45: 9.789052
A46: Avg. Cash Conversion Cycle | B46: NA | C46: -4.8 | D46: -15.9 | E46: -15.4 | F46: -10.2 | G46: -7.7 | H46: -3.3
A48: Long Term Solvency
A49: Total Debt/Equity | B49: NA | C49: 0.008371 | D49: 2.564523 | E49: 0.001993 | F49: 0.009967 | G49: 0.064674 | H49: 0.073048
A50: Total Debt/Capital | B50: NA | C50: 0.008302 | D50: 0.719457 | E50: 0.001989 | F50: 0.009869 | G50: 0.060745 | H50: 0.068075
A51: LT Debt/Equity | B51: NA | C51: 0.008371 | D51: 0.024841 | E51: 0.001993 | F51: 0.009967 | G51: 0.064674 | H51: 0.073048
A52: LT Debt/Capital | B52: NA | C52: 0.008302 | D52: 0.006969 | E52: 0.001989 | F52: 0.009869 | G52: 0.060745 | H52: 0.068075
A53: Total Liabilities/Total Assets | B53: 0.276776 | C53: 0.322932 | D53: 0.848123 | E53: 0.586298 | F53: 0.625872 | G53: 0.523 | H53: 0.534008
A55: EBIT / Interest Exp. | B55: 30.038461 | C55: 154.11538 | D55: 8.89863 | E55: 61.319277 | F55: 74.435828 | G55: 21.35423 | H55: 19.499212
A56: EBITDA / Interest Exp. | B56: 43.897435 | C56: 222.21154 | D56: 24.813698 | E56: 92.108433 | F56: 113.21123 | G56: 34.564211 | H56: 31.811023
A57: (EBITDA-CAPEX) / Interest Exp. | B57: NM | C57: NM | D57: NM | E57: NM | F57: NM | G57: NM | H57: NM
A58: Total Debt/EBITDA | B58: NA | C58: 0.027087 | D58: 3.567737 | E58: 0.010235 | F58: 0.0474 | G58: 0.255648 | H58: 0.281023
A59: Net Debt/EBITDA | B59: NM | C59: NM | D59: 3.272165 | E59: NM | F59: NM | G59: NM | H59: NM
A60: Total Debt/(EBITDA-CAPEX) | B60: NA | C60: NM | D60: NM | E60: NM | F60: NM | G60: NM | H60: NM
A61: Net Debt/(EBITDA-CAPEX) | B61: NM | C61: NM | D61: NM | E61: NM | F61: NM | G61: NM | H61: NM
A63: Altman Z Score | B63: NA | C63: NA | D63: NA | E63: 2.782246 | F63: 2.259082 | G63: 3.426696 | H63: 3.383846
A65: Growth Over Prior Year
A66: Total Revenue | B66: NA | C66: 0.445632 | D66: 0.437493 | E66: 0.607964 | F66: 0.408637 | G66: 0.336474 | H66: 0.309621
A67: Gross Profit | B67: NA | C67: 0.521203 | D67: 0.409359 | E67: 0.718769 | F67: 0.402447 | G67: 0.308979 | H67: 0.24882
A68: EBITDA | B68: NA | C68: 0.687353 | D68: -0.216184 | E68: 2.376393 | F68: 0.384597 | G68: 0.341229 | H68: 0.349365
A69: EBITA | B69: NA | C69: 0.7102 | D69: -0.59471 | E69: 5.267857 | F69: 0.367472 | G69: 0.260282 | H69: 0.291316
A70: EBIT | B70: NA | C70: 0.7102 | D70: -0.59471 | E70: 5.267857 | F70: 0.367472 | G70: 0.260282 | H70: 0.291316
A71: Earnings from Cont. Ops. | B71: NA | C71: 0.312121 | D71: -0.609442 | E71: 0.474976 | F71: 6.088988 | G71: -0.598845 | H71: -0.558592
A72: Net Income | B72: NA | C72: 0.312121 | D72: -0.609442 | E72: NM | F72: NM | G72: NM | H72: -0.930496
A73: Normalized Net Income | B73: NA | C73: 0.757615 | D73: -0.637654 | E73: -0.655806 | F73: 11.415911 | G73: 0.59158 | H73: 0.585923
A74: Diluted EPS before Extra | B74: NA | C74: NA | D74: -0.609367 | E74: NM | F74: NM | G74: NM | H74: -0.93489
A76: Accounts Receivable | B76: NA | C76: -0.287187 | D76: 0.338753 | E76: 0.816464 | F76: 0.069093 | G76: 0.201528 | H76: -0.002171
A77: Inventory | B77: NA | C77: 0.362139 | D77: 0.598187 | E77: 0.026465 | F77: 0.484346 | G77: 0.560794 | H77: 0.301218
A78: Net PP&E | B78: NA | C78: 0.512981 | D78: 0.848384 | E78: 0.326806 | F78: 0.464558 | G78: 0.373033 | H78: 0.386222
A79: Total Assets | B79: NA | C79: 0.25304 | D79: 0.502417 | E79: 3.574949 | F79: 0.41799 | G79: -0.125583 | H79: -0.099264
A81: Tangible Book Value | B81: NA | C81: 0.173072 | D81: -0.681735 | E81: 7.39684 | F81: 0.516173 | G81: 0.112953 | H81: 0.13171
A82: Common Equity | B82: NA | C82: 0.173072 | D82: -0.662985 | E82: 6.985317 | F82: 0.512577 | G82: 0.113701 | H82: 0.13171
A83: Cash from Ops. | B83: NA | C83: 0.106696 | D83: 0.051067 | E83: 2.037249 | F83: 0.315744 | G83: 0.305664 | H83: 0.447788
A84: Capital Expenditures | B84: NA | C84: 0.467379 | D84: 0.760837 | E84: 0.126319 | F84: 0.694834 | G84: 0.130435 | H84: 0.237326
A85: Levered Free Cash Flow | B85: NA | C85: NA | D85: NM | E85: NM | F85: NM | G85: NM | H85: NM
A86: Unlevered Free Cash Flow | B86: NA | C86: NA | D86: NM | E86: NM | F86: NM | G86: NM | H86: NM
A87: Dividend per Share | B87: NA | C87: NA | D87: NA | E87: NA | F87: NA | G87: NA | H87: NA
A89: Compound Annual Growth Rate Over Two Years
A90: Total Revenue | B90: NA | C90: NA | D90: 0.441557 | E90: 0.520341 | F90: 0.505004 | G90: 0.372081 | H90: 0.357162
A91: Gross Profit | B91: NA | C91: NA | D91: 0.464214 | E91: 0.556395 | F91: 0.552573 | G91: 0.354908 | H91: 0.342831
A92: EBITDA | B92: NA | C92: NA | D92: 0.150033 | E92: 0.626798 | F92: 1.162163 | G92: 0.362741 | H92: 0.328422
A93: EBITA | B93: NA | C93: NA | D93: -0.167457 | E93: 0.593833 | F93: 1.927648 | G93: 0.312784 | H93: 0.265272
A94: EBIT | B94: NA | C94: NA | D94: -0.167457 | E94: 0.593833 | F94: 1.927648 | G94: 0.312784 | H94: 0.265272
A95: Earnings from Cont. Ops. | B95: NA | C95: NA | D95: -0.284137 | E95: -0.241011 | F95: 2.233588 | G95: 0.686354 | H95: -0.249059
A96: Net Income | B96: NA | C96: NA | D96: -0.284137 | E96: NM | F96: 1.424108 | G96: NM | H96: -0.585247
A97: Normalized Net Income | B97: NA | C97: NA | D97: -0.201962 | E97: -0.646847 | F97: 1.06724 | G97: 3.445326 | H97: 1.653538
A98: Diluted EPS before Extra | B98: NA | C98: NA | D98: NA | E98: NM | F98: 1.745472 | G98: NM | H98: -0.676664
A100: Accounts Receivable | B100: NA | C100: NA | D100: -0.023126 | E100: 0.559422 | F100: 0.393546 | G100: 0.133378 | H100: 0.230292
A101: Inventory | B101: NA | C101: NA | D101: 0.47545 | E101: 0.280813 | F101: 0.234354 | G101: 0.52209 | H101: 0.37554
A102: Net PP&E | B102: NA | C102: NA | D102: 0.672295 | E102: 0.566029 | F102: 0.393982 | G102: 0.418057 | H102: 0.397942
A103: Total Assets | B103: NA | C103: NA | D103: 0.372075 | E103: 1.621733 | F103: 1.547005 | G103: 0.113514 | H103: 0.088163
A105: Tangible Book Value | B105: NA | C105: NA | D105: -0.388978 | E105: 0.634756 | F105: 2.568062 | G105: 0.299012 | H105: 0.267607
A106: Common Equity | B106: NA | C106: NA | D106: -0.371237 | E106: 0.64048 | F106: 2.475401 | G106: 0.297906 | H106: 0.267607
A107: Cash from Ops. | B107: NA | C107: NA | D107: 0.078523 | E107: 0.786716 | F107: 0.999061 | G107: 0.310695 | H107: 0.342677
A108: Capital Expenditures | B108: NA | C108: NA | D108: 0.607425 | E108: 0.408284 | F108: 0.381639 | G108: 0.384161 | H108: 0.324547
A109: Levered Free Cash Flow | B109: NA | C109: NA | D109: NA | E109: NM | F109: NM | G109: NM | H109: NM
A110: Unlevered Free Cash Flow | B110: NA | C110: NA | D110: NA | E110: NM | F110: NM | G110: NM | H110: NM
A111: Dividend per Share | B111: NA | C111: NA | D111: NA | E111: NA | F111: NA | G111: NA | H111: NA
A113: Compound Annual Growth Rate Over Three Years
A114: Total Revenue | B114: NA | C114: NA | D114: NA | E114: 0.495019 | F114: 0.482156 | G114: 0.44659 | H114: 0.423515
A115: Gross Profit | B115: NA | C115: NA | D115: NA | E115: 0.544575 | F115: 0.503288 | G115: 0.466715 | H115: 0.445855
A116: EBITDA | B116: NA | C116: NA | D116: NA | E116: 0.646738 | F116: 0.54169 | G116: 0.843996 | H116: 0.785174
A117: EBITA | B117: NA | C117: NA | D117: NA | E117: 0.631715 | F117: 0.514496 | G117: 1.210558 | H117: 1.122828
A118: EBIT | B118: NA | C118: NA | D118: NA | E118: 0.631715 | F118: 0.514496 | G118: 1.210558 | H118: 1.122828
A119: Earnings from Cont. Ops. | B119: NA | C119: NA | D119: NA | E119: -0.089077 | F119: 0.598399 | G119: 0.612727 | H119: NM
A120: Net Income | B120: NA | C120: NA | D120: NA | E120: NM | F120: 0.319056 | G120: NM | H120: NM
...

Sheet Supplemental
A5: Shake Shack Inc. (NYSE:SHAK) > Financials > Supplemental
A7: In Thousands of the reported currency, except per share items. | B7: Restatement: | C7: Latest Filings | E7: Period Type: | F7: Annual
B8: Currency: | C8: Reported Currency | E8: Conversion: | F8: Historical
B9: Order: | C9: Latest on Right | E9: Units: | F9: Thousands (k)
B10: Decimals: | C10: Capital IQ (Default) | E10: Source: | F10: Capital IQ & Proprietary Data
A13: Supplemental
A14: For the Fiscal Period Ending | B14: 12 months Dec-26-2012 | C14: 12 months Dec-25-2013 | D14: 12 months Dec-31-2014 | E14: 12 months Dec-30-2015 | F14: 12 months Dec-28-2016 | G14: 12 months Dec-27-2017
A15: Currency | B15: USD | C15: USD | D15: USD | E15: USD | F15: USD | G15: USD
A16: Options Outstanding - Class A
A17: Options Out. at the Beginning of the Period | B17: - | C17: - | D17: - | E17: - | F17: 2574.981 | G17: 2364.722
A19: Options Granted During the Period | B19: - | C19: - | D19: - | E19: 2622.281 | F19: 16.931 | G19: 5.15
A20: Options Exercised During the Period | B20: - | C20: - | D20: - | E20: - | F20: 160.23 | G20: 359.011
A21: Options Cancelled During the Period | B21: - | C21: - | D21: - | E21: 47.3 | F21: 66.96 | G21: 291.52
A22: Options Out. at the End of the Period | B22: - | C22: - | D22: - | E22: 2574.981 | F22: 2364.722 | G22: 1719.341
A23: W/Avg. Strike Price of Out. at the End of the Period | B23: - | C23: - | D23: - | E23: 21 | F23: 21.1 | G23: 21.16
A24: W/Avg. Strike Price of Granted | B24: - | C24: - | D24: - | E24: 21 | F24: 34.74 | G24: 38.91
A26: Options Outstanding - All Classes
A27: Options Out. at the Beginning of the Period | B27: - | C27: - | D27: - | E27: - | F27: 2574.981 | G27: 2364.722
A28: Options Granted During the Period | B28: - | C28: - | D28: - | E28: 2622.281 | F28: 16.931 | G28: 5.15
A29: Options Exercised During the Period | B29: - | C29: - | D29: - | E29: - | F29: 160.23 | G29: 359.011
A30: Options Cancelled During the Period | B30: - | C30: - | D30: - | E30: 47.3 | F30: 66.96 | G30: 291.52
A31: Options Out. at the End of the Period | B31: - | C31: - | D31: - | E31: 2574.981 | F31: 2364.722 | G31: 1719.341
A33: Stock Based Compensation
A34: Restr. Stock Comp. Exp., Before Tax | B34: 450 | C34: 93 | D34: 165 | E34: 605 | F34: - | G34: 280
A35: Restr. Stock Comp. Exp. Tax Effect | B35: - | C35: -2 | D35: -4 | E35: - | F35: - | G35: -
A36: Restr. Stock Comp. Exp., After Tax | B36: - | C36: 91 | D36: 161 | E36: - | F36: - | G36: -
A37: Stock Options Comp. Exp., Before Tax | B37: - | C37: - | D37: - | E37: 4314 | F37: 4262 | G37: 3474
A38: Stock Based Comp. Exp., Before Tax | B38: 450 | C38: 93 | D38: 165 | E38: 16681 | F38: 5354 | G38: 5623
A39: Stock Based Comp. Exp. Tax Effect | B39: - | C39: -2 | D39: -4 | E39: -482 | F39: -168 | G39: -198
A40: Stock Based Comp. Exp., After Tax | B40: - | C40: 91 | D40: 161 | E40: 16199 | F40: 5186 | G40: 5425
A42: Loss Carry Forward Related Items
A43: NOL C/F, After Five Years | B43: - | C43: - | D43: - | E43: - | F43: 216220 | G43: 70834
A44: Total NOL C/F | B44: - | C44: - | D44: - | E44: - | F44: 216220 | G44: 70834
A45: Max. Year for NOL C/F | B45: - | C45: - | D45: - | E45: - | F45: 2036 | G45: -
A47: Tax Benefit C/F, After Five Years | B47: - | C47: - | D47: - | E47: - | F47: 1084 | G47: 2328
A48: Total Tax Benefit C/F | B48: - | C48: - | D48: - | E48: - | F48: 1084 | G48: 2328
A50: Capitalized Interest Data
A51: Interest Capitalized | B51: - | C51: - | D51: - | E51: 108 | F51: - | G51: 164
A53: Fair Value Measurements
A54: Level 1 Assets - Quoted Prices | B54: - | C54: - | D54: - | E54: 33 | F54: 65517 | G54: 66293
A55: Level 2 Assets - Observable Prices | B55: - | C55: - | D55: - | E55: 2386 | F55: 2446 | G55: 2112
A56: Fair Value of Assets | B56: - | C56: - | D56: - | E56: 2419 | F56: 67963 | G56: 68405
A59: Filing Date | B59: 42090 | C59: 42459 | D59: 42807 | E59: 43157 | F59: 43157 | G59: 43157

Sheet Segments
A5: Shake Shack Inc. (NYSE:SHAK) > Financials > Segments
A7: In Thousands of the reported currency. | B7: View By: | C7: Line Items | E7: Restatement: | F7: Latest Filings
B8: Period Type: | C8: Annual | E8: Order: | F8: Latest on Right
B9: Currency: | C9: Reported Currency | E9: Conversion: | F9: Historical
B10: Units: | C10: Thousands (k) | E10: Decimals: | F10: Capital IQ (Default)
A13: Business Segments
A14: For the Fiscal Period Ending | B14: 12 months Dec-26-2012 | C14: Reclassified 12 months Dec-25-2013 | D14: 12 months Dec-31-2014 | E14: Reclassified 12 months Dec-30-2015 | F14: 12 months Dec-28-2016 | G14: 12 months Dec-27-2017
A15: Currency | B15: USD | C15: USD | D15: USD | E15: USD | F15: USD | G15: USD
A16: Revenues
A17: Operates and Licenses Restaurants | B17: 57038 | C17: 82456 | D17: 118530 | E17: 190592 | F17: 268475 | G17: 358810
A18: Total Revenues | B18: 57038 | C18: 82456 | D18: 118530 | E18: 190592 | F18: 268475 | G18: 358810
A20: Operating Profit Before Tax
A21: Operates and Licenses Restaurants | B21: 4686 | C21: 5935 | D21: 3143 | E21: 6753 | F21: 27805 | G21: 33813
A22: Total Operating Profit Before Tax | B22: 4686 | C22: 5935 | D22: 3143 | E22: 6753 | F22: 27805 | G22: 33813
A24: Interest Expense
A25: Operates and Licenses Restaurants | B25: -156 | C25: -52 | D25: -365 | E25: -332 | F25: -374 | G25: -1643
A26: Total Interest Expense | B26: -156 | C26: -52 | D26: -365 | E26: -332 | F26: -374 | G26: -1643
A28: Net Profit Before Tax
A29: Operates and Licenses Restaurants | B29: 4530 | C29: 5883 | D29: 2780 | E29: 6428 | F29: 28496 | G29: 160293
A30: Total Net Profit Before Tax | B30: 4530 | C30: 5883 | D30: 2780 | E30: 6428 | F30: 28496 | G30: 160293
A32: Tax Expense
A33: Operates and Licenses Restaurants | B33: 397 | C33: 460 | D33: 662 | E33: 3304 | F33: 6350 | G33: 151409
A34: Total Tax Expense | B34: 397 | C34: 460 | D34: 662 | E34: 3304 | F34: 6350 | G34: 151409
A36: Net Profit After Tax
A37: Operates and Licenses Restaurants | B37: 4133 | C37: 5423 | D37: 2118 | E37: -8776 | F37: 12446 | G37: -320
A38: Total Net Profit After Tax | B38: 4133 | C38: 5423 | D38: 2118 | E38: -8776 | F38: 12446 | G38: -320
A40: Assets
A41: Operates and Licenses Restaurants | B41: 44068 | C41: 55219 | D41: 82962 | E41: 379547 | F41: 538194 | G41: 470606
A42: Total Assets | B42: 44068 | C42: 55219 | D42: 82962 | E42: 379547 | F42: 538194 | G42: 470606
A44: Depreciation & Amortization
A45: Operates and Licenses Restaurants | B45: 2162 | C45: 3541 | D45: 5809 | E45: 10222 | F45: 14502 | G45: 21704
A46: Total Depreciation & Amortization | B46: 2162 | C46: 3541 | D46: 5809 | E46: 10222 | F46: 14502 | G46: 21704
A48: Capital Expenditure
A49: Operates and Licenses Restaurants | B49: -11036 | C49: -16194 | D49: -28515 | E49: -32117 | F49: -54433 | G49: -61533
A50: Total Capital Expenditure | B50: -11036 | C50: -16194 | D50: -28515 | E50: -32117 | F50: -54433 | G50: -61533
A53: Filing Date | B53: 42090 | C53: 42459 | D53: 42807 | E53: 43157 | F53: 43157 | G53: 43157
A56: Geographic Segments
A57: For the Fiscal Period Ending | B57: 12 months Dec-26-2012 | C57: Reclassified 12 months Dec-25-2013 | D57: 12 months Dec-31-2014 | E57: Reclassified 12 months Dec-30-2015 | F57: 12 months Dec-28-2016 | G57: 12 months Dec-27-2017
A58: Currency | B58: USD | C58: USD | D58: USD | E58: USD | F58: USD | G58: USD
A59: Revenues
A60: United States | B60: 55804 | C60: 78937 | D60: 112743 | E60: 184408 | F60: 260602 | G60: 348575
A61: Other Countries | B61: 1234 | C61: 3519 | D61: 5787 | E61: 6184 | F61: 7873 | G61: 10235
A62: Total Revenues | B62: 57038 | C62: 82456 | D62: 118530 | E62: 190592 | F62: 268475 | G62: 358810
A64: Assets
A65: United States | B65: - | C65: 55219 | D65: 82962 | E65: 379547 | F65: 538194 | G65: 470606
A66: Total Assets | B66: - | C66: 55219 | D66: 82962 | E66: 379547 | F66: 538194 | G66: 470606
A69: Filing Date | B69: 42090 | C69: 42459 | D69: 42807 | E69: 43157 | F69: 43157 | G69: 43157

Sheet WACC
A1: Ticker | B1: NYSE:SHAK | D1: Currency | E1: USD | G1: Date | H1: 43291 | J1: Conversion | K1: Historical | M1: Index | N1: ^SPX | P1: Filing | Q1: Latest Fully Reported | AJ1: =_xll.ciqfunctions.udf.CIQ("3602","iq_ev_over_ltm_ebitda") -> #CIQINACTIVE
A3: WACC ANALYSIS
A4: Shake Shack Inc. (NYSE:SHAK)
A5: (USD in millions)
A7: ASSUMPTIONS | J7: BETA CALCULATION
L8: 5Yr Avg | M8: Levered | N8: Total | O8: Mkt. Val. | P8: Pref | Q8: Debt/ | R8: Pref/ | S8: Unlevered | U8: Capital IQ Inputs: | AX8: =MATCH($C$22,$AX$12:$AX$123,0) -> 102 | AY8: =COUNTIF($AX$12:$AX$123,$C$22) -> 11
A9: Tax Rate (5 Year Average) | H9: 0.21 | J9: Ticker | K9: Name | L9: Tax Rate | M9: Beta | N9: Debt | O9: Equity | P9: Equity | Q9: Equity | R9: Equity | S9: Beta(2) | U9: Total Debt | Z9: 51.114 | BK9: =AVERAGEIF(BK11:BK15,">0",BK11:BK15) -> #DIV/0! | BS9: =IF(ISERROR(AVERAGEIF(BS11:BS511,">0",BS11:BS511)),0,AVERAGEIF(BS11:BS511,">0",BS11:BS511)) -> 0
A10: Risk-Free Rate of Return (Rf)(1) | H10: 0.0287 | J10: ZOES | K10: Zoe's Kitchen, Inc. | L10: 0.3753025 | M10: 0.14797 | N10: 47.634 | O10: 195.64016 | P10: 0 | Q10: 0.24347762 | R10: 0 | S10: 0.12843505 | T10: 1 | U10: Total Preferred | Z10: 0 | BF10: =_xll.ciqfunctions.udf.CIQRANGE($B$1,"iq_bond_list",1,500,,,,,"Bonds") -> #CIQINACTIVE | BG10: Issue Date | BK10: Coupon | BN10: =_xll.ciqfunctions.udf.CIQRANGE($B$1,"iq_fixed_income_list",1,500,,,,,"Fixed Income") -> #CIQINACTIVE | BR10: Preferred | BS10: Coupon
A11: S&P 500 Market Return (Rm) - Yearly for Last 10 Years | H11: 0.08037375 | J11: CMG | K11: Chipotle Mexican Grill, Inc. | L11: 0.3829536 | M11: 0.4133 | N11: 0 | O11: 12624.019 | P11: 0 | Q11: 0 | R11: 0 | S11: 0.4133 | T11: =T10+1 -> 2 | U11: Market Cap | Z11: 1771.5913 | AT11: Country | AV11: CIQ ID | AX11: Country | AY11: Gov.Bond Id | AZ11: Name | BG11: =IF($BF11="","",_xll.ciqfunctions.udf.CIQ($BF11,"iq_offer_date")) | BH11: =IF($BF11="","",RANK(BG11,$BG$11:$BG$511)+COUNTIF($BG$11:BG11,BG11)-1) | BI11: 1 | BJ11: =IF(INDEX($BF$11:$BF$511,MATCH(BI11,$BH$11:$BH$511,0))=0,"NA",INDEX($BF$11:$BF$511,MATCH(BI11,$BH$11:$BH$511,0))) -> #N/A | BK11: =IF($BJ11="NA","NA",_xll.ciqfunctions.udf.CIQ($BJ11,"iq_bond_coupon")/100) -> #N/A | BM11: 1 | BO11: =IF($BN11="","",_xll.ciqfunctions.udf.CIQ($BN11,"iq_security_level")) | BP11: =IF(BN11="","",IF(BO11="Preferred",1,0)) | BR11: =IF($BN11="","",IF(ISERROR(INDEX($BN$11:$BN$510,MATCH(BM11,$BP$11:$BP$510,0))),"",INDEX($BN$11:$BN$510,MATCH(BM11,$BP$11:$BP$510,0)))) | BS11: =IF($BR11="","",_xll.ciqfunctions.udf.CIQ($BR11,"iq_bond_coupon")/100)
A12: Size Premium | H12: 0 | J12: NDLS | K12: Noodles & Company | L12: 0.400461 | M12: -0.62773 | N12: 62.871 | O12: 489.81043 | P12: 0 | Q12: 0.12835782 | R12: 0 | S12: -0.58287458 | T12: =T11+1 -> 3 | U12: EBT | Z12: 160.95 | AS12: 1 | AT12: Australia | AU12: AU | AV12: IQ25104817 | AX12: Australia | AY12: IQ50027528 | AZ12: Australia Government Debt - 2 Year | BG12: =IF($BF12="","",_xll.ciqfunctions.udf.CIQ($BF12,"iq_offer_date")) | BH12: =IF($BF12="","",RANK(BG12,$BG$11:$BG$511)+COUNTIF($BG$11:BG12,BG12)-1) | BI12: =BI11+1 -> 2 | BJ12: =IF(INDEX($BF$11:$BF$511,MATCH(BI12,$BH$11:$BH$511,0))=0,"NA",INDEX($BF$11:$BF$511,MATCH(BI12,$BH$11:$BH$511,0))) -> #N/A | BK12: =IF($BJ12="NA","NA",_xll.ciqfunctions.udf.CIQ($BJ12,"iq_bond_coupon")/100) -> #N/A | BM12: =BM11+1 -> 2 | BO12: =IF($BN12="","",_xll.ciqfunctions.udf.CIQ($BN12,"iq_security_level")) | BP12: =IF(BN12="","",IF(BO12="Preferred",BP11+1,BP11)) | BR12: =IF($BN12="","",IF(ISERROR(INDEX($BN$11:$BN$510,MATCH(BM12,$BP$11:$BP$510,0))),"",INDEX($BN$11:$BN$510,MATCH(BM12,$BP$11:$BP$510,0)))) | BS12: =IF($BR12="","",_xll.ciqfunctions.udf.CIQ($BR12,"iq_bond_coupon")/100)
A13: NYSE:SHAK D/(D+P+E) | H13: 0.028042932 | J13: HABT | K13: The Habit Restaurants, Inc. | L13: 0.3894688 | M13: 0.52329 | N13: 17.221 | O13: 215.29553 | P13: 0 | Q13: 0.079987727 | R13: 0 | S13: 0.498925 | T13: =T12+1 -> 4 | U13: Taxes | Z13: 150.949 | AS13: =AS12+1 -> 2 | AT13: Canada | AU13: CA | AV13: IQ4080736 | AX13: Australia | AY13: IQ100893239 | AZ13: Australia Government Debt - 3 Year | BG13: =IF($BF13="","",_xll.ciqfunctions.udf.CIQ($BF13,"iq_offer_date")) | BH13: =IF($BF13="","",RANK(BG13,$BG$11:$BG$511)+COUNTIF($BG$11:BG13,BG13)-1) | BI13: =BI12+1 -> 3 | BJ13: =IF(INDEX($BF$11:$BF$511,MATCH(BI13,$BH$11:$BH$511,0))=0,"NA",INDEX($BF$11:$BF$511,MATCH(BI13,$BH$11:$BH$511,0))) -> #N/A | BK13: =IF($BJ13="NA","NA",_xll.ciqfunctions.udf.CIQ($BJ13,"iq_bond_coupon")/100) -> #N/A | BM13: =BM12+1 -> 3 | BO13: =IF($BN13="","",_xll.ciqfunctions.udf.CIQ($BN13,"iq_security_level")) | BP13: =IF(BN13="","",IF(BO13="Preferred",BP12+1,BP12)) | BR13: =IF($BN13="","",IF(ISERROR(INDEX($BN$11:$BN$510,MATCH(BM13,$BP$11:$BP$510,0))),"",INDEX($BN$11:$BN$510,MATCH(BM13,$BP$11:$BP$510,0)))) | BS13: =IF($BR13="","",_xll.ciqfunctions.udf.CIQ($BR13,"iq_bond_coupon")/100)
A14: NYSE:SHAK D/E | H14: 0.028852027 | J14: WEN | K14: The Wendy's Company | L14: 0.3518153 | M14: 0.56057 | N14: 2808.021 | O14: 4188.6275 | P14: 0 | Q14: 0.67039167 | R14: 0 | S14: 0.39076703 | T14: =T13+1 -> 5 | U14: Latest FYE | Z14: 43096 | AS14: =AS13+1 -> 3 | AT14: China | AU14: CN | AV14: IQ28461984 | AX14: Australia | AY14: IQ50027529 | AZ14: Australia Government Debt - 5 Year | BG14: =IF($BF14="","",_xll.ciqfunctions.udf.CIQ($BF14,"iq_offer_date")) | BH14: =IF($BF14="","",RANK(BG14,$BG$11:$BG$511)+COUNTIF($BG$11:BG14,BG14)-1) | BI14: =BI13+1 -> 4 | BJ14: =IF(INDEX($BF$11:$BF$511,MATCH(BI14,$BH$11:$BH$511,0))=0,"NA",INDEX($BF$11:$BF$511,MATCH(BI14,$BH$11:$BH$511,0))) -> #N/A | BK14: =IF($BJ14="NA","NA",_xll.ciqfunctions.udf.CIQ($BJ14,"iq_bond_coupon")/100) -> #N/A | BM14: =BM13+1 -> 4 | BO14: =IF($BN14="","",_xll.ciqfunctions.udf.CIQ($BN14,"iq_security_level")) | BP14: =IF(BN14="","",IF(BO14="Preferred",BP13+1,BP13)) | BR14: =IF($BN14="","",IF(ISERROR(INDEX($BN$11:$BN$510,MATCH(BM14,$BP$11:$BP$510,0))),"",INDEX($BN$11:$BN$510,MATCH(BM14,$BP$11:$BP$510,0)))) | BS14: =IF($BR14="","",_xll.ciqfunctions.udf.CIQ($BR14,"iq_bond_coupon")/100)
A15: NYSE:SHAK P/E | H15: 0 | J15: MCD | K15: McDonald's Corporation | L15: 0.3389388 | M15: 0.68144 | N15: 30888 | O15: 126115.19 | P15: 0 | Q15: 0.24491894 | R15: 0 | S15: 0.58648441 | T15: =T14+1 -> 6 | U15: Latest FQE | Z15: 43187 | AS15: =AS14+1 -> 4 | AT15: Denmark | AU15: DK | AV15: IQ35414816 | AX15: Australia | AY15: IQ100893231 | AZ15: Australia Government Debt - 7 Year | BG15: =IF($BF15="","",_xll.ciqfunctions.udf.CIQ($BF15,"iq_offer_date")) | BH15: =IF($BF15="","",RANK(BG15,$BG$11:$BG$511)+COUNTIF($BG$11:BG15,BG15)-1) | BI15: =BI14+1 -> 5 | BJ15: =IF(INDEX($BF$11:$BF$511,MATCH(BI15,$BH$11:$BH$511,0))=0,"NA",INDEX($BF$11:$BF$511,MATCH(BI15,$BH$11:$BH$511,0))) -> #N/A | BK15: =IF($BJ15="NA","NA",_xll.ciqfunctions.udf.CIQ($BJ15,"iq_bond_coupon")/100) -> #N/A | BM15: =BM14+1 -> 5 | BO15: =IF($BN15="","",_xll.ciqfunctions.udf.CIQ($BN15,"iq_security_level")) | BP15: =IF(BN15="","",IF(BO15="Preferred",BP14+1,BP14)) | BR15: =IF($BN15="","",IF(ISERROR(INDEX($BN$11:$BN$510,MATCH(BM15,$BP$11:$BP$510,0))),"",INDEX($BN$11:$BN$510,MATCH(BM15,$BP$11:$BP$510,0)))) | BS15: =IF($BR15="","",_xll.ciqfunctions.udf.CIQ($BR15,"iq_bond_coupon")/100)
A16: Choice for Cost of Debt | G16: Corp Yield Curve | U16: Today | Z16: 43291 | AS16: =AS15+1 -> 5 | AT16: France | AU16: FR | AV16: IQ3474783 | AX16: Australia | AY16: IQ50027527 | AZ16: Australia Government Debt - 10 Year | BG16: =IF($BF16="","",_xll.ciqfunctions.udf.CIQ($BF16,"iq_offer_date")) | BH16: =IF($BF16="","",RANK(BG16,$BG$11:$BG$511)+COUNTIF($BG$11:BG16,BG16)-1) | BM16: =BM15+1 -> 6 | BO16: =IF($BN16="","",_xll.ciqfunctions.udf.CIQ($BN16,"iq_security_level")) | BP16: =IF(BN16="","",IF(BO16="Preferred",BP15+1,BP15)) | BR16: =IF($BN16="","",IF(ISERROR(INDEX($BN$11:$BN$510,MATCH(BM16,$BP$11:$BP$510,0))),"",INDEX($BN$11:$BN$510,MATCH(BM16,$BP$11:$BP$510,0)))) | BS16: =IF($BR16="","",_xll.ciqfunctions.udf.CIQ($BR16,"iq_bond_coupon")/100)
A17: NYSE:SHAK Cost of Debt (Rd) - Average of Last 5 Issued Bonds | H17: 0 | J17: Average | M17: 0.28314 | S17: 0.23917282 | U17: Days Remaining in FY | AS17: =AS16+1 -> 6 | AT17: Germany | AU17: DE | AV17: IQ8201718 | AX17: Australia | AY17: IQ100893243 | AZ17: Australia Government Debt - 15 Year | BG17: =IF($BF17="","",_xll.ciqfunctions.udf.CIQ($BF17,"iq_offer_date")) | BH17: =IF($BF17="","",RANK(BG17,$BG$11:$BG$511)+COUNTIF($BG$11:BG17,BG17)-1) | BM17: =BM16+1 -> 7 | BO17: =IF($BN17="","",_xll.ciqfunctions.udf.CIQ($BN17,"iq_security_level")) | BP17: =IF(BN17="","",IF(BO17="Preferred",BP16+1,BP16)) | BR17: =IF($BN17="","",IF(ISERROR(INDEX($BN$11:$BN$510,MATCH(BM17,$BP$11:$BP$510,0))),"",INDEX($BN$11:$BN$510,MATCH(BM17,$BP$11:$BP$510,0)))) | BS17: =IF($BR17="","",_xll.ciqfunctions.udf.CIQ($BR17,"iq_bond_coupon")/100)
A18: Comparable Corporate Yield Curve Rate | H18: 0.03826 | AS18: =AS17+1 -> 7 | AT18: Hong Kong | AU18: HK | AV18: IQ22453044 | AX18: Canada | AY18: IQ50027538 | AZ18: Canada Government Debt - 2 Year | BG18: =IF($BF18="","",_xll.ciqfunctions.udf.CIQ($BF18,"iq_offer_date")) | BH18: =IF($BF18="","",RANK(BG18,$BG$11:$BG$511)+COUNTIF($BG$11:BG18,BG18)-1) | BM18: =BM17+1 -> 8 | BO18: =IF($BN18="","",_xll.ciqfunctions.udf.CIQ($BN18,"iq_security_level")) | BP18: =IF(BN18="","",IF(BO18="Preferred",BP17+1,BP17)) | BR18: =IF($BN18="","",IF(ISERROR(INDEX($BN$11:$BN$510,MATCH(BM18,$BP$11:$BP$510,0))),"",INDEX($BN$11:$BN$510,MATCH(BM18,$BP$11:$BP$510,0)))) | BS18: =IF($BR18="","",_xll.ciqfunctions.udf.CIQ($BR18,"iq_bond_coupon")/100)
A19: NYSE:SHAK Cost of Preferred (Rp) | H19: 0 | J19: Average Unlevered Beta for Comps | S19: 0.23917282 | U19: Beta Selection | Z19: 2 | AS19: =AS18+1 -> 8 | AT19: Italy | AU19: IT | AV19: IQ3534701 | AX19: Canada | AY19: IQ100893055 | AZ19: Canada Government Debt - 3 Year | BG19: =IF($BF19="","",_xll.ciqfunctions.udf.CIQ($BF19,"iq_offer_date")) | BH19: =IF($BF19="","",RANK(BG19,$BG$11:$BG$511)+COUNTIF($BG$11:BG19,BG19)-1) | BM19: =BM18+1 -> 9 | BO19: =IF($BN19="","",_xll.ciqfunctions.udf.CIQ($BN19,"iq_security_level")) | BP19: =IF(BN19="","",IF(BO19="Preferred",BP18+1,BP18)) | BR19: =IF($BN19="","",IF(ISERROR(INDEX($BN$11:$BN$510,MATCH(BM19,$BP$11:$BP$510,0))),"",INDEX($BN$11:$BN$510,MATCH(BM19,$BP$11:$BP$510,0)))) | BS19: =IF($BR19="","",_xll.ciqfunctions.udf.CIQ($BR19,"iq_bond_coupon")/100)
