Workbook
Name _toc1: 하이트진로_DART!#REF!
Name Case_Financing: #REF!
Name Case_Operating: #REF!
Name Circ: Cover!$K$6
Name Circ: #REF!
Name Circ_LBO: #REF!
Name Date: [1]WACC!$H$1
Name Days: #REF!
Name GVKey: ""
Name IQ_CH: 110000
Name IQ_CQ: 5000
Name IQ_CY: 10000
Name IQ_DAILY: 500000
Name IQ_FH: 100000
Name IQ_FQ: 500
Name IQ_FY: 1000
Name IQ_LTM: 2000
Name IQ_MONTH: 15000
Name IQ_NTM: 6000
Name IQ_WEEK: 50000
Name IQ_YTD: 3000
Name List: '[1]Input Tab'!$AD$15:$AD$19
Name SPSet: "current"
Name SPWS_WBID: "D37EBD5C-BA90-4B94-B2F1-78539D014FA9"

Sheet Cover
B2: 가치평가 시트 구성하기 | K2: OB맥주 가치평가 실습
D6: Latest update: | F6: =TODAY() -> 45831
C29: © 2021 Wall Street Training Asia Inc.
C30: No portion of this report may be reproduced, reused, or otherwise distributed in any form without prior written consent.
C31: For more information, please visit/contatct Wall Street Training Asia Inc. through www.wallstreettraining.co.kr
C33: © 2021 (주)월스트릿트레이닝아시아.
C34: 이 파일은 대한민국 및 미국 저작권법의 보호를 받는 저작물 입니다.
C35: 파일의 원 저자로부터 서면에 의한 허락없이 이 파일의 일부나 전체를 어떠한 형태로도 가공/배포할 수 없습니다.
C36: 이를 위반시에는 형사/민사상의 법적 책임을 질수 있으며, 특별한 문의가 있는경우 www.wallstreettraining.co.kr에 있는 정보로 연락주시기 바랍니다.

Sheet Trading Comps >>>
A1: OB맥주 – Trading Comps >>>
B84: =IFERROR((B79+B82)/(B66+B83),0) -> 0 | C84: =IFERROR((C79+C82)/(C66+C83),0) -> 0 | D84: =IFERROR((D79+D82)/(D66+D83),0) -> 0 | F84: =IFERROR((F79+F82)/(F66+F83),0) -> 0 | G84: =IFERROR((G79+G82)/(G66+G83),0) -> 0 | H84: =IFERROR((H79+H82)/(H66+H83),0) -> 0 | I84: =IFERROR((I79+I82)/(I66+I83),0) -> 0

Sheet Trading Comps_Input
A1: OB맥주
A2: Comparable Company Analysis ("Trading Comps") - Input
A4: x | B4: Market Data Inputs
B5: (Reported currencies in millions, except per share data)
C6: Korea | E6: Asia | G6: Other Markets
C7: Korea | D7: Korea | E7: Japan | F7: China | G7: Denmark | H7: Netherlands | I7: Canada | J7: USA
C8: KRW | D8: KRW | E8: JPY | F8: CNY | G8: DKK | H8: EUR | I8: USD | J8: USD
B9: Company Name | C9: Oriental Brewery | D9: Hite Brewery | E9: ASAHI GROUP | F9: TSINGTAO BREWERY | G9: CARLSBERG | H9: HEINEKEN | I9: MOLSON COORS | J9: BOSTON BEER
B10: Ticker | C10: OB | D10: KRX: 103150 | E10: TYO: 2502 | F10: SEHK:168 | G10: CPSE:CARL B | H10: ENXTAM:HEIA | I10: NYSE: TAP | J10: NYSE: SAM
B11: Date of latest quarter | C11: 40178 | D11: 40178 | E11: 40178 | F11: 40178 | G11: 40178 | H11: 40178 | I11: 40178 | J11: 40178
B12: Date of latest fiscal year end | C12: 40178 | D12: 40178 | E12: 40178 | F12: 40178 | G12: 40178 | H12: 40178 | I12: 40178 | J12: 40178
B13: Latest quarter | C13: Q4 | D13: Q4 | E13: Q4 | F13: Q4 | G13: Q4 | H13: Q4 | I13: Q4 | J13: Q4
B14: Stock price on current date | D14: 170000 | E14: 1732 | F14: 16.48 | G14: 396.1 | H14: 35.81 | I14: =45.92/2 -> 22.96 | J14: 47.53
B15: Preferred stock price on current date | D15: 68700
B16: Corporate tax rate (marginal tax rate) | C16: 0.242 | D16: 0.242 | E16: 0.4069 | F16: 0.25 | G16: 0.25 | H16: 0.255 | I16: 0.392 | J16: 0.392
B17: Currency conversion rate to KRW on the date below | C17: 1 | D17: 1 | E17: 12.68258 | F17: 170.70285 | G17: 224.05884 | H17: 1680.3066 | I17: 1171.5775 | J17: 1171.5775
B18: Share price date | C18: 40179 | D18: 40182 | E18: 40182 | F18: 40180 | G18: 40182 | H18: 40182 | I18: 40182 | J18: 40182
B19: Market Capitalization in USD
A21: x | B21: Shares Data
B23: Basic shares outstanding | C23: 20.11 | D23: 41.973814 | E23: 464.87462 | F23: 1315.3464 | G23: 152.55 | H23: 488.66661 | I23: 184.4 | J23: 14.059
B24: Options exercisable
B25: 1 | E25: 0.018 | G25: 0.024715 | H25: 0.032265 | I25: 7.4 | J25: 2.159604
B26: =B25+1 -> 2 | E26: 0.1966 | G26: 0.038436 | H26: 0.2814
B27: =B26+1 -> 3 | E27: 0.33 | G27: 0.045202 | H27: 0.026288
B28: =B27+1 -> 4 | E28: 0.133 | G28: 0.04429 | H28: 0.263958
B29: =B28+1 -> 5 | E29: 0.5179 | G29: 0.061938 | H29: 0.053083
B30: =B29+1 -> 6 | E30: 0.5875 | G30: 0.064416 | H30: 0.562862
B31: =B30+1 -> 7 | E31: 0.62 | G31: 0.099718
B32: =B31+1 -> 8 | G32: 0.025514
B33: =B32+1 -> 9
B34: =B33+1 -> 10
C35: =SUM(C25:C34) -> 0 | D35: =SUM(D25:D34) -> 0 | E35: =SUM(E25:E34) -> 2.403 | F35: =SUM(F25:F34) -> 0 | G35: =SUM(G25:G34) -> 0.404229 | H35: =SUM(H25:H34) -> 1.219856 | I35: =SUM(I25:I34) -> 7.4 | J35: =SUM(J25:J34) -> 2.159604
B36: Exercise price
B37: 1 | E37: 1115 | G37: 261.39 | H37: 36.03 | I37: 37 | J37: 30.23
B38: =B37+1 -> 2 | E38: 1185 | G38: 173.12 | H38: 36.03
B39: =B38+1 -> 3 | E39: 1090 | G39: 216.65 | H39: 44.22
B40: =B39+1 -> 4 | E40: 830 | G40: 232.71 | H40: 44.22
B41: =B40+1 -> 5 | E41: 1205 | G41: 306.89 | H41: 21.9
B42: =B41+1 -> 6 | E42: 1374 | G42: 472.11 | H42: 21.9
B43: =B42+1 -> 7 | E43: 1688 | G43: 446.9
B44: =B43+1 -> 8 | G44: 268.9
B45: =B44+1 -> 9
B46: =B45+1 -> 10
B48: Gross proceeds from exercise of options | C48: =SUMPRODUCT((C37:C46<C14)*(C37:C46),C25:C34) -> 0 | D48: =SUMPRODUCT((D37:D46<D14)*(D37:D46),D25:D34) -> 0 | E48: =SUMPRODUCT((E37:E46<E14)*(E37:E46),E25:E34) -> 3200.9855 | F48: =SUMPRODUCT((F37:F46<F14)*(F37:F46),F25:F34) -> 0 | G48: =SUMPRODUCT((G37:G46<G14)*(G37:G46),G25:G34) -> 59.082901 | H48: =SUMPRODUCT((H37:H46<H14)*(H37:H46),H25:H34) -> 13.489195 | I48: =SUMPRODUCT((I37:I46<I14)*(I37:I46),I25:I34) -> 0 | J48: =SUMPRODUCT((J37:J46<J14)*(J37:J46),J25:J34) -> 65.284829
B49: Gross dilution | C49: =SUMIF(C37:C46,"<"&C14,C25:C34) -> 0 | D49: =SUMIF(D37:D46,"<"&D14,D25:D34) -> 0 | E49: =SUMIF(E37:E46,"<"&E14,E25:E34) -> 2.403 | F49: =SUMIF(F37:F46,"<"&F14,F25:F34) -> 0 | G49: =SUMIF(G37:G46,"<"&G14,G25:G34) -> 0.240095 | H49: =SUMIF(H37:H46,"<"&H14,G25:G34) -> 0.126354 | I49: =SUMIF(I37:I46,"<"&I14,I25:I34) -> 0 | J49: =SUMIF(J37:J46,"<"&J14,J25:J34) -> 2.159604
B50: Dilution from exercisable options | C50: =IFERROR(C49-C48/C14,0) -> 0 | D50: =IFERROR(D49-D48/D14,0) -> 0 | E50: =IFERROR(E49-E48/E14,0) -> 0.55485595 | F50: =IFERROR(F49-F48/F14,0) -> 0 | G50: =IFERROR(G49-G48/G14,0) -> 0.090933423 | H50: =IFERROR(H49-H48/H14,0) -> -0.25033395 | I50: =IFERROR(I49-I48/I14,0) -> 0 | J50: =IFERROR(J49-J48/J14,0) -> 0.78605405
B51: Dilution from convertible debt
B52: Dilution from convertible preferred stock / other
B53: Diluted common shares outstanding | C53: =OB맥주_DART!D254/10^6 -> 20.611 | D53: =+하이트진로_DART!C275/10^6 -> 9.557852 | E53: =E23+SUM(E50:E52) -> 465.42948 | F53: =F23+SUM(F50:F52) -> 1315.3464 | G53: =G23+SUM(G50:G52) -> 152.64093 | H53: =H23+SUM(H50:H52) -> 488.41627 | I53: =I23+SUM(I50:I52) -> 184.4 | J53: =J23+SUM(J50:J52) -> 14.845054
B54: Preferred shares outstanding (non-dilutive) | D54: =+하이트진로_DART!D275/10^6 -> 0.372545
A56: x | B56: Financials
B58: Latest Fiscal Year
C59: =C12 -> 40178 | D59: =D12 -> 40178 | E59: =E12 -> 40178 | F59: =F12 -> 40178 | G59: =G12 -> 40178 | H59: =H12 -> 40178 | I59: =I12 -> 40178 | J59: =J12 -> 40178
B60: Revenues | C60: =OB맥주_DART!F113 -> 816110.19 | D60: =+하이트진로_DART!D96/10^6 -> 1049536 | E60: 1022318 | F60: 18026.108 | G60: 59382 | H60: 14701 | I60: 3032.4 | J60: 415.053
B61: COGS (enter as -) | C61: =-OB맥주_DART!F117 -> -346672.53 | D61: =-하이트진로_DART!D101/10^6 -> -516464.51 | E61: -508293 | F61: -10311.587 | G61: -30187 | H61: -9466 | I61: -1726.9 | J61: -201.235
B62: Gross Profit | C62: =(SUM(C60:C61)) -> 469437.65 | D62: =(SUM(D60:D61)) -> 533071.44 | E62: =SUM(E60:E61) -> 514025 | F62: =SUM(F60:F61) -> 7714.5205 | G62: =SUM(G60:G61) -> 29195 | H62: =SUM(H60:H61) -> 5235 | I62: =SUM(I60:I61) -> 1305.5 | J62: =SUM(J60:J61) -> 213.818
B63: SG&A/Other operating expenses (enter as -) | C63: =-OB맥주_DART!F126 -> -273132 | D63: =-하이트진로_DART!D110/10^6 -> -346124.49 | E63: -431248 | F63: -6003.3946 | G63: -20172 | H63: -3458 | I63: -900.8 | J63: -158.498
B64: Operating income (EBIT) | C64: =(SUM(C62:C63)) -> 196305.66 | D64: =(SUM(D62:D63)) -> 186946.95 | E64: =SUM(E62:E63) -> 82777 | F64: =SUM(F62:F63) -> 1711.1258 | G64: =SUM(G62:G63) -> 9023 | H64: =SUM(H62:H63) -> 1777 | I64: =SUM(I62:I63) -> 404.7 | J64: =SUM(J62:J63) -> 55.32
B65: Nonoperating income / (expense) | C65: =OB맥주_DART!G138 -> -18738.184 | D65: =(+하이트진로_DART!D138-하이트진로_DART!D145)/(10^6) -> -57875.339 | E65: 5301 | F65: 28.178223 | G65: -3318 | H65: -349 | I65: 312.8 | J65: -0.888
B66: Pretax income | C66: =C64+C65 -> 177567.47 | D66: =D64+D65 -> 129071.61 | E66: =E64+E65 -> 88078 | F66: =F64+F65 -> 1739.304 | G66: =SUM(G64:G65) -> 5705 | H66: =SUM(H64:H65) -> 1428 | I66: =SUM(I64:I65) -> 717.5 | J66: =SUM(J64:J65) -> 54.432
B67: Tax benefit / (expense) | C67: =-OB맥주_DART!F151 -> -50768.022 | D67: =-하이트진로_DART!D156/10^6 -> -29656.899 | E67: -41471 | F67: -440.22111 | G67: -1538 | H67: -286 | I67: 14.7 | J67: -23.249
B68: Earnings of discontinued ops | C68: 0 | D68: 0 | E68: 0 | F68: 0 | G68: 0 | H68: 0 | I68: -9 | J68: 0
B69: Subsidiary's net income before acquisition | D69: =-하이트진로_DART!D157/10^6 -> -182.83173
B70: Net income to company | C70: =SUM(C66:C68) -> 126799.45 | D70: =SUM(D66:D69) -> 99231.88 | E70: =SUM(E66:E68) -> 46607 | F70: =SUM(F66:F68) -> 1299.0829 | G70: =SUM(G66:G68) -> 4167 | H70: =SUM(H66:H68) -> 1142 | I70: =SUM(I66:I68) -> 723.2 | J70: =SUM(J66:J68) -> 31.183
B71: Minotrity interest | C71: 0 | D71: 0 | E71: 1038 | F71: -49.1 | G71: -565 | H71: -124 | I71: -2.8 | J71: 0
B72: Net income | C72: =(SUM(C70:C71)) -> 126799.45 | D72: =(SUM(D70:D71)) -> 99231.88 | E72: =SUM(E70:E71) -> 47645 | F72: =SUM(F70:F71) -> 1249.9829 | G72: =SUM(G70:G71) -> 3602 | H72: =SUM(H70:H71) -> 1018 | I72: =SUM(I70:I71) -> 720.4 | J72: =SUM(J70:J71) -> 31.183
B73: Preferred stock dividends | C73: 0 | D73: =+하이트진로_DART!D263/10^6 -> 1043.126 | E73: 0 | F73: 0 | G73: 0 | H73: 0 | I73: 0 | J73: 0
B74: Net income to common stock shareholders | C74: =+C72-C73 -> 126799.45 | D74: =+D72-D73 -> 98188.754 | E74: =+E72-E73 -> 47645 | F74: =+F72-F73 -> 1249.9829 | G74: =+G72-G73 -> 3602 | H74: =+H72-H73 -> 1018 | I74: =+I72-I73 -> 720.4 | J74: =+J72-J73 -> 31.183
B75: Diluted weighted average shares out. | C75: =OB맥주_DART!D254/10^6 -> 20.611 | D75: =+하이트진로_DART!E275/10^6 -> 9.930397 | E75: 465.19234 | F75: 1315.7989 | G75: 152.654 | H75: 489.97459 | I75: 185.9 | J75: 14.356
B77: Non-GAAP exclusions
B78: Restructuring | C78: 0 | D78: 0 | E78: 0 | F78: 0 | G78: =-67-40-20-31-34-56-95-72-100 -> -515 | H78: 0 | I78: =-(7.6+0.9) -> -8.5 | J78: 0
B79: Other unusal items | C79: 0 | D79: =-(+하이트진로_DART!D157)/(10^6) -> -182.83173 | E79: 0 | F79: 190.4449 | G79: 0 | H79: 0 | I79: -10.4 | J79: 0
B80: Excluded operating (expense) / income | C80: =+SUM(C78,C79) -> 0 | D80: =+SUM(D78,D79) -> -182.83173 | E80: =+SUM(E78,E79) -> 0 | F80: =+SUM(F78,F79) -> 190.4449 | G80: =+SUM(G78,G79) -> -515 | H80: =+SUM(H78,H79) -> 0 | I80: =+SUM(I78,I79) -> -18.9 | J80: =+SUM(J78,J79) -> 0
B82: Merger | C82: 0 | D82: 0 | E82: 0 | F82: 0 | G82: -17 | H82: 0 | I82: -5.7 | J82: 0
B83: GW impairment | C83: 0 | D83: 0 | E83: 0 | F83: 0 | G83: 0 | H83: -1 | I83: 0 | J83: 0
B84: Gain (Loss) on sale of invest. | C84: =-OB맥주_DART!E143 -> -238.2 | D84: 0 | E84: -887 | F84: -1.8 | G84: =3-41 -> -38 | H84: 14 | I84: 46 | J84: 0
B85: Gain (Loss) on sale of assets | C85: =OB맥주_DART!G135 -> 871.43611 | D85: =(+하이트진로_DART!C143-하이트진로_DART!C150)/(10^6) -> -3747.4055 | E85: 6914 | F85: -39.8 | G85: =61+40-10-60 -> 31 | H85: 39 | I85: 0 | J85: 0
B86: Asset Writedown | C86: =-OB맥주_DART!E145 -> -96.044994 | D86: =(-하이트진로_DART!C153)/(10^6) -> -1997.0925 | E86: -8318 | F86: -67.9 | G86: -37 | H86: -187 | I86: 0 | J86: -1
B87: Affiliate | C87: 0 | D87: 0 | E87: 8512 | F87: 0 | G87: 104 | H87: 127 | I87: =382-1.2 -> 380.8 | J87: 0
B88: Currency | C88: =-OB맥주_DART!G132 -> -3222.2556 | D88: =+(SUM(하이트진로_DART!C141:C142)-SUM(하이트진로_DART!C147:C148))/10^6 -> 24092.607 | E88: 1815 | F88: 3.478996 | G88: -582 | H88: -47 | I88: 6.1 | J88: 0
B89: Other non-op | C89: 0 | D89: =+(SUM(하이트진로_DART!C140,하이트진로_DART!C144)-SUM(하이트진로_DART!C149,하이트진로_DART!C151:C152,하이트진로_DART!C154))/10^6 -> -28188.197 | E89: -862 | F89: -11.4 | G89: 0 | H89: 238 | I89: =5.3+2.8-1.5-3.6+3.6 -> 6.6 | J89: 0
B90: Excluded nonoperating (expense) / income | C90: =+SUM(C82:C89) -> -2685.0644 | D90: =+SUM(D82:D89) -> -9840.0878 | E90: =+SUM(E82:E89) -> 7174 | F90: =+SUM(F82:F89) -> -117.421 | G90: =+SUM(G82:G89) -> -539 | H90: =+SUM(H82:H89) -> 183 | I90: =+SUM(I82:I89) -> 433.8 | J90: =+SUM(J82:J89) -> -1
B91: Tax effect of non-GAAP exclusions | C91: =+C90*C16*-1 -> 649.78559 | D91: =+D90*D16*-1 -> 2381.3013 | E91: =+E90*E16*-1 -> -2919.1006 | F91: =+F90*F16*-1 -> 29.355251 | G91: =+G90*G16*-1 -> 134.75 | H91: =+H90*H16*-1 -> -46.665 | I91: =+I90*I16*-1 -> -170.0496 | J91: =+J90*J16*-1 -> 0.392
B93: Normalized (Non-GAAP) financials
B94: EBIT | C94: =C64-C80 -> 196305.66 | D94: =D64-D80 -> 187129.78 | E94: =E64-E80 -> 82777 | F94: =F64-F80 -> 1520.6809 | G94: =G64-G80 -> 9538 | H94: =H64-H80 -> 1777 | I94: =I64-I80 -> 423.6 | J94: =J64-J80 -> 55.32
B95: Depreciation and amortization expense | C95: =OB맥주_DART!G160 -> 55129.79 | D95: =+(하이트진로_DART!C174+하이트진로_DART!C176)/10^6 -> 72484.729 | E95: 58372 | F95: 544.76173 | G95: 3769 | H95: 895 | I95: 208 | J95: 16.919
B96: EBITDA | C96: =C94+C95 -> 251435.45 | D96: =D94+D95 -> 259614.51 | E96: =E94+E95 -> 141149 | F96: =F94+F95 -> 2065.4427 | G96: =G94+G95 -> 13307 | H96: =H94+H95 -> 2672 | I96: =I94+I95 -> 631.6 | J96: =J94+J95 -> 72.239
B97: Pretax income | C97: =C66-C80-C90 -> 180252.54 | D97: =D66-D80-D90 -> 139094.53 | E97: =E66-E80-E90 -> 80904 | F97: =F66-F80-F90 -> 1666.2802 | G97: =G66-G80-G90 -> 6759 | H97: =H66-H80-H90 -> 1245 | I97: =I66-I80-I90 -> 302.6 | J97: =J66-J80-J90 -> 55.432
B98: Tax benefit / (expense) | C98: =-C97*C16 -> -43621.114 | D98: =-D97*D16 -> -33660.876 | E98: =-E97*E16 -> -32919.838 | F98: =-F97*F16 -> -416.57004 | G98: =-G97*G16 -> -1689.75 | H98: =-H97*H16 -> -317.475 | I98: =-I97*I16 -> -118.6192 | J98: =-J97*J16 -> -21.729344
B99: Net income | C99: =C97+C98 -> 136631.42 | D99: =D97+D98 -> 105433.65 | E99: =E97+E98 -> 47984.162 | F99: =F97+F98 -> 1249.7101 | G99: =G97+G98 -> 5069.25 | H99: =H97+H98 -> 927.525 | I99: =I97+I98 -> 183.9808 | J99: =J97+J98 -> 33.702656
B100: Preferred stock dividends | C100: =+C73 -> 0 | D100: =+D73 -> 1043.126 | E100: =+E73 -> 0 | F100: =+F73 -> 0 | G100: =+G73 -> 0 | H100: =+H73 -> 0 | I100: =+I73 -> 0 | J100: =+J73 -> 0
B101: Net income to common stock shareholders | C101: =+C99-C100 -> 136631.42 | D101: =+D99-D100 -> 104390.53 | E101: =+E99-E100 -> 47984.162 | F101: =+F99-F100 -> 1249.7101 | G101: =+G99-G100 -> 5069.25 | H101: =+H99-H100 -> 927.525 | I101: =+I99-I100 -> 183.9808 | J101: =+J99-J100 -> 33.702656
B104: Diluted EPS calculation
B105: Diluted EPS | C105: =C101/C53 -> 6629.0535 | D105: =D101/D53 -> 10921.965 | E105: =E101/E53 -> 103.09653 | F105: =F101/F53 -> 0.95009959 | G105: =G101/G53 -> 33.210292 | H105: =H101/H53 -> 1.8990461 | I105: =I101/I53 -> 0.99772668 | J105: =J101/J53 -> 2.2702953
B107: Last Fiscal Year
B108: Year ending date | C108: =C12 -> 40178 | D108: =D12 -> 40178 | E108: =E12 -> 40178 | F108: =F12 -> 40178 | G108: =G12 -> 40178 | H108: =H12 -> 40178 | I108: =I12 -> 40178 | J108: =J12 -> 40178
B109: Revenues - LFY | C109: =C60 -> 816110.19 | D109: =D60 -> 1049536 | E109: =E60 -> 1022318 | F109: =F60 -> 18026.108 | G109: =G60 -> 59382 | H109: =H60 -> 14701 | I109: =I60 -> 3032.4 | J109: =J60 -> 415.053
B110: EBITDA - LFY | C110: =C96 -> 251435.45 | D110: =D96 -> 259614.51 | E110: =E96 -> 141149 | F110: =F96 -> 2065.4427 | G110: =G96 -> 13307 | H110: =H96 -> 2672 | I110: =I96 -> 631.6 | J110: =J96 -> 72.239
B111: EBIT - LFY | C111: =C94 -> 196305.66 | D111: =D94 -> 187129.78 | E111: =E94 -> 82777 | F111: =F94 -> 1520.6809 | G111: =G94 -> 9538 | H111: =H94 -> 1777 | I111: =I94 -> 423.6 | J111: =J94 -> 55.32
B112: EPS - LFY | C112: =C105 -> 6629.0535 | D112: =D105 -> 10921.965 | E112: =E105 -> 103.09653 | F112: =F105 -> 0.95009959 | G112: =G105 -> 33.210292 | H112: =H105 -> 1.8990461 | I112: =I105 -> 0.99772668 | J112: =J105 -> 2.2702953
...

Sheet _CIQHiddenCacheSheet
A1: 2 | B1: BAABTAVMT0NBTAFI/////wFQAwAAADBDSVEuTllTRTpJQk0uSVFfRUJJVERBX0VTVF9DSVEuRlkyMDEwLjIwMjAtMTAtMTcFAAAAAAAAAAgAAAATKENhcGFiaWxpdHkgTmVlZGVkKSxzQlbjctgIKgD79+Ry2AgmQ0lRLk5ZU0U6SUJNLklRX0VCSVREQV9FU1RfQ0lRLkZZMjAxMC4FAAAAAAAAAAgAAAATKENhcGFiaWxpdHkgTmVlZGVkKT59CVfjctgIvO0ygyBz2AgwQ0lRLk5ZU0U6SUJNLklRX0VCSVREQV9FU1RfQ0lRLkZZMjAxMC4yMDIwLTEwLTE4BQAAAAAAAAAIAAAAEyhDYXBhYmlsaXR5IE5lZWRlZCm3Ri+DIHPYCKrqsewyc9gI

Sheet 함수 실습 (실습)
C3: VLOOKUP
D4: Oriental Brewery
C5: 국내 총 선호도 | D5: =VLOOKUP(D$4,$C$10:$E$17,2,FALSE) -> 1등
C6: 국내 30대 선호도 | D6: =VLOOKUP(D$4,$C$10:$E$17,3,FALSE) -> 2등
D9: 국내 총 선호도 | E9: 국내 30대 선호도
C10: Oriental Brewery | D10: 1등 | E10: 2등
C11: Hite Brewery | D11: 5등 | E11: 3등
C12: ASAHI GROUP | D12: 3등 | E12: 5등
C13: TSINGTAO BREWERY | D13: 2등 | E13: 6등
C14: CARLSBERG | D14: 8등 | E14: 1등
C15: HEINEKEN | D15: 3등 | E15: 3등
C16: MOLSON COORS | D16: 6등 | E16: 8등
C17: BOSTON BEER | D17: 7등 | E17: 7등
C25: HLOOKUP
D26: 국내 총 선호도 | E26: 국내 30대 선호도
C27: Oriental Brewery | D27: =HLOOKUP($C$27,$C$31:$K$33,2,FALSE) -> 1등 | E27: =HLOOKUP($C$27,$C$31:$K$33,3,FALSE) -> 2등
C28: Oriental Brewery | D28: {=VLOOKUP($C$27,TRANSPOSE($C$31:$K$33),2,FALSE)} -> 1등 | E28: {=VLOOKUP($C$27,TRANSPOSE($C$31:$K$33),3,FALSE)} -> 2등
D31: Oriental Brewery | E31: Hite Brewery | F31: ASAHI GROUP | G31: TSINGTAO BREWERY | H31: CARLSBERG | I31: HEINEKEN | J31: MOLSON COORS | K31: BOSTON BEER
C32: 국내 선호도 | D32: 1등 | E32: 5등 | F32: 3등 | G32: 2등 | H32: 8등 | I32: 3등 | J32: 6등 | K32: 7등
C33: 국내 30대 선호도 | D33: 2등 | E33: 3등 | F33: 5등 | G33: 6등 | H33: 1등 | I33: 3등 | J33: 8등 | K33: 7등

Sheet 함수 실습 (정답)
C3: VLOOKUP
D4: Oriental Brewery
C5: 국내 총 선호도 | D5: =VLOOKUP(D$4,$C$10:$E$17,2,FALSE) -> 1등
C6: 국내 30대 선호도 | D6: =VLOOKUP(D$4,$C$10:$E$17,3,FALSE) -> 2등
D9: 국내 총 선호도 | E9: 국내 30대 선호도
C10: Oriental Brewery | D10: 1등 | E10: 2등
C11: Hite Brewery | D11: 5등 | E11: 3등
C12: ASAHI GROUP | D12: 3등 | E12: 5등
C13: TSINGTAO BREWERY | D13: 2등 | E13: 6등
C14: CARLSBERG | D14: 8등 | E14: 1등
C15: HEINEKEN | D15: 3등 | E15: 3등
C16: MOLSON COORS | D16: 6등 | E16: 8등
C17: BOSTON BEER | D17: 7등 | E17: 7등
C25: HLOOKUP
D26: 국내 총 선호도 | E26: 국내 30대 선호도
C27: Oriental Brewery | D27: =HLOOKUP($C27,$C$31:$K$33,2,FALSE) -> 1등 | E27: =HLOOKUP($C27,$C$31:$K$33,3,FALSE) -> 2등
D31: Oriental Brewery | E31: Hite Brewery | F31: ASAHI GROUP | G31: TSINGTAO BREWERY | H31: CARLSBERG | I31: HEINEKEN | J31: MOLSON COORS | K31: BOSTON BEER
C32: 국내 선호도 | D32: 1등 | E32: 5등 | F32: 3등 | G32: 2등 | H32: 8등 | I32: 3등 | J32: 6등 | K32: 7등
C33: 국내 30대 선호도 | D33: 2등 | E33: 3등 | F33: 5등 | G33: 6등 | H33: 1등 | I33: 3등 | J33: 8등 | K33: 7등

Sheet Trading Comps_Output (실습)
A1: OB맥주
A2: Comparable Company Analysis ("Trading Comps") - Output
B4: Company name | C4: Ticker | D4: Market capitalization (mm) | E4: Enterprise value (EV) | F4: Revenues - LFY | G4: EBITDA - LFY | H4: EBIT - LFY | I4: EPS - LFY | J4: Revenues - Calendar year 1 | K4: EBITDA - Calendar year 1 | L4: EBIT - Calendar year 1 | M4: EPS - Calendar year 1 | N4: Long-term growth rate | O4: Net debt | P4: Diluted shares outstanding (mm)
F5: EV / Revenues - LFY | G5: EV / EBITDA - LFY | H5: EV / EBIT - LFY | I5: P/E - LFY | J5: EV / Revenues - Year 1 | K5: EV / EBITDA - Year 1 | L5: EV / EBIT - Year 1 | M5: P/E - Year 1 | N5: PE/LTG (PEG ratio)
B7: 재무정보 요약
B9: 단순 링크
F11: Last Fiscal Year (LTM) | J11: Year 1 Forecast - Calendar Year
B12: Name | C12: Ticker | D12: Market cap (mm) | E12: Enterprise value | F12: Revenues | G12: EBITDA | H12: EBIT | I12: EPS | J12: Revenues | K12: EBITDA | L12: EBIT | M12: EPS | N12: LT growth rate | O12: Net debt | P12: Diluted shares outstanding
B13: Place target in first position
B14: Oriental Brewery | C14: =+'Trading Comps_Input'!C10 -> OB | F14: =+'Trading Comps_Input'!C109 -> 816110.19 | G14: =+'Trading Comps_Input'!C110 -> 251435.45 | H14: =+'Trading Comps_Input'!C111 -> 196305.66 | I14: =+'Trading Comps_Input'!C112 -> 6629.0535 | J14: =+'Trading Comps_Input'!C129 -> 840593.49 | K14: =+'Trading Comps_Input'!C130 -> 258978.51 | L14: =+'Trading Comps_Input'!C131 -> 202194.82 | M14: =+'Trading Comps_Input'!C132 -> 6827.9251 | N14: =+'Trading Comps_Input'!C146 -> 0.025 | O14: =+'Trading Comps_Input'!C123 -> 301945.91 | P14: =+'Trading Comps_Input'!C168 -> 20.611 | S14: ①
B15: HITE Brewery | C15: =+'Trading Comps_Input'!D10 -> KRX: 103150 | D15: =+'Trading Comps_Input'!D170 -> 1624834.8 | E15: =+'Trading Comps_Input'!D173 -> 2618390.5 | F15: =+'Trading Comps_Input'!D109 -> 1049536 | G15: =+'Trading Comps_Input'!D110 -> 259614.51 | H15: =+'Trading Comps_Input'!D111 -> 187129.78 | I15: =+'Trading Comps_Input'!D112 -> 10921.965 | J15: =+'Trading Comps_Input'!D129 -> 1066105.2 | K15: =+'Trading Comps_Input'!D130 -> 232221.75 | L15: =+'Trading Comps_Input'!D131 -> 151914.49 | M15: =+'Trading Comps_Input'!D132 -> 6821.3098 | N15: =+'Trading Comps_Input'!D146 -> 0.025 | O15: =+'Trading Comps_Input'!D123 -> 993555.63 | P15: =+'Trading Comps_Input'!D168 -> 9.557852 | S15: ②
B16: ASAHI GROUP | C16: =+'Trading Comps_Input'!E10 -> TYO: 2502 | D16: =+'Trading Comps_Input'!E170 -> 806123.85 | E16: =+'Trading Comps_Input'!E173 -> 1184147.9 | F16: =+'Trading Comps_Input'!E109 -> 1022318 | G16: =+'Trading Comps_Input'!E110 -> 141149 | H16: =+'Trading Comps_Input'!E111 -> 82777 | I16: =+'Trading Comps_Input'!E112 -> 103.09653 | J16: =+'Trading Comps_Input'!E129 -> 1084231.5 | K16: =+'Trading Comps_Input'!E130 -> 162376.01 | L16: =+'Trading Comps_Input'!E131 -> 95386.573 | M16: =+'Trading Comps_Input'!E132 -> 115.68564 | N16: =+'Trading Comps_Input'!E146 -> 0.035 | O16: =+'Trading Comps_Input'!E123 -> 378024 | P16: =+'Trading Comps_Input'!E168 -> 465.42948 | S16: ③
B17: TSINGTAO BREWERY | C17: =+'Trading Comps_Input'!F10 -> SEHK:168 | D17: =+'Trading Comps_Input'!F170 -> 21676.909 | E17: =+'Trading Comps_Input'!F173 -> 17888.829 | F17: =+'Trading Comps_Input'!F109 -> 18026.108 | G17: =+'Trading Comps_Input'!F110 -> 2065.4427 | H17: =+'Trading Comps_Input'!F111 -> 1520.6809 | I17: =+'Trading Comps_Input'!F112 -> 0.95009959 | J17: =+'Trading Comps_Input'!F129 -> 20524.904 | K17: =+'Trading Comps_Input'!F130 -> 2486.2697 | L17: =+'Trading Comps_Input'!F131 -> 1905.3395 | M17: =+'Trading Comps_Input'!F132 -> 1.129899 | N17: =+'Trading Comps_Input'!F146 -> 0.035 | O17: =+'Trading Comps_Input'!F123 -> -3788.0802 | P17: =+'Trading Comps_Input'!F168 -> 1315.3464
B18: CARLSBERG | C18: CPSE: CARL B | D18: =+'Trading Comps_Input'!G170 -> 60461.074 | E18: =+'Trading Comps_Input'!G173 -> 101784.07 | F18: =+'Trading Comps_Input'!G109 -> 59382 | G18: =+'Trading Comps_Input'!G110 -> 13307 | H18: =+'Trading Comps_Input'!G111 -> 9538 | I18: =+'Trading Comps_Input'!G112 -> 33.210292 | J18: =+'Trading Comps_Input'!G129 -> 60124.231 | K18: =+'Trading Comps_Input'!G130 -> 13519.078 | L18: =+'Trading Comps_Input'!G131 -> 9759.7655 | M18: =+'Trading Comps_Input'!G132 -> 33.09819 | N18: =+'Trading Comps_Input'!G146 -> 0.03 | O18: =+'Trading Comps_Input'!G123 -> 41323 | P18: =+'Trading Comps_Input'!G168 -> 152.64093 | S18: ※
B19: HEINEKEN | C19: =+'Trading Comps_Input'!H10 -> ENXTAM:HEIA | D19: =+'Trading Comps_Input'!H170 -> 17490.187 | E19: =+'Trading Comps_Input'!H173 -> 25968.187 | F19: =+'Trading Comps_Input'!H109 -> 14701 | G19: =+'Trading Comps_Input'!H110 -> 2672 | H19: =+'Trading Comps_Input'!H111 -> 1777 | I19: =+'Trading Comps_Input'!H112 -> 1.8990461 | J19: =+'Trading Comps_Input'!H129 -> 16327.516 | K19: =+'Trading Comps_Input'!H130 -> 3186.5033 | L19: =+'Trading Comps_Input'!H131 -> 1986.2587 | M19: =+'Trading Comps_Input'!H132 -> 2.711287 | N19: =+'Trading Comps_Input'!H146 -> 0.035 | O19: =+'Trading Comps_Input'!H123 -> 8478 | P19: =+'Trading Comps_Input'!H168 -> 488.41627
B20: MOLSON COORS | C20: =+'Trading Comps_Input'!I10 -> NYSE: TAP | D20: =+'Trading Comps_Input'!I170 -> 4233.824 | E20: =+'Trading Comps_Input'!I173 -> 5225.824 | F20: =+'Trading Comps_Input'!I109 -> 3032.4 | G20: =+'Trading Comps_Input'!I110 -> 631.6 | H20: =+'Trading Comps_Input'!I111 -> 423.6 | I20: =+'Trading Comps_Input'!I112 -> 0.99772668 | J20: =+'Trading Comps_Input'!I129 -> 3371.9869 | K20: =+'Trading Comps_Input'!I130 -> 639.03857 | L20: =+'Trading Comps_Input'!I131 -> 426.09416 | M20: =+'Trading Comps_Input'!I132 -> 3.668696 | N20: =+'Trading Comps_Input'!I146 -> 0.015 | O20: =+'Trading Comps_Input'!I123 -> 992 | P20: =+'Trading Comps_Input'!I168 -> 184.4
B21: BOSTON BEER | C21: =+'Trading Comps_Input'!J10 -> NYSE: SAM | D21: =+'Trading Comps_Input'!J170 -> 705.58542 | E21: =+'Trading Comps_Input'!J173 -> 650.10442 | F21: =+'Trading Comps_Input'!J109 -> 415.053 | G21: =+'Trading Comps_Input'!J110 -> 72.239 | H21: =+'Trading Comps_Input'!J111 -> 55.32 | I21: =+'Trading Comps_Input'!J112 -> 2.2702953 | J21: =+'Trading Comps_Input'!J129 -> 446.19518 | K21: =+'Trading Comps_Input'!J130 -> 102.67356 | L21: =+'Trading Comps_Input'!J131 -> 83.819889 | M21: =+'Trading Comps_Input'!J132 -> 3.407229 | N21: =+'Trading Comps_Input'!J146 -> 0.035 | O21: =+'Trading Comps_Input'!J123 -> -55.481 | P21: =+'Trading Comps_Input'!J168 -> 14.845054
B24: Vlookup
F26: Last Fiscal Year (LTM) | J26: Year 1 Forecast - Calendar Year
B27: Name | C27: Ticker | D27: Market cap (mm) | E27: Enterprise value | F27: Revenues | G27: EBITDA | H27: EBIT | I27: EPS | J27: Revenues | K27: EBITDA | L27: EBIT | M27: EPS | N27: LT growth rate | O27: Net debt | P27: Diluted shares outstanding
B29: Oriental Brewery | C29: =VLOOKUP(C$4,'Trading Comps_Input'!$B$9:$J$188,MATCH($B42,$B$42:$B$49,0)+1,FALSE) -> OB | D29: =VLOOKUP(D$4,'Trading Comps_Input'!$B$9:$J$188,MATCH($B42,$B$42:$B$49,0)+1,FALSE) -> 0 | E29: =VLOOKUP(E$4,'Trading Comps_Input'!$B$9:$J$188,MATCH($B42,$B$42:$B$49,0)+1,FALSE) -> 0 | F29: =VLOOKUP(F$4,'Trading Comps_Input'!$B$9:$J$188,MATCH($B42,$B$42:$B$49,0)+1,FALSE) -> 816110.19 | G29: =VLOOKUP(G$4,'Trading Comps_Input'!$B$9:$J$188,MATCH($B42,$B$42:$B$49,0)+1,FALSE) -> 251435.45 | H29: =VLOOKUP(H$4,'Trading Comps_Input'!$B$9:$J$188,MATCH($B42,$B$42:$B$49,0)+1,FALSE) -> 196305.66 | I29: =VLOOKUP(I$4,'Trading Comps_Input'!$B$9:$J$188,MATCH($B42,$B$42:$B$49,0)+1,FALSE) -> 6629.0535 | J29: =VLOOKUP(J$4,'Trading Comps_Input'!$B$9:$J$188,MATCH($B42,$B$42:$B$49,0)+1,FALSE) -> 840593.49 | ... P29: =VLOOKUP(P$4,'Trading Comps_Input'!$B$9:$J$188,MATCH($B42,$B$42:$B$49,0)+1,FALSE) -> 20.611
B30: HITE Brewery | C30: =VLOOKUP(C$4,'Trading Comps_Input'!$B$9:$J$188,MATCH($B43,$B$42:$B$49,0)+1,FALSE) -> KRX: 103150 | D30: =VLOOKUP(D$4,'Trading Comps_Input'!$B$9:$J$188,MATCH($B43,$B$42:$B$49,0)+1,FALSE) -> 1624834.8 | E30: =VLOOKUP(E$4,'Trading Comps_Input'!$B$9:$J$188,MATCH($B43,$B$42:$B$49,0)+1,FALSE) -> 2618390.5 | F30: =VLOOKUP(F$4,'Trading Comps_Input'!$B$9:$J$188,MATCH($B43,$B$42:$B$49,0)+1,FALSE) -> 1049536 | G30: =VLOOKUP(G$4,'Trading Comps_Input'!$B$9:$J$188,MATCH($B43,$B$42:$B$49,0)+1,FALSE) -> 259614.51 | H30: =VLOOKUP(H$4,'Trading Comps_Input'!$B$9:$J$188,MATCH($B43,$B$42:$B$49,0)+1,FALSE) -> 187129.78 | I30: =VLOOKUP(I$4,'Trading Comps_Input'!$B$9:$J$188,MATCH($B43,$B$42:$B$49,0)+1,FALSE) -> 10921.965 | J30: =VLOOKUP(J$4,'Trading Comps_Input'!$B$9:$J$188,MATCH($B43,$B$42:$B$49,0)+1,FALSE) -> 1066105.2 | ... P30: =VLOOKUP(P$4,'Trading Comps_Input'!$B$9:$J$188,MATCH($B43,$B$42:$B$49,0)+1,FALSE) -> 9.557852
B31: ASAHI GROUP | C31: =VLOOKUP(C$4,'Trading Comps_Input'!$B$9:$J$188,MATCH($B44,$B$42:$B$49,0)+1,FALSE) -> TYO: 2502 | D31: =VLOOKUP(D$4,'Trading Comps_Input'!$B$9:$J$188,MATCH($B44,$B$42:$B$49,0)+1,FALSE) -> 806123.85 | E31: =VLOOKUP(E$4,'Trading Comps_Input'!$B$9:$J$188,MATCH($B44,$B$42:$B$49,0)+1,FALSE) -> 1184147.9 | F31: =VLOOKUP(F$4,'Trading Comps_Input'!$B$9:$J$188,MATCH($B44,$B$42:$B$49,0)+1,FALSE) -> 1022318 | G31: =VLOOKUP(G$4,'Trading Comps_Input'!$B$9:$J$188,MATCH($B44,$B$42:$B$49,0)+1,FALSE) -> 141149 | H31: =VLOOKUP(H$4,'Trading Comps_Input'!$B$9:$J$188,MATCH($B44,$B$42:$B$49,0)+1,FALSE) -> 82777 | I31: =VLOOKUP(I$4,'Trading Comps_Input'!$B$9:$J$188,MATCH($B44,$B$42:$B$49,0)+1,FALSE) -> 103.09653 | J31: =VLOOKUP(J$4,'Trading Comps_Input'!$B$9:$J$188,MATCH($B44,$B$42:$B$49,0)+1,FALSE) -> 1084231.5 | ... P31: =VLOOKUP(P$4,'Trading Comps_Input'!$B$9:$J$188,MATCH($B44,$B$42:$B$49,0)+1,FALSE) -> 465.42948
B32: TSINGTAO BREWERY | C32: =VLOOKUP(C$4,'Trading Comps_Input'!$B$9:$J$188,MATCH($B45,$B$42:$B$49,0)+1,FALSE) -> SEHK:168 | D32: =VLOOKUP(D$4,'Trading Comps_Input'!$B$9:$J$188,MATCH($B45,$B$42:$B$49,0)+1,FALSE) -> 21676.909 | E32: =VLOOKUP(E$4,'Trading Comps_Input'!$B$9:$J$188,MATCH($B45,$B$42:$B$49,0)+1,FALSE) -> 17888.829 | F32: =VLOOKUP(F$4,'Trading Comps_Input'!$B$9:$J$188,MATCH($B45,$B$42:$B$49,0)+1,FALSE) -> 18026.108 | G32: =VLOOKUP(G$4,'Trading Comps_Input'!$B$9:$J$188,MATCH($B45,$B$42:$B$49,0)+1,FALSE) -> 2065.4427 | H32: =VLOOKUP(H$4,'Trading Comps_Input'!$B$9:$J$188,MATCH($B45,$B$42:$B$49,0)+1,FALSE) -> 1520.6809 | I32: =VLOOKUP(I$4,'Trading Comps_Input'!$B$9:$J$188,MATCH($B45,$B$42:$B$49,0)+1,FALSE) -> 0.95009959 | J32: =VLOOKUP(J$4,'Trading Comps_Input'!$B$9:$J$188,MATCH($B45,$B$42:$B$49,0)+1,FALSE) -> 20524.904 | ... P32: =VLOOKUP(P$4,'Trading Comps_Input'!$B$9:$J$188,MATCH($B45,$B$42:$B$49,0)+1,FALSE) -> 1315.3464
B33: CARLSBERG | C33: =VLOOKUP(C$4,'Trading Comps_Input'!$B$9:$J$188,MATCH($B46,$B$42:$B$49,0)+1,FALSE) -> CPSE:CARL B | D33: =VLOOKUP(D$4,'Trading Comps_Input'!$B$9:$J$188,MATCH($B46,$B$42:$B$49,0)+1,FALSE) -> 60461.074 | E33: =VLOOKUP(E$4,'Trading Comps_Input'!$B$9:$J$188,MATCH($B46,$B$42:$B$49,0)+1,FALSE) -> 101784.07 | F33: =VLOOKUP(F$4,'Trading Comps_Input'!$B$9:$J$188,MATCH($B46,$B$42:$B$49,0)+1,FALSE) -> 59382 | G33: =VLOOKUP(G$4,'Trading Comps_Input'!$B$9:$J$188,MATCH($B46,$B$42:$B$49,0)+1,FALSE) -> 13307 | H33: =VLOOKUP(H$4,'Trading Comps_Input'!$B$9:$J$188,MATCH($B46,$B$42:$B$49,0)+1,FALSE) -> 9538 | I33: =VLOOKUP(I$4,'Trading Comps_Input'!$B$9:$J$188,MATCH($B46,$B$42:$B$49,0)+1,FALSE) -> 33.210292 | J33: =VLOOKUP(J$4,'Trading Comps_Input'!$B$9:$J$188,MATCH($B46,$B$42:$B$49,0)+1,FALSE) -> 60124.231 | ... P33: =VLOOKUP(P$4,'Trading Comps_Input'!$B$9:$J$188,MATCH($B46,$B$42:$B$49,0)+1,FALSE) -> 152.64093
B34: HEINEKEN | C34: =VLOOKUP(C$4,'Trading Comps_Input'!$B$9:$J$188,MATCH($B47,$B$42:$B$49,0)+1,FALSE) -> ENXTAM:HEIA | D34: =VLOOKUP(D$4,'Trading Comps_Input'!$B$9:$J$188,MATCH($B47,$B$42:$B$49,0)+1,FALSE) -> 17490.187 | E34: =VLOOKUP(E$4,'Trading Comps_Input'!$B$9:$J$188,MATCH($B47,$B$42:$B$49,0)+1,FALSE) -> 25968.187 | F34: =VLOOKUP(F$4,'Trading Comps_Input'!$B$9:$J$188,MATCH($B47,$B$42:$B$49,0)+1,FALSE) -> 14701 | G34: =VLOOKUP(G$4,'Trading Comps_Input'!$B$9:$J$188,MATCH($B47,$B$42:$B$49,0)+1,FALSE) -> 2672 | H34: =VLOOKUP(H$4,'Trading Comps_Input'!$B$9:$J$188,MATCH($B47,$B$42:$B$49,0)+1,FALSE) -> 1777 | I34: =VLOOKUP(I$4,'Trading Comps_Input'!$B$9:$J$188,MATCH($B47,$B$42:$B$49,0)+1,FALSE) -> 1.8990461 | J34: =VLOOKUP(J$4,'Trading Comps_Input'!$B$9:$J$188,MATCH($B47,$B$42:$B$49,0)+1,FALSE) -> 16327.516 | ... P34: =VLOOKUP(P$4,'Trading Comps_Input'!$B$9:$J$188,MATCH($B47,$B$42:$B$49,0)+1,FALSE) -> 488.41627
B35: MOLSON COORS | C35: =VLOOKUP(C$4,'Trading Comps_Input'!$B$9:$J$188,MATCH($B48,$B$42:$B$49,0)+1,FALSE) -> NYSE: TAP | D35: =VLOOKUP(D$4,'Trading Comps_Input'!$B$9:$J$188,MATCH($B48,$B$42:$B$49,0)+1,FALSE) -> 4233.824 | E35: =VLOOKUP(E$4,'Trading Comps_Input'!$B$9:$J$188,MATCH($B48,$B$42:$B$49,0)+1,FALSE) -> 5225.824 | F35: =VLOOKUP(F$4,'Trading Comps_Input'!$B$9:$J$188,MATCH($B48,$B$42:$B$49,0)+1,FALSE) -> 3032.4 | G35: =VLOOKUP(G$4,'Trading Comps_Input'!$B$9:$J$188,MATCH($B48,$B$42:$B$49,0)+1,FALSE) -> 631.6 | H35: =VLOOKUP(H$4,'Trading Comps_Input'!$B$9:$J$188,MATCH($B48,$B$42:$B$49,0)+1,FALSE) -> 423.6 | I35: =VLOOKUP(I$4,'Trading Comps_Input'!$B$9:$J$188,MATCH($B48,$B$42:$B$49,0)+1,FALSE) -> 0.99772668 | J35: =VLOOKUP(J$4,'Trading Comps_Input'!$B$9:$J$188,MATCH($B48,$B$42:$B$49,0)+1,FALSE) -> 3371.9869 | ... P35: =VLOOKUP(P$4,'Trading Comps_Input'!$B$9:$J$188,MATCH($B48,$B$42:$B$49,0)+1,FALSE) -> 184.4
B36: BOSTON BEER | C36: =VLOOKUP(C$4,'Trading Comps_Input'!$B$9:$J$188,MATCH($B49,$B$42:$B$49,0)+1,FALSE) -> NYSE: SAM | D36: =VLOOKUP(D$4,'Trading Comps_Input'!$B$9:$J$188,MATCH($B49,$B$42:$B$49,0)+1,FALSE) -> 705.58542 | E36: =VLOOKUP(E$4,'Trading Comps_Input'!$B$9:$J$188,MATCH($B49,$B$42:$B$49,0)+1,FALSE) -> 650.10442 | F36: =VLOOKUP(F$4,'Trading Comps_Input'!$B$9:$J$188,MATCH($B49,$B$42:$B$49,0)+1,FALSE) -> 415.053 | G36: =VLOOKUP(G$4,'Trading Comps_Input'!$B$9:$J$188,MATCH($B49,$B$42:$B$49,0)+1,FALSE) -> 72.239 | H36: =VLOOKUP(H$4,'Trading Comps_Input'!$B$9:$J$188,MATCH($B49,$B$42:$B$49,0)+1,FALSE) -> 55.32 | I36: =VLOOKUP(I$4,'Trading Comps_Input'!$B$9:$J$188,MATCH($B49,$B$42:$B$49,0)+1,FALSE) -> 2.2702953 | J36: =VLOOKUP(J$4,'Trading Comps_Input'!$B$9:$J$188,MATCH($B49,$B$42:$B$49,0)+1,FALSE) -> 446.19518 | ... P36: =VLOOKUP(P$4,'Trading Comps_Input'!$B$9:$J$188,MATCH($B49,$B$42:$B$49,0)+1,FALSE) -> 14.845054
B38: Vlookup & Match
B40: Match
C41: 범위 안에서 순서
B42: Oriental Brewery | C42: =MATCH($B42,$B$42:$B$49,0)+1 -> 2
B43: HITE Brewery | C43: =MATCH($B43,$B$42:$B$49,0)+1 -> 3
B44: ASAHI GROUP | C44: =MATCH($B44,$B$42:$B$49,0)+1 -> 4
B45: TSINGTAO BREWERY | C45: =MATCH($B45,$B$42:$B$49,0)+1 -> 5
B46: CARLSBERG | C46: =MATCH($B46,$B$42:$B$49,0)+1 -> 6
B47: HEINEKEN | C47: =MATCH($B47,$B$42:$B$49,0)+1 -> 7
B48: MOLSON COORS | C48: =MATCH($B48,$B$42:$B$49,0)+1 -> 8
B49: BOSTON BEER | C49: =MATCH($B49,$B$42:$B$49,0)+1 -> 9
F53: Last Fiscal Year (LTM) | J53: Year 1 Forecast - Calendar Year
B54: Name | C54: Ticker | D54: Market cap (mm) | E54: Enterprise value | F54: Revenues | G54: EBITDA | H54: EBIT | I54: EPS | J54: Revenues | K54: EBITDA | L54: EBIT | M54: EPS | N54: LT growth rate | O54: Net debt | P54: Diluted shares outstanding
B56: Oriental Brewery | C56: =VLOOKUP(C$4,'Trading Comps_Input'!$B$9:$J$188,MATCH($B42,$B$42:$B$49,0)+1,FALSE) -> OB | D56: =VLOOKUP(D$4,'Trading Comps_Input'!$B$9:$J$188,MATCH($B42,$B$42:$B$49,0)+1,FALSE) -> 0 | E56: =VLOOKUP(E$4,'Trading Comps_Input'!$B$9:$J$188,MATCH($B42,$B$42:$B$49,0)+1,FALSE) -> 0 | F56: =VLOOKUP(F$4,'Trading Comps_Input'!$B$9:$J$188,MATCH($B42,$B$42:$B$49,0)+1,FALSE) -> 816110.19 | G56: =VLOOKUP(G$4,'Trading Comps_Input'!$B$9:$J$188,MATCH($B42,$B$42:$B$49,0)+1,FALSE) -> 251435.45 | H56: =VLOOKUP(H$4,'Trading Comps_Input'!$B$9:$J$188,MATCH($B42,$B$42:$B$49,0)+1,FALSE) -> 196305.66 | I56: =VLOOKUP(I$4,'Trading Comps_Input'!$B$9:$J$188,MATCH($B42,$B$42:$B$49,0)+1,FALSE) -> 6629.0535 | J56: =VLOOKUP(J$4,'Trading Comps_Input'!$B$9:$J$188,MATCH($B42,$B$42:$B$49,0)+1,FALSE) -> 840593.49 | ... P56: =VLOOKUP(P$4,'Trading Comps_Input'!$B$9:$J$188,MATCH($B42,$B$42:$B$49,0)+1,FALSE) -> 20.611
B57: HITE Brewery | C57: =VLOOKUP(C$4,'Trading Comps_Input'!$B$9:$J$188,MATCH($B43,$B$42:$B$49,0)+1,FALSE) -> KRX: 103150 | D57: =VLOOKUP(D$4,'Trading Comps_Input'!$B$9:$J$188,MATCH($B43,$B$42:$B$49,0)+1,FALSE) -> 1624834.8 | E57: =VLOOKUP(E$4,'Trading Comps_Input'!$B$9:$J$188,MATCH($B43,$B$42:$B$49,0)+1,FALSE) -> 2618390.5 | F57: =VLOOKUP(F$4,'Trading Comps_Input'!$B$9:$J$188,MATCH($B43,$B$42:$B$49,0)+1,FALSE) -> 1049536 | G57: =VLOOKUP(G$4,'Trading Comps_Input'!$B$9:$J$188,MATCH($B43,$B$42:$B$49,0)+1,FALSE) -> 259614.51 | H57: =VLOOKUP(H$4,'Trading Comps_Input'!$B$9:$J$188,MATCH($B43,$B$42:$B$49,0)+1,FALSE) -> 187129.78 | I57: =VLOOKUP(I$4,'Trading Comps_Input'!$B$9:$J$188,MATCH($B43,$B$42:$B$49,0)+1,FALSE) -> 10921.965 | J57: =VLOOKUP(J$4,'Trading Comps_Input'!$B$9:$J$188,MATCH($B43,$B$42:$B$49,0)+1,FALSE) -> 1066105.2 | ... P57: =VLOOKUP(P$4,'Trading Comps_Input'!$B$9:$J$188,MATCH($B43,$B$42:$B$49,0)+1,FALSE) -> 9.557852
B58: ASAHI GROUP | C58: =VLOOKUP(C$4,'Trading Comps_Input'!$B$9:$J$188,MATCH($B44,$B$42:$B$49,0)+1,FALSE) -> TYO: 2502 | D58: =VLOOKUP(D$4,'Trading Comps_Input'!$B$9:$J$188,MATCH($B44,$B$42:$B$49,0)+1,FALSE) -> 806123.85 | E58: =VLOOKUP(E$4,'Trading Comps_Input'!$B$9:$J$188,MATCH($B44,$B$42:$B$49,0)+1,FALSE) -> 1184147.9 | F58: =VLOOKUP(F$4,'Trading Comps_Input'!$B$9:$J$188,MATCH($B44,$B$42:$B$49,0)+1,FALSE) -> 1022318 | G58: =VLOOKUP(G$4,'Trading Comps_Input'!$B$9:$J$188,MATCH($B44,$B$42:$B$49,0)+1,FALSE) -> 141149 | H58: =VLOOKUP(H$4,'Trading Comps_Input'!$B$9:$J$188,MATCH($B44,$B$42:$B$49,0)+1,FALSE) -> 82777 | I58: =VLOOKUP(I$4,'Trading Comps_Input'!$B$9:$J$188,MATCH($B44,$B$42:$B$49,0)+1,FALSE) -> 103.09653 | J58: =VLOOKUP(J$4,'Trading Comps_Input'!$B$9:$J$188,MATCH($B44,$B$42:$B$49,0)+1,FALSE) -> 1084231.5 | ... P58: =VLOOKUP(P$4,'Trading Comps_Input'!$B$9:$J$188,MATCH($B44,$B$42:$B$49,0)+1,FALSE) -> 465.42948
B59: TSINGTAO BREWERY | C59: =VLOOKUP(C$4,'Trading Comps_Input'!$B$9:$J$188,MATCH($B45,$B$42:$B$49,0)+1,FALSE) -> SEHK:168 | D59: =VLOOKUP(D$4,'Trading Comps_Input'!$B$9:$J$188,MATCH($B45,$B$42:$B$49,0)+1,FALSE) -> 21676.909 | E59: =VLOOKUP(E$4,'Trading Comps_Input'!$B$9:$J$188,MATCH($B45,$B$42:$B$49,0)+1,FALSE) -> 17888.829 | F59: =VLOOKUP(F$4,'Trading Comps_Input'!$B$9:$J$188,MATCH($B45,$B$42:$B$49,0)+1,FALSE) -> 18026.108 | G59: =VLOOKUP(G$4,'Trading Comps_Input'!$B$9:$J$188,MATCH($B45,$B$42:$B$49,0)+1,FALSE) -> 2065.4427 | H59: =VLOOKUP(H$4,'Trading Comps_Input'!$B$9:$J$188,MATCH($B45,$B$42:$B$49,0)+1,FALSE) -> 1520.6809 | I59: =VLOOKUP(I$4,'Trading Comps_Input'!$B$9:$J$188,MATCH($B45,$B$42:$B$49,0)+1,FALSE) -> 0.95009959 | J59: =VLOOKUP(J$4,'Trading Comps_Input'!$B$9:$J$188,MATCH($B45,$B$42:$B$49,0)+1,FALSE) -> 20524.904 | ... P59: =VLOOKUP(P$4,'Trading Comps_Input'!$B$9:$J$188,MATCH($B45,$B$42:$B$49,0)+1,FALSE) -> 1315.3464
B60: CARLSBERG | C60: =VLOOKUP(C$4,'Trading Comps_Input'!$B$9:$J$188,MATCH($B46,$B$42:$B$49,0)+1,FALSE) -> CPSE:CARL B | D60: =VLOOKUP(D$4,'Trading Comps_Input'!$B$9:$J$188,MATCH($B46,$B$42:$B$49,0)+1,FALSE) -> 60461.074 | E60: =VLOOKUP(E$4,'Trading Comps_Input'!$B$9:$J$188,MATCH($B46,$B$42:$B$49,0)+1,FALSE) -> 101784.07 | F60: =VLOOKUP(F$4,'Trading Comps_Input'!$B$9:$J$188,MATCH($B46,$B$42:$B$49,0)+1,FALSE) -> 59382 | G60: =VLOOKUP(G$4,'Trading Comps_Input'!$B$9:$J$188,MATCH($B46,$B$42:$B$49,0)+1,FALSE) -> 13307 | H60: =VLOOKUP(H$4,'Trading Comps_Input'!$B$9:$J$188,MATCH($B46,$B$42:$B$49,0)+1,FALSE) -> 9538 | I60: =VLOOKUP(I$4,'Trading Comps_Input'!$B$9:$J$188,MATCH($B46,$B$42:$B$49,0)+1,FALSE) -> 33.210292 | J60: =VLOOKUP(J$4,'Trading Comps_Input'!$B$9:$J$188,MATCH($B46,$B$42:$B$49,0)+1,FALSE) -> 60124.231 | ... P60: =VLOOKUP(P$4,'Trading Comps_Input'!$B$9:$J$188,MATCH($B46,$B$42:$B$49,0)+1,FALSE) -> 152.64093
B61: HEINEKEN | C61: =VLOOKUP(C$4,'Trading Comps_Input'!$B$9:$J$188,MATCH($B47,$B$42:$B$49,0)+1,FALSE) -> ENXTAM:HEIA | D61: =VLOOKUP(D$4,'Trading Comps_Input'!$B$9:$J$188,MATCH($B47,$B$42:$B$49,0)+1,FALSE) -> 17490.187 | E61: =VLOOKUP(E$4,'Trading Comps_Input'!$B$9:$J$188,MATCH($B47,$B$42:$B$49,0)+1,FALSE) -> 25968.187 | F61: =VLOOKUP(F$4,'Trading Comps_Input'!$B$9:$J$188,MATCH($B47,$B$42:$B$49,0)+1,FALSE) -> 14701 | G61: =VLOOKUP(G$4,'Trading Comps_Input'!$B$9:$J$188,MATCH($B47,$B$42:$B$49,0)+1,FALSE) -> 2672 | H61: =VLOOKUP(H$4,'Trading Comps_Input'!$B$9:$J$188,MATCH($B47,$B$42:$B$49,0)+1,FALSE) -> 1777 | I61: =VLOOKUP(I$4,'Trading Comps_Input'!$B$9:$J$188,MATCH($B47,$B$42:$B$49,0)+1,FALSE) -> 1.8990461 | J61: =VLOOKUP(J$4,'Trading Comps_Input'!$B$9:$J$188,MATCH($B47,$B$42:$B$49,0)+1,FALSE) -> 16327.516 | ... P61: =VLOOKUP(P$4,'Trading Comps_Input'!$B$9:$J$188,MATCH($B47,$B$42:$B$49,0)+1,FALSE) -> 488.41627
B62: MOLSON COORS | C62: =VLOOKUP(C$4,'Trading Comps_Input'!$B$9:$J$188,MATCH($B48,$B$42:$B$49,0)+1,FALSE) -> NYSE: TAP | D62: =VLOOKUP(D$4,'Trading Comps_Input'!$B$9:$J$188,MATCH($B48,$B$42:$B$49,0)+1,FALSE) -> 4233.824 | E62: =VLOOKUP(E$4,'Trading Comps_Input'!$B$9:$J$188,MATCH($B48,$B$42:$B$49,0)+1,FALSE) -> 5225.824 | F62: =VLOOKUP(F$4,'Trading Comps_Input'!$B$9:$J$188,MATCH($B48,$B$42:$B$49,0)+1,FALSE) -> 3032.4 | G62: =VLOOKUP(G$4,'Trading Comps_Input'!$B$9:$J$188,MATCH($B48,$B$42:$B$49,0)+1,FALSE) -> 631.6 | H62: =VLOOKUP(H$4,'Trading Comps_Input'!$B$9:$J$188,MATCH($B48,$B$42:$B$49,0)+1,FALSE) -> 423.6 | I62: =VLOOKUP(I$4,'Trading Comps_Input'!$B$9:$J$188,MATCH($B48,$B$42:$B$49,0)+1,FALSE) -> 0.99772668 | J62: =VLOOKUP(J$4,'Trading Comps_Input'!$B$9:$J$188,MATCH($B48,$B$42:$B$49,0)+1,FALSE) -> 3371.9869 | ... P62: =VLOOKUP(P$4,'Trading Comps_Input'!$B$9:$J$188,MATCH($B48,$B$42:$B$49,0)+1,FALSE) -> 184.4
B63: BOSTON BEER | C63: =VLOOKUP(C$4,'Trading Comps_Input'!$B$9:$J$188,MATCH($B49,$B$42:$B$49,0)+1,FALSE) -> NYSE: SAM | D63: =VLOOKUP(D$4,'Trading Comps_Input'!$B$9:$J$188,MATCH($B49,$B$42:$B$49,0)+1,FALSE) -> 705.58542 | E63: =VLOOKUP(E$4,'Trading Comps_Input'!$B$9:$J$188,MATCH($B49,$B$42:$B$49,0)+1,FALSE) -> 650.10442 | F63: =VLOOKUP(F$4,'Trading Comps_Input'!$B$9:$J$188,MATCH($B49,$B$42:$B$49,0)+1,FALSE) -> 415.053 | G63: =VLOOKUP(G$4,'Trading Comps_Input'!$B$9:$J$188,MATCH($B49,$B$42:$B$49,0)+1,FALSE) -> 72.239 | H63: =VLOOKUP(H$4,'Trading Comps_Input'!$B$9:$J$188,MATCH($B49,$B$42:$B$49,0)+1,FALSE) -> 55.32 | I63: =VLOOKUP(I$4,'Trading Comps_Input'!$B$9:$J$188,MATCH($B49,$B$42:$B$49,0)+1,FALSE) -> 2.2702953 | J63: =VLOOKUP(J$4,'Trading Comps_Input'!$B$9:$J$188,MATCH($B49,$B$42:$B$49,0)+1,FALSE) -> 446.19518 | ... P63: =VLOOKUP(P$4,'Trading Comps_Input'!$B$9:$J$188,MATCH($B49,$B$42:$B$49,0)+1,FALSE) -> 14.845054
B65: Hlookup & Match
B67: 동일한 논리, 차이점은 단지 어떻게 present하고 싶은지에 따라 HLOOKUP을 사용할 수 있음
B69: Company name | C69: Oriental Brewery | D69: HITE Brewery | E69: ASAHI GROUP | F69: TSINGTAO BREWERY | G69: CARLSBERG | H69: HEINEKEN | I69: MOLSON COORS | J69: BOSTON BEER
B70: Ticker | C70: =HLOOKUP(C$69,'Trading Comps_Input'!$B$9:$J$188,MATCH($B70,'Trading Comps_Input'!$B$9:$B$188,0),FALSE) -> OB | D70: =HLOOKUP(D$69,'Trading Comps_Input'!$B$9:$J$188,MATCH($B70,'Trading Comps_Input'!$B$9:$B$188,0),FALSE) -> KRX: 103150 | E70: =HLOOKUP(E$69,'Trading Comps_Input'!$B$9:$J$188,MATCH($B70,'Trading Comps_Input'!$B$9:$B$188,0),FALSE) -> TYO: 2502 | F70: =HLOOKUP(F$69,'Trading Comps_Input'!$B$9:$J$188,MATCH($B70,'Trading Comps_Input'!$B$9:$B$188,0),FALSE) -> SEHK:168 | G70: =HLOOKUP(G$69,'Trading Comps_Input'!$B$9:$J$188,MATCH($B70,'Trading Comps_Input'!$B$9:$B$188,0),FALSE) -> CPSE:CARL B | H70: =HLOOKUP(H$69,'Trading Comps_Input'!$B$9:$J$188,MATCH($B70,'Trading Comps_Input'!$B$9:$B$188,0),FALSE) -> ENXTAM:HEIA | I70: =HLOOKUP(I$69,'Trading Comps_Input'!$B$9:$J$188,MATCH($B70,'Trading Comps_Input'!$B$9:$B$188,0),FALSE) -> NYSE: TAP | J70: =HLOOKUP(J$69,'Trading Comps_Input'!$B$9:$J$188,MATCH($B70,'Trading Comps_Input'!$B$9:$B$188,0),FALSE) -> NYSE: SAM
B71: Market capitalization (mm) | C71: {=TRANSPOSE(D56:P63)} -> 0 | D71: 1624834.8 | E71: 806123.85 | F71: 21676.909 | G71: 60461.074 | H71: 17490.187 | I71: 4233.824 | J71: 705.58542
B72: Enterprise value (EV) | C72: 0 | D72: 2618390.5 | E72: 1184147.9 | F72: 17888.829 | G72: 101784.07 | H72: 25968.187 | I72: 5225.824 | J72: 650.10442
B73: Revenues - LFY | C73: 816110.19 | D73: 1049536 | E73: 1022318 | F73: 18026.108 | G73: 59382 | H73: 14701 | I73: 3032.4 | J73: 415.053
B74: EBITDA - LFY | C74: 251435.45 | D74: 259614.51 | E74: 141149 | F74: 2065.4427 | G74: 13307 | H74: 2672 | I74: 631.6 | J74: 72.239
B75: EBIT - LFY | C75: 196305.66 | D75: 187129.78 | E75: 82777 | F75: 1520.6809 | G75: 9538 | H75: 1777 | I75: 423.6 | J75: 55.32
B76: EPS - LFY | C76: 6629.0535 | D76: 10921.965 | E76: 103.09653 | F76: 0.95009959 | G76: 33.210292 | H76: 1.8990461 | I76: 0.99772668 | J76: 2.2702953
B77: Revenues - Calendar year 1 | C77: 840593.49 | D77: 1066105.2 | E77: 1084231.5 | F77: 20524.904 | G77: 60124.231 | H77: 16327.516 | I77: 3371.9869 | J77: 446.19518
B78: EBITDA - Calendar year 1 | C78: 258978.51 | D78: 232221.75 | E78: 162376.01 | F78: 2486.2697 | G78: 13519.078 | H78: 3186.5033 | I78: 639.03857 | J78: 102.67356
B79: EBIT - Calendar year 1 | C79: 202194.82 | D79: 151914.49 | E79: 95386.573 | F79: 1905.3395 | G79: 9759.7655 | H79: 1986.2587 | I79: 426.09416 | J79: 83.819889
B80: EPS - Calendar year 1 | C80: 6827.9251 | D80: 6821.3098 | E80: 115.68564 | F80: 1.129899 | G80: 33.09819 | H80: 2.711287 | I80: 3.668696 | J80: 3.407229
B81: Long-term growth rate | C81: 0.025 | D81: 0.025 | E81: 0.035 | F81: 0.035 | G81: 0.03 | H81: 0.035 | I81: 0.015 | J81: 0.035
B82: Net debt | C82: 301945.91 | D82: 993555.63 | E82: 378024 | F82: -3788.0802 | G82: 41323 | H82: 8478 | I82: 992 | J82: -55.481
B83: Diluted shares outstanding (mm) | C83: 20.611 | D83: 9.557852 | E83: 465.42948 | F83: 1315.3464 | G83: 152.64093 | H83: 488.41627 | I83: 184.4 | J83: 14.845054
B87: Transpose
B88: {=TRANSPOSE(B69:B83)} -> Company name | C88: Ticker | D88: Market capitalization (mm) | E88: Enterprise value (EV) | F88: Revenues - LFY | G88: EBITDA - LFY | H88: EBIT - LFY | I88: EPS - LFY | J88: Revenues - Calendar year 1 | K88: EBITDA - Calendar year 1 | L88: EBIT - Calendar year 1 | M88: EPS - Calendar year 1 | N88: Long-term growth rate | O88: Net debt | P88: Diluted shares outstanding (mm)
B89: {=TRANSPOSE(C69:J69)} -> Oriental Brewery | C89: {=TRANSPOSE(C70:J70)} -> OB
B90: HITE Brewery | C90: KRX: 103150
B91: ASAHI GROUP | C91: TYO: 2502
B92: TSINGTAO BREWERY | C92: SEHK:168
B93: CARLSBERG | C93: CPSE:CARL B
B94: HEINEKEN | C94: ENXTAM:HEIA
B95: MOLSON COORS | C95: NYSE: TAP
B96: BOSTON BEER | C96: NYSE: SAM
B99: Alt, e, s, e
B100: Company name | C100: Ticker | D100: Market capitalization (mm) | E100: Enterprise value (EV) | F100: Revenues - LFY | G100: EBITDA - LFY | H100: EBIT - LFY | I100: EPS - LFY | J100: Revenues - Calendar year 1 | K100: EBITDA - Calendar year 1 | L100: EBIT - Calendar year 1 | M100: EPS - Calendar year 1 | N100: Long-term growth rate | O100: Net debt | P100: Diluted shares outstanding (mm)
B101: Oriental Brewery
B102: HITE Brewery
B103: ASAHI GROUP
B104: TSINGTAO BREWERY
B105: CARLSBERG
B106: HEINEKEN
B107: MOLSON COORS
B108: BOSTON BEER
B117: 결과 거래배수
F118: Last Fiscal Year (LTM) | J118: Year 1 Forecast - Calendar Year
A119: x | B119: Name | C119: Ticker | F119: EV / Revenues | G119: EV / EBITDA | H119: EV / EBIT | I119: P/E | J119: EV / Revenues | K119: EV / EBITDA | L119: EV / EBIT | M119: P/E | N119: PEG ratio
B121: Oriental Brewery | C121: =C56 -> OB
B122: HITE Brewery | C122: =C57 -> KRX: 103150 | F122: =VLOOKUP(F$5,'Trading Comps_Input'!$B$9:$J$188,MATCH($B42,$B$42:$B$49,0)+2,FALSE) -> 2.4948078 | G122: =VLOOKUP(G$5,'Trading Comps_Input'!$B$9:$J$188,MATCH($B42,$B$42:$B$49,0)+2,FALSE) -> 10.085686 | H122: =VLOOKUP(H$5,'Trading Comps_Input'!$B$9:$J$188,MATCH($B42,$B$42:$B$49,0)+2,FALSE) -> 13.992377 | I122: =VLOOKUP(I$5,'Trading Comps_Input'!$B$9:$J$188,MATCH($B42,$B$42:$B$49,0)+2,FALSE) -> 15.564964 | J122: =VLOOKUP(J$5,'Trading Comps_Input'!$B$9:$J$188,MATCH($B42,$B$42:$B$49,0)+2,FALSE) -> 2.4560338 | K122: =VLOOKUP(K$5,'Trading Comps_Input'!$B$9:$J$188,MATCH($B42,$B$42:$B$49,0)+2,FALSE) -> 11.275389 | L122: =VLOOKUP(L$5,'Trading Comps_Input'!$B$9:$J$188,MATCH($B42,$B$42:$B$49,0)+2,FALSE) -> 17.235949 | M122: =VLOOKUP(M$5,'Trading Comps_Input'!$B$9:$J$188,MATCH($B42,$B$42:$B$49,0)+2,FALSE) -> 24.9219 | N122: =VLOOKUP(N$5,'Trading Comps_Input'!$B$9:$J$188,MATCH($B42,$B$42:$B$49,0)+2,FALSE) -> 9.96876
B123: ASAHI GROUP | C123: =C58 -> TYO: 2502 | F123: =VLOOKUP(F$5,'Trading Comps_Input'!$B$9:$J$188,MATCH($B43,$B$42:$B$49,0)+2,FALSE) -> 1.158297 | G123: =VLOOKUP(G$5,'Trading Comps_Input'!$B$9:$J$188,MATCH($B43,$B$42:$B$49,0)+2,FALSE) -> 8.3893464 | H123: =VLOOKUP(H$5,'Trading Comps_Input'!$B$9:$J$188,MATCH($B43,$B$42:$B$49,0)+2,FALSE) -> 14.305276 | I123: =VLOOKUP(I$5,'Trading Comps_Input'!$B$9:$J$188,MATCH($B43,$B$42:$B$49,0)+2,FALSE) -> 16.79979 | J123: =VLOOKUP(J$5,'Trading Comps_Input'!$B$9:$J$188,MATCH($B43,$B$42:$B$49,0)+2,FALSE) -> 1.092154 | K123: =VLOOKUP(K$5,'Trading Comps_Input'!$B$9:$J$188,MATCH($B43,$B$42:$B$49,0)+2,FALSE) -> 7.2926283 | L123: =VLOOKUP(L$5,'Trading Comps_Input'!$B$9:$J$188,MATCH($B43,$B$42:$B$49,0)+2,FALSE) -> 12.414199 | M123: =VLOOKUP(M$5,'Trading Comps_Input'!$B$9:$J$188,MATCH($B43,$B$42:$B$49,0)+2,FALSE) -> 14.971607 | N123: =VLOOKUP(N$5,'Trading Comps_Input'!$B$9:$J$188,MATCH($B43,$B$42:$B$49,0)+2,FALSE) -> 4.277602
B124: TSINGTAO BREWERY | C124: =C59 -> SEHK:168 | F124: =VLOOKUP(F$5,'Trading Comps_Input'!$B$9:$J$188,MATCH($B44,$B$42:$B$49,0)+2,FALSE) -> 0.99238446 | G124: =VLOOKUP(G$5,'Trading Comps_Input'!$B$9:$J$188,MATCH($B44,$B$42:$B$49,0)+2,FALSE) -> 8.6610147 | H124: =VLOOKUP(H$5,'Trading Comps_Input'!$B$9:$J$188,MATCH($B44,$B$42:$B$49,0)+2,FALSE) -> 11.763697 | I124: =VLOOKUP(I$5,'Trading Comps_Input'!$B$9:$J$188,MATCH($B44,$B$42:$B$49,0)+2,FALSE) -> 17.34555 | J124: =VLOOKUP(J$5,'Trading Comps_Input'!$B$9:$J$188,MATCH($B44,$B$42:$B$49,0)+2,FALSE) -> 0.87156703 | K124: =VLOOKUP(K$5,'Trading Comps_Input'!$B$9:$J$188,MATCH($B44,$B$42:$B$49,0)+2,FALSE) -> 7.1950477 | L124: =VLOOKUP(L$5,'Trading Comps_Input'!$B$9:$J$188,MATCH($B44,$B$42:$B$49,0)+2,FALSE) -> 9.3887884 | M124: =VLOOKUP(M$5,'Trading Comps_Input'!$B$9:$J$188,MATCH($B44,$B$42:$B$49,0)+2,FALSE) -> 14.585374 | N124: =VLOOKUP(N$5,'Trading Comps_Input'!$B$9:$J$188,MATCH($B44,$B$42:$B$49,0)+2,FALSE) -> 4.1672498
B125: CARLSBERG | C125: =C60 -> CPSE:CARL B | F125: =VLOOKUP(F$5,'Trading Comps_Input'!$B$9:$J$188,MATCH($B45,$B$42:$B$49,0)+2,FALSE) -> 1.714056 | G125: =VLOOKUP(G$5,'Trading Comps_Input'!$B$9:$J$188,MATCH($B45,$B$42:$B$49,0)+2,FALSE) -> 7.6489121 | H125: =VLOOKUP(H$5,'Trading Comps_Input'!$B$9:$J$188,MATCH($B45,$B$42:$B$49,0)+2,FALSE) -> 10.671427 | I125: =VLOOKUP(I$5,'Trading Comps_Input'!$B$9:$J$188,MATCH($B45,$B$42:$B$49,0)+2,FALSE) -> 11.927025 | J125: =VLOOKUP(J$5,'Trading Comps_Input'!$B$9:$J$188,MATCH($B45,$B$42:$B$49,0)+2,FALSE) -> 1.6928961 | K125: =VLOOKUP(K$5,'Trading Comps_Input'!$B$9:$J$188,MATCH($B45,$B$42:$B$49,0)+2,FALSE) -> 7.5289213 | L125: =VLOOKUP(L$5,'Trading Comps_Input'!$B$9:$J$188,MATCH($B45,$B$42:$B$49,0)+2,FALSE) -> 10.428947 | M125: =VLOOKUP(M$5,'Trading Comps_Input'!$B$9:$J$188,MATCH($B45,$B$42:$B$49,0)+2,FALSE) -> 11.967422 | N125: =VLOOKUP(N$5,'Trading Comps_Input'!$B$9:$J$188,MATCH($B45,$B$42:$B$49,0)+2,FALSE) -> 3.9891406
B126: HEINEKEN | C126: =C61 -> ENXTAM:HEIA | F126: =VLOOKUP(F$5,'Trading Comps_Input'!$B$9:$J$188,MATCH($B46,$B$42:$B$49,0)+2,FALSE) -> 1.7664232 | G126: =VLOOKUP(G$5,'Trading Comps_Input'!$B$9:$J$188,MATCH($B46,$B$42:$B$49,0)+2,FALSE) -> 9.7186328 | H126: =VLOOKUP(H$5,'Trading Comps_Input'!$B$9:$J$188,MATCH($B46,$B$42:$B$49,0)+2,FALSE) -> 14.613498 | I126: =VLOOKUP(I$5,'Trading Comps_Input'!$B$9:$J$188,MATCH($B46,$B$42:$B$49,0)+2,FALSE) -> 18.856836 | J126: =VLOOKUP(J$5,'Trading Comps_Input'!$B$9:$J$188,MATCH($B46,$B$42:$B$49,0)+2,FALSE) -> 1.5904555 | K126: =VLOOKUP(K$5,'Trading Comps_Input'!$B$9:$J$188,MATCH($B46,$B$42:$B$49,0)+2,FALSE) -> 8.1494305 | L126: =VLOOKUP(L$5,'Trading Comps_Input'!$B$9:$J$188,MATCH($B46,$B$42:$B$49,0)+2,FALSE) -> 13.07392 | M126: =VLOOKUP(M$5,'Trading Comps_Input'!$B$9:$J$188,MATCH($B46,$B$42:$B$49,0)+2,FALSE) -> 13.20775 | N126: =VLOOKUP(N$5,'Trading Comps_Input'!$B$9:$J$188,MATCH($B46,$B$42:$B$49,0)+2,FALSE) -> 3.7736428
B127: MOLSON COORS | C127: =C62 -> NYSE: TAP | F127: =VLOOKUP(F$5,'Trading Comps_Input'!$B$9:$J$188,MATCH($B47,$B$42:$B$49,0)+2,FALSE) -> 1.7233294 | G127: =VLOOKUP(G$5,'Trading Comps_Input'!$B$9:$J$188,MATCH($B47,$B$42:$B$49,0)+2,FALSE) -> 8.2739455 | H127: =VLOOKUP(H$5,'Trading Comps_Input'!$B$9:$J$188,MATCH($B47,$B$42:$B$49,0)+2,FALSE) -> 12.336695 | I127: =VLOOKUP(I$5,'Trading Comps_Input'!$B$9:$J$188,MATCH($B47,$B$42:$B$49,0)+2,FALSE) -> 23.012314 | J127: =VLOOKUP(J$5,'Trading Comps_Input'!$B$9:$J$188,MATCH($B47,$B$42:$B$49,0)+2,FALSE) -> 1.5497759 | K127: =VLOOKUP(K$5,'Trading Comps_Input'!$B$9:$J$188,MATCH($B47,$B$42:$B$49,0)+2,FALSE) -> 8.1776347 | L127: =VLOOKUP(L$5,'Trading Comps_Input'!$B$9:$J$188,MATCH($B47,$B$42:$B$49,0)+2,FALSE) -> 12.264482 | M127: =VLOOKUP(M$5,'Trading Comps_Input'!$B$9:$J$188,MATCH($B47,$B$42:$B$49,0)+2,FALSE) -> 6.2583545 | N127: =VLOOKUP(N$5,'Trading Comps_Input'!$B$9:$J$188,MATCH($B47,$B$42:$B$49,0)+2,FALSE) -> 4.1722363
B128: BOSTON BEER | C128: =C63 -> NYSE: SAM | F128: =VLOOKUP(F$5,'Trading Comps_Input'!$B$9:$J$188,MATCH($B48,$B$42:$B$49,0)+2,FALSE) -> 1.5663166 | G128: =VLOOKUP(G$5,'Trading Comps_Input'!$B$9:$J$188,MATCH($B48,$B$42:$B$49,0)+2,FALSE) -> 8.9993552 | H128: =VLOOKUP(H$5,'Trading Comps_Input'!$B$9:$J$188,MATCH($B48,$B$42:$B$49,0)+2,FALSE) -> 11.751707 | I128: =VLOOKUP(I$5,'Trading Comps_Input'!$B$9:$J$188,MATCH($B48,$B$42:$B$49,0)+2,FALSE) -> 20.935603 | J128: =VLOOKUP(J$5,'Trading Comps_Input'!$B$9:$J$188,MATCH($B48,$B$42:$B$49,0)+2,FALSE) -> 1.4569956 | K128: =VLOOKUP(K$5,'Trading Comps_Input'!$B$9:$J$188,MATCH($B48,$B$42:$B$49,0)+2,FALSE) -> 6.3317605 | L128: =VLOOKUP(L$5,'Trading Comps_Input'!$B$9:$J$188,MATCH($B48,$B$42:$B$49,0)+2,FALSE) -> 7.7559685 | M128: =VLOOKUP(M$5,'Trading Comps_Input'!$B$9:$J$188,MATCH($B48,$B$42:$B$49,0)+2,FALSE) -> 13.949752 | N128: =VLOOKUP(N$5,'Trading Comps_Input'!$B$9:$J$188,MATCH($B48,$B$42:$B$49,0)+2,FALSE) -> 3.9856435
A131: x | E131: High | F131: =MAX(F$121:F$128) -> 2.4948078 | G131: =MAX(G$121:G$128) -> 10.085686 | H131: =MAX(H$121:H$128) -> 14.613498 | I131: =MAX(I$121:I$128) -> 23.012314 | J131: =MAX(J$121:J$128) -> 2.4560338 | K131: =MAX(K$121:K$128) -> 11.275389 | L131: =MAX(L$121:L$128) -> 17.235949 | M131: =MAX(M$121:M$128) -> 24.9219 | N131: =MAX(N$121:N$128) -> 9.96876
E132: Median | F132: =MEDIAN(F$121:F$128) -> 1.714056 | G132: =MEDIAN(G$121:G$128) -> 8.6610147 | H132: =MEDIAN(H$121:H$128) -> 12.336695 | I132: =MEDIAN(I$121:I$128) -> 17.34555 | J132: =MEDIAN(J$121:J$128) -> 1.5497759 | K132: =MEDIAN(K$121:K$128) -> 7.5289213 | L132: =MEDIAN(L$121:L$128) -> 12.264482 | M132: =MEDIAN(M$121:M$128) -> 13.949752 | N132: =MEDIAN(N$121:N$128) -> 4.1672498
E133: Low | F133: =MIN(F$121:F$128) -> 0.99238446 | G133: =MIN(G$121:G$128) -> 7.6489121 | H133: =MIN(H$121:H$128) -> 10.671427 | I133: =MIN(I$121:I$128) -> 11.927025 | J133: =MIN(J$121:J$128) -> 0.87156703 | K133: =MIN(K$121:K$128) -> 6.3317605 | L133: =MIN(L$121:L$128) -> 7.7559685 | M133: =MIN(M$121:M$128) -> 6.2583545 | N133: =MIN(N$121:N$128) -> 3.7736428
...

Sheet Trading Comps_Output (정답)
A1: OB맥주
A2: Comparable Company Analysis ("Trading Comps") - Output
B4: Company name | C4: Ticker | D4: Market capitalization (mm) | E4: Enterprise value (EV) | F4: Revenues - LFY | G4: EBITDA - LFY | H4: EBIT - LFY | I4: EPS - LFY | J4: Revenues - Calendar year 1 | K4: EBITDA - Calendar year 1 | L4: EBIT - Calendar year 1 | M4: EPS - Calendar year 1 | N4: Long-term growth rate | O4: Net debt | P4: Diluted shares outstanding (mm)
F5: EV / Revenues - LFY | G5: EV / EBITDA - LFY | H5: EV / EBIT - LFY | I5: P/E - LFY | J5: EV / Revenues - Year 1 | K5: EV / EBITDA - Year 1 | L5: EV / EBIT - Year 1 | M5: P/E - Year 1 | N5: PE/LTG (PEG ratio)
B7: 재무정보 요약
B9: 단순 링크
F11: Last Fiscal Year (LTM) | J11: Year 1 Forecast - Calendar Year
B12: Name | C12: Ticker | D12: Market cap (mm) | E12: Enterprise value | F12: Revenues | G12: EBITDA | H12: EBIT | I12: EPS | J12: Revenues | K12: EBITDA | L12: EBIT | M12: EPS | N12: LT growth rate | O12: Net debt | P12: Diluted shares outstanding
B13: Place target in first position
B14: Oriental Brewery | C14: =+'Trading Comps_Input'!C10 -> OB | F14: =+'Trading Comps_Input'!C109 -> 816110.19 | G14: =+'Trading Comps_Input'!C110 -> 251435.45 | H14: =+'Trading Comps_Input'!C111 -> 196305.66 | I14: =+'Trading Comps_Input'!C112 -> 6629.0535 | J14: =+'Trading Comps_Input'!C129 -> 840593.49 | K14: =+'Trading Comps_Input'!C130 -> 258978.51 | L14: =+'Trading Comps_Input'!C131 -> 202194.82 | M14: =+'Trading Comps_Input'!C132 -> 6827.9251 | N14: =+'Trading Comps_Input'!C146 -> 0.025 | O14: =+'Trading Comps_Input'!C123 -> 301945.91 | P14: =+'Trading Comps_Input'!C168 -> 20.611 | S14: ①
B15: HITE Brewery | C15: =+'Trading Comps_Input'!D10 -> KRX: 103150 | D15: =+'Trading Comps_Input'!D170 -> 1624834.8 | E15: =+'Trading Comps_Input'!D173 -> 2618390.5 | F15: =+'Trading Comps_Input'!D109 -> 1049536 | G15: =+'Trading Comps_Input'!D110 -> 259614.51 | H15: =+'Trading Comps_Input'!D111 -> 187129.78 | I15: =+'Trading Comps_Input'!D112 -> 10921.965 | J15: =+'Trading Comps_Input'!D129 -> 1066105.2 | K15: =+'Trading Comps_Input'!D130 -> 232221.75 | L15: =+'Trading Comps_Input'!D131 -> 151914.49 | M15: =+'Trading Comps_Input'!D132 -> 6821.3098 | N15: =+'Trading Comps_Input'!D146 -> 0.025 | O15: =+'Trading Comps_Input'!D123 -> 993555.63 | P15: =+'Trading Comps_Input'!D168 -> 9.557852 | S15: ②
B16: ASAHI GROUP | C16: =+'Trading Comps_Input'!E10 -> TYO: 2502 | D16: =+'Trading Comps_Input'!E170 -> 806123.85 | E16: =+'Trading Comps_Input'!E173 -> 1184147.9 | F16: =+'Trading Comps_Input'!E109 -> 1022318 | G16: =+'Trading Comps_Input'!E110 -> 141149 | H16: =+'Trading Comps_Input'!E111 -> 82777 | I16: =+'Trading Comps_Input'!E112 -> 103.09653 | J16: =+'Trading Comps_Input'!E129 -> 1084231.5 | K16: =+'Trading Comps_Input'!E130 -> 162376.01 | L16: =+'Trading Comps_Input'!E131 -> 95386.573 | M16: =+'Trading Comps_Input'!E132 -> 115.68564 | N16: =+'Trading Comps_Input'!E146 -> 0.035 | O16: =+'Trading Comps_Input'!E123 -> 378024 | P16: =+'Trading Comps_Input'!E168 -> 465.42948 | S16: ③
B17: TSINGTAO BREWERY | C17: =+'Trading Comps_Input'!F10 -> SEHK:168 | D17: =+'Trading Comps_Input'!F170 -> 21676.909 | E17: =+'Trading Comps_Input'!F173 -> 17888.829 | F17: =+'Trading Comps_Input'!F109 -> 18026.108 | G17: =+'Trading Comps_Input'!F110 -> 2065.4427 | H17: =+'Trading Comps_Input'!F111 -> 1520.6809 | I17: =+'Trading Comps_Input'!F112 -> 0.95009959 | J17: =+'Trading Comps_Input'!F129 -> 20524.904 | K17: =+'Trading Comps_Input'!F130 -> 2486.2697 | L17: =+'Trading Comps_Input'!F131 -> 1905.3395 | M17: =+'Trading Comps_Input'!F132 -> 1.129899 | N17: =+'Trading Comps_Input'!F146 -> 0.035 | O17: =+'Trading Comps_Input'!F123 -> -3788.0802 | P17: =+'Trading Comps_Input'!F168 -> 1315.3464
B18: CARLSBERG | C18: =+'Trading Comps_Input'!G10 -> CPSE:CARL B | D18: =+'Trading Comps_Input'!G170 -> 60461.074 | E18: =+'Trading Comps_Input'!G173 -> 101784.07 | F18: =+'Trading Comps_Input'!G109 -> 59382 | G18: =+'Trading Comps_Input'!G110 -> 13307 | H18: =+'Trading Comps_Input'!G111 -> 9538 | I18: =+'Trading Comps_Input'!G112 -> 33.210292 | J18: =+'Trading Comps_Input'!G129 -> 60124.231 | K18: =+'Trading Comps_Input'!G130 -> 13519.078 | L18: =+'Trading Comps_Input'!G131 -> 9759.7655 | M18: =+'Trading Comps_Input'!G132 -> 33.09819 | N18: =+'Trading Comps_Input'!G146 -> 0.03 | O18: =+'Trading Comps_Input'!G123 -> 41323 | P18: =+'Trading Comps_Input'!G168 -> 152.64093 | S18: ※
B19: HEINEKEN | C19: =+'Trading Comps_Input'!H10 -> ENXTAM:HEIA | D19: =+'Trading Comps_Input'!H170 -> 17490.187 | E19: =+'Trading Comps_Input'!H173 -> 25968.187 | F19: =+'Trading Comps_Input'!H109 -> 14701 | G19: =+'Trading Comps_Input'!H110 -> 2672 | H19: =+'Trading Comps_Input'!H111 -> 1777 | I19: =+'Trading Comps_Input'!H112 -> 1.8990461 | J19: =+'Trading Comps_Input'!H129 -> 16327.516 | K19: =+'Trading Comps_Input'!H130 -> 3186.5033 | L19: =+'Trading Comps_Input'!H131 -> 1986.2587 | M19: =+'Trading Comps_Input'!H132 -> 2.711287 | N19: =+'Trading Comps_Input'!H146 -> 0.035 | O19: =+'Trading Comps_Input'!H123 -> 8478 | P19: =+'Trading Comps_Input'!H168 -> 488.41627
B20: MOLSON COORS | C20: =+'Trading Comps_Input'!I10 -> NYSE: TAP | D20: =+'Trading Comps_Input'!I170 -> 4233.824 | E20: =+'Trading Comps_Input'!I173 -> 5225.824 | F20: =+'Trading Comps_Input'!I109 -> 3032.4 | G20: =+'Trading Comps_Input'!I110 -> 631.6 | H20: =+'Trading Comps_Input'!I111 -> 423.6 | I20: =+'Trading Comps_Input'!I112 -> 0.99772668 | J20: =+'Trading Comps_Input'!I129 -> 3371.9869 | K20: =+'Trading Comps_Input'!I130 -> 639.03857 | L20: =+'Trading Comps_Input'!I131 -> 426.09416 | M20: =+'Trading Comps_Input'!I132 -> 3.668696 | N20: =+'Trading Comps_Input'!I146 -> 0.015 | O20: =+'Trading Comps_Input'!I123 -> 992 | P20: =+'Trading Comps_Input'!I168 -> 184.4
B21: BOSTON BEER | C21: =+'Trading Comps_Input'!J10 -> NYSE: SAM | D21: =+'Trading Comps_Input'!J170 -> 705.58542 | E21: =+'Trading Comps_Input'!J173 -> 650.10442 | F21: =+'Trading Comps_Input'!J109 -> 415.053 | G21: =+'Trading Comps_Input'!J110 -> 72.239 | H21: =+'Trading Comps_Input'!J111 -> 55.32 | I21: =+'Trading Comps_Input'!J112 -> 2.2702953 | J21: =+'Trading Comps_Input'!J129 -> 446.19518 | K21: =+'Trading Comps_Input'!J130 -> 102.67356 | L21: =+'Trading Comps_Input'!J131 -> 83.819889 | M21: =+'Trading Comps_Input'!J132 -> 3.407229 | N21: =+'Trading Comps_Input'!J146 -> 0.035 | O21: =+'Trading Comps_Input'!J123 -> -55.481 | P21: =+'Trading Comps_Input'!J168 -> 14.845054
B24: Vlookup
F26: Last Fiscal Year (LTM) | J26: Year 1 Forecast - Calendar Year
B27: Name | C27: Ticker | D27: Market cap (mm) | E27: Enterprise value | F27: Revenues | G27: EBITDA | H27: EBIT | I27: EPS | J27: Revenues | K27: EBITDA | L27: EBIT | M27: EPS | N27: LT growth rate | O27: Net debt | P27: Diluted shares outstanding
B29: Oriental Brewery | C29: =VLOOKUP(C$4,'Trading Comps_Input'!$B$9:$J$188,2,FALSE) -> OB | D29: =VLOOKUP(D$4,'Trading Comps_Input'!$B$9:$J$188,2,FALSE) -> 0 | E29: =VLOOKUP(E$4,'Trading Comps_Input'!$B$9:$J$188,2,FALSE) -> 0 | F29: =VLOOKUP(F$4,'Trading Comps_Input'!$B$9:$J$188,2,FALSE) -> 816110.19 | G29: =VLOOKUP(G$4,'Trading Comps_Input'!$B$9:$J$188,2,FALSE) -> 251435.45 | H29: =VLOOKUP(H$4,'Trading Comps_Input'!$B$9:$J$188,2,FALSE) -> 196305.66 | I29: =VLOOKUP(I$4,'Trading Comps_Input'!$B$9:$J$188,2,FALSE) -> 6629.0535 | J29: =VLOOKUP(J$4,'Trading Comps_Input'!$B$9:$J$188,2,FALSE) -> 840593.49 | ... P29: =VLOOKUP(P$4,'Trading Comps_Input'!$B$9:$J$188,2,FALSE) -> 20.611
B30: HITE Brewery | C30: =VLOOKUP(C$4,'Trading Comps_Input'!$B$9:$J$188,3,FALSE) -> KRX: 103150 | D30: =VLOOKUP(D$4,'Trading Comps_Input'!$B$9:$J$188,3,FALSE) -> 1624834.8 | E30: =VLOOKUP(E$4,'Trading Comps_Input'!$B$9:$J$188,3,FALSE) -> 2618390.5 | F30: =VLOOKUP(F$4,'Trading Comps_Input'!$B$9:$J$188,3,FALSE) -> 1049536 | G30: =VLOOKUP(G$4,'Trading Comps_Input'!$B$9:$J$188,3,FALSE) -> 259614.51 | H30: =VLOOKUP(H$4,'Trading Comps_Input'!$B$9:$J$188,3,FALSE) -> 187129.78 | I30: =VLOOKUP(I$4,'Trading Comps_Input'!$B$9:$J$188,3,FALSE) -> 10921.965 | J30: =VLOOKUP(J$4,'Trading Comps_Input'!$B$9:$J$188,3,FALSE) -> 1066105.2 | ... P30: =VLOOKUP(P$4,'Trading Comps_Input'!$B$9:$J$188,3,FALSE) -> 9.557852
B31: ASAHI GROUP | C31: =VLOOKUP(C$4,'Trading Comps_Input'!$B$9:$J$188,5,FALSE) -> SEHK:168 | D31: =VLOOKUP(D$4,'Trading Comps_Input'!$B$9:$J$188,5,FALSE) -> 21676.909 | E31: =VLOOKUP(E$4,'Trading Comps_Input'!$B$9:$J$188,5,FALSE) -> 17888.829 | F31: =VLOOKUP(F$4,'Trading Comps_Input'!$B$9:$J$188,5,FALSE) -> 18026.108 | G31: =VLOOKUP(G$4,'Trading Comps_Input'!$B$9:$J$188,5,FALSE) -> 2065.4427 | H31: =VLOOKUP(H$4,'Trading Comps_Input'!$B$9:$J$188,5,FALSE) -> 1520.6809 | I31: =VLOOKUP(I$4,'Trading Comps_Input'!$B$9:$J$188,5,FALSE) -> 0.95009959 | J31: =VLOOKUP(J$4,'Trading Comps_Input'!$B$9:$J$188,5,FALSE) -> 20524.904 | ... P31: =VLOOKUP(P$4,'Trading Comps_Input'!$B$9:$J$188,5,FALSE) -> 1315.3464
B32: TSINGTAO BREWERY | C32: =VLOOKUP(C$4,'Trading Comps_Input'!$B$9:$J$188,6,FALSE) -> CPSE:CARL B | D32: =VLOOKUP(D$4,'Trading Comps_Input'!$B$9:$J$188,6,FALSE) -> 60461.074 | E32: =VLOOKUP(E$4,'Trading Comps_Input'!$B$9:$J$188,6,FALSE) -> 101784.07 | F32: =VLOOKUP(F$4,'Trading Comps_Input'!$B$9:$J$188,6,FALSE) -> 59382 | G32: =VLOOKUP(G$4,'Trading Comps_Input'!$B$9:$J$188,6,FALSE) -> 13307 | H32: =VLOOKUP(H$4,'Trading Comps_Input'!$B$9:$J$188,6,FALSE) -> 9538 | I32: =VLOOKUP(I$4,'Trading Comps_Input'!$B$9:$J$188,6,FALSE) -> 33.210292 | J32: =VLOOKUP(J$4,'Trading Comps_Input'!$B$9:$J$188,6,FALSE) -> 60124.231 | ... P32: =VLOOKUP(P$4,'Trading Comps_Input'!$B$9:$J$188,6,FALSE) -> 152.64093
B33: CARLSBERG | C33: =VLOOKUP(C$4,'Trading Comps_Input'!$B$9:$J$188,8,FALSE) -> NYSE: TAP | D33: =VLOOKUP(D$4,'Trading Comps_Input'!$B$9:$J$188,8,FALSE) -> 4233.824 | E33: =VLOOKUP(E$4,'Trading Comps_Input'!$B$9:$J$188,8,FALSE) -> 5225.824 | F33: =VLOOKUP(F$4,'Trading Comps_Input'!$B$9:$J$188,8,FALSE) -> 3032.4 | G33: =VLOOKUP(G$4,'Trading Comps_Input'!$B$9:$J$188,8,FALSE) -> 631.6 | H33: =VLOOKUP(H$4,'Trading Comps_Input'!$B$9:$J$188,8,FALSE) -> 423.6 | I33: =VLOOKUP(I$4,'Trading Comps_Input'!$B$9:$J$188,8,FALSE) -> 0.99772668 | J33: =VLOOKUP(J$4,'Trading Comps_Input'!$B$9:$J$188,8,FALSE) -> 3371.9869 | ... P33: =VLOOKUP(P$4,'Trading Comps_Input'!$B$9:$J$188,8,FALSE) -> 184.4
B34: HEINEKEN | C34: =VLOOKUP(C$4,'Trading Comps_Input'!$B$9:$J$188,9,FALSE) -> NYSE: SAM | D34: =VLOOKUP(D$4,'Trading Comps_Input'!$B$9:$J$188,9,FALSE) -> 705.58542 | E34: =VLOOKUP(E$4,'Trading Comps_Input'!$B$9:$J$188,9,FALSE) -> 650.10442 | F34: =VLOOKUP(F$4,'Trading Comps_Input'!$B$9:$J$188,9,FALSE) -> 415.053 | G34: =VLOOKUP(G$4,'Trading Comps_Input'!$B$9:$J$188,9,FALSE) -> 72.239 | H34: =VLOOKUP(H$4,'Trading Comps_Input'!$B$9:$J$188,9,FALSE) -> 55.32 | I34: =VLOOKUP(I$4,'Trading Comps_Input'!$B$9:$J$188,9,FALSE) -> 2.2702953 | J34: =VLOOKUP(J$4,'Trading Comps_Input'!$B$9:$J$188,9,FALSE) -> 446.19518 | ... P34: =VLOOKUP(P$4,'Trading Comps_Input'!$B$9:$J$188,9,FALSE) -> 14.845054
B35: MOLSON COORS | C35: =VLOOKUP(C$4,'Trading Comps_Input'!$B$9:$J$188,10,FALSE) -> #REF! | D35: =VLOOKUP(D$4,'Trading Comps_Input'!$B$9:$J$188,10,FALSE) -> #REF! | E35: =VLOOKUP(E$4,'Trading Comps_Input'!$B$9:$J$188,10,FALSE) -> #REF! | F35: =VLOOKUP(F$4,'Trading Comps_Input'!$B$9:$J$188,10,FALSE) -> #REF! | G35: =VLOOKUP(G$4,'Trading Comps_Input'!$B$9:$J$188,10,FALSE) -> #REF! | H35: =VLOOKUP(H$4,'Trading Comps_Input'!$B$9:$J$188,10,FALSE) -> #REF! | I35: =VLOOKUP(I$4,'Trading Comps_Input'!$B$9:$J$188,10,FALSE) -> #REF! | J35: =VLOOKUP(J$4,'Trading Comps_Input'!$B$9:$J$188,10,FALSE) -> #REF! | ... P35: =VLOOKUP(P$4,'Trading Comps_Input'!$B$9:$J$188,10,FALSE) -> #REF!
B36: BOSTON BEER | C36: =VLOOKUP(C$4,'Trading Comps_Input'!$B$9:$J$188,11,FALSE) -> #REF! | D36: =VLOOKUP(D$4,'Trading Comps_Input'!$B$9:$J$188,11,FALSE) -> #REF! | E36: =VLOOKUP(E$4,'Trading Comps_Input'!$B$9:$J$188,11,FALSE) -> #REF! | F36: =VLOOKUP(F$4,'Trading Comps_Input'!$B$9:$J$188,11,FALSE) -> #REF! | G36: =VLOOKUP(G$4,'Trading Comps_Input'!$B$9:$J$188,11,FALSE) -> #REF! | H36: =VLOOKUP(H$4,'Trading Comps_Input'!$B$9:$J$188,11,FALSE) -> #REF! | I36: =VLOOKUP(I$4,'Trading Comps_Input'!$B$9:$J$188,11,FALSE) -> #REF! | J36: =VLOOKUP(J$4,'Trading Comps_Input'!$B$9:$J$188,11,FALSE) -> #REF! | ... P36: =VLOOKUP(P$4,'Trading Comps_Input'!$B$9:$J$188,11,FALSE) -> #REF!
B38: Vlookup & Match
B40: Match
C41: 범위 안에서 순서
B42: Oriental Brewery | C42: =MATCH(B42,$B$42:$B$49,0) -> 1
B43: HITE Brewery | C43: =MATCH(B43,$B$42:$B$49,0) -> 2
B44: ASAHI GROUP | C44: =MATCH(B44,$B$42:$B$49,0) -> 3
B45: TSINGTAO BREWERY | C45: =MATCH(B45,$B$42:$B$49,0) -> 4
B46: CARLSBERG | C46: =MATCH(B46,$B$42:$B$49,0) -> 5
B47: HEINEKEN | C47: =MATCH(B47,$B$42:$B$49,0) -> 6
B48: MOLSON COORS | C48: =MATCH(B48,$B$42:$B$49,0) -> 7
B49: BOSTON BEER | C49: =MATCH(B49,$B$42:$B$49,0) -> 8
F53: Last Fiscal Year (LTM) | J53: Year 1 Forecast - Calendar Year
B54: Name | C54: Ticker | D54: Market cap (mm) | E54: Enterprise value | F54: Revenues | G54: EBITDA | H54: EBIT | I54: EPS | J54: Revenues | K54: EBITDA | L54: EBIT | M54: EPS | N54: LT growth rate | O54: Net debt | P54: Diluted shares outstanding
B56: Oriental Brewery | C56: =VLOOKUP(C$4,'Trading Comps_Input'!$B$9:$J$188,MATCH($B56,'Trading Comps_Input'!$C$9:$J$9,0)+1,FALSE) -> OB | D56: =VLOOKUP(D$4,'Trading Comps_Input'!$B$9:$J$188,MATCH($B56,'Trading Comps_Input'!$C$9:$J$9,0)+1,FALSE) -> 0 | E56: =VLOOKUP(E$4,'Trading Comps_Input'!$B$9:$J$188,MATCH($B56,'Trading Comps_Input'!$C$9:$J$9,0)+1,FALSE) -> 0 | F56: =VLOOKUP(F$4,'Trading Comps_Input'!$B$9:$J$188,MATCH($B56,'Trading Comps_Input'!$C$9:$J$9,0)+1,FALSE) -> 816110.19 | G56: =VLOOKUP(G$4,'Trading Comps_Input'!$B$9:$J$188,MATCH($B56,'Trading Comps_Input'!$C$9:$J$9,0)+1,FALSE) -> 251435.45 | H56: =VLOOKUP(H$4,'Trading Comps_Input'!$B$9:$J$188,MATCH($B56,'Trading Comps_Input'!$C$9:$J$9,0)+1,FALSE) -> 196305.66 | I56: =VLOOKUP(I$4,'Trading Comps_Input'!$B$9:$J$188,MATCH($B56,'Trading Comps_Input'!$C$9:$J$9,0)+1,FALSE) -> 6629.0535 | J56: =VLOOKUP(J$4,'Trading Comps_Input'!$B$9:$J$188,MATCH($B56,'Trading Comps_Input'!$C$9:$J$9,0)+1,FALSE) -> 840593.49 | ... P56: =VLOOKUP(P$4,'Trading Comps_Input'!$B$9:$J$188,MATCH($B56,'Trading Comps_Input'!$C$9:$J$9,0)+1,FALSE) -> 20.611
B57: HITE Brewery | C57: =VLOOKUP(C$4,'Trading Comps_Input'!$B$9:$J$188,MATCH($B57,'Trading Comps_Input'!$B$9:$J$9,0),FALSE) -> KRX: 103150 | D57: =VLOOKUP(D$4,'Trading Comps_Input'!$B$9:$J$188,MATCH($B57,'Trading Comps_Input'!$B$9:$J$9,0),FALSE) -> 1624834.8 | E57: =VLOOKUP(E$4,'Trading Comps_Input'!$B$9:$J$188,MATCH($B57,'Trading Comps_Input'!$B$9:$J$9,0),FALSE) -> 2618390.5 | F57: =VLOOKUP(F$4,'Trading Comps_Input'!$B$9:$J$188,MATCH($B57,'Trading Comps_Input'!$B$9:$J$9,0),FALSE) -> 1049536 | G57: =VLOOKUP(G$4,'Trading Comps_Input'!$B$9:$J$188,MATCH($B57,'Trading Comps_Input'!$B$9:$J$9,0),FALSE) -> 259614.51 | H57: =VLOOKUP(H$4,'Trading Comps_Input'!$B$9:$J$188,MATCH($B57,'Trading Comps_Input'!$B$9:$J$9,0),FALSE) -> 187129.78 | I57: =VLOOKUP(I$4,'Trading Comps_Input'!$B$9:$J$188,MATCH($B57,'Trading Comps_Input'!$B$9:$J$9,0),FALSE) -> 10921.965 | J57: =VLOOKUP(J$4,'Trading Comps_Input'!$B$9:$J$188,MATCH($B57,'Trading Comps_Input'!$B$9:$J$9,0),FALSE) -> 1066105.2 | ... P57: =VLOOKUP(P$4,'Trading Comps_Input'!$B$9:$J$188,MATCH($B57,'Trading Comps_Input'!$B$9:$J$9,0),FALSE) -> 9.557852
B58: ASAHI GROUP | C58: =VLOOKUP(C$4,'Trading Comps_Input'!$B$9:$J$188,MATCH($B58,'Trading Comps_Input'!$B$9:$J$9,0),FALSE) -> TYO: 2502 | D58: =VLOOKUP(D$4,'Trading Comps_Input'!$B$9:$J$188,MATCH($B58,'Trading Comps_Input'!$B$9:$J$9,0),FALSE) -> 806123.85 | E58: =VLOOKUP(E$4,'Trading Comps_Input'!$B$9:$J$188,MATCH($B58,'Trading Comps_Input'!$B$9:$J$9,0),FALSE) -> 1184147.9 | F58: =VLOOKUP(F$4,'Trading Comps_Input'!$B$9:$J$188,MATCH($B58,'Trading Comps_Input'!$B$9:$J$9,0),FALSE) -> 1022318 | G58: =VLOOKUP(G$4,'Trading Comps_Input'!$B$9:$J$188,MATCH($B58,'Trading Comps_Input'!$B$9:$J$9,0),FALSE) -> 141149 | H58: =VLOOKUP(H$4,'Trading Comps_Input'!$B$9:$J$188,MATCH($B58,'Trading Comps_Input'!$B$9:$J$9,0),FALSE) -> 82777 | I58: =VLOOKUP(I$4,'Trading Comps_Input'!$B$9:$J$188,MATCH($B58,'Trading Comps_Input'!$B$9:$J$9,0),FALSE) -> 103.09653 | J58: =VLOOKUP(J$4,'Trading Comps_Input'!$B$9:$J$188,MATCH($B58,'Trading Comps_Input'!$B$9:$J$9,0),FALSE) -> 1084231.5 | ... P58: =VLOOKUP(P$4,'Trading Comps_Input'!$B$9:$J$188,MATCH($B58,'Trading Comps_Input'!$B$9:$J$9,0),FALSE) -> 465.42948
B59: TSINGTAO BREWERY | C59: =VLOOKUP(C$4,'Trading Comps_Input'!$B$9:$J$188,MATCH($B59,'Trading Comps_Input'!$B$9:$J$9,0),FALSE) -> SEHK:168 | D59: =VLOOKUP(D$4,'Trading Comps_Input'!$B$9:$J$188,MATCH($B59,'Trading Comps_Input'!$B$9:$J$9,0),FALSE) -> 21676.909 | E59: =VLOOKUP(E$4,'Trading Comps_Input'!$B$9:$J$188,MATCH($B59,'Trading Comps_Input'!$B$9:$J$9,0),FALSE) -> 17888.829 | F59: =VLOOKUP(F$4,'Trading Comps_Input'!$B$9:$J$188,MATCH($B59,'Trading Comps_Input'!$B$9:$J$9,0),FALSE) -> 18026.108 | G59: =VLOOKUP(G$4,'Trading Comps_Input'!$B$9:$J$188,MATCH($B59,'Trading Comps_Input'!$B$9:$J$9,0),FALSE) -> 2065.4427 | H59: =VLOOKUP(H$4,'Trading Comps_Input'!$B$9:$J$188,MATCH($B59,'Trading Comps_Input'!$B$9:$J$9,0),FALSE) -> 1520.6809 | I59: =VLOOKUP(I$4,'Trading Comps_Input'!$B$9:$J$188,MATCH($B59,'Trading Comps_Input'!$B$9:$J$9,0),FALSE) -> 0.95009959 | J59: =VLOOKUP(J$4,'Trading Comps_Input'!$B$9:$J$188,MATCH($B59,'Trading Comps_Input'!$B$9:$J$9,0),FALSE) -> 20524.904 | ... P59: =VLOOKUP(P$4,'Trading Comps_Input'!$B$9:$J$188,MATCH($B59,'Trading Comps_Input'!$B$9:$J$9,0),FALSE) -> 1315.3464
B60: CARLSBERG | C60: =VLOOKUP(C$4,'Trading Comps_Input'!$B$9:$J$188,MATCH($B60,'Trading Comps_Input'!$B$9:$J$9,0),FALSE) -> CPSE:CARL B | D60: =VLOOKUP(D$4,'Trading Comps_Input'!$B$9:$J$188,MATCH($B60,'Trading Comps_Input'!$B$9:$J$9,0),FALSE) -> 60461.074 | E60: =VLOOKUP(E$4,'Trading Comps_Input'!$B$9:$J$188,MATCH($B60,'Trading Comps_Input'!$B$9:$J$9,0),FALSE) -> 101784.07 | F60: =VLOOKUP(F$4,'Trading Comps_Input'!$B$9:$J$188,MATCH($B60,'Trading Comps_Input'!$B$9:$J$9,0),FALSE) -> 59382 | G60: =VLOOKUP(G$4,'Trading Comps_Input'!$B$9:$J$188,MATCH($B60,'Trading Comps_Input'!$B$9:$J$9,0),FALSE) -> 13307 | H60: =VLOOKUP(H$4,'Trading Comps_Input'!$B$9:$J$188,MATCH($B60,'Trading Comps_Input'!$B$9:$J$9,0),FALSE) -> 9538 | I60: =VLOOKUP(I$4,'Trading Comps_Input'!$B$9:$J$188,MATCH($B60,'Trading Comps_Input'!$B$9:$J$9,0),FALSE) -> 33.210292 | J60: =VLOOKUP(J$4,'Trading Comps_Input'!$B$9:$J$188,MATCH($B60,'Trading Comps_Input'!$B$9:$J$9,0),FALSE) -> 60124.231 | ... P60: =VLOOKUP(P$4,'Trading Comps_Input'!$B$9:$J$188,MATCH($B60,'Trading Comps_Input'!$B$9:$J$9,0),FALSE) -> 152.64093
B61: HEINEKEN | C61: =VLOOKUP(C$4,'Trading Comps_Input'!$B$9:$J$188,MATCH($B61,'Trading Comps_Input'!$B$9:$J$9,0),FALSE) -> ENXTAM:HEIA | D61: =VLOOKUP(D$4,'Trading Comps_Input'!$B$9:$J$188,MATCH($B61,'Trading Comps_Input'!$B$9:$J$9,0),FALSE) -> 17490.187 | E61: =VLOOKUP(E$4,'Trading Comps_Input'!$B$9:$J$188,MATCH($B61,'Trading Comps_Input'!$B$9:$J$9,0),FALSE) -> 25968.187 | F61: =VLOOKUP(F$4,'Trading Comps_Input'!$B$9:$J$188,MATCH($B61,'Trading Comps_Input'!$B$9:$J$9,0),FALSE) -> 14701 | G61: =VLOOKUP(G$4,'Trading Comps_Input'!$B$9:$J$188,MATCH($B61,'Trading Comps_Input'!$B$9:$J$9,0),FALSE) -> 2672 | H61: =VLOOKUP(H$4,'Trading Comps_Input'!$B$9:$J$188,MATCH($B61,'Trading Comps_Input'!$B$9:$J$9,0),FALSE) -> 1777 | I61: =VLOOKUP(I$4,'Trading Comps_Input'!$B$9:$J$188,MATCH($B61,'Trading Comps_Input'!$B$9:$J$9,0),FALSE) -> 1.8990461 | J61: =VLOOKUP(J$4,'Trading Comps_Input'!$B$9:$J$188,MATCH($B61,'Trading Comps_Input'!$B$9:$J$9,0),FALSE) -> 16327.516 | ... P61: =VLOOKUP(P$4,'Trading Comps_Input'!$B$9:$J$188,MATCH($B61,'Trading Comps_Input'!$B$9:$J$9,0),FALSE) -> 488.41627
B62: MOLSON COORS | C62: =VLOOKUP(C$4,'Trading Comps_Input'!$B$9:$J$188,MATCH($B62,'Trading Comps_Input'!$B$9:$J$9,0),FALSE) -> NYSE: TAP | D62: =VLOOKUP(D$4,'Trading Comps_Input'!$B$9:$J$188,MATCH($B62,'Trading Comps_Input'!$B$9:$J$9,0),FALSE) -> 4233.824 | E62: =VLOOKUP(E$4,'Trading Comps_Input'!$B$9:$J$188,MATCH($B62,'Trading Comps_Input'!$B$9:$J$9,0),FALSE) -> 5225.824 | F62: =VLOOKUP(F$4,'Trading Comps_Input'!$B$9:$J$188,MATCH($B62,'Trading Comps_Input'!$B$9:$J$9,0),FALSE) -> 3032.4 | G62: =VLOOKUP(G$4,'Trading Comps_Input'!$B$9:$J$188,MATCH($B62,'Trading Comps_Input'!$B$9:$J$9,0),FALSE) -> 631.6 | H62: =VLOOKUP(H$4,'Trading Comps_Input'!$B$9:$J$188,MATCH($B62,'Trading Comps_Input'!$B$9:$J$9,0),FALSE) -> 423.6 | I62: =VLOOKUP(I$4,'Trading Comps_Input'!$B$9:$J$188,MATCH($B62,'Trading Comps_Input'!$B$9:$J$9,0),FALSE) -> 0.99772668 | J62: =VLOOKUP(J$4,'Trading Comps_Input'!$B$9:$J$188,MATCH($B62,'Trading Comps_Input'!$B$9:$J$9,0),FALSE) -> 3371.9869 | ... P62: =VLOOKUP(P$4,'Trading Comps_Input'!$B$9:$J$188,MATCH($B62,'Trading Comps_Input'!$B$9:$J$9,0),FALSE) -> 184.4
B63: BOSTON BEER | C63: =VLOOKUP(C$4,'Trading Comps_Input'!$B$9:$J$188,MATCH($B63,'Trading Comps_Input'!$B$9:$J$9,0),FALSE) -> NYSE: SAM | D63: =VLOOKUP(D$4,'Trading Comps_Input'!$B$9:$J$188,MATCH($B63,'Trading Comps_Input'!$B$9:$J$9,0),FALSE) -> 705.58542 | E63: =VLOOKUP(E$4,'Trading Comps_Input'!$B$9:$J$188,MATCH($B63,'Trading Comps_Input'!$B$9:$J$9,0),FALSE) -> 650.10442 | F63: =VLOOKUP(F$4,'Trading Comps_Input'!$B$9:$J$188,MATCH($B63,'Trading Comps_Input'!$B$9:$J$9,0),FALSE) -> 415.053 | G63: =VLOOKUP(G$4,'Trading Comps_Input'!$B$9:$J$188,MATCH($B63,'Trading Comps_Input'!$B$9:$J$9,0),FALSE) -> 72.239 | H63: =VLOOKUP(H$4,'Trading Comps_Input'!$B$9:$J$188,MATCH($B63,'Trading Comps_Input'!$B$9:$J$9,0),FALSE) -> 55.32 | I63: =VLOOKUP(I$4,'Trading Comps_Input'!$B$9:$J$188,MATCH($B63,'Trading Comps_Input'!$B$9:$J$9,0),FALSE) -> 2.2702953 | J63: =VLOOKUP(J$4,'Trading Comps_Input'!$B$9:$J$188,MATCH($B63,'Trading Comps_Input'!$B$9:$J$9,0),FALSE) -> 446.19518 | ... P63: =VLOOKUP(P$4,'Trading Comps_Input'!$B$9:$J$188,MATCH($B63,'Trading Comps_Input'!$B$9:$J$9,0),FALSE) -> 14.845054
B65: Hlookup & Match
B67: 동일한 논리, 차이점은 단지 어떻게 present하고 싶은지에 따라 HLOOKUP을 사용할 수 있음
B69: Company name | C69: Oriental Brewery | D69: HITE Brewery | E69: ASAHI GROUP | F69: TSINGTAO BREWERY | G69: CARLSBERG | H69: HEINEKEN | I69: MOLSON COORS | J69: BOSTON BEER
B70: Ticker | C70: =HLOOKUP(C$69,'Trading Comps_Input'!$B$9:$J$188,MATCH($B70,'Trading Comps_Input'!$B$9:$B$188,0),FALSE) -> OB | D70: =HLOOKUP(D$69,'Trading Comps_Input'!$B$9:$J$188,MATCH($B70,'Trading Comps_Input'!$B$9:$B$188,0),FALSE) -> KRX: 103150 | E70: =HLOOKUP(E$69,'Trading Comps_Input'!$B$9:$J$188,MATCH($B70,'Trading Comps_Input'!$B$9:$B$188,0),FALSE) -> TYO: 2502 | F70: =HLOOKUP(F$69,'Trading Comps_Input'!$B$9:$J$188,MATCH($B70,'Trading Comps_Input'!$B$9:$B$188,0),FALSE) -> SEHK:168 | G70: =HLOOKUP(G$69,'Trading Comps_Input'!$B$9:$J$188,MATCH($B70,'Trading Comps_Input'!$B$9:$B$188,0),FALSE) -> CPSE:CARL B | H70: =HLOOKUP(H$69,'Trading Comps_Input'!$B$9:$J$188,MATCH($B70,'Trading Comps_Input'!$B$9:$B$188,0),FALSE) -> ENXTAM:HEIA | I70: =HLOOKUP(I$69,'Trading Comps_Input'!$B$9:$J$188,MATCH($B70,'Trading Comps_Input'!$B$9:$B$188,0),FALSE) -> NYSE: TAP | J70: =HLOOKUP(J$69,'Trading Comps_Input'!$B$9:$J$188,MATCH($B70,'Trading Comps_Input'!$B$9:$B$188,0),FALSE) -> NYSE: SAM
B71: Market capitalization (mm) | C71: =HLOOKUP(C$69,'Trading Comps_Input'!$B$9:$J$188,MATCH($B71,'Trading Comps_Input'!$B$9:$B$188,0),FALSE) -> 0 | D71: =HLOOKUP(D$69,'Trading Comps_Input'!$B$9:$J$188,MATCH($B71,'Trading Comps_Input'!$B$9:$B$188,0),FALSE) -> 1624834.8 | E71: =HLOOKUP(E$69,'Trading Comps_Input'!$B$9:$J$188,MATCH($B71,'Trading Comps_Input'!$B$9:$B$188,0),FALSE) -> 806123.85 | F71: =HLOOKUP(F$69,'Trading Comps_Input'!$B$9:$J$188,MATCH($B71,'Trading Comps_Input'!$B$9:$B$188,0),FALSE) -> 21676.909 | G71: =HLOOKUP(G$69,'Trading Comps_Input'!$B$9:$J$188,MATCH($B71,'Trading Comps_Input'!$B$9:$B$188,0),FALSE) -> 60461.074 | H71: =HLOOKUP(H$69,'Trading Comps_Input'!$B$9:$J$188,MATCH($B71,'Trading Comps_Input'!$B$9:$B$188,0),FALSE) -> 17490.187 | I71: =HLOOKUP(I$69,'Trading Comps_Input'!$B$9:$J$188,MATCH($B71,'Trading Comps_Input'!$B$9:$B$188,0),FALSE) -> 4233.824 | J71: =HLOOKUP(J$69,'Trading Comps_Input'!$B$9:$J$188,MATCH($B71,'Trading Comps_Input'!$B$9:$B$188,0),FALSE) -> 705.58542
B72: Enterprise value (EV) | C72: =HLOOKUP(C$69,'Trading Comps_Input'!$B$9:$J$188,MATCH($B72,'Trading Comps_Input'!$B$9:$B$188,0),FALSE) -> 0 | D72: =HLOOKUP(D$69,'Trading Comps_Input'!$B$9:$J$188,MATCH($B72,'Trading Comps_Input'!$B$9:$B$188,0),FALSE) -> 2618390.5 | E72: =HLOOKUP(E$69,'Trading Comps_Input'!$B$9:$J$188,MATCH($B72,'Trading Comps_Input'!$B$9:$B$188,0),FALSE) -> 1184147.9 | F72: =HLOOKUP(F$69,'Trading Comps_Input'!$B$9:$J$188,MATCH($B72,'Trading Comps_Input'!$B$9:$B$188,0),FALSE) -> 17888.829 | G72: =HLOOKUP(G$69,'Trading Comps_Input'!$B$9:$J$188,MATCH($B72,'Trading Comps_Input'!$B$9:$B$188,0),FALSE) -> 101784.07 | H72: =HLOOKUP(H$69,'Trading Comps_Input'!$B$9:$J$188,MATCH($B72,'Trading Comps_Input'!$B$9:$B$188,0),FALSE) -> 25968.187 | I72: =HLOOKUP(I$69,'Trading Comps_Input'!$B$9:$J$188,MATCH($B72,'Trading Comps_Input'!$B$9:$B$188,0),FALSE) -> 5225.824 | J72: =HLOOKUP(J$69,'Trading Comps_Input'!$B$9:$J$188,MATCH($B72,'Trading Comps_Input'!$B$9:$B$188,0),FALSE) -> 650.10442
B73: Revenues - LFY | C73: =HLOOKUP(C$69,'Trading Comps_Input'!$B$9:$J$188,MATCH($B73,'Trading Comps_Input'!$B$9:$B$188,0),FALSE) -> 816110.19 | D73: =HLOOKUP(D$69,'Trading Comps_Input'!$B$9:$J$188,MATCH($B73,'Trading Comps_Input'!$B$9:$B$188,0),FALSE) -> 1049536 | E73: =HLOOKUP(E$69,'Trading Comps_Input'!$B$9:$J$188,MATCH($B73,'Trading Comps_Input'!$B$9:$B$188,0),FALSE) -> 1022318 | F73: =HLOOKUP(F$69,'Trading Comps_Input'!$B$9:$J$188,MATCH($B73,'Trading Comps_Input'!$B$9:$B$188,0),FALSE) -> 18026.108 | G73: =HLOOKUP(G$69,'Trading Comps_Input'!$B$9:$J$188,MATCH($B73,'Trading Comps_Input'!$B$9:$B$188,0),FALSE) -> 59382 | H73: =HLOOKUP(H$69,'Trading Comps_Input'!$B$9:$J$188,MATCH($B73,'Trading Comps_Input'!$B$9:$B$188,0),FALSE) -> 14701 | I73: =HLOOKUP(I$69,'Trading Comps_Input'!$B$9:$J$188,MATCH($B73,'Trading Comps_Input'!$B$9:$B$188,0),FALSE) -> 3032.4 | J73: =HLOOKUP(J$69,'Trading Comps_Input'!$B$9:$J$188,MATCH($B73,'Trading Comps_Input'!$B$9:$B$188,0),FALSE) -> 415.053
B74: EBITDA - LFY | C74: =HLOOKUP(C$69,'Trading Comps_Input'!$B$9:$J$188,MATCH($B74,'Trading Comps_Input'!$B$9:$B$188,0),FALSE) -> 251435.45 | D74: =HLOOKUP(D$69,'Trading Comps_Input'!$B$9:$J$188,MATCH($B74,'Trading Comps_Input'!$B$9:$B$188,0),FALSE) -> 259614.51 | E74: =HLOOKUP(E$69,'Trading Comps_Input'!$B$9:$J$188,MATCH($B74,'Trading Comps_Input'!$B$9:$B$188,0),FALSE) -> 141149 | F74: =HLOOKUP(F$69,'Trading Comps_Input'!$B$9:$J$188,MATCH($B74,'Trading Comps_Input'!$B$9:$B$188,0),FALSE) -> 2065.4427 | G74: =HLOOKUP(G$69,'Trading Comps_Input'!$B$9:$J$188,MATCH($B74,'Trading Comps_Input'!$B$9:$B$188,0),FALSE) -> 13307 | H74: =HLOOKUP(H$69,'Trading Comps_Input'!$B$9:$J$188,MATCH($B74,'Trading Comps_Input'!$B$9:$B$188,0),FALSE) -> 2672 | I74: =HLOOKUP(I$69,'Trading Comps_Input'!$B$9:$J$188,MATCH($B74,'Trading Comps_Input'!$B$9:$B$188,0),FALSE) -> 631.6 | J74: =HLOOKUP(J$69,'Trading Comps_Input'!$B$9:$J$188,MATCH($B74,'Trading Comps_Input'!$B$9:$B$188,0),FALSE) -> 72.239
B75: EBIT - LFY | C75: =HLOOKUP(C$69,'Trading Comps_Input'!$B$9:$J$188,MATCH($B75,'Trading Comps_Input'!$B$9:$B$188,0),FALSE) -> 196305.66 | D75: =HLOOKUP(D$69,'Trading Comps_Input'!$B$9:$J$188,MATCH($B75,'Trading Comps_Input'!$B$9:$B$188,0),FALSE) -> 187129.78 | E75: =HLOOKUP(E$69,'Trading Comps_Input'!$B$9:$J$188,MATCH($B75,'Trading Comps_Input'!$B$9:$B$188,0),FALSE) -> 82777 | F75: =HLOOKUP(F$69,'Trading Comps_Input'!$B$9:$J$188,MATCH($B75,'Trading Comps_Input'!$B$9:$B$188,0),FALSE) -> 1520.6809 | G75: =HLOOKUP(G$69,'Trading Comps_Input'!$B$9:$J$188,MATCH($B75,'Trading Comps_Input'!$B$9:$B$188,0),FALSE) -> 9538 | H75: =HLOOKUP(H$69,'Trading Comps_Input'!$B$9:$J$188,MATCH($B75,'Trading Comps_Input'!$B$9:$B$188,0),FALSE) -> 1777 | I75: =HLOOKUP(I$69,'Trading Comps_Input'!$B$9:$J$188,MATCH($B75,'Trading Comps_Input'!$B$9:$B$188,0),FALSE) -> 423.6 | J75: =HLOOKUP(J$69,'Trading Comps_Input'!$B$9:$J$188,MATCH($B75,'Trading Comps_Input'!$B$9:$B$188,0),FALSE) -> 55.32
B76: EPS - LFY | C76: =HLOOKUP(C$69,'Trading Comps_Input'!$B$9:$J$188,MATCH($B76,'Trading Comps_Input'!$B$9:$B$188,0),FALSE) -> 6629.0535 | D76: =HLOOKUP(D$69,'Trading Comps_Input'!$B$9:$J$188,MATCH($B76,'Trading Comps_Input'!$B$9:$B$188,0),FALSE) -> 10921.965 | E76: =HLOOKUP(E$69,'Trading Comps_Input'!$B$9:$J$188,MATCH($B76,'Trading Comps_Input'!$B$9:$B$188,0),FALSE) -> 103.09653 | F76: =HLOOKUP(F$69,'Trading Comps_Input'!$B$9:$J$188,MATCH($B76,'Trading Comps_Input'!$B$9:$B$188,0),FALSE) -> 0.95009959 | G76: =HLOOKUP(G$69,'Trading Comps_Input'!$B$9:$J$188,MATCH($B76,'Trading Comps_Input'!$B$9:$B$188,0),FALSE) -> 33.210292 | H76: =HLOOKUP(H$69,'Trading Comps_Input'!$B$9:$J$188,MATCH($B76,'Trading Comps_Input'!$B$9:$B$188,0),FALSE) -> 1.8990461 | I76: =HLOOKUP(I$69,'Trading Comps_Input'!$B$9:$J$188,MATCH($B76,'Trading Comps_Input'!$B$9:$B$188,0),FALSE) -> 0.99772668 | J76: =HLOOKUP(J$69,'Trading Comps_Input'!$B$9:$J$188,MATCH($B76,'Trading Comps_Input'!$B$9:$B$188,0),FALSE) -> 2.2702953
B77: Revenues - Calendar year 1 | C77: =HLOOKUP(C$69,'Trading Comps_Input'!$B$9:$J$188,MATCH($B77,'Trading Comps_Input'!$B$9:$B$188,0),FALSE) -> 840593.49 | D77: =HLOOKUP(D$69,'Trading Comps_Input'!$B$9:$J$188,MATCH($B77,'Trading Comps_Input'!$B$9:$B$188,0),FALSE) -> 1066105.2 | E77: =HLOOKUP(E$69,'Trading Comps_Input'!$B$9:$J$188,MATCH($B77,'Trading Comps_Input'!$B$9:$B$188,0),FALSE) -> 1084231.5 | F77: =HLOOKUP(F$69,'Trading Comps_Input'!$B$9:$J$188,MATCH($B77,'Trading Comps_Input'!$B$9:$B$188,0),FALSE) -> 20524.904 | G77: =HLOOKUP(G$69,'Trading Comps_Input'!$B$9:$J$188,MATCH($B77,'Trading Comps_Input'!$B$9:$B$188,0),FALSE) -> 60124.231 | H77: =HLOOKUP(H$69,'Trading Comps_Input'!$B$9:$J$188,MATCH($B77,'Trading Comps_Input'!$B$9:$B$188,0),FALSE) -> 16327.516 | I77: =HLOOKUP(I$69,'Trading Comps_Input'!$B$9:$J$188,MATCH($B77,'Trading Comps_Input'!$B$9:$B$188,0),FALSE) -> 3371.9869 | J77: =HLOOKUP(J$69,'Trading Comps_Input'!$B$9:$J$188,MATCH($B77,'Trading Comps_Input'!$B$9:$B$188,0),FALSE) -> 446.19518
B78: EBITDA - Calendar year 1 | C78: =HLOOKUP(C$69,'Trading Comps_Input'!$B$9:$J$188,MATCH($B78,'Trading Comps_Input'!$B$9:$B$188,0),FALSE) -> 258978.51 | D78: =HLOOKUP(D$69,'Trading Comps_Input'!$B$9:$J$188,MATCH($B78,'Trading Comps_Input'!$B$9:$B$188,0),FALSE) -> 232221.75 | E78: =HLOOKUP(E$69,'Trading Comps_Input'!$B$9:$J$188,MATCH($B78,'Trading Comps_Input'!$B$9:$B$188,0),FALSE) -> 162376.01 | F78: =HLOOKUP(F$69,'Trading Comps_Input'!$B$9:$J$188,MATCH($B78,'Trading Comps_Input'!$B$9:$B$188,0),FALSE) -> 2486.2697 | G78: =HLOOKUP(G$69,'Trading Comps_Input'!$B$9:$J$188,MATCH($B78,'Trading Comps_Input'!$B$9:$B$188,0),FALSE) -> 13519.078 | H78: =HLOOKUP(H$69,'Trading Comps_Input'!$B$9:$J$188,MATCH($B78,'Trading Comps_Input'!$B$9:$B$188,0),FALSE) -> 3186.5033 | I78: =HLOOKUP(I$69,'Trading Comps_Input'!$B$9:$J$188,MATCH($B78,'Trading Comps_Input'!$B$9:$B$188,0),FALSE) -> 639.03857 | J78: =HLOOKUP(J$69,'Trading Comps_Input'!$B$9:$J$188,MATCH($B78,'Trading Comps_Input'!$B$9:$B$188,0),FALSE) -> 102.67356
B79: EBIT - Calendar year 1 | C79: =HLOOKUP(C$69,'Trading Comps_Input'!$B$9:$J$188,MATCH($B79,'Trading Comps_Input'!$B$9:$B$188,0),FALSE) -> 202194.82 | D79: =HLOOKUP(D$69,'Trading Comps_Input'!$B$9:$J$188,MATCH($B79,'Trading Comps_Input'!$B$9:$B$188,0),FALSE) -> 151914.49 | E79: =HLOOKUP(E$69,'Trading Comps_Input'!$B$9:$J$188,MATCH($B79,'Trading Comps_Input'!$B$9:$B$188,0),FALSE) -> 95386.573 | F79: =HLOOKUP(F$69,'Trading Comps_Input'!$B$9:$J$188,MATCH($B79,'Trading Comps_Input'!$B$9:$B$188,0),FALSE) -> 1905.3395 | G79: =HLOOKUP(G$69,'Trading Comps_Input'!$B$9:$J$188,MATCH($B79,'Trading Comps_Input'!$B$9:$B$188,0),FALSE) -> 9759.7655 | H79: =HLOOKUP(H$69,'Trading Comps_Input'!$B$9:$J$188,MATCH($B79,'Trading Comps_Input'!$B$9:$B$188,0),FALSE) -> 1986.2587 | I79: =HLOOKUP(I$69,'Trading Comps_Input'!$B$9:$J$188,MATCH($B79,'Trading Comps_Input'!$B$9:$B$188,0),FALSE) -> 426.09416 | J79: =HLOOKUP(J$69,'Trading Comps_Input'!$B$9:$J$188,MATCH($B79,'Trading Comps_Input'!$B$9:$B$188,0),FALSE) -> 83.819889
B80: EPS - Calendar year 1 | C80: =HLOOKUP(C$69,'Trading Comps_Input'!$B$9:$J$188,MATCH($B80,'Trading Comps_Input'!$B$9:$B$188,0),FALSE) -> 6827.9251 | D80: =HLOOKUP(D$69,'Trading Comps_Input'!$B$9:$J$188,MATCH($B80,'Trading Comps_Input'!$B$9:$B$188,0),FALSE) -> 6821.3098 | E80: =HLOOKUP(E$69,'Trading Comps_Input'!$B$9:$J$188,MATCH($B80,'Trading Comps_Input'!$B$9:$B$188,0),FALSE) -> 115.68564 | F80: =HLOOKUP(F$69,'Trading Comps_Input'!$B$9:$J$188,MATCH($B80,'Trading Comps_Input'!$B$9:$B$188,0),FALSE) -> 1.129899 | G80: =HLOOKUP(G$69,'Trading Comps_Input'!$B$9:$J$188,MATCH($B80,'Trading Comps_Input'!$B$9:$B$188,0),FALSE) -> 33.09819 | H80: =HLOOKUP(H$69,'Trading Comps_Input'!$B$9:$J$188,MATCH($B80,'Trading Comps_Input'!$B$9:$B$188,0),FALSE) -> 2.711287 | I80: =HLOOKUP(I$69,'Trading Comps_Input'!$B$9:$J$188,MATCH($B80,'Trading Comps_Input'!$B$9:$B$188,0),FALSE) -> 3.668696 | J80: =HLOOKUP(J$69,'Trading Comps_Input'!$B$9:$J$188,MATCH($B80,'Trading Comps_Input'!$B$9:$B$188,0),FALSE) -> 3.407229
B81: Long-term growth rate | C81: =HLOOKUP(C$69,'Trading Comps_Input'!$B$9:$J$188,MATCH($B81,'Trading Comps_Input'!$B$9:$B$188,0),FALSE) -> 0.025 | D81: =HLOOKUP(D$69,'Trading Comps_Input'!$B$9:$J$188,MATCH($B81,'Trading Comps_Input'!$B$9:$B$188,0),FALSE) -> 0.025 | E81: =HLOOKUP(E$69,'Trading Comps_Input'!$B$9:$J$188,MATCH($B81,'Trading Comps_Input'!$B$9:$B$188,0),FALSE) -> 0.035 | F81: =HLOOKUP(F$69,'Trading Comps_Input'!$B$9:$J$188,MATCH($B81,'Trading Comps_Input'!$B$9:$B$188,0),FALSE) -> 0.035 | G81: =HLOOKUP(G$69,'Trading Comps_Input'!$B$9:$J$188,MATCH($B81,'Trading Comps_Input'!$B$9:$B$188,0),FALSE) -> 0.03 | H81: =HLOOKUP(H$69,'Trading Comps_Input'!$B$9:$J$188,MATCH($B81,'Trading Comps_Input'!$B$9:$B$188,0),FALSE) -> 0.035 | I81: =HLOOKUP(I$69,'Trading Comps_Input'!$B$9:$J$188,MATCH($B81,'Trading Comps_Input'!$B$9:$B$188,0),FALSE) -> 0.015 | J81: =HLOOKUP(J$69,'Trading Comps_Input'!$B$9:$J$188,MATCH($B81,'Trading Comps_Input'!$B$9:$B$188,0),FALSE) -> 0.035
... B83: Diluted shares outstanding (mm) | C83: =HLOOKUP(C$69,'Trading Comps_Input'!$B$9:$J$188,MATCH($B83,'Trading Comps_Input'!$B$9:$B$188,0),FALSE) -> 20.611 | D83: =HLOOKUP(D$69,'Trading Comps_Input'!$B$9:$J$188,MATCH($B83,'Trading Comps_Input'!$B$9:$B$188,0),FALSE) -> 9.557852 | E83: =HLOOKUP(E$69,'Trading Comps_Input'!$B$9:$J$188,MATCH($B83,'Trading Comps_Input'!$B$9:$B$188,0),FALSE) -> 465.42948 | F83: =HLOOKUP(F$69,'Trading Comps_Input'!$B$9:$J$188,MATCH($B83,'Trading Comps_Input'!$B$9:$B$188,0),FALSE) -> 1315.3464 | G83: =HLOOKUP(G$69,'Trading Comps_Input'!$B$9:$J$188,MATCH($B83,'Trading Comps_Input'!$B$9:$B$188,0),FALSE) -> 152.64093 | H83: =HLOOKUP(H$69,'Trading Comps_Input'!$B$9:$J$188,MATCH($B83,'Trading Comps_Input'!$B$9:$B$188,0),FALSE) -> 488.41627 | I83: =HLOOKUP(I$69,'Trading Comps_Input'!$B$9:$J$188,MATCH($B83,'Trading Comps_Input'!$B$9:$B$188,0),FALSE) -> 184.4 | J83: =HLOOKUP(J$69,'Trading Comps_Input'!$B$9:$J$188,MATCH($B83,'Trading Comps_Input'!$B$9:$B$188,0),FALSE) -> 14.845054
B87: Transpose
B88: {=TRANSPOSE(B69:J83)} -> Company name | C88: Ticker | D88: Market capitalization (mm) | E88: Enterprise value (EV) | F88: Revenues - LFY | G88: EBITDA - LFY | H88: EBIT - LFY | I88: EPS - LFY | J88: Revenues - Calendar year 1 | K88: EBITDA - Calendar year 1 | L88: EBIT - Calendar year 1 | M88: EPS - Calendar year 1 | N88: Long-term growth rate | O88: Net debt | P88: Diluted shares outstanding (mm)
B89: Oriental Brewery | C89: OB | D89: 0 | E89: 0 | F89: 816110.19 | G89: 251435.45 | H89: 196305.66 | I89: 6629.0535 | J89: 840593.49 | K89: 258978.51 | L89: 202194.82 | M89: 6827.9251 | N89: 0.025 | O89: 301945.91 | P89: 20.611
B90: HITE Brewery | C90: KRX: 103150 | D90: 1624834.8 | E90: 2618390.5 | F90: 1049536 | G90: 259614.51 | H90: 187129.78 | I90: 10921.965 | J90: 1066105.2 | K90: 232221.75 | L90: 151914.49 | M90: 6821.3098 | N90: 0.025 | O90: 993555.63 | P90: 9.557852
B91: ASAHI GROUP | C91: TYO: 2502 | D91: 806123.85 | E91: 1184147.9 | F91: 1022318 | G91: 141149 | H91: 82777 | I91: 103.09653 | J91: 1084231.5 | K91: 162376.01 | L91: 95386.573 | M91: 115.68564 | N91: 0.035 | O91: 378024 | P91: 465.42948
B92: TSINGTAO BREWERY | C92: SEHK:168 | D92: 21676.909 | E92: 17888.829 | F92: 18026.108 | G92: 2065.4427 | H92: 1520.6809 | I92: 0.95009959 | J92: 20524.904 | K92: 2486.2697 | L92: 1905.3395 | M92: 1.129899 | N92: 0.035 | O92: -3788.0802 | P92: 1315.3464
B93: CARLSBERG | C93: CPSE:CARL B | D93: 60461.074 | E93: 101784.07 | F93: 59382 | G93: 13307 | H93: 9538 | I93: 33.210292 | J93: 60124.231 | K93: 13519.078 | L93: 9759.7655 | M93: 33.09819 | N93: 0.03 | O93: 41323 | P93: 152.64093
B94: HEINEKEN | C94: ENXTAM:HEIA | D94: 17490.187 | E94: 25968.187 | F94: 14701 | G94: 2672 | H94: 1777 | I94: 1.8990461 | J94: 16327.516 | K94: 3186.5033 | L94: 1986.2587 | M94: 2.711287 | N94: 0.035 | O94: 8478 | P94: 488.41627
B95: MOLSON COORS | C95: NYSE: TAP | D95: 4233.824 | E95: 5225.824 | F95: 3032.4 | G95: 631.6 | H95: 423.6 | I95: 0.99772668 | J95: 3371.9869 | K95: 639.03857 | L95: 426.09416 | M95: 3.668696 | N95: 0.015 | O95: 992 | P95: 184.4
B96: BOSTON BEER | C96: NYSE: SAM | D96: 705.58542 | E96: 650.10442 | F96: 415.053 | G96: 72.239 | H96: 55.32 | I96: 2.2702953 | J96: 446.19518 | K96: 102.67356 | L96: 83.819889 | M96: 3.407229 | N96: 0.035 | O96: -55.481 | P96: 14.845054
B99: Alt, e, s, e
B100: Company name | C100: Ticker | D100: Market capitalization (mm) | E100: Enterprise value (EV) | F100: Revenues - LFY | G100: EBITDA - LFY | H100: EBIT - LFY | I100: EPS - LFY | J100: Revenues - Calendar year 1 | K100: EBITDA - Calendar year 1 | L100: EBIT - Calendar year 1 | M100: EPS - Calendar year 1 | N100: Long-term growth rate | O100: Net debt | P100: Diluted shares outstanding (mm)
B101: Oriental Brewery | C101: =HLOOKUP($B101,'Trading Comps_Input'!$B$9:$J$188,MATCH(C$100,'Trading Comps_Input'!$B$9:$B$188,0),FALSE) -> OB | D101: =HLOOKUP($B101,'Trading Comps_Input'!$B$9:$J$188,MATCH(D$100,'Trading Comps_Input'!$B$9:$B$188,0),FALSE) -> 0 | E101: =HLOOKUP($B101,'Trading Comps_Input'!$B$9:$J$188,MATCH(E$100,'Trading Comps_Input'!$B$9:$B$188,0),FALSE) -> 0 | F101: =HLOOKUP($B101,'Trading Comps_Input'!$B$9:$J$188,MATCH(F$100,'Trading Comps_Input'!$B$9:$B$188,0),FALSE) -> 816110.19 | G101: =HLOOKUP($B101,'Trading Comps_Input'!$B$9:$J$188,MATCH(G$100,'Trading Comps_Input'!$B$9:$B$188,0),FALSE) -> 251435.45 | H101: =HLOOKUP($B101,'Trading Comps_Input'!$B$9:$J$188,MATCH(H$100,'Trading Comps_Input'!$B$9:$B$188,0),FALSE) -> 196305.66 | I101: =HLOOKUP($B101,'Trading Comps_Input'!$B$9:$J$188,MATCH(I$100,'Trading Comps_Input'!$B$9:$B$188,0),FALSE) -> 6629.0535 | J101: =HLOOKUP($B101,'Trading Comps_Input'!$B$9:$J$188,MATCH(J$100,'Trading Comps_Input'!$B$9:$B$188,0),FALSE) -> 840593.49 | ... P101: =HLOOKUP($B101,'Trading Comps_Input'!$B$9:$J$188,MATCH(P$100,'Trading Comps_Input'!$B$9:$B$188,0),FALSE) -> 20.611
B102: HITE Brewery | C102: =HLOOKUP($B102,'Trading Comps_Input'!$B$9:$J$188,MATCH(C$100,'Trading Comps_Input'!$B$9:$B$188,0),FALSE) -> KRX: 103150 | D102: =HLOOKUP($B102,'Trading Comps_Input'!$B$9:$J$188,MATCH(D$100,'Trading Comps_Input'!$B$9:$B$188,0),FALSE) -> 1624834.8 | E102: =HLOOKUP($B102,'Trading Comps_Input'!$B$9:$J$188,MATCH(E$100,'Trading Comps_Input'!$B$9:$B$188,0),FALSE) -> 2618390.5 | F102: =HLOOKUP($B102,'Trading Comps_Input'!$B$9:$J$188,MATCH(F$100,'Trading Comps_Input'!$B$9:$B$188,0),FALSE) -> 1049536 | G102: =HLOOKUP($B102,'Trading Comps_Input'!$B$9:$J$188,MATCH(G$100,'Trading Comps_Input'!$B$9:$B$188,0),FALSE) -> 259614.51 | H102: =HLOOKUP($B102,'Trading Comps_Input'!$B$9:$J$188,MATCH(H$100,'Trading Comps_Input'!$B$9:$B$188,0),FALSE) -> 187129.78 | I102: =HLOOKUP($B102,'Trading Comps_Input'!$B$9:$J$188,MATCH(I$100,'Trading Comps_Input'!$B$9:$B$188,0),FALSE) -> 10921.965 | J102: =HLOOKUP($B102,'Trading Comps_Input'!$B$9:$J$188,MATCH(J$100,'Trading Comps_Input'!$B$9:$B$188,0),FALSE) -> 1066105.2 | ... P102: =HLOOKUP($B102,'Trading Comps_Input'!$B$9:$J$188,MATCH(P$100,'Trading Comps_Input'!$B$9:$B$188,0),FALSE) -> 9.557852
B103: ASAHI GROUP | C103: =HLOOKUP($B103,'Trading Comps_Input'!$B$9:$J$188,MATCH(C$100,'Trading Comps_Input'!$B$9:$B$188,0),FALSE) -> TYO: 2502 | D103: =HLOOKUP($B103,'Trading Comps_Input'!$B$9:$J$188,MATCH(D$100,'Trading Comps_Input'!$B$9:$B$188,0),FALSE) -> 806123.85 | E103: =HLOOKUP($B103,'Trading Comps_Input'!$B$9:$J$188,MATCH(E$100,'Trading Comps_Input'!$B$9:$B$188,0),FALSE) -> 1184147.9 | F103: =HLOOKUP($B103,'Trading Comps_Input'!$B$9:$J$188,MATCH(F$100,'Trading Comps_Input'!$B$9:$B$188,0),FALSE) -> 1022318 | G103: =HLOOKUP($B103,'Trading Comps_Input'!$B$9:$J$188,MATCH(G$100,'Trading Comps_Input'!$B$9:$B$188,0),FALSE) -> 141149 | H103: =HLOOKUP($B103,'Trading Comps_Input'!$B$9:$J$188,MATCH(H$100,'Trading Comps_Input'!$B$9:$B$188,0),FALSE) -> 82777 | I103: =HLOOKUP($B103,'Trading Comps_Input'!$B$9:$J$188,MATCH(I$100,'Trading Comps_Input'!$B$9:$B$188,0),FALSE) -> 103.09653 | J103: =HLOOKUP($B103,'Trading Comps_Input'!$B$9:$J$188,MATCH(J$100,'Trading Comps_Input'!$B$9:$B$188,0),FALSE) -> 1084231.5 | ... P103: =HLOOKUP($B103,'Trading Comps_Input'!$B$9:$J$188,MATCH(P$100,'Trading Comps_Input'!$B$9:$B$188,0),FALSE) -> 465.42948
B104: TSINGTAO BREWERY | C104: =HLOOKUP($B104,'Trading Comps_Input'!$B$9:$J$188,MATCH(C$100,'Trading Comps_Input'!$B$9:$B$188,0),FALSE) -> SEHK:168 | D104: =HLOOKUP($B104,'Trading Comps_Input'!$B$9:$J$188,MATCH(D$100,'Trading Comps_Input'!$B$9:$B$188,0),FALSE) -> 21676.909 | E104: =HLOOKUP($B104,'Trading Comps_Input'!$B$9:$J$188,MATCH(E$100,'Trading Comps_Input'!$B$9:$B$188,0),FALSE) -> 17888.829 | F104: =HLOOKUP($B104,'Trading Comps_Input'!$B$9:$J$188,MATCH(F$100,'Trading Comps_Input'!$B$9:$B$188,0),FALSE) -> 18026.108 | G104: =HLOOKUP($B104,'Trading Comps_Input'!$B$9:$J$188,MATCH(G$100,'Trading Comps_Input'!$B$9:$B$188,0),FALSE) -> 2065.4427 | H104: =HLOOKUP($B104,'Trading Comps_Input'!$B$9:$J$188,MATCH(H$100,'Trading Comps_Input'!$B$9:$B$188,0),FALSE) -> 1520.6809 | I104: =HLOOKUP($B104,'Trading Comps_Input'!$B$9:$J$188,MATCH(I$100,'Trading Comps_Input'!$B$9:$B$188,0),FALSE) -> 0.95009959 | J104: =HLOOKUP($B104,'Trading Comps_Input'!$B$9:$J$188,MATCH(J$100,'Trading Comps_Input'!$B$9:$B$188,0),FALSE) -> 20524.904 | ... P104: =HLOOKUP($B104,'Trading Comps_Input'!$B$9:$J$188,MATCH(P$100,'Trading Comps_Input'!$B$9:$B$188,0),FALSE) -> 1315.3464
B105: CARLSBERG | C105: =HLOOKUP($B105,'Trading Comps_Input'!$B$9:$J$188,MATCH(C$100,'Trading Comps_Input'!$B$9:$B$188,0),FALSE) -> CPSE:CARL B | D105: =HLOOKUP($B105,'Trading Comps_Input'!$B$9:$J$188,MATCH(D$100,'Trading Comps_Input'!$B$9:$B$188,0),FALSE) -> 60461.074 | E105: =HLOOKUP($B105,'Trading Comps_Input'!$B$9:$J$188,MATCH(E$100,'Trading Comps_Input'!$B$9:$B$188,0),FALSE) -> 101784.07 | F105: =HLOOKUP($B105,'Trading Comps_Input'!$B$9:$J$188,MATCH(F$100,'Trading Comps_Input'!$B$9:$B$188,0),FALSE) -> 59382 | G105: =HLOOKUP($B105,'Trading Comps_Input'!$B$9:$J$188,MATCH(G$100,'Trading Comps_Input'!$B$9:$B$188,0),FALSE) -> 13307 | H105: =HLOOKUP($B105,'Trading Comps_Input'!$B$9:$J$188,MATCH(H$100,'Trading Comps_Input'!$B$9:$B$188,0),FALSE) -> 9538 | I105: =HLOOKUP($B105,'Trading Comps_Input'!$B$9:$J$188,MATCH(I$100,'Trading Comps_Input'!$B$9:$B$188,0),FALSE) -> 33.210292 | J105: =HLOOKUP($B105,'Trading Comps_Input'!$B$9:$J$188,MATCH(J$100,'Trading Comps_Input'!$B$9:$B$188,0),FALSE) -> 60124.231 | ... P105: =HLOOKUP($B105,'Trading Comps_Input'!$B$9:$J$188,MATCH(P$100,'Trading Comps_Input'!$B$9:$B$188,0),FALSE) -> 152.64093
B106: HEINEKEN | C106: =HLOOKUP($B106,'Trading Comps_Input'!$B$9:$J$188,MATCH(C$100,'Trading Comps_Input'!$B$9:$B$188,0),FALSE) -> ENXTAM:HEIA | D106: =HLOOKUP($B106,'Trading Comps_Input'!$B$9:$J$188,MATCH(D$100,'Trading Comps_Input'!$B$9:$B$188,0),FALSE) -> 17490.187 | E106: =HLOOKUP($B106,'Trading Comps_Input'!$B$9:$J$188,MATCH(E$100,'Trading Comps_Input'!$B$9:$B$188,0),FALSE) -> 25968.187 | F106: =HLOOKUP($B106,'Trading Comps_Input'!$B$9:$J$188,MATCH(F$100,'Trading Comps_Input'!$B$9:$B$188,0),FALSE) -> 14701 | G106: =HLOOKUP($B106,'Trading Comps_Input'!$B$9:$J$188,MATCH(G$100,'Trading Comps_Input'!$B$9:$B$188,0),FALSE) -> 2672 | H106: =HLOOKUP($B106,'Trading Comps_Input'!$B$9:$J$188,MATCH(H$100,'Trading Comps_Input'!$B$9:$B$188,0),FALSE) -> 1777 | I106: =HLOOKUP($B106,'Trading Comps_Input'!$B$9:$J$188,MATCH(I$100,'Trading Comps_Input'!$B$9:$B$188,0),FALSE) -> 1.8990461 | J106: =HLOOKUP($B106,'Trading Comps_Input'!$B$9:$J$188,MATCH(J$100,'Trading Comps_Input'!$B$9:$B$188,0),FALSE) -> 16327.516 | ... P106: =HLOOKUP($B106,'Trading Comps_Input'!$B$9:$J$188,MATCH(P$100,'Trading Comps_Input'!$B$9:$B$188,0),FALSE) -> 488.41627
B107: MOLSON COORS | C107: =HLOOKUP($B107,'Trading Comps_Input'!$B$9:$J$188,MATCH(C$100,'Trading Comps_Input'!$B$9:$B$188,0),FALSE) -> NYSE: TAP | D107: =HLOOKUP($B107,'Trading Comps_Input'!$B$9:$J$188,MATCH(D$100,'Trading Comps_Input'!$B$9:$B$188,0),FALSE) -> 4233.824 | E107: =HLOOKUP($B107,'Trading Comps_Input'!$B$9:$J$188,MATCH(E$100,'Trading Comps_Input'!$B$9:$B$188,0),FALSE) -> 5225.824 | F107: =HLOOKUP($B107,'Trading Comps_Input'!$B$9:$J$188,MATCH(F$100,'Trading Comps_Input'!$B$9:$B$188,0),FALSE) -> 3032.4 | G107: =HLOOKUP($B107,'Trading Comps_Input'!$B$9:$J$188,MATCH(G$100,'Trading Comps_Input'!$B$9:$B$188,0),FALSE) -> 631.6 | H107: =HLOOKUP($B107,'Trading Comps_Input'!$B$9:$J$188,MATCH(H$100,'Trading Comps_Input'!$B$9:$B$188,0),FALSE) -> 423.6 | I107: =HLOOKUP($B107,'Trading Comps_Input'!$B$9:$J$188,MATCH(I$100,'Trading Comps_Input'!$B$9:$B$188,0),FALSE) -> 0.99772668 | J107: =HLOOKUP($B107,'Trading Comps_Input'!$B$9:$J$188,MATCH(J$100,'Trading Comps_Input'!$B$9:$B$188,0),FALSE) -> 3371.9869 | ... P107: =HLOOKUP($B107,'Trading Comps_Input'!$B$9:$J$188,MATCH(P$100,'Trading Comps_Input'!$B$9:$B$188,0),FALSE) -> 184.4
B108: BOSTON BEER | C108: =HLOOKUP($B108,'Trading Comps_Input'!$B$9:$J$188,MATCH(C$100,'Trading Comps_Input'!$B$9:$B$188,0),FALSE) -> NYSE: SAM | D108: =HLOOKUP($B108,'Trading Comps_Input'!$B$9:$J$188,MATCH(D$100,'Trading Comps_Input'!$B$9:$B$188,0),FALSE) -> 705.58542 | E108: =HLOOKUP($B108,'Trading Comps_Input'!$B$9:$J$188,MATCH(E$100,'Trading Comps_Input'!$B$9:$B$188,0),FALSE) -> 650.10442 | F108: =HLOOKUP($B108,'Trading Comps_Input'!$B$9:$J$188,MATCH(F$100,'Trading Comps_Input'!$B$9:$B$188,0),FALSE) -> 415.053 | G108: =HLOOKUP($B108,'Trading Comps_Input'!$B$9:$J$188,MATCH(G$100,'Trading Comps_Input'!$B$9:$B$188,0),FALSE) -> 72.239 | H108: =HLOOKUP($B108,'Trading Comps_Input'!$B$9:$J$188,MATCH(H$100,'Trading Comps_Input'!$B$9:$B$188,0),FALSE) -> 55.32 | I108: =HLOOKUP($B108,'Trading Comps_Input'!$B$9:$J$188,MATCH(I$100,'Trading Comps_Input'!$B$9:$B$188,0),FALSE) -> 2.2702953 | J108: =HLOOKUP($B108,'Trading Comps_Input'!$B$9:$J$188,MATCH(J$100,'Trading Comps_Input'!$B$9:$B$188,0),FALSE) -> 446.19518 | ... P108: =HLOOKUP($B108,'Trading Comps_Input'!$B$9:$J$188,MATCH(P$100,'Trading Comps_Input'!$B$9:$B$188,0),FALSE) -> 14.845054
B117: 결과 거래배수
F118: Last Fiscal Year (LTM) | J118: Year 1 Forecast - Calendar Year
A119: x | B119: Name | C119: Ticker | F119: EV / Revenues | G119: EV / EBITDA | H119: EV / EBIT | I119: P/E | J119: EV / Revenues | K119: EV / EBITDA | L119: EV / EBIT | M119: P/E | N119: PEG ratio
B121: Oriental Brewery | C121: =C56 -> OB
B122: HITE Brewery | C122: =C57 -> KRX: 103150 | F122: =VLOOKUP(F$5,'Trading Comps_Input'!$B$9:$J$188,MATCH($B122,'Trading Comps_Input'!$B$9:$J$9,0),FALSE) -> 2.4948078 | G122: =VLOOKUP(G$5,'Trading Comps_Input'!$B$9:$J$188,MATCH($B122,'Trading Comps_Input'!$B$9:$J$9,0),FALSE) -> 10.085686 | H122: =VLOOKUP(H$5,'Trading Comps_Input'!$B$9:$J$188,MATCH($B122,'Trading Comps_Input'!$B$9:$J$9,0),FALSE) -> 13.992377 | I122: =VLOOKUP(I$5,'Trading Comps_Input'!$B$9:$J$188,MATCH($B122,'Trading Comps_Input'!$B$9:$J$9,0),FALSE) -> 15.564964 | J122: =VLOOKUP(J$5,'Trading Comps_Input'!$B$9:$J$188,MATCH($B122,'Trading Comps_Input'!$B$9:$J$9,0),FALSE) -> 2.4560338 | K122: =VLOOKUP(K$5,'Trading Comps_Input'!$B$9:$J$188,MATCH($B122,'Trading Comps_Input'!$B$9:$J$9,0),FALSE) -> 11.275389 | L122: =VLOOKUP(L$5,'Trading Comps_Input'!$B$9:$J$188,MATCH($B122,'Trading Comps_Input'!$B$9:$J$9,0),FALSE) -> 17.235949 | M122: =VLOOKUP(M$5,'Trading Comps_Input'!$B$9:$J$188,MATCH($B122,'Trading Comps_Input'!$B$9:$J$9,0),FALSE) -> 24.9219 | N122: =VLOOKUP(N$5,'Trading Comps_Input'!$B$9:$J$188,MATCH($B122,'Trading Comps_Input'!$B$9:$J$9,0),FALSE) -> 9.96876
B123: ASAHI GROUP | C123: =C58 -> TYO: 2502 | F123: =VLOOKUP(F$5,'Trading Comps_Input'!$B$9:$J$188,MATCH($B123,'Trading Comps_Input'!$B$9:$J$9,0),FALSE) -> 1.158297 | G123: =VLOOKUP(G$5,'Trading Comps_Input'!$B$9:$J$188,MATCH($B123,'Trading Comps_Input'!$B$9:$J$9,0),FALSE) -> 8.3893464 | H123: =VLOOKUP(H$5,'Trading Comps_Input'!$B$9:$J$188,MATCH($B123,'Trading Comps_Input'!$B$9:$J$9,0),FALSE) -> 14.305276 | I123: =VLOOKUP(I$5,'Trading Comps_Input'!$B$9:$J$188,MATCH($B123,'Trading Comps_Input'!$B$9:$J$9,0),FALSE) -> 16.79979 | J123: =VLOOKUP(J$5,'Trading Comps_Input'!$B$9:$J$188,MATCH($B123,'Trading Comps_Input'!$B$9:$J$9,0),FALSE) -> 1.092154 | K123: =VLOOKUP(K$5,'Trading Comps_Input'!$B$9:$J$188,MATCH($B123,'Trading Comps_Input'!$B$9:$J$9,0),FALSE) -> 7.2926283 | L123: =VLOOKUP(L$5,'Trading Comps_Input'!$B$9:$J$188,MATCH($B123,'Trading Comps_Input'!$B$9:$J$9,0),FALSE) -> 12.414199 | M123: =VLOOKUP(M$5,'Trading Comps_Input'!$B$9:$J$188,MATCH($B123,'Trading Comps_Input'!$B$9:$J$9,0),FALSE) -> 14.971607 | N123: =VLOOKUP(N$5,'Trading Comps_Input'!$B$9:$J$188,MATCH($B123,'Trading Comps_Input'!$B$9:$J$9,0),FALSE) -> 4.277602
B124: TSINGTAO BREWERY | C124: =C59 -> SEHK:168 | F124: =VLOOKUP(F$5,'Trading Comps_Input'!$B$9:$J$188,MATCH($B124,'Trading Comps_Input'!$B$9:$J$9,0),FALSE) -> 0.99238446 | G124: =VLOOKUP(G$5,'Trading Comps_Input'!$B$9:$J$188,MATCH($B124,'Trading Comps_Input'!$B$9:$J$9,0),FALSE) -> 8.6610147 | H124: =VLOOKUP(H$5,'Trading Comps_Input'!$B$9:$J$188,MATCH($B124,'Trading Comps_Input'!$B$9:$J$9,0),FALSE) -> 11.763697 | I124: =VLOOKUP(I$5,'Trading Comps_Input'!$B$9:$J$188,MATCH($B124,'Trading Comps_Input'!$B$9:$J$9,0),FALSE) -> 17.34555 | J124: =VLOOKUP(J$5,'Trading Comps_Input'!$B$9:$J$188,MATCH($B124,'Trading Comps_Input'!$B$9:$J$9,0),FALSE) -> 0.87156703 | K124: =VLOOKUP(K$5,'Trading Comps_Input'!$B$9:$J$188,MATCH($B124,'Trading Comps_Input'!$B$9:$J$9,0),FALSE) -> 7.1950477 | L124: =VLOOKUP(L$5,'Trading Comps_Input'!$B$9:$J$188,MATCH($B124,'Trading Comps_Input'!$B$9:$J$9,0),FALSE) -> 9.3887884 | M124: =VLOOKUP(M$5,'Trading Comps_Input'!$B$9:$J$188,MATCH($B124,'Trading Comps_Input'!$B$9:$J$9,0),FALSE) -> 14.585374 | N124: =VLOOKUP(N$5,'Trading Comps_Input'!$B$9:$J$188,MATCH($B124,'Trading Comps_Input'!$B$9:$J$9,0),FALSE) -> 4.1672498
B125: CARLSBERG | C125: =C60 -> CPSE:CARL B | F125: =VLOOKUP(F$5,'Trading Comps_Input'!$B$9:$J$188,MATCH($B125,'Trading Comps_Input'!$B$9:$J$9,0),FALSE) -> 1.714056 | G125: =VLOOKUP(G$5,'Trading Comps_Input'!$B$9:$J$188,MATCH($B125,'Trading Comps_Input'!$B$9:$J$9,0),FALSE) -> 7.6489121 | H125: =VLOOKUP(H$5,'Trading Comps_Input'!$B$9:$J$188,MATCH($B125,'Trading Comps_Input'!$B$9:$J$9,0),FALSE) -> 10.671427 | I125: =VLOOKUP(I$5,'Trading Comps_Input'!$B$9:$J$188,MATCH($B125,'Trading Comps_Input'!$B$9:$J$9,0),FALSE) -> 11.927025 | J125: =VLOOKUP(J$5,'Trading Comps_Input'!$B$9:$J$188,MATCH($B125,'Trading Comps_Input'!$B$9:$J$9,0),FALSE) -> 1.6928961 | K125: =VLOOKUP(K$5,'Trading Comps_Input'!$B$9:$J$188,MATCH($B125,'Trading Comps_Input'!$B$9:$J$9,0),FALSE) -> 7.5289213 | L125: =VLOOKUP(L$5,'Trading Comps_Input'!$B$9:$J$188,MATCH($B125,'Trading Comps_Input'!$B$9:$J$9,0),FALSE) -> 10.428947 | M125: =VLOOKUP(M$5,'Trading Comps_Input'!$B$9:$J$188,MATCH($B125,'Trading Comps_Input'!$B$9:$J$9,0),FALSE) -> 11.967422 | N125: =VLOOKUP(N$5,'Trading Comps_Input'!$B$9:$J$188,MATCH($B125,'Trading Comps_Input'!$B$9:$J$9,0),FALSE) -> 3.9891406
B126: HEINEKEN | C126: =C61 -> ENXTAM:HEIA | F126: =VLOOKUP(F$5,'Trading Comps_Input'!$B$9:$J$188,MATCH($B126,'Trading Comps_Input'!$B$9:$J$9,0),FALSE) -> 1.7664232 | G126: =VLOOKUP(G$5,'Trading Comps_Input'!$B$9:$J$188,MATCH($B126,'Trading Comps_Input'!$B$9:$J$9,0),FALSE) -> 9.7186328 | H126: =VLOOKUP(H$5,'Trading Comps_Input'!$B$9:$J$188,MATCH($B126,'Trading Comps_Input'!$B$9:$J$9,0),FALSE) -> 14.613498 | I126: =VLOOKUP(I$5,'Trading Comps_Input'!$B$9:$J$188,MATCH($B126,'Trading Comps_Input'!$B$9:$J$9,0),FALSE) -> 18.856836 | J126: =VLOOKUP(J$5,'Trading Comps_Input'!$B$9:$J$188,MATCH($B126,'Trading Comps_Input'!$B$9:$J$9,0),FALSE) -> 1.5904555 | K126: =VLOOKUP(K$5,'Trading Comps_Input'!$B$9:$J$188,MATCH($B126,'Trading Comps_Input'!$B$9:$J$9,0),FALSE) -> 8.1494305 | L126: =VLOOKUP(L$5,'Trading Comps_Input'!$B$9:$J$188,MATCH($B126,'Trading Comps_Input'!$B$9:$J$9,0),FALSE) -> 13.07392 | M126: =VLOOKUP(M$5,'Trading Comps_Input'!$B$9:$J$188,MATCH($B126,'Trading Comps_Input'!$B$9:$J$9,0),FALSE) -> 13.20775 | N126: =VLOOKUP(N$5,'Trading Comps_Input'!$B$9:$J$188,MATCH($B126,'Trading Comps_Input'!$B$9:$J$9,0),FALSE) -> 3.7736428
B127: MOLSON COORS | C127: =C62 -> NYSE: TAP | F127: =VLOOKUP(F$5,'Trading Comps_Input'!$B$9:$J$188,MATCH($B127,'Trading Comps_Input'!$B$9:$J$9,0),FALSE) -> 1.7233294 | G127: =VLOOKUP(G$5,'Trading Comps_Input'!$B$9:$J$188,MATCH($B127,'Trading Comps_Input'!$B$9:$J$9,0),FALSE) -> 8.2739455 | H127: =VLOOKUP(H$5,'Trading Comps_Input'!$B$9:$J$188,MATCH($B127,'Trading Comps_Input'!$B$9:$J$9,0),FALSE) -> 12.336695 | I127: =VLOOKUP(I$5,'Trading Comps_Input'!$B$9:$J$188,MATCH($B127,'Trading Comps_Input'!$B$9:$J$9,0),FALSE) -> 23.012314 | J127: =VLOOKUP(J$5,'Trading Comps_Input'!$B$9:$J$188,MATCH($B127,'Trading Comps_Input'!$B$9:$J$9,0),FALSE) -> 1.5497759 | K127: =VLOOKUP(K$5,'Trading Comps_Input'!$B$9:$J$188,MATCH($B127,'Trading Comps_Input'!$B$9:$J$9,0),FALSE) -> 8.1776347 | L127: =VLOOKUP(L$5,'Trading Comps_Input'!$B$9:$J$188,MATCH($B127,'Trading Comps_Input'!$B$9:$J$9,0),FALSE) -> 12.264482 | M127: =VLOOKUP(M$5,'Trading Comps_Input'!$B$9:$J$188,MATCH($B127,'Trading Comps_Input'!$B$9:$J$9,0),FALSE) -> 6.2583545 | N127: =VLOOKUP(N$5,'Trading Comps_Input'!$B$9:$J$188,MATCH($B127,'Trading Comps_Input'!$B$9:$J$9,0),FALSE) -> 4.1722363
B128: BOSTON BEER | C128: =C63 -> NYSE: SAM | F128: =VLOOKUP(F$5,'Trading Comps_Input'!$B$9:$J$188,MATCH($B128,'Trading Comps_Input'!$B$9:$J$9,0),FALSE) -> 1.5663166 | G128: =VLOOKUP(G$5,'Trading Comps_Input'!$B$9:$J$188,MATCH($B128,'Trading Comps_Input'!$B$9:$J$9,0),FALSE) -> 8.9993552 | H128: =VLOOKUP(H$5,'Trading Comps_Input'!$B$9:$J$188,MATCH($B128,'Trading Comps_Input'!$B$9:$J$9,0),FALSE) -> 11.751707 | I128: =VLOOKUP(I$5,'Trading Comps_Input'!$B$9:$J$188,MATCH($B128,'Trading Comps_Input'!$B$9:$J$9,0),FALSE) -> 20.935603 | J128: =VLOOKUP(J$5,'Trading Comps_Input'!$B$9:$J$188,MATCH($B128,'Trading Comps_Input'!$B$9:$J$9,0),FALSE) -> 1.4569956 | K128: =VLOOKUP(K$5,'Trading Comps_Input'!$B$9:$J$188,MATCH($B128,'Trading Comps_Input'!$B$9:$J$9,0),FALSE) -> 6.3317605 | L128: =VLOOKUP(L$5,'Trading Comps_Input'!$B$9:$J$188,MATCH($B128,'Trading Comps_Input'!$B$9:$J$9,0),FALSE) -> 7.7559685 | M128: =VLOOKUP(M$5,'Trading Comps_Input'!$B$9:$J$188,MATCH($B128,'Trading Comps_Input'!$B$9:$J$9,0),FALSE) -> 13.949752 | N128: =VLOOKUP(N$5,'Trading Comps_Input'!$B$9:$J$188,MATCH($B128,'Trading Comps_Input'!$B$9:$J$9,0),FALSE) -> 3.9856435
A131: x | E131: High | F131: =MAX(F121:F128) -> 2.4948078 | G131: =MAX(G121:G128) -> 10.085686 | H131: =MAX(H121:H128) -> 14.613498 | I131: =MAX(I121:I128) -> 23.012314 | J131: =MAX(J121:J128) -> 2.4560338 | K131: =MAX(K121:K128) -> 11.275389 | L131: =MAX(L121:L128) -> 17.235949 | M131: =MAX(M121:M128) -> 24.9219 | N131: =MAX(N121:N128) -> 9.96876
E132: Median | F132: =MEDIAN(F121:F128) -> 1.714056 | G132: =MEDIAN(G121:G128) -> 8.6610147 | H132: =MEDIAN(H121:H128) -> 12.336695 | I132: =MEDIAN(I121:I128) -> 17.34555 | J132: =MEDIAN(J121:J128) -> 1.5497759 | K132: =MEDIAN(K121:K128) -> 7.5289213 | L132: =MEDIAN(L121:L128) -> 12.264482 | M132: =MEDIAN(M121:M128) -> 13.949752 | N132: =MEDIAN(N121:N128) -> 4.1672498
E133: Low | F133: =MIN(F121:F128) -> 0.99238446 | G133: =MIN(G121:G128) -> 7.6489121 | H133: =MIN(H121:H128) -> 10.671427 | I133: =MIN(I121:I128) -> 11.927025 | J133: =MIN(J121:J128) -> 0.87156703 | K133: =MIN(K121:K128) -> 6.3317605 | L133: =MIN(L121:L128) -> 7.7559685 | M133: =MIN(M121:M128) -> 6.2583545 | N133: =MIN(N121:N128) -> 3.7736428
E134: Mean | F134: =AVERAGE(F121:F128) -> 1.6308021 | G134: =AVERAGE(G121:G128) -> 8.8252704 | H134: =AVERAGE(H121:H128) -> 12.776383 | I134: =AVERAGE(I121:I128) -> 17.77744 | J134: =AVERAGE(J121:J128) -> 1.5299826 | K134: =AVERAGE(K121:K128) -> 7.9929731 | L134: =AVERAGE(L121:L128) -> 11.794608 | M134: =AVERAGE(M121:M128) -> 14.266023 | N134: =AVERAGE(N121:N128) -> 4.9048964
...

Sheet OB_IS
A4: Oriental Brewery Co., Ltd. > Financials > Income Statement
A5: (In KRW millions, except per share items)
B6: Template: | C6: Standard | E6: Restatement: | F6: Latest Filings
B7: Period Type: | C7: Annual | E7: Order: | F7: Latest on Right
B8: Currency: | C8: Reported Currency | E8: Conversion: | F8: Historical
B9: Units: | C9: S&P Capital IQ (Default) | E9: Decimals: | F9: Capital IQ (Default)
B10: Source: | C10: Capital IQ & Proprietary Data
A12: Income Statement
A13: For the Fiscal Period Ending | B13: 39447 | C13: =+B13+366 -> 39813 | D13: =+C13+365 -> 40178 | E13: =+D13+365 -> 40543 | F13: =+E13+365 -> 40908 | G13: =+F13+366 -> 41274 | H13: =+G13+365 -> 41639
A15: Total Revenue | B15: 662072.62 | C15: 750526.94 | D15: 816110.19 | E15: 914149.16 | F15: 1073545.8 | G15: 1259710.9 | H15: 1484804.1
E16: =+E15/D15-1 -> 0.12012958 | F16: =+F15/E15-1 -> 0.17436617 | G16: =+G15/F15-1 -> 0.17341139 | H16: =+H15/G15-1 -> 0.17868641
A17: Cost Of Goods Sold | B17: 265158.53 | C17: 315913.47 | D17: 349660.5 | E17: 406299.97 | F17: 470314.39 | G17: 536603.93 | H17: 606993.14
A18: Gross Profit | B18: 396914.09 | C18: 434613.48 | D18: 466449.68 | E18: 507849.19 | F18: 603231.46 | G18: 723106.99 | H18: 877811
E19: =+E18/E15 -> 0.55554302 | F19: =+F18/F15 -> 0.56190563 | G19: =+G18/G15 -> 0.57402613 | H19: =+H18/H15 -> 0.59119649
A20: Selling General & Admin Exp. | B20: 253281.82 | C20: 256313.7 | D20: 262873.2 | E20: 277598.13 | F20: 314661.23 | G20: 350889.41 | H20: 398398.75
A21: Other Operating Expense/(Income) | B21: 0 | C21: 8158.752 | D21: 7270.824 | E21: 4314.8515 | F21: 4120.79 | G21: 4243.746 | H21: 6680.279
A23: Other Operating Exp., Total | B23: 253281.82 | C23: 264472.45 | D23: 270144.03 | E23: 281912.98 | F23: 318782.02 | G23: 355133.15 | H23: 405079.03
E24: =+E20/E15 -> 0.30366831 | F24: =+F20/F15 -> 0.2931046 | G24: =+G20/G15 -> 0.27854756 | H24: =+H20/H15 -> 0.26831738
A25: Operating Income | B25: 143632.27 | C25: 170141.03 | D25: 196305.66 | E25: 225936.21 | F25: 284449.44 | G25: 367973.83 | H25: 472731.97 | I25: =+H25+OB_SCF!H18 -> 528953.74
A27: Interest Expense | B27: -5668 | C27: -3224.3 | D27: -5138.9 | E27: -71687.2 | F27: -42354 | G27: -26167 | H27: -33001.5
A28: Interest and Invest. Income | B28: 13049.877 | C28: 14630.322 | D28: 12756.581 | E28: 10694.386 | F28: 10212.608 | G28: 9954.414 | H28: 10805.082
A29: Net Interest Exp. | B29: 7381.83 | C29: 11406.065 | D29: 7617.654 | E29: -60992.8 | F29: -32141.4 | G29: -16212.6 | H29: -22196.4
A31: Income/(Loss) from Affiliates | B31: 0 | C31: 8549.355 | D31: 1553.68 | E31: 0 | F31: 0 | G31: 0 | H31: 0
A32: Currency Exchange Gains (Loss) | B32: -217.5 | C32: -2011.5 | D32: 3222.256 | E32: -11663.5 | F32: -24.7 | G32: 905.117 | H32: -240.7
A33: Other Non-Operating Inc. (Exp.) | B33: 2343.007 | C33: 2774.987 | D33: -31669 | E33: -39490.2 | F33: -14453.5 | G33: -3241 | H33: -13374.6
A34: EBT Excl. Unusual Items | B34: 153139.64 | C34: 190859.97 | D34: 177030.28 | E34: 113789.66 | F34: 237829.86 | G34: 349425.3 | H34: 436920.28
A36: Gain (Loss) On Sale Of Assets | B36: 17778.667 | C36: 8630.429 | D36: 537.236 | E36: 3410.393 | F36: 157.526 | G36: -849.2 | H36: -73.5
A37: EBT Incl. Unusual Items | B37: 170918.3 | C37: 199490.4 | D37: 177567.48 | E37: 117200.06 | F37: 237987.39 | G37: 348576.11 | H37: 436846.83
A39: Income Tax Expense | B39: 54995.362 | C39: 80275.802 | D39: 50768.022 | E39: -14364.8 | F39: 66042.093 | G39: 82529.94 | H39: 126675.18
A40: Net Income | B40: 115922.94 | C40: 119214.6 | D40: 126799.45 | E40: 131564.89 | F40: 171945.3 | G40: 266046.17 | H40: 310171.65
D41: =SUM(D39:D40) -> 177567.47
D43: =sum -> #NAME?

Sheet OB_BS
A4: Oriental Brewery Co., Ltd. > Financials > Balance Sheet
A5: (In KRW millions, except per share items)
B6: Template: | C6: Standard | E6: Restatement: | F6: Latest Filings
B7: Period Type: | C7: Annual | E7: Order: | F7: Latest on Right
B8: Currency: | C8: Reported Currency | E8: Conversion: | F8: Historical
B9: Units: | C9: S&P Capital IQ (Default) | E9: Decimals: | F9: Capital IQ (Default)
B10: Source: | C10: Capital IQ & Proprietary Data
A12: Balance Sheet
A13: For the Fiscal Period Ending | B13: 39447 | C13: =+B13+366 -> 39813 | D13: =+C13+365 -> 40178 | E13: =+D13+365 -> 40543 | F13: =+E13+365 -> 40908 | G13: =+F13+366 -> 41274 | H13: =+G13+365 -> 41639
A14: ASSETS
A15: Cash And Equivalents | B15: 141202.33 | C15: 81719.097 | D15: 134104.49 | E15: 175503.16 | F15: 167647.66 | G15: 177904.76 | H15: 444287.57
A16: Short Term Investments | B16: 89.244 | C16: 188.98 | D16: 4.235 | E16: 3.60977 | F16: 2.445 | G16: 108.77177 | H16: 0
A17: Total Cash & ST Investments | B17: 141291.58 | C17: 81908.077 | D17: 134108.72 | E17: 175506.77 | F17: 167650.11 | G17: 178013.53 | H17: 444287.57
A19: Total Receivables | B19: 226950.08 | C19: 229792.84 | D19: 258384.84 | E19: 260889.7 | F19: 271626.56 | G19: 280582.46 | H19: 312554.32
A21: Inventory | B21: 48102.141 | C21: 52157.859 | D21: 53492.258 | E21: 55540.348 | F21: 66835.084 | G21: 79230.575 | H21: 79888.535
A22: Prepaid Exp. | B22: 1152.09 | C22: 1080.39 | D22: 3597.209 | E22: 2066.914 | F22: 2264.013 | G22: 2596.118 | H22: 2608.543
A23: Other Current Assets | B23: 13358.04 | C23: 12582.742 | D23: 10870.469 | E23: 1257.6361 | F23: 242.61466 | G23: 68.01793 | H23: 2623.8174
A24: Total Current Assets | B24: =+SUM(B17,B19,B21:B23) -> 430853.92 | C24: =+SUM(C17,C19,C21:C23) -> 377521.91 | D24: =+SUM(D17,D19,D21:D23) -> 460453.5 | E24: =+SUM(E17,E19,E21:E23) -> 495261.37 | F24: =+SUM(F17,F19,F21:F23) -> 508618.39 | G24: =+SUM(G17,G19,G21:G23) -> 540490.7 | H24: =+SUM(H17,H19,H21:H23) -> 841962.79
A26: Net Property, Plant & Equipment | B26: 437536.34 | C26: 596454.36 | D26: 593634.67 | E26: 674308.3 | F26: 685008.4 | G26: 692900.25 | H26: 735282.5
A28: Long-term Investments | B28: 1286.272 | C28: 2447.457 | D28: 3989.137 | E28: 86.177 | F28: 190.929 | G28: 76.321 | H28: 70.906
A29: Goodwill | B29: 227469.21 | C29: 207826.93 | D29: 188184.65 | E29: 1154161.9 | F29: 1154161.9 | G29: 1154161.9 | H29: 1154161.9
A30: Other Intangibles | B30: 2152.108 | C30: 2117.013 | D30: 1526.279 | E30: 318637.24 | F30: 320029.15 | G30: 319782.61 | H30: 320981.33
A31: Other Long-Term Assets | B31: 40981.933 | C31: 35771.736 | D31: 34348.367 | E31: 42059.105 | F31: 31510.953 | G31: 26742.144 | H31: 26919.647
A32: Total Assets | B32: 1140279.8 | C32: 1222139.4 | D32: 1282136.6 | E32: 2691722.1 | F32: 2705668.6 | G32: 2739546.8 | H32: 3084051.6
A34: LIABILITIES
A35: Accounts Payable | B35: 24162.548 | C35: 33300.754 | D35: 24499.906 | E35: 58075.117 | F35: 92453.967 | G35: 81839.462 | H35: 95145.573
A36: Accrued Exp. | B36: 203701.35 | C36: 132604.03 | D36: 177498.84 | E36: 15329.192 | F36: 14650.694 | G36: 11473.718 | H36: 16989.548
A37: Short-term Borrowings | B37: 5363.161 | C37: 57020.228 | D37: 543.518 | E37: 62462.076 | F37: 2744.347 | G37: 83763.821 | H37: 109562.34
A38: Curr. Port. of LT Debt | B38: 30000 | C38: 40000 | D38: 0 | E38: 0 | F38: 0 | G38: 0 | H38: 56000
A39: Curr. Income Taxes Payable | B39: 46644.962 | C39: 69712.11 | D39: 56040.605 | E39: 104411.86 | F39: 155952.82 | G39: 159134.77 | H39: 176159.6
A40: Other Current Liabilities | B40: 64549.265 | C40: 66266.028 | D40: 73223.31 | E40: 221759.47 | F40: 336808.56 | G40: 288577.95 | H40: 369116.16
A41: Total Current Liabilities | B41: =+SUM(B35:B40) -> 374421.29 | C41: =+SUM(C35:C40) -> 398903.15 | D41: =+SUM(D35:D40) -> 331806.18 | E41: =+SUM(E35:E40) -> 462037.71 | F41: =+SUM(F35:F40) -> 602610.39 | G41: =+SUM(G35:G40) -> 624789.72 | H41: =+SUM(H35:H40) -> 822973.23
A43: Long-Term Debt | B43: 40000 | C43: 0 | D43: 435506.88 | E43: 756323.79 | F43: 469282.64 | G43: 320000 | H43: 652000
A44: Pension & Other Post-Retire. Benefits | B44: 14269.711 | C44: 12573.013 | D44: 12191.977 | E44: 17200.424 | F44: 24024.284 | G44: 31647.672 | H44: 23523.297
A45: Total Liabilities | B45: 428691 | C45: 411476.16 | D45: 779505.04 | E45: 1236478.8 | F45: 1096497.9 | G45: 976972.22 | H45: 1499281.7
A47: EQUITIES
A48: Pref. Stock, Non-Redeem. | B48: 1000 | C48: 1000 | D48: 1000 | E48: 0 | F48: 0 | G48: 0 | H48: 0
A49: Total Pref. Equity | B49: 1000 | C49: 1000 | D49: 1000 | E49: 0 | F49: 0 | G49: 0 | H49: 0
A51: Common Stock | B51: 52800 | C51: 52800 | D51: 40222 | E51: 22011 | F51: 22011 | G51: 22011 | H51: 22011
A52: Additional Paid In Capital | B52: 464625.34 | C52: 464625.34 | D52: 42495.798 | E52: 1295399.1 | F52: 1295399.1 | G52: 31926.5 | H52: 31926.5
A53: Retained Earnings | B53: 193190.9 | C53: 155105.05 | D53: 281904.5 | E53: 137833.13 | F53: 291760.53 | G53: 1708637.1 | H53: 1530832.4
A54: Comprehensive Inc. and Other | B54: -27.4 | C54: 137132.85 | D54: 137009.27 | E54: 0 | F54: 0 | G54: 0 | H54: 0
A55: Total Common Equity | B55: 710588.79 | C55: 809663.24 | D55: 501631.57 | E55: 1455243.3 | F55: 1609170.7 | G55: 1762574.6 | H55: 1584769.9
A57: Total Equity | B57: 711588.79 | C57: 810663.24 | D57: 502631.57 | E57: 1455243.3 | F57: 1609170.7 | G57: 1762574.6 | H57: 1584769.9
A59: Total Liabilities And Equity | B59: 1140279.8 | C59: 1222139.4 | D59: 1282136.6 | E59: 2691722.1 | F59: 2705668.6 | G59: 2739546.8 | H59: 3084051.6

Sheet OB_SCF
A4: Oriental Brewery Co., Ltd. > Financials > Cash Flow
A5: (In KRW millions, except per share items)
B6: Template: | C6: Standard | E6: Restatement: | F6: Latest Filings
B7: Period Type: | C7: Annual | E7: Order: | F7: Latest on Right
B8: Currency: | C8: Reported Currency | E8: Conversion: | F8: Historical
B9: Units: | C9: S&P Capital IQ (Default) | E9: Decimals: | F9: Capital IQ (Default)
B10: Source: | C10: Capital IQ & Proprietary Data
A12: Cash Flow
A13: For the Fiscal Period Ending | B13: 39447 | C13: =+B13+366 -> 39813 | D13: =+C13+365 -> 40178 | E13: =+D13+365 -> 40543 | F13: =+E13+365 -> 40908 | G13: =+F13+366 -> 41274 | H13: =+G13+365 -> 41639
A15: Net Income | B15: 115922.94 | C15: 119214.6 | D15: 126799.45 | E15: 131564.89 | F15: 171945.3 | G15: 266046.16 | H15: 310171.65
A16: Depreciation & Amort. | B16: 39936.53 | C16: 35844.876 | D16: 34788.295 | E16: 73202.869 | F16: 60511.428 | G16: 51203.203 | H16: 54341.732
A17: Amort. of Goodwill and Intangibles | B17: 20354.736 | C17: 20382.632 | D17: 20341.495 | E17: 646.51103 | F17: 1307.0763 | G17: 1463.8054 | H17: 1880.0388
A18: Depreciation & Amort., Total | B18: 60291.266 | C18: 56227.508 | D18: 55129.79 | E18: 73849.38 | F18: 61818.505 | G18: 52667.009 | H18: 56221.771
A20: (Gain) Loss From Sale Of Assets | B20: -2404.7 | C20: -8630.4 | D20: -871.4 | E20: -3410.4 | F20: -157.5 | G20: 849.19228 | H20: 73.45231
A21: (Gain) Loss On Sale Of Invest. | B21: -15373.9 | C21: 0 | D21: 238.2 | E21: 0 | F21: 0 | G21: 0 | H21: 0
A22: Asset Writedown & Restructuring Costs | B22: 0 | C22: 0 | D22: 96.045 | E22: 0 | F22: 0 | G22: 0 | H22: 0
A23: (Income) Loss on Equity Invest. | B23: 0 | C23: -8549.4 | D23: -1553.7 | E23: 0 | F23: 0 | G23: 0 | H23: 0
A24: Provision & Write-off of Bad debts | B24: 0 | C24: -41.5 | D24: 0 | E24: 0 | F24: 0 | G24: 0 | H24: 0
A25: Other Operating Activities | B25: 8267.89 | C25: 14797.511 | D25: 13328.396 | E25: -2887.4 | F25: 75230.673 | G25: 10824.419 | H25: 28873.066
A26: Change in Acc. Receivable | B26: 20997.179 | C26: -3283 | D26: -29408.4 | E26: 15029.931 | F26: -1283.3 | G26: -4046.8 | H26: -20143.1
A27: Change In Inventories | B27: 4003.087 | C27: -3902.2 | D27: -1334.4 | E27: -1735.4 | F27: -11294.7 | G27: -12395.5 | H27: -658
A28: Change in Acc. Payable | B28: 5027.253 | C28: 9402.063 | D28: -8488.5 | E28: 31714.339 | F28: 34321.705 | G28: -10527.1 | H28: 13346.441
A29: Change in Inc. Taxes | B29: 25966.695
A30: Change in Def. Taxes | B30: -2430.2 | C30: -802.8 | D30: 3098.86 | E30: 0 | F30: 0 | G30: 0 | H30: 0
A31: Change in Other Net Operating Assets | B31: 67769.167 | C31: -85183.8 | D31: 35982.529 | E31: -50629.4 | F31: 100329.21 | G31: -54350.4 | H31: 51774.873
A32: Cash from Ops. | B32: 288036.59 | C32: 79984.676 | D32: 178762.76 | E32: 193495.89 | F32: 430909.79 | G32: 249066.98 | H32: 439660.14
A34: Capital Expenditure | B34: -27941.8 | C34: -24923.9 | D34: -32498.4 | E34: -40189.3 | F34: -67237.1 | G34: -54157.2 | H34: -94961.3
A35: Sale of Property, Plant, and Equipment | B35: 2423.77 | C35: 809.897 | D35: 951.18 | E35: 15467.406 | F35: 1543.2296 | G35: 824.12039 | H35: 1144.5641
A36: Sale (Purchase) of Real Estate properties | B36: 37471 | C36: 13518.224 | D36: 289.615 | E36: 0 | F36: 0 | G36: 0 | H36: 0
A37: Sale (Purchase) of Intangible assets | B37: -975.3 | C37: -705.3 | D37: -104.8 | E37: -2008.5 | F37: -1967.8 | G37: -1823.5 | H37: -2919.4
A38: Invest. in Marketable & Equity Securt. | B38: 581.971 | C38: 88.434 | D38: -43.4 | E38: 2.47 | F38: 1.705 | G38: 8.2815 | H38: 114.18677
A39: Net (Inc.) Dec. in Loans Originated/Sold | B39: 10389.694 | C39: -100.3 | D39: 941.405 | E39: 703.314 | F39: 1435.5665 | G39: 893.74656 | H39: 755.96244
A40: Other Investing Activities | B40: 584.613 | C40: 7294.786 | D40: 529.646 | E40: -683.7 | F40: 4079.1382 | G40: -1378.7 | H40: -3355.9
A41: Cash from Investing | B41: 22533.946 | C41: -4018.2 | D41: -29934.7 | E41: -26708.3 | F41: -62145.3 | G41: -55633.3 | H41: -99221.9
A43: Short Term Debt Issued | B43: 5275.372 | C43: 51850.678 | D43: 30781.22 | E43: 22318.951 | F43: 0 | G43: 80806.583 | H43: 26470.337
... A59: Net Change in Cash | B59: 131603.65 | C59: -59483.2 | D59: 52385.39 | E59: 37359.039 | F59: -7855.5 | G59: 10257.098 | H59: 266382.81

Sheet OB맥주_DART
A1: 2009년 감사보고서
B2: http://dart.fss.or.kr/dsaf001/main.do?rcpNo=20100405001258
A4: Balance Sheet
B5: 오비맥주주식회사 | D5: 1000000 | F5: (단위 : 백만원)
B6: 과 목 | C6: 2008.12 | E6: 2009.12
B7: 자 산
B8: Ⅰ. 유동자산 | C8: 0 | D8: 339045.18 | E8: 0 | F8: 422042.33
B9: (1) 당좌자산 | C9: 0 | D9: 286887.32 | E9: 0 | F9: 368550.07
B10: 현금및현금성자산(주17) | C10: 81719.097 | D10: 0 | E10: 134104.49 | F10: 0
B11: 매출채권(주6,17,18,19) | C11: 218112.47 | D11: 0 | E11: 249749.45 | F11: 0
B12: 대손충당금 | C12: -29030.693 | D12: 0 | E12: -31213.61 | F12: 0
B13: 미수금(주6) | C13: 2110.6583 | D13: 0 | E13: 1574.6837 | F13: 0
B14: 대손충당금 | C14: -240.3611 | D14: 0 | E14: -240.3611 | F14: 0
B15: 단기대여금 | C15: 250 | D15: 0 | E15: - | F15: 0
B16: 미수수익 | C16: 114.03914 | D16: 0 | E16: 103.51522 | F16: 0
B17: 선급비용 | C17: 1080.3904 | D17: 0 | E17: 3597.2095 | F17: 0
B18: 만기보유증권(주4) | C18: 188.98 | D18: 0 | E18: 4.235 | F18: 0
B19: 통화선도(주20) | C19: - | D19: 0 | E19: 214.90201 | F19: 0
B20: 기타의당좌자산 | C20: 226.20197 | D20: 0 | E20: 776.41008 | F20: 0
B21: 이연법인세자산(주24) | C21: 12356.54 | D21: 0 | E21: 9879.1557 | F21: 0
B22: (2) 재고자산(주8) | C22: 0 | D22: 52157.859 | E22: 0 | F22: 53492.258
B23: 제품 | C23: 9789.9654 | D23: 0 | E23: 8069.5017 | F23: 0
B24: 평가손실충당금 | C24: -80.042788 | D24: 0 | E24: -101.64298 | F24: 0
B25: 원재료 | C25: 10526.066 | D25: 0 | E25: 18631.857 | F25: 0
B26: 소모품 | C26: 1559.7621 | D26: 0 | E26: 1599.1537 | F26: 0
B27: 재공품 | C27: 24101.728 | D27: 0 | E27: 23290.793 | F27: 0
B28: 미착품 | C28: 4939.6034 | D28: 0 | E28: 1109.8461 | F28: 0
B29: 선전품 | C29: 1320.776 | D29: 0 | E29: 892.75027 | F29: 0
B30: Ⅱ. 비유동자산 | C30: 0 | D30: 883094.22 | E30: 0 | F30: 860094.27
B31: (1) 투자자산 | C31: 0 | D31: 3709.466 | E31: 0 | F31: 5251.1457
... B41: 감가상각누계액 | C41: -23263.284 | D41: 0 | E41: -25155.059 | F41: 0
B42: 손상차손누계액 | C42: - | D42: 0 | E42: -24.234369 | F42: 0
B43: 기계장치 | C43: 465570.66 | D43: 0 | E43: 473922.11 | F43: 0
B44: 감가상각누계액 | C44: -415512.47 | D44: 0 | E44: -429375.57 | F44: 0
B45: 손상차손누계액 | C45: - | D45: 0 | E45: -71.810625 | F45: 0
B46: 용기 | C46: 98372.943 | D46: 0 | E46: 106995.1 | F46: 0
B47: 감가상각누계액 | C47: -84572.16 | D47: 0 | E47: -87964.871 | F47: 0
B48: 차량운반구 | C48: 3872.726 | D48: 0 | E48: 4087.868 | F48: 0
B49: 감가상각누계액 | C49: -2900.251 | D49: 0 | E49: -2960.3549 | F49: 0
B50: 공구와기구 | C50: 6272.3338 | D50: 0 | E50: 6624.4296 | F50: 0
B51: 감가상각누계액 | C51: -4953.1111 | D51: 0 | E51: -5579.0018 | F51: 0
B52: 비품 | C52: 42880.228 | D52: 0 | E52: 44830.408 | F52: 0
B53: 감가상각누계액 | C53: -32855.748 | D53: 0 | E53: -33597.565 | F53: 0
B54: 건설중인자산 | C54: 104.98834 | D54: 0 | E54: 2360.0143 | F54: 0
B55: (3) 무형자산 | C55: 0 | D55: 209943.94 | E55: 0 | F55: 189710.93
B56: 영업권(주10) | C56: 207826.93 | D56: 0 | E56: 188184.65 | F56: 0
B57: 산업재산권(주11) | C57: 792.60066 | D57: 0 | E57: 679.6933 | F57: 0
... B68: 부 채 | C68: 0 | D68: 0 | E68: 0 | F68: 0
B69: Ⅰ. 유동부채 | C69: 0 | D69: 366572.19 | E69: 0 | F69: 298892.69 | G69: =E71+E84+E85 -> 436050.4
B70: 매입채무(주17) | C70: 33300.754 | D70: 0 | E70: 24499.906 | F70: 0
B71: 단기차입금(주14,17) | C71: 57020.228 | D71: 0 | E71: 543.5178 | F71: 0
B72: 미지급금(주6,17) | C72: 45320.419 | D72: 0 | E72: 49192.721 | F72: 0
B73: 미지급법인세(주24) | C73: 37381.152 | D73: 0 | E73: 23127.111 | F73: 0
B74: 선수금 | C74: 267.69313 | D74: 0 | E74: 257.99406 | F74: 0
B75: 예수금 | C75: 128787.63 | D75: 0 | E75: 176021.94 | F75: 0
B76: 미지급비용(주6,17) | C76: 3816.4046 | D76: 0 | E76: 1476.9026 | F76: 0
B77: 환매채무(주19) | C77: 130.53913 | D77: 0 | E77: 177.1423 | F77: 0
B78: 수입보증금 | C78: 20179.092 | D78: 0 | E78: 23110.836 | F78: 0
B79: 임대보증금 | C79: 126.11 | D79: 0 | E79: 126.11 | F79: 0
B80: 통화선도(주20) | C80: - | D80: 0 | E80: 357.77827 | F80: 0
B81: 유동성사채(주13) | C81: 40000 | D81: 0 | E81: - | F81: 0
B82: 기타의유동부채 | C82: 242.17625 | D82: 0 | E82: 0.730003 | F82: 0
B83: Ⅱ. 비유동부채 | C83: 0 | D83: 44903.97 | E83: 0 | F83: 480612.35
B84: 사채(주17,19) | C84: - | D84: 0 | E84: 155482.29 | F84: 0
B85: 장기차입금(주14,19) | C85: - | D85: 0 | E85: 280024.59 | F85: 0
B86: 퇴직급여충당부채(주15) | C86: 42392.945 | D86: 0 | E86: 39702.11 | F86: 0
B87: 퇴직보험예치금 | C87: -29401.504 | D87: 0 | E87: -27239.307 | F87: 0
B88: 국민연금전환금 | C88: -418.4282 | D88: 0 | E88: -270.8259 | F88: 0
B89: 이연법인세부채(주7,24) | C89: 32330.958 | D89: 0 | E89: 32913.494 | F89: 0
B90: 부 채 총 계 | C90: 0 | D90: 411476.16 | E90: 0 | F90: 779505.04
B91: 자 본 | C91: 0 | D91: 0 | E91: 0 | F91: 0
B92: Ⅰ. 자본금(주21) | C92: 0 | D92: 53800 | E92: 0 | F92: 41222
B93: 보통주자본금 | C93: 52800 | D93: 0 | E93: 40222 | F93: 0
B94: 우선주자본금 | C94: 1000 | D94: 0 | E94: 1000 | F94: 0
B95: Ⅱ. 자본잉여금(주21) | C95: 0 | D95: 464625.34 | E95: 0 | F95: 42495.798
B96: 주식발행초과금 | C96: 464625.34 | D96: 0 | E96: 2404.6694 | F96: 0
B97: 감자차익 | C97: - | D97: 0 | E97: 40091.128 | F97: 0
B98: Ⅲ. 자본조정 | C98: 0 | D98: - | E98: 0 | F98: -1.45536
B99: 기타의자본조정 | C99: - | D99: 0 | E99: -1.45536 | F99: 0
B100: Ⅳ. 기타포괄손익누계액 | C100: 0 | D100: 137132.85 | E100: 0 | F100: 137010.72
B101: 통화선도평가손실(주20,26) | C101: - | D101: 0 | E101: -271.19593 | F101: 0
B102: 통화선도평가이익(주20,26) | C102: - | D102: 0 | E102: 162.89572 | F102: 0
B103: 재평가잉여금(주7,26) | C103: 137132.85 | D103: 0 | E103: 137119.02 | F103: 0
B104: Ⅳ. 이익잉여금 | C104: 0 | D104: 155105.05 | E104: 0 | F104: 281904.5
B105: 법정적립금(주22) | C105: 19654.144 | D105: 0 | E105: 29042.244 | F105: 0
B106: 미처분이익잉여금 | C106: 135450.91 | D106: 0 | E106: 252862.26 | F106: 0
B107: 자 본 총 계 | C107: 0 | D107: 810663.24 | E107: 0 | F107: 502631.57
B108: 부 채 와 자 본 총 계 | C108: 0 | D108: 1222139.4 | E108: 0 | F108: 1282136.6
A110: Income Statement
B111: 오비맥주주식회사 | F111: (단위 : 백만원)
B112: 과 목 | C112: 2008.12 | E112: 2009.12
B113: Ⅰ. 매출액 | C113: 0 | D113: 750526.94 | E113: 0 | F113: 816110.19
B114: (1) 제품매출 | C114: 1388443.4 | D114: 0 | E114: 1496974 | F114: 0
B115: (2) 기타매출(주6) | C115: 3946.5063 | D115: 0 | E115: 4283.4982 | F115: 0
B116: (3) 주세 등 | C116: -641862.95 | D116: 0 | E116: -685147.36 | F116: 0
B117: Ⅱ. 매출원가 | C117: 0 | D117: 311618.01 | E117: 0 | F117: 346672.53
B118: (1) 제품매출원가 | C118: 310746.07 | D118: 0 | E118: 345930.19 | F118: 0
B119: 기초제품재고액 | C119: 8627.938 | D119: 0 | E119: 9709.9226 | F119: 0
B120: 당기제품제조원가 | C120: 313237.33 | D120: 0 | E120: 344931.98 | F120: 0
B121: 계 | C121: 321865.27 | D121: 0 | E121: 354641.9 | F121: 0
...

Sheet 하이트진로_DART
A1: 2009년 연결감사보고서
B2: http://dart.fss.or.kr/dsaf001/main.do?rcpNo=20100331000603&dcmNo=2586232
B4: 하이트맥주 연결재무제표
A6: Balance Sheet
B7: 회사명 : 하이트맥주 주식회사와 그 종속회사 | C7: (단위 : 원)
B8: 과 목 | C8: 제 2(당) 기
B9: 자 산
B10: I.유동자산 | D10: 572179733499
B11: (1)당좌자산 | D11: 451266611275
B12: 현금및현금성자산 <주석 18> | C12: 44233059985
B13: 단기투자자산 <주석 8,9,20> | C13: 10360561262
B14: 매출채권 <주석 13,18,20> | C14: 375090064170
B15: 대손충당금 | C15: -34918594728
B16: 미수금 <주석 20> | C16: 38129508346
B17: 대손충당금 | C17: -2478586454
B18: 미수수익 | C18: 418068883
B19: 선급금 | C19: 4514000725
B20: 선급비용 | C20: 6944756405
B21: 유동성이연법인세자산 <주석 26> | C21: 8973772681
B22: (2)재고자산 <주석 12> | D22: 120913122224
B23: 제품 | C23: 15100040414
B24: 재공품 | C24: 23986082064
B25: 원재료 | C25: 47232429099
B26: 저장품 | C26: 9734469435
B27: 상품 | C27: 6484855483
B28: 미착품 | C28: 18375245729
B29: II.비유동자산 | D29: 1729565479684
B30: (1)투자자산 | D30: 1965768911
B31: 장기금융상품 <주석 7> | C31: 183700000
B32: 매도가능증권 <주석 9> | C32: 1655400911
B33: 장기대여금 <주석 20> | C33: 126668000
B34: (2)유형자산 <주석 2,10,12,23> | D34: 1643409698974
B35: 토지 | C35: 445545967978
B36: 설비자산 | C36: 1827294910673
B37: 감가상각누계액 | C37: -663346149670
B38: 건설중인 자산 | C38: 33914969993
B39: (3)무형자산 <주석 11> | D39: 12555632493
B40: 영업권 | C40: 12546520208
B41: 기타의무형자산 | C41: 9112285
B42: (4)기타비유동자산 | D42: 71634379306
B43: 장기매출채권 <주석 13> | C43: 22808191744
B44: 대손충당금 | C44: -4371956100
B45: 보증금 <주석 20> | C45: 42619682085
B46: 기타의비유동자산 <주석 20> | C46: 10367544043
B47: 비유동성이연법인세자산 <주석 26> | C47: 210917534
B48: 자 산 총 계 | D48: 2301745213183
B49: 부 채
B50: I.유동부채 | D50: 1136276184243
B51: 단기차입금 <주석 14,15,18,23,24> | C51: 562162920635
B52: 매입채무 <주석 18,20> | C52: 26416576617
B53: 미지급금 <주석 20> | C53: 65789368987
B54: 예수금 | C54: 241759961014
B55: 미지급비용 | C55: 14027868901
B56: 미지급법인세 | C56: 6658733561
B57: 선수금 | C57: 8371341056
B58: 유동성사채 <주석 16> | C58: 200000000000
B59: 유동성사채할인발행차금 | C59: -82643871
B60: 유동성파생상품부채 <주석 15> | C60: 11172057343 | F60: 차입금 추가하기 /// EJS!!: 차입금에 대한 환율리스크를 헤지하기 위해서 계약한 파생상품은 차입금에 포함시켜야될까? // CIQ는 이를 Debt에 포함시켰음 // 나는 포함시키지는 않음
B61: II.비유동부채 | D61: 323959751113
B62: 사채 <주석 16> | C62: 250000000000
B63: 사채할인발행차금 | C63: -696928495
B64: 퇴직급여충당부채 <주석 17> | C64: 85137344851
B65: 퇴직보험예치금 | C65: -67688753496
B66: 퇴직연금운용자산 | C66: -2449795179
B67: 국민연금전환금 | C67: -1159045656
B68: 임대보증금 <주석 20> | C68: 22876220727
B69: 비유동성이연법인세부채 <주석 26> | C69: 37940708361
B70: 부 채 총 계 | D70: 1460235935356
B71: 자 본
B72: I.지배회사지분 | D72: 841509277827
B73: (1)자본금 <주석 21> | D73: 49684265000
B74: 보통주자본금 | C74: 47819590000
B75: 우선주자본금 | C75: 1864675000
B76: (2)연결자본잉여금 | D76: 516746572978
B77: 주식발행초과금 | C77: 516746572978
B78: (3)연결자본조정 | D78: -1071624000
B79: 자기주식 <주석 22> | C79: -1071624000
B80: (4)연결기타포괄손익누계액 <주석 25> | D80: 149406485633
B81: 매도가능증권평가이익 | C81: 88655854
B82: 토지재평가이익 <주석 2,10> | C82: 149317829779
B83: (5)연결이익잉여금 | D83: 126743578216
B84: 법정적립금 | C84: 2500000000
B85: 임의적립금 | C85: 25000000000
B86: 미처분이익잉여금 | C86: 99243578216
B87: II.소수주주지분 | D87: 0
B88: 자 본 총 계 | D88: 841509277827
B89: 부 채 와 자 본 총 계 | D89: 2301745213183
B91: "첨부된 연결재무제표에 대한 주석 참조"
A93: Income Statement
B94: 회사명 : 하이트맥주 주식회사와 그 종속회사 | C94: (단위 : 원)
B95: 과 목 | C95: 제 2(당) 기
B96: I.매출액 <주석 20> | D96: 1049535950404
B97: 1.총매출액 | C97: 1954625321186
B98: 가.주류매출액 | C98: 1950594008558
B99: 나.기타매출액 | C99: 4031312628
B100: 2.주세 등 | C100: -905089370782
B101: II.매출원가 <주석 20> | D101: 516464509487
B102: 기초상품및제품재고액 | C102: 19719895067
B103: 당기제품제조원가 | C103: 505775005915
B104: 당기상품매입액 | C104: 24971086669
...
