Workbook
Name Com_Data_sum_035900: '요약 재무제표'!$B$2

Sheet Estimate ▶
A3: 클래시스(214150.KQ)_PER
A5: Estimate Sheets >>>
C7: Chungang-Univ. Financial Institute
C8: R.F.S .
C9: Valuation Model
C19: RFS 정식 회원 외 본 가치평가 모델의 무단 사용 및 수정을 금하며, 본 양식의 원 저작권은 중앙대학교 R.F.S. 학회에 있음을 밝힙니다.
C20: 원 제작자: 28기 김 건 (zzkan103@gmail.com)
C21: 1st Version: 2021.03.02

Sheet Valuation
A1: 클래시스(214150.KQ)
A2: Assumption Sheet
A3: (units in Millions KRW )
B6: 클래시스 PER Valuation | H6: 일자 | I6: 선행 PER
B7: 12M Fwd 당기순이익 | D7: =SUM('비용 추정'!O54:R54) -> 147350.08 | E7: (백만원) | F7: (A) | H7: 43800 | I7: 24.2295
C8: Target P/E | D8: =AVERAGE(I10:I11)*1.5 -> 34.625025 | E8: (배) | F8: (B) | H8: 44166 | I8: 20.1253
B9: 적정 기업가치 | D9: =D8*D7/100 -> 51020.004 | E9: (억원) | F9: (C) = (A)*(B) | H9: 44531 | I9: 22.1561
B10: 발행 주식 수 | D10: 65505 | E10: (천 주) | F10: (D) | H10: 44896 | I10: 17.8089
B11: 적정주가 | D11: =(D9*100000000)/(D10*1000) -> 77887.19 | E11: 원 | F11: (E) = (C)/(D) | H11: 45261 | I11: 28.3578
B12: Target Price | D12: 77900 | E12: 원 | F12: 목표주가 | H12: 45627 | I12: 24.9142
B13: Current Price | D13: 58000 | E13: 원 | F13: 25.04.01 기준 | H13: 45992 | I13: 26.0792
B14: Upside | D14: =(D12/D13-1)*100 -> 34.310345 | E14: %

Sheet Expected IS
A1: 클래시스(214150.KQ)
A2: Assumption Sheet
A3: (units in Millions KRW )
B5: 단위: 백만원 | C5: 1Q22 | D5: 2Q22 | E5: 3Q22 | F5: 4Q22 | G5: 1Q23 | H5: 2Q23 | I5: 3Q23 | J5: 4Q23 | K5: 1Q24 | L5: 2Q24 | M5: 3Q24 | N5: 4Q24 | O5: 1Q25E | P5: 2Q25E | Q5: 3Q25E | R5: 4Q25E | S5: 2023 | T5: 2024 | U5: 2025
B6: 매출액 | C6: ='비용 추정'!C6 -> 35382 | D6: ='비용 추정'!D6 -> 32686 | E6: ='비용 추정'!E6 -> 33268 | F6: ='비용 추정'!F6 -> 40467 | G6: ='비용 추정'!G6 -> 38974 | H6: ='비용 추정'!H6 -> 45897 | I6: ='비용 추정'!I6 -> 48243 | J6: ='비용 추정'!J6 -> 47008 | ... N6: ='비용 추정'!N6 -> 74403 | O6: ='매출액 추정'!O6 -> 80584.532 | P6: ='매출액 추정'!P6 -> 82456.052 | Q6: ='매출액 추정'!Q6 -> 91470.968 | R6: ='매출액 추정'!R6 -> 100949.82 | T6: =SUM(K6:N6) -> 242939 | U6: =SUM(O6:R6) -> 355461.37
B7: 매출원가 | C7: ='비용 추정'!C7 -> 8800 | D7: ='비용 추정'!D7 -> 8277 | E7: ='비용 추정'!E7 -> 7317 | F7: ='비용 추정'!F7 -> 9241 | G7: ='비용 추정'!G7 -> 8764 | H7: ='비용 추정'!H7 -> 9577 | I7: ='비용 추정'!I7 -> 11234 | J7: ='비용 추정'!J7 -> 10099 | ... R7: ='비용 추정'!R7 -> 19180.466 | T7: =SUM(K7:N7) -> 51812 | U7: =SUM(O7:R7) -> 73322.96
B8: (%) | C8: 0.24872106 | D8: 0.25324318 | E8: 0.21994108 | F8: 0.22835891 | G8: 0.22486786 | H8: 0.20865833 | I8: 0.23284832 | J8: 0.21484948 | K8: 0.20200877 | L8: 0.19114418 | M8: 0.21567307 | N8: 0.23645234 | O8: =O7/O6 -> 0.22484164 | P8: =P7/P6 -> 0.21322776 | Q8: =Q7/Q6 -> 0.20161388 | R8: =R7/R6 -> 0.19 | T8: =SUM(K8:N8) -> 0.84527836 | U8: =SUM(O8:R8) -> 0.82968328
B9: 매출총이익 | C9: =C6-C7 -> 26582 | D9: =D6-D7 -> 24409 | E9: =E6-E7 -> 25951 | F9: =F6-F7 -> 31226 | G9: =G6-G7 -> 30210 | H9: =H6-H7 -> 36320 | I9: =I6-I7 -> 37009 | J9: =J6-J7 -> 36909 | ... R9: =R6-R7 -> 81769.356 | T9: =SUM(K9:N9) -> 191127 | U9: =SUM(O9:R9) -> 282138.41
B10: GPM(%) | C10: 0.75127894 | D10: 0.74675682 | E10: 0.78005892 | F10: 0.77164109 | G10: 0.77513214 | H10: 0.79134167 | I10: 0.76715168 | J10: 0.78515052 | K10: 0.79799123 | L10: 0.80885582 | M10: 0.78432693 | N10: 0.76354766 | O10: =O9/O6 -> 0.77515836 | P10: =P9/P6 -> 0.78677224 | Q10: =Q9/Q6 -> 0.79838612 | R10: =R9/R6 -> 0.81 | T10: =SUM(K10:N10) -> 3.1547216 | U10: =SUM(O10:R10) -> 3.1703167
B11: 판매비와 관리비 | C11: ='비용 추정'!C11 -> 9876.724 | D11: ='비용 추정'!D11 -> 9144.9522 | E11: ='비용 추정'!E11 -> 8471.9286 | F11: ='비용 추정'!F11 -> 11797.212 | G11: ='비용 추정'!G11 -> 10318.628 | H11: ='비용 추정'!H11 -> 13174.374 | I11: ='비용 추정'!I11 -> 12348.212 | J11: ='비용 추정'!J11 -> 14985.469 | ... R11: ='비용 추정'!R11 -> 27636.256 | T11: =SUM(K11:N11) -> 68671.739 | U11: =SUM(O11:R11) -> 97266.365
B12: (%) | C12: 0.27913287 | D12: 0.27976992 | E12: 0.25462907 | F12: 0.29152149 | G12: 0.26476625 | H12: 0.28702776 | I12: 0.25593832 | J12: 0.31879587 | K12: 0.27181961 | L12: 0.27793194 | M12: 0.29703437 | N12: 0.28228993 | O12: =O11/O6 -> 0.27399257 | P12: =P11/P6 -> 0.27386846 | Q12: =Q11/Q6 -> 0.27296567 | R12: =R11/R6 -> 0.2737623 | T12: =SUM(K12:N12) -> 1.1290758 | U12: =SUM(O12:R12) -> 1.094589
B13: 영업이익 | C13: ='비용 추정'!C44 -> 16705.276 | D13: ='비용 추정'!D44 -> 15264.048 | E13: ='비용 추정'!E44 -> 17479.071 | F13: ='비용 추정'!F44 -> 19428.788 | G13: ='비용 추정'!G44 -> 19891.372 | H13: ='비용 추정'!H44 -> 23145.626 | I13: ='비용 추정'!I44 -> 24660.788 | J13: ='비용 추정'!J44 -> 21923.531 | ... N13: ='비용 추정'!N44 -> 35806.308 | O13: =O9-O11 -> 40386.211 | P13: =P9-P11 -> 42292.021 | Q13: =Q9-Q11 -> 48060.717 | R13: =R9-R11 -> 54133.1 | T13: =SUM(K13:N13) -> 122455.26 | U13: =SUM(O13:R13) -> 184872.05
B14: OPM(%) | C14: 0.47214607 | D14: 0.4669869 | E14: 0.52542984 | F14: 0.4801196 | G14: 0.51036588 | H14: 0.50431391 | I14: 0.51121336 | J14: 0.46635464 | K14: 0.52617162 | L14: 0.53092389 | M14: 0.48729256 | N14: 0.48125773 | O14: =O13/O6 -> 0.50116579 | P14: =P13/P6 -> 0.51290378 | Q14: =Q13/Q6 -> 0.52542045 | R14: =R13/R6 -> 0.5362377 | T14: =SUM(K14:N14) -> 2.0256458 | U14: =SUM(O14:R14) -> 2.0757277
B15: 지분법손익 | C15: 0 | D15: 0 | E15: 0 | F15: 0 | G15: 0 | H15: 0 | I15: 0 | J15: 0 | K15: 0 | L15: 267 | M15: -822.65555 | N15: -511 | O15: ='비용 추정'!O46 -> -511 | P15: ='비용 추정'!P46 -> -511 | Q15: ='비용 추정'!Q46 -> -511 | R15: ='비용 추정'!R46 -> -511 | T15: =SUM(K15:N15) -> -1066.6555 | U15: =SUM(O15:R15) -> -2044
B16: 금융수익 | C16: 704 | D16: 2974 | E16: 5432 | F16: -6526 | G16: 4394 | H16: 2027 | I16: 4088 | J16: -1850 | K16: 6480 | L16: 4854 | M16: -3060 | N16: 15933 | O16: ='비용 추정'!O47 -> 2419 | P16: ='비용 추정'!P47 -> 2419 | Q16: ='비용 추정'!Q47 -> 2419 | R16: ='비용 추정'!R47 -> 2419 | T16: =SUM(K16:N16) -> 24207 | U16: =SUM(O16:R16) -> 9676
B17: 금융비용 | C17: -792 | D17: -731 | E17: -770 | F17: -2380 | G17: -1145 | H17: -489 | I17: -564 | J17: -1395 | K17: -556 | L17: -536 | M17: -2674.6856 | N17: -144 | O17: {='비용 추정'!O48:R48} -> -937.9607 | P17: -937.9607 | Q17: -937.9607 | R17: -937.9607 | T17: =SUM(K17:N17) -> -3910.6856 | U17: =SUM(O17:R17) -> -3751.8428
B18: 기타수익 | C18: 2 | D18: 27 | E18: 5 | F18: 30338 | G18: 1 | H18: 15 | I18: 15 | J18: 17.429602 | K18: 0.4 | L18: 10 | M18: 1.375159 | N18: 17.402788 | O18: ='비용 추정'!O49 -> 0 | P18: ='비용 추정'!P49 -> 0 | Q18: ='비용 추정'!Q49 -> 0 | R18: ='비용 추정'!R49 -> 0 | T18: =SUM(K18:N18) -> 29.177947 | U18: =SUM(O18:R18) -> 0
B19: 기타비용 | C19: -0.002 | D19: -0.2 | E19: -0.06 | F19: -400 | G19: -11 | H19: -51 | I19: -434 | J19: -398 | K19: -346 | L19: -1241 | M19: -2.069708 | N19: -12190 | O19: ='비용 추정'!O50 -> 0 | P19: ='비용 추정'!P50 -> 0 | Q19: ='비용 추정'!Q50 -> 0 | R19: ='비용 추정'!R50 -> 0 | T19: =SUM(K19:N19) -> -13779.07 | U19: =SUM(O19:R19) -> 0
B20: 법인세차감전순이익 | C20: =C13+SUM(C16:C19) -> 16619.274 | D20: =D13+SUM(D16:D19) -> 17533.848 | E20: =E13+SUM(E16:E19) -> 22146.011 | F20: =F13+SUM(F16:F19) -> 40460.788 | G20: =G13+SUM(G16:G19) -> 23130.372 | H20: =H13+SUM(H16:H19) -> 24647.626 | I20: =I13+SUM(I16:I19) -> 27765.788 | J20: =J13+SUM(J16:J19) -> 18297.961 | K20: =K13+SUM(K16:K19) -> 32056.101 | L20: =L13+SUM(L15:L19) -> 34573.482 | M20: =M13+SUM(M15:M19) -> 22393.734 | N20: =N13+SUM(N15:N19) -> 38911.711 | O20: ='비용 추정'!O51 -> 41356.752 | P20: ='비용 추정'!P51 -> 43262.573 | Q20: ='비용 추정'!Q51 -> 49031.281 | R20: ='비용 추정'!R51 -> 55103.676 | T20: =SUM(K20:N20) -> 127935.03 | U20: =SUM(O20:R20) -> 188754.28
B21: 법인세비용 | C21: -3802 | D21: -3725 | E21: -3430 | F21: -10424 | G21: -4355 | H21: -6089 | I21: -6575 | J21: -2597 | K21: -6002.4 | L21: -7961 | M21: -5908.5838 | N21: -10514.903 | O21: ='비용 추정'!O52 -> -9027.2983 | P21: ='비용 추정'!P52 -> -9405.4734 | Q21: ='비용 추정'!Q52 -> -10679.875 | R21: ='비용 추정'!R52 -> -12291.551 | T21: =SUM(K21:N21) -> -30386.887 | U21: =SUM(O21:R21) -> -41404.197
B22: 당기순이익 | C22: 12816.998 | D22: 13807.8 | E22: 18716.94 | F22: 30037 | G22: 18775 | H22: 18560 | I22: 21194 | J22: 15698.43 | K22: 26084 | L22: 26580 | M22: 16485.381 | N22: 28398 | O22: ='비용 추정'!O54 -> 32329.453 | P22: ='비용 추정'!P54 -> 33857.1 | Q22: ='비용 추정'!Q54 -> 38351.407 | R22: ='비용 추정'!R54 -> 42812.125 | T22: =SUM(K22:N22) -> 97547.381 | U22: =SUM(O22:R22) -> 147350.08
B23: (%) | C23: 0.36225652 | D23: 0.42246359 | E23: 0.56261092 | F23: 0.74225912 | G23: 0.48173141 | H23: 0.40437492 | I23: 0.4392903 | J23: 0.33397361 | K23: 0.51775541 | L23: 0.45249485 | M23: 0.27746626 | N23: 0.38167303 | O23: =O22/O6 -> 0.40118683 | P23: =P22/P6 -> 0.41060782 | Q23: =Q22/Q6 -> 0.41927409 | R23: =R22/R6 -> 0.42409312 | T23: =SUM(K23:N23) -> 1.6293896 | U23: =SUM(O23:R23) -> 1.6551619
B24: 감가상각비 | C24: 946 | D24: 974 | E24: 1003 | F24: 976 | G24: 984.205 | H24: 1033 | I24: 1103 | J24: 1158 | K24: 1159.778 | L24: 1176.567 | M24: 1204 | N24: 3664 | T24: =SUM(K24:N24) -> 7204.345 | U24: =SUM(O24:R24) -> 0
B25: EBITDA | C25: 17651 | D25: 16237 | E25: 18483 | F25: 20405 | G25: 20875.205 | H25: 24180 | I25: 25767 | J25: 23079 | K25: 27667.778 | L25: 32363.567 | M25: 30156 | N25: 39471.5 | T25: =SUM(K25:N25) -> 129658.84 | U25: =SUM(O25:R25) -> 0
B26: (%) | C26: 0.49888358 | D26: 0.49678742 | E26: 0.55557893 | F26: 0.50423802 | G26: 0.53561875 | H26: 0.52682034 | I26: 0.53407536 | J26: 0.49099032 | K26: 0.54919268 | L26: 0.55095363 | M26: 0.50755714 | N26: 0.53050239 | T26: =SUM(K26:N26) -> 2.1382058 | U26: =SUM(O26:R26) -> 0

Sheet 매출액 추정
A1: 클래시스(214150.KQ)
A2: Assumption Sheet
A3: (units in Millions KRW )
B5: (단위: 백만 원) | C5: 1Q22 | D5: 2Q22 | E5: 3Q22 | F5: 4Q22 | G5: 1Q23 | H5: 2Q23 | I5: 3Q23 | J5: 4Q23 | K5: 1Q24 | L5: 2Q24 | M5: 3Q24 | N5: 4Q24 | O5: 1Q25E | P5: 2Q25E | Q5: 3Q25E | R5: 4Q25E | S5: 1Q26E | T5: 2Q26E | U5: 3Q26E | V5: 4Q26E | W5: 2024 | X5: 2025E | Y5: 2026E
B6: 전체 매출액 | C6: =SUM(C8,C18,C20) -> 35382 | D6: =SUM(D8,D18,D20) -> 32686 | E6: =SUM(E8,E18,E20) -> 33268 | F6: =SUM(F8,F18,F20) -> 40467 | G6: =SUM(G8,G18,G20) -> 38974 | H6: =SUM(H8,H18,H20) -> 45897 | I6: =SUM(I8,I18,I20) -> 48243 | J6: =SUM(J8,J18,J20) -> 47008 | ... M6: =SUM(M8,M18,M20) -> 59414 | N6: =SUM(N8,N18,N20,N16) -> 74403 | O6: =SUM(O8,O18,O20,O16) -> 80584.532 | P6: =SUM(P8,P18,P20,P16) -> 82456.052 | Q6: =SUM(Q8,Q18,Q20,Q16) -> 91470.968 | R6: =SUM(R8,R18,R20,R16) -> 100949.82 | S6: =SUM(S8,S18,S20,S16) -> 107625.71 | T6: =SUM(T8,T18,T20,T16) -> 116479.59 | U6: =SUM(U8,U18,U20,U16) -> 124912.66 | V6: =SUM(V8,V18,V20,V16) -> 131740.97 | W6: =SUM(W8,W16,W18,W20) -> 242939 | X6: =SUM(X8,X18,X20,X16) -> 355461.37 | Y6: =SUM(Y8,Y18,Y20,Y16) -> 480758.93
B7: YoY% | G7: =G6/C6-1 -> 0.10152055 | H7: =H6/D6-1 -> 0.40417916 | I7: =I6/E6-1 -> 0.45013226 | J7: =J6/F6-1 -> 0.16163788 | K7: =K6/G6-1 -> 0.29186124 | L7: =L6/H6-1 -> 0.28054121 | M7: =M6/I6-1 -> 0.23155691 | N7: =N6/J6-1 -> 0.58277314 | ... V7: =V6/R6-1 -> 0.30501441 | X7: =X6/W6-1 -> 0.46317131 | Y7: =Y6/X6-1 -> 0.35249275
B8: 의료기기 | C8: =SUM(C10,C12,C14) -> 34293 | D8: =SUM(D10,D12,D14) -> 31395 | E8: =SUM(E10,E12,E14) -> 32305 | F8: =SUM(F10,F12,F14) -> 39694 | G8: =SUM(G10,G12,G14) -> 38207 | H8: =SUM(H10,H12,H14) -> 45263 | I8: =SUM(I10,I12,I14) -> 47201 | J8: =SUM(J10,J12,J14) -> 45445 | ... V8: =SUM(V10,V12,V14) -> 106584.25 | W8: =SUM(K8:N8) -> 225735 | X8: =SUM(X10,X12,X14) -> 286160.9 | Y8: =SUM(Y10,Y12,Y14) -> 385796.95
B9: % of sales | C9: =C8/C6 -> 0.96922164 | D9: =D8/D6 -> 0.96050297 | E9: =E8/E6 -> 0.97105326 | F9: =F8/F6 -> 0.98089802 | G9: =G8/G6 -> 0.98032021 | H9: =H8/H6 -> 0.98618646 | I9: =I8/I6 -> 0.97840101 | J9: =J8/J6 -> 0.96675034 | ... Y9: =Y8/Y6 -> 0.80247484
B10: 클래시스 | C10: =8752+11789 -> 20541 | D10: =18116+19559-C10 -> 17134 | E10: =29609+23586-D10-C10 -> 15520 | F10: =44284+29903-SUM(C10:E10) -> 20992 | G10: =12460+5893 -> 18353 | H10: =28766+11544-G10 -> 21957 | I10: =46546+19586-G10-H10 -> 25822 | J10: =63157+26822-SUM(G10:I10) -> 23847 | K10: =14261+6537 -> 20798 | L10: =37562+13130-K10 -> 29894 | M10: =62935+19296-K10-L10 -> 31539 | N10: =84686+26302-SUM(K10:M10) -> 28757 | O10: =의료기기!O6 -> 32402.688 | P10: =의료기기!P6 -> 35838.045 | Q10: =의료기기!Q6 -> 38404.647 | R10: =의료기기!R6 -> 42455.888 | S10: =의료기기!S6 -> 45291.604 | T10: =의료기기!T6 -> 48588.353 | U10: =의료기기!U6 -> 52429.855 | V10: =의료기기!V6 -> 55663.928 | W10: =SUM(K10:N10) -> 110988 | X10: =SUM(O10:R10) -> 149101.27 | Y10: =SUM(S10:V10) -> 201973.74
B11: % of sales | C11: =C10/C6 -> 0.58054943 | D11: =D10/D6 -> 0.52419996 | E11: =E10/E6 -> 0.46651437 | F11: =F10/F6 -> 0.51874367 | G11: =G10/G6 -> 0.47090368 | H11: =H10/H6 -> 0.47839728 | I11: =I10/I6 -> 0.53524864 | J11: =J10/J6 -> 0.50729663 | ... Y11: =Y10/Y6 -> 0.42011438
B12: 클루덤 | C12: =1864+130 -> 1994 | D12: =3991+308-C12 -> 2305 | E12: =5376+446-C12-D12 -> 1523 | F12: =7397+519-SUM(C12:E12) -> 2094 | G12: =1042+126 -> 1168 | H12: =2449+251-G12 -> 1532 | I12: =3266+316-G12-H12 -> 882 | J12: =4770+325-SUM(G12:I12) -> 1513 | K12: =1332+66 -> 1398 | L12: =2277+125-K12 -> 1004 | M12: =3395+203-L12-K12 -> 1196 | N12: =4524+363-SUM(K12:M12) -> 1289 | O12: =의료기기!Q75 -> 1221.75 | P12: =의료기기!R75 -> 1177.6875 | Q12: =의료기기!S75 -> 1221.1094 | R12: =의료기기!T75 -> 1227.3867 | S12: =의료기기!U75 -> 1211.9834 | T12: =의료기기!V75 -> 1209.5417 | U12: =의료기기!W75 -> 1217.5053 | V12: =의료기기!X75 -> 1216.6043 | ... Y12: =의료기기!AA75 -> 4855.6348
B13: % of sales | C13: =C12/C6 -> 0.056356339 | D13: =D12/D6 -> 0.070519488 | E13: =E12/E6 -> 0.045779728 | F13: =F12/F6 -> 0.051745867 | G13: =G12/G6 -> 0.029968697 | H13: =H12/H6 -> 0.033379088 | I13: =I12/I6 -> 0.018282445 | J13: =J12/J6 -> 0.032186011 | ... Y13: =Y12/Y6 -> 0.010099937
B14: 소모품 등 | C14: =8300+3458 -> 11758 | D14: =15836+7878-C14 -> 11956 | E14: =25620+13356-C14-D14 -> 15262 | F14: =34715+20869-SUM(C14:E14) -> 16608 | G14: =10478+8208 -> 18686 | H14: =23984+16476-G14 -> 21774 | I14: =36143+24814-G14-H14 -> 20497 | J14: =47778+33264-SUM(G14:I14) -> 20085 | K14: =17358+9138 -> 26496 | L14: =32836+19725-K14 -> 26065 | M14: =46414+32158-L14-K14 -> 26011 | N14: =64512+45348-SUM(K14:M14) -> 31288 | O14: =소모품!P6 -> 32450.63 | P14: =소모품!Q6 -> 29635.387 | Q14: =소모품!R6 -> 33324.639 | R14: =소모품!S6 -> 36801.046 | S14: =소모품!T6 -> 39398.318 | T14: =소모품!U6 -> 43497.969 | U14: =소모품!V6 -> 46367.57 | V14: =소모품!W6 -> 49703.714 | W14: =SUM(K14:N14) -> 109860 | X14: =SUM(O14:R14) -> 132211.7 | Y14: =SUM(S14:V14) -> 178967.57
B15: % of sales | C15: =C14/C6 -> 0.33231587 | D15: =D14/D6 -> 0.36578352 | E15: =E14/E6 -> 0.45875917 | F15: =F14/F6 -> 0.41040848 | G15: =G14/G6 -> 0.47944784 | H15: =H14/H6 -> 0.47441009 | I15: =I14/I6 -> 0.42486993 | J15: =J14/J6 -> 0.4272677 | ... Y15: =Y14/Y6 -> 0.37226052
B16: 이루다 | N16: =8350+3334 -> 11684 | O16: ='이루다 및 기타'!L6 -> 13129.464 | P16: ='이루다 및 기타'!M6 -> 14494.183 | Q16: ='이루다 및 기타'!N6 -> 17334.635 | R16: ='이루다 및 기타'!O6 -> 19150.079 | S16: ='이루다 및 기타'!P6 -> 20425.775 | T16: ='이루다 및 기타'!Q6 -> 21906.191 | U16: ='이루다 및 기타'!R6 -> 23628.502 | V16: ='이루다 및 기타'!S6 -> 23866.673 | W16: =N16 -> 11684 | X16: =SUM(O16:R16) -> 64108.361 | Y16: =SUM(S16:V16) -> 89827.141
B17: % of sales | N17: =N16/N6 -> 0.15703668 | O17: =O16/O6 -> 0.16292784 | P17: =P16/P6 -> 0.17578071 | Q17: =Q16/Q6 -> 0.18950969 | R17: =R16/R6 -> 0.18969899 | S17: =S16/S6 -> 0.18978528 | T17: =T16/T6 -> 0.18806892 | U17: =U16/U6 -> 0.18916018 | ... Y17: =Y16/Y6 -> 0.18684446
B18: 화장품 및 개인용 미용기기 | C18: =366+212 -> 578 | D18: =818+450-C18 -> 690 | E18: =978+725-C18-D18 -> 435 | F18: =1073+891-SUM(C18:E18) -> 261 | G18: =63+213 -> 276 | H18: =97+420-G18 -> 241 | I18: =375+782-G18-H18 -> 640 | J18: =1358+1073-SUM(G18:I18) -> 1274 | K18: =669+696 -> 1365 | L18: =1295+1616-K18 -> 1546 | M18: =1451+1892-K18-L18 -> 432 | N18: =1680+2828-SUM(K18:M18) -> 1165 | O18: ='이루다 및 기타'!Q16 -> 1127 | P18: ='이루다 및 기타'!R16 -> 1067.5 | Q18: ='이루다 및 기타'!S16 -> 947.875 | R18: ='이루다 및 기타'!T16 -> 1076.8438 | S18: ='이루다 및 기타'!U16 -> 1054.8047 | T18: ='이루다 및 기타'!V16 -> 1036.7559 | U18: ='이루다 및 기타'!W16 -> 1029.0698 | V18: ='이루다 및 기타'!X16 -> 1049.3685 | W18: =SUM(K18:N18) -> 4508 | X18: =SUM(O18:R18) -> 4219.2188 | Y18: =SUM(S18:V18) -> 4169.9989
B19: % of sales | C19: =C18/C6 -> 0.01633599 | D19: =D18/D6 -> 0.021109955 | E19: =E18/E6 -> 0.013075628 | F19: =F18/F6 -> 0.0064496998 | G19: =G18/G6 -> 0.0070816442 | H19: =H18/H6 -> 0.0052508879 | I19: =I18/I6 -> 0.013266173 | J19: =J18/J6 -> 0.02710177 | ... Y19: =Y18/Y6 -> 0.0086737835
B20: 기타 | C20: =511 -> 511 | D20: =1112-C20 -> 601 | E20: =1640-C20-D20 -> 528 | F20: =2152-SUM(C20:E20) -> 512 | G20: =491 -> 491 | H20: =884-G20 -> 393 | I20: =1286-G20-H20 -> 402 | J20: =1575-SUM(G20:I20) -> 289 | K20: =292 -> 292 | L20: =556-K20 -> 264 | M20: =792-K20-L20 -> 236 | N20: =1012-SUM(K20:M20) -> 220 | O20: ='이루다 및 기타'!Q18 -> 253 | P20: ='이루다 및 기타'!R18 -> 243.25 | Q20: ='이루다 및 기타'!S18 -> 238.0625 | R20: ='이루다 및 기타'!T18 -> 238.57812 | S20: ='이루다 및 기타'!U18 -> 243.22266 | T20: ='이루다 및 기타'!V18 -> 240.77832 | U20: ='이루다 및 기타'!W18 -> 240.1604 | V20: ='이루다 및 기타'!X18 -> 240.68488 | W20: =SUM(K20:N20) -> 1012 | X20: =SUM(O20:R20) -> 972.89062 | Y20: =SUM(S20:V20) -> 964.84625
B21: % of sales | C21: =C20/C6 -> 0.014442372 | D21: =D20/D6 -> 0.018387077 | E21: =E20/E6 -> 0.015871107 | F21: =F20/F6 -> 0.012652285 | G21: =G20/G6 -> 0.012598142 | H21: =H20/H6 -> 0.0085626512 | I21: =I20/I6 -> 0.0083328151 | J21: =J20/J6 -> 0.0061478897 | ... Y21: =Y20/Y6 -> 0.0020069232

Sheet 의료기기
A1: 클래시스(214150.KQ)
A2: Assumption Sheet
A3: (units in Millions KRW )
Q4: =O6/N6-1 -> 0.12677568 | R4: =O8/N8-1 -> 0.14466002 | S4: =P8/O8-1 -> 0.11793023 | T4: =Q8/P8-1 -> 0.074277458 | U4: =R8/Q8-1 -> 0.11879344 | V4: =S8/R8-1 -> 0.069844814 | W4: =T8/S8-1 -> 0.078166722 | X4: =U8/T8-1 -> 0.086617113
B5: (단위: 백만 원) | C5: 1Q22 | D5: 2Q22 | E5: 3Q22 | F5: 4Q22 | G5: 1Q23 | H5: 2Q23 | I5: 3Q23 | J5: 4Q23 | K5: 1Q24 | L5: 2Q24 | M5: 3Q24 | N5: 4Q24 | O5: 1Q25E | P5: 2Q25E | Q5: 3Q25E | R5: 4Q25E | S5: 1Q26E | T5: 2Q26E | U5: 3Q26E | V5: 4Q26E | W5: 2024 | X5: 2025E | Y5: 2026E
B6: 클래시스 | C6: =C8+C24 -> 20541 | D6: =D8+D24 -> 17134 | E6: =E8+E24 -> 15520 | F6: =F8+F24 -> 20992 | G6: =G8+G24 -> 18353 | H6: =H8+H24 -> 21957 | I6: =I8+I24 -> 25826 | J6: =J8+J24 -> 23843 | ... V6: =V8+V24 -> 55663.928 | W6: =SUM(W8,W24) -> 110988 | X6: =SUM(X8,X18,X20,X16) -> 144138.02 | Y6: =SUM(Y8,Y18,Y20,Y16) -> 226898.85
B7: YoY% | G7: =G6/C6-1 -> -0.10651867 | H7: =H6/D6-1 -> 0.2814871 | I7: =I6/E6-1 -> 0.66404639 | J7: =J6/F6-1 -> 0.13581364 | K7: =K6/G6-1 -> 0.13322073 | L7: =L6/H6-1 -> 0.36147925 | M7: =M6/I6-1 -> 0.22121118 | N7: =N6/J6-1 -> 0.20609823 | ... V7: =V6/R6-1 -> 0.31110032 | X7: =X6/W6-1 -> 0.29868116 | Y7: =Y6/X6-1 -> 0.57417757
B8: 수출 | C8: 8752 | D8: =18116-C8 -> 9364 | E8: =29609-D8-C8 -> 11493 | F8: =44284-SUM(C8:E8) -> 14675 | G8: =12460 -> 12460 | H8: =28766-G8 -> 16306 | I8: =46547-G8-H8 -> 17781 | J8: =63157-SUM(G8:I8) -> 16610 | K8: 14261 | L8: =37562-K8 -> 23301 | M8: =62935-L8-K8 -> 25373 | N8: =84686-SUM(K8:M8) -> 21751 | O8: =SUM(O10,O12,O14,O16,O18,O20,O22) -> 24897.5 | P8: =SUM(P10,P12,P14,P16,P18,P20,P22) -> 27833.668 | Q8: =SUM(Q10,Q12,Q14,Q16,Q18,Q20,Q22) -> 29901.082 | R8: =SUM(R10,R12,R14,R16,R18,R20,R22) -> 33453.134 | S8: =SUM(S10,S12,S14,S16,S18,S20,S22) -> 35789.662 | T8: =SUM(T10,T12,T14,T16,T18,T20,T22) -> 38587.223 | U8: =SUM(U10,U12,U14,U16,U18,U20,U22) -> 41929.537 | V8: =SUM(V10,V12,V14,V16,V18,V20,V22) -> 44664.421 | W8: =SUM(K8:N8) -> 84686 | X8: =SUM(O8:R8) -> 116085.38 | Y8: =SUM(S8:V8) -> 160970.84
B9: YoY% | G9: =G8/C8-1 -> 0.42367459 | H9: =H8/D8-1 -> 0.74134985 | I9: =I8/E8-1 -> 0.54711564 | J9: =J8/F8-1 -> 0.1318569 | K9: =K8/G8-1 -> 0.14454254 | L9: =L8/H8-1 -> 0.4289832 | M9: =M8/I8-1 -> 0.42697261 | N9: =N8/J8-1 -> 0.30951234 | ... V9: =V8/R8-1 -> 0.33513412 | W9: =W8/W6 -> 0.76301943 | X9: =X8/X6 -> 0.80537655 | Y9: =Y8/Y6 -> 0.70943879
B10: 브라질 | C10: =D29 -> 1951.2059 | D10: =E29 -> 1891.7553 | E10: =F29 -> 4334.8029 | F10: =G29 -> 7807.1331 | G10: =H29 -> 5591.1359 | H10: =I29 -> 7369.2029 | I10: =J29 -> 8161.6163 | J10: =K29 -> 6176.9533 | ... V10: =W29 -> 7266.8986 | W10: =SUM(K10:N10) -> 24335.661 | X10: =SUM(O10:R10) -> 25349.646 | Y10: =SUM(S10:V10) -> 28053.609
B11: % of sales | C11: =C10/C6 -> 0.094990796 | D11: =D10/D6 -> 0.11040944 | E11: =E10/E6 -> 0.27930431 | F11: =F10/F6 -> 0.37190992 | G11: =G10/G6 -> 0.30464425 | H11: =H10/H6 -> 0.33561975 | I11: =I10/I6 -> 0.31602325 | J11: =J10/J6 -> 0.25906779 | ... Y11: =Y10/Y6 -> 0.12363927
B12: 태국 | C12: =D34 -> 780.23817 | D12: =E34 -> 1126.6227 | E12: =F34 -> 1977.4494 | F12: =G34 -> 845.13544 | G12: =H34 -> 1562.9588 | H12: =I34 -> 3043.3784 | I12: =J34 -> 1705.71 | J12: =K34 -> 1178.7979 | ... V12: =W34 -> 3768.8525 | W12: =SUM(K12:N12) -> 11242.389 | X12: =SUM(O12:R12) -> 12063.75 | Y12: =SUM(S12:V12) -> 14254.048
B13: % of sales | C13: =C12/C6 -> 0.03798443 | D13: =D12/D6 -> 0.06575363 | E13: =E12/E6 -> 0.12741298 | F13: =F12/F6 -> 0.040259882 | G13: =G12/G6 -> 0.085160944 | H13: =H12/H6 -> 0.13860629 | I13: =I12/I6 -> 0.066046233 | J13: =J12/J6 -> 0.04944 | ... Y13: =Y12/Y6 -> 0.062821158
B14: 일본 | C14: =D39 -> 2468.9227 | D14: =E39 -> 2443.5705 | E14: =F39 -> 2507.6452 | F14: =G39 -> 2281.3472 | G14: =H39 -> 2568.3709 | H14: =I39 -> 2161.6156 | I14: =J39 -> 2315.9367 | J14: =K39 -> 2245.4536 | ... V14: =W39 -> 2277.52 | W14: =SUM(K14:N14) -> 6692.3571 | X14: =SUM(O14:R14) -> 7210.4406 | Y14: =SUM(S14:V14) -> 8591.9967
B15: % of sales | C15: =C14/C6 -> 0.12019486 | D15: =D14/D6 -> 0.1426153 | E15: =E14/E6 -> 0.16157508 | F15: =F14/F6 -> 0.10867698 | G15: =G14/G6 -> 0.13994284 | H15: =H14/H6 -> 0.098447674 | I15: =I14/I6 -> 0.08967462 | J15: =J14/J6 -> 0.094176637 | ... Y15: =Y14/Y6 -> 0.03786708
B16: 미국 | C16: - | D16: - | E16: - | F16: - | G16: - | H16: - | I16: - | J16: - | N16: =E44 -> 3312 | O16: =F44 -> 4554 | P16: =G44 -> 5796 | Q16: =H44 -> 7038 | R16: =I44 -> 8280 | S16: =J44 -> 9522 | T16: =K44 -> 10764 | U16: =L44 -> 12006 | V16: =M44 -> 13248 | W16: =N16 -> 3312 | X16: =SUM(O16:R16) -> 25668 | Y16: =SUM(S16:V16) -> 45540
B17: % of sales | K17: =K16/K6 -> 0 | L17: =L16/L6 -> 0 | M17: =M16/M6 -> 0 | N17: =N16/N6 -> 0.11517196 | O17: =O16/O6 -> 0.14054389 | P17: =P16/P6 -> 0.16172757 | Q17: =Q16/Q6 -> 0.18325907 | R17: =R16/R6 -> 0.19502595 | ... Y17: =Y16/Y6 -> 0.20070618
B18: 유럽 | C18: - | D18: - | E18: - | F18: - | G18: - | H18: - | I18: - | J18: - | R18: =E51 -> 2384.64 | S18: =F51 -> 3278.88 | T18: =G51 -> 4173.12 | U18: =H51 -> 5067.36 | V18: =I51 -> 5961.6 | X18: =R18 -> 2384.64 | Y18: =SUM(S18:V18) -> 18480.96
B19: % of sales | K19: =K18/K6 -> 0 | L19: =L18/L6 -> 0 | M19: =M18/M6 -> 0 | N19: =N18/N6 -> 0 | O19: =O18/O6 -> 0 | P19: =P18/P6 -> 0 | Q19: =Q18/Q6 -> 0 | R19: =R18/R6 -> 0.056167475 | ... Y19: =Y18/Y6 -> 0.081450216
B20: 중국 | C20: - | D20: - | E20: - | F20: - | G20: - | H20: - | I20: - | J20: - | U20: =G56 -> 802.96509 | V20: =H56 -> 1104.077 | Y20: =SUM(U20:V20) -> 1907.0421
B21: % of sales | K21: =K20/K6 -> 0 | L21: =L20/L6 -> 0 | M21: =M20/M6 -> 0 | N21: =N20/N6 -> 0 | O21: =O20/O6 -> 0 | P21: =P20/P6 -> 0 | Q21: =Q20/Q6 -> 0 | R21: =R20/R6 -> 0 | ... Y21: =Y20/Y6 -> 0.0084048118
B22: 기타 | C22: =C8-SUM(C10,C12,C14) -> 3551.6332 | D22: =D8-SUM(D10,D12,D14) -> 3902.0514 | E22: =E8-SUM(E10,E12,E14) -> 2673.1026 | F22: =F8-SUM(F10,F12,F14) -> 3741.3843 | G22: =G8-SUM(G10,G12,G14) -> 2737.5344 | H22: =H8-SUM(H10,H12,H14) -> 3731.8031 | I22: =I8-SUM(I10,I12,I14) -> 5597.7369 | J22: =J8-SUM(J10,J12,J14) -> 7008.7953 | ... M22: =M8-SUM(M10,M12,M14) -> 13378.307 | N22: =N8-SUM(N10,N12,N14,N16) -> 11811.98 | O22: =AVERAGE(K22:N22) -> 9775.8984 | P22: =AVERAGE(L22:O22) -> 11077.828 | Q22: =AVERAGE(M22:P22) -> 11511.003 | R22: =AVERAGE(N22:Q22) -> 11044.177 | S22: =AVERAGE(O22:R22) -> 10852.227 | T22: =AVERAGE(P22:S22) -> 11121.309 | U22: =AVERAGE(Q22:T22) -> 11132.179 | V22: =AVERAGE(R22:U22) -> 11037.473 | W22: =SUM(K22:N22) -> 39103.594 | X22: =SUM(O22:R22) -> 43408.907 | Y22: =SUM(S22:V22) -> 44143.187
B23: % of sales | C23: =C22/C8 -> 0.40580818 | D23: =D22/D8 -> 0.41670775 | E23: =E22/E8 -> 0.23258528 | F23: =F22/F8 -> 0.25494953 | G23: =G22/G8 -> 0.21970581 | H23: =H22/H8 -> 0.22886073 | I23: =I22/I8 -> 0.31481564 | J23: =J22/J8 -> 0.42196239 | ... Y23: =Y22/Y8 -> 0.27423095
B24: 내수 | C24: 11789 | D24: =19559-C24 -> 7770 | E24: =23586-C24-D24 -> 4027 | F24: =29903-SUM(C24:E24) -> 6317 | G24: =5893 -> 5893 | H24: =11544-G24 -> 5651 | I24: =19589-G24-H24 -> 8045 | J24: =26822-SUM(G24:I24) -> 7233 | K24: =6537 -> 6537 | L24: =13130-K24 -> 6593 | M24: =19296-L24-K24 -> 6166 | N24: =26302-K24-L24-M24 -> 7006 | O24: 7505.1884 | P24: 8004.3767 | Q24: 8503.5651 | R24: 9002.7534 | S24: 9501.9418 | T24: 10001.13 | U24: 10500.318 | V24: 10999.507 | W24: =SUM(K24:N24) -> 26302 | X24: =SUM(O24:R24) -> 33015.884 | Y24: =SUM(S24:V24) -> 41002.897
B25: YoY% | G25: =G24/C24-1 -> -0.50012724 | H25: =H24/D24-1 -> -0.27271557 | I25: =I24/E24-1 -> 0.99776509 | J25: =J24/F24-1 -> 0.14500554 | K25: =K24/G24-1 -> 0.1092822 | L25: =L24/H24-1 -> 0.16669616 | M25: =M24/I24-1 -> -0.23356122 | N25: =N24/J24-1 -> -0.031383935 | ... V25: =V24/R24-1 -> 0.22179364 | W25: =W24/W6 -> 0.23698057 | X25: =X24/X6 -> 0.22905742 | Y25: =Y24/Y6 -> 0.18071003
Q26: =O24/N24-1 -> 0.071251549 | R26: =P24/O24-1 -> 0.066512435 | S26: =Q24/P24-1 -> 0.062364425 | T26: =R24/Q24-1 -> 0.05870342 | U26: =S24/R24-1 -> 0.055448409 | V26: =T24/S24-1 -> 0.052535404 | W26: =U24/T24-1 -> 0.049913194 | X26: =V24/U24-1 -> 0.047540306
B28: (단위: 백만 원) | D28: 1Q22 | E28: 2Q22 | F28: 3Q22 | G28: 4Q22 | H28: 1Q23 | I28: 2Q23 | J28: 3Q23 | K28: 4Q23 | L28: 1Q24 | M28: 2Q24 | N28: 3Q24 | O28: 4Q24 | P28: 1Q25E | Q28: 2Q25E | R28: 3Q25E | S28: 4Q25E | T28: 1Q26E | U28: 2Q26E | V28: 3Q26E | W28: 4Q26E | X28: 2024 | Y28: 2025E | Z28: 2026E | AB28: EBD 침투율 | AC28: (단위:%) | AD28: 24E | AE28: 25E | AF28: 26E | AG28: 27E | AH28: 28E | AI28: 29E | AJ28: 30E | AM28: 2022 | AN28: 2023 | AO28: 2024
B29: 브라질 | D29: 1951.2059 | E29: 1891.7553 | F29: 4334.8029 | G29: 7807.1331 | H29: 5591.1359 | I29: 7369.2029 | J29: 8161.6163 | K29: 6176.9533 | L29: 4355.3811 | M29: 7579.674 | N29: 9015.3743 | O29: 3385.2312 | P29: 6083.9151 | Q29: 6252.9128 | R29: 6421.9104 | S29: 6590.9081 | T29: 6759.9057 | U29: 6928.9033 | V29: 7097.901 | W29: =AVERAGE(L29:O29)*AF38/AD38 -> 7266.8986 | X29: =SUM(L29:O29) -> 24335.661 | Y29: =SUM(P29:S29) -> 25349.646 | Z29: =SUM(T29:W29) -> 28053.609 | AB29: HIFU | AC29: BR | AD29: 12.8 | AE29: 13.266667 | AF29: 13.733333 | AG29: 14.2 | AH29: 14.666667 | AI29: 15.133333 | AJ29: 15.6 | AL29: 원/달러 | AM29: 1205.5 | AN29: 1231.9 | AO29: 1334.6
C30: YoY% | H30: =H29/D29-1 -> 1.8654771 | I30: =I29/E29-1 -> 2.8954313 | J30: =J29/F29-1 -> 0.88281142 | K30: =K29/G29-1 -> -0.20880646 | L30: =L29/H29-1 -> -0.22102034 | M30: =M29/I29-1 -> 0.028560895 | N30: =N29/J29-1 -> 0.10460648 | O30: =O29/K29-1 -> -0.45195778 | ... W30: =W29/S29-1 -> 0.1025641 | AC30: TH | AD30: 38.7 | AE30: 43.066667 | AF30: 47.433333 | AG30: 51.8 | AH30: 56.166667 | AI30: 60.533333 | AJ30: 64.9
F31: =G29/F29-1 -> 0.80103533 | M31: =M29/L29-1 -> 0.74030097 | N31: =N29/M29-1 -> 0.18941452 | AC31: JP | AD31: 11.9 | AE31: 12.3 | AF31: 12.7 | AG31: 13.1 | AH31: 13.5 | AI31: 13.9 | AJ31: 14.3
AB32: MRF | AC32: BR | AD32: 1 | AE32: 1.5 | AF32: 2 | AG32: 2.5 | AH32: 3 | AI32: 3.5 | AJ32: 4
B33: (단위: 백만 원) | D33: 1Q22 | E33: 2Q22 | F33: 3Q22 | G33: 4Q22 | H33: 1Q23 | I33: 2Q23 | J33: 3Q23 | K33: 4Q23 | L33: 1Q24 | M33: 2Q24 | N33: 3Q24 | O33: 4Q24 | P33: 1Q25E | Q33: 2Q25E | R33: 3Q25E | S33: 4Q25E | T33: 1Q26E | U33: 2Q26E | V33: 3Q26E | W33: 4Q26E | X33: 2024 | Y33: 2025E | Z33: 2026E | AC33: TH | AD33: 23 | AE33: 29.166667 | AF33: 35.333333 | AG33: 41.5 | AH33: 47.666667 | AI33: 53.833333 | AJ33: 60
B34: 태국 | D34: 780.23817 | E34: 1126.6227 | F34: 1977.4494 | G34: 845.13544 | H34: 1562.9588 | I34: 3043.3784 | J34: 1705.71 | K34: 1178.7979 | L34: 3080.5705 | M34: 4877.3794 | N34: 1639.159 | O34: 1645.2797 | P34: 2810.5972 | Q34: 2947.4908 | R34: 3084.3844 | S34: 3221.278 | T34: 3358.1716 | U34: 3495.0653 | V34: 3631.9589 | W34: =AVERAGE(L34:O34)*AF39/AD39 -> 3768.8525 | X34: =SUM(L34:O34) -> 11242.389 | Y34: =SUM(P34:S34) -> 12063.75 | Z34: =SUM(T34:W34) -> 14254.048 | AC34: JP | AD34: 3 | AE34: 4.8333333 | AF34: 6.6666667 | AG34: 8.5 | AH34: 10.333333 | AI34: 12.166667 | AJ34: 14
C35: YoY% | H35: =H34/D34-1 -> 1.0031817 | I35: =I34/E34-1 -> 1.7013288 | J35: =J34/F34-1 -> -0.13741913 | K35: =K34/G34-1 -> 0.39480356 | L35: =L34/H34-1 -> 0.97098636 | M35: =M34/I34-1 -> 0.60262012 | N35: =N34/J34-1 -> -0.039016626 | O35: =O34/K34-1 -> 0.39572671 | ... W35: =W34/S34-1 -> 0.16998672 | AB35: MNRF | AC35: BR | AD35: 3 | AE35: 3.6666667 | AF35: 4.3333333 | AG35: 5 | AH35: 5.6666667 | AI35: 6.3333333 | AJ35: 7
M36: =M34/L34-1 -> 0.58327148 | AC36: TH | AD36: 4 | AE36: 4.6666667 | AF36: 5.3333333 | AG36: 6 | AH36: 6.6666667 | AI36: 7.3333333 | AJ36: 8
AC37: JP | AD37: 3 | AE37: 4 | AF37: 5 | AG37: 6 | AH37: 7 | AI37: 8 | AJ37: 9
B38: (단위: 백만 원) | D38: 1Q22 | E38: 2Q22 | F38: 3Q22 | G38: 4Q22 | H38: 1Q23 | I38: 2Q23 | J38: 3Q23 | K38: 4Q23 | L38: 1Q24 | M38: 2Q24 | N38: 3Q24 | O38: 4Q24 | P38: 1Q25E | Q38: 2Q25E | R38: 3Q25E | S38: 4Q25E | T38: 1Q26E | U38: 2Q26E | V38: 3Q26E | W38: 4Q26E | X38: 2024 | Y38: 2025E | Z38: 2026E | AB38: EBD(Average) | AC38: BR | AD38: =AVERAGE(AD29,AD32,AD35) -> 5.6 | AE38: =AVERAGE(AE29,AE32,AE35) -> 6.1444444 | AF38: =AVERAGE(AF29,AF32,AF35) -> 6.6888889 | AG38: =AVERAGE(AG29,AG32,AG35) -> 7.2333333 | AH38: =AVERAGE(AH29,AH32,AH35) -> 7.7777778 | AI38: =AVERAGE(AI29,AI32,AI35) -> 8.3222222 | AJ38: =AVERAGE(AJ29,AJ32,AJ35) -> 8.8666667
B39: 일본 | D39: 2468.9227 | E39: 2443.5705 | F39: 2507.6452 | G39: 2281.3472 | H39: 2568.3709 | I39: 2161.6156 | J39: 2315.9367 | K39: 2245.4536 | L39: 2256.8672 | M39: 1498.8212 | N39: 1340.1593 | O39: 1596.5095 | P39: 1673.0893 | Q39: 1759.4365 | R39: 1845.7838 | S39: 1932.131 | T39: 2018.4783 | U39: 2104.8255 | V39: 2191.1728 | W39: =AVERAGE(L39:O39)*AF40/AD40 -> 2277.52 | X39: =SUM(L39:O39) -> 6692.3571 | Y39: =SUM(P39:S39) -> 7210.4406 | Z39: =SUM(T39:W39) -> 8591.9967 | AC39: TH | AD39: =AVERAGE(AD30,AD33,AD36) -> 21.9 | AE39: =AVERAGE(AE30,AE33,AE36) -> 25.633333 | AF39: =AVERAGE(AF30,AF33,AF36) -> 29.366667 | AG39: =AVERAGE(AG30,AG33,AG36) -> 33.1 | AH39: =AVERAGE(AH30,AH33,AH36) -> 36.833333 | AI39: =AVERAGE(AI30,AI33,AI36) -> 40.566667 | AJ39: =AVERAGE(AJ30,AJ33,AJ36) -> 44.3
C40: YoY% | H40: =H39/D39-1 -> 0.040280018 | I40: =I39/E39-1 -> -0.11538647 | J40: =J39/F39-1 -> -0.076449588 | K40: =K39/G39-1 -> -0.015733528 | L40: =L39/H39-1 -> -0.12128455 | M40: =M39/I39-1 -> -0.30661992 | N40: =N39/J39-1 -> -0.42133166 | O40: =O39/K39-1 -> -0.28900357 | ... W40: =W39/S39-1 -> 0.17876065 | AC40: JP | AD40: =AVERAGE(AD31,AD34,AD37) -> 5.9666667 | AE40: =AVERAGE(AE31,AE34,AE37) -> 7.0444444 | AF40: =AVERAGE(AF31,AF34,AF37) -> 8.1222222 | AG40: =AVERAGE(AG31,AG34,AG37) -> 9.2 | AH40: =AVERAGE(AH31,AH34,AH37) -> 10.277778 | AI40: =AVERAGE(AI31,AI34,AI37) -> 11.355556 | AJ40: =AVERAGE(AJ31,AJ34,AJ37) -> 12.433333
B43: (단위: 백만 원) | E43: 4Q24 | F43: 1Q25E | G43: 2Q25E | H43: 3Q25E | I43: 4Q25E | J43: 1Q26E | K43: 2Q26E | L43: 3Q26E | M43: 4Q26E | N43: 2024 | O43: 2025E | P43: 2026E
B44: 미국 | E44: =E46*E47 -> 3312 | F44: =F46*F47 -> 4554 | G44: =G46*G47 -> 5796 | H44: =H46*H47 -> 7038 | I44: =I46*I47 -> 8280 | J44: =J46*J47 -> 9522 | K44: =K46*K47 -> 10764 | L44: =L46*L47 -> 12006 | M44: =M46*M47 -> 13248 | N44: =E44 -> 3312 | O44: =SUM(F44:I44) -> 25668 | P44: =SUM(J44:M44) -> 45540
C45: YoY% | I45: =I44/E44-1 -> 1.5 | J45: =J44/F44-1 -> 1.0909091 | K45: =K44/G44-1 -> 0.85714286 | L45: =L44/H44-1 -> 0.70588235 | M45: =M44/I44-1 -> 0.6 | O45: =O44/N44-1 -> 6.75 | P45: =P44/O44-1 -> 0.77419355
C46: 판매대수(볼뉴머) | E46: 25 | F46: 34.375 | G46: 43.75 | H46: 53.125 | I46: 62.5 | J46: 71.875 | K46: 81.25 | L46: 90.625 | M46: 100 | O46: =SUM(F46:I46) -> 193.75 | P46: =SUM(J46:M46) -> 343.75
C47: ASP(볼뉴머) | E47: =90000*1472/1000000 -> 132.48 | F47: =90000*1472/1000000 -> 132.48 | G47: =90000*1472/1000000 -> 132.48 | H47: =90000*1472/1000000 -> 132.48 | I47: =90000*1472/1000000 -> 132.48 | J47: =90000*1472/1000000 -> 132.48 | K47: =90000*1472/1000000 -> 132.48 | L47: =90000*1472/1000000 -> 132.48 | M47: =90000*1472/1000000 -> 132.48
B50: (단위: 백만 원) | E50: 4Q25E | F50: 1Q26E | G50: 2Q26E | H50: 3Q26E | I50: 4Q26E | J50: 2025E | K50: 2026E | O50: 24년 글로벌 미용의료기기 시장 | Q50: (단위: mn$)
B51: 유럽 | E51: =E44*0.4*1.8 -> 2384.64 | F51: =F44*0.4*1.8 -> 3278.88 | G51: =G44*0.4*1.8 -> 4173.12 | H51: =H44*0.4*1.8 -> 5067.36 | I51: =I44*0.4*1.8 -> 5961.6 | J51: =E51 -> 2384.64 | K51: =SUM(F51:I51) -> 18480.96 | O51: 전체 | Q51: 2709000
C52: YoY% | I52: =I51/E51-1 -> 1.5 | K52: =K51/J51-1 -> 6.75 | O52: 미국 | Q52: 1147000
O53: 유럽 | Q53: 460000 | R53: =Q53/Q51 -> 0.16980436 | S53: =Q53/Q52 -> 0.40104621
O54: 중국 | Q54: 176000 | R54: =Q54/Q51 -> 0.064968623 | S54: =Q54/Q52 -> 0.15344377
B55: (단위: 백만 원) | E55: 1Q26E | F55: 2Q26E | G55: 3Q26E | H55: 4Q26E | I55: 2026E
B56: 중국 | G56: =E44*S54*1.58 -> 802.96509 | H56: =F44*S54*1.58 -> 1104.077 | I56: =G56+H56 -> 1907.0421
C57: YoY%
AD59: *중국인 입국자 수 추이
B60: (단위: 백만 원) | E60: 1Q22 | F60: 2Q22 | G60: 3Q22 | H60: 4Q22 | I60: 1Q23 | J60: 2Q23 | K60: 3Q23 | L60: 4Q23 | M60: 1Q24 | N60: 2Q24 | O60: 3Q24 | P60: 4Q24 | Q60: 1Q25E | R60: 2Q25E | S60: 3Q25E | T60: 4Q25E | U60: 1Q26E | V60: 2Q26E | W60: 3Q26E | X60: 4Q26E | Y60: 2024 | Z60: 2025E | AA60: 2026E | AC60: 연도 | AD60: 관광객 수 (단위: 만 명)
B61: 내수 | E61: 11789 | F61: =19559-E61 -> 7770 | G61: =23586-E61-F61 -> 4027 | H61: =29903-SUM(E61:G61) -> 6317 | I61: =5893 -> 5893 | J61: =11544-I61 -> 5651 | K61: =19589-I61-J61 -> 8045 | L61: =26822-SUM(I61:K61) -> 7233 | M61: =6537 -> 6537 | N61: =13130-M61 -> 6593 | O61: =19296-N61-M61 -> 6166 | P61: 7006 | Q61: 7505.1884 | R61: 8004.3767 | S61: 8503.5651 | T61: 9002.7534 | U61: 9501.9418 | V61: 10001.13 | W61: 10500.318 | X61: 10999.507 | Y61: =SUM(M61:P61) -> 26302 | Z61: =SUM(Q61:T61) -> 33015.884 | AA61: =SUM(U61:X61) -> 41002.897 | AC61: 2015 | AD61: 598
C62: YoY% | I62: =I61/E61-1 -> -0.50012724 | J62: =J61/F61-1 -> -0.27271557 | K62: =K61/G61-1 -> 0.99776509 | L62: =L61/H61-1 -> 0.14500554 | M62: =M61/I61-1 -> 0.1092822 | N62: =N61/J61-1 -> 0.16669616 | O62: =O61/K61-1 -> -0.23356122 | P62: =P61/L61-1 -> -0.031383935 | ... X62: =X61/T61-1 -> 0.22179364 | Z62: =Z61/Y61-1 -> 0.25526133 | AA62: =AA61/Z61-1 -> 0.24191428 | AC62: 2016 | AD62: 807
AC63: 2017 | AD63: 417
AC64: 2018 | AD64: 478
AC65: 2019 | AD65: 602
AC66: 2020 | AD66: 69
AC67: 2021 | AD67: 17
AC68: 2022 | AD68: 23
AC69: 2023 | AD69: 204
AC70: 2024 | AD70: 460 | AE70: =AD70/AD62 -> 0.57001239
B74: (단위: 백만 원) | E74: 1Q22 | F74: 2Q22 | G74: 3Q22 | H74: 4Q22 | I74: 1Q23 | J74: 2Q23 | K74: 3Q23 | L74: 4Q23 | M74: 1Q24 | N74: 2Q24 | O74: 3Q24 | P74: 4Q24 | Q74: 1Q25E | R74: 2Q25E | S74: 3Q25E | T74: 4Q25E | U74: 1Q26E | V74: 2Q26E | W74: 3Q26E | X74: 4Q26E | Y74: 2024 | Z74: 2025E | AA74: 2026E
B75: 클루덤 | E75: =1864+130 -> 1994 | F75: =3991+308-E75 -> 2305 | G75: =5376+446-E75-F75 -> 1523 | H75: =7397+519-SUM(E75:G75) -> 2094 | I75: =1042+126 -> 1168 | J75: =2449+251-I75 -> 1532 | K75: =3266+316-I75-J75 -> 882 | L75: =4770+325-SUM(I75:K75) -> 1513 | M75: =1332+66 -> 1398 | N75: =2277+125-M75 -> 1004 | O75: =3395+203-N75-M75 -> 1196 | P75: =4524+363-SUM(M75:O75) -> 1289 | Q75: =AVERAGE(M75:P75) -> 1221.75 | R75: =AVERAGE(N75:Q75) -> 1177.6875 | S75: =AVERAGE(O75:R75) -> 1221.1094 | T75: =AVERAGE(P75:S75) -> 1227.3867 | U75: =AVERAGE(Q75:T75) -> 1211.9834 | V75: =AVERAGE(R75:U75) -> 1209.5417 | W75: =AVERAGE(S75:V75) -> 1217.5053 | X75: =AVERAGE(T75:W75) -> 1216.6043 | Y75: =SUM(M75:P75) -> 4887 | Z75: =SUM(Q75:T75) -> 4847.9336 | AA75: =SUM(U75:X75) -> 4855.6348
C76: YoY% | I76: =I75/E75-1 -> -0.41424273 | J76: =J75/F75-1 -> -0.33535792 | K76: =K75/G75-1 -> -0.42087984 | L76: =L75/H75-1 -> -0.27745941 | M76: =M75/I75-1 -> 0.19691781 | N76: =N75/J75-1 -> -0.34464752 | O76: =O75/K75-1 -> 0.35600907 | P76: =P75/L75-1 -> -0.14805023 | ... X76: =X75/T75-1 -> -0.0087848636

Sheet 소모품
A1: 클래시스(214150.KQ)
A2: Assumption Sheet
A3: (units in Millions KRW )
B5: (단위: 백만 원) | D5: 1Q22 | E5: 2Q22 | F5: 3Q22 | G5: 4Q22 | H5: 1Q23 | I5: 2Q23 | J5: 3Q23 | K5: 4Q23 | L5: 1Q24 | M5: 2Q24 | N5: 3Q24 | O5: 4Q24 | P5: 1Q25E | Q5: 2Q25E | R5: 3Q25E | S5: 4Q25E | T5: 1Q26E | U5: 2Q26E | V5: 3Q26E | W5: 4Q26E | X5: 2024 | Y5: 2025E | Z5: 2026E
B6: 소모품 | D6: 11758 | E6: 11956 | F6: 15252 | G6: 16618 | H6: 18686 | I6: 26556 | J6: 15715 | K6: 20086 | L6: 26496 | M6: 26065 | N6: 26011 | O6: 31288 | P6: =의료기기!M6*1.01194946+534.756199 -> 32450.63 | Q6: =의료기기!N6*1.01194946+534.756199 -> 29635.387 | R6: =의료기기!O6*1.01194946+534.756199 -> 33324.639 | S6: =의료기기!P6*1.01194946+534.756199 -> 36801.046 | T6: =의료기기!Q6*1.01194946+534.756199 -> 39398.318 | U6: =의료기기!R6*1.01194946+534.756199 -> 43497.969 | V6: =의료기기!S6*1.01194946+534.756199 -> 46367.57 | W6: =의료기기!T6*1.01194946+534.756199 -> 49703.714 | X6: =SUM(L6:O6) -> 109860 | Y6: =SUM(P6:S6) -> 132211.7 | Z6: =SUM(T6:W6) -> 178967.57
C7: YoY% | H7: =H6/D6-1 -> 0.58921585 | I7: =I6/E6-1 -> 1.2211442 | J7: =J6/F6-1 -> 0.030356675 | K7: =K6/G6-1 -> 0.20868937 | L7: =L6/H6-1 -> 0.41795997 | M7: =M6/I6-1 -> -0.01848923 | N7: =N6/J6-1 -> 0.65517022 | O7: =O6/K6-1 -> 0.55770188 | ... W7: =W6/S6-1 -> 0.35060601 | Y7: =Y6/X6-1 -> 0.20345624 | Z7: =Z6/Y6-1 -> 0.35364395
D9: 계수 | E9: 표준 오차 | F9: t 통계량 | G9: P-값 | H9: 하위 95% | I9: 상위 95% | J9: 하위 95.0% | K9: 상위 95.0%
C10: Y 절편 | D10: 534.7562 | E10: 6488.9559 | F10: 0.082410207 | G10: 0.93634515 | H10: -14428.803 | I10: 15498.315 | J10: -14428.803 | K10: 15498.315
C11: X 1 | D11: 1.0119495 | E11: 0.29670873 | F11: 3.4105821 | G11: 0.009215214 | H11: 0.32773791 | I11: 1.696161 | J11: 0.32773791 | K11: 1.696161

Sheet 이루다 및 기타
A1: 클래시스(214150.KQ)
A2: Assumption Sheet
A3: (units in Millions KRW )
B5: (단위: 백만 원) | D5: 1Q23 | E5: 2Q23 | F5: 3Q23 | G5: 4Q23 | H5: 1Q24 | I5: 2Q24 | J5: 3Q24 | K5: 4Q24 | L5: 1Q25E | M5: 2Q25E | N5: 3Q25E | O5: 4Q25E | P5: 1Q26E | Q5: 2Q26E | R5: 3Q26E | S5: 4Q26E | T5: 2024 | U5: 2025E | V5: 2026E
B6: 이루다 | D6: 11161 | E6: 14372 | F6: 13971 | G6: 16702 | H6: 14088 | I6: 12241 | K6: =SUM(K8,K10) -> 11684 | L6: =L8+L10 -> 13129.464 | M6: =SUM(M8,M10) -> 14494.183 | N6: =SUM(N8,N10) -> 17334.635 | O6: =SUM(O8,O10) -> 19150.079 | P6: =SUM(P8,P10) -> 20425.775 | Q6: =SUM(Q8,Q10) -> 21906.191 | R6: =SUM(R8,R10) -> 23628.502 | S6: =SUM(S8,S10) -> 23866.673 | T6: =SUM(T8,X18,X20,X16) -> 28797.053 | U6: =U8+U10 -> 64108.361 | V6: =V8+V10 -> 89827.141
C7: YoY% | H7: 0.26225249 | I7: -0.14827442 | J7: =J6/F6-1 -> -1 | L7: =L6/H6-1 -> -0.068039197 | M7: =M6/I6-1 -> 0.18406855 | N7: =N6/J6-1 -> #DIV/0! | O7: =O6/K6-1 -> 0.63900029 | P7: =P6/L6-1 -> 0.55572046 | Q7: =Q6/M6-1 -> 0.51137811 | R7: =R6/N6-1 -> 0.36308044 | S7: =S6/O6-1 -> 0.24629628 | U7: =U6/T6-1 -> 1.2262125 | V7: =V6/U6-1 -> 0.40117668
C8: 수출 | D8: 8316 | E8: 10718 | F8: 10597 | G8: 13168 | H8: 10352 | I8: 8805 | K8: 8350 | L8: =K8*(의료기기!R4+1) -> 9557.9111 | M8: =L8*(의료기기!S4+1) -> 10685.078 | N8: =M8*(G12+1) -> 13277.447 | O8: =N8*(의료기기!U4+1) -> 14854.72 | P8: =O8*(의료기기!V4+1) -> 15892.246 | Q8: =P8*(의료기기!W4+1) -> 17134.49 | R8: =Q8*(의료기기!X4+1) -> 18618.63 | S8: =R8*(의료기기!Y4+1) -> 18618.63 | T8: =SUM(H8:K8) -> 27507 | U8: =SUM(L8:O8) -> 48375.156 | V8: =SUM(P8:S8) -> 70263.997
C9: % of sales | D9: 0.74509453 | E9: 0.74575564 | F9: 0.75849975 | G9: 0.78840857 | H9: 0.73480977 | I9: 0.71930398 | J9: =J8/J6 -> #DIV/0! | K9: =K8/K6 -> 0.71465252 | L9: =L8/L6 -> 0.72797422 | M9: =M8/M6 -> 0.73719765 | N9: =N8/N6 -> 0.76594903 | O9: =O8/O6 -> 0.7757002 | P9: =P8/P6 -> 0.77804858 | Q9: =Q8/Q6 -> 0.7821757 | ... V9: =V8/V6 -> 0.78221344
C10: 내수 | D10: 2845 | E10: 3654 | F10: 3374 | G10: 3534 | H10: 3736 | I10: 3436 | K10: 3334 | L10: =K10*(의료기기!Q26+1) -> 3571.5527 | M10: =L10*(의료기기!R26+1) -> 3809.1053 | N10: =M10*G25 -> 4057.1882 | O10: ='이루다 및 기타'!N10*(의료기기!T26+1) -> 4295.359 | P10: ='이루다 및 기타'!O10*(의료기기!U26+1) -> 4533.5298 | Q10: ='이루다 및 기타'!P10*(의료기기!V26+1) -> 4771.7006 | R10: ='이루다 및 기타'!Q10*(의료기기!W26+1) -> 5009.8715 | S10: ='이루다 및 기타'!R10*(의료기기!X26+1) -> 5248.0423 | T10: =SUM(H10:K10) -> 10506 | U10: =SUM(L10:O10) -> 15733.205 | V10: =SUM(P10:S10) -> 19563.144
C11: % of sales | D11: 0.25490547 | E11: 0.25424436 | F11: 0.24150025 | G11: 0.21159143 | H11: 0.26519023 | I11: 0.28069602 | J11: =J10/J6 -> #DIV/0! | K11: =K10/K6 -> 0.28534748 | L11: =L10/L6 -> 0.27202578 | M11: =M10/M6 -> 0.26280235 | N11: =N10/N6 -> 0.23405097 | O11: =O10/O6 -> 0.2242998 | P11: =P10/P6 -> 0.22195142 | Q11: =Q10/Q6 -> 0.2178243 | ... V11: =V10/V6 -> 0.21778656
G12: =G8/F8-1 -> 0.24261583
B15: (단위: 백만 원) | E15: 1Q22 | F15: 2Q22 | G15: 3Q22 | H15: 4Q22 | I15: 1Q23 | J15: 2Q23 | K15: 3Q23 | L15: 4Q23 | M15: 1Q24 | N15: 2Q24 | O15: 3Q24 | P15: 4Q24 | Q15: 1Q25E | R15: 2Q25E | S15: 3Q25E | T15: 4Q25E | U15: 1Q26E | V15: 2Q26E | W15: 3Q26E | X15: 4Q26E | Y15: 2024 | Z15: 2025E | AA15: 2026E
B16: 화장품 및 개인용 의료기기 | E16: =366+212 -> 578 | F16: =818+450-E16 -> 690 | G16: =978+725-E16-F16 -> 435 | H16: =1073+891-SUM(E16:G16) -> 261 | I16: =63+213 -> 276 | J16: =97+420-I16 -> 241 | K16: =375+782-I16-J16 -> 640 | L16: =1358+1073-SUM(I16:K16) -> 1274 | M16: =669+696 -> 1365 | N16: =1295+1616-M16 -> 1546 | O16: =1451+1892-M16-N16 -> 432 | P16: =1680+2828-SUM(M16:O16) -> 1165 | Q16: =AVERAGE(M16:P16) -> 1127 | R16: =AVERAGE(N16:Q16) -> 1067.5 | S16: =AVERAGE(O16:R16) -> 947.875 | T16: =AVERAGE(P16:S16) -> 1076.8438 | U16: =AVERAGE(Q16:T16) -> 1054.8047 | V16: =AVERAGE(R16:U16) -> 1036.7559 | W16: =AVERAGE(S16:V16) -> 1029.0698 | X16: =AVERAGE(T16:W16) -> 1049.3685 | Y16: =SUM(M16:P16) -> 4508 | Z16: =SUM(Q16:T16) -> 4219.2188 | AA16: =SUM(U16:X16) -> 4169.9989
C17: YoY% | I17: =I16/E16-1 -> -0.52249135 | J17: =J16/F16-1 -> -0.65072464 | K17: =K16/G16-1 -> 0.47126437 | L17: =L16/H16-1 -> 3.8812261 | M17: =M16/I16-1 -> 3.9456522 | N17: =N16/J16-1 -> 5.4149378 | O17: =O16/K16-1 -> -0.325 | P17: =P16/L16-1 -> -0.0855573 | ... X17: =X16/T16-1 -> -0.025514583 | Z17: =Z16/Y16-1 -> -0.064059727 | AA17: =AA16/Z16-1 -> -0.011665631
B18: 기타 | E18: =511 -> 511 | F18: =1112-E18 -> 601 | G18: =1640-E18-F18 -> 528 | H18: =2152-SUM(E18:G18) -> 512 | I18: =491 -> 491 | J18: =884-I18 -> 393 | K18: =1286-I18-J18 -> 402 | L18: =1575-SUM(I18:K18) -> 289 | M18: =292 -> 292 | N18: =556-M18 -> 264 | O18: =792-M18-N18 -> 236 | P18: =1012-SUM(M18:O18) -> 220 | Q18: =AVERAGE(M18:P18) -> 253 | R18: =AVERAGE(N18:Q18) -> 243.25 | S18: =AVERAGE(O18:R18) -> 238.0625 | T18: =AVERAGE(P18:S18) -> 238.57812 | U18: =AVERAGE(Q18:T18) -> 243.22266 | V18: =AVERAGE(R18:U18) -> 240.77832 | W18: =AVERAGE(S18:V18) -> 240.1604 | X18: =AVERAGE(T18:W18) -> 240.68488 | Y18: =SUM(M18:P18) -> 1012 | Z18: =SUM(Q18:T18) -> 972.89062 | AA18: =SUM(U18:X18) -> 964.84625
C19: YoY% | I19: =I18/E18-1 -> -0.039138943 | J19: =J18/F18-1 -> -0.34608985 | K19: =K18/G18-1 -> -0.23863636 | L19: =L18/H18-1 -> -0.43554688 | M19: =M18/I18-1 -> -0.40529532 | N19: =N18/J18-1 -> -0.32824427 | O19: =O18/K18-1 -> -0.41293532 | P19: =P18/L18-1 -> -0.23875433 | ... X19: =X18/T18-1 -> 0.0088304428 | Z19: =Z18/Y18-1 -> -0.038645627 | AA19: =AA18/Z18-1 -> -0.0082685272
C22: 이루다 매출 | D22: 시크릿 듀오 21년 7월 출시
C23: 1Q21 | D23: 2Q21 | E23: 3Q21 | F23: 4Q21
B24: 수출 | C24: =3265+437 -> 3702 | D24: =6669+700-C24 -> 3667 | E24: =11113+1312-D24-C24 -> 5056 | F24: =15725+2031-SUM(C24:E24) -> 5331
B25: 내수 | C25: =860+186 -> 1046 | D25: =1896+736-C25 -> 1586 | E25: =2480+889-C25-D25 -> 737 | F25: =3636+1255-SUM(C25:E25) -> 1522 | G25: =F25/E25-1 -> 1.0651289
C26: =SUM(C24:C25) -> 4748 | D26: =SUM(D24:D25) -> 5253 | E26: =SUM(E24:E25) -> 5793 | F26: =SUM(F24:F25) -> 6853
D27: =D26/C26-1 -> 0.10636057
D29: =D25/C25-1 -> 0.51625239 | F29: =E25/D25-1 -> -0.53530895

Sheet 비용 추정
A1: 클래시스(214150.KQ)
A2: Assumption Sheet
A3: (units in Millions KRW )
W4: 2024
B5: (단위: 백만원) | C5: 1Q22 | D5: 2Q22 | E5: 3Q22 | F5: 4Q22 | G5: 1Q23 | H5: 2Q23 | I5: 3Q23 | J5: 4Q23 | K5: 1Q24 | L5: 2Q24 | M5: 3Q24 | N5: 4Q24 | O5: 1Q25E | P5: 2Q25E | Q5: 3Q25E | R5: 4Q25E | Z5: Description
B6: 매출액 | C6: ='매출액 추정'!C6 -> 35382 | D6: ='매출액 추정'!D6 -> 32686 | E6: ='매출액 추정'!E6 -> 33268 | F6: ='매출액 추정'!F6 -> 40467 | G6: ='매출액 추정'!G6 -> 38974 | H6: ='매출액 추정'!H6 -> 45897 | I6: ='매출액 추정'!I6 -> 48243 | J6: ='매출액 추정'!J6 -> 47008 | ... R6: ='매출액 추정'!R6 -> 100949.82
B7: 매출원가 | C7: 8800 | D7: 8277 | E7: 7317 | F7: 9241 | G7: 8764 | H7: 9577 | I7: 11234 | J7: 10099 | K7: 10177 | L7: 11228 | M7: 12814 | N7: 17593 | O7: =O6*O8 -> 18118.758 | P7: =P6*P8 -> 17581.919 | Q7: =Q6*Q8 -> 18441.817 | R7: =R6*R8 -> 19180.466 | Z7: 매출원가율의 경우, 소모품의 판매 비중이 높아짐에 따라 하락할 것으로 예상됨. 이에 따라 4Q25E의 매출원가율을 과거 최소치였던 19%로 가정하고 점차 감소하는 시나리오로 추정.
B8: 매출원가율(%) | C8: =C7/C6 -> 0.24871404 | D8: =D7/D6 -> 0.25322768 | E8: =E7/E6 -> 0.21994108 | F8: =F7/F6 -> 0.22835891 | G8: =G7/G6 -> 0.22486786 | H8: =H7/H6 -> 0.20866288 | I8: =I7/I6 -> 0.2328628 | J8: =J7/J6 -> 0.21483577 | ... M8: =M7/M6 -> 0.21567307 | N8: 0.23645552 | O8: 0.22484164 | P8: 0.21322776 | Q8: 0.20161388 | R8: 0.19
B9: 매출총이익 | C9: =C6-C7 -> 26582 | D9: =D6-D7 -> 24409 | E9: =E6-E7 -> 25951 | F9: =F6-F7 -> 31226 | G9: =G6-G7 -> 30210 | H9: =H6-H7 -> 36320 | I9: =I6-I7 -> 37009 | J9: =J6-J7 -> 36909 | ... R9: =R6-R7 -> 81769.356
B10: GPM(%) | C10: =C9/C6 -> 0.75128596 | D10: =D9/D6 -> 0.74677232 | E10: =E9/E6 -> 0.78005892 | F10: =F9/F6 -> 0.77164109 | G10: =G9/G6 -> 0.77513214 | H10: =H9/H6 -> 0.79133712 | I10: =I9/I6 -> 0.7671372 | J10: =J9/J6 -> 0.78516423 | ... R10: =R9/R6 -> 0.81
B11: 판매비와 관리비 | C11: 9876.724 | D11: 9144.9522 | E11: 8471.9286 | F11: 11797.212 | G11: 10318.628 | H11: 13174.374 | I11: 12348.212 | J11: 14985.469 | K11: 13694.299 | L11: 16325.518 | M11: 17648.23 | N11: 21003.692 | O11: =SUM(O12:O43) -> 22079.563 | P11: =SUM(P12:P43) -> 22582.112 | Q11: =SUM(Q12:Q43) -> 24968.435 | R11: =SUM(R12:R43) -> 27636.256 | T11: of sales(%) | U11: 2022 | V11: 2023 | W11: 2024 | X11: 2025E
B12: 급여 | C12: 2562.656 | D12: =(2546211-40)/1000 -> 2546.171 | E12: 2828.2032 | F12: 2085.9336 | G12: 2200.0245 | H12: 2437.2019 | I12: 2533.016 | J12: 2500.849 | K12: 2749.218 | L12: 2864.951 | M12: 3187.89 | N12: 3684.084 | O12: =K12*(1.036) -> 2848.1898 | P12: =L12*(1.036) -> 2968.0892 | Q12: =M12*(1.036) -> 3302.654 | R12: =N12*(1.036) -> 3816.711 | T12: 급여 | U12: =SUM(C12:F12)/SUM('매출액 추정'!$C$6:$F$6) -> 0.070682311 | V12: =SUM(G12:J12)/SUM('매출액 추정'!$G$6:$J$6) -> 0.053691894 | W12: =SUM(K12:N12)/SUM('매출액 추정'!$K$6:$N$6) -> 0.051396206 | X12: =SUM(O12:R12)/SUM($O$6:$R$6) -> 0.036391139 | Z12: 급여의 경우, 국회예산정책처에서 발표한 명목임금상승률 전망치를 이용하여 25년 각 분기 추정
B13: 경상연구개발비 | C13: 1092.835 | D13: 1018.4202 | E13: 1003.5314 | F13: 1314.9905 | G13: 2115.6629 | H13: 2282.4004 | I13: 2213.2935 | J13: 2589.286 | K13: 2799.651 | L13: 2824.206 | M13: 3075.951 | N13: 3917.86 | O13: =N13*(1+(O$6/N$6-1)) -> 4243.3627 | P13: =O13*(1+(P$6/O$6-1)) -> 4341.9119 | Q13: =P13*(1+(Q$6/P$6-1)) -> 4816.6129 | R13: =Q13*(1+(R$6/Q$6-1)) -> 5315.7436 | T13: 경상연구개발비 | U13: =SUM(C13:F13)/SUM('매출액 추정'!$C$6:$F$6) -> 0.031238952 | V13: =SUM(G13:J13)/SUM('매출액 추정'!$G$6:$J$6) -> 0.051080061 | W13: =SUM(K13:N13)/SUM('매출액 추정'!$K$6:$N$6) -> 0.051937598 | X13: =SUM(O13:R13)/SUM($O$6:$R$6) -> 0.052657285 | Z13: 경상연구개발비의 경우, 해외 수출 확대와 함께 신제품 출시를 위해 가속화될 것으로 예상. 매출액 연동
B14: 광고선전비 | C14: 1609.318 | D14: 2002.1938 | E14: 1112.29 | F14: 1190.3856 | G14: 1318.6465 | H14: 3702.8743 | I14: 1466.4202 | J14: 2541.797 | K14: 2227.27 | L14: 2516.354 | M14: 4737.623 | N14: 3339.496 | O14: =N14*(1+(O$6/N$6-1)) -> 3616.9472 | P14: =O14*(1+(P$6/O$6-1)) -> 3700.9483 | Q14: =P14*(1+(Q$6/P$6-1)) -> 4105.5728 | R14: =Q14*(1+(R$6/Q$6-1)) -> 4531.0206 | T14: 광고선전비 | U14: =SUM(C14:F14)/SUM('매출액 추정'!$C$6:$F$6) -> 0.041707068 | V14: =SUM(G14:J14)/SUM('매출액 추정'!$G$6:$J$6) -> 0.050131233 | W14: =SUM(K14:N14)/SUM('매출액 추정'!$K$6:$N$6) -> 0.052773507 | X14: =SUM(O14:R14)/SUM($O$6:$R$6) -> 0.044883889 | Z14: 광고선전비의 경우, 해외 수출 확대와 함께 증가할 것으로 예상. 매출액 연동
B15: 지급수수료 | C15: 949.162 | D15: 1007.9808 | E15: 1128.655 | F15: 3590.6121 | G15: 1768.3492 | H15: 1043.257 | I15: 1980.7434 | J15: 2706.989 | K15: 1694.518 | L15: 3164.735 | M15: 2169.672 | N15: 3366.532 | O15: =O$6*(AVERAGE($U15:$W15)) -> 3532.4891 | P15: =P6*(AVERAGE($U15:$W15)) -> 3614.5287 | Q15: =Q6*(AVERAGE($U15:$W15)) -> 4009.705 | R15: =R6*(AVERAGE($U15:$W15)) -> 4425.2183 | T15: 지급수수료 | U15: =SUM(C15:F15)/SUM('매출액 추정'!$C$6:$F$6) -> 0.047082289 | V15: =SUM(G15:J15)/SUM('매출액 추정'!$G$6:$J$6) -> 0.041634773 | W15: =SUM(K15:N15)/SUM('매출액 추정'!$K$6:$N$6) -> 0.0427904 | X15: =SUM(O15:R15)/SUM($O$6:$R$6) -> 0.043835821 | Z15: 지급수수료의 경우, 상대방에게 용역 서비스를 제공받고 지급하는 비용이기에 변동비적 성격을 지님. of sales(%)를 3Y Average Flat하게 적용.
B16: 판매수수료 | C16: 1687.354 | D16: 1004.6254 | E16: 487.68333 | F16: 646.59672 | G16: 578.01816 | H16: 748.22562 | I16: 1013.4578 | J16: 855.827 | K16: 800.017 | L16: 1167.424 | M16: 841.407 | N16: 614.918 | O16: =O$6*(AVERAGE($U16:$W16)) -> 1579.912 | P16: =P$6*(AVERAGE($U16:$W16)) -> 1616.6044 | Q16: =Q$6*(AVERAGE($U16:$W16)) -> 1793.3476 | R16: =R$6*(AVERAGE($U16:$W16)) -> 1979.1867 | T16: 판매수수료 | U16: =SUM(C16:F16)/SUM('매출액 추정'!$C$6:$F$6) -> 0.026982923 | V16: =SUM(G16:J16)/SUM('매출액 추정'!$G$6:$J$6) -> 0.017740912 | W16: =SUM(K16:N16)/SUM('매출액 추정'!$K$6:$N$6) -> 0.01409311 | X16: =SUM(O16:R16)/SUM($O$6:$R$6) -> 0.019605649 | Z16: 판매수수료의 경우, 지급수수료와 유사하게 of sales(%)를 3Y Average Flat으로 적용
B17: 감가상각비 | C17: 372.006 | D17: 375.74756 | E17: 279.53081 | F17: 402.86608 | G17: 437.11959 | H17: 469.51039 | I17: 517.76484 | J17: 548.078 | K17: 572.452 | L17: 586.394 | M17: 602.235 | N17: 800.573 | O17: =O$6*(AVERAGE($U17:$W17)) -> 848.30443 | P17: =P$6*(AVERAGE($U17:$W17)) -> 868.00571 | Q17: =Q$6*(AVERAGE($U17:$W17)) -> 962.90473 | R17: =R$6*(AVERAGE($U17:$W17)) -> 1062.6876 | T17: 감가상각비 | U17: =SUM(C17:F17)/SUM('매출액 추정'!$C$6:$F$6) -> 0.010085474 | V17: =SUM(G17:J17)/SUM('매출액 추정'!$G$6:$J$6) -> 0.01095076 | W17: =SUM(K17:N17)/SUM('매출액 추정'!$K$6:$N$6) -> 0.010544433 | X17: =SUM(O17:R17)/SUM($O$6:$R$6) -> 0.010526889 | Z17: 감가상각비의 경우, CAPEX 투자 규모와 그에 따른 상각비를 알 수 없기에 of sales(%)를 3Y Average Flat하게 적용.
B18: 복리후생비 | C18: 454.866 | D18: 266.88399 | E18: 340.25054 | F18: 529.43001 | G18: 233.44265 | H18: 305.30156 | I18: 348.89246 | J18: 546.723 | K18: 278.994 | L18: 545.755 | M18: 438.022 | N18: 831.262 | O18: =O12*(AVERAGE($C18:$N18)/AVERAGE($C12:$N12)) -> 453.1429 | P18: =P12*(AVERAGE($C18:$N18)/AVERAGE($C12:$N12)) -> 472.21872 | Q18: =Q12*(AVERAGE($C18:$N18)/AVERAGE($C12:$N12)) -> 525.4475 | R18: =R12*(AVERAGE($C18:$N18)/AVERAGE($C12:$N12)) -> 607.23323 | T18: 복리후생비 | U18: =SUM(C18:F18)/SUM('매출액 추정'!$C$6:$F$6) -> 0.011222827 | V18: =SUM(G18:J18)/SUM('매출액 추정'!$G$6:$J$6) -> 0.0079632675 | W18: =SUM(K18:N18)/SUM('매출액 추정'!$K$6:$N$6) -> 0.0086195835 | X18: =SUM(O18:R18)/SUM($O$6:$R$6) -> 0.0057897778 | Z18: 복리후생비의 경우, 과거 3개년 급여 대비 복리후생비의 비중을 이용하여 추정.
B19: 판매보증비 | C19: 203.873 | D19: 232.85805 | E19: 281.3032 | F19: 441.71843 | G19: 64.267548 | H19: 318.97146 | I19: 294.51956 | J19: 368.287 | K19: 132.081 | L19: 332.43 | M19: 367.562 | N19: 51.542 | O19: =AVERAGE(C19:N19) -> 257.4511 | P19: =O19 -> 257.4511 | Q19: =P19 -> 257.4511 | R19: =Q19 -> 257.4511 | T19: 판매보증비 | U19: =SUM(C19:F19)/SUM('매출액 추정'!$C$6:$F$6) -> 0.0081786187 | V19: =SUM(G19:J19)/SUM('매출액 추정'!$G$6:$J$6) -> 0.0058074281 | W19: =SUM(K19:N19)/SUM('매출액 추정'!$K$6:$N$6) -> 0.0036371888 | X19: =SUM(O19:R19)/SUM($O$6:$R$6) -> 0.0028970923 | Z19: 판매보증비의 경우, 무상 보증 및 수비 서리스에 대한 비용을 판매되는 시점에 회계상 비용으로 인식하는 계정. of sales(%)가 감소하는 것을 확인하고 고정비라 판단. 이에 과거 3개년 판매보증비를 Average Flat하게 적용.
B20: 퇴직급여 | C20: 209.562 | D20: 142.01616 | E20: 197.85279 | F20: 238.0868 | G20: 150.03006 | H20: 232.56943 | I20: 181.35998 | J20: 183.42 | K20: 246.473 | L20: 202.922 | M20: 231.603 | N20: 240.495 | O20: =K20*(1.036) -> 255.34603 | P20: =L20*(1.036) -> 210.22719 | Q20: =M20*(1.036) -> 239.94071 | R20: =N20*(1.036) -> 249.15282 | T20: 퇴직급여 | U20: =SUM(C20:F20)/SUM('매출액 추정'!$C$6:$F$6) -> 0.0055536043 | V20: =SUM(G20:J20)/SUM('매출액 추정'!$G$6:$J$6) -> 0.0041492959 | W20: =SUM(K20:N20)/SUM('매출액 추정'!$K$6:$N$6) -> 0.0037931044 | X20: =SUM(O20:R20)/SUM($O$6:$R$6) -> 0.0026857116 | Z20: 퇴직급여의 경우, 급여 상승분을 적용하여 추정.
B21: 주식보상비용 | C21: - | D21: - | E21: - | F21: - | G21: 11.087277 | H21: 505.73929 | I21: 505.94601 | J21: 505.946 | K21: 420.395 | L21: 366.752 | M21: 570.868 | N21: 600.095 | O21: =AVERAGE(G21:N21) -> 435.85357 | P21: =O21 -> 435.85357 | Q21: =P21 -> 435.85357 | R21: =Q21 -> 435.85357 | T21: 주식보상비용 | U21: =SUM(C21:F21)/SUM('매출액 추정'!$C$6:$F$6) -> 0 | V21: =SUM(G21:J21)/SUM('매출액 추정'!$G$6:$J$6) -> 0.0084871286 | W21: =SUM(K21:N21)/SUM('매출액 추정'!$K$6:$N$6) -> 0.0080600892 | X21: =SUM(O21:R21)/SUM($O$6:$R$6) -> 0.0049046518 | Z21: 주식보상비용의 대표적인 예로는 스톡옵션, 추정이 불가하기에 과거 2개년 Average Flat 적용.
B22: 여비교통비 | C22: 27.038 | D22: 83.06734 | E22: 21.423727 | F22: 181.33515 | G22: 297.81258 | H22: 205.48039 | I22: 329.74875 | J22: 178.56 | K22: 360.69 | L22: 297.809 | M22: 201.619 | N22: 371.605 | O22: =N22*(1+(O$6/N$6-1)) -> 402.4786 | P22: =O22*(1+(P$6/O$6-1)) -> 411.82588 | Q22: =P22*(1+(Q$6/P$6-1)) -> 456.85079 | R22: =Q22*(1+(R$6/Q$6-1)) -> 504.19282 | T22: 여비교통비 | U22: =SUM(C22:F22)/SUM('매출액 추정'!$C$6:$F$6) -> 0.00220633 | V22: =SUM(G22:J22)/SUM('매출액 추정'!$G$6:$J$6) -> 0.005616203 | W22: =SUM(K22:N22)/SUM('매출액 추정'!$K$6:$N$6) -> 0.0050700917 | X22: =SUM(O22:R22)/SUM($O$6:$R$6) -> 0.0049944895 | Z22: 여비교통비의 경우, 23년 이후 증가세에 있음. 증가세 반영하기 위해 매출액 연동.
B23: 접대비 | C23: 0.791 | D23: 15.033637 | E23: 12.58849 | F23: 30.456055 | G23: 57.180141 | H23: 36.38579 | I23: 40.064523 | J23: 46.426 | K23: 49.115 | L23: 61.862 | M23: 46.462 | N23: 79.42 | O23: =N23*(1+(O$6/N$6-1)) -> 86.018354 | P23: =O23*(1+(P$6/O$6-1)) -> 88.01607 | Q23: =P23*(1+(Q$6/P$6-1)) -> 97.638862 | R23: =Q23*(1+(R$6/Q$6-1)) -> 107.75688 | T23: 접대비 | U23: =SUM(C23:F23)/SUM('매출액 추정'!$C$6:$F$6) -> 0.00041514765 | V23: =SUM(G23:J23)/SUM('매출액 추정'!$G$6:$J$6) -> 0.0009996361 | W23: =SUM(K23:N23)/SUM('매출액 추정'!$K$6:$N$6) -> 0.00097497314 | X23: =SUM(O23:R23)/SUM($O$6:$R$6) -> 0.0010674301 | Z23: 접대비 또한, 23년 이후 증가세에 있음. 증가세 반영하기 위해 매출액 연동
B24: 통신비 | C24: 8.457 | D24: 7.177509 | E24: 8.819771 | F24: 12.125935 | G24: 14.199509 | H24: 11.701801 | I24: 9.973207 | J24: 19.741 | K24: 12.244 | L24: 13.321 | M24: 12.759 | N24: 20.369 | O24: =O$6*(AVERAGE($U24:$W24)) -> 21.71287 | P24: =P$6*(AVERAGE($U24:$W24)) -> 22.217137 | Q24: =Q$6*(AVERAGE($U24:$W24)) -> 24.646135 | R24: =R$6*(AVERAGE($U24:$W24)) -> 27.200138 | T24: 통신비 | U24: =SUM(C24:F24)/SUM('매출액 추정'!$C$6:$F$6) -> 0.00025796503 | V24: =SUM(G24:J24)/SUM('매출액 추정'!$G$6:$J$6) -> 0.00030876582 | W24: =SUM(K24:N24)/SUM('매출액 추정'!$K$6:$N$6) -> 0.00024159563 | X24: =SUM(O24:R24)/SUM($O$6:$R$6) -> 0.00026944216 | Z24: 통신비의 경우, 금액적 유의성이 낮고 of sales(%)가 일정한 것을 이용하여 of sales(%)를 3Y Average Flat하게 적용.
B25: 수도광열비 | C25: 35.083 | D25: 33.5948 | E25: 44.243822 | F25: 21.433001 | G25: 50.38956 | H25: 25.129489 | I25: 41.697079 | J25: 32.992 | K25: 56.122 | L25: 31.164 | M25: 54.83 | N25: 40.246 | O25: =O$6*(AVERAGE($U25:$W25)) -> 68.014621 | P25: =P$6*(AVERAGE($U25:$W25)) -> 69.594213 | Q25: =Q$6*(AVERAGE($U25:$W25)) -> 77.202945 | R25: =R$6*(AVERAGE($U25:$W25)) -> 85.203248 | T25: 수도광열비 | U25: =SUM(C25:F25)/SUM('매출액 추정'!$C$6:$F$6) -> 0.00094747377 | V25: =SUM(G25:J25)/SUM('매출액 추정'!$G$6:$J$6) -> 0.00083392438 | W25: =SUM(K25:N25)/SUM('매출액 추정'!$K$6:$N$6) -> 0.00075064934 | X25: =SUM(O25:R25)/SUM($O$6:$R$6) -> 0.00084401583 | Z25: 수도광열비 또한 금액적 유의성이 낮고 of sales(%)가 일정한 것을 이용하여 of sales(%)를 3Y Average Flat하게 적용.
B26: 세금과공과금 | C26: 56.388 | D26: 14.398234 | E26: 173.238 | F26: 130.98468 | G26: 120.27808 | H26: 20.276854 | I26: 146.90984 | J26: 130.556 | K26: 153.551 | L26: 20.03 | M26: 196.536 | N26: 165.5 | O26: =O$6*(AVERAGE($U26:$W26)) -> 192.59918 | P26: =P$6*(AVERAGE($U26:$W26)) -> 197.07216 | Q26: =Q$6*(AVERAGE($U26:$W26)) -> 218.61805 | R26: =R$6*(AVERAGE($U26:$W26)) -> 241.27277 | T26: 세금과공과금 | U26: =SUM(C26:F26)/SUM('매출액 추정'!$C$6:$F$6) -> 0.0026445767 | V26: =SUM(G26:J26)/SUM('매출액 추정'!$G$6:$J$6) -> 0.0023207646 | W26: =SUM(K26:N26)/SUM('매출액 추정'!$K$6:$N$6) -> 0.0022047386 | X26: =SUM(O26:R26)/SUM($O$6:$R$6) -> 0.0023900267 | Z26: 세금과공과금의 경우, of sales(%)를 3Y Average Flat 적용.
B27: 지급임차료 | C27: 1.422 | D27: 1.4286 | E27: 1.4658 | F27: 1.4307 | G27: 3.39635 | H27: 5.40565 | I27: 2.712442 | J27: 1.037 | K27: 3.088 | L27: 3.499 | M27: 5.337 | N27: 21.762 | O27: =AVERAGE(C27:M27) -> 2.7475038 | P27: =O27 -> 2.7475038 | Q27: =P27 -> 2.7475038 | R27: =Q27 -> 2.7475038 | T27: 지급임차료 | U27: =SUM(C27:F27)/SUM('매출액 추정'!$C$6:$F$6) -> 4.0528762e-05 | V27: =SUM(G27:J27)/SUM('매출액 추정'!$G$6:$J$6) -> 6.9683004e-05 | W27: =SUM(K27:N27)/SUM('매출액 추정'!$K$6:$N$6) -> 0.00013866032 | X27: =SUM(O27:R27)/SUM($O$6:$R$6) -> 3.0917608e-05 | Z27: 지급임차료의 경우, 4Q24를 제외하고 고정비적 성격을 지님, 이에 4Q24 제외한 3Y Average Flat 적용
B28: 수선비 | C28: 4.804 | D28: 4.572074 | E28: 0.405 | F28: 59.746849 | G28: 18.80726 | H28: 17.956078 | I28: 11.445129 | J28: 4.679 | K28: 4.37 | L28: 2.863 | M28: 23.274 | N28: 59.781 | O28: =O$6*(AVERAGE($U28:$W28)) -> 31.040694 | P28: =P$6*(AVERAGE($U28:$W28)) -> 31.761593 | Q28: =Q$6*(AVERAGE($U28:$W28)) -> 35.234086 | R28: =R$6*(AVERAGE($U28:$W28)) -> 38.885285 | T28: 수선비 | U28: =SUM(C28:F28)/SUM('매출액 추정'!$C$6:$F$6) -> 0.00049031348 | V28: =SUM(G28:J28)/SUM('매출액 추정'!$G$6:$J$6) -> 0.00029362025 | W28: =SUM(K28:N28)/SUM('매출액 추정'!$K$6:$N$6) -> 0.00037164885 | X28: =SUM(O28:R28)/SUM($O$6:$R$6) -> 0.0003851942 | Z28: 수선비의 경우, of sales(%)를 3Y Average Flat 적용.
B29: 보험료 | C29: 9.639 | D29: 16.886823 | E29: 20.170973 | F29: 44.28228 | G29: 19.556208 | H29: 13.572042 | I29: 15.336374 | J29: 19.056 | K29: 17.312 | L29: 16.168 | M29: 16.893 | N29: 22.999 | O29: =AVERAGE(C29:N29) -> 19.322642 | P29: =O29 -> 19.322642 | Q29: =P29 -> 19.322642 | R29: =Q29 -> 19.322642 | T29: 보험료 | U29: =SUM(C29:F29)/SUM('매출액 추정'!$C$6:$F$6) -> 0.00064158781 | V29: =SUM(G29:J29)/SUM('매출액 추정'!$G$6:$J$6) -> 0.00037486051 | W29: =SUM(K29:N29)/SUM('매출액 추정'!$K$6:$N$6) -> 0.0003020182 | X29: =SUM(O29:R29)/SUM($O$6:$R$6) -> 0.00021743731 | Z29: 보험료의 경우, 지속적으로 하락하는 경향을 가짐. 고정비라 판단한 후 3Y Average Flat 적용.
B30: 차량유지비 | C30: 44.571 | D30: 53.847982 | E30: 44.451177 | F30: 51.430019 | G30: 44.444368 | H30: 50.81905 | I30: 53.849183 | J30: 56.368 | K30: 55.029 | L30: 64.144 | M30: 58.103 | N30: 78.839 | O30: =AVERAGE(C30:M30) -> 52.459707 | P30: =O30 -> 52.459707 | Q30: =P30 -> 52.459707 | R30: =Q30 -> 52.459707 | T30: 차량유지비 | U30: =SUM(C30:F30)/SUM('매출액 추정'!$C$6:$F$6) -> 0.001370212 | V30: =SUM(G30:J30)/SUM('매출액 추정'!$G$6:$J$6) -> 0.0011407857 | W30: =SUM(K30:N30)/SUM('매출액 추정'!$K$6:$N$6) -> 0.0010542358 | X30: =SUM(O30:R30)/SUM($O$6:$R$6) -> 0.00059032807 | Z30: 차량유지비의 경우, 4Q24를 제외하고 고정비적 성격을 지님. 이에 4Q24 제외한 3Y Average Flat 적용
B31: 운반비 | C31: 73.371 | D31: 91.085303 | E31: 80.111605 | F31: 153.96195 | G31: 131.2097 | H31: 131.01561 | I31: 79.050153 | J31: 66.116 | K31: 74.62 | L31: 77.12 | M31: 111.517 | N31: 143.761 | O31: =N31*(1+(O$6/N$6-1)) -> 155.70492 | P31: =O31*(1+(P$6/O$6-1)) -> 159.32106 | Q31: =P31*(1+(Q$6/P$6-1)) -> 176.73962 | R31: =Q31*(1+(R$6/Q$6-1)) -> 195.0546 | T31: 운반비 | U31: =SUM(C31:F31)/SUM('매출액 추정'!$C$6:$F$6) -> 0.0028104473 | V31: =SUM(G31:J31)/SUM('매출액 추정'!$G$6:$J$6) -> 0.0022617529 | W31: =SUM(K31:N31)/SUM('매출액 추정'!$K$6:$N$6) -> 0.0016753918 | X31: =SUM(O31:R31)/SUM($O$6:$R$6) -> 0.0019321936 | Z31: 운반비의 경우, 제품 판매가 늘어날수록 늘어날 것으로 예상되는 계정이기에 매출액과 연동.
B32: 교육훈련비 | C32: 0.945 | D32: 2.242995 | E32: 0.969 | F32: 0.518 | G32: 1.471 | H32: 4.65 | I32: 6.124335 | J32: 3.561 | K32: 7.955 | L32: 24.12 | M32: 1.441 | N32: 8.459 | O32: =AVERAGE(C32:K32,M32:N32) -> 3.4851209 | P32: =O32 -> 3.4851209 | Q32: =P32 -> 3.4851209 | R32: =Q32 -> 3.4851209 | T32: 교육훈련비 | U32: =SUM(C32:F32)/SUM('매출액 추정'!$C$6:$F$6) -> 3.2968238e-05 | V32: =SUM(G32:J32)/SUM('매출액 추정'!$G$6:$J$6) -> 8.7753495e-05 | W32: =SUM(K32:N32)/SUM('매출액 추정'!$K$6:$N$6) -> 0.00017278 | X32: =SUM(O32:R32)/SUM($O$6:$R$6) -> 3.9217998e-05 | Z32: 교육훈련비의 경우, 금액적 유의성이 낮고 2Q24 특이값을 제외하면 고정비적 성격을 지니는 것으로 파악됨. 이에 2Q24제외하여 3Y Average Flat
B33: 도서인쇄비 | C33: 129.95 | D33: 25.52452 | E33: 49.280889 | F33: 65.498146 | G33: 64.94883 | H33: 58.761779 | I33: 19.258518 | J33: 86.635 | K33: 96.108 | L33: 50.777 | M33: 144.327 | N33: 141.717 | O33: =O$6*(AVERAGE($U33:$W33)) -> 133.30295 | P33: =P$6*(AVERAGE($U33:$W33)) -> 136.39882 | Q33: =Q$6*(AVERAGE($U33:$W33)) -> 151.3113 | R33: =R$6*(AVERAGE($U33:$W33)) -> 166.99122 | T33: 도서인쇄비 | U33: =SUM(C33:F33)/SUM('매출액 추정'!$C$6:$F$6) -> 0.0019058381 | V33: =SUM(G33:J33)/SUM('매출액 추정'!$G$6:$J$6) -> 0.0012747145 | W33: =SUM(K33:N33)/SUM('매출액 추정'!$K$6:$N$6) -> 0.0017820482 | X33: =SUM(O33:R33)/SUM($O$6:$R$6) -> 0.0016542002 | Z33: 도서인쇄비의 경우, of sales(%)를 3Y Average Flat 적용
B34: 사무용품비 | C34: 4.576 | D34: 3.36409 | E34: 4.331566 | F34: 10.280646 | G34: 5.484949 | H34: 3.45338 | I34: 6.524536 | J34: 3.936 | K34: 5.001 | L34: 4.627 | M34: 4.072 | N34: 4.943 | O34: =AVERAGE(C34:N34) -> 5.0495139 | P34: =O34 -> 5.0495139 | Q34: =P34 -> 5.0495139 | R34: =Q34 -> 5.0495139 | T34: 사무용품비 | U34: =SUM(C34:F34)/SUM('매출액 추정'!$C$6:$F$6) -> 0.00015903967 | V34: =SUM(G34:J34)/SUM('매출액 추정'!$G$6:$J$6) -> 0.00010769848 | W34: =SUM(K34:N34)/SUM('매출액 추정'!$K$6:$N$6) -> 7.6739428e-05 | X34: =SUM(O34:R34)/SUM($O$6:$R$6) -> 5.6822083e-05 | Z34: 사무용품비의 경우, 금액적 유의성이 낮음. 3Y Average Flat 적용
B35: 소모품비 | C35: 44.045 | D35: 37.768633 | E35: 37.536 | F35: 25.192686 | G35: 15.141788 | H35: 66.614672 | I35: 26.903271 | J35: 29.285 | K35: 58.144 | L35: 47.667 | M35: 54.434 | N35: 34.818 | O35: =O$6*(AVERAGE($U35:$W35)) -> 69.519961 | P35: =P$6*(AVERAGE($U35:$W35)) -> 71.134514 | Q35: =Q$6*(AVERAGE($U35:$W35)) -> 78.911647 | R35: =R$6*(AVERAGE($U35:$W35)) -> 87.089017 | T35: 소모품비 | U35: =SUM(C35:F35)/SUM('매출액 추정'!$C$6:$F$6) -> 0.0010193178 | V35: =SUM(G35:J35)/SUM('매출액 추정'!$G$6:$J$6) -> 0.00076584055 | W35: =SUM(K35:N35)/SUM('매출액 추정'!$K$6:$N$6) -> 0.00080292995 | X35: =SUM(O35:R35)/SUM($O$6:$R$6) -> 0.00086269609 | Z35: 소모품비의 경우, of sales(%)를 3Y Average Flay 적용
B36: 판매촉진비 | C36: 31.414 | D36: 14.068715 | E36: 11.994956 | F36: 116.45084 | G36: 4.917 | H36: 0.061 | I36: 0.067 | J36: 185.621 | K36: 0.756 | L36: 2.604 | M36: 2.181 | N36: 16.705 | O36: =AVERAGE(G36:N36) -> 26.614 | P36: =AVERAGE(H36:O36) -> 29.326125 | Q36: =AVERAGE(I36:P36) -> 32.984266 | R36: =AVERAGE(J36:Q36) -> 37.098924 | T36: 판매촉진비 | U36: =SUM(C36:F36)/SUM('매출액 추정'!$C$6:$F$6) -> 0.0012265503 | V36: =SUM(G36:J36)/SUM('매출액 추정'!$G$6:$J$6) -> 0.0010585381 | W36: =SUM(K36:N36)/SUM('매출액 추정'!$K$6:$N$6) -> 9.1570312e-05 | X36: =SUM(O36:R36)/SUM($O$6:$R$6) -> 0.00035453448 | Z36: 판매촉진비의 경우 판매실적 등에 따라 장려금을 지급하는 비용. 분기별 편차가 크고 연도별 편차도 큰 것을 확인. 이에 과거 8개 분기 이동평균 적용.
B37: 대손상각비 | C37: 33.86 | D37: -37.278755 | E37: 60.165 | F37: -37.021383 | G37: 98.425215 | H37: 55.146087 | I37: 114.90418 | J37: 181.214 | K37: -21.588 | L37: 399.49 | M37: -231.911 | N37: -109.558 | O37: =AVERAGE(G37:N37) -> 60.76531 | P37: =AVERAGE(H37:O37) -> 56.057822 | Q37: =AVERAGE(I37:P37) -> 56.171789 | R37: =AVERAGE(J37:Q37) -> 48.83024 | T37: 대손상각비 | U37: =SUM(C37:F37)/SUM('매출액 추정'!$C$6:$F$6) -> 0.00013910046 | V37: =SUM(G37:J37)/SUM('매출액 추정'!$G$6:$J$6) -> 0.0024965828 | W37: =SUM(K37:N37)/SUM('매출액 추정'!$K$6:$N$6) -> 0.00014996769 | X37: =SUM(O37:R37)/SUM($O$6:$R$6) -> 0.00062404857 | Z37: 대손상각비의 경우, 대손충당금의 환입이 이뤄질 경우 (-)의 값으로 나타나는 것으로 확인. 이에 과거 8개 분기 이동평균 사용.
B38: 수출제비용 | C38: 57.458 | D38: 33.599286 | E38: 93.052617 | F38: 45.360547 | G38: 52.9771 | H38: 52.276433 | I38: 67.488317 | J38: 36.13 | K38: 33.728 | L38: 51.594 | M38: 38.889 | N38: 69.262 | O38: =N38*(의료기기!O10/의료기기!N10) -> 124.47721 | P38: =O38*(의료기기!P10/의료기기!O10) -> 127.93491 | Q38: =P38*(의료기기!Q10/의료기기!P10) -> 131.39261 | R38: =Q38*(의료기기!R10/의료기기!Q10) -> 134.85031 | T38: 수출제비용 | U38: =SUM(C38:F38)/SUM('매출액 추정'!$C$6:$F$6) -> 0.0016182341 | V38: =SUM(G38:J38)/SUM('매출액 추정'!$G$6:$J$6) -> 0.0011596132 | W38: =SUM(K38:N38)/SUM('매출액 추정'!$K$6:$N$6) -> 0.0007963851 | X38: =SUM(O38:R38)/SUM($O$6:$R$6) -> 0.0014591038 | Z38: 수출제비용의 경우 상품 및 제품의 수출과정에서 발생하는 비용. 동사의 수출 매출 성장률을 적용하여 추정.
B39: 무형고정자산상각비 | C39: 35.301 | D39: 37.984363 | E39: 42.474 | F39: 47.204268 | G39: 55.694633 | H39: 60.048096 | I39: 62.690651 | J39: 73.491 | K39: 77.32 | L39: 77.891 | M39: 85.728 | N39: 1925.538 | O39: =N39*(1+(O$6/N$6-1)) -> 2085.5151 | P39: =O39*(1+(P$6/O$6-1)) -> 2133.9497 | Q39: =P39*(1+(Q$6/P$6-1)) -> 2367.2543 | R39: =Q39*(1+(R$6/Q$6-1)) -> 2612.5656 | T39: 무형고정자산상각비 | U39: =SUM(C39:F39)/SUM('매출액 추정'!$C$6:$F$6) -> 0.0011492256 | V39: =SUM(G39:J39)/SUM('매출액 추정'!$G$6:$J$6) -> 0.0013986319 | W39: =SUM(K39:N39)/SUM('매출액 추정'!$K$6:$N$6) -> 0.0089177818 | X39: =SUM(O39:R39)/SUM($O$6:$R$6) -> 0.025879844 | Z39: 무형고정자산상각비의 경우 특이값인 4Q24를 제외하고 지속적으로 상승하고 있는 것을 확인. 추세를 반영하기 위해 매출액 연동.
B40: 견본비 | C40: 133.682 | D40: 109.68913 | E40: 105.90593 | F40: 395.9214 | G40: 379.64014 | H40: 302.40015 | I40: 248.01012 | J40: 472.778 | K40: 713.299 | L40: 428.989 | M40: 492.848 | N40: 335.04 | O40: =N40*(1+(O$6/N$6-1)) -> 362.87571 | P40: =O40*(1+(P$6/O$6-1)) -> 371.30325 | Q40: =P40*(1+(Q$6/P$6-1)) -> 411.89781 | R40: =Q40*(1+(R$6/Q$6-1)) -> 454.58151 | T40: 견본비 | U40: =SUM(C40:F40)/SUM('매출액 추정'!$C$6:$F$6) -> 0.0052551671 | V40: =SUM(G40:J40)/SUM('매출액 추정'!$G$6:$J$6) -> 0.0077882125 | W40: =SUM(K40:N40)/SUM('매출액 추정'!$K$6:$N$6) -> 0.0081097559 | X40: =SUM(O40:R40)/SUM($O$6:$R$6) -> 0.0045030442 | Z40: 견본비의 경우 상품 또는 제품의 판매를 목적으로 거래처에 무상으로 제공하는 상품 또는 제품 비용을 의미한다. 동사의 무상 제공 소모품이 이에 해당한다고 판단하며, 매출액과 연동.
B41: 건물관리비 | C41: - | D41: - | E41: - | F41: - | G41: - | H41: - | I41: - | J41: - | K41: 0 | L41: 58.679 | M41: 92.209 | N41: 113.511 | O41: =O$6*$W$41 -> 87.702962 | P41: =P$6*$W$41 -> 89.739802 | Q41: =Q$6*$W$41 -> 99.55105 | R41: =R$6*$W$41 -> 109.86722 | T41: 건물관리비 | U41: =SUM(C41:F41)/SUM('매출액 추정'!$C$6:$F$6) -> 0 | V41: =SUM(G41:J41)/SUM('매출액 추정'!$G$6:$J$6) -> 0 | W41: =SUM(K41:N41)/SUM('매출액 추정'!$K$6:$N$6) -> 0.0010883349 | X41: =SUM(O41:R41)/SUM($O$6:$R$6) -> 0.0010883349 | Z41: 건물관리비의 경우 24년 처음 발생하기 시작하였으며 이에 추세를 반영하기 어려움. 24년 of sales(%)를 25년에 똑같이 적용.
B42: 잡급 | C42: 2.297 | D42: - | E42: - | F42: - | G42: 1.76 | H42: 0 | I42: 0 | J42: 0 | K42: 0 | L42: 0.6 | M42: 0 | N42: 0 | O42: 0 | P42: 0 | Q42: 0 | R42: 0 | T42: 잡급 | U42: =SUM(C42:F42)/SUM('매출액 추정'!$C$6:$F$6) -> 1.6198529e-05 | V42: =SUM(G42:J42)/SUM('매출액 추정'!$G$6:$J$6) -> 9.7711551e-06 | W42: =SUM(K42:N42)/SUM('매출액 추정'!$K$6:$N$6) -> 2.4697558e-06 | X42: =SUM(O42:R42)/SUM($O$6:$R$6) -> 0 | Z42: 0 Flat
B43: 회의비 | C43: - | D43: - | E43: - | F43: - | G43: 4.244793 | H43: 7.167865 | I43: 10.04043 | J43: 10.085 | K43: 16.366 | L43: 18.577 | M43: 13.849 | N43: 12.118 | O43: =O6*(AVERAGE($V$43:$W$43)) -> 17.157023 | P43: =P6*(AVERAGE($V$43:$W$43)) -> 17.555483 | Q43: =Q6*(AVERAGE($V$43:$W$43)) -> 19.474823 | R43: =R6*(AVERAGE($V$43:$W$43)) -> 21.492939 | T43: 회의비 | U43: =SUM(C43:F43)/SUM('매출액 추정'!$C$6:$F$6) -> 0 | V43: =SUM(G43:J43)/SUM('매출액 추정'!$G$6:$J$6) -> 0.00017509293 | W43: =SUM(K43:N43)/SUM('매출액 추정'!$K$6:$N$6) -> 0.00025072137 | X43: =SUM(O43:R43)/SUM($O$6:$R$6) -> 0.00021290715 | Z43: 회의비의 경우, 23년부터 발생 시작. 과거 2개년 of sales(%)의 Average Flat 적용.
B44: 영업이익 | C44: =C9-C11 -> 16705.276 | D44: =D9-D11 -> 15264.048 | E44: =E9-E11 -> 17479.071 | F44: =F9-F11 -> 19428.788 | G44: =G9-G11 -> 19891.372 | H44: =H9-H11 -> 23145.626 | I44: =I9-I11 -> 24660.788 | J44: =J9-J11 -> 21923.531 | ... R44: =R9-R11 -> 54133.1 | T44: 합계 | U44: =SUM(U12:U43) -> 0.27708029 | V44: =SUM(V12:V43) -> 0.2821792 | W44: =SUM(W12:W43) -> 0.28267071 | X44: =SUM(X12:X43) -> 0.27363413
B45: OPM(%) | C45: =C44/C6 -> 0.47214052 | D45: =D44/D6 -> 0.46699039 | E45: =E44/E6 -> 0.52540193 | F45: =F44/F6 -> 0.48011438 | G45: =G44/G6 -> 0.51037544 | H45: =H44/H6 -> 0.50429497 | I45: =I44/I6 -> 0.51117858 | J45: =J44/J6 -> 0.46637872 | ... R45: =R44/R6 -> 0.5362377
B46: 지분법손익 | C46: 0 | D46: 0 | E46: 0 | F46: 0 | G46: 0 | H46: 0 | I46: 0 | J46: 0 | K46: 0 | L46: 267 | M46: -822.65555 | N46: -511 | O46: -511 | P46: -511 | Q46: -511 | R46: -511 | Z46: 지분법손익의 경우, 자세한 추정이 어렵기에 4Q24 Flat 적용
B47: 금융손익 | C47: 704 | D47: 2974 | E47: 5432 | F47: -6526 | G47: 4394 | H47: 2027 | I47: 4088 | J47: -1850 | K47: 6480 | L47: 4854 | M47: -3060 | N47: 15933 | O47: =AVERAGE(G47:M47) -> 2419 | P47: =O47 -> 2419 | Q47: =P47 -> 2419 | R47: =Q47 -> 2419 | Z47: 금융손익의 경우, 특이값인 4Q24를 제외한 2Y Average Flat 적용
B48: 금융비용 | C48: -792 | D48: -731 | E48: -770 | F48: -2380 | G48: -1145 | H48: -489 | I48: -564 | J48: -1395 | K48: -556 | L48: -536 | M48: -2674.6856 | N48: -144 | O48: =AVERAGE(G48:N48) -> -937.9607 | P48: =O48 -> -937.9607 | Q48: =P48 -> -937.9607 | R48: =Q48 -> -937.9607 | Z48: 금용비용 또한 마찬가지로 2Y Average Flat 적용
B49: 기타수익 | C49: 2 | D49: 27 | E49: 5 | F49: 30338 | G49: 1 | H49: 15 | I49: 15 | J49: 17.429602 | K49: 0.4 | L49: 10 | M49: 1.375159 | N49: 17.402788 | O49: 0 | P49: 0 | Q49: 0 | R49: 0 | Z49: 기타손익의 경우, 자세한 추정이 어렵기에 0 Flat 적용
B50: 기타비용 | C50: -0.002 | D50: -0.2 | E50: -0.06 | F50: -400 | G50: -11 | H50: -51 | I50: -434 | J50: -398 | K50: -346 | L50: -1241 | M50: -2.069708 | N50: -12190 | O50: 0 | P50: 0 | Q50: 0 | R50: 0
B51: 법인세차감전순이익 | C51: =SUM(C44,SUM(C47:C50)) -> 16619.274 | D51: =SUM(D44,SUM(D47:D50)) -> 17533.848 | E51: =SUM(E44,SUM(E47:E50)) -> 22146.011 | F51: =SUM(F44,SUM(F47:F50)) -> 40460.788 | G51: =SUM(G44,SUM(G47:G50)) -> 23130.372 | H51: =SUM(H44,SUM(H47:H50)) -> 24647.626 | I51: =SUM(I44,SUM(I47:I50)) -> 27765.788 | J51: =SUM(J44,SUM(J47:J50)) -> 18297.961 | K51: =SUM(K44,SUM(K47:K50)) -> 32056.101 | L51: =SUM(L44,SUM(L46:L50)) -> 34573.482 | M51: =SUM(M44,SUM(M46:M50)) -> 22393.734 | N51: =SUM(N44,SUM(N46:N50)) -> 38911.711 | O51: =SUM(O44:O50) -> 41356.752 | P51: =SUM(P44:P50) -> 43262.573 | Q51: =SUM(Q44:Q50) -> 49031.281 | R51: =SUM(R44:R50) -> 55103.676
B52: 법인세비용 | C52: -3802 | D52: -3725 | E52: -3430 | F52: -10424 | G52: -4355 | H52: -6089 | I52: -6575 | J52: -2597 | K52: -6002.4 | L52: -7961 | M52: -5908.5838 | N52: -10514 | O52: =-O51*O53 -> -9027.2983 | P52: =-P51*P53 -> -9405.4734 | Q52: =-Q51*Q53 -> -10679.875 | R52: =-R51*R53 -> -12291.551
B53: 법인세율(%) | C53: =-C52/C51 -> 0.22877052 | D53: =-D52/D51 -> 0.21244624 | E53: =-E52/E51 -> 0.15488116 | F53: =-F52/F51 -> 0.25763215 | G53: =-G52/G51 -> 0.18828058 | H53: =-H52/H51 -> 0.24704204 | I53: =-I52/I51 -> 0.23680221 | J53: =-J52/J51 -> 0.14192839 | ... N53: =-N52/N51 -> 0.27020143 | O53: =AVERAGE(C53:N53) -> 0.21827871 | P53: =AVERAGE(D53:O53) -> 0.21740439 | Q53: =AVERAGE(E53:P53) -> 0.21781757 | R53: =AVERAGE(F53:Q53) -> 0.22306227 | Z53: 법인세율의 경우, 과거 3개년 유효세율의 Average Flat 적용
B54: 당기순이익 | C54: =C51+C52 -> 12817.274 | D54: =D51+D52 -> 13808.848 | E54: =E51+E52 -> 18716.011 | F54: =F51+F52 -> 30036.788 | G54: =G51+G52 -> 18775.372 | H54: =H51+H52 -> 18558.626 | I54: =I51+I52 -> 21190.788 | J54: =J51+J52 -> 15700.961 | ... R54: =R51+R52 -> 42812.125

Sheet 요약 재무제표
B1: (단위: 십억원) | H1: `
B2: 예상 포괄손익계산서 (요약) | C2: 2022 | D2: 2023 | E2: 2024 | F2: 2025E | H2: 예상 재무상태표 (요약) | I2: 2022 | J2: 2023 | K2: 2024E | L2: 2025E | R2: Historical | T2: Projection | W2: FCF란 뭘까? (brunch.co.kr) | Z2: ◀ 해당 내용 참고하여 작성함
B3: 매출액 | C3: 141.8 | D3: 180.1 | E3: 242.9 | F3: =355.5 -> 355.5 | H3: 유동자산 | I3: 147.8 | J3: 185.7 | K3: 234.2 | L3: =SUM(L4:L7) -> 364.19448 | P3: in KRW Mn | R3: 2022 | S3: 2023 | T3: 2024 | U3: 2025
B4: 매출원가 | C4: =33.6 -> 33.6 | D4: 39.7 | E4: =E3-E5 -> 51.8 | F4: =F3-F5 -> 73.4 | H4: 현금 및 현금성자산 | I4: 26 | J4: 18.3 | K4: =E50 -> 21.1 | L4: =F50 -> 54.91426 | P4: EBIT | R4: =C8 -> 68.9 | S4: =D8 -> 89.6 | T4: =E8 -> 122.4 | U4: =F8 -> 185.4 | W4: FCFF = NI + NCC + Int*(1-tex rate) - Capex -WC
B5: 매출총이익 | C5: 108.1 | D5: 140.4 | E5: 191.1 | F5: 282.1 | H5: 매출채권 및 기타채권 | I5: 8.4 | J5: 18.2 | K5: =T17 -> 19.09926 | L5: =U17 -> 25.906037 | Q5: % effective tax rate | R5: =-R6/R4 -> 0.030478955 | S5: =-S6/S4 -> 0.022321429 | T5: =-T6/T4 -> 0.024509804 | U5: =-U6/U4 -> 0.022653722 | W5: FCF = NI + NCC - Capex -WC
B6: 판매비와관리비 | C6: 9.9 | D6: 14.3 | E6: =E5-E7 -> 68.7 | F6: =F5-F7 -> 96.7 | H6: 재고자산 | I6: 23.9 | J6: 19.4 | K6: =T18 -> 4.8819726 | L6: =U18 -> 7.8278969 | P6: (-) | Q6: EBIT법인세 | R6: =C13 -> -2.1 | S6: =D13 -> -2 | T6: =E13 -> -3 | U6: =F13 -> -4.2 | W6: FCF = FCFF - Int*(1-tex rate)
B7: 조정영업이익 | C7: =C8 -> 68.9 | D7: =D8 -> 89.6 | E7: =E8 -> 122.4 | F7: =F8 -> 185.4 | H7: 기타유동자산 | I7: =I3-SUM(I4:I6) -> 89.5 | J7: =J3-SUM(J4:J6) -> 129.8 | K7: =K3-SUM(K4:K6) -> 189.11877 | L7: =K7*(1+K7/J7-1) -> 275.54629 | Q7: 이자비용
B8: 영업이익 | C8: 68.9 | D8: 89.6 | E8: 122.4 | F8: 185.4 | H8: 비유동자산 | I8: =SUM(I9:I11) -> 183.6 | J8: =SUM(J9:J11) -> 189.7 | K8: =SUM(K9:K11) -> 374.2 | L8: =SUM(L9:L11) -> 285.6 | P8: NOPAT(세후영업이익) | R8: 53.7 | S8: 70.9 | T8: =93.4 -> 93.4 | U8: 185
B9: 비영업손익 | C9: 0 | D9: 0 | E9: =E8-E10-E12 -> -7.9 | F9: =F8-F10-F12 -> -13.5 | H9: 투자자산 | I9: 77.9 | J9: 47.9 | K9: 40.1 | L9: =AVERAGE(J9:K9) -> 44 | Q9: % Yoy Growth | S9: =S8/R8-1 -> 0.32029795 | T9: =T8/S8-1 -> 0.31734838 | U9: =U8/T8-1 -> 0.98072805
B10: 금융손익 | C10: 0.3 | D10: 0.9 | E10: 2.4 | F10: 9.6 | H10: 유형자산 | I10: 104.2 | J10: 139 | K10: 193.2 | L10: =K10 -> 193.2 | Q10: Change in NWC | R10: =R23 -> 8.3 | S10: =S23 -> 5.1 | T10: =T23 -> -28.518767 | U10: =U23 -> 24.042642
B11: 관계기업등 투자손익 | C11: 0 | D11: 0 | E11: 0 | F11: 0 | H11: 무형자산 | I11: 1.5 | J11: 2.8 | K11: 140.9 | L11: =AVERAGE(I11:K11) -> 48.4 | Q11: Net Capex | R11: =R36 -> 30.2 | S11: =S36 -> 7.7 | T11: =T36 -> 9.5 | U11: =U36 -> 14.551463
B12: 세전계속사업손익 | C12: 96.7 | D12: 93.8 | E12: 127.9 | F12: 189.3 | H12: 자산총계 | I12: =I8+I3 -> 331.4 | J12: =J8+J3 -> 375.4 | K12: =K8+K3 -> 608.4 | L12: =L8+L3 -> 649.79448 | M12: =K20+K26 -> 609.7 | N12: =L20+L26 -> 692.92681 | P12: (-) Reinvestment | R12: =R10+R11 -> 38.5 | S12: =S10+S11 -> 12.8 | T12: =T10+T11 -> -19.018767 | U12: =U10+U11 -> 38.594105
B13: 법인세 비용 | C13: -2.1 | D13: -2 | E13: -3 | F13: -4.2 | H13: 유동부채 | I13: 36.2 | J13: 29.2 | K13: 128.9 | L13: =SUM(L14:L16) -> 45.810059 | P13: FCFF(기업잉여현금흐름) | R13: =R8-R12 -> 15.2 | S13: =S8-S12 -> 58.1 | T13: =T8-T12 -> 112.41877 | U13: =U8-U12 -> 146.4059
B14: 계속사업이익 | C14: 75.4 | D14: 74.2 | E14: ='Expected IS'!T22/1000 -> 97.547381 | F14: ='Expected IS'!U22/1000 -> 147.35008 | H14: 매입채무 및 기타채무 | I14: 2.1 | J14: 2.3 | K14: 17.2 | L14: =U20 -> 2.9100593 | P14: FCF(잉여현금흐름) | R14: =C23 -> 27 | S14: =D23 -> 60 | T14: =T13-T7*(1-T5) -> 112.41877 | U14: =U13-U7*(1-U5) -> 146.4059
B15: 중단사업이익 | C15: 0 | D15: 0 | E15: 0 | F15: 0 | H15: 유동성장기부채 | I15: 2.4 | J15: 2.4 | K15: 72.8 | L15: =AVERAGE(J15:K15) -> 37.6
B16: 당기순이익 | C16: 75.4 | D16: 74.2 | E16: =E14 -> 97.547381 | F16: =F14 -> 147.35008 | H16: 기타유동부채 | I16: 5.3 | J16: 4.6 | K16: 5.3 | L16: =K16 -> 5.3 | P16: Change in Net Working Capital | R16: 2022 | S16: 2023 | T16: 2024 | U16: 2025
B17: 지배주주 | C17: =C16 -> 75.4 | D17: =D16 -> 74.2 | E17: =E16 -> 97.547381 | F17: =F16 -> 147.35008 | H17: 비유동부채 | I17: =SUM(I18:I19) -> 65.6 | J17: =SUM(J18:J19) -> 62.7 | K17: =SUM(K18:K19) -> 26.8 | L17: =SUM(L18:L19) -> 53.966667 | Q17: 매출채권 | R17: =I5 -> 8.4 | S17: =J5 -> 18.2 | T17: =T26*E3/365 -> 19.09926 | U17: =U26*F3/365 -> 25.906037
B18: 비지배주주 | C18: 0 | D18: 0 | E18: 0 | F18: 0 | H18: 장기금융부채 | I18: 64.4 | J18: 62 | K18: 11.5 | L18: =AVERAGE(I18:K18) -> 45.966667 | Q18: 재고자산 | R18: =I6 -> 23.9 | S18: =J6 -> 19.4 | T18: =T27*E4/365 -> 4.8819726 | U18: =U27*F4/365 -> 7.8278969
B19: 총포괄이익 | C19: 75.4 | D19: 74.3 | E19: =E16 -> 97.547381 | F19: =F16 -> 147.35008 | H19: 기타비유동부채 | I19: 1.2 | J19: 0.7 | K19: 15.3 | L19: =AVERAGE(J19:K19) -> 8 | Q19: 영업용 유동자산 | R19: =SUM(R17:R18) -> 32.3 | S19: =SUM(S17:S18) -> 37.6 | T19: =SUM(T17:T18) -> 23.981233 | U19: =SUM(U17:U18) -> 33.733934
B20: 지배주주 | C20: =C19 -> 75.4 | D20: =D19 -> 74.3 | E20: =E19 -> 97.547381 | F20: =F19 -> 147.35008 | H20: 부채총계 | I20: =SUM(I17,I13) -> 101.8 | J20: =SUM(J17,J13) -> 91.9 | K20: =SUM(K17,K13) -> 155.7 | L20: =SUM(L17,L13) -> 99.776726 | Q20: 매입채무 | R20: =I14 -> 2.1 | S20: =J14 -> 2.3 | T20: =K14 -> 17.2 | U20: =U28*F4/365 -> 2.9100593
B21: 비지배주주 | C21: 0 | D21: 0 | E21: 0 | F21: 0 | H21: 지배주주지분 | I21: 229.6 | J21: 283.5 | K21: 454 | L21: =K21+(L24-K24) -> 593.15008 | Q21: 영업용 유동부채 | R21: =SUM(R20) -> 2.1 | S21: =SUM(S20) -> 2.3 | T21: =SUM(T20) -> 17.2 | U21: =SUM(U20) -> 2.9100593
B22: EBITDA | C22: 72.8 | D22: 93.9 | E22: =E8+E31 -> 127.2 | F22: =F8+F31 -> 192.56428 | H22: 자본금 | I22: 6.5 | J22: 6.5 | K22: 6.7 | L22: =K22 -> 6.7 | P22: 순운전자본 | R22: =R19-R21 -> 30.2 | S22: =S19-S21 -> 35.3 | T22: =T19-T21 -> 6.7812329 | U22: =U19-U21 -> 30.823875
B23: FCF | C23: 27 | D23: 60 | E23: =T14 -> 112.41877 | F23: =U14 -> 146.4059 | H23: 자본잉여금 | I23: 24.2 | J23: 24.2 | K23: 106.3 | L23: =AVERAGE(I23:K23) -> 51.566667 | P23: 순운전자본의 변동 | R23: =8.3 -> 8.3 | S23: =S22-R22 -> 5.1 | T23: =T22-S22 -> -28.518767 | U23: =U22-T22 -> 24.042642
B24: EBITDA 마진율 (%) | C24: =C22/C3*100 -> 51.339915 | D24: =D22/D3*100 -> 52.137701 | E24: =E22/E3*100 -> 52.367229 | F24: =F22/F3*100 -> 54.167167 | H24: 이익잉여금 | I24: 204.2 | J24: 271 | K24: 336 | L24: =K24+(F16+F46) -> 475.15008 | P24: Ratio & Assumption
B25: 영업이익률 (%) | C25: =C8/C3*100 -> 48.589563 | D25: =D8/D3*100 -> 49.750139 | E25: =E8/E3*100 -> 50.391107 | F25: =F8/F3*100 -> 52.151899 | H25: 비지배주주지분 | I25: 0 | J25: 0 | K25: 0 | L25: 0 | P25: 회전일수
B26: 지배주주귀속 순이익률 (%) | C26: =C16/C3*100 -> 53.173484 | D26: =D16/D3*100 -> 41.199334 | E26: =E16/E3*100 -> 40.159481 | F26: =F16/F3*100 -> 41.448688 | H26: 자본총계 | I26: =SUM(I25,I21) -> 229.6 | J26: =SUM(J25,J21) -> 283.5 | K26: =SUM(K25,K21) -> 454 | L26: =SUM(L25,L21) -> 593.15008 | Q26: 매출채권회전일수 | R26: =I41 -> 13.619403 | S26: =J41 -> 24.496644 | T26: 28.7 | U26: =AVERAGE(S26:T26) -> 26.598322 | W26: =1-S26/R26 -> -0.79865772
Q27: 재고자산회전일수 | R27: =I42 -> 51.408451 | S27: =J42 -> 43.452381 | T27: 34.4 | U27: =AVERAGE(S27:T27) -> 38.92619
B28: 예상 현금흐름표 (요약) (십억원) | C28: 2022 | D28: 2023 | E28: 2024E | F28: 2025E | H28: 예상 주당가치 및 valuation (요약) | I28: 2022 | J28: 2023 | K28: 2024E | L28: 2025E | Q28: 매입채무회전일수 | R28: =I43 -> 6.25 | S28: =J43 -> 11.442006 | T28: 17.5 | U28: =AVERAGE(S28:T28) -> 14.471003
B29: 영업활동으로 인한 현금흐름 | C29: =54.7 -> 54.7 | D29: 64.7 | E29: 102.7 | F29: =SUM(F30:F37) -> 118.68926 | H29: P/E (x) | I29: 15.81 | J29: 32.94 | K29: 31.41 | L29: =$W$44/L32 -> 25.82882 | Q29: 현금전환주기 | R29: =SUM(R26:R27)-R28 -> 58.777854 | S29: =SUM(S26:S27)-S28 -> 56.507019 | T29: =SUM(T26:T27)-T28 -> 45.6 | U29: =SUM(U26:U27)-U28 -> 51.053509
B30: 당기순이익 | C30: =C16 -> 75.4 | D30: =D16 -> 74.2 | E30: =E16 -> 97.547381 | F30: =F16 -> 147.35008 | H30: P/B (x) | I30: 5.16 | J30: 8.52 | K30: 6.88 | L30: =$W$44/L33 -> 6.4163841
B31: 감가상각비 | C31: 3.2 | D31: 3.7 | E31: 4.8 | F31: =U34 -> 7.1642779 | H31: EV/EBITDA (x) | I31: 15.78 | J31: 25.28 | K31: 23.56 | L31: =W38/F22 -> 18.778145 | P31: Net Capex | R31: 2022 | S31: 2023 | T31: 2024 | U31: 2025
B32: 외화환산손실(이익) | C32: -0.8 | D32: -2.2 | E32: -12.8 | F32: =AVERAGE(C32:E32) -> -5.2666667 | H32: EPS (원) | I32: 1164 | J32: 1146 | K32: 1517 | L32: =F16*1000000000/W35 -> 2249.4253 | Q32: 기초 유무형자산 | R32: =R34+R35-R33 -> 80.4 | S32: =R35 -> 104.2 | T32: =S35 -> 139 | U32: =T35 -> 138.9
B33: 자산처분손실(이익) | C33: -30 | D33: -16 | E33: -11 | F33: =AVERAGE(C33:E33) -> -19 | H33: BPS (원) | I33: 3564 | J33: 4430 | K33: 6930 | L33: =L26*1000000000/W35 -> 9054.9442 | Q33: Capex | R33: 27 | S33: 4 | T33: 4.7 | U33: =U39*F3 -> 7.3871851
B34: 지분법, 관계기업손실(이익) | C34: 0 | D34: 0 | E34: 1.1 | F34: 0 | H34: DPS (원) | I34: 116 | J34: 200 | K34: 257 | L34: 550 | Q34: 감가상각비 | R34: 3.2 | S34: 3.7 | T34: 4.8 | U34: =F$3*U40 -> 7.1642779 | W34: 주식수
B35: 운전자본변동 | C35: -8 | D35: -5 | E35: 29 | F35: =-U23 -> -24.042642 | H35: 배당성향 (%) | I35: 9.91 | J35: 17.24 | K35: 17.2 | L35: =-F46/F16*100 -> 5.5649782 | Q35: 기말 유형자산 | R35: =I10 -> 104.2 | S35: =J10 -> 139 | T35: =T32+T33-T34 -> 138.9 | U35: =T32 -> 139 | W35: 65505659
B36: 법인세납부 | C36: -1 | D36: -2.8 | E36: -2.1 | F36: =-F13 -> 4.2 | H36: 배당수익률 (%) | I36: 0.5 | J36: 0.5 | K36: 0.5 | L36: =-F46/W42*100 -> 0.21511018 | P36: Net Capex | R36: =R33+R34 -> 30.2 | S36: =S33+S34 -> 7.7 | T36: =T33+T34 -> 9.5 | U36: =U33+U34 -> 14.551463
B37: 기타 | C37: =C29-SUM(C30:C36) -> 15.9 | D37: =D29-SUM(D30:D36) -> 12.8 | E37: =E29-SUM(E30:E36) -> -3.8473805 | F37: =AVERAGE(C37:E37) -> 8.2842065 | H37: 매출액증가율 (%) | I37: =(1418/1006-1)*100 -> 40.954274 | J37: =(D3/C3-1)*100 -> 27.009873 | K37: =(E3/D3-1)*100 -> 34.869517 | L37: =(F3/E3-1)*100 -> 46.356525 | P37: Ratio & Assumption | W37: ev
B38: 투자활동으로 인한 현금흐름 | C38: -92 | D38: -48.2 | E38: -82.5 | F38: =SUM(F39:F42) -> -66.325 | H38: EBITDA증가율 (%) | I38: 34.2 | J38: 29 | K38: =(E22/D22-1)*100 -> 35.463259 | L38: =(F22/E22-1)*100 -> 51.387011 | Q38: % Net Capex / Sales | R38: =R36/C3 -> 0.21297602 | S38: =S36/D3 -> 0.042754026 | T38: =T36/E3 -> 0.039110745 | U38: =U36/F3 -> 0.040932385 | W38: =W42-J4-J9-J7 -> 3616
B39: 유형자산처분(취득) | C39: -27.5 | D39: -4.5 | E39: -4.1 | F39: =AVERAGE(D39:E39) -> -4.3 | H39: 조정영업이익증가율 (%) | I39: 33.2 | J39: 30 | K39: =(E8/D8-1)*100 -> 36.607143 | L39: =(F8/E8-1)*100 -> 51.470588 | Q39: % Capex / Sales | R39: =R33/C3 -> 0.19040903 | S39: =S33/D3 -> 0.022209883 | T39: =T33/E3 -> 0.019349527 | U39: =AVERAGE(S39:T39) -> 0.020779705
B40: 무형자산감소(증가) | C40: -5.2 | D40: -16.4 | E40: -67.1 | F40: =AVERAGE(C40:E40) -> -29.566667 | H40: EPS증가율 (%) | I40: 71.9 | J40: -1.5 | K40: =(E16/D16-1)*100 -> 31.465472 | L40: =(F16/E16-1)*100 -> 51.054886 | Q40: % D&A / Sales | R40: =R34/C3 -> 0.022566996 | S40: =S34/D3 -> 0.020544142 | T40: =T34/E3 -> 0.019761219 | U40: =AVERAGE(S40:T40) -> 0.02015268
B41: 장단기금융자산의 감소(증가) | C41: 0.4 | D41: 1.1 | E41: =AVERAGE(C41:D41) -> 0.75 | F41: =AVERAGE(D41:E41) -> 0.925 | H41: 매출채권 회전일수 | I41: =365/26.8 -> 13.619403 | J41: =365/14.9 -> 24.496644 | K41: =365/12.7 -> 28.740157 | L41: =U26 -> 26.598322 | Q41: % Capex / D&A | R41: =R34/R35 -> 0.030710173 | S41: =S34/S35 -> 0.026618705 | T41: =T34/T35 -> 0.034557235 | U41: =U34/U35 -> 0.051541567 | W41: 시총
B42: 기타투자활동 | C42: =C38-SUM(C39:C41) -> -59.7 | D42: =D38-SUM(D39:D41) -> -28.4 | E42: =E38-SUM(E39:E41) -> -12.05 | F42: =AVERAGE(C42:E42) -> -33.383333 | H42: 재고자산 회전일수 | I42: =365/7.1 -> 51.408451 | J42: =365/8.4 -> 43.452381 | K42: =365/10.6 -> 34.433962 | L42: =U27 -> 38.92619 | W42: 3812
B43: 재무활동으로 인한 현금흐름 | C43: 21.1 | D43: -25.6 | E43: -16.7 | F43: =SUM(F44:F47) -> -18.55 | H43: 매입채무 회전일수 | I43: =365/58.4 -> 6.25 | J43: =365/31.9 -> 11.442006 | K43: =365/20.9 -> 17.464115 | L43: =U28 -> 14.471003 | W43: 주가
B44: 장기차입금의 증가 | C44: 69 | D44: 0 | E44: 0 | F44: 0 | H44: ROA (%) | I44: =C16/I12*100 -> 22.751961 | J44: =D16/J12*100 -> 19.765583 | K44: =E16/K12*100 -> 16.033429 | L44: =F16/L12*100 -> 22.676414 | W44: 58100
B45: 단기차입금 상환 | C45: -37.2 | D45: -2.4 | E45: -2.9 | F45: =AVERAGE(D45:E45) -> -2.65 | H45: ROE (%) | I45: =C16/I26*100 -> 32.839721 | J45: =D16/J26*100 -> 26.17284 | K45: =E16/K26*100 -> 21.486207 | L45: =F16/L26*100 -> 24.841956
B46: 배당금의 지급 | C46: -4.3 | D46: -7.5 | E46: -12.8 | F46: =AVERAGE(C46:E46) -> -8.2 | H46: ROIC (%) | I46: 31.4 | J46: 33.3 | K46: =T8/(K5+K6+K10)*100 -> 43.005558 | L46: =U8/(L5+L6+L10)*100 -> 81.521523
B47: 기타재무활동 | C47: =C43-SUM(C44:C46) -> -6.4 | D47: =D43-SUM(D44:D46) -> -15.7 | E47: =E43-SUM(E44:E46) -> -1 | F47: =AVERAGE(C47:E47) -> -7.7 | H47: 부채비율 (%) | I47: =I20/I12*100 -> 30.718165 | J47: =J20/J12*100 -> 24.480554 | K47: =K20/K12*100 -> 25.591716 | L47: =L20/L12*100 -> 15.355121
B48: 현금의 증가 | C48: -16.2 | D48: -9.1 | E48: 3.4 | F48: =SUM(F43,F38,F29) -> 33.81426 | H48: 유동비율 (%) | I48: =I3/I13*100 -> 408.28729 | J48: =J3/J13*100 -> 635.9589 | K48: =K3/K13*100 -> 181.69123 | L48: =L3/L13*100 -> 795.00985
B49: 기초현금 | C49: 42.2 | D49: 25.4 | E49: 17.7 | F49: =E50 -> 21.1 | H49: 이자보상배율(%) | I49: 26.4 | J49: 45.8 | K49: 37 | L49: 31.3
B50: 기말현금 | C50: 25.4 | D50: 17.7 | E50: =E49+E48 -> 21.1 | F50: =F49+F48 -> 54.91426 | H50: 자기자본비율 (%) | I50: =I26/I12*100 -> 69.281835 | J50: =J26/J12*100 -> 75.519446 | K50: =K26/K12*100 -> 74.621959 | L50: =L26/L12*100 -> 91.282721

Sheet Row data ▶
A3: 클래시스(214150.KQ)_PER
A5: Estimate Sheets >>>
C7: Chungang-Univ. Financial Institute
C8: R.F.S .
C9: Valuation Model
C19: RFS 정식 회원 외 본 가치평가 모델의 무단 사용 및 수정을 금하며, 본 양식의 원 저작권은 중앙대학교 R.F.S. 학회에 있음을 밝힙니다.
C20: 원 제작자: 28기 김 건 (zzkan103@gmail.com)
C21: 1st Version: 2021.03.02

Sheet IS(Quarterly)
B1: Last Refresh: 2025-03-25 19:46:30
A2: Financial Statements
A3: 기업 | B3: A214150(클래시스) - Fiscal Month:12, 201412부터 IFRS 적용
A4: 회계유형 | B4: 연결 | C4: 회계기준 | D4: IFRS
A5: 리포트 | B5: 손익계산서 | C5: New
A6: 형식 | B6: 약식(COMPARE)
A7: 출력 | B7: 당분기 | C7: 백만원
A8: 회계연도 | B8: 2022 | C8: Current
A9: 계정코드 | B9: 계정명 | C9: 단위 | D9: 202203(1Q) | E9: 202206(2Q) | F9: 202209(3Q) | G9: 202212(4Q) | H9: 202303(1Q) | I9: 202306(2Q) | J9: 202309(3Q) | K9: 202312(4Q) | L9: 202403(1Q) | M9: 202406(2Q) | N9: 202409(3Q)
D10: IFRS(연결) | E10: IFRS(연결) | F10: IFRS(연결) | G10: IFRS(연결) | H10: IFRS(연결) | I10: IFRS(연결) | J10: IFRS(연결) | K10: IFRS(연결) | L10: IFRS(연결) | M10: IFRS(연결) | N10: IFRS(연결)
A11: 4001210000 | B11: 매출액(수익)(*) | C11: 백만원 | D11: 35381.924 | E11: 32684.579 | F11: 33268.981 | G11: 40467.758 | H11: 38974.116 | I11: 45897.817 | J11: 48246.061 | K11: 47004.804 | L11: 50379.745 | M11: 58742.16 | N11: 59413.229
A12: 4001210010 | B12: *수출(*) | C12: 백만원 | K12: 117063.15 | L12: 33649.947 | M12: 40319.8 | N12: 40225.008
A13: 4001210020 | B13: *내수 | C13: 백만원 | K13: 63059.649 | L13: 16729.799 | M13: 18422.358 | N13: 19188.222
A14: 4001210320 | B14: 매출원가(*) | C14: 백만원 | D14: 8800.3212 | E14: 8277.4647 | F14: 7317.0074 | G14: 9241.4253 | H14: 8763.6302 | I14: 9577.5275 | J14: 11233.861 | K14: 10098.715 | L14: 10176.868 | M14: 11227.806 | N14: 12814.133
A15: 4001210780 | B15: 매출총이익(손실) | C15: 백만원 | D15: 26581.603 | E15: 24407.115 | F15: 25951.974 | G15: 31226.333 | H15: 30210.486 | I15: 36320.29 | J15: 37012.2 | K15: 36906.089 | L15: 40202.877 | M15: 47514.354 | N15: 46599.096
A16: 4001290000 | B16: 판매비와관리비(*) | C16: 백만원 | D16: 9876.7234 | E16: 9144.9526 | F16: 8471.9288 | G16: 11797.212 | H16: 10318.628 | I16: 13174.374 | J16: 12348.212 | K16: 14985.469 | L16: 13694.299 | M16: 16325.518 | N16: 17648.23
A17: 4001290010 | B17: 인건비(*) | C17: 백만원 | D17: 3229.38 | E17: 2955.072 | F17: 3366.307 | G17: 2853.451 | H17: 2596.345 | I17: 3480.812 | J17: 3569.214 | K17: 3736.938 | L17: 3695.08 | M17: 3980.98 | N17: 4428.383
A18: 4001290020 | B18: 유무형자산상각비(*) | C18: 백만원 | D18: 407.307 | E18: 413.732 | F18: 322.005 | G18: 450.069 | H18: 492.815 | I18: 529.558 | J18: 580.456 | K18: 621.568 | L18: 649.772 | M18: 664.285 | N18: 687.963
A19: 4001211300 | B19: 연구개발비 | C19: 백만원 | D19: 1092.835 | E19: 1018.42 | F19: 1003.531 | G19: 1314.991 | H19: 2115.663 | I19: 2282.4 | J19: 2213.294 | K19: 2589.286 | L19: 2799.651 | M19: 2824.206 | N19: 3075.951
A20: 4001211060 | B20: 광고선전비 | C20: 백만원 | D20: 1609.318 | E20: 2002.194 | F20: 1112.29 | G20: 1190.385 | H20: 1318.646 | I20: 3702.874 | J20: 1466.42 | K20: 2541.798 | L20: 2227.27 | M20: 2516.354 | N20: 4737.623
A21: 4001290040 | B21: 판매비(*) | C21: 백만원 | D21: 2221.012 | E21: 1448.646 | F21: 1120.217 | G21: 1762.989 | H21: 1309.455 | I21: 1608.096 | J21: 1817.497 | K21: 2165.973 | L21: 1732.913 | M21: 2459.651 | N21: 1622.493
A22: 4001290090 | B22: 관리비(*) | C22: 백만원 | D22: 1316.871 | E22: 1306.889 | F22: 1547.579 | G22: 4225.326 | H22: 2481.459 | I22: 1563.466 | J22: 2691.291 | K22: 3319.82 | L22: 2573.247 | M22: 3861.465 | N22: 3081.968
A23: 4001290110 | B23: 기타원가성비용(*) | C23: 백만원
A24: 4001211420 | B24: 기타 | C24: 백만원 | H24: 4.245 | I24: 7.168 | J24: 10.04 | K24: 10.085 | L24: 16.366 | M24: 18.577 | N24: 13.849
A25: 4001211430 | B25: 영업이익(손실) | C25: 백만원 | D25: 16704.879 | E25: 15262.162 | F25: 17480.045 | G25: 19429.121 | H25: 19891.858 | I25: 23145.916 | J25: 24663.988 | K25: 21920.619 | L25: 26508.578 | M25: 31188.836 | N25: 28950.866
A26: 4001290120 | B26: 금융수익(*) | C26: 백만원 | D26: 704.01 | E26: 2974.952 | F26: 5432.017 | G26: -6526.859 | H26: 4394.451 | I26: 2027.676 | J26: 4088.313 | K26: -1850.126 | L26: 6484.52 | M26: 4854.464 | N26: -3059.722
A27: 4001290750 | B27: 이자수익 | C27: 백만원 | D27: 9.954 | E27: 18.441 | F27: 79.262 | G27: 664.458 | H27: 934.555 | I27: 1139.498 | J27: 1277.244 | K27: 1276.569 | L27: 1340.199 | M27: 1151.098 | N27: 1161.075
A28: 4001290760 | B28: 배당금수익 | C28: 백만원
A29: 4001211480 | B29: 외환이익(*) | C29: 백만원 | D29: 694.056 | E29: 2956.511 | F29: 5352.755 | G29: -7389.952 | H29: 3264.211 | I29: 678.856 | J29: 2579.921 | K29: -3616.612 | L29: 4829.809 | M29: 3414.367 | N29: -4510.791
A30: 4001211520 | B30: 대손충당금환입액 | C30: 백만원
A31: 4001211600 | B31: 매출채권처분이익 | C31: 백만원
A32: 4001211605 | B32: 당기손익-공정가치측정 금융자산관련이익 | C32: 백만원
A33: 4001290130 | B33: 금융자산처분이익(*) | C33: 백만원
A34: 4001290150 | B34: 금융자산평가이익(*) | C34: 백만원 | G34: 198.635 | H34: 195.685 | I34: 209.322 | J34: 231.148 | K34: 489.917 | L34: 314.512 | M34: 288.999 | N34: 289.994
A35: 4001211720 | B35: 금융자산손상차손환입(*) | C35: 백만원
A36: 4001211680 | B36: 파생상품이익(*) | C36: 백만원
A37: 4001290170 | B37: 기타금융수익(*) | C37: 백만원
A38: 4001290180 | B38: 금융원가(*) | C38: 백만원 | D38: 792.769 | E38: 731.877 | F38: 770.954 | G38: 2380.106 | H38: 1145.475 | I38: 489.866 | J38: 999.445 | K38: 959.971 | L38: 556.172 | M38: 536.151 | N38: 2674.685
A39: 4001290770 | B39: 이자비용 | C39: 백만원 | D39: 567.608 | E39: 750.544 | F39: 769.184 | G39: 522.512 | H39: 503.852 | I39: 491.464 | J39: 465.672 | K39: 497.696 | L39: 475.783 | M39: 470.455 | N39: 470.768
A40: 4001211820 | B40: 외환손실(*) | C40: 백만원 | D40: 176.375 | E40: -18.667 | F40: 1.77 | G40: 1857.594 | H40: 641.623 | I40: -1.598 | J40: 99.204 | K40: 896.844 | L40: 80.389 | M40: 65.696 | N40: 1339.255
A41: 4001211860 | B41: 대손상각비 | C41: 백만원
A42: 4001211865 | B42: 당기손익-공정가치측정 금융자산관련손실 | C42: 백만원
A43: 4001211940 | B43: 매출채권처분손실 | C43: 백만원 | J43: 434.569 | K43: -434.569 | N43: 219.662
A44: 4001290190 | B44: 금융자산처분손실(*) | C44: 백만원
A45: 4001290210 | B45: 금융자산평가손실(*) | C45: 백만원 | D45: 48.786
A46: 4001212060 | B46: 금융자산손상차손(*) | C46: 백만원
A47: 4001212020 | B47: 파생상품손실(*) | C47: 백만원 | N47: 645
A48: 4001290230 | B48: 기타금융원가(*) | C48: 백만원
A49: 4001290240 | B49: 기타수익(*) | C49: 백만원 | D49: 2.704 | E49: 27.242 | F49: 5.43 | G49: 30338.773 | H49: 1.254 | I49: 15.486 | J49: 15.52 | K49: 17.429 | L49: 0.364 | M49: 9.545 | N49: 1.375
A50: 4001280000 | B50: 이자수익 | C50: 백만원
A51: 4001280010 | B51: 배당금수익 | C51: 백만원
A52: 4001290250 | B52: 외환이익(*) | C52: 백만원
A53: 4001280050 | B53: 재고자산감모손실환입 | C53: 백만원
A54: 4001280060 | B54: 재고자산폐기(처분)이익 | C54: 백만원
A55: 4001280065 | B55: 당기손익-공정가치측정 금융자산평가이익 | C55: 백만원
A56: 4001290260 | B56: 자산처분(폐기)이익(*) | C56: 백만원 | F56: 4.725 | G56: 30333.899 | I56: 12.999 | J56: 3.279 | K56: 0.324 | M56: 9.542 | N56: 1.363
A57: 4001280140 | B57: 자산평가이익 | C57: 백만원
A58: 4001290280 | B58: 자산손상차손환입(*) | C58: 백만원
A59: 4001290300 | B59: 파생상품이익(*) | C59: 백만원
A60: 4001280240 | B60: 임대료수익 | C60: 백만원
A61: 4001280250 | B61: 로열티수익 | C61: 백만원
A62: 4001280260 | B62: 수수료수익 | C62: 백만원
A63: 4001280270 | B63: 대손충당금환입 | C63: 백만원
A64: 4001280280 | B64: 충당부채환입액 | C64: 백만원
A65: 4001290310 | B65: 기타(*) | C65: 백만원 | D65: 2.704 | E65: 27.242 | F65: 0.705 | G65: 4.874 | H65: 1.254 | I65: 2.487 | J65: 12.241 | K65: 17.105 | L65: 0.364 | M65: 0.003 | N65: 0.012
A66: 4001290320 | B66: 기타비용(*) | C66: 백만원 | D66: 0.002 | E66: 0.24 | F66: 0.061 | G66: 400.031 | H66: 11.722 | I66: 51.324 | K66: 832.738 | L66: 345.901 | M66: 1241.228 | N66: -2.07
A67: 4001280400 | B67: 이자비용 | C67: 백만원
A68: 4001290330 | B68: 외환손실(*) | C68: 백만원
A69: 4001280440 | B69: 재고자산감모손실 | C69: 백만원
A70: 4001280450 | B70: 재고자산폐기(처분)손실 | C70: 백만원
A71: 4001280455 | B71: 당기손익-공정가치측정 금융자산평가손실 | C71: 백만원
A72: 4001290340 | B72: 자산처분(폐기)손실(*) | C72: 백만원 | D72: 0.002 | E72: 0.237 | F72: 0.002 | G72: 51.086 | H72: 6.643 | K72: 775.781 | L72: 330.399 | M72: 249.228
A73: 4001280540 | B73: 자산평가손실 | C73: 백만원
A74: 4001290360 | B74: 자산손상차손(*) | C74: 백만원
A75: 4001290380 | B75: 파생상품손실(*) | C75: 백만원 | M75: 992
A76: 4001280650 | B76: 기타대손상각비 | C76: 백만원
A77: 4001280660 | B77: 충당부채전입액 | C77: 백만원
A78: 4001290390 | B78: 기타(*) | C78: 백만원 | E78: 0.003 | F78: 0.059 | G78: 348.945 | H78: 5.079 | I78: 51.324 | K78: 56.957 | L78: 15.502 | N78: -2.07
A79: 4001290640 | B79: 종속기업,공동지배기업및관계기업관련손익(*) | C79: 백만원 | M79: 267.11147 | N79: -822.65555
A80: 4001290650 | B80: 지분법손익(*) | C80: 백만원 | N80: -822.65555
A81: 4001290680 | B81: 종속기업,공동지배기업및관계기업투자주식처분손익(*) | C81: 백만원
A82: 4001290710 | B82: 종속기업,공동지배기업및관계기업투자주식손상관련손익(*) | C82: 백만원
A83: 4001290740 | B83: 기타(*) | C83: 백만원 | M83: 267.11147
A84: 4001212380 | B84: 법인세비용차감전계속사업이익 | C84: 백만원 | D84: 16618.822 | E84: 17532.24 | F84: 22146.476 | G84: 40460.899 | H84: 23130.366 | I84: 24647.888 | J84: 27768.376 | K84: 18295.214 | L84: 32091.389 | M84: 34542.577 | N84: 22397.247
A85: 4001212390 | B85: 법인세비용 | C85: 백만원 | D85: 3802.2583 | E85: 3724.2453 | F85: 3430.2591 | G85: 10423.027 | H85: 4355.187 | I85: 6089.3659 | J85: 6574.9536 | K85: 2597.1347 | L85: 6001.47 | M85: 7961.878 | N85: 5908.5838
A86: 4001212400 | B86: 종속회사매수일전순손익 | C86: 백만원
A87: 4001212410 | B87: 처분된종속회사순손익 | C87: 백만원
A88: 4001212420 | B88: 계속영업이익(손실) | C88: 백만원 | D88: 12816.564 | E88: 13807.994 | F88: 18716.217 | G88: 30037.872 | H88: 18775.179 | I88: 18558.523 | J88: 21193.422 | K88: 15698.08 | L88: 26089.919 | M88: 26580.699 | N88: 16488.664
A89: 4001212430 | B89: 중단영업이익(손실) | C89: 백만원
A90: 4001212450 | B90: 당기순이익(손실) | C90: 백만원 | D90: 12816.564 | E90: 13807.994 | F90: 18716.217 | G90: 30037.872 | H90: 18775.179 | I90: 18558.523 | J90: 21193.422 | K90: 15698.08 | L90: 26089.919 | M90: 26580.699 | N90: 16488.664
A91: 4001220000 | B91: 기타포괄손익(*) | C91: 백만원 | D91: 17.89674 | E91: 21.09476 | F91: 39.49054 | G91: -63.25968 | H91: 38.23175 | I91: -14.30068 | J91: 15.34422 | K91: -14.47489 | L91: 24.25222 | M91: 21.62569 | N91: -15.58477
A92: 4001220120 | B92: 총포괄손익 | C92: 백만원 | D92: 12834.46 | E92: 13829.089 | F92: 18755.708 | G92: 29974.612 | H92: 18813.41 | I92: 18544.222 | J92: 21208.766 | K92: 15683.605 | L92: 26114.171 | M92: 26602.325 | N92: 16473.079
A93: 4001230000 | B93: (당기순손익귀속)지배기업주주지분 | C93: 백만원 | D93: 12816.564 | E93: 13807.994 | F93: 18716.217 | G93: 30037.872 | H93: 18775.179 | I93: 18558.523 | J93: 21193.422 | K93: 15698.08 | L93: 26089.919 | M93: 26580.699 | N93: 16488.664
A94: 4001230030 | B94: (당기순손익귀속)비지배주주지분 | C94: 백만원
A95: 4001230060 | B95: (총포괄손익귀속)지배기업주주지분 | C95: 백만원 | D95: 12834.46 | E95: 13829.089 | F95: 18755.708 | G95: 29974.612 | H95: 18813.41 | I95: 18544.222 | J95: 21208.766 | K95: 15683.605 | L95: 26114.171 | M95: 26602.325 | N95: 16473.079
A96: 4001230070 | B96: (총포괄손익귀속)비지배주주지분 | C96: 백만원
A97: 4001230080 | B97: 주당계속영업이익 | C97: 원 | D97: 198 | E97: 213 | F97: 289 | G97: 465 | H97: 292 | I97: 288 | J97: 329 | K97: 246 | L97: 408 | M97: 415 | N97: 258
A98: 4001230090 | B98: 주당순손익 | C98: 원 | D98: 198 | E98: 213 | F98: 289 | G98: 465 | H98: 292 | I98: 288 | J98: 329 | K98: 246 | L98: 408 | M98: 415 | N98: 258
A99: 4001230100 | B99: 희석주당계속영업이익 | C99: 원 | J99: 328 | K99: 824 | L99: 406 | M99: 413 | N99: 257
A100: 4001230110 | B100: 희석주당순손익 | C100: 원 | J100: 328 | K100: 824 | L100: 406 | M100: 413 | N100: 257
...

Sheet BS(Quarterly)
B1: Last Refresh: 2025-03-25 19:46:58
A2: Financial Statements
A3: 기업 | B3: A214150(클래시스) - Fiscal Month:12, 201412부터 IFRS 적용
A4: 회계유형 | B4: 연결 | C4: 회계기준 | D4: IFRS
A5: 리포트 | B5: 재무상태표 | C5: New
A6: 형식 | B6: 약식(COMPARE)
A7: 출력 | B7: 당분기 | C7: 백만원
A8: 회계연도 | B8: 2022 | C8: Current
A9: 계정코드 | B9: 계정명 | C9: 단위 | D9: 202203(1Q) | E9: 202206(2Q) | F9: 202209(3Q) | G9: 202212(4Q) | H9: 202303(1Q) | I9: 202306(2Q) | J9: 202309(3Q) | K9: 202312(4Q) | L9: 202403(1Q) | M9: 202406(2Q) | N9: 202409(3Q)
D10: IFRS(연결) | E10: IFRS(연결) | F10: IFRS(연결) | G10: IFRS(연결) | H10: IFRS(연결) | I10: IFRS(연결) | J10: IFRS(연결) | K10: IFRS(연결) | L10: IFRS(연결) | M10: IFRS(연결) | N10: IFRS(연결)
A11: 4001190010 | B11: 자산(*) | C11: 백만원 | D11: 304075.81 | E11: 312182.55 | F11: 334294.16 | G11: 331411.11 | H11: 352378.26 | I11: 359536.77 | J11: 363110.05 | K11: 375443.02 | L11: 402862.56 | M11: 418525.09 | N11: 433669.19
A12: 4001190240 | B12: 유동자산(*) | C12: 백만원 | D12: 92715.111 | E12: 101291.64 | F12: 123516.09 | G12: 147788.69 | H12: 168588.54 | I12: 171307.52 | J12: 174594.22 | K12: 185737.48 | L12: 212555.73 | M12: 187148.8 | N12: 202195.67
A13: 4001190250 | B13: 재고자산(*) | C13: 백만원 | D13: 18897.354 | E13: 22425.612 | F13: 25110.389 | G13: 23397.667 | H13: 22444.799 | I13: 22393.908 | J13: 21607.032 | K13: 19434.328 | L13: 19355.876 | M13: 17860.256 | N13: 16736.942
A14: 4001190260 | B14: 유동생물자산(*) | C14: 백만원
A15: 4001190270 | B15: 유동금융자산(*) | C15: 백만원 | D15: 1781 | E15: 21881 | F15: 19796.285 | G15: 87219.081 | H15: 117358.37 | I15: 121282.69 | J15: 116870.06 | K15: 119501.66 | L15: 108304.49 | M15: 111047.03 | N15: 145489.15
A16: 4001190300 | B16: 매출채권및기타유동채권(*) | C16: 백만원 | D16: 5994.478 | E16: 5349.6292 | F16: 8579.132 | G16: 8437.622 | H16: 11746.179 | I16: 14297.198 | J16: 18206.947 | K16: 18162.51 | L16: 24382.318 | M16: 32243.455 | N16: 33227.051
A17: 4001113900 | B17: 당기법인세자산(선급법인세) | C17: 백만원 | D17: 24.95822 | E17: 26.65055 | F17: 29.57553 | G17: 24.52732 | H17: 25.23375 | I17: 26.89875 | J17: 203.45596 | K17: 25.52638 | L17: 26.6406 | M17: 27.46969 | N17: 26.15808
A18: 4001180995 | B18: 계약자산(**) | C18: 백만원
A19: 4001113903 | B19: 반품(환불)자산 | C19: 백만원
A20: 4001113904 | B20: 배출권 | C20: 백만원
A21: 4001190340 | B21: 기타유동자산(*) | C21: 백만원 | D21: 8540.7059 | E21: 3564.5272 | F21: 3332.3225 | G21: 2705.3075 | H21: 3831.1789 | I21: 3222.8783 | J21: 10766.059 | K21: 10277.254 | L21: 9879.9717 | M21: 1697.3777 | N21: 3526.2995
A22: 4001190370 | B22: 현금및현금성자산(*) | C22: 백만원 | D22: 57476.614 | E22: 48044.219 | F22: 66668.39 | G22: 26004.485 | H22: 13182.789 | I22: 10083.953 | J22: 6940.666 | K22: 18336.205 | L22: 50606.435 | M22: 24273.217 | N22: 3190.069
A23: 4001114130 | B23: 매각예정비유동자산및처분자산집단(*) | C23: 백만원
A24: 4001190020 | B24: 비유동자산(*) | C24: 백만원 | D24: 211360.7 | E24: 210890.91 | F24: 210778.07 | G24: 183622.42 | H24: 183789.71 | I24: 188229.25 | J24: 188515.83 | K24: 189705.54 | L24: 190306.83 | M24: 231376.29 | N24: 231473.52
A25: 4001190030 | B25: 유형자산(*) | C25: 백만원 | D25: 104563.8 | E25: 132475.07 | F25: 131988.2 | G25: 104241.59 | H25: 121179 | I25: 121940.52 | J25: 125210.87 | K25: 138988.71 | L25: 143523.98 | M25: 143385.58 | N25: 150171.23
A26: 4001190070 | B26: 무형자산(*) | C26: 백만원 | D26: 1214.577 | E26: 1368.981 | F26: 1456.995 | G26: 1478.37 | H26: 1644.948 | I26: 1945.869 | J26: 2336.794 | K26: 2822.297 | L26: 4575.238 | M26: 6514.283 | N26: 7605.381
A27: 4001190110 | B27: 비유동생물자산(*) | C27: 백만원
A28: 4001190120 | B28: 투자부동산(*) | C28: 백만원 | D28: 103467.48 | E28: 74917.255 | F28: 74762.03 | G28: 74654.142 | H28: 57707.046 | I28: 57623.529 | J28: 54579.835 | K28: 41087.737 | L28: 36270.455 | M28: 36217.657 | N28: 29487.665
A29: 4001190130 | B29: 장기금융자산(*) | C29: 백만원 | D29: 1447.6804 | E29: 1385.356 | F29: 1584.0399 | G29: 1369.6593 | H29: 1355.51 | I29: 5026.7076 | J29: 4753.4536 | K29: 4207.6556 | L29: 3536.3856 | M29: 4082.6756 | N29: 3711.1356
A30: 4001111660 | B30: 관계기업등지분관련투자자산(*) | C30: 백만원 | M30: 39124.213 | N30: 38303.347
A31: 4001190160 | B31: 장기매출채권및기타비유동채권(*) | C31: 백만원
A32: 4001112490 | B32: 이연법인세자산 | C32: 백만원 | G32: 788.00773 | H32: 797.83571 | I32: 217.46076 | J32: 217.46076 | K32: 1381.8307 | L32: 1381.8307 | M32: 1169.6126 | N32: 1359.2326
A33: 4001112500 | B33: 장기당기법인세자산 | C33: 백만원
A34: 4001180575 | B34: 계약자산(**) | C34: 백만원
A35: 4001112503 | B35: 반품(환불)자산 | C35: 백만원
A36: 4001112504 | B36: 배출권 | C36: 백만원
A37: 4001190200 | B37: 기타비유동자산(*) | C37: 백만원 | D37: 667.17364 | E37: 744.2542 | F37: 986.79747 | G37: 1090.6441 | H37: 1105.3705 | I37: 1475.1588 | J37: 1417.4188 | K37: 1217.3038 | L37: 1018.9436 | M37: 882.26793 | N37: 835.52929
A38: 4001112880 | B38: 기타금융업자산 | C38: 백만원
A39: 4001190440 | B39: 부채(*) | C39: 백만원 | D39: 131659.39 | E39: 125937.04 | F39: 132548.08 | G39: 101857.25 | H39: 111471.35 | I39: 99556.265 | J39: 91940.688 | K39: 91942.522 | L39: 105627.4 | M39: 93593.966 | N39: 91694.122
A40: 4001190610 | B40: 유동부채(*) | C40: 백만원 | D40: 28639.067 | E40: 23830.714 | F40: 30950.188 | G40: 36225.225 | H40: 46341.958 | I40: 34842.198 | J40: 28294.889 | K40: 29246.387 | L40: 105042.7 | M40: 93051.083 | N40: 91165.17
A41: 4001181470 | B41: 단기사채(**) | C41: 백만원
A42: 4001121700 | B42: 단기차입금(*) | C42: 백만원 | E42: 2400
A43: 4001190620 | B43: 유동성장기부채(*) | C43: 백만원 | D43: 2400 | F43: 2400 | G43: 2400 | H43: 2400 | I43: 2400 | J43: 2600 | K43: 2400 | L43: 63800 | M43: 63200 | N43: 62600
A44: 4001190630 | B44: 유동금융부채(*) | C44: 백만원 | D44: 481.78481 | E44: 479.70976 | F44: 536.50388 | G44: 557.30324 | H44: 561.09968 | I44: 776.72406 | J44: 804.78166 | K44: 739.36938 | L44: 677.20358 | M44: 580.89419 | N44: 553.40617
A45: 4001190660 | B45: 매입채무및기타유동채무(*) | C45: 백만원 | D45: 11311.295 | E45: 5969.282 | F45: 7965.945 | G45: 8570.101 | H45: 15379.224 | I45: 8397.252 | J45: 11243.934 | K45: 9607.711 | L45: 21606.479 | M45: 11798.183 | N45: 12514.356
A46: 4001190680 | B46: 유동종업원급여충당부채(*) | C46: 백만원
A47: 4001122460 | B47: 기타단기충당부채(*) | C47: 백만원 | D47: 903.98603 | E47: 947.98933 | F47: 1080.8322 | G47: 1225.9501 | H47: 1102.3744 | I47: 1214.7489 | J47: 1319.069 | K47: 1382.8205 | L47: 1328.667 | M47: 1429.283 | N47: 1534.8468
A48: 4001122560 | B48: 당기법인세부채(미지급법인세) | C48: 백만원 | D48: 7204.8423 | E48: 7508.6095 | F48: 6609.5542 | G48: 18158.545 | H48: 22372.973 | I48: 17544.983 | J48: 7499.4959 | K48: 10482.475 | L48: 11927.342 | M48: 12515.592 | N48: 9333.4812
A49: 4001122561 | B49: 계약부채 | C49: 백만원
A50: 4001122562 | B50: 반품(환불)부채 | C50: 백만원
A51: 4001122563 | B51: 배출부채 | C51: 백만원
A52: 4001190690 | B52: 기타유동부채(*) | C52: 백만원 | D52: 6337.159 | E52: 6525.123 | F52: 12357.352 | G52: 5313.326 | H52: 4526.287 | I52: 4508.491 | J52: 4827.609 | K52: 4634.01 | L52: 5703.008 | M52: 3527.13 | N52: 4629.08
A53: 4001122680 | B53: 매각예정으로분류된처분자산집단에포함된부채(*) | C53: 백만원
A54: 4001190450 | B54: 비유동부채(*) | C54: 백만원 | D54: 103020.32 | E54: 102106.32 | F54: 101597.89 | G54: 65632.026 | H54: 65129.396 | I54: 64714.067 | J54: 63645.798 | K54: 62696.135 | L54: 584.69604 | M54: 542.88337 | N54: 528.95109
A55: 4001190460 | B55: 사채(*) | C55: 백만원
A56: 4001190470 | B56: 장기차입금(*) | C56: 백만원 | D56: 101200 | E56: 100600 | F56: 100000 | G56: 64400 | H56: 63800 | I56: 63200 | J56: 62600 | K56: 62000
A57: 4001190480 | B57: 비유동금융부채(*) | C57: 백만원 | D57: 191.29386 | E57: 270.78499 | F57: 457.16446 | G57: 541.31383 | H57: 553.68366 | I57: 708.35488 | J57: 623.37625 | K57: 488.71345 | L57: 352.27404 | M57: 310.46137 | N57: 296.52909
A58: 4001190500 | B58: 장기매입채무및기타비유동채무(*) | C58: 백만원 | D58: 1253.361 | E58: 853.134 | F58: 745.712 | G58: 690.712 | H58: 775.712 | I58: 805.712 | J58: 422.422 | K58: 207.422 | L58: 232.422 | M58: 232.422 | N58: 232.422
A59: 4001190570 | B59: 비유동종업원급여충당부채(*) | C59: 백만원
A60: 4001121280 | B60: 기타장기충당부채(*) | C60: 백만원
A61: 4001121380 | B61: 이연법인세부채 | C61: 백만원 | D61: 375.66885 | E61: 382.40359 | F61: 395.01139
A62: 4001181370 | B62: 장기당기법인세부채(미지급법인세)(**) | C62: 백만원
A63: 4001121401 | B63: 계약부채 | C63: 백만원
A64: 4001121402 | B64: 반품(환불)부채 | C64: 백만원
A65: 4001121403 | B65: 배출부채 | C65: 백만원
A66: 4001190580 | B66: 기타비유동부채(*) | C66: 백만원
A67: 4001121620 | B67: 기타금융업부채 | C67: 백만원
A68: 4001190380 | B68: 자본(*) | C68: 백만원 | D68: 172416.42 | E68: 186245.51 | F68: 201746.08 | G68: 229553.86 | H68: 240906.9 | I68: 259980.5 | J68: 271169.36 | K68: 283500.5 | L68: 297235.16 | M68: 324931.12 | N68: 341975.07
A69: 4001130010 | B69: *수권주식수 | C69: 주 | D69: 100000000 | E69: 100000000 | F69: 100000000 | G69: 100000000 | H69: 100000000 | I69: 100000000 | J69: 100000000 | K69: 100000000 | L69: 100000000 | M69: 100000000 | N69: 100000000
A70: 4001130020 | B70: *주당액면가액 | C70: 원 | D70: 100 | E70: 100 | F70: 100 | G70: 100 | H70: 100 | I70: 100 | J70: 100 | K70: 100 | L70: 100 | M70: 100 | N70: 100
A71: 4001130030 | B71: *발행한주식총수(*) | C71: 주 | D71: 64776702 | E71: 64776702 | F71: 64776702 | G71: 64776702 | H71: 64776702 | I71: 64776702 | J71: 64776702 | K71: 64776702 | L71: 63999519 | M71: 63999519 | N71: 63999519
A72: 4001130040 | B72: *보통주 | C72: 주 | D72: 64776702 | E72: 64776702 | F72: 64776702 | G72: 64776702 | H72: 64776702 | I72: 64776702 | J72: 64776702 | K72: 64776702 | L72: 63999519 | M72: 63999519 | N72: 63999519
A73: 4001130050 | B73: *우선주 | C73: 주
A74: 4001190390 | B74: 지배기업주주지분(*) | C74: 백만원 | D74: 172416.42 | E74: 186245.51 | F74: 201746.08 | G74: 229553.86 | H74: 240906.9 | I74: 259980.5 | J74: 271169.36 | K74: 283500.5 | L74: 297235.16 | M74: 324931.12 | N74: 341975.07
A75: 4001130070 | B75: 자본금(*) | C75: 백만원 | D75: 6477.6702 | E75: 6477.6702 | F75: 6477.6702 | G75: 6477.6702 | H75: 6477.6702 | I75: 6477.6702 | J75: 6477.6702 | K75: 6477.6702 | L75: 6477.6702 | M75: 6477.6702 | N75: 6477.6702
A76: 4001130670 | B76: 신종자본증권 | C76: 백만원
A77: 4001190400 | B77: 자본잉여금(*) | C77: 백만원 | D77: 24229.755 | E77: 24229.755 | F77: 24229.755 | G77: 24229.755 | H77: 24229.755 | I77: 24229.755 | J77: 24229.755 | K77: 24229.755 | L77: 24229.755 | M77: 24229.755 | N77: 24229.755
A78: 4001190420 | B78: 기타자본(*) | C78: 백만원 | F78: -3255.1378 | G78: -5421.9761 | H78: -5410.8888 | I78: -4888.807 | J78: -14908.717 | K78: -18253.886 | L78: 2166.4939 | M78: 3260.1294 | N78: 3830.9977
A79: 4001130360 | B79: 기타포괄손익누계액(*) | C79: 백만원 | D79: 40.75591 | E79: 61.85067 | F79: 101.34121 | G79: 38.08153 | H79: 76.31329 | I79: 69.31065 | J79: 84.65487 | K79: 62.88194 | L79: 87.13416 | M79: 108.76 | N79: 93.17508
A80: 4001130470 | B80: 이익잉여금(결손금)(*) | C80: 백만원 | D80: 141668.24 | E80: 155476.24 | F80: 174192.45 | G80: 204230.33 | H80: 215534.05 | I80: 234092.58 | J80: 255286 | K80: 270984.08 | L80: 264274.11 | M80: 290854.81 | N80: 307343.47
A81: 4001130640 | B81: 비지배주주지분 | C81: 백만원

Sheet CFS(Quarterly)
B1: Last Refresh: 2025-03-25 19:47:04
A2: Financial Statements
A3: 기업 | B3: A214150(클래시스) - Fiscal Month:12, 201412부터 IFRS 적용
A4: 회계유형 | B4: 연결 | C4: 회계기준 | D4: IFRS
A5: 리포트 | B5: 현금흐름표 | C5: New
A6: 형식 | B6: 약식(COMPARE)
A7: 출력 | B7: 당분기 | C7: 백만원
A8: 회계연도 | B8: 2022 | C8: Current
A9: 계정코드 | B9: 계정명 | C9: 단위 | D9: 202203(1Q) | E9: 202206(2Q) | F9: 202209(3Q) | G9: 202212(4Q) | H9: 202303(1Q) | I9: 202306(2Q) | J9: 202309(3Q) | K9: 202312(4Q) | L9: 202403(1Q) | M9: 202406(2Q) | N9: 202409(3Q)
D10: IFRS(연결) | E10: IFRS(연결) | F10: IFRS(연결) | G10: IFRS(연결) | H10: IFRS(연결) | I10: IFRS(연결) | J10: IFRS(연결) | K10: IFRS(연결) | L10: IFRS(연결) | M10: IFRS(연결) | N10: IFRS(연결)
A11: 4001390000 | B11: 영업활동으로인한현금흐름(간접법)(*) | C11: 백만원 | D11: 9083.9007 | E11: 13723.005 | F11: 16093.878 | G11: 15853.721 | H11: 16486.393 | I11: 13631.965 | J11: 2575.7079 | K11: 31937.907 | L11: 19373.27 | M11: 30645.53 | N11: 13148.509
A12: 4001310010 | B12: *(직접법)총현금유입(*) | C12: 백만원
A13: 4001310100 | B13: *(직접법)총현금유출(*) | C13: 백만원
A14: 4001310190 | B14: 당기순손익 | C14: 백만원 | D14: 12816.564 | E14: 13807.994 | F14: 18716.217 | G14: 30037.872 | H14: 18775.179 | I14: 18558.523 | J14: 21193.422 | K14: 15698.08 | L14: 26089.919 | M14: 26580.699 | N14: 16488.664
A15: 4001310200 | B15: 법인세비용차감전계속사업이익 | C15: 백만원
A16: 4001390010 | B16: 현금유출이없는비용등가산(*) | C16: 백만원 | D16: 5894.552 | E16: 5410.2021 | F16: 5780.9019 | G16: 13428.969 | H16: 7107.24 | I16: 8726.707 | J16: 9951.98 | K16: 5865.5743 | L16: 8895.935 | M16: 11982.72 | N16: 10720.63
A17: 4001390040 | B17: (현금유입이없는수익등차감)(*) | C17: 백만원 | D17: 652.114 | E17: 2615.6595 | F17: 5257.4195 | G17: 23663.243 | H17: 4150.503 | I17: 1876.819 | J17: 3946.974 | K17: -2042.4101 | L17: 6244.309 | M17: 4166.449 | N17: -4070.667
A18: 4001390060 | B18: 영업활동으로인한자산부채변동(운전자본변동)(*) | C18: 백만원 | D18: -5863.121 | E18: 1206.7335 | F18: 1878.9556 | G18: -3644.6861 | H18: -5615.7944 | I18: -1852.1682 | J18: -8824.4409 | K18: 7789.5207 | L18: -5771.4182 | M18: 2029.2847 | N18: -9547.2018
A19: 4001390070 | B19: 자산의감소(증가)(*) | C19: 백만원 | D19: -9494.042 | E19: 2163.8397 | F19: -5918.7077 | G19: 2837.4401 | H19: -4349.532 | I19: -2327.118 | J19: -11613.633 | K19: 9745.3316 | L19: -6227.135 | M19: 1214.446 | N19: -11482.352
A20: 4001390110 | B20: 부채의증가(감소)(*) | C20: 백만원 | D20: 3630.921 | E20: -957.10617 | F20: 7797.6632 | G20: -6482.1261 | H20: -1266.262 | I20: 474.95 | J20: 2789.19 | K20: -1955.8095 | L20: 455.717 | M20: 814.838 | N20: 1935.15
A21: 4001312260 | B21: 정부보조금등의변동 | C21: 백만원
A22: 4001312270 | B22: 기타운전자본의변동 | C22: 백만원
A23: 4001312280 | B23: *영업에서창출된현금흐름 | C23: 백만원 | D23: 12195.881 | E23: 17809.271 | F23: 21118.655 | G23: 16158.911 | H23: 16116.121 | I23: 23556.242 | J23: 18373.987 | K23: 31395.585 | L23: 22970.127 | M23: 36426.255 | N23: 21732.759
A24: 4001312290 | B24: 이자수입 | C24: 백만원 | D24: 9.95447 | E24: 66.30484 | F24: 68.44141 | G24: 241.63864 | H24: 850.51608 | I24: 1014.0505 | J24: 1142.6222 | K24: 1602.6468 | L24: 1427.8098 | M24: 1123.7495 | N24: 1161.376
A25: 4001312300 | B25: 이자지급(-) | C25: 백만원 | D25: -567.6084 | E25: -742.21351 | F25: -764.04745 | G25: -499.88514 | H25: -480.24526 | I25: -486.75813 | J25: -320.46148 | K25: -483.76229 | L25: -468.06493 | M25: -469.01902 | N25: -464.90185
A26: 4001312310 | B26: 배당금수입 | C26: 백만원
A27: 4001312320 | B27: 배당금지급(-) | C27: 백만원
A28: 4001312330 | B28: 법인세환입 | C28: 백만원
A29: 4001312340 | B29: 법인세납부(-) | C29: 백만원 | D29: -2554.3275 | E29: -3410.355 | F29: -4329.1709 | G29: -46.94383 | I29: -10451.57 | J29: -16620.44 | K29: -576.56149 | L29: -4556.6031 | M29: -6435.4515 | N29: -9280.7277
A30: 4001312350 | B30: 중단영업관련현금흐름 | C30: 백만원
A31: 4001390160 | B31: 투자활동으로인한현금흐름(*) | C31: 백만원 | D31: -63506.529 | E31: -20391.568 | F31: 1598.4593 | G31: -9695.2145 | H31: -30886.727 | I31: -9172.2794 | J31: 3427.8833 | K31: -11526.635 | L31: 13045.954 | M31: -43185.759 | N31: -32645.16
A32: 4001390170 | B32: 투자활동으로인한현금유입액(*) | C32: 백만원 | D32: 5135.5651 | E32: -1.43493 | F32: 140.28331 | G32: 65516.965 | H32: 5698.9367 | I32: 314.03204 | J32: 4560.8481 | K32: 5132.5639 | L32: 89463.695 | M32: 74849.2 | N32: 75260.564
A33: 4001390270 | B33: (투자활동으로인한현금유출액)(*) | C33: 백만원 | D33: 68642.094 | E33: 20390.133 | F33: -1458.1759 | G33: 75212.179 | H33: 36585.664 | I33: 9486.3115 | J33: 1132.9648 | K33: 16659.199 | L33: 76417.741 | M33: 118034.96 | N33: 107905.72
A34: 4001321350 | B34: 이자수입 | C34: 백만원
A35: 4001321360 | B35: 이자지급(-) | C35: 백만원
A36: 4001321370 | B36: 배당금수입 | C36: 백만원
A37: 4001321380 | B37: 배당금지급(-) | C37: 백만원
A38: 4001321390 | B38: 법인세환입 | C38: 백만원
A39: 4001321400 | B39: 법인세납부(-) | C39: 백만원
A40: 4001321410 | B40: 중단영업관련현금흐름 | C40: 백만원
A41: 4001390370 | B41: 재무활동으로인한현금흐름(*) | C41: 백만원 | D41: 68468.897 | E41: -5344.8557 | F41: -4100.6237 | G41: -37968.179 | H41: -911.6274 | I41: -8261.7096 | J41: -11305.814 | K41: -5164.8109 | L41: -970.0179 | M41: -13605.194 | N41: -912.6259
A42: 4001390380 | B42: 재무활동으로인한현금유입액(*) | C42: 백만원 | D42: 69108.845 | E42: 20 | F42: 15 | G42: 50 | H42: 85 | I42: 32 | L42: 25
A43: 4001390470 | B43: (재무활동으로인한현금유출액)(*) | C43: 백만원 | D43: 639.94831 | E43: 1093.5427 | F43: 4115.6237 | G43: 38018.179 | H43: 996.6274 | I43: 822.2579 | J43: 11305.814 | K43: 5164.811 | L43: 995.0179 | M43: 805.2899 | N43: 912.6259
A44: 4001330680 | B44: 이자수입 | C44: 백만원
A45: 4001330690 | B45: 이자지급(-) | C45: 백만원
A46: 4001330700 | B46: 배당금수입 | C46: 백만원
A47: 4001330710 | B47: 배당금지급(-) | C47: 백만원 | E47: -4271.313 | I47: -7471.4517 | K47: 1e-05 | M47: -12799.904
A48: 4001330720 | B48: 법인세환입 | C48: 백만원
A49: 4001330730 | B49: 법인세납부(-) | C49: 백만원
A50: 4001330740 | B50: 중단영업관련현금흐름 | C50: 백만원
A51: 4001340000 | B51: 영업투자재무활동기타현금흐름 | C51: 백만원
A52: 4001340010 | B52: 연결범위변동으로인한현금의증가 | C52: 백만원
A53: 4001340020 | B53: 환율변동효과 | C53: 백만원 | D53: 642.09215 | E53: 2581.023 | F53: 5032.4575 | G53: -8854.2326 | H53: 2490.2655 | I53: 703.18755 | J53: 2158.9354 | K53: -3850.921 | L53: 821.02355 | M53: -187.79549 | N53: -673.8708
A54: 4001340030 | B54: 현금및현금성자산의증가 | C54: 백만원 | D54: 14688.361 | E54: -9432.3956 | F54: 18624.171 | G54: -40663.905 | H54: -12821.696 | I54: -3098.8365 | J54: -3143.2872 | K54: 11395.54 | L54: 32270.229 | M54: -26333.218 | N54: -21083.148
A55: 4001340040 | B55: 기초현금및현금성자산 | C55: 백만원 | D55: 42788.254 | E55: 57476.615 | F55: 48044.219 | G55: 66668.39 | H55: 26004.485 | I55: 13182.789 | J55: 10083.953 | K55: 6940.6655 | L55: 18336.205 | M55: 50606.435 | N55: 24273.217
A56: 4001340050 | B56: 기말현금및현금성자산 | C56: 백만원 | D56: 57476.615 | E56: 48044.219 | F56: 66668.39 | G56: 26004.485 | H56: 13182.789 | I56: 10083.953 | J56: 6940.6655 | K56: 18336.205 | L56: 50606.435 | M56: 24273.217 | N56: 3190.0689

Sheet IS(Yearly)
B1: Last Refresh: 2025-04-01 12:01:27
A2: Financial Statements
A3: Company | B3: A214150(클래시스) - Fiscal Month:12, 201412부터 IFRS 적용
A4: Type | B4: 연결 | C4: Accounting Std. | D4: IFRS
A5: Report | B5: 손익계산서 | C5: New
A6: Form | B6: 약식(COMPARE)
A7: Output | B7: 결산 | C7: 백만원
A8: Fiscal Year | B8: 2021 | C8: Current
A9: 계정코드 | B9: 계정명 | C9: 단위 | D9: 202112 | E9: 202212 | F9: 202312 | G9: 202412
D10: IFRS(연결) | E10: IFRS(연결) | F10: IFRS(연결) | G10: IFRS(연결)
A11: 4001210000 | B11: 매출액(수익)(*) | C11: 백만원 | D11: 100596.94 | E11: 141803.24 | F11: 180122.8 | G11: 242938.97
A12: 4001210010 | B12: *수출(*) | C12: 백만원
A13: 4001210020 | B13: *내수 | C13: 백만원
A14: 4001210320 | B14: 매출원가(*) | C14: 백만원 | D14: 22744.272 | E14: 33636.219 | F14: 39673.734 | G14: 51811.436
A15: 4001210780 | B15: 매출총이익(손실) | C15: 백만원 | D15: 77852.664 | E15: 108167.02 | F15: 140449.06 | G15: 191127.53
A16: 4001290000 | B16: 판매비와관리비(*) | C16: 백만원 | D16: 26139.943 | E16: 39290.816 | F16: 50826.682 | G16: 68684.935
A17: 4001290010 | B17: 인건비(*) | C17: 백만원 | D17: 10813.849 | E17: 12404.21 | F17: 13383.309 | G17: 17460.38
A18: 4001290020 | B18: 유무형자산상각비(*) | C18: 백만원 | D18: 1064.403 | E18: 1593.113 | F18: 2224.397 | G18: 4741.327
A19: 4001211300 | B19: 연구개발비 | C19: 백만원 | D19: 4700.593 | E19: 4429.777 | F19: 9200.643 | G19: 12617.668
A20: 4001211060 | B20: 광고선전비 | C20: 백만원 | D20: 4215.073 | E20: 5914.187 | F20: 9029.738 | G20: 12820.742
A21: 4001290040 | B21: 판매비(*) | C21: 백만원 | D21: 2053.355 | E21: 6552.864 | F21: 6901.021 | G21: 6936.726
A22: 4001290090 | B22: 관리비(*) | C22: 백만원 | D22: 3292.67 | E22: 8396.665 | F22: 10056.036 | G22: 14047.182
A23: 4001290110 | B23: 기타원가성비용(*) | C23: 백만원
A24: 4001211420 | B24: 기타 | C24: 백만원 | F24: 31.538 | G24: 60.91
A25: 4001211430 | B25: 영업이익(손실) | C25: 백만원 | D25: 51712.72 | E25: 68876.207 | F25: 89622.382 | G25: 122442.59
A26: 4001290120 | B26: 금융수익(*) | C26: 백만원 | D26: 4211.433 | E26: 2584.12 | F26: 8660.314 | G26: 24212.614
A27: 4001290750 | B27: 이자수익 | C27: 백만원 | D27: 57.275 | E27: 772.115 | F27: 4627.866 | G27: 4801.445
A28: 4001290760 | B28: 배당금수익 | C28: 백만원
A29: 4001211480 | B29: 외환이익(*) | C29: 백만원 | D29: 3989.394 | E29: 1613.37 | F29: 2906.376 | G29: 16322.233
A30: 4001211520 | B30: 대손충당금환입액 | C30: 백만원
A31: 4001211600 | B31: 매출채권처분이익 | C31: 백만원
A32: 4001211605 | B32: 당기손익-공정가치측정 금융자산관련이익 | C32: 백만원
A33: 4001290130 | B33: 금융자산처분이익(*) | C33: 백만원
A34: 4001290150 | B34: 금융자산평가이익(*) | C34: 백만원 | D34: 164.764 | E34: 198.635 | F34: 1126.072 | G34: 3088.936
A35: 4001211720 | B35: 금융자산손상차손환입(*) | C35: 백만원
A36: 4001211680 | B36: 파생상품이익(*) | C36: 백만원
A37: 4001290170 | B37: 기타금융수익(*) | C37: 백만원
A38: 4001290180 | B38: 금융원가(*) | C38: 백만원 | D38: 367.148 | E38: 4675.706 | F38: 3594.757 | G38: 4683.624
A39: 4001290770 | B39: 이자비용 | C39: 백만원 | D39: 93.054 | E39: 2609.848 | F39: 1958.684 | G39: 2040.647
A40: 4001211820 | B40: 외환손실(*) | C40: 백만원 | D40: 274.094 | E40: 2017.072 | F40: 1636.073 | G40: 966.127
A41: 4001211860 | B41: 대손상각비 | C41: 백만원
A42: 4001211865 | B42: 당기손익-공정가치측정 금융자산관련손실 | C42: 백만원
A43: 4001211940 | B43: 매출채권처분손실 | C43: 백만원
A44: 4001290190 | B44: 금융자산처분손실(*) | C44: 백만원
A45: 4001290210 | B45: 금융자산평가손실(*) | C45: 백만원 | E45: 48.786 | G45: 28.527
A46: 4001212060 | B46: 금융자산손상차손(*) | C46: 백만원
A47: 4001212020 | B47: 파생상품손실(*) | C47: 백만원 | G47: 1648.323
A48: 4001290230 | B48: 기타금융원가(*) | C48: 백만원
A49: 4001290240 | B49: 기타수익(*) | C49: 백만원 | D49: 214.611 | E49: 30374.149 | F49: 49.689 | G49: 28.09
A50: 4001280000 | B50: 이자수익 | C50: 백만원
A51: 4001280010 | B51: 배당금수익 | C51: 백만원
A52: 4001290250 | B52: 외환이익(*) | C52: 백만원
A53: 4001280050 | B53: 재고자산감모손실환입 | C53: 백만원
A54: 4001280060 | B54: 재고자산폐기(처분)이익 | C54: 백만원
A55: 4001280065 | B55: 당기손익-공정가치측정 금융자산평가이익 | C55: 백만원
A56: 4001290260 | B56: 자산처분(폐기)이익(*) | C56: 백만원 | D56: 7.175 | E56: 30338.624 | F56: 16.602 | G56: 12.136
A57: 4001280140 | B57: 자산평가이익 | C57: 백만원
A58: 4001290280 | B58: 자산손상차손환입(*) | C58: 백만원
A59: 4001290300 | B59: 파생상품이익(*) | C59: 백만원
A60: 4001280240 | B60: 임대료수익 | C60: 백만원 | D60: 116.825
A61: 4001280250 | B61: 로열티수익 | C61: 백만원
A62: 4001280260 | B62: 수수료수익 | C62: 백만원
A63: 4001280270 | B63: 대손충당금환입 | C63: 백만원
A64: 4001280280 | B64: 충당부채환입액 | C64: 백만원
A65: 4001290310 | B65: 기타(*) | C65: 백만원 | D65: 90.611 | E65: 35.525 | F65: 33.087 | G65: 15.954
A66: 4001290320 | B66: 기타비용(*) | C66: 백만원 | D66: 147.028 | E66: 400.334 | F66: 895.784 | G66: 13002.234
A67: 4001280400 | B67: 이자비용 | C67: 백만원
A68: 4001290330 | B68: 외환손실(*) | C68: 백만원
A69: 4001280440 | B69: 재고자산감모손실 | C69: 백만원
A70: 4001280450 | B70: 재고자산폐기(처분)손실 | C70: 백만원
A71: 4001280455 | B71: 당기손익-공정가치측정 금융자산평가손실 | C71: 백만원
A72: 4001290340 | B72: 자산처분(폐기)손실(*) | C72: 백만원 | D72: 31.758 | E72: 51.327 | F72: 782.424 | G72: 1177.676
A73: 4001280540 | B73: 자산평가손실 | C73: 백만원
A74: 4001290360 | B74: 자산손상차손(*) | C74: 백만원
A75: 4001290380 | B75: 파생상품손실(*) | C75: 백만원
A76: 4001280650 | B76: 기타대손상각비 | C76: 백만원
A77: 4001280660 | B77: 충당부채전입액 | C77: 백만원
A78: 4001290390 | B78: 기타(*) | C78: 백만원 | D78: 115.27 | E78: 349.007 | F78: 113.36 | G78: 11824.558
A79: 4001290640 | B79: 종속기업,공동지배기업및관계기업관련손익(*) | C79: 백만원 | G79: -1066.4454
A80: 4001290650 | B80: 지분법손익(*) | C80: 백만원 | G80: -1066.4454
A81: 4001290680 | B81: 종속기업,공동지배기업및관계기업투자주식처분손익(*) | C81: 백만원
A82: 4001290710 | B82: 종속기업,공동지배기업및관계기업투자주식손상관련손익(*) | C82: 백만원
A83: 4001290740 | B83: 기타(*) | C83: 백만원
A84: 4001212380 | B84: 법인세비용차감전계속사업이익 | C84: 백만원 | D84: 55624.589 | E84: 96758.437 | F84: 93841.844 | G84: 127930.99
A85: 4001212390 | B85: 법인세비용 | C85: 백만원 | D85: 11819.912 | E85: 21379.789 | F85: 19616.641 | G85: 30387.239
A86: 4001212400 | B86: 종속회사매수일전순손익 | C86: 백만원
A87: 4001212410 | B87: 처분된종속회사순손익 | C87: 백만원
A88: 4001212420 | B88: 계속영업이익(손실) | C88: 백만원 | D88: 43804.676 | E88: 75378.647 | F88: 74225.203 | G88: 97543.754
A89: 4001212430 | B89: 중단영업이익(손실) | C89: 백만원
A90: 4001212450 | B90: 당기순이익(손실) | C90: 백만원 | D90: 43804.676 | E90: 75378.647 | F90: 74225.203 | G90: 97543.754
A91: 4001220000 | B91: 기타포괄손익(*) | C91: 백만원 | D91: 51.42638 | E91: 15.22236 | F91: 24.8004 | G91: 85.12543
A92: 4001220120 | B92: 총포괄손익 | C92: 백만원 | D92: 43856.103 | E92: 75393.87 | F92: 74250.004 | G92: 97628.879
A93: 4001230000 | B93: (당기순손익귀속)지배기업주주지분 | C93: 백만원 | D93: 43804.676 | E93: 75378.647 | F93: 74225.203 | G93: 97875.278
A94: 4001230030 | B94: (당기순손익귀속)비지배주주지분 | C94: 백만원 | G94: -331.52455
A95: 4001230060 | B95: (총포괄손익귀속)지배기업주주지분 | C95: 백만원 | D95: 43856.103 | E95: 75393.87 | F95: 74250.004 | G95: 97960.404
A96: 4001230070 | B96: (총포괄손익귀속)비지배주주지분 | C96: 백만원 | G96: -331.52455
A97: 4001230080 | B97: 주당계속영업이익 | C97: 원 | D97: 677 | E97: 1165 | F97: 1155
A98: 4001230090 | B98: 주당순손익 | C98: 원 | D98: 677 | E98: 1165 | F98: 1155
A99: 4001230100 | B99: 희석주당계속영업이익 | C99: 원 | D99: 676 | F99: 1152
A100: 4001230110 | B100: 희석주당순손익 | C100: 원 | D100: 676 | F100: 1152
...

Sheet BS(Yearly)
B1: Last Refresh: 2025-04-01 12:01:05
A2: Financial Statements
A3: Company | B3: A214150(클래시스) - Fiscal Month:12, 201412부터 IFRS 적용
A4: Type | B4: 연결 | C4: Accounting Std. | D4: IFRS
A5: Report | B5: 재무상태표 | C5: New
A6: Form | B6: 약식(COMPARE)
A7: Output | B7: 결산 | C7: 백만원
A8: Fiscal Year | B8: 2021 | C8: Current
A9: 계정코드 | B9: 계정명 | C9: 단위 | D9: 202112 | E9: 202212 | F9: 202312 | G9: 202412
D10: IFRS(연결) | E10: IFRS(연결) | F10: IFRS(연결) | G10: IFRS(연결)
A11: 4001190010 | B11: 자산(*) | C11: 백만원 | D11: 216379.21 | E11: 331411.11 | F11: 375443.02 | G11: 608378.81
A12: 4001190240 | B12: 유동자산(*) | C12: 백만원 | D12: 73140.021 | E12: 147788.69 | F12: 185737.48 | G12: 234201.82
A13: 4001190250 | B13: 재고자산(*) | C13: 백만원 | D13: 16465.364 | E13: 23397.667 | F13: 19434.328 | G13: 29999.807
A14: 4001190260 | B14: 유동생물자산(*) | C14: 백만원
A15: 4001190270 | B15: 유동금융자산(*) | C15: 백만원 | D15: 5983.0815 | E15: 87219.081 | F15: 119501.66 | G15: 136814.3
A16: 4001190300 | B16: 매출채권및기타유동채권(*) | C16: 백만원 | D16: 2163.766 | E16: 8437.622 | F16: 18162.51 | G16: 39005.333
A17: 4001113900 | B17: 당기법인세자산(선급법인세) | C17: 백만원 | D17: 24.43552 | E17: 24.52732 | F17: 25.52638 | G17: 28.7328
A18: 4001180995 | B18: 계약자산(**) | C18: 백만원
A19: 4001113903 | B19: 반품(환불)자산 | C19: 백만원
A20: 4001113904 | B20: 배출권 | C20: 백만원
A21: 4001190340 | B21: 기타유동자산(*) | C21: 백만원 | D21: 5715.1206 | E21: 2705.3075 | F21: 10277.254 | G21: 5608.5786
A22: 4001190370 | B22: 현금및현금성자산(*) | C22: 백만원 | D22: 42788.254 | E22: 26004.485 | F22: 18336.205 | G22: 22745.071
A23: 4001114130 | B23: 매각예정비유동자산및처분자산집단(*) | C23: 백만원
A24: 4001190020 | B24: 비유동자산(*) | C24: 백만원 | D24: 143239.18 | E24: 183622.42 | F24: 189705.54 | G24: 374176.99
A25: 4001190030 | B25: 유형자산(*) | C25: 백만원 | D25: 80704.633 | E25: 104241.59 | F25: 138988.71 | G25: 193172.86
A26: 4001190070 | B26: 무형자산(*) | C26: 백만원 | D26: 1123.998 | E26: 1478.37 | F26: 2822.297 | G26: 140947.98
A27: 4001190110 | B27: 비유동생물자산(*) | C27: 백만원
A28: 4001190120 | B28: 투자부동산(*) | C28: 백만원 | D28: 58418.164 | E28: 74654.142 | F28: 41087.737 | G28: 29444.615
A29: 4001190130 | B29: 장기금융자산(*) | C29: 백만원 | D29: 2191.6456 | E29: 1369.6593 | F29: 4207.6556 | G29: 9838.4147
A30: 4001111660 | B30: 관계기업등지분관련투자자산(*) | C30: 백만원
A31: 4001190160 | B31: 장기매출채권및기타비유동채권(*) | C31: 백만원
A32: 4001112490 | B32: 이연법인세자산 | C32: 백만원 | E32: 788.00773 | F32: 1381.8307
A33: 4001112500 | B33: 장기당기법인세자산 | C33: 백만원
A34: 4001180575 | B34: 계약자산(**) | C34: 백만원
A35: 4001112503 | B35: 반품(환불)자산 | C35: 백만원
A36: 4001112504 | B36: 배출권 | C36: 백만원
A37: 4001190200 | B37: 기타비유동자산(*) | C37: 백만원 | D37: 800.74314 | E37: 1090.6441 | F37: 1217.3038 | G37: 773.10977
A38: 4001112880 | B38: 기타금융업자산 | C38: 백만원
A39: 4001190440 | B39: 부채(*) | C39: 백만원 | D39: 52634.774 | E39: 101857.25 | F39: 91942.522 | G39: 155734.89
A40: 4001190610 | B40: 유동부채(*) | C40: 백만원 | D40: 16793.038 | E40: 36225.225 | F40: 29246.387 | G40: 128903.65
A41: 4001181470 | B41: 단기사채(**) | C41: 백만원 | G41: 2096.5291
A42: 4001121700 | B42: 단기차입금(*) | C42: 백만원 | G42: 3876.44
A43: 4001190620 | B43: 유동성장기부채(*) | C43: 백만원 | E43: 2400 | F43: 2400 | G43: 72840.385
A44: 4001190630 | B44: 유동금융부채(*) | C44: 백만원 | D44: 514.15452 | E44: 557.30324 | F44: 739.36938 | G44: 545.65061
A45: 4001190660 | B45: 매입채무및기타유동채무(*) | C45: 백만원 | D45: 3986.424 | E45: 8570.101 | F45: 9607.711 | G45: 24641.429
A46: 4001190680 | B46: 유동종업원급여충당부채(*) | C46: 백만원
A47: 4001122460 | B47: 기타단기충당부채(*) | C47: 백만원 | D47: 827.52125 | E47: 1225.9501 | F47: 1382.8205 | G47: 2217.168
A48: 4001122560 | B48: 당기법인세부채(미지급법인세) | C48: 백만원 | D48: 5965.6538 | E48: 18158.545 | F48: 10482.475 | G48: 17398.948
A49: 4001122561 | B49: 계약부채 | C49: 백만원
A50: 4001122562 | B50: 반품(환불)부채 | C50: 백만원
A51: 4001122563 | B51: 배출부채 | C51: 백만원
A52: 4001190690 | B52: 기타유동부채(*) | C52: 백만원 | D52: 5499.284 | E52: 5313.326 | F52: 4634.01 | G52: 5287.103
A53: 4001122680 | B53: 매각예정으로분류된처분자산집단에포함된부채(*) | C53: 백만원
A54: 4001190450 | B54: 비유동부채(*) | C54: 백만원 | D54: 35841.736 | E54: 65632.026 | F54: 62696.135 | G54: 26831.243
A55: 4001190460 | B55: 사채(*) | C55: 백만원
A56: 4001190470 | B56: 장기차입금(*) | C56: 백만원 | D56: 35000 | E56: 64400 | F56: 62000 | G56: 11512.117
A57: 4001190480 | B57: 비유동금융부채(*) | C57: 백만원 | D57: 291.45045 | E57: 541.31383 | F57: 488.71345 | G57: 1416.9704
A58: 4001190500 | B58: 장기매입채무및기타비유동채무(*) | C58: 백만원 | D58: 178 | E58: 690.712 | F58: 207.422 | G58: 125
A59: 4001190570 | B59: 비유동종업원급여충당부채(*) | C59: 백만원
A60: 4001121280 | B60: 기타장기충당부채(*) | C60: 백만원
A61: 4001121380 | B61: 이연법인세부채 | C61: 백만원 | D61: 372.2851 | G61: 13777.156
A62: 4001181370 | B62: 장기당기법인세부채(미지급법인세)(**) | C62: 백만원
A63: 4001121401 | B63: 계약부채 | C63: 백만원
A64: 4001121402 | B64: 반품(환불)부채 | C64: 백만원
A65: 4001121403 | B65: 배출부채 | C65: 백만원
A66: 4001190580 | B66: 기타비유동부채(*) | C66: 백만원
A67: 4001121620 | B67: 기타금융업부채 | C67: 백만원
A68: 4001190380 | B68: 자본(*) | C68: 백만원 | D68: 163744.43 | E68: 229553.86 | F68: 283500.5 | G68: 452643.91
A69: 4001130010 | B69: *수권주식수 | C69: 주 | D69: 100000000 | E69: 100000000 | F69: 100000000 | G69: 100000000
A70: 4001130020 | B70: *주당액면가액 | C70: 원 | D70: 100 | E70: 100 | F70: 100 | G70: 100
A71: 4001130030 | B71: *발행한주식총수(*) | C71: 주 | D71: 64716864 | E71: 64776702 | F71: 64776702 | G71: 65505659
A72: 4001130040 | B72: *보통주 | C72: 주 | D72: 64716864 | E72: 64776702 | F72: 64776702 | G72: 65505659
A73: 4001130050 | B73: *우선주 | C73: 주
A74: 4001190390 | B74: 지배기업주주지분(*) | C74: 백만원 | D74: 163744.43 | E74: 229553.86 | F74: 283500.5 | G74: 453964.81
A75: 4001130070 | B75: 자본금(*) | C75: 백만원 | D75: 6471.6864 | E75: 6477.6702 | F75: 6477.6702 | G75: 6628.2842
A76: 4001130670 | B76: 신종자본증권 | C76: 백만원
A77: 4001190400 | B77: 자본잉여금(*) | C77: 백만원 | D77: 24122.104 | E77: 24229.755 | F77: 24229.755 | G77: 106314.39
A78: 4001190420 | B78: 기타자본(*) | C78: 백만원 | D78: 4.78915 | E78: -5421.9761 | F78: -18253.886 | G78: 4814.6642
A79: 4001130360 | B79: 기타포괄손익누계액(*) | C79: 백만원 | D79: 22.85917 | E79: 38.08153 | F79: 62.88194 | G79: 148.00737
A80: 4001130470 | B80: 이익잉여금(결손금)(*) | C80: 백만원 | D80: 133122.99 | E80: 204230.33 | F80: 270984.08 | G80: 336059.47
A81: 4001130640 | B81: 비지배주주지분 | C81: 백만원 | G81: -1320.8937

Sheet CFS(Yearly)
B1: Last Refresh: 2025-04-01 12:01:44
A2: Financial Statements
A3: Company | B3: A214150(클래시스) - Fiscal Month:12, 201412부터 IFRS 적용
A4: Type | B4: 연결 | C4: Accounting Std. | D4: IFRS
A5: Report | B5: 현금흐름표 | C5: New
A6: Form | B6: 약식(COMPARE)
A7: Output | B7: 결산 | C7: 백만원
A8: Fiscal Year | B8: 2021 | C8: Current
A9: 계정코드 | B9: 계정명 | C9: 단위 | D9: 202112 | E9: 202212 | F9: 202312 | G9: 202412
D10: IFRS(연결) | E10: IFRS(연결) | F10: IFRS(연결) | G10: IFRS(연결)
A11: 4001390000 | B11: 영업활동으로인한현금흐름(간접법)(*) | C11: 백만원 | D11: 36367.042 | E11: 54754.505 | F11: 64631.972 | G11: 102800.41
A12: 4001310010 | B12: *(직접법)총현금유입(*) | C12: 백만원
A13: 4001310100 | B13: *(직접법)총현금유출(*) | C13: 백만원
A14: 4001310190 | B14: 당기순손익 | C14: 백만원 | D14: 43804.676 | E14: 75378.647 | F14: 74225.203 | G14: 97543.754
A15: 4001310200 | B15: 법인세비용차감전계속사업이익 | C15: 백만원
A16: 4001390010 | B16: 현금유출이없는비용등가산(*) | C16: 백만원 | D16: 15108.985 | E16: 30514.625 | F16: 31651.502 | G16: 58557.22
A17: 4001390040 | B17: (현금유입이없는수익등차감)(*) | C17: 백만원 | D17: 4060.311 | E17: 32188.436 | F17: 7931.885 | G17: 20726.016
A18: 4001390060 | B18: 영업활동으로인한자산부채변동(운전자본변동)(*) | C18: 백만원 | D18: -9613.3294 | E18: -6422.1179 | F18: -8502.8829 | G18: -14923.836
A19: 4001390070 | B19: 자산의감소(증가)(*) | C19: 백만원 | D19: -10822.224 | E19: -10411.47 | F19: -8544.952 | G19: -10264.713
A20: 4001390110 | B20: 부채의증가(감소)(*) | C20: 백만원 | D20: 1208.896 | E20: 3989.3519 | F20: 42.068 | G20: -4659.121
A21: 4001312260 | B21: 정부보조금등의변동 | C21: 백만원
A22: 4001312270 | B22: 기타운전자본의변동 | C22: 백만원
A23: 4001312280 | B23: *영업에서창출된현금흐름 | C23: 백만원 | D23: 45240.021 | E23: 67282.718 | F23: 89441.937 | G23: 120451.12
A24: 4001312290 | B24: 이자수입 | C24: 백만원 | D24: 42.05205 | E24: 386.33936 | F24: 4609.8355 | G24: 4868.4463
A25: 4001312300 | B25: 이자지급(-) | C25: 백만원 | D25: -93.05443 | E25: -2573.7545 | F25: -1771.2272 | G25: -1916.1799
A26: 4001312310 | B26: 배당금수입 | C26: 백만원
A27: 4001312320 | B27: 배당금지급(-) | C27: 백만원
A28: 4001312330 | B28: 법인세환입 | C28: 백만원
A29: 4001312340 | B29: 법인세납부(-) | C29: 백만원 | D29: -8821.9757 | E29: -10340.797 | F29: -27648.572 | G29: -20602.982
A30: 4001312350 | B30: 중단영업관련현금흐름 | C30: 백만원
A31: 4001390160 | B31: 투자활동으로인한현금흐름(*) | C31: 백만원 | D31: -92466.135 | E31: -91994.853 | F31: -48157.758 | G31: -82247.361
A32: 4001390170 | B32: 투자활동으로인한현금유입액(*) | C32: 백만원 | D32: 4537.5575 | E32: 70791.378 | F32: 15706.381 | G32: 348347.65
A33: 4001390270 | B33: (투자활동으로인한현금유출액)(*) | C33: 백만원 | D33: 97003.692 | E33: 162786.23 | F33: 63864.138 | G33: 430595.01
A34: 4001321350 | B34: 이자수입 | C34: 백만원
A35: 4001321360 | B35: 이자지급(-) | C35: 백만원
A36: 4001321370 | B36: 배당금수입 | C36: 백만원
A37: 4001321380 | B37: 배당금지급(-) | C37: 백만원
A38: 4001321390 | B38: 법인세환입 | C38: 백만원
A39: 4001321400 | B39: 법인세납부(-) | C39: 백만원
A40: 4001321410 | B40: 중단영업관련현금흐름 | C40: 백만원
A41: 4001390370 | B41: 재무활동으로인한현금흐름(*) | C41: 백만원 | D41: 30719.729 | E41: 21055.239 | F41: -25643.962 | G41: -16738.605
A42: 4001390380 | B42: 재무활동으로인한현금유입액(*) | C42: 백만원 | D42: 35013.999 | E42: 69193.845 | F42: 117 | G42: 80
A43: 4001390470 | B43: (재무활동으로인한현금유출액)(*) | C43: 백만원 | D43: 411.71949 | E43: 43867.294 | F43: 18289.51 | G43: 4018.7016
A44: 4001330680 | B44: 이자수입 | C44: 백만원
A45: 4001330690 | B45: 이자지급(-) | C45: 백만원
A46: 4001330700 | B46: 배당금수입 | C46: 백만원
A47: 4001330710 | B47: 배당금지급(-) | C47: 백만원 | D47: -3882.5501 | E47: -4271.313 | F47: -7471.4516 | G47: -12799.904
A48: 4001330720 | B48: 법인세환입 | C48: 백만원
A49: 4001330730 | B49: 법인세납부(-) | C49: 백만원
A50: 4001330740 | B50: 중단영업관련현금흐름 | C50: 백만원
A51: 4001340000 | B51: 영업투자재무활동기타현금흐름 | C51: 백만원
A52: 4001340010 | B52: 연결범위변동으로인한현금의증가 | C52: 백만원
A53: 4001340020 | B53: 환율변동효과 | C53: 백만원 | D53: 3784.1211 | E53: -598.66006 | F53: 1501.4674 | G53: 461.00001
A54: 4001340030 | B54: 현금및현금성자산의증가 | C54: 백만원 | D54: -21595.242 | E54: -16783.769 | F54: -7668.28 | G54: 4275.4407
A55: 4001340040 | B55: 기초현금및현금성자산 | C55: 백만원 | D55: 64383.496 | E55: 42788.254 | F55: 26004.485 | G55: 18469.63
A56: 4001340050 | B56: 기말현금및현금성자산 | C56: 백만원 | D56: 42788.254 | E56: 26004.485 | F56: 18336.205 | G56: 22745.071

Sheet 장비-소모품 회귀분석
A1: 요약 출력
A3: 회귀분석 통계량
A4: 다중 상관계수 | B4: 0.76974248
A5: 결정계수 | B5: 0.59250349
A6: 조정된 결정계수 | B6: 0.54156643
A7: 표준 오차 | B7: 3828.3323
A8: 관측수 | B8: 10
A10: 분산 분석
B11: 자유도 | C11: 제곱합 | D11: 제곱 평균 | E11: F 비 | F11: 유의한 F
A12: 회귀 | B12: 1 | C12: 1.7048111e+08 | D12: 1.7048111e+08 | E12: 11.63207 | F12: 0.009215214
A13: 잔차 | B13: 8 | C13: 1.1724903e+08 | D13: 14656128
A14: 계 | B14: 9 | C14: 2.8773013e+08
B16: 계수 | C16: 표준 오차 | D16: t 통계량 | E16: P-값 | F16: 하위 95% | G16: 상위 95% | H16: 하위 95.0% | I16: 상위 95.0%
A17: Y 절편 | B17: 534.7562 | C17: 6488.9559 | D17: 0.082410207 | E17: 0.93634515 | F17: -14428.803 | G17: 15498.315 | H17: -14428.803 | I17: 15498.315
A18: X 1 | B18: 1.0119495 | C18: 0.29670873 | D18: 3.4105821 | E18: 0.009215214 | F18: 0.32773791 | G18: 1.696161 | H18: 0.32773791 | I18: 1.696161
B20: y: 소모품매출액
B21: x; 2분기 이전 클래시스 매출액
B22: y=534.7562 + 1.011949x
