Workbook
Name _MOD1: #REF!
Name _MOD1: #REF!
Name _MOD1: #REF!
Name _MOD1: #REF!
Name \a: #N/A
Name \b: #N/A
Name \I: #REF!
Name \I: #REF!
Name \I: #REF!
Name \I: #REF!
Name \P: #REF!
Name \P: #REF!
Name A_K___s__Global__I_T: #REF!
Name A_K___s__Global__I_T: #REF!
Name Acc_payable_growth_fore: #REF!
Name Acc_payable_growth_fore: #REF!
Name Acc_Rec_growth_fore: #REF!
Name Acc_Rec_growth_fore: #REF!
Name Accrued_compensation_growth_fore: #REF!
Name Accrued_compensation_growth_fore: #REF!
Name Accrued_expenses_growth_fore: #REF!
Name Accrued_expenses_growth_fore: #REF!
Name Accum_Cap_Expenses_growth_fore: #REF!
Name Accum_Cap_Expenses_growth_fore: #REF!
Name Accum_Goodwill_Amort_growth_fore: #REF!
Name Accum_Goodwill_Amort_growth_fore: #REF!
Name Adj_net_oper_fore: #REF!
Name Adj_net_oper_fore: #REF!
Name AveSize: #REF!
Name AveSize: #REF!
Name BS_C: #REF!
Name BS_C: #REF!
Name Case_Offset: #REF!
Name Case_Offset: #REF!
Name Case_Offset: #REF!
Name Case_Offset: #REF!
Name Cash_fore: #REF!
Name Cash_fore: #REF!
Name Cash_growth_fore: #REF!
Name Cash_growth_fore: #REF!
Name Cash_operating_taxes_fore: #REF!
Name Cash_operating_taxes_fore: #REF!
Name CDS: #REF!
Name CDS: #REF!
Name CE_C: #REF!
Name CE_C: #REF!
Name CF_C: #REF!
Name CF_C: #REF!
Name CFormats: #REF!
Name CFormats: #REF!
Name codeDestination: #REF!
Name codeDestination: #REF!
Name CODELK_Path: #REF!
Name CODELK_Path: #REF!
Name ColumnHeading: #REF!
Name ColumnHeading: #REF!
Name Com_Data_sum_035900: '요약 재무제표'!$B$5
Name Comdty: #REF!
Name Comdty: #REF!
Name Corp: #REF!

Sheet Estimate Logic - HRSG
B1: Estimation
B2: Estimate Logic - HRSG
B5: (단위: 백만 원) | C5: 2025 | D5: 2026 | E5: 2027 | F5: 2028
B6: HRSG | C6: 377429.13 | D6: 733774.78 | E6: 753165.03 | F6: 794672.44 | H6: HRSG 사업부 매출은 기존 공시 수주와 신규 수주로 나누어 추정하였다.
B7: YoY % | C7: 0.45717656 | D7: 0.94413923 | E7: 0.026425352 | F7: 0.055110636 | H7: 신규 수주의 경우 국내외 해외 주요 시장 (중동, 미국, 일본)으로 구분하고, 수주 가능성에 따라 Bull/Base/Bear 세 가지 케이스로 분류했다.
B8: 국내 | C8: 121883.49 | D8: 143683.12 | E8: 137753.31 | F8: 72697.732
B9: 해외 | C9: 255545.64 | D9: 590091.65 | E9: 615411.72 | F9: 721974.7
B10: 중동 | C10: 204714.19 | D10: 480874.94 | E10: 444139.64 | F10: 513181.5
B11: 일본 | C11: 35999.228 | D11: 109216.71 | E11: 136552.5 | F11: 113425.37
B12: 미국 | C12: 0 | D12: 0 | E12: 34719.574 | F12: 95367.834
B13: 기타 | C13: 14832.22 | D13: 0 | E13: 0 | F13: 0
B15: 기존수주 매출 (추정) | C15: 2025 | D15: 2026 | E15: 2027 | F15: 2028
B16: 국내 | C16: 121883.49 | D16: 130988.42 | E16: 79532.855 | F16: 10609.75 | H16: 기존 수주는 공시된 수주 계약을 대상으로, 유사한 계약의 진행율을 반영하여 분기별로 분배하였다.
B17: 중동 | C17: 251483.67 | D17: 561196.44 | E17: 140217.35 | F17: 0
B18: 일본 | C18: 35999.228 | D18: 104798.67 | E18: 119343.66 | F18: 79288.997
B19: 기타 | C19: 14832.22 | D19: 0 | E19: 0 | F19: 0

Sheet Estimate Logic - BOP

Sheet Estimate Logic - 비용

Sheet Valuation ▶
A3: 비에이치아이(083650.KQ)
A5: Valuation Sheets >>>

Sheet EVEBITDA
B1: 비에이치아이(083650.KQ)
B2: EV/EBITDA Valuation Sheet
B3: (In KRW millions)
B5: EV/EBITDA Valuation Table | G5: EV/EBITDA Valuation Table
B6: 26F EBITDA (Bull) | C6: =M42 -> 1115.0315 | D6: (억원) | G6: 26F EBITDA (Base) | H6: =M43 -> 1074.9139 | I6: (억원)
B7: Target EV/EBITDA | C7: =$P$44 -> 18.5745 | D7: (배) | G7: Target EV/EBITDA | H7: =$P$44 -> 18.5745 | I7: (배)
B8: EV | C8: =C6*C7 -> 20711.152 | D8: (억원) | E8: (A) | G8: EV | H8: =H6*H7 -> 19965.988 | I8: (억원) | J8: (A)
B9: 비영업가치 | C9: =#REF! -> #REF! | D9: (억원) | E9: (B) | G9: 비영업가치 | H9: =#REF! -> #REF! | I9: (억원) | J9: (B)
B10: 순차입금 | C10: =$M$45 -> 819.46968 | D10: (억원) | E10: (C) | G10: 순차입금 | H10: =$M$45 -> 819.46968 | I10: (억원) | J10: (C)
B11: 주주가치 | C11: =C8+C9-C10 -> #REF! | D11: (억원) | E11: (A)+(B)-(C)-(D) | G11: 주주가치 | H11: =H8+H9-H10 -> #REF! | I11: (억원) | J11: (A)+(B)-(C)-(D)
B12: 발행주식수 | C12: =$P$48 -> 30944375 | G12: 발행주식수 | H12: =$P$48 -> 30944375
B13: Target Price | C13: =ROUND(C11*100000000/C12,-2) -> #REF! | G13: Target Price | H13: =ROUND(H11*100000000/H12,-2) -> #REF!
B14: Current Price | C14: =$P$49 -> 40300 | G14: Current Price | H14: =$P$49 -> 40300
B15: Upside | C15: =C13/C14-1 -> #REF! | G15: Upside | H15: =H13/H14-1 -> #REF!
B17: EV/EBITDA Valuation Table | G17: EV/EBITDA Valuation Table
B18: 27F EBITDA (Bull) | C18: =N42 -> 1265.8318 | D18: (억원) | G18: 27F EBITDA (Base) | H18: =N43 -> 1182.1407 | I18: (억원)
B19: Target EV/EBITDA | C19: =$P$44 -> 18.5745 | D19: (배) | G19: Target EV/EBITDA | H19: =$P$44 -> 18.5745 | I19: (배)
B20: EV | C20: =C18*C19 -> 23512.193 | D20: (억원) | E20: (A) | G20: EV | H20: =H18*H19 -> 21957.673 | I20: (억원) | J20: (A)
B21: 비영업가치 | C21: =#REF! -> #REF! | D21: (억원) | E21: (B) | G21: 비영업가치 | H21: =#REF! -> #REF! | I21: (억원) | J21: (B)
B22: 순차입금 | C22: =$N$45 -> 148.58324 | D22: (억원) | E22: (C) | G22: 순차입금 | H22: =$N$45 -> 148.58324 | I22: (억원) | J22: (C)
B23: 주주가치 | C23: =C20+C21-C22 -> #REF! | D23: (억원) | E23: (A)+(B)-(C)-(D) | G23: 주주가치 | H23: =H20+H21-H22 -> #REF! | I23: (억원) | J23: (A)+(B)-(C)-(D)
B24: 발행주식수 | C24: =$P$48 -> 30944375 | G24: 발행주식수 | H24: =$P$48 -> 30944375
B25: Target Price | C25: =ROUND(C23*100000000/C24,-2) -> #REF! | G25: Target Price | H25: =ROUND(H23*100000000/H24,-2) -> #REF!
B26: Current Price | C26: =$P$49 -> 40300 | G26: Current Price | H26: =$P$49 -> 40300
B27: Upside | C27: =C25/C26-1 -> #REF! | G27: Upside | H27: =H25/H26-1 -> #REF!
B29: EV/EBITDA Valuation Table | G29: EV/EBITDA Valuation Table
B30: 28F EBITDA (Bull) | C30: =O42 -> 1551.7574 | D30: (억원) | G30: 28F EBITDA (Base) | H30: =O43 -> 1149.2465 | I30: (억원)
B31: Target EV/EBITDA | C31: =$P$44 -> 18.5745 | D31: (배) | G31: Target EV/EBITDA | H31: =$P$44 -> 18.5745 | I31: (배)
B32: EV | C32: =C30*C31 -> 28823.118 | D32: (억원) | E32: (A) | G32: EV | H32: =H30*H31 -> 21346.68 | I32: (억원) | J32: (A)
B33: 비영업가치 | C33: =#REF! -> #REF! | D33: (억원) | E33: (B) | G33: 비영업가치 | H33: =#REF! -> #REF! | I33: (억원) | J33: (B)
B34: 순차입금 | C34: =$O$45 -> -104.86935 | D34: (억원) | E34: (C) | G34: 순차입금 | H34: =$O$45 -> -104.86935 | I34: (억원) | J34: (C)
B35: 주주가치 | C35: =C32+C33-C34 -> #REF! | D35: (억원) | E35: (A)+(B)-(C)-(D) | G35: 주주가치 | H35: =H32+H33-H34 -> #REF! | I35: (억원) | J35: (A)+(B)-(C)-(D)
B36: 발행주식수 | C36: =$P$48 -> 30944375 | G36: 발행주식수 | H36: =$P$48 -> 30944375
B37: Target Price | C37: =ROUND(C35*100000000/C36,-2) -> #REF! | G37: Target Price | H37: =ROUND(H35*100000000/H36,-2) -> #REF!
B38: Current Price | C38: =$P$49 -> 40300 | G38: Current Price | H38: =$P$49 -> 40300
B39: Upside | C39: =C37/C38-1 -> #REF! | G39: Upside | H39: =H37/H38-1 -> #REF!
S40: Peer Group Valuation Table
B41: EV/EBITDA Valuation Table | G41: EV/EBITDA Valuation Table | M41: 2026 | N41: 2027 | O41: 2028 | P41: Avg | Q41: 100 | S41: Ticker | T41: 기업명 | U41: Refinitiv | V41: Cap IQ | W41: 시가총액
B42: 27-28F avg. EBITDA (Bull) | C42: =P42 -> 1408.7946 | D42: (억원) | G42: 27-28F avg. EBITDA (Base) | H42: =P43 -> 1165.6936 | I42: (억원) | L42: EBITDA - Bull Case | M42: 1115.0315 | N42: 1265.8318 | O42: 1551.7574 | P42: =AVERAGE(N42:O42) -> 1408.7946 | S42: GEV | T42: GE Vernova | U42: 36.91 | V42: 38.75
B43: Target EV/EBITDA | C43: =$P$44 -> 18.5745 | D43: (배) | G43: Target EV/EBITDA | H43: =$P$44 -> 18.5745 | I43: (배) | L43: EBITDA - Base Case | M43: 1074.9139 | N43: 1182.1407 | O43: 1149.2465 | P43: =AVERAGE(N43:O43) -> 1165.6936 | S43: 7011 | T43: Mitsubishi Heavy Industry | U43: 19.2 | V43: 21.02 | W43: 81211.93 | X43: 12121184
B44: EV | C44: =C42*C43 -> 26167.656 | D44: (억원) | E44: (A) | G44: EV | H44: =H42*H43 -> 21652.176 | I44: (억원) | J44: (A) | L44: Target EV/EBITDA Multiple | P44: =U47*70% -> 18.5745 | S44: BWXT | T44: BWX Technologies | U44: 25.3 | V44: 26.73 | W44: 13729.69
B45: 순차입금 | C45: =$P$45 -> 21.856945 | D45: (억원) | E45: (B) | G45: 순차입금 | H45: =$P$45 -> 21.856945 | I45: (억원) | J45: (B) | L45: 순차입급 | M45: =M46-M47 -> 819.46968 | N45: =N46-N47 -> 148.58324 | O45: =O46-O47 -> -104.86935 | P45: =AVERAGE(N45:O45) -> 21.856945 | Q45: 이자부부채 - 현금 및 현금성 자산 | S45: 043020 | T45: Doosan enerbility | U45: 24.73 | V45: 27.55
B46: 주주가치 | C46: =C44-C45 -> 26145.799 | D46: (억원) | E46: (A)+(B) | G46: 주주가치 | H46: =H44-H45 -> 21630.32 | I46: (억원) | J46: (A)+(B) | L46: 이자부 부채 | M46: ='요약 재무제표'!P17 -> 1563.7791 | N46: ='요약 재무제표'!Q17 -> 1261.4843 | O46: ='요약 재무제표'!R17 -> 1544.2791 | P46: =AVERAGE(N46:O46) -> 1402.8817 | Q46: 장단기 차입금, 유동성 장기부채 | T46: Industry Median | U46: 10.7
B47: 발행주식수 | C47: =$P$48 -> 30944375 | G47: 발행주식수 | H47: =$P$48 -> 30944375 | L47: 현금 및 현금성 자산 | M47: ='요약 재무제표'!P7 -> 744.30945 | N47: ='요약 재무제표'!Q7 -> 1112.901 | O47: ='요약 재무제표'!R7 -> 1649.1484 | P47: =AVERAGE(N47:O47) -> 1381.0247 | U47: =AVERAGE(U42:U45) -> 26.535 | V47: =AVERAGE(V42:V45) -> 28.5125
B48: Target Price | C48: =ROUND(C46*100000000/C47,-2) -> 84500 | G48: Target Price | H48: =ROUND(H46*100000000/H47,-2) -> 69900 | L48: 발행주식수 | P48: 30944375
B49: Current Price | C49: =$P$49 -> 40300 | G49: Current Price | H49: =$P$49 -> 40300 | L49: 현재주가 (07.30) | P49: 40300
B50: Upside | C50: =C48/C49-1 -> 1.0967742 | G50: Upside | H50: =H48/H49-1 -> 0.73449132

Sheet Estimate ▶
A2: ='Valuation ▶'!A3 -> 비에이치아이(083650.KQ)
A4: Estimate Sheets (추정재무제표 작성) >>>

Sheet Expected IS
B1: Estimation
B2: Expected IS
B5: 계정명 | C5: 단위 | D5: 202112 | E5: 202212 | F5: 202312 | G5: 202412 | H5: 202512 | I5: 202612 | J5: 202712 | K5: 202812
D6: IFRS(연결) | E6: IFRS(연결) | F6: IFRS(연결) | G6: IFRS(연결) | H6: IFRS(연결) | I6: IFRS(연결) | J6: IFRS(연결) | K6: IFRS(연결)
B7: 매출액(수익)(*) | C7: 백만원 | D7: 234883.72 | E7: 330197.11 | F7: 367399.21 | G7: 404741.04 | H7: ='Case Summary'!U9 -> 818060.13 | I7: ='Case Summary'!V9 -> 1055423.5 | J7: ='Case Summary'!W9 -> 1121745.8 | K7: ='Case Summary'!X9 -> 1225142.9
B8: 매출원가(*) | C8: 백만원 | D8: 241249.52 | E8: 295265.47 | F8: 323957.62 | G8: 345623.02 | H8: ='비용 세부항목 추정'!G7+'비용 세부항목 추정'!G38+'비용 세부항목 추정'!G49+'비용 세부항목 추정'!G61 -> 715009.6 | I8: ='비용 세부항목 추정'!H7+'비용 세부항목 추정'!H38+'비용 세부항목 추정'!H49+'비용 세부항목 추정'!H61 -> 895855.7 | J8: ='비용 세부항목 추정'!I7+'비용 세부항목 추정'!I38+'비용 세부항목 추정'!I49+'비용 세부항목 추정'!I61 -> 962321.77 | K8: ='비용 세부항목 추정'!J7+'비용 세부항목 추정'!J38+'비용 세부항목 추정'!J49+'비용 세부항목 추정'!J61 -> 1062888.4
B9: 매출원가율(%) | D9: =D8/D7 -> 1.0271019 | E9: =E8/E7 -> 0.89420974 | F9: =F8/F7 -> 0.88175917 | G9: =G8/G7 -> 0.85393619 | H9: =H8/H7 -> 0.87403062 | I9: =I8/I7 -> 0.84881161 | J9: =J8/J7 -> 0.85787861 | K9: =K8/K7 -> 0.86756283
B10: 매출총이익(손실) | C10: 백만원 | D10: -6365.8024 | E10: 34931.638 | F10: 43441.587 | G10: 59118.018 | H10: =H7-H8 -> 103050.53 | I10: =I7-I8 -> 159567.78 | J10: =J7-J8 -> 159424.08 | K10: =K7-K8 -> 162254.45
B11: 판매비와관리비(*) | C11: 백만원 | D11: 24245.078 | E11: 26823.584 | F11: 28354.888 | G11: 37190.759 | H11: =SUM(H12:H14) -> 39220.871 | I11: =SUM(I12:I14) -> 47346.999 | J11: =SUM(J12:J14) -> 52260.258 | K11: =SUM(K12:K14) -> 58465.989
B12: 인건비(*) | C12: 백만원 | D12: 13000.707 | E12: 13948.49 | F12: 14157.436 | G12: 17165.349 | H12: ='비용 세부항목 추정'!G74 -> 20255.34 | I12: ='비용 세부항목 추정'!H74 -> 23564.003 | J12: ='비용 세부항목 추정'!I74 -> 27131.2 | K12: ='비용 세부항목 추정'!J74 -> 31238.412
B13: 유무형자산상각비(*) | C13: 백만원 | D13: 1041.959 | E13: 1176.78 | F13: 1715.522 | G13: 1913.114 | H13: ='비용 세부항목 추정'!G75 -> 1913.114 | I13: ='비용 세부항목 추정'!H75 -> 1913.114 | J13: ='비용 세부항목 추정'!I75 -> 1913.114 | K13: ='비용 세부항목 추정'!J75 -> 1913.114
B14: 기타 | C14: 백만원 | D14: 21175 | E14: 31102 | F14: 16399 | G14: 13332 | H14: ='비용 세부항목 추정'!G76+'비용 세부항목 추정'!G78+'비용 세부항목 추정'!G79 -> 17052.417 | I14: ='비용 세부항목 추정'!H76+'비용 세부항목 추정'!H78+'비용 세부항목 추정'!H79 -> 21869.882 | J14: ='비용 세부항목 추정'!I76+'비용 세부항목 추정'!I78+'비용 세부항목 추정'!I79 -> 23215.944 | K14: ='비용 세부항목 추정'!J76+'비용 세부항목 추정'!J78+'비용 세부항목 추정'!J79 -> 25314.463
B15: 영업이익(손실) | C15: 백만원 | D15: -30610.88 | E15: 8108.0541 | F15: 15086.698 | G15: 21927.258 | H15: =H10-H11 -> 63829.657 | I15: =I10-I11 -> 112220.78 | J15: =J10-J11 -> 107163.82 | K15: =K10-K11 -> 103788.46
B16: 영업이익률(%) | D16: =D15/D7 -> -0.13032355 | E16: =E15/E7 -> 0.024555194 | F16: =F15/F7 -> 0.041063502 | G16: =G15/G7 -> 0.054176019 | H16: =H15/H7 -> 0.07802563 | I16: =I15/I7 -> 0.10632773 | J16: =J15/J7 -> 0.095533063 | K16: =K15/K7 -> 0.084715398
B17: EBITDA | E17: =E15+'비용 세부항목 추정'!D75+'비용 세부항목 추정'!D62 -> 18664.418 | F17: =F15+'비용 세부항목 추정'!E75+'비용 세부항목 추정'!E62 -> 25681.561 | G17: =G15+'비용 세부항목 추정'!F75+'비용 세부항목 추정'!F62 -> 27985.154 | H17: =H15+'비용 세부항목 추정'!G75+'비용 세부항목 추정'!G62 -> 75077.104 | I17: =I15+'비용 세부항목 추정'!H75+'비용 세부항목 추정'!H62 -> 123331.65 | J17: =J15+'비용 세부항목 추정'!I75+'비용 세부항목 추정'!I62 -> 118214.07 | K17: =K15+'비용 세부항목 추정'!J75+'비용 세부항목 추정'!J62 -> 114924.65
B18: EBITDA Margin(%) | E18: =E17/E7 -> 0.05652508 | F18: =F17/F7 -> 0.06990097 | G18: =G17/G7 -> 0.069143358 | H18: =H17/H7 -> 0.091774554 | I18: =I17/I7 -> 0.11685513 | J18: =J17/J7 -> 0.10538401 | K18: =K17/K7 -> 0.093805105
B19: 금융수익(*) | C19: 백만원 | D19: 7196.576 | E19: 8323.576 | F19: 10770.512 | G19: 18569.587 | H19: =SUM(H20:H22) -> 8406.7293 | I19: =SUM(I20:I22) -> 8406.7293 | J19: =SUM(J20:J22) -> 8406.7293 | K19: =SUM(K20:K22) -> 8406.7293
B20: 이자수익 | C20: 백만원 | D20: 141.376 | E20: 281.418 | F20: 958.346 | G20: 1352.583 | H20: ='비용 세부항목 추정'!G86 -> 864.11567 | I20: ='비용 세부항목 추정'!H86 -> 864.11567 | J20: ='비용 세부항목 추정'!I86 -> 864.11567 | K20: ='비용 세부항목 추정'!J86 -> 864.11567
B21: 외환이익(*) | C21: 백만원 | D21: 5857.794 | E21: 7309.414 | F21: 8337.759 | G21: 16104.774 | H21: ='비용 세부항목 추정'!G87 -> 7168.3223 | I21: ='비용 세부항목 추정'!H87 -> 7168.3223 | J21: ='비용 세부항목 추정'!I87 -> 7168.3223 | K21: ='비용 세부항목 추정'!J87 -> 7168.3223
B22: 파생상품이익(*) | C22: 백만원 | D22: 553.496 | E22: 2.7 | F22: 769.799 | G22: 350.375 | H22: ='비용 세부항목 추정'!G88 -> 374.29133 | I22: ='비용 세부항목 추정'!H88 -> 374.29133 | J22: ='비용 세부항목 추정'!I88 -> 374.29133 | K22: ='비용 세부항목 추정'!J88 -> 374.29133
B23: 금융원가(*) | C23: 백만원 | D23: 13853.979 | E23: 37272.428 | F23: 22758.852 | G23: 44883.533 | H23: =SUM(H24:H27) -> 36955.902 | I23: =SUM(I24:I27) -> 36955.902 | J23: =SUM(J24:J27) -> 36955.902 | K23: =SUM(K24:K27) -> 36955.902
B24: 이자비용 | C24: 백만원 | D24: 6922.606 | E24: 9204.768 | F24: 11546.804 | G24: 10416.514 | H24: ='비용 세부항목 추정'!G91 -> 10389.362 | I24: ='비용 세부항목 추정'!H91 -> 10389.362 | J24: ='비용 세부항목 추정'!I91 -> 10389.362 | K24: ='비용 세부항목 추정'!J91 -> 10389.362
B25: 외환손실(*) | C25: 백만원 | D25: 2956.485 | E25: 7109.659 | F25: 7083.603 | G25: 10073.078 | H25: ='비용 세부항목 추정'!G92 -> 10073.078 | I25: ='비용 세부항목 추정'!H92 -> 10073.078 | J25: ='비용 세부항목 추정'!I92 -> 10073.078 | K25: ='비용 세부항목 추정'!J92 -> 10073.078
B26: 파생상품손실(*) | C26: 백만원 | D26: 3914.981 | E26: 20942.7 | F26: 2631.475 | G26: 21948.104 | H26: ='비용 세부항목 추정'!G93 -> 15174.093 | I26: ='비용 세부항목 추정'!H93 -> 15174.093 | J26: ='비용 세부항목 추정'!I93 -> 15174.093 | K26: ='비용 세부항목 추정'!J93 -> 15174.093
B27: 기타금융원가(*) | C27: 백만원 | G27: 2412 | H27: ='비용 세부항목 추정'!G94 -> 1319.3693 | I27: ='비용 세부항목 추정'!H94 -> 1319.3693 | J27: ='비용 세부항목 추정'!I94 -> 1319.3693 | K27: ='비용 세부항목 추정'!J94 -> 1319.3693
B28: 금융손익 | D28: =D19-D23 -> -6657.403 | E28: =E19-E23 -> -28948.852 | F28: =F19-F23 -> -11988.34 | G28: =G19-G23 -> -26313.946 | H28: =H19-H23 -> -28549.173 | I28: =I19-I23 -> -28549.173 | J28: =J19-J23 -> -28549.173 | K28: =K19-K23 -> -28549.173
B29: 기타손익 | D29: 3506.399 | E29: 1286.204 | F29: 2118.717 | G29: 840.821 | H29: ='비용 세부항목 추정'!G95 -> 840.821 | I29: ='비용 세부항목 추정'!H95 -> 840.821 | J29: ='비용 세부항목 추정'!I95 -> 840.821 | K29: ='비용 세부항목 추정'!J95 -> 840.821
B30: 종속기업,공동지배기업및관계기업관련손익(*) | C30: 백만원 | D30: -722.69736 | E30: -1220.522 | F30: -1392.16 | G30: -399.343 | H30: ='비용 세부항목 추정'!G96 -> -399.343 | I30: ='비용 세부항목 추정'!H96 -> -399.343 | J30: ='비용 세부항목 추정'!I96 -> -399.343 | K30: ='비용 세부항목 추정'!J96 -> -399.343
B31: 법인세비용차감전계속사업이익 | C31: 백만원 | D31: -34484.581 | E31: -20775.115 | F31: 3824.9159 | G31: -3945.2096 | H31: =H15+H28+H29+H30 -> 35721.962 | I31: =I15+I28+I29+I30 -> 84113.084 | J31: =J15+J28+J29+J30 -> 79056.122 | K31: =K15+K28+K29+K30 -> 75680.77
B32: 법인세비용 | C32: 백만원 | D32: 102.52471 | E32: -1657.3597 | F32: -3638.8661 | G32: -23530.262 | H32: =H31*21% -> 7501.6119 | I32: =I31*21% -> 17663.748 | J32: =J31*21% -> 16601.786 | K32: =K31*21% -> 15892.962
B33: 유효법인세율 | D33: =D32/D31 -> -0.0029730594 | E33: =E32/E31 -> 0.079776194 | F33: =F32/F31 -> -0.95135847 | G33: =G32/G31 -> 5.9642616 | H33: =H32/H31 -> 0.21 | I33: =I32/I31 -> 0.21 | J33: =J32/J31 -> 0.21 | K33: =K32/K31 -> 0.21 | AE33: 1000
B34: 당기순이익(손실) | C34: 백만원 | D34: -34587.106 | E34: -19117.756 | F34: 7463.782 | G34: 19585.052 | H34: =H31-H32 -> 28220.35 | I34: =I31-I32 -> 66449.336 | J34: =J31-J32 -> 62454.336 | K34: =K31-K32 -> 59787.808
O36: 매출원가+판관비 | AG36: 2024 | AT36: 1000
B37: 계정명 | C37: 단위 | D37: 202112 | E37: 202212 | F37: 202312 | G37: 202412 | H37: 202512 | I37: 202612 | J37: 202712 | K37: 202812 | O37: 구 분 | P37: 2021 | Q37: 2022 | R37: 2023 | S37: 2024 | V37: 판관비 | X37: 계정명 | Y37: 단위 | Z37: 202012 | AA37: 202112 | AB37: 202212 | AC37: 202312 | AD37: 202412 | AG37: 사업부문 | AH37: 매입유형 | AI37: 품 목 | AJ37: 구체적용도 | AK37: 매입액 | AL37: 비율 | AQ37: 31065.084 | AR37: 33357.715 | AS37: 37304.193 | AT37: 43458.932
B38: 매출액(수익)(*) | C38: 백만원 | D38: 234883.72 | E38: 330197.11 | F38: 367399.21 | G38: 404741.04 | O38: 원재료 사용액 | P38: 118149580 | Q38: 107443312 | R38: 92510020 | S38: 106199675 | U38: 종업원급여 | V38: 직원급여 | X38: 매출액(수익)(*) | Z38: 243441.15 | AA38: 234883.72 | AB38: 330197.11 | AC38: 367399.21 | AD38: 404741.04 | AG38: 비에이치아이 | AH38: 원재료 | AI38: Tube | AJ38: 제품 제작에 | AK38: 44240 | AL38: 15.5
B39: 매출원가(*) | C39: 백만원 | D39: 241249.52 | E39: 295265.47 | F39: 323957.62 | G39: 345623.02 | O39: 종업원급여 | P39: 31065084 | Q39: 33357715 | R39: 37304193 | S39: 43458932 | V39: 퇴직급여 | X39: 매출원가(*) | Z39: 209367.57 | AA39: 241249.52 | AB39: 295265.47 | AC39: 323957.62 | AD39: 345623.02 | AI39: Plate | AJ39: 필요한 원재료 | AK39: 30388 | AL39: 10.6
B40: 원재료 사용액 | C40: 백만원 | D40: =P50 -> 118149580 | E40: =Q50 -> 107443312 | F40: =R50 -> 92510020 | G40: =S50 -> 106199675 | O40: 감가상각비 | P40: 8451273 | Q40: 8194515 | R40: 8384344 | S40: 4360717 | V40: 복리후생비 | X40: 원재료 사용액 | AA40: 118149.58 | AB40: 107443.31 | AC40: 92510.02 | AD40: 106199.68 | AI40: Pipe | AK40: 13429 | AL40: 4.7
B41: 외주가공비 | C41: 백만원 | D41: =P56 -> 68726184 | E41: =Q56 -> 124425012 | F41: =R56 -> 162700676 | G41: =S56 -> 169062007 | O41: 무형자산상각비 | P41: 2334760 | Q41: 2361849 | R41: 2210519 | S41: 1697179 | U41: 감가상각비 | V41: 감가상각비 | AA41: =AA40/AA38 -> 0.50301307 | AB41: =AB40/AB38 -> 0.32539144 | AC41: =AC40/AC38 -> 0.251797 | AD41: =AD40/AD38 -> 0.26238919 | AE41: =AVERAGE(AC41:AD41) -> 0.2570931 | AI41: Forging | AK41: 3162 | AL41: 1.1
B42: 종업원급여 | C42: 백만원 | D42: =P51 -> #REF! | E42: =Q51 -> #REF! | F42: =R51 -> #REF! | G42: =S51 -> #REF! | O42: 지급수수료 | P42: 9545010 | Q42: 13135121 | R42: 13777995 | S42: 19144745 | U42: 무형자산상각비 | V42: 무형자산상각비 | X42: 외주가공비 | AA42: 68726.184 | AB42: 124425.01 | AC42: 162700.68 | AD42: 169062.01 | AI42: 기타 | AK42: 7708 | AL42: 2.7
B43: 감가상각비 및 무형자산상각비 | C43: 백만원 | D43: =P52+P53 -> #REF! | E43: =Q52+Q53 -> #REF! | F43: =R52+R53 -> #REF! | G43: =S52+S53 -> #REF! | O43: 지급임차료 | P43: 439149 | Q43: 454860 | R43: 547485 | S43: 803576 | U43: 지급수수료 | V43: 지급수수료 | AA43: =AA42/AA38 -> 0.29259663 | AB43: =AB42/AB38 -> 0.37682042 | AC43: =AC42/AC38 -> 0.44284438 | AD43: =AD42/AD38 -> 0.41770414 | AH43: 외주가공비 등 | AI43: 가공·제작 | AJ43: 가공 및 제작 | AK43: 187057 | AL43: 65.4
B44: 운반비 | C44: 백만원 | D44: =P57 -> #REF! | E44: =Q57 -> #REF! | F44: =R57 -> #REF! | G44: =S57 -> #REF! | O44: 외주가공비 | P44: 68726184 | Q44: 124425012 | R44: 162700676 | S44: 169062007 | U44: 지급임차료 | V44: 지급임차료 | X44: 종업원급여 | AA44: 18100.127 | AB44: 19458.435 | AC44: 23214.915 | AD44: 26366.582 | AI44: & 설치
B45: 지급수수료 | C45: 백만원 | D45: =P54 -> #REF! | E45: =Q54 -> #REF! | F45: =R54 -> #REF! | G45: =S54 -> #REF! | O45: 운반비 | P45: 3344129 | Q45: 12327057 | R45: 8820988 | S45: 3350557 | U45: 운반비 | V45: 운반비 | AB45: =AB44/AA44-1 -> 0.075044114 | AC45: =AC44/AB44-1 -> 0.1930515 | AD45: =AD44/AC44-1 -> 0.13576044
B46: 지급임차료 | C46: 백만원 | D46: =P55 -> #REF! | E46: =Q55 -> #REF! | F46: =R55 -> #REF! | G46: =S55 -> #REF! | O46: 기타 | P46: 23439427 | Q46: 20389614 | R46: 26056290 | S46: 34736392 | U46: 기타 | V46: 여비교통비 | X46: 감가상각비 및 무형자산상각비 | AA46: 9744.074 | AB46: 9379.584 | AC46: 8879.341 | AD46: 4144.782
B47: 기타 | C47: 백만원 | D47: =P58 -> #REF! | E47: =Q58 -> #REF! | F47: =R58 -> #REF! | G47: =S58 -> #REF! | O47: 합 계 | P47: 265494596 | Q47: 322089055 | R47: 352312510 | S47: 382813780 | V47: 접대비 | X47: 운반비 | AA47: 3342.034 | AB47: 12326.903 | AC47: 8820.988 | AD47: 3349.84 | AG47: 품 목 | AJ47: 2021 | AK47: 2022 | AL47: 2023 | AM47: 2024 | AN47: 전망
V48: 통신비 | X48: 지급수수료 | AA48: 4363.501 | AB48: 7587.156 | AC48: 7757.874 | AD48: 10930.226 | AG48: TUBE | AH48: C/S | AI48: 국 내 | AJ48: 1800 | AK48: 1900 | AL48: 2800 | AM48: 2500 | AN48: 주요 원래료인 철강 가격은 중국 수요 둔화 및 공급과잉으로 하향압력 예상, 따라서 보수적 추정을 위해 현재 가격 유지
B49: 계정명 | C49: 단위 | D49: 202112 | E49: 202212 | F49: 202312 | G49: 202412 | H49: 202512 | I49: 202612 | J49: 202712 | K49: 202812 | O49: 매출원가 | P49: 2021 | Q49: 2022 | R49: 2023 | S49: 2024 | V49: 수도광열비 | X49: 지급임차료 | AA49: 183.549 | AB49: 71.24 | AC49: 154.613 | AD49: 293.057 | AH49: SUS | AI49: 국 내 | AJ49: 9000 | AK49: 10000 | AL49: 12000 | AM49: 11000 | AN49: 또한, 동사의 구매력 강화로 원재료비 절감 추세를 고려하면 보수적 추정
B50: 판매비와관리비(*) | C50: 백만원 | D50: 24245.078 | E50: 26823.584 | F50: 28354.888 | G50: 37190.759 | O50: 원재료 사용액 | P50: =P38 -> 118149580 | Q50: =Q38 -> 107443312 | R50: =R38 -> 92510020 | S50: =S38 -> 106199675 | V50: 전력비 | X50: 기타 | AA50: 18640.469 | AB50: 14573.829 | AC50: 19919.195 | AD50: 25276.852 | AH50: C/S | AI50: 해 외 | AJ50: 2.3 | AK50: 2.4 | AL50: 1.7 | AM50: 1.3 | AN50: 따라서 현재의 매출원가 대비 원재료 사용액 비중 최근 2개년 평균값으로 원재료 비중 설정
B51: 인건비(*) | C51: 백만원 | D51: 13000.707 | E51: 13948.49 | F51: 14157.436 | G51: 17165.349 | O51: 종업원급여 | P51: =P39-SUM(#REF!) -> #REF! | Q51: =Q39-SUM(#REF!) -> #REF! | R51: =R39-SUM(#REF!) -> #REF! | S51: =S39-SUM(#REF!) -> #REF! | V51: 세금과공과 | AH51: ALLOY | AI51: 해 외 | AJ51: 5.6 | AK51: 5.8 | AL51: 3.3 | AM51: 3
B52: 유무형자산상각비(*) | C52: 백만원 | D52: 1041.959 | E52: 1176.78 | F52: 1715.522 | G52: 1913.114 | O52: 감가상각비 | P52: =P40-#REF! -> #REF! | Q52: =Q40-#REF! -> #REF! | R52: =R40-#REF! -> #REF! | S52: =S40-#REF! -> #REF! | V52: 수선비 | AH52: SUS | AI52: 해 외 | AJ52: 13.5 | AK52: 14 | AL52: 12.5 | AM52: 12.1
B53: 판매비(*) | C53: 백만원 | D53: 19.025 | E53: 464.984 | F53: 207.734 | G53: 1484.122 | O53: 무형자산상각비 | P53: =P41-#REF! -> #REF! | Q53: =Q41-#REF! -> #REF! | R53: =R41-#REF! -> #REF! | S53: =S41-#REF! -> #REF! | V53: 보험료 | Y53: 234883.72 | Z53: 330197.11 | AA53: 367399.21 | AB53: 404741.04 | AC53: 1000 | AH53: Ti(관세포함) | AI53: 해 외 | AJ53: 25 | AK53: 24 | AL53: 24 | AM53: 24
B54: 관리비(*) | C54: 백만원 | D54: 10162.212 | E54: 11202.228 | F54: 12257.797 | G54: 16614.842 | O54: 지급수수료 | P54: =P42-#REF! -> #REF! | Q54: =Q42-#REF! -> #REF! | R54: =R42-#REF! -> #REF! | S54: =S42-#REF! -> #REF! | V54: 차량유지비 | X54: 지급수수료 | Y54: 9545.01 | Z54: 13135.121 | AA54: 13777.995 | AB54: 19144.745 | AG54: PIPE | AH54: C/S | AI54: 국 내 | AJ54: 1700 | AK54: 1800 | AL54: 2300 | AM54: 2100
B55: 기타 | C55: 백만원 | D55: 21.175 | E55: 31.102 | F55: 16.399 | G55: 13.332 | O55: 지급임차료 | P55: =P43-#REF! -> #REF! | Q55: =Q43-#REF! -> #REF! | R55: =R43-#REF! -> #REF! | S55: =S43-#REF! -> #REF! | V55: 교육훈련비 | Y55: =Y54/Y53 -> 0.040637172 | Z55: =Z54/Z53 -> 0.039779637 | AA55: =AA54/AA53 -> 0.037501428 | AB55: =AB54/AB53 -> 0.04730122 | AH55: SUS(SML‘S) | AI55: 국 내 | AJ55: 10000 | AK55: 11000 | AL55: 17000 | AM55: 12500
O56: 외주가공비 | P56: =P44 -> 68726184 | Q56: =Q44 -> 124425012 | R56: =R44 -> 162700676 | S56: =S44 -> 169062007 | V56: 도서인쇄비 | X56: 판관 | Y56: 5181.509 | Z56: 5547.965 | AA56: 6020.121 | AB56: 8214.519 | AH56: SUS (ERW) | AI56: 국 내 | AJ56: 5500 | AK56: 5800 | AL56: 7500 | AM56: 7000
B57: 계정명 | C57: 단위 | D57: 202112 | E57: 202212 | F57: 202312 | G57: 202412 | H57: 202512 | I57: 202612 | J57: 202712 | K57: 202812 | O57: 운반비 | P57: =P45-#REF! -> #REF! | Q57: =Q45-#REF! -> #REF! | R57: =R45-#REF! -> #REF! | S57: =S45-#REF! -> #REF! | V57: 사무용품비 | Y57: =Y56/Y53 -> 0.02205989 | Z57: =Z56/Z53 -> 0.016801979 | AA57: =AA56/AA53 -> 0.016385776 | AB57: =AB56/AB53 -> 0.02029574 | AG57: PLATE | AH57: C/S | AI57: 국 내 | AJ57: 1400 | AK57: 1450 | AL57: 1200 | AM57: 1100
B58: 금융수익(*) | C58: 백만원 | D58: 7196.576 | E58: 8323.576 | F58: 10770.512 | G58: 18569.587 | O58: 기타 | P58: =P46-SUM(#REF!) -> #REF! | Q58: =Q46-SUM(#REF!) -> #REF! | R58: =R46-SUM(#REF!) -> #REF! | S58: =S46-SUM(#REF!) -> #REF! | V58: 소모품비 | X58: 원가 | Y58: 4363.501 | Z58: 7587.156 | AA58: 7757.874 | AB58: 10930.226 | AH58: SUS | AI58: 국 내 | AJ58: 4500 | AK58: 5000 | AL58: 4000 | AM58: 3700
B59: 이자수익 | C59: 백만원 | D59: 141.376 | E59: 281.418 | F59: 958.346 | G59: 1352.583 | O59: 합 계 | P59: =SUM(P50:P58) -> #REF! | Q59: =SUM(Q50:Q58) -> #REF! | R59: =SUM(R50:R58) -> #REF! | S59: =SUM(S50:S58) -> #REF! | V59: 대손상각비 | Y59: =Y58/Y53 -> 0.018577282 | Z59: =Z58/Z53 -> 0.022977657 | AA59: =AA58/AA53 -> 0.021115652 | AB59: =AB58/AB53 -> 0.02700548
B60: 배당금수익 | C60: 백만원 | D60: 131.445 | E60: 92.436 | F60: 242.705 | G60: 190.575 | V60: 경조비
B61: 외환이익(*) | C61: 백만원 | D61: 5857.794 | E61: 7309.414 | F61: 8337.759 | G61: 16104.774 | V61: 보상비
B62: 금융자산평가이익(*) | C62: 백만원 | D62: 512.465 | E62: 637.608 | F62: 461.903 | G62: 571.28 | V62: 잡비
B63: 파생상품이익(*) | C63: 백만원 | D63: 553.496 | E63: 2.7 | F63: 769.799 | G63: 350.375 | V63: 합 계
B64: 금융원가(*) | C64: 백만원 | D64: 13853.979 | E64: 37272.428 | F64: 22758.852 | G64: 44883.533
B65: 이자비용 | C65: 백만원 | D65: 6922.606 | E65: 9204.768 | F65: 11546.804 | G65: 10416.514 | O65: 유형자산
B66: 외환손실(*) | C66: 백만원 | D66: 2956.485 | E66: 7109.659 | F66: 7083.603 | G66: 10073.078 | O66: (단위 : 천원)
B67: 매출채권처분손실 | C67: 백만원 | D67: 45.58 | E67: 4.603 | F67: 133.846 | G67: 31.97 | O67: 구 분 | P67: 취득원가 | Q67: 정부보조금 | R67: 감가상각누계액 | S67: 손상차손누계액 | T67: 장부금액
B68: 금융자산평가손실(*) | C68: 백만원 | D68: 14.327 | E68: 10.698 | F68: 63.125 | G68: 1.867 | O68: 토지 | P68: 144354284 | Q68: - | R68: - | S68: - | T68: 144354284
B69: 금융자산손상차손(*) | C69: 백만원 | F69: 1299.999 | O69: 건물 | P69: 66936647 | Q69: - | R69: -2655388 | S69: - | T69: 64281259
B70: 파생상품손실(*) | C70: 백만원 | D70: 3914.981 | E70: 20942.7 | F70: 2631.475 | G70: 21948.104 | O70: 구축물 | P70: 3767674 | Q70: -12089 | R70: -2286127 | S70: - | T70: 1469458
B71: 기타금융원가(*) | C71: 백만원 | G71: 2412 | O71: 기계장치 | P71: 26596797 | Q71: -247116 | R71: -20644750 | S71: -556 | T71: 5704375
B72: 금융손익 | D72: =D58-D64 -> -6657.403 | E72: =E58-E64 -> -28948.852 | F72: =F58-F64 -> -11988.34 | G72: =G58-G64 -> -26313.946 | H72: =H58-H64 -> 0 | I72: =I58-I64 -> 0 | J72: =J58-J64 -> 0 | K72: =K58-K64 -> 0 | O72: 차량운반구 | P72: 1422407 | Q72: - | R72: -970015 | S72: - | T72: 452392
O73: 공구와기구 | P73: 660510 | Q73: -49974 | R73: -581388 | S73: - | T73: 29148
O74: 비품 | P74: 4942327 | Q74: -1 | R74: -3933979 | S74: - | T74: 1008347
O75: 건설중인자산 | P75: 3617512 | Q75: - | R75: - | S75: - | T75: 3617512
O76: 사용권자산 | P76: 2066085 | Q76: - | R76: -650419 | S76: - | T76: 1415666
O77: 합 계 | P77: 254364243 | Q77: -309180 | R77: -31722066 | S77: -556 | T77: 222,332,44
P79: =P71/P77 -> 0.10456185

Sheet Case Summary
B1: Estimation
B2: Case Summary
B5: Active Scenario | C5: Base
B6: Scenario Number | C6: =IF(C5="Bull",1, IF(C5="Base",2,3)) -> 2
C7: =2000+RIGHT(C8,2) -> 2025 | D7: =2000+RIGHT(D8,2) -> 2025 | E7: =2000+RIGHT(E8,2) -> 2025 | F7: =2000+RIGHT(F8,2) -> 2025 | G7: =2000+RIGHT(G8,2) -> 2026 | H7: =2000+RIGHT(H8,2) -> 2026 | I7: =2000+RIGHT(I8,2) -> 2026 | J7: =2000+RIGHT(J8,2) -> 2026 | ... R7: =2000+RIGHT(R8,2) -> 2028
A8: x | B8: (단위: 백만 원) | C8: 1Q25 | D8: 2Q25 | E8: 3Q25 | F8: 4Q25 | G8: 1Q26 | H8: 2Q26 | I8: 3Q26 | J8: 4Q26 | K8: 1Q27 | L8: 2Q27 | M8: 3Q27 | N8: 4Q27 | O8: 1Q28 | P8: 2Q28 | Q8: 3Q28 | R8: 4Q28 | T8: 2024 | U8: 2025 | V8: 2026 | W8: 2027 | X8: 2028 | Z8: CAGR
B9: 매출액 | C9: 135275 | D9: =SUM(D11,D13,D15,D17) -> 144360.4 | E9: =SUM(E11,E13,E15,E17) -> 196610.33 | F9: =SUM(F11,F13,F15,F17) -> 247366.4 | G9: =SUM(G11,G13,G15,G17) -> 270455.87 | H9: =SUM(H11,H13,H15,H17) -> 273993.95 | I9: =SUM(I11,I13,I15,I17) -> 265735.06 | J9: =SUM(J11,J13,J15,J17) -> 245238.61 | K9: =SUM(K11,K13,K15,K17) -> 253748.96 | ... R9: =SUM(R11,R13,R15,R17) -> 276407.28 | T9: 404742 | U9: =SUM(U11,U13,U15,U17) -> 818060.13 | V9: =SUM(V11,V13,V15,V17) -> 1055423.5 | W9: =SUM(W11,W13,W15,W17) -> 1121745.8 | X9: =SUM(X11,X13,X15,X17) -> 1225142.9 | Z9: =RATE(3,0,-U9,X9) -> 0.14410839
B10: YoY / QoQ % | D10: =D9/C9-1 -> 0.067162443 | E10: =E9/D9-1 -> 0.36194088 | F10: =F9/E9-1 -> 0.25815566 | G10: =G9/F9-1 -> 0.093341188 | H10: =H9/G9-1 -> 0.013081892 | I10: =I9/H9-1 -> -0.030142603 | J10: =J9/I9-1 -> -0.077131148 | K10: =K9/J9-1 -> 0.034702361 | ... R10: =R9/Q9-1 -> -0.1797091 | U10: =U9/T9-1 -> 1.0211891 | V10: =V9/U9-1 -> 0.29015392 | W10: =W9/V9-1 -> 0.062839579 | X10: =X9/W9-1 -> 0.092175082
B11: HRSG | C11: =CHOOSE($C$6,HRSG!C42,HRSG!C47,HRSG!C52) -> 98656 | D11: =CHOOSE($C$6,HRSG!D42,HRSG!D47,HRSG!D52) -> 100885.48 | E11: =CHOOSE($C$6,HRSG!E42,HRSG!E47,HRSG!E52) -> 136278.53 | F11: =CHOOSE($C$6,HRSG!F42,HRSG!F47,HRSG!F52) -> 187034.6 | G11: =CHOOSE($C$6,HRSG!G42,HRSG!G47,HRSG!G52) -> 210124.07 | H11: =CHOOSE($C$6,HRSG!H42,HRSG!H47,HRSG!H52) -> 213662.14 | I11: =CHOOSE($C$6,HRSG!I42,HRSG!I47,HRSG!I52) -> 205403.25 | J11: =CHOOSE($C$6,HRSG!J42,HRSG!J47,HRSG!J52) -> 184906.8 | ... R11: =CHOOSE($C$6,HRSG!R42,HRSG!R47,HRSG!R52) -> 161686.25 | T11: 259014 | U11: =SUMIF($C$7:$R$7,U$8,$C11:$R11) -> 522854.61 | V11: =SUMIF($C$7:$R$7,V$8,$C11:$R11) -> 814096.27 | W11: =SUMIF($C$7:$R$7,W$8,$C11:$R11) -> 753165.03 | X11: =SUMIF($C$7:$R$7,X$8,$C11:$R11) -> 794672.44 | Z11: =RATE(3,0,-U11,X11) -> 0.14974731
B12: YoY % | D12: =D11/C11-1 -> 0.022598557 | E12: =E11/D11-1 -> 0.35082396 | F12: =F11/E11-1 -> 0.37244362 | G12: =G11/F11-1 -> 0.12345028 | H12: =H11/G11-1 -> 0.016838026 | I12: =I11/H11-1 -> -0.038653973 | J12: =J11/I11-1 -> -0.099786393 | K12: =K11/J11-1 -> -0.11114149 | ... R12: =R11/Q11-1 -> -0.27247493 | U12: =U11/T11-1 -> 1.0186345 | V12: =V11/U11-1 -> 0.55702228 | W12: =W11/V11-1 -> -0.07484525 | X12: =X11/W11-1 -> 0.055110636
B13: Boiler | C13: =Boiler!C9 -> 20124 | D13: =Boiler!D9 -> 20124 | E13: =Boiler!E9 -> 36980.886 | F13: =Boiler!F9 -> 36980.886 | G13: =Boiler!G9 -> 36980.886 | H13: =Boiler!H9 -> 36980.886 | I13: =Boiler!I9 -> 36980.886 | J13: =Boiler!J9 -> 36980.886 | ... R13: =Boiler!R9 -> 57400.886 | T13: 68413 | U13: =SUMIF($C$7:$R$7,U$8,$C13:$R13) -> 114209.77 | V13: =SUMIF($C$7:$R$7,V$8,$C13:$R13) -> 147923.54 | W13: =SUMIF($C$7:$R$7,W$8,$C13:$R13) -> 229603.54 | X13: =SUMIF($C$7:$R$7,X$8,$C13:$R13) -> 229603.54 | Z13: =RATE(3,0,-재무분석!W40,재무분석!Z40) -> 0.10708628
B14: YoY % | D14: =D13/C13-1 -> 0 | E14: =E13/D13-1 -> 0.83765085 | F14: =F13/E13-1 -> 0 | G14: =G13/F13-1 -> 0 | H14: =H13/G13-1 -> 0 | I14: =I13/H13-1 -> 0 | J14: =J13/I13-1 -> 0 | K14: =K13/J13-1 -> 0.55217715 | ... R14: =R13/Q13-1 -> 0 | U14: =U13/T13-1 -> 0.66941621 | V14: =V13/U13-1 -> 0.29519165 | W14: =W13/V13-1 -> 0.55217715 | X14: =X13/W13-1 -> 0
B15: BOP | C15: =CHOOSE($C$6,BOP!C53,BOP!C58,BOP!C63) -> 98656 | D15: =CHOOSE($C$6,BOP!D53,BOP!D58,BOP!D63) -> 11063.916 | E15: =CHOOSE($C$6,BOP!E53,BOP!E58,BOP!E63) -> 11063.916 | F15: =CHOOSE($C$6,BOP!F53,BOP!F58,BOP!F63) -> 11063.916 | G15: =CHOOSE($C$6,BOP!G53,BOP!G58,BOP!G63) -> 11063.916 | H15: =CHOOSE($C$6,BOP!H53,BOP!H58,BOP!H63) -> 11063.916 | I15: =CHOOSE($C$6,BOP!I53,BOP!I58,BOP!I63) -> 11063.916 | J15: =CHOOSE($C$6,BOP!J53,BOP!J58,BOP!J63) -> 11063.916 | ... R15: =CHOOSE($C$6,BOP!R53,BOP!R58,BOP!R63) -> 45033.147 | T15: 14305 | U15: =SUMIF($C$7:$R$7,U$8,$C15:$R15) -> 131847.75 | V15: =SUMIF($C$7:$R$7,V$8,$C15:$R15) -> 44255.665 | W15: =SUMIF($C$7:$R$7,W$8,$C15:$R15) -> 89829.271 | X15: =SUMIF($C$7:$R$7,X$8,$C15:$R15) -> 151718.88 | Z15: =RATE(3,0,-U15,X15) -> 0.047905947
B16: YoY % | D16: =D15/C15-1 -> -0.88785359 | E16: =E15/D15-1 -> 0 | F16: =F15/E15-1 -> 0 | G16: =G15/F15-1 -> 0 | H16: =H15/G15-1 -> 0 | I16: =I15/H15-1 -> 0 | J16: =J15/I15-1 -> 0 | K16: =K15/J15-1 -> 0.78102331 | ... R16: =R15/Q15-1 -> 0 | U16: =U15/T15-1 -> 8.2168996 | V16: =V15/U15-1 -> -0.66434266 | W16: =W15/V15-1 -> 1.0297802 | X16: =X15/W15-1 -> 0.68896932
B17: 기타 | C17: 12287 | D17: =C17 -> 12287 | E17: =D17 -> 12287 | F17: =E17 -> 12287 | G17: =F17 -> 12287 | H17: =G17 -> 12287 | I17: =H17 -> 12287 | J17: =I17 -> 12287 | K17: =J17 -> 12287 | ... R17: =Q17 -> 12287 | T17: 63010 | U17: =SUMIF($C$7:$R$7,U$8,$C17:$R17) -> 49148 | V17: =SUMIF($C$7:$R$7,V$8,$C17:$R17) -> 49148 | W17: =SUMIF($C$7:$R$7,W$8,$C17:$R17) -> 49148 | X17: =SUMIF($C$7:$R$7,X$8,$C17:$R17) -> 49148 | Z17: =RATE(3,0,-U17,X17) -> 4.5814405e-14
B18: YoY % | D18: =D17/C17-1 -> 0 | E18: =E17/D17-1 -> 0 | F18: =F17/E17-1 -> 0 | G18: =G17/F17-1 -> 0 | H18: =H17/G17-1 -> 0 | I18: =I17/H17-1 -> 0 | J18: =J17/I17-1 -> 0 | K18: =K17/J17-1 -> 0 | ... R18: =R17/Q17-1 -> 0 | U18: =U17/T17-1 -> -0.21999683 | V18: =V17/U17-1 -> 0 | W18: =W17/V17-1 -> 0 | X18: =X17/W17-1 -> 0
B20: (단위: 백만 원) | C20: 2016 | D20: =C20+1 -> 2017 | E20: =D20+1 -> 2018 | F20: =E20+1 -> 2019 | G20: =F20+1 -> 2020 | H20: =G20+1 -> 2021 | I20: =H20+1 -> 2022 | J20: =I20+1 -> 2023 | K20: =J20+1 -> 2024 | ... O20: =N20+1 -> 2028
A21: x | B21: 신규수주 | C21: =SUMIF(수주내역!$G$4:$G$68,C$20,수주내역!$E$4:$E$68) -> 255521.71 | D21: =SUMIF(수주내역!$G$4:$G$68,D$20,수주내역!$E$4:$E$68) -> 47224.688 | E21: =SUMIF(수주내역!$G$4:$G$68,E$20,수주내역!$E$4:$E$68) -> 50863.127 | F21: =SUMIF(수주내역!$G$4:$G$68,F$20,수주내역!$E$4:$E$68) -> 118121.03 | G21: =SUMIF(수주내역!$G$4:$G$68,G$20,수주내역!$E$4:$E$68) -> 143578.22 | H21: =SUMIF(수주내역!$G$4:$G$68,H$20,수주내역!$E$4:$E$68) -> 349188.39 | I21: =SUMIF(수주내역!$G$4:$G$68,I$20,수주내역!$E$4:$E$68) -> 313975.63 | J21: =SUMIF(수주내역!$G$4:$G$68,J$20,수주내역!$E$4:$E$68) -> 360259.61 | K21: =SUMIF(수주내역!$G$4:$G$68,K$20,수주내역!$E$4:$E$68) -> 1344171.6 | L21: =SUM(L22,L29,L30,L31,L32) -> 1613571.5 | M21: =SUM(M22,M29,M30,M31,M32) -> 995986.71 | N21: =SUM(N22,N29,N30,N31,N32) -> 1273498.1 | O21: =SUM(O22,O29,O30,O31,O32) -> 390261.74
B22: HRSG | C22: =SUMIFS(수주내역!$E$4:$E$68,수주내역!$C$4:$C$68,$B22,수주내역!$G$4:$G$68,C$20) -> 65858.959 | D22: =SUMIFS(수주내역!$E$4:$E$68,수주내역!$C$4:$C$68,$B22,수주내역!$G$4:$G$68,D$20) -> 47224.688 | E22: =SUMIFS(수주내역!$E$4:$E$68,수주내역!$C$4:$C$68,$B22,수주내역!$G$4:$G$68,E$20) -> 0 | F22: =SUMIFS(수주내역!$E$4:$E$68,수주내역!$C$4:$C$68,$B22,수주내역!$G$4:$G$68,F$20) -> 57152.291 | G22: =SUMIFS(수주내역!$E$4:$E$68,수주내역!$C$4:$C$68,$B22,수주내역!$G$4:$G$68,G$20) -> 143578.22 | H22: =SUMIFS(수주내역!$E$4:$E$68,수주내역!$C$4:$C$68,$B22,수주내역!$G$4:$G$68,H$20) -> 180863.44 | I22: =SUMIFS(수주내역!$E$4:$E$68,수주내역!$C$4:$C$68,$B22,수주내역!$G$4:$G$68,I$20) -> 206944.62 | J22: =SUMIFS(수주내역!$E$4:$E$68,수주내역!$C$4:$C$68,$B22,수주내역!$G$4:$G$68,J$20) -> 104341.65 | K22: =SUMIFS(수주내역!$E$4:$E$68,수주내역!$C$4:$C$68,$B22,수주내역!$G$4:$G$68,K$20) -> 1071639.3 | L22: =SUMIFS(수주내역!$E$4:$E$68,수주내역!$C$4:$C$68,$B22,수주내역!$G$4:$G$68,L$20)+CHOOSE($C$6,'Case Summary'!J36,'Case Summary'!J37,'Case Summary'!J38) -> 777716.77 | M22: =CHOOSE($C$6,'Case Summary'!K36,'Case Summary'!K37,'Case Summary'!K38) -> 838618.5 | N22: =CHOOSE($C$6,'Case Summary'!L36,'Case Summary'!L37,'Case Summary'!L38) -> 688599.07 | O22: =CHOOSE($C$6,'Case Summary'!M36,'Case Summary'!M37,'Case Summary'!M38) -> 66187.838
B23: 국내 | C23: =SUMIFS(수주내역!$E$4:$E$68,수주내역!$C$4:$C$68,'Case Summary'!$B$22,수주내역!$D$4:$D$68,'Case Summary'!$B23,수주내역!$G$4:$G$68,'Case Summary'!C$20) -> 0 | D23: =SUMIFS(수주내역!$E$4:$E$68,수주내역!$C$4:$C$68,'Case Summary'!$B$22,수주내역!$D$4:$D$68,'Case Summary'!$B23,수주내역!$G$4:$G$68,'Case Summary'!D$20) -> 0 | E23: =SUMIFS(수주내역!$E$4:$E$68,수주내역!$C$4:$C$68,'Case Summary'!$B$22,수주내역!$D$4:$D$68,'Case Summary'!$B23,수주내역!$G$4:$G$68,'Case Summary'!E$20) -> 0 | F23: =SUMIFS(수주내역!$E$4:$E$68,수주내역!$C$4:$C$68,'Case Summary'!$B$22,수주내역!$D$4:$D$68,'Case Summary'!$B23,수주내역!$G$4:$G$68,'Case Summary'!F$20) -> 0 | G23: =SUMIFS(수주내역!$E$4:$E$68,수주내역!$C$4:$C$68,'Case Summary'!$B$22,수주내역!$D$4:$D$68,'Case Summary'!$B23,수주내역!$G$4:$G$68,'Case Summary'!G$20) -> 92547.218 | H23: =SUMIFS(수주내역!$E$4:$E$68,수주내역!$C$4:$C$68,'Case Summary'!$B$22,수주내역!$D$4:$D$68,'Case Summary'!$B23,수주내역!$G$4:$G$68,'Case Summary'!H$20) -> 41326.552 | I23: =SUMIFS(수주내역!$E$4:$E$68,수주내역!$C$4:$C$68,'Case Summary'!$B$22,수주내역!$D$4:$D$68,'Case Summary'!$B23,수주내역!$G$4:$G$68,'Case Summary'!I$20) -> 153838.69 | J23: =SUMIFS(수주내역!$E$4:$E$68,수주내역!$C$4:$C$68,'Case Summary'!$B$22,수주내역!$D$4:$D$68,'Case Summary'!$B23,수주내역!$G$4:$G$68,'Case Summary'!J$20) -> 87500 | K23: =SUMIFS(수주내역!$E$4:$E$68,수주내역!$C$4:$C$68,'Case Summary'!$B$22,수주내역!$D$4:$D$68,'Case Summary'!$B23,수주내역!$G$4:$G$68,'Case Summary'!K$20) -> 272266.21 | L23: =SUMIFS(수주내역!$E$4:$E$68,수주내역!$C$4:$C$68,'Case Summary'!$B$22,수주내역!$D$4:$D$68,'Case Summary'!$B23,수주내역!$G$4:$G$68,'Case Summary'!L$20)+CHOOSE($C$6,'Case Summary'!C36,'Case Summary'!C37,'Case Summary'!C38) -> 43475 | M23: =CHOOSE($C$6,'Case Summary'!D36,'Case Summary'!D37,'Case Summary'!D38) -> 43475 | N23: =CHOOSE($C$6,'Case Summary'!E36,'Case Summary'!E37,'Case Summary'!E38) -> 165707.14 | O23: =CHOOSE($C$6,'Case Summary'!F36,'Case Summary'!F37,'Case Summary'!F38) -> 0
B24: 해외 | C24: =SUM(C25:C28) -> 65858.959 | D24: =SUM(D25:D28) -> 47224.688 | E24: =SUM(E25:E28) -> 0 | F24: =SUM(F25:F28) -> 57152.291 | G24: =SUM(G25:G28) -> 51031 | H24: =SUM(H25:H28) -> 139536.89 | I24: =SUM(I25:I28) -> 53105.933 | J24: =SUM(J25:J28) -> 16841.65 | ... O24: =SUM(O25:O28) -> 66187.838
B25: 중동 | C25: =SUMIFS(수주내역!$E$4:$E$68,수주내역!$C$4:$C$68,'Case Summary'!$B$22,수주내역!$D$4:$D$68,'Case Summary'!$B25,수주내역!$G$4:$G$68,'Case Summary'!C$20) -> 0 | D25: =SUMIFS(수주내역!$E$4:$E$68,수주내역!$C$4:$C$68,'Case Summary'!$B$22,수주내역!$D$4:$D$68,'Case Summary'!$B25,수주내역!$G$4:$G$68,'Case Summary'!D$20) -> 47224.688 | E25: =SUMIFS(수주내역!$E$4:$E$68,수주내역!$C$4:$C$68,'Case Summary'!$B$22,수주내역!$D$4:$D$68,'Case Summary'!$B25,수주내역!$G$4:$G$68,'Case Summary'!E$20) -> 0 | F25: =SUMIFS(수주내역!$E$4:$E$68,수주내역!$C$4:$C$68,'Case Summary'!$B$22,수주내역!$D$4:$D$68,'Case Summary'!$B25,수주내역!$G$4:$G$68,'Case Summary'!F$20) -> 0 | G25: =SUMIFS(수주내역!$E$4:$E$68,수주내역!$C$4:$C$68,'Case Summary'!$B$22,수주내역!$D$4:$D$68,'Case Summary'!$B25,수주내역!$G$4:$G$68,'Case Summary'!G$20) -> 0 | H25: =SUMIFS(수주내역!$E$4:$E$68,수주내역!$C$4:$C$68,'Case Summary'!$B$22,수주내역!$D$4:$D$68,'Case Summary'!$B25,수주내역!$G$4:$G$68,'Case Summary'!H$20) -> 0 | I25: =SUMIFS(수주내역!$E$4:$E$68,수주내역!$C$4:$C$68,'Case Summary'!$B$22,수주내역!$D$4:$D$68,'Case Summary'!$B25,수주내역!$G$4:$G$68,'Case Summary'!I$20) -> 0 | J25: =SUMIFS(수주내역!$E$4:$E$68,수주내역!$C$4:$C$68,'Case Summary'!$B$22,수주내역!$D$4:$D$68,'Case Summary'!$B25,수주내역!$G$4:$G$68,'Case Summary'!J$20) -> 0 | K25: =SUMIFS(수주내역!$E$4:$E$68,수주내역!$C$4:$C$68,'Case Summary'!$B$22,수주내역!$D$4:$D$68,'Case Summary'!$B25,수주내역!$G$4:$G$68,'Case Summary'!K$20) -> 409476.53 | L25: =SUMIFS(수주내역!$E$4:$E$68,수주내역!$C$4:$C$68,'Case Summary'!$B$22,수주내역!$D$4:$D$68,'Case Summary'!$B25,수주내역!$G$4:$G$68,'Case Summary'!L$20)+CHOOSE($C$6,'Case Summary'!C41,'Case Summary'!C42,'Case Summary'!C43) -> 601866.09 | M25: =CHOOSE($C$6,'Case Summary'!D41,'Case Summary'!D42,'Case Summary'!D43) -> 634608.99 | N25: =CHOOSE($C$6,'Case Summary'!E41,'Case Summary'!E42,'Case Summary'!E43) -> 359582.52 | O25: =CHOOSE($C$6,'Case Summary'!F41,'Case Summary'!F42,'Case Summary'!F43) -> 0
B26: 일본 | C26: =SUMIFS(수주내역!$E$4:$E$68,수주내역!$C$4:$C$68,'Case Summary'!$B$22,수주내역!$D$4:$D$68,'Case Summary'!$B26,수주내역!$G$4:$G$68,'Case Summary'!C$20) -> 0 | D26: =SUMIFS(수주내역!$E$4:$E$68,수주내역!$C$4:$C$68,'Case Summary'!$B$22,수주내역!$D$4:$D$68,'Case Summary'!$B26,수주내역!$G$4:$G$68,'Case Summary'!D$20) -> 0 | E26: =SUMIFS(수주내역!$E$4:$E$68,수주내역!$C$4:$C$68,'Case Summary'!$B$22,수주내역!$D$4:$D$68,'Case Summary'!$B26,수주내역!$G$4:$G$68,'Case Summary'!E$20) -> 0 | F26: =SUMIFS(수주내역!$E$4:$E$68,수주내역!$C$4:$C$68,'Case Summary'!$B$22,수주내역!$D$4:$D$68,'Case Summary'!$B26,수주내역!$G$4:$G$68,'Case Summary'!F$20) -> 0 | G26: =SUMIFS(수주내역!$E$4:$E$68,수주내역!$C$4:$C$68,'Case Summary'!$B$22,수주내역!$D$4:$D$68,'Case Summary'!$B26,수주내역!$G$4:$G$68,'Case Summary'!G$20) -> 0 | H26: =SUMIFS(수주내역!$E$4:$E$68,수주내역!$C$4:$C$68,'Case Summary'!$B$22,수주내역!$D$4:$D$68,'Case Summary'!$B26,수주내역!$G$4:$G$68,'Case Summary'!H$20) -> 0 | I26: =SUMIFS(수주내역!$E$4:$E$68,수주내역!$C$4:$C$68,'Case Summary'!$B$22,수주내역!$D$4:$D$68,'Case Summary'!$B26,수주내역!$G$4:$G$68,'Case Summary'!I$20) -> 0 | J26: =SUMIFS(수주내역!$E$4:$E$68,수주내역!$C$4:$C$68,'Case Summary'!$B$22,수주내역!$D$4:$D$68,'Case Summary'!$B26,수주내역!$G$4:$G$68,'Case Summary'!J$20) -> 16841.65 | K26: =SUMIFS(수주내역!$E$4:$E$68,수주내역!$C$4:$C$68,'Case Summary'!$B$22,수주내역!$D$4:$D$68,'Case Summary'!$B26,수주내역!$G$4:$G$68,'Case Summary'!K$20) -> 389896.53 | L26: =SUMIFS(수주내역!$E$4:$E$68,수주내역!$C$4:$C$68,'Case Summary'!$B$22,수주내역!$D$4:$D$68,'Case Summary'!$B26,수주내역!$G$4:$G$68,'Case Summary'!L$20)+CHOOSE($C$6,'Case Summary'!C51,'Case Summary'!C52,'Case Summary'!C53) -> 132375.68 | M26: =CHOOSE($C$6,'Case Summary'!D51,'Case Summary'!D52,'Case Summary'!D53) -> 66187.838 | N26: =CHOOSE($C$6,'Case Summary'!E51,'Case Summary'!E52,'Case Summary'!E53) -> 66187.838 | O26: =CHOOSE($C$6,'Case Summary'!F51,'Case Summary'!F52,'Case Summary'!F53) -> 66187.838
B27: 미국 | C27: 0 | D27: 0 | E27: 0 | F27: 0 | G27: 0 | H27: 0 | I27: 0 | J27: 0 | K27: 0 | L27: 0 | M27: =CHOOSE($C$6,'Case Summary'!D46,'Case Summary'!D47,'Case Summary'!D48) -> 94346.67 | N27: =CHOOSE($C$6,'Case Summary'!E46,'Case Summary'!E47,'Case Summary'!E48) -> 97121.572 | O27: =CHOOSE($C$6,'Case Summary'!F46,'Case Summary'!F47,'Case Summary'!F48) -> 0
B28: 기타 | C28: =SUMIFS(수주내역!$E$4:$E$68,수주내역!$C$4:$C$68,'Case Summary'!$B$22,수주내역!$D$4:$D$68,"해외",수주내역!$G$4:$G$68,'Case Summary'!C$20) -> 65858.959 | D28: =SUMIFS(수주내역!$E$4:$E$68,수주내역!$C$4:$C$68,'Case Summary'!$B$22,수주내역!$D$4:$D$68,"해외",수주내역!$G$4:$G$68,'Case Summary'!D$20) -> 0 | E28: =SUMIFS(수주내역!$E$4:$E$68,수주내역!$C$4:$C$68,'Case Summary'!$B$22,수주내역!$D$4:$D$68,"해외",수주내역!$G$4:$G$68,'Case Summary'!E$20) -> 0 | F28: =SUMIFS(수주내역!$E$4:$E$68,수주내역!$C$4:$C$68,'Case Summary'!$B$22,수주내역!$D$4:$D$68,"해외",수주내역!$G$4:$G$68,'Case Summary'!F$20) -> 57152.291 | G28: =SUMIFS(수주내역!$E$4:$E$68,수주내역!$C$4:$C$68,'Case Summary'!$B$22,수주내역!$D$4:$D$68,"해외",수주내역!$G$4:$G$68,'Case Summary'!G$20) -> 51031 | H28: =SUMIFS(수주내역!$E$4:$E$68,수주내역!$C$4:$C$68,'Case Summary'!$B$22,수주내역!$D$4:$D$68,"해외",수주내역!$G$4:$G$68,'Case Summary'!H$20) -> 139536.89 | I28: =SUMIFS(수주내역!$E$4:$E$68,수주내역!$C$4:$C$68,'Case Summary'!$B$22,수주내역!$D$4:$D$68,"해외",수주내역!$G$4:$G$68,'Case Summary'!I$20) -> 53105.933 | J28: =SUMIFS(수주내역!$E$4:$E$68,수주내역!$C$4:$C$68,'Case Summary'!$B$22,수주내역!$D$4:$D$68,"해외",수주내역!$G$4:$G$68,'Case Summary'!J$20) -> 0 | ... L28: =SUMIFS(수주내역!$E$4:$E$68,수주내역!$C$4:$C$68,'Case Summary'!$B$22,수주내역!$D$4:$D$68,"해외",수주내역!$G$4:$G$68,'Case Summary'!L$20) -> 0 | M28: 0 | N28: 0 | O28: 0
B29: Boiler | C29: =SUMIFS(수주내역!$E$4:$E$68,수주내역!$C$4:$C$68,$B29,수주내역!$G$4:$G$68,C$20) -> 113969.99 | D29: =SUMIFS(수주내역!$E$4:$E$68,수주내역!$C$4:$C$68,$B29,수주내역!$G$4:$G$68,D$20) -> 0 | E29: =SUMIFS(수주내역!$E$4:$E$68,수주내역!$C$4:$C$68,$B29,수주내역!$G$4:$G$68,E$20) -> 50863.127 | F29: =SUMIFS(수주내역!$E$4:$E$68,수주내역!$C$4:$C$68,$B29,수주내역!$G$4:$G$68,F$20) -> 32268.741 | G29: =SUMIFS(수주내역!$E$4:$E$68,수주내역!$C$4:$C$68,$B29,수주내역!$G$4:$G$68,G$20) -> 0 | H29: =SUMIFS(수주내역!$E$4:$E$68,수주내역!$C$4:$C$68,$B29,수주내역!$G$4:$G$68,H$20) -> 77427.682 | I29: =SUMIFS(수주내역!$E$4:$E$68,수주내역!$C$4:$C$68,$B29,수주내역!$G$4:$G$68,I$20) -> 107031 | J29: =SUMIFS(수주내역!$E$4:$E$68,수주내역!$C$4:$C$68,$B29,수주내역!$G$4:$G$68,J$20) -> 255917.96 | ... L29: =SUMIFS(수주내역!$E$4:$E$68,수주내역!$C$4:$C$68,$B29,수주내역!$G$4:$G$68,L$20) -> 517732.4 | M29: 0 | N29: 0 | O29: 0
B30: BOP | C30: =SUMIFS(수주내역!$E$4:$E$68,수주내역!$C$4:$C$68,$B30,수주내역!$G$4:$G$68,C$20) -> 75692.754 | D30: =SUMIFS(수주내역!$E$4:$E$68,수주내역!$C$4:$C$68,$B30,수주내역!$G$4:$G$68,D$20) -> 0 | E30: =SUMIFS(수주내역!$E$4:$E$68,수주내역!$C$4:$C$68,$B30,수주내역!$G$4:$G$68,E$20) -> 0 | F30: =SUMIFS(수주내역!$E$4:$E$68,수주내역!$C$4:$C$68,$B30,수주내역!$G$4:$G$68,F$20) -> 0 | G30: =SUMIFS(수주내역!$E$4:$E$68,수주내역!$C$4:$C$68,$B30,수주내역!$G$4:$G$68,G$20) -> 0 | H30: =SUMIFS(수주내역!$E$4:$E$68,수주내역!$C$4:$C$68,$B30,수주내역!$G$4:$G$68,H$20) -> 90897.264 | I30: =SUMIFS(수주내역!$E$4:$E$68,수주내역!$C$4:$C$68,$B30,수주내역!$G$4:$G$68,I$20) -> 0 | J30: =SUMIFS(수주내역!$E$4:$E$68,수주내역!$C$4:$C$68,$B30,수주내역!$G$4:$G$68,J$20) -> 0 | K30: =SUMIFS(수주내역!$E$4:$E$68,수주내역!$C$4:$C$68,$B30,수주내역!$G$4:$G$68,K$20) -> 91538.3 | L30: =SUMIFS(수주내역!$E$4:$E$68,수주내역!$C$4:$C$68,$B30,수주내역!$G$4:$G$68,L$20)+CHOOSE($C$6,J41,J42,J43) -> 318122.29 | M30: =CHOOSE($C$6,K41,K42,K43) -> 157368.21 | N30: =CHOOSE($C$6,L41,L42,L43) -> 584898.99 | O30: =CHOOSE($C$6,M41,M42,M43) -> 324073.9
B31: EPC | C31: =SUMIFS(수주내역!$E$4:$E$68,수주내역!$C$4:$C$68,$B31,수주내역!$G$4:$G$68,C$20) -> 0 | D31: =SUMIFS(수주내역!$E$4:$E$68,수주내역!$C$4:$C$68,$B31,수주내역!$G$4:$G$68,D$20) -> 0 | E31: =SUMIFS(수주내역!$E$4:$E$68,수주내역!$C$4:$C$68,$B31,수주내역!$G$4:$G$68,E$20) -> 0 | F31: =SUMIFS(수주내역!$E$4:$E$68,수주내역!$C$4:$C$68,$B31,수주내역!$G$4:$G$68,F$20) -> 0 | G31: =SUMIFS(수주내역!$E$4:$E$68,수주내역!$C$4:$C$68,$B31,수주내역!$G$4:$G$68,G$20) -> 0 | H31: =SUMIFS(수주내역!$E$4:$E$68,수주내역!$C$4:$C$68,$B31,수주내역!$G$4:$G$68,H$20) -> 0 | I31: =SUMIFS(수주내역!$E$4:$E$68,수주내역!$C$4:$C$68,$B31,수주내역!$G$4:$G$68,I$20) -> 0 | J31: =SUMIFS(수주내역!$E$4:$E$68,수주내역!$C$4:$C$68,$B31,수주내역!$G$4:$G$68,J$20) -> 0 | ... L31: =SUMIFS(수주내역!$E$4:$E$68,수주내역!$C$4:$C$68,$B31,수주내역!$G$4:$G$68,L$20) -> 0 | M31: 0 | N31: 0 | O31: 0
B32: 기타 | C32: =SUMIFS(수주내역!$E$4:$E$68,수주내역!$C$4:$C$68,$B32,수주내역!$G$4:$G$68,C$20) -> 0 | D32: =SUMIFS(수주내역!$E$4:$E$68,수주내역!$C$4:$C$68,$B32,수주내역!$G$4:$G$68,D$20) -> 0 | E32: =SUMIFS(수주내역!$E$4:$E$68,수주내역!$C$4:$C$68,$B32,수주내역!$G$4:$G$68,E$20) -> 0 | F32: =SUMIFS(수주내역!$E$4:$E$68,수주내역!$C$4:$C$68,$B32,수주내역!$G$4:$G$68,F$20) -> 28700 | G32: =SUMIFS(수주내역!$E$4:$E$68,수주내역!$C$4:$C$68,$B32,수주내역!$G$4:$G$68,G$20) -> 0 | H32: =SUMIFS(수주내역!$E$4:$E$68,수주내역!$C$4:$C$68,$B32,수주내역!$G$4:$G$68,H$20) -> 0 | I32: =SUMIFS(수주내역!$E$4:$E$68,수주내역!$C$4:$C$68,$B32,수주내역!$G$4:$G$68,I$20) -> 0 | J32: =SUMIFS(수주내역!$E$4:$E$68,수주내역!$C$4:$C$68,$B32,수주내역!$G$4:$G$68,J$20) -> 0 | ... L32: =SUMIFS(수주내역!$E$4:$E$68,수주내역!$C$4:$C$68,$B32,수주내역!$G$4:$G$68,L$20) -> 0 | M32: 0 | N32: 0 | O32: 0
B35: HRSG 국내 | C35: 2025 | D35: 2026 | E35: 2027 | F35: 2028 | G35: 2029 | I35: HRSG 전체 | J35: 2025 | K35: 2026 | L35: 2027 | M35: 2028 | N35: 2029
B36: Bull | C36: =C37+SUMIFS('HRSG 수주 시나리오'!$F$16:$F$21,'HRSG 수주 시나리오'!$B$16:$B$21,"잠재",'HRSG 수주 시나리오'!$I$16:$I$21,C$40) -> 107646.88 | D36: =D37+SUMIFS('HRSG 수주 시나리오'!$F$16:$F$21,'HRSG 수주 시나리오'!$B$16:$B$21,"잠재",'HRSG 수주 시나리오'!$I$16:$I$21,D$40) -> 43475 | E36: =E37+SUMIFS('HRSG 수주 시나리오'!$F$16:$F$21,'HRSG 수주 시나리오'!$B$16:$B$21,"잠재",'HRSG 수주 시나리오'!$I$16:$I$21,E$40) -> 229879.02 | F36: =F37+SUMIFS('HRSG 수주 시나리오'!$F$16:$F$21,'HRSG 수주 시나리오'!$B$16:$B$21,"잠재",'HRSG 수주 시나리오'!$I$16:$I$21,F$40) -> 0 | G36: =G37+SUMIFS('HRSG 수주 시나리오'!$F$16:$F$21,'HRSG 수주 시나리오'!$B$16:$B$21,"잠재",'HRSG 수주 시나리오'!$I$16:$I$21,G$40) -> 0 | I36: Bull | J36: =SUMIF($B$35:$B$53,$I36,C$35:C$53) -> 173834.71 | K36: =SUMIF($B$35:$B$53,$I36,D$35:D$53) -> 838618.5 | L36: =SUMIF($B$35:$B$53,$I36,E$35:E$53) -> 930518.01 | M36: =SUMIF($B$35:$B$53,$I36,F$35:F$53) -> 66187.838 | N36: =SUMIF($B$35:$B$53,$I36,G$35:G$53) -> 0
B37: Base | C37: =C38+SUMIFS('HRSG 수주 시나리오'!$F$16:$F$21,'HRSG 수주 시나리오'!$B$16:$B$21,"가능",'HRSG 수주 시나리오'!$I$16:$I$21,C$40) -> 43475 | D37: =D38+SUMIFS('HRSG 수주 시나리오'!$F$16:$F$21,'HRSG 수주 시나리오'!$B$16:$B$21,"가능",'HRSG 수주 시나리오'!$I$16:$I$21,D$40) -> 43475 | E37: =E38+SUMIFS('HRSG 수주 시나리오'!$F$16:$F$21,'HRSG 수주 시나리오'!$B$16:$B$21,"가능",'HRSG 수주 시나리오'!$I$16:$I$21,E$40) -> 165707.14 | F37: =F38+SUMIFS('HRSG 수주 시나리오'!$F$16:$F$21,'HRSG 수주 시나리오'!$B$16:$B$21,"가능",'HRSG 수주 시나리오'!$I$16:$I$21,F$40) -> 0 | G37: =G38+SUMIFS('HRSG 수주 시나리오'!$F$16:$F$21,'HRSG 수주 시나리오'!$B$16:$B$21,"가능",'HRSG 수주 시나리오'!$I$16:$I$21,G$40) -> 0 | I37: Base | J37: =SUMIF($B$35:$B$53,$I37,C$35:C$53) -> 109662.84 | K37: =SUMIF($B$35:$B$53,$I37,D$35:D$53) -> 838618.5 | L37: =SUMIF($B$35:$B$53,$I37,E$35:E$53) -> 688599.07 | M37: =SUMIF($B$35:$B$53,$I37,F$35:F$53) -> 66187.838 | N37: =SUMIF($B$35:$B$53,$I37,G$35:G$53) -> 0
B38: Bear | C38: =SUMIFS('HRSG 수주 시나리오'!$F$16:$F$21,'HRSG 수주 시나리오'!$B$16:$B$21,"확실",'HRSG 수주 시나리오'!$I$16:$I$21,C$40) -> 43475 | D38: =SUMIFS('HRSG 수주 시나리오'!$F$16:$F$21,'HRSG 수주 시나리오'!$B$16:$B$21,"확실",'HRSG 수주 시나리오'!$I$16:$I$21,D$40) -> 43475 | E38: =SUMIFS('HRSG 수주 시나리오'!$F$16:$F$21,'HRSG 수주 시나리오'!$B$16:$B$21,"확실",'HRSG 수주 시나리오'!$I$16:$I$21,E$40) -> 0 | F38: =SUMIFS('HRSG 수주 시나리오'!$F$16:$F$21,'HRSG 수주 시나리오'!$B$16:$B$21,"확실",'HRSG 수주 시나리오'!$I$16:$I$21,F$40) -> 0 | G38: =SUMIFS('HRSG 수주 시나리오'!$F$16:$F$21,'HRSG 수주 시나리오'!$B$16:$B$21,"확실",'HRSG 수주 시나리오'!$I$16:$I$21,G$40) -> 0 | I38: Bear | J38: =SUMIF($B$35:$B$53,$I38,C$35:C$53) -> 43475 | K38: =SUMIF($B$35:$B$53,$I38,D$35:D$53) -> 388111.99 | L38: =SUMIF($B$35:$B$53,$I38,E$35:E$53) -> 140922.57 | M38: =SUMIF($B$35:$B$53,$I38,F$35:F$53) -> 0 | N38: =SUMIF($B$35:$B$53,$I38,G$35:G$53) -> 0
B40: HRSG 중동 | C40: 2025 | D40: 2026 | E40: 2027 | F40: 2028 | G40: 2029 | I40: BOP 전체 | J40: 2025 | K40: 2026 | L40: 2027 | M40: 2028 | N40: 2029
B41: Bull | C41: =C42+SUMIFS('HRSG 수주 시나리오'!$F$38:$F$44,'HRSG 수주 시나리오'!$B$38:$B$44,"잠재",'HRSG 수주 시나리오'!$I$38:$I$44,C$40) -> 0 | D41: =D42+SUMIFS('HRSG 수주 시나리오'!$F$38:$F$44,'HRSG 수주 시나리오'!$B$38:$B$44,"잠재",'HRSG 수주 시나리오'!$I$38:$I$44,D$40) -> 634608.99 | E41: =E42+SUMIFS('HRSG 수주 시나리오'!$F$38:$F$44,'HRSG 수주 시나리오'!$B$38:$B$44,"잠재",'HRSG 수주 시나리오'!$I$38:$I$44,E$40) -> 454082.52 | F41: =F42+SUMIFS('HRSG 수주 시나리오'!$F$38:$F$44,'HRSG 수주 시나리오'!$B$38:$B$44,"잠재",'HRSG 수주 시나리오'!$I$38:$I$44,F$40) -> 0 | G41: =G42+SUMIFS('HRSG 수주 시나리오'!$F$38:$F$44,'HRSG 수주 시나리오'!$B$38:$B$44,"잠재",'HRSG 수주 시나리오'!$I$38:$I$44,G$40) -> 0 | I41: Bull | J41: =J42+SUMIFS('BOP 수주 시나리오'!$G$20:$G$83,'BOP 수주 시나리오'!$B$20:$B$83,"잠재",'BOP 수주 시나리오'!$J$20:$J$83,J$40) -> 171154.99 | K41: =K42+SUMIFS('BOP 수주 시나리오'!$G$20:$G$83,'BOP 수주 시나리오'!$B$20:$B$83,"잠재",'BOP 수주 시나리오'!$J$20:$J$83,K$40) -> 476829.61 | L41: =L42+SUMIFS('BOP 수주 시나리오'!$G$20:$G$83,'BOP 수주 시나리오'!$B$20:$B$83,"잠재",'BOP 수주 시나리오'!$J$20:$J$83,L$40) -> 1005729.2 | M41: =M42+SUMIFS('BOP 수주 시나리오'!$G$20:$G$83,'BOP 수주 시나리오'!$B$20:$B$83,"잠재",'BOP 수주 시나리오'!$J$20:$J$83,M$40) -> 648647.85 | N41: =N42+SUMIFS('BOP 수주 시나리오'!$G$20:$G$83,'BOP 수주 시나리오'!$B$20:$B$83,"잠재",'BOP 수주 시나리오'!$J$20:$J$83,N$40) -> 155140.76
B42: Base | C42: =C43+SUMIFS('HRSG 수주 시나리오'!$F$38:$F$44,'HRSG 수주 시나리오'!$B$38:$B$44,"가능",'HRSG 수주 시나리오'!$I$38:$I$44,C$40) -> 0 | D42: =D43+SUMIFS('HRSG 수주 시나리오'!$F$38:$F$44,'HRSG 수주 시나리오'!$B$38:$B$44,"가능",'HRSG 수주 시나리오'!$I$38:$I$44,D$40) -> 634608.99 | E42: =E43+SUMIFS('HRSG 수주 시나리오'!$F$38:$F$44,'HRSG 수주 시나리오'!$B$38:$B$44,"가능",'HRSG 수주 시나리오'!$I$38:$I$44,E$40) -> 359582.52 | F42: =F43+SUMIFS('HRSG 수주 시나리오'!$F$38:$F$44,'HRSG 수주 시나리오'!$B$38:$B$44,"가능",'HRSG 수주 시나리오'!$I$38:$I$44,F$40) -> 0 | G42: =G43+SUMIFS('HRSG 수주 시나리오'!$F$38:$F$44,'HRSG 수주 시나리오'!$B$38:$B$44,"가능",'HRSG 수주 시나리오'!$I$38:$I$44,G$40) -> 0 | I42: Base | J42: =J43+SUMIFS('BOP 수주 시나리오'!$G$20:$G$83,'BOP 수주 시나리오'!$B$20:$B$83,"가능",'BOP 수주 시나리오'!$J$20:$J$83,J$40) -> 171154.99 | K42: =K43+SUMIFS('BOP 수주 시나리오'!$G$20:$G$83,'BOP 수주 시나리오'!$B$20:$B$83,"가능",'BOP 수주 시나리오'!$J$20:$J$83,K$40) -> 157368.21 | L42: =L43+SUMIFS('BOP 수주 시나리오'!$G$20:$G$83,'BOP 수주 시나리오'!$B$20:$B$83,"가능",'BOP 수주 시나리오'!$J$20:$J$83,L$40) -> 584898.99 | M42: =M43+SUMIFS('BOP 수주 시나리오'!$G$20:$G$83,'BOP 수주 시나리오'!$B$20:$B$83,"가능",'BOP 수주 시나리오'!$J$20:$J$83,M$40) -> 324073.9 | N42: =N43+SUMIFS('BOP 수주 시나리오'!$G$20:$G$83,'BOP 수주 시나리오'!$B$20:$B$83,"가능",'BOP 수주 시나리오'!$J$20:$J$83,N$40) -> 0
B43: Bear | C43: =SUMIFS('HRSG 수주 시나리오'!$F$38:$F$44,'HRSG 수주 시나리오'!$B$38:$B$44,"확실",'HRSG 수주 시나리오'!$I$38:$I$44,C$40) -> 0 | D43: =SUMIFS('HRSG 수주 시나리오'!$F$38:$F$44,'HRSG 수주 시나리오'!$B$38:$B$44,"확실",'HRSG 수주 시나리오'!$I$38:$I$44,D$40) -> 344636.99 | E43: =SUMIFS('HRSG 수주 시나리오'!$F$38:$F$44,'HRSG 수주 시나리오'!$B$38:$B$44,"확실",'HRSG 수주 시나리오'!$I$38:$I$44,E$40) -> 140922.57 | F43: =SUMIFS('HRSG 수주 시나리오'!$F$38:$F$44,'HRSG 수주 시나리오'!$B$38:$B$44,"확실",'HRSG 수주 시나리오'!$I$38:$I$44,F$40) -> 0 | G43: =SUMIFS('HRSG 수주 시나리오'!$F$38:$F$44,'HRSG 수주 시나리오'!$B$38:$B$44,"확실",'HRSG 수주 시나리오'!$I$38:$I$44,G$40) -> 0 | I43: Bear | J43: =SUMIFS('BOP 수주 시나리오'!$G$20:$G$83,'BOP 수주 시나리오'!$B$20:$B$83,"확실",'BOP 수주 시나리오'!$J$20:$J$83,J$40) -> 171154.99 | K43: =SUMIFS('BOP 수주 시나리오'!$G$20:$G$83,'BOP 수주 시나리오'!$B$20:$B$83,"확실",'BOP 수주 시나리오'!$J$20:$J$83,K$40) -> 0 | L43: =SUMIFS('BOP 수주 시나리오'!$G$20:$G$83,'BOP 수주 시나리오'!$B$20:$B$83,"확실",'BOP 수주 시나리오'!$J$20:$J$83,L$40) -> 394232.27 | M43: =SUMIFS('BOP 수주 시나리오'!$G$20:$G$83,'BOP 수주 시나리오'!$B$20:$B$83,"확실",'BOP 수주 시나리오'!$J$20:$J$83,M$40) -> 32394.625 | N43: =SUMIFS('BOP 수주 시나리오'!$G$20:$G$83,'BOP 수주 시나리오'!$B$20:$B$83,"확실",'BOP 수주 시나리오'!$J$20:$J$83,N$40) -> 0
B45: HRSG 미국 | C45: 2025 | D45: 2026 | E45: 2027 | F45: 2028 | G45: 2029
B46: Bull | C46: =C47+SUMIFS('HRSG 수주 시나리오'!$F$54:$F$56,'HRSG 수주 시나리오'!$B$54:$B$56,"잠재",'HRSG 수주 시나리오'!$I$54:$I$56,C$40) -> 0 | D46: =D47+SUMIFS('HRSG 수주 시나리오'!$F$54:$F$56,'HRSG 수주 시나리오'!$B$54:$B$56,"잠재",'HRSG 수주 시나리오'!$I$54:$I$56,D$40) -> 94346.67 | E46: =E47+SUMIFS('HRSG 수주 시나리오'!$F$54:$F$56,'HRSG 수주 시나리오'!$B$54:$B$56,"잠재",'HRSG 수주 시나리오'!$I$54:$I$56,E$40) -> 180368.63 | F46: =F47+SUMIFS('HRSG 수주 시나리오'!$F$54:$F$56,'HRSG 수주 시나리오'!$B$54:$B$56,"잠재",'HRSG 수주 시나리오'!$I$54:$I$56,F$40) -> 0 | G46: =G47+SUMIFS('HRSG 수주 시나리오'!$F$54:$F$56,'HRSG 수주 시나리오'!$B$54:$B$56,"잠재",'HRSG 수주 시나리오'!$I$54:$I$56,G$40) -> 0
B47: Base | C47: =C48+SUMIFS('HRSG 수주 시나리오'!$F$54:$F$56,'HRSG 수주 시나리오'!$B$54:$B$56,"가능",'HRSG 수주 시나리오'!$I$54:$I$56,C$40) -> 0 | D47: =D48+SUMIFS('HRSG 수주 시나리오'!$F$54:$F$56,'HRSG 수주 시나리오'!$B$54:$B$56,"가능",'HRSG 수주 시나리오'!$I$54:$I$56,D$40) -> 94346.67 | E47: =E48+SUMIFS('HRSG 수주 시나리오'!$F$54:$F$56,'HRSG 수주 시나리오'!$B$54:$B$56,"가능",'HRSG 수주 시나리오'!$I$54:$I$56,E$40) -> 97121.572 | F47: =F48+SUMIFS('HRSG 수주 시나리오'!$F$54:$F$56,'HRSG 수주 시나리오'!$B$54:$B$56,"가능",'HRSG 수주 시나리오'!$I$54:$I$56,F$40) -> 0 | G47: =G48+SUMIFS('HRSG 수주 시나리오'!$F$54:$F$56,'HRSG 수주 시나리오'!$B$54:$B$56,"가능",'HRSG 수주 시나리오'!$I$54:$I$56,G$40) -> 0
B48: Bear | C48: =SUMIFS('HRSG 수주 시나리오'!$F$54:$F$56,'HRSG 수주 시나리오'!$B$54:$B$56,"확실",'HRSG 수주 시나리오'!$I$54:$I$56,C$40) -> 0 | D48: =SUMIFS('HRSG 수주 시나리오'!$F$54:$F$56,'HRSG 수주 시나리오'!$B$54:$B$56,"확실",'HRSG 수주 시나리오'!$I$54:$I$56,D$40) -> 0 | E48: =SUMIFS('HRSG 수주 시나리오'!$F$54:$F$56,'HRSG 수주 시나리오'!$B$54:$B$56,"확실",'HRSG 수주 시나리오'!$I$54:$I$56,E$40) -> 0 | F48: =SUMIFS('HRSG 수주 시나리오'!$F$54:$F$56,'HRSG 수주 시나리오'!$B$54:$B$56,"확실",'HRSG 수주 시나리오'!$I$54:$I$56,F$40) -> 0 | G48: =SUMIFS('HRSG 수주 시나리오'!$F$54:$F$56,'HRSG 수주 시나리오'!$B$54:$B$56,"확실",'HRSG 수주 시나리오'!$I$54:$I$56,G$40) -> 0
B50: HRSG 일본 | C50: 2025 | D50: 2026 | E50: 2027 | F50: 2028 | G50: 2029
B51: Bull | C51: =C52+SUMIFS('HRSG 수주 시나리오'!$F$67:$F$70,'HRSG 수주 시나리오'!$B$67:$B$70,"잠재",'HRSG 수주 시나리오'!$I$67:$I$70,C$40) -> 66187.838 | D51: =D52+SUMIFS('HRSG 수주 시나리오'!$F$67:$F$70,'HRSG 수주 시나리오'!$B$67:$B$70,"잠재",'HRSG 수주 시나리오'!$I$67:$I$70,D$40) -> 66187.838 | E51: =E52+SUMIFS('HRSG 수주 시나리오'!$F$67:$F$70,'HRSG 수주 시나리오'!$B$67:$B$70,"잠재",'HRSG 수주 시나리오'!$I$67:$I$70,E$40) -> 66187.838 | F51: =F52+SUMIFS('HRSG 수주 시나리오'!$F$67:$F$70,'HRSG 수주 시나리오'!$B$67:$B$70,"잠재",'HRSG 수주 시나리오'!$I$67:$I$70,F$40) -> 66187.838 | G51: =G52+SUMIFS('HRSG 수주 시나리오'!$F$67:$F$70,'HRSG 수주 시나리오'!$B$67:$B$70,"잠재",'HRSG 수주 시나리오'!$I$67:$I$70,G$40) -> 0
B52: Base | C52: =C53+SUMIFS('HRSG 수주 시나리오'!$F$67:$F$70,'HRSG 수주 시나리오'!$B$67:$B$70,"가능",'HRSG 수주 시나리오'!$I$67:$I$70,C$40) -> 66187.838 | D52: =D53+SUMIFS('HRSG 수주 시나리오'!$F$67:$F$70,'HRSG 수주 시나리오'!$B$67:$B$70,"가능",'HRSG 수주 시나리오'!$I$67:$I$70,D$40) -> 66187.838 | E52: =E53+SUMIFS('HRSG 수주 시나리오'!$F$67:$F$70,'HRSG 수주 시나리오'!$B$67:$B$70,"가능",'HRSG 수주 시나리오'!$I$67:$I$70,E$40) -> 66187.838 | F52: =F53+SUMIFS('HRSG 수주 시나리오'!$F$67:$F$70,'HRSG 수주 시나리오'!$B$67:$B$70,"가능",'HRSG 수주 시나리오'!$I$67:$I$70,F$40) -> 66187.838 | G52: =G53+SUMIFS('HRSG 수주 시나리오'!$F$67:$F$70,'HRSG 수주 시나리오'!$B$67:$B$70,"가능",'HRSG 수주 시나리오'!$I$67:$I$70,G$40) -> 0
B53: Bear | C53: =SUMIFS('HRSG 수주 시나리오'!$F$67:$F$70,'HRSG 수주 시나리오'!$B$67:$B$70,"확실",'HRSG 수주 시나리오'!$I$67:$I$70,C$40) -> 0 | D53: =SUMIFS('HRSG 수주 시나리오'!$F$67:$F$70,'HRSG 수주 시나리오'!$B$67:$B$70,"확실",'HRSG 수주 시나리오'!$I$67:$I$70,D$40) -> 0 | E53: =SUMIFS('HRSG 수주 시나리오'!$F$67:$F$70,'HRSG 수주 시나리오'!$B$67:$B$70,"확실",'HRSG 수주 시나리오'!$I$67:$I$70,E$40) -> 0 | F53: =SUMIFS('HRSG 수주 시나리오'!$F$67:$F$70,'HRSG 수주 시나리오'!$B$67:$B$70,"확실",'HRSG 수주 시나리오'!$I$67:$I$70,F$40) -> 0 | G53: =SUMIFS('HRSG 수주 시나리오'!$F$67:$F$70,'HRSG 수주 시나리오'!$B$67:$B$70,"확실",'HRSG 수주 시나리오'!$I$67:$I$70,G$40) -> 0

Sheet 요약 재무제표
B1: Estimation
B2: 요약재무제표
B4: (단위: 억원), Base | C4: 100 | O4: =SUM(O23,O29)-O15 -> -21.706776 | P4: =SUM(P23,P29)-P15 -> -40.19508 | Q4: =SUM(Q23,Q29)-Q15 -> 1.671835 | R4: =SUM(R23,R29)-R15 -> 6.8882414
B5: 예상 포괄손익계산서 (요약) | C5: 2022 | D5: 2023 | E5: 2024 | F5: 2025E | G5: 2026E | H5: 2027E | I5: 2028E | K5: 예상 재무상태표 (요약) | L5: 2022 | M5: 2023 | N5: 2024 | O5: 2025E | P5: 2026E | Q5: 2027E | R5: 2028E | V5: Historical | Y5: Projection
B6: 매출액 | C6: =('Expected IS'!E7)/100 -> 3301.9711 | D6: =('Expected IS'!F7)/100 -> 3673.9921 | E6: =('Expected IS'!G7)/100 -> 4047.4104 | F6: =('Expected IS'!H7)/100 -> 8180.6013 | G6: =('Expected IS'!I7)/100 -> 10554.235 | H6: =('Expected IS'!J7)/100 -> 11217.458 | I6: =('Expected IS'!K7)/100 -> 12251.429 | K6: 유동자산 | L6: 2022.3102 | M6: 1880.8048 | N6: 2473.2046 | O6: =SUM(O7:O10) -> 3903.2216 | P6: =SUM(P7:P10) -> 5299.524 | Q6: =SUM(Q7:Q10) -> 5875.6656 | R6: =SUM(R7:R10) -> 6940.9499 | U6: in KRW Mn | V6: 2022 | W6: 2023 | X6: 2024 | Y6: 2025 | Z6: 2026 | AA6: 2027 | AB6: 2028
B7: 매출원가 | C7: =('Expected IS'!E8)/100 -> 2952.6547 | D7: =('Expected IS'!F8)/100 -> 3239.5762 | E7: =('Expected IS'!G8)/100 -> 3456.2302 | F7: =('Expected IS'!H8)/100 -> 7150.096 | G7: =('Expected IS'!I8)/100 -> 8958.557 | H7: =('Expected IS'!J8)/100 -> 9623.2177 | I7: =('Expected IS'!K8)/100 -> 10628.884 | K7: 현금 및 현금성자산 | L7: 236.03234 | M7: 138.72466 | N7: 176.07752 | O7: =F53 -> 348.66451 | P7: =G53 -> 744.30945 | Q7: =H53 -> 1112.901 | R7: =I53 -> 1649.1484 | U7: EBIT | V7: =C11 -> 81.080541 | W7: =D11 -> 150.86698 | X7: =E11 -> 219.27258 | Y7: =F11 -> 638.29657 | Z7: =G11 -> 1122.2078 | AA7: =H11 -> 1071.6382 | AB7: =I11 -> 1037.8846 | AD7: FCFF = NI + NCC + Int*(1-tex rate) - Capex -WC
B8: 매출총이익 | C8: =('Expected IS'!E10)/100 -> 349.31638 | D8: =('Expected IS'!F10)/100 -> 434.41587 | E8: =('Expected IS'!G10)/100 -> 591.18018 | F8: =('Expected IS'!H10)/100 -> 1030.5053 | G8: =('Expected IS'!I10)/100 -> 1595.6778 | H8: =('Expected IS'!J10)/100 -> 1594.2408 | I8: =('Expected IS'!K10)/100 -> 1622.5445 | K8: 매출채권 | L8: 1609.6437 | M8: 1439.2019 | N8: 1891.4084 | O8: =(Y20) -> 3204.5623 | P8: =(Z20) -> 4134.3787 | Q8: =(AA20) -> 4394.1813 | R8: =(AB20) -> 4799.2153 | U8: % effective tax rate | V8: 0.21 | W8: 0.21 | X8: 0.21 | Y8: ='Expected IS'!H33 -> 0.21 | Z8: ='Expected IS'!I33 -> 0.21 | AA8: ='Expected IS'!J33 -> 0.21 | AB8: ='Expected IS'!K33 -> 0.21 | AD8: FCF = NI + NCC - Capex -WC
B9: 판매비와관리비 | C9: =('Expected IS'!E11)/100 -> 268.23584 | D9: =('Expected IS'!F11)/100 -> 283.54888 | E9: =('Expected IS'!G11)/100 -> 371.90759 | F9: =('Expected IS'!H11)/100 -> 392.20871 | G9: =('Expected IS'!I11)/100 -> 473.46999 | H9: =('Expected IS'!J11)/100 -> 522.60258 | I9: =('Expected IS'!K11)/100 -> 584.65989 | K9: 재고자산 | L9: 43.527623 | M9: 55.213445 | N9: 108.05143 | O9: =(Y21) -> 198.11453 | P9: =(Z21) -> 216.37699 | Q9: =(AA21) -> 198.22156 | R9: =(AB21) -> 181.15249 | U9: (-) EBIT법인세 | V9: =V7*V8 -> 17.026914 | W9: =W7*W8 -> 31.682066 | X9: =X7*X8 -> 46.047243 | Y9: =Y7*Y8 -> 134.04228 | Z9: =Z7*Z8 -> 235.66364 | AA9: =AA7*AA8 -> 225.04402 | AB9: =AB7*AB8 -> 217.95578 | AD9: FCF = FCFF - Int*(1-tex rate)
B10: 조정영업이익 | C10: =('Expected IS'!E15)/100 -> 81.080541 | D10: =('Expected IS'!F15)/100 -> 150.86698 | E10: =('Expected IS'!G15)/100 -> 219.27258 | F10: =('Expected IS'!H15)/100 -> 638.29657 | G10: =('Expected IS'!I15)/100 -> 1122.2078 | H10: =('Expected IS'!J15)/100 -> 1071.6382 | I10: =('Expected IS'!K15)/100 -> 1037.8846 | K10: 기타유동자산 | L10: 133.1065 | M10: 247.66479 | N10: 297.66724 | O10: =N10/SUM(N10,N14)*O30 -> 151.8802 | P10: =O10/SUM(O10,O14)*P30 -> 204.45892 | Q10: =P10/SUM(P10,P14)*Q30 -> 170.36177 | R10: =Q10/SUM(Q10,Q14)*R30 -> 311.43367 | U10: NOPAT(세후영업이익) | V10: =V7-V9 -> 64.053627 | W10: =W7-W9 -> 119.18492 | X10: =X7-X9 -> 173.22534 | Y10: =Y7-Y9 -> 504.25429 | Z10: =Z7-Z9 -> 886.54415 | AA10: =AA7-AA9 -> 846.59415 | AB10: =AB7-AB9 -> 819.92887
B11: 영업이익 | C11: =(C10) -> 81.080541 | D11: =(D10) -> 150.86698 | E11: =(E10) -> 219.27258 | F11: =(F10) -> 638.29657 | G11: =(G10) -> 1122.2078 | H11: =(H10) -> 1071.6382 | I11: =(I10) -> 1037.8846 | K11: 비유동자산 | L11: 2471.4332 | M11: 2373.6906 | N11: 2774.5595 | O11: =SUM(O12:O14) -> 2659.8413 | P11: =SUM(P12:P14) -> 2784.2032 | Q11: =SUM(Q12:Q14) -> 2796.6844 | R11: =SUM(R12:R14) -> 3035.9988 | U11: % Yoy Growth | W11: =W10/V10-1 -> 0.86070517 | X11: =X10/W10-1 -> 0.45341665 | Y11: =Y10/X10-1 -> 1.910973 | Z11: =Z10/Y10-1 -> 0.75812913 | AA11: =AA10/Z10-1 -> -0.045062613 | AB11: =AB10/AA10-1 -> -0.031497129
B12: 비영업손익 | C12: =('Expected IS'!E29)/100 -> 12.86204 | D12: =('Expected IS'!F29)/100 -> 21.18717 | E12: =('Expected IS'!G29)/100 -> 8.40821 | F12: =('Expected IS'!H29)/100 -> 8.40821 | G12: =('Expected IS'!I29)/100 -> 8.40821 | H12: =('Expected IS'!J29)/100 -> 8.40821 | I12: =('Expected IS'!K29)/100 -> 8.40821 | K12: 유형자산 | L12: 1960.9198 | M12: 1920.7693 | N12: 2223.3244 | O12: =Y40 -> 2288.3185 | P12: =Z40 -> 2348.9877 | Q12: =AA40 -> 2405.9075 | R12: =AB40 -> 2460.3473 | U12: Change in NWC | V12: =V26 -> 0 | W12: =W26 -> -734.41241 | X12: =X26 -> 371.61774 | Y12: =Y26 -> -294.43955 | Z12: =Z26 -> 135.32106 | AA12: =AA26 -> -39.361017 | AB12: =AB26 -> -44.619731
B13: 금융손익 | C13: =('Expected IS'!E28)/100 -> -289.48852 | D13: =('Expected IS'!F28)/100 -> -119.8834 | E13: =('Expected IS'!G28)/100 -> -263.13946 | F13: =('Expected IS'!H28)/100 -> -285.49173 | G13: =('Expected IS'!I28)/100 -> -285.49173 | H13: =('Expected IS'!J28)/100 -> -285.49173 | I13: =('Expected IS'!K28)/100 -> -285.49173 | K13: 무형자산 | L13: 188.05134 | M13: 170.08757 | N13: 164.58958 | O13: =AVERAGE(L13:N13) -> 174.24283 | P13: =AVERAGE(M13:O13) -> 169.63999 | Q13: =AVERAGE(N13:P13) -> 169.4908 | R13: =AVERAGE(O13:Q13) -> 171.12454 | U13: Net Capex | V13: =V41 -> 35.126903 | W13: =W41 -> 65.798162 | X13: =X41 -> 363.13407 | Y13: =Y41 -> 177.46854 | Z13: =Z41 -> 171.77794 | AA13: =AA41 -> 167.42233 | AB13: =AB41 -> 165.80172
B14: 관계기업등 투자손익 | C14: =('Expected IS'!E30)/100 -> -12.20522 | D14: =('Expected IS'!F30)/100 -> -13.9216 | E14: =('Expected IS'!G30)/100 -> -3.99343 | F14: =('Expected IS'!H30)/100 -> -3.99343 | G14: =('Expected IS'!I30)/100 -> -3.99343 | H14: =('Expected IS'!J30)/100 -> -3.99343 | I14: =('Expected IS'!K30)/100 -> -3.99343 | K14: 기타비유동자산 | L14: 322.46206 | M14: 282.83377 | N14: 386.64546 | O14: =N14/SUM(N10,N14)*O30 -> 197.28 | P14: =O14/SUM(O10,O14)*P30 -> 265.57546 | Q14: =P14/SUM(P10,P14)*Q30 -> 221.28604 | R14: =Q14/SUM(Q10,Q14)*R30 -> 404.52694 | U14: (-) Reinvestment | V14: =V12+V13 -> 35.126903 | W14: =W12+W13 -> -668.61425 | X14: =X12+X13 -> 734.75181 | Y14: =Y12+Y13 -> -116.97102 | Z14: =Z12+Z13 -> 307.099 | AA14: =AA12+AA13 -> 128.06132 | AB14: =AB12+AB13 -> 121.18199
B15: 세전계속사업손익 | C15: =('Expected IS'!E31)/100 -> -207.75115 | D15: =('Expected IS'!F31)/100 -> 38.249159 | E15: =('Expected IS'!G31)/100 -> -39.452096 | F15: =('Expected IS'!H31)/100 -> 357.21962 | G15: =('Expected IS'!I31)/100 -> 841.13084 | H15: =('Expected IS'!J31)/100 -> 790.56122 | I15: =('Expected IS'!K31)/100 -> 756.8077 | K15: 자산총계 | L15: 4493.7433 | M15: 4254.4954 | N15: 5247.7641 | O15: =O11+O6 -> 6563.0629 | P15: =P11+P6 -> 8083.7272 | Q15: =Q11+Q6 -> 8672.35 | R15: =R11+R6 -> 9976.9487 | U15: FCFF(기업잉여현금흐름) | V15: =V10-V14 -> 28.926724 | W15: =W10-W14 -> 787.79917 | X15: =X10-X14 -> -561.52647 | Y15: =Y10-Y14 -> 621.2253 | Z15: =Z10-Z14 -> 579.44515 | AA15: =AA10-AA14 -> 718.53284 | AB15: =AB10-AB14 -> 698.74688
B16: 법인세 비용 | C16: =('Expected IS'!E32)/100 -> -16.573597 | D16: =('Expected IS'!F32)/100 -> -36.388661 | E16: =('Expected IS'!G32)/100 -> -235.30262 | F16: =('Expected IS'!H32)/100 -> 75.016119 | G16: =('Expected IS'!I32)/100 -> 176.63748 | H16: =('Expected IS'!J32)/100 -> 166.01786 | I16: =('Expected IS'!K32)/100 -> 158.92962 | K16: 유동부채 | L16: 3098.9525 | M16: 3211.3515 | N16: 3799.0561 | O16: =SUM(O17:O19) -> 4959.4812 | P16: =SUM(P17:P19) -> 5801.5541 | Q16: =SUM(Q17:Q19) -> 5806.8636 | R16: =SUM(R17:R19) -> 6501.2406 | U16: 이자비용 | V16: =C37 -> 0.92436 | W16: =D37 -> 2.42705 | X16: =E37 -> 1.905745 | Y16: =F37 -> 1.752385 | Z16: =G37 -> 2.0283933 | AA16: =H37 -> 1.8955078 | AB16: =I37 -> 1.8920954
B17: 계속사업이익 | C17: =('Expected IS'!E34)/100 -> -191.17756 | D17: =('Expected IS'!F34)/100 -> 74.637821 | E17: =('Expected IS'!G34)/100 -> 195.85052 | F17: =('Expected IS'!H34)/100 -> 282.2035 | G17: =('Expected IS'!I34)/100 -> 664.49336 | H17: =('Expected IS'!J34)/100 -> 624.54336 | I17: =('Expected IS'!K34)/100 -> 597.87808 | K17: 단기차입금 및 유동성장기부채 | L17: 1544.2791 | M17: 1563.7791 | N17: 1261.4843 | O17: =L17 -> 1544.2791 | P17: =M17 -> 1563.7791 | Q17: =N17 -> 1261.4843 | R17: =O17 -> 1544.2791 | U17: FCF(잉여현금흐름) | V17: =V15+V16 -> 29.851084 | W17: =W15+W16 -> 790.22622 | X17: =X15+X16 -> -559.62073 | Y17: =Y15+Y16 -> 622.97769 | Z17: =Z15+Z16 -> 581.47354 | AA17: =AA15+AA16 -> 720.42835 | AB17: =AB15+AB16 -> 700.63898
B18: 중단사업이익 | C18: 0 | D18: 0 | E18: 0 | F18: 0 | G18: 0 | H18: 0.01 | I18: 0.02 | K18: 매입채무 | L18: 1471.9461 | M18: 1605.3729 | N18: 2325.9805 | O18: =Y23 -> 3303.0295 | P18: =Z23 -> 4115.7872 | Q18: =AA23 -> 4396.7954 | R18: =AB23 -> 4829.3801
B19: 당기순이익 | C19: =C17 -> -191.17756 | D19: =D17 -> 74.637821 | E19: =E17 -> 195.85052 | F19: =F17 -> 282.2035 | G19: =G17 -> 664.49336 | H19: =H17 -> 624.54336 | I19: =I17 -> 597.87808 | K19: 기타유동부채 | L19: 82.727322 | M19: 42.199431 | N19: 211.59123 | O19: =AVERAGE(L19:N19) -> 112.17266 | P19: =AVERAGE(M19:O19) -> 121.98777 | Q19: =AVERAGE(N19:P19) -> 148.58389 | R19: =AVERAGE(O19:Q19) -> 127.58144 | U19: Change in Net Working Capital | V19: 2022 | W19: 2023 | X19: 2024 | Y19: 2025 | Z19: 2026 | AA19: 2027 | AB19: 2028
B20: 지배주주 | C20: 0 | D20: 0 | E20: 0 | F20: 0 | G20: 0 | H20: 0 | I20: 0 | K20: 비유동부채 | L20: 899.40531 | M20: 306.11393 | N20: 284.24241 | O20: =SUM(O21:O22) -> 304.41837 | P20: =SUM(P21:P22) -> 298.25824 | Q20: =SUM(Q21:Q22) -> 295.63967 | R20: =SUM(R21:R22) -> 299.43876 | U20: 매출채권 | V20: =('BS (Yearly)'!E8)/100 -> 1609.6437 | W20: =('BS (Yearly)'!F8)/100 -> 1439.2019 | X20: =('BS (Yearly)'!G8)/100 -> 1891.4084 | Y20: =Y29*Y33/365 -> 3204.5623 | Z20: =Z29*Z33/365 -> 4134.3787 | AA20: =AA29*AA33/365 -> 4394.1813 | AB20: =AB29*AB33/365 -> 4799.2153
B21: 비지배주주 | C21: 0 | D21: 0 | E21: 0 | F21: 0 | G21: 0 | H21: 0 | I21: 0 | K21: 장기차입금 | L21: 576.50654 | M21: 0 | N21: 0 | O21: =N21 -> 0 | P21: =O21 -> 0 | Q21: =P21 -> 0 | R21: =Q21 -> 0 | U21: 재고자산 | V21: =('BS (Yearly)'!E6)/100 -> 43.527623 | W21: =('BS (Yearly)'!F6)/100 -> 55.213445 | X21: =('BS (Yearly)'!G6)/100 -> 108.05143 | Y21: =Y30*Y34/365 -> 198.11453 | Z21: =Z30*Z34/365 -> 216.37699 | AA21: =AA30*AA34/365 -> 198.22156 | AB21: =AB30*AB34/365 -> 181.15249
B22: 총포괄이익 | C22: =(C19)/100 -> -1.9117756 | D22: =(D19)/100 -> 0.74637821 | E22: =(E19)/100 -> 1.9585052 | F22: =(F19)/100 -> 2.822035 | G22: =(G19)/100 -> 6.6449336 | H22: =(H19)/100 -> 6.2454336 | I22: =(I19)/100 -> 5.9787808 | K22: 기타비유동부채 | L22: 322.89876 | M22: 306.11393 | N22: 284.24241 | O22: =AVERAGE(L22:N22) -> 304.41837 | P22: =AVERAGE(M22:O22) -> 298.25824 | Q22: =AVERAGE(N22:P22) -> 295.63967 | R22: =AVERAGE(O22:Q22) -> 299.43876 | U22: 영업용 유동자산 | V22: =V20+V21 -> 1653.1713 | W22: =W20+W21 -> 1494.4153 | X22: =X20+X21 -> 1999.4598 | Y22: =Y20+Y21 -> 3402.6769 | Z22: =Z20+Z21 -> 4350.7557 | AA22: =AA20+AA21 -> 4592.4028 | AB22: =AB20+AB21 -> 4980.3678
B23: 지배주주 | C23: 0 | D23: 0 | E23: 0 | F23: 0 | G23: 0 | H23: 0 | I23: 0 | K23: 부채총계 | L23: 3998.3578 | M23: 3517.4654 | N23: 4083.2985 | O23: =O20+O16 -> 5263.8996 | P23: =P20+P16 -> 6099.8124 | Q23: =Q20+Q16 -> 6102.5033 | R23: =R20+R16 -> 6800.6794 | U23: 매입채무 | V23: =('BS (Yearly)'!D25)/100 -> 896.28975 | W23: =('BS (Yearly)'!E25)/100 -> 1471.9461 | X23: =('BS (Yearly)'!F25)/100 -> 1605.3729 | Y23: =Y31*Y34/365 -> 3303.0295 | Z23: =Z31*Z34/365 -> 4115.7872 | AA23: =AA31*AA34/365 -> 4396.7954 | AB23: =AB31*AB34/365 -> 4829.3801
B24: 비지배주주 | C24: 0 | D24: 0 | E24: 0 | F24: 0 | G24: 0 | H24: 0 | I24: 0 | K24: 지배주주지분 | L24: 493.33303 | M24: 735.44422 | N24: 1163.6119 | O24: =N24+(O27+N27) -> 1276.5952 | P24: =O24+(P27-O27) -> 1941.0886 | Q24: =P24+(Q27-P27) -> 2565.6319 | R24: =Q24+(R27-Q27) -> 3163.51 | U24: 영업용 유동부채 | V24: =V23 -> 896.28975 | W24: =W23 -> 1471.9461 | X24: =X23 -> 1605.3729 | Y24: =Y23 -> 3303.0295 | Z24: =Z23 -> 4115.7872 | AA24: =AA23 -> 4396.7954 | AB24: =AB23 -> 4829.3801
B25: EBITDA | C25: =('Expected IS'!E17)/100 -> 186.64418 | D25: =('Expected IS'!F17)/100 -> 256.81561 | E25: =('Expected IS'!G17)/100 -> 279.85154 | F25: =('Expected IS'!H17)/100 -> 750.77104 | G25: =('Expected IS'!I17)/100 -> 1233.3165 | H25: =('Expected IS'!J17)/100 -> 1182.1407 | I25: =('Expected IS'!K17)/100 -> 1149.2465 | K25: 자본금 | L25: 130 | M25: 154.72188 | N25: 154.72188 | O25: =N25 -> 154.72188 | P25: =O25 -> 154.72188 | Q25: =P25 -> 154.72188 | R25: =Q25 -> 154.72188 | U25: 순운전자본 | V25: =V22-V24 -> 756.88158 | W25: =W22-W24 -> 22.469173 | X25: =X22-X24 -> 394.08692 | Y25: =Y22-Y24 -> 99.647364 | Z25: =Z22-Z24 -> 234.96842 | AA25: =AA22-AA24 -> 195.60741 | AB25: =AB22-AB24 -> 150.98768
B26: FCF | K26: 자본잉여금 | L26: 109.11501 | M26: 260.98611 | N26: 260.2861 | O26: =N26 -> 260.2861 | P26: =O26 -> 260.2861 | Q26: =P26 -> 260.2861 | R26: =Q26 -> 260.2861 | U26: 순운전자본의 변동 | W26: =W25-V25 -> -734.41241 | X26: =X25-W25 -> 371.61774 | Y26: =Y25-X25 -> -294.43955 | Z26: =Z25-Y25 -> 135.32106 | AA26: =AA25-Z25 -> -39.361017 | AB26: =AB25-AA25 -> -44.619731
B27: EBITDA 마진율 (%) | C27: =C25/C6*100 -> 5.652508 | D27: =D25/D6*100 -> 6.990097 | E27: =E25/E6*100 -> 6.9143358 | F27: =F25/F6*100 -> 9.1774554 | G27: =G25/G6*100 -> 11.685513 | H27: =H25/H6*100 -> 10.538401 | I27: =I25/I6*100 -> 9.3805105 | K27: 이익잉여금 | L27: -339.7232 | M27: -271.77552 | N27: -84.61008 | O27: =N27+F19 -> 197.59342 | P27: =O27+G19 -> 862.08678 | Q27: =P27+H19 -> 1486.6301 | R27: =Q27+I19 -> 2084.5082 | U27: Ratio & Assumption
B28: 영업이익률 (%) | C28: =C11/C6*100 -> 2.4555194 | D28: =D11/D6*100 -> 4.1063502 | E28: =E11/E6*100 -> 5.4176019 | F28: =F11/F6*100 -> 7.802563 | G28: =G11/G6*100 -> 10.632773 | H28: =H11/H6*100 -> 9.5533063 | I28: =I11/I6*100 -> 8.4715398 | K28: 비지배주주지분 | L28: 2.0524881 | M28: 1.5857823 | N28: 0.8537268 | O28: =N28/E19*O27 -> 0.8613242 | P28: =O28/F19*P27 -> 2.6312084 | Q28: =P28/G19*Q27 -> 5.8866407 | R28: =Q28/H19*R27 -> 19.647556 | U28: 회전일수
B29: 지배주주귀속 순이익률 (%) | K29: 자본총계 | L29: 495.38552 | M29: 737.03 | N29: 1164.4656 | O29: =SUM(O28,O24) -> 1277.4565 | P29: =SUM(P28,P24) -> 1943.7198 | Q29: =SUM(Q28,Q24) -> 2571.5186 | R29: =SUM(R28,R24) -> 3183.1576 | U29: 매출채권회전일수 | V29: =365*V20/V33 -> 177.93007 | W29: =365*W20/W33 -> 142.98035 | X29: =365*X20/X33 -> 170.56933 | Y29: =W29 -> 142.98035 | Z29: =Y29 -> 142.98035 | AA29: =Z29 -> 142.98035 | AB29: =AA29 -> 142.98035
O30: 349.1602 | P30: 470.03438 | Q30: 391.6478 | R30: 715.96062 | U30: 재고자산회전일수 | V30: =365*V21/V34 -> 5.380779 | W30: =365*W21/W34 -> 6.2208469 | X30: =365*X21/X34 -> 11.410922 | Y30: =X30-($X30-$AB30)/4 -> 10.113403 | Z30: =Y30-($X30-$AB30)/4 -> 8.8158843 | AA30: =Z30-($X30-$AB30)/4 -> 7.5183656 | AB30: =W30 -> 6.2208469
B31: 예상 현금흐름표 (요약) (십억원) | C31: 2022 | D31: 2023 | E31: 2024 | F31: 2025E | G31: 2026E | H31: 2027E | I31: 2028E | K31: 예상 주당가치 및 valuation (요약) | L31: 2022 | M31: 2023 | N31: 2024 | O31: 2025E | P31: 2026E | Q31: 2027E | R31: 2028E | U31: 매입채무회전일수 | V31: =365*V23/V34 -> 110.79716 | W31: =365*W23/W34 -> 165.84279 | X31: =365*X23/X34 -> 169.53764 | Y31: =X31-($X31-$AB31)/4 -> 168.61393 | Z31: =Y31-($X31-$AB31)/4 -> 167.69021 | AA31: =Z31-($X31-$AB31)/4 -> 166.7665 | AB31: =W31 -> 165.84279
B32: 영업활동으로 인한 현금흐름 | C32: =('CFS (Yearly)'!E4)/100 -> 152.42141 | D32: =('CFS (Yearly)'!F4)/100 -> 437.15224 | E32: =('CFS (Yearly)'!G4)/100 -> 399.63226 | F32: =SUM(F33:F39) -> 291.4022 | G32: =SUM(G33:G39) -> 673.47783 | H32: =SUM(H33:H39) -> 622.7471 | I32: =SUM(I33:I39) -> 744.58038 | K32: P/E (x) | L32: N/A | M32: 30.4 | N32: 24.4 | O32: 30.3 | P32: 24.1 | Q32: 43.2 | U32: 현금전환주기 | V32: =V29+V30-V31 -> 72.51369 | W32: =W29+W30-W31 -> -16.641586 | X32: =X29+X30-X31 -> 12.442608 | Y32: =Y29+Y30-Y31 -> -15.520172 | Z32: =Z29+Z30-Z31 -> -15.893977 | AA32: =AA29+AA30-AA31 -> -16.267781 | AB32: =AB29+AB30-AB31 -> -16.641586
B33: 당기순이익(손실) | C33: =('CFS (Yearly)'!E5)/100 -> -191.17756 | D33: =('CFS (Yearly)'!F5)/100 -> 74.63782 | E33: =('CFS (Yearly)'!G5)/100 -> 195.85052 | F33: =F19 -> 282.2035 | G33: =G19 -> 664.49336 | H33: =H19 -> 624.54336 | I33: =I19 -> 597.87808 | K33: P/B (x) | L33: 3.4 | M33: 3.4 | N33: 4.1 | O33: 4.8 | P33: 4 | Q33: 3.4 | U33: 매출액 | V33: =C6 -> 3301.9711 | W33: =D6 -> 3673.9921 | X33: =E6 -> 4047.4104 | Y33: =F6 -> 8180.6013 | Z33: =G6 -> 10554.235 | AA33: =H6 -> 11217.458 | AB33: =I6 -> 12251.429
B34: 유무형자산상각비 | C34: =(V39)/100 -> 1.0556364 | D34: =(W39)/100 -> 1.0594863 | E34: =(X39)/100 -> 0.6057896 | F34: =(Y39)/100 -> 1.1247447 | G34: =(Z39)/100 -> 1.1110867 | H34: =(AA39)/100 -> 1.1050256 | I34: =(AB39)/100 -> 1.113619 | K34: EV/EBITDA (x) | U34: 매출원가 | V34: =C7 -> 2952.6547 | W34: =D7 -> 3239.5762 | X34: =E7 -> 3456.2302 | Y34: =F7 -> 7150.096 | Z34: =G7 -> 8958.557 | AA34: =H7 -> 9623.2177 | AB34: =I7 -> 10628.884
B35: 운전자본의 변동 | C35: =('CFS (Yearly)'!E9)/100 -> 59.86765 | D35: =('CFS (Yearly)'!F9)/100 -> 197.25756 | E35: =('CFS (Yearly)'!G9)/100 -> 127.82714 | F35: -166 | G35: -130 | H35: -132 | I35: =(AVERAGE(F35:H35))/100 -> -1.4266667 | K35: EPS (원) | L35: =C19/$U$49*10^8 -> -617.81037 | M35: =D19/$U$49*10^8 -> 241.19996 | N35: =E19/$U$49*10^8 -> 632.91155 | O35: =F19/$U$49*10^8 -> 911.97026 | P35: =G19/$U$49*10^8 -> 2147.3801 | Q35: =H19/$U$49*10^8 -> 2018.2775 | R35: =I19/$U$49*10^8 -> 1932.1058
B36: 이자수취(지급) | C36: =('CFS (Yearly)'!E15+'CFS (Yearly)'!E16)/100 -> -89.284561 | D36: =('CFS (Yearly)'!F15+'CFS (Yearly)'!F16)/100 -> -102.94618 | E36: =('CFS (Yearly)'!G15+'CFS (Yearly)'!G16)/100 -> -93.484099 | F36: =AVERAGE(C36:E36) -> -95.238282 | G36: =AVERAGE(D36:F36) -> -97.222855 | H36: =AVERAGE(E36:G36) -> -95.315079 | I36: =AVERAGE(F36:H36) -> -95.925405 | K36: BPS (원) | U36: Net Capex | V36: 2022 | W36: 2023 | X36: 2024 | Y36: 2025 | Z36: 2026 | AA36: 2027 | AB36: 2028
B37: 배당금수입(지급) | C37: =('CFS (Yearly)'!E17)/100 -> 0.92436 | D37: =('CFS (Yearly)'!F17)/100 -> 2.42705 | E37: =('CFS (Yearly)'!G17)/100 -> 1.905745 | F37: =AVERAGE(C37:E37) -> 1.752385 | G37: =AVERAGE(D37:F37) -> 2.0283933 | H37: =AVERAGE(E37:G37) -> 1.8955078 | I37: =AVERAGE(F37:H37) -> 1.8920954 | K37: DPS (원) | U37: 기초 유형자산 | V37: ='BS (Yearly)'!D13/100 -> 2031.3565 | W37: =V40 -> 1960.9198 | X37: =W40 -> 1920.7693 | Y37: =X40 -> 2223.3244 | Z37: =Y40 -> 2288.3185 | AA37: =Z40 -> 2348.9877 | AB37: =AA40 -> 2405.9075
B38: 법인세환입(납부) | C38: =('CFS (Yearly)'!E19+'CFS (Yearly)'!E20)/100 -> -8.2396756 | D38: =('CFS (Yearly)'!F19+'CFS (Yearly)'!F20)/100 -> -1.7820948 | E38: =('CFS (Yearly)'!G19+'CFS (Yearly)'!G20)/100 -> -4.9578652 | F38: =AVERAGE(C38:E38) -> -4.9932119 | G38: =AVERAGE(D38:F38) -> -3.9110573 | H38: =AVERAGE(E38:G38) -> -4.6207115 | I38: =AVERAGE(F38:H38) -> -4.5083269 | K38: 배당성향 (%) | U38: Capex | V38: -15.168 | W38: -42.073 | X38: -44.695 | Y38: =X38*(1+$AC$38) -> -47.480404 | Z38: =Y38*(1+$AC$38) -> -50.439394 | AA38: =Z38*(1+$AC$38) -> -53.58279 | AB38: =AA38*(1+$AC$38) -> -56.922083 | AC38: =X38/W38-1 -> 0.062320253
B39: 기타 영업현금흐름 | C39: =(C32-SUM(C33:C38)) -> 379.27556 | D39: =(D32-SUM(D33:D38)) -> 266.4986 | E39: =(E32-SUM(E33:E38)) -> 171.88503 | F39: =AVERAGE(C39:E39) -> 272.55306 | G39: =AVERAGE(D39:F39) -> 236.9789 | H39: =AVERAGE(E39:G39) -> 227.139 | I39: =AVERAGE(F39:H39) -> 245.55699 | K39: 매출액증가율 (%) | U39: 감가상각비 | V39: =('비용 세부항목 추정'!D62+'비용 세부항목 추정'!D75)/100 -> 105.56364 | W39: =('비용 세부항목 추정'!E62+'비용 세부항목 추정'!E75)/100 -> 105.94863 | X39: =('비용 세부항목 추정'!F62+'비용 세부항목 추정'!F75)/100 -> 60.57896 | Y39: =('비용 세부항목 추정'!G62+'비용 세부항목 추정'!G75)/100 -> 112.47447 | Z39: =('비용 세부항목 추정'!H62+'비용 세부항목 추정'!H75)/100 -> 111.10867 | AA39: =('비용 세부항목 추정'!I62+'비용 세부항목 추정'!I75)/100 -> 110.50256 | AB39: =('비용 세부항목 추정'!J62+'비용 세부항목 추정'!J75)/100 -> 111.3619
B40: 투자활동으로 인한 현금흐름 | C40: =('CFS (Yearly)'!E22)/100 -> -251.83735 | D40: =('CFS (Yearly)'!F22)/100 -> -150.02307 | E40: =('CFS (Yearly)'!G22)/100 -> -2.1158982 | F40: =SUM(F41:F43) -> -21.817994 | G40: =SUM(G41:G43) -> 5.5436385 | H40: =SUM(H41:H43) -> -5.3064435 | I40: =SUM(I41:I43) -> 1.4088548 | K40: EBITDA증가율 (%) | U40: 기말 유형자산 | V40: =L12 -> 1960.9198 | W40: =M12 -> 1920.7693 | X40: =N12 -> 2223.3244 | Y40: =Y37+Y38+Y39 -> 2288.3185 | Z40: =Z37+Z38+Z39 -> 2348.9877 | AA40: =AA37+AA38+AA39 -> 2405.9075 | AB40: =AB37+AB38+AB39 -> 2460.3473
B41: 유무형자산처분(취득) | C41: =(V38)/100 -> -0.15168 | D41: =(W38)/100 -> -0.42073 | E41: =(X38)/100 -> -0.44695 | F41: =(Y38)/100 -> -0.47480404 | G41: =(Z38)/100 -> -0.50439394 | H41: =(AA38)/100 -> -0.5358279 | I41: =(AB38)/100 -> -0.56922083 | K41: 조정영업이익증가율 (%) | U41: Net Capex | V41: =V40-V37+V39 -> 35.126903 | W41: =W40-W37+W39 -> 65.798162 | X41: =X40-X37+X39 -> 363.13407 | Y41: =Y40-Y37+Y39 -> 177.46854 | Z41: =Z40-Z37+Z39 -> 171.77794 | AA41: =AA40-AA37+AA39 -> 167.42233 | AB41: =AB40-AB37+AB39 -> 165.80172
B42: 투자자산의 감소(증가) | C42: 0 | D42: -5 | E42: 14 | F42: -20 | G42: 7 | H42: -4 | I42: 3 | K42: EPS증가율 (%) | U42: Ratio & Assumption
B43: 기타 | C43: =(C40-C41)/100 -> -2.5168567 | D43: =(D40-D41)/100 -> -1.4960234 | E43: =(E40-E41)/100 -> -0.016689482 | F43: =AVERAGE(C43:E43) -> -1.3431899 | G43: =AVERAGE(D43:F43) -> -0.95196759 | H43: =AVERAGE(E43:G43) -> -0.77061564 | I43: =AVERAGE(F43:H43) -> -1.0219244 | K43: 매출채권 회전일수 | U43: % Net Capex / Sales | V43: =V41/C6 -> 0.010638162 | W43: =W41/D6 -> 0.017909174 | X43: =X41/E6 -> 0.089720102 | Y43: =Y41/F6 -> 0.021693825 | Z43: =Z41/G6 -> 0.016275736 | AA43: =AA41/H6 -> 0.014925157 | AB43: =AB41/I6 -> 0.013533256
B44: 재무활동으로 인한 현금흐름 | C44: =('CFS (Yearly)'!E32)/100 -> 225.42514 | D44: =('CFS (Yearly)'!F32)/100 -> -386.95887 | E44: =('CFS (Yearly)'!G32)/100 -> -366.17071 | F44: -97 | G44: =AVERAGE(D44:F44) -> -283.37653 | H44: =AVERAGE(E44:G44) -> -248.84908 | I44: =AVERAGE(F44:H44) -> -209.74187 | K44: 재고자산 회전일수 | U44: % Capex / Sales | V44: =-V38/C6 -> 0.0045936199 | W44: =-W38/D6 -> 0.011451576 | X44: =-X38/E6 -> 0.011042863 | Y44: =-Y38/F6 -> 0.0058040237 | Z44: =-Z38/G6 -> 0.0047790669 | AA44: =-AA38/H6 -> 0.0047767318 | AB44: =-AB38/I6 -> 0.0046461588
B45: 외화단기차입금의 순증감 | K45: 매입채무 회전일수 | U45: % D&A / Sales | V45: =V39/C6 -> 0.031969886 | W45: =W39/D6 -> 0.028837468 | X45: =X39/E6 -> 0.014967338 | Y45: =Y39/F6 -> 0.013748925 | Z45: =Z39/G6 -> 0.010527401 | AA45: =AA39/H6 -> 0.0098509446 | AB45: =AB39/I6 -> 0.0090897073
B46: 장단기금융부채의 증가(감소) | K46: ROA (%) | U46: % Capex / D&A | V46: =-V38/V39 -> 0.14368584 | W46: =-W38/W39 -> 0.39710754 | X46: =-X38/X39 -> 0.73779741 | Y46: =-Y38/Y39 -> 0.42214383 | Z46: =-Z38/Z39 -> 0.45396454 | AA46: =-AA38/AA39 -> 0.48490089 | AB46: =-AB38/AB39 -> 0.51114505
B47: 이자지급(재무) | K47: ROE (%) | L47: =C19/L24 -> -0.38752232 | M47: =D19/M24 -> 0.10148672 | N47: =E19/N24 -> 0.16831259 | O47: =F19/O24 -> 0.2210595 | P47: =G19/P24 -> 0.34233026 | Q47: =H19/Q24 -> 0.24342672 | R47: =I19/R24 -> 0.188992
B48: 배당금의 지급 | K48: ROIC (%) | U48: 발행주식총수
B49: 기타재무활동 | K49: 부채비율 (%) | U49: 30944375
B50: 현금의 증가 | K50: 유동비율 (%) | U50: EV
B51: 기초현금 | C51: =('CFS (Yearly)'!E46)/100 -> 110.24895 | D51: =('CFS (Yearly)'!F46)/100 -> 236.03234 | E51: =('CFS (Yearly)'!G46)/100 -> 138.72466 | F51: =E53 -> 176.08031 | G51: =F53 -> 348.66451 | H51: =G53 -> 744.30945 | I51: =H53 -> 1112.901 | K51: 당좌비율 (%) | U51: =U53*10^4-M7-#REF!-M10 -> #REF!
B52: 환율변동효과 | C52: 0 | E52: =(17608-17007)/100 -> 6.01 | K52: 자기자본비율 (%) | U52: 시총(십억)
B53: 기말현금 | C53: =('CFS (Yearly)'!E47)/100 -> 236.03234 | D53: =(D51+D32+D40+D44+D52) -> 136.20264 | E53: =(E51+E32+E40+E44+E52) -> 176.08031 | F53: =(F51+F32+F40+F44+F52) -> 348.66451 | G53: =(G51+G32+G40+G44+G52) -> 744.30945 | H53: =(H51+H32+H40+H44+H52) -> 1112.901 | I53: =(I51+I32+I40+I44+I52) -> 1649.1484

Sheet HRSG
B1: Estimation
B2: HRSG
B5: Active Scenario | C5: Bear | X5: 24-28 CAGR
B6: Scenario Number | C6: =IF(C5="Bull",1, IF(C5="Base",2,3)) -> 3 | X6: =RATE(5,0,-T9,X9) -> 0.087942477
C7: =2000+RIGHT(C8,2) -> #VALUE! | D7: =2000+RIGHT(D8,2) -> 2025 | E7: =2000+RIGHT(E8,2) -> 2025 | F7: =2000+RIGHT(F8,2) -> 2025 | G7: =2000+RIGHT(G8,2) -> 2026 | H7: =2000+RIGHT(H8,2) -> 2026 | I7: =2000+RIGHT(I8,2) -> 2026 | J7: =2000+RIGHT(J8,2) -> 2026 | ... R7: =2000+RIGHT(R8,2) -> 2028
A8: x | B8: (단위: 백만 원) | C8: 1Q25A | D8: 2Q25 | E8: 3Q25 | F8: 4Q25 | G8: 1Q26 | H8: 2Q26 | I8: 3Q26 | J8: 4Q26 | K8: 1Q27 | L8: 2Q27 | M8: 3Q27 | N8: 4Q27 | O8: 1Q28 | P8: 2Q28 | Q8: 3Q28 | R8: 4Q28 | T8: 2024 | U8: 2025 | V8: 2026 | W8: 2027 | X8: 2028 | Z8: 추정 논리
B9: =B2 -> HRSG | C9: 98656 | D9: =SUM(D11:D12) -> 96056.026 | E9: =SUM(E11:E12) -> 115943.97 | F9: =SUM(F11:F12) -> 165429.13 | G9: =SUM(G11:G12) -> 187247.69 | H9: =SUM(H11:H12) -> 189821.45 | I9: =SUM(I11:I12) -> 181562.56 | J9: =SUM(J11:J12) -> 170725.03 | K9: =SUM(K11:K12) -> 156018.91 | ... R9: =SUM(R11:R12) -> 67712.327 | T9: 259014 | U9: =SUMIF($C$7:$R$7,U$8,$C9:$R9) -> 377429.13 | V9: =SUMIF($C$7:$R$7,V$8,$C9:$R9) -> 729356.74 | W9: =SUMIF($C$7:$R$7,W$8,$C9:$R9) -> 545026.94 | X9: =SUMIF($C$7:$R$7,X$8,$C9:$R9) -> 394777.97
B10: QoQ % | D10: =D9/C9-1 -> -0.026353935 | E10: =E9/D9-1 -> 0.20704527 | F10: =F9/E9-1 -> 0.42680234 | G10: =G9/F9-1 -> 0.1318907 | H10: =H9/G9-1 -> 0.013745211 | I10: =I9/H9-1 -> -0.043508732 | J10: =J9/I9-1 -> -0.059690366 | K10: =K9/J9-1 -> -0.086139202 | ... R10: =R9/Q9-1 -> -0.29057777 | U10: =U9/T9-1 -> 0.45717656 | V10: =V9/U9-1 -> 0.93243362 | W10: =W9/V9-1 -> -0.25272928 | X10: =X9/W9-1 -> -0.27567256
B11: 국내 | C11: =C18+CHOOSE($C$6,C24,C25,C26) -> 25988.066 | D11: =D18+CHOOSE($C$6,D24,D25,D26) -> 37613.773 | E11: =E18+CHOOSE($C$6,E24,E25,E26) -> 40607.89 | F11: =F18+CHOOSE($C$6,F24,F25,F26) -> 43661.829 | G11: =G18+CHOOSE($C$6,G24,G25,G26) -> 38769.682 | H11: =H18+CHOOSE($C$6,H24,H25,H26) -> 37030.114 | I11: =I18+CHOOSE($C$6,I24,I25,I26) -> 37083.919 | J11: =J18+CHOOSE($C$6,J24,J25,J26) -> 30799.406 | ... R11: =R18+CHOOSE($C$6,R24,R25,R26) -> 5760.4375 | T11: 150052 | U11: =SUMIF($C$7:$R$7,U$8,$C11:$R11) -> 121883.49 | V11: =SUMIF($C$7:$R$7,V$8,$C11:$R11) -> 143683.12 | W11: =SUMIF($C$7:$R$7,W$8,$C11:$R11) -> 120768.89 | X11: =SUMIF($C$7:$R$7,X$8,$C11:$R11) -> 33521.075
B12: 해외 | C12: =SUM(C13:C16) -> 72667.934 | D12: =SUM(D13:D16) -> 58442.253 | E12: =SUM(E13:E16) -> 75336.082 | F12: =SUM(F13:F16) -> 121767.3 | G12: =SUM(G13:G16) -> 148478.01 | H12: =SUM(H13:H16) -> 152791.34 | I12: =SUM(I13:I16) -> 144478.64 | J12: =SUM(J13:J16) -> 139925.62 | ... R12: =SUM(R13:R16) -> 61951.89 | T12: 108962 | U12: =SUMIF($C$7:$R$7,U$8,$C12:$R12) -> 255545.64 | V12: =SUMIF($C$7:$R$7,V$8,$C12:$R12) -> 585673.62 | W12: =SUMIF($C$7:$R$7,W$8,$C12:$R12) -> 424258.05 | X12: =SUMIF($C$7:$R$7,X$8,$C12:$R12) -> 361256.89
B13: 중동 | C13: =C19+CHOOSE($C$6,C28,C29,C30) -> 17797.935 | D13: =D19+CHOOSE($C$6,D28,D29,D30) -> 41884.666 | E13: =E19+CHOOSE($C$6,E28,E29,E30) -> 60273.328 | F13: =F19+CHOOSE($C$6,F28,F29,F30) -> 102556.19 | G13: =G19+CHOOSE($C$6,G28,G29,G30) -> 123821.26 | H13: =H19+CHOOSE($C$6,H28,H29,H30) -> 127978.8 | I13: =I19+CHOOSE($C$6,I28,I29,I30) -> 117366.08 | J13: =J19+CHOOSE($C$6,J28,J29,J30) -> 111708.81 | ... R13: =R19+CHOOSE($C$6,R28,R29,R30) -> 41201.868 | U13: =SUMIF($C$7:$R$7,U$8,$C13:$R13) -> 204714.19 | V13: =SUMIF($C$7:$R$7,V$8,$C13:$R13) -> 480874.94 | W13: =SUMIF($C$7:$R$7,W$8,$C13:$R13) -> 304914.38 | X13: =SUMIF($C$7:$R$7,X$8,$C13:$R13) -> 281967.89
B14: 일본 | C14: =C20+CHOOSE($C$6,C32,C33,C34) -> 9049.9246 | D14: =D20+CHOOSE($C$6,D32,D33,D34) -> 9635.1719 | E14: =E20+CHOOSE($C$6,E32,E33,E34) -> 11107.851 | F14: =F20+CHOOSE($C$6,F32,F33,F34) -> 15256.205 | G14: =G20+CHOOSE($C$6,G32,G33,G34) -> 24656.756 | H14: =H20+CHOOSE($C$6,H32,H33,H34) -> 24812.541 | I14: =I20+CHOOSE($C$6,I32,I33,I34) -> 27112.569 | J14: =J20+CHOOSE($C$6,J32,J33,J34) -> 28216.807 | ... R14: =R20+CHOOSE($C$6,R32,R33,R34) -> 20750.021 | U14: =SUMIF($C$7:$R$7,U$8,$C14:$R14) -> 35999.228 | V14: =SUMIF($C$7:$R$7,V$8,$C14:$R14) -> 104798.67 | W14: =SUMIF($C$7:$R$7,W$8,$C14:$R14) -> 119343.66 | X14: =SUMIF($C$7:$R$7,X$8,$C14:$R14) -> 79288.997
B15: 미국 | C15: =CHOOSE($C$6,C36,C37,C38) -> 0 | D15: =CHOOSE($C$6,D36,D37,D38) -> 0 | E15: =CHOOSE($C$6,E36,E37,E38) -> 0 | F15: =CHOOSE($C$6,F36,F37,F38) -> 0 | G15: =CHOOSE($C$6,G36,G37,G38) -> 0 | H15: =CHOOSE($C$6,H36,H37,H38) -> 0 | I15: =CHOOSE($C$6,I36,I37,I38) -> 0 | J15: =CHOOSE($C$6,J36,J37,J38) -> 0 | ... R15: =CHOOSE($C$6,R36,R37,R38) -> 0 | U15: =SUMIF($C$7:$R$7,U$8,$C15:$R15) -> 0 | V15: =SUMIF($C$7:$R$7,V$8,$C15:$R15) -> 0 | W15: =SUMIF($C$7:$R$7,W$8,$C15:$R15) -> 0 | X15: =SUMIF($C$7:$R$7,X$8,$C15:$R15) -> 0
B16: 기타 | C16: =C21 -> 45820.075 | D16: =D21 -> 6922.4148 | E16: =E21 -> 3954.9025 | F16: =F21 -> 3954.9025 | G16: =G21 -> 0 | H16: =H21 -> 0 | I16: =I21 -> 0 | J16: =J21 -> 0 | ... R16: =R21 -> 0 | U16: =SUMIF($C$7:$R$7,U$8,$C16:$R16) -> 14832.22 | V16: =SUMIF($C$7:$R$7,V$8,$C16:$R16) -> 0 | W16: =SUMIF($C$7:$R$7,W$8,$C16:$R16) -> 0 | X16: =SUMIF($C$7:$R$7,X$8,$C16:$R16) -> 0
A17: x | B17: 기존수주 매출 (추정) | C17: ='기존수주 매출'!AF26 -> 59758.34 | D17: ='기존수주 매출'!AG26 -> 96056.026 | E17: ='기존수주 매출'!AH26 -> 115943.97 | F17: ='기존수주 매출'!AI26 -> 165429.13 | G17: ='기존수주 매출'!AJ26 -> 187247.69 | H17: ='기존수주 매출'!AK26 -> 187886.82 | I17: ='기존수주 매출'!AL26 -> 177693.29 | J17: ='기존수주 매출'!AM26 -> 163834.24 | ... R17: ='기존수주 매출'!AU26 -> 20750.021 | T17: 기존수주 매출 (추정) | Z17: HRSG 기존수주 매출 추정논리
B18: 국내 | C18: ='기존수주 매출'!AF27 -> 25988.066 | D18: ='기존수주 매출'!AG27 -> 37613.773 | E18: ='기존수주 매출'!AH27 -> 40607.89 | F18: ='기존수주 매출'!AI27 -> 43661.829 | G18: ='기존수주 매출'!AJ27 -> 38769.682 | H18: ='기존수주 매출'!AK27 -> 35095.477 | I18: ='기존수주 매출'!AL27 -> 33214.644 | J18: ='기존수주 매출'!AM27 -> 23908.619 | ... R18: ='기존수주 매출'!AU27 -> 0 | T18: 국내 | U18: =SUMIF($C$7:$R$7,U$8,$C18:$R18) -> 121883.49 | V18: =SUMIF($C$7:$R$7,V$8,$C18:$R18) -> 130988.42 | W18: =SUMIF($C$7:$R$7,W$8,$C18:$R18) -> 79532.855 | X18: =SUMIF($C$7:$R$7,X$8,$C18:$R18) -> 10609.75 | Z18: 기존 수주의 경우 공시된 수주에 한해 진행률을 기반으로 분기별 매출액을 추정. 진행률은 지역과 공사기간을 중심으로 기존 수주 진행률 시나리오를 반영
B19: 중동 | C19: ='기존수주 매출'!AF28 -> 17797.935 | D19: ='기존수주 매출'!AG28 -> 41884.666 | E19: ='기존수주 매출'!AH28 -> 60273.328 | F19: ='기존수주 매출'!AI28 -> 102556.19 | G19: ='기존수주 매출'!AJ28 -> 123821.26 | H19: ='기존수주 매출'!AK28 -> 127978.8 | I19: ='기존수주 매출'!AL28 -> 117366.08 | J19: ='기존수주 매출'!AM28 -> 111708.81 | ... R19: ='기존수주 매출'!AU28 -> 0 | T19: 중동 | U19: =SUMIF($C$7:$R$7,U$8,$C19:$R19) -> 204714.19 | V19: =SUMIF($C$7:$R$7,V$8,$C19:$R19) -> 480874.94 | W19: =SUMIF($C$7:$R$7,W$8,$C19:$R19) -> 140217.35 | X19: =SUMIF($C$7:$R$7,X$8,$C19:$R19) -> 0 | Z19: 본래 계약으로 공시된 공사 기한보다 1~2개 분기 연장되는 사례가 잦아, 보수적 추정을 위해 진행률은 공사 기간+2~3개 분기로 반영
B20: 일본 | C20: ='기존수주 매출'!AF29 -> 9049.9246 | D20: ='기존수주 매출'!AG29 -> 9635.1719 | E20: ='기존수주 매출'!AH29 -> 11107.851 | F20: ='기존수주 매출'!AI29 -> 15256.205 | G20: ='기존수주 매출'!AJ29 -> 24656.756 | H20: ='기존수주 매출'!AK29 -> 24812.541 | I20: ='기존수주 매출'!AL29 -> 27112.569 | J20: ='기존수주 매출'!AM29 -> 28216.807 | ... R20: ='기존수주 매출'!AU29 -> 20750.021 | T20: 일본 | U20: =SUMIF($C$7:$R$7,U$8,$C20:$R20) -> 35999.228 | V20: =SUMIF($C$7:$R$7,V$8,$C20:$R20) -> 104798.67 | W20: =SUMIF($C$7:$R$7,W$8,$C20:$R20) -> 119343.66 | X20: =SUMIF($C$7:$R$7,X$8,$C20:$R20) -> 79288.997 | Z20: #1 중동 수주, 5~7개 분기
B21: 기타 | C21: ='기존수주 매출'!AF30+C9-C17 -> 45820.075 | D21: ='기존수주 매출'!AG30 -> 6922.4148 | E21: ='기존수주 매출'!AH30 -> 3954.9025 | F21: ='기존수주 매출'!AI30 -> 3954.9025 | G21: ='기존수주 매출'!AJ30 -> 0 | H21: ='기존수주 매출'!AK30 -> 0 | I21: ='기존수주 매출'!AL30 -> 0 | J21: ='기존수주 매출'!AM30 -> 0 | K21: ='기존수주 매출'!AN30 -> 0 | ... R21: ='기존수주 매출'!AU30 -> 0 | T21: 기타 | U21: =SUMIF($C$7:$R$7,U$8,$C21:$R21) -> 14832.22 | V21: =SUMIF($C$7:$R$7,V$8,$C21:$R21) -> 0 | W21: =SUMIF($C$7:$R$7,W$8,$C21:$R21) -> 0 | X21: =SUMIF($C$7:$R$7,X$8,$C21:$R21) -> 0 | Z21: #2 국내 수주, 5~7개 분기
A22: x | B22: 신규 수주 매출 (추정) | T22: 신규 수주 매출 (추정) | Z22: HRSG 신규수주 추정 논리
B23: 국내 | T23: 국내 | Z23: 국내
B24: Bull | C24: ='HRSG 수주 시나리오'!P23 -> 0 | D24: ='HRSG 수주 시나리오'!Q23 -> 0 | E24: ='HRSG 수주 시나리오'!R23 -> 0 | F24: ='HRSG 수주 시나리오'!S23 -> 0 | G24: ='HRSG 수주 시나리오'!T23 -> 2855.6484 | H24: ='HRSG 수주 시나리오'!U23 -> 4790.2859 | I24: ='HRSG 수주 시나리오'!V23 -> 11184.869 | J24: ='HRSG 수주 시나리오'!W23 -> 14206.381 | ... R24: ='HRSG 수주 시나리오'!AE23 -> 29529.601 | T24: Bull | U24: =SUMIF($C$7:$R$7,U$8,$C24:$R24) -> 0 | V24: =SUMIF($C$7:$R$7,V$8,$C24:$R24) -> 33037.184 | W24: =SUMIF($C$7:$R$7,W$8,$C24:$R24) -> 87899.95 | X24: =SUMIF($C$7:$R$7,X$8,$C24:$R24) -> 105083.14 | Z24: 정부 주도 노후화 석탄화력발전소 대체 프로젝트 수주 계약의 매출인식 기반 28기의 프로젝트 중 주기기공급자 미선정 건 반영
B25: Base | C25: ='HRSG 수주 시나리오'!P24 -> 0 | D25: ='HRSG 수주 시나리오'!Q24 -> 0 | E25: ='HRSG 수주 시나리오'!R24 -> 0 | F25: ='HRSG 수주 시나리오'!S24 -> 0 | G25: ='HRSG 수주 시나리오'!T24 -> 0 | H25: ='HRSG 수주 시나리오'!U24 -> 1934.6375 | I25: ='HRSG 수주 시나리오'!V24 -> 3869.275 | J25: ='HRSG 수주 시나리오'!W24 -> 6890.7875 | ... R25: ='HRSG 수주 시나리오'!AE24 -> 16053.507 | T25: Base | U25: =SUMIF($C$7:$R$7,U$8,$C25:$R25) -> 0 | V25: =SUMIF($C$7:$R$7,V$8,$C25:$R25) -> 12694.7 | W25: =SUMIF($C$7:$R$7,W$8,$C25:$R25) -> 58220.458 | X25: =SUMIF($C$7:$R$7,X$8,$C25:$R25) -> 62087.982 | Z25: Bear case: 동사의 과거 동일 프로젝트 수주율 기반 가정
B26: Bear | C26: ='HRSG 수주 시나리오'!P25 -> 0 | D26: ='HRSG 수주 시나리오'!Q25 -> 0 | E26: ='HRSG 수주 시나리오'!R25 -> 0 | F26: ='HRSG 수주 시나리오'!S25 -> 0 | G26: ='HRSG 수주 시나리오'!T25 -> 0 | H26: ='HRSG 수주 시나리오'!U25 -> 1934.6375 | I26: ='HRSG 수주 시나리오'!V25 -> 3869.275 | J26: ='HRSG 수주 시나리오'!W25 -> 6890.7875 | ... R26: ='HRSG 수주 시나리오'!AE25 -> 5760.4375 | T26: Bear | U26: =SUMIF($C$7:$R$7,U$8,$C26:$R26) -> 0 | V26: =SUMIF($C$7:$R$7,V$8,$C26:$R26) -> 12694.7 | W26: =SUMIF($C$7:$R$7,W$8,$C26:$R26) -> 41236.037 | X26: =SUMIF($C$7:$R$7,X$8,$C26:$R26) -> 22911.325 | Z26: Bull case: EPC 래퍼런스 반영하여 용인집단발전 6기 중 2기 선정
B27: 중동 | T27: 중동 | Z27: 중동
B28: Bull | C28: ='HRSG 수주 시나리오'!P46 -> 0 | D28: ='HRSG 수주 시나리오'!Q46 -> 0 | E28: ='HRSG 수주 시나리오'!R46 -> 0 | F28: ='HRSG 수주 시나리오'!S46 -> 0 | G28: ='HRSG 수주 시나리오'!T46 -> 0 | H28: ='HRSG 수주 시나리오'!U46 -> 0 | I28: ='HRSG 수주 시나리오'!V46 -> 0 | J28: ='HRSG 수주 시나리오'!W46 -> 0 | ... R28: ='HRSG 수주 시나리오'!AE46 -> 105372.06 | T28: Bull | U28: =SUMIF($C$7:$R$7,U$8,$C28:$R28) -> 0 | V28: =SUMIF($C$7:$R$7,V$8,$C28:$R28) -> 0 | W28: =SUMIF($C$7:$R$7,W$8,$C28:$R28) -> 303922.3 | X28: =SUMIF($C$7:$R$7,X$8,$C28:$R28) -> 547957.5 | Z28: 24년 계약 진행한 사우디 메가 프로젝트 수주계약의 매출인식 기반, '계약 체결 후 3~6개월 내 선금 10% 수령 (선급금), 2분기 후 매출 인식 시작
B29: Base | C29: ='HRSG 수주 시나리오'!P47 -> 0 | D29: ='HRSG 수주 시나리오'!Q47 -> 0 | E29: ='HRSG 수주 시나리오'!R47 -> 0 | F29: ='HRSG 수주 시나리오'!S47 -> 0 | G29: ='HRSG 수주 시나리오'!T47 -> 0 | H29: ='HRSG 수주 시나리오'!U47 -> 0 | I29: ='HRSG 수주 시나리오'!V47 -> 0 | J29: ='HRSG 수주 시나리오'!W47 -> 0 | ... R29: ='HRSG 수주 시나리오'!AE47 -> 89307.057 | T29: Base | U29: =SUMIF($C$7:$R$7,U$8,$C29:$R29) -> 0 | V29: =SUMIF($C$7:$R$7,V$8,$C29:$R29) -> 0 | W29: =SUMIF($C$7:$R$7,W$8,$C29:$R29) -> 303922.3 | X29: =SUMIF($C$7:$R$7,X$8,$C29:$R29) -> 513181.5 | Z29: 중동 지역 수주 전반이 계약부터 7분기 이내를 공사기한으로 명시하나, 이후 수주계약의 공사 기한이 정정되는 사례 다수 존재, 최대 2분기까지 연장 가능성
B30: Bear | C30: ='HRSG 수주 시나리오'!P48 -> 0 | D30: ='HRSG 수주 시나리오'!Q48 -> 0 | E30: ='HRSG 수주 시나리오'!R48 -> 0 | F30: ='HRSG 수주 시나리오'!S48 -> 0 | G30: ='HRSG 수주 시나리오'!T48 -> 0 | H30: ='HRSG 수주 시나리오'!U48 -> 0 | I30: ='HRSG 수주 시나리오'!V48 -> 0 | J30: ='HRSG 수주 시나리오'!W48 -> 0 | ... R30: ='HRSG 수주 시나리오'!AE48 -> 41201.868 | T30: Bear | U30: =SUMIF($C$7:$R$7,U$8,$C30:$R30) -> 0 | V30: =SUMIF($C$7:$R$7,V$8,$C30:$R30) -> 0 | W30: =SUMIF($C$7:$R$7,W$8,$C30:$R30) -> 164697.03 | X30: =SUMIF($C$7:$R$7,X$8,$C30:$R30) -> 281967.89 | Z30: 기존 SEPCO(사우디 지역) 수주 계약의 진행률을 이용하여 매출인식, ASP는 기존 국가 수주계약 반영
B31: 일본 | T31: 일본 | Z31: 일본
B32: Bull | C32: ='HRSG 수주 시나리오'!P72 -> 0 | D32: ='HRSG 수주 시나리오'!Q72 -> 0 | E32: ='HRSG 수주 시나리오'!R72 -> 0 | F32: ='HRSG 수주 시나리오'!S72 -> 0 | G32: ='HRSG 수주 시나리오'!T72 -> 0 | H32: ='HRSG 수주 시나리오'!U72 -> 1472.6794 | I32: ='HRSG 수주 시나리오'!V72 -> 1472.6794 | J32: ='HRSG 수주 시나리오'!W72 -> 1472.6794 | ... R32: ='HRSG 수주 시나리오'!AE72 -> 9630.3304 | T32: Bull | U32: =SUMIF($C$7:$R$7,U$8,$C32:$R32) -> 0 | V32: =SUMIF($C$7:$R$7,V$8,$C32:$R32) -> 4418.0382 | W32: =SUMIF($C$7:$R$7,W$8,$C32:$R32) -> 17208.838 | X32: =SUMIF($C$7:$R$7,X$8,$C32:$R32) -> 34136.378 | Z32: 일본 노후화 발전소 9.3GW 중 Toshiba, Fuji Electric의 점유율 30% 수주 가정
B33: Base | C33: ='HRSG 수주 시나리오'!P73 -> 0 | D33: ='HRSG 수주 시나리오'!Q73 -> 0 | E33: ='HRSG 수주 시나리오'!R73 -> 0 | F33: ='HRSG 수주 시나리오'!S73 -> 0 | G33: ='HRSG 수주 시나리오'!T73 -> 0 | H33: ='HRSG 수주 시나리오'!U73 -> 1472.6794 | I33: ='HRSG 수주 시나리오'!V73 -> 1472.6794 | J33: ='HRSG 수주 시나리오'!W73 -> 1472.6794 | ... R33: ='HRSG 수주 시나리오'!AE73 -> 9630.3304 | T33: Base | U33: =SUMIF($C$7:$R$7,U$8,$C33:$R33) -> 0 | V33: =SUMIF($C$7:$R$7,V$8,$C33:$R33) -> 4418.0382 | W33: =SUMIF($C$7:$R$7,W$8,$C33:$R33) -> 17208.838 | X33: =SUMIF($C$7:$R$7,X$8,$C33:$R33) -> 34136.378 | Z33: 가장 최근 홋카이도 이시카리완 향 수주 매출 규모의 계약이 매년 존재함을 가정
B34: Bear | C34: ='HRSG 수주 시나리오'!P74 -> 0 | D34: ='HRSG 수주 시나리오'!Q74 -> 0 | E34: ='HRSG 수주 시나리오'!R74 -> 0 | F34: ='HRSG 수주 시나리오'!S74 -> 0 | G34: ='HRSG 수주 시나리오'!T74 -> 0 | H34: ='HRSG 수주 시나리오'!U74 -> 0 | I34: ='HRSG 수주 시나리오'!V74 -> 0 | J34: ='HRSG 수주 시나리오'!W74 -> 0 | ... R34: ='HRSG 수주 시나리오'!AE74 -> 0 | T34: Bear | U34: =SUMIF($C$7:$R$7,U$8,$C34:$R34) -> 0 | V34: =SUMIF($C$7:$R$7,V$8,$C34:$R34) -> 0 | W34: =SUMIF($C$7:$R$7,W$8,$C34:$R34) -> 0 | X34: =SUMIF($C$7:$R$7,X$8,$C34:$R34) -> 0 | Z34: 일본 수주 레퍼런스 및 통상적인 HRSG 리드타임 (1.5~2년) 적용
B35: 미국 | T35: 미국 | Z35: 미국
B36: Bull | C36: ='HRSG 수주 시나리오'!P58 -> 0 | D36: ='HRSG 수주 시나리오'!Q58 -> 0 | E36: ='HRSG 수주 시나리오'!R58 -> 0 | F36: ='HRSG 수주 시나리오'!S58 -> 0 | G36: ='HRSG 수주 시나리오'!T58 -> 0 | H36: ='HRSG 수주 시나리오'!U58 -> 0 | I36: ='HRSG 수주 시나리오'!V58 -> 0 | J36: ='HRSG 수주 시나리오'!W58 -> 0 | ... R36: ='HRSG 수주 시나리오'!AE58 -> 40097.335 | T36: Bull | U36: =SUMIF($C$7:$R$7,U$8,$C36:$R36) -> 0 | V36: =SUMIF($C$7:$R$7,V$8,$C36:$R36) -> 0 | W36: =SUMIF($C$7:$R$7,W$8,$C36:$R36) -> 34719.574 | X36: =SUMIF($C$7:$R$7,X$8,$C36:$R36) -> 126002.75 | Z36: 기존 Foster Wheeler 네트워크 기반 Duke Energy 수주 가능성 반영
B37: Base | C37: ='HRSG 수주 시나리오'!P59 -> 0 | D37: ='HRSG 수주 시나리오'!Q59 -> 0 | E37: ='HRSG 수주 시나리오'!R59 -> 0 | F37: ='HRSG 수주 시나리오'!S59 -> 0 | G37: ='HRSG 수주 시나리오'!T59 -> 0 | H37: ='HRSG 수주 시나리오'!U59 -> 0 | I37: ='HRSG 수주 시나리오'!V59 -> 0 | J37: ='HRSG 수주 시나리오'!W59 -> 0 | ... R37: ='HRSG 수주 시나리오'!AE59 -> 25945.334 | T37: Base | U37: =SUMIF($C$7:$R$7,U$8,$C37:$R37) -> 0 | V37: =SUMIF($C$7:$R$7,V$8,$C37:$R37) -> 0 | W37: =SUMIF($C$7:$R$7,W$8,$C37:$R37) -> 34719.574 | X37: =SUMIF($C$7:$R$7,X$8,$C37:$R37) -> 95367.834 | Z37: Bull Case의 경우 미국에서 입찰 대기중인 Monroe CCPP 수주 가정
B38: Bear | C38: ='HRSG 수주 시나리오'!P60 -> 0 | D38: ='HRSG 수주 시나리오'!Q60 -> 0 | E38: ='HRSG 수주 시나리오'!R60 -> 0 | F38: ='HRSG 수주 시나리오'!S60 -> 0 | G38: ='HRSG 수주 시나리오'!T60 -> 0 | H38: ='HRSG 수주 시나리오'!U60 -> 0 | I38: ='HRSG 수주 시나리오'!V60 -> 0 | J38: ='HRSG 수주 시나리오'!W60 -> 0 | ... R38: ='HRSG 수주 시나리오'!AE60 -> 0 | T38: Bear | U38: =SUMIF($C$7:$R$7,U$8,$C38:$R38) -> 0 | V38: =SUMIF($C$7:$R$7,V$8,$C38:$R38) -> 0 | W38: =SUMIF($C$7:$R$7,W$8,$C38:$R38) -> 0 | X38: =SUMIF($C$7:$R$7,X$8,$C38:$R38) -> 0 | Z38: ASP는 기존 Siemens 향 수주 계약분 반영, 가격 상승 예상되나 보수적 추정
C39: =C9=SUM(C11:C12) -> TRUE | D39: =D9=SUM(D11:D12) -> TRUE | E39: =E9=SUM(E11:E12) -> TRUE | F39: =F9=SUM(F11:F12) -> TRUE | G39: =G9=SUM(G11:G12) -> TRUE | H39: =H9=SUM(H11:H12) -> TRUE | I39: =I9=SUM(I11:I12) -> TRUE | J39: =J9=SUM(J11:J12) -> TRUE | ... R39: =R9=SUM(R11:R12) -> TRUE
B40: Bull | T40: (단위: 백만 원)
B41: (단위: 백만 원) | C41: 1Q25A | D41: 2Q25 | E41: 3Q25 | F41: 4Q25 | G41: 1Q26 | H41: 2Q26 | I41: 3Q26 | J41: 4Q26 | K41: 1Q27 | L41: 2Q27 | M41: 3Q27 | N41: 4Q27 | O41: 1Q28 | P41: 2Q28 | Q41: 3Q28 | R41: 4Q28 | T41: HRSG 신규수주 | U41: 2025 | V41: 2026 | W41: 2027 | X41: 2028
B42: HRSG | C42: 98656 | D42: 100885.48 | E42: 136278.53 | F42: 187034.6 | G42: 212979.72 | H42: 216517.79 | I42: 212718.85 | J42: 192222.4 | K42: 172858.76 | L42: 189761.66 | M42: 212444.62 | N42: 207779.49 | O42: 208824.9 | P42: 225904.34 | Q42: 262969.93 | R42: 205379.34 | T42: 국내
B43: YoY % | D43: 0.022598557 | E43: 0.35082396 | F43: 0.37244362 | G43: 0.1387183 | H43: 0.016612261 | I43: -0.01754565 | J43: -0.096354649 | K43: -0.1007356 | L43: 0.097784464 | M43: 0.11953393 | N43: -0.021959269 | O43: 0.0050313594 | P43: 0.081788319 | Q43: 0.16407647 | R43: -0.21900064 | T43: Bull | U43: =U44+SUMIFS('HRSG 수주 시나리오'!$F$16:$F$21,'HRSG 수주 시나리오'!$B$16:$B$21,"잠재",'HRSG 수주 시나리오'!$I$16:$I$21,U$41) -> 107646.88 | V43: =V44+SUMIFS('HRSG 수주 시나리오'!$F$16:$F$21,'HRSG 수주 시나리오'!$B$16:$B$21,"잠재",'HRSG 수주 시나리오'!$I$16:$I$21,V$41) -> 43475 | W43: =W44+SUMIFS('HRSG 수주 시나리오'!$F$16:$F$21,'HRSG 수주 시나리오'!$B$16:$B$21,"잠재",'HRSG 수주 시나리오'!$I$16:$I$21,W$41) -> 229879.02 | X43: =X44+SUMIFS('HRSG 수주 시나리오'!$F$16:$F$21,'HRSG 수주 시나리오'!$B$16:$B$21,"잠재",'HRSG 수주 시나리오'!$I$16:$I$21,X$41) -> 0
T44: Base | U44: =U45+SUMIFS('HRSG 수주 시나리오'!$F$16:$F$21,'HRSG 수주 시나리오'!$B$16:$B$21,"가능",'HRSG 수주 시나리오'!$I$16:$I$21,U$41) -> 43475 | V44: =V45+SUMIFS('HRSG 수주 시나리오'!$F$16:$F$21,'HRSG 수주 시나리오'!$B$16:$B$21,"가능",'HRSG 수주 시나리오'!$I$16:$I$21,V$41) -> 43475 | W44: =W45+SUMIFS('HRSG 수주 시나리오'!$F$16:$F$21,'HRSG 수주 시나리오'!$B$16:$B$21,"가능",'HRSG 수주 시나리오'!$I$16:$I$21,W$41) -> 165707.14 | X44: =X45+SUMIFS('HRSG 수주 시나리오'!$F$16:$F$21,'HRSG 수주 시나리오'!$B$16:$B$21,"가능",'HRSG 수주 시나리오'!$I$16:$I$21,X$41) -> 0
B45: Base | T45: Bear | U45: =SUMIFS('HRSG 수주 시나리오'!$F$16:$F$21,'HRSG 수주 시나리오'!$B$16:$B$21,"확실",'HRSG 수주 시나리오'!$I$16:$I$21,U$41) -> 43475 | V45: =SUMIFS('HRSG 수주 시나리오'!$F$16:$F$21,'HRSG 수주 시나리오'!$B$16:$B$21,"확실",'HRSG 수주 시나리오'!$I$16:$I$21,V$41) -> 43475 | W45: =SUMIFS('HRSG 수주 시나리오'!$F$16:$F$21,'HRSG 수주 시나리오'!$B$16:$B$21,"확실",'HRSG 수주 시나리오'!$I$16:$I$21,W$41) -> 0 | X45: =SUMIFS('HRSG 수주 시나리오'!$F$16:$F$21,'HRSG 수주 시나리오'!$B$16:$B$21,"확실",'HRSG 수주 시나리오'!$I$16:$I$21,X$41) -> 0
B46: (단위: 백만 원) | C46: 1Q25A | D46: 2Q25 | E46: 3Q25 | F46: 4Q25 | G46: 1Q26 | H46: 2Q26 | I46: 3Q26 | J46: 4Q26 | K46: 1Q27 | L46: 2Q27 | M46: 3Q27 | N46: 4Q27 | O46: 1Q28 | P46: 2Q28 | Q46: 3Q28 | R46: 4Q28 | T46: 중동
B47: HRSG | C47: 98656 | D47: 100885.48 | E47: 136278.53 | F47: 187034.6 | G47: 210124.07 | H47: 213662.14 | I47: 205403.25 | J47: 184906.8 | K47: 164355.99 | L47: 181258.89 | M47: 207535.47 | N47: 200014.69 | O47: 202439.8 | P47: 208304.9 | Q47: 222241.48 | R47: 161686.25 | T47: Bull | U47: =U48+SUMIFS('HRSG 수주 시나리오'!$F$38:$F$44,'HRSG 수주 시나리오'!$B$38:$B$44,"잠재",'HRSG 수주 시나리오'!$I$38:$I$44,U$41) -> 0 | V47: =V48+SUMIFS('HRSG 수주 시나리오'!$F$38:$F$44,'HRSG 수주 시나리오'!$B$38:$B$44,"잠재",'HRSG 수주 시나리오'!$I$38:$I$44,V$41) -> 634608.99 | W47: =W48+SUMIFS('HRSG 수주 시나리오'!$F$38:$F$44,'HRSG 수주 시나리오'!$B$38:$B$44,"잠재",'HRSG 수주 시나리오'!$I$38:$I$44,W$41) -> 454082.52 | X47: =X48+SUMIFS('HRSG 수주 시나리오'!$F$38:$F$44,'HRSG 수주 시나리오'!$B$38:$B$44,"잠재",'HRSG 수주 시나리오'!$I$38:$I$44,X$41) -> 0
B48: YoY % | D48: 0.022598557 | E48: 0.35082396 | F48: 0.37244362 | G48: 0.12345028 | H48: 0.016838026 | I48: -0.038653973 | J48: -0.099786393 | K48: -0.11114149 | L48: 0.10284323 | M48: 0.14496713 | N48: -0.036238513 | O48: 0.012124652 | P48: 0.028972089 | Q48: 0.066904705 | R48: -0.27247493 | T48: Base | U48: =U49+SUMIFS('HRSG 수주 시나리오'!$F$38:$F$44,'HRSG 수주 시나리오'!$B$38:$B$44,"가능",'HRSG 수주 시나리오'!$I$38:$I$44,U$41) -> 0 | V48: =V49+SUMIFS('HRSG 수주 시나리오'!$F$38:$F$44,'HRSG 수주 시나리오'!$B$38:$B$44,"가능",'HRSG 수주 시나리오'!$I$38:$I$44,V$41) -> 634608.99 | W48: =W49+SUMIFS('HRSG 수주 시나리오'!$F$38:$F$44,'HRSG 수주 시나리오'!$B$38:$B$44,"가능",'HRSG 수주 시나리오'!$I$38:$I$44,W$41) -> 359582.52 | X48: =X49+SUMIFS('HRSG 수주 시나리오'!$F$38:$F$44,'HRSG 수주 시나리오'!$B$38:$B$44,"가능",'HRSG 수주 시나리오'!$I$38:$I$44,X$41) -> 0
T49: Bear | U49: =U50+SUMIFS('HRSG 수주 시나리오'!$F$38:$F$44,'HRSG 수주 시나리오'!$B$38:$B$44,"확실",'HRSG 수주 시나리오'!$I$38:$I$44,U$41) -> 0 | V49: =V50+SUMIFS('HRSG 수주 시나리오'!$F$38:$F$44,'HRSG 수주 시나리오'!$B$38:$B$44,"확실",'HRSG 수주 시나리오'!$I$38:$I$44,V$41) -> 344636.99 | W49: =W50+SUMIFS('HRSG 수주 시나리오'!$F$38:$F$44,'HRSG 수주 시나리오'!$B$38:$B$44,"확실",'HRSG 수주 시나리오'!$I$38:$I$44,W$41) -> 140922.57 | X49: =X50+SUMIFS('HRSG 수주 시나리오'!$F$38:$F$44,'HRSG 수주 시나리오'!$B$38:$B$44,"확실",'HRSG 수주 시나리오'!$I$38:$I$44,X$41) -> 0
B50: Bear | T50: 일본
B51: (단위: 백만 원) | C51: 1Q25A | D51: 2Q25 | E51: 3Q25 | F51: 4Q25 | G51: 1Q26 | H51: 2Q26 | I51: 3Q26 | J51: 4Q26 | K51: 1Q27 | L51: 2Q27 | M51: 3Q27 | N51: 4Q27 | O51: 1Q28 | P51: 2Q28 | Q51: 3Q28 | R51: 4Q28 | T51: Bull | U51: =U52+SUMIFS('HRSG 수주 시나리오'!$F$67:$F$70,'HRSG 수주 시나리오'!$B$67:$B$70,"잠재",'HRSG 수주 시나리오'!$I$67:$I$70,U$41) -> 66187.838 | V51: =V52+SUMIFS('HRSG 수주 시나리오'!$F$67:$F$70,'HRSG 수주 시나리오'!$B$67:$B$70,"잠재",'HRSG 수주 시나리오'!$I$67:$I$70,V$41) -> 66187.838 | W51: =W52+SUMIFS('HRSG 수주 시나리오'!$F$67:$F$70,'HRSG 수주 시나리오'!$B$67:$B$70,"잠재",'HRSG 수주 시나리오'!$I$67:$I$70,W$41) -> 66187.838 | X51: =X52+SUMIFS('HRSG 수주 시나리오'!$F$67:$F$70,'HRSG 수주 시나리오'!$B$67:$B$70,"잠재",'HRSG 수주 시나리오'!$I$67:$I$70,X$41) -> 66187.838
B52: HRSG | C52: 98656 | D52: 100885.48 | E52: 136278.53 | F52: 187034.6 | G52: 210124.07 | H52: 212189.46 | I52: 203930.57 | J52: 183434.12 | K52: 156018.91 | L52: 137436.43 | M52: 131618.71 | N52: 119952.9 | O52: 121063.81 | P52: 110554.69 | Q52: 95447.146 | R52: 67712.327 | T52: Base | U52: =U53+SUMIFS('HRSG 수주 시나리오'!$F$67:$F$70,'HRSG 수주 시나리오'!$B$67:$B$70,"가능",'HRSG 수주 시나리오'!$I$67:$I$70,U$41) -> 66187.838 | V52: =V53+SUMIFS('HRSG 수주 시나리오'!$F$67:$F$70,'HRSG 수주 시나리오'!$B$67:$B$70,"가능",'HRSG 수주 시나리오'!$I$67:$I$70,V$41) -> 66187.838 | W52: =W53+SUMIFS('HRSG 수주 시나리오'!$F$67:$F$70,'HRSG 수주 시나리오'!$B$67:$B$70,"가능",'HRSG 수주 시나리오'!$I$67:$I$70,W$41) -> 66187.838 | X52: =X53+SUMIFS('HRSG 수주 시나리오'!$F$67:$F$70,'HRSG 수주 시나리오'!$B$67:$B$70,"가능",'HRSG 수주 시나리오'!$I$67:$I$70,X$41) -> 66187.838
B53: YoY % | D53: 0.022598557 | E53: 0.35082396 | F53: 0.37244362 | G53: 0.12345028 | H53: 0.0098294079 | I53: -0.038922247 | J53: -0.100507 | K53: -0.14945537 | L53: -0.11910404 | M53: -0.042330263 | N53: -0.08863338 | O53: 0.0092612208 | P53: -0.086806449 | Q53: -0.13665219 | R53: -0.29057777 | T53: Bear | U53: =U54+SUMIFS('HRSG 수주 시나리오'!$F$67:$F$70,'HRSG 수주 시나리오'!$B$67:$B$70,"확실",'HRSG 수주 시나리오'!$I$67:$I$70,U$41) -> 0 | V53: =V54+SUMIFS('HRSG 수주 시나리오'!$F$67:$F$70,'HRSG 수주 시나리오'!$B$67:$B$70,"확실",'HRSG 수주 시나리오'!$I$67:$I$70,V$41) -> 0 | W53: =W54+SUMIFS('HRSG 수주 시나리오'!$F$67:$F$70,'HRSG 수주 시나리오'!$B$67:$B$70,"확실",'HRSG 수주 시나리오'!$I$67:$I$70,W$41) -> 0 | X53: =X54+SUMIFS('HRSG 수주 시나리오'!$F$67:$F$70,'HRSG 수주 시나리오'!$B$67:$B$70,"확실",'HRSG 수주 시나리오'!$I$67:$I$70,X$41) -> 0
T54: 미국
T55: Bull | U55: =U56+SUMIFS('HRSG 수주 시나리오'!$F$54:$F$56,'HRSG 수주 시나리오'!$B$54:$B$56,"잠재",'HRSG 수주 시나리오'!$I$54:$I$56,U$41) -> 0 | V55: =V56+SUMIFS('HRSG 수주 시나리오'!$F$54:$F$56,'HRSG 수주 시나리오'!$B$54:$B$56,"잠재",'HRSG 수주 시나리오'!$I$54:$I$56,V$41) -> 94346.67 | W55: =W56+SUMIFS('HRSG 수주 시나리오'!$F$54:$F$56,'HRSG 수주 시나리오'!$B$54:$B$56,"잠재",'HRSG 수주 시나리오'!$I$54:$I$56,W$41) -> 180368.63 | X55: =X56+SUMIFS('HRSG 수주 시나리오'!$F$54:$F$56,'HRSG 수주 시나리오'!$B$54:$B$56,"잠재",'HRSG 수주 시나리오'!$I$54:$I$56,X$41) -> 0
T56: Base | U56: =U57+SUMIFS('HRSG 수주 시나리오'!$F$54:$F$56,'HRSG 수주 시나리오'!$B$54:$B$56,"가능",'HRSG 수주 시나리오'!$I$54:$I$56,U$41) -> 0 | V56: =V57+SUMIFS('HRSG 수주 시나리오'!$F$54:$F$56,'HRSG 수주 시나리오'!$B$54:$B$56,"가능",'HRSG 수주 시나리오'!$I$54:$I$56,V$41) -> 94346.67 | W56: =W57+SUMIFS('HRSG 수주 시나리오'!$F$54:$F$56,'HRSG 수주 시나리오'!$B$54:$B$56,"가능",'HRSG 수주 시나리오'!$I$54:$I$56,W$41) -> 97121.572 | X56: =X57+SUMIFS('HRSG 수주 시나리오'!$F$54:$F$56,'HRSG 수주 시나리오'!$B$54:$B$56,"가능",'HRSG 수주 시나리오'!$I$54:$I$56,X$41) -> 0
T57: Bear | U57: =U39+SUMIFS('HRSG 수주 시나리오'!$F$54:$F$56,'HRSG 수주 시나리오'!$B$54:$B$56,"확실",'HRSG 수주 시나리오'!$I$54:$I$56,U$41) -> 0 | V57: =V39+SUMIFS('HRSG 수주 시나리오'!$F$54:$F$56,'HRSG 수주 시나리오'!$B$54:$B$56,"확실",'HRSG 수주 시나리오'!$I$54:$I$56,V$41) -> 0 | W57: =W39+SUMIFS('HRSG 수주 시나리오'!$F$54:$F$56,'HRSG 수주 시나리오'!$B$54:$B$56,"확실",'HRSG 수주 시나리오'!$I$54:$I$56,W$41) -> 0 | X57: =X39+SUMIFS('HRSG 수주 시나리오'!$F$54:$F$56,'HRSG 수주 시나리오'!$B$54:$B$56,"확실",'HRSG 수주 시나리오'!$I$54:$I$56,X$41) -> 0

Sheet Boiler
B1: Estimation
B2: Boiler
B5: Active Scenario | C5: Bull | X5: 24-28 CAGR
B6: Scenario Number | C6: =IF(C5="Bull",1, IF(C5="Base",2,3)) -> 1 | X6: =RATE(5,0,-T9,X9) -> 0.27399578
C7: =2000+RIGHT(C8,2) -> #VALUE! | D7: =2000+RIGHT(D8,2) -> 2025 | E7: =2000+RIGHT(E8,2) -> 2025 | F7: =2000+RIGHT(F8,2) -> 2025 | G7: =2000+RIGHT(G8,2) -> 2026 | H7: =2000+RIGHT(H8,2) -> 2026 | I7: =2000+RIGHT(I8,2) -> 2026 | J7: =2000+RIGHT(J8,2) -> 2026 | ... R7: =2000+RIGHT(R8,2) -> 2028
A8: x | B8: (단위: 백만 원) | C8: 1Q25A | D8: 2Q25 | E8: 3Q25 | F8: 4Q25 | G8: 1Q26 | H8: 2Q26 | I8: 3Q26 | J8: 4Q26 | K8: 1Q27 | L8: 2Q27 | M8: 3Q27 | N8: 4Q27 | O8: 1Q28 | P8: 2Q28 | Q8: 3Q28 | R8: 4Q28 | T8: 2024 | U8: 2025 | V8: 2026 | W8: 2027 | X8: 2028 | Z8: 추정 논리
B9: =B2 -> Boiler | C9: =SUM(C11,C14) -> 20124 | D9: =SUM(D11,D14) -> 20124 | E9: =SUM(E11,E14) -> 36980.886 | F9: =SUM(F11,F14) -> 36980.886 | G9: =SUM(G11,G14) -> 36980.886 | H9: =SUM(H11,H14) -> 36980.886 | I9: =SUM(I11,I14) -> 36980.886 | J9: =SUM(J11,J14) -> 36980.886 | ... R9: =SUM(R11,R14) -> 57400.886 | T9: 68413 | U9: =SUMIF($C$7:$R$7,U$8,$C9:$R9) -> 94085.771 | V9: =SUMIF($C$7:$R$7,V$8,$C9:$R9) -> 147923.54 | W9: =SUMIF($C$7:$R$7,W$8,$C9:$R9) -> 229603.54 | X9: =SUMIF($C$7:$R$7,X$8,$C9:$R9) -> 229603.54
B10: YoY % | D10: =D9/C9-1 -> 0 | E10: =E9/D9-1 -> 0.83765085 | F10: =F9/E9-1 -> 0 | G10: =G9/F9-1 -> 0 | H10: =H9/G9-1 -> 0 | I10: =I9/H9-1 -> 0 | J10: =J9/I9-1 -> 0 | K10: =K9/J9-1 -> 0.55217715 | ... R10: =R9/Q9-1 -> 0 | U10: =U9/T9-1 -> 0.37526159 | V10: =V9/U9-1 -> 0.57222012 | W10: =W9/V9-1 -> 0.55217715 | X10: =X9/W9-1 -> 0
B11: 기존수주 매출 (추정) | C11: =SUM(C12:C13) -> 20124 | D11: =SUM(D12:D13) -> 20124 | E11: =SUM(E12:E13) -> 36980.886 | F11: =SUM(F12:F13) -> 36980.886 | G11: =SUM(G12:G13) -> 36980.886 | H11: =SUM(H12:H13) -> 36980.886 | I11: =SUM(I12:I13) -> 36980.886 | J11: =SUM(J12:J13) -> 36980.886 | ... R11: =SUM(R12:R13) -> 36980.886
B12: 필리핀 San Miguel CFBC 보일러 | C12: ='기존수주 매출'!AF44 -> 0 | D12: ='기존수주 매출'!AG44 -> 0 | E12: ='기존수주 매출'!AH44 -> 36980.886 | F12: ='기존수주 매출'!AI44 -> 36980.886 | G12: ='기존수주 매출'!AJ44 -> 36980.886 | H12: ='기존수주 매출'!AK44 -> 36980.886 | I12: ='기존수주 매출'!AL44 -> 36980.886 | J12: ='기존수주 매출'!AM44 -> 36980.886 | ... R12: ='기존수주 매출'!AU44 -> 36980.886 | Z12: 25년 4월 수주 계약을 맺은 필리핀향 CFBC 보일러 매출 인식은 3Q25에 시작될 것으로 전망. 유사한 사례가 없어 진행률 일괄 적용.
B13: 기타 보일러 매출 | C13: =재무분석!AA40 -> 20124 | D13: =C13 -> 20124 | E13: 0 | F13: 0 | G13: 0 | H13: 0 | I13: 0 | J13: 0 | K13: 0 | L13: 0 | M13: 0 | N13: 0 | O13: 0 | P13: 0 | Q13: 0 | R13: 0
B14: 신규 수주 매출 (추정) | C14: =SUM(C15:C16) -> 0 | D14: =SUM(D15:D16) -> 0 | E14: =SUM(E15:E16) -> 0 | F14: =SUM(F15:F16) -> 0 | G14: =SUM(G15:G16) -> 0 | H14: =SUM(H15:H16) -> 0 | I14: =SUM(I15:I16) -> 0 | J14: =SUM(J15:J16) -> 0 | ... R14: =SUM(R15:R16) -> 20420 | Z14: 삼척블루파워, 당진화력발전소(암모니아 혼소 보일러)의 경우 26 실증사업 진행 후 27년 설치부터 공사 기한인 3개년 간 매출 인식 가정. 유사한 사례가 없어 진행률 일괄 적용
B15: 삼척블루파워 CFBC 보일러 | C15: ='기존수주 매출'!AF48 -> 0 | D15: ='기존수주 매출'!AG48 -> 0 | E15: ='기존수주 매출'!AH48 -> 0 | F15: ='기존수주 매출'!AI48 -> 0 | G15: ='기존수주 매출'!AJ48 -> 0 | H15: ='기존수주 매출'!AK48 -> 0 | I15: ='기존수주 매출'!AL48 -> 0 | J15: ='기존수주 매출'!AM48 -> 0 | ... R15: ='기존수주 매출'!AU48 -> 10220
B16: 당진화력발전소 PC보일러 | C16: ='기존수주 매출'!AF49 -> 0 | D16: ='기존수주 매출'!AG49 -> 0 | E16: ='기존수주 매출'!AH49 -> 0 | F16: ='기존수주 매출'!AI49 -> 0 | G16: ='기존수주 매출'!AJ49 -> 0 | H16: ='기존수주 매출'!AK49 -> 0 | I16: ='기존수주 매출'!AL49 -> 0 | J16: ='기존수주 매출'!AM49 -> 0 | ... R16: ='기존수주 매출'!AU49 -> 10200

Sheet BOP
B1: Estimation
B2: BOP
B5: Active Scenario | C5: Base | X5: 24-28 CAGR
B6: Scenario Number | C6: =IF(C5="Bull",1, IF(C5="Base",2,3)) -> 2 | X6: =RATE(5,0,-T9,X9) -> 0.60365283
C7: =2000+RIGHT(C8,2) -> #VALUE! | D7: =2000+RIGHT(D8,2) -> 2025 | E7: =2000+RIGHT(E8,2) -> 2025 | F7: =2000+RIGHT(F8,2) -> 2025 | G7: =2000+RIGHT(G8,2) -> 2026 | H7: =2000+RIGHT(H8,2) -> 2026 | I7: =2000+RIGHT(I8,2) -> 2026 | J7: =2000+RIGHT(J8,2) -> 2026 | ... R7: =2000+RIGHT(R8,2) -> 2028
A8: x | B8: (단위: 백만 원) | C8: 1Q25A | D8: 2Q25 | E8: 3Q25 | F8: 4Q25 | G8: 1Q26 | H8: 2Q26 | I8: 3Q26 | J8: 4Q26 | K8: 1Q27 | L8: 2Q27 | M8: 3Q27 | N8: 4Q27 | O8: 1Q28 | P8: 2Q28 | Q8: 3Q28 | R8: 4Q28 | T8: 2024 | U8: 2025 | V8: 2026 | W8: 2027 | X8: 2028 | Z8: 추정 논리
B9: =B2 -> BOP | C9: 98656 | D9: =SUM(D11:D12) -> 11063.916 | E9: =SUM(E11:E12) -> 11063.916 | F9: =SUM(F11:F12) -> 11063.916 | G9: =SUM(G11:G12) -> 11063.916 | H9: =SUM(H11:H12) -> 11063.916 | I9: =SUM(I11:I12) -> 11063.916 | J9: =SUM(J11:J12) -> 11063.916 | K9: =SUM(K11:K12) -> 19705.093 | ... R9: =SUM(R11:R12) -> 45033.147 | T9: 14305 | U9: =SUMIF($C$7:$R$7,U$8,$C9:$R9) -> 33191.749 | V9: =SUMIF($C$7:$R$7,V$8,$C9:$R9) -> 44255.665 | W9: =SUMIF($C$7:$R$7,W$8,$C9:$R9) -> 89829.271 | X9: =SUMIF($C$7:$R$7,X$8,$C9:$R9) -> 151718.88
B10: YoY % | D10: =D9/C9-1 -> -0.88785359 | E10: =E9/D9-1 -> 0 | F10: =F9/E9-1 -> 0 | G10: =G9/F9-1 -> 0 | H10: =H9/G9-1 -> 0 | I10: =I9/H9-1 -> 0 | J10: =J9/I9-1 -> 0 | K10: =K9/J9-1 -> 0.78102331 | ... R10: =R9/Q9-1 -> 0 | U10: =U9/T9-1 -> 1.32029 | V10: =V9/U9-1 -> 0.33333333 | W10: =W9/V9-1 -> 1.0297802 | X10: =X9/W9-1 -> 0.68896932
B11: 국내 | C11: =C16+CHOOSE($C$6,C21,C22,C23) -> 98656 | D11: =D16+CHOOSE($C$6,D21,D22,D23) -> 11063.916 | E11: =E16+CHOOSE($C$6,E21,E22,E23) -> 11063.916 | F11: =F16+CHOOSE($C$6,F21,F22,F23) -> 11063.916 | G11: =G16+CHOOSE($C$6,G21,G22,G23) -> 11063.916 | H11: =H16+CHOOSE($C$6,H21,H22,H23) -> 11063.916 | I11: =I16+CHOOSE($C$6,I21,I22,I23) -> 11063.916 | J11: =J16+CHOOSE($C$6,J21,J22,J23) -> 11063.916 | ... R11: =R16+CHOOSE($C$6,R21,R22,R23) -> 19705.093 | U11: =SUMIF($C$7:$R$7,U$8,$C11:$R11) -> 33191.749 | V11: =SUMIF($C$7:$R$7,V$8,$C11:$R11) -> 44255.665 | W11: =SUMIF($C$7:$R$7,W$8,$C11:$R11) -> 83657.968 | X11: =SUMIF($C$7:$R$7,X$8,$C11:$R11) -> 78820.371
B12: 해외 | C12: =SUM(C13:C15) -> 0 | D12: =SUM(D13:D15) -> 0 | E12: =SUM(E13:E15) -> 0 | F12: =SUM(F13:F15) -> 0 | G12: =SUM(G13:G15) -> 0 | H12: =SUM(H13:H15) -> 0 | I12: =SUM(I13:I15) -> 0 | J12: =SUM(J13:J15) -> 0 | ... R12: =SUM(R13:R15) -> 25328.054 | U12: =SUMIF($C$7:$R$7,U$8,$C12:$R12) -> 0 | V12: =SUMIF($C$7:$R$7,V$8,$C12:$R12) -> 0 | W12: =SUMIF($C$7:$R$7,W$8,$C12:$R12) -> 6171.3025 | X12: =SUMIF($C$7:$R$7,X$8,$C12:$R12) -> 72898.511
B13: 유럽 | C13: =CHOOSE($C$6,C25,C26,C27) -> 0 | D13: =CHOOSE($C$6,D25,D26,D27) -> 0 | E13: =CHOOSE($C$6,E25,E26,E27) -> 0 | F13: =CHOOSE($C$6,F25,F26,F27) -> 0 | G13: =CHOOSE($C$6,G25,G26,G27) -> 0 | H13: =CHOOSE($C$6,H25,H26,H27) -> 0 | I13: =CHOOSE($C$6,I25,I26,I27) -> 0 | J13: =CHOOSE($C$6,J25,J26,J27) -> 0 | ... R13: =CHOOSE($C$6,R25,R26,R27) -> 16071.1 | U13: =SUMIF($C$7:$R$7,U$8,$C13:$R13) -> 0 | V13: =SUMIF($C$7:$R$7,V$8,$C13:$R13) -> 0 | W13: =SUMIF($C$7:$R$7,W$8,$C13:$R13) -> 0 | X13: =SUMIF($C$7:$R$7,X$8,$C13:$R13) -> 42041.998
B14: 북미 | C14: =CHOOSE($C$6,C29,C30,C31) -> 0 | D14: =CHOOSE($C$6,D29,D30,D31) -> 0 | E14: =CHOOSE($C$6,E29,E30,E31) -> 0 | F14: =CHOOSE($C$6,F29,F30,F31) -> 0 | G14: =CHOOSE($C$6,G29,G30,G31) -> 0 | H14: =CHOOSE($C$6,H29,H30,H31) -> 0 | I14: =CHOOSE($C$6,I29,I30,I31) -> 0 | J14: =CHOOSE($C$6,J29,J30,J31) -> 0 | ... R14: =CHOOSE($C$6,R29,R30,R31) -> 9256.9538 | U14: =SUMIF($C$7:$R$7,U$8,$C14:$R14) -> 0 | V14: =SUMIF($C$7:$R$7,V$8,$C14:$R14) -> 0 | W14: =SUMIF($C$7:$R$7,W$8,$C14:$R14) -> 6171.3025 | X14: =SUMIF($C$7:$R$7,X$8,$C14:$R14) -> 30856.513
B15: 중동 | C15: =CHOOSE($C$6,C33,C34,C35) -> 0 | D15: =CHOOSE($C$6,D33,D34,D35) -> 0 | E15: =CHOOSE($C$6,E33,E34,E35) -> 0 | F15: =CHOOSE($C$6,F33,F34,F35) -> 0 | G15: =CHOOSE($C$6,G33,G34,G35) -> 0 | H15: =CHOOSE($C$6,H33,H34,H35) -> 0 | I15: =CHOOSE($C$6,I33,I34,I35) -> 0 | J15: =CHOOSE($C$6,J33,J34,J35) -> 0 | ... R15: =CHOOSE($C$6,R33,R34,R35) -> 0 | U15: =SUMIF($C$7:$R$7,U$8,$C15:$R15) -> 0 | V15: =SUMIF($C$7:$R$7,V$8,$C15:$R15) -> 0 | W15: =SUMIF($C$7:$R$7,W$8,$C15:$R15) -> 0 | X15: =SUMIF($C$7:$R$7,X$8,$C15:$R15) -> 0
A16: x | B16: 기존수주 매출 (추정) | C16: =SUM(C17:C18) -> 98656 | D16: =SUM(D17:D18) -> 8645.1176 | E16: =SUM(E17:E18) -> 8645.1176 | F16: =SUM(F17:F18) -> 8645.1176 | G16: =SUM(G17:G18) -> 8645.1176 | H16: =SUM(H17:H18) -> 8645.1176 | I16: =SUM(I17:I18) -> 8645.1176 | J16: =SUM(J17:J18) -> 8645.1176 | ... R16: =SUM(R17:R18) -> 8645.1176
B17: 국내 (한수원 신한울 3,4호기) | C17: =SUM('BOP 수주 시나리오'!Q20:Q22) -> 0 | D17: =SUM('BOP 수주 시나리오'!R20:R22) -> 8645.1176 | E17: =SUM('BOP 수주 시나리오'!S20:S22) -> 8645.1176 | F17: =SUM('BOP 수주 시나리오'!T20:T22) -> 8645.1176 | G17: =SUM('BOP 수주 시나리오'!U20:U22) -> 8645.1176 | H17: =SUM('BOP 수주 시나리오'!V20:V22) -> 8645.1176 | I17: =SUM('BOP 수주 시나리오'!W20:W22) -> 8645.1176 | J17: =SUM('BOP 수주 시나리오'!X20:X22) -> 8645.1176 | ... R17: =SUM('BOP 수주 시나리오'!AF20:AF22) -> 8645.1176
B18: 기타 BOP (원전 외) | C18: =C9-C17 -> 98656 | D18: 0 | E18: 0 | F18: 0 | G18: 0 | H18: 0 | I18: 0 | J18: 0 | K18: 0 | L18: 0 | M18: 0 | N18: 0 | O18: 0 | P18: 0 | Q18: 0 | R18: 0
A19: x | B19: 신규 수주 매출 (추정) | T19: HRSG 신규수주 | U19: 2025 | V19: 2026 | W19: 2027 | X19: 2028 | Z19: 보조기기 공급계약 시점 추정 논리
B20: 국내 | T20: 국내 | Z20: 결론: 통상적인 BOP 계약시기 및 과거 수주 사례(UAE 바라카 프로젝트 및 미국 보글 3,4호기-섬머 3,4호기)의 수주 시점을 고려하여, 다음과 같이 추정하였다.
B21: Bull | C21: =C22 -> 0 | D21: =D22 -> 2418.7986 | E21: =E22 -> 2418.7986 | F21: =F22 -> 2418.7986 | G21: =G22 -> 2418.7986 | H21: =H22 -> 2418.7986 | I21: =I22 -> 2418.7986 | J21: =J22 -> 2418.7986 | ... R21: =R22 -> 11059.975 | T21: Bull | U21: =U22 -> 24187.986 | V21: =V22 -> 0 | W21: =W22 -> 171087.99 | X21: =X22 -> 0 | Z21: 근거1. 보조기기는 주로 시공사 및 주기기 공급업체 선정 1,2년 후 ~ 구조물 공사 시작(착공)전 12~18개월 전에 공급 계약을 진행한다.
B22: Base | C22: =C23 -> 0 | D22: =D23 -> 2418.7986 | E22: =E23 -> 2418.7986 | F22: =F23 -> 2418.7986 | G22: =G23 -> 2418.7986 | H22: =H23 -> 2418.7986 | I22: =I23 -> 2418.7986 | J22: =J23 -> 2418.7986 | ... R22: =R23 -> 11059.975 | T22: Base | U22: =U23 -> 24187.986 | V22: =V23 -> 0 | W22: =W23 -> 171087.99 | X22: =X23 -> 0 | Z22: 또한 구조물의 시공 단계별로 수주가 진행되며, 보통 격납건물용인 SSLW, CLP, CPP가 먼저 발주되고, 다음으로 복수기가 발주되며, 마지막으로 착공 이전 급수가열기 및 탈기기의 발주가 진행된다.
B23: Bear | C23: =SUM('BOP 수주 시나리오'!R23:R27) -> 0 | D23: =SUM('BOP 수주 시나리오'!S23:S27) -> 2418.7986 | E23: =SUM('BOP 수주 시나리오'!T23:T27) -> 2418.7986 | F23: =SUM('BOP 수주 시나리오'!U23:U27) -> 2418.7986 | G23: =SUM('BOP 수주 시나리오'!V23:V27) -> 2418.7986 | H23: =SUM('BOP 수주 시나리오'!W23:W27) -> 2418.7986 | I23: =SUM('BOP 수주 시나리오'!X23:X27) -> 2418.7986 | J23: =SUM('BOP 수주 시나리오'!Y23:Y27) -> 2418.7986 | ... R23: =SUM('BOP 수주 시나리오'!AG23:AG27) -> 11059.975 | T23: Bear | U23: =SUMIF('BOP 수주 시나리오'!$J$23:$J$27,BOP!U$19,'BOP 수주 시나리오'!$G$23:$G$27) -> 24187.986 | V23: =SUMIF('BOP 수주 시나리오'!$J$23:$J$27,BOP!V$19,'BOP 수주 시나리오'!$G$23:$G$27) -> 0 | W23: =SUMIF('BOP 수주 시나리오'!$J$23:$J$27,BOP!W$19,'BOP 수주 시나리오'!$G$23:$G$27) -> 171087.99 | X23: =SUMIF('BOP 수주 시나리오'!$J$23:$J$27,BOP!X$19,'BOP 수주 시나리오'!$G$23:$G$27) -> 0 | Z23: 근거2. 한편 국내에서 진행되는 프로젝트와 달리, 해외 프로젝트는 대형부품의 출하 및 선적, 현지 공급망 통과, 설계사 검안 등의 이유로 추가적인 시간이 소요된다. 따라서 통상적인 수주시기보다 이른 시점에 발주가 진행된다.
B24: 유럽 | T24: 유럽 | Z24: * 단, 폴란드는 동사가 현지업체 ZKE Ferrum과 폴란드 원전 보조기기 개발 및 공급 협력을 체결했기 때문에, CLP, CPP, SSLW의 패키징이 가능하다고 가정하였다.
B25: Bull | C25: ='BOP 수주 시나리오'!Q64 -> 0 | D25: ='BOP 수주 시나리오'!R64 -> 0 | E25: ='BOP 수주 시나리오'!S64 -> 0 | F25: ='BOP 수주 시나리오'!T64 -> 0 | G25: ='BOP 수주 시나리오'!U64 -> 0 | H25: ='BOP 수주 시나리오'!V64 -> 0 | I25: ='BOP 수주 시나리오'!W64 -> 0 | J25: ='BOP 수주 시나리오'!X64 -> 0 | ... R25: ='BOP 수주 시나리오'!AF64 -> 36952.767 | T25: Bull | U25: =U26+SUMIFS('BOP 수주 시나리오'!$G$40:$G$63,'BOP 수주 시나리오'!$B$40:$B$63,"잠재",'BOP 수주 시나리오'!$J$40:$J$63,U$19) -> 0 | V25: =V26+SUMIFS('BOP 수주 시나리오'!$G$40:$G$63,'BOP 수주 시나리오'!$B$40:$B$63,"잠재",'BOP 수주 시나리오'!$J$40:$J$63,V$19) -> 0 | W25: =W26+SUMIFS('BOP 수주 시나리오'!$G$40:$G$63,'BOP 수주 시나리오'!$B$40:$B$63,"잠재",'BOP 수주 시나리오'!$J$40:$J$63,W$19)-SUM('BOP 수주 시나리오'!G56:G57) -> 643974.46 | X25: =X26+SUMIFS('BOP 수주 시나리오'!$G$40:$G$63,'BOP 수주 시나리오'!$B$40:$B$63,"잠재",'BOP 수주 시나리오'!$J$40:$J$63,X$19)-SUM('BOP 수주 시나리오'!I58:I59) -> 419500.72
B26: Base | C26: ='BOP 수주 시나리오'!Q65 -> 0 | D26: ='BOP 수주 시나리오'!R65 -> 0 | E26: ='BOP 수주 시나리오'!S65 -> 0 | F26: ='BOP 수주 시나리오'!T65 -> 0 | G26: ='BOP 수주 시나리오'!U65 -> 0 | H26: ='BOP 수주 시나리오'!V65 -> 0 | I26: ='BOP 수주 시나리오'!W65 -> 0 | J26: ='BOP 수주 시나리오'!X65 -> 0 | ... R26: ='BOP 수주 시나리오'!AF65 -> 16071.1 | T26: Base | U26: =U27+SUMIFS('BOP 수주 시나리오'!$G$40:$G$63,'BOP 수주 시나리오'!$B$40:$B$63,"가능",'BOP 수주 시나리오'!$J$40:$J$63,U$19) -> 0 | V26: =V27+SUMIFS('BOP 수주 시나리오'!$G$40:$G$63,'BOP 수주 시나리오'!$B$40:$B$63,"가능",'BOP 수주 시나리오'!$J$40:$J$63,V$19) -> 0 | W26: =W27+SUMIFS('BOP 수주 시나리오'!$G$40:$G$63,'BOP 수주 시나리오'!$B$40:$B$63,"가능",'BOP 수주 시나리오'!$J$40:$J$63,W$19) -> 308898.86 | X26: =X27+SUMIFS('BOP 수주 시나리오'!$G$40:$G$63,'BOP 수주 시나리오'!$B$40:$B$63,"가능",'BOP 수주 시나리오'!$J$40:$J$63,X$19) -> 219161.76 | Z26: 보조기기 공급 품목 추정 논리
B27: Bear | C27: ='BOP 수주 시나리오'!Q66 -> 0 | D27: ='BOP 수주 시나리오'!R66 -> 0 | E27: ='BOP 수주 시나리오'!S66 -> 0 | F27: ='BOP 수주 시나리오'!T66 -> 0 | G27: ='BOP 수주 시나리오'!U66 -> 0 | H27: ='BOP 수주 시나리오'!V66 -> 0 | I27: ='BOP 수주 시나리오'!W66 -> 0 | J27: ='BOP 수주 시나리오'!X66 -> 0 | ... R27: ='BOP 수주 시나리오'!AF66 -> 16071.1 | T27: Bear | U27: =U28+SUMIFS('BOP 수주 시나리오'!$G$40:$G$63,'BOP 수주 시나리오'!$B$40:$B$63,"확실",'BOP 수주 시나리오'!$J$40:$J$63,U$19) -> 0 | V27: =V28+SUMIFS('BOP 수주 시나리오'!$G$40:$G$63,'BOP 수주 시나리오'!$B$40:$B$63,"확실",'BOP 수주 시나리오'!$J$40:$J$63,V$19) -> 0 | W27: =W28+SUMIFS('BOP 수주 시나리오'!$G$40:$G$63,'BOP 수주 시나리오'!$B$40:$B$63,"확실",'BOP 수주 시나리오'!$J$40:$J$63,W$19) -> 223144.29 | X27: =X28+SUMIFS('BOP 수주 시나리오'!$G$40:$G$63,'BOP 수주 시나리오'!$B$40:$B$63,"확실",'BOP 수주 시나리오'!$J$40:$J$63,X$19) -> 32394.625
B28: 북미 | T28: 북미 | Z28: 1. 국내 및 해외 한수원향 수주는 BOP 패키징으로 수주가 진행되어, 주요 품목인 SSLW, CLP, CCP, Condenser, FH&D 모두 수주되는 것으로 가정하였다.
B29: Bull | C29: ='BOP 수주 시나리오'!Q75 -> 0 | D29: ='BOP 수주 시나리오'!R75 -> 0 | E29: ='BOP 수주 시나리오'!S75 -> 0 | F29: ='BOP 수주 시나리오'!T75 -> 0 | G29: ='BOP 수주 시나리오'!U75 -> 0 | H29: ='BOP 수주 시나리오'!V75 -> 0 | I29: ='BOP 수주 시나리오'!W75 -> 0 | J29: ='BOP 수주 시나리오'!X75 -> 0 | ... R29: ='BOP 수주 시나리오'!AF75 -> 9256.9538 | T29: Bull | U29: =U30+SUMIFS('BOP 수주 시나리오'!$G$70:$G$73,'BOP 수주 시나리오'!$B$70:$B$73,"잠재",'BOP 수주 시나리오'!$J$70:$J$73,BOP!U$19) -> 0 | V29: =V30+SUMIFS('BOP 수주 시나리오'!$G$70:$G$73,'BOP 수주 시나리오'!$B$70:$B$73,"잠재",'BOP 수주 시나리오'!$J$70:$J$73,BOP!V$19) -> 157368.21 | W29: =W30+SUMIFS('BOP 수주 시나리오'!$G$70:$G$73,'BOP 수주 시나리오'!$B$70:$B$73,"잠재",'BOP 수주 시나리오'!$J$70:$J$73,BOP!W$19) -> 104912.14 | X29: =X30+SUMIFS('BOP 수주 시나리오'!$G$70:$G$73,'BOP 수주 시나리오'!$B$70:$B$73,"잠재",'BOP 수주 시나리오'!$J$70:$J$73,BOP!X$19) -> 104912.14
B30: Base | C30: ='BOP 수주 시나리오'!Q76 -> 0 | D30: ='BOP 수주 시나리오'!R76 -> 0 | E30: ='BOP 수주 시나리오'!S76 -> 0 | F30: ='BOP 수주 시나리오'!T76 -> 0 | G30: ='BOP 수주 시나리오'!U76 -> 0 | H30: ='BOP 수주 시나리오'!V76 -> 0 | I30: ='BOP 수주 시나리오'!W76 -> 0 | J30: ='BOP 수주 시나리오'!X76 -> 0 | ... R30: ='BOP 수주 시나리오'!AF76 -> 9256.9538 | T30: Base | U30: =U31+SUMIFS('BOP 수주 시나리오'!$G$70:$G$73,'BOP 수주 시나리오'!$B$70:$B$73,"가능",'BOP 수주 시나리오'!$J$70:$J$73,BOP!U$19) -> 0 | V30: =V31+SUMIFS('BOP 수주 시나리오'!$G$70:$G$73,'BOP 수주 시나리오'!$B$70:$B$73,"가능",'BOP 수주 시나리오'!$J$70:$J$73,BOP!V$19) -> 157368.21 | W30: =W31+SUMIFS('BOP 수주 시나리오'!$G$70:$G$73,'BOP 수주 시나리오'!$B$70:$B$73,"가능",'BOP 수주 시나리오'!$J$70:$J$73,BOP!W$19) -> 104912.14 | X30: =X31+SUMIFS('BOP 수주 시나리오'!$G$70:$G$73,'BOP 수주 시나리오'!$B$70:$B$73,"가능",'BOP 수주 시나리오'!$J$70:$J$73,BOP!X$19) -> 104912.14 | Z30: 2. 해외 웨스팅하우스 향 수주는 CLP 및 CPP, Condenser의 수주만 가정한다.
B31: Bear | C31: ='BOP 수주 시나리오'!Q77 -> 0 | D31: ='BOP 수주 시나리오'!R77 -> 0 | E31: ='BOP 수주 시나리오'!S77 -> 0 | F31: ='BOP 수주 시나리오'!T77 -> 0 | G31: ='BOP 수주 시나리오'!U77 -> 0 | H31: ='BOP 수주 시나리오'!V77 -> 0 | I31: ='BOP 수주 시나리오'!W77 -> 0 | J31: ='BOP 수주 시나리오'!X77 -> 0 | ... R31: ='BOP 수주 시나리오'!AF77 -> 0 | T31: Bear | U31: =U32+SUMIFS('BOP 수주 시나리오'!$G$70:$G$73,'BOP 수주 시나리오'!$B$70:$B$73,"확실",'BOP 수주 시나리오'!$J$70:$J$73,BOP!U$19) -> 0 | V31: =V32+SUMIFS('BOP 수주 시나리오'!$G$70:$G$73,'BOP 수주 시나리오'!$B$70:$B$73,"확실",'BOP 수주 시나리오'!$J$70:$J$73,BOP!V$19) -> 0 | W31: =W32+SUMIFS('BOP 수주 시나리오'!$G$70:$G$73,'BOP 수주 시나리오'!$B$70:$B$73,"확실",'BOP 수주 시나리오'!$J$70:$J$73,BOP!W$19) -> 0 | X31: =X32+SUMIFS('BOP 수주 시나리오'!$G$70:$G$73,'BOP 수주 시나리오'!$B$70:$B$73,"확실",'BOP 수주 시나리오'!$J$70:$J$73,BOP!X$19) -> 0 | Z31: 웨스팅하우스는 "Buy where we build"라는 슬로건을 내세워 현지중심 공급망 확보에 주력한다. 따라서 주요설비 외 품목들은 현지기업을 통해 조달할 가능성이 높다.
B32: 중동 | T32: 중동 | Z32: 다만 CLP, CPP, Condenser 등은 원전의 안전과 관련된 고도의 기술력을 요구하며 과거 납품 레퍼런스가 있는 제품이기에 수주 가능성이 높다고 판단한다.
B33: Bull | C33: ='BOP 수주 시나리오'!Q85 -> 0 | D33: ='BOP 수주 시나리오'!R85 -> 0 | E33: ='BOP 수주 시나리오'!S85 -> 0 | F33: ='BOP 수주 시나리오'!T85 -> 0 | G33: ='BOP 수주 시나리오'!U85 -> 0 | H33: ='BOP 수주 시나리오'!V85 -> 0 | I33: ='BOP 수주 시나리오'!W85 -> 0 | J33: ='BOP 수주 시나리오'!X85 -> 0 | ... R33: ='BOP 수주 시나리오'!AF85 -> 18791.847 | T33: Bull | U33: =U34+SUMIFS('BOP 수주 시나리오'!$G$81:$G$83,'BOP 수주 시나리오'!$B$81:$B$83,"잠재",'BOP 수주 시나리오'!$J$81:$J$83,BOP!U$19) -> 0 | V33: =V34+SUMIFS('BOP 수주 시나리오'!$G$81:$G$83,'BOP 수주 시나리오'!$B$81:$B$83,"잠재",'BOP 수주 시나리오'!$J$81:$J$83,BOP!V$19) -> 319461.39 | W33: =W34+SUMIFS('BOP 수주 시나리오'!$G$81:$G$83,'BOP 수주 시나리오'!$B$81:$B$83,"잠재",'BOP 수주 시나리오'!$J$81:$J$83,BOP!W$19) -> 0 | X33: =X34+SUMIFS('BOP 수주 시나리오'!$G$81:$G$83,'BOP 수주 시나리오'!$B$81:$B$83,"잠재",'BOP 수주 시나리오'!$J$81:$J$83,BOP!X$19) -> 124234.99
B34: Base | C34: ='BOP 수주 시나리오'!Q86 -> 0 | D34: ='BOP 수주 시나리오'!R86 -> 0 | E34: ='BOP 수주 시나리오'!S86 -> 0 | F34: ='BOP 수주 시나리오'!T86 -> 0 | G34: ='BOP 수주 시나리오'!U86 -> 0 | H34: ='BOP 수주 시나리오'!V86 -> 0 | I34: ='BOP 수주 시나리오'!W86 -> 0 | J34: ='BOP 수주 시나리오'!X86 -> 0 | ... R34: ='BOP 수주 시나리오'!AF86 -> 0 | T34: Base | U34: =U35+SUMIFS('BOP 수주 시나리오'!$G$81:$G$83,'BOP 수주 시나리오'!$B$81:$B$83,"가능",'BOP 수주 시나리오'!$J$81:$J$83,BOP!U$19) -> 0 | V34: =V35+SUMIFS('BOP 수주 시나리오'!$G$81:$G$83,'BOP 수주 시나리오'!$B$81:$B$83,"가능",'BOP 수주 시나리오'!$J$81:$J$83,BOP!V$19) -> 0 | W34: =W35+SUMIFS('BOP 수주 시나리오'!$G$81:$G$83,'BOP 수주 시나리오'!$B$81:$B$83,"가능",'BOP 수주 시나리오'!$J$81:$J$83,BOP!W$19) -> 0 | X34: =X35+SUMIFS('BOP 수주 시나리오'!$G$81:$G$83,'BOP 수주 시나리오'!$B$81:$B$83,"가능",'BOP 수주 시나리오'!$J$81:$J$83,BOP!X$19) -> 0
B35: Bear | C35: ='BOP 수주 시나리오'!Q87 -> 0 | D35: ='BOP 수주 시나리오'!R87 -> 0 | E35: ='BOP 수주 시나리오'!S87 -> 0 | F35: ='BOP 수주 시나리오'!T87 -> 0 | G35: ='BOP 수주 시나리오'!U87 -> 0 | H35: ='BOP 수주 시나리오'!V87 -> 0 | I35: ='BOP 수주 시나리오'!W87 -> 0 | J35: ='BOP 수주 시나리오'!X87 -> 0 | ... R35: ='BOP 수주 시나리오'!AF87 -> 0 | T35: Bear | U35: =U36+SUMIFS('BOP 수주 시나리오'!$G$81:$G$83,'BOP 수주 시나리오'!$B$81:$B$83,"확실",'BOP 수주 시나리오'!$J$81:$J$83,BOP!U$19) -> 0 | V35: =V36+SUMIFS('BOP 수주 시나리오'!$G$81:$G$83,'BOP 수주 시나리오'!$B$81:$B$83,"확실",'BOP 수주 시나리오'!$J$81:$J$83,BOP!V$19) -> 0 | W35: =W36+SUMIFS('BOP 수주 시나리오'!$G$81:$G$83,'BOP 수주 시나리오'!$B$81:$B$83,"확실",'BOP 수주 시나리오'!$J$81:$J$83,BOP!W$19) -> 0 | X35: =X36+SUMIFS('BOP 수주 시나리오'!$G$81:$G$83,'BOP 수주 시나리오'!$B$81:$B$83,"확실",'BOP 수주 시나리오'!$J$81:$J$83,BOP!X$19) -> 0
C36: =C9=SUM(C11:C12) -> TRUE | D36: =D9=SUM(D11:D12) -> TRUE | E36: =E9=SUM(E11:E12) -> TRUE | F36: =F9=SUM(F11:F12) -> TRUE | G36: =G9=SUM(G11:G12) -> TRUE | H36: =H9=SUM(H11:H12) -> TRUE | I36: =I9=SUM(I11:I12) -> TRUE | J36: =J9=SUM(J11:J12) -> TRUE | ... R36: =R9=SUM(R11:R12) -> TRUE
B51: Bull
B52: (단위: 백만 원) | C52: 1Q25A | D52: 2Q25 | E52: 3Q25 | F52: 4Q25 | G52: 1Q26 | H52: 2Q26 | I52: 3Q26 | J52: 4Q26 | K52: 1Q27 | L52: 2Q27 | M52: 3Q27 | N52: 4Q27 | O52: 1Q28 | P52: 2Q28 | Q52: 3Q28 | R52: 4Q28
B53: BOP | C53: 98656 | D53: 11063.916 | E53: 11063.916 | F53: 11063.916 | G53: 11063.916 | H53: 11063.916 | I53: 11063.916 | J53: 11063.916 | K53: 19705.093 | L53: 22123.891 | M53: 32517.483 | N53: 30098.684 | O53: 30098.684 | P53: 69058.344 | Q53: 84706.66 | R53: 84706.66
B54: YoY % | D54: -0.88785359 | E54: 0 | F54: 0 | G54: 0 | H54: 0 | I54: 0 | J54: 0 | K54: 0.78102331 | L54: 0.12274992 | M54: 0.46979039 | N54: -0.074384559 | O54: 0 | P54: 1.2943974 | Q54: 0.22659558 | R54: 0
B56: Base
B57: (단위: 백만 원) | C57: 1Q25A | D57: 2Q25 | E57: 3Q25 | F57: 4Q25 | G57: 1Q26 | H57: 2Q26 | I57: 3Q26 | J57: 4Q26 | K57: 1Q27 | L57: 2Q27 | M57: 3Q27 | N57: 4Q27 | O57: 1Q28 | P57: 2Q28 | Q57: 3Q28 | R57: 4Q28
B58: BOP | C58: 98656 | D58: 11063.916 | E58: 11063.916 | F58: 11063.916 | G58: 11063.916 | H58: 11063.916 | I58: 11063.916 | J58: 11063.916 | K58: 19705.093 | L58: 22123.891 | M58: 25209.543 | N58: 22790.744 | O58: 22790.744 | P58: 38861.844 | Q58: 45033.147 | R58: 45033.147
B59: YoY % | D59: -0.88785359 | E59: 0 | F59: 0 | G59: 0 | H59: 0 | I59: 0 | J59: 0 | K59: 0.78102331 | L59: 0.12274992 | M59: 0.13947145 | N59: -0.09594774 | O59: 0 | P59: 0.70515909 | Q59: 0.15880107 | R59: 0
B61: Bear
B62: (단위: 백만 원) | C62: 1Q25A | D62: 2Q25 | E62: 3Q25 | F62: 4Q25 | G62: 1Q26 | H62: 2Q26 | I62: 3Q26 | J62: 4Q26 | K62: 1Q27 | L62: 2Q27 | M62: 3Q27 | N62: 4Q27 | O62: 1Q28 | P62: 2Q28 | Q62: 3Q28 | R62: 4Q28
B63: BOP | C63: 98656 | D63: 11063.916 | E63: 11063.916 | F63: 11063.916 | G63: 11063.916 | H63: 11063.916 | I63: 11063.916 | J63: 11063.916 | K63: 19705.093 | L63: 22123.891 | M63: 22123.891 | N63: 19705.093 | O63: 19705.093 | P63: 29604.891 | Q63: 35776.193 | R63: 35776.193
B64: YoY % | D64: -0.88785359 | E64: 0 | F64: 0 | G64: 0 | H64: 0 | I64: 0 | J64: 0 | K64: 0.78102331 | L64: 0.12274992 | M64: 0 | N64: -0.10932971 | O64: 0 | P64: 0.50239793 | Q64: 0.20845551 | R64: 0

Sheet 비용 세부항목 추정
B1: Estimation
B2: 매출원가 및 비용 세부항목 추정
B5: 1. 원재료 및 상품의 사용 | K5: 추정 논리
B6: (단위: 백만 원) | C6: 2021 | D6: 2022 | E6: 2023 | F6: 2024 | G6: 2025 | H6: 2026 | I6: 2027 | J6: 2028
B7: 원재료 사용액 | C7: 118149.58 | D7: 107443.31 | E7: 92510.02 | F7: 106199.68 | G7: =G8*G9 -> 228941.66 | H7: =H8*H9 -> 279351.39 | I7: =I8*I9 -> 301723.54 | J7: =J8*J9 -> 332225.16 | K7: 주요 원재료인 철강 가격은 중국 수요 둔화 및 공급과잉으로 하향압력 예상, 따라서 보수적 추정을 위해 현재 가격 유지
B8: 매출액 | C8: 234883.72 | D8: 330197.11 | E8: 367399.21 | F8: 404741.04 | G8: ='Expected IS'!H7 -> 818060.13 | H8: ='Expected IS'!I7 -> 1055423.5 | I8: ='Expected IS'!J7 -> 1121745.8 | J8: ='Expected IS'!K7 -> 1225142.9 | K8: 동사의 구매력 강화로 원재료비 감소 추세가 확인되나, 보수적 추정을 위해 매출 대비 원재료 사용액 비중의 2개년 평균값을 적용
B9: 원재료 및 상품의 사용/매출액 | C9: =C7/C8 -> 0.50301307 | D9: =D7/D8 -> 0.32539144 | E9: =E7/E8 -> 0.251797 | F9: =F7/F8 -> 0.26238919 | G9: =AVERAGE(D9:F9) -> 0.27985921 | H9: =AVERAGE(E9:G9) -> 0.2646818 | I9: =AVERAGE(F9:H9) -> 0.26897674 | J9: =AVERAGE(G9:I9) -> 0.27117258
B13: 주요 원재료 가격 변동 추이 및 비율
B14: 품 목 | E14: 2021 | F14: 2022 | G14: 2023 | H14: 2024
B15: TUBE | C15: C/S | D15: 국 내 | E15: 1800 | F15: 1900 | G15: 2800 | H15: 2500
C16: SUS | D16: 국 내 | E16: 9000 | F16: 10000 | G16: 12000 | H16: 11000
C17: C/S | D17: 해 외 | E17: 2.3 | F17: 2.4 | G17: 1.7 | H17: 1.3
C18: ALLOY | D18: 해 외 | E18: 5.6 | F18: 5.8 | G18: 3.3 | H18: 3
C19: SUS | D19: 해 외 | E19: 13.5 | F19: 14 | G19: 12.5 | H19: 12.1
C20: Ti(관세포함) | D20: 해 외 | E20: 25 | F20: 24 | G20: 24 | H20: 24
B21: PIPE | C21: C/S | D21: 국 내 | E21: 1700 | F21: 1800 | G21: 2300 | H21: 2100
C22: SUS(SML‘S) | D22: 국 내 | E22: 10000 | F22: 11000 | G22: 17000 | H22: 12500
C23: SUS (ERW) | D23: 국 내 | E23: 5500 | F23: 5800 | G23: 7500 | H23: 7000
B24: PLATE | C24: C/S | D24: 국 내 | E24: 1400 | F24: 1450 | G24: 1200 | H24: 1100
C25: SUS | D25: 국 내 | E25: 4500 | F25: 5000 | G25: 4000 | H25: 3700
B26: 품 목 | C26: 구체적용도 | E26: 2021 | F26: 2022 | G26: 2023 | H26: 2024 | I26: 비율
B27: Tube | C27: 제품 제작에 필요한 원재료 | E27: 23658 | F27: 44093 | G27: 28685 | H27: 44240 | I27: 15.5
B28: Plate | E28: 14529 | F28: 26582 | G28: 20896 | H28: 30388 | I28: 10.6
B29: Pipe | E29: 10550 | F29: 9420 | G29: 5366 | H29: 13429 | I29: 4.7
B30: Forging | E30: 1060 | F30: 930 | G30: 3041 | H30: 3162 | I30: 1.1
B31: 기타 | E31: 67797 | F31: 25180 | G31: 18450 | H31: 7708 | I31: 2.7
B32: 가공·제작 | C32: 가공 및 제작 | E32: 72189 | F32: 127490 | G32: 173458 | H32: 187057 | I32: 65.4
B33: & 설치
E34: 189783 | F34: 233695 | G34: 249896 | H34: 285984
B36: 2. 외주가공비 | K36: 추정 논리
B37: (단위: 백만 원) | C37: 2021 | D37: 2022 | E37: 2023 | F37: 2024 | G37: 2025 | H37: 2026 | I37: 2027 | J37: 2028 | K37: 동사 제품의 생산은 매출이 늘어날 때 외주인력을 동원해 매출증감에 대처함. 따라서 외주가공비는 매출액 변화와 함께 증감. 특히 캐파증설 없이 외주가공을 통해 생산 확대한다는 점을 고려해 매출액 대비 외주가공비 비중이 확대될 것으로 가정
B38: 외주가공비 | C38: 68726.184 | D38: 124425.01 | E38: 162700.68 | F38: 169062.01 | G38: =G39*G40 -> 387781.03 | H38: =H39*H40 -> 504460.04 | I38: =I39*I40 -> 540621.33 | J38: =J39*J40 -> 600320 | K38: 또한 2028년 매출이 2025년 대비 약 2배 증가하지만, ①대량발주를 통한 단가 협상력 강화, ②고정비 분산효과, ③공정 표준화를 통한 효율성 개선 등으로 외주가공비 비중은 47%→50%로 제한적 증가에 그칠 것으로 예상
B39: 매출액 | C39: 234883.72 | D39: 330197.11 | E39: 367399.21 | F39: 404741.04 | G39: =G8 -> 818060.13 | H39: =H8 -> 1055423.5 | I39: =I8 -> 1121745.8 | J39: =J8 -> 1225142.9 | K39: 따라서 매출 대비 외주가공비 비중 최근 2개년 평균값에 매출 성장이 2배였던 시기의 비중 성장률을 적용
B40: 외주가공비/매출액 | C40: =C38/C39 -> 0.29259663 | D40: =D38/D39 -> 0.37682042 | E40: =E38/E39 -> 0.44284438 | F40: =F38/F39 -> 0.41770414 | G40: =G41 -> 0.47402509 | H40: =G40*(1+RATE(4,0,-G40,J40)) -> 0.47796932 | I40: =H40*(1+RATE(4,0,-G40,J40)) -> 0.48194636 | J40: 0.49 | K40: 상관계수 | L40: =CORREL(C38:F38,C39:F39) -> 0.98635904
F41: =RATE(2,0,-C40,D40) -> 0.13483456 | G41: =F40*(1+$F$41) -> 0.47402509
B43: 3. 인건비 추정 | K43: 추정 논리
B44: (단위: 백만 원) | C44: 2021 | D44: 2022 | E44: 2023 | F44: 2024 | G44: 2025 | H44: 2026 | I44: 2027 | J44: 2028
B45: 인건비 | C45: 31065.084 | D45: 33357.715 | E45: 37304.193 | F45: 43458.932 | G45: =G46*G48 -> 51164.548 | H45: =H46*H48 -> 58910.008 | I45: =I46*I48 -> 67828.001 | J45: =J46*J48 -> 78096.03
B46: 종업원수 | C46: 397 | D46: 423 | E46: 454 | F46: 558 | G46: =F46*1.05 -> 585.9 | H46: =G46*1.05 -> 615.195 | I46: =H46*1.05 -> 645.95475 | J46: =I46*1.05 -> 678.25249
B47: 전년대비 증가인원(명) | C47: 0 | D47: =D46-C46 -> 26 | E47: =E46-D46 -> 31 | F47: =F46-E46 -> 104 | G47: =G46-F46 -> 27.9 | H47: =H46-G46 -> 29.295 | I47: =I46-H46 -> 30.75975 | J47: =J46-I46 -> 32.297738
B48: 인당급여(백만 원/ 명) | C48: =C45/C46 -> 78.249582 | D48: =D45/D46 -> 78.859846 | E48: =E45/E46 -> 82.167826 | F48: =F45/F46 -> 77.883391 | G48: =K48*(1+$L$48) -> 87.326418 | H48: =G48*(1+$L$48) -> 95.758268 | I48: =H48*(1+$L$48) -> 105.00426 | J48: =I48*(1+$L$48) -> 115.14301 | K48: =AVERAGE(D48:F48) -> 79.637021 | L48: =AVERAGE(G54:G55) -> 0.096555553
B49: 매출원가 인건비 | C49: 18100.127 | D49: 19458.435 | E49: 23214.915 | F49: 26366.582 | G49: =G45*G50 -> 30909.208 | H49: =H45*H50 -> 35346.005 | I49: =I45*I50 -> 40696.801 | J49: =J45*J50 -> 46857.618 | K49: 대규모 충원 계획이 없고, 부족한 인력은 외주로 보충하기에 종업원 수는 현재의 증가세인 5%를 유지할 것으로 추정
B50: %of 인건비 | C50: =C49/C45 -> 0.5826518 | D50: =D49/D45 -> 0.58332638 | E50: =E49/E45 -> 0.62231382 | F50: =F49/F45 -> 0.6067011 | G50: =AVERAGE(D50:F50) -> 0.60411377 | H50: 0.6 | I50: 0.6 | J50: 0.6 | K50: 급여 수준은 3개년 평균 임금에 평균 임금상승률을 적용해 산출
B51: 판관비 인건비 | C51: =C45-C49 -> 12964.957 | D51: =D45-D49 -> 13899.28 | E51: =E45-E49 -> 14089.278 | F51: =F45-F49 -> 17092.35 | G51: =G45*G52 -> 20255.34 | H51: =H45*H52 -> 23564.003 | I51: =I45*I52 -> 27131.2 | J51: =J45*J52 -> 31238.412
B52: %of 인건비 | C52: =C51/C45 -> 0.4173482 | D52: =D51/D45 -> 0.41667362 | E52: =E51/E45 -> 0.37768618 | F52: =F51/F45 -> 0.3932989 | G52: =AVERAGE(D52:F52) -> 0.39588623 | H52: 0.4 | I52: 0.4 | J52: 0.4
B53: 직원별 평균 임금
B54: 남 | D54: 61 | E54: 66 | F54: 76 | G54: =RATE(3,0,-D54,F54) -> 0.076038769
B55: 녀 | D55: 33 | E55: 37 | F55: 46 | G55: =RATE(3,0,-D55,F55) -> 0.11707234
J58: 1000
B59: 4. 기타 | K59: 추정 논리
B60: (단위: 백만 원) | C60: 2021 | D60: 2022 | E60: 2023 | F60: 2024 | G60: 2025 | H60: 2026 | I60: 2027 | J60: 2028
B61: 기타 매출원가 | C61: =SUM(C62:C64,C66:C67) -> 36273.627 | D61: =SUM(D62:D64,D66:D67) -> 43938.712 | E61: =SUM(E62:E64,E66:E67) -> 45532.011 | F61: =SUM(F62:F64,F66:F67) -> 43994.757 | G61: =SUM(G62:G64,G66:G67) -> 67377.703 | H61: =SUM(H62:H64,H66:H67) -> 76698.268 | I61: =SUM(I62:I64,I66:I67) -> 79280.105 | J61: =SUM(J62:J64,J66:J67) -> 83485.633
B62: 감가상각비 및 무형자산상각비 | C62: 9744.074 | D62: 9379.584 | E62: 8879.341 | F62: 4144.782 | G62: =AVERAGE(C62:E62) -> 9334.333 | H62: =AVERAGE(D62:E62,G62) -> 9197.7527 | I62: =AVERAGE(E62,G62:H62) -> 9137.1422 | J62: =AVERAGE(G62:I62) -> 9223.076 | K62: 감가상각비의 경우 일시적 변동이 있던 24년을 제외하고 매년 일정하기에 3개년 이동평균값으로 적용. 동사 제품 제조의 핵심은 설계인력이며, 실제로 유형자산 중 기계장치의 비중은 10%에 불과하고 대부분 토지 및 건물임을 고려해 현재의 비중이 유지될 것으로 판단함.
B63: 운반비 | C63: 3342.034 | D63: 12326.903 | E63: 8820.988 | F63: 3349.84 | G63: =G8*$X$67 -> 13205.853 | H63: =H8*$X$67 -> 17037.583 | I63: =I8*$X$67 -> 18108.217 | J63: =J8*$X$67 -> 19777.344 | K63: 운반비는 유가와 연동되는 경향을 보이며, 유가 전망치는 28년까지 하향 안정세를 이룰 것으로 예상. 따라서 현재의 가격대와 % of sales을 유지할 것으로 가정 | T63: 2021 | U63: 2022 | V63: 2023 | W63: 2024 | AA63: 기관 | AB63: 2025년 | AC63: 2026년 | AD63: 2027년 | AE63: 2028년 | AF63: 주요 근거
B64: 지급수수료 | C64: 4363.501 | D64: 7587.156 | E64: 7757.874 | F64: 10930.226 | G64: =G39*G65 -> 19387.695 | H64: =H39*H65 -> 25013.111 | I64: =I39*I65 -> 26584.924 | J64: =J39*J65 -> 29035.392 | K64: 지급수수료는 매출이 커지며 외주인력에 지급하는 비용도 증가하기에 % of sales 3개년 이동평균 적용 | S64: 유가(Brent/USD) | T64: 71 | U64: 100 | V64: 82 | W64: 81 | X64: 상관계수 | AA64: BMI (Fitch Solutions) | AB64: $82/bbl | AC64: $81/bbl | AD64: $81/bbl | AE64: $81/bbl | AF64: 비OPEC+ 국가들의 꾸준한 생산량 증가와 점진적인 수요 둔화의 균형.
B65: 지급수수료/매출액 | C65: =C64/C$39 -> 0.018577282 | D65: =D64/D39 -> 0.022977657 | E65: =E64/E39 -> 0.021115652 | F65: =F64/F39 -> 0.02700548 | G65: =AVERAGE(D65:F65) -> 0.023699597 | H65: =$G$65 -> 0.023699597 | I65: =$G$65 -> 0.023699597 | J65: =$G$65 -> 0.023699597 | S65: 운반비 | T65: 3342.034 | U65: 12326.903 | V65: 8820.988 | W65: 3349.84 | X65: =CORREL(T64:W64,T65:W65) -> 0.87651036 | AA65: 미국 에너지정보청 (EIA) | AB65: $74/bbl | AC65: $66/bbl | AD65: - | AE65: $73/bbl | AF65: 비OPEC+의 생산 증가로 인한 재고 누적 및 장기적인 수요 정체.
B66: 지급임차료 | C66: 183.549 | D66: 71.24 | E66: 154.613 | F66: 293.057 | G66: =AVERAGE(D66:F66) -> 172.97 | H66: =G66 -> 172.97 | I66: =H66 -> 172.97 | J66: =I66 -> 172.97 | K66: 경향성 없음. 3개년 평균Flat | S66: 매출액 | T66: 234883.72 | U66: 330197.11 | V66: 367399.21 | W66: 404741.04 | AA66: LongForecast | AB66: - | AC66: - | AD66: - | AE66: $40-60/bbl | AF66: 경기 침체 가능성 또는 에너지 부문의 기술적 변화로 인한 수요 약세.
B67: 기타 | C67: 18640.469 | D67: 14573.829 | E67: 19919.195 | F67: 25276.852 | G67: =F67 -> 25276.852 | H67: =G67 -> 25276.852 | I67: =H67 -> 25276.852 | J67: =I67 -> 25276.852 | K67: 경향성 없음. 3개년 평균Flat | S67: 운반비/매출액 | T67: =T65/T66 -> 0.014228462 | U67: =U65/U66 -> 0.037331953 | V67: =V65/V66 -> 0.024009273 | W67: =W65/W66 -> 0.008276502 | X67: =AVERAGE(V67:W67) -> 0.016142888 | AA67: CoinPriceForecast | AB67: - | AC67: - | AD67: - | AE67: $46-50/bbl | AF67: 장기적인 수요 약세와 공급 과잉 상태 지속.
AA68: Bloomberg Consensus | AB68: $73/bbl | AC68: $71/bbl | AD68: $75/bbl | AE68: $74/bbl | AF68: 다양한 기관들의 예측을 종합한 평균치.
J70: 1000
B71: 판매관리비 | K71: 추정 논리
B72: (단위: 백만 원) | C72: 2021 | D72: 2022 | E72: 2023 | F72: 2024 | G72: 2025 | H72: 2026 | I72: 2027 | J72: 2028
B73: 판매비와 관리비 | C73: 24245.078 | D73: 26823.584 | E73: 28354.888 | F73: 37190.759 | G73: =SUM(G74:G79) -> 39220.892 | H73: =SUM(H74:H79) -> 47347.02 | I73: =SUM(I74:I79) -> 52260.278 | J73: =SUM(J74:J79) -> 58466.009
B74: 인건비 | C74: 13000.707 | D74: 13948.49 | E74: 14157.436 | F74: 17165.349 | G74: =G51 -> 20255.34 | H74: =H51 -> 23564.003 | I74: =I51 -> 27131.2 | J74: =J51 -> 31238.412 | K74: 인건비는 매출원가의 인건비와 동일한 방식으로 추정
B75: 유무형자산상각비 | C75: 1041.959 | D75: 1176.78 | E75: 1715.522 | F75: 1913.114 | G75: =F75 -> 1913.114 | H75: =G75 -> 1913.114 | I75: =H75 -> 1913.114 | J75: =I75 -> 1913.114 | K75: 유무형자산상각비는 추가 설비 증대 계획 없음을 고려해 3개년 평균 적용
B76: 지급수수료 | C76: 5181.509 | D76: 5547.965 | E76: 6020.121 | F76: 8214.519 | G76: =G39*G77 -> 16603.136 | H76: =H39*H77 -> 21420.601 | I76: =I39*I77 -> 22766.662 | J76: =J39*J77 -> 24865.181
B77: 지급수수료/매출액 | C77: =C76/C$39 -> 0.02205989 | D77: =D76/D$39 -> 0.016801979 | E77: =E76/E$39 -> 0.016385776 | F77: =F76/F$39 -> 0.02029574 | G77: =F77 -> 0.02029574 | H77: =G77 -> 0.02029574 | I77: =H77 -> 0.02029574 | J77: =I77 -> 0.02029574 | K77: 경향성 없음. 3개년 % of sales 평균Flat
B78: 지급임차료 | C78: 255.6 | D78: 383.62 | E78: 392.872 | F78: 510.519 | G78: =AVERAGE(D78:F78) -> 429.00367 | H78: =G78 -> 429.00367 | I78: =H78 -> 429.00367 | J78: =I78 -> 429.00367 | K78: 경향성 없음. 3개년 평균Flat
B79: 기타 | C79: 21.175 | D79: 31.102 | E79: 16.399 | F79: 13.332 | G79: =AVERAGE(D79:F79) -> 20.277667 | H79: =G79 -> 20.277667 | I79: =H79 -> 20.277667 | J79: =I79 -> 20.277667 | K79: 경향성 없음. 3개년 평균Flat
B83: 영업외손익 | K83: 추정 논리
B84: (단위: 백만 원) | C84: 2021 | D84: 2022 | E84: 2023 | F84: 2024 | G84: 2025 | H84: 2026 | I84: 2027 | J84: 2028
B85: 금융수익 | C85: 7196.576 | D85: 8323.576 | E85: 10770.512 | F85: 18569.587 | G85: =SUM(G86:G92) -> 66557.241 | H85: =SUM(H86:H92) -> 66557.949 | I85: =SUM(I86:I92) -> 66567.372 | J85: =SUM(J86:J92) -> 66560.854
B86: 이자수익 | C86: 141.376 | D86: 281.418 | E86: 958.346 | F86: 1352.583 | G86: =AVERAGE(D86:F86) -> 864.11567 | H86: =G86 -> 864.11567 | I86: =H86 -> 864.11567 | J86: =I86 -> 864.11567 | K86: 금리 하락기인점을 반영하여 더 증가하지 않고 최근 3개년 평균값 flat
B87: 외환이익 | C87: 5857.794 | D87: 7309.414 | E87: 8337.759 | F87: 16104.774 | G87: =AVERAGE(C87:E87) -> 7168.3223 | H87: =G87 -> 7168.3223 | I87: =H87 -> 7168.3223 | J87: =I87 -> 7168.3223 | K87: 외환이익은 환율 하락을 반영해 최근 상승분을 제외한 3개년 평균값 flat
B88: 파생상품이익 | C88: 553.496 | D88: 2.7 | E88: 769.799 | F88: 350.375 | G88: =AVERAGE(D88:F88) -> 374.29133 | H88: =G88 -> 374.29133 | I88: =H88 -> 374.29133 | J88: =I88 -> 374.29133 | K88: 경향성 없음. 3개년 평균Flat
B89: 기타 | C89: =C85-SUM(C86:C88) -> 643.91 | D89: =D85-SUM(D86:D88) -> 730.044 | E89: =E85-SUM(E86:E88) -> 704.608 | F89: =F85-SUM(F86:F88) -> 761.855 | G89: =AVERAGE(D89:F89) -> 732.169 | H89: =AVERAGE(E89:G89) -> 732.87733 | I89: =AVERAGE(F89:H89) -> 742.30044 | J89: =AVERAGE(G89:I89) -> 735.78226 | K89: 경향성 없음. 3개년 평균Flat
B90: 금융원가 | C90: 13853.979 | D90: 37272.428 | E90: 22758.852 | F90: 44883.533 | G90: =SUM(G91:G94) -> 36955.902 | H90: =SUM(H91:H94) -> 36955.902 | I90: =SUM(I91:I94) -> 36955.902 | J90: =SUM(J91:J94) -> 36955.902
B91: 이자비용 | C91: 6922.606 | D91: 9204.768 | E91: 11546.804 | F91: 10416.514 | G91: =AVERAGE(D91:F91) -> 10389.362 | H91: =G91 -> 10389.362 | I91: =H91 -> 10389.362 | J91: =I91 -> 10389.362 | K91: 이자비용또한 금리 하락기이나 보수적 관점에서 현재 수준을 유지하고, 전환사채가 25년부터 사라짐을 감안해 최근 3개년 평균값을 flat
B92: 외환손실 | C92: 2956.485 | D92: 7109.659 | E92: 7083.603 | F92: 10073.078 | G92: =F92 -> 10073.078 | H92: =G92 -> 10073.078 | I92: =H92 -> 10073.078 | J92: =I92 -> 10073.078 | K92: 환율 하락으로 환손실 반영하여 최근 크게 발생한 값으로 flat
B93: 파생상품손실 | C93: 3914.981 | D93: 20942.7 | E93: 2631.475 | F93: 21948.104 | G93: =AVERAGE(D93:F93) -> 15174.093 | H93: =G93 -> 15174.093 | I93: =H93 -> 15174.093 | J93: =I93 -> 15174.093 | K93: 경향성 없음. 3개년 평균Flat
B94: 기타 | C94: =C90-SUM(C91:C93) -> 59.907 | D94: =D90-SUM(D91:D93) -> 15.301 | E94: =E90-SUM(E91:E93) -> 1496.97 | F94: =F90-SUM(F91:F93) -> 2445.837 | G94: =AVERAGE(D94:F94) -> 1319.3693 | H94: =G94 -> 1319.3693 | I94: =H94 -> 1319.3693 | J94: =I94 -> 1319.3693 | K94: 경향성 없음. 3개년 평균Flat
B95: 기타손익 | C95: 3506.399 | D95: 1286.204 | E95: 2118.717 | F95: 840.821 | G95: =F95 -> 840.821 | H95: =G95 -> 840.821 | I95: =H95 -> 840.821 | J95: =I95 -> 840.821 | K95: 경향성이 없어 flat
B96: 종속기업,공동지배기업및관계기업관련손익(*) | C96: -722.69736 | D96: -1220.522 | E96: -1392.16 | F96: -399.343 | G96: =F96 -> -399.343 | H96: =G96 -> -399.343 | I96: =H96 -> -399.343 | J96: =I96 -> -399.343 | K96: 종속기업관련손익은 종속기업 중 하나인 아레테자원환경의 지분율이 55%에서 100%로 변화했고, 수익환경이 개선된 추세를 반영해 최근 값으로 적용
B97: 법인세비용차감전계속사업이익 | C97: -34484.581 | D97: -20775.115 | E97: 3824.9159 | F97: -3945.2096
B98: 법인세비용 | C98: 102.52471 | D98: -1657.3597 | E98: -3638.8661 | F98: -23530.262 | G98: =G97*G99 -> 0 | H98: =H97*H99 -> 0 | I98: =I97*I99 -> 0 | J98: =J97*J99 -> 0 | K98: 적자로 인해 법인세 비용을 지불한 경우가 드물어 세무조정을 배제하고 회계이익을 과세소득으로 가정하여 과세표준을 바탕으로 법인세율을 적용
B99: 유효법인세율(%) | G99: 0.21 | H99: 0.21 | I99: 0.21 | J99: 0.21

Sheet 기존수주 매출
O1: =2000+RIGHT(O2,2) -> 2020 | P1: =2000+RIGHT(P2,2) -> 2021 | Q1: =2000+RIGHT(Q2,2) -> 2021 | R1: =2000+RIGHT(R2,2) -> 2021 | S1: =2000+RIGHT(S2,2) -> 2021 | T1: =2000+RIGHT(T2,2) -> 2022 | U1: =2000+RIGHT(U2,2) -> 2022 | V1: =2000+RIGHT(V2,2) -> 2022 | ... BC1: =2000+RIGHT(BC2,2) -> 2030
B2: 진행률 | C2: 계약명 | D2: 사업부 | E2: 지역 | F2: 계약금액(백만원) | G2: 계약시기 | H2: 수주연도 | I2: 공사기한 | J2: 선금10% | K2: 매출인식 | L2: 공사기한 | M2: 계약기간(Q) | O2: 4Q20 | P2: 1Q21 | Q2: 2Q21 | R2: 3Q21 | S2: 4Q21 | T2: 1Q22 | U2: 2Q22 | V2: 3Q22 | W2: 4Q22 | X2: 1Q23 | Y2: 2Q23 | Z2: 3Q23 | AA2: 4Q23 | AB2: 1Q24 | AC2: 2Q24 | AD2: 3Q24 | AE2: 4Q24 | AF2: 1Q25 | AG2: 2Q25 | AH2: 3Q25 | AI2: 4Q25 | AJ2: 1Q26 | AK2: 2Q26 | AL2: 3Q26 | AM2: 4Q26 | AN2: 1Q27 | AO2: 2Q27 | AP2: 3Q27 | AQ2: 4Q27 | AR2: 1Q28 | AS2: 2Q28 | AT2: 3Q28 | AU2: 4Q28 | AV2: 1Q29 | AW2: 2Q29 | AX2: 3Q29 | AY2: 4Q29 | AZ2: 1Q30 | BA2: 2Q30 | BB2: 3Q30 | BC2: 4Q30
B3: 22 | C3: HRSG
B4: 1 | C4: 삼성물산 | D4: HRSG | E4: 중동 | F4: 145773.3 | G4: 45864 | H4: 2025 | I4: 46631 | J4: 4Q25 | K4: 1Q26 | L4: 3Q27 | M4: 7 | O4: =IF(O$2=$K4,$F4*CHOOSE($B4,$O$33,$O$35,$O$37),0) -> 0 | P4: =IF(P$2=$K4,$F4*CHOOSE($B4,$O$33,$O$35,$O$37),0) -> 0 | Q4: =IF(Q$2=$K4,$F4*CHOOSE($B4,$O$33,$O$35,$O$37),0) -> 0 | R4: =IF(R$2=$K4,$F4*CHOOSE($B4,$O$33,$O$35,$O$37),0) -> 0 | S4: =IF(S$2=$K4,$F4*CHOOSE($B4,$O$33,$O$35,$O$37),0) -> 0 | T4: =IF(T$2=$K4,$F4*CHOOSE($B4,$O$33,$O$35,$O$37),0) -> 0 | U4: =IF(U$2=$K4,$F4*CHOOSE($B4,$O$33,$O$35,$O$37),0) -> 0 | V4: =IF(V$2=$K4,$F4*CHOOSE($B4,$O$33,$O$35,$O$37),0) -> 0 | ... AJ4: =IF(AJ$2=$K4,$F4*CHOOSE($B4,$O$33,$O$35,$O$37),0) -> 5539.3854 | AK4: =$F$4*P33 -> 23323.728 | AL4: =$F$4*Q33 -> 24781.461 | AM4: =$F$4*R33 -> 26239.194 | AN4: =$F$4*S33 -> 25656.101 | AO4: =$F$4*T33 -> 25656.101 | AP4: =$F$4*U33 -> 14577.33 | AQ4: =$F$4*V33 -> 0 | AR4: =$F$4*W33 -> 0 | ... BC4: =$F$4*AH33 -> 0 | BD4: =SUM(O4:BC4) -> 145773.3
B5: 1 | C5: JV of PSP, PCI, PC | D5: HRSG | E5: 중동 | F5: 163173.5 | G5: 45769 | H5: 2025 | I5: 46436 | J5: 3Q25 | K5: 4Q25 | L5: 1Q27 | M5: 6 | O5: =IF(O$2=$K5,$F5*CHOOSE($B5,$O$33,$O$35,$O$37),0) -> 0 | P5: =IF(P$2=$K5,$F5*CHOOSE($B5,$O$33,$O$35,$O$37),0) -> 0 | Q5: =IF(Q$2=$K5,$F5*CHOOSE($B5,$O$33,$O$35,$O$37),0) -> 0 | R5: =IF(R$2=$K5,$F5*CHOOSE($B5,$O$33,$O$35,$O$37),0) -> 0 | S5: =IF(S$2=$K5,$F5*CHOOSE($B5,$O$33,$O$35,$O$37),0) -> 0 | T5: =IF(T$2=$K5,$F5*CHOOSE($B5,$O$33,$O$35,$O$37),0) -> 0 | U5: =IF(U$2=$K5,$F5*CHOOSE($B5,$O$33,$O$35,$O$37),0) -> 0 | V5: =IF(V$2=$K5,$F5*CHOOSE($B5,$O$33,$O$35,$O$37),0) -> 0 | ... AI5: =IF(AI$2=$K5,$F5*CHOOSE($B5,$O$33,$O$35,$O$37),0) -> 6200.593 | AJ5: =$F$5*P33 -> 26107.76 | AK5: =$F$5*Q33 -> 27739.495 | AL5: =$F$5*R33 -> 29371.23 | AM5: =$F$5*S33 -> 28718.536 | AN5: =$F$5*T33 -> 28718.536 | AO5: =$F$5*U33 -> 16317.35 | AP5: =$F$5*V33 -> 0 | AQ5: =$F$5*W33 -> 0 | ... BC5: =$F$5*AI33 -> 0 | BD5: =SUM(O5:BC5) -> 163173.5
B6: 4 | C6: FuJi Electric | D6: HRSG | E6: 일본 | F6: 66187.838 | G6: 45747 | H6: 2025 | I6: 47618 | J6: 2Q25 | K6: 3Q25 | L6: 2Q30 | M6: 20 | O6: =IF(O$2=$K6,$F6*CHOOSE($B6,$O$33,$O$35,$O$37),0) -> 0 | P6: =IF(P$2=$K6,$F6*CHOOSE($B6,$O$33,$O$35,$O$37),0) -> 0 | Q6: =IF(Q$2=$K6,$F6*CHOOSE($B6,$O$33,$O$35,$O$37),0) -> 0 | R6: =IF(R$2=$K6,$F6*CHOOSE($B6,$O$33,$O$35,$O$37),0) -> 0 | S6: =IF(S$2=$K6,$F6*CHOOSE($B6,$O$33,$O$35,$O$37),0) -> 0 | T6: =IF(T$2=$K6,$F6*CHOOSE($B6,$O$33,$O$35,$O$37),0) -> 0 | U6: =IF(U$2=$K6,$F6*CHOOSE($B6,$O$33,$O$35,$O$37),0) -> 0 | V6: =IF(V$2=$K6,$F6*CHOOSE($B6,$O$33,$O$35,$O$37),0) -> 0 | ... AG6: =IF(AG$2=$K6,$F6*CHOOSE($B6,$O$33,$O$35,$O$37),0) -> 0 | AH6: =IF(AH$2=$K6,$F6*CHOOSE($B6,$O$33,$O$35,$O$37,$O$39),0) -> 1472.6794 | AI6: =$F$6*P39 -> 1472.6794 | AJ6: =$F$6*Q39 -> 1472.6794 | AK6: =$F$6*R39 -> 1472.6794 | AL6: =$F$6*S39 -> 3772.7068 | AM6: =$F$6*T39 -> 3772.7068 | AN6: =$F$6*U39 -> 3772.7068 | AO6: =$F$6*V39 -> 3772.7068 | AP6: =$F$6*W39 -> 4384.9443 | ... BC6: =$F$6*AJ39 -> 0 | BD6: =SUM(O6:BC6) -> 66187.838
B7: 1 | C7: 하얼빈일렉트릭(HEI) | D7: HRSG | E7: 중동 | F7: 148525.81 | G7: 45689 | H7: 2025 | I7: 46264 | J7: 2Q25 | K7: 3Q25 | L7: 3Q26 | M7: 5 | O7: =IF(O$2=$K7,$F7*CHOOSE($B7,$O$33,$O$35,$O$37),0) -> 0 | P7: =IF(P$2=$K7,$F7*CHOOSE($B7,$O$33,$O$35,$O$37),0) -> 0 | Q7: =IF(Q$2=$K7,$F7*CHOOSE($B7,$O$33,$O$35,$O$37),0) -> 0 | R7: =IF(R$2=$K7,$F7*CHOOSE($B7,$O$33,$O$35,$O$37),0) -> 0 | S7: =IF(S$2=$K7,$F7*CHOOSE($B7,$O$33,$O$35,$O$37),0) -> 0 | T7: =IF(T$2=$K7,$F7*CHOOSE($B7,$O$33,$O$35,$O$37),0) -> 0 | U7: =IF(U$2=$K7,$F7*CHOOSE($B7,$O$33,$O$35,$O$37),0) -> 0 | V7: =IF(V$2=$K7,$F7*CHOOSE($B7,$O$33,$O$35,$O$37),0) -> 0 | ... AH7: =IF(AH$2=$K7,$F7*CHOOSE($B7,$O$33,$O$35,$O$37),0) -> 5643.9808 | AI7: =$F$7*P33 -> 23764.13 | AJ7: =$F$7*Q33 -> 25249.388 | AK7: =$F$7*R33 -> 26734.646 | AL7: =$F$7*S33 -> 26140.543 | AM7: =$F$7*T33 -> 26140.543 | AN7: =$F$7*U33 -> 14852.581 | AO7: =$F$7*V33 -> 0 | AP7: =$F$7*W33 -> 0 | ... BC7: =$F$7*AJ33 -> 0 | BD7: =SUM(O7:BC7) -> 148525.81
B8: 1 | C8: 하얼빈일렉트릭(HEI)(2) | D8: HRSG | E8: 중동 | F8: 144393.48 | G8: 45689 | H8: 2025 | I8: 46264 | J8: 2Q25 | K8: 3Q25 | L8: 3Q26 | M8: 5 | O8: =IF(O$2=$K8,$F8*CHOOSE($B8,$O$33,$O$35,$O$37),0) -> 0 | P8: =IF(P$2=$K8,$F8*CHOOSE($B8,$O$33,$O$35,$O$37),0) -> 0 | Q8: =IF(Q$2=$K8,$F8*CHOOSE($B8,$O$33,$O$35,$O$37),0) -> 0 | R8: =IF(R$2=$K8,$F8*CHOOSE($B8,$O$33,$O$35,$O$37),0) -> 0 | S8: =IF(S$2=$K8,$F8*CHOOSE($B8,$O$33,$O$35,$O$37),0) -> 0 | T8: =IF(T$2=$K8,$F8*CHOOSE($B8,$O$33,$O$35,$O$37),0) -> 0 | U8: =IF(U$2=$K8,$F8*CHOOSE($B8,$O$33,$O$35,$O$37),0) -> 0 | V8: =IF(V$2=$K8,$F8*CHOOSE($B8,$O$33,$O$35,$O$37),0) -> 0 | ... AH8: =IF(AH$2=$K8,$F8*CHOOSE($B8,$O$33,$O$35,$O$37),0) -> 5486.9523 | AI8: =$F$8*P33 -> 23102.957 | AJ8: =$F$8*Q33 -> 24546.892 | AK8: =$F$8*R33 -> 25990.827 | AL8: =$F$8*S33 -> 25413.253 | AM8: =$F$8*T33 -> 25413.253 | AN8: =$F$8*U33 -> 14439.348 | AO8: =$F$8*V33 -> 0 | AP8: =$F$8*W33 -> 0 | ... BC8: =$F$8*AJ33 -> 0 | BD8: =SUM(O8:BC8) -> 144393.48
B9: 3 | C9: 한국남동발전 | D9: HRSG | E9: 국내 | F9: 136900 | G9: 45618 | H9: 2024 | I9: 46568 | J9: 1Q25 | K9: 2Q25 | L9: 2Q27 | M9: 9 | O9: =IF(O$2=$K9,$F9*CHOOSE($B9,$O$33,$O$35,$O$37),0) -> 0 | P9: =IF(P$2=$K9,$F9*CHOOSE($B9,$O$33,$O$35,$O$37),0) -> 0 | Q9: =IF(Q$2=$K9,$F9*CHOOSE($B9,$O$33,$O$35,$O$37),0) -> 0 | R9: =IF(R$2=$K9,$F9*CHOOSE($B9,$O$33,$O$35,$O$37),0) -> 0 | S9: =IF(S$2=$K9,$F9*CHOOSE($B9,$O$33,$O$35,$O$37),0) -> 0 | T9: =IF(T$2=$K9,$F9*CHOOSE($B9,$O$33,$O$35,$O$37),0) -> 0 | U9: =IF(U$2=$K9,$F9*CHOOSE($B9,$O$33,$O$35,$O$37),0) -> 0 | V9: =IF(V$2=$K9,$F9*CHOOSE($B9,$O$33,$O$35,$O$37),0) -> 0 | ... AG9: =IF(AG$2=$K9,$F9*CHOOSE($B9,$O$33,$O$35,$O$37),0) -> 6092.05 | AH9: =$F$9*P37 -> 6092.05 | AI9: =$F$9*Q37 -> 15606.6 | AJ9: =$F$9*R37 -> 15606.6 | AK9: =$F$9*S37 -> 18139.25 | AL9: =$F$9*T37 -> 18139.25 | AM9: =$F$9*U37 -> 10472.85 | AN9: =$F$9*V37 -> 10472.85 | AO9: =$F$9*W37 -> 7529.5 | ... BC9: =$F$9*AK37 -> 0 | BD9: =SUM(O9:BC9) -> 136900
B10: 1 | C10: Alghanim International General Trading & Construction | D10: HRSG | E10: 중동 | F10: 51972.886 | G10: 45590 | H10: 2024 | I10: 46102 | J10: 1Q25 | K10: 2Q25 | L10: 1Q26 | M10: 4 | O10: =IF(O$2=$K10,$F10*CHOOSE($B10,$O$33,$O$35,$O$37),0) -> 0 | P10: =IF(P$2=$K10,$F10*CHOOSE($B10,$O$33,$O$35,$O$37),0) -> 0 | Q10: =IF(Q$2=$K10,$F10*CHOOSE($B10,$O$33,$O$35,$O$37),0) -> 0 | R10: =IF(R$2=$K10,$F10*CHOOSE($B10,$O$33,$O$35,$O$37),0) -> 0 | S10: =IF(S$2=$K10,$F10*CHOOSE($B10,$O$33,$O$35,$O$37),0) -> 0 | T10: =IF(T$2=$K10,$F10*CHOOSE($B10,$O$33,$O$35,$O$37),0) -> 0 | U10: =IF(U$2=$K10,$F10*CHOOSE($B10,$O$33,$O$35,$O$37),0) -> 0 | V10: =IF(V$2=$K10,$F10*CHOOSE($B10,$O$33,$O$35,$O$37),0) -> 0 | ... AG10: =IF(AG$2=$K10,$F10*CHOOSE($B10,$O$33,$O$35,$O$37),0) -> 1974.9697 | AH10: =$F$10*P33 -> 8315.6618 | AI10: =$F$10*Q33 -> 8835.3907 | AJ10: =$F$10*R33 -> 9355.1196 | AK10: =$F$10*S33 -> 9147.228 | AL10: =$F$10*T33 -> 9147.228 | AM10: =$F$10*U33 -> 5197.2886 | AN10: =$F$10*V33 -> 0 | AO10: =$F$10*W33 -> 0 | ... BC10: =$F$10*AK33 -> 0 | BD10: =SUM(O10:BC10) -> 51972.886
B11: 2 | C11: 포스코 | D11: HRSG | E11: 국내 | F11: 21900 | G11: 45589 | H11: 2024 | I11: 46203 | J11: 1Q25 | K11: 2Q25 | L11: 2Q26 | M11: 5 | O11: =IF(O$2=$K11,$F11*CHOOSE($B11,$O$33,$O$35,$O$37),0) -> 0 | P11: =IF(P$2=$K11,$F11*CHOOSE($B11,$O$33,$O$35,$O$37),0) -> 0 | Q11: =IF(Q$2=$K11,$F11*CHOOSE($B11,$O$33,$O$35,$O$37),0) -> 0 | R11: =IF(R$2=$K11,$F11*CHOOSE($B11,$O$33,$O$35,$O$37),0) -> 0 | S11: =IF(S$2=$K11,$F11*CHOOSE($B11,$O$33,$O$35,$O$37),0) -> 0 | T11: =IF(T$2=$K11,$F11*CHOOSE($B11,$O$33,$O$35,$O$37),0) -> 0 | U11: =IF(U$2=$K11,$F11*CHOOSE($B11,$O$33,$O$35,$O$37),0) -> 0 | V11: =IF(V$2=$K11,$F11*CHOOSE($B11,$O$33,$O$35,$O$37),0) -> 0 | ... AG11: =IF(AG$2=$K11,$F11*CHOOSE($B11,$O$33,$O$35,$O$37),0) -> 1949.1 | AH11: =$F$11*P35 -> 4993.2 | AI11: =$F$11*Q35 -> 4171.95 | AJ11: =$F$11*R35 -> 3350.7 | AK11: =$F$11*S35 -> 2409 | AL11: =$F$11*T35 -> 3394.5 | AM11: =$F$11*U35 -> 1631.55 | AN11: =$F$11*V35 -> 0 | AO11: =$F$11*W35 -> 0 | ... BC11: =$F$11*AK35 -> 0 | BD11: =SUM(O11:BC11) -> 21900
B12: 1 | C12: 삼성C&T | D12: HRSG | E12: 중동 | F12: 25123.61 | G12: 45511 | H12: 2024 | I12: 45978 | J12: 4Q24 | K12: 1Q25 | L12: 4Q25 | M12: 4 | O12: =IF(O$2=$K12,$F12*CHOOSE($B12,$O$33,$O$35,$O$37),0) -> 0 | P12: =IF(P$2=$K12,$F12*CHOOSE($B12,$O$33,$O$35,$O$37),0) -> 0 | Q12: =IF(Q$2=$K12,$F12*CHOOSE($B12,$O$33,$O$35,$O$37),0) -> 0 | R12: =IF(R$2=$K12,$F12*CHOOSE($B12,$O$33,$O$35,$O$37),0) -> 0 | S12: =IF(S$2=$K12,$F12*CHOOSE($B12,$O$33,$O$35,$O$37),0) -> 0 | T12: =IF(T$2=$K12,$F12*CHOOSE($B12,$O$33,$O$35,$O$37),0) -> 0 | U12: =IF(U$2=$K12,$F12*CHOOSE($B12,$O$33,$O$35,$O$37),0) -> 0 | V12: =IF(V$2=$K12,$F12*CHOOSE($B12,$O$33,$O$35,$O$37),0) -> 0 | ... AF12: =IF(AF$2=$K12,$F12*CHOOSE($B12,$O$33,$O$35,$O$37),0) -> 954.69717 | AG12: =$F$12*P33 -> 4019.7776 | AH12: =$F$12*Q33 -> 4271.0137 | AI12: =$F$12*R33 -> 4522.2498 | AJ12: =$F$12*S33 -> 4421.7553 | AK12: =$F$12*T33 -> 4421.7553 | AL12: =$F$12*U33 -> 2512.361 | AM12: =$F$12*V33 -> 0 | AN12: =$F$12*W33 -> 0 | ... BC12: =$F$12*AL33 -> 0 | BD12: =SUM(O12:BC12) -> 25123.61
B13: 4 | C13: Toshiba-TPSC | D13: HRSG | E13: 일본 | F13: 270519.45 | G13: 45503 | H13: 2024 | I13: 47812 | J13: 4Q24 | K13: 1Q25 | L13: 4Q30 | M13: 24 | O13: =IF(O$2=$K13,$F13*CHOOSE($B13,$O$33,$O$35,$O$37),0) -> 0 | P13: =IF(P$2=$K13,$F13*CHOOSE($B13,$O$33,$O$35,$O$37),0) -> 0 | Q13: =IF(Q$2=$K13,$F13*CHOOSE($B13,$O$33,$O$35,$O$37),0) -> 0 | R13: =IF(R$2=$K13,$F13*CHOOSE($B13,$O$33,$O$35,$O$37),0) -> 0 | S13: =IF(S$2=$K13,$F13*CHOOSE($B13,$O$33,$O$35,$O$37),0) -> 0 | T13: =IF(T$2=$K13,$F13*CHOOSE($B13,$O$33,$O$35,$O$37),0) -> 0 | U13: =IF(U$2=$K13,$F13*CHOOSE($B13,$O$33,$O$35,$O$37),0) -> 0 | V13: =IF(V$2=$K13,$F13*CHOOSE($B13,$O$33,$O$35,$O$37),0) -> 0 | ... AE13: =IF(AE$2=$K13,$F13*CHOOSE($B13,$O$33,$O$35,$O$37),0) -> 0 | AF13: =IF(AF$2=$K13,$F13*CHOOSE($B13,$O$33,$O$35,$O$37,$O$39),0) -> 6019.0577 | AG13: =$F$13*P39 -> 6019.0577 | AH13: =$F$13*Q39 -> 6019.0577 | AI13: =$F$13*R39 -> 6019.0577 | AJ13: =$F$13*S39 -> 15419.609 | AK13: =$F$13*T39 -> 15419.609 | AL13: =$F$13*U39 -> 15419.609 | AM13: =$F$13*V39 -> 15419.609 | AN13: =$F$13*W39 -> 17921.914 | ... BC13: =$F$13*AL39 -> 0 | BD13: =SUM(O13:BC13) -> 270519.45
B14: 2 | C14: 삼성물산(2) | D14: HRSG | E14: 국내 | F14: 24766.214 | G14: 45460 | H14: 2024 | I14: 45991 | J14: 3Q24 | K14: 4Q24 | L14: 4Q25 | M14: 5 | O14: =IF(O$2=$K14,$F14*CHOOSE($B14,$O$33,$O$35,$O$37),0) -> 0 | P14: =IF(P$2=$K14,$F14*CHOOSE($B14,$O$33,$O$35,$O$37),0) -> 0 | Q14: =IF(Q$2=$K14,$F14*CHOOSE($B14,$O$33,$O$35,$O$37),0) -> 0 | R14: =IF(R$2=$K14,$F14*CHOOSE($B14,$O$33,$O$35,$O$37),0) -> 0 | S14: =IF(S$2=$K14,$F14*CHOOSE($B14,$O$33,$O$35,$O$37),0) -> 0 | T14: =IF(T$2=$K14,$F14*CHOOSE($B14,$O$33,$O$35,$O$37),0) -> 0 | U14: =IF(U$2=$K14,$F14*CHOOSE($B14,$O$33,$O$35,$O$37),0) -> 0 | V14: =IF(V$2=$K14,$F14*CHOOSE($B14,$O$33,$O$35,$O$37),0) -> 0 | ... AE14: =IF(AE$2=$K14,$F14*CHOOSE($B14,$O$33,$O$35,$O$37),0) -> 2204.1931 | AF14: =$F$14*P35 -> 5646.6968 | AG14: =$F$14*Q35 -> 4717.9638 | AH14: =$F$14*R35 -> 3789.2308 | AI14: =$F$14*S35 -> 2724.2836 | AJ14: =$F$14*T35 -> 3838.7632 | AK14: =$F$14*U35 -> 1845.083 | AL14: =$F$14*V35 -> 0 | AM14: =$F$14*W35 -> 0 | ... BC14: =$F$14*AM35 -> 0 | BD14: =SUM(O14:BC14) -> 24766.214
B15: 4 | C15: Toshiba-TPSC(2) | D15: HRSG | E15: 일본 | F15: 119377.08 | G15: 45436 | H15: 2024 | I15: 47526 | J15: 3Q24 | K15: 4Q24 | L15: 1Q30 | M15: 22 | O15: =IF(O$2=$K15,$F15*CHOOSE($B15,$O$33,$O$35,$O$37),0) -> 0 | P15: =IF(P$2=$K15,$F15*CHOOSE($B15,$O$33,$O$35,$O$37),0) -> 0 | Q15: =IF(Q$2=$K15,$F15*CHOOSE($B15,$O$33,$O$35,$O$37),0) -> 0 | R15: =IF(R$2=$K15,$F15*CHOOSE($B15,$O$33,$O$35,$O$37),0) -> 0 | S15: =IF(S$2=$K15,$F15*CHOOSE($B15,$O$33,$O$35,$O$37),0) -> 0 | T15: =IF(T$2=$K15,$F15*CHOOSE($B15,$O$33,$O$35,$O$37),0) -> 0 | U15: =IF(U$2=$K15,$F15*CHOOSE($B15,$O$33,$O$35,$O$37),0) -> 0 | V15: =IF(V$2=$K15,$F15*CHOOSE($B15,$O$33,$O$35,$O$37),0) -> 0 | ... AD15: =IF(AD$2=$K15,$F15*CHOOSE($B15,$O$33,$O$35,$O$37),0) -> 0 | AE15: =IF(AE$2=$K15,$F15*CHOOSE($B15,$O$33,$O$35,$O$37,$O$39),0) -> 2656.1401 | AF15: =$F$15*P39 -> 2656.1401 | AG15: =$F$15*Q39 -> 2656.1401 | AH15: =$F$15*R39 -> 2656.1401 | AI15: =$F$15*S39 -> 6804.4938 | AJ15: =$F$15*T39 -> 6804.4938 | AK15: =$F$15*U39 -> 6804.4938 | AL15: =$F$15*V39 -> 6804.4938 | AM15: =$F$15*W39 -> 7908.7318 | ... BC15: =$F$15*AM39 -> 0 | BD15: =SUM(O15:BC15) -> 119377.08
B16: 3 | C16: 두산에너빌리티(2) | D16: HRSG | E16: 국내 | F16: 41200 | G16: 45384 | H16: 2024 | I16: 46387 | J16: 3Q24 | K16: 4Q24 | L16: 4Q26 | M16: 9 | O16: =IF(O$2=$K16,$F16*CHOOSE($B16,$O$33,$O$35,$O$37),0) -> 0 | P16: =IF(P$2=$K16,$F16*CHOOSE($B16,$O$33,$O$35,$O$37),0) -> 0 | Q16: =IF(Q$2=$K16,$F16*CHOOSE($B16,$O$33,$O$35,$O$37),0) -> 0 | R16: =IF(R$2=$K16,$F16*CHOOSE($B16,$O$33,$O$35,$O$37),0) -> 0 | S16: =IF(S$2=$K16,$F16*CHOOSE($B16,$O$33,$O$35,$O$37),0) -> 0 | T16: =IF(T$2=$K16,$F16*CHOOSE($B16,$O$33,$O$35,$O$37),0) -> 0 | U16: =IF(U$2=$K16,$F16*CHOOSE($B16,$O$33,$O$35,$O$37),0) -> 0 | V16: =IF(V$2=$K16,$F16*CHOOSE($B16,$O$33,$O$35,$O$37),0) -> 0 | ... AE16: =IF(AE$2=$K16,$F16*CHOOSE($B16,$O$33,$O$35,$O$37),0) -> 1833.4 | AF16: =$F$16*P37 -> 1833.4 | AG16: =$F$16*Q37 -> 4696.8 | AH16: =$F$16*R37 -> 4696.8 | AI16: =$F$16*S37 -> 5459 | AJ16: =$F$16*T37 -> 5459 | AK16: =$F$16*U37 -> 3151.8 | AL16: =$F$16*V37 -> 3151.8 | AM16: =$F$16*W37 -> 2266 | ... BC16: =$F$16*AM37 -> 0 | BD16: =SUM(O16:BC16) -> 41200
B17: 3 | C17: 대우건설 | D17: HRSG | E17: 국내 | F17: 47500 | G17: 45355 | H17: 2024 | I17: 46296 | J17: 2Q24 | K17: 3Q24 | L17: 4Q26 | M17: 10 | O17: =IF(O$2=$K17,$F17*CHOOSE($B17,$O$33,$O$35,$O$37),0) -> 0 | P17: =IF(P$2=$K17,$F17*CHOOSE($B17,$O$33,$O$35,$O$37),0) -> 0 | Q17: =IF(Q$2=$K17,$F17*CHOOSE($B17,$O$33,$O$35,$O$37),0) -> 0 | R17: =IF(R$2=$K17,$F17*CHOOSE($B17,$O$33,$O$35,$O$37),0) -> 0 | S17: =IF(S$2=$K17,$F17*CHOOSE($B17,$O$33,$O$35,$O$37),0) -> 0 | T17: =IF(T$2=$K17,$F17*CHOOSE($B17,$O$33,$O$35,$O$37),0) -> 0 | U17: =IF(U$2=$K17,$F17*CHOOSE($B17,$O$33,$O$35,$O$37),0) -> 0 | V17: =IF(V$2=$K17,$F17*CHOOSE($B17,$O$33,$O$35,$O$37),0) -> 0 | ... AD17: =IF(AD$2=$K17,$F17*CHOOSE($B17,$O$33,$O$35,$O$37),0) -> 2113.75 | AE17: =$F$17*P37 -> 2113.75 | AF17: =$F$17*Q37 -> 5415 | AG17: =$F$17*R37 -> 5415 | AH17: =$F$17*S37 -> 6293.75 | AI17: =$F$17*T37 -> 6293.75 | AJ17: =$F$17*U37 -> 3633.75 | AK17: =$F$17*V37 -> 3633.75 | AL17: =$F$17*W37 -> 2612.5 | ... BC17: =$F$17*AN37 -> 0 | BD17: =SUM(O17:BC17) -> 47500
B18: 1 | C18: SEPCO3 | D18: HRSG | E18: 중동 | F18: 106211.19 | G18: 45352 | H18: 2024 | I18: 45920 | J18: 2Q24 | K18: 3Q24 | L18: 3Q25 | M18: 5 | O18: =IF(O$2=$K18,$F18*CHOOSE($B18,$O$33,$O$35,$O$37),0) -> 0 | P18: =IF(P$2=$K18,$F18*CHOOSE($B18,$O$33,$O$35,$O$37),0) -> 0 | Q18: =IF(Q$2=$K18,$F18*CHOOSE($B18,$O$33,$O$35,$O$37),0) -> 0 | R18: =IF(R$2=$K18,$F18*CHOOSE($B18,$O$33,$O$35,$O$37),0) -> 0 | S18: =IF(S$2=$K18,$F18*CHOOSE($B18,$O$33,$O$35,$O$37),0) -> 0 | T18: =IF(T$2=$K18,$F18*CHOOSE($B18,$O$33,$O$35,$O$37),0) -> 0 | U18: =IF(U$2=$K18,$F18*CHOOSE($B18,$O$33,$O$35,$O$37),0) -> 0 | V18: =IF(V$2=$K18,$F18*CHOOSE($B18,$O$33,$O$35,$O$37),0) -> 0 | ... AD18: =IF(AD$2=$K18,$F18*CHOOSE($B18,$O$33,$O$35,$O$37),0) -> 4036.0252 | AE18: =$F$18*P33 -> 16993.791 | AF18: =IF(AF$2=$K18,$F18*CHOOSE($B18,$O$33,$O$35,$O$37),0) -> 0 | AG18: =$F$18*Q33 -> 18055.902 | AH18: =$F$18*R33 -> 19118.014 | AI18: =$F$18*S33 -> 18693.17 | AJ18: =$F$18*T33 -> 18693.17 | AK18: =$F$18*U33 -> 10621.119 | AL18: =$F$18*V33 -> 0 | AM18: =$F$18*W33 -> 0 | AN18: =$F$18*X33 -> 0 | ... BC18: =$F$18*AM33 -> 0 | BD18: =SUM(O18:BC18) -> 106211.19
B19: 1 | C19: SEPCO3(2) | D19: HRSG | E19: 중동 | F19: 99077.869 | G19: 45352 | H19: 2024 | I19: 45920 | J19: 2Q24 | K19: 3Q24 | L19: 3Q25 | M19: 5 | O19: =IF(O$2=$K19,$F19*CHOOSE($B19,$O$33,$O$35,$O$37),0) -> 0 | P19: =IF(P$2=$K19,$F19*CHOOSE($B19,$O$33,$O$35,$O$37),0) -> 0 | Q19: =IF(Q$2=$K19,$F19*CHOOSE($B19,$O$33,$O$35,$O$37),0) -> 0 | R19: =IF(R$2=$K19,$F19*CHOOSE($B19,$O$33,$O$35,$O$37),0) -> 0 | S19: =IF(S$2=$K19,$F19*CHOOSE($B19,$O$33,$O$35,$O$37),0) -> 0 | T19: =IF(T$2=$K19,$F19*CHOOSE($B19,$O$33,$O$35,$O$37),0) -> 0 | U19: =IF(U$2=$K19,$F19*CHOOSE($B19,$O$33,$O$35,$O$37),0) -> 0 | V19: =IF(V$2=$K19,$F19*CHOOSE($B19,$O$33,$O$35,$O$37),0) -> 0 | ... AD19: =IF(AD$2=$K19,$F19*CHOOSE($B19,$O$33,$O$35,$O$37),0) -> 3764.959 | AE19: =$F$19*P33 -> 15852.459 | AF19: =$F$19*Q33 -> 16843.238 | AG19: =$F$19*R33 -> 17834.016 | AH19: =$F$19*S33 -> 17437.705 | AI19: =$F$19*T33 -> 17437.705 | AJ19: =$F$19*U33 -> 9907.7869 | AK19: =$F$19*V33 -> 0 | AL19: =$F$19*W33 -> 0 | ... BC19: =$F$19*AN33 -> 0 | BD19: =SUM(O19:BC19) -> 99077.869
B20: 4 | C20: Toshiba-TPSC(3) | D20: HRSG | E20: 일본 | F20: 16841.65 | G20: 45244 | H20: 2023 | I20: 46387 | J20: 1Q24 | K20: 2Q24 | L20: 4Q26 | M20: 11 | O20: =IF(O$2=$K20,$F20*CHOOSE($B20,$O$33,$O$35,$O$37),0) -> 0 | P20: =IF(P$2=$K20,$F20*CHOOSE($B20,$O$33,$O$35,$O$37),0) -> 0 | Q20: =IF(Q$2=$K20,$F20*CHOOSE($B20,$O$33,$O$35,$O$37),0) -> 0 | R20: =IF(R$2=$K20,$F20*CHOOSE($B20,$O$33,$O$35,$O$37),0) -> 0 | S20: =IF(S$2=$K20,$F20*CHOOSE($B20,$O$33,$O$35,$O$37),0) -> 0 | T20: =IF(T$2=$K20,$F20*CHOOSE($B20,$O$33,$O$35,$O$37),0) -> 0 | U20: =IF(U$2=$K20,$F20*CHOOSE($B20,$O$33,$O$35,$O$37),0) -> 0 | V20: =IF(V$2=$K20,$F20*CHOOSE($B20,$O$33,$O$35,$O$37),0) -> 0 | ... AB20: =IF(AB$2=$K20,$F20*CHOOSE($B20,$O$33,$O$35,$O$37),0) -> 0 | AC20: =IF(AC$2=$K20,$F20*CHOOSE($B20,$O$33,$O$35,$O$37,$O$39),0) -> 374.72672 | AD20: =$F$20*P39 -> 374.72672 | AE20: =$F$20*Q39 -> 374.72672 | AF20: =$F$20*R39 -> 374.72672 | AG20: =$F$20*S39 -> 959.97408 | AH20: =$F$20*T39 -> 959.97408 | AI20: =$F$20*U39 -> 959.97408 | AJ20: =$F$20*V39 -> 959.97408 | AK20: =$F$20*W39 -> 1115.7593 | ... BC20: =$F$20*AO39 -> 0 | BD20: =SUM(O20:BC20) -> 16841.65
B21: 3 | C21: 두산에너빌리티(3) | D21: HRSG | E21: 국내 | F21: 44850 | G21: 45203 | H21: 2023 | I21: 46203 | J21: 1Q24 | K21: 2Q24 | L21: 2Q26 | M21: 9 | O21: =IF(O$2=$K21,$F21*CHOOSE($B21,$O$33,$O$35,$O$37),0) -> 0 | P21: =IF(P$2=$K21,$F21*CHOOSE($B21,$O$33,$O$35,$O$37),0) -> 0 | Q21: =IF(Q$2=$K21,$F21*CHOOSE($B21,$O$33,$O$35,$O$37),0) -> 0 | R21: =IF(R$2=$K21,$F21*CHOOSE($B21,$O$33,$O$35,$O$37),0) -> 0 | S21: =IF(S$2=$K21,$F21*CHOOSE($B21,$O$33,$O$35,$O$37),0) -> 0 | T21: =IF(T$2=$K21,$F21*CHOOSE($B21,$O$33,$O$35,$O$37),0) -> 0 | U21: =IF(U$2=$K21,$F21*CHOOSE($B21,$O$33,$O$35,$O$37),0) -> 0 | V21: =IF(V$2=$K21,$F21*CHOOSE($B21,$O$33,$O$35,$O$37),0) -> 0 | ... AC21: =IF(AC$2=$K21,$F21*CHOOSE($B21,$O$33,$O$35,$O$37),0) -> 1995.825 | AD21: =$F$21*P37 -> 1995.825 | AE21: =$F$21*Q37 -> 5112.9 | AF21: =$F$21*R37 -> 5112.9 | AG21: =$F$21*S37 -> 5942.625 | AH21: =$F$21*T37 -> 5942.625 | AI21: =$F$21*U37 -> 3431.025 | AJ21: =$F$21*V37 -> 3431.025 | AK21: =$F$21*W37 -> 2466.75 | ... BC21: =$F$21*AO37 -> 0 | BD21: =SUM(O21:BC21) -> 44850
B22: 4 | C22: 대우건설(2) | D22: HRSG | E22: 국내 | F22: 90192 | G22: 44831 | H22: 2022 | I22: 46777 | J22: 4Q22 | K22: 1Q23 | L22: 1Q28 | M22: 21 | O22: =IF(O$2=$K22,$F22*CHOOSE($B22,$O$33,$O$35,$O$37),0) -> 0 | P22: =IF(P$2=$K22,$F22*CHOOSE($B22,$O$33,$O$35,$O$37),0) -> 0 | Q22: =IF(Q$2=$K22,$F22*CHOOSE($B22,$O$33,$O$35,$O$37),0) -> 0 | R22: =IF(R$2=$K22,$F22*CHOOSE($B22,$O$33,$O$35,$O$37),0) -> 0 | S22: =IF(S$2=$K22,$F22*CHOOSE($B22,$O$33,$O$35,$O$37),0) -> 0 | T22: =IF(T$2=$K22,$F22*CHOOSE($B22,$O$33,$O$35,$O$37),0) -> 0 | U22: =IF(U$2=$K22,$F22*CHOOSE($B22,$O$33,$O$35,$O$37),0) -> 0 | V22: =IF(V$2=$K22,$F22*CHOOSE($B22,$O$33,$O$35,$O$37),0) -> 0 | W22: =IF(W$2=$K22,$F22*CHOOSE($B22,$O$33,$O$35,$O$37),0) -> 0 | X22: =IF(X$2=$K22,$F22*CHOOSE($B22,$O$33,$O$35,$O$37,$O$39),0) -> 2006.772 | Y22: =$F$22*P39 -> 2006.772 | Z22: =$F$22*Q39 -> 2006.772 | AA22: =$F$22*R39 -> 2006.772 | AB22: =$F$22*S39 -> 5140.944 | AC22: =$F$22*T39 -> 5140.944 | AD22: =$F$22*U39 -> 5140.944 | AE22: =$F$22*V39 -> 5140.944 | AF22: =$F$22*W39 -> 5975.22 | ... BC22: =$F$22*AT39 -> 0 | BD22: =SUM(O22:BC22) -> 90192
B23: 3 | C23: (주)포스코이앤씨 | D23: HRSG | E23: 국내 | F23: 36451.8 | G23: 44722 | H23: 2022 | I23: 45838 | J23: 3Q22 | K23: 4Q22 | L23: 2Q25 | M23: 11 | O23: =IF(O$2=$K23,$F23*CHOOSE($B23,$O$33,$O$35,$O$37),0) -> 0 | P23: =IF(P$2=$K23,$F23*CHOOSE($B23,$O$33,$O$35,$O$37),0) -> 0 | Q23: =IF(Q$2=$K23,$F23*CHOOSE($B23,$O$33,$O$35,$O$37),0) -> 0 | R23: =IF(R$2=$K23,$F23*CHOOSE($B23,$O$33,$O$35,$O$37),0) -> 0 | S23: =IF(S$2=$K23,$F23*CHOOSE($B23,$O$33,$O$35,$O$37),0) -> 0 | T23: =IF(T$2=$K23,$F23*CHOOSE($B23,$O$33,$O$35,$O$37),0) -> 0 | U23: =IF(U$2=$K23,$F23*CHOOSE($B23,$O$33,$O$35,$O$37),0) -> 0 | V23: =IF(V$2=$K23,$F23*CHOOSE($B23,$O$33,$O$35,$O$37),0) -> 0 | W23: =IF(W$2=$K23,$F23*CHOOSE($B23,$O$33,$O$35,$O$37),0) -> 1622.1051 | X23: =$F$23*P37 -> 1622.1051 | Y23: =$F$23*Q37 -> 4155.5052 | Z23: =$F$23*R37 -> 4155.5052 | AA23: =$F$23*S37 -> 4829.8635 | AB23: =$F$23*T37 -> 4829.8635 | AC23: =$F$23*U37 -> 2788.5627 | AD23: =$F$23*V37 -> 2788.5627 | AE23: =$F$23*W37 -> 2004.849 | ... BC23: =$F$23*AU37 -> 0 | BD23: =SUM(O23:BC23) -> 36451.8
B24: 3 | C24: 삼성물산(3) | D24: HRSG | E24: 해외 | F24: 53105.933 | G24: 44568 | H24: 2022 | I24: 45870 | J24: 2Q22 | K24: 3Q22 | L24: 3Q25 | M24: 13 | O24: =IF(O$2=$K24,$F24*CHOOSE($B24,$O$33,$O$35,$O$37),0) -> 0 | P24: =IF(P$2=$K24,$F24*CHOOSE($B24,$O$33,$O$35,$O$37),0) -> 0 | Q24: =IF(Q$2=$K24,$F24*CHOOSE($B24,$O$33,$O$35,$O$37),0) -> 0 | R24: =IF(R$2=$K24,$F24*CHOOSE($B24,$O$33,$O$35,$O$37),0) -> 0 | S24: =IF(S$2=$K24,$F24*CHOOSE($B24,$O$33,$O$35,$O$37),0) -> 0 | T24: =IF(T$2=$K24,$F24*CHOOSE($B24,$O$33,$O$35,$O$37),0) -> 0 | U24: =IF(U$2=$K24,$F24*CHOOSE($B24,$O$33,$O$35,$O$37),0) -> 0 | V24: =IF(V$2=$K24,$F24*CHOOSE($B24,$O$33,$O$35,$O$37),0) -> 2363.214 | W24: =$F$24*P37 -> 2363.214 | X24: =$F$24*Q37 -> 6054.0764 | Y24: =$F$24*R37 -> 6054.0764 | Z24: =$F$24*S37 -> 7036.5362 | AA24: =$F$24*T37 -> 7036.5362 | AB24: =$F$24*U37 -> 4062.6039 | AC24: =$F$24*V37 -> 4062.6039 | AD24: =$F$24*W37 -> 2920.8263 | ... BC24: =$F$24*AV37 -> 0 | BD24: =SUM(O24:BC24) -> 53105.933
B25: 4 | C25: 현대건설(2) | D25: HRSG | E25: 해외 | F25: 51031 | G25: 44035 | H25: 2020 | I25: 46233 | J25: 4Q20 | K25: 1Q21 | L25: 3Q26 | M25: 23 | O25: =IF(O$2=$K25,$F25*CHOOSE($B25,$O$33,$O$35,$O$37),0) -> 0 | P25: =IF(P$2=$K25,$F25*CHOOSE($B25,$O$33,$O$35,$O$37,$O$39),0) -> 1135.4398 | Q25: =$F$25*P39 -> 1135.4398 | R25: =$F$25*Q39 -> 1135.4398 | S25: =$F$25*R39 -> 1135.4397 | T25: =$F$25*S39 -> 2908.767 | U25: =$F$25*T39 -> 2908.767 | V25: =$F$25*U39 -> 2908.767 | W25: =$F$25*V39 -> 2908.767 | X25: =$F$25*W39 -> 3380.8037 | ... BC25: =$F$25*BB39 -> 0 | BD25: =SUM(O25:BC25) -> 51031
M26: TOTAL | O26: =SUM(O4:O25) -> 0 | P26: =SUM(P4:P25) -> 1135.4398 | Q26: =SUM(Q4:Q25) -> 1135.4398 | R26: =SUM(R4:R25) -> 1135.4398 | S26: =SUM(S4:S25) -> 1135.4397 | T26: =SUM(T4:T25) -> 2908.767 | U26: =SUM(U4:U25) -> 2908.767 | V26: =SUM(V4:V25) -> 5271.981 | ... BC26: =SUM(BC4:BC25) -> 0 | BD26: .
M27: 국내 | O27: =SUMIF($E$4:$E$25,$M27,O$4:O$25) -> 0 | P27: =SUMIF($E$4:$E$25,$M27,P$4:P$25) -> 0 | Q27: =SUMIF($E$4:$E$25,$M27,Q$4:Q$25) -> 0 | R27: =SUMIF($E$4:$E$25,$M27,R$4:R$25) -> 0 | S27: =SUMIF($E$4:$E$25,$M27,S$4:S$25) -> 0 | T27: =SUMIF($E$4:$E$25,$M27,T$4:T$25) -> 0 | U27: =SUMIF($E$4:$E$25,$M27,U$4:U$25) -> 0 | V27: =SUMIF($E$4:$E$25,$M27,V$4:V$25) -> 0 | ... BC27: =SUMIF($E$4:$E$25,$M27,BC$4:BC$25) -> 0
M28: 중동 | O28: =SUMIF($E$4:$E$25,$M28,O$4:O$25) -> 0 | P28: =SUMIF($E$4:$E$25,$M28,P$4:P$25) -> 0 | Q28: =SUMIF($E$4:$E$25,$M28,Q$4:Q$25) -> 0 | R28: =SUMIF($E$4:$E$25,$M28,R$4:R$25) -> 0 | S28: =SUMIF($E$4:$E$25,$M28,S$4:S$25) -> 0 | T28: =SUMIF($E$4:$E$25,$M28,T$4:T$25) -> 0 | U28: =SUMIF($E$4:$E$25,$M28,U$4:U$25) -> 0 | V28: =SUMIF($E$4:$E$25,$M28,V$4:V$25) -> 0 | ... BC28: =SUMIF($E$4:$E$25,$M28,BC$4:BC$25) -> 0
M29: 일본 | O29: =SUMIF($E$4:$E$25,$M29,O$4:O$25) -> 0 | P29: =SUMIF($E$4:$E$25,$M29,P$4:P$25) -> 0 | Q29: =SUMIF($E$4:$E$25,$M29,Q$4:Q$25) -> 0 | R29: =SUMIF($E$4:$E$25,$M29,R$4:R$25) -> 0 | S29: =SUMIF($E$4:$E$25,$M29,S$4:S$25) -> 0 | T29: =SUMIF($E$4:$E$25,$M29,T$4:T$25) -> 0 | U29: =SUMIF($E$4:$E$25,$M29,U$4:U$25) -> 0 | V29: =SUMIF($E$4:$E$25,$M29,V$4:V$25) -> 0 | ... BC29: =SUMIF($E$4:$E$25,$M29,BC$4:BC$25) -> 0
M30: 기타 | O30: =O26-SUM(O27:O29) -> 0 | P30: =P26-SUM(P27:P29) -> 1135.4398 | Q30: =Q26-SUM(Q27:Q29) -> 1135.4398 | R30: =R26-SUM(R27:R29) -> 1135.4398 | S30: =S26-SUM(S27:S29) -> 1135.4397 | T30: =T26-SUM(T27:T29) -> 2908.767 | U30: =U26-SUM(U27:U29) -> 2908.767 | V30: =V26-SUM(V27:V29) -> 5271.981 | ... BC30: =BC26-SUM(BC27:BC29) -> 0
A32: x | C32: 진행률 | O32: 1 | P32: 2 | Q32: 3 | R32: 4 | S32: 5 | T32: 6 | U32: 7 | V32: 8 | W32: 9 | X32: 10 | Y32: 11 | Z32: 12 | AA32: 13 | AB32: 14 | AC32: 15 | AD32: 16 | AE32: 17 | AF32: 18 | AG32: 19 | AH32: 20
B33: 1 | C33: SEPCO3 | D33: HRSG | E33: 중동 | F33: 106211.19 | G33: 45352 | H33: 2024 | I33: 45920 | J33: 2Q24 | K33: 3Q24 | L33: 3Q25 | M33: 5 | O33: =O34 -> 0.038 | P33: =P34-O34 -> 0.16 | Q33: =AVERAGE(P33,R33) -> 0.17 | R33: 0.18 | S33: =S34-R34 -> 0.176 | T33: =T34-S34 -> 0.176 | U33: =100%-SUM(O33:T33) -> 0.1
O34: =수주내역!R27 -> 0.038 | P34: =수주내역!S27 -> 0.198 | Q34: =수주내역!T27 -> 0.44 | R34: =수주내역!U27 -> 0.648 | S34: =AVERAGE(R34,T34) -> 0.824 | T34: 1
B35: 2 | C35: 에스케이에코엔지니어링㈜ | D35: HRSG | E35: 국내 | F35: 27194.889 | G35: 44742 | H35: 2022 | I35: 45291 | J35: 3Q22 | K35: 4Q22 | L35: 4Q23 | M35: 5 | O35: =O36 -> 0.089 | P35: =P36-O36 -> 0.228 | Q35: =AVERAGE(P35,R35) -> 0.1905 | R35: =R36-Q36 -> 0.153 | S35: =S36-R36 -> 0.11 | T35: =T36-S36 -> 0.155 | U35: =100%-SUM(O35:T35) -> 0.0745
O36: =수주내역!L34 -> 0.089 | P36: =수주내역!M34 -> 0.317 | Q36: =수주내역!N34 -> 0.582 | R36: =수주내역!O34 -> 0.735 | S36: =수주내역!P34 -> 0.845 | T36: 1
B37: 3 | C37: (주)포스코이앤씨 | D37: HRSG | E37: 국내 | F37: 36451.8 | G37: 44722 | H37: 2022 | I37: 45838 | J37: 3Q22 | K37: 4Q22 | L37: 2Q25 | M37: 11 | O37: =O38 -> 0.0445 | P37: =P38-O38 -> 0.0445 | Q37: =Q38-P38 -> 0.114 | R37: =R38-Q38 -> 0.114 | S37: =S38-R38 -> 0.1325 | T37: =T38-S38 -> 0.1325 | U37: =U38-T38 -> 0.0765 | V37: =V38-U38 -> 0.0765 | W37: =W38-V38 -> 0.055 | ... Z37: =Z38-Y38 -> 0.0775 | AA37: =100%-SUM(O37:Z37) -> 0
N38: 0 | O38: =AVERAGE(N38,P38) -> 0.0445 | P38: =O36 -> 0.089 | Q38: =AVERAGE(P38,R38) -> 0.203 | R38: =P36 -> 0.317 | S38: =AVERAGE(R38,T38) -> 0.4495 | T38: =Q36 -> 0.582 | U38: =AVERAGE(T38,V38) -> 0.6585 | V38: =R36 -> 0.735 | W38: =AVERAGE(V38,X38) -> 0.79 | X38: =S36 -> 0.845 | Y38: =AVERAGE(X38,Z38) -> 0.9225 | Z38: =T36 -> 1
B39: 4 | D39: HRSG | M39: 20 | O39: =O40 -> 0.02225 | P39: =P40-O40 -> 0.02225 | Q39: =Q40-P40 -> 0.02225 | R39: =R40-Q40 -> 0.02225 | S39: =S40-R40 -> 0.057 | T39: =T40-S40 -> 0.057 | U39: =U40-T40 -> 0.057 | V39: =V40-U40 -> 0.057 | W39: =W40-V40 -> 0.06625 | ... AH39: =AH40-AG40 -> 0.0775 | AI39: =100%-SUM(O39:AH39) -> 0
C40: #3번 시나리오 2배 기간으로 적용 | N40: 0 | O40: =AVERAGE(N40,P40) -> 0.02225 | P40: =O38 -> 0.0445 | Q40: =AVERAGE(P40,R40) -> 0.06675 | R40: =P38 -> 0.089 | S40: =AVERAGE(R40,T40) -> 0.146 | T40: =Q38 -> 0.203 | U40: =AVERAGE(T40,V40) -> 0.26 | V40: =R38 -> 0.317 | W40: =AVERAGE(V40,X40) -> 0.38325 | X40: =S38 -> 0.4495 | Y40: =AVERAGE(X40,Z40) -> 0.51575 | Z40: =T38 -> 0.582 | AA40: =AVERAGE(Z40,AB40) -> 0.62025 | AB40: =U38 -> 0.6585 | AC40: =AVERAGE(AB40,AD40) -> 0.69675 | AD40: =V38 -> 0.735 | AE40: =AVERAGE(AD40,AF40) -> 0.79 | AF40: =X38 -> 0.845 | AG40: =AVERAGE(AF40,AH40) -> 0.9225 | AH40: =Z38 -> 1
M42: 1
A43: x | C43: Boiler
B44: 1 | C44: San Miguel Global Power Holdings(SMCGP) | D44: Boiler | E44: 동남아 | F44: 517732.4 | G44: 45772 | H44: 2025 | I44: 47026 | J44: 3Q25 | K44: =J44 -> 3Q25 | L44: 3Q28 | M44: 14 | O44: =IF(O$2=$K44,$F44*CHOOSE($B44,$O$33,$O$35,$O$37),0) -> 0 | P44: =IF(P$2=$K44,$F44*CHOOSE($B44,$O$33,$O$35,$O$37),0) -> 0 | Q44: =IF(Q$2=$K44,$F44*CHOOSE($B44,$O$33,$O$35,$O$37),0) -> 0 | R44: =IF(R$2=$K44,$F44*CHOOSE($B44,$O$33,$O$35,$O$37),0) -> 0 | S44: =IF(S$2=$K44,$F44*CHOOSE($B44,$O$33,$O$35,$O$37),0) -> 0 | T44: =IF(T$2=$K44,$F44*CHOOSE($B44,$O$33,$O$35,$O$37),0) -> 0 | U44: =IF(U$2=$K44,$F44*CHOOSE($B44,$O$33,$O$35,$O$37),0) -> 0 | V44: =IF(V$2=$K44,$F44*CHOOSE($B44,$O$33,$O$35,$O$37),0) -> 0 | ... AG44: =IF(AG$2=$K44,$F44*CHOOSE($B44,$O$33,$O$35,$O$37),0) -> 0 | AH44: =IF(AH$2=$K44,$F$44/M44) -> 36980.886 | AI44: =AH44 -> 36980.886 | AJ44: =AI44 -> 36980.886 | AK44: =AJ44 -> 36980.886 | AL44: =AK44 -> 36980.886 | AM44: =AL44 -> 36980.886 | AN44: =AM44 -> 36980.886 | AO44: =AN44 -> 36980.886 | AP44: =AO44 -> 36980.886 | ... AU44: =AT44 -> 36980.886 | AV44: =$F$44*AB58 -> 0 | AW44: =$F$44*AC58 -> 0 | AX44: =$F$44*AD58 -> 0 | AY44: =$F$44*AE58 -> 0 | AZ44: =$F$44*AF58 -> 0 | BA44: =$F$44*AG58 -> 0 | BB44: =$F$44*AH58 -> 0 | BC44: =$F$44*AI58 -> 0 | BD44: =SUM(O44:BC44) -> 517732.4
C45: MC-HDEC-CC1 Consortium | D45: Boiler | E45: 동남아 | F45: 51320 | G45: 44790 | H45: 2022 | I45: 45763 | J45: 4Q22 | K45: 1Q23 | L45: 2Q25 | M45: 11
C46: 현대제철 | D46: Boiler | E46: 국내 | F46: 22930 | G46: 44571 | H46: 2022 | I46: 46492 | J46: 2Q22 | K46: 3Q22 | L46: 2Q27 | M46: 21
C48: 삼척블루파워 (CFBC) | F48: 122640 | J48: 3Q26 | K48: 1Q27 | L48: 2Q29 | M48: 12 | O48: =IF(O$2=$K48,$F48/$M48,0) -> 0 | P48: =IF(P$2=$K48,$F48/$M48,0) -> 0 | Q48: =IF(Q$2=$K48,$F48/$M48,0) -> 0 | R48: =IF(R$2=$K48,$F48/$M48,0) -> 0 | S48: =IF(S$2=$K48,$F48/$M48,0) -> 0 | T48: =IF(T$2=$K48,$F48/$M48,0) -> 0 | U48: =IF(U$2=$K48,$F48/$M48,0) -> 0 | V48: =IF(V$2=$K48,$F48/$M48,0) -> 0 | ... AN48: =IF(AN$2=$K48,$F48/$M48,0) -> 10220 | AO48: =AN48 -> 10220 | AP48: =AO48 -> 10220 | AQ48: =AP48 -> 10220 | AR48: =AQ48 -> 10220 | AS48: =AR48 -> 10220 | AT48: =AS48 -> 10220 | AU48: =AT48 -> 10220 | AV48: =AU48 -> 10220 | ... AY48: =AX48 -> 10220 | BA48: =IF(BA$2=$K48,$F48/$M48,0) -> 0 | BB48: =IF(BB$2=$K48,$F48/$M48,0) -> 0 | BC48: =IF(BC$2=$K48,$F48/$M48,0) -> 0 | BD48: =SUM(O48:BC48) -> 122640
C49: 당진화력발전소(PC) | F49: 122400 | J49: 3Q26 | K49: 1Q27 | L49: 2Q29 | M49: 12 | O49: =IF(O$2=$K49,$F49/$M49,0) -> 0 | P49: =IF(P$2=$K49,$F49/$M49,0) -> 0 | Q49: =IF(Q$2=$K49,$F49/$M49,0) -> 0 | R49: =IF(R$2=$K49,$F49/$M49,0) -> 0 | S49: =IF(S$2=$K49,$F49/$M49,0) -> 0 | T49: =IF(T$2=$K49,$F49/$M49,0) -> 0 | U49: =IF(U$2=$K49,$F49/$M49,0) -> 0 | V49: =IF(V$2=$K49,$F49/$M49,0) -> 0 | ... AN49: =IF(AN$2=$K49,$F49/$M49,0) -> 10200 | AO49: =AN49 -> 10200 | AP49: =AO49 -> 10200 | AQ49: =AP49 -> 10200 | AR49: =AQ49 -> 10200 | AS49: =AR49 -> 10200 | AT49: =AS49 -> 10200 | AU49: =AT49 -> 10200 | AV49: =AU49 -> 10200 | ... AY49: =AX49 -> 10200 | BA49: =IF(BA$2=$K49,$F49/$M49,0) -> 0 | BB49: =IF(BB$2=$K49,$F49/$M49,0) -> 0 | BC49: =IF(BC$2=$K49,$F49/$M49,0) -> 0 | BD49: =SUM(O49:BC49) -> 122400
O50: =SUM(O44:O49) -> 0 | P50: =SUM(P44:P49) -> 0 | Q50: =SUM(Q44:Q49) -> 0 | R50: =SUM(R44:R49) -> 0 | S50: =SUM(S44:S49) -> 0 | T50: =SUM(T44:T49) -> 0 | U50: =SUM(U44:U49) -> 0 | V50: =SUM(V44:V49) -> 0 | ... BC50: =SUM(BC44:BC49) -> 0
B51: Boiler 기존수주 매출 추정논리
B52: HRSG와 같은 논리로 진행률 반영
B53: 삼척블루파워, 당진화력발전소(암모니아 혼소 보일러) 의 경우 26년 설치부터 진행률로 반영하여 공사 기한인 3개년 간 매출 인식 가정
A55: x | C55: 진행률 | O55: 1 | P55: 2 | Q55: 3 | R55: 4 | S55: 5 | T55: 6 | U55: 7 | V55: 8 | W55: 9 | X55: 10 | Y55: 11 | Z55: 12 | AA55: 13 | AB55: 14 | AC55: 15 | AD55: 16 | AE55: 17 | AF55: 18 | AG55: 19 | AH55: 20
C56: 현대엔지니어링 | D56: Boiler | E56: 해외 | F56: 32781.005 | G56: 44671 | H56: 2022 | I56: 45291 | J56: 3Q22 | K56: 4Q22 | L56: 4Q23 | M56: 5 | O56: =O57 -> 0.03 | P56: =P57-O57 -> 0.103 | Q56: =Q57-P57 -> 0.212 | R56: =R57-Q57 -> 0.304 | S56: =S57-R57 -> 0.272 | T56: =T57-S57 -> 0.059 | U56: =U57-T57 -> 0.02
O57: =수주내역!K36 -> 0.03 | P57: =수주내역!L36 -> 0.133 | Q57: =수주내역!M36 -> 0.345 | R57: =수주내역!N36 -> 0.649 | S57: =수주내역!O36 -> 0.921 | T57: =수주내역!P36 -> 0.98 | U57: 1
B58: 1 | C58: 공사기한 10개월 | M58: 10 | O58: =O59 -> 0.03 | P58: =P59-O59 -> 0.105 | Q58: =Q59-P59 -> 0.105 | R58: =R59-Q59 -> 0.105 | S58: =S59-R59 -> 0.10133333 | T58: =T59-S59 -> 0.10133333 | U58: =U59-T59 -> 0.10133333 | V58: =V59-U59 -> 0.0585 | W58: =W59-V59 -> 0.0585 | ... AA58: =AA59-Z59 -> 0.0585
O59: =O57 -> 0.03 | P59: =O59+($R$59-$O$59)/3 -> 0.135 | Q59: =P59+($R$59-$O$59)/3 -> 0.24 | R59: =Q57 -> 0.345 | S59: =R59+($U$59-$R$59)/3 -> 0.44633333 | T59: =S59+($U$59-$R$59)/3 -> 0.54766667 | U59: =R57 -> 0.649 | V59: =U59+($AA$59-$U$59)/6 -> 0.7075 | W59: =V59+($AA$59-$U$59)/6 -> 0.766 | X59: =W59+($AA$59-$U$59)/6 -> 0.8245 | Y59: =X59+($AA$59-$U$59)/6 -> 0.883 | Z59: =Y59+($AA$59-$U$59)/6 -> 0.9415 | AA59: =U57 -> 1

Sheet BOP 수주이력
A1: 발주처 | B1: 품목 | C1: 지역 | D1: 계약금액(백만원) | E1: 계약시기 | F1: 수주연도 | G1: 공사기한 | H1: 메모
A2: 한국수력원자력 | B2: 원전 BOP | C2: 국내 | D2: 46830 | E2: 45813 | F2: 2025 | G2: 47330 | H2: 신한울 3,4호기 Condenser
A3: 한국수력원자력(2) | B3: 원전 BOP | C3: 국내 | D3: 58597.3 | E3: 45699 | F3: 2025 | G3: 47299 | H3: 신한울 3,4호기 CLP, CPP | M3: 미국 보글, 섬머 | N3: UAE 바라카
A4: 한국수력원자력(3) | B4: 원전 BOP | C4: 국내 | D4: 41540 | E4: 45699 | F4: 2025 | G4: 47330 | H4: 신한울 3,4호기 SSLW | L4: SSLW | N4: O
A5: 한화에너지 | B5: 화력 BOP | C5: 국내 | D5: 32941 | E5: 45376 | F5: 2024 | G5: 45930 | H5: 군산 G-2 보일러 연료 이송 시스템 | L5: CLP
A6: OPC Sorek 2 Ltd (OPC) | B6: 화력 BOP | C6: 해외 | D6: 11665.001 | E6: 44469 | F6: 2021 | G6: 45626 | H6: 이스라엘 LNG 복합화력 발전소 BOP | L6: Condenser | M6: O
A7: KC코트렐 | B7: 화력 BOP | C7: 국내 | D7: 62692.262 | E7: 44435 | F7: 2021 | G7: 44806 | H7: 화력발전소 환경설비 공급 | L7: FH &D | N7: O
A8: 세아STX엔테크 | B8: 화력 BOP | C8: 국내 | D8: 16540 | E8: 44263 | F8: 2021 | G8: 44680 | H8: 화력발전소 환경설비 공급
A9: Toshiba | B9: 원전 BOP | C9: 해외 | D9: 50863 | E9: 43210 | F9: =YEAR(E9) -> 2018 | H9: 보글, 섬머 CPP(추정)
A10: 한국수력원자력㈜ 새울원자력본부 | B10: 원전 BOP | C10: 국내 | D10: 19198.138 | E10: 42734 | F10: 2016 | G10: 43646 | H10: 새울 3,4호기 FH & D
A11: 한국수력원자력㈜ 새울원자력본부(2) | B11: 원전 BOP | C11: 국내 | D11: 35020.679 | E11: 42551 | F11: 2016 | G11: 44440 | H11: 새울 3,4호기 CLP
A12: 한국수력원자력㈜ 새울원자력본부(3) | B12: 원전 BOP | C12: 국내 | D12: 21473.937 | E12: 42480 | F12: 2016 | G12: 43951 | H12: 새울 3,4호기 SSLW
A13: 한국수력원자력 | B13: 원전 Strainer | C13: 국내 | D13: 19380 | E13: 41761 | F13: =YEAR(E13) -> 2014
A14: 한국전력공사 | B14: 원전 BOP | C14: 해외 | D14: 5976 | E14: 40939 | F14: =YEAR(E14) -> 2012 | H14: UAE 바라카
A15: 한국전력공사 | B15: 원전 BOP | C15: 국내 | D15: 24570 | E15: 40892 | F15: 2011 | G15: 42993 | H15: UAE 바라카 FH & D
A16: Toshiba | B16: 원전 BOP | C16: 해외 | D16: 5448 | E16: 40816 | F16: =YEAR(E16) -> 2011 | H16: 보글, 섬머 ?
A17: Toshiba | B17: 원전 BOP | C17: 해외 | D17: 5510 | E17: 40816 | F17: =YEAR(E17) -> 2011 | H17: 보글, 섬머 ?
A18: 한국전력공사(2) | B18: 원전 BOP | C18: 국내 | D18: 41843.587 | E18: 40722 | F18: 2011 | G18: 43235 | H18: UAE 바라카 SSLW(CPP 포함인지 모름)
A19: Toshiba | B19: 원전 BOP | C19: 해외 | D19: 5841 | E19: 40400 | F19: =YEAR(E19) -> 2010 | G19: 41516 | H19: 보글, 섬머 Water box
A20: Toshiba | B20: 원전 BOP | C20: 해외 | D20: 82691 | E20: 40295 | F20: =YEAR(E20) -> 2010 | G20: 41790 | H20: 보글, 섬머 Condenser(추정)
B22: 2024 | C22: 2025 | D22: 2026 | E22: 2027
A23: 한국전력공사(경주 ARA 프로젝트) | B23: 10 | C23: 39 | D23: 39 | E23: 39 | H23: 해양용 SMR 개발 원자로

Sheet BOP 수주 시나리오
R1: =2000+RIGHT(R2,2) -> 2025 | S1: =2000+RIGHT(S2,2) -> 2025 | T1: =2000+RIGHT(T2,2) -> 2025 | U1: =2000+RIGHT(U2,2) -> 2026 | V1: =2000+RIGHT(V2,2) -> 2026 | W1: =2000+RIGHT(W2,2) -> 2026 | X1: =2000+RIGHT(X2,2) -> 2026 | Y1: =2000+RIGHT(Y2,2) -> 2027 | ... AZ1: =2000+RIGHT(AZ2,2) -> 2033
C2: 지역 | D2: 발주처 | E2: 계약명 | F2: 규모 | G2: 계약금액(백만원) | H2: ASP | I2: 계약시기 | J2: 수주연도 | K2: 선금 30% | L2: 매출인식 | M2: 착공시점 | N2: 공사기한 | O2: 가동목표시점 | R2: 2Q25 | S2: 3Q25 | T2: 4Q25 | U2: 1Q26 | V2: 2Q26 | W2: 3Q26 | X2: 4Q26 | Y2: 1Q27 | Z2: 2Q27 | AA2: 3Q27 | AB2: 4Q27 | AC2: 1Q28 | AD2: 2Q28 | AE2: 3Q28 | AF2: 4Q28 | AG2: 1Q29 | AH2: 2Q29 | AI2: 3Q29 | AJ2: 4Q29 | AK2: 1Q30 | AL2: 2Q30 | AM2: 3Q30 | AN2: 4Q30 | AO2: 1Q31 | AP2: 2Q31 | AQ2: 3Q31 | AR2: 4Q31 | AS2: 1Q32 | AT2: 2Q32 | AU2: 3Q32 | AV2: 4Q32 | AW2: 1Q33 | AX2: 2Q33 | AY2: 3Q33 | AZ2: 4Q33
BA3: .
A4: x | B4: 전체 | BA4: .
E5: BULL | R5: =SUMIF($E$9:$E$87,$E5,R$9:R$87) -> 8645.1176 | S5: =SUMIF($E$9:$E$87,$E5,S$9:S$87) -> 11063.916 | T5: =SUMIF($E$9:$E$87,$E5,T$9:T$87) -> 11063.916 | U5: =SUMIF($E$9:$E$87,$E5,U$9:U$87) -> 11063.916 | V5: =SUMIF($E$9:$E$87,$E5,V$9:V$87) -> 11063.916 | W5: =SUMIF($E$9:$E$87,$E5,W$9:W$87) -> 11063.916 | X5: =SUMIF($E$9:$E$87,$E5,X$9:X$87) -> 11063.916 | Y5: =SUMIF($E$9:$E$87,$E5,Y$9:Y$87) -> 11063.916 | ... AZ5: =SUMIF($E$9:$E$87,$E5,AZ$9:AZ$87) -> 28573.212
E6: BASE | R6: =SUMIF($E$9:$E$87,$E6,R$9:R$87) -> 8645.1176 | S6: =SUMIF($E$9:$E$87,$E6,S$9:S$87) -> 11063.916 | T6: =SUMIF($E$9:$E$87,$E6,T$9:T$87) -> 11063.916 | U6: =SUMIF($E$9:$E$87,$E6,U$9:U$87) -> 11063.916 | V6: =SUMIF($E$9:$E$87,$E6,V$9:V$87) -> 11063.916 | W6: =SUMIF($E$9:$E$87,$E6,W$9:W$87) -> 11063.916 | X6: =SUMIF($E$9:$E$87,$E6,X$9:X$87) -> 11063.916 | Y6: =SUMIF($E$9:$E$87,$E6,Y$9:Y$87) -> 11063.916 | ... AZ6: =SUMIF($E$9:$E$87,$E6,AZ$9:AZ$87) -> 6171.3025
E7: BEAR | R7: =SUMIF($E$9:$E$87,$E7,R$9:R$87) -> 8645.1176 | S7: =SUMIF($E$9:$E$87,$E7,S$9:S$87) -> 11063.916 | T7: =SUMIF($E$9:$E$87,$E7,T$9:T$87) -> 11063.916 | U7: =SUMIF($E$9:$E$87,$E7,U$9:U$87) -> 11063.916 | V7: =SUMIF($E$9:$E$87,$E7,V$9:V$87) -> 11063.916 | W7: =SUMIF($E$9:$E$87,$E7,W$9:W$87) -> 11063.916 | X7: =SUMIF($E$9:$E$87,$E7,X$9:X$87) -> 11063.916 | Y7: =SUMIF($E$9:$E$87,$E7,Y$9:Y$87) -> 11063.916 | ... AZ7: =SUMIF($E$9:$E$87,$E7,AZ$9:AZ$87) -> 0
A9: x | B9: 국내 | BA9: .
BA10: . | BF10: 보조기기 공급계약 시점 추정 논리 | BL10: 공급계약시점(착공기준 몇분기 이전인지) | BM10: SSLW | BN10: CLP, CPP | BO10: Condenser | BP10: Feedwater Heaters & Deaerators
B11: History | C11: 국내 | D11: 한수원 | E11: 새울 3,4호기 SSLW | F11: 2800 | G11: 21474 | L11: 선급금 | M11: 0.3 | BA11: .
B12: History | C12: 국내 | D12: 한수원 | E12: 새울 3,4호기 CLP | F12: 2800 | G12: 35020 | BA12: . | BF12: 결론: 통상적인 BOP 계약시기 및 과거 수주 사례(UAE 바라카 프로젝트 및 미국 보글 3,4호기-섬머 3,4호기)의 수주 시점을 고려하여, 다음과 같이 추정하였다. 근거1. 보조기기는 주로 시공사 및 주기기 공급업체 선정 1,2년 후 ~ 구조물 공사 시작(착공)전 12~18개월 전에 공급 계약을 진행한다. 또한 구조물의 시공 단계별로 수주가 진행되며, 보통 격납건물용인 SSLW, CLP, CPP가 먼저 발주되고, 다음으로 복수기가 발주되며, 마지막으로 착공 이전 급수가열기 및 탈기기의 발주가 진행된다. 근거2. 한편 국내에서 진행되는 프로젝트와 달리, 해외 프로젝트는 대형부품의 출하 및 선적, 현지 공급망 통과, 설계사 검안 등의 이유로 추가적인 시간이 소요된다. 따라서 통상적인 수주시기보다 이른 시점에 발주가 진행된다. * 단, 폴란드는 동사가 현지업체 ZKE Ferrum과 폴란드 원전 보조기기 개발 및 공급 협력을 체결했기 때문에, CLP, CPP, SSLW의 패키징이 가능하다고 가정하였다. | BL12: 국내 | BM12: 4Q | BN12: 4Q | BO12: 2Q | BP12: 1Q
B13: History | C13: 국내 | D13: 한수원 | E13: 새울 3,4호기 Feedwater Heater & Deareators | F13: 2800 | G13: 19455 | I13: 평균 공급기간 | J13: SSLW | K13: CLP 및 CPP | L13: Condenser | M13: FH & D | BL13: 해외(한수원 향) | BM13: 6Q | BN13: 6Q | BO13: 3Q | BP13: 2Q
B14: History | C14: 국내 | D14: 한수원 | E14: 신한울 3,4호기 CLP, CPP | F14: 2800 | G14: 58597 | I14: 개월 | J14: 52 | K14: 52 | L14: 48 | M14: 30 | BL14: 해외(웨스팅하우스 향) | BM14: 6Q | BN14: 6Q | BO14: 3Q | BP14: 2Q
B15: History | C15: 국내 | D15: 한수원 | E15: 신한울 3,4호기 SSLW | F15: 2800 | G15: 41450
B16: History | C16: 국내 | D16: 한수원 | E16: 신한울 3,4호기 Condenser | F16: 2800 | G16: 46830 | I16: 계약시기
I17: 국내 | J17: 1 | K17: 1 | L17: 0 | M17: -2 | BL17: 품목별 평균 공급기간 | BM17: SSLW | BN17: CLP, CPP | BO17: Condenser | BP17: Feedwater Heaters & Deaerators
I18: 해외 | J18: 6 | K18: 6 | L18: 4 | M18: 2 | BA18: . | BL18: 개월 | BM18: 52 | BN18: 52 | BO18: 48 | BP18: 30
BA19: .
A20: =IF(G20=BA20,"","F") | B20: 확실 | C20: 국내 | D20: 한수원 | E20: 신한울 3,4호기 CLP, CPP | F20: 2800 | G20: 58597 | H20: =G14/F14 -> 20.9275 | I20: 1Q25 | J20: =2000+RIGHT(I20,2) -> 2025 | K20: =I20 -> 1Q25 | L20: =M20 -> 2Q25 | M20: 2Q25 | N20: 2Q29 | P20: =LEFT(N20)-LEFT(L20)+(RIGHT(N20,2)-RIGHT(L20,2))*4+1 -> 17 | R20: {=_xlfn.IFS(SUM($Q20:Q20)>=$G20,0,$L20=R$2,$G20/$P20,Q20>0,$G20/$P20,TRUE,0)} -> 3446.8824 | S20: {=_xlfn.IFS(SUM($Q20:R20)>=$G20,0,$L20=S$2,$G20/$P20,R20>0,$G20/$P20,TRUE,0)} -> 3446.8824 | T20: {=_xlfn.IFS(SUM($Q20:S20)>=$G20,0,$L20=T$2,$G20/$P20,S20>0,$G20/$P20,TRUE,0)} -> 3446.8824 | U20: {=_xlfn.IFS(SUM($Q20:T20)>=$G20,0,$L20=U$2,$G20/$P20,T20>0,$G20/$P20,TRUE,0)} -> 3446.8824 | V20: {=_xlfn.IFS(SUM($Q20:U20)>=$G20,0,$L20=V$2,$G20/$P20,U20>0,$G20/$P20,TRUE,0)} -> 3446.8824 | W20: {=_xlfn.IFS(SUM($Q20:V20)>=$G20,0,$L20=W$2,$G20/$P20,V20>0,$G20/$P20,TRUE,0)} -> 3446.8824 | X20: {=_xlfn.IFS(SUM($Q20:W20)>=$G20,0,$L20=X$2,$G20/$P20,W20>0,$G20/$P20,TRUE,0)} -> 3446.8824 | Y20: {=_xlfn.IFS(SUM($Q20:X20)>=$G20,0,$L20=Y$2,$G20/$P20,X20>0,$G20/$P20,TRUE,0)} -> 3446.8824 | ... AZ20: {=_xlfn.IFS(SUM($Q20:AY20)>=$G20,0,$L20=AZ$2,$G20/$P20,AY20>0,$G20/$P20,TRUE,0)} -> 0 | BA20: =SUM(R20:AZ20) -> 58597
A21: =IF(G21=BA21,"","F") | B21: 확실 | C21: 국내 | D21: 한수원 | E21: 신한울 3,4호기 SSLW | F21: 2800 | G21: 41540 | H21: =G15/F15 -> 14.803571 | I21: 1Q25 | J21: 2025 | K21: =I21 -> 1Q25 | L21: =M21 -> 2Q25 | M21: 2Q25 | N21: 2Q29 | P21: =LEFT(N21)-LEFT(L21)+(RIGHT(N21,2)-RIGHT(L21,2))*4+1 -> 17 | R21: {=_xlfn.IFS(SUM($Q21:Q21)>=$G21,0,$L21=R$2,$G21/$P21,Q21>0,$G21/$P21,TRUE,0)} -> 2443.5294 | S21: {=_xlfn.IFS(SUM($Q21:R21)>=$G21,0,$L21=S$2,$G21/$P21,R21>0,$G21/$P21,TRUE,0)} -> 2443.5294 | T21: {=_xlfn.IFS(SUM($Q21:S21)>=$G21,0,$L21=T$2,$G21/$P21,S21>0,$G21/$P21,TRUE,0)} -> 2443.5294 | U21: {=_xlfn.IFS(SUM($Q21:T21)>=$G21,0,$L21=U$2,$G21/$P21,T21>0,$G21/$P21,TRUE,0)} -> 2443.5294 | V21: {=_xlfn.IFS(SUM($Q21:U21)>=$G21,0,$L21=V$2,$G21/$P21,U21>0,$G21/$P21,TRUE,0)} -> 2443.5294 | W21: {=_xlfn.IFS(SUM($Q21:V21)>=$G21,0,$L21=W$2,$G21/$P21,V21>0,$G21/$P21,TRUE,0)} -> 2443.5294 | X21: {=_xlfn.IFS(SUM($Q21:W21)>=$G21,0,$L21=X$2,$G21/$P21,W21>0,$G21/$P21,TRUE,0)} -> 2443.5294 | Y21: {=_xlfn.IFS(SUM($Q21:X21)>=$G21,0,$L21=Y$2,$G21/$P21,X21>0,$G21/$P21,TRUE,0)} -> 2443.5294 | ... AZ21: {=_xlfn.IFS(SUM($Q21:AY21)>=$G21,0,$L21=AZ$2,$G21/$P21,AY21>0,$G21/$P21,TRUE,0)} -> 0 | BA21: =SUM(R21:AZ21) -> 41540
A22: =IF(G22=BA22,"","F") | B22: 확실 | C22: 국내 | D22: 한수원 | E22: 신한울 3,4호기 Condenser | F22: 2800 | G22: 46830 | H22: =G16/F16 -> 16.725 | I22: 2Q25 | J22: 2025 | K22: =I22 -> 2Q25 | L22: =M22 -> 2Q25 | M22: 2Q25 | N22: 2Q29 | P22: =LEFT(N22)-LEFT(L22)+(RIGHT(N22,2)-RIGHT(L22,2))*4+1 -> 17 | R22: {=_xlfn.IFS(SUM($Q22:Q22)>=$G22,0,$L22=R$2,$G22/$P22,Q22>0,$G22/$P22,TRUE,0)} -> 2754.7059 | S22: {=_xlfn.IFS(SUM($Q22:R22)>=$G22,0,$L22=S$2,$G22/$P22,R22>0,$G22/$P22,TRUE,0)} -> 2754.7059 | T22: {=_xlfn.IFS(SUM($Q22:S22)>=$G22,0,$L22=T$2,$G22/$P22,S22>0,$G22/$P22,TRUE,0)} -> 2754.7059 | U22: {=_xlfn.IFS(SUM($Q22:T22)>=$G22,0,$L22=U$2,$G22/$P22,T22>0,$G22/$P22,TRUE,0)} -> 2754.7059 | V22: {=_xlfn.IFS(SUM($Q22:U22)>=$G22,0,$L22=V$2,$G22/$P22,U22>0,$G22/$P22,TRUE,0)} -> 2754.7059 | W22: {=_xlfn.IFS(SUM($Q22:V22)>=$G22,0,$L22=W$2,$G22/$P22,V22>0,$G22/$P22,TRUE,0)} -> 2754.7059 | X22: {=_xlfn.IFS(SUM($Q22:W22)>=$G22,0,$L22=X$2,$G22/$P22,W22>0,$G22/$P22,TRUE,0)} -> 2754.7059 | Y22: {=_xlfn.IFS(SUM($Q22:X22)>=$G22,0,$L22=Y$2,$G22/$P22,X22>0,$G22/$P22,TRUE,0)} -> 2754.7059 | ... AZ22: {=_xlfn.IFS(SUM($Q22:AY22)>=$G22,0,$L22=AZ$2,$G22/$P22,AY22>0,$G22/$P22,TRUE,0)} -> 0 | BA22: =SUM(R22:AZ22) -> 46830
A23: =IF(G23=BA23,"","F") | B23: 확실 | C23: 국내 | D23: 한수원 | E23: 신한울 3,4호기 Feedwater Heater & Deareators | F23: 2800 | G23: =(G21*G38)/G37 -> 24187.986 | H23: =G23/F23 -> 8.6385665 | I23: 3Q25 | J23: 2025 | K23: =I23 -> 3Q25 | L23: 3Q25 | M23: 2Q25 | N23: 4Q27 | P23: =LEFT(N23)-LEFT(L23)+(RIGHT(N23,2)-RIGHT(L23,2))*4+1 -> 10 | R23: {=_xlfn.IFS(SUM($Q23:Q23)>=$G23,0,$L23=R$2,$G23/$P23,Q23>0,$G23/$P23,TRUE,0)} -> 0 | S23: {=_xlfn.IFS(SUM($Q23:R23)>=$G23,0,$L23=S$2,$G23/$P23,R23>0,$G23/$P23,TRUE,0)} -> 2418.7986 | T23: {=_xlfn.IFS(SUM($Q23:S23)>=$G23,0,$L23=T$2,$G23/$P23,S23>0,$G23/$P23,TRUE,0)} -> 2418.7986 | U23: {=_xlfn.IFS(SUM($Q23:T23)>=$G23,0,$L23=U$2,$G23/$P23,T23>0,$G23/$P23,TRUE,0)} -> 2418.7986 | V23: {=_xlfn.IFS(SUM($Q23:U23)>=$G23,0,$L23=V$2,$G23/$P23,U23>0,$G23/$P23,TRUE,0)} -> 2418.7986 | W23: {=_xlfn.IFS(SUM($Q23:V23)>=$G23,0,$L23=W$2,$G23/$P23,V23>0,$G23/$P23,TRUE,0)} -> 2418.7986 | X23: {=_xlfn.IFS(SUM($Q23:W23)>=$G23,0,$L23=X$2,$G23/$P23,W23>0,$G23/$P23,TRUE,0)} -> 2418.7986 | Y23: {=_xlfn.IFS(SUM($Q23:X23)>=$G23,0,$L23=Y$2,$G23/$P23,X23>0,$G23/$P23,TRUE,0)} -> 2418.7986 | ... AZ23: {=_xlfn.IFS(SUM($Q23:AY23)>=$G23,0,$L23=AZ$2,$G23/$P23,AY23>0,$G23/$P23,TRUE,0)} -> 0 | BA23: =SUM(R23:AZ23) -> 24187.986
A24: =IF(G24=BA24,"","F") | B24: 확실 | C24: 국내 | D24: 한수원 | E24: 신규 원전 2기 CLP, CPP | F24: 2800 | G24: =ROUND(F24*H24, -2) -> 58600 | H24: =H20 -> 20.9275 | I24: 1Q27 | J24: 2027 | K24: =I24 -> 1Q27 | L24: =M24 -> 2Q27 | M24: 2Q27 | N24: 2Q31 | P24: =LEFT(N24)-LEFT(L24)+(RIGHT(N24,2)-RIGHT(L24,2))*4+1 -> 17 | R24: {=_xlfn.IFS(SUM($Q24:Q24)>=$G24,0,$L24=R$2,$G24/$P24,Q24>0,$G24/$P24,TRUE,0)} -> 0 | S24: {=_xlfn.IFS(SUM($R24:R24)>=$G24,0,$L24=S$2,$G24/$P24,R24>0,$G24/$P24,TRUE,0)} -> 0 | T24: {=_xlfn.IFS(SUM($R24:S24)>=$G24,0,$L24=T$2,$G24/$P24,S24>0,$G24/$P24,TRUE,0)} -> 0 | U24: {=_xlfn.IFS(SUM($R24:T24)>=$G24,0,$L24=U$2,$G24/$P24,T24>0,$G24/$P24,TRUE,0)} -> 0 | V24: {=_xlfn.IFS(SUM($R24:U24)>=$G24,0,$L24=V$2,$G24/$P24,U24>0,$G24/$P24,TRUE,0)} -> 0 | W24: {=_xlfn.IFS(SUM($R24:V24)>=$G24,0,$L24=W$2,$G24/$P24,V24>0,$G24/$P24,TRUE,0)} -> 0 | X24: {=_xlfn.IFS(SUM($R24:W24)>=$G24,0,$L24=X$2,$G24/$P24,W24>0,$G24/$P24,TRUE,0)} -> 0 | Y24: {=_xlfn.IFS(SUM($R24:X24)>=$G24,0,$L24=Y$2,$G24/$P24,X24>0,$G24/$P24,TRUE,0)} -> 0 | Z24: {=_xlfn.IFS(SUM($R24:Y24)>=$G24,0,$L24=Z$2,$G24/$P24,Y24>0,$G24/$P24,TRUE,0)} -> 3447.0588 | ... AZ24: {=_xlfn.IFS(SUM($R24:AY24)>=$G24,0,$L24=AZ$2,$G24/$P24,AY24>0,$G24/$P24,TRUE,0)} -> 0 | BA24: =SUM(R24:AZ24) -> 58600
A25: =IF(G25=BA25,"","F") | B25: 확실 | C25: 국내 | D25: 한수원 | E25: 신규 원전 2기 SSLW | F25: 2800 | G25: =ROUND(F25*H25, -2) -> 41500 | H25: =H21 -> 14.803571 | I25: 1Q27 | J25: 2027 | K25: =I25 -> 1Q27 | L25: =M25 -> 2Q27 | M25: 2Q27 | N25: 2Q31 | P25: =LEFT(N25)-LEFT(L25)+(RIGHT(N25,2)-RIGHT(L25,2))*4+1 -> 17 | R25: {=_xlfn.IFS(SUM($Q25:Q25)>=$G25,0,$L25=R$2,$G25/$P25,Q25>0,$G25/$P25,TRUE,0)} -> 0 | S25: {=_xlfn.IFS(SUM($R25:R25)>=$G25,0,$L25=S$2,$G25/$P25,R25>0,$G25/$P25,TRUE,0)} -> 0 | T25: {=_xlfn.IFS(SUM($R25:S25)>=$G25,0,$L25=T$2,$G25/$P25,S25>0,$G25/$P25,TRUE,0)} -> 0 | U25: {=_xlfn.IFS(SUM($R25:T25)>=$G25,0,$L25=U$2,$G25/$P25,T25>0,$G25/$P25,TRUE,0)} -> 0 | V25: {=_xlfn.IFS(SUM($R25:U25)>=$G25,0,$L25=V$2,$G25/$P25,U25>0,$G25/$P25,TRUE,0)} -> 0 | W25: {=_xlfn.IFS(SUM($R25:V25)>=$G25,0,$L25=W$2,$G25/$P25,V25>0,$G25/$P25,TRUE,0)} -> 0 | X25: {=_xlfn.IFS(SUM($R25:W25)>=$G25,0,$L25=X$2,$G25/$P25,W25>0,$G25/$P25,TRUE,0)} -> 0 | Y25: {=_xlfn.IFS(SUM($R25:X25)>=$G25,0,$L25=Y$2,$G25/$P25,X25>0,$G25/$P25,TRUE,0)} -> 0 | Z25: {=_xlfn.IFS(SUM($R25:Y25)>=$G25,0,$L25=Z$2,$G25/$P25,Y25>0,$G25/$P25,TRUE,0)} -> 2441.1765 | ... AZ25: {=_xlfn.IFS(SUM($R25:AY25)>=$G25,0,$L25=AZ$2,$G25/$P25,AY25>0,$G25/$P25,TRUE,0)} -> 0 | BA25: =SUM(R25:AZ25) -> 41500
A26: =IF(G26=BA26,"","F") | B26: 확실 | C26: 국내 | D26: 한수원 | E26: 신규 원전 2기 Condenser | F26: 2800 | G26: =ROUND(F26*H26, -2) -> 46800 | H26: =H22 -> 16.725 | I26: 2Q27 | J26: 2027 | K26: =I26 -> 2Q27 | L26: =M26 -> 2Q27 | M26: 2Q27 | N26: 2Q31 | P26: =LEFT(N26)-LEFT(L26)+(RIGHT(N26,2)-RIGHT(L26,2))*4+1 -> 17 | R26: {=_xlfn.IFS(SUM($Q26:Q26)>=$G26,0,$L26=R$2,$G26/$P26,Q26>0,$G26/$P26,TRUE,0)} -> 0 | S26: {=_xlfn.IFS(SUM($R26:R26)>=$G26,0,$L26=S$2,$G26/$P26,R26>0,$G26/$P26,TRUE,0)} -> 0 | T26: {=_xlfn.IFS(SUM($R26:S26)>=$G26,0,$L26=T$2,$G26/$P26,S26>0,$G26/$P26,TRUE,0)} -> 0 | U26: {=_xlfn.IFS(SUM($R26:T26)>=$G26,0,$L26=U$2,$G26/$P26,T26>0,$G26/$P26,TRUE,0)} -> 0 | V26: {=_xlfn.IFS(SUM($R26:U26)>=$G26,0,$L26=V$2,$G26/$P26,U26>0,$G26/$P26,TRUE,0)} -> 0 | W26: {=_xlfn.IFS(SUM($R26:V26)>=$G26,0,$L26=W$2,$G26/$P26,V26>0,$G26/$P26,TRUE,0)} -> 0 | X26: {=_xlfn.IFS(SUM($R26:W26)>=$G26,0,$L26=X$2,$G26/$P26,W26>0,$G26/$P26,TRUE,0)} -> 0 | Y26: {=_xlfn.IFS(SUM($R26:X26)>=$G26,0,$L26=Y$2,$G26/$P26,X26>0,$G26/$P26,TRUE,0)} -> 0 | Z26: {=_xlfn.IFS(SUM($R26:Y26)>=$G26,0,$L26=Z$2,$G26/$P26,Y26>0,$G26/$P26,TRUE,0)} -> 2752.9412 | ... AZ26: {=_xlfn.IFS(SUM($R26:AY26)>=$G26,0,$L26=AZ$2,$G26/$P26,AY26>0,$G26/$P26,TRUE,0)} -> 0 | BA26: =SUM(R26:AZ26) -> 46800
A27: =IF(G27=BA27,"","F") | B27: 확실 | C27: 국내 | D27: 한수원 | E27: 신규 원전 2기 Feedwater Heater & Deareators | F27: 2800 | G27: =G23 -> 24187.986 | H27: =H23 -> 8.6385665 | I27: 4Q27 | J27: 2027 | K27: =I27 -> 4Q27 | L27: 3Q27 | M27: 2Q27 | N27: 4Q29 | P27: =LEFT(N27)-LEFT(L27)+(RIGHT(N27,2)-RIGHT(L27,2))*4+1 -> 10 | R27: {=_xlfn.IFS(SUM($Q27:Q27)>=$G27,0,$L27=R$2,$G27/$P27,Q27>0,$G27/$P27,TRUE,0)} -> 0 | S27: {=_xlfn.IFS(SUM($R27:R27)>=$G27,0,$L27=S$2,$G27/$P27,R27>0,$G27/$P27,TRUE,0)} -> 0 | T27: {=_xlfn.IFS(SUM($R27:S27)>=$G27,0,$L27=T$2,$G27/$P27,S27>0,$G27/$P27,TRUE,0)} -> 0 | U27: {=_xlfn.IFS(SUM($R27:T27)>=$G27,0,$L27=U$2,$G27/$P27,T27>0,$G27/$P27,TRUE,0)} -> 0 | V27: {=_xlfn.IFS(SUM($R27:U27)>=$G27,0,$L27=V$2,$G27/$P27,U27>0,$G27/$P27,TRUE,0)} -> 0 | W27: {=_xlfn.IFS(SUM($R27:V27)>=$G27,0,$L27=W$2,$G27/$P27,V27>0,$G27/$P27,TRUE,0)} -> 0 | X27: {=_xlfn.IFS(SUM($R27:W27)>=$G27,0,$L27=X$2,$G27/$P27,W27>0,$G27/$P27,TRUE,0)} -> 0 | Y27: {=_xlfn.IFS(SUM($R27:X27)>=$G27,0,$L27=Y$2,$G27/$P27,X27>0,$G27/$P27,TRUE,0)} -> 0 | Z27: {=_xlfn.IFS(SUM($R27:Y27)>=$G27,0,$L27=Z$2,$G27/$P27,Y27>0,$G27/$P27,TRUE,0)} -> 0 | ... AZ27: {=_xlfn.IFS(SUM($R27:AY27)>=$G27,0,$L27=AZ$2,$G27/$P27,AY27>0,$G27/$P27,TRUE,0)} -> 0 | BA27: =SUM(R27:AZ27) -> 24187.986
E28: BULL | R28: =R29+SUMIF($B$20:$B$27,"잠재",R20:R27) -> 8645.1176 | S28: =S29+SUMIF($B$20:$B$27,"잠재",S20:S27) -> 11063.916 | T28: =T29+SUMIF($B$20:$B$27,"잠재",T20:T27) -> 11063.916 | U28: =U29+SUMIF($B$20:$B$27,"잠재",U20:U27) -> 11063.916 | V28: =V29+SUMIF($B$20:$B$27,"잠재",V20:V27) -> 11063.916 | W28: =W29+SUMIF($B$20:$B$27,"잠재",W20:W27) -> 11063.916 | X28: =X29+SUMIF($B$20:$B$27,"잠재",X20:X27) -> 11063.916 | Y28: =Y29+SUMIF($B$20:$B$27,"잠재",Y20:Y27) -> 11063.916 | ... AZ28: =AZ29+SUMIF($B$20:$B$27,"잠재",AZ20:AZ27) -> 0 | BA28: .
E29: BASE | R29: =R30+SUMIF($B$20:$B$27,"가능",R20:R27) -> 8645.1176 | S29: =S30+SUMIF($B$20:$B$27,"가능",S20:S27) -> 11063.916 | T29: =T30+SUMIF($B$20:$B$27,"가능",T20:T27) -> 11063.916 | U29: =U30+SUMIF($B$20:$B$27,"가능",U20:U27) -> 11063.916 | V29: =V30+SUMIF($B$20:$B$27,"가능",V20:V27) -> 11063.916 | W29: =W30+SUMIF($B$20:$B$27,"가능",W20:W27) -> 11063.916 | X29: =X30+SUMIF($B$20:$B$27,"가능",X20:X27) -> 11063.916 | Y29: =Y30+SUMIF($B$20:$B$27,"가능",Y20:Y27) -> 11063.916 | ... AZ29: =AZ30+SUMIF($B$20:$B$27,"가능",AZ20:AZ27) -> 0 | BA29: .
E30: BEAR | R30: =SUMIF($B$20:$B$27,"확실", R20:R27) -> 8645.1176 | S30: =SUMIF($B$20:$B$27,"확실", S20:S27) -> 11063.916 | T30: =SUMIF($B$20:$B$27,"확실", T20:T27) -> 11063.916 | U30: =SUMIF($B$20:$B$27,"확실", U20:U27) -> 11063.916 | V30: =SUMIF($B$20:$B$27,"확실", V20:V27) -> 11063.916 | W30: =SUMIF($B$20:$B$27,"확실", W20:W27) -> 11063.916 | X30: =SUMIF($B$20:$B$27,"확실", X20:X27) -> 11063.916 | Y30: =SUMIF($B$20:$B$27,"확실", Y20:Y27) -> 11063.916 | ... AZ30: =SUMIF($B$20:$B$27,"확실", AZ20:AZ27) -> 0 | BA30: .
A32: x | B32: 유럽 | BA32: .
H33: 총사업비 | I33: ASP | J33: 신한울 ASP | K33: 새울 ASP | L33: 적용 ASP | P33: 총사업비 | BA33: .
B34: History | C34: 미국 | D34: 웨스팅하우스 | E34: 미국 보글 3,4호기, 썸머 2,3호기 Condenser | F34: =ROUND(1117*4, -2) -> 4500 | G34: 82691 | H34: 18 | I34: =G34/((H34*1000000)/F34) -> 20.67275 | J34: =G22/((11.7*1000000)/F22) -> 11.207179 | L34: =H22 -> 16.725 | N34: 새울 3,4호기 | P34: 9.8 | BA34: .
B35: History | C35: 미국 | D35: 웨스팅하우스 | E35: 미국 보글 3,4호기, 썸머 2,3호기 Water Box | F35: =ROUND(1117*4, -2) -> 4500 | G35: 5842 | H35: 18 | N35: 신한울 3,4호기 | P35: 11.7 | BA35: .
B36: History | C36: 미국 | D36: 웨스팅하우스 | E36: 미국 보글 3,4호기, 썸머 2,3호기 CPP | F36: =ROUND(1117*4, -2) -> 4500 | G36: 50863 | H36: 18 | I36: =G36/((H36*1000000)/F36) -> 12.71575 | J36: =G24/((11.7*1000000)/F24) -> 14.023932 | L36: =H20 -> 20.9275 | N36: 두코바니 | P36: 26 | BA36: .
B37: History | C37: 중동 | D37: 한국전력공사 | E37: UAE 바라카 1~4호기 SSLW | F37: 5600 | G37: 41844 | H37: 21.4 | I37: =G37/((H37*1000000)/F37) -> 10.949832 | J37: =G25/((11.7*1000000)/F25) -> 9.9316239 | K37: =G11/((9.8/F11)*1000000) -> 6.1354286 | L37: =H21 -> 14.803571 | N37: 포메라니아 | P37: 24 | BA37: .
B38: History | C38: 중동 | D38: 한국전력공사 | E38: UAE 바라카 1~4호기 Feedwater Heater & Deareators | F38: 5600 | G38: 24365 | H38: 21.4 | I38: =G38/((H38*1000000)/F38) -> 6.3758879 | J38: =G26/((11.7*1000000)/F26) -> 11.2 | K38: =G13/((9.8/F13)*1000000) -> 5.5585714 | L38: =H23 -> 8.6385665 | BA38: . | BF38: 보조기기 공급 품목 추정 논리
BA39: .
A40: =IF(G40=BA40,"","F") | B40: 확실 | C40: 체코 | D40: 한수원 | E40: 두코바니 5,6호기 SSLW | F40: 2000 | G40: =F40*H40 -> 29607.143 | H40: =$L$37 -> 14.803571 | I40: 1Q27 | J40: =2000+RIGHT(I40,2) -> 2027 | L40: 3Q28 | M40: 3Q28 | N40: =LEFT(M40,2)&(4+RIGHT(M40,2)) -> 3Q32 | P40: =LEFT(N40)-LEFT(L40)+(RIGHT(N40,2)-RIGHT(L40,2))*4+1 -> 17 | S40: {=_xlfn.IFS(SUM($R40:R40)>=$G40,0,$L40=S$2,$G40/$P40,R40>0,$G40/$P40,TRUE,0)} -> 0 | T40: {=_xlfn.IFS(SUM($R40:S40)>=$G40,0,$L40=T$2,$G40/$P40,S40>0,$G40/$P40,TRUE,0)} -> 0 | U40: {=_xlfn.IFS(SUM($R40:T40)>=$G40,0,$L40=U$2,$G40/$P40,T40>0,$G40/$P40,TRUE,0)} -> 0 | V40: {=_xlfn.IFS(SUM($R40:U40)>=$G40,0,$L40=V$2,$G40/$P40,U40>0,$G40/$P40,TRUE,0)} -> 0 | W40: {=_xlfn.IFS(SUM($R40:V40)>=$G40,0,$L40=W$2,$G40/$P40,V40>0,$G40/$P40,TRUE,0)} -> 0 | X40: {=_xlfn.IFS(SUM($R40:W40)>=$G40,0,$L40=X$2,$G40/$P40,W40>0,$G40/$P40,TRUE,0)} -> 0 | Y40: {=_xlfn.IFS(SUM($R40:X40)>=$G40,0,$L40=Y$2,$G40/$P40,X40>0,$G40/$P40,TRUE,0)} -> 0 | Z40: {=_xlfn.IFS(SUM($R40:Y40)>=$G40,0,$L40=Z$2,$G40/$P40,Y40>0,$G40/$P40,TRUE,0)} -> 0 | ... AZ40: {=_xlfn.IFS(SUM($R40:AY40)>=$G40,0,$L40=AZ$2,$G40/$P40,AY40>0,$G40/$P40,TRUE,0)} -> 0 | BA40: =SUM(S40:AZ40) -> 29607.143 | BF40: 1. 국내 및 해외 한수원향 수주는 BOP 패키징으로 수주가 진행되어, 주요 품목인 SSLW, CLP, CCP, Condenser, FH&D 모두 수주되는 것으로 가정하였다. 2. 해외 웨스팅하우스 향 수주는 CLP 및 CPP, Condenser의 수주만 가정한다. 웨스팅하우스는 "Buy where we build"라는 슬로건을 내세워 현지중심 공급망 확보에 주력한다. 따라서 주요설비 외 품목들은 현지기업을 통해 조달할 가능성이 높다. 다만 CLP, CPP, Condenser 등은 원전의 안전과 관련된 고도의 기술력을 요구하며 과거 납품 레퍼런스가 있는 제품이기에 수주 가능성이 높다고 판단한다.
A41: =IF(G41=BA41,"","F") | B41: 확실 | C41: 체코 | D41: 한수원 | E41: 두코바니 5,6호기 CLP, CPP | F41: 2000 | G41: =F41*H41 -> 41855 | H41: =$L$36 -> 20.9275 | I41: 1Q27 | J41: =2000+RIGHT(I41,2) -> 2027 | L41: 3Q28 | M41: 3Q28 | N41: =LEFT(M41,2)&(4+RIGHT(M41,2)) -> 3Q32 | P41: =LEFT(N41)-LEFT(L41)+(RIGHT(N41,2)-RIGHT(L41,2))*4+1 -> 17 | S41: {=_xlfn.IFS(SUM($R41:R41)>=$G41,0,$L41=S$2,$G41/$P41,R41>0,$G41/$P41,TRUE,0)} -> 0 | T41: {=_xlfn.IFS(SUM($R41:S41)>=$G41,0,$L41=T$2,$G41/$P41,S41>0,$G41/$P41,TRUE,0)} -> 0 | U41: {=_xlfn.IFS(SUM($R41:T41)>=$G41,0,$L41=U$2,$G41/$P41,T41>0,$G41/$P41,TRUE,0)} -> 0 | V41: {=_xlfn.IFS(SUM($R41:U41)>=$G41,0,$L41=V$2,$G41/$P41,U41>0,$G41/$P41,TRUE,0)} -> 0 | W41: {=_xlfn.IFS(SUM($R41:V41)>=$G41,0,$L41=W$2,$G41/$P41,V41>0,$G41/$P41,TRUE,0)} -> 0 | X41: {=_xlfn.IFS(SUM($R41:W41)>=$G41,0,$L41=X$2,$G41/$P41,W41>0,$G41/$P41,TRUE,0)} -> 0 | Y41: {=_xlfn.IFS(SUM($R41:X41)>=$G41,0,$L41=Y$2,$G41/$P41,X41>0,$G41/$P41,TRUE,0)} -> 0 | Z41: {=_xlfn.IFS(SUM($R41:Y41)>=$G41,0,$L41=Z$2,$G41/$P41,Y41>0,$G41/$P41,TRUE,0)} -> 0 | ... AZ41: {=_xlfn.IFS(SUM($R41:AY41)>=$G41,0,$L41=AZ$2,$G41/$P41,AY41>0,$G41/$P41,TRUE,0)} -> 0 | BA41: =SUM(S41:AZ41) -> 41855
A42: =IF(G42=BA42,"","F") | B42: 확실 | C42: 체코 | D42: 한수원 | E42: 두코바니 5,6호기 Condenser | F42: 2000 | G42: =F42*H42 -> 33450 | H42: =$L$34 -> 16.725 | I42: 3Q27 | J42: =2000+RIGHT(I42,2) -> 2027 | L42: 3Q28 | M42: 3Q28 | N42: =LEFT(M42,2)&(4+RIGHT(M42,2)) -> 3Q32 | P42: =LEFT(N42)-LEFT(L42)+(RIGHT(N42,2)-RIGHT(L42,2))*4+1 -> 17 | S42: {=_xlfn.IFS(SUM($R42:R42)>=$G42,0,$L42=S$2,$G42/$P42,R42>0,$G42/$P42,TRUE,0)} -> 0 | T42: {=_xlfn.IFS(SUM($R42:S42)>=$G42,0,$L42=T$2,$G42/$P42,S42>0,$G42/$P42,TRUE,0)} -> 0 | U42: {=_xlfn.IFS(SUM($R42:T42)>=$G42,0,$L42=U$2,$G42/$P42,T42>0,$G42/$P42,TRUE,0)} -> 0 | V42: {=_xlfn.IFS(SUM($R42:U42)>=$G42,0,$L42=V$2,$G42/$P42,U42>0,$G42/$P42,TRUE,0)} -> 0 | W42: {=_xlfn.IFS(SUM($R42:V42)>=$G42,0,$L42=W$2,$G42/$P42,V42>0,$G42/$P42,TRUE,0)} -> 0 | X42: {=_xlfn.IFS(SUM($R42:W42)>=$G42,0,$L42=X$2,$G42/$P42,W42>0,$G42/$P42,TRUE,0)} -> 0 | Y42: {=_xlfn.IFS(SUM($R42:X42)>=$G42,0,$L42=Y$2,$G42/$P42,X42>0,$G42/$P42,TRUE,0)} -> 0 | Z42: {=_xlfn.IFS(SUM($R42:Y42)>=$G42,0,$L42=Z$2,$G42/$P42,Y42>0,$G42/$P42,TRUE,0)} -> 0 | ... AZ42: {=_xlfn.IFS(SUM($R42:AY42)>=$G42,0,$L42=AZ$2,$G42/$P42,AY42>0,$G42/$P42,TRUE,0)} -> 0 | BA42: =SUM(S42:AZ42) -> 33450
A43: =IF(G43=BA43,"","F") | B43: 잠재 | C43: 체코 | D43: 한수원 | E43: 두코바니 5,6호기 Feedwater Heater & Deareators | F43: 2000 | G43: =F43*H43 -> 17277.133 | H43: =$L$38 -> 8.6385665 | I43: 1Q28 | J43: =2000+RIGHT(I43,2) -> 2028 | L43: 3Q28 | M43: 3Q28 | N43: =IF(ISODD(VALUE(LEFT(M43,1))),"1","4")&"Q"&(1+2+RIGHT(M43,2)) -> 1Q31 | P43: =LEFT(N43)-LEFT(L43)+(RIGHT(N43,2)-RIGHT(L43,2))*4+1 -> 11 | S43: {=_xlfn.IFS(SUM($R43:R43)>=$G43,0,$L43=S$2,$G43/$P43,R43>0,$G43/$P43,TRUE,0)} -> 0 | T43: {=_xlfn.IFS(SUM($R43:S43)>=$G43,0,$L43=T$2,$G43/$P43,S43>0,$G43/$P43,TRUE,0)} -> 0 | U43: {=_xlfn.IFS(SUM($R43:T43)>=$G43,0,$L43=U$2,$G43/$P43,T43>0,$G43/$P43,TRUE,0)} -> 0 | V43: {=_xlfn.IFS(SUM($R43:U43)>=$G43,0,$L43=V$2,$G43/$P43,U43>0,$G43/$P43,TRUE,0)} -> 0 | W43: {=_xlfn.IFS(SUM($R43:V43)>=$G43,0,$L43=W$2,$G43/$P43,V43>0,$G43/$P43,TRUE,0)} -> 0 | X43: {=_xlfn.IFS(SUM($R43:W43)>=$G43,0,$L43=X$2,$G43/$P43,W43>0,$G43/$P43,TRUE,0)} -> 0 | Y43: {=_xlfn.IFS(SUM($R43:X43)>=$G43,0,$L43=Y$2,$G43/$P43,X43>0,$G43/$P43,TRUE,0)} -> 0 | Z43: {=_xlfn.IFS(SUM($R43:Y43)>=$G43,0,$L43=Z$2,$G43/$P43,Y43>0,$G43/$P43,TRUE,0)} -> 0 | ... AZ43: {=_xlfn.IFS(SUM($R43:AY43)>=$G43,0,$L43=AZ$2,$G43/$P43,AY43>0,$G43/$P43,TRUE,0)} -> 0 | BA43: =SUM(S43:AZ43) -> 17277.133
A44: =IF(G44=BA44,"","F") | B44: 가능 | C44: 체코 | D44: 한수원 | E44: 테믈린 3,4호기 SSLW | F44: 2400 | G44: =F44*H44 -> 35528.571 | H44: =$L$37 -> 14.803571 | I44: 2Q28 | J44: =2000+RIGHT(I44,2) -> 2028 | L44: =M44 -> 2Q29 | M44: 2Q29 | N44: =LEFT(M44,2)&(4+RIGHT(M44,2)) -> 2Q33 | P44: =LEFT(N44)-LEFT(L44)+(RIGHT(N44,2)-RIGHT(L44,2))*4+1 -> 17 | S44: {=_xlfn.IFS(SUM($R44:R44)>=$G44,0,$L44=S$2,$G44/$P44,R44>0,$G44/$P44,TRUE,0)} -> 0 | T44: {=_xlfn.IFS(SUM($R44:S44)>=$G44,0,$L44=T$2,$G44/$P44,S44>0,$G44/$P44,TRUE,0)} -> 0 | U44: {=_xlfn.IFS(SUM($R44:T44)>=$G44,0,$L44=U$2,$G44/$P44,T44>0,$G44/$P44,TRUE,0)} -> 0 | V44: {=_xlfn.IFS(SUM($R44:U44)>=$G44,0,$L44=V$2,$G44/$P44,U44>0,$G44/$P44,TRUE,0)} -> 0 | W44: {=_xlfn.IFS(SUM($R44:V44)>=$G44,0,$L44=W$2,$G44/$P44,V44>0,$G44/$P44,TRUE,0)} -> 0 | X44: {=_xlfn.IFS(SUM($R44:W44)>=$G44,0,$L44=X$2,$G44/$P44,W44>0,$G44/$P44,TRUE,0)} -> 0 | Y44: {=_xlfn.IFS(SUM($R44:X44)>=$G44,0,$L44=Y$2,$G44/$P44,X44>0,$G44/$P44,TRUE,0)} -> 0 | Z44: {=_xlfn.IFS(SUM($R44:Y44)>=$G44,0,$L44=Z$2,$G44/$P44,Y44>0,$G44/$P44,TRUE,0)} -> 0 | ... AZ44: {=_xlfn.IFS(SUM($R44:AY44)>=$G44,0,$L44=AZ$2,$G44/$P44,AY44>0,$G44/$P44,TRUE,0)} -> 0 | BA44: =SUM(S44:AZ44) -> 35528.571
A45: =IF(G45=BA45,"","F") | B45: 가능 | C45: 체코 | D45: 한수원 | E45: 테믈린 3,4호기 CLP, CPP | F45: 2400 | G45: =F45*H45 -> 50226 | H45: =$L$36 -> 20.9275 | I45: 2Q28 | J45: =2000+RIGHT(I45,2) -> 2028 | L45: =M45 -> 2Q29 | M45: 2Q29 | N45: =LEFT(M45,2)&(4+RIGHT(M45,2)) -> 2Q33 | P45: =LEFT(N45)-LEFT(L45)+(RIGHT(N45,2)-RIGHT(L45,2))*4+1 -> 17 | S45: {=_xlfn.IFS(SUM($R45:R45)>=$G45,0,$L45=S$2,$G45/$P45,R45>0,$G45/$P45,TRUE,0)} -> 0 | T45: {=_xlfn.IFS(SUM($R45:S45)>=$G45,0,$L45=T$2,$G45/$P45,S45>0,$G45/$P45,TRUE,0)} -> 0 | U45: {=_xlfn.IFS(SUM($R45:T45)>=$G45,0,$L45=U$2,$G45/$P45,T45>0,$G45/$P45,TRUE,0)} -> 0 | V45: {=_xlfn.IFS(SUM($R45:U45)>=$G45,0,$L45=V$2,$G45/$P45,U45>0,$G45/$P45,TRUE,0)} -> 0 | W45: {=_xlfn.IFS(SUM($R45:V45)>=$G45,0,$L45=W$2,$G45/$P45,V45>0,$G45/$P45,TRUE,0)} -> 0 | X45: {=_xlfn.IFS(SUM($R45:W45)>=$G45,0,$L45=X$2,$G45/$P45,W45>0,$G45/$P45,TRUE,0)} -> 0 | Y45: {=_xlfn.IFS(SUM($R45:X45)>=$G45,0,$L45=Y$2,$G45/$P45,X45>0,$G45/$P45,TRUE,0)} -> 0 | Z45: {=_xlfn.IFS(SUM($R45:Y45)>=$G45,0,$L45=Z$2,$G45/$P45,Y45>0,$G45/$P45,TRUE,0)} -> 0 | ... AZ45: {=_xlfn.IFS(SUM($R45:AY45)>=$G45,0,$L45=AZ$2,$G45/$P45,AY45>0,$G45/$P45,TRUE,0)} -> 0 | BA45: =SUM(S45:AZ45) -> 50226
