Workbook
Name _MOD1: #REF!
Name \a: #N/A
Name \b: #N/A
Name \I: #REF!
Name \P: #REF!
Name A_K___s__Global__I_T: #REF!
Name Acc_payable_growth_fore: #REF!
Name Acc_Rec_growth_fore: #REF!
Name Accrued_compensation_growth_fore: #REF!
Name Accrued_expenses_growth_fore: #REF!
Name Accum_Cap_Expenses_growth_fore: #REF!
Name Accum_Goodwill_Amort_growth_fore: #REF!
Name Adj_net_oper_fore: #REF!
Name AveSize: #REF!
Name BS_C: #REF!
Name Cash_fore: #REF!
Name Cash_growth_fore: #REF!
Name Cash_operating_taxes_fore: #REF!
Name CDS: #REF!
Name CE_C: #REF!
Name CF_C: #REF!
Name CFormats: #REF!
Name codeDestination: #REF!
Name CODELK_Path: #REF!
Name ColumnHeading: #REF!
Name Comdty: #REF!
Name Corp: #REF!
Name CR3RT: #REF!
Name CR3RTDK: #REF!
Name CR5RTDK: #REF!
Name CTopics: #REF!
Name Cur: #REF!
Name Customer_deposits_growth_fore: #REF!
Name Debt_Market_Cap_Ratio: #REF!
Name Deferred_tax_asset_growth_fore: #REF!
Name Deferred_tax_liability_growth_fore: #REF!
Name Dep_margin_fore: #REF!
Name Depreciation_fore: #REF!
Name DetailColumns: #REF!
Name DnA_fore: #REF!
Name DnA_growth_fore: #REF!
Name DR: #REF!
Name DSDDE_Path: #REF!
Name EBIT_fore: #REF!
Name EBIT_margin_fore: #REF!
Name EBITA_fore: #REF!
Name EBITDA_fore: #REF!
Name EBITDA_margin_fore: #REF!
Name Excel_Version: #REF!
Name Expl_forecast_1st_yr: #REF!
Name Expl_forecast_2nd_yr: #REF!
Name Expl_forecast_3rd_yr: #REF!
Name ExtFiles: #REF!
Name Fixed_asset_turns_fore: #REF!
Name Formats: #REF!
Name FR_COM_ABBR: " "
Name FR_COM_ABBR_LINK: " "
Name FR_COM_AGG: 0
Name FR_COM_NAME_LINK: " "
Name FR_COU_ABBR: " "

Sheet Valuation
B2: 테크윙(089030.KQ) Valuation&Estimation Logic
B10: RFS Research Team 2

Sheet Expected IS
A1: 테크윙(089030.KQ)
A2: Expected IS Sheet
A3: (units in Millions KRW )
B5: 단위: 백만 원 | C5: 1Q25 | D5: 2Q25 | E5: 3Q25 | F5: 4Q25E | G5: 1Q26E | H5: 2Q26E | I5: 3Q26E | J5: 4Q26E | K5: 2025E | L5: 2026E
B6: 매출액 | C6: ='매출 추정'!C6 -> 34587.215 | D6: ='매출 추정'!D6 -> 48893.653 | E6: ='매출 추정'!E6 -> 41765.844 | F6: ='매출 추정'!F6 -> 50314.986 | G6: ='매출 추정'!G6 -> 143990.83 | H6: ='매출 추정'!H6 -> 219447.31 | I6: ='매출 추정'!I6 -> 212606.61 | J6: ='매출 추정'!J6 -> 215989.92 | ... L6: ='매출 추정'!L6 -> 792034.67 | M6: =(L6-K6)/K6 -> 3.511432
B7: 매출원가 | C7: ='비용 추정'!G17 -> 19942.025 | D7: ='비용 추정'!H17 -> 30065.138 | E7: ='비용 추정'!I17 -> 22406.702 | F7: ='비용 추정'!J17 -> 28341.068 | G7: ='비용 추정'!K17 -> 75986.5 | H7: ='비용 추정'!L17 -> 115125.19 | I7: ='비용 추정'!M17 -> 110887.51 | J7: ='비용 추정'!N17 -> 112989.9 | K7: ='비용 추정'!R17 -> 100754.93 | L7: ='비용 추정'!S17 -> 414989.09
B8: (%) | C8: =C7/C6 -> 0.57657217 | D8: =D7/D6 -> 0.61490881 | E8: =E7/E6 -> 0.53648389 | F8: =F7/F6 -> 0.5632729 | G8: =G7/G6 -> 0.52771762 | H8: =H7/H6 -> 0.52461426 | I8: =I7/I6 -> 0.5215619 | J8: =J7/J6 -> 0.5231258 | ... L8: =L7/L6 -> 0.52395319
B9: 매출총이익 | C9: =C6-C7 -> 14645.189 | D9: =D6-D7 -> 18828.515 | E9: =E6-E7 -> 19359.141 | F9: =F6-F7 -> 21973.918 | G9: =G6-G7 -> 68004.333 | H9: =H6-H7 -> 104322.12 | I9: =I6-I7 -> 101719.1 | J9: =J6-J7 -> 103000.02 | ... L9: =L6-L7 -> 377045.57
B10: GPM(%) | C10: =C9/C6 -> 0.42342783 | D10: =D9/D6 -> 0.38509119 | E10: =E9/E6 -> 0.46351611 | F10: =F9/F6 -> 0.4367271 | G10: =G9/G6 -> 0.47228238 | H10: =H9/H6 -> 0.47538574 | I10: =I9/I6 -> 0.4784381 | J10: =J9/J6 -> 0.4768742 | ... L10: =L9/L6 -> 0.47604681
B11: 판매비와 관리비 | C11: ='비용 추정'!G29 -> 13347.369 | D11: ='비용 추정'!H29 -> 12624.412 | E11: ='비용 추정'!I29 -> 12248 | F11: ='비용 추정'!J29 -> 13792.022 | G11: ='비용 추정'!K29 -> 24877.947 | H11: ='비용 추정'!L29 -> 33524.442 | I11: ='비용 추정'!M29 -> 32755.164 | J11: ='비용 추정'!N29 -> 33160.866 | K11: ='비용 추정'!R29 -> 52011.803 | L11: ='비용 추정'!S29 -> 124318.42
B12: (%) | C12: =C11/C6 -> 0.38590471 | D12: =D11/D6 -> 0.25820145 | E12: =E11/E6 -> 0.29325398 | F12: =F11/F6 -> 0.2741136 | G12: =G11/G6 -> 0.17277452 | H12: =H11/H6 -> 0.15276761 | I12: =I11/I6 -> 0.15406466 | J12: =J11/J6 -> 0.15352969 | ... L12: =L11/L6 -> 0.15696083
B13: 영업이익 | C13: =C9-C11 -> 1297.8204 | D13: =D9-D11 -> 6204.103 | E13: =E9-E11 -> 7111.1414 | F13: =F9-F11 -> 8181.8958 | G13: =G9-G11 -> 43126.386 | H13: =H9-H11 -> 70797.681 | I13: =I9-I11 -> 68963.936 | J13: =J9-J11 -> 69839.153 | ... L13: =L9-L11 -> 252727.16 | M13: =(L13-K13)/K13 -> 10.086975
B14: OPM(%) | C14: =C13/C6 -> 0.037523125 | D14: =D13/D6 -> 0.12688974 | E14: =E13/E6 -> 0.17026213 | F14: =F13/F6 -> 0.1626135 | G14: =G13/G6 -> 0.29950786 | H14: =H13/H6 -> 0.32261813 | I14: =I13/I6 -> 0.32437344 | J14: =J13/J6 -> 0.3233445 | ... L14: =L13/L6 -> 0.31908598
B15: 금융수익 | C15: ='비용 추정'!G61 -> 857.441 | D15: ='비용 추정'!H61 -> 4146.555 | E15: ='비용 추정'!I61 -> -4293 | F15: ='비용 추정'!J61 -> 434.0035 | G15: ='비용 추정'!K61 -> 286.24987 | H15: ='비용 추정'!L61 -> 143.45209 | I15: ='비용 추정'!M61 -> -857.32363 | J15: ='비용 추정'!N61 -> 1.595459 | K15: ='비용 추정'!R61 -> 1144.9995 | L15: ='비용 추정'!S61 -> -426.02621
B16: 금융원가 | C16: ='비용 추정'!G65 -> 2220.026 | D16: ='비용 추정'!H65 -> 4778.148 | E16: ='비용 추정'!I65 -> 3088 | F16: ='비용 추정'!J65 -> 4537.9902 | G16: ='비용 추정'!K65 -> 3656.0411 | H16: ='비용 추정'!L65 -> 4015.0448 | I16: ='비용 추정'!M65 -> 3824.269 | J16: ='비용 추정'!N65 -> 4008.3363 | K16: ='비용 추정'!R65 -> 14624.164 | L16: ='비용 추정'!S65 -> 15503.691
B17: 기타수익 | C17: ='비용 추정'!G69 -> 2295.6 | D17: ='비용 추정'!H69 -> 22828.642 | E17: ='비용 추정'!I69 -> -6173 | F17: ='비용 추정'!J69 -> 5559.9407 | G17: ='비용 추정'!K69 -> 6127.7957 | H17: ='비용 추정'!L69 -> 7085.8446 | I17: ='비용 추정'!M69 -> 3150.1453 | J17: ='비용 추정'!N69 -> 5480.9316 | K17: ='비용 추정'!R69 -> 24511.183 | L17: ='비용 추정'!S69 -> 21844.717
B18: 기타비용 | C18: ='비용 추정'!G75 -> 4444.638 | D18: ='비용 추정'!H75 -> 574.804 | E18: ='비용 추정'!I75 -> 1711 | F18: ='비용 추정'!J75 -> 11819.798 | G18: ='비용 추정'!K75 -> 4637.5599 | H18: ='비용 추정'!L75 -> 4685.7904 | I18: ='비용 추정'!M75 -> 5713.537 | J18: ='비용 추정'!N75 -> 6714.1713 | K18: ='비용 추정'!R75 -> 18550.24 | L18: ='비용 추정'!S75 -> 21751.059
B19: 법인세차감전순이익 | C19: =C13+C15-C16+C17-C18 -> -2213.8026 | D19: =D13+D15-D16+D17-D18 -> 27826.348 | E19: =E13+E15-E16+E17-E18 -> -8153.8586 | F19: =F13+F15-F16+F17-F18 -> -2181.9479 | G19: =G13+G15-G16+G17-G18 -> 41246.831 | H19: =H13+H15-H16+H17-H18 -> 69326.143 | I19: =I13+I15-I16+I17-I18 -> 61718.952 | J19: =J13+J15-J16+J17-J18 -> 64599.172 | ... L19: =L13+L15-L16+L17-L18 -> 236891.1
B20: 법인세비용 | C20: ='비용 추정'!G82 -> -140.8909 | D20: ='비용 추정'!H82 -> 6260.4964 | E20: ='비용 추정'!I82 -> -1468 | F20: ='비용 추정'!J82 -> -1768.9954 | G20: ='비용 추정'!K82 -> 8244.3662 | H20: ='비용 추정'!L82 -> 13860.229 | I20: ='비용 추정'!M82 -> 12338.79 | J20: ='비용 추정'!N82 -> 12914.834 | K20: ='비용 추정'!R82 -> 2882.6101 | L20: ='비용 추정'!S82 -> 47358.219
B21: 당기순이익 | C21: =C19-C20 -> -2072.9117 | D21: =D19-D20 -> 21565.852 | E21: =E19-E20 -> -6685.8586 | F21: =F19-F20 -> -412.95249 | G21: =G19-G20 -> 33002.465 | H21: =H19-H20 -> 55465.914 | I21: =I19-I20 -> 49380.161 | J21: =J19-J20 -> 51684.338 | ... L21: =L19-L20 -> 189532.88
B22: (%) | C22: 0.13039223 | D22: 0.11330898 | E22: 0.12402988 | F22: 0.13575303 | G22: 0.12971337 | H22: 0.126987 | I22: 0.13464847 | J22: 0.13476415 | K22: 0.13476415 | L22: 0.13476415

Sheet 매출 추정
A1: 테크윙(089030.KQ)
A2: Revenue Estimation Sheet
A3: (units in Millions KRW )
B5: 단위: 백만 원 | C5: 1Q25 | D5: 2Q25 | E5: 3Q25 | F5: 4Q25E | G5: 1Q26E | H5: 2Q26E | I5: 3Q26E | J5: 4Q26E | K5: 2025E | L5: 2026E
B6: 매출 | C6: ='IS(Quaterly)'!L10 -> 34587.215 | D6: ='IS(Quaterly)'!M10 -> 48893.653 | E6: ='IS(Quaterly)'!N10 -> 41765.844 | F6: =F8+F10+F12+F14 -> 50314.986 | G6: =G8+G10+G12+G14 -> 143990.83 | H6: =H8+H10+H12+H14 -> 219447.31 | I6: =I8+I10+I12+I14 -> 212606.61 | J6: =J8+J10+J12+J14 -> 215989.92 | K6: =SUM(C6:F6) -> 175561.7 | L6: =SUM(G6:J6) -> 792034.67
B7: YoY(%) or QoQ(%) | C7: - | D7: =(D6-C6)/C6 -> 0.4136337 | E7: =(E6-D6)/D6 -> -0.14578189 | F7: =(F6-E6)/E6 -> 0.20469221 | G7: =(G6-F6)/F6 -> 1.8617882 | H7: =(H6-G6)/G6 -> 0.52403669 | I7: =(I6-H6)/H6 -> -0.031172435 | J7: =(J6-I6)/I6 -> 0.015913483 | K7: - | L7: =(L6-K6)/K6 -> 3.511432
B8: 큐브 프로버 | C8: 3000 | D8: 10000 | E8: 5000 | F8: =C20 -> 8000 | G8: =D20 -> 103950 | H8: =E20 -> 173250 | I8: =F20 -> 173250 | J8: =G20 -> 173250 | K8: =SUM(C8:F8) -> 26000 | L8: =SUM(G8:J8) -> 623700
B9: of Revenue(%) | C9: =C8/C$6 -> 0.086737253 | D9: =D8/D$6 -> 0.20452553 | E9: =E8/E$6 -> 0.11971505 | F9: =F8/F$6 -> 0.15899835 | G9: =G8/G$6 -> 0.72192096 | H9: =H8/H$6 -> 0.78948335 | I9: =I8/I$6 -> 0.81488531 | J9: =J8/J$6 -> 0.80212078 | ... L9: =L8/L$6 -> 0.78746553
B10: 핸들러 | C10: =12922-3000 -> 9922 | D10: =35790-D8-C10-C8 -> 12868 | E10: =49828-D10-C10-E8-D8-C8 -> 9038 | F10: =C44 -> 14276.143 | G10: =D44 -> 11210.702 | H10: =E44 -> 18433.584 | I10: =F44 -> 11415.143 | J10: =G44 -> 14561.476 | K10: =SUM(C10:F10) -> 46104.143 | L10: =SUM(G10:J10) -> 55620.905
B11: of Revenue(%) | C11: =C10/C$6 -> 0.28686901 | D11: =D10/D$6 -> 0.26318345 | E11: =E10/E$6 -> 0.21639692 | F11: =F10/F$6 -> 0.2837354 | G11: =G10/G$6 -> 0.077857055 | H11: =H10/H$6 -> 0.084000043 | I11: =I10/I$6 -> 0.053691384 | J11: =J10/J$6 -> 0.067417389 | ... L11: =L10/L$6 -> 0.070225341
B12: C.O.K | C12: 12512 | D12: 12688 | E12: 19189 | F12: =C54 -> 19500 | G12: =D54 -> 18691.684 | H12: =E54 -> 18691.684 | I12: =F54 -> 18691.684 | J12: =G54 -> 18691.684 | K12: =SUM(C12:F12) -> 63889 | L12: =SUM(G12:J12) -> 74766.737
B13: of Revenue(%) | C13: =C12/C$6 -> 0.36175217 | D13: =D12/D$6 -> 0.25950199 | E13: =E12/E$6 -> 0.45944241 | F13: =F12/F$6 -> 0.38755849 | G13: =G12/G$6 -> 0.12981163 | H13: =H12/H$6 -> 0.085176182 | I13: =I12/I$6 -> 0.087916762 | J13: =J12/J$6 -> 0.086539615 | ... L13: =L12/L$6 -> 0.094398314
B14: 기타 | C14: 9153.2149 | D14: 13337.653 | E14: 8538.8437 | F14: =E14 -> 8538.8437 | G14: =AVERAGE(D14:F14) -> 10138.447 | H14: =AVERAGE(E14:G14) -> 9072.0447 | I14: =AVERAGE(F14:H14) -> 9249.7783 | J14: =AVERAGE(G14:I14) -> 9486.7566 | K14: =SUM(C14:F14) -> 39568.555 | L14: =SUM(G14:J14) -> 37947.026
B15: of Revenue(%) | C15: =C14/C$6 -> 0.26464157 | D15: =D14/D$6 -> 0.27278904 | E15: =E14/E$6 -> 0.20444562 | F15: =F14/F$6 -> 0.16970776 | G15: =G14/G$6 -> 0.070410362 | H15: =H14/H$6 -> 0.041340423 | I15: =I14/I$6 -> 0.043506543 | J15: =J14/J$6 -> 0.04392222 | ... L15: =L14/L$6 -> 0.047910815
B17: 큐브 프로버 추정
B19: 단위: 백만 원 | C19: 4Q25E | D19: 1Q26E | E19: 2Q26E | F19: 3Q26E | G19: 4Q26E | H19: 2026E | J19: 단위: 대/백만 원
B20: 큐브 프로버 | C20: 8000 | D20: =D34 -> 103950 | E20: =E34 -> 173250 | F20: =F34 -> 173250 | G20: =G34 -> 173250 | H20: =SUM(D20:G20) -> 623700 | J20: 웨이퍼 출하량 1K당 필요한 큐브 프로버수 | M20: 1.5
B21: YoY(%) or QoQ(%) | C21: - | D21: =(D20-C20)/C20 -> 11.99375 | E21: =(E20-D20)/D20 -> 0.66666667 | F21: =(F20-E20)/E20 -> 0 | G21: =(G20-F20)/F20 -> 0 | H21: - | J21: 큐브 프로버 ASP | M21: 2200
B23: 단위: K | C23: 4Q25E | D23: 1Q26E | E23: 2Q26E | F23: 3Q26E | G23: 4Q26E | H23: 2026E
B24: 2026년 신규 라인 웨이퍼 증가량 | C24: - | D24: =D25+D28 -> 45 | E24: =E25+E28 -> 75 | F24: =F25+F28 -> 75 | G24: =G25+G28 -> 75 | H24: =SUM(D24:G24) -> 270 | J24: 동사가 퀄리피케이션을 통과한 2개사의 '26년 HBM 신규 증설 라인에 투입될 큐브 프로버의 매출만을 추정함.
B25: SK하이닉스(분기 총 출하량) | C25: - | D25: =D27*3 -> 15 | E25: =E27*3 -> 45 | F25: =F27*3 -> 30 | G25: =G27*3 -> 30 | H25: =SUM(D25:G25) -> 120
B26: M15X 분기별 월평균 웨이퍼 출하량 | C26: - | D26: =D27 -> 5 | E26: =D26+E27 -> 20 | F26: =E26+F27 -> 30 | G26: =F26+G27 -> 40 | H26: =SUM(D26:G26) -> 95 | J26: SK하이닉스의 경우, HBM용 증설 라인인 M15X의 웨이퍼 출하량 증가분을 기준으로 동사의 납품 대수를 추정함.
B27: M15X 웨이퍼 출하량 증가분 | C27: - | D27: 5 | E27: 15 | F27: 10 | G27: 10 | H27: -
B28: 삼성전자(분기 총 출하량) | C28: - | D28: =D30*3 -> 30 | E28: =E30*3 -> 30 | F28: =F30*3 -> 45 | G28: =G30*3 -> 45 | H28: =SUM(D28:G28) -> 150
B29: P4L 분기별 월평균 웨이퍼 출하량 | C29: - | D29: =D30 -> 10 | E29: =D29+E30 -> 20 | F29: =E29+F30 -> 35 | G29: =F29+G30 -> 50 | H29: =SUM(D29:G29) -> 115 | J29: 삼성전자의 경우, HBM용 증설 라인인 P4L의 웨이퍼 출하량 증가분을 기준으로 동사의 납품 대수를 추정함.
B30: P4L 웨이퍼 출하량 증가분 | C30: - | D30: 10 | E30: 10 | F30: 15 | G30: 15 | H30: -
B31: 판매대수(침투율 100%) | C31: 4 | D31: =D24*$M$20 -> 67.5 | E31: =E24*$M$20 -> 112.5 | F31: =F24*$M$20 -> 112.5 | G31: =G24*$M$20 -> 112.5 | H31: =H24*$M$20 -> 405 | J31: CAPA 증설이 앞당겨질 경우, 300대 이상의 판매량 기록도 가능할 것으로 전망함.
B32: Bull 큐브 프로버 매출 | C32: =C31*$M$21 -> 8800 | D32: =D31*$M$21 -> 148500 | E32: =E31*$M$21 -> 247500 | F32: =F31*$M$21 -> 247500 | G32: =G31*$M$21 -> 247500 | H32: =H31*$M$21 -> 891000 | J32: 침투율 100%를 Bull 케이스로 선정함.
B33: 판매대수(침투율 70%) | C33: 4 | D33: =D31*0.7 -> 47.25 | E33: =E31*0.7 -> 78.75 | F33: =F31*0.7 -> 78.75 | G33: =G31*0.7 -> 78.75 | H33: =H31*0.7 -> 283.5 | J33: 현재 동사의 CAPA 계획대로라면, 연간 큐브 프로버 약 290~300대 생산 가능함.
B34: Base 큐브 프로버 매출 | C34: =C33*$M$21 -> 8800 | D34: =D33*$M$21 -> 103950 | E34: =E33*$M$21 -> 173250 | F34: =F33*$M$21 -> 173250 | G34: =G33*$M$21 -> 173250 | H34: =H33*$M$21 -> 623700 | J34: 침투율 70%가 Base 케이스로 적합하다고 판단함.
B36: 단위: 대/% | C36: 4Q25E | D36: 1Q26E | E36: 2Q26E | F36: 3Q26E | G36: 4Q26E | H36: 2026E
B37: 분기당 큐브 프로버 생산 대수 | C37: =C38*C39*3 -> 54 | D37: =D38*D39*3 -> 54 | E37: =E38*E39*3 -> 68.25 | F37: =F38*F39*3 -> 84 | G37: =G38*G39*3 -> 84 | H37: =SUM(D37:G37) -> 290.25 | J37: 4Q25 큐브 프로버 매출의 경우, 전방사 장비 반입을 감안하여 1Q26부터 매출로 인식될 것으로 가정함.
B38: 월간 큐브프로버 최대 생산 CAPA | C38: 30 | D38: 30 | E38: 35 | F38: 40 | G38: 40 | H38: =SUM(D38:G38) -> 145
B39: 가동률 | C39: 0.6 | D39: 0.6 | E39: 0.65 | F39: 0.7 | G39: 0.7 | H39: -
B41: 핸들러 추정
B43: 단위: 백만 원 | C43: 4Q25E | D43: 1Q26E | E43: 2Q26E | F43: 3Q26E | G43: 4Q26E | H43: 2026E | J43: 단위: 백만 원 | M43: ASP
B44: 핸들러 | C44: =C46+C48 -> 14276.143 | D44: =D46+D48 -> 11210.702 | E44: =E46+E48 -> 18433.584 | F44: =F46+F48 -> 11415.143 | G44: =G46+G48 -> 14561.476 | H44: =H46+H48 -> 69897.048 | J44: 메모리핸들러 ASP | M44: 500
B45: YoY(%) or QoQ(%) | C45: - | D45: =(D44-C44)/C44 -> -0.2147247 | E45: =(E44-D44)/D44 -> 0.64428448 | F45: =(F44-E44)/E44 -> -0.38074207 | G45: =(G44-F44)/F44 -> 0.27562804 | H45: - | J45: 비메모리핸들러 ASP | M45: 300
B46: 메모리 핸들러 | C46: =C47*$M$44 -> 8276.1427 | D46: =D47*$M$44 -> 8060.7022 | E46: =E47*$M$44 -> 8458.5836 | F46: =F47*$M$44 -> 8265.1428 | G46: =G47*$M$44 -> 8261.4762 | H46: =H47*$M$44 -> 41322.048 | J46: 메모리 핸들러의 경우, 더 이상 성장여력이 제한될 것으로 판단. 25년 3분기 Avg Flat을 적용하여 동사의 납품대수를 추정함.
B47: 메모리 핸들러 Q | C47: 16.552285 | D47: 16.121404 | E47: 16.917167 | F47: 16.530286 | G47: 16.522952 | H47: =SUM(C47:G47) -> 82.644095
B48: 비메모리 핸들러 | C48: =C49*$M$45 -> 6000 | D48: =D49*$M$45 -> 3150 | E48: =E49*$M$45 -> 9975 | F48: =F49*$M$45 -> 3150 | G48: =G49*$M$45 -> 6300 | H48: =H49*$M$45 -> 28575 | J48: 비메모리핸들러의 경우, 데이터센터향 SSD 핸들러 발주 확대 증가분을 기준으로 동사의 납품 대수를 추정함.
B49: 비메모리 핸들러 Q | C49: 20 | D49: 10.5 | E49: 33.25 | F49: 10.5 | G49: 21 | H49: =SUM(C49:G49) -> 95.25 | J49: 월간 메모리 핸들러를 20대 가량 생산하기에 분기당 충분히 소화 가능
B51: C.O.K 추정
B53: 단위: 백만 원/수 | C53: 4Q25E | D53: 1Q26E | E53: 2Q26E | F53: 3Q26E | G53: 4Q26E | H53: 2026E | J53: 단위: 백만 원 | M53: ASP
B54: C.O.K | C54: =C56*$M$54 -> 19500 | D54: =D56*$M$54 -> 18691.684 | E54: =E56*$M$54 -> 18691.684 | F54: =F56*$M$54 -> 18691.684 | G54: =G56*$M$54 -> 18691.684 | H54: =SUM(D54:G54) -> 74766.737 | J54: C.O.K | M54: 30
B55: YoY(%) or QoQ(%) | C55: - | D55: =(D54-C54)/C54 -> -0.041452088 | E55: =(E54-D54)/D54 -> 0 | F55: =(F54-E54)/E54 -> 0 | G55: =(G54-F54)/F54 -> 0 | H55: - | J55: C.O.K의 경우, 반도체 전환 사이클 증가분에 따라 증가하는 성장률을 가산하여 동사의 납품 대수를 추정함.
B56: C.O.K Q | C56: 650 | D56: =$O$61/4 -> 623.05614 | E56: =$O$61/4 -> 623.05614 | F56: =$O$61/4 -> 623.05614 | G56: =$O$61/4 -> 623.05614 | H56: =SUM(D56:G56) -> 2492.2246
B58: 단위: 백만 원 | C58: 2014 | D58: 2015 | E58: 2016 | F58: 2017 | G58: 2018 | H58: 2019 | I58: 2020 | J58: 2021 | K58: 2022 | L58: 2023 | M58: 2024 | N58: 2025E | O58: 2026E
B59: C.O.K ASP | C59: 20 | D59: 20.833 | E59: 21.667 | F59: 22.5 | G59: 23.333 | H59: 24.167 | I59: 25 | J59: 25.833 | K59: 26.667 | L59: 27.5 | M59: 28.333 | N59: 29.167 | O59: 30
B60: 매출 | C60: 22500 | D60: 31900 | E60: 28400 | F60: 42700 | G60: 41400 | H60: 39800 | I60: 42800 | J60: 45700 | K60: 55500 | L60: 38300 | M60: 48200 | N60: 61000 | O60: =O61*O59 -> 74766.737
B61: Q | C61: =C60/C59 -> 1125 | D61: =D60/D59 -> 1531.2245 | E61: =E60/E59 -> 1310.7491 | F61: =F60/F59 -> 1897.7778 | G61: =G60/G59 -> 1774.3111 | H61: =H60/H59 -> 1646.8738 | I61: =I60/I59 -> 1712 | J61: =J60/J59 -> 1769.0551 | ... N61: =N60/N59 -> 2091.4047 | O61: =N61+O62 -> 2492.2246
B62: YoY Q 증가분 | D62: =D61-C61 -> 406.2245 | E62: =E61-D61 -> -220.47543 | F62: =F61-E61 -> 587.02871 | G62: =G61-F61 -> -123.46672 | H62: =H61-G61 -> -127.43723 | I62: =I61-H61 -> 65.126164 | J62: =J61-I61 -> 57.055085 | K62: =K61-J61 -> 312.1689 | ... N62: =N61-M61 -> 390.20818 | O62: =AVERAGE(D62,F62,M62,K62,N62) -> 400.8199
B64: 기타
B66: 단위: 백만 원/수 | C66: 4Q25E | D66: 1Q26E | E66: 2Q26E | F66: 3Q26E | G66: 4Q26E | H66: 2026E
B67: 기타 | C67: =E14 -> 8538.8437 | D67: =AVERAGE(D14:F14) -> 10138.447 | E67: =AVERAGE(E14:G14) -> 9072.0447 | F67: =AVERAGE(C67:E67) -> 9249.7783 | G67: =AVERAGE(D67:F67) -> 9486.7566 | H67: =SUM(D67:G67) -> 37947.026 | J67: 매출액 대비 비중이 작고 변동성이 존재하지 않으므로 직전 3개분기 이동평균을 적용함.
B68: YoY(%) or QoQ(%) | C68: 0.16970776 | D68: 0.070410362 | E68: 0.041340423 | F68: 0.043506543 | G68: 0.0030080989 | H68: -

Sheet PER
A1: 테크윙(089030.KQ)
A2: Historical PER Valuation
A3: (units in Millions KRW )
B5: 테크윙 Historical P/E Valuation
B6: '26E 당기순이익 | C6: ='Expected IS'!L21 -> 189532.88 | D6: 백만 원 | E6: (A)
B7: Target P/E | C7: =18 -> 18 | D7: 배 | E7: (B)
B8: 발행 주식 수 | C8: =WACC!E29 -> 38366816 | D8: 주 | E8: (C)
B9: '26E EPS | C9: =C6/C8*10^6 -> 4940.021 | D9: 원 | E9: (D)
B10: 적정주가 | C10: =C6*C7/C8*10^6 -> 88920.379 | D10: 원 | E10: (E)=(B)*(D)
B11: Target Price | C11: =ROUND(C10,-3) -> 89000 | D11: 원
B12: Current Price | C12: 47500 | D12: 원 | E12: '25.11.28 기준
B13: Upside | C13: =(C11-C12)/C12*100 -> 87.368421 | D13: %

Sheet DCF>>>
A1: 테크윙(089030.KQ)
A2: PEER PER Valuation
A3: (units in Millions KRW )
E5: 2022 | F5: 2023 | G5: 2024 | H5: 2025E | I5: 2026E | J5: 2027E | K5: 2028E | L5: 2029E | M5: 2030E | N5: Terminal Value | Q5: DCF Valuation | T5: (단위: 백만원, %)
A6: 매출액 | E6: 267491 | F6: 133604 | G6: 185507 | H6: ='매출 추정'!K6 -> 175561.7 | I6: ='매출 추정'!L6 -> 792034.67 | J6: =I6*1.1 -> 871238.14 | K6: =J6*1.05 -> 914800.04 | L6: =K6*1.05 -> 960540.04 | M6: =L6*1.05 -> 1008567 | Q6: WACC | T6: =F32 -> 0.098434027
A7: %YoY Growth | F7: =F6/E6-1 -> -0.50052899 | G7: =G6/F6-1 -> 0.38848388 | H7: =H6/G6-1 -> -0.053611467 | I7: =I6/H6-1 -> 3.511432 | J7: =J6/I6-1 -> 0.1 | K7: =K6/J6-1 -> 0.05 | L7: =L6/K6-1 -> 0.05 | M7: =M6/L6-1 -> 0.05 | Q7: Terminal growth rate(g) | T7: =F31 -> 0.03
A8: 매출원가 | E8: 158044 | F8: 84056 | G8: 114022 | H8: ='비용 추정'!R17 -> 100754.93 | I8: ='비용 추정'!S17 -> 414989.09 | J8: =I8*1.05 -> 435738.55 | K8: =J8*1.05 -> 457525.48 | L8: =K8*1.05 -> 480401.75 | M8: =L8*1.05 -> 504421.84 | Q8: ∑ PV of FCF | T8: =F36 -> 776428.28
A9: 매출총이익 | E9: =E6-E8 -> 109447 | F9: =F6-F8 -> 49548 | G9: =G6-G8 -> 71485 | H9: =H6-H8 -> 74806.764 | I9: =I6-I8 -> 377045.57 | J9: =J6-J8 -> 435499.59 | K9: =K6-K8 -> 457274.57 | L9: =L6-L8 -> 480138.29 | M9: =M6-M8 -> 504145.21 | Q9: PV of TV | T9: =F37 -> 2556667.5
A10: %GP Margin | E10: =E9/E6 -> 0.40916143 | F10: =F9/F6 -> 0.37085716 | G10: =G9/G6 -> 0.38534934 | H10: =H9/H6 -> 0.42609957 | I10: =I9/I6 -> 0.47604681 | J10: =J9/J6 -> 0.49986286 | K10: =K9/K6 -> 0.49986286 | L10: =L9/L6 -> 0.49986286 | M10: =M9/M6 -> 0.49986286 | Q10: 영업가치 | T10: =T8+T9 -> 3333095.8
A11: 판매비와관리비 | E11: 51774 | F11: 46388 | G11: 48075 | H11: ='비용 추정'!R29 -> 52011.803 | I11: ='비용 추정'!S29 -> 124318.42 | J11: =I11*1.05 -> 130534.34 | K11: =J11*1.05 -> 137061.06 | L11: =K11*1.05 -> 143914.11 | M11: =L11*1.05 -> 151109.81 | Q11: (+) 비영업자산가치 | T11: =F39 -> 103519
A12: 영업이익 | E12: =E9-E11 -> 57673 | F12: =F9-F11 -> 3160 | G12: =G9-G11 -> 23410 | H12: =H9-H11 -> 22794.961 | I12: =I9-I11 -> 252727.16 | J12: =J9-J11 -> 304965.25 | K12: =K9-K11 -> 320213.51 | L12: =L9-L11 -> 336224.19 | M12: =M9-M11 -> 353035.39 | Q12: (-) 타인자본가치 (순차입금) | T12: =F40 -> 287909
A13: %OP Margin | E13: =E12/E6 -> 0.21560725 | F13: =F12/F6 -> 0.023651986 | G13: =G12/G6 -> 0.1261947 | H13: =H12/H6 -> 0.12984017 | I13: =I12/I6 -> 0.31908598 | J13: =J12/J6 -> 0.35003661 | K13: =K12/K6 -> 0.35003661 | L13: =L12/L6 -> 0.35003661 | M13: =M12/M6 -> 0.35003661 | Q13: 주주가치(Equity Value) | T13: =T11+T10-T12 -> 3148705.8
A14: %YoY Growth | F14: =F12/E12-1 -> -0.94520833 | G14: =G12/F12-1 -> 6.4082278 | H14: =H12/G12-1 -> -0.026272508 | I14: =I12/H12-1 -> 10.086975 | J14: =J12/I12-1 -> 0.20669758 | K14: =K12/J12-1 -> 0.05 | L14: =L12/K12-1 -> 0.05 | M14: =M12/L12-1 -> 0.05 | Q14: 발행주식수 | T14: =F42 -> 38366816
A15: 세율 | E15: 0.19 | F15: 0.19 | G15: 0.19 | H15: ='비용 추정'!R83 -> 0.18869083 | I15: ='비용 추정'!$S$83 -> 0.19991557 | J15: ='비용 추정'!$S$83 -> 0.19991557 | K15: ='비용 추정'!$S$83 -> 0.19991557 | L15: ='비용 추정'!$S$83 -> 0.19991557 | M15: ='비용 추정'!$S$83 -> 0.19991557 | Q15: 적정주가: | T15: =F44 -> 82068.468
A16: 세후영업이익(NOPLAT) | E16: =E12*(1-E15) -> 46715.13 | F16: =F12*(1-F15) -> 2559.6 | G16: =G12*(1-G15) -> 18962.1 | H16: =H12*(1-H15) -> 18493.76 | I16: =I12*(1-I15) -> 202203.06 | J16: =J12*(1-J15) -> 243997.95 | K16: =K12*(1-K15) -> 256197.84 | L16: =L12*(1-L15) -> 269007.73 | M16: =M12*(1-M15) -> 282458.12 | Q16: 현재주가: | T16: 47500
A17: (+) 상각비 | E17: ='FA Schedule'!D37 -> 11152 | F17: ='FA Schedule'!E37 -> 10136 | G17: ='FA Schedule'!F37 -> 11856 | H17: ='FA Schedule'!G37 -> 15390.286 | I17: ='FA Schedule'!H37 -> 10927.578 | J17: ='FA Schedule'!I37 -> 10758.453 | K17: ='FA Schedule'!J37 -> 10534.246 | L17: ='FA Schedule'!K37 -> 8925.9794 | M17: ='FA Schedule'!L37 -> 8419.7898 | Q17: 상승(하락)여력: | T17: =T15/T16-1 -> 0.72775722
A18: 매출 대비 비중 | E18: =E17/E6 -> 0.041691122 | F18: =F17/F6 -> 0.075865992 | G18: =G17/G6 -> 0.063911335 | H18: =H17/H6 -> 0.087663118 | I18: =I17/I6 -> 0.013796843 | J18: =J17/J6 -> 0.012348465 | K18: =K17/K6 -> 0.011515354 | L18: =L17/L6 -> 0.0092926676 | M18: =M17/M6 -> 0.0083482698 | Q18: 투자의견 | T18: BUY
A20: (-) 순운전자본(NWC) 변동 (기말-기초) | F20: =F22-F21 -> -19842 | G20: =G22-G21 -> 1184 | H20: =H22-H21 -> 18691.054 | I20: =I22-I21 -> 133976.01 | J20: =J22-J21 -> 9768.0305 | K20: =K22-K21 -> 27441.32 | L20: =L22-L21 -> 2323.242 | M20: =M22-M21 -> 10321.127
A21: 기초 순운전자본 | F21: ='Change in NWC'!D15 -> 125560 | G21: ='Change in NWC'!E15 -> 105718 | H21: ='Change in NWC'!F15 -> 106902 | I21: ='Change in NWC'!G15 -> 125593.05 | J21: ='Change in NWC'!H15 -> 259569.06 | K21: ='Change in NWC'!I15 -> 269337.09 | L21: ='Change in NWC'!J15 -> 296778.41 | M21: ='Change in NWC'!K15 -> 299101.66
A22: 기말 순운전자본 | E22: ='Change in NWC'!D15 -> 125560 | F22: ='Change in NWC'!E15 -> 105718 | G22: ='Change in NWC'!F15 -> 106902 | H22: ='Change in NWC'!G15 -> 125593.05 | I22: ='Change in NWC'!H15 -> 259569.06 | J22: ='Change in NWC'!I15 -> 269337.09 | K22: ='Change in NWC'!J15 -> 296778.41 | L22: ='Change in NWC'!K15 -> 299101.66 | M22: ='Change in NWC'!L15 -> 309422.78
A23: 순운전자본 증감 매출 대비 비중 | F23: =F20/F6 -> -0.14851352 | G23: =G20/G6 -> 0.0063825085 | H23: =H20/H6 -> 0.10646431 | I23: =I20/I6 -> 0.16915422
A25: (-) Capex | E25: ='FA Schedule'!D35 -> 14158 | F25: ='FA Schedule'!E35 -> 53157 | G25: ='FA Schedule'!F35 -> 54010 | H25: ='FA Schedule'!G35 -> 35029.056 | I25: ='FA Schedule'!H35 -> 15390.286 | J25: ='FA Schedule'!I35 -> 10927.578 | K25: ='FA Schedule'!J35 -> 10758.453 | L25: ='FA Schedule'!K35 -> 10534.246 | M25: ='FA Schedule'!L35 -> 8925.9794
A26: 매출 대비 비중 | F26: =F25/F6 -> 0.39786982 | G26: =G25/G6 -> 0.29114804 | H26: =H25/H6 -> 0.19952562 | I26: =I25/I6 -> 0.019431328 | J26: =J25/J6 -> 0.012542584 | K26: =K25/K6 -> 0.011760443 | L26: =L25/L6 -> 0.010967003 | M26: =M25/M6 -> 0.0088501596
A28: 잉여현금흐름(FCF) | F28: =F16+F17-F20-F25 -> -20619.4 | G28: =G16+G17-G20-G25 -> -24375.9 | H28: =H16+H17-H20-H25 -> -19836.064 | I28: =I16+I17-I20-I25 -> 63764.344 | J28: =J16+J17-J20-J25 -> 234060.79 | K28: =K16+K17-K20-K25 -> 228532.32 | L28: =L16+L17-L20-L25 -> 265076.23 | M28: =M16+M17-M20-M25 -> 271630.8
A30: 잔존가치(Terminal Value) | F30: =N31 -> 4088313.1
A31: 영구성장률(g) | F31: 0.03 | N31: =(M28*(1+F31))/(F32-F31) -> 4088313.1
A32: WACC(Wacc sheet 참고) | F32: =WACC!E16 -> 0.098434027
A33: 현재가치 계수 | I33: =1/(1+$F$32)^I34 -> 0.91038695 | J33: =1/(1+$F$32)^J34 -> 0.82880439 | K33: =1/(1+$F$32)^K34 -> 0.7545327 | L33: =1/(1+$F$32)^L34 -> 0.68691672 | M33: =1/(1+$F$32)^M34 -> 0.62536002
A34: 연도 | I34: 1 | J34: 2 | K34: 3 | L34: 4 | M34: 5
A35: 추정연도(2026~2030) FCF의 현재가치 | I35: =I28*I33 -> 58050.227 | J35: =J28*J33 -> 193990.61 | K35: =K28*K33 -> 172435.1 | L35: =L28*L33 -> 182085.29 | M35: =M28*M33 -> 169867.04
A36: 추정연도 FCF의 현재가치의 합 | F36: =SUM(H35:M35) -> 776428.28
A37: 잔존가치(Terminal Value)의 현재가치 | F37: =F30*M33 -> 2556667.5
A38: 기업가치(EV) | F38: =F36+F37 -> 3333095.8
A39: (+) 비영업용 자산 가치 | F39: 103519
A40: (-) 타인자본가치 (순차입금) | F40: 287909
A41: 보통주 자기자본의 가치(주주가치) | F41: =F38+F39-F40 -> 3148705.8
A42: (÷) 발행주식수 | F42: =WACC!E29 -> 38366816
A44: 목표 가격(Target Price,원) | F44: =F41*1000000/F42 -> 82068.468
A45: 시가총액(백만원) | F45: =F41 -> 3148705.8

Sheet WACC
A1: 테크윙(089030.KQ)
A2: Weighted Average Cost of Capital
A3: (units in Millions KRW )
B5: WACC Calculation Table | G5: Description | K5: 이자부 부채 | L5: 24년말 | M5: 3Q25 | N5: 평균이자부부채 | O5: 3Q25 누적 이자비용 | P5: 이자율
B6: Wd(Debt/Capital) | E6: =E30 -> 0.14339891 | G6: 시가 총액 대비 차입금 비율 | K6: 단기차입금 | L6: 69135 | M6: 85500
B7: We(Equity/Capital) | E7: =1-E6 -> 0.85660109 | K7: 유동성장기차입금 | L7: 95718 | M7: 42181
B8: Rd(타인자본비용) | E8: =P10 -> 0.034899784 | K8: 장기차입금 | L8: 87726 | M8: 177236
B9: (1-t) | E9: 0.81 | G9: IS sheet 참고 | K9: 기타부채 | L9: 203 | M9: 165
B10: Rd*(1-t)*Wd | E10: =E8*E9*E6 -> 0.0040537187 | K10: 합계 | L10: =SUM(L6:L9) -> 252782 | M10: =SUM(M6:M9) -> 305082 | N10: =AVERAGE(L10:M10) -> 278932 | O10: 7301 | P10: =O10/N10*12/9 -> 0.034899784
B11: 무위험수익률(Rf) | E11: 0.0308 | G11: 국고채 5년 수익률(2025.11.19)
B12: 시장위험프리미엄(MRP, Rm-Rf) | E12: 0.07 | G12: 한공회 리스크프리미엄(25.06.10)
B13: β(조정베타) | E13: =1.201*2/3+1*1/3 -> 1.134 | G13: 5년베타 1.201
B14: Re(자기자본비용) | E14: =E11+E13*(E12) -> 0.11018 | G14: Re=Rf+β(Rm-Rf)
B15: Re*We | E15: =E14*E7 -> 0.094380308
B16: WACC | E16: =E15+E10 -> 0.098434027
B19: Wd(Debt/Capital)
B20: FY25 차입금 시가/자본 시가
B21: 차입금 | E21: 금액(백만원)
B22: 단기차입금 | E22: 85500
B23: 유동성장기차입금 | E23: 42181
B24: 장기차입금 | E24: 177236
B25: 기타부채 | E25: 165
B26: 합계 | E26: =SUM(E22:E25) -> 305082
B27: 시가총액(백만원) | E27: =E28*E29*0.000001 -> 1822423.8
B28: 주가(원) | E28: 47500
B29: 발행주식수 | E29: 38366816
B30: Wd | E30: =E26/(E26+E27) -> 0.14339891

Sheet Change in NWC
A1: 테크윙(089030.KQ)
A2: Change in NWC
A3: (units in Millions KRW )
A5: Historical | G5: Pro Forma | N5: Description
D6: 2022A | E6: 2023A | F6: 2024A | G6: 2025E | H6: 2026E | I6: 2027E | J6: 2028E | K6: 2029E | L6: 2030E
A7: 매출채권 | D7: 53299 | E7: 39462 | F7: 43796 | G7: =G25/$B$24*G19 -> 56793.526 | H7: =H25/$B$24*H19 -> 236304.01 | I7: =I25/$B$24*I19 -> 245762.72 | J7: =J25/$B$24*J19 -> 275638.75 | K7: =K25/$B$24*K19 -> 282317.26 | L7: =L25/$B$24*L19 -> 294941.97 | N7: 매출채권회전일로 추정
A8: 재고자산 | D8: 86833 | E8: 81331 | F8: 79266 | G8: =AVERAGE(D8:F8) -> 82476.667 | H8: =AVERAGE(E8:G8) -> 81024.556 | I8: =AVERAGE(F8:H8) -> 80922.407 | J8: =AVERAGE(G8:I8) -> 81474.543 | K8: =AVERAGE(H8:J8) -> 81140.502 | L8: =AVERAGE(I8:K8) -> 81179.151 | N8: 동사는 주문제작 방식을 이용하기에 재고자산 잔액 변동이 크게 없을것이라 판단. 직전 3개년 average flat
A9: 기타 유동자산 | D9: 2185 | E9: 1940 | F9: 1536 | G9: =AVERAGE(D9:F9) -> 1887 | H9: =AVERAGE(E9:G9) -> 1787.6667 | I9: =AVERAGE(F9:H9) -> 1736.8889 | J9: =AVERAGE(G9:I9) -> 1803.8519 | K9: =AVERAGE(H9:J9) -> 1776.1358 | L9: =AVERAGE(I9:K9) -> 1772.2922 | N9: 직전 3개년 이동평균 적용.
A10: 영업용 유동자산 | D10: =SUM(D7:D9) -> 142317 | E10: =SUM(E7:E9) -> 122733 | F10: =SUM(F7:F9) -> 124598 | G10: =SUM(G7:G9) -> 141157.19 | H10: =SUM(H7:H9) -> 319116.23 | I10: =SUM(I7:I9) -> 328422.02 | J10: =SUM(J7:J9) -> 358917.14 | K10: =SUM(K7:K9) -> 365233.9 | L10: =SUM(L7:L9) -> 377893.42
A12: 매입채무 | D12: 12617 | E12: 14156 | F12: 14953 | G12: =G30/$B$29*G20 -> 12316.805 | H12: =H30/$B$29*H20 -> 56597.392 | I12: =I30/$B$29*I20 -> 56104.888 | J12: =J30/$B$29*J20 -> 59079.68 | K12: =K30/$B$29*K20 -> 63135.953 | L12: =L30/$B$29*L20 -> 65458.84 | N12: 매입채무회전일로 추정
A13: 기타 유동부채 | D13: 4140 | E13: 2859 | F13: 2743 | G13: =AVERAGE(D13:F13) -> 3247.3333 | H13: =AVERAGE(E13:G13) -> 2949.7778 | I13: =AVERAGE(F13:H13) -> 2980.037 | J13: =AVERAGE(G13:I13) -> 3059.0494 | K13: =AVERAGE(H13:J13) -> 2996.2881 | L13: =AVERAGE(I13:K13) -> 3011.7915 | N13: 직전 3개년 이동평균 적용.
A14: 영업용 유동부채 | D14: =SUM(D12:D13) -> 16757 | E14: =SUM(E12:E13) -> 17015 | F14: =SUM(F12:F13) -> 17696 | G14: =SUM(G12:G13) -> 15564.138 | H14: =SUM(H12:H13) -> 59547.169 | I14: =SUM(I12:I13) -> 59084.925 | J14: =SUM(J12:J13) -> 62138.73 | K14: =SUM(K12:K13) -> 66132.241 | L14: =SUM(L12:L13) -> 68470.631
A15: 순운전자본 | D15: =D10-D14 -> 125560 | E15: =E10-E14 -> 105718 | F15: =F10-F14 -> 106902 | G15: =G10-G14 -> 125593.05 | H15: =H10-H14 -> 259569.06 | I15: =I10-I14 -> 269337.09 | J15: =J10-J14 -> 296778.41 | K15: =K10-K14 -> 299101.66 | L15: =L10-L14 -> 309422.78
A17: 순운전자본의 증감 | E17: =E15-D15 -> -19842 | F17: =F15-E15 -> 1184 | G17: =G15-F15 -> 18691.054 | H17: =H15-G15 -> 133976.01 | I17: =I15-H15 -> 9768.0305 | J17: =J15-I15 -> 27441.32 | K17: =K15-J15 -> 2323.242 | L17: =L15-K15 -> 10321.127
A18: IS Data
A19: 매출액 | D19: ='DCF>>>'!E6 -> 267491 | E19: ='DCF>>>'!F6 -> 133604 | F19: ='DCF>>>'!G6 -> 185507 | G19: ='DCF>>>'!H6 -> 175561.7 | H19: ='DCF>>>'!I6 -> 792034.67 | I19: ='DCF>>>'!J6 -> 871238.14 | J19: ='DCF>>>'!K6 -> 914800.04 | K19: ='DCF>>>'!L6 -> 960540.04 | L19: ='DCF>>>'!M6 -> 1008567
A20: 매출원가 | D20: ='DCF>>>'!E8 -> 158044 | E20: ='DCF>>>'!F8 -> 84056 | F20: ='DCF>>>'!G8 -> 114022 | G20: ='DCF>>>'!H8 -> 100754.93 | H20: ='DCF>>>'!I8 -> 414989.09 | I20: ='DCF>>>'!J8 -> 435738.55 | J20: ='DCF>>>'!K8 -> 457525.48 | K20: ='DCF>>>'!L8 -> 480401.75 | L20: ='DCF>>>'!M8 -> 504421.84
A22: Assumptions
A23: 순운전자본(Net Working Capital) 항목
A24: 영업일: | B24: 365
A25: 매출채권회전일수(DSO) | D25: =(AVERAGE(D7)/E19*$B$24) -> 145.61042 | E25: =(AVERAGE(D7:E7)/E19*$B$24) -> 126.7094 | F25: =(AVERAGE(E7:F7)/F19*$B$24) -> 81.908419 | G25: =AVERAGE(D25:F25) -> 118.07608 | H25: =AVERAGE(E25:G25) -> 108.89797 | I25: =AVERAGE(F25:H25) -> 102.96082 | J25: =AVERAGE(G25:I25) -> 109.97829 | K25: =AVERAGE(H25:J25) -> 107.27903 | L25: =AVERAGE(I25:K25) -> 106.73938 | N25: 직전 3개년 이동평균
A28: 순운전자본(Net Working Capital) 항목
A29: 영업일: | B29: 365
A30: 매입채무회전일수(DPO) | D30: =AVERAGE(D12)/D20*$B$29 -> 29.138752 | E30: =AVERAGE(D12:E12)/E20*$B$29 -> 58.128777 | F30: =AVERAGE(E12:F12)/F20*$B$29 -> 46.590943 | G30: =AVERAGE(D30:F30) -> 44.619491 | H30: =AVERAGE(E30:G30) -> 49.779737 | I30: =AVERAGE(F30:H30) -> 46.996724 | J30: =AVERAGE(G30:I30) -> 47.131984 | K30: =AVERAGE(H30:J30) -> 47.969482 | L30: =AVERAGE(I30:K30) -> 47.366063 | N30: 직전 3개년 이동평균
A32: Ratio
A33: 매출채권/매출 | D33: =D7/D19 -> 0.1992553 | E33: =E7/E19 -> 0.29536541 | F33: =F7/F19 -> 0.23608813 | G33: =G7/G19 -> 0.32349611 | H33: =H7/H19 -> 0.29835059 | I33: =I7/I19 -> 0.28208444 | J33: =J7/J19 -> 0.30131038 | K33: =K7/K19 -> 0.29391514 | L33: =L7/L19 -> 0.29243665
A34: 매출채권/매출원가 | D34: =D7/D20 -> 0.33724153 | E34: =E7/E20 -> 0.46947273 | F34: =F7/F20 -> 0.38410131 | G34: =G7/G20 -> 0.56367985 | H34: =H7/H20 -> 0.56942222 | I34: =I7/I20 -> 0.56401419 | J34: =J7/J20 -> 0.60245552 | K34: =K7/K20 -> 0.58766909 | L34: =L7/L20 -> 0.58471293
A35: 순운전자본/매출 | D35: =D15/D19 -> 0.46939897 | E35: =E15/E19 -> 0.7912787 | F35: =F15/F19 -> 0.57626936 | G35: =G15/G19 -> 0.71537845 | H35: =H15/H19 -> 0.32772437 | I35: =I15/I19 -> 0.30914291 | J35: =J15/J19 -> 0.32441889 | K35: =K15/K19 -> 0.31138906 | L35: =L15/L19 -> 0.30679446
A36: 영업용유동자산/영업용유동부채 | D36: =D10/D14 -> 8.492988 | E36: =E10/E14 -> 7.2132236 | F36: =F10/F14 -> 7.0410262 | G36: =G10/G14 -> 9.0693869 | H36: =H10/H14 -> 5.3590496 | I36: =I10/I14 -> 5.558474 | J36: =J10/J14 -> 5.7760618 | K36: =K10/K14 -> 5.5227812 | L36: =L10/L14 -> 5.5190584
A37: 순운전자본/총자산 | D37: =D15/D42 -> 0.25716229 | E37: =E15/E42 -> 0.21757734 | F37: =F15/F42 -> 0.21117654 | G37: =G15/G42 -> 0.22467452 | H37: =H15/H42 -> 0.30182449 | I37: =I15/I42 -> 0.28471152 | J37: =J15/J42 -> 0.29878024 | K37: =K15/K42 -> 0.28678015 | L37: =L15/L42 -> 0.28254866
A40: 총자산 추정
A41: 총자산 회전율 | D41: =D43/D42 -> 0.54785439 | E41: =E43/E42 -> 0.27496928 | F41: =F43/F42 -> 0.36645457 | G41: =G43/G42 -> 0.31406386 | H41: =H43/H42 -> 0.92097054 | I41: =I43/I42 -> 0.92097054 | J41: =J43/J42 -> 0.92097054 | K41: =K43/K42 -> 0.92097054 | L41: =L43/L42 -> 0.92097054
A42: 총자산 | D42: 488252 | E42: 485887 | F42: 506221 | G42: 559000 | H42: 860000 | I42: =H42*1.1 -> 946000 | J42: =I42*1.05 -> 993300 | K42: =J42*1.05 -> 1042965 | L42: =K42*1.05 -> 1095113.3
A43: 매출액 | D43: =D19 -> 267491 | E43: =E19 -> 133604 | F43: =F19 -> 185507 | G43: =G19 -> 175561.7 | H43: =H19 -> 792034.67 | I43: =I19 -> 871238.14 | J43: =J19 -> 914800.04 | K43: =K19 -> 960540.04 | L43: =L19 -> 1008567

Sheet FA Schedule
A1: 테크윙(089030.KQ)
A2: FA Schedule
A3: (units in Millions KRW )
A5: Historical | G5: Pro Forma | N5: Description
D6: 2022A | E6: 2023A | F6: 2024A | G6: 2025E | H6: 2026E | I6: 2027E | J6: 2028E | K6: 2029E | L6: 2030E
A7: 유형자산 | D7: 242657 | E7: 270619 | F7: 232023 | G7: =G17 -> 233189.32 | H7: =H17 -> 219219.96 | I7: =I17 -> 203297.02 | J7: =J17 -> 188060.41 | K7: =K17 -> 175418 | L7: =L17 -> 162836.49
A8: 무형자산 | D8: 18200 | E8: 20950 | F8: 11736 | G8: 44101 | H8: 45830 | I8: =I28 -> 5834.2273 | J8: =J28 -> 4555.3381 | K8: =K28 -> 3509.4401 | L8: =L28 -> 2696.7893
A9: 기타 | D9: =D10-SUM(D7:D8) -> 46117 | E9: =E10-SUM(E7:E8) -> 50524 | F9: =F10-SUM(F7:F8) -> 106386 | G9: =AVERAGE(D9:F9) -> 67675.667 | H9: =AVERAGE(E9:G9) -> 74861.889 | I9: =AVERAGE(F9:H9) -> 82974.519 | J9: =AVERAGE(G9:I9) -> 75170.691 | K9: =AVERAGE(H9:J9) -> 77669.033 | L9: =AVERAGE(I9:K9) -> 78604.748 | N9: 직전 3개년 이동 평균 적용.
A10: 비유동자산 | D10: 306974 | E10: 342093 | F10: 350145 | G10: 53132 | H10: 61629 | I10: =SUM(I7:I9) -> 292105.77 | J10: =SUM(J7:J9) -> 267786.44 | K10: =SUM(K7:K9) -> 256596.47 | L10: =SUM(L7:L9) -> 244138.03
A12: 유형자산 Schedule
A13: 기초 유형자산 | D13: 241596 | E13: =D17 -> 242657 | F13: =E17 -> 270619 | G13: =F17 -> 232023 | H13: =G17 -> 233189.32 | I13: =H17 -> 219219.96 | J13: =I17 -> 203297.02 | K13: =J17 -> 188060.41 | L13: =K17 -> 175418
A14: Capex | D14: 9594 | E14: 44070 | F14: 52218 | G14: =G13*G19 -> 32041.056 | H14: =G15 -> 13488 | I14: =H15 -> 9349.3683 | J14: =I15 -> 9572.2362 | K14: =J15 -> 9615.3135 | L14: =K15 -> 8215.4396
A15: 감가상각비 | D15: 7601 | E15: 7129 | F15: 8868 | G15: =10116*4/3 -> 13488 | H15: =H13*H20 -> 9349.3683 | I15: =I13*I20 -> 9572.2362 | J15: =J13*J20 -> 9615.3135 | K15: =K13*K20 -> 8215.4396 | L15: =L13*L20 -> 7873.1671 | N15: 4Q25의 경우 앞선 3개분기의 감가상각비 지출액이 큰 변화가 없기에 이를 고려하여 반영함.
A16: 기타증감 | D16: =D17-SUM(D13:D15) -> -16134 | E16: =E17-SUM(E13:E15) -> -23237 | F16: =F17-SUM(F13:F15) -> -99682 | G16: =G13*G21 -> -17386.74 | H16: =H13*H21 -> -18107.987 | I16: =I13*I21 -> -15700.071 | J16: =J13*J21 -> -15193.531 | K16: =K13*K21 -> -14042.29 | L16: =L13*L21 -> -12923.778 | N16: 24년의 경우 일부 유형자산이 투자부동산으로 계정 대체 되었음. 이를 이상치로 판단하여 81,879로 제외한 금액 비율 산정 후 이동평균
A17: 기말 유형자산 | D17: =D7 -> 242657 | E17: =E7 -> 270619 | F17: =F7 -> 232023 | G17: =G13+G14-G15+G16 -> 233189.32 | H17: =H13+H14-H15+H16 -> 219219.96 | I17: =I13+I14-I15+I16 -> 203297.02 | J17: =J13+J14-J15+J16 -> 188060.41 | K17: =K13+K14-K15+K16 -> 175418 | L17: =L13+L14-L15+L16 -> 162836.49
A19: 기초 유형자산 대비 Capex | D19: =D14/D13 -> 0.039710922 | E19: =E14/E13 -> 0.18161438 | F19: =F14/F13 -> 0.19295763 | G19: =AVERAGE(D19:F19) -> 0.13809431 | H19: =H14/H13 -> 0.057841415 | I19: =I14/I13 -> 0.042648344 | J19: =J14/J13 -> 0.04708498 | K19: =K14/K13 -> 0.051128854 | L19: =L14/L13 -> 0.046833504 | N19: 23,'24,'25년 CAPA증설에 따라 CAPEX지출 높음. 이후 CAPA증설 일정 없기에 전기 감가상각비 만큼 지출된다 가정
A20: 기초 유형자산 대비 감가상각비 | D20: =D15/D13 -> 0.031461614 | E20: =E15/E13 -> 0.029378918 | F20: =F15/F13 -> 0.032769318 | G20: =G15/G13 -> 0.058132168 | H20: =AVERAGE(E20:G20) -> 0.040093468 | I20: =AVERAGE(F20:H20) -> 0.043664984 | J20: =AVERAGE(G20:I20) -> 0.047296873 | K20: =AVERAGE(H20:J20) -> 0.043685109 | L20: =AVERAGE(I20:K20) -> 0.044882322 | N20: 직전 3개년 Average flat 적용.
A21: 기초 유형자산 대비 기타증감 | D21: =D16/D13 -> -0.066780907 | E21: =E16/E13 -> -0.095760683 | F21: =-(98729-81879)/F13 -> -0.06226466 | G21: =AVERAGE(D21:F21) -> -0.074935417 | H21: =AVERAGE(E21:G21) -> -0.077653586 | I21: =AVERAGE(F21:H21) -> -0.071617888 | J21: =AVERAGE(G21:I21) -> -0.07473563 | K21: =AVERAGE(H21:J21) -> -0.074669035 | L21: =AVERAGE(I21:K21) -> -0.073674184 | N21: 직전 3개년 Average flat 적용.
A23: 무형자산 Schedule
A24: 기초 무형자산 | D24: 19902 | E24: =D28 -> 18200 | F24: =E28 -> 20950 | G24: =F28 -> 11736 | H24: =G28 -> 10075.075 | I24: =H28 -> 7713.3937 | J24: =I28 -> 5834.2273 | K24: =J28 -> 4555.3381 | L24: =K28 -> 3509.4401
A25: Capex | D25: =4564 -> 4564 | E25: 9087 | F25: 1792 | G25: =F26 -> 2988 | H25: =G26 -> 1902.2857 | I25: =H26 -> 1578.2096 | J25: =I26 -> 1186.2172 | K25: =J26 -> 918.93245 | L25: =K26 -> 710.53977
A26: 상각비 | D26: 3551 | E26: 3007 | F26: 2988 | G26: =G24*G31 -> 1902.2857 | H26: =H24*H31 -> 1578.2096 | I26: =I24*I31 -> 1186.2172 | J26: =J24*J31 -> 918.93245 | K26: =K24*K31 -> 710.53977 | L26: =L24*L31 -> 546.62268
A27: 기타증감 | D27: =D28-SUM(D24:D26) -> -9817 | E27: =E28-SUM(E24:E26) -> -9344 | F27: =F28-SUM(F24:F26) -> -13994 | G27: =G24*G32 -> -6551.2111 | H27: =H24*H32 -> -5842.1762 | I27: =I24*I32 -> -4643.5933 | J27: =J24*J32 -> -3384.0389 | K27: =K24*K32 -> -2675.3702 | L27: =L24*L32 -> -2069.8132
A28: 기말 무형자산 | D28: =D8 -> 18200 | E28: =E8 -> 20950 | F28: =F8 -> 11736 | G28: =SUM(G24:G27) -> 10075.075 | H28: =SUM(H24:H27) -> 7713.3937 | I28: =SUM(I24:I27) -> 5834.2273 | J28: =SUM(J24:J27) -> 4555.3381 | K28: =SUM(K24:K27) -> 3509.4401 | L28: =SUM(L24:L27) -> 2696.7893
A30: 기초 무형자산 대비 Capex | D30: =D25/D24 -> 0.22932369 | E30: =E25/E24 -> 0.49928571 | F30: =F25/F24 -> 0.085536993 | G30: =G25/G24 -> 0.25460123 | H30: =H25/H24 -> 0.18881108 | I30: =I25/I24 -> 0.20460639 | J30: =J25/J24 -> 0.20332036 | K30: =K25/K24 -> 0.20172651 | L30: =L25/L24 -> 0.20246528 | N30: 전기 상각비만큼 CAPEX 지출한다 가정
A31: 기초 무형자산 대비 상각비 | D31: =D26/D24 -> 0.17842428 | E31: =E26/E24 -> 0.16521978 | F31: =F26/F24 -> 0.1426253 | G31: =AVERAGE(D31:F31) -> 0.16208979 | H31: =AVERAGE(E31:G31) -> 0.15664495 | I31: =AVERAGE(F31:H31) -> 0.15378668 | J31: =AVERAGE(G31:I31) -> 0.15750714 | K31: =AVERAGE(H31:J31) -> 0.15597959 | L31: =AVERAGE(I31:K31) -> 0.1557578 | N31: 직전 3개년 Average flat 적용.
A32: 기초 무형자산 대비 기타증감 | D32: =D27/D24 -> -0.49326701 | E32: =E27/E24 -> -0.51340659 | F32: =F27/F24 -> -0.66797136 | G32: =AVERAGE(D32:F32) -> -0.55821499 | H32: =AVERAGE(E32:G32) -> -0.57986431 | I32: =AVERAGE(F32:H32) -> -0.60201689 | J32: =AVERAGE(G32:I32) -> -0.58003206 | K32: =AVERAGE(H32:J32) -> -0.58730442 | L32: =AVERAGE(I32:K32) -> -0.58978446 | N32: 직전 3개년 Average flat 적용.
A34: Capex / D&A
A35: Total Capex | D35: =D14+D25 -> 14158 | E35: =E14+E25 -> 53157 | F35: =F14+F25 -> 54010 | G35: =G14+G25 -> 35029.056 | H35: =H14+H25 -> 15390.286 | I35: =I14+I25 -> 10927.578 | J35: =J14+J25 -> 10758.453 | K35: =K14+K25 -> 10534.246 | L35: =L14+L25 -> 8925.9794
A36: of revenue (%) | D36: 0.052928884 | E36: 0.39786982 | F36: 0.29114804 | G36: 0.20361848 | H36: 0.057304651 | I36: 0.055696285 | J36: 0.054755468 | K36: 0.058216414 | L36: 0.059972834
A37: Total D&A | D37: =D15+D26 -> 11152 | E37: =E15+E26 -> 10136 | F37: =F15+F26 -> 11856 | G37: =G15+G26 -> 15390.286 | H37: =H15+H26 -> 10927.578 | I37: =I15+I26 -> 10758.453 | J37: =J15+J26 -> 10534.246 | K37: =K15+K26 -> 8925.9794 | L37: =L15+L26 -> 8419.7898
A38: of revenue (%) | D38: ='FA Schedule'!D37/'DCF>>>'!E6 -> 0.041691122 | E38: ='FA Schedule'!E37/'DCF>>>'!F6 -> 0.075865992 | F38: ='FA Schedule'!F37/'DCF>>>'!G6 -> 0.063911335 | G38: ='FA Schedule'!G37/'DCF>>>'!H6 -> 0.087663118 | H38: ='FA Schedule'!H37/'DCF>>>'!I6 -> 0.013796843 | I38: ='FA Schedule'!I37/'DCF>>>'!J6 -> 0.012348465 | J38: ='FA Schedule'!J37/'DCF>>>'!K6 -> 0.011515354 | K38: ='FA Schedule'!K37/'DCF>>>'!L6 -> 0.0092926676 | L38: ='FA Schedule'!L37/'DCF>>>'!M6 -> 0.0083482698

Sheet 비용 추정
A1: 테크윙(089030.KQ)
A2: Assumption Sheet
A3: (units in Millions KRW )
B5: 비용추정 | P5: 비용추정
B6: (단위: 백만원) | C6: 1Q24 | D6: 2Q24 | E6: 3Q24 | F6: 4Q24 | G6: 1Q25 | H6: 2Q25 | I6: 3Q25 | J6: 4Q25 | K6: 1Q26 | L6: 2Q26 | M6: 3Q26 | N6: 4Q26 | P6: (단위: 원) | Q6: 2024A | R6: 2025E | S6: 2026E
B7: 매출액 | C7: ='IS(Quaterly)'!H10 -> 40339.439 | D7: ='IS(Quaterly)'!I10 -> 50769.762 | E7: ='IS(Quaterly)'!J10 -> 46721.567 | F7: ='IS(Quaterly)'!K10 -> 47676.403 | G7: ='IS(Quaterly)'!L10 -> 34587.215 | H7: ='IS(Quaterly)'!M10 -> 48893.653 | I7: 41766 | J7: ='매출 추정'!F6 -> 50314.986 | K7: ='매출 추정'!G6 -> 143990.83 | L7: ='매출 추정'!H6 -> 219447.31 | M7: ='매출 추정'!I6 -> 212606.61 | N7: ='매출 추정'!J6 -> 215989.92 | P7: 매출액 | Q7: =SUM(C7:F7) -> 185507.17 | R7: =SUM(G7:J7) -> 175561.85 | S7: =SUM(K7:N7) -> 792034.67
B8: % YoY | G8: =G7/C7-1 -> -0.14259553 | H8: =H7/D7-1 -> -0.036953291 | I8: =I7/E7-1 -> -0.10606594 | J8: =J7/F7-1 -> 0.055343587 | K8: =K7/G7-1 -> 3.1631231 | L8: =L7/H7-1 -> 3.4882577 | M8: =M7/I7-1 -> 4.090423 | N8: =N7/J7-1 -> 3.2927552 | P8: % YoY | R8: =R7/Q7-1 -> -0.053611497 | S8: =S7/R7-1 -> 3.511428
B9: 큐브 프로버 | C9: 0 | D9: 0 | E9: 0 | F9: 0 | G9: ='매출 추정'!C8 -> 3000 | H9: ='매출 추정'!D8 -> 10000 | I9: ='매출 추정'!E8 -> 5000 | J9: ='매출 추정'!F8 -> 8000 | K9: ='매출 추정'!G8 -> 103950 | L9: ='매출 추정'!H8 -> 173250 | M9: ='매출 추정'!I8 -> 173250 | N9: ='매출 추정'!J8 -> 173250 | P9: 큐브 프로버 | Q9: =SUM(C9:F9) -> 0 | R9: =SUM(G9:J9) -> 26000 | S9: =SUM(K9:N9) -> 623700
B10: % of sales | C10: =C9/C7 -> 0 | D10: =D9/D7 -> 0 | E10: =E9/E7 -> 0 | F10: =F9/F7 -> 0 | G10: =G9/G7 -> 0.086737253 | H10: =H9/H7 -> 0.20452553 | I10: =I9/I7 -> 0.1197146 | J10: =J9/J7 -> 0.15899835 | ... N10: =N9/N7 -> 0.80212078 | P10: % of sales | Q10: =Q9/Q7 -> 0 | R10: =R9/R7 -> 0.14809595 | S10: =S9/S7 -> 0.78746553
B11: 핸들러 | C11: 18327 | D11: 22323 | E11: 21025 | F11: 20491 | G11: ='매출 추정'!C10 -> 9922 | H11: ='매출 추정'!D10 -> 12868 | I11: ='매출 추정'!E10 -> 9038 | J11: ='매출 추정'!F10 -> 14276.143 | K11: ='매출 추정'!G10 -> 11210.702 | L11: ='매출 추정'!H10 -> 18433.584 | M11: ='매출 추정'!I10 -> 11415.143 | N11: ='매출 추정'!J10 -> 14561.476 | P11: 핸들러 | Q11: =SUM(C11:F11) -> 82166 | R11: =SUM(G11:J11) -> 46104.143 | S11: =SUM(K11:N11) -> 55620.905
B12: % of sales | C12: =C11/C7 -> 0.45431966 | D12: =D11/D7 -> 0.43969085 | E12: =E11/E7 -> 0.45000631 | F12: =F11/F7 -> 0.42979333 | G12: =G11/G7 -> 0.28686901 | H12: =H11/H7 -> 0.26318345 | I12: =I11/I7 -> 0.21639611 | J12: =J11/J7 -> 0.2837354 | ... N12: =N11/N7 -> 0.067417389 | P12: % of sales | Q12: =Q11/Q7 -> 0.44292627 | R12: =R11/R7 -> 0.26260911 | S12: =S11/S7 -> 0.070225341
B13: C.O.K | C13: 11390 | D13: 13212 | E13: 12148 | F13: 11435 | G13: ='매출 추정'!C12 -> 12512 | H13: ='매출 추정'!D12 -> 12688 | I13: ='매출 추정'!E12 -> 19189 | J13: ='매출 추정'!F12 -> 19500 | K13: ='매출 추정'!G12 -> 18691.684 | L13: ='매출 추정'!H12 -> 18691.684 | M13: ='매출 추정'!I12 -> 18691.684 | N13: ='매출 추정'!J12 -> 18691.684 | P13: C.O.K | Q13: =SUM(C13:F13) -> 48185 | R13: =SUM(G13:J13) -> 63889 | S13: =SUM(K13:N13) -> 74766.737
B14: % of sales | C14: =C13/C7 -> 0.28235395 | D14: =D13/D7 -> 0.26023364 | E14: =E13/E7 -> 0.2600084 | F14: =F13/F7 -> 0.23984611 | G14: =G13/G7 -> 0.36175217 | H14: =H13/H7 -> 0.25950199 | I14: =I13/I7 -> 0.45944069 | J14: =J13/J7 -> 0.38755849 | ... N14: =N13/N7 -> 0.086539615 | P14: % of sales | Q14: =Q13/Q7 -> 0.25974737 | R14: =R13/R7 -> 0.36391163 | S14: =S13/S7 -> 0.094398314
B15: 기타 | C15: 10622 | D15: 15235 | E15: 13549 | F15: 15751 | G15: ='매출 추정'!C14 -> 9153.2149 | H15: ='매출 추정'!D14 -> 13337.653 | I15: ='매출 추정'!E14 -> 8538.8437 | J15: ='매출 추정'!F14 -> 8538.8437 | K15: ='매출 추정'!G14 -> 10138.447 | L15: ='매출 추정'!H14 -> 9072.0447 | M15: ='매출 추정'!I14 -> 9249.7783 | N15: ='매출 추정'!J14 -> 9486.7566 | P15: 기타 | Q15: =SUM(C15:F15) -> 55157 | R15: =SUM(G15:J15) -> 39568.555 | S15: =SUM(K15:N15) -> 37947.026
B16: % of sales | C16: =C15/C7 -> 0.26331551 | D16: =D15/D7 -> 0.30008019 | E16: =E15/E7 -> 0.28999455 | F16: =F15/F7 -> 0.33037308 | G16: =G15/G7 -> 0.26464157 | H16: =H15/H7 -> 0.27278904 | I16: =I15/I7 -> 0.20444485 | J16: =J15/J7 -> 0.16970776 | ... N16: =N15/N7 -> 0.04392222 | P16: % of sales | Q16: =Q15/Q7 -> 0.29733082 | R16: =R15/R7 -> 0.22538242 | S16: =S15/S7 -> 0.047910815
B17: 매출원가 | C17: ='IS(Quaterly)'!H13 -> 24298.609 | D17: ='IS(Quaterly)'!I13 -> 30584.084 | E17: ='IS(Quaterly)'!J13 -> 27986.516 | F17: ='IS(Quaterly)'!K13 -> 31152.326 | G17: ='IS(Quaterly)'!L13 -> 19942.025 | H17: ='IS(Quaterly)'!M13 -> 30065.138 | I17: ='IS(Quaterly)'!N13 -> 22406.702 | J17: =SUM(J19,J21,J23,J25) -> 28341.068 | K17: =SUM(K19,K21,K23,K25) -> 75986.5 | L17: =SUM(L19,L21,L23,L25) -> 115125.19 | M17: =SUM(M19,M21,M23,M25) -> 110887.51 | N17: =SUM(N19,N21,N23,N25) -> 112989.9 | P17: 매출원가 | Q17: =SUM(C17:F17) -> 114021.53 | R17: =SUM(G17:J17) -> 100754.93 | S17: =SUM(K17:N17) -> 414989.09
B18: % of sales | C18: =C17/C7 -> 0.60235367 | D18: =D17/D7 -> 0.60240747 | E18: =E17/E7 -> 0.59900636 | F18: =F17/F7 -> 0.65341183 | G18: =G17/G7 -> 0.57657217 | H18: =H17/H7 -> 0.61490881 | I18: =I17/I7 -> 0.53648188 | J18: =J17/J7 -> 0.5632729 | ... N18: =N17/N7 -> 0.5231258 | P18: % of sales | Q18: =Q17/Q7 -> 0.61464758 | R18: =R17/R7 -> 0.57389992 | S18: =S17/S7 -> 0.52395319
B19: 큐브 프로버 | C19: 0 | D19: 0 | E19: 0 | F19: 0 | G19: =G9*0.51 -> 1530 | H19: =H9*0.51 -> 5100 | I19: =I9*0.51 -> 2550 | J19: =J9*0.51 -> 4080 | K19: =K9*0.51 -> 53014.5 | L19: =L9*0.51 -> 88357.5 | M19: =M9*0.51 -> 88357.5 | N19: =N9*0.51 -> 88357.5 | P19: 큐브 프로버 | Q19: =SUM(C19:F19) -> 0 | R19: =SUM(G19:J19) -> 13260 | S19: =SUM(K19:N19) -> 318087 | V19: IR 자료를 토대로 매출원가를 역산하였음.
B20: % of cogs | C20: =C19/C17 -> 0 | D20: =D19/D17 -> 0 | E20: =E19/E17 -> 0 | F20: =F19/F17 -> 0 | G20: =G19/G17 -> 0.076722397 | H20: =H19/H17 -> 0.16963169 | I20: =I19/I17 -> 0.11380523 | J20: =J19/J17 -> 0.1439607 | ... N20: =N19/N17 -> 0.78199468 | P20: % of cogs | Q20: =Q19/Q17 -> 0 | R20: =R19/R17 -> 0.13160646 | S20: =S19/S17 -> 0.76649484
B21: 핸들러 | C21: =C11*0.62 -> 11362.74 | D21: =D11*0.62 -> 13840.26 | E21: =E11*0.62 -> 13035.5 | F21: =F11*0.62 -> 12704.42 | G21: =G11*0.62 -> 6151.64 | H21: =H11*0.62 -> 7978.16 | I21: =I11*0.62 -> 5603.56 | J21: =J11*0.62 -> 8851.2085 | ... N21: =N11*0.62 -> 9028.1153 | P21: 핸들러 | Q21: =SUM(C21:F21) -> 50942.92 | R21: =SUM(G21:J21) -> 28584.568 | S21: =SUM(K21:N21) -> 34484.961 | V21: IR 자료를 토대로 매출원가를 역산하였음.
B22: % of cogs | C22: =C21/C17 -> 0.46762924 | D22: =D21/D17 -> 0.45253145 | E22: =E21/E17 -> 0.46577788 | F22: =F21/F17 -> 0.4078161 | G22: =G21/G17 -> 0.30847619 | H22: =H21/H17 -> 0.2653625 | I22: =I21/I17 -> 0.2500841 | J22: =J21/J17 -> 0.31231033 | ... N22: =N21/N17 -> 0.079901968 | P22: % of cogs | Q22: =Q21/Q17 -> 0.44678332 | R22: =R21/R17 -> 0.28370391 | S22: =S21/S17 -> 0.083098476
B23: C.O.K | C23: =C13*0.51 -> 5808.9 | D23: =D13*0.51 -> 6738.12 | E23: =E13*0.51 -> 6195.48 | F23: =F13*0.51 -> 5831.85 | G23: =G13*0.51 -> 6381.12 | H23: =H13*0.51 -> 6470.88 | I23: =I13*0.51 -> 9786.39 | J23: =J13*0.51 -> 9945 | ... N23: =N13*0.51 -> 9532.759 | P23: C.O.K | Q23: =SUM(C23:F23) -> 24574.35 | R23: =SUM(G23:J23) -> 32583.39 | S23: =SUM(K23:N23) -> 38131.036 | V23: IR 자료를 토대로 매출원가를 역산하였음.
B24: % of cogs | C24: =C23/C17 -> 0.23906307 | D24: =D23/D17 -> 0.22031459 | E24: =E23/E17 -> 0.22137375 | F24: =F23/F17 -> 0.18720432 | G24: =G23/G17 -> 0.31998354 | H24: =H23/H17 -> 0.21522868 | I24: =I23/I17 -> 0.43676173 | J24: =J23/J17 -> 0.3509042 | ... N24: =N23/N17 -> 0.084368241 | P24: % of cogs | Q24: =Q23/Q17 -> 0.21552376 | R24: =R23/R17 -> 0.3233925 | S24: =S23/S17 -> 0.091884429
B25: 기타 | C25: =C15*0.64 -> 6798.08 | D25: =D15*0.64 -> 9750.4 | E25: =E15*0.64 -> 8671.36 | F25: =F15*0.64 -> 10080.64 | G25: =G15*0.64 -> 5858.0575 | H25: =H15*0.64 -> 8536.0977 | I25: =I15*0.64 -> 5464.86 | J25: =J15*0.64 -> 5464.86 | ... N25: =N15*0.64 -> 6071.5242 | P25: 기타 | Q25: =SUM(C25:F25) -> 35300.48 | R25: =SUM(G25:J25) -> 25323.875 | S25: =SUM(K25:N25) -> 24286.097 | V25: IR 자료를 토대로 매출원가를 역산하였음.
B26: % of cogs | C26: =C25/C17 -> 0.2797724 | D26: =D25/D17 -> 0.31880634 | E26: =E25/E17 -> 0.30984064 | F26: =F25/F17 -> 0.32359189 | G26: =G25/G17 -> 0.29375439 | H26: =H25/H17 -> 0.28392013 | I26: =I25/I17 -> 0.24389399 | J26: =J25/J17 -> 0.19282477 | ... N26: =N25/N17 -> 0.053735106 | P26: % of cogs | Q26: =Q25/Q17 -> 0.30959485 | R26: =R25/R17 -> 0.25134129 | S26: =S25/S17 -> 0.058522253
B27: 매출총이익 | C27: =C7-C17 -> 16040.83 | D27: =D7-D17 -> 20185.678 | E27: =E7-E17 -> 18735.051 | F27: =F7-F17 -> 16524.077 | G27: =G7-G17 -> 14645.189 | H27: =H7-H17 -> 18828.515 | I27: =I7-I17 -> 19359.298 | J27: =J7-J17 -> 21973.918 | ... N27: =N7-N17 -> 103000.02 | P27: 매출총이익 | Q27: =Q7-Q17 -> 71485.637 | R27: =R7-R17 -> 74806.92 | S27: =S7-S17 -> 377045.57 | AH27: 2022 | AI27: 2023 | AJ27: 2024
B28: GPM(%) | C28: =C27/C7 -> 0.39764633 | D28: =D27/D7 -> 0.39759253 | E28: =E27/E7 -> 0.40099364 | F28: =F27/F7 -> 0.34658817 | G28: =G27/G7 -> 0.42342783 | H28: =H27/H7 -> 0.38509119 | I28: =I27/I7 -> 0.46351812 | J28: =J27/J7 -> 0.4367271 | ... N28: =N27/N7 -> 0.4768742 | P28: GPM(%) | Q28: =Q27/Q7 -> 0.38535242 | R28: =R27/R7 -> 0.42610008 | S28: =S27/S7 -> 0.47604681 | U28: 25년 | V28: 26년 | AG28: 매출액 | AH28: 267491 | AI28: 133604 | AJ28: 185507
B29: 판매비와 관리비 | C29: =SUM(C31,C33,C35,C37,C39,C41,C43,C45,C47,C49,C51,C53,C55,C57) -> 10467 | D29: =SUM(D31,D33,D35,D37,D39,D41,D43,D45,D47,D49,D51,D53,D55,D57) -> 13010.248 | E29: =SUM(E31,E33,E35,E37,E39,E41,E43,E45,E47,E49,E51,E53,E55,E57) -> 12557.111 | F29: =SUM(F31,F33,F35,F37,F39,F41,F43,F45,F47,F49,F51,F53,F55,F57) -> 12037.136 | G29: =SUM(G31,G33,G35,G37,G39,G41,G43,G45,G47,G49,G51,G53,G55,G57) -> 13347.369 | H29: =SUM(H31,H33,H35,H37,H39,H41,H43,H45,H47,H49,H51,H53,H55,H57) -> 12624.412 | I29: =SUM(I31,I33,I35,I37,I39,I41,I43,I45,I47,I49,I51,I53,I55,I57) -> 12248 | J29: =SUM(J31,J33,J35,J37,J39,J41,J43,J45,J47,J49,J51,J53,J55,J57) -> 13792.022 | ... N29: =SUM(N31,N33,N35,N37,N39,N41,N43,N45,N47,N49,N51,N53,N55,N57) -> 33160.866 | P29: 판매비와 관리비 | Q29: =SUM(C29:F29) -> 48071.495 | R29: =SUM(G29:J29) -> 52011.803 | S29: =SUM(K29:N29) -> 124318.42 | U29: =(1+3.6%)^0.25/100 -> 0.01008881 | V29: =(1+3.9%)^0.25/100 -> 0.010096106 | AG29: 판매관리비 | AH29: =SUM(AH31,AH33,AH35,AH37,AH39,AH41,AH43,AH45,AH47,AH49,AH51,AH53,AH55,AH57,) -> 51773 | AI29: =SUM(AI31,AI33,AI35,AI37,AI39,AI41,AI43,AI45,AI47,AI49,AI51,AI53,AI55,AI57,) -> 46388 | AJ29: =SUM(AJ31,AJ33,AJ35,AJ37,AJ39,AJ41,AJ43,AJ45,AJ47,AJ49,AJ51,AJ53,AJ55,AJ57,) -> 48071
B30: % of sales | C30: =C29/C7 -> 0.25947312 | D30: =D29/D7 -> 0.25625978 | E30: =E29/E7 -> 0.26876477 | F30: =F29/F7 -> 0.25247576 | G30: =G29/G7 -> 0.38590471 | H30: =H29/H7 -> 0.25820145 | I30: =I29/I7 -> 0.29325289 | J30: =J29/J7 -> 0.2741136 | ... N30: =N29/N7 -> 0.15352969 | P30: % of sales | Q30: =Q29/Q7 -> 0.25913551 | R30: =R29/R7 -> 0.29625914 | S30: =S29/S7 -> 0.15696083
B31: 인건비 | C31: 4266 | D31: 5320 | E31: ='IS(Quaterly)'!J16 -> 4101.076 | F31: ='IS(Quaterly)'!K16 -> 4100.136 | G31: ='IS(Quaterly)'!L16 -> 4167.65 | H31: ='IS(Quaterly)'!M16 -> 4289.259 | I31: 3755 | J31: =$AD$31*J7 -> 4958.7355 | K31: =$AD$31*K7 -> 14190.851 | L31: =$AD$31*L7 -> 21627.377 | M31: =$AD$31*M7 -> 20953.199 | N31: =$AD$31*N7 -> 21286.638 | P31: 인건비 | Q31: =SUM(C31:F31) -> 17787.212 | R31: =SUM(G31:J31) -> 17170.645 | S31: =SUM(K31:N31) -> 78058.065 | V31: 매출액과 상관계수가 높기에 직전 3개년 매출액 대비 비율 average 하여 적용. | AD31: =AVERAGE(AH32:AJ32) -> 0.098553848 | AG31: 인건비 | AH31: 19491 | AI31: 16956 | AJ31: 17787
B32: % of sales | C32: =C31/C7 -> 0.10575259 | D32: =D31/D7 -> 0.10478678 | E32: =E31/E7 -> 0.087776936 | F32: =F31/F7 -> 0.085999273 | G32: =G31/G7 -> 0.12049684 | H32: =H31/H7 -> 0.087726295 | I32: =I31/I7 -> 0.089905665 | J32: =J31/J7 -> 0.098553848 | ... N32: =N31/N7 -> 0.098553848 | P32: % of sales | Q32: =Q31/Q7 -> 0.095884229 | R32: =R31/R7 -> 0.09780396 | S32: =S31/S7 -> 0.098553848 | AH32: =AH31/$AH$28 -> 0.072866003 | AI32: =AI31/$AI$28 -> 0.12691237 | AJ32: =AJ31/$AJ$28 -> 0.095883174
B33: 여비교통비 | C33: 309 | D33: 428 | E33: 394 | F33: 412 | G33: 301 | H33: 278 | I33: 329 | J33: =J7*$AD$33 -> 553.33879 | K33: =K7*$AD$33 -> 1583.5384 | L33: =L7*$AD$33 -> 2413.3707 | M33: =M7*$AD$33 -> 2338.14 | N33: =N7*$AD$33 -> 2375.348 | P33: 여비교통비 | Q33: =SUM(C33:F33) -> 1543 | R33: =SUM(G33:J33) -> 1461.3388 | S33: =SUM(K33:N33) -> 8710.397 | V33: 매출액과 상관계수가 높기에 직전 3개년 매출액 대비 비율 average 하여 적용. | AD33: =AVERAGE(AH34:AJ34) -> 0.010997495 | AG33: 여비교통비 | AH33: 3509 | AI33: 1544 | AJ33: 1543
B34: % of sales | C34: =C33/C7 -> 0.0076599975 | D34: =D33/D7 -> 0.0084302147 | E34: =E33/E7 -> 0.0084329363 | F34: =F33/F7 -> 0.0086415915 | G34: =G33/G7 -> 0.0087026377 | H34: =H33/H7 -> 0.0056858096 | I34: =I33/I7 -> 0.0078772207 | J34: =J33/J7 -> 0.010997495 | ... N34: =N33/N7 -> 0.010997495 | P34: % of sales | Q34: =Q33/Q7 -> 0.0083177378 | R34: =R33/R7 -> 0.0083237831 | S34: =S33/S7 -> 0.010997495 | AH34: =AH33/$AH$28 -> 0.013118198 | AI34: =AI33/$AI$28 -> 0.01155654 | AJ34: =AJ33/$AJ$28 -> 0.0083177454
B35: 대손상각비 | C35: -585 | D35: -398 | E35: 160 | F35: -1047 | G35: 367 | H35: -47 | I35: 1039 | J35: =AVERAGE(F35:I35) -> 78 | K35: =AVERAGE(G35:J35) -> 359.25 | L35: =AVERAGE(H35:K35) -> 357.3125 | M35: =AVERAGE(I35:L35) -> 458.39062 | N35: =AVERAGE(J35:M35) -> 313.23828 | P35: 대손상각비 | Q35: =SUM(C35:F35) -> -1870 | R35: =SUM(G35:J35) -> 1437 | S35: =SUM(K35:N35) -> 1488.1914 | V35: 직전 4Q Average Flat 적용함. | AD35: =AVERAGE(AH36:AJ36) -> 0.001393074 | AG35: 대손상각비 | AH35: 655 | AI35: 1578 | AJ35: -1870
B36: % of sales | C36: =C35/C7 -> -0.014501937 | D36: =D35/D7 -> -0.0078393118 | E36: =E35/E7 -> 0.0034245427 | F36: =F35/F7 -> -0.021960549 | G36: =G35/G7 -> 0.010610857 | H36: =H35/H7 -> -0.00096126997 | I36: =I35/I7 -> 0.024876694 | J36: =J35/J7 -> 0.0015502339 | ... N36: =N35/N7 -> 0.0014502449 | P36: % of sales | Q36: =Q35/Q7 -> -0.010080473 | R36: =R35/R7 -> 0.0081851494 | S36: =S35/S7 -> 0.0018789473 | AH36: =AH35/$AH$28 -> 0.0024486805 | AI36: =AI35/$AI$28 -> 0.011811024 | AJ36: =AJ35/$AJ$28 -> -0.010080482
B37: 감가상각비 | C37: 738 | D37: 843 | E37: 1226 | F37: 1275 | G37: 1639 | H37: 1664 | I37: 1746 | J37: =AVERAGE(F37:I37) -> 1581 | K37: =AVERAGE(G37:J37) -> 1657.5 | L37: =AVERAGE(H37:K37) -> 1662.125 | M37: =AVERAGE(I37:L37) -> 1661.6562 | N37: =AVERAGE(J37:M37) -> 1640.5703 | P37: 감가상각비 | Q37: =SUM(C37:F37) -> 4082 | R37: =SUM(G37:J37) -> 6630 | S37: =SUM(K37:N37) -> 6621.8516 | V37: 직전 4Q Average Flat 적용함. | AD37: =AVERAGE(AH38:AJ38) -> 0.018397598 | AG37: 감가상각비 | AH37: 2683 | AI37: 3094 | AJ37: 4082
B38: % of sales | C38: =C37/C7 -> 0.018294751 | D38: =D37/D7 -> 0.016604372 | E38: =E37/E7 -> 0.026240558 | F38: =F37/F7 -> 0.026742789 | G38: =G37/G7 -> 0.047387452 | H38: =H37/H7 -> 0.034033047 | I38: =I37/I7 -> 0.041804338 | J38: =J37/J7 -> 0.03142205 | ... N38: =N37/N7 -> 0.0075955875 | P38: % of sales | Q38: =Q37/Q7 -> 0.02200454 | R38: =R37/R7 -> 0.037764468 | S38: =S37/S7 -> 0.0083605577 | AH38: =AH37/$AH$28 -> 0.010030244 | AI38: =AI37/$AI$28 -> 0.023157989 | AJ38: =AJ37/$AJ$28 -> 0.02200456
B39: 무형자산상각비 | C39: 199 | D39: 205 | E39: 203 | F39: 193 | G39: 191 | H39: 140 | I39: 135 | J39: =AVERAGE(F39:I39) -> 164.75 | K39: =AVERAGE(G39:J39) -> 157.6875 | L39: =AVERAGE(H39:K39) -> 149.35938 | M39: =AVERAGE(I39:L39) -> 151.69922 | N39: =AVERAGE(J39:M39) -> 155.87402 | P39: 무형자산상각비 | Q39: =SUM(C39:F39) -> 800 | R39: =SUM(G39:J39) -> 630.75 | S39: =SUM(K39:N39) -> 614.62012 | V39: 직전 4Q Average Flat 적용함. | AD39: =AVERAGE(AH40:AJ40) -> 0.0042819844 | AG39: 무형자산상각비 | AH39: 751 | AI39: 765 | AJ39: 800
B40: % of sales | C40: =C39/C7 -> 0.0049331376 | D40: =D39/D7 -> 0.0040378365 | E40: =E39/E7 -> 0.0043448885 | F40: =F39/F7 -> 0.0040481242 | G40: =G39/G7 -> 0.0055222718 | H40: =H39/H7 -> 0.0028633574 | I40: =I39/I7 -> 0.0032322942 | J40: =J39/J7 -> 0.0032743723 | ... N40: =N39/N7 -> 0.00072167269 | P40: % of sales | Q40: =Q39/Q7 -> 0.0043125018 | R40: =R39/R7 -> 0.0035927509 | S40: =S39/S7 -> 0.00077600153 | AH40: =AH39/$AH$28 -> 0.0028075711 | AI40: =AI39/$AI$28 -> 0.0057258765 | AJ40: =AJ39/$AJ$28 -> 0.0043125057
B41: 임차료 | C41: 98 | D41: 92 | E41: 114 | F41: 56 | G41: 33 | H41: 135 | I41: 72 | J41: =AVERAGE(F41:I41) -> 74 | K41: =AVERAGE(G41:J41) -> 78.5 | L41: =AVERAGE(H41:K41) -> 89.875 | M41: =AVERAGE(I41:L41) -> 78.59375 | N41: =AVERAGE(J41:M41) -> 80.242188 | P41: 임차료 | Q41: =SUM(C41:F41) -> 360 | R41: =SUM(G41:J41) -> 314 | S41: =SUM(K41:N41) -> 327.21094 | V41: 직전 4Q Average Flat 적용함. | AD41: =AVERAGE(AH42:AJ42) -> 0.0021471267 | AG41: 임차료 | AH41: 343 | AI41: 430 | AJ41: 360
B42: % of sales | C42: =C41/C7 -> 0.0024293843 | D42: =D41/D7 -> 0.0018121022 | E42: =E41/E7 -> 0.0024399867 | F42: =F41/F7 -> 0.0011745853 | G42: =G41/G7 -> 0.00095410978 | H42: =H41/H7 -> 0.0027610946 | I42: =I41/I7 -> 0.0017238902 | J42: =J41/J7 -> 0.0014707348 | ... N42: =N41/N7 -> 0.00037150895 | P42: % of sales | Q42: =Q41/Q7 -> 0.0019406258 | R42: =R41/R7 -> 0.0017885434 | S42: =S41/S7 -> 0.00041312704 | AH42: =AH41/$AH$28 -> 0.0012822861 | AI42: =AI41/$AI$28 -> 0.0032184665 | AJ42: =AJ41/$AJ$28 -> 0.0019406276
B43: 접대비 | C43: 67 | D43: 79 | E43: 88 | F43: 84 | G43: 68 | H43: 62 | I43: 43 | J43: =$AD$43*J7 -> 90.988492 | K43: =$AD$43*K7 -> 260.38979 | L43: =$AD$43*L7 -> 396.84359 | M43: =$AD$43*M7 -> 384.47301 | N43: =$AD$43*N7 -> 390.59132 | P43: 접대비 | Q43: =SUM(C43:F43) -> 318 | R43: =SUM(G43:J43) -> 263.98849 | S43: =SUM(K43:N43) -> 1432.2977 | V43: 매출액과 상관게수 높음 직전 3개년 매출액 대비 비율 average | AD43: =AVERAGE(AH44:AJ44) -> 0.0018083775 | AG43: 접대비 | AH43: 392 | AI43: 300 | AJ43: 318
B44: % of sales | C44: =C43/C7 -> 0.0016609056 | D44: =D43/D7 -> 0.0015560443 | E44: =E43/E7 -> 0.0018834985 | F44: =F43/F7 -> 0.0017618779 | G44: =G43/G7 -> 0.0019660444 | H44: =H43/H7 -> 0.0012680583 | I44: =I43/I7 -> 0.0010295456 | J44: =J43/J7 -> 0.0018083775 | ... N44: =N43/N7 -> 0.0018083775 | P44: % of sales | Q44: =Q43/Q7 -> 0.0017142194 | R44: =R43/R7 -> 0.001503678 | S44: =S43/S7 -> 0.0018083775 | AH44: =AH43/$AH$28 -> 0.0014654699 | AI44: =AI43/$AI$28 -> 0.0022454418 | AJ44: =AJ43/$AJ$28 -> 0.001714221
B45: 지급수수료 | C45: 1000 | D45: 1084 | E45: 772 | F45: 876 | G45: 1748 | H45: 724 | I45: 849 | J45: =AVERAGE(F45:I45) -> 1049.25 | K45: =AVERAGE(G45:J45) -> 1092.5625 | L45: =AVERAGE(H45:K45) -> 928.70312 | M45: =AVERAGE(I45:L45) -> 979.87891 | N45: =AVERAGE(J45:M45) -> 1012.5986 | P45: 지급수수료 | Q45: =SUM(C45:F45) -> 3732 | R45: =SUM(G45:J45) -> 4370.25 | S45: =SUM(K45:N45) -> 4013.7432 | V45: 직전 4Q Average Flat 적용함. | AD45: =AVERAGE(AH46:AJ46) -> 0.021280201 | AG45: 지급수수료 | AH45: 4658 | AI45: 3515 | AJ45: 3732
B46: % of sales | C46: =C45/C7 -> 0.024789636 | D46: =D45/D7 -> 0.021351292 | E46: =E45/E7 -> 0.016523418 | F46: =F45/F7 -> 0.018373869 | G46: =G45/G7 -> 0.050538906 | H46: =H45/H7 -> 0.014807648 | I46: =I45/I7 -> 0.020327539 | J46: =J45/J7 -> 0.020853628 | ... N46: =N45/N7 -> 0.0046881755 | P46: % of sales | Q46: =Q45/Q7 -> 0.020117821 | R46: =R45/R7 -> 0.024892936 | S46: =S45/S7 -> 0.0050676357 | AH46: =AH45/$AH$28 -> 0.01741367 | AI46: =AI45/$AI$28 -> 0.026309093 | AJ46: =AJ45/$AJ$28 -> 0.020117839
B47: 차량유지비 | C47: 50 | D47: 38 | E47: 36 | F47: 39 | G47: 39 | H47: 82 | I47: 45 | J47: =AVERAGE(F47:I47) -> 51.25 | K47: =AVERAGE(G47:J47) -> 54.3125 | L47: =AVERAGE(H47:K47) -> 58.140625 | M47: =AVERAGE(I47:L47) -> 52.175781 | N47: =AVERAGE(J47:M47) -> 53.969727 | P47: 차량유지비 | Q47: =SUM(C47:F47) -> 163 | R47: =SUM(G47:J47) -> 217.25 | S47: =SUM(K47:N47) -> 218.59863 | V47: 직전 4Q Average Flat 적용함. | AD47: =AVERAGE(AH48:AJ48) -> 0.0011969447 | AG47: 차량유지비 | AH47: 273 | AI47: 226 | AJ47: 163
B48: % of sales | C48: =C47/C7 -> 0.0012394818 | D48: =D47/D7 -> 0.00074847701 | E48: =E47/E7 -> 0.0007705221 | F48: =F47/F7 -> 0.00081801473 | G48: =G47/G7 -> 0.0011275843 | H48: =H47/H7 -> 0.0016771093 | I48: =I47/I7 -> 0.0010774314 | J48: =J47/J7 -> 0.0010185832 | ... N48: =N47/N7 -> 0.00024987151 | P48: % of sales | Q48: =Q47/Q7 -> 0.00087867223 | R48: =R47/R7 -> 0.0012374556 | S48: =S47/S7 -> 0.00027599629 | AH48: =AH47/$AH$28 -> 0.0010205951 | AI48: =AI47/$AI$28 -> 0.0016915661 | AJ48: =AJ47/$AJ$28 -> 0.00087867304
B49: 경상연구개발비 | C49: 3970 | D49: ='IS(Quaterly)'!I18 -> 4518.248 | E49: ='IS(Quaterly)'!J18 -> 4553.035 | F49: 5626 | G49: ='IS(Quaterly)'!L18 -> 3893.984 | H49: ='IS(Quaterly)'!M18 -> 4376.273 | I49: 3618 | J49: =AVERAGE(F49:I49) -> 4378.5643 | K49: =AVERAGE(G49:J49) -> 4066.7053 | L49: =AVERAGE(H49:K49) -> 4109.8856 | M49: =AVERAGE(I49:L49) -> 4043.2888 | N49: =AVERAGE(J49:M49) -> 4149.611 | P49: 경상연구개발비 | Q49: =SUM(C49:F49) -> 18667.283 | R49: =SUM(G49:J49) -> 16266.821 | S49: =SUM(K49:N49) -> 16369.491 | V49: 직전 4Q Average Flat 적용함. | AD49: =AVERAGE(AH50:AJ50) -> 0.09085658 | AG49: 경상연구개발비 | AH49: 14656 | AI49: 15652 | AJ49: 18667
B50: % of sales | C50: =C49/C7 -> 0.098414855 | D50: =D49/D7 -> 0.088994862 | E50: =E49/E7 -> 0.097450392 | F50: =F49/F7 -> 0.11800387 | G50: =G49/G7 -> 0.11258449 | H50: =H49/H7 -> 0.089505954 | I50: =I49/I7 -> 0.086625485 | J50: =J49/J7 -> 0.087023063 | ... N50: =N49/N7 -> 0.019212059 | P50: % of sales | Q50: =Q49/Q7 -> 0.10062836 | R50: =R49/R7 -> 0.092655784 | S50: =S49/S7 -> 0.020667644 | AH50: =AH49/$AH$28 -> 0.054790628 | AI50: =AI49/$AI$28 -> 0.11715218 | AJ50: =AJ49/$AJ$28 -> 0.10062693
B51: 판매보증비 | C51: 83 | D51: 75 | E51: 119 | F51: -97 | G51: ='IS(Quaterly)'!L20 -> 550.735 | H51: ='IS(Quaterly)'!M20 -> 170.88 | I51: 117 | J51: =AVERAGE(F51:I51) -> 185.40375 | K51: =AVERAGE(G51:J51) -> 256.00469 | L51: =AVERAGE(H51:K51) -> 182.32211 | M51: =AVERAGE(I51:L51) -> 185.18264 | N51: =AVERAGE(J51:M51) -> 202.2283 | P51: 판매보증비 | Q51: =SUM(C51:F51) -> 180 | R51: =SUM(G51:J51) -> 1024.0187 | S51: =SUM(K51:N51) -> 825.73773 | V51: 직전 4Q Average Flat 적용함. | AD51: =AVERAGE(AH52:AJ52) -> 0.002866836 | AG51: 판매보증비 | AH51: 1088 | AI51: 476 | AJ51: 180
B52: % of sales | C52: =C51/C7 -> 0.0020575398 | D52: =D51/D7 -> 0.0014772573 | E52: =E51/E7 -> 0.0025470036 | F52: =F51/F7 -> -0.0020345495 | G52: =G51/G7 -> 0.01592308 | H52: =H51/H7 -> 0.0034949322 | I52: =I51/I7 -> 0.0028013216 | J52: =J51/J7 -> 0.0036848614 | ... N52: =N51/N7 -> 0.00093628582 | P52: % of sales | Q52: =Q51/Q7 -> 0.00097031289 | R52: =R51/R7 -> 0.0058328089 | S52: =S51/S7 -> 0.0010425525 | AH52: =AH51/$AH$28 -> 0.0040674266 | AI52: =AI51/$AI$28 -> 0.0035627676 | AJ52: =AJ51/$AJ$28 -> 0.00097031379
B53: 운반비 | C53: 61 | D53: 132 | E53: 65 | F53: 89 | G53: 51 | H53: 69 | I53: 94 | J53: =$AD$53*J7 -> 172.12368 | K53: =$AD$53*K7 -> 492.58152 | L53: =$AD$53*L7 -> 750.71231 | M53: =$AD$53*M7 -> 727.31078 | N53: =$AD$53*N7 -> 738.88483 | P53: 운반비 | Q53: =SUM(C53:F53) -> 347 | R53: =SUM(G53:J53) -> 386.12368 | S53: =SUM(K53:N53) -> 2709.4894 | V53: 매출액과 상관계수가 높기에 직전 3개년 매출액 대비 비율 average 하여 적용. | AD53: =AVERAGE(AH54:AJ54) -> 0.0034209228 | AG53: 운반비 | AH53: 1448 | AI53: 398 | AJ53: 347
B54: % of sales | C54: =C53/C7 -> 0.0015121678 | D54: =D53/D7 -> 0.0025999728 | E54: =E53/E7 -> 0.0013912205 | F54: =F53/F7 -> 0.0018667516 | G54: =G53/G7 -> 0.0014745333 | H54: =H53/H7 -> 0.0014112261 | I54: =I53/I7 -> 0.0022506345 | J54: =J53/J7 -> 0.0034209228 | ... N54: =N53/N7 -> 0.0034209228 | P54: % of sales | Q54: =Q53/Q7 -> 0.0018705476 | R54: =R53/R7 -> 0.0021993598 | S54: =S53/S7 -> 0.0034209228 | AH54: =AH53/$AH$28 -> 0.0054132662 | AI54: =AI53/$AI$28 -> 0.0029789527 | AJ54: =AJ53/$AJ$28 -> 0.0018705494
B55: 포장비 | C55: 71 | D55: 81 | E55: 84 | F55: 94 | G55: 71 | H55: 92 | I55: 98 | J55: =$AD$55*J7 -> 89.367619 | K55: =$AD$55*K7 -> 255.75119 | L55: =$AD$55*L7 -> 389.7742 | M55: =$AD$55*M7 -> 377.62399 | N55: =$AD$55*N7 -> 383.63331 | P55: 포장비 | Q55: =SUM(C55:F55) -> 330 | R55: =SUM(G55:J55) -> 350.36762 | S55: =SUM(K55:N55) -> 1406.7827 | V55: 매출액과 상관계수가 높기에 직전 3개년 매출액 대비 비율 average 하여 적용. | AD55: =AVERAGE(AH56:AJ56) -> 0.001776163 | AG55: 포장비 | AH55: 495 | AI55: 227 | AJ55: 330
B56: % of sales | C56: =C55/C7 -> 0.0017600642 | D56: =D55/D7 -> 0.0015954378 | E56: =E55/E7 -> 0.0017978849 | F56: =F55/F7 -> 0.0019716252 | G56: =G55/G7 -> 0.0020527816 | H56: =H55/H7 -> 0.0018816348 | I56: =I55/I7 -> 0.0023464062 | J56: =J55/J7 -> 0.001776163 | ... N56: =N55/N7 -> 0.001776163 | P56: % of sales | Q56: =Q55/Q7 -> 0.001778907 | R56: =R55/R7 -> 0.0019956933 | S56: =S55/S7 -> 0.001776163 | AH56: =AH55/$AH$28 -> 0.0018505296 | AI56: =AI55/$AI$28 -> 0.0016990509 | AJ56: =AJ55/$AJ$28 -> 0.0017789086
B57: 기타비용 | C57: 140 | D57: 513 | E57: 642 | F57: 337 | G57: 227 | H57: 589 | I57: 308 | J57: =AVERAGE(F57:I57) -> 365.25 | K57: =AVERAGE(G57:J57) -> 372.3125 | L57: =AVERAGE(H57:K57) -> 408.64062 | M57: =AVERAGE(I57:L57) -> 363.55078 | N57: =AVERAGE(J57:M57) -> 377.43848 | P57: 기타비용 | Q57: =SUM(C57:F57) -> 1632 | R57: =SUM(G57:J57) -> 1489.25 | S57: =SUM(K57:N57) -> 1521.9424 | V57: 직전 4Q Average Flat 적용함. | AD57: =AVERAGE(AH58:AJ58) -> 0.0076524123 | AG57: 기타비용 | AH57: 1331 | AI57: 1227 | AJ57: 1632
B58: % of sales | C58: =C57/C7 -> 0.0034705491 | D58: =D57/D7 -> 0.01010444 | E58: =E57/E7 -> 0.013740978 | F58: =F57/F7 -> 0.0070684862 | G58: =G57/G7 -> 0.0065631188 | H58: =H57/H7 -> 0.012046553 | I58: =I57/I7 -> 0.0073744194 | J58: =J57/J7 -> 0.0072592686 | ... N58: =N57/N7 -> 0.0017474819 | P58: % of sales | Q58: =Q57/Q7 -> 0.0087975036 | R58: =R57/R7 -> 0.0084827653 | S58: =S57/S7 -> 0.0019215603 | AH58: =AH57/$AH$28 -> 0.0049758683 | AI58: =AI57/$AI$28 -> 0.0091838568 | AJ58: =AJ57/$AJ$28 -> 0.0087975117
B59: 영업이익 | C59: =C27-C29 -> 5573.8298 | D59: =D27-D29 -> 7175.4302 | E59: =E27-E29 -> 6177.9404 | F59: =F27-F29 -> 4486.9413 | G59: =G27-G29 -> 1297.8204 | H59: =H27-H29 -> 6204.103 | I59: =I27-I29 -> 7111.2977 | J59: =J27-J29 -> 8181.8958 | ... N59: =N27-N29 -> 69839.153 | P59: 영업이익 | Q59: =Q27-Q29 -> 23414.142 | R59: =R27-R29 -> 22795.117 | S59: =S27-S29 -> 252727.16
B60: OPM(%) | C60: =C59/C7 -> 0.13817321 | D60: =D59/D7 -> 0.14133275 | E60: =E59/E7 -> 0.13222888 | F60: =F59/F7 -> 0.094112412 | G60: =G59/G7 -> 0.037523125 | H60: =H59/H7 -> 0.12688974 | I60: =I59/I7 -> 0.17026523 | J60: =J59/J7 -> 0.1626135 | ... N60: =N59/N7 -> 0.3233445 | P60: OPM(%) | Q60: =Q59/Q7 -> 0.12621691 | R60: =R59/R7 -> 0.12984094 | S60: =S59/S7 -> 0.31908598 | AG60: 상관계수 측정
B61: 금융수익 | C61: =SUM(C62:C64) -> 549.529 | D61: =SUM(D62:D64) -> 756.944 | E61: =SUM(E62:E64) -> 362.569 | F61: =SUM(F62:F64) -> 1031.955 | G61: =SUM(G62:G64) -> 857.441 | H61: =SUM(H62:H64) -> 4146.555 | I61: =SUM(I62:I64) -> -4293 | J61: =SUM(J62:J64) -> 434.0035 | ... N61: =SUM(N62:N64) -> 1.595459 | P61: 금융수익 | Q61: =SUM(C61:F61) -> 2700.997 | R61: =SUM(G61:J61) -> 1144.9995 | S61: =SUM(K61:N61) -> -426.02621 | AG61: 판관비 세부항목
B62: 이자수익 | C62: ='IS(Quaterly)'!H26 -> 273.223 | D62: ='IS(Quaterly)'!I26 -> 248.92 | E62: ='IS(Quaterly)'!J26 -> 204.423 | F62: ='IS(Quaterly)'!K26 -> 124.029 | G62: ='IS(Quaterly)'!L26 -> 112.246 | H62: ='IS(Quaterly)'!M26 -> 90.621 | I62: 107 | J62: =AVERAGE(F62:I62) -> 108.474 | K62: =AVERAGE(G62:J62) -> 104.58525 | L62: =AVERAGE(H62:K62) -> 102.67006 | M62: =AVERAGE(I62:L62) -> 105.68233 | N62: =AVERAGE(J62:M62) -> 105.35291 | P62: 이자수익 | Q62: =SUM(C62:F62) -> 850.595 | R62: =SUM(G62:J62) -> 418.341 | S62: =SUM(K62:N62) -> 418.29055 | V62: 직전 4Q Average Flat 적용함. | AG62: 인건비 | AH62: =CORREL($AH$28:$AJ$28,AH31:AJ31) -> 0.9977381
B63: 외환이익 | C63: ='IS(Quaterly)'!H28 -> 276.306 | D63: ='IS(Quaterly)'!I28 -> 116.236 | E63: ='IS(Quaterly)'!J28 -> 158.146 | F63: ='IS(Quaterly)'!K28 -> 900.989 | G63: ='IS(Quaterly)'!L28 -> 745.195 | H63: ='IS(Quaterly)'!M28 -> 4055.934 | I63: -4400 | J63: =AVERAGE(F63:I63) -> 325.5295 | K63: =AVERAGE(G63:J63) -> 181.66463 | L63: =AVERAGE(H63:K63) -> 40.782031 | M63: =AVERAGE(I63:L63) -> -963.00596 | N63: =AVERAGE(J63:M63) -> -103.75745 | P63: 외환이익 | Q63: =SUM(C63:F63) -> 1451.677 | R63: =SUM(G63:J63) -> 726.6585 | S63: =SUM(K63:N63) -> -844.31676 | V63: 직전 4Q Average Flat 적용함. | AG63: 여비교통비 | AH63: =CORREL($AH$28:$AJ$28,AH33:AJ33) -> 0.92297972
B64: 대손충당금환입액 | C64: ='IS(Quaterly)'!H29 -> 0 | D64: ='IS(Quaterly)'!I29 -> 391.788 | E64: ='IS(Quaterly)'!J29 -> 0 | F64: ='IS(Quaterly)'!K29 -> 6.937 | G64: ='IS(Quaterly)'!L29 -> 0 | H64: ='IS(Quaterly)'!M29 -> 0 | I64: 0 | J64: =AVERAGE(G64:I64) -> 0 | K64: =AVERAGE(H64:J64) -> 0 | L64: =AVERAGE(I64:K64) -> 0 | M64: =AVERAGE(J64:L64) -> 0 | N64: =AVERAGE(K64:M64) -> 0 | P64: 당기손익-공정가치측정금융자산평가이익 | Q64: =SUM(C64:F64) -> 398.725 | R64: =SUM(G64:J64) -> 0 | S64: =SUM(K64:N64) -> 0 | V64: 직전 4Q Average Flat 적용함. | AG64: 대손상각비 | AH64: =CORREL($AH$28:$AJ$28,AH35:AJ35) -> -0.13213848
B65: 금융원가 | C65: =SUM(C66:C68) -> 4431.189 | D65: =SUM(D66:D68) -> 3954.907 | E65: =SUM(E66:E68) -> -458.31 | F65: =SUM(F66:F68) -> 8065.787 | G65: =SUM(G66:G68) -> 2220.026 | H65: =SUM(H66:H68) -> 4778.148 | I65: =SUM(I66:I68) -> 3088 | J65: =SUM(J66:J68) -> 4537.9902 | ... N65: =SUM(N66:N68) -> 4008.3363 | P65: 금융원가 | Q65: =SUM(C65:F65) -> 15993.573 | R65: =SUM(G65:J65) -> 14624.164 | S65: =SUM(K65:N65) -> 15503.691 | AG65: 감가상각비 | AH65: =CORREL($AH$28:$AJ$28,AH37:AJ37) -> -0.40668908
B66: 이자비용 | C66: ='IS(Quaterly)'!H38 -> 1897.945 | D66: ='IS(Quaterly)'!I38 -> 2036.685 | E66: ='IS(Quaterly)'!J38 -> 2317.653 | F66: ='IS(Quaterly)'!K38 -> 2120.32 | G66: ='IS(Quaterly)'!L38 -> 2070.21 | H66: ='IS(Quaterly)'!M38 -> 2473.559 | I66: 2757 | J66: =AVERAGE(F66:I66) -> 2355.2722 | K66: =AVERAGE(G66:J66) -> 2414.0103 | L66: =AVERAGE(H66:K66) -> 2499.9604 | M66: =AVERAGE(I66:L66) -> 2506.5607 | N66: =AVERAGE(J66:M66) -> 2443.9509 | P66: 이자비용 | Q66: =SUM(C66:F66) -> 8372.603 | R66: =SUM(G66:J66) -> 9656.0413 | S66: =SUM(K66:N66) -> 9864.4824 | V66: 직전 4Q Average Flat 적용함. | AG66: 무형자산상각비 | AH66: =CORREL($AH$28:$AJ$28,AH39:AJ39) -> -0.39863732
B67: 외환손실 | C67: ='IS(Quaterly)'!H39 -> 2533.244 | D67: ='IS(Quaterly)'!I39 -> 1918.222 | E67: ='IS(Quaterly)'!J39 -> -2775.963 | F67: ='IS(Quaterly)'!K39 -> 5945.467 | G67: ='IS(Quaterly)'!L39 -> 149.816 | H67: ='IS(Quaterly)'!M39 -> 454.589 | I67: 331 | J67: =AVERAGE(F67:I67) -> 1720.218 | K67: =AVERAGE(G67:J67) -> 663.90575 | L67: =AVERAGE(H67:K67) -> 792.42819 | M67: =AVERAGE(I67:L67) -> 876.88798 | N67: =AVERAGE(J67:M67) -> 1013.36 | P67: 외환손실 | Q67: =SUM(C67:F67) -> 7620.97 | R67: =SUM(G67:J67) -> 2655.623 | S67: =SUM(K67:N67) -> 3346.5819 | V67: 직전 4Q Average Flat 적용함. | AG67: 임차료 | AH67: =CORREL($AH$28:$AJ$28,AH41:AJ41) -> -0.89283236
B68: 대손상각비 | C68: ='IS(Quaterly)'!H40 -> 0 | D68: ='IS(Quaterly)'!I40 -> 0 | E68: ='IS(Quaterly)'!J40 -> 0 | F68: ='IS(Quaterly)'!K40 -> 0 | G68: ='IS(Quaterly)'!L40 -> 0 | H68: ='IS(Quaterly)'!M40 -> 1850 | I68: 0 | J68: =AVERAGE(F68:I68) -> 462.5 | K68: =AVERAGE(G68:J68) -> 578.125 | L68: =AVERAGE(H68:K68) -> 722.65625 | M68: =AVERAGE(I68:L68) -> 440.82031 | N68: =AVERAGE(J68:M68) -> 551.02539 | P68: 대손상각비 | Q68: =SUM(C68:F68) -> 0 | R68: =SUM(G68:J68) -> 2312.5 | S68: =SUM(K68:N68) -> 2292.627 | V68: 직전 4Q Average Flat 적용함. | AG68: 접대비 | AH68: =CORREL($AH$28:$AJ$28,AH43:AJ43) -> 0.97824861
B69: 기타수익 | C69: =SUM(C70:C74) -> 3039.781 | D69: =SUM(D70:D74) -> 4595.377 | E69: =SUM(E70:E74) -> 2970.072 | F69: =SUM(F70:F74) -> 3288.521 | G69: =SUM(G70:G74) -> 2295.6 | H69: =SUM(H70:H74) -> 22828.642 | I69: =SUM(I70:I74) -> -6173 | J69: =SUM(J70:J74) -> 5559.9407 | ... N69: =SUM(N70:N74) -> 5480.9316 | P69: 기타수익 | Q69: =SUM(C69:F69) -> 13893.751 | R69: =SUM(G69:J69) -> 24511.183 | S69: =SUM(K69:N69) -> 21844.717 | AG69: 지급수수료 | AH69: =CORREL($AH$28:$AJ$28,AH45:AJ45) -> 0.97699718
B70: 외환이익 | C70: ='IS(Quaterly)'!H51 -> 2037.124 | D70: ='IS(Quaterly)'!I51 -> 2051.843 | E70: ='IS(Quaterly)'!J51 -> -595.239 | F70: ='IS(Quaterly)'!K51 -> 4037.772 | G70: ='IS(Quaterly)'!L51 -> 334.78 | H70: ='IS(Quaterly)'!M51 -> -143.317 | I70: 3482 | J70: =AVERAGE(F70:I70) -> 1927.8087 | K70: =AVERAGE(G70:J70) -> 1400.3179 | L70: =AVERAGE(H70:K70) -> 1666.7024 | M70: =AVERAGE(I70:L70) -> 2119.2073 | N70: =AVERAGE(J70:M70) -> 1778.5091 | P70: 외환이익 | Q70: =SUM(C70:F70) -> 7531.5 | R70: =SUM(G70:J70) -> 5601.2717 | S70: =SUM(K70:N70) -> 6964.7367 | V70: 직전 4Q Average Flat 적용함. | AG70: 차량유지비 | AH70: =CORREL($AH$28:$AJ$28,AH47:AJ47) -> 0.53863213
B71: 자산처분이익 | C71: ='IS(Quaterly)'!H55 -> 861.856 | D71: ='IS(Quaterly)'!I55 -> 2108.197 | E71: ='IS(Quaterly)'!J55 -> 0 | F71: ='IS(Quaterly)'!K55 -> 3.087 | G71: ='IS(Quaterly)'!L55 -> 30.221 | H71: ='IS(Quaterly)'!M55 -> 3.879 | I71: 6 | J71: =AVERAGE(F71:I71) -> 10.79675 | K71: =AVERAGE(G71:J71) -> 12.724187 | L71: =AVERAGE(H71:K71) -> 8.3499844 | M71: =AVERAGE(I71:L71) -> 9.4677305 | N71: =AVERAGE(J71:M71) -> 10.334663 | P71: 자산처분이익 | Q71: =SUM(C71:F71) -> 2973.14 | R71: =SUM(G71:J71) -> 50.89675 | S71: =SUM(K71:N71) -> 40.876565 | V71: 직전 4Q Average Flat 적용함. | AG71: 경상연구개발비 | AH71: =CORREL($AH$28:$AJ$28,AH49:AJ49) -> -0.3613979
B72: 파생상품이익 | C72: ='IS(Quaterly)'!H58 -> 69 | D72: ='IS(Quaterly)'!I58 -> 368.37 | E72: ='IS(Quaterly)'!J58 -> 3508.364 | F72: ='IS(Quaterly)'!K58 -> -805.354 | G72: ='IS(Quaterly)'!L58 -> 1897.562 | H72: ='IS(Quaterly)'!M58 -> 22877.879 | I72: -9740 | J72: =AVERAGE(F72:I72) -> 3557.5217 | K72: =AVERAGE(G72:J72) -> 4648.2407 | L72: =AVERAGE(H72:K72) -> 5335.9104 | M72: =AVERAGE(I72:L72) -> 950.4182 | N72: =AVERAGE(J72:M72) -> 3623.0227 | P72: 파생상품이익 | Q72: =SUM(C72:F72) -> 3140.38 | R72: =SUM(G72:J72) -> 18592.963 | S72: =SUM(K72:N72) -> 14557.592 | V72: 직전 4Q Average Flat 적용함. | AG72: 판매보증비 | AH72: =CORREL($AH$28:$AJ$28,AH51:AJ51) -> 0.75186233
B73: 임대료수익 | C73: ='IS(Quaterly)'!H59 -> 45.9 | D73: ='IS(Quaterly)'!I59 -> 20.53 | E73: ='IS(Quaterly)'!J59 -> 10.5 | F73: ='IS(Quaterly)'!K59 -> 10.5 | G73: ='IS(Quaterly)'!L59 -> 24.26 | H73: ='IS(Quaterly)'!M59 -> 36.9 | I73: 38 | J73: =AVERAGE(F73:I73) -> 27.415 | K73: =AVERAGE(G73:J73) -> 31.64375 | L73: =AVERAGE(H73:K73) -> 33.489688 | M73: =AVERAGE(I73:L73) -> 32.637109 | N73: =AVERAGE(J73:M73) -> 31.296387 | P73: 임대료수익 | Q73: =SUM(C73:F73) -> 87.43 | R73: =SUM(G73:J73) -> 126.575 | S73: =SUM(K73:N73) -> 129.06693 | V73: 직전 4Q Average Flat 적용함. | AG73: 운반비 | AH73: =CORREL($AH$28:$AJ$28,AH53:AJ53) -> 0.90659726
B74: 기타 | C74: ='IS(Quaterly)'!H64 -> 25.901 | D74: ='IS(Quaterly)'!I64 -> 46.437 | E74: ='IS(Quaterly)'!J64 -> 46.447 | F74: ='IS(Quaterly)'!K64 -> 42.516 | G74: ='IS(Quaterly)'!L64 -> 8.777 | H74: ='IS(Quaterly)'!M64 -> 53.301 | I74: 41 | J74: =AVERAGE(F74:I74) -> 36.3985 | K74: =AVERAGE(G74:J74) -> 34.869125 | L74: =AVERAGE(H74:K74) -> 41.392156 | M74: =AVERAGE(I74:L74) -> 38.414945 | N74: =AVERAGE(J74:M74) -> 37.768682 | P74: 기타 | Q74: =SUM(C74:F74) -> 161.301 | R74: =SUM(G74:J74) -> 139.4765 | S74: =SUM(K74:N74) -> 152.44491 | V74: 직전 4Q Average Flat 적용함. | AG74: 포장비 | AH74: =CORREL($AH$28:$AJ$28,AH55:AJ55) -> 0.99999284
B75: 기타비용 | C75: =SUM(C76:C80) -> 15357.19 | D75: =SUM(D76:D80) -> 11398.289 | E75: =SUM(E76:E80) -> -7874.135 | F75: =SUM(F76:F80) -> 40548.749 | G75: =SUM(G76:G80) -> 4444.638 | H75: =SUM(H76:H80) -> 574.804 | I75: =SUM(I76:I80) -> 1711 | J75: =SUM(J76:J80) -> 11819.798 | ... N75: =SUM(N76:N80) -> 6714.1713 | P75: 기타비용 | Q75: =SUM(C75:F75) -> 59430.093 | R75: =SUM(G75:J75) -> 18550.24 | S75: =SUM(K75:N75) -> 21751.059 | AG75: 기타비용 | AH75: =CORREL($AH$28:$AJ$28,AH57:AJ57) -> 0.12052698
B76: 외화손실 | C76: ='IS(Quaterly)'!H67 -> 60.173 | D76: ='IS(Quaterly)'!I67 -> 114.596 | E76: ='IS(Quaterly)'!J67 -> 1583.302 | F76: ='IS(Quaterly)'!K67 -> -800.821 | G76: ='IS(Quaterly)'!L67 -> 451.231 | H76: ='IS(Quaterly)'!M67 -> 2544.441 | I76: -624 | J76: =AVERAGE(F76:I76) -> 392.71275 | K76: =AVERAGE(G76:J76) -> 691.09619 | L76: =AVERAGE(H76:K76) -> 751.06248 | M76: =AVERAGE(I76:L76) -> 302.71786 | N76: =AVERAGE(J76:M76) -> 534.39732 | P76: 외환손실 | Q76: =SUM(C76:F76) -> 957.25 | R76: =SUM(G76:J76) -> 2764.3847 | S76: =SUM(K76:N76) -> 2279.2738 | V76: 직전 4Q Average Flat 적용함.
B77: 자산처분손실 | C77: ='IS(Quaterly)'!H71 -> 256.899 | D77: ='IS(Quaterly)'!I71 -> -228.323 | E77: ='IS(Quaterly)'!J71 -> 0 | F77: ='IS(Quaterly)'!K71 -> 0.001 | G77: ='IS(Quaterly)'!L71 -> 0.199 | H77: ='IS(Quaterly)'!M71 -> 0 | I77: 0 | J77: =AVERAGE(F77:I77) -> 0.05 | K77: =AVERAGE(G77:J77) -> 0.06225 | L77: =AVERAGE(H77:K77) -> 0.0280625 | M77: =AVERAGE(I77:L77) -> 0.035078125 | N77: =AVERAGE(J77:M77) -> 0.043847656 | P77: 자산처분손실 | Q77: =SUM(C77:F77) -> 28.577 | R77: =SUM(G77:J77) -> 0.249 | S77: =SUM(K77:N77) -> 0.16923828 | V77: 직전 4Q Average Flat 적용함.
B78: 자산손상차손 | C78: ='IS(Quaterly)'!H73 -> 0 | D78: ='IS(Quaterly)'!I73 -> 0 | E78: ='IS(Quaterly)'!J73 -> 0 | F78: ='IS(Quaterly)'!K73 -> 8008.672 | G78: ='IS(Quaterly)'!L73 -> 1.67 | H78: ='IS(Quaterly)'!M73 -> -1.67 | I78: 0 | J78: =AVERAGE(F78:I78) -> 2002.168 | K78: =AVERAGE(G78:J78) -> 500.542 | L78: =AVERAGE(H78:K78) -> 625.26 | M78: =AVERAGE(I78:L78) -> 781.9925 | N78: =AVERAGE(J78:M78) -> 977.49063 | P78: 자산손상차손 | Q78: =SUM(C78:F78) -> 8008.672 | R78: =SUM(G78:J78) -> 2002.168 | S78: =SUM(K78:N78) -> 2885.2851 | V78: 직전 4Q Average Flat 적용함.
B79: 파생상품손실 | C79: ='IS(Quaterly)'!H74 -> 14992.432 | D79: ='IS(Quaterly)'!I74 -> 11189.196 | E79: ='IS(Quaterly)'!J74 -> -9465.817 | F79: ='IS(Quaterly)'!K74 -> 33337.795 | G79: ='IS(Quaterly)'!L74 -> 3969.376 | H79: ='IS(Quaterly)'!M74 -> -1971.068 | I79: 2333 | J79: =AVERAGE(F79:I79) -> 9417.2758 | K79: =AVERAGE(G79:J79) -> 3437.1459 | L79: =AVERAGE(H79:K79) -> 3304.0884 | M79: =AVERAGE(I79:L79) -> 4622.8775 | N79: =AVERAGE(J79:M79) -> 5195.3469 | P79: 파생상품손실 | Q79: =SUM(C79:F79) -> 50053.606 | R79: =SUM(G79:J79) -> 13748.584 | S79: =SUM(K79:N79) -> 16559.459 | V79: 직전 4Q Average Flat 적용함.
B80: 기타 | C80: ='IS(Quaterly)'!H77 -> 47.686 | D80: ='IS(Quaterly)'!I77 -> 322.82 | E80: ='IS(Quaterly)'!J77 -> 8.38 | F80: ='IS(Quaterly)'!K77 -> 3.102 | G80: ='IS(Quaterly)'!L77 -> 22.162 | H80: ='IS(Quaterly)'!M77 -> 3.101 | I80: 2 | J80: =AVERAGE(F80:I80) -> 7.59125 | K80: =AVERAGE(G80:J80) -> 8.7135625 | L80: =AVERAGE(H80:K80) -> 5.3514531 | M80: =AVERAGE(I80:L80) -> 5.9140664 | N80: =AVERAGE(J80:M80) -> 6.892583 | P80: 기타 | Q80: =SUM(C80:F80) -> 381.988 | R80: =SUM(G80:J80) -> 34.85425 | S80: =SUM(K80:N80) -> 26.871665 | V80: 직전 4Q Average Flat 적용함.
B81: 법인세차감 전 순이익 | C81: =C59+C61-C65+C69-C75 -> -10625.239 | D81: =D59+D61-D65+D69-D75 -> -2825.4448 | E81: =E59+E61-E65+E69-E75 -> 17843.026 | F81: =F59+F61-F65+F69-F75 -> -39807.119 | G81: =G59+G61-G65+G69-G75 -> -2213.8026 | H81: =H59+H61-H65+H69-H75 -> 27826.348 | I81: =I59+I61-I65+I69-I75 -> -8153.7023 | J81: =J59+J61-J65+J69-J75 -> -2181.9479 | ... N81: =N59+N61-N65+N69-N75 -> 64599.172 | P81: 법인세차감 전 순이익 | Q81: =SUM(C81:F81) -> -35414.776 | R81: =SUM(G81:J81) -> 15276.895 | S81: =SUM(K81:N81) -> 236891.1
B82: 법인세비용 | C82: ='IS(Quaterly)'!H84 -> -2410.7002 | D82: ='IS(Quaterly)'!I84 -> -1401.3293 | E82: ='IS(Quaterly)'!J84 -> 3736.7567 | F82: ='IS(Quaterly)'!K84 -> -13372.116 | G82: ='IS(Quaterly)'!L84 -> -140.8909 | H82: ='IS(Quaterly)'!M84 -> 6260.4964 | I82: -1468 | J82: =R82-SUM(G82:I82) -> -1768.9954 | K82: =(200*0.1+(K81*4-200)*0.2)/4 -> 8244.3662 | L82: =(200*0.1+(L81*4-200)*0.2)/4 -> 13860.229 | M82: =(200*0.1+(M81*4-200)*0.2)/4 -> 12338.79 | N82: =S82-SUM(K82:M82) -> 12914.834 | P82: 법인세비용 | Q82: =SUM(C82:F82) -> -13447.389 | R82: =200*0.09+(R81-200)*0.19 -> 2882.6101 | S82: =200*0.1+(S81-200)*0.2 -> 47358.219
B83: % 유효법인세율 | C83: =C82/C81 -> 0.22688432 | D83: =D82/D81 -> 0.49596767 | E83: =E82/E81 -> 0.20942393 | F83: =F82/F81 -> 0.33592273 | G83: =G82/G81 -> 0.063642034 | H83: =H82/H81 -> 0.22498448 | I83: =I82/I81 -> 0.18004091 | J83: =J82/J81 -> 0.81074137 | ... N83: =N82/N81 -> 0.1999226 | P83: % 유효법인세율 | Q83: =Q82/Q81 -> 0.37971125 | R83: =R82/R81 -> 0.18869083 | S83: =S82/S81 -> 0.19991557 | V83: 법인세율에 따라 계산함.
B84: 당기순이익 | C84: =C81-C82 -> -8214.539 | D84: =D81-D82 -> -1424.1156 | E84: =E81-E82 -> 14106.27 | F84: =F81-F82 -> -26435.003 | G84: =G81-G82 -> -2072.9117 | H84: =H81-H82 -> 21565.852 | I84: =I81-I82 -> -6685.7023 | J84: =J81-J82 -> -412.95249 | ... N84: =N81-N82 -> 51684.338 | P84: 당기순이익 | Q84: =Q81-Q82 -> -21967.387 | R84: =R81-R82 -> 12394.285 | S84: =S81-S82 -> 189532.88

Sheet RAW DATA>>>
B2: 테크윙(089030.KQ) RAW DATA
B10: RFS Research Team 2

Sheet IS(Quaterly)
A1: Financial Statements
A2: Company | B2: A089030(테크윙) - Fiscal Month:12, 201106부터 IFRS 적용
A3: Type | B3: 연결 | C3: Accounting Std. | D3: IFRS
A4: Report | B4: 손익계산서 | C4: New
A5: Form | B5: 약식(COMPARE)
A6: Output | B6: 당분기 | C6: 백만원
A7: Fiscal Year | B7: 2023 | C7: Current
A8: 계정코드 | B8: 계정명 | C8: 단위 | D8: 202303(1Q) | E8: 202306(2Q) | F8: 202309(3Q) | G8: 202312(4Q) | H8: 202403(1Q) | I8: 202406(2Q) | J8: 202409(3Q) | K8: 202412(4Q) | L8: 202503(1Q) | M8: 202506(2Q) | N8: 202509(3Q)
D9: IFRS(연결) | E9: IFRS(연결) | F9: IFRS(연결) | G9: IFRS(연결) | H9: IFRS(연결) | I9: IFRS(연결) | J9: IFRS(연결) | K9: IFRS(연결) | L9: IFRS(연결) | M9: IFRS(연결) | N9: IFRS(연결)
A10: 4001210000 | B10: 매출액(수익)(*) | C10: 백만원 | D10: 28622.483 | E10: 39490.614 | F10: 24330.7 | G10: 41160.463 | H10: 40339.439 | I10: 50769.762 | J10: 46721.567 | K10: 47676.403 | L10: 34587.215 | M10: 48893.653 | N10: 41765.844
A11: 4001210010 | B11: *수출(*) | C11: 백만원 | H11: 29844.904 | J11: 36809.142 | K11: 71635.804 | L11: 25066.01 | M11: 48893.653
A12: 4001210020 | B12: *내수 | C12: 백만원 | H12: 10494.535 | J12: 9912.425 | K12: 26810.361 | L12: 9521.205
A13: 4001210320 | B13: 매출원가(*) | C13: 백만원 | D13: 16557.603 | E13: 24010.858 | F13: 15297.826 | G13: 28189.93 | H13: 24298.609 | I13: 30584.084 | J13: 27986.516 | K13: 31152.326 | L13: 19942.025 | M13: 30065.138 | N13: 22406.702
A14: 4001210780 | B14: 매출총이익(손실) | C14: 백만원 | D14: 12064.879 | E14: 15479.756 | F14: 9032.8738 | G14: 12970.533 | H14: 16040.83 | I14: 20185.678 | J14: 18735.051 | K14: 16524.077 | L14: 14645.189 | M14: 18828.515 | N14: 19359.141
A15: 4001290000 | B15: 판매비와관리비(*) | C15: 백만원 | D15: 11673.425 | E15: 13048.805 | F15: 11722.846 | G15: 9942.4785 | H15: 10467.713 | I15: 13010.374 | J15: 12558.272 | K15: 12038.2 | L15: 12861.812 | M15: 12467.433 | N15: 12248.046
A16: 4001290010 | B16: 인건비(*) | C16: 백만원 | D16: 4417.614 | E16: 4361.619 | F16: 4091.537 | G16: 4084.438 | H16: 4266.409 | I16: 5320.179 | J16: 4101.076 | K16: 4100.136 | L16: 4167.65 | M16: 4289.259 | N16: 3754.945
A17: 4001290020 | B17: 유무형자산상각비(*) | C17: 백만원 | D17: 985.161 | E17: 984.234 | F17: 954.462 | G17: 935.893 | H17: 937.219 | I17: 1047.862 | J17: 1428.892 | K17: 1468.03 | L17: 1829.404 | M17: 1803.772 | N17: 1880.601
A18: 4001211300 | B18: 연구개발비 | C18: 백만원 | D18: 4189.642 | E18: 4113.692 | F18: 3915.861 | G18: 3433.152 | H18: 3969.884 | I18: 4518.248 | J18: 4553.035 | K18: 5626.013 | L18: 3893.984 | M18: 4376.273 | N18: 3618.253
A19: 4001211060 | B19: 광고선전비 | C19: 백만원
A20: 4001290040 | B20: 판매비(*) | C20: 백만원 | D20: 305.425 | E20: 1358.089 | F20: 1136.518 | G20: -121.172 | H20: -369.252 | I20: -109.802 | J20: 429.189 | K20: -960.53 | L20: 550.735 | M20: 170.88 | N20: 1348.717
A21: 4001290090 | B21: 관리비(*) | C21: 백만원 | D21: 1426.618 | E21: 1761.52 | F21: 1419.439 | G21: 1406.761 | H21: 1523.623 | I21: 1720.977 | J21: 1404.204 | K21: 1466.843 | L21: 2193.347 | M21: 1237.775 | N21: 1337.31
A22: 4001290110 | B22: 기타원가성비용(*) | C22: 백만원
A23: 4001211420 | B23: 기타 | C23: 백만원 | D23: 348.965 | E23: 469.651 | F23: 205.029 | G23: 203.408 | H23: 139.83 | I23: 512.91 | J23: 641.876 | K23: 337.708 | L23: 226.692 | M23: 589.474 | N23: 308.22
A24: 4001211430 | B24: 영업이익(손실) | C24: 백만원 | D24: 391.45394 | E24: 2430.9511 | F24: -2689.9726 | G24: 3028.0547 | H24: 5573.1168 | I24: 7175.3038 | J24: 6176.779 | K24: 4485.8777 | L24: 1783.3769 | M24: 6361.0817 | N24: 7111.0949
A25: 4001290120 | B25: 금융수익(*) | C25: 백만원 | D25: 567.531 | E25: 656.843 | F25: 510.283 | G25: 2147.428 | H25: 549.529 | I25: 756.944 | J25: 362.569 | K25: 1031.955 | L25: 857.441 | M25: 4146.555 | N25: -4293.175
A26: 4001290750 | B26: 이자수익 | C26: 백만원 | D26: 288.958 | E26: 279.396 | F26: 332.861 | G26: 266.95 | H26: 273.223 | I26: 248.92 | J26: 204.423 | K26: 124.029 | L26: 112.246 | M26: 90.621 | N26: 106.93
A27: 4001290760 | B27: 배당금수익 | C27: 백만원
A28: 4001211480 | B28: 외환이익(*) | C28: 백만원 | D28: 278.573 | E28: 377.447 | F28: 177.422 | G28: 1775.97 | H28: 276.306 | I28: 116.236 | J28: 158.146 | K28: 900.989 | L28: 745.195 | M28: 4055.934 | N28: -4400.105
A29: 4001211520 | B29: 대손충당금환입액 | C29: 백만원 | G29: 104.508 | I29: 391.788 | K29: 6.937
A30: 4001211600 | B30: 매출채권처분이익 | C30: 백만원
A31: 4001211605 | B31: 당기손익-공정가치측정 금융자산관련이익 | C31: 백만원
A32: 4001290130 | B32: 금융자산처분이익(*) | C32: 백만원
A33: 4001290150 | B33: 금융자산평가이익(*) | C33: 백만원
A34: 4001211720 | B34: 금융자산손상차손환입(*) | C34: 백만원
A35: 4001211680 | B35: 파생상품이익(*) | C35: 백만원
A36: 4001290170 | B36: 기타금융수익(*) | C36: 백만원
A37: 4001290180 | B37: 금융원가(*) | C37: 백만원 | D37: 2623.478 | E37: 1992.308 | F37: 241.71 | G37: 1655.046 | H37: 4431.189 | I37: 3954.907 | J37: -458.31 | K37: 8065.787 | L37: 2220.026 | M37: 4778.148 | N37: 3088.027
A38: 4001290770 | B38: 이자비용 | C38: 백만원 | D38: 1022.592 | E38: 1201.502 | F38: 1408.632 | G38: 2041.622 | H38: 1897.945 | I38: 2036.685 | J38: 2317.653 | K38: 2120.32 | L38: 2070.21 | M38: 2473.559 | N38: 2757.012
A39: 4001211820 | B39: 외환손실(*) | C39: 백만원 | D39: 1600.886 | E39: 790.806 | F39: -1166.922 | G39: -386.576 | H39: 2533.244 | I39: 1918.222 | J39: -2775.963 | K39: 5945.467 | L39: 149.816 | M39: 454.589 | N39: 331.015
A40: 4001211860 | B40: 대손상각비 | C40: 백만원 | M40: 1850
A41: 4001211865 | B41: 당기손익-공정가치측정 금융자산관련손실 | C41: 백만원
A42: 4001211940 | B42: 매출채권처분손실 | C42: 백만원
A43: 4001290190 | B43: 금융자산처분손실(*) | C43: 백만원
A44: 4001290210 | B44: 금융자산평가손실(*) | C44: 백만원
A45: 4001212060 | B45: 금융자산손상차손(*) | C45: 백만원
A46: 4001212020 | B46: 파생상품손실(*) | C46: 백만원
A47: 4001290230 | B47: 기타금융원가(*) | C47: 백만원
A48: 4001290240 | B48: 기타수익(*) | C48: 백만원 | D48: 3884.05 | E48: 1370.497 | F48: 2311.968 | G48: 2779.099 | H48: 3039.781 | I48: 4595.377 | J48: 2970.072 | K48: 3288.521 | L48: 2295.6 | M48: 22828.642 | N48: -6174.045
A49: 4001280000 | B49: 이자수익 | C49: 백만원
A50: 4001280010 | B50: 배당금수익 | C50: 백만원
A51: 4001290250 | B51: 외환이익(*) | C51: 백만원 | D51: 1544.842 | E51: 167.568 | F51: 906.21 | G51: -509.244 | H51: 2037.124 | I51: 2051.843 | J51: -595.239 | K51: 4037.772 | L51: 334.78 | M51: -143.317 | N51: 3481.174
A52: 4001280050 | B52: 재고자산감모손실환입 | C52: 백만원
A53: 4001280060 | B53: 재고자산폐기(처분)이익 | C53: 백만원
A54: 4001280065 | B54: 당기손익-공정가치측정 금융자산평가이익 | C54: 백만원
A55: 4001290260 | B55: 자산처분(폐기)이익(*) | C55: 백만원 | D55: 5.438 | E55: 32.315 | F55: 48.11 | G55: 0.307 | H55: 861.856 | I55: 2108.197 | K55: 3.087 | L55: 30.221 | M55: 3.879 | N55: 5.908
A56: 4001280140 | B56: 자산평가이익 | C56: 백만원
A57: 4001290280 | B57: 자산손상차손환입(*) | C57: 백만원
A58: 4001290300 | B58: 파생상품이익(*) | C58: 백만원 | D58: 2321.98 | E58: 1095.764 | F58: 1284.303 | G58: 3172.16 | H58: 69 | I58: 368.37 | J58: 3508.364 | K58: -805.354 | L58: 1897.562 | M58: 22877.879 | N58: -9740.065
A59: 4001280240 | B59: 임대료수익 | C59: 백만원 | D59: 3 | E59: 40.427 | F59: 44.7 | G59: 45.9 | H59: 45.9 | I59: 20.53 | J59: 10.5 | K59: 10.5 | L59: 24.26 | M59: 36.9 | N59: 37.5
A60: 4001280250 | B60: 로열티수익 | C60: 백만원
A61: 4001280260 | B61: 수수료수익 | C61: 백만원
A62: 4001280270 | B62: 대손충당금환입 | C62: 백만원
A63: 4001280280 | B63: 충당부채환입액 | C63: 백만원
A64: 4001290310 | B64: 기타(*) | C64: 백만원 | D64: 8.79 | E64: 34.423 | F64: 28.645 | G64: 69.976 | H64: 25.901 | I64: 46.437 | J64: 46.447 | K64: 42.516 | L64: 8.777 | M64: 53.301 | N64: 41.438
A65: 4001290320 | B65: 기타비용(*) | C65: 백만원 | D65: 10224.085 | E65: 3350.324 | F65: 13001.045 | G65: -2813.657 | H65: 15357.19 | I65: 11398.289 | J65: -7874.135 | K65: 40548.749 | L65: 4444.638 | M65: 574.804 | N65: 1711.079
A66: 4001280400 | B66: 이자비용 | C66: 백만원
A67: 4001290330 | B67: 외환손실(*) | C67: 백만원 | D67: 227.607 | E67: 379.015 | F67: 2802.457 | G67: 808.59 | H67: 60.173 | I67: 114.596 | J67: 1583.302 | K67: -800.821 | L67: 451.231 | M67: 2544.441 | N67: -624.072
A68: 4001280440 | B68: 재고자산감모손실 | C68: 백만원
A69: 4001280450 | B69: 재고자산폐기(처분)손실 | C69: 백만원
A70: 4001280455 | B70: 당기손익-공정가치측정 금융자산평가손실 | C70: 백만원
A71: 4001290340 | B71: 자산처분(폐기)손실(*) | C71: 백만원 | H71: 256.899 | I71: -228.323 | K71: 0.001 | L71: 0.199
A72: 4001280540 | B72: 자산평가손실 | C72: 백만원
A73: 4001290360 | B73: 자산손상차손(*) | C73: 백만원 | G73: 3196.248 | K73: 8008.672 | L73: 1.67 | M73: -1.67
A74: 4001290380 | B74: 파생상품손실(*) | C74: 백만원 | D74: 9880.043 | E74: 2872.55 | F74: 10162.204 | G74: -6857.914 | H74: 14992.432 | I74: 11189.196 | J74: -9465.817 | K74: 33337.795 | L74: 3969.376 | M74: -1971.068 | N74: 2332.346
A75: 4001280650 | B75: 기타대손상각비 | C75: 백만원
A76: 4001280660 | B76: 충당부채전입액 | C76: 백만원
A77: 4001290390 | B77: 기타(*) | C77: 백만원 | D77: 116.435 | E77: 98.759 | F77: 36.384 | G77: 39.419 | H77: 47.686 | I77: 322.82 | J77: 8.38 | K77: 3.102 | L77: 22.162 | M77: 3.101 | N77: 2.805
A78: 4001290640 | B78: 종속기업,공동지배기업및관계기업관련손익(*) | C78: 백만원
A79: 4001290650 | B79: 지분법손익(*) | C79: 백만원
A80: 4001290680 | B80: 종속기업,공동지배기업및관계기업투자주식처분손익(*) | C80: 백만원
A81: 4001290710 | B81: 종속기업,공동지배기업및관계기업투자주식손상관련손익(*) | C81: 백만원
A82: 4001290740 | B82: 기타(*) | C82: 백만원
A83: 4001212380 | B83: 법인세비용차감전계속사업이익 | C83: 백만원 | D83: -8004.5285 | E83: -884.3424 | F83: -13110.477 | G83: 9113.195 | H83: -10625.951 | I83: -2825.5715 | J83: 17841.865 | K83: -39808.185 | L83: -1728.2468 | M83: 27983.327 | N83: -8155.2323
A84: 4001212390 | B84: 법인세비용 | C84: 백만원 | D84: -776.35285 | E84: 78.07228 | F84: -1537.1441 | G84: 446.60327 | H84: -2410.7002 | I84: -1401.3293 | J84: 3736.7567 | K84: -13372.116 | L84: -140.8909 | M84: 6260.4964 | N84: -1468.3379
A85: 4001212400 | B85: 종속회사매수일전순손익 | C85: 백만원
A86: 4001212410 | B86: 처분된종속회사순손익 | C86: 백만원
A87: 4001212420 | B87: 계속영업이익(손실) | C87: 백만원 | D87: -7228.1757 | E87: -962.41468 | F87: -11573.333 | G87: 8666.5918 | H87: -8215.2512 | I87: -1424.2422 | J87: 14105.109 | K87: -26436.068 | L87: -1587.3559 | M87: 21722.83 | N87: -6686.8943
A88: 4001212430 | B88: 중단영업이익(손실) | C88: 백만원
A89: 4001212450 | B89: 당기순이익(손실) | C89: 백만원 | D89: -7228.1757 | E89: -962.41468 | F89: -11573.333 | G89: 8666.5918 | H89: -8215.2512 | I89: -1424.2422 | J89: 14105.109 | K89: -26436.068 | L89: -1587.3559 | M89: 21722.83 | N89: -6686.8943
A90: 4001220000 | B90: 기타포괄손익(*) | C90: 백만원 | D90: -1207.7517 | E90: 644.60171 | F90: 576.04549 | G90: -853.01479 | H90: -440.86965 | I90: -155.65448 | J90: 75.42464 | K90: -145.6864 | L90: -1416.105 | M90: 685.78781 | N90: 597.65612
A91: 4001220120 | B91: 총포괄손익 | C91: 백만원 | D91: -8435.9274 | E91: -317.81297 | F91: -10997.287 | G91: 7813.577 | H91: -8656.1208 | I91: -1579.8967 | J91: 14180.533 | K91: -26581.755 | L91: -3003.4609 | M91: 22408.618 | N91: -6089.2382
A92: 4001230000 | B92: (당기순손익귀속)지배기업주주지분 | C92: 백만원 | D92: -6226.9136 | E92: -440.56123 | F92: -11253.544 | G92: 8611.3801 | H92: -8251.3096 | I92: -1138.4768 | J92: 14599.37 | K92: -26090.96 | L92: -1326.1644 | M92: 21499.9 | N92: -6180.42
A93: 4001230030 | B93: (당기순손익귀속)비지배주주지분 | C93: 백만원 | D93: -1001.2621 | E93: -521.85346 | F93: -319.7889 | G93: 55.21168 | H93: 36.05841 | I93: -285.76539 | J93: -494.26138 | K93: -345.1082 | L93: -261.19152 | M93: 222.93059 | N93: -506.47428
A94: 4001230060 | B94: (총포괄손익귀속)지배기업주주지분 | C94: 백만원 | D94: -7378.6536 | E94: 196.25246 | F94: -10691.49 | G94: 7812.0162 | H94: -8685.918 | I94: -1271.4231 | J94: 14691.398 | K94: -26237.784 | L94: -2670.568 | M94: 22178.274 | N94: -5595.151
A95: 4001230070 | B95: (총포괄손익귀속)비지배주주지분 | C95: 백만원 | D95: -1057.2738 | E95: -514.06543 | F95: -305.79782 | G95: 1.5608 | H95: 29.79719 | I95: -308.47361 | J95: -510.86465 | K95: -343.97072 | L95: -332.89291 | M95: 230.34408 | N95: -494.08722
A96: 4001230080 | B96: 주당계속영업이익 | C96: 원
A97: 4001230090 | B97: 주당순손익 | C97: 원
A98: 4001230100 | B98: 희석주당계속영업이익 | C98: 원
A99: 4001230110 | B99: 희석주당순손익 | C99: 원
A100: 4001230120 | B100: (지배기업주주지분)주당계속영업이익 | C100: 원 | D100: -174 | E100: -12 | F100: -315 | G100: 241 | H100: -231 | I100: -32 | J100: 408 | K100: -729 | L100: -37 | M100: 602 | N100: -173
...

Sheet IS(Yearly)
A2: Financial Statements
A3: Company | B3: A089030(테크윙) - Fiscal Month:12, 201106부터 IFRS 적용
A4: Type | B4: 연결 | C4: Accounting Std. | D4: IFRS
A5: Report | B5: 손익계산서 | C5: New
A6: Form | B6: 약식(COMPARE)
A7: Output | B7: 결산 | C7: 백만원
A8: Fiscal Year | B8: 2023 | C8: Current
A9: 계정코드 | B9: 계정명 | C9: 단위 | D9: 202312 | E9: 202412
D10: IFRS(연결) | E10: IFRS(연결)
A11: 4001210000 | B11: 매출액(수익)(*) | C11: 백만원 | D11: 133604.26 | E11: 185507.17
A12: 4001210010 | B12: *수출(*) | C12: 백만원 | E12: 138289.85
A13: 4001210020 | B13: *내수 | C13: 백만원 | E13: 47217.321
A14: 4001210320 | B14: 매출원가(*) | C14: 백만원 | D14: 84056.218 | E14: 114021.53
A15: 4001210780 | B15: 매출총이익(손실) | C15: 백만원 | D15: 49548.043 | E15: 71485.637
A16: 4001290000 | B16: 판매비와관리비(*) | C16: 백만원 | D16: 46387.556 | E16: 48074.559
A17: 4001290010 | B17: 인건비(*) | C17: 백만원 | D17: 16955.208 | E17: 17787.8
A18: 4001290020 | B18: 유무형자산상각비(*) | C18: 백만원 | D18: 3859.75 | E18: 4882.003
A19: 4001211300 | B19: 연구개발비 | C19: 백만원 | D19: 15652.347 | E19: 18667.18
A20: 4001211060 | B20: 광고선전비 | C20: 백만원
A21: 4001290040 | B21: 판매비(*) | C21: 백만원 | D21: 2678.86 | E21: -1010.395
A22: 4001290090 | B22: 관리비(*) | C22: 백만원 | D22: 6014.338 | E22: 6115.647
A23: 4001290110 | B23: 기타원가성비용(*) | C23: 백만원
A24: 4001211420 | B24: 기타 | C24: 백만원 | D24: 1227.053 | E24: 1632.324
A25: 4001211430 | B25: 영업이익(손실) | C25: 백만원 | D25: 3160.4871 | E25: 23411.077
A26: 4001290120 | B26: 금융수익(*) | C26: 백만원 | D26: 3882.085 | E26: 2700.997
A27: 4001290750 | B27: 이자수익 | C27: 백만원 | D27: 1168.165 | E27: 850.595
A28: 4001290760 | B28: 배당금수익 | C28: 백만원
A29: 4001211480 | B29: 외환이익(*) | C29: 백만원 | D29: 2609.412 | E29: 1451.677
A30: 4001211520 | B30: 대손충당금환입액 | C30: 백만원 | D30: 104.508 | E30: 398.725
A31: 4001211600 | B31: 매출채권처분이익 | C31: 백만원
A32: 4001211605 | B32: 당기손익-공정가치측정 금융자산관련이익 | C32: 백만원
A33: 4001290130 | B33: 금융자산처분이익(*) | C33: 백만원
A34: 4001290150 | B34: 금융자산평가이익(*) | C34: 백만원
A35: 4001211720 | B35: 금융자산손상차손환입(*) | C35: 백만원
A36: 4001211680 | B36: 파생상품이익(*) | C36: 백만원
A37: 4001290170 | B37: 기타금융수익(*) | C37: 백만원
A38: 4001290180 | B38: 금융원가(*) | C38: 백만원 | D38: 6512.542 | E38: 15993.573
A39: 4001290770 | B39: 이자비용 | C39: 백만원 | D39: 5674.348 | E39: 8372.603
A40: 4001211820 | B40: 외환손실(*) | C40: 백만원 | D40: 838.194 | E40: 7620.97
A41: 4001211860 | B41: 대손상각비 | C41: 백만원
A42: 4001211865 | B42: 당기손익-공정가치측정 금융자산관련손실 | C42: 백만원
A43: 4001211940 | B43: 매출채권처분손실 | C43: 백만원
A44: 4001290190 | B44: 금융자산처분손실(*) | C44: 백만원
A45: 4001290210 | B45: 금융자산평가손실(*) | C45: 백만원
A46: 4001212060 | B46: 금융자산손상차손(*) | C46: 백만원
A47: 4001212020 | B47: 파생상품손실(*) | C47: 백만원
A48: 4001290230 | B48: 기타금융원가(*) | C48: 백만원
A49: 4001290240 | B49: 기타수익(*) | C49: 백만원 | D49: 10345.614 | E49: 13893.751
A50: 4001280000 | B50: 이자수익 | C50: 백만원
A51: 4001280010 | B51: 배당금수익 | C51: 백만원
A52: 4001290250 | B52: 외환이익(*) | C52: 백만원 | D52: 2109.376 | E52: 7531.5
A53: 4001280050 | B53: 재고자산감모손실환입 | C53: 백만원
A54: 4001280060 | B54: 재고자산폐기(처분)이익 | C54: 백만원
A55: 4001280065 | B55: 당기손익-공정가치측정 금융자산평가이익 | C55: 백만원
A56: 4001290260 | B56: 자산처분(폐기)이익(*) | C56: 백만원 | D56: 86.17 | E56: 2973.14
A57: 4001280140 | B57: 자산평가이익 | C57: 백만원
A58: 4001290280 | B58: 자산손상차손환입(*) | C58: 백만원
A59: 4001290300 | B59: 파생상품이익(*) | C59: 백만원 | D59: 7874.207 | E59: 3140.38
A60: 4001280240 | B60: 임대료수익 | C60: 백만원 | D60: 134.027 | E60: 87.43
A61: 4001280250 | B61: 로열티수익 | C61: 백만원
A62: 4001280260 | B62: 수수료수익 | C62: 백만원
A63: 4001280270 | B63: 대손충당금환입 | C63: 백만원
A64: 4001280280 | B64: 충당부채환입액 | C64: 백만원
A65: 4001290310 | B65: 기타(*) | C65: 백만원 | D65: 141.834 | E65: 161.301
A66: 4001290320 | B66: 기타비용(*) | C66: 백만원 | D66: 23761.797 | E66: 59430.093
A67: 4001280400 | B67: 이자비용 | C67: 백만원
A68: 4001290330 | B68: 외환손실(*) | C68: 백만원 | D68: 4217.669 | E68: 957.25
A69: 4001280440 | B69: 재고자산감모손실 | C69: 백만원
A70: 4001280450 | B70: 재고자산폐기(처분)손실 | C70: 백만원
A71: 4001280455 | B71: 당기손익-공정가치측정 금융자산평가손실 | C71: 백만원
A72: 4001290340 | B72: 자산처분(폐기)손실(*) | C72: 백만원 | E72: 28.577
A73: 4001280540 | B73: 자산평가손실 | C73: 백만원
A74: 4001290360 | B74: 자산손상차손(*) | C74: 백만원 | D74: 3196.248 | E74: 8008.672
A75: 4001290380 | B75: 파생상품손실(*) | C75: 백만원 | D75: 16056.883 | E75: 50053.606
A76: 4001280650 | B76: 기타대손상각비 | C76: 백만원
A77: 4001280660 | B77: 충당부채전입액 | C77: 백만원
A78: 4001290390 | B78: 기타(*) | C78: 백만원 | D78: 290.997 | E78: 381.988
A79: 4001290640 | B79: 종속기업,공동지배기업및관계기업관련손익(*) | C79: 백만원
A80: 4001290650 | B80: 지분법손익(*) | C80: 백만원
A81: 4001290680 | B81: 종속기업,공동지배기업및관계기업투자주식처분손익(*) | C81: 백만원
A82: 4001290710 | B82: 종속기업,공동지배기업및관계기업투자주식손상관련손익(*) | C82: 백만원
A83: 4001290740 | B83: 기타(*) | C83: 백만원
A84: 4001212380 | B84: 법인세비용차감전계속사업이익 | C84: 백만원 | D84: -12886.153 | E84: -35417.842
A85: 4001212390 | B85: 법인세비용 | C85: 백만원 | D85: -1788.8214 | E85: -13447.389
A86: 4001212400 | B86: 종속회사매수일전순손익 | C86: 백만원
A87: 4001212410 | B87: 처분된종속회사순손익 | C87: 백만원
A88: 4001212420 | B88: 계속영업이익(손실) | C88: 백만원 | D88: -11097.331 | E88: -21970.453
A89: 4001212430 | B89: 중단영업이익(손실) | C89: 백만원
A90: 4001212450 | B90: 당기순이익(손실) | C90: 백만원 | D90: -11097.331 | E90: -21970.453
A91: 4001220000 | B91: 기타포괄손익(*) | C91: 백만원 | D91: -840.1193 | E91: -666.78589
A92: 4001220120 | B92: 총포괄손익 | C92: 백만원 | D92: -11937.451 | E92: -22637.239
A93: 4001230000 | B93: (당기순손익귀속)지배기업주주지분 | C93: 백만원 | D93: -9309.6387 | E93: -20881.377
A94: 4001230030 | B94: (당기순손익귀속)비지배주주지분 | C94: 백만원 | D94: -1787.6928 | E94: -1089.0766
A95: 4001230060 | B95: (총포괄손익귀속)지배기업주주지분 | C95: 백만원 | D95: -10061.874 | E95: -21503.727
A96: 4001230070 | B96: (총포괄손익귀속)비지배주주지분 | C96: 백만원 | D96: -1875.5763 | E96: -1133.5118
A97: 4001230080 | B97: 주당계속영업이익 | C97: 원
A98: 4001230090 | B98: 주당순손익 | C98: 원
A99: 4001230100 | B99: 희석주당계속영업이익 | C99: 원
A100: 4001230110 | B100: 희석주당순손익 | C100: 원
A101: 4001230120 | B101: (지배기업주주지분)주당계속영업이익 | C101: 원 | D101: -260 | E101: -584
...

Sheet BS(Quaterly)
A1: Financial Statements
A2: Company | B2: A089030(테크윙) - Fiscal Month:12, 201106부터 IFRS 적용
A3: Type | B3: 연결 | C3: Accounting Std. | D3: IFRS
A4: Report | B4: 재무상태표 | C4: New
A5: Form | B5: 약식(COMPARE)
A6: Output | B6: 당분기 | C6: 백만원
A7: Fiscal Year | B7: 2023 | C7: Current
A8: 계정코드 | B8: 계정명 | C8: 단위 | D8: 202303(1Q) | E8: 202306(2Q) | F8: 202309(3Q) | G8: 202312(4Q) | H8: 202403(1Q) | I8: 202406(2Q) | J8: 202409(3Q) | K8: 202412(4Q) | L8: 202503(1Q) | M8: 202506(2Q) | N8: 202509(3Q)
D9: IFRS(연결) | E9: IFRS(연결) | F9: IFRS(연결) | G9: IFRS(연결) | H9: IFRS(연결) | I9: IFRS(연결) | J9: IFRS(연결) | K9: IFRS(연결) | L9: IFRS(연결) | M9: IFRS(연결) | N9: IFRS(연결)
A10: 4001190010 | B10: 자산(*) | C10: 백만원 | D10: 479198.05 | E10: 478999.32 | F10: 484835.75 | G10: 485887.42 | H10: 499714.22 | I10: 498871.66 | J10: 502168.99 | K10: 506220.63 | L10: 520661.09 | M10: 541601.16 | N10: 551448.91
A11: 4001190240 | B11: 유동자산(*) | C11: 백만원 | D11: 180751.07 | E11: 166659.8 | F11: 153434.48 | G11: 143794.84 | H11: 155733.62 | I11: 168836.45 | J11: 163099.45 | K11: 156076.11 | L11: 153663.68 | M11: 173129.16 | N11: 187259.66
A12: 4001190250 | B12: 재고자산(*) | C12: 백만원 | D12: 86195.41 | E12: 83209.054 | F12: 88246.809 | G12: 81331.311 | H12: 83827.093 | I12: 83475.529 | J12: 84475.992 | K12: 79265.623 | L12: 91638.836 | M12: 108747.89 | N12: 115521.83
A13: 4001190260 | B13: 유동생물자산(*) | C13: 백만원
A14: 4001190270 | B14: 유동금융자산(*) | C14: 백만원 | D14: 7775.4743 | E14: 6444.0694 | F14: 5162.4138 | G14: 6452.2612 | H14: 3707.2993 | I14: 3921.359 | J14: 5048.5443 | K14: 4200.211 | L14: 6103.449 | M14: 4479.677 | N14: 4101.568
A15: 4001190300 | B15: 매출채권및기타유동채권(*) | C15: 백만원 | D15: 49670.192 | E15: 42062.831 | F15: 36836.223 | G15: 40094.052 | H15: 38274.419 | I15: 57599.209 | J15: 46240.677 | K15: 43944.254 | L15: 33980.857 | M15: 40084.768 | N15: 42068.507
A16: 4001113900 | B16: 당기법인세자산(선급법인세) | C16: 백만원 | D16: 48.99475 | E16: 0.62402 | F16: 93.41766 | G16: 363.58251 | H16: 438.66722 | J16: 41.04539 | K16: 1646.7075 | L16: 78.23437 | M16: 114.31735 | N16: 282.45699
A17: 4001180995 | B17: 계약자산(**) | C17: 백만원 | N17: 5478.6281
A18: 4001113903 | B18: 반품(환불)자산 | C18: 백만원
A19: 4001113904 | B19: 배출권 | C19: 백만원
A20: 4001190340 | B20: 기타유동자산(*) | C20: 백만원 | D20: 5229.7052 | E20: 2803.3042 | F20: 1935.5383 | G20: 1939.525 | H20: 8431.5577 | I20: 3757.5103 | J20: 4679.2625 | K20: 1536.4635 | L20: 3367.7743 | M20: 2388.2689 | N20: 2798.7699
A21: 4001190370 | B21: 현금및현금성자산(*) | C21: 백만원 | D21: 31831.293 | E21: 32139.923 | F21: 21160.084 | G21: 13614.104 | H21: 21054.588 | I21: 20082.843 | J21: 22613.934 | K21: 25482.851 | L21: 18494.525 | M21: 17314.24 | N21: 17007.9
A22: 4001114130 | B22: 매각예정비유동자산및처분자산집단(*) | C22: 백만원
A23: 4001190020 | B23: 비유동자산(*) | C23: 백만원 | D23: 298446.99 | E23: 312339.51 | F23: 331401.27 | G23: 342092.59 | H23: 343980.6 | I23: 330035.21 | J23: 339069.54 | K23: 350144.52 | L23: 366997.42 | M23: 368472 | N23: 364189.25
A24: 4001190030 | B24: 유형자산(*) | C24: 백만원 | D24: 235582.97 | E24: 246417.26 | F24: 258925.47 | G24: 270618.68 | H24: 281658.52 | I24: 204878.91 | J24: 218568.64 | K24: 232023.07 | L24: 248029.36 | M24: 251545.64 | N24: 250021.09
A25: 4001190070 | B25: 무형자산(*) | C25: 백만원 | D25: 17826.275 | E25: 18686.467 | F25: 22028.51 | G25: 20950.303 | H25: 21122.681 | I25: 21292.491 | J25: 21533.563 | K25: 11735.798 | L25: 13030.108 | M25: 13466.56 | N25: 13715.81
A26: 4001190110 | B26: 비유동생물자산(*) | C26: 백만원
A27: 4001190120 | B27: 투자부동산(*) | C27: 백만원 | D27: 15928.243 | E27: 15894.261 | F27: 15860.278 | G27: 15826.295 | H27: 15792.312 | I27: 81561.498 | J27: 81405.461 | K27: 80608.319 | L27: 80131.729 | M27: 79655.14 | N27: 79178.55
A28: 4001190130 | B28: 장기금융자산(*) | C28: 백만원 | D28: 23331.734 | E28: 24344.071 | F28: 26579.955 | G28: 26967.577 | H28: 18088.181 | I28: 11819.751 | J28: 7251.7732 | K28: 7239.4133 | L28: 7268.8781 | M28: 11347.002 | N28: 8640.4733
A29: 4001111660 | B29: 관계기업등지분관련투자자산(*) | C29: 백만원
A30: 4001190160 | B30: 장기매출채권및기타비유동채권(*) | C30: 백만원 | D30: 1278.1649 | E30: 1103.7444 | F30: 964.10658 | G30: 1286.2612 | H30: 875.43852 | I30: 708.34249 | J30: 535.88769 | K30: 318.40496 | L30: 317.83148 | M30: 288.96311 | N30: 464.62829
A31: 4001112490 | B31: 이연법인세자산 | C31: 백만원 | D31: 4499.593 | E31: 5893.7065 | F31: 7042.9468 | G31: 6443.4651 | H31: 6443.4651 | I31: 9774.2134 | J31: 9774.2134 | K31: 18219.505 | L31: 18219.505 | M31: 12168.699 | N31: 12168.699
A32: 4001112500 | B32: 장기당기법인세자산 | C32: 백만원
A33: 4001180575 | B33: 계약자산(**) | C33: 백만원
A34: 4001112503 | B34: 반품(환불)자산 | C34: 백만원
A35: 4001112504 | B35: 배출권 | C35: 백만원
A36: 4001190200 | B36: 기타비유동자산(*) | C36: 백만원
A37: 4001112880 | B37: 기타금융업자산 | C37: 백만원
A38: 4001190440 | B38: 부채(*) | C38: 백만원 | D38: 260109.6 | E38: 260228.67 | F38: 277062.39 | G38: 270300.49 | H38: 297429.67 | I38: 298167 | J38: 287283.8 | K38: 317917.19 | L38: 340007.38 | M38: 338538.83 | N38: 354475.82
A39: 4001190610 | B39: 유동부채(*) | C39: 백만원 | D39: 180727.38 | E39: 173823.31 | F39: 140261.16 | G39: 139213.89 | H39: 167038.77 | I39: 151387.54 | J39: 200795.61 | K39: 218505.56 | L39: 242180.26 | M39: 241212.13 | N39: 162019.79
A40: 4001181470 | B40: 단기사채(**) | C40: 백만원
A41: 4001121700 | B41: 단기차입금(*) | C41: 백만원 | D41: 62250 | E41: 72500 | F41: 73500 | G41: 73873.215 | H41: 88543.331 | I41: 70240.038 | J41: 69235.837 | K41: 69134.845 | L41: 82630.896 | M41: 105500 | N41: 85500
A42: 4001190620 | B42: 유동성장기부채(*) | C42: 백만원 | D42: 84876.147 | E42: 75450.447 | F42: 36256.882 | G42: 38052.193 | H42: 39730.667 | I42: 34293.167 | J42: 88894.264 | K42: 95848.851 | L42: 96590.959 | M42: 91680.464 | N42: 42180.807
A43: 4001190630 | B43: 유동금융부채(*) | C43: 백만원 | D43: 11141.379 | E43: 9072.9089 | F43: 12102.619 | G43: 3134.8323 | H43: 12621.666 | I43: 19690.601 | J43: 7920.8261 | K43: 31870.606 | L43: 29145.237 | M43: 6820.1553 | N43: 10132.595
A44: 4001190660 | B44: 매입채무및기타유동채무(*) | C44: 백만원 | D44: 13688.387 | E44: 12386.245 | F44: 13879.052 | G44: 20668.425 | H44: 22677.214 | I44: 23500.404 | J44: 27081.967 | K44: 17984.827 | L44: 30812.918 | M44: 34326.573 | N44: 21688.371
A45: 4001190680 | B45: 유동종업원급여충당부채(*) | C45: 백만원 | D45: 1677.594 | J45: 1640.095
A46: 4001122460 | B46: 기타단기충당부채(*) | C46: 백만원 | D46: 600.28826 | E46: 547.36081 | F46: 556.29789 | G46: 628.42697 | H46: 572.16836 | I46: 548.089 | J46: 518.88851 | K46: 354.81218 | L46: 273.8182 | M46: 287.92085 | N46: 313.12882
A47: 4001122560 | B47: 당기법인세부채(미지급법인세) | C47: 백만원 | D47: 1937.1423 | E47: 601.01008 | I47: 202.174 | J47: 3942.9891 | K47: 570.0842 | L47: 407.77242 | M47: 138.33965 | N47: 118.93312
A48: 4001122561 | B48: 계약부채 | C48: 백만원
A49: 4001122562 | B49: 반품(환불)부채 | C49: 백만원
A50: 4001122563 | B50: 배출부채 | C50: 백만원
A51: 4001190690 | B51: 기타유동부채(*) | C51: 백만원 | D51: 4556.439 | E51: 3265.34 | F51: 3966.311 | G51: 2856.792 | H51: 2893.72 | I51: 2913.064 | J51: 1560.741 | K51: 2741.539 | L51: 2318.661 | M51: 2458.681 | N51: 2085.957
A52: 4001122680 | B52: 매각예정으로분류된처분자산집단에포함된부채(*) | C52: 백만원
A53: 4001190450 | B53: 비유동부채(*) | C53: 백만원 | D53: 79382.22 | E53: 86405.361 | F53: 136801.23 | G53: 131086.6 | H53: 130390.9 | I53: 146779.47 | J53: 86488.196 | K53: 99411.627 | L53: 97827.118 | M53: 97326.695 | N53: 192456.03
A54: 4001190460 | B54: 사채(*) | C54: 백만원
A55: 4001190470 | B55: 장기차입금(*) | C55: 백만원 | D55: 67892.78 | E55: 75773.69 | F55: 126671.04 | G55: 120237.75 | H55: 118316.46 | I55: 135045.17 | J55: 74655.72 | K55: 87725.52 | L55: 84435.32 | M55: 82511.76 | N55: 177236.22
A56: 4001190480 | B56: 비유동금융부채(*) | C56: 백만원 | D56: 122.76087 | E56: 166.71915 | F56: 124.89317 | G56: 97.30415 | H56: 80.46646 | I56: 61.84856 | J56: 59.58538 | K56: 71.83526 | L56: 45.16256 | M56: 2336.7163 | N56: 3151.2782
A57: 4001190500 | B57: 장기매입채무및기타비유동채무(*) | C57: 백만원 | D57: 169.5 | E57: 168.9 | F57: 27.4 | G57: 25.9 | H57: 25 | I57: 24.1 | J57: 26.9 | K57: 28.7 | L57: 29.3 | M57: 30.2 | N57: 29.4
A58: 4001190570 | B58: 비유동종업원급여충당부채(*) | C58: 백만원 | D58: 10963.454 | E58: 10116.522 | F58: 9824.119 | G58: 10583.786 | H58: 11458.866 | I58: 11503.679 | J58: 11568.733 | K58: 11426.622 | L58: 12530.634 | M58: 12317.31 | N58: 11903.175
A59: 4001121280 | B59: 기타장기충당부채(*) | C59: 백만원 | D59: 233.72413 | E59: 179.52971 | F59: 153.77718 | G59: 141.85971 | H59: 135.53477 | I59: 144.66906 | J59: 177.25709 | K59: 158.94971 | L59: 125.39975 | M59: 130.70853 | N59: 135.95411
A60: 4001121380 | B60: 이연법인세부채 | C60: 백만원
A61: 4001181370 | B61: 장기당기법인세부채(미지급법인세)(**) | C61: 백만원
A62: 4001121401 | B62: 계약부채 | C62: 백만원
A63: 4001121402 | B63: 반품(환불)부채 | C63: 백만원
A64: 4001121403 | B64: 배출부채 | C64: 백만원
A65: 4001190580 | B65: 기타비유동부채(*) | C65: 백만원 | H65: 374.57545 | L65: 661.30097
A66: 4001121620 | B66: 기타금융업부채 | C66: 백만원
A67: 4001190380 | B67: 자본(*) | C67: 백만원 | D67: 219088.46 | E67: 218770.65 | F67: 207773.36 | G67: 215586.94 | H67: 202284.55 | I67: 200704.66 | J67: 214885.19 | K67: 188303.43 | L67: 180653.71 | M67: 203062.33 | N67: 196973.09
A68: 4001130010 | B68: *수권주식수 | C68: 주 | D68: 200000000 | E68: 200000000 | F68: 200000000 | G68: 200000000 | H68: 200000000 | I68: 200000000 | J68: 200000000 | K68: 200000000 | L68: 200000000 | M68: 200000000 | N68: 200000000
A69: 4001130020 | B69: *주당액면가액 | C69: 원 | D69: 500 | E69: 500 | F69: 500 | G69: 500 | H69: 500 | I69: 500 | J69: 500 | K69: 500 | L69: 500 | M69: 500 | N69: 500
A70: 4001130030 | B70: *발행한주식총수(*) | C70: 주 | D70: 37353645 | E70: 37353645 | F70: 37353645 | G70: 37353645 | H70: 37353645 | I70: 37353645 | J70: 37353645 | K70: 37353645 | L70: 37353645 | M70: 37353645 | N70: 37353645
A71: 4001130040 | B71: *보통주 | C71: 주 | D71: 37353645 | E71: 37353645 | F71: 37353645 | G71: 37353645 | H71: 37353645 | I71: 37353645 | J71: 37353645 | K71: 37353645 | L71: 37353645 | M71: 37353645 | N71: 37353645
A72: 4001130050 | B72: *우선주 | C72: 주
A73: 4001190390 | B73: 지배기업주주지분(*) | C73: 백만원 | D73: 219584.92 | E73: 219781.17 | F73: 209089.68 | G73: 216901.7 | H73: 203569.52 | I73: 202298.1 | J73: 216989.5 | K73: 190751.71 | L73: 183434.88 | M73: 205613.16 | N73: 200086.91
A74: 4001130070 | B74: 자본금(*) | C74: 백만원 | D74: 18977.721 | E74: 18977.721 | F74: 18977.721 | G74: 18977.721 | H74: 18977.721 | I74: 18977.721 | J74: 18977.721 | K74: 18977.721 | L74: 18977.721 | M74: 18977.721 | N74: 18977.721
A75: 4001130670 | B75: 신종자본증권 | C75: 백만원
A76: 4001190400 | B76: 자본잉여금(*) | C76: 백만원 | D76: 40815.398 | E76: 39757.781 | F76: 40815.398 | G76: 40815.398 | H76: 40815.398 | I76: 40815.398 | J76: 40815.398 | K76: 40815.398 | L76: 40815.398 | M76: 40815.398 | N76: 39757.781
A77: 4001190420 | B77: 기타자본(*) | C77: 백만원 | D77: -14287.02 | E77: -14287.02 | F77: -14287.02 | G77: -14287.02 | H77: -14287.02 | I77: -14287.02 | J77: -14287.02 | K77: -14287.02 | L77: -14287.02 | M77: -14266.805 | N77: -14197.899
A78: 4001130360 | B78: 기타포괄손익누계액(*) | C78: 백만원 | D78: -1016.269 | E78: -40.21549 | F78: -1106.369 | G78: -1094.58 | H78: -1084.377 | I78: -1057.431 | J78: -1028.441 | K78: -981.226 | L78: -952.675 | M78: -1003.362 | N78: 86.76165
A79: 4001130470 | B79: 이익잉여금(결손금)(*) | C79: 백만원 | D79: 175095.09 | E79: 175372.91 | F79: 164689.95 | G79: 172490.18 | H79: 159147.8 | I79: 157849.43 | J79: 172511.84 | K79: 146226.84 | L79: 138881.46 | M79: 161090.2 | N79: 155462.55
A80: 4001130640 | B80: 비지배주주지분 | C80: 백만원 | D80: -496.46249 | E80: -1010.5279 | F80: -1316.3257 | G80: -1314.7649 | H80: -1284.9678 | I80: -1593.4414 | J80: -2104.306 | K80: -2448.2767 | L80: -2781.1696 | M80: -2550.8256 | N80: -3113.8192

Sheet BS(Yearly)
A2: Financial Statements
A3: Company | B3: A089030(테크윙) - Fiscal Month:12, 201106부터 IFRS 적용
A4: Type | B4: 연결 | C4: Accounting Std. | D4: IFRS
A5: Report | B5: 재무상태표 | C5: New
A6: Form | B6: 약식(COMPARE)
A7: Output | B7: 결산 | C7: 백만원
A8: Fiscal Year | B8: 2023 | C8: Current
A9: 계정코드 | B9: 계정명 | C9: 단위 | D9: 202312 | E9: 202412
D10: IFRS(연결) | E10: IFRS(연결)
A11: 4001190010 | B11: 자산(*) | C11: 백만원 | D11: 485887.42 | E11: 506220.63
A12: 4001190240 | B12: 유동자산(*) | C12: 백만원 | D12: 143794.84 | E12: 156076.11
A13: 4001190250 | B13: 재고자산(*) | C13: 백만원 | D13: 81331.311 | E13: 79265.623
A14: 4001190260 | B14: 유동생물자산(*) | C14: 백만원
A15: 4001190270 | B15: 유동금융자산(*) | C15: 백만원 | D15: 6452.2612 | E15: 4200.211
A16: 4001190300 | B16: 매출채권및기타유동채권(*) | C16: 백만원 | D16: 40094.052 | E16: 43944.254
A17: 4001113900 | B17: 당기법인세자산(선급법인세) | C17: 백만원 | D17: 363.58251 | E17: 1646.7075
A18: 4001180995 | B18: 계약자산(**) | C18: 백만원
A19: 4001113903 | B19: 반품(환불)자산 | C19: 백만원
A20: 4001113904 | B20: 배출권 | C20: 백만원
A21: 4001190340 | B21: 기타유동자산(*) | C21: 백만원 | D21: 1939.525 | E21: 1536.4635
A22: 4001190370 | B22: 현금및현금성자산(*) | C22: 백만원 | D22: 13614.104 | E22: 25482.851
A23: 4001114130 | B23: 매각예정비유동자산및처분자산집단(*) | C23: 백만원
A24: 4001190020 | B24: 비유동자산(*) | C24: 백만원 | D24: 342092.59 | E24: 350144.52
A25: 4001190030 | B25: 유형자산(*) | C25: 백만원 | D25: 270618.68 | E25: 232023.07
A26: 4001190070 | B26: 무형자산(*) | C26: 백만원 | D26: 20950.303 | E26: 11735.798
A27: 4001190110 | B27: 비유동생물자산(*) | C27: 백만원
A28: 4001190120 | B28: 투자부동산(*) | C28: 백만원 | D28: 15826.295 | E28: 80608.319
A29: 4001190130 | B29: 장기금융자산(*) | C29: 백만원 | D29: 26967.577 | E29: 7239.4133
A30: 4001111660 | B30: 관계기업등지분관련투자자산(*) | C30: 백만원
A31: 4001190160 | B31: 장기매출채권및기타비유동채권(*) | C31: 백만원 | D31: 1286.2612 | E31: 318.40496
A32: 4001112490 | B32: 이연법인세자산 | C32: 백만원 | D32: 6443.4651 | E32: 18219.505
A33: 4001112500 | B33: 장기당기법인세자산 | C33: 백만원
A34: 4001180575 | B34: 계약자산(**) | C34: 백만원
A35: 4001112503 | B35: 반품(환불)자산 | C35: 백만원
A36: 4001112504 | B36: 배출권 | C36: 백만원
A37: 4001190200 | B37: 기타비유동자산(*) | C37: 백만원
A38: 4001112880 | B38: 기타금융업자산 | C38: 백만원
A39: 4001190440 | B39: 부채(*) | C39: 백만원 | D39: 270300.49 | E39: 317917.19
A40: 4001190610 | B40: 유동부채(*) | C40: 백만원 | D40: 139213.89 | E40: 218505.56
A41: 4001181470 | B41: 단기사채(**) | C41: 백만원
A42: 4001121700 | B42: 단기차입금(*) | C42: 백만원 | D42: 73873.215 | E42: 69134.845
A43: 4001190620 | B43: 유동성장기부채(*) | C43: 백만원 | D43: 38052.193 | E43: 95848.851
A44: 4001190630 | B44: 유동금융부채(*) | C44: 백만원 | D44: 3134.8323 | E44: 31870.606
A45: 4001190660 | B45: 매입채무및기타유동채무(*) | C45: 백만원 | D45: 20668.425 | E45: 17984.827
A46: 4001190680 | B46: 유동종업원급여충당부채(*) | C46: 백만원
A47: 4001122460 | B47: 기타단기충당부채(*) | C47: 백만원 | D47: 628.42697 | E47: 354.81218
A48: 4001122560 | B48: 당기법인세부채(미지급법인세) | C48: 백만원 | E48: 570.0842
A49: 4001122561 | B49: 계약부채 | C49: 백만원
A50: 4001122562 | B50: 반품(환불)부채 | C50: 백만원
A51: 4001122563 | B51: 배출부채 | C51: 백만원
A52: 4001190690 | B52: 기타유동부채(*) | C52: 백만원 | D52: 2856.792 | E52: 2741.539
A53: 4001122680 | B53: 매각예정으로분류된처분자산집단에포함된부채(*) | C53: 백만원
A54: 4001190450 | B54: 비유동부채(*) | C54: 백만원 | D54: 131086.6 | E54: 99411.627
A55: 4001190460 | B55: 사채(*) | C55: 백만원
A56: 4001190470 | B56: 장기차입금(*) | C56: 백만원 | D56: 120237.75 | E56: 87725.52
A57: 4001190480 | B57: 비유동금융부채(*) | C57: 백만원 | D57: 97.30415 | E57: 71.83526
A58: 4001190500 | B58: 장기매입채무및기타비유동채무(*) | C58: 백만원 | D58: 25.9 | E58: 28.7
A59: 4001190570 | B59: 비유동종업원급여충당부채(*) | C59: 백만원 | D59: 10583.786 | E59: 11426.622
A60: 4001121280 | B60: 기타장기충당부채(*) | C60: 백만원 | D60: 141.85971 | E60: 158.94971
A61: 4001121380 | B61: 이연법인세부채 | C61: 백만원
A62: 4001181370 | B62: 장기당기법인세부채(미지급법인세)(**) | C62: 백만원
A63: 4001121401 | B63: 계약부채 | C63: 백만원
A64: 4001121402 | B64: 반품(환불)부채 | C64: 백만원
A65: 4001121403 | B65: 배출부채 | C65: 백만원
A66: 4001190580 | B66: 기타비유동부채(*) | C66: 백만원
A67: 4001121620 | B67: 기타금융업부채 | C67: 백만원
A68: 4001190380 | B68: 자본(*) | C68: 백만원 | D68: 215586.94 | E68: 188303.43
A69: 4001130010 | B69: *수권주식수 | C69: 주 | D69: 200000000 | E69: 200000000
A70: 4001130020 | B70: *주당액면가액 | C70: 원 | D70: 500 | E70: 500
A71: 4001130030 | B71: *발행한주식총수(*) | C71: 주 | D71: 37353645 | E71: 37353645
A72: 4001130040 | B72: *보통주 | C72: 주 | D72: 37353645 | E72: 37353645
A73: 4001130050 | B73: *우선주 | C73: 주
A74: 4001190390 | B74: 지배기업주주지분(*) | C74: 백만원 | D74: 216901.7 | E74: 190751.71
A75: 4001130070 | B75: 자본금(*) | C75: 백만원 | D75: 18977.721 | E75: 18977.721
A76: 4001130670 | B76: 신종자본증권 | C76: 백만원
A77: 4001190400 | B77: 자본잉여금(*) | C77: 백만원 | D77: 40815.398 | E77: 40815.398
A78: 4001190420 | B78: 기타자본(*) | C78: 백만원 | D78: -14287.02 | E78: -14287.02
A79: 4001130360 | B79: 기타포괄손익누계액(*) | C79: 백만원 | D79: -1094.58 | E79: -981.226
A80: 4001130470 | B80: 이익잉여금(결손금)(*) | C80: 백만원 | D80: 172490.18 | E80: 146226.84
A81: 4001130640 | B81: 비지배주주지분 | C81: 백만원 | D81: -1314.7649 | E81: -2448.2767

Sheet CF(Quaterly)
A1: Financial Statements
A2: Company | B2: A089030(테크윙) - Fiscal Month:12, 201106부터 IFRS 적용
A3: Type | B3: 연결 | C3: Accounting Std. | D3: IFRS
A4: Report | B4: 현금흐름표 | C4: New
A5: Form | B5: 약식(COMPARE)
A6: Output | B6: 당분기 | C6: 백만원
A7: Fiscal Year | B7: 2023 | C7: Current
A8: 계정코드 | B8: 계정명 | C8: 단위 | D8: 202303(1Q) | E8: 202306(2Q) | F8: 202309(3Q) | G8: 202312(4Q) | H8: 202403(1Q) | I8: 202406(2Q) | J8: 202409(3Q) | K8: 202412(4Q) | L8: 202503(1Q) | M8: 202506(2Q) | N8: 202509(3Q)
D9: IFRS(연결) | E9: IFRS(연결) | F9: IFRS(연결) | G9: IFRS(연결) | H9: IFRS(연결) | I9: IFRS(연결) | J9: IFRS(연결) | K9: IFRS(연결) | L9: IFRS(연결) | M9: IFRS(연결) | N9: IFRS(연결)
A10: 4001390000 | B10: 영업활동으로인한현금흐름(간접법)(*) | C10: 백만원 | D10: -2629.4205 | E10: 13689.146 | F10: 2128.4368 | G10: 7183.355 | H10: 1182.8776 | I10: 778.16298 | J10: 14072.245 | K10: 16688.992 | L10: 11817.977 | M10: -13964.963 | N10: -16824.52
A11: 4001310010 | B11: *(직접법)총현금유입(*) | C11: 백만원
A12: 4001310100 | B12: *(직접법)총현금유출(*) | C12: 백만원
A13: 4001310190 | B13: 당기순손익 | C13: 백만원 | D13: -7228.176 | E13: -962.414 | F13: -11573.333 | G13: 8666.592 | H13: -8215.251 | I13: -1424.242 | J13: 14105.108 | K13: -26436.068 | L13: -1587.356 | M13: 21722.83 | N13: -6686.894
A14: 4001310200 | B14: 법인세비용차감전계속사업이익 | C14: 백만원
A15: 4001390010 | B15: 현금유출이없는비용등가산(*) | C15: 백만원 | D15: 15997.485 | E15: 9463.341 | F15: 17653.505 | G15: 2577.557 | H15: 23771.87 | I15: 18883.593 | J15: -3676.517 | K15: 57651.79 | L15: 11297.985 | M15: 14873.196 | N15: 10291.266
A16: 4001390040 | B16: (현금유입이없는수익등차감)(*) | C16: 백만원 | D16: 2387.6 | E16: 2906.485 | F16: 3725.379 | G16: 3801.173 | H16: 5105.525 | I16: 5528.607 | J16: -1359.65 | K16: 16454.553 | L16: 2986.056 | M16: 26705.678 | N16: -10515.42
A17: 4001390060 | B17: 영업활동으로인한자산부채변동(운전자본변동)(*) | C17: 백만원 | D17: -5838.286 | E17: 12115.343 | F17: 1299.498 | G17: 2291.981 | H17: -6694.966 | I17: -9819.728 | J17: 5011.109 | K17: 4519.881 | L17: 6111.106 | M17: -20895.132 | N17: -27983.01
A18: 4001390070 | B18: 자산의감소(증가)(*) | C18: 백만원 | D18: 3875.527 | E18: 9243.811 | F18: 121.965 | G18: 866.956 | H18: -3941.294 | I18: -13601.949 | J18: 5276.406 | K18: 8404.437 | L18: -4210.68 | M18: -25130.979 | N18: -14625.834
A19: 4001390110 | B19: 부채의증가(감소)(*) | C19: 백만원 | D19: -9713.813 | E19: 2871.532 | F19: 1177.533 | G19: 1425.025 | H19: -2753.672 | I19: 3782.221 | J19: -265.297 | K19: -3884.556 | L19: 10321.786 | M19: 4235.847 | N19: -13357.176
A20: 4001312260 | B20: 정부보조금등의변동 | C20: 백만원
A21: 4001312270 | B21: 기타운전자본의변동 | C21: 백만원
A22: 4001312280 | B22: *영업에서창출된현금흐름 | C22: 백만원 | D22: 543.423 | E22: 17709.785 | F22: 3654.291 | G22: 9734.957 | H22: 3756.128 | I22: 2111.016 | J22: 16799.35 | K22: 19281.05 | L22: 12835.679 | M22: -11004.784 | N22: -13863.218
A23: 4001312290 | B23: 이자수입 | C23: 백만원 | D23: 316.95675 | E23: 280.50183 | F23: 423.46312 | G23: 182.21603 | H23: 269.81211 | I23: 233.25141 | J23: 152.23995 | K23: 42.50564 | L23: 244.16964 | M23: 85.56827 | N23: 101.8049
A24: 4001312300 | B24: 이자지급(-) | C24: 백만원 | D24: -1390.306 | E24: -1663.603 | F24: -1734.6444 | G24: -2573.5671 | H24: -2767.7746 | I24: -2830.651 | J24: -2835.5877 | K24: -2601.8342 | L24: -2689.5215 | M24: -2807.1897 | N24: -2887.7933
A25: 4001312310 | B25: 배당금수입 | C25: 백만원
A26: 4001312320 | B26: 배당금지급(-) | C26: 백만원
A27: 4001312330 | B27: 법인세환입 | C27: 백만원 | I27: 1189.2584 | J27: -43.75677 | K27: -32.72967 | L27: 1427.6496 | M27: -238.55813 | N27: -175.31343
A28: 4001312340 | B28: 법인세납부(-) | C28: 백만원 | D28: -2099.4953 | E28: -2637.5374 | F28: -214.67257 | G28: -160.25084 | H28: -75.28759 | I28: 75.28759
A29: 4001312350 | B29: 중단영업관련현금흐름 | C29: 백만원
A30: 4001390160 | B30: 투자활동으로인한현금흐름(*) | C30: 백만원 | D30: -13549.1 | E30: -16678.56 | F30: -24299.5 | G30: -12689.943 | H30: -5819.3599 | I30: 11872.217 | J30: -7978.7873 | K30: -27979.659 | L30: -30214.243 | M30: -2357.9848 | N30: -7066.6737
A31: 4001390170 | B31: 투자활동으로인한현금유입액(*) | C31: 백만원 | D31: 49998.022 | E31: -39876.292 | F31: 4213.8931 | G31: 1789.9608 | H31: 12390.906 | I31: 27656.652 | J31: 9610.3521 | K31: -4816.6861 | L31: 1407.4815 | M31: 1490.1966 | N31: 790.69272
A32: 4001390270 | B32: (투자활동으로인한현금유출액)(*) | C32: 백만원 | D32: 63547.122 | E32: -23197.732 | F32: 28513.393 | G32: 14479.903 | H32: 18210.266 | I32: 15784.435 | J32: 17589.139 | K32: 23162.972 | L32: 31621.725 | M32: 3848.1814 | N32: 7857.3664
A33: 4001321350 | B33: 이자수입 | C33: 백만원
A34: 4001321360 | B34: 이자지급(-) | C34: 백만원
A35: 4001321370 | B35: 배당금수입 | C35: 백만원
A36: 4001321380 | B36: 배당금지급(-) | C36: 백만원
A37: 4001321390 | B37: 법인세환입 | C37: 백만원
A38: 4001321400 | B38: 법인세납부(-) | C38: 백만원
A39: 4001321410 | B39: 중단영업관련현금흐름 | C39: 백만원
A40: 4001390370 | B40: 재무활동으로인한현금흐름(*) | C40: 백만원 | D40: 24538.23 | E40: 3662.0523 | F40: 11233.131 | G40: -2080.1852 | H40: 12217.055 | I40: -13408.065 | J40: -4105.3001 | K40: 13777.5 | L40: 10967.329 | M40: 15780.797 | N40: 23412.781
A41: 4001390380 | B41: 재무활동으로인한현금유입액(*) | C41: 백만원 | D41: 30000 | E41: 20500 | F41: 13000 | G41: -9126.7851 | H41: 20043.172 | I41: 17000 | K41: 16362.873 | L41: 15000 | M41: 24000 | N41: 50900
A42: 4001390470 | B42: (재무활동으로인한현금유출액)(*) | C42: 백만원 | D42: 5461.7696 | E42: 12191.686 | F42: 1766.8689 | G42: -7046.5999 | H42: 7826.1171 | I42: 25761.804 | J42: 4105.3001 | K42: 2585.3724 | L42: 4032.6709 | M42: 3572.9416 | N42: 27487.219
A43: 4001330680 | B43: 이자수입 | C43: 백만원
A44: 4001330690 | B44: 이자지급(-) | C44: 백만원
A45: 4001330700 | B45: 배당금수입 | C45: 백만원
A46: 4001330710 | B46: 배당금지급(-) | C46: 백만원 | E46: -4646.2616 | I46: -4646.2616 | M46: -4646.2616
A47: 4001330720 | B47: 법인세환입 | C47: 백만원
A48: 4001330730 | B48: 법인세납부(-) | C48: 백만원
A49: 4001330740 | B49: 중단영업관련현금흐름 | C49: 백만원
A50: 4001340000 | B50: 영업투자재무활동기타현금흐름 | C50: 백만원
A51: 4001340010 | B51: 연결범위변동으로인한현금의증가 | C51: 백만원
A52: 4001340020 | B52: 환율변동효과 | C52: 백만원 | D52: 141.14498 | E52: -364.00806 | F52: -41.90643 | G52: 40.79288 | H52: -140.08798 | I52: -214.05976 | J52: 542.9334 | K52: 382.08322 | L52: 440.61132 | M52: -638.13348 | N52: 172.07358
A53: 4001340030 | B53: 현금및현금성자산의증가 | C53: 백만원 | D53: 8500.8548 | E53: 308.63016 | F53: -10979.839 | G53: -7545.9799 | H53: 7440.4843 | I53: -971.74539 | J53: 2531.091 | K53: 2868.9171 | L53: -6988.3263 | M53: -1180.2849 | N53: -306.33943
A54: 4001340040 | B54: 기초현금및현금성자산 | C54: 백만원 | D54: 23330.438 | E54: 31831.293 | F54: 32139.923 | G54: 21160.084 | H54: 13614.104 | I54: 21054.588 | J54: 20082.843 | K54: 22613.934 | L54: 25482.851 | M54: 18494.525 | N54: 17314.24
A55: 4001340050 | B55: 기말현금및현금성자산 | C55: 백만원 | D55: 31831.293 | E55: 32139.923 | F55: 21160.084 | G55: 13614.104 | H55: 21054.588 | I55: 20082.843 | J55: 22613.934 | K55: 25482.851 | L55: 18494.525 | M55: 17314.24 | N55: 17007.9

Sheet CF(Yearly)
A2: Financial Statements
A3: Company | B3: A089030(테크윙) - Fiscal Month:12, 201106부터 IFRS 적용
A4: Type | B4: 연결 | C4: Accounting Std. | D4: IFRS
A5: Report | B5: 현금흐름표 | C5: New
A6: Form | B6: 약식(COMPARE)
A7: Output | B7: 결산 | C7: 백만원
A8: Fiscal Year | B8: 2023 | C8: Current
A9: 계정코드 | B9: 계정명 | C9: 단위 | D9: 202312 | E9: 202412
D10: IFRS(연결) | E10: IFRS(연결)
A11: 4001390000 | B11: 영업활동으로인한현금흐름(간접법)(*) | C11: 백만원 | D11: 20371.517 | E11: 32722.278
A12: 4001310010 | B12: *(직접법)총현금유입(*) | C12: 백만원
A13: 4001310100 | B13: *(직접법)총현금유출(*) | C13: 백만원
A14: 4001310190 | B14: 당기순손익 | C14: 백만원 | D14: -11097.331 | E14: -21970.453
A15: 4001310200 | B15: 법인세비용차감전계속사업이익 | C15: 백만원
A16: 4001390010 | B16: 현금유출이없는비용등가산(*) | C16: 백만원 | D16: 45691.888 | E16: 96630.736
A17: 4001390040 | B17: (현금유입이없는수익등차감)(*) | C17: 백만원 | D17: 12820.637 | E17: 25729.035
A18: 4001390060 | B18: 영업활동으로인한자산부채변동(운전자본변동)(*) | C18: 백만원 | D18: 9868.536 | E18: -6983.704
A19: 4001390070 | B19: 자산의감소(증가)(*) | C19: 백만원 | D19: 14108.259 | E19: -3862.4
A20: 4001390110 | B20: 부채의증가(감소)(*) | C20: 백만원 | D20: -4239.723 | E20: -3121.304
A21: 4001312260 | B21: 정부보조금등의변동 | C21: 백만원
A22: 4001312270 | B22: 기타운전자본의변동 | C22: 백만원
A23: 4001312280 | B23: *영업에서창출된현금흐름 | C23: 백만원 | D23: 31642.456 | E23: 41947.544
A24: 4001312290 | B24: 이자수입 | C24: 백만원 | D24: 1203.1377 | E24: 697.80911
A25: 4001312300 | B25: 이자지급(-) | C25: 백만원 | D25: -7362.1204 | E25: -11035.848
A26: 4001312310 | B26: 배당금수입 | C26: 백만원
A27: 4001312320 | B27: 배당금지급(-) | C27: 백만원
A28: 4001312330 | B28: 법인세환입 | C28: 백만원 | E28: 1112.772
A29: 4001312340 | B29: 법인세납부(-) | C29: 백만원 | D29: -5111.956
A30: 4001312350 | B30: 중단영업관련현금흐름 | C30: 백만원
A31: 4001390160 | B31: 투자활동으로인한현금흐름(*) | C31: 백만원 | D31: -67217.103 | E31: -29905.589
A32: 4001390170 | B32: 투자활동으로인한현금유입액(*) | C32: 백만원 | D32: 16125.584 | E32: 44841.224
A33: 4001390270 | B33: (투자활동으로인한현금유출액)(*) | C33: 백만원 | D33: 83342.687 | E33: 74746.813
A34: 4001321350 | B34: 이자수입 | C34: 백만원
A35: 4001321360 | B35: 이자지급(-) | C35: 백만원
A36: 4001321370 | B36: 배당금수입 | C36: 백만원
A37: 4001321380 | B37: 배당금지급(-) | C37: 백만원
A38: 4001321390 | B38: 법인세환입 | C38: 백만원
A39: 4001321400 | B39: 법인세납부(-) | C39: 백만원
A40: 4001321410 | B40: 중단영업관련현금흐름 | C40: 백만원
A41: 4001390370 | B41: 재무활동으로인한현금흐름(*) | C41: 백만원 | D41: 37353.229 | E41: 8481.1897
A42: 4001390380 | B42: 재무활동으로인한현금유입액(*) | C42: 백만원 | D42: 54373.215 | E42: 53406.045
A43: 4001390470 | B43: (재무활동으로인한현금유출액)(*) | C43: 백만원 | D43: 12373.725 | E43: 40278.593
A44: 4001330680 | B44: 이자수입 | C44: 백만원
A45: 4001330690 | B45: 이자지급(-) | C45: 백만원
A46: 4001330700 | B46: 배당금수입 | C46: 백만원
A47: 4001330710 | B47: 배당금지급(-) | C47: 백만원 | D47: -4646.2616 | E47: -4646.2616
A48: 4001330720 | B48: 법인세환입 | C48: 백만원
A49: 4001330730 | B49: 법인세납부(-) | C49: 백만원
A50: 4001330740 | B50: 중단영업관련현금흐름 | C50: 백만원
A51: 4001340000 | B51: 영업투자재무활동기타현금흐름 | C51: 백만원
A52: 4001340010 | B52: 연결범위변동으로인한현금의증가 | C52: 백만원
A53: 4001340020 | B53: 환율변동효과 | C53: 백만원 | D53: -223.97663 | E53: 570.86888
A54: 4001340030 | B54: 현금및현금성자산의증가 | C54: 백만원 | D54: -9716.3339 | E54: 11868.747
A55: 4001340040 | B55: 기초현금및현금성자산 | C55: 백만원 | D55: 23330.438 | E55: 13614.104
A56: 4001340050 | B56: 기말현금및현금성자산 | C56: 백만원 | D56: 13614.104 | E56: 25482.851
