Workbook
Name Com_Data_sum_035900: '요약 재무제표'!$B$4

Sheet Estimation ▶
A1: 한화솔루션(009830.KS)_EV/EBITDA
A3: Estimation Sheets >>>
B5: Chungang-Univ. Financial Institute
B6: R.F.S .
B7: Valuation Model
B17: RFS 정식 회원 외 본 가치평가 모델의 무단 사용 및 수정을 금하며, 본 양식의 원 저작권은 중앙대학교 R.F.S. 학회에 있음을 밝힙니다.
B18: 원 제작자: 28기 김 건 (zzkan103@gmail.com)
B19: 1st Version: 2021.03.02

Sheet Valuation
B2: 한화솔루션 EV/EBITDA Valuation
B3: 25E EBITDA | C3: 18486.584 | D3: (억원)
B4: Target EV/EBITDA | C4: =G5*0.75 -> 9.6 | D4: (배) | E4: 신재생에너지 업종 평균 25% 할인 | G4: 신재생에너지 업종 12mf EV/EBITDA
B5: EV | C5: =C3*C4 -> 177471.21 | D5: (억원) | E5: (A) | G5: 12.8
B6: 비영업가치 | C6: =SUM(C7,C11)*0.5 -> 25409 | D6: (억원) | E6: (B) 장부가 50% 할인
B7: 관계기업/공동기업 | C7: 37309
B8: 한화임팩트 | C8: 28069
B9: 한화호텔앤드리조트 | C9: 4670
B10: 기타 | C10: 4570
B11: 공동기업 | C11: 13509
B12: 여천NCC | C12: 4213
B13: 기타 | C13: 9296
B14: 순차입금 | C14: 118541 | D14: (억원) | E14: (C)
B15: 비지배지분 | C15: 11536 | D15: (억원) | E15: (D)
B16: 주주가치 | C16: =C5+C6-C14-C15 -> 72803.209 | D16: (억원) | E16: (A)+(B)-(C)-(D)
B17: 발행주식수 | C17: 169348279
B18: Target Price | C18: =C16*100000000/C17 -> 42990.227 | E18: 목표주가 43,000 원
B19: Current Price | C19: 28400
B20: Upside | C20: =C18/C19-1 -> 0.51374038

Sheet Expected IS
A1: 한화솔루션(0009830)
A2: Assumption Sheet
A3: (units in Millions KRW )
B5: 단위: 백만원 | C5: 1Q23 | D5: 2Q23 | E5: 3Q23 | F5: 4Q23 | G5: 1Q24 | H5: 2Q24 | I5: 3Q24 | J5: 4Q24 | K5: 1Q25E | L5: 2Q25E | M5: 3Q25E | N5: 4Q25E
B6: 매출액 | C6: 31002 | D6: 33930 | E6: 29258 | F6: =132887-SUM(C6:E6) -> 38697 | G6: 23928 | H6: 26793 | I6: 27732 | J6: =123940-SUM(G6:I6) -> 45487 | K6: 30945 | L6: ='매출액 추정 ▶'!L6 -> 37903.962 | M6: ='매출액 추정 ▶'!M6 -> 40297.066 | N6: ='매출액 추정 ▶'!N6 -> 56155.624 | O6: =SUM(K6:N6) -> 165301.65
B7: 매출원가 | C7: 24243 | D7: 28047 | E7: 24616 | F7: 33592 | G7: 21958 | H7: 23331 | I7: 24664 | J7: 40129 | K7: 26443 | L7: 31822.772 | M7: 33394.012 | N7: 47363.544 | O7: =SUM(K7:N7) -> 139023.33
B8: (%) | C8: =C7/C6 -> 0.78198181 | D8: =D7/D6 -> 0.82661362 | E8: =E7/E6 -> 0.84134254 | F8: =F7/F6 -> 0.86807763 | G8: =G7/G6 -> 0.91766968 | H8: =H7/H6 -> 0.87078715 | I8: =I7/I6 -> 0.88936968 | J8: =J7/J6 -> 0.8822081 | ... N8: =N7/N6 -> 0.84343368
B9: 매출총이익 | C9: =C6-C7 -> 6759 | D9: =D6-D7 -> 5883 | E9: =E6-E7 -> 4642 | F9: =F6-F7 -> 5105 | G9: =G6-G7 -> 1970 | H9: =H6-H7 -> 3462 | I9: =I6-I7 -> 3068 | J9: =J6-J7 -> 5358 | ... N9: =N6-N7 -> 8792.0796 | O9: =SUM(K9:N9) -> 26278.323
B10: GPM(%) | C10: =C9/C6 -> 0.21801819 | D10: =D9/D6 -> 0.17338638 | E10: =E9/E6 -> 0.15865746 | F10: =F9/F6 -> 0.13192237 | G10: =G9/G6 -> 0.082330324 | H10: =H9/H6 -> 0.12921285 | I10: =I9/I6 -> 0.11063032 | J10: =J9/J6 -> 0.1177919 | ... N10: =N9/N6 -> 0.15656632
B11: 판매비와 관리비 | C11: 4044 | D11: 3943 | E11: 3659 | F11: 4697 | G11: 4136 | H11: 4539 | I11: 3877 | J11: 4309 | K11: 4199 | L11: 4338.15 | M11: 4437.3219 | N11: 4922.6591 | O11: =SUM(K11:N11) -> 17897.131
B12: (%) | C12: =C11/C6 -> 0.1304432 | D12: =D11/D6 -> 0.11620984 | E12: =E11/E6 -> 0.12505981 | F12: =F11/F6 -> 0.12137892 | G12: =G11/G6 -> 0.17285189 | H12: =H11/H6 -> 0.16940992 | I12: =I11/I6 -> 0.13980239 | J12: =J11/J6 -> 0.094730363 | ... N12: =N11/N6 -> 0.087661017
B13: 영업이익 | C13: 2715 | D13: 1940 | E13: 983 | F13: 408 | G13: -2166 | H13: -1077 | I13: -809 | J13: 1049 | K13: 303 | L13: 1743.04 | M13: 2465.7317 | N13: 3869.4205 | O13: =SUM(K13:N13) -> 8381.1922
B14: OPM(%) | C14: =C13/C6 -> 0.087574995 | D14: =D13/D6 -> 0.05717654 | E14: =E13/E6 -> 0.033597649 | F14: =F13/F6 -> 0.010543453 | G14: =G13/G6 -> -0.090521565 | H14: =H13/H6 -> -0.040197066 | I14: =I13/I6 -> -0.029172076 | J14: =J13/J6 -> 0.023061534 | ... N14: =N13/N6 -> 0.068905307
B15: 지분법손익 | C15: 249 | D15: -755 | E15: 285 | F15: 362 | G15: -516 | H15: -494 | I15: -1012 | J15: -1245 | K15: -1367 | L15: -592.75 | M15: -592.75 | N15: -592.75
B16: 금융수익 | C16: 181 | D16: 205 | E16: 254 | F16: 313 | G16: 262 | H16: 349 | I16: 230 | J16: 242 | K16: 296 | L16: 259.11111 | M16: 259.11111 | N16: 259.11111
B17: 금융비용 | C17: -821 | D17: -913 | E17: -1120 | F17: -1307 | G17: -1381 | H17: -1642 | I17: -1558 | J17: -903 | K17: 1346 | L17: -934.75 | M17: -934.75 | N17: -934.75
B18: 기타수익 | C18: 2780 | D18: 1434 | E18: 1224 | F18: 635 | G18: 1685 | H18: 1489 | I18: 525 | J18: 3244 | K18: 1117 | L18: 1419.125 | M18: 1419.125 | N18: 1419.125
B19: 기타비용 | C19: -3092 | D19: -1468 | E19: -1290 | F19: -4221 | G19: -3058 | H19: -1734 | I19: -1077 | J19: -4640 | K19: -2376 | L19: -2483 | M19: -2483 | N19: -2483
B20: 법인세차감전순이익 | C20: =SUM(C13,C15:C19) -> 2012 | D20: =D13+SUM(D15:D19) -> 443 | E20: =SUM(E13,E15:E19) -> 336 | F20: =SUM(F13,F15:F19) -> -3810 | G20: =G13+SUM(G15:G19) -> -5174 | H20: =H13+SUM(H15:H19) -> -3109 | I20: =I13+SUM(I15:I19) -> -3701 | J20: =J13+SUM(J15:J19) -> -2253 | K20: =K13+SUM(K15:K19) -> -681 | L20: =SUM(L13:L19) -> -589.17789 | M20: =SUM(M13:M19) -> 133.52901 | N20: =SUM(N13:N19) -> 1537.2255
B21: 법인세비용 | C21: 606 | D21: 222 | E21: 130 | F21: =411-E21-D21-C21 -> -547 | G21: -691 | H21: -641 | I21: =-116 -> -116 | J21: =-3156-SUM(G21:I21) -> -1708 | K21: -392 | L21: 0 | M21: 0 | N21: =2*0.09+198*0.19+636*0.21 -> 171.36
B22: 당기순이익 | C22: =C20+C21 -> 2618 | D22: =D20+D21 -> 665 | E22: =E20+E21 -> 466 | F22: =F20+F21 -> -4357 | G22: =G20+G21 -> -5865 | H22: =H20+H21 -> -3750 | I22: =I20+I21 -> -3817 | J22: =J20+J21 -> -3961 | ... N22: =N20+N21 -> 1708.5855
B23: (%) | C23: =C22/C6 -> 0.084446165 | D23: =D22/D6 -> 0.019599175 | E23: =E22/E6 -> 0.015927268 | F23: =F22/F6 -> -0.11259271 | G23: =G22/G6 -> -0.24511033 | H23: =H22/H6 -> -0.13996193 | I23: =I22/I6 -> -0.13763883 | J23: =J22/J6 -> -0.087079825 | ... N23: =N22/N6 -> 0.030425903

Sheet 매출액 추정 ▶
A1: 한화솔루션(009830.KS)
A2: Assumption Sheet
A3: (댠위: 억원)
B5: (단위: 억원) | C5: 1Q23 | D5: 2Q23 | E5: 3Q23 | F5: 4Q23 | G5: 1Q24 | H5: 2Q24 | I5: 3Q24 | J5: 4Q24 | K5: 1Q25 | L5: 2Q25 | M5: 3Q25 | N5: 4Q25 | O5: 2023 | P5: 2024 | Q5: 2025E
B6: 전체 매출액 | C6: =SUM(C8,C10,C12,C14) -> 30533 | D6: =SUM(D8,D10,D12,D14) -> 33327 | E6: =SUM(E8,E10,E12,E14) -> 28740 | F6: =SUM(F8,F10,F12,F14) -> 38185 | G6: =SUM(G8,G10,G12,G14) -> 28116 | H6: =SUM(H8,H10,H12,H14) -> 28940 | I6: =SUM(I8,I10,I12,I14) -> 27820 | J6: =SUM(J8,J10,J12,J14) -> 46429 | ... Q6: =SUM(Q8,Q10,Q12,Q14) -> 165301.65
B7: YoY% | G7: =G6/C6-1 -> -0.079160253 | H7: =H6/D6-1 -> -0.13163501 | I7: =I6/E6-1 -> -0.032011134 | J7: =J6/F6-1 -> 0.21589629 | K7: =K6/G6-1 -> 0.10061886 | L7: =L6/H6-1 -> 0.30974297 | M7: =M6/I6-1 -> 0.44849266 | N7: =N6/J6-1 -> 0.20949458 | P7: =P6/O6-1 -> 0.0039759911 | Q7: =Q6/P6-1 -> 0.25891361
B8: 신재생에너지 | C8: 13483 | D8: 16002 | E8: 12585 | F8: 23186 | G8: 12223 | H8: 12224 | I8: 11886 | J8: 28690 | K8: 15992 | L8: =신재생에너지!L6 -> 22002.475 | M8: =신재생에너지!M6 -> 24588.124 | N8: =신재생에너지!N6 -> 40629.037 | O8: =SUM(C8:F8) -> 65256 | P8: =SUM(G8:J8) -> 65023 | Q8: =SUM(K8:N8) -> 103211.64
B9: % of sales | C9: =C8/C6 -> 0.44158779 | D9: =D8/D6 -> 0.48015123 | E9: =E8/E6 -> 0.43789144 | F9: =F8/F6 -> 0.60720178 | G9: =G8/G6 -> 0.43473467 | H9: =H8/H6 -> 0.42239115 | I9: =I8/I6 -> 0.42724659 | J9: =J8/J6 -> 0.61793276 | ... Q9: =Q8/Q6 -> 0.62438357
B10: 케미칼 | C10: 13475 | D10: 13413 | E10: 12859 | F10: 11227 | G10: 12223 | H10: 12224 | I10: 11886 | J10: 11839 | K10: 10736 | L10: =케미칼!L20 -> 11633.909 | M10: =케미칼!M20 -> 11239.551 | N10: =케미칼!N20 -> 10875.279 | O10: =SUM(C10:F10) -> 50974 | P10: =SUM(G10:J10) -> 48172 | Q10: =SUM(K10:N10) -> 44484.739
B11: % of sales | C11: =C10/C6 -> 0.44132578 | D11: =D10/D6 -> 0.40246647 | E11: =E10/E6 -> 0.44742519 | F11: =F10/F6 -> 0.29401597 | G11: =G10/G6 -> 0.43473467 | H11: =H10/H6 -> 0.42239115 | I11: =I10/I6 -> 0.42724659 | J11: =J10/J6 -> 0.25499149 | ... Q11: =Q10/Q6 -> 0.26911249
B12: 첨단소재 | C12: 2535 | D12: 2642 | E12: 2354 | F12: 2358 | G12: 2496 | H12: 2659 | I12: 2546 | J12: 2675 | K12: 2738 | L12: =첨단소재!L6 -> 2725.4662 | M12: =첨단소재!M6 -> 2871.4903 | N12: =첨단소재!N6 -> 3016.973 | O12: =SUM(C12:F12) -> 9889 | P12: =SUM(G12:J12) -> 10376 | Q12: =SUM(K12:N12) -> 11351.929
B13: % of sales | C13: =C12/C6 -> 0.083024924 | D13: =D12/D6 -> 0.079275062 | E13: =E12/E6 -> 0.08190675 | F13: =F12/F6 -> 0.061751997 | G13: =G12/G6 -> 0.088775075 | H13: =H12/H6 -> 0.091879751 | I13: =I12/I6 -> 0.091516894 | J13: =J12/J6 -> 0.057614853 | ... Q13: =Q12/Q6 -> 0.068674023
B14: 기타 | C14: 1040 | D14: 1270 | E14: 942 | F14: 1414 | G14: 1174 | H14: 1833 | I14: 1502 | J14: 3225 | K14: 1479 | L14: =AVERAGE(C14:K14) -> 1542.1111 | M14: =AVERAGE(D14:L14) -> 1597.9012 | N14: =AVERAGE(E14:M14) -> 1634.3347 | O14: =SUM(C14:F14) -> 4666 | P14: =SUM(G14:J14) -> 7734 | Q14: =SUM(K14:N14) -> 6253.3471
B15: % of sales | C15: =C14/C6 -> 0.034061507 | D15: =D14/D6 -> 0.03810724 | E15: =E14/E6 -> 0.032776618 | F15: =F14/F6 -> 0.037030247 | G15: =G14/G6 -> 0.041755584 | H15: =H14/H6 -> 0.063337941 | I15: =I14/I6 -> 0.053989935 | J15: =J14/J6 -> 0.069460897 | ... Q15: =Q14/Q6 -> 0.037829913

Sheet 신재생에너지
A1: 한화솔루션(009830.KS)
A2: Assumption Sheet
A3: (댠위: 억원)
B5: (단위: 억원) | C5: 1Q23 | D5: 2Q23 | E5: 3Q23 | F5: 4Q23 | G5: 1Q24 | H5: 2Q24 | I5: 3Q24 | J5: 4Q24 | K5: 1Q25 | L5: 2Q25 | M5: 3Q25 | N5: 4Q25
B6: 신재생에너지 | C6: 13661 | D6: 16290 | E6: 12799 | F6: 23409 | G6: 7641 | H6: 9802 | I6: 11525 | J6: 28690 | K6: 15992 | L6: =L7+L8+L9 -> 22002.475 | M6: =M7+M8+M9 -> 24588.124 | N6: =N7+N8+N9 -> 40629.037
B7: 개발자산 매각/EPC | C7: 1650 | D7: 3250 | E7: 4018 | F7: 11579 | G7: 3427 | H7: 4052 | I7: 5785 | J7: 16336 | K7: 4190 | L7: =L14 -> 6307.1322 | M7: =M14 -> 8356.8306 | N7: =N14 -> 23840.885
B8: 모듈 및 기타 | C8: =C6-C7 -> 12011 | D8: =D6-D7 -> 13040 | E8: =E6-E7 -> 8781 | F8: =F6-F7 -> 11830 | G8: =G6-G7 -> 4214 | H8: =H6-H7 -> 5750 | I8: =I6-I7 -> 5740 | J8: =J6-J7 -> 12354 | K8: =K6-K7-K9 -> 5866 | L8: =L18 -> 9683.0143 | M8: =M18 -> 10142.636 | N8: =N18 -> 10623.167
B9: 주택용 에너지 사업 | C9: - | D9: - | E9: - | F9: - | G9: - | H9: - | I9: - | J9: - | K9: 5936 | L9: =D27 -> 6012.3284 | M9: =E27 -> 6088.6568 | N9: =F27 -> 6164.9852
B10: 연결조정 | C10: =C11-C6 -> -178 | D10: =D11-D6 -> -288 | E10: =E11-E6 -> -214 | F10: =F11-F6 -> -223 | G10: =G11-G6 -> 4582 | H10: =H11-H6 -> 2422 | I10: =I11-I6 -> 361 | J10: =J11-J6 -> 0 | K10: =K11-K6 -> 0 | L10: 0 | M10: 0 | N10: 0
B11: 총합 | C11: 13483 | D11: 16002 | E11: 12585 | F11: 23186 | G11: 12223 | H11: 12224 | I11: 11886 | J11: 28690 | K11: 15992 | L11: =L6 -> 22002.475 | M11: =M6 -> 24588.124 | N11: =N6 -> 40629.037
B13: (단위: 억원) | C13: 1Q23 | D13: 2Q23 | E13: 3Q23 | F13: 4Q23 | G13: 1Q24 | H13: 2Q24 | I13: 3Q24 | J13: 4Q24 | K13: 1Q25 | L13: 2Q25 | M13: 3Q25 | N13: 4Q25
B14: 개발자산 매각/EPC | C14: 1650 | D14: 3250 | E14: 4018 | F14: 11579 | G14: 3427 | H14: 4052 | I14: 5785 | J14: 16336 | K14: 4190 | L14: =K14*L15/K15 -> 6307.1322 | M14: =L14*M15/L15 -> 8356.8306 | N14: =M14*N15/M15 -> 23840.885
B15: 매출액 분기 비중 | C15: =C7/SUM($C$7:$F$7) -> 0.080499585 | D15: =D7/SUM($C$7:$F$7) -> 0.15855979 | E15: =E7/SUM($C$7:$F$7) -> 0.19602869 | F15: =F7/SUM($C$7:$F$7) -> 0.56491194 | G15: =G7/SUM($G$7:$J$7) -> 0.11577703 | H15: =H7/SUM($G$7:$J$7) -> 0.13689189 | I15: =I7/SUM($G$7:$J$7) -> 0.19543919 | J15: =J7/SUM($G$7:$J$7) -> 0.55189189 | K15: =AVERAGE(C15,G15) -> 0.098138306 | L15: =AVERAGE(D15,H15) -> 0.14772584 | M15: =AVERAGE(E15,I15) -> 0.19573394 | N15: =AVERAGE(F15,J15) -> 0.55840192
B17: (단위: 억원) | C17: 1Q23 | D17: 2Q23 | E17: 3Q23 | F17: 4Q23 | G17: 1Q24 | H17: 2Q24 | I17: 3Q24 | J17: 4Q24 | K17: 1Q25 | L17: 2Q25 | M17: 3Q25 | N17: 4Q25
B18: 모듈 및 기타 | C18: 12011 | D18: 13040 | E18: 8781 | F18: 11830 | G18: 4214 | H18: 5750 | I18: 5740 | J18: 12354 | K18: 5866 | L18: =L19+L22 -> 9683.0143 | M18: =M19+M22 -> 10142.636 | N18: =N19+N22 -> 10623.167
B19: 수출 | C19: =C18-C22 -> 11545 | D19: =D18-D22 -> 12279 | E19: =E18-E22 -> 7945 | F19: =F18-F22 -> 10156 | G19: =G18-G22 -> 3567 | H19: =H18-H22 -> 4874 | I19: =I18-I22 -> 5155 | J19: =J18-J22 -> 11496 | K19: =K18-K22 -> 5459 | L19: =L20*L21*10 -> 9040.9635 | M19: =M20*M21*10 -> 9540.4502 | N19: =N20*N21*10 -> 9999.0009
B20: 생산량(GW) | C20: =255.660250971286/$O$20 -> 0.25566025 | D20: =303.570750958145/O20 -> 0.30357075 | E20: =380.668148734659/O20 -> 0.38066815 | F20: =1338.56939584892/O20 -> 1.3385694 | G20: =1211.25/O20 -> 1.21125 | H20: =1788.75/O20 -> 1.78875 | I20: =1871.25/O20 -> 1.87125 | J20: =1953.75/O20 -> 1.95375 | K20: =1953.75/O20-C30 -> 1.51565 | L20: =2100/O20-D30 -> 1.6562667 | M20: =2100/O20-E30 -> 1.6506333 | N20: =2100/O20-F30 -> 1.645 | O20: 1000
B21: 단가(원/W) | C21: =C19/C20/10 -> 4515.7587 | D21: =D19/D20/10 -> 4044.8561 | E21: =E19/E20/10 -> 2087.1197 | F21: =F19/F20/10 -> 758.72047 | G21: =G19/G20/10 -> 294.48916 | H21: =H19/H20/10 -> 272.48078 | I21: =I19/I20/10 -> 275.4843 | J21: =J19/J20/10 -> 588.40691 | K21: =K19/K20/10 -> 360.1755 | L21: =0.4*L26 -> 545.864 | M21: =0.425*M26 -> 577.98725 | N21: =0.45*N26 -> 607.842 | O21: 100000000 | P21: 100000000
B22: 내수 | C22: 466 | D22: =1227-C22 -> 761 | E22: =2063-SUM(C22:D22) -> 836 | F22: =3737-SUM(C22:E22) -> 1674 | G22: 647 | H22: =1523-G22 -> 876 | I22: =2108-SUM(G22:H22) -> 585 | J22: =2966-SUM(G22:I22) -> 858 | K22: 407 | L22: =L23*1000000000*L24/100000000 -> 642.05087 | M22: =M23*1000000000*M24/100000000 -> 602.18604 | N22: =N23*1000000000*N24/100000000 -> 624.16637 | O22: =1000000000 -> 1000000000
B23: 생산량(GW) | C23: =C22*100000000/C24/1000000000 -> 0.087924528 | D23: =D22*100000000/D24/1000000000 -> 0.14863281 | E23: =E22*100000000/E24/1000000000 -> 0.176 | F23: =F22*100000000/F24/1000000000 -> 0.48381503 | G23: =G22*100000000/G24/1000000000 -> 0.20345912 | H23: =H22*100000000/H24/1000000000 -> 0.29795918 | I23: =I22*100000000/I24/1000000000 -> 0.19117647 | J23: =J22*100000000/J24/1000000000 -> 0.31428571 | K23: =K22*100000000/K24/1000000000 -> 0.15130112 | L23: =AVERAGE(H23:K23) -> 0.23868062 | M23: =AVERAGE(I23:L23) -> 0.22386098 | N23: =AVERAGE(J23:M23) -> 0.23203211
B24: 단가(원/W) | C24: 530 | D24: 512 | E24: 475 | F24: 346 | G24: 318 | H24: 294 | I24: 306 | J24: 273 | K24: 269 | L24: =K24 -> 269 | M24: =K24 -> 269 | N24: =K24 -> 269
B26: (단위: 억원) | C26: 1Q25 | D26: 2Q25 | E26: 3Q25 | F26: 4Q25 | L26: 1364.66 | M26: 1359.97 | N26: 1350.76
B27: 주택용 에너지 사업 | C27: 5936 | D27: =D30*D31 -> 6012.3284 | E27: =E30*E31 -> 6088.6568 | F27: =F30*F31 -> 6164.9852
B28: 주택용 태양광 설치량(GW) | C28: 1.3 | D28: 1.3 | E28: 1.3 | F28: 1.3
B29: 한화큐셀 점유율(%) | C29: 0.337 | D29: 0.34133333 | E29: 0.34566667 | F29: 0.35
B30: 한화큐셀 Q(GW) | C30: =C28*C29 -> 0.4381 | D30: =D28*D29 -> 0.44373333 | E30: =E28*E29 -> 0.44936667 | F30: =F28*F29 -> 0.455
B31: 한화큐셀 P(억원/GW) | C31: =C27/C30 -> 13549.418 | D31: =C31 -> 13549.418 | E31: =C31 -> 13549.418 | F31: =C31 -> 13549.418
B33: 모듈 P=(셀 원가+모듈 제조비용-AMPC)*(1+판매세)
B34: 셀 원가= (웨이퍼 원가+셀 제조비용)*(1+총 관세)+운임-AMPC

Sheet 케미칼
A1: 한화솔루션(009830.KS)
A2: Assumption Sheet
A3: (댠위: 억원)
B5: (단위: 억원) | C5: 1Q23 | D5: 2Q23 | E5: 3Q23 | F5: 4Q23 | G5: 1Q24 | H5: 2Q24 | I5: 3Q24 | J5: 4Q24 | K5: 1Q25 | L5: 2Q25 | M5: 3Q25 | N5: 4Q25 | P5: Note
B6: 기초소재 | C6: =SUM(C7,C10,C13,C16) -> 15885.964 | D6: =SUM(D7,D10,D13,D16) -> 13550.149 | E6: =SUM(E7,E10,E13,E16) -> 15191.9 | F6: =SUM(F7,F10,F13,F16) -> 13299.909 | G6: =SUM(G7,G10,G13,G16) -> 14760.064 | H6: =SUM(H7,H10,H13,H16) -> 15333.209 | I6: =SUM(I7,I10,I13,I16) -> 14339.996 | J6: =SUM(J7,J10,J13,J16) -> 14394.667 | ... N6: =SUM(N7,N10,N13,N16) -> 12500.556 | P6: 감소세는 선형회귀 추정
B7: LDPE | C7: =C8*C9*C$23/100000000 -> 3164.0468 | D7: =D8*D9*D$23/100000000 -> 2514.5423 | E7: =E8*E9*E$23/100000000 -> 2745.7428 | F7: =F8*F9*F$23/100000000 -> 2581.484 | G7: =G8*G9*G$23/100000000 -> 3000.3851 | H7: =H8*H9*H$23/100000000 -> 3040.4804 | I7: =I8*I9*I$23/100000000 -> 3082.1814 | J7: =J8*J9*J$23/100000000 -> 2935.7774 | K7: =K8*K9*K$23/100000000 -> 2882.307 | L7: 2744.4282 | M7: 2680.196 | N7: 2597.1992 | P7: 보합세는 4Q Moving Average
B8: 생산량(톤) | C8: =229590 -> 229590 | D8: =429000-C8 -> 199410 | E8: =645401-SUM(C8:D8) -> 216401 | F8: =846000-SUM(C8:E8) -> 200599 | G8: 218537 | H8: =422010-G8 -> 203473 | I8: =626213-SUM(G8:H8) -> 204203 | J8: =811456-SUM(G8:I8) -> 185243 | K8: 176201 | L8: 180608.08 | M8: 175981.77 | N8: 171355.45
B9: 단가(USD/MT) | C9: 1077 | D9: 957 | E9: 966 | F9: 974 | G9: 1031 | H9: 1088 | I9: 1111 | J9: 1130 | K9: 1125 | L9: 1113.5 | M9: 1119.875 | N9: 1122.0938
B10: PVC | C10: =C11*C12*C$23/100000000 -> 4315.0845 | D10: =D11*D12*D$23/100000000 -> 3032.7316 | E10: =E11*E12*E$23/100000000 -> 4813.3131 | F10: =F11*F12*F$23/100000000 -> 3592.5618 | G10: =G11*G12*G$23/100000000 -> 4089.6184 | H10: =H11*H12*H$23/100000000 -> 4215.946 | I10: =I11*I12*I$23/100000000 -> 3877.3308 | J10: =J11*J12*J$23/100000000 -> 3731.827 | K10: =K11*K12*K$23/100000000 -> 3647.1149 | L10: 3568.4404 | M10: 3498.954 | N10: 3457.9557
B11: 생산량(톤) | C11: =292728+91351 -> 384079 | D11: =588263+90141-C11 -> 294325 | E11: =857134+267079-SUM(C11:D11) -> 445809 | F11: =1141189+340328-SUM(C11:E11) -> 357304 | G11: =309463+89377 -> 398840 | H11: =609287+176646-G11 -> 387093 | I11: =890891+260001-SUM(G11:H11) -> 364959 | J11: =1166604+338123-SUM(G11:I11) -> 353835 | K11: =264185+84667 -> 348852 | L11: 363684.75 | M11: 357832.69 | N11: 356051.11
B12: 단가(USD/MT) | C12: 878 | D12: 782 | E12: 822 | F12: 761 | G12: 770 | H12: 793 | I12: 782 | J12: 752 | K12: 719 | L12: 719 | M12: 719 | N12: 719
B13: 가성소다 | C13: =C14*C15*C$23/100000000 -> 5221.1161 | D13: =D14*D15*D$23/100000000 -> 4442.1365 | E13: =E14*E15*E$23/100000000 -> 4071.0167 | F13: =F14*F15*F$23/100000000 -> 4018.2608 | G13: =G14*G15*G$23/100000000 -> 4146.112 | H13: =H14*H15*H$23/100000000 -> 4598.6339 | I13: =I14*I15*I$23/100000000 -> 4784.9406 | J13: =J14*J15*J$23/100000000 -> 5913.7384 | K13: =K14*K15*K$23/100000000 -> 6042.4422 | L13: 5197.6603 | M13: 5340.374 | N13: 5440.8032
B14: 생산량(톤) | C14: =871853 -> 871853 | D14: =1795485-C14 -> 923632 | E14: =2676000-SUM(C14:D14) -> 880515 | F14: =3444000-SUM(C14:E14) -> 768000 | G14: =862463 -> 862463 | H14: =1734412-G14 -> 871949 | I14: =2635190-SUM(G14:H14) -> 900778 | J14: =3566000-SUM(G14:I14) -> 930810 | K14: =874862 -> 874862 | L14: 894599.75 | M14: 900262.44 | N14: 900133.55
B15: 단가(USD/톤) | C15: 468 | D15: 365 | E15: 352 | F15: 396 | G15: 361 | H15: 384 | I15: 391 | J15: 453 | K15: 475 | L15: 425.75 | M15: 436.1875 | N15: 447.48438
B16: TDI | C16: =C17*C18*C$23/100000000 -> 3185.7162 | D16: =D17*D18*D$23/100000000 -> 3560.7383 | E16: =E17*E18*E$23/100000000 -> 3561.8273 | F16: =F17*F18*F$23/100000000 -> 3107.6027 | G16: =G17*G18*G$23/100000000 -> 3523.948 | H16: =H17*H18*H$23/100000000 -> 3478.1492 | I16: =I17*I18*I$23/100000000 -> 2595.5434 | J16: =J17*J18*J$23/100000000 -> 1813.3243 | K16: =K17*K18*K$23/100000000 -> 1590.765 | L16: 1748.6568 | M16: 1345.3031 | N16: 1004.5975
B17: 생산량(톤) | C17: =99188 -> 99188 | D17: =219292-C17 -> 120104 | E17: =347750-SUM(C17:D17) -> 128458 | F17: =465000-SUM(C17:E17) -> 117250 | G17: =132979 -> 132979 | H17: =258784-G17 -> 125805 | I17: =358810-SUM(G17:H17) -> 100026 | J17: =432903-SUM(G17:I17) -> 74093 | K17: =61462 -> 61462 | L17: 78492.278 | M17: 63738.096 | N17: 50542.143
B18: 단가(USD/MT) | C18: 2510 | D18: 2250 | E18: 2111 | F18: 2006 | G18: 1990 | H18: 2013 | I18: 1910 | J18: 1745 | K18: 1780 | L18: 1632.5 | M18: 1552 | N18: 1471.5
B19: 연결조정 | C19: =C20-C6 -> -2410.9637 | D19: =D20-D6 -> -137.14865 | E19: =E20-E6 -> -2332.8999 | F19: =F20-F6 -> -2072.9093 | G19: =G20-G6 -> -2537.0635 | H19: =H20-H6 -> -3109.2095 | I19: =I20-I6 -> -2453.9961 | J19: =J20-J6 -> -2555.6671 | K19: =K20-K6 -> -3426.6291 | L19: -1625.2763 | M19: -1625.2763 | N19: -1625.2763
B20: 총합 | C20: 13475 | D20: 13413 | E20: 12859 | F20: 11227 | G20: 12223 | H20: 12224 | I20: 11886 | J20: 11839 | K20: 10736 | L20: 11633.909 | M20: 11239.551 | N20: 10875.279
B22: (단위: 억원) | C22: 1Q23 | D22: 2Q23 | E22: 3Q23 | F22: 4Q23 | G22: 1Q24 | H22: 2Q24 | I22: 3Q24 | J22: 4Q24 | K22: 1Q25 | L22: 2Q25 | M22: 3Q25 | N22: 4Q25
B23: 분기 avg 환율 | C23: 1279.6 | D23: 1317.65 | E23: 1313.48 | F23: 1321.24 | G23: 1331.66 | H23: 1373.43 | I23: 1358.57 | J23: 1402.5 | K23: 1454.05 | L23: 1364.66 | M23: 1359.97 | N23: 1350.76

Sheet 첨단소재
A1: 한화솔루션(009830.KS)
A2: Assumption Sheet
A3: (댠위: 억원)
B5: (단위: 억원) | C5: 1Q23 | D5: 2Q23 | E5: 3Q23 | F5: 4Q23 | G5: 1Q24 | H5: 2Q24 | I5: 3Q24 | J5: 4Q24 | K5: 1Q25 | L5: 2Q25 | M5: 3Q25 | N5: 4Q25 | P5: Note
B6: 첨단소재 | C6: =C7+C10 -> 2535 | D6: =D7+D10 -> 2642 | E6: =E7+E10 -> 2354 | F6: =F7+F10 -> 2358 | G6: =G7+G10 -> 2496 | H6: =H7+H10 -> 2659 | I6: =I7+I10 -> 2546 | J6: =J7+J10 -> 2675 | K6: =K7+K10 -> 2737.9921 | L6: 2725.4662 | M6: 2871.4903 | N6: 3016.973 | P6: 감소세는 선형회귀 추정
B7: GMT | C7: =C8*C9/100000000 -> 485.14851 | D7: =D8*D9/100000000 -> 475.04271 | E7: =E8*E9/100000000 -> 480.97148 | F7: =F8*F9/100000000 -> 471.33798 | G7: =G8*G9/100000000 -> 442.92585 | H7: =H8*H9/100000000 -> 439.61819 | I7: =I8*I9/100000000 -> 439.45817 | J7: =J8*J9/100000000 -> 426.54246 | K7: =K8*K9/100000000 -> 415.6106 | L7: 430.47006 | M7: 428.14154 | N7: 425.27153 | P7: 보합세는 4Q Moving Average
B8: 생산량(kg) | C8: 14430354 | D8: 14417078 | E8: 14636990 | F8: 14569953 | G8: 13632682 | H8: 13423456 | I8: 13369582 | J8: 12945143 | K8: 12321690 | L8: 13014968 | M8: 12912846 | N8: 12798662
B9: 단가(원/kg) | C9: 3362 | D9: 3295 | E9: 3286 | F9: 3235 | G9: 3249 | H9: 3275 | I9: 3287 | J9: 3295 | K9: 3373 | L9: 3307.5 | M9: 3315.625 | N9: 3322.7812
B10: EVA Sheet | C10: =C11*C12/100000000 -> 2049.8515 | D10: =D11*D12/100000000 -> 2166.9573 | E10: =E11*E12/100000000 -> 1873.0285 | F10: =F11*F12/100000000 -> 1886.662 | G10: =G11*G12/100000000 -> 2053.0741 | H10: =H11*H12/100000000 -> 2219.3818 | I10: =I11*I12/100000000 -> 2106.5418 | J10: =J11*J12/100000000 -> 2248.4575 | K10: =K11*K12/100000000 -> 2322.3815 | L10: 2294.9961 | M10: 2443.3488 | N10: 2591.7015
B11: 생산량(m) | C11: 93814714 | D11: 94379673 | E11: 85021721 | F11: 87874337 | G11: 1.2775819e+08 | H11: 1.3666144e+08 | I11: 1.3895395e+08 | J11: 1.5701519e+08 | K11: 183587471 | L11: 1.8142262e+08 | M11: 1.931501e+08 | N11: 2.0487759e+08
B12: 단가(원/m) | C12: 2185 | D12: 2296 | E12: 2203 | F12: 2147 | G12: 1607 | H12: 1624 | I12: 1516 | J12: 1432 | K12: 1265 | L12: 1265 | M12: 1265 | N12: 1265

Sheet 비용 추정
A1: 한화솔루션(0009830)
A2: Assumption Sheet
A3: (units in Millions KRW )
R4: 2024
B5: (단위: 억 원) | C5: 1Q23 | D5: 2Q23 | E5: 3Q23 | F5: 4Q23 | G5: 1Q24 | H5: 2Q24 | I5: 3Q24 | J5: 4Q24 | K5: 1Q25 | L5: 2Q25E | M5: 3Q25E | N5: 4Q25E | U5: Description
B6: 매출액 | C6: 31002 | D6: 33930 | E6: 29258 | F6: =132887-SUM(C6:E6) -> 38697 | G6: 23928 | H6: 26793 | I6: 27732 | J6: =123940-SUM(G6:I6) -> 45487 | K6: 30945 | L6: ='매출액 추정 ▶'!L6 -> 37903.962 | M6: ='매출액 추정 ▶'!M6 -> 40297.066 | N6: ='매출액 추정 ▶'!N6 -> 56155.624
B7: 매출원가 | C7: 24243 | D7: 28047 | E7: 24616 | F7: 33592 | G7: 21958 | H7: 23331 | I7: 24664 | J7: 40129 | K7: 26443 | L7: =L44 -> 31822.772 | M7: =M44 -> 33394.012 | N7: =N44 -> 47363.544
B8: 매출원가율(%) | C8: =C7/C6 -> 0.78198181 | D8: =D7/D6 -> 0.82661362 | E8: =E7/E6 -> 0.84134254 | F8: =F7/F6 -> 0.86807763 | G8: =G7/G6 -> 0.91766968 | H8: =H7/H6 -> 0.87078715 | I8: =I7/I6 -> 0.88936968 | J8: =J7/J6 -> 0.8822081 | ... N8: =N7/N6 -> 0.84343368
B9: 매출총이익 | C9: =C6-C7 -> 6759 | D9: =D6-D7 -> 5883 | E9: =E6-E7 -> 4642 | F9: =F6-F7 -> 5105 | G9: =G6-G7 -> 1970 | H9: =H6-H7 -> 3462 | I9: =I6-I7 -> 3068 | J9: =J6-J7 -> 5358 | ... N9: =N6-N7 -> 8792.0796
B10: GPM(%) | C10: =C9/C6 -> 0.21801819 | D10: =D9/D6 -> 0.17338638 | E10: =E9/E6 -> 0.15865746 | F10: =F9/F6 -> 0.13192237 | G10: =G9/G6 -> 0.082330324 | H10: =H9/H6 -> 0.12921285 | I10: =I9/I6 -> 0.11063032 | J10: =J9/J6 -> 0.1177919 | ... N10: =N9/N6 -> 0.15656632 | P10: 명목임금상승률 1.72 | Q10: 0.0043
B11: 판매비와 관리비 | C11: 4044 | D11: 3943 | E11: 3659 | F11: =16343-C11-D11-E11 -> 4697 | G11: 4136 | H11: 4539 | I11: 3877 | J11: =16861-SUM(G11:I11) -> 4309 | K11: 4199 | L11: =SUM(L12:L21) -> 4338.15 | M11: =SUM(M12:M21) -> 4437.3219 | N11: =SUM(N12:N21) -> 4922.6591 | P11: of sales(%) | Q11: 2023 | R11: 2024 | S11: 2025E
B12: 급여 | C12: 1266 | D12: 1156 | E12: 1049 | F12: =4924-C12-D12-E12 -> 1453 | G12: 1508 | H12: 1500 | I12: 1210 | J12: 1152 | K12: 1213 | L12: =K12*(1+$Q$10) -> 1218.2159 | M12: =L12*(1+$Q$10) -> 1223.4542 | N12: =M12*(1+$Q$10) -> 1228.7151 | P12: 급여 | Q12: =SUM(C12:F12)/SUM(C$6:F$6) -> 0.037054038 | R12: =SUM(G12:J12)/SUM(G$6:J$6) -> 0.043327416 | S12: =SUM(K12:N12)/SUM($K$6:$N$6) -> 0.029542265 | U12: 급여의 경우, '25년 명목임금상승률 전망치를 반영하여 각 분기를 추정함
B13: 퇴직급여 | C13: 98 | D13: 72 | E13: 67 | F13: =302-C13-D13-E13 -> 65 | G13: 77 | H13: 71 | I13: 75 | J13: 76 | K13: 69 | L13: =K13*(1+(L$12/K$12-1)) -> 69.2967 | M13: =L13*(1+(M$12/L$12-1)) -> 69.594676 | N13: =M13*(1+(N$12/M$12-1)) -> 69.893933 | P13: 퇴직급여 | Q13: =SUM(C13:F13)/SUM(C$6:F$6) -> 0.0022726076 | R13: =SUM(G13:J13)/SUM(G$6:J$6) -> 0.0024124576 | S13: =SUM(K13:N13)/SUM($K$6:$N$6) -> 0.0016804751 | U13: 퇴직급여의 경우, 급여 내 퇴직급여 비율의 4개분기 평균값을 flat하게 적용함
B14: 복리후생비 | C14: 203 | D14: 192 | E14: 221 | F14: =868-C14-D14-E14 -> 252 | G14: 299 | H14: 273 | I14: 259 | J14: 263 | K14: 313 | L14: {=L12*AVERAGE($C14:$J14/AVERAGE($C12:$J12))} -> 232.18764 | M14: {=M12*AVERAGE($C14:$J14/AVERAGE($C12:$J12))} -> 233.18605 | N14: {=N12*AVERAGE($C14:$J14/AVERAGE($C12:$J12))} -> 234.18875 | P14: 복리후생비 | Q14: =SUM(C14:F14)/SUM(C$6:F$6) -> 0.0065318654 | R14: =SUM(G14:J14)/SUM(G$6:J$6) -> 0.0088268517 | S14: =SUM(K14:N14)/SUM($K$6:$N$6) -> 0.0061255434 | U14: 복리후생비의 경우, 과거 2개년 급여 대비 복리후생비의 비중을 적용하여 추정함
B15: 감가상각비 | C15: =92+3 -> 95 | D15: =103+3 -> 106 | E15: =43+3 -> 46 | F15: =32+2 -> 34 | G15: 89 | H15: 103 | I15: 98 | J15: 95 | K15: 208 | L15: =L6*AVERAGE($Q15:$R15) -> 98.946782 | M15: =M6*AVERAGE($Q15:$R15) -> 105.19389 | N15: =N6*AVERAGE($Q15:$R15) -> 146.59202 | P15: 감가상각비 | Q15: =SUM(C15:F15)/SUM(C$6:F$6) -> 0.0021145786 | R15: =SUM(G15:J15)/SUM(G$6:J$6) -> 0.0031063418 | S15: =SUM(K15:N15)/SUM($K$6:$N$6) -> 0.0033800793
B16: 무형자산상각비 | C16: 85 | D16: 73 | E16: 153 | F16: =471-C16-D16-E16 -> 160 | G16: 154 | H16: 122 | I16: 128 | J16: 133 | K16: 121 | L16: =('FA Schedule'!E21-'비용 추정'!K16)/3 -> 137.05209 | M16: =L16 -> 137.05209 | N16: =M16 -> 137.05209 | P16: 무형자산상각비 | Q16: =SUM(C16:F16)/SUM(C$6:F$6) -> 0.0035443648 | R16: =SUM(G16:J16)/SUM(G$6:J$6) -> 0.0043327416 | S16: =SUM(K16:N16)/SUM($K$6:$N$6) -> 0.0032193039
B17: 외주용역비 | C17: 157 | D17: 206 | E17: 191 | F17: =866-C17-D17-E17 -> 312 | G17: 305 | H17: 382 | I17: 356 | J17: 336 | K17: 378 | L17: =L6*AVERAGE($Q17:$R17) -> 334.37295 | M17: =M6*AVERAGE($Q17:$R17) -> 355.48392 | N17: =N6*AVERAGE($Q17:$R17) -> 495.38151 | P17: 외주용역비 | Q17: =SUM(C17:F17)/SUM(C$6:F$6) -> 0.006516815 | R17: =SUM(G17:J17)/SUM(G$6:J$6) -> 0.011126351 | S17: =SUM(K17:N17)/SUM($K$6:$N$6) -> 0.0094568831 | U17: 외주용역비의 경우, of sales(%)를 2개년도 평균값을 flat하게 적용함
B18: 운반비 | C18: 404 | D18: 425 | E18: 392 | F18: =1625-C18-D18-E18 -> 404 | G18: 287 | H18: 333 | I18: 279 | J18: 337 | K18: 330 | L18: =K18*(1+(L$6/K$6-1)) -> 404.21093 | M18: =L18*(1+(M$6/L$6-1)) -> 429.73119 | N18: =M18*(1+(N$6/M$6-1)) -> 598.84815 | P18: 운반비 | Q18: =SUM(C18:F18)/SUM(C$6:F$6) -> 0.012228435 | R18: =SUM(G18:J18)/SUM(G$6:J$6) -> 0.0099725674 | S18: =SUM(K18:N18)/SUM($K$6:$N$6) -> 0.010664081 | U18: 운반비의 경우, 매출액 확대에 따라 증가할 것으로 예상되어 매출액과 연동하여 추정함
B19: 보관비 | C19: 251 | D19: 253 | E19: 256 | F19: =1045-C19-D19-E19 -> 285 | G19: 275 | H19: 312 | I19: 319 | J19: 254 | K19: 309 | L19: =L6*AVERAGE($Q19:$R19) -> 326.4136 | M19: =M6*AVERAGE($Q19:$R19) -> 347.02204 | N19: =N6*AVERAGE($Q19:$R19) -> 483.58953 | P19: 보관비 | Q19: =SUM(C19:F19)/SUM(C$6:F$6) -> 0.0078638242 | R19: =SUM(G19:J19)/SUM(G$6:J$6) -> 0.0093593674 | S19: =SUM(K19:N19)/SUM($K$6:$N$6) -> 0.0088687872 | U19: 보관비의 경우, of sales(%)를 2개년도 평균값을 flat하게 적용함
B20: 경상개발비 | C20: 217 | D20: 163 | E20: 181 | F20: =672-C20-D20-E20 -> 111 | G20: 154 | H20: 139 | I20: 113 | J20: 135 | K20: 152 | L20: =L6*AVERAGE($Q20:$R20) -> 178.56449 | M20: =M6*AVERAGE($Q20:$R20) -> 189.83834 | N20: =N6*AVERAGE($Q20:$R20) -> 264.54756 | P20: 경상개발비 | Q20: =SUM(C20:F20)/SUM(C$6:F$6) -> 0.0050569281 | R20: =SUM(G20:J20)/SUM(G$6:J$6) -> 0.0043650153 | S20: =SUM(K20:N20)/SUM($K$6:$N$6) -> 0.0047485937 | U20: 경상개발비의 경우, of sales(%)를 2개년도 평균값을 flat하게 적용함
B21: 기타 | C21: =C11-C12-C13-C14-C15-C16-C17-C18-C19-C20 -> 1268 | D21: =D11-D12-D13--D14-D15-D16--D17-D18-D19-D20 -> 2093 | E21: =E11-E12-E13-E14-E15-E16-E17-E18-E19-E20 -> 1103 | F21: =F11-F12-F13-F14-F15-F16-F17-F18-F19-F20 -> 1621 | G21: 988 | H21: 1304 | I21: 1040 | J21: 1527 | K21: 1106 | L21: =AVERAGE(C21:K21) -> 1338.8889 | M21: =AVERAGE(D21:L21) -> 1346.7654 | N21: =AVERAGE(E21:M21) -> 1263.8505 | P21: 합계 | Q21: =SUM(C21:F21)/SUM(C$6:F$6) -> 0.045790785 | R21: =SUM(R12:R20) -> 0.096829111 | S21: =SUM(S12:S21) -> #DIV/0! | U21: 기타의 경우, 금액적 유의성이 낮아 2개년도 이동평균 적용함
B22: 영업이익 | C22: =C9-C11 -> 2715 | D22: =D9-D11 -> 1940 | E22: =E9-E11 -> 983 | F22: =F9-F11 -> 408 | G22: =G9-G11 -> -2166 | H22: =H9-H11 -> -1077 | I22: =I9-I11 -> -809 | J22: =J9-J11 -> 1049 | ... N22: =N9-N11 -> 3869.4205
B23: OPM(%) | C23: =C22/C6 -> 0.087574995 | D23: =D22/D6 -> 0.05717654 | E23: =E22/E6 -> 0.033597649 | F23: =F22/F6 -> 0.010543453 | G23: =G22/G6 -> -0.090521565 | H23: =H22/H6 -> -0.040197066 | I23: =I22/I6 -> -0.029172076 | J23: =J22/J6 -> 0.023061534 | ... N23: =N22/N6 -> 0.068905307 | P23: =H13/H12 -> 0.047333333 | Q23: =I13/I12 -> 0.061983471 | R23: =J13/J12 -> 0.065972222 | S23: =K13/K12 -> 0.056883759
B24: 지분법손익 | C24: 249 | D24: -755 | E24: 285 | F24: =141-SUM(C24:E24) -> 362 | G24: -516 | H24: -494 | I24: -1012 | J24: =-3267-SUM(G24:I24) -> -1245 | K24: -1367 | L24: =AVERAGE(D24:K24) -> -592.75 | M24: =L24 -> -592.75 | N24: =L24 -> -592.75
B25: 금융손익 | C25: 181 | D25: 205 | E25: 254 | F25: =953-E25-D25-C25 -> 313 | G25: 262 | H25: 349 | I25: 230 | J25: =1083-SUM(G25:I25) -> 242 | K25: 296 | L25: =AVERAGE(C25:K25) -> 259.11111 | M25: =L25 -> 259.11111 | N25: =M25 -> 259.11111 | U25: 금융손익의 경우, 2개년도 이동평균 flat 적용함
B26: 금융비용 | C26: -821 | D26: -913 | E26: -1120 | F26: =-4161-SUM(C26:E26) -> -1307 | G26: -1381 | H26: -1642 | I26: -1558 | J26: =-5484-SUM(G26:I26) -> -903 | K26: 1346 | L26: =AVERAGE(D26:K26) -> -934.75 | M26: =L26 -> -934.75 | N26: =L26 -> -934.75 | U26: 금융비용의 경우, 2개년도 이동평균 flat 적용함
B27: 기타수익 | C27: 2780 | D27: 1434 | E27: 1224 | F27: =6073-E27-D27-C27 -> 635 | G27: 1685 | H27: 1489 | I27: 525 | J27: =6943-SUM(G27:I27) -> 3244 | K27: 1117 | L27: =AVERAGE(D27:K27) -> 1419.125 | M27: =L27 -> 1419.125 | N27: =L27 -> 1419.125 | U27: 기타수익의 경우, 2개년도 이동평균 flat 적용함
B28: 기타비용 | C28: -3092 | D28: -1468 | E28: -1290 | F28: =-10071-SUM(C28:E28) -> -4221 | G28: -3058 | H28: -1734 | I28: -1077 | J28: =-10509-SUM(G28:I28) -> -4640 | K28: -2376 | L28: =AVERAGE(D28:K28) -> -2483 | M28: =L28 -> -2483 | N28: =L28 -> -2483 | U28: 기타비용의 경우, 2개년도 이동평균 flat 적용함
B29: 법인세차감전순이익 | C29: =SUM(C22,C24:C28) -> 2012 | D29: =D22+SUM(D24:D28) -> 443 | E29: =SUM(E22,E24:E28) -> 336 | F29: =SUM(F22,F24:F28) -> -3810 | G29: =G22+SUM(G24:G28) -> -5174 | H29: =H22+SUM(H24:H28) -> -3109 | I29: =I22+SUM(I24:I28) -> -3701 | J29: =J22+SUM(J24:J28) -> -2253 | K29: =K22+SUM(K24:K28) -> -681 | L29: =SUM(L22:L28) -> -589.17789 | M29: =SUM(M22:M28) -> 133.52901 | N29: =SUM(N22:N28) -> 1537.2255
B30: 법인세비용 | C30: 606 | D30: 222 | E30: 130 | F30: =411-E30-D30-C30 -> -547 | G30: -691 | H30: -641 | I30: =-116 -> -116 | J30: =-3156-SUM(G30:I30) -> -1708 | K30: -392 | L30: 0 | M30: 0 | N30: =2*0.09+198*0.19+636*0.21 -> 171.36 | U30: 법인세비용의 경우, 흑자시 표준세율을 적용함
B31: 법인세율(%) | C31: =C30/C29 -> 0.30119284 | D31: =D30/D29 -> 0.50112867 | E31: =E30/E29 -> 0.38690476 | F31: =F30/F29 -> 0.14356955 | G31: =G30/G29 -> 0.13355238 | H31: =H30/H29 -> 0.20617562 | I31: =I30/I29 -> 0.03134288 | J31: =J30/J29 -> 0.75810031 | K31: =K30/K29 -> 0.57562408 | L31: 0 | M31: =L31 -> 0 | N31: =N30/N29 -> 0.11147356
B32: 계속영업이익 | C32: =C29-C30 -> 1406 | D32: =D29-D30 -> 221 | E32: =E29-E30 -> 206 | F32: =F29-F30 -> -3263 | G32: =G29-G30 -> -4483 | H32: =H29-H30 -> -2468 | I32: =I29-I30 -> -3585 | J32: =J29-J30 -> -545 | ... N32: =N29-N30 -> 1365.8655
B33: 중단영업분기순손익 | C33: -72 | D33: -12 | F33: =-84-SUM(C33:D33) -> 0 | H33: -829 | I33: -288 | J33: =-2598-SUM(H33:I33) -> -1481 | K33: -13 | L33: 0 | M33: 0 | N33: 0
B34: 당기순이익 | C34: =C32+C33 -> 1334 | D34: =D32+D33 -> 209 | E34: =E32+E33 -> 206 | F34: =F32+F33 -> -3263 | G34: =G32+G33 -> -4483 | H34: =H32+H33 -> -3297 | I34: =I32+I33 -> -3873 | J34: =J32+J33 -> -2026 | ... N34: =N32+N33 -> 1365.8655
B35: 지배지분순이익 | C35: 1162 | D35: =71 -> 71 | E35: 59 | F35: =-2081-SUM(C35:E35) -> -3373 | G35: -4591 | H35: -3671 | I35: -4005 | J35: =-14044-SUM(G35:I35) -> -1777 | K35: -445 | L35: =L34*L36 -> -650.71366 | M35: =M34*M36 -> 147.47524 | N35: =N34*N36 -> 1508.5212
B36: % | C36: =C35/C34 -> 0.87106447 | D36: =D35/D34 -> 0.33971292 | E36: =E35/E34 -> 0.28640777 | F36: =F35/F34 -> 1.0337113 | G36: =G35/G34 -> 1.024091 | H36: =H35/H34 -> 1.1134365 | I36: =I35/I34 -> 1.0340821 | J36: =J35/J34 -> 0.87709773 | K36: =K35/K34 -> 1.4735099 | L36: =AVERAGE(G36:K36) -> 1.1044434 | M36: =L36 -> 1.1044434 | N36: =L36 -> 1.1044434
B37: 비지배지분순이익 | C37: 172 | D37: =137 -> 137 | E37: 147 | F37: =528-SUM(C37:E37) -> 72 | G37: 107 | H37: 373 | I37: 129 | J37: =354-SUM(G37:I37) -> -255 | K37: 143 | L37: =L34*L38 -> 58.917789 | M37: =M34*M38 -> -13.352901 | N37: =N34*N38 -> -136.58655
B38: % | C38: =C37/C34 -> 0.12893553 | D38: =D37/D34 -> 0.65550239 | E38: =E37/E34 -> 0.71359223 | F38: =F37/F34 -> -0.022065584 | G38: =G37/G34 -> -0.023867946 | H38: =H37/H34 -> -0.11313315 | I38: =I37/I34 -> -0.033307514 | J38: =J37/J34 -> 0.12586377 | K38: =K37/K34 -> -0.47350993 | L38: -0.1 | M38: -0.1 | N38: -0.1
B42: (단위: 억 원) | C42: 1Q23 | D42: 2Q23 | E42: 3Q23 | F42: 4Q23 | G42: 1Q24 | H42: 2Q24 | I42: 3Q24 | J42: 4Q24 | K42: 1Q25 | L42: 2Q25E | M42: 3Q25E | N42: 4Q25E
B43: 매출액 | C43: 31002 | D43: 33930 | E43: 29258 | F43: 38697 | G43: 23928 | H43: 26793 | I43: 27732 | J43: 45487 | K43: 30945 | L43: 37903.962 | M43: 40297.066 | N43: 56155.624
B44: 매출원가 | C44: 24243 | D44: 28047 | E44: 24616 | F44: 33592 | G44: 21958 | H44: 23331 | I44: 24664 | J44: 40129 | K44: 26443 | L44: =L45-L47 -> 31822.772 | M44: =M45-M47 -> 33394.012 | N44: =N45-N47 -> 47363.544
B45: AMPC 반영 전 매출원가 | C45: =C44+C47 -> 24472 | D45: =D44+D47 -> 28327 | E45: =E44+E47 -> 24966 | F45: =F44+F47 -> 34830 | G45: =G44+G47 -> 22924 | H45: =H44+H47 -> 24799 | I45: =I44+I47 -> 25880 | J45: =J44+J47 -> 42030 | K45: =K44+K47 -> 28282 | L45: =L43*L46 -> 33828.822 | M45: =M43*M46 -> 35461.418 | N45: =N43*N46 -> 49416.949
B46: 매출원가율 | C46: =C45/C43 -> 0.78936843 | D46: =D45/D43 -> 0.8348659 | E46: =E45/E43 -> 0.85330508 | F46: =F45/F43 -> 0.90006977 | G46: =G45/G43 -> 0.95804079 | H46: =H45/H43 -> 0.92557758 | I46: =I45/I43 -> 0.93321794 | J46: =J45/J43 -> 0.92400026 | K46: =K45/K43 -> 0.91394409 | L46: =AVERAGE(C46:K46) -> 0.89248776 | M46: 0.88 | N46: 0.88
B47: AMPC 보조금 | C47: 229 | D47: 280 | E47: 350 | F47: 1238 | G47: 966 | H47: 1468 | I47: 1216 | J47: 1901 | K47: 1839 | L47: 2006.0502 | M47: 2067.4057 | N47: 2053.4048
I52: =AVERAGE(C46:F46,H46:K46) -> 0.88429363
P59: ]

Sheet AMPC 보조금 수령액
C3: (단위: 억 원) | E3: 1Q23 | F3: 2Q23 | G3: 3Q23 | H3: 4Q23 | I3: 1Q24 | J3: 2Q24 | K3: 3Q24 | L3: 4Q24 | M3: 1Q25 | N3: 2Q25E | O3: 3Q25E | P3: 4Q25E | Q3: 2023 | R3: 2024 | S3: 2025E
C4: AMPC 보조금 (단위: 억 원) | E4: 229 | F4: 280 | G4: 350 | H4: 1238 | I4: 966 | J4: 1468 | K4: 1216 | L4: 1901 | M4: 1839 | N4: =N20*F32*N27*N5/100000000 -> 2006.0502 | O4: =O20*O27*F32*O5/100000000+O24*O28*F32*O5/1000000000+O25*O29*F32*O5/1000000000 -> 2067.4057 | P4: =P20*P27*F32*P5/100000000+P24*P28*F32*P5/1000000000+P25*P29*F32*P5/1000000000 -> 2053.4048 | Q4: =SUM(E4:H4) -> 2097 | R4: =SUM(I4:L4) -> 5551 | S4: =SUM(M4:P4) -> 7965.8606
C5: 환율 | E5: 1279.6 | F5: 1317.65 | G5: 1313.48 | H5: 1321.24 | I5: 1331.66 | J5: 1373.43 | K5: 1358.57 | L5: 1402.5 | M5: 1454.05 | N5: 1364.66 | O5: 1359.97 | P5: 1350.76
C6: 생산능력(CAPA)
C7: 모듈 | D7: 합산 | E7: =E8 -> 425 | F7: =F8 -> 425 | G7: =G8+G9 -> 1275 | H7: =H8+H9 -> 1275 | I7: 1275 | J7: 2100 | K7: 2100 | L7: 2100 | M7: 2100 | N7: =SUM(N8:N10) -> 2100 | O7: 2100 | P7: 2100 | Q7: =SUM(E7:H7) -> 3400 | R7: =SUM(I7:L7) -> 7575 | S7: =SUM(M7:P7) -> 8400
D8: 달튼 1공장 | E8: 425 | F8: 425 | G8: 425 | H8: 425 | I8: 425 | J8: 425 | K8: 425 | L8: 425 | M8: 425 | N8: 425 | O8: 425 | P8: 425 | Q8: =SUM(E8:H8) -> 1700 | R8: =SUM(I8:L8) -> 1700 | S8: =SUM(M8:P8) -> 1700
D9: 달튼 2공장 | E9: - | F9: - | G9: 850 | H9: 850 | I9: 850 | J9: 850 | K9: 850 | L9: 850 | M9: 850 | N9: 850 | O9: 850 | P9: 850 | Q9: =SUM(G9:H9) -> 1700 | R9: =SUM(I9:L9) -> 3400 | S9: =SUM(M9:P9) -> 3400
D10: 카터스빌 3공장 | E10: - | F10: - | G10: - | H10: - | I10: - | J10: 825 | K10: 825 | L10: 825 | M10: 825 | N10: 825 | O10: 825 | P10: 825 | Q10: - | R10: =SUM(J10:L10) -> 2475 | S10: =SUM(M10:P10) -> 3300
C11: 셀 | D11: 카터스빌 3공장 | E11: - | F11: - | G11: - | H11: - | I11: - | J11: - | K11: - | L11: - | M11: - | N11: - | O11: 825 | P11: 825 | Q11: - | R11: - | S11: =SUM(O11:P11) -> 1650
C12: 웨이퍼 | D12: 카터스빌 3공장 | E12: - | F12: - | G12: - | H12: - | I12: - | J12: - | K12: - | L12: - | M12: - | N12: - | O12: 825 | P12: 825 | Q12: - | R12: - | S12: =SUM(O12:P12) -> 1650
C13: 가동률 | G13: =35000000000/$D$27/$F$32/G5/G7 -> 0.29856325 | H13: =123800000000/$D$27/$F$32/H5/H7 -> 1.0498583
C14: 모듈 | D14: 달튼 1공장 | E14: =22900000000/$D$27/$F$32/E5/E7 -> 0.60155353 | F14: =28000000000/$D$27/$F$32/F5/F7 -> 0.71428412 | I14: 0.95 | J14: 0.95 | K14: 0.95 | L14: 0.95 | M14: 0.95 | N14: 1 | O14: 1 | P14: 1
D15: 달튼 2공장 | E15: - | F15: - | I15: 0.95 | J15: 0.95 | K15: 0.95 | L15: 0.95 | M15: 0.95 | N15: 1 | O15: 1 | P15: 1
D16: 카터스빌 3공장 | E16: - | F16: - | G16: - | H16: - | I16: - | J16: 0.7 | K16: 0.8 | L16: 0.9 | M16: 0.9 | N16: 1 | O16: 1 | P16: 1
C17: 셀 | D17: 카터스빌 3공장 | E17: - | F17: - | G17: - | H17: - | I17: - | J17: - | K17: - | L17: - | M17: - | N17: - | O17: 0.7 | P17: 0.7
C18: 웨이퍼 | D18: 카터스빌 3공장 | E18: - | F18: - | G18: - | H18: - | I18: - | J18: - | K18: - | L18: - | M18: - | N18: - | O18: 0.7 | P18: 0.7
C19: 생산량
C20: 모듈 | D20: 합산 | E20: =E21 -> 255.66025 | F20: =F21 -> 303.57075 | G20: =G7*G13 -> 380.66815 | H20: =H7*H13 -> 1338.5694 | I20: =SUM(I21:I22) -> 1211.25 | J20: =SUM(J21:J23) -> 1788.75 | K20: =SUM(K21:K23) -> 1871.25 | L20: =SUM(L21:L23) -> 1953.75 | M20: =SUM(M21:M23) -> 1953.75 | N20: =SUM(N21:N23) -> 2100 | O20: =SUM(O21:O23) -> 2100 | P20: =SUM(P21:P23) -> 2100 | Q20: =SUM(E20:H20) -> 2278.4685 | R20: =SUM(I20:L20) -> 6825 | S20: =SUM(M20:P20) -> 8253.75
D21: 달튼 1공장 | E21: =E8*E14 -> 255.66025 | F21: =F8*F14 -> 303.57075 | I21: =I8*I14 -> 403.75 | J21: =J8*J14 -> 403.75 | K21: =K8*K14 -> 403.75 | L21: =L8*L14 -> 403.75 | M21: =M8*M14 -> 403.75 | N21: =N8*N14 -> 425 | O21: =O8*O14 -> 425 | P21: =P8 -> 425
D22: 달튼 2공장 | E22: - | F22: - | G22: - | H22: - | I22: =I9*I15 -> 807.5 | J22: =J9*J15 -> 807.5 | K22: =K9*K15 -> 807.5 | L22: =L9*L15 -> 807.5 | M22: =M9*M15 -> 807.5 | N22: =N9*N15 -> 850 | O22: =O9*O15 -> 850 | P22: =P9 -> 850
D23: 카터스빌 3공장 | E23: - | F23: - | G23: - | H23: - | I23: - | J23: =J10*J16 -> 577.5 | K23: =K10*K16 -> 660 | L23: =L10*L16 -> 742.5 | M23: =M10*M16 -> 742.5 | N23: =N10*N16 -> 825 | O23: =O10*O16 -> 825 | P23: =P10*P16 -> 825
C24: 셀 | D24: 카터스빌 3공장 | E24: - | F24: - | G24: - | H24: - | I24: - | J24: - | K24: - | L24: - | M24: - | O24: =O11*O17 -> 577.5 | P24: =P11*P17 -> 577.5
C25: 웨이퍼 | D25: 카터스빌 3공장 | E25: - | F25: - | G25: - | H25: - | I25: - | J25: - | K25: - | L25: - | M25: - | O25: =O12*O18 -> 577.5 | P25: =P12*P18 -> 577.5
C26: 보조금($/W)
C27: 모듈 | D27: 0.07 | E27: =D27 -> 0.07 | F27: =E27 -> 0.07 | G27: =F27 -> 0.07 | H27: =G27 -> 0.07 | I27: =H27 -> 0.07 | J27: =I27 -> 0.07 | K27: =J27 -> 0.07 | L27: =K27 -> 0.07 | ... S27: =R27 -> 0.07
C28: 셀 | D28: 0.04 | E28: =D28 -> 0.04 | F28: =E28 -> 0.04 | G28: =F28 -> 0.04 | H28: =G28 -> 0.04 | I28: =H28 -> 0.04 | J28: =I28 -> 0.04 | K28: =J28 -> 0.04 | L28: =K28 -> 0.04 | ... S28: =R28 -> 0.04
C29: 웨이퍼 | D29: 0.0469 | E29: =D29 -> 0.0469 | F29: =E29 -> 0.0469 | G29: =F29 -> 0.0469 | H29: =G29 -> 0.0469 | I29: =H29 -> 0.0469 | J29: =I29 -> 0.0469 | K29: =J29 -> 0.0469 | L29: =K29 -> 0.0469 | ... S29: =R29 -> 0.0469
C30: 보조금=생산량*제품당 보조금*환율
E31: W | G31: 가동률 역산 | H31: E27*생산량*E5
E32: MW | F32: 1000000 | H32: =E4*D27/F32/E5 -> 1.2527352e-08
E33: GW | F33: 1000000000
F35: =F33/F32 -> 1000

Sheet 요약 재무제표
B1: Format | C1: 추정치 입력 | E1: 다른 시트 참조 | H1: *회계 공부를 해 본 적이 없는 그냥 평범한 사람이 만든 양식입니다. 참고하여 요약재무제표 만들어 주시기를 바랍니다. (36기 홍우현 제작)
C2: 기존 수식 활용 | E2: 하드코딩(Data 직접 입력) | H2: *틀린 부분이 있거나 더 좋은 추정 방식이 있을경우 적극적으로 업데이트해서 좋은 양식으로 발전시켰으면 좋겠습니다. 후배 기수 회계사님들 잘 부탁드립니다.
B3: (단위: 십억원) | H3: `
B4: 예상 포괄손익계산서 (요약) | C4: 2022 | D4: 2023 | E4: 2024 | F4: 2025E | H4: 예상 재무상태표 (요약) | I4: 2022 | J4: 2023 | K4: 2024 | L4: 2025E | R4: Historical | T4: Projection | W4: FCF란 뭘까? (brunch.co.kr) | Z4: ◀ 해당 내용 참고하여 작성함
B5: 매출액 | C5: =131307.5288752/10 -> 13130.753 | D5: =130785.3618047/10 -> 13078.536 | E5: =123940.2364901/10 -> 12394.024 | F5: 16530.2 | H5: 유동자산 | I5: 8573.3 | J5: 9797.4 | K5: 10883 | L5: =SUM(L6:L9) -> 8596.2925 | P5: in KRW Mn | R5: 2022 | S5: 2023 | T5: 2024 | U5: 2025
B6: 매출원가 | C6: =107317.5326426/10 -> 10731.753 | D6: =109132.408346/10 -> 10913.241 | E6: =110081.6832241/10 -> 11008.168 | F6: =F5-F7 -> 13902.4 | H6: 현금 및 현금성자산 | I6: 2548 | J6: 1958 | K6: 2184 | L6: =F52 -> 2660.5 | P6: EBIT | R6: =C10 -> 923.72665 | S6: =D10 -> 579.23703 | T6: =E10 -> -300.23796 | U6: =F10 -> 838.1 | W6: FCFF = NI + NCC + Int*(1-tex rate) - Capex -WC
B7: 매출총이익 | C7: =C5-C6 -> 2398.9996 | D7: =D5-D6 -> 2165.2953 | E7: =E5-E6 -> 1385.8553 | F7: 2627.8 | H7: 매출채권 및 기타채권 | I7: 2055 | J7: 2023 | K7: =2305+374 -> 2679 | L7: =U19 -> 2810.544 | Q7: % effective tax rate | R7: =R8/R6 -> 0.21867941 | S7: =S8/S6 -> 0.070955409 | T7: =T8/T6 -> 1.0511662 | U7: =-U8/U6 -> 0.26369168 | W7: FCF = NI + NCC - Capex -WC
B8: 판매비와관리비 | C8: =14752.72969/10 -> 1475.273 | D8: =15860.5831833/10 -> 1586.0583 | E8: =16860.9328654/10 -> 1686.0933 | F8: =F7-F9 -> 1789.7 | H8: 재고자산 | I8: 3060 | J8: 3447 | K8: 4258 | L8: =U20 -> 3047.1014 | P8: (-) | Q8: EBIT법인세 | R8: =C15 -> 202 | S8: =D15 -> 41.1 | T8: =E15 -> -315.6 | U8: =F15 -> -221 | W8: FCF = FCFF - Int*(1-tex rate)
B9: 조정영업이익 | C9: =C10 -> 923.72665 | D9: =D10 -> 579.23703 | E9: =E10 -> -300.23796 | F9: =F10 -> 838.1 | H9: 기타유동자산 | I9: 909 | J9: =J5-SUM(J6:J8) -> 2369.4 | K9: 1762 | L9: =N10-SUM(L6:L8) -> 78.147183 | Q9: 이자비용
B10: 영업이익 | C10: =9237.2665426/10 -> 923.72665 | D10: =5792.3702753/10 -> 579.23703 | E10: =-3002.3795995/10 -> -300.23796 | F10: 838.1 | H10: 비유동자산 | I10: 13634.4 | J10: =SUM(J11:J13)+1517 -> 14993 | K10: 19154 | L10: =SUM(L11:L13) -> 17497.167 | N10: =N14-L10 -> 8596.2925 | P10: NOPAT(세후영업이익) | R10: =R6-R8 -> 721.72665 | S10: =S6-S8 -> 538.13703 | T10: =T6-T8 -> 15.36204 | U10: =U6-U8 -> 1059.1
B11: 비영업손익 | C11: -355 | D11: =D10-D12-D13-D14 -> 560.23703 | E11: =E10-E12-E13-E14 -> 1047.762 | F11: =F10-F12-F13-F14 -> 921.2 | H11: 투자자산 | I11: 4197 | J11: 4653 | K11: 5434 | L11: =AVERAGE(I11:K11) -> 4761.3333 | Q11: % Yoy Growth | S11: =S10/R10-1 -> -0.25437557 | T11: =T10/S10-1 -> -0.97145329 | U11: =U10/T10-1 -> 67.942666
B12: 금융손익 | C12: 30 | D12: 95.3 | E12: 108.3 | F12: 107.3 | H12: 유형자산 | I12: 6879 | J12: 7050 | K12: 10727 | L12: =U37 -> 11011.5 | Q12: Change in NWC | R12: =R25 -> 257.4 | S12: =S25 -> -839.3 | T12: =T25 -> 1418.7 | U12: =U25 -> 447.90282
B13: 관계기업등 투자손익 | C13: -102 | D13: 25.6 | E13: -32.7 | F13: -31.5 | H13: 무형자산 | I13: 1644 | J13: 1773 | K13: 1756 | L13: =AVERAGE(I13:K13) -> 1724.3333 | M13: 24년 자산총계 | N13: 25년 자산총계 | Q13: Net Capex | R13: =R38 -> 3701.9 | S13: =S38 -> 1673.7 | T13: =T38 -> 4412.7 | U13: =U38 -> 3010.6
B14: 세전계속사업손익 | C14: 569 | D14: =D15+D16 -> -101.9 | E14: =E15+E16 -> -1423.6 | F14: =F16+F15 -> -158.9 | H14: 자산총계 | I14: =I5+I10+1624 -> 23831.7 | J14: =J10+J5 -> 24790.4 | K14: =K10+K5 -> 30037 | L14: =L10+L5 -> 26093.459 | M14: =K22+K28 -> 30036.9 | N14: =L22+L28 -> 26093.459 | P14: (-) Reinvestment | R14: =R12+R13 -> 3959.3 | S14: =S12+S13 -> 834.4 | T14: =T12+T13 -> 5831.4 | U14: =U12+U13 -> 3458.5028
B15: 법인세 비용 | C15: 202 | D15: 41.1 | E15: -315.6 | F15: -221 | H15: 유동부채 | I15: 6808.5 | J15: 8734.1 | K15: 11707.6 | L15: =SUM(L16:L18) -> 8717.7425 | P15: FCFF(기업잉여현금흐름) | R15: =R10-R14 -> -3237.5733 | S15: =S10-S14 -> -296.26297 | T15: =T10-T14 -> -5816.038 | U15: =U10-U14 -> -2399.4028
B16: 계속사업이익 | C16: 247 | D16: -143 | E16: -1108 | F16: 62.1 | H16: 매입채무 및 기타채무 | I16: 2780.6 | J16: 3974.9 | K16: 4023.2 | L16: =U22 -> 2495.9425 | P16: FCF(잉여현금흐름) | R16: =C25 -> -787.2 | S16: =D25 -> -1872.5 | T16: -2759.1 | U16: =U15-U9*(1-U7) -> -2399.4028
B17: 중단사업이익 | C17: 19 | D17: -8.4 | E17: -259.8 | F17: -1.3 | H17: 단기금융부채 | I17: =I15-I16-I18 -> 3951.6 | J17: =J15-J16-J18 -> 4578.9 | K17: =K15-K16-K18 -> 7266.3 | L17: =AVERAGE(J17:K17) -> 5922.6
B18: 당기순이익 | C18: 366 | D18: =D16+D17 -> -151.4 | E18: =E16+E17 -> -1367.8 | F18: 60.8 | H18: 기타유동부채 | I18: 76.3 | J18: 180.3 | K18: 418.1 | L18: =AVERAGE(J18:K18) -> 299.2 | M18: (단위: 십억원) | P18: Change in Net Working Capital | R18: 2022 | S18: 2023 | T18: 2024 | U18: 2025
B19: 지배주주 | C19: 359 | D19: -208.1 | E19: -1404.4 | F19: -77 | H19: 비유동부채 | I19: 5685.4 | J19: 6776.1 | K19: 7722.4 | L19: =SUM(L20:L21) -> 6731.0667 | M19: 유동주식수 | N19: 171892536 | Q19: 매출채권 | R19: =I7 -> 2055 | S19: =J7 -> 2023 | T19: =K7 -> 2679 | U19: =U28*F5/365 -> 2810.544
B20: 비지배주주 | C20: 7 | D20: 52.8 | E20: 35.4 | F20: 17.2 | H20: 장기금융부채 | I20: =I19-I21 -> 5681.6 | J20: =J19-J21 -> 6773.2 | K20: =K19-K21 -> 7714.4 | L20: =AVERAGE(I20:K20) -> 6723.0667 | M20: Enterprise Value | N20: =N21+(K17+K20-K6-K11) -> 12244.7 | Q20: 재고자산 | R20: =I8 -> 3060 | S20: =J8 -> 3447 | T20: =K8 -> 4258 | U20: =U29*F6/365 -> 3047.1014
B21: 총포괄이익 | C21: 584.8 | D21: -67 | E21: 756.9 | F21: =F18+788.6 -> 849.4 | H21: 기타비유동부채 | I21: 3.8 | J21: 2.9 | K21: 8 | L21: =K21 -> 8 | M21: 시가총액 | N21: 4882 | Q21: 영업용 유동자산 | R21: =SUM(R19:R20) -> 5115 | S21: =SUM(S19:S20) -> 5470 | T21: =SUM(T19:T20) -> 6937 | U21: =SUM(U19:U20) -> 5857.6454
B22: 지배주주 | C22: 580.5 | D22: -124.9 | E22: 648 | F22: =F21*0.92 -> 781.448 | H22: 부채총계 | I22: =SUM(I19,I15)+1441 -> 13934.9 | J22: =SUM(J19,J15) -> 15510.2 | K22: =SUM(K19,K15) -> 19430 | L22: =SUM(L19,L15) -> 15448.809 | M22: 현재주가 | N22: 28500 | Q22: 매입채무 | R22: =I16 -> 2780.6 | S22: =J16 -> 3974.9 | T22: =K16 -> 4023.2 | U22: =U30*F6/365 -> 2495.9425
B23: 비지배주주 | C23: 4.3 | D23: 57.8 | E23: 108.9 | F23: =F21-F22 -> 67.952 | H23: 지배주주지분 | I23: 8920.6 | J23: 8117.2 | K23: 9449.7 | L23: =K23+(L26-K26) -> 9484.5 | Q23: 영업용 유동부채 | R23: =SUM(R22) -> 2780.6 | S23: =SUM(S22) -> 3974.9 | T23: =SUM(T22) -> 4023.2 | U23: =SUM(U22) -> 2495.9425
B24: EBITDA | C24: 1599 | D24: 1283 | E24: =E10+E33 -> 419.56204 | F24: =F10+F33 -> 1848.6 | H24: 자본금 | I24: 978.2 | J24: 888.6 | K24: 828.6 | L24: =AVERAGE(I24:K24) -> 898.46667 | P24: 순운전자본 | R24: =R21-R23 -> 2334.4 | S24: =S21-S23 -> 1495.1 | T24: =T21-T23 -> 2913.8 | U24: =U21-U23 -> 3361.7028
B25: FCF | C25: -787.2 | D25: -1872.5 | E25: =T16 -> -2759.1 | F25: =U16 -> -2399.4028 | H25: 자본잉여금 | I25: 2320.1 | J25: 1496.3 | K25: 1562.4 | L25: =AVERAGE(I25:K25) -> 1792.9333 | P25: 순운전자본의 변동 | R25: =R24-2077 -> 257.4 | S25: =S24-R24 -> -839.3 | T25: =T24-S24 -> 1418.7 | U25: =U24-T24 -> 447.90282
B26: EBITDA 마진율 (%) | C26: =C24/C5*100 -> 12.17752 | D26: =D24/D5*100 -> 9.8099664 | E26: =E24/E5*100 -> 3.3851964 | F26: =F24/F5*100 -> 11.183168 | H26: 이익잉여금 | I26: 5561.4 | J26: 5609.4 | K26: 4123.4 | L26: =K26+(F18+F48) -> 4158.2 | P26: Ratio & Assumption
B27: 영업이익률 (%) | C27: =C10/C5*100 -> 7.0348339 | D27: =D10/D5*100 -> 4.4289133 | E27: =E10/E5*100 -> -2.4224414 | F27: =F10/F5*100 -> 5.0701141 | H27: 비지배주주지분 | I27: 976.3 | J27: 1163.1 | K27: 1157.2 | L27: =AVERAGE(J27:K27) -> 1160.15 | P27: 회전일수
B28: 지배주주귀속 순이익률 (%) | C28: =C18/C5*100 -> 2.7873497 | D28: =D18/D5*100 -> -1.1576219 | E28: =E18/E5*100 -> -11.035964 | F28: =F18/F5*100 -> 0.36781164 | H28: 자본총계 | I28: =SUM(I27,I23) -> 9896.9 | J28: =SUM(J27,J23) -> 9280.3 | K28: =SUM(K27,K23) -> 10606.9 | L28: =SUM(L27,L23) -> 10644.65 | Q28: 매출채권회전일수 | R28: =I43 -> 55.05279 | S28: =J43 -> 61.864407 | T28: =K43 -> 69.259962 | U28: =AVERAGE(R28:T28) -> 62.059053 | W28: =1-S28/R28 -> -0.12372881
C29: 116 | D29: 518 | E29: 638 | Q29: 재고자산회전일수 | R29: =I44 -> 73.58871 | S29: =J44 -> 90.79602 | T29: =K44 -> 113.35404 | U29: 80
B30: 예상 현금흐름표 (요약) (십억원) | C30: 2022 | D30: 2023 | E30: 2024E | F30: 2025E | H30: 예상 주당가치 및 valuation (요약) | I30: 2022 | J30: 2023 | K30: 2024E | L30: 2025E | Q30: 매입채무회전일수 | R30: =I45 -> 50.624133 | S30: =J45 -> 51.192146 | T30: =K45 -> 65.529623 | U30: =T30 -> 65.529623
B31: 영업활동으로 인한 현금흐름 | C31: =SUM(C32,C33,C37:C39) -> 116 | D31: =SUM(D32,D33,D37:D39) -> 518 | E31: =SUM(E32,E33,E37:E39) -> 638 | F31: =SUM(F32,F33,F36:F39) -> 1745.5 | H31: P/E (x) | I31: 23.1 | J31: N/A | K31: N/A | L31: =$N$22/L34 -> 80.574626 | Q31: 현금전환주기 | R31: =SUM(R28:R29)-R30 -> 78.017367 | S31: =SUM(S28:S29)-S30 -> 101.46828 | T31: =SUM(T28:T29)-T30 -> 117.08438 | U31: =SUM(U28:U29)-U30 -> 76.52943
B32: 당기순이익 | C32: =C18 -> 366 | D32: =D18 -> -151.4 | E32: =E18 -> -1367.8 | F32: =F18 -> 60.8 | H32: P/B (x) | I32: 0.9 | J32: 0.9 | K32: 0.3 | L32: =$N$22/L35 -> 0.4602253
B33: 감가상각비(계) | C33: =SUM(C34:C36) -> 675.3 | D33: =SUM(D34:D36) -> 681.3 | E33: =SUM(E34:E36) -> 719.8 | F33: =SUM(F34:F36) -> 1010.5 | H33: EV/EBITDA (x) | I33: 9 | J33: 12.1 | K33: 35.3 | L33: =N20/F24 -> 6.6237693 | P33: Net Capex | R33: 2022 | S33: 2023 | T33: 2024 | U33: 2025
B34: 유형자산 감가상각비 | C34: 570 | D34: 579 | E34: 576 | F34: 883.3 | H34: EPS (원) | I34: 1864 | J34: -1172 | K34: -8050 | L34: =F18*1000000000/N19 -> 353.70937 | Q34: 기초 유형자산 | R34: =R36+R37-R35 -> 5948.9 | S34: =R37 -> 6879 | T34: =S37 -> 7050 | U34: =T37 -> 10022.1
B35: 무형자산 상각비 | C35: 65.1 | D35: 38 | E35: 66 | F35: 53.2 | H35: BPS (원) | I35: 46957 | J35: 45654 | K35: 54793 | L35: =L28*1000000000/N19 -> 61926.191 | Q35: Capex | R35: 2316 | S35: 1000.1 | T35: 3692.4 | U35: 2000
B36: 사용권자산 상각비 | C36: 40.2 | D36: 64.3 | E36: 77.8 | F36: 74 | H36: DPS (원) | I36: 0 | J36: 300 | K36: 300 | L36: 300 | Q36: 감가상각비 | R36: 1385.9 | S36: 673.6 | T36: 720.3 | U36: 1010.6
B37: 영업활동 자산부채 변동 | C37: -1626 | D37: -499 | E37: 134 | F37: =AVERAGE(C37:E37) -> -663.66667 | H37: 배당성향 (%) | I37: 0 | J37: -24.4 | K37: =-E48/E18*100 -> -10.089194 | L37: =-F48/F18*100 -> 42.763158 | Q37: 기말 유형자산 | R37: =I12 -> 6879 | S37: =J12 -> 7050 | T37: =T34+T35-T36 -> 10022.1 | U37: =U34+U35-U36 -> 11011.5
B38: 법인세납부 | C38: -219 | D38: -498 | E38: -71.8 | F38: =-F15 -> 221 | H38: 배당수익률 (%) | I38: 0 | J38: 0.8 | K38: =-E48/N21*100 -> 2.8267104 | L38: =-F48/N21*100 -> 0.53256862 | P38: Net Capex | R38: =R35+R36 -> 3701.9 | S38: =S35+S36 -> 1673.7 | T38: =T35+T36 -> 4412.7 | U38: =U35+U36 -> 3010.6
B39: 기타 | C39: =C29-C32-C33-C37-C38 -> 919.7 | D39: =D29-D32-D33-D37-D38 -> 985.1 | E39: =E29-E32-E33-E37-E38 -> 1223.8 | F39: =AVERAGE(C39:E39) -> 1042.8667 | H39: 매출액증가율 (%) | I39: =(C5/10217-1)*100 -> 28.518674 | J39: =(D5/C5-1)*100 -> -0.39766727 | K39: =(E5/D5-1)*100 -> -5.233862 | L39: =(F5/E5-1)*100 -> 33.372345 | P39: Ratio & Assumption
B40: 투자활동으로 인한 현금흐름 | C40: -1477 | D40: -2799 | E40: -3287 | F40: =SUM(F41:F44) -> -2521 | H40: EBITDA증가율 (%) | I40: =(C24/743.4-1)*100 -> 115.09282 | J40: =(D24/C24-1)*100 -> -19.762351 | K40: =(E24/D24-1)*100 -> -67.29836 | L40: =(F24/E24-1)*100 -> 340.6023 | Q40: % Net Capex / Sales | R40: =R38/C5 -> 0.28192595 | S40: =S38/D5 -> 0.12797304 | T40: =T38/E5 -> 0.3560345 | U40: =U38/F5 -> 0.18212726
B41: 유형자산처분(취득) | C41: -889 | D41: -2359 | E41: =-3344 -> -3344 | F41: =AVERAGE(C41:E41) -> -2197.3333 | H41: 조정영업이익증가율 (%) | I41: =(C10/703.5-1)*100 -> 31.304428 | J41: =(D10/C10-1)*100 -> -37.29346 | K41: =(E10/D10-1)*100 -> -151.83335 | L41: =(F10/-E10-1)*100 -> 179.14525 | Q41: % Capex / Sales | R41: =R35/C5 -> 0.17637983 | S41: =S35/D5 -> 0.076468802 | T41: 0.1 | U41: 0.08
B42: 무형자산감소(증가) | C42: -37 | D42: -18 | E42: -21 | F42: =AVERAGE(C42:E42) -> -25.333333 | H42: EPS증가율 (%) | I42: -43.5 | J42: 적전 | K42: 적지 | L42: 흑전 | Q42: % D&A / Sales | R42: =R36/C5 -> 0.10554612 | S42: =S36/D5 -> 0.051504235 | T42: 0.02 | U42: 0.02
B43: 장단기금융자산의 감소(증가) | C43: -120 | D43: 160 | E43: -107 | F43: =AVERAGE(C43:E43) -> -22.333333 | H43: 매출채권 회전일수 | I43: =365/6.63 -> 55.05279 | J43: =365/5.9 -> 61.864407 | K43: =365/5.27 -> 69.259962 | L43: =U28 -> 62.059053 | Q43: % Capex / D&A | R43: =R36/R37 -> 0.20146824 | S43: =S36/S37 -> 0.095546099 | T43: =T36/T37 -> 0.071871165 | U43: =U36/U37 -> 0.091776779
B44: 기타투자활동 | C44: =C40-SUM(C41:C43) -> -431 | D44: =D40-SUM(D41:D43) -> -582 | E44: =E40-SUM(E41:E43) -> 185 | F44: =AVERAGE(C44:E44) -> -276 | H44: 재고자산 회전일수 | I44: =365/4.96 -> 73.58871 | J44: =365/4.02 -> 90.79602 | K44: =365/3.22 -> 113.35404 | L44: =U29 -> 80
B45: 재무활동으로 인한 현금흐름 | C45: 2322 | D45: 1609 | E45: =SUM(E46:E49) -> 2676 | F45: =SUM(F46:F49) -> 1252 | H45: 매입채무 회전일수 | I45: =365/7.21 -> 50.624133 | J45: =365/7.13 -> 51.192146 | K45: =365/5.57 -> 65.529623 | L45: =U30 -> 65.529623
B46: 장단기금융부채의 증가(감소) | C46: 1566 | D46: 1784 | E46: 3485 | F46: =AVERAGE(C46:D46) -> 1675 | H46: ROA (%) | I46: 1.7 | J46: =D18/J14*100 -> -0.61072028 | K46: =E18/K14*100 -> -4.5537171 | L46: =F18/L14*100 -> 0.23300858
B47: 자본의 증가(감소) | C47: 317 | D47: -913 | E47: 66 | F47: =AVERAGE(D47:E47) -> -423.5 | H47: ROE (%) | I47: 4.2 | J47: =D18/J28*100 -> -1.6314128 | K47: =E18/K28*100 -> -12.895379 | L47: =F18/L28*100 -> 0.57117895
B48: 배당금의 지급 | C48: 0 | D48: -52 | E48: -138 | F48: =AVERAGE(C48:D48) -> -26 | H48: ROIC (%) | I48: 5.6 | J48: 7.1 | K48: =T10/(K7+K8+K12)*100 -> 0.086968071 | L48: =U10/(L7+L8+L12)*100 -> 6.2783264
B49: 기타재무활동 | C49: =C45-C46-C47 -> 439 | D49: =D45-D46-D47-D48 -> 790 | E49: -737 | F49: =AVERAGE(D49:E49) -> 26.5 | H49: 부채비율 (%) | I49: =I22/I28*100 -> 140.80065 | J49: =J22/J28*100 -> 167.13037 | K49: =K22/K28*100 -> 183.18265 | L49: =L22/L28*100 -> 145.13215
B50: 현금의 증가 | C50: 965 | D50: -658 | E50: 226 | F50: =SUM(F45,F40,F31) -> 476.5 | H50: 유동비율 (%) | I50: =I5/I15 -> 1.2592054 | J50: =J5/J15*100 -> 112.17412 | K50: =K5/K15*100 -> 92.956712 | L50: =L5/L15*100 -> 98.606864
B51: 기초현금 | C51: 1652 | D51: 2616 | E51: 1958 | F51: =E52 -> 2184 | H51: 당좌비율 (%) | I51: =(I5-I8)/I15*100 -> 80.97672 | J51: =(J5-J8)/J15*100 -> 72.708121 | K51: =(K5-K8)/K15*100 -> 56.587174 | L51: =(L5-L8)/L15*100 -> 63.653992
B52: 기말현금 | C52: 2616 | D52: 1958 | E52: 2184 | F52: =F51+F50 -> 2660.5 | H52: 자기자본비율 (%) | I52: =I28/I14*100 -> 41.528301 | J52: =J28/J14*100 -> 37.435056 | K52: =K28/K14*100 -> 35.312781 | L52: =L28/L14*100 -> 40.794323

Sheet FA Schedule
A1: 한화솔루션(009830.KS)
A2: Assumption Sheet
A3: (댠위: 억원)
B5: (단위: 억원) | C5: 2023 | D5: 2024 | E5: 2025E | G5: (단위: 억원) | H5: 2023 | I5: 2024 | J5: 2025E | L5: (단위: 억원) | M5: 2023 | N5: 2024 | O5: 2025E
B6: 유형자산 | C6: =C16 -> 70498 | D6: 107270 | E6: =E16 -> 129147.56 | G6: Total Capex | H6: =C13+C20+C27 -> 10001 | I6: =D13+D20+D27 -> 36924 | J6: =E13+E20+E27 -> 29562.29 | L6: 매출액 | M6: ='[1]매출액 추정 ▶'!O6 -> 130785 | N6: ='[1]매출액 추정 ▶'!P6 -> 131305 | O6: ='매출액 추정 ▶'!Q6 -> 165301.65
B7: 무형자산 | C7: 17226 | D7: 17557 | E7: =E23 -> 17871.765 | G7: Total D&A | H7: =C14+C21+C28 -> 6736 | I7: =D14+D21+D28 -> 7203 | J7: =E14+E21+E28 -> 10105.584
B8: 사용권자산 | C8: 2265 | D8: 2950 | E8: =E30 -> 2665.3833
B11: (단위: 억원) | C11: 2023 | D11: 2024 | E11: 2025E | G11: (단위: %) | H11: 2023 | I11: 2024 | J11: 2025E
B12: 기초 유형자산 | C12: 68829 | D12: =C16 -> 70498 | E12: =D16 -> 107270 | G12: 매출액 대비 Capex | H12: =C13/M6 -> 0.07022212 | I12: =D13/N6 -> 0.26722516 | J12: =AVERAGE(H12:I12) -> 0.16872364
B13: (+) Capex | C13: =9177+7 -> 9184 | D13: 35088 | E13: =O6*J12 -> 27890.297 | G13: 기초 유형자산 대비 감가상각비 | H13: =C14/C12 -> 0.082944689 | I13: =D14/D12 -> 0.081747 | J13: =AVERAGE(H13:I13) -> 0.082345844
B14: (-) 감가상각비 | C14: =5705+4 -> 5709 | D14: 5763 | E14: =E12*J13 -> 8833.2387
B15: (+) 기타 증감 | C15: =C16-C12-C13+C14 -> -1806 | D15: =D16-D12-D13+D14 -> 7447 | E15: =AVERAGE(C15:D15) -> 2820.5
B16: 기말 유형자산 | C16: 70498 | D16: 107270 | E16: =E12+E13-E14+E15 -> 129147.56
B18: (단위: 억원) | C18: 2023 | D18: 2024 | E18: 2025E | G18: (단위: %) | H18: 2023 | I18: 2024 | J18: 2025E
B19: 기초 무형자산 | C19: =16444+55 -> 16499 | D19: 17726 | E19: =D23 -> 17557 | G19: 매출액 대비 Capex | H19: =C20/M6 -> 0.0011851512 | I19: =D20/N6 -> 0.0014393968 | J19: =AVERAGE(H19:I19) -> 0.001312274
B20: (+) Capex | C20: =113+42 -> 155 | D20: 189 | E20: =O6*J19 -> 216.92106 | G20: 기초 무형자산 대비 상각비 | H20: =C21/C19 -> 0.023274138 | I20: =D21/D19 -> 0.037346271 | J20: =AVERAGE(H20:I20) -> 0.030310204
B21: (-) 감가상각비 | C21: =378+6 -> 384 | D21: 662 | E21: =E19*J20 -> 532.15626
B22: (+) 기타 증감 | C22: =C23-C19-C20+C21 -> 956 | D22: =D23-D19-D20+D21 -> 304 | E22: =AVERAGE(C22:D22) -> 630
B23: 기말 무형자산 | C23: 17226 | D23: 17557 | E23: =E19+E20-E21+E22 -> 17871.765
B25: (단위: 억원) | C25: 2023 | D25: 2024 | E25: 2025E | G25: (단위: %) | H25: 2023 | I25: 2024 | J25: 2025E
B26: 기초 사용권자산 | C26: =4059+2 -> 4061 | D26: 2265 | E26: =D30 -> 2950 | G26: 매출액 대비 Capex | H26: =C27/M6 -> 0.0050617426 | I26: =D27/N6 -> 0.012543315 | J26: =AVERAGE(H26:I26) -> 0.0088025289
B27: (+) Capex | C27: =660+2 -> 662 | D27: 1647 | E27: =O6*J26 -> 1455.0726 | G27: 기초 사용권자산 대비 감가상각비 | H27: =C28/C26 -> 0.15833539 | I27: =D28/D26 -> 0.34348786 | J27: =AVERAGE(H27:I27) -> 0.25091162
B28: (-) 감가상각비 | C28: =641+2 -> 643 | D28: 778 | E28: =E26*J27 -> 740.18929
B29: (+) 기타 증감 | C29: =C30-C26-C27+C28 -> -1815 | D29: =D30-D26-D27+D28 -> -184 | E29: =AVERAGE(C29:D29) -> -999.5
B30: 기말 사용권자산 | C30: 2265 | D30: 2950 | E30: =E26+E27-E28+E29 -> 2665.3833

Sheet HISTORICAL▶
A1: 한화솔루션(009830.KS)_EV/EBITDA
A3: HISTORICAL DATA >>>
B5: Chungang-Univ. Financial Institute
B6: R.F.S .
B7: Valuation Model
B17: RFS 정식 회원 외 본 가치평가 모델의 무단 사용 및 수정을 금하며, 본 양식의 원 저작권은 중앙대학교 R.F.S. 학회에 있음을 밝힙니다.
B18: 원 제작자: 28기 김 건 (zzkan103@gmail.com)
B19: 1st Version: 2021.03.02

Sheet BS(Q)
B1: Last Refresh: 2025-05-24 13:23:02
A2: Financial Statements
A3: 기업 | B3: A009830(한화솔루션) - Fiscal Month:12, 201103부터 IFRS 적용
A4: 회계유형 | B4: 연결 | C4: 회계기준 | D4: IFRS
A5: 리포트 | B5: 재무상태표 | C5: New
A6: 형식 | B6: 약식(COMPARE)
A7: 출력 | B7: 당분기 | C7: 억원
A8: 회계연도 | B8: 2022 | C8: Current
A9: 계정코드 | B9: 계정명 | C9: 단위 | D9: 202203(1Q) | E9: 202206(2Q) | F9: 202209(3Q) | G9: 202212(4Q) | H9: 202303(1Q) | I9: 202306(2Q) | J9: 202309(3Q) | K9: 202312(4Q) | L9: 202403(1Q) | M9: 202406(2Q) | N9: 202409(3Q) | O9: 202412(4Q) | P9: 202503(1Q)
D10: IFRS(연결) | E10: IFRS(연결) | F10: IFRS(연결) | G10: IFRS(연결) | H10: IFRS(연결) | I10: IFRS(연결) | J10: IFRS(연결) | K10: IFRS(연결) | L10: IFRS(연결) | M10: IFRS(연결) | N10: IFRS(연결) | O10: IFRS(연결) | P10: IFRS(연결)
A11: 4001190010 | B11: 자산(*) | C11: 억원 | D11: 211504.66 | E11: 224844.06 | F11: 238877.59 | G11: 238318.84 | H11: 221294.07 | I11: 232311.34 | J11: 249664.13 | K11: 247904.24 | L11: 269021.8 | M11: 291517.29 | N11: 294091.63 | O11: 300368.31 | P11: 304814.84
A12: 4001190240 | B12: 유동자산(*) | C12: 억원 | D12: 64924.188 | E12: 74329.041 | F12: 84009.35 | G12: 85732.954 | H12: 77362.554 | I12: 82136.597 | J12: 91159.491 | K12: 97973.721 | L12: 100983.84 | M12: 95576.243 | N12: 94046.216 | O12: 108826.65 | P12: 105772.39
A13: 4001190250 | B13: 재고자산(*) | C13: 억원 | D13: 24155.084 | E13: 29715.657 | F13: 34745.678 | G13: 30601.078 | H13: 32070.131 | I13: 32446.198 | J13: 33107.43 | K13: 34474.813 | L13: 38030.839 | M13: 40314.554 | N13: 43491.069 | O13: 42575.477 | P13: 44180.31
A14: 4001190260 | B14: 유동생물자산(*) | C14: 억원
A15: 4001190270 | B15: 유동금융자산(*) | C15: 억원 | D15: 2545.0981 | E15: 2439.2426 | F15: 2606.184 | G15: 2561.2984 | H15: 4071.0909 | I15: 1816.6798 | J15: 2254.8183 | K15: 3681.6373 | L15: 2422.1048 | M15: 2448.0469 | N15: 2796.4289 | O15: 3737.3693 | P15: 5134.17
A16: 4001190300 | B16: 매출채권및기타유동채권(*) | C16: 억원 | D16: 19448.575 | E16: 19509.982 | F16: 19708.857 | G16: 22798.068 | H16: 17206.8 | I16: 19135.375 | J16: 19995.364 | K16: 31876.68 | L16: 23667.346 | M16: 24655.045 | N16: 19137.432 | O16: 29675.511 | P16: 25446.77
A17: 4001113900 | B17: 당기법인세자산(선급법인세) | C17: 억원 | D17: 33.980405 | E17: 158.28791 | F17: 282.48835 | G17: 179.46308 | H17: 175.48916 | I17: 335.87122 | J17: 675.8224 | K17: 415.72736 | L17: 381.62434 | M17: 260.31286 | N17: 339.82812 | O17: 553.13091 | P17: 555.49
A18: 4001180995 | B18: 계약자산(**) | C18: 억원 | D18: 257.96039 | E18: 280.88354 | F18: 567.76372 | G18: 626.43122 | H18: 615.44633 | I18: 854.90409 | J18: 1274.4749 | K18: 3759.2226 | L18: 3808.8158 | M18: 3682.8717 | N18: 3583.0599 | O18: 3806.8755 | P18: 4440.84
A19: 4001113903 | B19: 반품(환불)자산 | C19: 억원 | D19: 0.60008 | E19: 0.61506 | F19: 0.49704 | G19: 0.72445
A20: 4001113904 | B20: 배출권 | C20: 억원 | D20: 40.46519 | E20: 24.3167 | F20: 35.07157 | G20: 29.94038 | H20: 43.19087 | I20: 25.41965 | J20: 21.3355 | K20: 17.32413 | L20: 17.32413 | M20: 13.88628 | N20: 10.79468 | O20: 11.43374 | P20: 11.43
A21: 4001190340 | B21: 기타유동자산(*) | C21: 억원 | D21: 3420.4794 | E21: 3764.2677 | F21: 3809.4843 | G21: 3079.6143 | H21: 3113.6416 | I21: 3813.6613 | J21: 5061.1176 | K21: 4167.7697 | L21: 4313.4763 | M21: 5407.5839 | N21: 3922.3525 | O21: 5650.0176 | P21: 6196.02
A22: 4001190370 | B22: 현금및현금성자산(*) | C22: 억원 | D22: 14948.167 | E22: 18435.788 | F22: 22253.326 | G22: 25483.797 | H22: 20064.588 | I22: 23708.488 | J22: 28769.128 | K22: 19580.547 | L22: 28342.313 | M22: 18793.942 | N22: 20319.332 | O22: 21843.806 | P22: 19350.85
A23: 4001114130 | B23: 매각예정비유동자산및처분자산집단(*) | C23: 억원 | D23: 73.7775 | G23: 372.54007 | H23: 2.1761658 | N23: 445.91833 | O23: 973.02938 | P23: 456.51
A24: 4001190020 | B24: 비유동자산(*) | C24: 억원 | D24: 131782.74 | E24: 134301.82 | F24: 139446.55 | G24: 136343.75 | H24: 127761.75 | I24: 132503.03 | J24: 141771.11 | K24: 149930.52 | L24: 147215.9 | M24: 172347.37 | N24: 177469.83 | O24: 191541.66 | P24: 199042.45
A25: 4001190030 | B25: 유형자산(*) | C25: 억원 | D25: 67091.978 | E25: 68155.502 | F25: 69386.193 | G25: 68794.515 | H25: 60758.755 | I25: 63817.771 | J25: 69659.5 | K25: 70497.835 | L25: 75607.799 | M25: 93123.824 | N25: 98090.678 | O25: 107269.64 | P25: 111827.15
A26: 4001190070 | B26: 무형자산(*) | C26: 억원 | D26: 15738.573 | E26: 15716.151 | F26: 16684.94 | G26: 16444.376 | H26: 17418.074 | I26: 17197.193 | J26: 17405.411 | K26: 17725.761 | L26: 18143.111 | M26: 17641.347 | N26: 17786.498 | O26: 17557.426 | P26: 18089.58
A27: 4001190110 | B27: 비유동생물자산(*) | C27: 억원
A28: 4001190120 | B28: 투자부동산(*) | C28: 억원 | D28: 2126.0419 | E28: 2098.9892 | F28: 2087.0015 | G28: 1997.6283 | H28: 1857.6482 | I28: 1887.0453 | J28: 1888.6471 | K28: 1916.6698 | L28: 1049.6517 | M28: 1932.0539 | N28: 1931.7484 | O28: 1965.6832 | P28: 1962.72
A29: 4001190130 | B29: 장기금융자산(*) | C29: 억원 | D29: 3262.0602 | E29: 3411.1252 | F29: 4121.4419 | G29: 4520.2169 | H29: 4358.5599 | I29: 4102.0293 | J29: 4037.2981 | K29: 4935.4425 | L29: 3055.6185 | M29: 3197.4428 | N29: 2703.6909 | O29: 5034.9009 | P29: 5946.03
A30: 4001111660 | B30: 관계기업등지분관련투자자산(*) | C30: 억원 | D30: 37554.509 | E30: 38804.035 | F30: 40651.044 | G30: 37446.276 | H30: 37719.567 | I30: 38827.801 | J30: 41380.26 | K30: 41597.179 | L30: 40901.78 | M30: 47289.261 | N30: 47952.519 | O30: 49304.474 | P30: 50818.44
A31: 4001190160 | B31: 장기매출채권및기타비유동채권(*) | C31: 억원 | D31: 53.922841 | E31: 56.525377 | F31: 40.843838 | G31: 62.156102 | H31: 1155.4052 | I31: 1413.1941 | J31: 2733.4154 | K31: 6885.4541 | L31: 962.72926 | M31: 937.87316 | N31: 964.84258 | O31: 1460.1683 | P31: 1338.11
A32: 4001112490 | B32: 이연법인세자산 | C32: 억원 | D32: 1419.7466 | E32: 1321.794 | F32: 1583.7561 | G32: 2012.9173 | H32: 1487.294 | I32: 1372.9939 | J32: 1207.9019 | K32: 1842.9539 | L32: 2688.7375 | M32: 2416.6081 | N32: 2084.2146 | O32: 2893.6629 | P32: 3459.99
A33: 4001112500 | B33: 장기당기법인세자산 | C33: 억원
A34: 4001180575 | B34: 계약자산(**) | C34: 억원
A35: 4001112503 | B35: 반품(환불)자산 | C35: 억원
A36: 4001112504 | B36: 배출권 | C36: 억원
A37: 4001190200 | B37: 기타비유동자산(*) | C37: 억원 | D37: 4535.9101 | E37: 4737.6944 | F37: 4891.3301 | G37: 5065.6619 | H37: 3006.4449 | I37: 3885.0067 | J37: 3458.673 | K37: 4529.2214 | L37: 4806.4701 | M37: 5808.9585 | N37: 5955.6333 | O37: 6055.713 | P37: 5600.43
A38: 4001112880 | B38: 기타금융업자산 | C38: 억원 | D38: 14797.735 | E38: 16213.206 | F38: 15421.685 | G38: 16242.142 | H38: 16169.773 | I38: 17671.71 | J38: 16733.53 | L38: 20822.061 | M38: 23593.68 | N38: 22575.592
A39: 4001190440 | B39: 부채(*) | C39: 억원 | D39: 128015.05 | E39: 133642.57 | F39: 142439.98 | G39: 139349.73 | H39: 127692.87 | I39: 138106.13 | J39: 154278.81 | K39: 155101.87 | L39: 182830.58 | M39: 193381.61 | N39: 193738.66 | O39: 194299.75 | P39: 200421.89
A40: 4001190610 | B40: 유동부채(*) | C40: 억원 | D40: 61959.342 | E40: 65002.733 | F40: 73337.628 | G40: 68084.914 | H40: 59171.122 | I40: 59986.554 | J40: 67541.363 | K40: 87341.103 | L40: 96241.104 | M40: 101470.35 | N40: 103913.95 | O40: 117075.52 | P40: 121396.94
A41: 4001181470 | B41: 단기사채(**) | C41: 억원
A42: 4001121700 | B42: 단기차입금(*) | C42: 억원 | D42: 22995.043 | F42: 29650.627 | G42: 24430.177 | H42: 21500.439 | I42: 25222.4 | J42: 31257.32 | K42: 29470.517 | L42: 42009.109 | M42: 47414.687 | N42: 53601.702 | O42: 51098.996 | P42: 63349.76
A43: 4001190620 | B43: 유동성장기부채(*) | C43: 억원 | D43: 7095.9516 | E43: 30509.837 | F43: 7948.6322 | G43: 5597.9287 | H43: 5694.6937 | I43: 4905.4457 | J43: 5368.1805 | K43: 8411.4676 | L43: 13285.054 | M43: 13639.773 | N43: 12960.455 | O43: 11891.669 | P43: 8746.64
A44: 4001190630 | B44: 유동금융부채(*) | C44: 억원 | D44: 2157.1948 | E44: 2256.9874 | F44: 2208.2598 | G44: 1960.5967 | H44: 1789.0157 | I44: 1686.2972 | J44: 1993.336 | K44: 1786.9207 | L44: 1206.8602 | M44: 1201.9382 | N44: 1178.731 | O44: 1261.8316 | P44: 1204.8
A45: 4001190660 | B45: 매입채무및기타유동채무(*) | C45: 억원 | D45: 25314.953 | E45: 25945.255 | F45: 25372.382 | G45: 27805.79 | H45: 23027.274 | I45: 22397.6 | J45: 20694.181 | K45: 39749.173 | L45: 32103.443 | M45: 29855.047 | N45: 27722.559 | O45: 40231.556 | P45: 36322.01
A46: 4001190680 | B46: 유동종업원급여충당부채(*) | C46: 억원
A47: 4001122460 | B47: 기타단기충당부채(*) | C47: 억원 | D47: 542.06338 | E47: 504.69922 | F47: 544.75031 | G47: 478.34554 | H47: 510.2643 | I47: 469.52064 | J47: 441.77248 | K47: 430.3094 | L47: 445.28343 | M47: 431.76667 | N47: 431.85103 | O47: 693.68458 | P47: 686.73
A48: 4001122560 | B48: 당기법인세부채(미지급법인세) | C48: 억원 | D48: 692.71298 | E48: 2154.4294 | F48: 2778.4541 | G48: 3856.3243 | H48: 2127.8039 | I48: 370.25456 | J48: 378.84414 | K48: 430.46784 | L48: 363.87975 | M48: 338.40052 | N48: 172.49797 | O48: 360.76762 | P48: 320.75
A49: 4001122561 | B49: 계약부채 | C49: 억원 | D49: 3010.1785 | E49: 3534.7119 | F49: 4655.8209 | G49: 3179.1231 | H49: 3681.8296 | I49: 4292.6988 | J49: 6702.0062 | K49: 5259.1314 | L49: 6248.9151 | M49: 7806.1077 | N49: 7097.4111 | O49: 7128.8845 | P49: 7591.94
A50: 4001122562 | B50: 반품(환불)부채 | C50: 억원 | D50: 12.9947 | E50: 12.65898 | F50: 13.51149 | G50: 13.52275
A51: 4001122563 | B51: 배출부채 | C51: 억원
A52: 4001190690 | B52: 기타유동부채(*) | C52: 억원 | D52: 138.24967 | E52: 84.15453 | F52: 165.18992 | G52: 763.10609 | H52: 839.80172 | I52: 642.33657 | J52: 705.72305 | K52: 1803.1164 | L52: 578.55917 | M52: 782.63241 | N52: 748.73961 | O52: 4180.9774 | P52: 3174.31
A53: 4001122680 | B53: 매각예정으로분류된처분자산집단에포함된부채(*) | C53: 억원 | O53: 227.15651
A54: 4001190450 | B54: 비유동부채(*) | C54: 억원 | D54: 52995.373 | E54: 54185.56 | F54: 55478.561 | G54: 56854.321 | H54: 54166.624 | I54: 62337.317 | J54: 71930.821 | K54: 67760.766 | L54: 69800.933 | M54: 72362.098 | N54: 71888.611 | O54: 77224.229 | P54: 79024.95
A55: 4001190460 | B55: 사채(*) | C55: 억원 | D55: 19602.098 | E55: 18193.934 | F55: 18849.522 | G55: 20473.074 | H55: 21112.949 | I55: 23151.585 | J55: 28683.258 | K55: 23874.659 | L55: 21602.66 | M55: 19143.037 | N55: 21885.882 | O55: 21914.192 | P55: 21658.33
A56: 4001190470 | B56: 장기차입금(*) | C56: 억원 | D56: 17113.473 | E56: 18494.145 | F56: 20036.853 | G56: 21580.552 | H56: 22313.195 | I56: 28795.016 | J56: 33037.719 | K56: 31786.231 | L56: 37578.58 | M56: 39391.353 | N56: 36030.779 | O56: 42314.499 | P56: 44137.1
A57: 4001190480 | B57: 비유동금융부채(*) | C57: 억원 | D57: 4783.0013 | E57: 4573.7379 | F57: 4719.7988 | G57: 5806.7797 | H57: 2534.5403 | I57: 2502.8493 | J57: 2325.425 | K57: 2406.602 | L57: 2659.2124 | M57: 3604.1006 | N57: 3874.3342 | O57: 4106.0832 | P57: 4263.18
A58: 4001190500 | B58: 장기매입채무및기타비유동채무(*) | C58: 억원 | D58: 2033.2854 | E58: 2122.493 | F58: 797.48723 | G58: 929.3652 | H58: 1083.9419 | I58: 1018.7332 | J58: 880.25136 | K58: 2751.6272 | L58: 1059.7661 | M58: 1137.251 | N58: 1111.8411 | O58: 944.22468 | P58: 941.47
A59: 4001190570 | B59: 비유동종업원급여충당부채(*) | C59: 억원 | D59: 4987.3952 | E59: 5140.7457 | F59: 5233.6222 | G59: 4268.1571 | H59: 3786.2897 | I59: 3801.0006 | J59: 3909.7916 | K59: 3866.4055 | L59: 3975.1791 | M59: 4041.9224 | N59: 4133.7722 | O59: 3860.3994 | P59: 3894.51
A60: 4001121280 | B60: 기타장기충당부채(*) | C60: 억원 | D60: 1182.5081 | E60: 1221.2044 | F60: 1302.8863 | G60: 1275.0871 | H60: 1288.5116 | I60: 1312.9482 | J60: 1316.7439 | K60: 1339.1039 | L60: 1380.4778 | M60: 1411.1685 | N60: 1421.9505 | O60: 1564.0289 | P60: 1587.22
A61: 4001121380 | B61: 이연법인세부채 | C61: 억원 | D61: 3224.2595 | E61: 4367.9892 | F61: 4465.6609 | G61: 2297.1822 | H61: 1974.3681 | I61: 1660.4402 | J61: 1684.6787 | K61: 1698.6856 | L61: 1487.4276 | M61: 3484.5996 | N61: 3267.2385 | O61: 2320.4565 | P61: 2334.72
A62: 4001181370 | B62: 장기당기법인세부채(미지급법인세)(**) | C62: 억원
A63: 4001121401 | B63: 계약부채 | C63: 억원 | E63: 11.53782 | F63: 9.52566 | G63: 186.21457 | H63: 34.60331 | I63: 66.68991 | J63: 65.51498 | K63: 8.23683 | L63: 7.11092 | M63: 100.30324 | N63: 118.92315 | O63: 118.7935 | P63: 129.18
A64: 4001121402 | B64: 반품(환불)부채 | C64: 억원 | O64: 1.30811 | P64: 1.94
A65: 4001121403 | B65: 배출부채 | C65: 억원
A66: 4001190580 | B66: 기타비유동부채(*) | C66: 억원 | D66: 69.352574 | E66: 59.77326 | F66: 63.20493 | G66: 37.9089 | H66: 38.22495 | I66: 28.05462 | J66: 27.43835 | K66: 29.21581 | L66: 50.51899 | M66: 48.36313 | N66: 43.88978 | O66: 80.243 | P66: 77.3
A67: 4001121620 | B67: 기타금융업부채 | C67: 억원 | D67: 13060.335 | E67: 14454.278 | F67: 13623.794 | G67: 14410.494 | H67: 14355.128 | I67: 15782.261 | J67: 14806.625 | L67: 16788.542 | M67: 19549.153 | N67: 17936.104
A68: 4001190380 | B68: 자본(*) | C68: 억원 | D68: 83489.615 | E68: 91201.493 | F68: 96437.602 | G68: 98969.116 | H68: 93601.201 | I68: 94205.209 | J68: 95385.317 | K68: 92802.367 | L68: 86191.224 | M68: 98135.685 | N68: 100352.97 | O68: 106068.56 | P68: 104392.95
A69: 4001130010 | B69: *수권주식수 | C69: 주 | D69: 300000000 | E69: 300000000 | F69: 300000000 | G69: 300000000 | H69: 300000000 | I69: 300000000 | J69: 300000000 | K69: 300000000 | L69: 300000000 | M69: 300000000 | N69: 300000000 | O69: 300000000 | P69: 300000000
A70: 4001130020 | B70: *주당액면가액 | C70: 원 | D70: 5000 | E70: 5000 | F70: 5000 | G70: 5000 | H70: 5000 | I70: 5000 | J70: 5000 | K70: 5000 | L70: 5000 | M70: 5000 | N70: 5000 | O70: 5000 | P70: 5000
A71: 4001130030 | B71: *발행한주식총수(*) | C71: 주 | D71: 192402234 | E71: 192402234 | F71: 192402234 | G71: 192402234 | H71: 174467885 | I71: 174467885 | J71: 174467885 | K71: 174467885 | L71: 174467885 | M71: 174467885 | N71: 174467885 | O71: 174467885 | P71: 174467885
A72: 4001130040 | B72: *보통주 | C72: 주 | D72: 191278497 | E72: 191278497 | F72: 191278497 | G72: 191278497 | H72: 171892536 | I72: 171892536 | J72: 171892536 | K72: 171892536 | L72: 171892536 | M72: 171892536 | N72: 171892536 | O72: 171892536 | P72: 171892536
A73: 4001130050 | B73: *우선주 | C73: 주 | D73: 1123737 | E73: 1123737 | F73: 1123737 | G73: 1123737 | H73: 2575349 | I73: 2575349 | J73: 2575349 | K73: 2575349 | L73: 2575349 | M73: 2575349 | N73: 2575349 | O73: 2575349 | P73: 2575349
A74: 4001190390 | B74: 지배기업주주지분(*) | C74: 억원 | D74: 82817.532 | E74: 88169.653 | F74: 93169.87 | G74: 89205.71 | H74: 84075.978 | I74: 83435.93 | J74: 84409.011 | K74: 81171.666 | L74: 74823.555 | M74: 86562.963 | N74: 88709.992 | O74: 94496.501 | P74: 92856.76
A75: 4001130070 | B75: 자본금(*) | C75: 억원 | D75: 9782.4065 | E75: 9782.4065 | F75: 9782.4065 | G75: 9782.4065 | H75: 8885.6891 | I75: 8885.6891 | J75: 8885.6891 | K75: 8885.6891 | L75: 8885.6891 | M75: 8885.6891 | N75: 8885.6891 | O75: 8885.6891 | P75: 8885.69
A76: 4001130670 | B76: 신종자본증권 | C76: 억원 | N76: 6967.9414 | O76: 6967.9414 | P76: 6967.94
A77: 4001190400 | B77: 자본잉여금(*) | C77: 억원 | D77: 19552.107 | E77: 21771.948 | F77: 21480.397 | G77: 23200.511 | H77: 15539.675 | I77: 15492.956 | J77: 15535.458 | K77: 14962.94 | L77: 14813.165 | M77: 15437.454 | N77: 15397.047 | O77: 15624.21 | P77: 15658.82
A78: 4001190420 | B78: 기타자본(*) | C78: 억원 | D78: -885.25238 | E78: -842.21416 | F78: -842.3113 | G78: -1541.5394 | H78: -1301.1043 | I78: -1398.5503 | J78: -1441.0997 | K78: -1350.8221 | L78: -1346.3776 | M78: -1355.593 | N78: -1478.3255 | O78: -1503.7151 | P78: -1502.42
A79: 4001130360 | B79: 기타포괄손익누계액(*) | C79: 억원 | D79: 2408.2989 | E79: 2853.4948 | F79: 6359.1851 | G79: 2150.277 | H79: 4001.4465 | I79: 3440.4005 | J79: 4308.7034 | K79: 2579.5864 | L79: 4186.1737 | M79: 16822.913 | N79: 15615.289 | O79: 23198.023 | P79: 22755.94
A80: 4001130470 | B80: 이익잉여금(결손금)(*) | C80: 억원 | D80: 51959.972 | E80: 54604.018 | F80: 56390.193 | G80: 55614.054 | H80: 56950.271 | I80: 57015.435 | J80: 57120.26 | K80: 56094.273 | L80: 48284.904 | M80: 46772.499 | N80: 43322.351 | O80: 41324.353 | P80: 40090.79
A81: 4001130640 | B81: 비지배주주지분 | C81: 억원 | D81: 672.08348 | E81: 3031.8391 | F81: 3267.7325 | G81: 9763.4057 | H81: 9525.2226 | I81: 10769.279 | J81: 10976.307 | K81: 11630.702 | L81: 11367.669 | M81: 11572.722 | N81: 11642.98 | O81: 11572.06 | P81: 11536.19

Sheet IS(Q)
B1: Last Refresh: 2025-05-24 13:23:10
A2: Financial Statements
A3: 기업 | B3: A009830(한화솔루션) - Fiscal Month:12, 201103부터 IFRS 적용
A4: 회계유형 | B4: 연결 | C4: 회계기준 | D4: IFRS
A5: 리포트 | B5: 손익계산서 | C5: New
A6: 형식 | B6: 약식(COMPARE)
A7: 출력 | B7: 당분기 | C7: 억원
A8: 회계연도 | B8: 2022 | C8: Current
A9: 계정코드 | B9: 계정명 | C9: 단위 | D9: 202203(1Q) | E9: 202206(2Q) | F9: 202209(3Q) | G9: 202212(4Q) | H9: 202303(1Q) | I9: 202306(2Q) | J9: 202309(3Q) | K9: 202312(4Q) | L9: 202403(1Q) | M9: 202406(2Q) | N9: 202409(3Q) | O9: 202412(4Q) | P9: 202503(1Q)
D10: IFRS(연결) | E10: IFRS(연결) | F10: IFRS(연결) | G10: IFRS(연결) | H10: IFRS(연결) | I10: IFRS(연결) | J10: IFRS(연결) | K10: IFRS(연결) | L10: IFRS(연결) | M10: IFRS(연결) | N10: IFRS(연결) | O10: IFRS(연결) | P10: IFRS(연결)
A11: 4001210000 | B11: 매출액(수익)(*) | C11: 억원 | D11: 28487.974 | E11: 32590.363 | F11: 32397.933 | G11: 37831.26 | H11: 31001.576 | I11: 33641.789 | J11: 29044.312 | K11: 37097.684 | L11: 23533.87 | M11: 26793.095 | N11: 27732.493 | O11: 45880.778 | P11: 30944.76
A12: 4001210010 | B12: *수출(*) | C12: 억원
A13: 4001210020 | B13: *내수 | C13: 억원
A14: 4001210320 | B14: 매출원가(*) | C14: 억원 | D14: 23568.531 | E14: 26085.297 | F14: 25582.171 | G14: 32081.534 | H14: 24243.207 | I14: 27992.396 | J14: 24613.801 | K14: 32283.004 | L14: 21785.36 | M14: 23331.762 | N14: 24665.169 | O14: 40299.392 | P14: 26442.63
A15: 4001210780 | B15: 매출총이익(손실) | C15: 억원 | D15: 4919.4431 | E15: 6505.0658 | F15: 6815.762 | G15: 5749.7253 | H15: 6758.3694 | I15: 5649.3932 | J15: 4430.5108 | K15: 4814.6801 | L15: 1748.51 | M15: 3461.3331 | N15: 3067.3239 | O15: 5581.3862 | P15: 4502.13
A16: 4001290000 | B16: 판매비와관리비(*) | C16: 억원 | D16: 3452.7485 | E16: 3782.0713 | F16: 3447.4525 | G16: 4070.4573 | H16: 4043.973 | I16: 3827.2609 | J16: 3537.7592 | K16: 4451.5902 | L16: 3894.85 | M16: 4538.9027 | N16: 3877.2348 | O16: 4549.9453 | P16: 4198.99
A17: 4001290010 | B17: 인건비(*) | C17: 억원 | D17: 1079.1049 | E17: 1252.5885 | F17: 1459.5166 | G17: 1373.9994 | H17: 1574.1082 | I17: 1381.1501 | J17: 1288.324 | K17: 1841.2576 | L17: 1691.67 | M17: 1852.1235 | N17: 1551.4639 | O17: 1857.1656 | P17: 1627.15
A18: 4001290020 | B18: 유무형자산상각비(*) | C18: 억원 | D18: 191.20544 | E18: 221.75762 | F18: 259.18444 | G18: 228.97272 | H18: 268.26335 | I18: 249.09523 | J18: 276.78602 | K18: 312.2043 | L18: 334.38 | M18: 353.38595 | N18: 308.25088 | O18: 348.23869 | P18: 330.41
A19: 4001211300 | B19: 연구개발비 | C19: 억원 | D19: 435.95114 | E19: 175.91529 | F19: 364.27731 | G19: 435.05942 | H19: 415.9708 | I19: 309.0081 | J19: 338.93937 | K19: 207.48853 | L19: 243.58 | M19: 220.61852 | N19: 182.19893 | O19: 269.9386 | P19: 229.79
A20: 4001211060 | B20: 광고선전비 | C20: 억원 | D20: 37.88362 | E20: 64.87314 | F20: 50.29258 | G20: 92.90651 | H20: 116.71128 | I20: 84.97209 | J20: -34.34496 | K20: 120.6677 | L20: 46.51 | M20: 71.20174 | N20: 61.49535 | O20: 64.21939 | P20: 36.41
A21: 4001290040 | B21: 판매비(*) | C21: 억원 | D21: 1139.2879 | E21: 1124.5722 | F21: 607.52016 | G21: 893.28615 | H21: 961.74411 | I21: 965.5096 | J21: 908.81597 | K21: 1025.7562 | L21: 784.66 | M21: 995.81879 | N21: 899.23558 | O21: 1006.0728 | P21: 942.47
A22: 4001290090 | B22: 관리비(*) | C22: 억원 | D22: 577.97505 | E22: 919.38369 | F22: 706.90212 | G22: 892.88685 | H22: 673.94472 | I22: 806.49048 | J22: 767.2255 | K22: 896.22734 | L22: 774.02 | M22: 1006.3863 | N22: 836.62704 | O22: 965.92024 | P22: 927.83
A23: 4001290110 | B23: 기타원가성비용(*) | C23: 억원
A24: 4001211420 | B24: 기타 | C24: 억원 | D24: -8.65953 | E24: 22.98088 | F24: -0.24071 | G24: 153.34627 | H24: 33.23051 | I24: 31.03527 | J24: -7.98673 | K24: 47.98848 | L24: 20.03 | M24: 39.36788 | N24: 37.96313 | O24: 38.39002 | P24: 104.93
A25: 4001211430 | B25: 영업이익(손실) | C25: 억원 | D25: 1466.6946 | E25: 2722.9945 | F25: 3368.3095 | G25: 1679.268 | H25: 2714.3964 | I25: 1822.1323 | J25: 892.75163 | K25: 363.08993 | L25: -2146.34 | M25: -1077.5696 | N25: -809.91092 | O25: 1031.4409 | P25: 303.14
A26: 4001290120 | B26: 금융수익(*) | C26: 억원 | D26: 39.79615 | E26: 52.88484 | F26: 52.47492 | G26: 153.29072 | H26: 181.2969 | I26: 195.85965 | J26: 249.21926 | K26: 294.12108 | L26: 250.76 | M26: 349.90223 | N26: 229.85152 | O26: 252.29388 | P26: 296.28
A27: 4001290750 | B27: 이자수익 | C27: 억원 | D27: 34.99848 | E27: 45.85004 | F27: 52.06968 | G27: 152.90602 | H27: 173.42719 | I27: 189.19872 | J27: 249.21926 | K27: 271.58068 | L27: 248.11 | M27: 325.88976 | N27: 229.0193 | O27: 230.80198 | P27: 284.41
A28: 4001290760 | B28: 배당금수익 | C28: 억원 | D28: 4.79767 | E28: 0.05047 | H28: 3.54921 | I28: 6.27246 | K28: 13.18874 | M28: 25.89291 | N28: -0.00146 | O28: 8.12954 | P28: 11.87
A29: 4001211480 | B29: 외환이익(*) | C29: 억원
A30: 4001211520 | B30: 대손충당금환입액 | C30: 억원
A31: 4001211600 | B31: 매출채권처분이익 | C31: 억원
A32: 4001211605 | B32: 당기손익-공정가치측정 금융자산관련이익 | C32: 억원
A33: 4001290130 | B33: 금융자산처분이익(*) | C33: 억원
A34: 4001290150 | B34: 금융자산평가이익(*) | C34: 억원
A35: 4001211720 | B35: 금융자산손상차손환입(*) | C35: 억원
A36: 4001211680 | B36: 파생상품이익(*) | C36: 억원
A37: 4001290170 | B37: 기타금융수익(*) | C37: 억원 | E37: 6.98433 | F37: 0.40524 | G37: 0.3847 | H37: 4.3205 | I37: 0.38847 | K37: 9.35166 | L37: 2.65 | M37: -1.88044 | N37: 0.83368 | O37: 13.36236
A38: 4001290180 | B38: 금융원가(*) | C38: 억원 | D38: 358.38115 | E38: 416.5918 | F38: 530.21922 | G38: 704.22819 | H38: 821.35869 | I38: 897.65393 | J38: 1113.4604 | K38: 1281.6701 | L38: 1378.63 | M38: 1642.0242 | N38: 1558.5295 | O38: 905.01842 | P38: 1367.2
A39: 4001290770 | B39: 이자비용 | C39: 억원 | D39: 351.99241 | E39: 416.5918 | F39: 530.21922 | G39: 710.61693 | H39: 821.35869 | I39: 897.65393 | J39: 1113.4604 | K39: 1281.6701 | L39: 1378.63 | M39: 1642.0242 | N39: 1558.5295 | O39: 905.01842 | P39: 1367.2
A40: 4001211820 | B40: 외환손실(*) | C40: 억원
A41: 4001211860 | B41: 대손상각비 | C41: 억원
A42: 4001211865 | B42: 당기손익-공정가치측정 금융자산관련손실 | C42: 억원
A43: 4001211940 | B43: 매출채권처분손실 | C43: 억원
A44: 4001290190 | B44: 금융자산처분손실(*) | C44: 억원
A45: 4001290210 | B45: 금융자산평가손실(*) | C45: 억원
A46: 4001212060 | B46: 금융자산손상차손(*) | C46: 억원
A47: 4001212020 | B47: 파생상품손실(*) | C47: 억원
A48: 4001290230 | B48: 기타금융원가(*) | C48: 억원 | D48: 6.38874 | G48: -6.38874
A49: 4001290240 | B49: 기타수익(*) | C49: 억원 | D49: 1126.68 | E49: 2829.0745 | F49: 3855.6649 | G49: 1306.0252 | H49: 2780.295 | I49: 1329.4335 | J49: 1163.769 | K49: 369.56342 | L49: 1663.49 | M49: 1489.6979 | N49: 525.17001 | O49: 3264.2659 | P49: 1116.96
A50: 4001280000 | B50: 이자수익 | C50: 억원
A51: 4001280010 | B51: 배당금수익 | C51: 억원
A52: 4001290250 | B52: 외환이익(*) | C52: 억원 | D52: 671.17636 | E52: 1697.9131 | F52: 3097.1278 | G52: 729.95087 | H52: 1661.6767 | I52: 1125.6542 | J52: 715.37821 | K52: 183.4315 | L52: 1008.8 | M52: 970.71591 | N52: 386.85494 | O52: 1135.7238 | P52: 669.18
A53: 4001280050 | B53: 재고자산감모손실환입 | C53: 억원
A54: 4001280060 | B54: 재고자산폐기(처분)이익 | C54: 억원
A55: 4001280065 | B55: 당기손익-공정가치측정 금융자산평가이익 | C55: 억원 | D55: 0.66495 | E55: 6.41786 | F55: 8.3671 | G55: 0.23541 | H55: 14.49265 | I55: 43.29028 | J55: -31.22932 | K55: -20.95358 | L55: 1.8 | M55: -1.80081 | N55: 0.80633 | O55: -0.80552 | P55: 24.57
A56: 4001290260 | B56: 자산처분(폐기)이익(*) | C56: 억원 | D56: 22.56876 | E56: 75.97548 | F56: 29.6393 | G56: 12.18141 | H56: 360.24701 | I56: -42.76264 | J56: 15.06212 | K56: -247.45982 | L56: 10.71 | M56: 2.13952 | N56: 4.90526 | O56: 17.17896 | P56: 66.71
A57: 4001280140 | B57: 자산평가이익 | C57: 억원 | P57: 0.67
A58: 4001290280 | B58: 자산손상차손환입(*) | C58: 억원 | H58: 5.11053 | I58: -0.00054 | J58: -0.04236 | K58: -0.03177 | L58: 4.71 | M58: 0.06991 | N58: 0.10592 | O58: 0.10841
A59: 4001290300 | B59: 파생상품이익(*) | C59: 억원 | D59: 361.62372 | E59: 545.85295 | F59: 890.49983 | G59: 367.73428 | H59: 650.34596 | I59: 142.44624 | J59: 311.42584 | K59: -123.95456 | L59: 492.3 | M59: 423.35997 | N59: -147.15263 | O59: 1596.5724 | P59: 244.54
A60: 4001280240 | B60: 임대료수익 | C60: 억원 | D60: 0.711 | E60: 0.7296 | F60: 1.00169 | G60: 3.35488 | H60: 0.94992 | I60: 1.03282 | J60: 0.93058 | K60: 1.72791 | L60: 1.03 | M60: 1.02516 | N60: 1.04335 | O60: 0.9236 | P60: 1.15
A61: 4001280250 | B61: 로열티수익 | C61: 억원
A62: 4001280260 | B62: 수수료수익 | C62: 억원
A63: 4001280270 | B63: 대손충당금환입 | C63: 억원 | E63: 0.59323 | F63: -0.00581 | G63: -0.37895 | H63: 4.86281 | I63: 0.11917 | J63: 9.53133 | K63: 5.0246 | L63: 0.98 | M63: 1.72409 | N63: 1.38462 | O63: -0.13222 | P63: 0.29
A64: 4001280280 | B64: 충당부채환입액 | C64: 억원 | D64: 0.0027 | G64: -0.0027
A65: 4001290310 | B65: 기타(*) | C65: 억원 | D65: 69.93252 | E65: 501.59228 | F65: -170.96495 | G65: 192.95005 | H65: 82.60945 | I65: 59.65398 | J65: 142.71258 | K65: 571.77914 | L65: 143.16 | M65: 92.46417 | N65: 277.22222 | O65: 514.69649 | P65: 109.85
A66: 4001290320 | B66: 기타비용(*) | C66: 억원 | D66: 1005.8682 | E66: 2396.3274 | F66: 3867.7651 | G66: 2860.2592 | H66: 3092.0654 | I66: 1335.3659 | J66: 1205.3616 | K66: 2122.8354 | L66: 1671.33 | M66: 1734.7319 | N66: 1077.5811 | O66: 6025.4283 | P66: 2376.06
A67: 4001280400 | B67: 이자비용 | C67: 억원
A68: 4001290330 | B68: 외환손실(*) | C68: 억원 | D68: 907.02805 | E68: 2002.1897 | F68: 3329.3424 | G68: 483.17922 | H68: 1786.3639 | I68: 840.90951 | J68: 789.11802 | K68: 141.91493 | L68: 1216.87 | M68: 1193.4827 | N68: 441.62246 | O68: 1410.8752 | P68: 756.12
A69: 4001280440 | B69: 재고자산감모손실 | C69: 억원
A70: 4001280450 | B70: 재고자산폐기(처분)손실 | C70: 억원 | D70: 4.35825 | E70: 0.10101 | G70: 0.34444 | H70: 0.3509 | I70: 0.03425 | J70: 1.17494 | K70: 3.39667 | L70: 21.52 | M70: 0.10217 | N70: -0.20126 | O70: 49.71259
A71: 4001280455 | B71: 당기손익-공정가치측정 금융자산평가손실 | C71: 억원 | D71: 2.81124 | E71: 13.82339 | F71: -1.27739 | G71: 15.87944 | H71: 67.95914 | I71: 23.71139 | J71: 55.18766 | K71: -41.77782 | L71: 98.26 | M71: -6.25016 | N71: 101.65297 | O71: 536.77076 | P71: 921.47
A72: 4001290340 | B72: 자산처분(폐기)손실(*) | C72: 억원 | D72: 11.906 | E72: 23.93574 | F72: 18.30961 | G72: 260.86148 | H72: 19.507 | I72: 36.06827 | J72: 21.76641 | K72: 29.91139 | L72: 16 | M72: 191.11708 | N72: 174.63538 | O72: 186.90384 | P72: 37.56
A73: 4001280540 | B73: 자산평가손실 | C73: 억원 | P73: 4.28
A74: 4001290360 | B74: 자산손상차손(*) | C74: 억원 | E74: 117.38668 | F74: 60.72282 | G74: 449.13794 | I74: 2.81084 | J74: -2.81084 | K74: 1521.7556 | L74: 11.51 | M74: 0.13687 | N74: 0.06071 | O74: 1143.7039
A75: 4001290380 | B75: 파생상품손실(*) | C75: 억원 | D75: 30.80615 | E75: 122.51314 | F75: 267.63708 | G75: 1150.1943 | H75: 388.32167 | I75: 239.89874 | J75: 193.88199 | K75: 271.44469 | L75: 209.08 | M75: 138.34673 | N75: 202.4406 | O75: 469.589 | P75: 280.01
A76: 4001280650 | B76: 기타대손상각비 | C76: 억원 | E76: 0.5119 | F76: 0.38521 | G76: 12.48127 | H76: 1.55131 | I76: 0.13156 | J76: 0.36606 | K76: 4.35033 | M76: -0.00191 | O76: 13.35753 | P76: 6.55
A77: 4001280660 | B77: 충당부채전입액 | C77: 억원
A78: 4001290390 | B78: 기타(*) | C78: 억원 | D78: 48.95847 | E78: 115.86587 | F78: 192.64538 | G78: 488.18107 | H78: 828.01149 | I78: 191.80138 | J78: 146.67732 | K78: 191.83961 | L78: 98.09 | M78: 217.79833 | N78: 157.3702 | O78: 2214.5154 | P78: 370.07
A79: 4001290640 | B79: 종속기업,공동지배기업및관계기업관련손익(*) | C79: 억원 | D79: -63.347989 | E79: 552.49432 | F79: -707.23937 | G79: -800.65118 | H79: 249.52777 | I79: -734.3521 | J79: 305.9438 | K79: 1013.5726 | L79: -506.84 | M79: -494.83814 | N79: -1012.7132 | O79: -1252.3951 | P79: 1346.03
A80: 4001290650 | B80: 지분법손익(*) | C80: 억원 | D80: -63.347989 | E80: 552.49432 | F80: -707.23937 | G80: -800.65118 | H80: 249.52777 | I80: -734.3521 | J80: 305.9438 | K80: 1013.5726 | L80: -506.84 | M80: -494.83814 | N80: -1012.7132 | O80: -1252.3951 | P80: 1346.03
A81: 4001290680 | B81: 종속기업,공동지배기업및관계기업투자주식처분손익(*) | C81: 억원
A82: 4001290710 | B82: 종속기업,공동지배기업및관계기업투자주식손상관련손익(*) | C82: 억원
A83: 4001290740 | B83: 기타(*) | C83: 억원
A84: 4001212380 | B84: 법인세비용차감전계속사업이익 | C84: 억원 | D84: 1205.5735 | E84: 3344.5289 | F84: 2171.2256 | G84: -1226.5546 | H84: 2012.092 | I84: 380.05346 | J84: 292.86166 | K84: -1364.1585 | L84: -3788.89 | M84: -3109.5637 | N84: -3703.7132 | O84: -3634.8411 | P84: -680.85
A85: 4001212390 | B85: 법인세비용 | C85: 억원 | D85: 216.00256 | E85: 899.45131 | F85: 839.21763 | G85: 68.095365 | H85: 606.44916 | I85: 224.49339 | J85: 132.24784 | K85: -497.36324 | L85: -691.16 | M85: -640.83807 | N85: -115.69857 | O85: -1708.7538 | P85: -391.57
A86: 4001212400 | B86: 종속회사매수일전순손익 | C86: 억원
A87: 4001212410 | B87: 처분된종속회사순손익 | C87: 억원
A88: 4001212420 | B88: 계속영업이익(손실) | C88: 억원 | D88: 989.57091 | E88: 2445.0776 | F88: 1332.008 | G88: -1298.5714 | H88: 1405.6428 | I88: 155.56008 | J88: 160.61382 | K88: -904.35985 | L88: -3097.73 | M88: -2468.7256 | N88: -3588.0146 | O88: -1937.8009 | P88: -289.28
A89: 4001212430 | B89: 중단영업이익(손실) | C89: 억원 | D89: 41.404958 | E89: 0.1833902 | F89: 53.748183 | G89: 96.809809 | H89: -71.563365 | I89: 74.042056 | J89: 66.466999 | K89: -1768.6281 | L89: -1373.24 | M89: -828.72934 | N89: -288.44975 | O89: -107.11449 | P89: -12.67
A90: 4001212450 | B90: 당기순이익(손실) | C90: 억원 | D90: 1030.9759 | E90: 2445.261 | F90: 1385.7562 | G90: -1201.7615 | H90: 1334.0795 | I90: 229.60214 | J90: 227.08082 | K90: -2672.988 | L90: -4470.97 | M90: -3297.455 | N90: -3876.4644 | O90: -2044.9154 | P90: -301.95
A91: 4001220000 | B91: 기타포괄손익(*) | C91: 억원 | D91: 1315.4798 | E91: 748.71667 | F91: 4068.6655 | G91: -3944.7708 | H91: 2208.7275 | I91: -909.55591 | J91: 920.03986 | K91: -2007.4689 | L91: 1736.57 | M91: 13033.528 | N91: -1330.9473 | O91: 7819.5745 | P91: -403.02
A92: 4001220120 | B92: 총포괄손익 | C92: 억원 | D92: 2346.4557 | E92: 3193.9777 | F92: 5454.4216 | G92: -5146.5324 | H92: 3542.8069 | I92: -679.95377 | J92: 1147.1207 | K92: -4680.4568 | L92: -2734.4 | M92: 9736.0729 | N92: -5207.4117 | O92: 5774.659 | P92: -704.97
A93: 4001230000 | B93: (당기순손익귀속)지배기업주주지분 | C93: 억원 | D93: 1009.0579 | E93: 2390.4133 | F93: 1370.382 | G93: -1178.3905 | H93: 1162.4829 | I93: 92.412722 | J93: 79.827836 | K93: -2745.1095 | L93: -4578.09 | M93: -3670.6185 | N93: -4005.3928 | O93: -1789.8923 | P93: -444.67
A94: 4001230030 | B94: (당기순손익귀속)비지배주주지분 | C94: 억원 | D94: 21.91796 | E94: 54.847718 | F94: 15.374127 | G94: -23.371087 | H94: 171.5966 | I94: 137.18941 | J94: 147.25298 | K94: 72.121544 | L94: 107.12 | M94: 373.16356 | N94: 128.92844 | O94: -255.02311 | P94: 142.72
A95: 4001230060 | B95: (총포괄손익귀속)지배기업주주지분 | C95: 억원 | D95: 2269.684 | E95: 3089.2427 | F95: 5291.8647 | G95: -4845.8716 | H95: 3182.7959 | I95: -739.24817 | J95: 933.85382 | K95: -4626.3371 | L95: -2972.64 | M95: 8965.2799 | N95: -5212.685 | O95: 5700.1671 | P95: -873.81
A96: 4001230070 | B96: (총포괄손익귀속)비지배주주지분 | C96: 억원 | D96: 76.771668 | E96: 104.73502 | F96: 162.55698 | G96: -300.6608 | H96: 360.01101 | I96: 59.294399 | J96: 213.26686 | K96: -54.119703 | L96: 238.24 | M96: 770.79305 | N96: 5.2733553 | O96: 74.491922 | P96: 168.84
A97: 4001230080 | B97: 주당계속영업이익 | C97: 원
A98: 4001230090 | B98: 주당순손익 | C98: 원
A99: 4001230100 | B99: 희석주당계속영업이익 | C99: 원
A100: 4001230110 | B100: 희석주당순손익 | C100: 원
...

Sheet CFS(Q)
B1: Last Refresh: 2025-05-24 13:23:20
A2: Financial Statements
A3: 기업 | B3: A009830(한화솔루션) - Fiscal Month:12, 201103부터 IFRS 적용
A4: 회계유형 | B4: 연결 | C4: 회계기준 | D4: IFRS
A5: 리포트 | B5: 현금흐름표 | C5: New
A6: 형식 | B6: 약식(COMPARE)
A7: 출력 | B7: 당분기 | C7: 억원
A8: 회계연도 | B8: 2022 | C8: Current
A9: 계정코드 | B9: 계정명 | C9: 단위 | D9: 202203(1Q) | E9: 202206(2Q) | F9: 202209(3Q) | G9: 202212(4Q) | H9: 202303(1Q) | I9: 202306(2Q) | J9: 202309(3Q) | K9: 202312(4Q) | L9: 202403(1Q) | M9: 202406(2Q) | N9: 202409(3Q) | O9: 202412(4Q) | P9: 202503(1Q)
D10: IFRS(연결) | E10: IFRS(연결) | F10: IFRS(연결) | G10: IFRS(연결) | H10: IFRS(연결) | I10: IFRS(연결) | J10: IFRS(연결) | K10: IFRS(연결) | L10: IFRS(연결) | M10: IFRS(연결) | N10: IFRS(연결) | O10: IFRS(연결) | P10: IFRS(연결)
A11: 4001390000 | B11: 영업활동으로인한현금흐름(간접법)(*) | C11: 억원 | D11: -3241.1741 | E11: 749.97051 | F11: 684.16482 | G11: 2964.2061 | H11: 3702.1775 | I11: -2226.5206 | J11: -62.953102 | K11: 3766.8377 | L11: -5246.39 | M11: -3560.6879 | N11: 2442.8082 | O11: 12749.135 | P11: -1732.04
A12: 4001310010 | B12: *(직접법)총현금유입(*) | C12: 억원
A13: 4001310100 | B13: *(직접법)총현금유출(*) | C13: 억원
A14: 4001310190 | B14: 당기순손익 | C14: 억원 | I14: 1584.899 | J14: 227.08082 | K14: -2694.2054 | L14: -4470.97 | M14: -3306.2368 | N14: -3876.4644 | O14: -2036.1336 | P14: -301.95
A15: 4001310200 | B15: 법인세비용차감전계속사업이익 | C15: 억원 | D15: 1254.3616 | E15: 3344.527 | F15: 2224.7141 | G15: -1131.2141 | H15: 1933.9035 | I15: -1933.9035
A16: 4001390010 | B16: 현금유출이없는비용등가산(*) | C16: 억원 | D16: 3257.3989 | E16: 4628.6115 | F16: 6119.1648 | G16: 4985.8035 | H16: 5692.4869 | I16: 4761.1016 | J16: 2737.6854 | K16: 7648.2081 | L16: 6711.37 | M16: 6263.0123 | N16: 5218.8797 | O16: 8859.0557 | P16: 5679.36
A17: 4001390040 | B17: (현금유입이없는수익등차감)(*) | C17: 억원 | D17: 1147.7357 | E17: 2463.7384 | F17: 1897.3207 | G17: 86.01398 | H17: 2494.5411 | I17: 573.55822 | J17: 976.26791 | K17: 1176.7514 | L17: 2315.43 | M17: 1705.8555 | N17: -0.50194 | O17: 3503.2138 | P17: 2810.46
A18: 4001390060 | B18: 영업활동으로인한자산부채변동(운전자본변동)(*) | C18: 억원 | D18: -6409.7689 | E18: -4001.9275 | F18: -4843.1471 | G18: -1009.8504 | H18: 263.99277 | I18: -4283.9661 | J18: -1947.27 | K18: 979.06099 | L18: -5181.02 | M18: -4829.4552 | N18: 1284.2626 | O18: 9564.4736 | P18: -4104.8
A19: 4001390070 | B19: 자산의감소(증가)(*) | C19: 억원 | D19: -5684.5299 | E19: -5500.5119 | F19: -2071.5293 | G19: 5493.1208 | H19: 2472.0363 | I19: -6196.7279 | J19: -4321.1909 | K19: -4310.5262 | L19: -5290.32 | M19: -5165.918 | N19: 2707.7514 | O19: -1577.77 | P19: 2317.9
A20: 4001390110 | B20: 부채의증가(감소)(*) | C20: 억원 | D20: -725.23892 | E20: 1498.5844 | F20: -2771.6178 | G20: -6502.9713 | H20: -2208.0435 | I20: 1912.7617 | J20: 2373.9209 | K20: 5289.5872 | L20: 109.3 | M20: 336.46282 | N20: -1423.4888 | O20: 11142.244 | P20: -6422.7
A21: 4001312260 | B21: 정부보조금등의변동 | C21: 억원
A22: 4001312270 | B22: 기타운전자본의변동 | C22: 억원
A23: 4001312280 | B23: *영업에서창출된현금흐름 | C23: 억원 | D23: -3045.7441 | E23: 1507.4726 | F23: 1603.4111 | G23: 2758.725 | H23: 5395.8422 | I23: -445.4272 | J23: 41.22828 | K23: 4756.3123 | L23: -5256.05 | M23: -3578.5351 | N23: 2627.1798 | O23: 12884.182 | P23: -1537.85
A24: 4001312290 | B24: 이자수입 | C24: 억원 | D24: 183.67478 | E24: 183.9 | F24: 210.25666 | G24: 212.79806 | H24: 263.06567 | I24: 268.67734 | J24: 270.91009 | K24: 282.10149 | L24: 296.92 | M24: 326.59135 | N24: 317.91485 | O24: 90.530308 | P24: 43.65
A25: 4001312300 | B25: 이자지급(-) | C25: 억원 | D25: -58.38796 | E25: -74.913697 | F25: -93.655874 | G25: -33.116635 | H25: -159.78399 | I25: -173.5213 | J25: -178.17112 | K25: -159.86865 | L25: -196.46 | M25: -208.75435 | N25: -151.26358 | O25: -49.790426 | P25: -34.03
A26: 4001312310 | B26: 배당금수입 | C26: 억원
A27: 4001312320 | B27: 배당금지급(-) | C27: 억원
A28: 4001312330 | B28: 법인세환입 | C28: 억원
A29: 4001312340 | B29: 법인세납부(-) | C29: 억원 | D29: -320.7169 | E29: -866.48836 | F29: -1035.8471 | G29: 25.799656 | H29: -1796.9464 | I29: -1876.2494 | J29: -196.92034 | K29: -1111.7074 | L29: -90.8 | M29: -99.989769 | N29: -351.02289 | O29: -175.78716 | P29: -203.81
A30: 4001312350 | B30: 중단영업관련현금흐름 | C30: 억원
A31: 4001390160 | B31: 투자활동으로인한현금흐름(*) | C31: 억원 | D31: -4847.9284 | E31: -2715.4791 | F31: -4239.8809 | G31: -2962.5162 | H31: -5432.0792 | I31: -5516.627 | J31: -9867.3637 | K31: -7175.3998 | L31: -6303.02 | M31: -8938.6537 | N31: -10649.15 | O31: -6983.186 | P31: -8804.15
A32: 4001390170 | B32: 투자활동으로인한현금유입액(*) | C32: 억원 | D32: 804.44239 | E32: 470.06659 | F32: 80.864667 | G32: 1765.7027 | H32: 3368.7077 | I32: -449.03102 | J32: 30.899143 | K32: 944.37226 | L32: 1336.24 | M32: 517.73412 | N32: 534.36754 | O32: 6264.4668 | P32: 734.86
A33: 4001390270 | B33: (투자활동으로인한현금유출액)(*) | C33: 억원 | D33: 5591.524 | E33: 3458.7367 | F33: 4394.9491 | G33: 5111.2937 | H33: 8988.9188 | I33: 5588.6584 | J33: 10271.657 | K33: 8605.9906 | L33: 7942.96 | M33: 10328.713 | N33: 11440.023 | O33: 13881.392 | P33: 10077.27
A34: 4001321350 | B34: 이자수입 | C34: 억원 | F34: 52.943643 | G34: 72.374123 | H34: 184.90968 | I34: 170.23575 | J34: 354.31792 | K34: 309.57742 | L34: 295.58 | M34: 322.5899 | N34: 256.45729 | O34: 522.7665 | P34: 347.47
A35: 4001321360 | B35: 이자지급(-) | C35: 억원 | D35: -77.341773 | E35: 59.020218 | F35: 18.321554
A36: 4001321370 | B36: 배당금수입 | C36: 억원 | D36: 16.495031 | E36: 214.17076 | F36: 2.9383791 | G36: 310.70065 | H36: 3.22214 | I36: 350.82665 | J36: 19.076284 | K36: 176.64112 | L36: 8.12 | M36: 549.73541 | N36: 0.0488991 | O36: 110.97255 | P36: 190.79
A37: 4001321380 | B37: 배당금지급(-) | C37: 억원
A38: 4001321390 | B38: 법인세환입 | C38: 억원
A39: 4001321400 | B39: 법인세납부(-) | C39: 억원
A40: 4001321410 | B40: 중단영업관련현금흐름 | C40: 억원
A41: 4001390370 | B41: 재무활동으로인한현금흐름(*) | C41: 억원 | D41: 6551.7699 | E41: 5367.868 | F41: 6721.2604 | G41: 4582.1653 | H41: -4342.8176 | I41: 11139.774 | J41: 14500.866 | K41: -5210.7128 | L41: 21003.62 | M41: 2379.5597 | N41: 10666.774 | O41: -7290.5915 | P41: 8012.18
A42: 4001390380 | B42: 재무활동으로인한현금유입액(*) | C42: 억원 | D42: 13280.956 | E42: 18565.673 | F42: 15110.708 | G42: 21017.719 | H42: 8690.9433 | I42: 22494.192 | J42: 17565.661 | K42: 7357.2934 | L42: 30201.31 | M42: 12429.193 | N42: 23212.879 | O42: 22190.599 | P42: 25708.44
A43: 4001390470 | B43: (재무활동으로인한현금유출액)(*) | C43: 억원 | D43: 6039.4294 | E43: 13182.449 | F43: 8242.8315 | G43: 15742.38 | H43: 12263.716 | I43: 10768.629 | J43: 1562.0423 | K43: 11265.855 | L43: 7907.32 | M43: 8055.5744 | N43: 10073.856 | O43: 28509.908 | P43: 16139.03
A44: 4001330680 | B44: 이자수입 | C44: 억원
A45: 4001330690 | B45: 이자지급(-) | C45: 억원 | D45: -689.75706 | E45: -15.356381 | F45: -146.61648 | G45: -693.17371 | H45: -770.04439 | I45: -585.78915 | J45: -980.48217 | K45: -1302.1512 | L45: -1290.37 | M45: -1477.1213 | N45: -1713.3087 | O45: -867.15771 | P45: -1453.1
A46: 4001330700 | B46: 배당금수입 | C46: 억원
A47: 4001330710 | B47: 배당금지급(-) | C47: 억원 | J47: -522.27037 | M47: -516.93736 | N47: -758.94027 | O47: -104.125 | P47: -104.13
A48: 4001330720 | B48: 법인세환입 | C48: 억원
A49: 4001330730 | B49: 법인세납부(-) | C49: 억원
A50: 4001330740 | B50: 중단영업관련현금흐름 | C50: 억원
A51: 4001340000 | B51: 영업투자재무활동기타현금흐름 | C51: 억원 | O51: -25.78009
A52: 4001340010 | B52: 연결범위변동으로인한현금의증가 | C52: 억원
A53: 4001340020 | B53: 환율변동효과 | C53: 억원 | D53: 161.4987 | E53: 511.12714 | F53: 263.79036 | G53: -904.4626 | H53: 506.33376 | I53: -70.292544 | J53: 294.56671 | K53: -586.92491 | L53: 756.87 | M53: 213.2373 | N53: -658.84916 | O53: 1707.5638 | P53: 31.05
A54: 4001340030 | B54: 현금및현금성자산의증가 | C54: 억원 | D54: -1375.8339 | E54: 3913.4866 | F54: 3429.3347 | G54: 3679.3926 | H54: -5566.3855 | I54: 3326.3335 | J54: 4865.1156 | K54: -9206.1998 | L54: 10211.08 | M54: -9906.5446 | N54: 1801.5829 | O54: 157.1409 | P54: -2492.96
A55: 4001340040 | B55: 기초현금및현금성자산 | C55: 억원 | D55: 16515.303 | E55: 15139.469 | F55: 19052.956 | G55: 22482.29 | H55: 26161.683 | I55: 20595.297 | J55: 23921.631 | K55: 28786.747 | L55: 19580.55 | M55: 29791.63 | N55: 19885.082 | O55: 21686.665 | P55: 21843.81
A56: 4001340050 | B56: 기말현금및현금성자산 | C56: 억원 | D56: 15139.469 | E56: 19052.956 | F56: 22482.29 | G56: 26161.683 | H56: 20595.297 | I56: 23921.631 | J56: 28786.747 | K56: 19580.547 | L56: 29791.63 | M56: 19885.082 | N56: 21686.665 | O56: 21843.806 | P56: 19350.85

Sheet BS(A)
B1: Last Refresh: 2025-05-24 13:35:01
A2: Financial Statements
A3: 기업 | B3: A009830(한화솔루션) - Fiscal Month:12, 201103부터 IFRS 적용
A4: 회계유형 | B4: 연결 | C4: 회계기준 | D4: IFRS
A5: 리포트 | B5: 재무상태표 | C5: New
A6: 형식 | B6: 약식(COMPARE)
A7: 출력 | B7: 결산 | C7: 억원
A8: 회계연도 | B8: 2022 | C8: Current
A9: 계정코드 | B9: 계정명 | C9: 단위 | D9: 202212 | E9: 202312 | F9: 202412
D10: IFRS(연결) | E10: IFRS(연결) | F10: IFRS(연결)
A11: 4001190010 | B11: 자산(*) | C11: 억원 | D11: 238318.84 | E11: 247904.24 | F11: 300368.31
A12: 4001190240 | B12: 유동자산(*) | C12: 억원 | D12: 85732.954 | E12: 97973.721 | F12: 108826.65
A13: 4001190250 | B13: 재고자산(*) | C13: 억원 | D13: 30601.078 | E13: 34474.813 | F13: 42575.477
A14: 4001190260 | B14: 유동생물자산(*) | C14: 억원
A15: 4001190270 | B15: 유동금융자산(*) | C15: 억원 | D15: 2561.2984 | E15: 3681.6373 | F15: 3737.3693
A16: 4001190300 | B16: 매출채권및기타유동채권(*) | C16: 억원 | D16: 22798.068 | E16: 31876.68 | F16: 29675.511
A17: 4001113900 | B17: 당기법인세자산(선급법인세) | C17: 억원 | D17: 179.46308 | E17: 415.72736 | F17: 553.13091
A18: 4001180995 | B18: 계약자산(**) | C18: 억원 | D18: 626.43122 | E18: 3759.2226 | F18: 3806.8755
A19: 4001113903 | B19: 반품(환불)자산 | C19: 억원 | D19: 0.72445
A20: 4001113904 | B20: 배출권 | C20: 억원 | D20: 29.94038 | E20: 17.32413 | F20: 11.43374
A21: 4001190340 | B21: 기타유동자산(*) | C21: 억원 | D21: 3079.6143 | E21: 4167.7697 | F21: 5650.0176
A22: 4001190370 | B22: 현금및현금성자산(*) | C22: 억원 | D22: 25483.797 | E22: 19580.547 | F22: 21843.806
A23: 4001114130 | B23: 매각예정비유동자산및처분자산집단(*) | C23: 억원 | D23: 372.54007 | F23: 973.02938
A24: 4001190020 | B24: 비유동자산(*) | C24: 억원 | D24: 136343.75 | E24: 149930.52 | F24: 191541.66
A25: 4001190030 | B25: 유형자산(*) | C25: 억원 | D25: 68794.515 | E25: 70497.835 | F25: 107269.64
A26: 4001190070 | B26: 무형자산(*) | C26: 억원 | D26: 16444.376 | E26: 17725.761 | F26: 17557.426
A27: 4001190110 | B27: 비유동생물자산(*) | C27: 억원
A28: 4001190120 | B28: 투자부동산(*) | C28: 억원 | D28: 1997.6283 | E28: 1916.6698 | F28: 1965.6832
A29: 4001190130 | B29: 장기금융자산(*) | C29: 억원 | D29: 4520.2169 | E29: 4935.4425 | F29: 5034.9009
A30: 4001111660 | B30: 관계기업등지분관련투자자산(*) | C30: 억원 | D30: 37446.276 | E30: 41597.179 | F30: 49304.474
A31: 4001190160 | B31: 장기매출채권및기타비유동채권(*) | C31: 억원 | D31: 62.156102 | E31: 6885.4541 | F31: 1460.1683
A32: 4001112490 | B32: 이연법인세자산 | C32: 억원 | D32: 2012.9173 | E32: 1842.9539 | F32: 2893.6629
A33: 4001112500 | B33: 장기당기법인세자산 | C33: 억원
A34: 4001180575 | B34: 계약자산(**) | C34: 억원
A35: 4001112503 | B35: 반품(환불)자산 | C35: 억원
A36: 4001112504 | B36: 배출권 | C36: 억원
A37: 4001190200 | B37: 기타비유동자산(*) | C37: 억원 | D37: 5065.6619 | E37: 4529.2214 | F37: 6055.713
A38: 4001112880 | B38: 기타금융업자산 | C38: 억원 | D38: 16242.142
A39: 4001190440 | B39: 부채(*) | C39: 억원 | D39: 139349.73 | E39: 155101.87 | F39: 194299.75
A40: 4001190610 | B40: 유동부채(*) | C40: 억원 | D40: 68084.914 | E40: 87341.103 | F40: 117075.52
A41: 4001181470 | B41: 단기사채(**) | C41: 억원
A42: 4001121700 | B42: 단기차입금(*) | C42: 억원 | D42: 24430.177 | E42: 29470.517 | F42: 51098.996
A43: 4001190620 | B43: 유동성장기부채(*) | C43: 억원 | D43: 5597.9287 | E43: 8411.4676 | F43: 11891.669
A44: 4001190630 | B44: 유동금융부채(*) | C44: 억원 | D44: 1960.5967 | E44: 1786.9207 | F44: 1261.8316
A45: 4001190660 | B45: 매입채무및기타유동채무(*) | C45: 억원 | D45: 27805.79 | E45: 39749.173 | F45: 40231.556
A46: 4001190680 | B46: 유동종업원급여충당부채(*) | C46: 억원
A47: 4001122460 | B47: 기타단기충당부채(*) | C47: 억원 | D47: 478.34554 | E47: 430.3094 | F47: 693.68458
A48: 4001122560 | B48: 당기법인세부채(미지급법인세) | C48: 억원 | D48: 3856.3243 | E48: 430.46784 | F48: 360.76762
A49: 4001122561 | B49: 계약부채 | C49: 억원 | D49: 3179.1231 | E49: 5259.1314 | F49: 7128.8845
A50: 4001122562 | B50: 반품(환불)부채 | C50: 억원 | D50: 13.52275
A51: 4001122563 | B51: 배출부채 | C51: 억원
A52: 4001190690 | B52: 기타유동부채(*) | C52: 억원 | D52: 763.10609 | E52: 1803.1164 | F52: 4180.9774
A53: 4001122680 | B53: 매각예정으로분류된처분자산집단에포함된부채(*) | C53: 억원 | F53: 227.15651
A54: 4001190450 | B54: 비유동부채(*) | C54: 억원 | D54: 56854.321 | E54: 67760.766 | F54: 77224.229
A55: 4001190460 | B55: 사채(*) | C55: 억원 | D55: 20473.074 | E55: 23874.659 | F55: 21914.192
A56: 4001190470 | B56: 장기차입금(*) | C56: 억원 | D56: 21580.552 | E56: 31786.231 | F56: 42314.499
A57: 4001190480 | B57: 비유동금융부채(*) | C57: 억원 | D57: 5806.7797 | E57: 2406.602 | F57: 4106.0832
A58: 4001190500 | B58: 장기매입채무및기타비유동채무(*) | C58: 억원 | D58: 929.3652 | E58: 2751.6272 | F58: 944.22468
A59: 4001190570 | B59: 비유동종업원급여충당부채(*) | C59: 억원 | D59: 4268.1571 | E59: 3866.4055 | F59: 3860.3994
A60: 4001121280 | B60: 기타장기충당부채(*) | C60: 억원 | D60: 1275.0871 | E60: 1339.1039 | F60: 1564.0289
A61: 4001121380 | B61: 이연법인세부채 | C61: 억원 | D61: 2297.1822 | E61: 1698.6856 | F61: 2320.4565
A62: 4001181370 | B62: 장기당기법인세부채(미지급법인세)(**) | C62: 억원
A63: 4001121401 | B63: 계약부채 | C63: 억원 | D63: 186.21457 | E63: 8.23683 | F63: 118.7935
A64: 4001121402 | B64: 반품(환불)부채 | C64: 억원 | F64: 1.30811
A65: 4001121403 | B65: 배출부채 | C65: 억원
A66: 4001190580 | B66: 기타비유동부채(*) | C66: 억원 | D66: 37.9089 | E66: 29.21581 | F66: 80.243
A67: 4001121620 | B67: 기타금융업부채 | C67: 억원 | D67: 14410.494
A68: 4001190380 | B68: 자본(*) | C68: 억원 | D68: 98969.116 | E68: 92802.367 | F68: 106068.56
A69: 4001130010 | B69: *수권주식수 | C69: 주 | D69: 300000000 | E69: 300000000 | F69: 300000000
A70: 4001130020 | B70: *주당액면가액 | C70: 원 | D70: 5000 | E70: 5000 | F70: 5000
A71: 4001130030 | B71: *발행한주식총수(*) | C71: 주 | D71: 192402234 | E71: 174467885 | F71: 174467885
A72: 4001130040 | B72: *보통주 | C72: 주 | D72: 191278497 | E72: 171892536 | F72: 171892536
A73: 4001130050 | B73: *우선주 | C73: 주 | D73: 1123737 | E73: 2575349 | F73: 2575349
A74: 4001190390 | B74: 지배기업주주지분(*) | C74: 억원 | D74: 89205.71 | E74: 81171.666 | F74: 94496.501
A75: 4001130070 | B75: 자본금(*) | C75: 억원 | D75: 9782.4065 | E75: 8885.6891 | F75: 8885.6891
A76: 4001130670 | B76: 신종자본증권 | C76: 억원 | F76: 6967.9414
A77: 4001190400 | B77: 자본잉여금(*) | C77: 억원 | D77: 23200.511 | E77: 14962.94 | F77: 15624.21
A78: 4001190420 | B78: 기타자본(*) | C78: 억원 | D78: -1541.5394 | E78: -1350.8221 | F78: -1503.7151
A79: 4001130360 | B79: 기타포괄손익누계액(*) | C79: 억원 | D79: 2150.277 | E79: 2579.5864 | F79: 23198.023
A80: 4001130470 | B80: 이익잉여금(결손금)(*) | C80: 억원 | D80: 55614.054 | E80: 56094.273 | F80: 41324.353
A81: 4001130640 | B81: 비지배주주지분 | C81: 억원 | D81: 9763.4057 | E81: 11630.702 | F81: 11572.06

Sheet IS(A)
B1: Last Refresh: 2025-05-24 13:36:03
A2: Financial Statements
A3: 기업 | B3: A009830(한화솔루션) - Fiscal Month:12, 201103부터 IFRS 적용
A4: 회계유형 | B4: 연결 | C4: 회계기준 | D4: IFRS
A5: 리포트 | B5: 손익계산서 | C5: New
A6: 형식 | B6: 약식(COMPARE)
A7: 출력 | B7: 결산 | C7: 억원
A8: 회계연도 | B8: 2022 | C8: Current
A9: 계정코드 | B9: 계정명 | C9: 단위 | D9: 202212 | E9: 202312 | F9: 202412
D10: IFRS(연결) | E10: IFRS(연결) | F10: IFRS(연결)
A11: 4001210000 | B11: 매출액(수익)(*) | C11: 억원 | D11: 131307.53 | E11: 130785.36 | F11: 123940.24
A12: 4001210010 | B12: *수출(*) | C12: 억원
A13: 4001210020 | B13: *내수 | C13: 억원
A14: 4001210320 | B14: 매출원가(*) | C14: 억원 | D14: 107317.53 | E14: 109132.41 | F14: 110081.68
A15: 4001210780 | B15: 매출총이익(손실) | C15: 억원 | D15: 23989.996 | E15: 21652.953 | F15: 13858.553
A16: 4001290000 | B16: 판매비와관리비(*) | C16: 억원 | D16: 14752.73 | E16: 15860.583 | F16: 16860.933
A17: 4001290010 | B17: 인건비(*) | C17: 억원 | D17: 5165.2095 | E17: 6084.8399 | F17: 6952.423
A18: 4001290020 | B18: 유무형자산상각비(*) | C18: 억원 | D18: 901.12022 | E18: 1106.3489 | F18: 1344.2555
A19: 4001211300 | B19: 연구개발비 | C19: 억원 | D19: 1411.2032 | E19: 1271.4068 | F19: 916.33605
A20: 4001211060 | B20: 광고선전비 | C20: 억원 | D20: 245.95585 | E20: 288.00611 | F20: 243.42648
A21: 4001290040 | B21: 판매비(*) | C21: 억원 | D21: 3764.6663 | E21: 3861.8259 | F21: 3685.7872
A22: 4001290090 | B22: 관리비(*) | C22: 억원 | D22: 3097.1477 | E22: 3143.888 | F22: 3582.9536
A23: 4001290110 | B23: 기타원가성비용(*) | C23: 억원
A24: 4001211420 | B24: 기타 | C24: 억원 | D24: 167.42691 | E24: 104.26753 | F24: 135.75103
A25: 4001211430 | B25: 영업이익(손실) | C25: 억원 | D25: 9237.2665 | E25: 5792.3703 | F25: -3002.3796
A26: 4001290120 | B26: 금융수익(*) | C26: 억원 | D26: 298.44663 | E26: 920.49689 | F26: 1082.8076
A27: 4001290750 | B27: 이자수익 | C27: 억원 | D27: 285.82422 | E27: 883.42585 | F27: 1033.821
A28: 4001290760 | B28: 배당금수익 | C28: 억원 | D28: 4.84814 | E28: 23.01041 | F28: 34.02099
A29: 4001211480 | B29: 외환이익(*) | C29: 억원
A30: 4001211520 | B30: 대손충당금환입액 | C30: 억원
A31: 4001211600 | B31: 매출채권처분이익 | C31: 억원
A32: 4001211605 | B32: 당기손익-공정가치측정 금융자산관련이익 | C32: 억원
A33: 4001290130 | B33: 금융자산처분이익(*) | C33: 억원
A34: 4001290150 | B34: 금융자산평가이익(*) | C34: 억원
A35: 4001211720 | B35: 금융자산손상차손환입(*) | C35: 억원
A36: 4001211680 | B36: 파생상품이익(*) | C36: 억원
A37: 4001290170 | B37: 기타금융수익(*) | C37: 억원 | D37: 7.77427 | E37: 14.06063 | F37: 14.9656
A38: 4001290180 | B38: 금융원가(*) | C38: 억원 | D38: 2009.4204 | E38: 4114.1431 | F38: 5484.2022
A39: 4001290770 | B39: 이자비용 | C39: 억원 | D39: 2009.4204 | E39: 4114.1431 | F39: 5484.2022
A40: 4001211820 | B40: 외환손실(*) | C40: 억원
A41: 4001211860 | B41: 대손상각비 | C41: 억원
A42: 4001211865 | B42: 당기손익-공정가치측정 금융자산관련손실 | C42: 억원
A43: 4001211940 | B43: 매출채권처분손실 | C43: 억원
A44: 4001290190 | B44: 금융자산처분손실(*) | C44: 억원
A45: 4001290210 | B45: 금융자산평가손실(*) | C45: 억원
A46: 4001212060 | B46: 금융자산손상차손(*) | C46: 억원
A47: 4001212020 | B47: 파생상품손실(*) | C47: 억원
A48: 4001290230 | B48: 기타금융원가(*) | C48: 억원
A49: 4001290240 | B49: 기타수익(*) | C49: 억원 | D49: 9117.4447 | E49: 5643.0609 | F49: 6942.6239
A50: 4001280000 | B50: 이자수익 | C50: 억원
A51: 4001280010 | B51: 배당금수익 | C51: 억원
A52: 4001290250 | B52: 외환이익(*) | C52: 억원 | D52: 6196.1681 | E52: 3686.1405 | F52: 3502.0947
A53: 4001280050 | B53: 재고자산감모손실환입 | C53: 억원
A54: 4001280060 | B54: 재고자산폐기(처분)이익 | C54: 억원
A55: 4001280065 | B55: 당기손익-공정가치측정 금융자산평가이익 | C55: 억원 | D55: 15.68532 | E55: 5.60003
A56: 4001290260 | B56: 자산처분(폐기)이익(*) | C56: 억원 | D56: 140.36495 | E56: 85.08667 | F56: 34.93374
A57: 4001280140 | B57: 자산평가이익 | C57: 억원
A58: 4001290280 | B58: 자산손상차손환입(*) | C58: 억원 | E58: 5.03586 | F58: 4.99424
A59: 4001290300 | B59: 파생상품이익(*) | C59: 억원 | D59: 2165.7108 | E59: 980.26348 | F59: 2365.0797
A60: 4001280240 | B60: 임대료수익 | C60: 억원 | D60: 5.79717 | E60: 4.64123 | F60: 4.02211
A61: 4001280250 | B61: 로열티수익 | C61: 억원
A62: 4001280260 | B62: 수수료수익 | C62: 억원
A63: 4001280270 | B63: 대손충당금환입 | C63: 억원 | D63: 0.20847 | E63: 19.53791 | F63: 3.95649
A64: 4001280280 | B64: 충당부채환입액 | C64: 억원
A65: 4001290310 | B65: 기타(*) | C65: 억원 | D65: 593.5099 | E65: 856.75515 | F65: 1027.5429
A66: 4001290320 | B66: 기타비용(*) | C66: 억원 | D66: 10130.22 | E66: 7755.6283 | F66: 10509.071
A67: 4001280400 | B67: 이자비용 | C67: 억원
A68: 4001290330 | B68: 외환손실(*) | C68: 억원 | D68: 6721.7393 | E68: 3558.3063 | F68: 4262.8504
A69: 4001280440 | B69: 재고자산감모손실 | C69: 억원
A70: 4001280450 | B70: 재고자산폐기(처분)손실 | C70: 억원 | D70: 4.8037 | E70: 4.95676 | F70: 71.1335
A71: 4001280455 | B71: 당기손익-공정가치측정 금융자산평가손실 | C71: 억원 | D71: 31.23668 | E71: 105.08037 | F71: 730.43357
A72: 4001290340 | B72: 자산처분(폐기)손실(*) | C72: 억원 | D72: 315.01283 | E72: 107.25307 | F72: 568.6563
A73: 4001280540 | B73: 자산평가손실 | C73: 억원
A74: 4001290360 | B74: 자산손상차손(*) | C74: 억원 | D74: 627.24744 | E74: 1521.7556 | F74: 1155.4115
A75: 4001290380 | B75: 파생상품손실(*) | C75: 억원 | D75: 1571.1507 | E75: 1093.5471 | F75: 1019.4563
A76: 4001280650 | B76: 기타대손상각비 | C76: 억원 | D76: 13.37838 | E76: 6.39926 | F76: 13.35562
A77: 4001280660 | B77: 충당부채전입액 | C77: 억원
A78: 4001290390 | B78: 기타(*) | C78: 억원 | D78: 845.65079 | E78: 1358.3298 | F78: 2687.774
A79: 4001290640 | B79: 종속기업,공동지배기업및관계기업관련손익(*) | C79: 억원 | D79: -1018.7442 | E79: 834.69203 | F79: -3266.7865
A80: 4001290650 | B80: 지분법손익(*) | C80: 억원 | D80: -1018.7442 | E80: 834.69203 | F80: -3266.7865
A81: 4001290680 | B81: 종속기업,공동지배기업및관계기업투자주식처분손익(*) | C81: 억원
A82: 4001290710 | B82: 종속기업,공동지배기업및관계기업투자주식손상관련손익(*) | C82: 억원
A83: 4001290740 | B83: 기타(*) | C83: 억원
A84: 4001212380 | B84: 법인세비용차감전계속사업이익 | C84: 억원 | D84: 5494.7734 | E84: 1320.8486 | F84: -14237.008
A85: 4001212390 | B85: 법인세비용 | C85: 억원 | D85: 2022.7669 | E85: 465.82715 | F85: -3156.4504
A86: 4001212400 | B86: 종속회사매수일전순손익 | C86: 억원
A87: 4001212410 | B87: 처분된종속회사순손익 | C87: 억원
A88: 4001212420 | B88: 계속영업이익(손실) | C88: 억원 | D88: 3468.0852 | E88: 817.45688 | F88: -11092.271
A89: 4001212430 | B89: 중단영업이익(손실) | C89: 억원 | D89: 192.14634 | E89: -1699.6824 | F89: -2597.5336
A90: 4001212450 | B90: 당기순이익(손실) | C90: 억원 | D90: 3660.2315 | E90: -882.22554 | F90: -13689.805
A91: 4001220000 | B91: 기타포괄손익(*) | C91: 억원 | D91: 2188.0911 | E91: 211.74256 | F91: 21258.725
A92: 4001220120 | B92: 총포괄손익 | C92: 억원 | D92: 5848.3226 | E92: -670.48298 | F92: 7568.9203
A93: 4001230000 | B93: (당기순손익귀속)지배기업주주지분 | C93: 억원 | D93: 3591.4628 | E93: -1410.3861 | F93: -14043.994
A94: 4001230030 | B94: (당기순손익귀속)비지배주주지분 | C94: 억원 | D94: 68.768717 | E94: 528.16053 | F94: 354.18889
A95: 4001230060 | B95: (총포괄손익귀속)지배기업주주지분 | C95: 억원 | D95: 5804.9198 | E95: -1248.9355 | F95: 6480.122
A96: 4001230070 | B96: (총포괄손익귀속)비지배주주지분 | C96: 억원 | D96: 43.402863 | E96: 578.45256 | F96: 1088.7983
A97: 4001230080 | B97: 주당계속영업이익 | C97: 원
A98: 4001230090 | B98: 주당순손익 | C98: 원
A99: 4001230100 | B99: 희석주당계속영업이익 | C99: 원
A100: 4001230110 | B100: 희석주당순손익 | C100: 원
...

Sheet CFS(A)
B1: Last Refresh: 2025-05-24 13:36:12
A2: Financial Statements
A3: 기업 | B3: A009830(한화솔루션) - Fiscal Month:12, 201103부터 IFRS 적용
A4: 회계유형 | B4: 연결 | C4: 회계기준 | D4: IFRS
A5: 리포트 | B5: 현금흐름표 | C5: New
A6: 형식 | B6: 약식(COMPARE)
A7: 출력 | B7: 결산 | C7: 억원
A8: 회계연도 | B8: 2022 | C8: Current
A9: 계정코드 | B9: 계정명 | C9: 단위 | D9: 202212 | E9: 202312 | F9: 202412
D10: IFRS(연결) | E10: IFRS(연결) | F10: IFRS(연결)
A11: 4001390000 | B11: 영업활동으로인한현금흐름(간접법)(*) | C11: 억원 | D11: 1157.1672 | E11: 5179.5415 | F11: 6384.865
A12: 4001310010 | B12: *(직접법)총현금유입(*) | C12: 억원
A13: 4001310100 | B13: *(직접법)총현금유출(*) | C13: 억원
A14: 4001310190 | B14: 당기순손익 | C14: 억원 | E14: -882.22554 | F14: -13689.805
A15: 4001310200 | B15: 법인세비용차감전계속사업이익 | C15: 억원 | D15: 5692.3886
A16: 4001390010 | B16: 현금유출이없는비용등가산(*) | C16: 억원 | D16: 18990.979 | E16: 20839.482 | F16: 27052.318
A17: 4001390040 | B17: (현금유입이없는수익등차감)(*) | C17: 억원 | D17: 5594.8089 | E17: 5221.1187 | F17: 7523.9974
A18: 4001390060 | B18: 영업활동으로인한자산부채변동(운전자본변동)(*) | C18: 억원 | D18: -16264.694 | E18: -4988.1824 | F18: 838.26101
A19: 4001390070 | B19: 자산의감소(증가)(*) | C19: 억원 | D19: -7763.4503 | E19: -12356.409 | F19: -9326.2566
A20: 4001390110 | B20: 부채의증가(감소)(*) | C20: 억원 | D20: -8501.2436 | E20: 7368.2263 | F20: 10164.518
A21: 4001312260 | B21: 정부보조금등의변동 | C21: 억원
A22: 4001312270 | B22: 기타운전자본의변동 | C22: 억원
A23: 4001312280 | B23: *영업에서창출된현금흐름 | C23: 억원 | D23: 2823.8646 | E23: 9747.9555 | F23: 6676.7766
A24: 4001312290 | B24: 이자수입 | C24: 억원 | D24: 790.6295 | E24: 1084.7546 | F24: 1031.9565
A25: 4001312300 | B25: 이자지급(-) | C25: 억원 | D25: -260.07417 | E25: -671.34506 | F25: -606.26836
A26: 4001312310 | B26: 배당금수입 | C26: 억원
A27: 4001312320 | B27: 배당금지급(-) | C27: 억원
A28: 4001312330 | B28: 법인세환입 | C28: 억원
A29: 4001312340 | B29: 법인세납부(-) | C29: 억원 | D29: -2197.2527 | E29: -4981.8235 | F29: -717.59982
A30: 4001312350 | B30: 중단영업관련현금흐름 | C30: 억원
A31: 4001390160 | B31: 투자활동으로인한현금흐름(*) | C31: 억원 | D31: -14765.805 | E31: -27991.47 | F31: -32874.009
A32: 4001390170 | B32: 투자활동으로인한현금유입액(*) | C32: 억원 | D32: 3121.0763 | E32: 3894.9481 | F32: 8652.8085
A33: 4001390270 | B33: (투자활동으로인한현금유출액)(*) | C33: 억원 | D33: 18556.503 | E33: 33455.225 | F33: 43593.088
A34: 4001321350 | B34: 이자수입 | C34: 억원 | D34: 125.31777 | E34: 1019.0408 | F34: 1397.3937
A35: 4001321360 | B35: 이자지급(-) | C35: 억원
A36: 4001321370 | B36: 배당금수입 | C36: 억원 | D36: 544.30483 | E36: 549.76619 | F36: 668.87686
A37: 4001321380 | B37: 배당금지급(-) | C37: 억원
A38: 4001321390 | B38: 법인세환입 | C38: 억원
A39: 4001321400 | B39: 법인세납부(-) | C39: 억원
A40: 4001321410 | B40: 중단영업관련현금흐름 | C40: 억원
A41: 4001390370 | B41: 재무활동으로인한현금흐름(*) | C41: 억원 | D41: 23223.064 | E41: 16087.109 | F41: 26759.362
A42: 4001390380 | B42: 재무활동으로인한현금유입액(*) | C42: 억원 | D42: 67975.058 | E42: 56108.089 | F42: 88033.98
A43: 4001390470 | B43: (재무활동으로인한현금유출액)(*) | C43: 억원 | D43: 43207.09 | E43: 35860.243 | F43: 54546.658
A44: 4001330680 | B44: 이자수입 | C44: 억원
A45: 4001330690 | B45: 이자지급(-) | C45: 억원 | D45: -1544.9036 | E45: -3638.4669 | F45: -5347.9577
A46: 4001330700 | B46: 배당금수입 | C46: 억원
A47: 4001330710 | B47: 배당금지급(-) | C47: 억원 | E47: -522.27037 | F47: -1380.0026
A48: 4001330720 | B48: 법인세환입 | C48: 억원
A49: 4001330730 | B49: 법인세납부(-) | C49: 억원
A50: 4001330740 | B50: 중단영업관련현금흐름 | C50: 억원
A51: 4001340000 | B51: 영업투자재무활동기타현금흐름 | C51: 억원 | F51: -25.78009
A52: 4001340010 | B52: 연결범위변동으로인한현금의증가 | C52: 억원
A53: 4001340020 | B53: 환율변동효과 | C53: 억원 | D53: 31.953601 | E53: 143.68303 | F53: 2018.822
A54: 4001340030 | B54: 현금및현금성자산의증가 | C54: 억원 | D54: 9646.38 | E54: -6581.1362 | F54: 2263.2592
A55: 4001340040 | B55: 기초현금및현금성자산 | C55: 억원 | D55: 16515.303 | E55: 26161.683 | F55: 19580.547
A56: 4001340050 | B56: 기말현금및현금성자산 | C56: 억원 | D56: 26161.683 | E56: 19580.547 | F56: 21843.806
