Workbook

Sheet Estimate>>>
B2: HD현대마린솔루션 Valuation&Estimation Logic
B8: RFS Research Team 2

Sheet Valuation
A1: HD현대마린솔루션(443060.KS)
A2: Peer P/E Valuation Sheet
A3: (units in KRW)
B5: HD현대마린솔루션 Peer P/E Valuation | G5: 업종 | H5: 기업명 | I5: P/E | J5: 할인율
B6: '26E 당기순이익 | C6: =SUM('Expected IS'!J22:M22) -> 278630.75 | D6: 백만 원 | E6: (A) | G6: 항공 | H6: FTAI Aviation Ltd | I6: 49.21 | J6: 0
B7: Target P/E | C7: =I12 -> 47.976667 | D7: 배 | E7: (B) | G7: 항공 | H7: Heico | I7: 70.72 | J7: 0
B8: 발행 주식 수 | C8: 44829210 | D8: 주 | E8: (C) | G8: 발전설비 | H8: GE Vernova | I8: =133.2*(1-J8) -> 79.92 | J8: 0.4
B9: 적정주가 | C9: =C6*C7/C8*10^6 -> 298193.4 | D9: 원 | E9: (D)=(A)*(B)/(C) | G9: 방산 | H9: Raytheon Technologies | I9: 26.85 | J9: 0
B10: Target Price | C10: =ROUND(C9,-2) -> 298200 | D10: 원 | G10: 방산 | H10: Bae Syetems | I10: 29.66 | J10: 0
B11: Current Price | C11: 203500 | D11: 원 | E11: 25.09.22 기준 | G11: 철도 | H11: Alstom | I11: 31.5 | J11: 0
B12: Upside | C12: =(C10-C11)/C11*100 -> 46.535627 | D12: % | H12: Avg P/E | I12: =AVERAGE(I6:I11) -> 47.976667

Sheet Expected IS
A1: HD현대마린솔루션(443060.KS)
A2: Expected IS Sheet
A3: (units in Millions KRW )
B5: 단위: 백만 원 | C5: 2Q24 | D5: 3Q24 | E5: 4Q24 | F5: 1Q25 | G5: 2Q25 | H5: 3Q25E | I5: 4Q25E | J5: 1Q26E | K5: 2Q26E | L5: 3Q26E | M5: 4Q26E
B6: 매출액 | C6: ='IS(Quaterly)'!G10 -> 437855.16 | D6: ='IS(Quaterly)'!H10 -> 461261.44 | E6: ='IS(Quaterly)'!I10 -> 463372.92 | F6: ='IS(Quaterly)'!J10 -> 485597.83 | G6: ='IS(Quaterly)'!K10 -> 467721.57 | H6: =매출추정!I6*100 -> 469386.75 | I6: =매출추정!J6*100 -> 483293.63 | J6: =매출추정!K6*100 -> 508637.42 | K6: =매출추정!L6*100 -> 519267.74 | L6: =매출추정!M6*100 -> 538811.31 | M6: =매출추정!N6*100 -> 550319.23
B7: 매출원가 | C7: ='IS(Quaterly)'!G13 -> 343798 | D7: ='IS(Quaterly)'!H13 -> 355933.42 | E7: ='IS(Quaterly)'!I13 -> 373085.98 | F7: ='IS(Quaterly)'!J13 -> 377587.18 | G7: ='IS(Quaterly)'!K13 -> 358744.49 | H7: =비용추정!H7 -> 367643.87 | I7: =비용추정!I7 -> 375006.72 | J7: =비용추정!J7 -> 394395.26 | K7: =비용추정!K7 -> 404090.41 | L7: =비용추정!L7 -> 418392.04 | M7: =비용추정!M7 -> 427432.56
B8: (%) | C8: =C7/C6 -> 0.78518659 | D8: =D7/D6 -> 0.77165223 | E8: =E7/E6 -> 0.80515275 | F8: =F7/F6 -> 0.77757181 | G8: =G7/G6 -> 0.76700437 | H8: =H7/H6 -> 0.78324298 | I8: =I7/I6 -> 0.77593972 | J8: =J7/J6 -> 0.77539569 | ... M8: =M7/M6 -> 0.77669929
B9: 매출총이익 | C9: ='IS(Quaterly)'!G14 -> 94057.16 | D9: ='IS(Quaterly)'!H14 -> 105328.02 | E9: ='IS(Quaterly)'!I14 -> 90286.939 | F9: ='IS(Quaterly)'!J14 -> 108010.65 | G9: ='IS(Quaterly)'!K14 -> 108977.08 | H9: =H6-H7 -> 101742.87 | I9: =I6-I7 -> 108286.91 | J9: =J6-J7 -> 114242.16 | K9: =K6-K7 -> 115177.33 | L9: =L6-L7 -> 120419.26 | M9: =M6-M7 -> 122886.67
B10: GPM(%) | C10: =C9/C6 -> 0.21481341 | D10: =D9/D6 -> 0.22834777 | E10: =E9/E6 -> 0.19484725 | F10: =F9/F6 -> 0.22242819 | G10: =G9/G6 -> 0.23299563 | H10: =H9/H6 -> 0.21675702 | I10: =I9/I6 -> 0.22406028 | J10: =J9/J6 -> 0.22460431 | ... M10: =M9/M6 -> 0.22330071
B11: 판매비와 관리비 | C11: ='IS(Quaterly)'!G15 -> 23071.291 | D11: ='IS(Quaterly)'!H15 -> 21944.67 | E11: ='IS(Quaterly)'!I15 -> 24407.77 | F11: ='IS(Quaterly)'!J15 -> 25003.82 | G11: ='IS(Quaterly)'!K15 -> 25967.147 | H11: =비용추정!H11 -> 25534.997 | I11: =비용추정!I11 -> 25957.874 | J11: =비용추정!J11 -> 25964.082 | K11: =비용추정!K11 -> 26135.482 | L11: =비용추정!L11 -> 26176.755 | M11: =비용추정!M11 -> 26341.857
B12: (%) | C12: =C11/C6 -> 0.052691604 | D12: =D11/D6 -> 0.04757534 | E12: =E11/E6 -> 0.05267414 | F12: =F11/F6 -> 0.051490798 | G12: =G11/G6 -> 0.055518387 | H12: =H11/H6 -> 0.054400764 | I12: =I11/I6 -> 0.053710359 | J12: =J11/J6 -> 0.051046346 | ... M12: =M11/M6 -> 0.047866504
B13: 영업이익 | C13: ='IS(Quaterly)'!G24 -> 70985.869 | D13: ='IS(Quaterly)'!H24 -> 83383.35 | E13: ='IS(Quaterly)'!I24 -> 65879.169 | F13: ='IS(Quaterly)'!J24 -> 83006.827 | G13: ='IS(Quaterly)'!K24 -> 83009.935 | H13: =H9-H11 -> 76207.877 | I13: =I9-I11 -> 82329.033 | J13: =J9-J11 -> 88278.077 | K13: =K9-K11 -> 89041.843 | L13: =L9-L11 -> 94242.507 | M13: =M9-M11 -> 96544.815
B14: OPM(%) | C14: =C13/C6 -> 0.16212181 | D14: =D13/D6 -> 0.18077243 | E14: =E13/E6 -> 0.14217311 | F14: =F13/F6 -> 0.17093739 | G14: =G13/G6 -> 0.17747724 | H14: =H13/H6 -> 0.16235626 | I14: =I13/I6 -> 0.17034992 | J14: =J13/J6 -> 0.17355797 | ... M14: =M13/M6 -> 0.1754342
B15: 지분법손익 | C15: ='IS(Quaterly)'!G79 -> 0 | D15: ='IS(Quaterly)'!H79 -> -179.16728 | E15: ='IS(Quaterly)'!I79 -> -58.85354 | F15: ='IS(Quaterly)'!J79 -> -106.50236 | G15: ='IS(Quaterly)'!K79 -> -61.97999 | H15: =비용추정!H54 -> -101.62579 | I15: =비용추정!I54 -> -82.240421 | J15: =비용추정!J54 -> -88.087141 | K15: =비용추정!K54 -> -83.483336 | L15: =비용추정!L54 -> -88.859172 | M15: =비용추정!M54 -> -85.667517
B16: 금융수익 | C16: ='IS(Quaterly)'!G25 -> 10729.355 | D16: ='IS(Quaterly)'!H25 -> 9314.79 | E16: ='IS(Quaterly)'!I25 -> 29108.738 | F16: ='IS(Quaterly)'!J25 -> 15766.251 | G16: ='IS(Quaterly)'!K25 -> 16252.424 | H16: =비용추정!H56 -> 17610.551 | I16: =비용추정!I56 -> 19684.491 | J16: =비용추정!J56 -> 17328.429 | K16: =비용추정!K56 -> 17718.974 | L16: =비용추정!L56 -> 18085.611 | M16: =비용추정!M56 -> 18204.376
B17: 금융원가 | C17: ='IS(Quaterly)'!G37 -> 4267.171 | D17: ='IS(Quaterly)'!H37 -> 14714.404 | E17: ='IS(Quaterly)'!I37 -> 8263.257 | F17: ='IS(Quaterly)'!J37 -> 13365.847 | G17: ='IS(Quaterly)'!K37 -> 29691.852 | H17: =비용추정!H58 -> 16508.84 | I17: =비용추정!I58 -> 16957.449 | J17: =비용추정!J58 -> 19130.997 | K17: =비용추정!K58 -> 20572.285 | L17: =비용추정!L58 -> 18292.393 | M17: =비용추정!M58 -> 18738.281
B18: 기타수익 | C18: ='IS(Quaterly)'!G48 -> 214.759 | D18: ='IS(Quaterly)'!H48 -> -6.593 | E18: ='IS(Quaterly)'!I48 -> 424.728 | F18: ='IS(Quaterly)'!J48 -> 450.714 | G18: ='IS(Quaterly)'!K48 -> 105.875 | H18: =비용추정!H60 -> 243.681 | I18: =비용추정!I60 -> 306.2495 | J18: =비용추정!J60 -> 276.62987 | K18: =비용추정!K60 -> 233.10884 | L18: =비용추정!L60 -> 264.9173 | M18: =비용추정!M60 -> 270.22638
B19: 기타비용 | C19: ='IS(Quaterly)'!G65 -> 719.496 | D19: ='IS(Quaterly)'!H65 -> 482.051 | E19: ='IS(Quaterly)'!I65 -> 774.81 | F19: ='IS(Quaterly)'!J65 -> 1874.732 | G19: ='IS(Quaterly)'!K65 -> 1333.607 | H19: =비용추정!H62 -> 1116.3 | I19: =비용추정!I62 -> 1274.8622 | J19: =비용추정!J62 -> 1399.8753 | K19: =비용추정!K62 -> 1281.1611 | L19: =비용추정!L62 -> 1268.0497 | M19: =비용추정!M62 -> 1305.9871
B20: 법인세차감전순이익 | C20: ='IS(Quaterly)'!G83 -> 76943.316 | D20: ='IS(Quaterly)'!H83 -> 77315.925 | E20: ='IS(Quaterly)'!I83 -> 86315.712 | F20: ='IS(Quaterly)'!J83 -> 83876.711 | G20: ='IS(Quaterly)'!K83 -> 68280.796 | H20: =H13+H15+H16-H17+H18-H19 -> 76335.343 | I20: =I13+I15+I16-I17+I18-I19 -> 84005.222 | J20: =J13+J15+J16-J17+J18-J19 -> 85264.177 | K20: =K13+K15+K16-K17+K18-K19 -> 85056.997 | L20: =L13+L15+L16-L17+L18-L19 -> 92943.734 | M20: =M13+M15+M16-M17+M18-M19 -> 94889.482
B21: 법인세비용 | C21: ='IS(Quaterly)'!G84 -> 20264.116 | D21: ='IS(Quaterly)'!H84 -> 18786.758 | E21: ='IS(Quaterly)'!I84 -> 17908.97 | F21: ='IS(Quaterly)'!J84 -> 20558.525 | G21: ='IS(Quaterly)'!K84 -> 15283.742 | H21: =H20*비용추정!H66 -> 18117.363 | I21: =I20*비용추정!I66 -> 18396.648 | J21: =J20*비용추정!J66 -> 19287.103 | K21: =K20*비용추정!K66 -> 19116.747 | L21: =L20*비용추정!L66 -> 20393.614 | M21: =M20*비용추정!M66 -> 20726.178
B22: 당기순이익 | C22: ='IS(Quaterly)'!G89 -> 56679.2 | D22: ='IS(Quaterly)'!H89 -> 58529.167 | E22: ='IS(Quaterly)'!I89 -> 68406.742 | F22: ='IS(Quaterly)'!J89 -> 63318.186 | G22: ='IS(Quaterly)'!K89 -> 52997.054 | H22: =H20-H21 -> 58217.98 | I22: =I20-I21 -> 65608.574 | J22: =J20-J21 -> 65977.073 | K22: =K20-K21 -> 65940.25 | L22: =L20-L21 -> 72550.12 | M22: =M20-M21 -> 74163.304
B23: (%) | C23: =C22/C6 -> 0.12944737 | D23: =D22/D6 -> 0.12688936 | E23: =E22/E6 -> 0.14762784 | F23: =F22/F6 -> 0.13039223 | G23: =G22/G6 -> 0.11330898 | H23: =H22/H6 -> 0.12402988 | I23: =I22/I6 -> 0.13575303 | J23: =J22/J6 -> 0.12971337 | ... M23: =M22/M6 -> 0.13476415

Sheet 매출추정
A1: HD현대마린솔루션(443060.KS)
A2: Revenue Estimation Sheet
A3: (units in Hundred Millions KRW )
B5: 단위: 억 원 | C5: 1Q24 | D5: 2Q24 | E5: 3Q24 | F5: 4Q24 | G5: 1Q25 | H5: 2Q25 | I5: 3Q25E | J5: 4Q25E | K5: 1Q26E | L5: 2Q26E | M5: 3Q26E | N5: 4Q26E | P5: 2024A | Q5: 2025E | R5: 2026E
B6: 매출 | C6: 3830 | D6: ='IS(Quaterly)'!G10/100 -> 4378.5516 | E6: ='IS(Quaterly)'!H10/100 -> 4612.6144 | F6: ='IS(Quaterly)'!I10/100 -> 4633.7292 | G6: ='IS(Quaterly)'!J10/100 -> 4855.9783 | H6: ='IS(Quaterly)'!K10/100 -> 4677.2157 | I6: =I8+I14+I16+I18 -> 4693.8675 | J6: =J8+J14+J16+J18 -> 4832.9363 | K6: =K8+K14+K16+K18 -> 5086.3742 | L6: =L8+L14+L16+L18 -> 5192.6774 | M6: =M8+M14+M16+M18 -> 5388.1131 | N6: =N8+N14+N16+N18 -> 5503.1923 | P6: =SUM(C6:F6) -> 17454.895 | Q6: =SUM(G6:J6) -> 19059.998 | R6: =SUM(K6:N6) -> 21170.357
B7: YoY(%) or QoQ(%) | C7: - | D7: =(D6-C6)/C6 -> 0.14322496 | E7: =(E6-D6)/D6 -> 0.053456668 | F7: =(F6-E6)/E6 -> 0.004577633 | G7: =(G6-F6)/F6 -> 0.047963325 | H7: =(H6-G6)/G6 -> -0.036812889 | I7: =(I6-H6)/H6 -> 0.003560189 | J7: =(J6-I6)/I6 -> 0.029627773 | K7: =(K6-J6)/J6 -> 0.052439741 | ... N7: =(N6-M6)/M6 -> 0.021357983 | P7: - | Q7: =(Q6-P6)/P6 -> 0.091957159 | R7: =(R6-Q6)/Q6 -> 0.1107219
B8: AM 솔루션 | C8: 1692 | D8: =SUM(D10:D13) -> 2061 | E8: =SUM(E10:E13) -> 2192 | F8: =SUM(F10:F13) -> 2113 | G8: =SUM(G10:G13) -> 2161 | H8: =SUM(H10:H13) -> 2300 | I8: =SUM(I10:I13) -> 2468.1269 | J8: =SUM(J10:J13) -> 2567.3591 | K8: =SUM(K10:K13) -> 2668.1498 | ... N8: =SUM(N10:N13) -> 2958.9873 | P8: =SUM(C8:F8) -> 8058 | Q8: =SUM(G8:J8) -> 9496.486 | R8: =SUM(K8:N8) -> 11249.817
B9: of Revenue(%) | C9: =C8/C$6 -> 0.44177546 | D9: =D8/D$6 -> 0.4707036 | E9: =E8/E$6 -> 0.47521857 | F9: =F8/F$6 -> 0.4560042 | G9: =G8/G$6 -> 0.44501846 | H9: =H8/H$6 -> 0.49174555 | I9: =I8/I$6 -> 0.52581947 | J9: =J8/J$6 -> 0.53122139 | ... N9: =N8/N$6 -> 0.53768562 | P9: =P8/P$6 -> 0.461647 | Q9: =Q8/Q$6 -> 0.49824172 | R9: =R8/R$6 -> 0.53139475
B10: 엔진 | C10: 1081 | D10: 1245 | E10: 1547 | F10: 1450 | G10: =AM!G8 -> 1572 | H10: =AM!H8 -> 1568 | I10: =AM!I8 -> 1722.0397 | J10: =AM!J8 -> 1802.3473 | K10: =AM!K8 -> 1886.4 | L10: =AM!L8 -> 1974.3725 | M10: =AM!M8 -> 2066.4477 | N10: =AM!N8 -> 2162.8167 | P10: =SUM(C10:F10) -> 5323 | Q10: =SUM(G10:J10) -> 6664.387 | R10: =SUM(K10:N10) -> 8090.0369
B11: 비엔진 | C11: 287 | D11: 307 | E11: 262 | F11: 306 | G11: =AM!G16 -> 281 | H11: =AM!H16 -> 283 | I11: =AM!I16 -> 281.17341 | J11: =AM!J16 -> 278.91662 | K11: =AM!K16 -> 278.39409 | L11: =AM!L16 -> 277.90334 | M11: =AM!M16 -> 277.60624 | N11: =AM!N16 -> 277.45685 | P11: =SUM(C11:F11) -> 1162 | Q11: =SUM(G11:J11) -> 1124.09 | R11: =SUM(K11:N11) -> 1111.3605
B12: 육상발전 | C12: 115 | D12: 279 | E12: 193 | F12: 115 | G12: =AM!G18 -> 89 | H12: =AM!H18 -> 200 | I12: =AM!I18 -> 206.98006 | J12: =AM!J18 -> 216.26174 | K12: =AM!K18 -> 227.861 | L12: =AM!L18 -> 231.89971 | M12: =AM!M18 -> 234.82775 | N12: =AM!N18 -> 236.66213 | P12: =SUM(C12:F12) -> 702 | Q12: =SUM(G12:J12) -> 712.2418 | R12: =SUM(K12:N12) -> 931.25059
B13: 스마트케어 | C13: 209 | D13: 230 | E13: 190 | F13: 242 | G13: =AM!G20 -> 219 | H13: =AM!H20 -> 249 | I13: =AM!I20 -> 257.9337 | J13: =AM!J20 -> 269.8335 | K13: =AM!K20 -> 275.49475 | L13: =AM!L20 -> 278.74887 | M13: =AM!M20 -> 280.87326 | N13: =AM!N20 -> 282.05163 | P13: =SUM(C13:F13) -> 871 | Q13: =SUM(G13:J13) -> 995.7672 | R13: =SUM(K13:N13) -> 1117.1685
B14: 친환경 솔루션 | C14: 303 | D14: 346 | E14: 438 | F14: 548 | G14: 583 | H14: 328 | I14: =Retrofit!I6 -> 391.53745 | J14: =Retrofit!J6 -> 396.0782 | K14: =Retrofit!K6 -> 589.45501 | L14: =Retrofit!L6 -> 590.7023 | M14: =Retrofit!M6 -> 685.28887 | N14: =Retrofit!N6 -> 707.19361 | P14: =SUM(C14:F14) -> 1635 | Q14: =SUM(G14:J14) -> 1698.6156 | R14: =SUM(K14:N14) -> 2572.6398
B15: of Revenue(%) | C15: =C14/C$6 -> 0.079112272 | D15: =D14/D$6 -> 0.079021565 | E15: =E14/E$6 -> 0.094956995 | F15: =F14/F$6 -> 0.11826328 | G15: =G14/G$6 -> 0.1200582 | H15: =H14/H$6 -> 0.070127191 | I15: =I14/I$6 -> 0.083414679 | J15: =J14/J$6 -> 0.081953945 | ... N15: =N14/N$6 -> 0.12850607 | P15: =P14/P$6 -> 0.093669998 | Q15: =Q14/Q$6 -> 0.089119404 | R15: =R14/R$6 -> 0.12152085
B16: 디지털 솔루션 | C16: 174 | D16: 195 | E16: 171 | F16: 167 | G16: 198 | H16: 220 | I16: =Digital!I6 -> 230.36244 | J16: =Digital!J6 -> 233.68689 | K16: =Digital!K6 -> 230.90576 | L16: =Digital!L6 -> 232.45384 | M16: =Digital!M6 -> 232.56465 | N16: =Digital!N6 -> 232.03138 | P16: =SUM(C16:F16) -> 707 | Q16: =SUM(G16:J16) -> 882.04932 | R16: =SUM(K16:N16) -> 927.95562
B17: of Revenue(%) | C17: =C16/C$6 -> 0.045430809 | D17: =D16/D$6 -> 0.044535275 | E17: =E16/E$6 -> 0.037072252 | F17: =F16/F$6 -> 0.036040086 | G17: =G16/G$6 -> 0.040774482 | H17: =H16/H$6 -> 0.047036531 | I17: =I16/I$6 -> 0.04907732 | J17: =J16/J$6 -> 0.048352983 | ... N17: =N16/N$6 -> 0.042163051 | P17: =P16/P$6 -> 0.040504397 | Q17: =Q16/Q$6 -> 0.046277514 | R17: =R16/R$6 -> 0.043832781
B18: 벙커링 | C18: 1661 | D18: 1777 | E18: 1812 | F18: 1806 | G18: 1914 | H18: 1829 | I18: {=Bunkering!I6:N6} -> 1603.8407 | J18: 1635.8121 | K18: 1597.8636 | L18: 1606.5968 | M18: 1610.5046 | N18: 1604.9799 | P18: =SUM(C18:F18) -> 7056 | Q18: =SUM(G18:J18) -> 6982.6528 | R18: =SUM(K18:N18) -> 6419.945
B19: of Revenue(%) | C19: =C18/C$6 -> 0.43368146 | D19: =D18/D$6 -> 0.40584197 | E19: =E18/E$6 -> 0.39283579 | F19: =F18/F$6 -> 0.38975087 | G19: =G18/G$6 -> 0.39415333 | H19: =H18/H$6 -> 0.39104461 | I19: =I18/I$6 -> 0.34168854 | J19: =J18/J$6 -> 0.33847168 | ... N19: =N18/N$6 -> 0.29164526 | P19: =P18/P$6 -> 0.4042419 | Q19: =Q18/Q$6 -> 0.36635119 | R19: =R18/R$6 -> 0.30325162

Sheet AM
A1: HD현대마린솔루션(443060.KS)
A2: AM Solution Revenue Estimation Sheet
A3: (units in Hundred Millions KRW )
B5: 단위: 억 원 | C5: 2021A | D5: 2022A | E5: 2023A | F5: 2024A | G5: 1Q25 | H5: 2Q25 | I5: 3Q25E | J5: 4Q25E | K5: 1Q26E | L5: 2Q26E | M5: 3Q26E | N5: 4Q26E | P5: Description
B6: AM 솔루션 매출 | C6: =C8+C16+C18+C20 -> 3187.8931 | D6: =D8+D16+D18+D20 -> 4176.0573 | E6: =E8+E16+E18+E20 -> 5652.8282 | F6: =F8+F16+F18+F20 -> 8058 | G6: =G8+G16+G18+G20 -> 2161 | H6: =H8+H16+H18+H20 -> 2300 | I6: =I8+I16+I18+I20 -> 2468.1269 | J6: =J8+J16+J18+J20 -> 2567.3591 | ... N6: =N8+N16+N18+N20 -> 2958.9873 | P6: AM 솔루션 부문 매출의 경우, 엔진, 비엔진, 육상발전, 스마트케어 부문 매출로 구분하여 추정함.
B7: YoY(%) or QoQ(%) | C7: - | D7: =(D6-C6)/C6 -> 0.30997408 | E7: =(E6-D6)/D6 -> 0.35362804 | F7: =(F6-E6)/E6 -> 0.42548113 | G7: - | H7: =(H6-G6)/G6 -> 0.064322073 | I7: =(I6-H6)/H6 -> 0.073098645 | J7: =(J6-I6)/I6 -> 0.040205495 | K7: =(K6-J6)/J6 -> 0.03925851 | L7: =(L6-K6)/K6 -> 0.035520722 | M7: =(M6-L6)/L6 -> 0.035046366 | N7: =(N6-M6)/M6 -> 0.034699629
B8: 엔진 | C8: =D8/(1+D9) -> 1373.0093 | D8: =E8/(1+E9) -> 2045.5467 | E8: =F8/(1+F9) -> 3205.4954 | F8: =매출추정!P10 -> 5323 | G8: 1572 | H8: 1568 | I8: =I10+I13 -> 1722.0397 | J8: =J10+J13 -> 1802.3473 | K8: =K10+K13 -> 1886.4 | L8: =L10+L13 -> 1974.3725 | M8: =M10+M13 -> 2066.4477 | N8: =N10+N13 -> 2162.8167
B9: of AM Solution Revenue(%) | C9: =C8/C$6 -> 0.43069491 | D9: =D8/D$6 -> 0.48982727 | E9: =E8/E$6 -> 0.56706046 | F9: =F8/F$6 -> 0.66058575 | G9: =G8/G$6 -> 0.727441 | H9: =H8/H$6 -> 0.68173913 | I9: =I8/I$6 -> 0.69771118 | J9: =J8/J$6 -> 0.70202382 | ... N9: =N8/N$6 -> 0.73093139
B10: 2행정 엔진 매출 | G10: 572 | H10: =AVERAGE(G10,I10)-79/2 -> 559.7973 | I10: =I12*I22 -> 626.59461 | J10: =J12*J22 -> 655.81593 | K10: =K12*K22 -> 686.4 | L10: =L12*L22 -> 718.41036 | M10: =M12*M22 -> 751.91353 | N10: =N12*N22 -> 786.97912
B11: of AM Solution Revenue(%) | G11: =G10/G$6 -> 0.26469227 | H11: =H10/H$6 -> 0.24339013 | I11: =I10/I$6 -> 0.25387455 | J11: =J10/J$6 -> 0.25544378 | K11: =K10/K$6 -> 0.25725692 | L11: =L10/L$6 -> 0.2600181 | M11: =M10/M$6 -> 0.26292936 | N11: =N10/N$6 -> 0.26596231
B12: 2행정 엔진 대수 | G12: =$C$33 -> 137.375 | H12: =$C$33 -> 137.375 | I12: =$C$33 -> 137.375 | J12: =$C$33 -> 137.375 | K12: =$C$33 -> 137.375 | L12: =$C$33 -> 137.375 | M12: =$C$33 -> 137.375 | N12: =$C$33 -> 137.375
B13: 4행정 엔진 매출 | G13: 1000 | H13: =AVERAGE(G13,I13)-79/2 -> 1008.2226 | I13: =I15*I24 -> 1095.4451 | J13: =J15*J24 -> 1146.5314 | K13: =K15*K24 -> 1200 | L13: =L15*L24 -> 1255.9622 | M13: =M15*M24 -> 1314.5341 | N13: =N15*N24 -> 1375.8376
B14: of AM Solution Revenue(%) | G14: =G13/G$6 -> 0.46274873 | H14: =H13/H$6 -> 0.43835763 | I14: =I13/I$6 -> 0.44383663 | J14: =J13/J$6 -> 0.44658004 | K14: =K13/K$6 -> 0.44974985 | L14: =L13/L$6 -> 0.45457709 | M14: =M13/M$6 -> 0.45966671 | N14: =N13/N$6 -> 0.46496908
B15: 4행정 엔진 대수 | G15: =$C$42 -> 72 | H15: =$C$42 -> 72 | I15: =$C$42 -> 72 | J15: =$C$42 -> 72 | K15: =$C$42 -> 72 | L15: =$C$42 -> 72 | M15: =$C$42 -> 72 | N15: =$C$42 -> 72
B16: 비엔진 | C16: =D16/(1+D17) -> 713.75122 | D16: =E16/(1+E17) -> 860.89039 | E16: =F16/(1+F17) -> 1015.5527 | F16: =매출추정!P11 -> 1162 | G16: 281 | H16: 283 | I16: =((H16-$F$16/4)/$F$16+1)*H16 -> 281.17341 | J16: =((I16-$F$16/4)/$F$16+1)*I16 -> 278.91662 | K16: =((J16-SUM(G16:J16)/4)/SUM(G16:J16)+1)*J16 -> 278.39409 | L16: =((K16-SUM(H16:K16)/4)/SUM(H16:K16)+1)*K16 -> 277.90334 | M16: =((L16-SUM(I16:L16)/4)/SUM(I16:L16)+1)*L16 -> 277.60624 | N16: =((M16-SUM(J16:M16)/4)/SUM(J16:M16)+1)*M16 -> 277.45685 | P16: 비엔진 부문 매출의 경우, 직전 2Y와 직전 2Q 모두 큰 변동성이 존재하지 않고, 동사의 향후 사업 성장여력이 제한된다고 판단됨.
B17: of AM Solution Revenue(%) | C17: =C16/C$6 -> 0.22389434 | D17: =D16/D$6 -> 0.20614908 | E17: =E16/E$6 -> 0.17965391 | F17: =F16/F$6 -> 0.14420452 | G17: =G16/G$6 -> 0.13003239 | H17: =H16/H$6 -> 0.12304348 | I17: =I16/I$6 -> 0.11392178 | J17: =J16/J$6 -> 0.1086395 | ... N17: =N16/N$6 -> 0.093767501 | P17: 따라서, 직전년 분기별 평균 매출에 추정 분기의 성장세를 반영하여 추정함.
B18: 육상발전 | C18: =D18/(1+D19) -> 508.91502 | D18: =E18/(1+E19) -> 579.54072 | E18: =F18/(1+F19) -> 645.74384 | F18: =매출추정!P12 -> 702 | G18: 89 | H18: 200 | I18: =((H18-$F$18/4)/$F$18+1)*H18 -> 206.98006 | J18: =((I18-$F$18/4)/$F$18+1)*I18 -> 216.26174 | K18: =((J18-SUM(G18:J18)/4)/SUM(G18:J18)+1)*J18 -> 227.861 | L18: =((K18-SUM(H18:K18)/4)/SUM(H18:K18)+1)*K18 -> 231.89971 | M18: =((L18-SUM(I18:L18)/4)/SUM(I18:L18)+1)*L18 -> 234.82775 | N18: =((M18-SUM(J18:M18)/4)/SUM(J18:M18)+1)*M18 -> 236.66213 | P18: 육상발전 부문 매출의 경우, 직전 2Y와 직전 2Q 모두 큰 변동성이 존재하지 않고, 동사의 향후 사업 성장여력이 제한된다고 판단됨.
B19: of AM Solution Revenue(%) | C19: =C18/C$6 -> 0.15963993 | D19: =D18/D$6 -> 0.138777 | E19: =E18/E$6 -> 0.11423376 | F19: =F18/F$6 -> 0.087118392 | G19: =G18/G$6 -> 0.041184637 | H19: =H18/H$6 -> 0.086956522 | I19: =I18/I$6 -> 0.08386119 | J19: =J18/J$6 -> 0.084235096 | ... N19: =N18/N$6 -> 0.079980785 | P19: 따라서, 직전년 분기별 평균 매출에 추정 분기의 성장세를 고려하여 추정함.
B20: 스마트케어 | C20: =D20/(1+D21) -> 592.2175 | D20: =E20/(1+E21) -> 690.07945 | E20: =F20/(1+F21) -> 786.03629 | F20: =매출추정!P13 -> 871 | G20: 219 | H20: 249 | I20: =((H20-$F$20/4)/$F$20+1)*H20 -> 257.9337 | J20: =((I20-$F$20/4)/$F$20+1)*I20 -> 269.8335 | K20: =((J20-SUM(G20:J20)/4)/SUM(G20:J20)+1)*J20 -> 275.49475 | L20: =((K20-SUM(H20:K20)/4)/SUM(H20:K20)+1)*K20 -> 278.74887 | M20: =((L20-SUM(I20:L20)/4)/SUM(I20:L20)+1)*L20 -> 280.87326 | N20: =((M20-SUM(J20:M20)/4)/SUM(J20:M20)+1)*M20 -> 282.05163 | P20: 스마트케어 부문 매출의 경우, 직전 2Y와 직전 2Q 모두 큰 변동성이 존재하지 않고, 동사의 향후 사업 성장여력이 제한된다고 판단됨.
B21: of AM Solution Revenue(%) | C21: =C20/C$6 -> 0.18577082 | D21: =D20/D$6 -> 0.16524664 | E21: =E20/E$6 -> 0.13905186 | F21: =F20/F$6 -> 0.10809134 | G21: =G20/G$6 -> 0.10134197 | H21: =H20/H$6 -> 0.10826087 | I21: =I20/I$6 -> 0.10450585 | J21: =J20/J$6 -> 0.10510158 | ... N21: =N20/N$6 -> 0.095320322 | P21: 따라서, 직전년 분기별 평균 매출에 추정 분기의 성장세를 고려하여 추정함.
B22: 2행정 ASP | G22: =C35 -> 4.1637853 | H22: =G22*(1+$O$22) -> 4.357964 | I22: =H22*(1+$O$22) -> 4.5611982 | J22: =I22*(1+$O$22) -> 4.7739103 | K22: =J22*(1+$O$22) -> 4.9965423 | L22: =K22*(1+$O$22) -> 5.2295568 | M22: =L22*(1+$O$22) -> 5.4734379 | N22: =M22*(1+$O$22) -> 5.7286924 | O22: =1.2^0.25-1 -> 0.046635139 | P22: AM 서비스 선박 ASP의 경우, 동사가 컨퍼런스콜에서 발표한 연간 단가 상승률 20%를 분기 가중평균 계산하여 적용함.
B23: YoY(%) | G23: - | H23: =(H22-G22)/G22 -> 0.046635139 | I23: =(I22-H22)/H22 -> 0.046635139 | J23: =(J22-I22)/I22 -> 0.046635139 | K23: =(K22-J22)/J22 -> 0.046635139 | L23: =(L22-K22)/K22 -> 0.046635139 | M23: =(M22-L22)/L22 -> 0.046635139 | N23: =(N22-M22)/M22 -> 0.046635139
B24: 4행정 ASP | G24: =C44 -> 13.888889 | H24: =G24*(1+$O$22) -> 14.536599 | I24: =H24*(1+$O$22) -> 15.214515 | J24: =I24*(1+$O$22) -> 15.924047 | K24: =J24*(1+$O$22) -> 16.666667 | L24: =K24*(1+$O$22) -> 17.443919 | M24: =L24*(1+$O$22) -> 18.257419 | N24: =M24*(1+$O$22) -> 19.108856 | P24: AM 서비스 선박 ASP의 경우, 동사가 컨퍼런스콜에서 발표한 연간 단가 상승률 20%를 분기 가중평균 계산하여 적용함.
B25: YoY(%) | G25: - | H25: =(H24-G24)/G24 -> 0.046635139 | I25: =(I24-H24)/H24 -> 0.046635139 | J25: =(J24-I24)/I24 -> 0.046635139 | K25: =(K24-J24)/J24 -> 0.046635139 | L25: =(L24-K24)/K24 -> 0.046635139 | M25: =(M24-L24)/L24 -> 0.046635139 | N25: =(N24-M24)/M24 -> 0.046635139
C28: 2005 | D28: 2006 | E28: 2007 | F28: 2008 | G28: 2009 | H28: 2010 | I28: 2011 | J28: 2012 | K28: 2013 | L28: 2014 | M28: 2015 | N28: 2016 | O28: 2017 | P28: 2018 | Q28: 2019 | R28: 2020 | S28: 2021 | T28: 2022 | U28: 2023 | V28: 2024 | W28: 2025 | X28: Total
B29: HD 조선 3사 2행정 연도별 선박 대수 | C29: 140 | D29: 152 | E29: 160 | F29: 186 | G29: 197 | H29: 175 | I29: 220 | J29: 203 | K29: 163 | L29: 148 | M29: 183 | N29: 167 | O29: 131 | P29: 100 | Q29: 145 | R29: 128 | S29: 128 | T29: 131 | U29: 130 | V29: 144 | W29: 102 | X29: 3233
B31: '25~'26년 AM 선박 예상 대수 | C31: =(C29+G29+H29+L29+M29+R29+S29) -> 1099 | E31: '25~'26년, 총 8개 분기간 '05년, '09년, '10년, '14년, '15년, '20년, '21년 인도된 2행정 선박들의 점검이 균등하게 이루어질 것으로 추정함.
B32: 선박당 2행정 탑재 수 | C32: 1 | E32: 선박당 2행정 엔진 탑재 수는 1대로 전제함.
B33: 분기당 AM 선박 예상 대수 | C33: =C31*C32/8 -> 137.375 | E33: 선박들의 정기 점검이 약 4~5년 주기로 진행된다는 점 참고.
B34: 1Q25 매출액(억 원) | C34: 572 | E34: 동사의 1Q25 컨퍼런스 콜 내용을 참고함.
B35: 2행정 엔진 AM ASP | C35: =C34/C33 -> 4.1637853 | E35: 1Q25 2행정 부문 매출액을 분기당 AM 선박 예상 대수로 나누어 2행정 엔진 AM ASP를 추정함.
C37: 2005 | D37: 2006 | E37: 2007 | F37: 2008 | G37: 2009 | H37: 2010 | I37: 2011 | J37: 2012 | K37: 2013 | L37: 2014 | M37: 2015 | N37: 2016 | O37: 2017 | P37: 2018 | Q37: 2019 | R37: 2020 | S37: 2021 | T37: 2022 | U37: 2023 | V37: 2024 | W37: 2025 | X37: Total
B38: HD 조선 3사 4행정 연도별 선박 대수 | C38: 2 | D38: 2 | E38: 1 | F38: 5 | G38: 21 | H38: 20 | I38: 20 | J38: 8 | K38: 17 | L38: 24 | M38: 15 | N38: 7 | O38: 5 | P38: 10 | Q38: 7 | R38: 8 | S38: 6 | T38: 6 | U38: 10 | V38: 6 | W38: 1 | X38: 201
B40: '25~'26년 AM 선박 예상 대수 | C40: =(C38+G38+H38+L38+M38+R38+S38) -> 96 | E40: '25~'26년, 총 8개 분기간 '05년, '09년, '10년, '14년, '15년, '20년, '21년 인도된 4행정 선박들의 점검이 균등하게 이루어질 것으로 추정함.
B41: 선박당 4행정 탑재 수 | C41: 6 | E41: 선박당 4행정 엔진 탑재 수는 6대로 전제함.
B42: 분기당 AM 선박 예상 대수 | C42: =C40*C41/8 -> 72 | E42: 선박들의 정기 점검이 약 4~5년 주기로 진행된다는 점 참고.
B43: 1Q25 매출액(억 원) | C43: 1000 | E43: 동사의 1Q25 컨퍼런스 콜 내용을 참고함.
B44: 4행정 엔진 AM ASP | C44: =C43/C42 -> 13.888889 | E44: 1Q25 4행정 부문 매출액을 분기당 AM 선박 예상 대수로 나누어 4행정 엔진 AM ASP를 추정함.
C47: 2005 | D47: 2006 | E47: 2007 | F47: 2008 | G47: 2009 | H47: 2010 | I47: 2011 | J47: 2012 | K47: 2013 | L47: 2014 | M47: 2015 | N47: 2016 | O47: 2017 | P47: 2018 | Q47: 2019 | R47: 2020 | S47: 2021 | T47: 2022 | U47: 2023 | V47: 2024 | W47: 2025 | X47: Total
B48: HD 조선 3사 2행정 연도별 선박 대수 | C48: 140 | D48: 152 | E48: 160 | F48: 186 | G48: 197 | H48: 175 | I48: 220 | J48: 203 | K48: 163 | L48: 148 | M48: 183 | N48: 167 | O48: 131 | P48: 100 | Q48: 145 | R48: 128 | S48: 128 | T48: 131 | U48: 130 | V48: 144 | W48: 102 | X48: 3233
B49: HD 조선 3사 4행정 연도별 선박 대수 | C49: 2 | D49: 2 | E49: 1 | F49: 5 | G49: 21 | H49: 20 | I49: 20 | J49: 8 | K49: 17 | L49: 24 | M49: 15 | N49: 7 | O49: 5 | P49: 10 | Q49: 7 | R49: 8 | S49: 6 | T49: 6 | U49: 10 | V49: 6 | W49: 1 | X49: 201

Sheet Retrofit
A1: HD현대마린솔루션(443060.KS)
A2: Retrofit Revenue Estimation Sheet
A3: (units in Hundred Millions KRW & Millions USD)
B5: 단위: 억 원 | C5: 2021A | D5: 2022A | E5: 2023A | F5: 2024A | G5: 1Q25 | H5: 2Q25 | I5: 3Q25E | J5: 4Q25E | K5: 1Q26E | L5: 2Q26E | M5: 3Q26E | N5: 4Q26E | P5: Description
B6: 친환경 솔루션 매출 | C6: 1530 | D6: 1940 | E6: 1690 | F6: =매출추정!P14 -> 1635 | G6: =매출추정!G14 -> 583 | H6: =매출추정!H14 -> 328 | I6: =I8+I16+I22+I24+I26 -> 391.53745 | J6: =J8+J16+J22+J24+J26 -> 396.0782 | K6: =K8+K16+K22+K24+K26 -> 589.45501 | L6: =L8+L16+L22+L24+L26 -> 590.7023 | M6: =M8+M16+M22+M24+M26 -> 685.28887 | N6: =N8+N16+N22+N24+N26 -> 707.19361 | P6: 친환경 솔루션 부문 매출의 경우, LNGC 부문 매출, 엔진 개조 부문 매출, 기타 매출, BWTS, EGCS 부문 매출로 구분하여 추정함.
B7: YoY(%) or QoQ(%) | C7: - | D7: =(D6-C6)/C6 -> 0.26797386 | E7: =(E6-D6)/D6 -> -0.12886598 | F7: =(F6-E6)/E6 -> -0.032544379 | G7: - | H7: =(H6-G6)/G6 -> -0.4373928 | I7: =(I6-H6)/H6 -> 0.19371173 | J7: =(J6-I6)/I6 -> 0.011597227 | K7: =(K6-J6)/J6 -> 0.48822889 | L7: =(L6-K6)/K6 -> 0.0021159973 | M7: =(M6-L6)/L6 -> 0.16012562 | N7: =(N6-M6)/M6 -> 0.03196424
B8: LNGC | I8: =I10+I14+I12 -> 185.29333 | J8: =J10+J14+J12 -> 187.44222 | K8: =K10+K14+K12 -> 446.43967 | L8: =L10+L14+L12 -> 446.6699 | M8: =M10+M14+M12 -> 471.45383 | N8: =N10+N14+N12 -> 493.96858 | P8: LNGC 부문 매출의 경우, 재액화, FSRU, FSU로 구분하여 추정함.
B9: YoY(%) or QoQ(%) | I9: - | J9: =(J8-I8)/I8 -> 0.011597227 | K9: =(K8-J8)/J8 -> 1.3817455 | L9: =(L8-K8)/K8 -> 0.00051571953 | M9: =(M8-L8)/L8 -> 0.055486006 | N9: =(N8-M8)/M8 -> 0.047755989
B10: 재액화 | I10: =I35*'환율&원유'!I7/100 -> 162.13167 | J10: =J35*'환율&원유'!J7/100 -> 164.01194 | K10: =K35*'환율&원유'!K7/100 -> 184.40074 | L10: =L35*'환율&원유'!L7/100 -> 208.92611 | M10: =M35*'환율&원유'!M7/100 -> 232.31461 | N10: =N35*'환율&원유'!N7/100 -> 231.65189 | P10: 재액화 부문 수주 잔고에서 매출로 전환되는 금액에 환율을 고려하여 추정함.
B11: of Retrofit Revenue(%) | I11: =I10/I$6 -> 0.41408981 | J11: =J10/J$6 -> 0.41408981 | K11: =K10/K$6 -> 0.31283259 | L11: =L10/L$6 -> 0.35369104 | M11: =M10/M$6 -> 0.33900245 | N11: =N10/N$6 -> 0.32756502
B12: FSU | I12: =I37*'환율&원유'!I7/100 -> 23.161667 | J12: =J37*'환율&원유'!J7/100 -> 23.430278 | K12: =K37*'환율&원유'!K7/100 -> 23.050093 | L12: =L37*'환율&원유'!L7/100 -> 46.428025 | M12: =M37*'환율&원유'!M7/100 -> 46.462922 | N12: =N37*'환율&원유'!N7/100 -> 69.495566 | P12: FSU 부문 수주 잔고에서 매출로 전환되는 금액에 환율을 고려하여 추정함.
B13: of Retrofit Revenue(%) | I13: =I12/I$6 -> 0.059155687 | J13: =J12/J$6 -> 0.059155687 | K13: =K12/K$6 -> 0.039104074 | L13: =L12/L$6 -> 0.078598009 | M13: =M12/M$6 -> 0.067800491 | N13: =N12/N$6 -> 0.098269505
B14: FSRU | I14: 0 | J14: 0 | K14: =K39*'환율&원유'!J7/100 -> 238.98883 | L14: =L39*'환율&원유'!K7/100 -> 191.31577 | M14: =M39*'환율&원유'!L7/100 -> 192.6763 | N14: =N39*'환율&원유'!M7/100 -> 192.82113 | P14: FSRU 부문 수주 잔고에서 매출로 전환되는 금액에 환율을 고려하여 추정함.
B15: of Retrofit Revenue(%) | I15: =I14/I$6 -> 0 | J15: =J14/J$6 -> 0 | K15: =K14/K$6 -> 0.40544033 | L15: =L14/L$6 -> 0.32387849 | M15: =M14/M$6 -> 0.28116071 | N15: =N14/N$6 -> 0.27265677
B16: 엔진 개조 | I16: =I20+I18 -> 74.222614 | J16: =J20+J18 -> 75.08339 | K16: =K20+K18 -> 73.865069 | L16: =L20+L18 -> 74.390358 | M16: =M20+M18 -> 144.14066 | N16: =N20+N18 -> 143.72947 | P16: 엔진 개조 부문 매출의 경우, EPLO, D/F로 구분하여 추정함.
B17: YoY(%) or QoQ(%) | I17: - | J17: =(J16-I16)/I16 -> 0.011597227 | K17: =(K16-J16)/J16 -> -0.016226235 | L17: =(L16-K16)/K16 -> 0.0071114575 | M17: =(M16-L16)/L16 -> 0.93762551 | N17: =(N16-M16)/M16 -> -0.0028526958
B18: EPLO | I18: =I43*'환율&원유'!I7/100 -> 74.222614 | J18: =J43*'환율&원유'!J7/100 -> 75.08339 | K18: =K43*'환율&원유'!K7/100 -> 73.865069 | L18: =L43*'환율&원유'!L7/100 -> 74.390358 | M18: =M43*'환율&원유'!M7/100 -> 74.446272 | N18: =N43*'환율&원유'!N7/100 -> 74.2339 | P18: EPLO 부문 수주 잔고에서 매출로 전환되는 금액에 환율을 고려하여 추정함.
B19: of Retrofit Revenue(%) | I19: =I18/I$6 -> 0.18956709 | J19: =J18/J$6 -> 0.18956709 | K19: =K18/K$6 -> 0.12531078 | L19: =L18/L$6 -> 0.12593545 | M19: =M18/M$6 -> 0.10863488 | N19: =N18/N$6 -> 0.1049697
B20: D/F | I20: 0 | J20: 0 | K20: 0 | L20: 0 | M20: =M45*'환율&원유'!M7/100 -> 69.694383 | N20: =N45*'환율&원유'!N7/100 -> 69.495566 | P20: D/F 부문 수주 잔고에서 매출로 전환되는 금액에 환율을 고려하여 추정함.
B21: of Retrofit Revenue(%) | I21: =I20/I$6 -> 0 | J21: =J20/J$6 -> 0 | K21: =K20/K$6 -> 0 | L21: =L20/L$6 -> 0 | M21: =M20/M$6 -> 0.10170074 | N21: =N20/N$6 -> 0.098269505
B22: 기타 | I22: =I47*'환율&원유'!I7/100 -> 69.485 | J22: =J47*'환율&원유'!J7/100 -> 70.290833 | K22: =K47*'환율&원유'!K7/100 -> 69.150278 | L22: =L47*'환율&원유'!L7/100 -> 69.642037 | M22: =M47*'환율&원유'!M7/100 -> 69.694383 | N22: =N47*'환율&원유'!N7/100 -> 69.495566 | P22: 기타 부문 수주 잔고에서 매출로 전환되는 금액에 환율을 고려하여 추정함.
B23: of Retrofit Revenue(%) | I23: =I22/I$6 -> 0.17746706 | J23: =J22/J$6 -> 0.17746706 | K23: =K22/K$6 -> 0.11731222 | L23: =L22/L$6 -> 0.11789701 | M23: =M22/M$6 -> 0.10170074 | N23: =N22/N$6 -> 0.098269505
B24: BWTS | I24: =I49*'환율&원유'!I14/100 -> 0 | J24: =J49*'환율&원유'!J14/100 -> 0 | K24: =K49*'환율&원유'!K14/100 -> 0 | L24: =L49*'환율&원유'!L14/100 -> 0 | M24: =M49*'환율&원유'!M14/100 -> 0 | N24: =N49*'환율&원유'!N14/100 -> 0 | P24: BWTS 부문 수주 잔고에서 매출로 전환되는 금액에 환율을 고려하여 추정함.
B25: of Retrofit Revenue(%) | I25: =I24/I$6 -> 0 | J25: =J24/J$6 -> 0 | K25: =K24/K$6 -> 0 | L25: =L24/L$6 -> 0 | M25: =M24/M$6 -> 0 | N25: =N24/N$6 -> 0
B26: EGCS | I26: =I51*'환율&원유'!I7/100 -> 62.5365 | J26: =J51*'환율&원유'!J7/100 -> 63.26175 | K26: =K51*'환율&원유'!K7/100 -> 0 | L26: =L51*'환율&원유'!L7/100 -> 0 | M26: =M51*'환율&원유'!M7/100 -> 0 | N26: =N51*'환율&원유'!N7/100 -> 0 | P26: EGCS 부문 수주 잔고에서 매출로 전환되는 금액에 환율을 고려하여 추정함.
B27: of Retrofit Revenue(%) | I27: =I26/I$6 -> 0.15972035 | J27: =J26/J$6 -> 0.15972035 | K27: =K26/K$6 -> 0 | L27: =L26/L$6 -> 0 | M27: =M26/M$6 -> 0 | N27: =N26/N$6 -> 0
B30: 단위: Mn $ | C30: 2021A | D30: 2022A | E30: 2023A | F30: 2024A | G30: 1Q25 | H30: 2Q25 | I30: 3Q25E | J30: 4Q25E | K30: 1Q26E | L30: 2Q26E | M30: 3Q26E | N30: 4Q26E | Q30: 수주 추정 Logic
B31: 친환경 솔루션 수주 잔고 | C31: 108 | D31: 82 | E31: 106 | F31: 125 | G31: 98 | H31: 146 | I31: =I48+I50+I33+I41+I46 -> 138.35417 | J31: =J48+J50+J33+J41+J46 -> 239.70833 | K31: =K48+K50+K33+K41+K46 -> 257.39583 | L31: =L48+L50+L33+L41+L46 -> 259.91667 | M31: =M48+M50+M33+M41+M46 -> 275.77083 | N31: =N48+N50+N33+N41+N46 -> 374.95833 | Q31: 수주 잔고의 경우, 매출 부문과 동일한 기준으로 구분함.
B32: YoY(%) or QoQ(%) | C32: - | D32: =(D31-C31)/C31 -> -0.24074074 | E32: =(E31-D31)/D31 -> 0.29268293 | F32: =(F31-E31)/E31 -> 0.17924528 | G32: - | H32: =(H31-G31)/G31 -> 0.48979592 | I32: =(I31-H31)/H31 -> -0.052368721 | J32: =(J31-I31)/I31 -> 0.7325704 | K32: =(K31-J31)/J31 -> 0.073787589 | L32: =(L31-K31)/K31 -> 0.0097936058 | M32: =(M31-L31)/L31 -> 0.060997114 | N32: =(N31-M31)/M31 -> 0.35967364
B33: LNGC 수주 잔고 | C33: 0 | D33: 0 | E33: 62 | F33: 118 | G33: 97 | H33: =H34+H36+H38 -> 80 | I33: =I34+I36+I38 -> 66.666667 | J33: =J34+J36+J38 -> 153.33333 | K33: =K34+K36+K38 -> 156.33333 | L33: =L34+L36+L38 -> 144.16667 | M33: =M34+M36+M38 -> 145.33333 | N33: =N34+N36+N38 -> 229.83333
B34: 재액화 | D34: 현재 7척 수주 잔고 | H34: 70 | I34: =H34-I35 -> 58.333333 | J34: =I34-J35 -> 46.666667 | K34: =J34+2*$P$35-K35 -> 53.333333 | L34: =K34+2*$P$35-L35 -> 58.333333 | M34: =L34+2*$P$35-M35 -> 61.666667 | N34: =M34+2*$P$35-N35 -> 65 | O34: 연간 재액화 Full CAPA(척) | P34: 10 | Q34: 동사의 재액화 CAPA는 충분하나, 선주들의 환경 규제 대비가 본격 개시되는 '26년부터 분기당 2척씩 수주할 것으로 추정함. 보유 중인 수주는 Full CAPA로 소진될 것으로 추정함.
B35: 매출 전환 | D35: 표준 공기 1.5년(6Q) | I35: =$P$35/6*7 -> 11.666667 | J35: =$P$35/6*7 -> 11.666667 | K35: =$P$35/6*8 -> 13.333333 | L35: =$P$35/6*9 -> 15 | M35: =$P$35/6*10 -> 16.666667 | N35: =$P$35/6*10 -> 16.666667 | O35: 재액화 ASP(Mn $) | P35: 10 | Q35: 2Q25 기준, 수주 잔고를 수주 척수로 나누어 ASP를 계산함. IR측 재액화 ASP 답변과 단가가 유사하므로 합리적이라 판단됨.
B36: FSU | D36: 현재 1척 수주 잔고 | H36: 10 | I36: =H36-I37 -> 8.3333333 | J36: =I36-J37 -> 6.6666667 | K36: =J36-K37+$P$37*$P$36/2 -> 20 | L36: =K36-L37 -> 16.666667 | M36: =L36-M37+$P$37*$P$36/2 -> 28.333333 | N36: =M36-N37 -> 23.333333 | O36: 연간 FSU Full CAPA(척) | P36: 3 | Q36: 동사의 엔지니어링 설비 관련 제한사항으로, 연간 FSU Full CAPA는 3척으로 확인됨.
B37: 매출 전환 | D37: 표준 공기 1.5년(6Q) | I37: =$H$36/6 -> 1.6666667 | J37: =$H$36/6 -> 1.6666667 | K37: =$H$36/6 -> 1.6666667 | L37: =$H$36/6*2 -> 3.3333333 | M37: =$H$36/6*2 -> 3.3333333 | N37: =$H$36/6*3 -> 5 | O37: FSU ASP(Mn $) | P37: 10 | Q37: 동사의 FSU Full CAPA와 관련 파이프라인 및 에너지 수요를 반영하여, 반기당 1척(1천만 불)씩 수주할 것으로 추정함. ASP의 경우 IR측 답변을 참고함.
B38: FSRU | D38: 4Q25 1척 수주 전망 | J38: =$P$38/2*$P$39 -> 100 | K38: =J38-K39 -> 83 | L38: =K38-L39 -> 69.166667 | M38: =L38-M39 -> 55.333333 | N38: =M38-N39+$P$38/2*$P$39 -> 141.5 | O38: 연간 FSRU Full CAPA(척) | P38: 2 | Q38: 동사의 설비 내 재기화 장치 관련 제한사항으로, 연간 FSRU Full CAPA는 2척으로 확인됨.
B39: 매출 전환 | D39: 표준 공기 1.5년(6Q) | K39: 17 | L39: =$K$38/6 -> 13.833333 | M39: =$K$38/6 -> 13.833333 | N39: =$K$38/6 -> 13.833333 | O39: FSRU ASP(Mn $) | P39: 100 | Q39: '26년에는 1척 수주 후, '27년부터는 Full CAPA가 가동될 것으로 전망함. ASP의 경우, IR측 답변을 참고함.
B40: 엔진 개조 수주 잔고 | C40: 0 | D40: 0 | E40: 62 | F40: 118 | G40: 97 | H40: =H44+H41 -> 47 | I40: =I44+I41 -> 61.6875 | J40: =J44+J41 -> 76.375 | K40: =K44+K41 -> 91.0625 | L40: =L44+L41 -> 105.75 | M40: =M44+M41 -> 150.4375 | N40: =N44+N41 -> 160.125
B41: EPLO | D41: 현재 88척 수주 잔고 | H41: 47 | I41: =H41-I43+$P$42*150/4 -> 61.6875 | J41: =I41-J43+$P$42*150/4 -> 76.375 | K41: =J41-K43+$P$42*150/4 -> 91.0625 | L41: =K41-L43+$P$42*150/4 -> 105.75 | M41: =L41-M43+$P$42*150/4 -> 120.4375 | N41: =M41-N43+$P$42*150/4 -> 135.125 | O41: 연간 EPLO Full CAPA(척) | P41: 40 | Q41: 엔진 Retrofit 관련 동사의 집중 사업부이므로, '25년 수주 목표 150척이 '26년에도 동일할 것으로 전제하고 이를 분기로 나눠 수주 잔고를 추정함.
B42: 선박수(척) | D42: 표준 공기 6개월(2Q) | H42: 88 | I42: =H42-$P$41/4+30 -> 108 | J42: =I42-$P$41/4+30 -> 128 | K42: =J42-$P$41/4+30 -> 148 | L42: =K42-$P$41/4+30 -> 168 | M42: =L42-$P$41/4+30 -> 188 | N42: =M42-$P$41/4+30 -> 208 | O42: EPLO ASP(Mn $) | P42: =H41/H42 -> 0.53409091 | Q42: 2Q25 기준, 수주 잔고를 수주 척수로 나누어 ASP를 계산함. IR측 EPLO ASP 답변과 단가가 유사하므로 합리적이라 판단됨.
B43: 매출 전환 | D43: 연간 150척 수주 목표 | I43: =$P$41/4*$P$42 -> 5.3409091 | J43: =$P$41/4*$P$42 -> 5.3409091 | K43: =$P$41/4*$P$42 -> 5.3409091 | L43: =$P$41/4*$P$42 -> 5.3409091 | M43: =$P$41/4*$P$42 -> 5.3409091 | N43: =$P$41/4*$P$42 -> 5.3409091 | O43: 분기당 EPLO 수주(척) | P43: =150/4 -> 37.5 | Q43: 동사의 EPLO 연간 수주 목표인 150척을 분기로 나누어 계산함.
B44: D/F | D44: 3Q26 1건 수주 전망 | M44: 30 | N44: =M44-N45 -> 25 | O44: 연간 D/F Full CAPA(척) | P44: - | Q44: D/F Full CAPA는 '27년부터 본격 가동될 것으로 전망되므로 추정하지 않음.
B45: 매출 전환 | D45: 표준 공기 1.5년(6Q) | M45: =$M$44/6 -> 5 | N45: =$M$44/6 -> 5 | O45: D/F ASP(Mn $) | P45: 30 | Q45: 선주들의 규제 대비가 본격 개시되는 '26년 하반기에 1건을 수주한 후, '27년부터 수주가 급등할 것으로 전망함. ASP의 경우, IR측 답변을 참고함.
B46: 기타 | H46: 10 | I46: =H46 -> 10 | J46: =I46 -> 10 | K46: =J46 -> 10 | L46: =K46 -> 10 | M46: =L46 -> 10 | N46: =M46 -> 10 | Q46: 기타 부문은 대부분 변동성이 크지 않은 구독형 매출에서 발생하므로 Flat 적용함.
B47: 매출 전환 | I47: 5 | J47: 5 | K47: 5 | L47: 5 | M47: 5 | N47: 5
B48: BWTS | C48: 63 | D48: 40 | E48: 18 | F48: 3 | G48: 1 | H48: 0 | I48: 0 | J48: 0 | K48: 0 | L48: 0 | M48: 0 | N48: 0 | Q48: BWTS의 경우, 2Q25부터 수주가 존재하지 않는 점과 현재 환경 규제 대응 방식으로 부적절하다고 판단되므로, 향후 수주가 존재하지 않을 것으로 추정함.
B49: 전환 | H49: 1
B50: EGCS | C50: 45 | D50: 42 | E50: 26 | F50: 4 | G50: 0 | H50: 9 | I50: 0 | J50: 0 | K50: 0 | L50: 0 | M50: 0 | N50: 0 | Q50: EGCS의 경우, '24년부터 수주가 급격히 감소한 점과 현재 환경 규제 대응 방식으로 부적절하다고 판단되므로, 향후 수주가 존재하지 않을 것으로 추정함.
B51: 매출 전환 | I51: 4.5 | J51: 4.5 | K51: 0 | L51: 0 | M51: 0 | N51: 0 | Q51: 현재 보유 중인 수주 잔고는 '25년 남은 두 분기에 걸쳐 매출로 전환될 것으로 추정함.

Sheet Digital
A1: HD현대마린솔루션(443060.KS)
A2: Digital Soultion Revenue Estimation Sheet
A3: (units in Hundred Millions KRW & Millions USD)
B5: 단위: 억 원 | C5: 2021A | D5: 2022A | E5: 2023A | F5: 2024A | G5: 1Q25 | H5: 2Q25 | I5: 3Q25E | J5: 4Q25E | K5: 1Q26E | L5: 2Q26E | M5: 3Q26E | N5: 4Q26E | P5: Description
B6: 디지털 솔루션 매출 | C6: =D6/(1+D7) -> 487.30777 | D6: =E6/(1+E7) -> 453.68353 | E6: =F6/(1+F7) -> 622.90749 | F6: 707 | G6: =매출추정!G16 -> 198 | H6: =매출추정!H16 -> 220 | I6: =I8+I10+I12 -> 230.36244 | J6: =J8+J10+J12 -> 233.68689 | K6: =K8+K10+K12 -> 230.90576 | L6: =L8+L10+L12 -> 232.45384 | M6: =M8+M10+M12 -> 232.56465 | N6: =N8+N10+N12 -> 232.03138 | P6: 디지털 솔루션의 경우, 주요 제품인 Shaft Generator, 그 외 수주가 전환됨에 따라 인식되는 매출, 기타 매출로 구분하여 추정함.
B7: YoY(%) or QoQ(%) | C7: - | D7: -0.069 | E7: 0.373 | F7: 0.135 | G7: - | H7: =(H6-G6)/G6 -> 0.11111111 | I7: =(I6-H6)/H6 -> 0.047101978 | J7: =(J6-I6)/I6 -> 0.014431394 | K7: =(K6-J6)/J6 -> -0.011901082 | L7: =(L6-K6)/K6 -> 0.0067043649 | M7: =(M6-L6)/L6 -> 0.00047671057 | N7: =(N6-M6)/M6 -> -0.0022929968
B8: Shaft Generator | H8: =H19 -> 100.72558 | I8: =I19 -> 103.41953 | J8: =J19 -> 104.61891 | K8: =K19 -> 102.92134 | L8: =L19 -> 103.65326 | M8: =M19 -> 103.73117 | N8: =N19 -> 103.43526
B9: of Retrofit Revenue(%) | I9: =I8/I$6 -> 0.44894271 | J9: =J8/J$6 -> 0.44768843 | K9: =K8/K$6 -> 0.44572879 | L9: =L8/L$6 -> 0.44590903 | M9: =M8/M$6 -> 0.44603156 | N9: =N8/N$6 -> 0.44578135
B10: 그외 수주 전환 매출 | H10: =H21*'환율&원유'!H7/100 -> 67.675 | I10: =I21*'환율&원유'!I7/100 -> 75.343482 | J10: =J21*'환율&원유'!J7/100 -> 77.468553 | K10: =K21*'환율&원유'!K7/100 -> 76.384997 | L10: =L21*'환율&원유'!L7/100 -> 77.201153 | M10: =M21*'환율&원유'!M7/100 -> 77.234056 | N10: =N21*'환율&원유'!N7/100 -> 76.9967
B11: of Retrofit Revenue(%) | I11: =I10/I$6 -> 0.32706496 | J11: =J10/J$6 -> 0.33150578 | K11: =K10/K$6 -> 0.33080594 | L11: =L10/L$6 -> 0.33211391 | M11: =M10/M$6 -> 0.33209715 | N11: =N10/N$6 -> 0.33183744
B12: 기타 | H12: =H6-H8-H10 -> 51.599419 | I12: =H12 -> 51.599419 | J12: =I12 -> 51.599419 | K12: =J12 -> 51.599419 | L12: =K12 -> 51.599419 | M12: =L12 -> 51.599419 | N12: =M12 -> 51.599419
B13: of Retrofit Revenue(%) | I13: =I12/I$6 -> 0.22399233 | J13: =J12/J$6 -> 0.22080579 | K13: =K12/K$6 -> 0.22346527 | L13: =L12/L$6 -> 0.22197706 | M13: =M12/M$6 -> 0.22187129 | N13: =N12/N$6 -> 0.22238121
B15: 단위: Mn $ | C15: 2021A | D15: 2022A | E15: 2023A | F15: 2024A | G15: 1Q25 | H15: 2Q25 | I15: 3Q25E | J15: 4Q25E | K15: 1Q26E | L15: 2Q26E | M15: 3Q26E | N15: 4Q26E | P15: *S/G는 Shaft Generator를 의미함. HD현대그룹의 신조 물량에 탑재되는 제품. 따라서 인도 예정 물량이 곧 S/G의 매출과 이어짐.
B16: 디지털 솔루션 수주 잔고 | C16: 65 | D16: 94 | E16: 112 | F16: 134 | G16: 140 | H16: 150 | I16: =H16+10 -> 160 | J16: =I16+10 -> 170 | K16: =J16+10 -> 180 | L16: =K16+10 -> 190 | M16: =L16+10 -> 200 | N16: =M16+10 -> 210 | P16: 디지털 솔루션 수주 잔고의 경우, HD현대그룹의 신조 인도 물량이 '26년까지 큰 변동성이 없다는 점을 고려하여 직전 분기 증가세를 Flat 적용함.
B17: S/G 수주 잔고 | G17: 59 | H17: 64 | I17: =H17+(I16-H16)*H8/H6 -> 68.578436 | J17: =I17+(J16-I16)*I8/I6 -> 73.067863 | K17: =J17+(K16-J16)*J8/J6 -> 77.544747 | L17: =K17+(L16-K16)*K8/K6 -> 82.002035 | M17: =L17+(M16-L16)*L8/L6 -> 86.461125 | N17: =M17+(N16-M16)*M8/M6 -> 90.921441 | P17: S/G 수주 잔고의 경우. 디지털 솔루션 수주 잔고의 증감(HD현대그룹의 신조 인도 물량)과 매우 유사하므로, 디지털 솔루션 수주 잔고에 직전 분기 매출 비중을 곱하여 향후 수주 잔고 증가세를 추정함.
B18: S/G 척수 | H18: 43 | I18: =H18+(I17-H17)/$O$23 -> 46.076136 | J18: =I18+(J17-I17)/$O$23 -> 49.09247 | K18: =J18+(K17-J17)/$O$23 -> 52.100377 | L18: =K18+(L17-K17)/$O$23 -> 55.095117 | M18: =L18+(M17-L17)/$O$23 -> 58.091068 | N18: =M18+(N17-M17)/$O$23 -> 61.087843 | P18: S/G의 선박 수의 경우, 직전 분기 대비 수주 증가분을 ASP로 나누어 선박수 증가세를 추정함.
B19: S/G 매출 | H19: =$O$23*5*'환율&원유'!H7/100 -> 100.72558 | I19: =$O$23*5*'환율&원유'!I7/100 -> 103.41953 | J19: =$O$23*5*'환율&원유'!J7/100 -> 104.61891 | K19: =$O$23*5*'환율&원유'!K7/100 -> 102.92134 | L19: =$O$23*5*'환율&원유'!L7/100 -> 103.65326 | M19: =$O$23*5*'환율&원유'!M7/100 -> 103.73117 | N19: =$O$23*5*'환율&원유'!N7/100 -> 103.43526 | P19: S/G 매출의 경우, 분기당 공사 가능한 선박 수에 ASP와 환율 전망치를 곱하여 추정함.
B20: S/G 제외 수주 잔고 | G20: =G16-G17 -> 81 | H20: =H16-H17 -> 86 | I20: =I16-I17 -> 91.421564 | J20: =J16-J17 -> 96.932137 | K20: =K16-K17 -> 102.45525 | L20: =L16-L17 -> 107.99797 | M20: =M16-M17 -> 113.53887 | N20: =N16-N17 -> 119.07856 | P20: 분기별 수주잔고 차이만큼, 수주가 매출로 전환될 것으로 추정함.
B21: S/G 제외 수주 전환액 | H21: =H20-G20 -> 5 | I21: =I20-H20 -> 5.4215645 | J21: =J20-I20 -> 5.5105729 | K21: =K20-J20 -> 5.5231157 | L21: =L20-K20 -> 5.5427121 | M21: =M20-L20 -> 5.5409097 | N21: =N20-M20 -> 5.5396844
M23: S/G ASP(Mn $): | O23: =H17/H18 -> 1.4883721 | P23: S/G ASP의 경우, 2Q25 기준 수주 잔고와 수주 척수를 이용하여 추정함.
P24: *OceanWise 구독의 경우, 구독 선박 수가 증가세를 보이고 있으나, 관련 매출이 공개되지 않고 그 금액 또한 미미할 것으로 판단되므로 매출에 포함시키지 않음.

Sheet Bunkering
A1: HD현대마린솔루션(443060.KS)
A2: Bunkering Revenue Estimation Sheet
A3: (units in Hundred Millions KRW )
B5: 단위: 억 원 | C5: 2021A | D5: 2022A | E5: 2023A | F5: 2024A | G5: 1Q25 | H5: 2Q25 | I5: 3Q25E | J5: 4Q25E | K5: 1Q26E | L5: 2Q26E | M5: 3Q26E | N5: 4Q26E | P5: Description
B6: 벙커링 매출 | C6: 5210 | D6: 6270 | E6: 5960 | F6: 7056 | G6: 1914 | H6: 1829 | I6: =I8+I14 -> 1603.8407 | J6: =J8+J14 -> 1635.8121 | K6: =K8+K14 -> 1597.8636 | L6: =L8+L14 -> 1606.5968 | M6: =M8+M14 -> 1610.5046 | N6: =N8+N14 -> 1604.9799 | P6: 벙커링의 경우, 출항/기항 선박의 수와 벙커유 판매량에 매우 큰 영향을 받음. 향후 큰 변동폭이 없을 것으로 전망되기에, 상관관계를 이용하여 매출을 추정함.
B7: YoY(%) or QoQ(%) | C7: - | D7: =(D6-C6)/C6 -> 0.20345489 | E7: =(E6-D6)/D6 -> -0.049441786 | F7: =(F6-E6)/E6 -> 0.18389262 | G7: - | H7: =(H6-G6)/G6 -> -0.044409613 | I7: =(I6-H6)/H6 -> -0.12310514 | J7: =(J6-I6)/I6 -> 0.01993426 | K7: =(K6-J6)/J6 -> -0.023198544 | L7: =(L6-K6)/K6 -> 0.0054655159 | M7: =(M6-L6)/L6 -> 0.0024323777 | N7: =(N6-M6)/M6 -> -0.0034304
B8: 출항 선박 매출 | C8: 260 | D8: 310 | E8: 300 | F8: 353 | G8: =$I$25*G10+$I$26 -> 76.023411 | H8: =$I$25*H10+$I$26 -> 76.023411 | I8: =$I$25*I10+$I$26 -> 76.023411 | J8: =$I$25*J10+$I$26 -> 76.023411 | K8: =$I$25*K10+$I$26 -> 59.459866 | L8: =$I$25*L10+$I$26 -> 59.459866 | M8: =$I$25*M10+$I$26 -> 59.459866 | N8: =$I$25*N10+$I$26 -> 59.459866 | P8: 직전 4개년간, 출항 선박 부문 매출과 신규 인도 선박 수 간의 상관계수가 0.8659로 유의미한 상관관계를 갖고 있다고 판단되므로,
B9: of Bunkering Revenue(%) | C9: =C8/C$6 -> 0.049904031 | D9: =D8/D$6 -> 0.049441786 | E9: =E8/E$6 -> 0.05033557 | F9: =F8/F$6 -> 0.050028345 | G9: =G8/G$6 -> 0.039719651 | H9: =H8/H$6 -> 0.041565561 | I9: =I8/I$6 -> 0.047400849 | J9: =J8/J$6 -> 0.046474416 | ... N9: =N8/N$6 -> 0.037047109 | P9: 향후 매출도 동일한 상관계수와 Slope/Intercept를 통해 추정함.
B10: 신규 인도(척) | C10: 119 | D10: 120 | E10: 124 | F10: 130 | G10: =G11+G12+G13 -> 30.75 | H10: =H11+H12+H13 -> 30.75 | I10: =I11+I12+I13 -> 30.75 | J10: =J11+J12+J13 -> 30.75 | K10: =K11+K12+K13 -> 28.25 | L10: =L11+L12+L13 -> 28.25 | M10: =M11+M12+M13 -> 28.25 | N10: =N11+N12+N13 -> 28.25
B11: HD현대중공업(척) | C11: 44 | D11: 37 | E11: 40 | F11: 44 | G11: =$P26/4 -> 11.5 | H11: =$P26/4 -> 11.5 | I11: =$P26/4 -> 11.5 | J11: =$P26/4 -> 11.5 | K11: =$Q26/4 -> 8.75 | L11: =$Q26/4 -> 8.75 | M11: =$Q26/4 -> 8.75 | N11: =$Q26/4 -> 8.75 | P11: HD현대중공업의 신규 인도 선박 수의 경우, Clarksons의 수치를 참조함.
B12: HD현대미포(척) | C12: 45 | D12: 53 | E12: 51 | F12: 55 | G12: =$P27/4 -> 11.5 | H12: =$P27/4 -> 11.5 | I12: =$P27/4 -> 11.5 | J12: =$P27/4 -> 11.5 | K12: =$Q27/4 -> 11.25 | L12: =$Q27/4 -> 11.25 | M12: =$Q27/4 -> 11.25 | N12: =$Q27/4 -> 11.25 | P12: HD현대미포의 신규 인도 선박 수의 경우, Clarksons의 수치를 참조함.
B13: HD현대삼호(척) | C13: 30 | D13: 30 | E13: 33 | F13: 31 | G13: =$P28/4 -> 7.75 | H13: =$P28/4 -> 7.75 | I13: =$P28/4 -> 7.75 | J13: =$P28/4 -> 7.75 | K13: =$Q28/4 -> 8.25 | L13: =$Q28/4 -> 8.25 | M13: =$Q28/4 -> 8.25 | N13: =$Q28/4 -> 8.25 | P13: HD현대삼호의 신규 인도 선박 수의 경우, Clarksons의 수치를 참조함.
B14: 기항 선박 매출 | C14: 4950 | D14: 5960 | E14: 5660 | F14: 6703 | G14: =G16+G19 -> 1837.9766 | H14: =H16+H19 -> 1752.9766 | I14: =I16+I19 -> 1527.8173 | J14: =J16+J19 -> 1559.7887 | K14: =K16+K19 -> 1538.4038 | L14: =L16+L19 -> 1547.1369 | M14: =M16+M19 -> 1551.0448 | N14: =N16+N19 -> 1545.5201 | P14: 직전 4개년간, 기항 선박 부문 매출과 해당 지역 HSFO 벙커량 추정치의 상관계수가 각각 0.9292, 0.9628로 유의미한 상관관계를 갖고 있다고 판단되므로,
B15: of Bunkering Revenue(%) | C15: =C14/C$6 -> 0.95009597 | D15: =D14/D$6 -> 0.95055821 | E15: =E14/E$6 -> 0.94966443 | F15: =F14/F$6 -> 0.94997166 | G15: =G14/G$6 -> 0.96028035 | H15: =H14/H$6 -> 0.95843444 | I15: =I14/I$6 -> 0.95259915 | J15: =J14/J$6 -> 0.95352558 | ... N15: =N14/N$6 -> 0.96295289 | P15: 향후 매출도 동일한 상관계수와 Slope/Intercept를 통해 추정함.
B16: 한국 | C16: 1825 | D16: 2200 | E16: 2080 | F16: 2471.5 | G16: =G6-G8-G19 -> 839.74326 | H16: =H6-H8-H19 -> 792.19277 | I16: =$I$29*I18*'환율&원유'!I6*'환율&원유'!I7/10^3+$I$30 -> 561.15911 | J16: =$I$29*J18*'환율&원유'!J6*'환율&원유'!J7/10^3+$I$30 -> 584.87336 | K16: =$I$29*K18*'환율&원유'!K6*'환율&원유'!K7/10^3+$I$30 -> 570.98845 | L16: =$I$29*L18*'환율&원유'!L6*'환율&원유'!L7/10^3+$I$30 -> 577.4882 | M16: =$I$29*M18*'환율&원유'!M6*'환율&원유'!M7/10^3+$I$30 -> 580.39666 | N16: =$I$29*N18*'환율&원유'!N6*'환율&원유'!N7/10^3+$I$30 -> 576.28486
B17: of Bunkering Revenue(%) | C17: =C16/C$6 -> 0.35028791 | D17: =D16/D$6 -> 0.35087719 | E17: =E16/E$6 -> 0.34899329 | F17: =F16/F$6 -> 0.35026927 | G17: =G16/G$6 -> 0.43873734 | H17: =H16/H$6 -> 0.43312891 | I17: =I16/I$6 -> 0.34988457 | J17: =J16/J$6 -> 0.35754312 | ... N17: =N16/N$6 -> 0.35906047
B18: 한국 기항 HSFO 벙커선 판매량(천 톤) | C18: 1414.464 | D18: 1146.834 | E18: 1304.13 | F18: 1393.7 | G18: =$P$31/4 -> 373.029 | H18: =$P$31/4 -> 373.029 | I18: =$P$31/4 -> 373.029 | J18: =$P$31/4 -> 373.029 | K18: =$Q$31/4 -> 378 | L18: =$Q$31/4 -> 378 | M18: =$Q$31/4 -> 378 | N18: =$Q$31/4 -> 378 | P18: 한국 기항 벙커선 판매량의 경우, Clarksons의 기항 선박수 연간 데이터와 선박당 벙커유 연간 판매량을 곱한 후 분기별로 추정함.
B19: 싱가포르 | C19: 3125 | D19: 3760 | E19: 3570 | F19: 4231.5 | G19: =$I$34*G21*'환율&원유'!G6*'환율&원유'!G7/1000+$I$35 -> 998.23333 | H19: =$I$34*H21*'환율&원유'!H6*'환율&원유'!H7/1000+$I$35 -> 960.78382 | I19: =$I$34*I21*'환율&원유'!I6*'환율&원유'!I7/1000+$I$35 -> 966.65818 | J19: =$I$34*J21*'환율&원유'!J6*'환율&원유'!J7/1000+$I$35 -> 974.91531 | K19: =$I$34*K21*'환율&원유'!K6*'환율&원유'!K7/1000+$I$35 -> 967.4153 | L19: =$I$34*L21*'환율&원유'!L6*'환율&원유'!L7/1000+$I$35 -> 969.6487 | M19: =$I$34*M21*'환율&원유'!M6*'환율&원유'!M7/1000+$I$35 -> 970.64809 | N19: =$I$34*N21*'환율&원유'!N6*'환율&원유'!N7/1000+$I$35 -> 969.23522
B20: of Bunkering Revenue(%) | C20: =C19/C$6 -> 0.59980806 | D20: =D19/D$6 -> 0.59968102 | E20: =E19/E$6 -> 0.59899329 | F20: =F19/F$6 -> 0.59970238 | G20: =G19/G$6 -> 0.52154301 | H20: =H19/H$6 -> 0.52530553 | I20: =I19/I$6 -> 0.60271458 | J20: =J19/J$6 -> 0.59598246 | ... N20: =N19/N$6 -> 0.60389242
B21: 싱가포르 기항 HSFO 벙커선 판매량(천 톤) | C21: 0 | D21: 4664 | E21: 5572 | F21: 6718 | G21: =$P$32/4 -> 1640 | H21: =$P$32/4 -> 1640 | I21: =$P$32/4 -> 1640 | J21: =$P$32/4 -> 1640 | K21: =$Q$32/4 -> 1640 | L21: =$Q$32/4 -> 1640 | M21: =$Q$32/4 -> 1640 | N21: =$Q$32/4 -> 1640 | P21: 싱가포르 기항 벙커선 판매량의 경우, Clarksons의 기항 선박수 연간 데이터와 선박당 벙커유 연간 판매량을 곱한 후 분기별로 추정함.
B24: 출항 선박 상관관계 | C24: 2021A | D24: 2022A | E24: 2023A | F24: 2024A | H24: 상관계수 | I24: =CORREL(C25:F25,C26:F26) -> 0.86585071 | L24: HD현대그룹 조선 3사 인도 선박 수 전망 | P24: 2025E | Q24: 2026E
B25: 출항 선박 매출 | C25: =C8 -> 260 | D25: =D8 -> 310 | E25: =E8 -> 300 | F25: =F8 -> 353 | H25: Slope | I25: =SLOPE(C25:F25,C26:F26) -> 6.6254181 | L25: 신규 인도(척) | P25: =P26+P27+P28 -> 123 | Q25: =Q26+Q27+Q28 -> 113
B26: 신규 인도(척) | C26: =C10 -> 119 | D26: =D10 -> 120 | E26: =E10 -> 124 | F26: =F10 -> 130 | H26: Intercept | I26: =INTERCEPT(C25:F25,C26:F26)/4 -> -127.70819 | L26: HD현대중공업(척) | P26: 46 | Q26: 35
L27: HD현대미포(척) | P27: 46 | Q27: 45
B28: 한국 기항 선박 상관관계 | C28: 2021A | D28: 2022A | E28: 2023A | F28: 2024A | H28: 상관계수 | I28: =CORREL(C29:F29,C30:F30) -> 0.92917944 | L28: HD현대삼호(척) | P28: 31 | Q28: 33
B29: 한국 기항 선박 매출 | C29: =C16 -> 1825 | D29: =D16 -> 2200 | E29: =E16 -> 2080 | F29: =F16 -> 2471.5 | H29: Slope | I29: =SLOPE(C29:F29,C30:F30) -> 0.01588041
B30: 한국 HSFO 벙커량 추정치 | C30: =C18*'환율&원유'!C6*'환율&원유'!C7/1000 -> 115392.46 | D30: =D18*'환율&원유'!D6*'환율&원유'!D7/1000 -> 146289.44 | E30: =E18*'환율&원유'!E6*'환율&원유'!E7/1000 -> 138926.44 | F30: =F18*'환율&원유'!F6*'환율&원유'!F7/1000 -> 150641.41 | H30: Intercept | I30: =INTERCEPT(C29:F29,C30:F30)/4 -> -11.098243 | L30: 지역별 HSFO 벙커선 판매량 전망 | P30: 2025E | Q30: 2026E
B31: 한국 HSFO 벙커량 추정치의 경우, 한국 기항 벙커선 판매량에 두바이 원유 가격과 원/달러 환율을 곱하여 그 총량을 추정함. | L31: 한국 기항 HSFO 벙커선 판매량(천 톤) | P31: 1492.116 | Q31: 1512
L32: 싱가포르 기항 HSFO 벙커선 판매량(천 톤) | P32: 6560 | Q32: 6560
B33: 싱가포르 기항 선박 상관관계 | C33: 2021A | D33: 2022A | E33: 2023A | F33: 2024A | H33: 상관계수 | I33: =CORREL(D34:F34,D35:F35) -> 0.96276863
B34: 싱가포르 기항 선박 매출 | C34: =C19 -> 3125 | D34: =D19 -> 3760 | E34: =E19 -> 3570 | F34: =F19 -> 4231.5 | H34: Slope | I34: =SLOPE(C34:F34,C35:F35) -> 0.0012577093
B35: 싱가포르 HSFO 벙커량 추정치 | C35: =C21*'환율&원유'!C6*'환율&원유'!C7/1000 -> 0 | D35: =D21*'환율&원유'!D6*'환율&원유'!D7/1000 -> 594936.97 | E35: =E21*'환율&원유'!E6*'환율&원유'!E7/1000 -> 593574.36 | F35: =F21*'환율&원유'!F6*'환율&원유'!F7/1000 -> 726131.17 | H35: Intercept | I35: =INTERCEPT(C34:F34,C35:F35)/4 -> 767.40228
B36: 싱가포르 HSFO 벙커량 추정치의 경우, 한국 기항 벙커선 판매량에 두바이 원유 가격과 원/달러 환율을 곱하여 그 총량을 추정함.

Sheet 환율&원유
A1: HD현대마린솔루션(443060.KS)
A2: DBL1 Commodity & Currency
A3: (units in $ & KRW/$)
C5: 2021A | D5: 2022A | E5: 2023A | F5: 2024A | G5: 1Q25 | H5: 2Q25 | I5: 3Q25E | J5: 4Q25E | K5: 1Q26E | L5: 2Q26E | M5: 3Q26E | N5: 4Q26E | P5: Description
B6: 두바이 원유($) | C6: 70.445 | D6: 98.06075 | E6: 81.0315 | F6: 78.36225 | G6: 75.91 | H6: 69.268 | I6: 69.513 | J6: =AVERAGE(G6:I6) -> 71.563667 | K6: =AVERAGE(H6:J6) -> 70.114889 | L6: =AVERAGE(I6:K6) -> 70.397185 | M6: =AVERAGE(J6:L6) -> 70.691914 | N6: =AVERAGE(K6:M6) -> 70.401329 | P6: 두바이 원유 가격의 경우, Bloomberg의 전망치를 참조함. 전망치가 존재하지 않은 4Q25부터는 직전 3Q Average Flat 적용함.
B7: 원/달러 환율 | C7: 1158.0715 | D7: 1300.82 | E7: 1314.65 | F7: 1379.33 | G7: 1474.25 | H7: 1353.5 | I7: 1389.7 | J7: =AVERAGE(G7:I7) -> 1405.8167 | K7: =AVERAGE(H7:J7) -> 1383.0056 | L7: =AVERAGE(I7:K7) -> 1392.8407 | M7: =AVERAGE(J7:L7) -> 1393.8877 | N7: =AVERAGE(K7:M7) -> 1389.9113 | P7: 원/달러 환율의 경우, Bloomberg 전망치를 참고함. 전망치가 존재하지 않는 4Q25부터는 직전 3Q Average Flat 적용함.

Sheet 비용추정
A1: HD현대마린솔루션(443060.KS)
A2: Assumption Sheet
A3: (units in Millions KRW )
B5: 단위: 백만 원 | C5: 2Q24 | D5: 3Q24 | E5: 4Q24 | F5: 1Q25 | G5: 2Q25 | H5: 3Q25E | I5: 4Q25E | J5: 1Q26E | K5: 2Q26E | L5: 3Q26E | M5: 4Q26E | O5: Description
B6: 매출액 | C6: ='IS(Quaterly)'!G10 -> 437855.16 | D6: ='IS(Quaterly)'!H10 -> 461261.44 | E6: ='IS(Quaterly)'!I10 -> 463372.92 | F6: ='IS(Quaterly)'!J10 -> 485597.83 | G6: ='IS(Quaterly)'!K10 -> 467721.57 | H6: =매출추정!I6*100 -> 469386.75 | I6: =매출추정!J6*100 -> 483293.63 | J6: =매출추정!K6*100 -> 508637.42 | K6: =매출추정!L6*100 -> 519267.74 | L6: =매출추정!M6*100 -> 538811.31 | M6: =매출추정!N6*100 -> 550319.23
B7: 매출원가 | C7: ='IS(Quaterly)'!G13 -> 343798 | D7: ='IS(Quaterly)'!H13 -> 355933.42 | E7: ='IS(Quaterly)'!I13 -> 373085.98 | F7: ='IS(Quaterly)'!J13 -> 377587.18 | G7: ='IS(Quaterly)'!K13 -> 358744.49 | H7: =H6*H8 -> 367643.87 | I7: =I6*I8 -> 375006.72 | J7: =J6*J8 -> 394395.26 | K7: =K6*K8 -> 404090.41 | L7: =L6*L8 -> 418392.04 | M7: =M6*M8 -> 427432.56 | O7: 매출원가의 경우, 동사가 모그룹 내 계열사들의 공급망을 이용하고, 자체 생산이 아닌 상품으로 취급하는 재화가 대부분이므로 매출액 대비 경향성을 반영하기 위하여 직전 4Q Average Flat 적용함.
B8: (%) | C8: =C7/C6 -> 0.78518659 | D8: =D7/D6 -> 0.77165223 | E8: =E7/E6 -> 0.80515275 | F8: =F7/F6 -> 0.77757181 | G8: =G7/G6 -> 0.76700437 | H8: =AVERAGE(E8:G8) -> 0.78324298 | I8: =AVERAGE(F8:H8) -> 0.77593972 | J8: =AVERAGE(G8:I8) -> 0.77539569 | K8: =AVERAGE(H8:J8) -> 0.77819279 | L8: =AVERAGE(I8:K8) -> 0.7765094 | M8: =AVERAGE(J8:L8) -> 0.77669929
B9: 매출총이익 | C9: ='IS(Quaterly)'!G14 -> 94057.16 | D9: ='IS(Quaterly)'!H14 -> 105328.02 | E9: ='IS(Quaterly)'!I14 -> 90286.939 | F9: ='IS(Quaterly)'!J14 -> 108010.65 | G9: ='IS(Quaterly)'!K14 -> 108977.08 | H9: =H6-H7 -> 101742.87 | I9: =I6-I7 -> 108286.91 | J9: =J6-J7 -> 114242.16 | K9: =K6-K7 -> 115177.33 | L9: =L6-L7 -> 120419.26 | M9: =M6-M7 -> 122886.67
B10: GPM(%) | C10: =C9/C6 -> 0.21481341 | D10: =D9/D6 -> 0.22834777 | E10: =E9/E6 -> 0.19484725 | F10: =F9/F6 -> 0.22242819 | G10: =G9/G6 -> 0.23299563 | H10: =H9/H6 -> 0.21675702 | I10: =I9/I6 -> 0.22406028 | J10: =J9/J6 -> 0.22460431 | ... M10: =M9/M6 -> 0.22330071
B11: 판매비와 관리비 | C11: ='IS(Quaterly)'!G15 -> 23071.291 | D11: ='IS(Quaterly)'!H15 -> 21944.67 | E11: ='IS(Quaterly)'!I15 -> 24407.77 | F11: ='IS(Quaterly)'!J15 -> 25003.82 | G11: ='IS(Quaterly)'!K15 -> 25967.147 | H11: =H51 -> 25534.997 | I11: =I51 -> 25957.874 | J11: =J51 -> 25964.082 | K11: =K51 -> 26135.482 | L11: =L51 -> 26176.755 | M11: =M51 -> 26341.857
B12: (%) | C12: =C11/C$6 -> 0.052691604 | D12: =D11/D$6 -> 0.04757534 | E12: =E11/E$6 -> 0.05267414 | F12: =F11/F$6 -> 0.051490798 | G12: =G11/G$6 -> 0.055518387 | H12: =H11/H$6 -> 0.054400764 | I12: =I11/I$6 -> 0.053710359 | J12: =J11/J$6 -> 0.051046346 | ... M12: =M11/M$6 -> 0.047866504
B13: 급여 | C13: 8578.007 | D13: 9172.313 | E13: 9314.703 | F13: 10343.031 | G13: 10338.994 | H13: =G13*(1+$N$13) -> 10443.302 | I13: =H13*(1+$N$13) -> 10548.663 | J13: =I13*(1+$N$14) -> 10655.163 | K13: =J13*(1+$N$14) -> 10762.739 | L13: =K13*(1+$N$14) -> 10871.4 | M13: =L13*(1+$N$14) -> 10981.159 | N13: =(1+3.6%)^0.25/100 -> 0.01008881 | O13: 급여의 경우, 국회예산정책처에서 발표한 연간 명목임금상승률 전망치를 분기로 계산하여 '25년 YoY+3.6%, '26년 YoY+3.9%로 각 분기 추정함.
B14: of sales(%) | C14: =C13/C$6 -> 0.019590969 | D14: =D13/D$6 -> 0.01988528 | E14: =E13/E$6 -> 0.020101958 | F14: =F13/F$6 -> 0.021299582 | G14: =G13/G$6 -> 0.022105019 | H14: =H13/H$6 -> 0.022248822 | I14: =I13/I$6 -> 0.021826612 | J14: =J13/J$6 -> 0.020948445 | ... M14: =M13/M$6 -> 0.019954162 | N14: =(1+3.9%)^0.25/100 -> 0.010096106
B15: 퇴직급여 | C15: 307.125 | D15: 362.536 | E15: 208.154 | F15: 394.631 | G15: 420.085 | H15: =G15*(1+$N$13) -> 424.32316 | I15: =H15*(1+$N$13) -> 428.60407 | J15: =I15*(1+$N$14) -> 432.93131 | K15: =J15*(1+$N$14) -> 437.30223 | L15: =K15*(1+$N$14) -> 441.71728 | M15: =L15*(1+$N$14) -> 446.1769 | O15: 퇴직급여의 경우, 급여 상승분을 적용하여 추정함.
B16: of sales(%) | C16: =C15/C$6 -> 0.00070143058 | D16: =D15/D$6 -> 0.00078596642 | E16: =E15/E$6 -> 0.00044921485 | F16: =F15/F$6 -> 0.00081267044 | G16: =G15/G$6 -> 0.00089815187 | H16: =H15/H$6 -> 0.00090399476 | I16: =I15/I$6 -> 0.0008868399 | J16: =J15/J$6 -> 0.00085115897 | ... M16: =M15/M$6 -> 0.00081076015
B17: 여비교통비 | C17: 290.742 | D17: 349.206 | E17: 490.195 | F17: 486.744 | G17: 412.799 | H17: =AVERAGE(D17:G17) -> 434.736 | I17: =AVERAGE(E17:H17) -> 456.1185 | J17: =AVERAGE(F17:I17) -> 447.59938 | K17: =AVERAGE(G17:J17) -> 437.81322 | L17: =AVERAGE(H17:K17) -> 444.06677 | M17: =AVERAGE(I17:L17) -> 446.39947 | O17: 여비교통비의 경우, 변동성이 낮으므로 직전 4Q Average Flat 적용함.
B18: of sales(%) | C18: =C17/C$6 -> 0.0006640141 | D18: =D17/D$6 -> 0.00075706741 | E18: =E17/E$6 -> 0.0010578844 | F18: =F17/F$6 -> 0.0010023603 | G18: =G17/G$6 -> 0.00088257422 | H18: =H17/H$6 -> 0.00092617869 | I18: =I17/I$6 -> 0.00094377097 | J18: =J17/J$6 -> 0.00087999694 | ... M18: =M17/M$6 -> 0.00081116458
B19: 지급수수료 | C19: 3581.408 | D19: 1754.789 | E19: 2315.326 | F19: 1739.365 | G19: 2623.333 | H19: =AVERAGE(D19:G19) -> 2108.2033 | I19: =AVERAGE(E19:H19) -> 2196.5568 | J19: =AVERAGE(F19:I19) -> 2166.8645 | K19: =AVERAGE(G19:J19) -> 2273.7394 | L19: =AVERAGE(H19:K19) -> 2186.341 | M19: =AVERAGE(I19:L19) -> 2205.8754 | O19: 지급수수료의 경우, 상장 후 첫 분기를 제외하고 매출 대비 매우 작은 폭의 변동성을 보이므로, 직전 4Q Average Flat 적용함.
B20: of sales(%) | C20: =C19/C$6 -> 0.0081794354 | D20: =D19/D$6 -> 0.0038043263 | E20: =E19/E$6 -> 0.0049966795 | F20: =F19/F$6 -> 0.0035819044 | G20: =G19/G$6 -> 0.0056087492 | H20: =H19/H$6 -> 0.0044913992 | I20: =I19/I$6 -> 0.0045449736 | J20: =J19/J$6 -> 0.0042601358 | ... M20: =M19/M$6 -> 0.0040083561
B21: 광고선전비 | C21: 115.089 | D21: 93.163 | E21: 132.197 | F21: 123.609 | G21: 186.689 | H21: =AVERAGE(D21:G21) -> 133.9145 | I21: =AVERAGE(E21:H21) -> 144.10237 | J21: =AVERAGE(F21:I21) -> 147.07872 | K21: =AVERAGE(G21:J21) -> 152.94615 | L21: =AVERAGE(H21:K21) -> 144.51044 | M21: =AVERAGE(I21:L21) -> 147.15942 | O21: 광고선전비의 경우, 변동성이 낮으므로 직전 4Q Average Flat 적용함.
B22: of sales(%) | C22: =C21/C$6 -> 0.00026284719 | D22: =D21/D$6 -> 0.0002019744 | E22: =E21/E$6 -> 0.00028529289 | F22: =F21/F$6 -> 0.00025455015 | G22: =G21/G$6 -> 0.00039914559 | H22: =H21/H$6 -> 0.00028529672 | I22: =I21/I$6 -> 0.00029816734 | J22: =J21/J$6 -> 0.0002891622 | ... M22: =M21/M$6 -> 0.00026740737
B23: 복리후생비 | C23: 2275.023 | D23: 2050.702 | E23: 2734.056 | F23: 2627.133 | G23: 2566.983 | H23: =AVERAGE(D23:G23) -> 2494.7185 | I23: =AVERAGE(E23:H23) -> 2605.7226 | J23: =AVERAGE(F23:I23) -> 2573.6393 | K23: =AVERAGE(G23:J23) -> 2560.2659 | L23: =AVERAGE(H23:K23) -> 2558.5866 | M23: =AVERAGE(I23:L23) -> 2574.5536 | O23: 복리후생비의 경우, 변동성이 낮으므로 직전 4Q Average Flat 적용함.
B24: of sales(%) | C24: =C23/C$6 -> 0.0051958346 | D24: =D23/D$6 -> 0.0044458562 | E24: =E23/E$6 -> 0.0059003361 | F24: =F23/F$6 -> 0.0054101004 | G24: =G23/G$6 -> 0.0054882716 | H24: =H23/H$6 -> 0.0053148465 | I24: =I23/I$6 -> 0.0053915931 | J24: =J23/J$6 -> 0.0050598701 | ... M24: =M23/M$6 -> 0.0046782912
B25: 교육훈련비 | C25: 80.429 | D25: 94.596 | E25: 208.569 | F25: 99.956 | G25: 171.853 | H25: =AVERAGE(D25:G25) -> 143.7435 | I25: =AVERAGE(E25:H25) -> 156.03037 | J25: =AVERAGE(F25:I25) -> 142.89572 | K25: =AVERAGE(G25:J25) -> 153.63065 | L25: =AVERAGE(H25:K25) -> 149.07506 | M25: =AVERAGE(I25:L25) -> 150.40795 | O25: 교육훈련비의 경우, 변동성이 낮으므로 직전 4Q Average Flat 적용함.
B26: of sales(%) | C26: =C25/C$6 -> 0.0001836886 | D26: =D25/D$6 -> 0.00020508109 | E26: =E25/E$6 -> 0.00045011046 | F26: =F25/F$6 -> 0.00020584112 | G26: =G25/G$6 -> 0.00036742586 | H26: =H25/H$6 -> 0.00030623681 | I26: =I25/I$6 -> 0.00032284799 | J26: =J25/J$6 -> 0.00028093827 | ... M26: =M25/M$6 -> 0.00027331037
B27: 임차료 | C27: 591.445 | D27: 718.374 | E27: 648.01 | F27: 700.178 | G27: 644.746 | H27: =AVERAGE(D27:G27) -> 677.827 | I27: =AVERAGE(E27:H27) -> 667.69025 | J27: =AVERAGE(F27:I27) -> 672.61031 | K27: =AVERAGE(G27:J27) -> 665.71839 | L27: =AVERAGE(H27:K27) -> 670.96149 | M27: =AVERAGE(I27:L27) -> 669.24511 | O27: 임차료의 경우, 변동성이 낮으므로 직전 4Q Average Flat 적용함.
B28: of sales(%) | C28: =C27/C$6 -> 0.0013507777 | D28: =D27/D$6 -> 0.0015574118 | E28: =E27/E$6 -> 0.0013984632 | F28: =F27/F$6 -> 0.0014418887 | G28: =G27/G$6 -> 0.0013784825 | H28: =H27/H$6 -> 0.0014440693 | I28: =I27/I$6 -> 0.0013815416 | J28: =J27/J$6 -> 0.0013223768 | ... M28: =M27/M$6 -> 0.0012161034
B29: 차량유지비 | C29: 131.221 | D29: 19.715 | E29: 98.998 | F29: 103.419 | G29: 83.292 | H29: =AVERAGE(D29:G29) -> 76.356 | I29: =AVERAGE(E29:H29) -> 90.51625 | J29: =AVERAGE(F29:I29) -> 88.395813 | K29: =AVERAGE(G29:J29) -> 84.640016 | L29: =AVERAGE(H29:K29) -> 84.97702 | M29: =AVERAGE(I29:L29) -> 87.132274 | O29: 차량유지비의 경우, 고정비적 성격을 지니므로 직전 4Q Average Flat 적용함.
B30: of sales(%) | C30: =C29/C$6 -> 0.00029969043 | D30: =D29/D$6 -> 4.2741488e-05 | E30: =E29/E$6 -> 0.00021364649 | F30: =F29/F$6 -> 0.00021297253 | G30: =G29/G$6 -> 0.00017808031 | H30: =H29/H$6 -> 0.00016267183 | I30: =I29/I$6 -> 0.00018729038 | J30: =J29/J$6 -> 0.00017378944 | ... M30: =M29/M$6 -> 0.00015833042
B31: 수도광열비 | C31: 92.208 | D31: 100.073 | E31: 98.568 | F31: 96.83 | G31: 101.732 | H31: =AVERAGE(D31:G31) -> 99.30075 | I31: =AVERAGE(E31:H31) -> 99.107687 | J31: =AVERAGE(F31:I31) -> 99.242609 | K31: =AVERAGE(G31:J31) -> 99.845762 | L31: =AVERAGE(H31:K31) -> 99.374202 | M31: =AVERAGE(I31:L31) -> 99.392565 | O31: 수도광열비의 경우, 변동성이 낮으므로 직전 4Q Average Flat 적용함.
B32: of sales(%) | C32: =C31/C$6 -> 0.00021059019 | D32: =D31/D$6 -> 0.00021695505 | E32: =E31/E$6 -> 0.00021271852 | F32: =F31/F$6 -> 0.00019940369 | G32: =G31/G$6 -> 0.00021750547 | H32: =H31/H$6 -> 0.00021155423 | I32: =I31/I$6 -> 0.00020506723 | J32: =J31/J$6 -> 0.00019511464 | ... M32: =M31/M$6 -> 0.00018060893
B33: 전산처리비 | C33: 455.565 | D33: 274.345 | E33: 125.862 | F33: 467.118 | G33: 487.784 | H33: =AVERAGE(F33:G33) -> 477.451 | I33: =AVERAGE(G33:H33) -> 482.6175 | J33: =AVERAGE(H33:I33) -> 480.03425 | K33: =AVERAGE(I33:J33) -> 481.32587 | L33: =AVERAGE(J33:K33) -> 480.68006 | M33: =AVERAGE(K33:L33) -> 481.00297 | O33: 전산처리비의 경우, 1Q25에 급격히 상승하여 유지되는 경향을 보이므로 직전 2Q Average Flat 적용함.
B34: of sales(%) | C34: =C33/C$6 -> 0.0010404468 | D34: =D33/D$6 -> 0.00059477116 | E34: =E33/E$6 -> 0.0002716214 | F34: =F33/F$6 -> 0.00096194417 | G34: =G33/G$6 -> 0.001042894 | H34: =H33/H$6 -> 0.0010171804 | I34: =I33/I$6 -> 0.00099860099 | J34: =J33/J$6 -> 0.0009437651 | ... M34: =M33/M$6 -> 0.00087404354
B35: 세금과공과 | C35: 53.386 | D35: 122.787 | E35: 225.78 | F35: 489.853 | G35: 373.855 | H35: =AVERAGE(F35:G35) -> 431.854 | I35: =AVERAGE(G35:H35) -> 402.8545 | J35: =AVERAGE(H35:I35) -> 417.35425 | K35: =AVERAGE(I35:J35) -> 410.10438 | L35: =AVERAGE(J35:K35) -> 413.72931 | M35: =AVERAGE(K35:L35) -> 411.91684 | O35: 세금과공과의 경우, 1Q25에 급격히 상승하여 유지되는 경향을 보이므로 직전 2Q Average Flat 적용함.
B36: of sales(%) | C36: =C35/C$6 -> 0.00012192616 | D36: =D35/D$6 -> 0.00026619828 | E36: =E35/E$6 -> 0.00048725333 | F36: =F35/F$6 -> 0.0010087627 | G36: =G35/G$6 -> 0.00079931101 | H36: =H35/H$6 -> 0.00092003876 | I36: =I35/I$6 -> 0.00083356054 | J36: =J35/J$6 -> 0.0008205339 | ... M36: =M35/M$6 -> 0.00074850527
B37: 연구개발비 | C37: 1212.474 | D37: 1928.862 | E37: 2241.111 | F37: 1138.046 | G37: 2003.149 | H37: =AVERAGE(D37:G37) -> 1827.792 | I37: =AVERAGE(E37:H37) -> 1802.5245 | J37: =AVERAGE(F37:I37) -> 1692.8779 | K37: =AVERAGE(G37:J37) -> 1831.5858 | L37: =AVERAGE(H37:K37) -> 1788.6951 | M37: =AVERAGE(I37:L37) -> 1778.9208 | O37: 연구개발비의 경우, 2H에 몰려 집행되는 경향이 있으나, 연간 총 비용으로 계산할 경우 변동성이 크지 않으므로 직전 4Q Average Flat 적용함.
B38: of sales(%) | C38: =C37/C$6 -> 0.0027691212 | D38: =D37/D$6 -> 0.0041817109 | E38: =E37/E$6 -> 0.004836517 | F38: =F37/F$6 -> 0.0023435978 | G38: =G37/G$6 -> 0.0042827809 | H38: =H37/H$6 -> 0.003894 | I38: =I37/I$6 -> 0.0037296674 | J38: =J37/J$6 -> 0.0033282606 | ... M38: =M37/M$6 -> 0.0032325253
B39: 감가상각비 | C39: 2318.754 | D39: 2464.516 | E39: 2398.924 | F39: 2499.549 | G39: 2505.53 | H39: =AVERAGE(D39:G39) -> 2467.1298 | I39: =AVERAGE(E39:H39) -> 2467.7832 | J39: =AVERAGE(F39:I39) -> 2484.998 | K39: =AVERAGE(G39:J39) -> 2481.3602 | L39: =AVERAGE(H39:K39) -> 2475.3178 | M39: =AVERAGE(I39:L39) -> 2477.3648 | O39: 감가상각비의 경우, 변동성이 낮으므로 직전 4Q Average Flat 적용함.
B40: of sales(%) | C40: =C39/C$6 -> 0.0052957101 | D40: =D39/D$6 -> 0.0053429916 | E40: =E39/E$6 -> 0.0051770915 | F40: =F39/F$6 -> 0.0051473645 | G40: =G39/G$6 -> 0.0053568836 | H40: =H39/H$6 -> 0.0052560703 | I40: =I39/I$6 -> 0.0051061778 | J40: =J39/J$6 -> 0.004885598 | ... M40: =M39/M$6 -> 0.0045016868
B41: 외주용역비 | C41: 1262.725 | D41: 1100.379 | E41: 1225.825 | F41: 824.785 | G41: 1298.429 | H41: =AVERAGE(C41,D41,E41,G41) -> 1221.8395 | I41: =AVERAGE(D41,E41,G41,H41) -> 1211.6181 | J41: =AVERAGE(E41,G41,H41,I41) -> 1239.4279 | K41: =AVERAGE(G41:J41) -> 1242.8286 | L41: =AVERAGE(H41:K41) -> 1228.9285 | M41: =AVERAGE(I41:L41) -> 1230.7008 | O41: 외주용역비의 경우, 급격히 감소한 1Q25를 제외한 직전 4Q Average Flat 적용함.
B42: of sales(%) | C42: =C41/C$6 -> 0.0028838875 | D42: =D41/D$6 -> 0.0023855864 | E42: =E41/E$6 -> 0.0026454394 | F42: =F41/F$6 -> 0.001698494 | G42: =G41/G$6 -> 0.0027760725 | H42: =H41/H$6 -> 0.002603055 | I42: =I41/I$6 -> 0.0025070021 | J42: =J41/J$6 -> 0.0024367611 | ... M42: =M41/M$6 -> 0.0022363398
B43: 대손상각비환입 | C43: -104.326 | D43: -183.524 | E43: 748.438 | F43: 19.888 | G43: -316.888 | H43: =AVERAGE(D43:G43) -> 66.9785 | I43: =AVERAGE(E43:H43) -> 129.60413 | J43: =AVERAGE(F43:I43) -> -25.104344 | K43: =AVERAGE(G43:J43) -> -36.35243 | L43: =AVERAGE(H43:K43) -> 33.781463 | M43: =AVERAGE(I43:L43) -> 25.482204 | O43: 대손상각비환입의 경우, 매출 대비 매우 작은 폭의 변동성을 보이므로, 직전 4Q Averge Flat 적용함.
B44: of sales(%) | C44: =C43/C$6 -> -0.00023826601 | D44: =D43/D$6 -> -0.00039787415 | E44: =E43/E$6 -> 0.0016151958 | F44: =F43/F$6 -> 4.0955702e-05 | G44: =G43/G$6 -> -0.00067751419 | H44: =H43/H$6 -> 0.00014269363 | I44: =I43/I$6 -> 0.00026816849 | J44: =J43/J$6 -> -4.9356069e-05 | ... M44: =M43/M$6 -> 4.6304404e-05
B45: 하자보수충당부채전입(환입) | C45: -8.552 | D45: -87.693 | E45: -9.849 | F45: -231.94 | G45: -22.423 | H45: =AVERAGE(D45:G45) -> -87.97625 | I45: =AVERAGE(E45:H45) -> -88.047062 | J45: =AVERAGE(F45:I45) -> -107.59658 | K45: =AVERAGE(G45:J45) -> -76.510723 | L45: =AVERAGE(H45:K45) -> -90.032653 | M45: =AVERAGE(I45:L45) -> -90.546754 | O45: 하자보수충당부채전입(환입)의 경우, 매출 대비 매우 작은 폭의 변동성을 보이므로, 직전 4Q Averge Flat 적용함.
B46: of sales(%) | C46: =C45/C$6 -> -1.9531573e-05 | D46: =D45/D$6 -> -0.00019011561 | E46: =E45/E$6 -> -2.1255018e-05 | F46: =F45/F$6 -> -0.00047763805 | G46: =G45/G$6 -> -4.7940915e-05 | H46: =H45/H$6 -> -0.00018742807 | I46: =I45/I$6 -> -0.0001821813 | J46: =J45/J$6 -> -0.00021153885 | ... M46: =M45/M$6 -> -0.00016453496
B47: 판매보증충당부채전입 | C47: 261.096 | D47: 75.485 | E47: 187.945 | F47: 319.09 | G47: 336.89 | H47: =AVERAGE(F47:G47) -> 327.99 | I47: =AVERAGE(G47:H47) -> 332.44 | J47: =AVERAGE(H47:I47) -> 330.215 | K47: =AVERAGE(I47:J47) -> 331.3275 | L47: =AVERAGE(J47:K47) -> 330.77125 | M47: =AVERAGE(K47:L47) -> 331.04937 | O47: 판매보증충당부채전입의 경우, 1Q25에 급격히 상승하여 유지되는 경향을 보이므로 직전 2Q Average Flat 적용함.
B48: of sales(%) | C48: =C47/C$6 -> 0.00059630678 | D48: =D47/D$6 -> 0.00016364906 | E48: =E47/E$6 -> 0.00040560203 | F48: =F47/F$6 -> 0.00065710755 | G48: =G47/G$6 -> 0.00072027895 | H48: =H47/H$6 -> 0.00069876281 | I48: =I47/I$6 -> 0.0006878634 | J48: =J47/J$6 -> 0.00064921491 | ... M48: =M47/M$6 -> 0.0006015588
B49: 기타 | C49: 1577.472 | D49: 1534.046 | E49: 1014.959 | F49: 2762.534 | G49: 1750.315 | H49: =AVERAGE(D49:G49) -> 1765.4635 | I49: =AVERAGE(E49:H49) -> 1823.3179 | J49: =AVERAGE(F49:I49) -> 2025.4076 | K49: =AVERAGE(G49:J49) -> 1841.126 | L49: =AVERAGE(H49:K49) -> 1863.8287 | M49: =AVERAGE(I49:L49) -> 1888.4201 | O49: 기타의 경우, 변동성이 낮으므로 직전 4Q Average Flat 적용함.
B50: of sales(%) | C50: =C49/C$6 -> 0.0036027256 | D50: =D49/D$6 -> 0.0033257625 | E50: =E49/E$6 -> 0.0021903718 | F50: =F49/F$6 -> 0.005688934 | G50: =G49/G$6 -> 0.0037422157 | H50: =H49/H$6 -> 0.0037612129 | I50: =I49/I$6 -> 0.0037726917 | J50: =J49/J$6 -> 0.0039820263 | ... M50: =M49/M$6 -> 0.0034314993
B51: 계 | C51: =SUM(C13:C49) -> 23071.34 | D51: =SUM(D13:D49) -> 21944.714 | E51: =SUM(E13:E49) -> 24407.821 | F51: =SUM(F13:F49) -> 25003.865 | G51: =SUM(G13:G49) -> 25967.199 | H51: =SUM(H13:H49) -> 25534.997 | I51: =SUM(I13:I49) -> 25957.874 | J51: =SUM(J13:J49) -> 25964.082 | ... M51: =SUM(M13:M49) -> 26341.857
B52: 영업이익 | C52: ='IS(Quaterly)'!G24 -> 70985.869 | D52: ='IS(Quaterly)'!H24 -> 83383.35 | E52: ='IS(Quaterly)'!I24 -> 65879.169 | F52: ='IS(Quaterly)'!J24 -> 83006.827 | G52: ='IS(Quaterly)'!K24 -> 83009.935 | H52: =H9-H11 -> 76207.877 | I52: =I9-I11 -> 82329.033 | J52: =J9-J11 -> 88278.077 | K52: =K9-K11 -> 89041.843 | L52: =L9-L11 -> 94242.507 | M52: =M9-M11 -> 96544.815
B53: OPM(%) | C53: =C52/C6 -> 0.16212181 | D53: =D52/D6 -> 0.18077243 | E53: =E52/E6 -> 0.14217311 | F53: =F52/F6 -> 0.17093739 | G53: =G52/G6 -> 0.17747724 | H53: =H52/H6 -> 0.16235626 | I53: =I52/I6 -> 0.17034992 | J53: =J52/J6 -> 0.17355797 | ... M53: =M52/M6 -> 0.1754342
B54: 지분법손익 | C54: ='IS(Quaterly)'!G79 -> 0 | D54: ='IS(Quaterly)'!H79 -> -179.16728 | E54: ='IS(Quaterly)'!I79 -> -58.85354 | F54: ='IS(Quaterly)'!J79 -> -106.50236 | G54: ='IS(Quaterly)'!K79 -> -61.97999 | H54: =AVERAGE(D54:G54) -> -101.62579 | I54: =AVERAGE(E54:H54) -> -82.240421 | J54: =AVERAGE(F54:I54) -> -88.087141 | K54: =AVERAGE(G54:J54) -> -83.483336 | L54: =AVERAGE(H54:K54) -> -88.859172 | M54: =AVERAGE(I54:L54) -> -85.667517 | O54: 지분법손익의 경우, 매출 대비 매우 작은 폭의 변동성을 보이므로 직전 4Q Average Flat 적용함.
B55: of sales(%) | C55: =C54/$C$6 -> 0 | D55: =D54/$C$6 -> -0.00040919303 | E55: =E54/$C$6 -> -0.00013441326 | F55: =F54/$C$6 -> -0.00024323651 | G55: =G54/$C$6 -> -0.00014155364 | H55: =H54/$C$6 -> -0.00023209911 | I55: =I54/$C$6 -> -0.00018782563 | J55: =J54/$C$6 -> -0.00020117872 | ... M55: =M54/$C$6 -> -0.00019565264
B56: 금융수익 | C56: ='IS(Quaterly)'!G25 -> 10729.355 | D56: ='IS(Quaterly)'!H25 -> 9314.79 | E56: ='IS(Quaterly)'!I25 -> 29108.738 | F56: ='IS(Quaterly)'!J25 -> 15766.251 | G56: ='IS(Quaterly)'!K25 -> 16252.424 | H56: =AVERAGE(D56:G56) -> 17610.551 | I56: =AVERAGE(E56:H56) -> 19684.491 | J56: =AVERAGE(F56:I56) -> 17328.429 | K56: =AVERAGE(G56:J56) -> 17718.974 | L56: =AVERAGE(H56:K56) -> 18085.611 | M56: =AVERAGE(I56:L56) -> 18204.376 | O56: 금융수익의 경우, 자세한 추정이 어렵고 변동성이 낮으므로 직전 4Q Average Flat 적용함.
B57: of sales(%) | C57: =C56/$C$6 -> 0.024504348 | D57: =D56/$C$6 -> 0.021273679 | E57: =E56/$C$6 -> 0.06648029 | F57: =F56/$C$6 -> 0.036007914 | G57: =G56/$C$6 -> 0.037118265 | H57: =H56/$C$6 -> 0.040220037 | I57: =I56/$C$6 -> 0.044956627 | J57: =J56/$C$6 -> 0.039575711 | ... M57: =M56/$C$6 -> 0.041576252
B58: 금융원가 | C58: ='IS(Quaterly)'!G37 -> 4267.171 | D58: ='IS(Quaterly)'!H37 -> 14714.404 | E58: ='IS(Quaterly)'!I37 -> 8263.257 | F58: ='IS(Quaterly)'!J37 -> 13365.847 | G58: ='IS(Quaterly)'!K37 -> 29691.852 | H58: =AVERAGE(D58:G58) -> 16508.84 | I58: =AVERAGE(E58:H58) -> 16957.449 | J58: =AVERAGE(F58:I58) -> 19130.997 | K58: =AVERAGE(G58:J58) -> 20572.285 | L58: =AVERAGE(H58:K58) -> 18292.393 | M58: =AVERAGE(I58:L58) -> 18738.281 | O58: 금융원가의 경우, 자세한 추정이 어렵고 변동성이 낮으므로 직전 4Q Average Flat 적용함.
B59: of sales(%) | C59: =C58/$C$6 -> 0.0097456223 | D59: =D58/$C$6 -> 0.033605643 | E59: =E58/$C$6 -> 0.018872124 | F59: =F58/$C$6 -> 0.030525727 | G59: =G58/$C$6 -> 0.067812041 | H59: =H58/$C$6 -> 0.037703884 | I59: =I58/$C$6 -> 0.038728444 | J59: =J58/$C$6 -> 0.043692524 | ... M59: =M58/$C$6 -> 0.042795615
B60: 기타수익 | C60: ='IS(Quaterly)'!G48 -> 214.759 | D60: ='IS(Quaterly)'!H48 -> -6.593 | E60: ='IS(Quaterly)'!I48 -> 424.728 | F60: ='IS(Quaterly)'!J48 -> 450.714 | G60: ='IS(Quaterly)'!K48 -> 105.875 | H60: =AVERAGE(D60:G60) -> 243.681 | I60: =AVERAGE(E60:H60) -> 306.2495 | J60: =AVERAGE(F60:I60) -> 276.62987 | K60: =AVERAGE(G60:J60) -> 233.10884 | L60: =AVERAGE(H60:K60) -> 264.9173 | M60: =AVERAGE(I60:L60) -> 270.22638 | O60: 기타수익의 경우, 매출 대비 매우 작은 폭의 변동성을 보이므로 직전 4Q Average Flat 적용함.
B61: of sales(%) | C61: =C60/$C$6 -> 0.00049047955 | D61: =D60/$C$6 -> -1.5057491e-05 | E61: =E60/$C$6 -> 0.0009700194 | F61: =F60/$C$6 -> 0.0010293678 | G61: =G60/$C$6 -> 0.00024180371 | H61: =H60/$C$6 -> 0.00055653335 | I61: =I60/$C$6 -> 0.00069943107 | J61: =J60/$C$6 -> 0.00063178398 | ... M61: =M60/$C$6 -> 0.00061715929
B62: 기타비용 | C62: ='IS(Quaterly)'!G65 -> 719.496 | D62: ='IS(Quaterly)'!H65 -> 482.051 | E62: ='IS(Quaterly)'!I65 -> 774.81 | F62: ='IS(Quaterly)'!J65 -> 1874.732 | G62: ='IS(Quaterly)'!K65 -> 1333.607 | H62: =AVERAGE(D62:G62) -> 1116.3 | I62: =AVERAGE(E62:H62) -> 1274.8622 | J62: =AVERAGE(F62:I62) -> 1399.8753 | K62: =AVERAGE(G62:J62) -> 1281.1611 | L62: =AVERAGE(H62:K62) -> 1268.0497 | M62: =AVERAGE(I62:L62) -> 1305.9871 | O62: 기타비용의 경우, 자세한 추정이 어렵고 변동성이 낮으므로 직전 4Q Average Flat 적용함.
B63: of sales(%) | C63: =C62/$C$6 -> 0.0016432283 | D63: =D62/$C$6 -> 0.0011009371 | E63: =E62/$C$6 -> 0.0017695578 | F63: =F62/$C$6 -> 0.0042816259 | G63: =G62/$C$6 -> 0.003045772 | H63: =H62/$C$6 -> 0.0025494732 | I63: =I62/$C$6 -> 0.0029116072 | J63: =J62/$C$6 -> 0.0031971196 | ... M63: =M62/$C$6 -> 0.002982692
B64: 법인세차감전순이익 | C64: ='IS(Quaterly)'!G83 -> 76943.316 | D64: ='IS(Quaterly)'!H83 -> 77315.925 | E64: ='IS(Quaterly)'!I83 -> 86315.712 | F64: ='IS(Quaterly)'!J83 -> 83876.711 | G64: ='IS(Quaterly)'!K83 -> 68280.796 | H64: =H52+H54+H56-H58+H60-H62 -> 76335.343 | I64: =I52+I54+I56-I58+I60-I62 -> 84005.222 | J64: =J52+J54+J56-J58+J60-J62 -> 85264.177 | K64: =K52+K54+K56-K58+K60-K62 -> 85056.997 | L64: =L52+L54+L56-L58+L60-L62 -> 92943.734 | M64: =M52+M54+M56-M58+M60-M62 -> 94889.482
B65: 법인세비용 | C65: 20264.116 | D65: 18786.758 | E65: 17908.97 | F65: 20558.525 | G65: 15283.742 | H65: =H6*H67 -> 18117.363 | I65: =I6*I67 -> 18396.648 | J65: =J6*J67 -> 19287.103 | K65: =K6*K67 -> 19116.747 | L65: =L6*L67 -> 20393.614 | M65: =M6*M67 -> 20726.178
B66: 유효 법인세율(%) | C66: =C65/C64 -> 0.26336421 | D66: =D65/D64 -> 0.24298691 | E66: =E65/E64 -> 0.20748216 | F66: =F65/F64 -> 0.24510409 | G66: =G65/G64 -> 0.22383662 | H66: =H65/H64 -> 0.23733912 | I66: =I65/I64 -> 0.2189941 | J66: =J65/J64 -> 0.22620407 | ... M66: =M65/M64 -> 0.2184244 | O66: 유효 법인세율에 대한 정확한 추정이 불가능하다고 판단되므로, 매출액 대비 법인세율에 직전 4Q Average Flat 적용하였다.
B67: 매출 대비 법인세율(%) | C67: =C65/C6 -> 0.046280409 | D67: =D65/D6 -> 0.040729088 | E67: =E65/E6 -> 0.038649151 | F67: =F65/F6 -> 0.042336525 | G67: =G65/G6 -> 0.03267701 | H67: =AVERAGE(D67:G67) -> 0.038597944 | I67: =AVERAGE(E67:H67) -> 0.038065158 | J67: =AVERAGE(F67:I67) -> 0.037919159 | K67: =AVERAGE(G67:J67) -> 0.036814818 | L67: =AVERAGE(H67:K67) -> 0.037849269 | M67: =AVERAGE(I67:L67) -> 0.037662101 | O67: 추정한 매출액에 대비하여 법인세율을 환산하였을 때, 한계 법인세율 이내이므로 합리적인 추정이라 판단하였다;
B68: 당기순이익 | C68: ='IS(Quaterly)'!G89 -> 56679.2 | D68: ='IS(Quaterly)'!H89 -> 58529.167 | E68: ='IS(Quaterly)'!I89 -> 68406.742 | F68: ='IS(Quaterly)'!J89 -> 63318.186 | G68: ='IS(Quaterly)'!K89 -> 52997.054 | H68: =H64-H65 -> 58217.98 | I68: =I64-I65 -> 65608.574 | J68: =J64-J65 -> 65977.073 | K68: =K64-K65 -> 65940.25 | L68: =L64-L65 -> 72550.12 | M68: =M64-M65 -> 74163.304
B69: (%) | C69: =C68/C6 -> 0.12944737 | D69: =D68/D6 -> 0.12688936 | E69: =E68/E6 -> 0.14762784 | F69: =F68/F6 -> 0.13039223 | G69: =G68/G6 -> 0.11330898 | H69: =H68/H6 -> 0.12402988 | I69: =I68/I6 -> 0.13575303 | J69: =J68/J6 -> 0.12971337 | ... M69: =M68/M6 -> 0.13476415

Sheet RAWDATA>>>
B2: HD현대마린솔루션 RAW DATA
B8: RFS Research Team 2

Sheet IS(Quaterly)
A1: Financial Statements
A2: Company | B2: A443060(HD현대마린솔루션) - Fiscal Month:12, 201712부터 IFRS 적용
A3: Type | B3: 연결 | C3: Accounting Std. | D3: IFRS
A4: Report | B4: 손익계산서 | C4: New
A5: Form | B5: 약식(COMPARE)
A6: Output | B6: 결산 | C6: 백만원
A7: Fiscal Year | B7: 2021 | C7: Current
A8: 계정코드 | B8: 계정명 | C8: 단위 | D8: 202112 | E8: 202212 | F8: 202312 | G8: 202406 | H8: 202409 | I8: 202412 | J8: 202503 | K8: 202506
D9: IFRS(연결) | E9: IFRS(연결) | F9: IFRS(연결) | G9: IFRS(연결) | H9: IFRS(연결) | I9: IFRS(연결) | J9: IFRS(연결) | K9: IFRS(연결)
A10: 4001210000 | B10: 매출액(수익)(*) | C10: 백만원 | D10: 1087745.8 | E10: 1333798.6 | F10: 1430463.2 | G10: 437855.16 | H10: 461261.44 | I10: 463372.92 | J10: 485597.83 | K10: 467721.57
A11: 4001210010 | B11: *수출(*) | C11: 백만원 | H11: 341781 | I11: 945115 | J11: 377736
A12: 4001210020 | B12: *내수 | C12: 백만원 | H12: 119480 | I12: 339083 | J12: 107862
A13: 4001210320 | B13: 매출원가(*) | C13: 백만원 | D13: 942316.24 | E13: 1138075.3 | F13: 1157570.4 | G13: 343798 | H13: 355933.42 | I13: 373085.98 | J13: 377587.18 | K13: 358744.49
A14: 4001210780 | B14: 매출총이익(손실) | C14: 백만원 | D14: 145429.56 | E14: 195723.24 | F14: 272892.78 | G14: 94057.16 | H14: 105328.02 | I14: 90286.939 | J14: 108010.65 | K14: 108977.08
A15: 4001290000 | B15: 판매비와관리비(*) | C15: 백만원 | D15: 32448.375 | E15: 53772.831 | F15: 71420.302 | G15: 23071.291 | H15: 21944.67 | I15: 24407.77 | J15: 25003.82 | K15: 25967.147
A16: 4001290010 | B16: 인건비(*) | C16: 백만원 | D16: 17489.673 | E16: 25329.429 | F16: 35800.276 | G16: 11160.155 | H16: 11585.551 | I16: 12256.913 | J16: 13364.795 | K16: 13326.062
A17: 4001290020 | B17: 유무형자산상각비(*) | C17: 백만원 | D17: 2360 | E17: 5956.265 | F17: 8144.743 | G17: 2318.754 | H17: 2464.516 | I17: 2398.924 | J17: 2499.549 | K17: 2505.53
A18: 4001211300 | B18: 연구개발비 | C18: 백만원 | D18: 800.563 | E18: 4629.468 | F18: 4637.048 | G18: 1212.474 | H18: 1928.862 | I18: 2241.111 | J18: 1138.046 | K18: 2003.149
A19: 4001211060 | B19: 광고선전비 | C19: 백만원 | D19: 164.648 | E19: 1342.268 | F19: 1200.004 | G19: 115.089 | H19: 93.163 | I19: 132.197 | J19: 123.609 | K19: 186.689
A20: 4001290040 | B20: 판매비(*) | C20: 백만원 | D20: 2389.261 | E20: -278.91 | F20: -5366.801 | G20: 148.218 | H20: -195.732 | I20: 926.534 | J20: 107.038 | K20: -2.421
A21: 4001290090 | B21: 관리비(*) | C21: 백만원 | D21: 9176.867 | E21: 12524.471 | F21: 18511.027 | G21: 6539.129 | H21: 4534.264 | I21: 5437.133 | J21: 5008.248 | K21: 6197.823
A22: 4001290110 | B22: 기타원가성비용(*) | C22: 백만원
A23: 4001211420 | B23: 기타 | C23: 백만원 | D23: 67.363 | E23: 4269.84 | F23: 8494.004 | G23: 1577.472 | H23: 1534.046 | I23: 1014.959 | J23: 2762.534 | K23: 1750.315
A24: 4001211430 | B24: 영업이익(손실) | C24: 백만원 | D24: 112981.19 | E24: 141950.41 | F24: 201472.48 | G24: 70985.869 | H24: 83383.35 | I24: 65879.169 | J24: 83006.827 | K24: 83009.935
A25: 4001290120 | B25: 금융수익(*) | C25: 백만원 | D25: 18646.664 | E25: 40210.225 | F25: 40724.494 | G25: 10729.355 | H25: 9314.79 | I25: 29108.738 | J25: 15766.251 | K25: 16252.424
A26: 4001290750 | B26: 이자수익 | C26: 백만원 | D26: 741.362 | E26: 880.983 | F26: 2344.028 | G26: 2989.879 | H26: 3783.724 | I26: 4065.535 | J26: 4504.184 | K26: 3748.156
A27: 4001290760 | B27: 배당금수익 | C27: 백만원 | D27: 145.552
A28: 4001211480 | B28: 외환이익(*) | C28: 백만원 | D28: 17759.75 | E28: 39329.242 | F28: 38380.466 | G28: 7739.476 | H28: 5520.071 | I28: 25053.214 | J28: 11262.067 | K28: 12349.374
A29: 4001211520 | B29: 대손충당금환입액 | C29: 백만원
A30: 4001211600 | B30: 매출채권처분이익 | C30: 백만원
A31: 4001211605 | B31: 당기손익-공정가치측정 금융자산관련이익 | C31: 백만원
A32: 4001290130 | B32: 금융자산처분이익(*) | C32: 백만원
A33: 4001290150 | B33: 금융자산평가이익(*) | C33: 백만원
A34: 4001211720 | B34: 금융자산손상차손환입(*) | C34: 백만원
A35: 4001211680 | B35: 파생상품이익(*) | C35: 백만원 | H35: 10.995 | I35: -10.011 | K35: 154.894
A36: 4001290170 | B36: 기타금융수익(*) | C36: 백만원
A37: 4001290180 | B37: 금융원가(*) | C37: 백만원 | D37: 9147.034 | E37: 36462.794 | F37: 40626.706 | G37: 4267.171 | H37: 14714.404 | I37: 8263.257 | J37: 13365.847 | K37: 29691.852
A38: 4001290770 | B38: 이자비용 | C38: 백만원 | D38: 1218.773 | E38: 2724.347 | F38: 6162.896 | G38: 1669.173 | H38: 452.573 | I38: 324.294 | J38: 283.666 | K38: 288.028
A39: 4001211820 | B39: 외환손실(*) | C39: 백만원 | D39: 7928.225 | E39: 33557.9 | F39: 34463.81 | G39: 2492.022 | H39: 14367.807 | I39: 7720.654 | J39: 13065.291 | K39: 29420.714
A40: 4001211860 | B40: 대손상각비 | C40: 백만원
A41: 4001211865 | B41: 당기손익-공정가치측정 금융자산관련손실 | C41: 백만원
A42: 4001211940 | B42: 매출채권처분손실 | C42: 백만원
A43: 4001290190 | B43: 금융자산처분손실(*) | C43: 백만원 | D43: 0.036
A44: 4001290210 | B44: 금융자산평가손실(*) | C44: 백만원
A45: 4001212060 | B45: 금융자산손상차손(*) | C45: 백만원
A46: 4001212020 | B46: 파생상품손실(*) | C46: 백만원 | G46: 105.976 | H46: -105.976 | I46: 218.309 | J46: 16.89 | K46: -16.89
A47: 4001290230 | B47: 기타금융원가(*) | C47: 백만원 | E47: 180.547
A48: 4001290240 | B48: 기타수익(*) | C48: 백만원 | D48: 212.046 | E48: 920.01 | F48: 778.972 | G48: 214.759 | H48: -6.593 | I48: 424.728 | J48: 450.714 | K48: 105.875
A49: 4001280000 | B49: 이자수익 | C49: 백만원
A50: 4001280010 | B50: 배당금수익 | C50: 백만원
A51: 4001290250 | B51: 외환이익(*) | C51: 백만원
A52: 4001280050 | B52: 재고자산감모손실환입 | C52: 백만원
A53: 4001280060 | B53: 재고자산폐기(처분)이익 | C53: 백만원
A54: 4001280065 | B54: 당기손익-공정가치측정 금융자산평가이익 | C54: 백만원
A55: 4001290260 | B55: 자산처분(폐기)이익(*) | C55: 백만원 | D55: 20.706 | E55: 9.646 | F55: 5.364 | G55: 1.764 | H55: 0.658 | I55: 0.037 | J55: 285.756 | K55: -0.013
A56: 4001280140 | B56: 자산평가이익 | C56: 백만원
A57: 4001290280 | B57: 자산손상차손환입(*) | C57: 백만원
A58: 4001290300 | B58: 파생상품이익(*) | C58: 백만원 | G58: 105.976 | H58: -105.976 | I58: 218.309 | J58: 16.89 | K58: -16.89
A59: 4001280240 | B59: 임대료수익 | C59: 백만원 | D59: 119.824 | E59: 134.962 | F59: 312.212 | G59: 68.376 | H59: 75.535 | I59: 69.663 | J59: 72.223 | K59: 80.975
A60: 4001280250 | B60: 로열티수익 | C60: 백만원
A61: 4001280260 | B61: 수수료수익 | C61: 백만원
A62: 4001280270 | B62: 대손충당금환입 | C62: 백만원 | F62: 44.389 | G62: 15.569 | H62: 0.878 | I62: 11.737 | J62: 50.825 | K62: -0.801
A63: 4001280280 | B63: 충당부채환입액 | C63: 백만원
A64: 4001290310 | B64: 기타(*) | C64: 백만원 | D64: 71.516 | E64: 775.402 | F64: 417.007 | G64: 23.074 | H64: 22.312 | I64: 124.982 | J64: 25.02 | K64: 42.604
A65: 4001290320 | B65: 기타비용(*) | C65: 백만원 | D65: 6024.996 | E65: 4719.32 | F65: 1340.798 | G65: 719.496 | H65: 482.051 | I65: 774.81 | J65: 1874.732 | K65: 1333.607
A66: 4001280400 | B66: 이자비용 | C66: 백만원
A67: 4001290330 | B67: 외환손실(*) | C67: 백만원
A68: 4001280440 | B68: 재고자산감모손실 | C68: 백만원
A69: 4001280450 | B69: 재고자산폐기(처분)손실 | C69: 백만원
A70: 4001280455 | B70: 당기손익-공정가치측정 금융자산평가손실 | C70: 백만원
A71: 4001290340 | B71: 자산처분(폐기)손실(*) | C71: 백만원 | D71: 0.215 | E71: 198.325 | F71: 146.216 | G71: 20.478 | H71: 0.011 | I71: 91.365
A72: 4001280540 | B72: 자산평가손실 | C72: 백만원
A73: 4001290360 | B73: 자산손상차손(*) | C73: 백만원
A74: 4001290380 | B74: 파생상품손실(*) | C74: 백만원 | H74: 10.995 | I74: -10.011 | K74: 154.894
A75: 4001280650 | B75: 기타대손상각비 | C75: 백만원 | D75: 4969.512 | E75: 3203.493 | F75: 81.134 | G75: 159.319 | H75: 82.793 | I75: -424.469 | J75: 39.182 | K75: 0.326
A76: 4001280660 | B76: 충당부채전입액 | C76: 백만원
A77: 4001290390 | B77: 기타(*) | C77: 백만원 | D77: 1055.269 | E77: 1317.502 | F77: 1113.448 | G77: 539.699 | H77: 388.252 | I77: 1117.925 | J77: 1835.55 | K77: 1178.387
A78: 4001290640 | B78: 종속기업,공동지배기업및관계기업관련손익(*) | C78: 백만원 | H78: -179.16728 | I78: -58.85354 | J78: -106.50236 | K78: -61.97999
A79: 4001290650 | B79: 지분법손익(*) | C79: 백만원 | H79: -179.16728 | I79: -58.85354 | J79: -106.50236 | K79: -61.97999
A80: 4001290680 | B80: 종속기업,공동지배기업및관계기업투자주식처분손익(*) | C80: 백만원
A81: 4001290710 | B81: 종속기업,공동지배기업및관계기업투자주식손상관련손익(*) | C81: 백만원
A82: 4001290740 | B82: 기타(*) | C82: 백만원
A83: 4001212380 | B83: 법인세비용차감전계속사업이익 | C83: 백만원 | D83: 116667.87 | E83: 141898.53 | F83: 201008.44 | G83: 76943.316 | H83: 77315.925 | I83: 86315.712 | J83: 83876.711 | K83: 68280.796
A84: 4001212390 | B84: 법인세비용 | C84: 백만원 | D84: 27103.889 | E84: 36972.022 | F84: 49892.265 | G84: 20264.116 | H84: 18786.758 | I84: 17908.97 | J84: 20558.525 | K84: 15283.742
A85: 4001212400 | B85: 종속회사매수일전순손익 | C85: 백만원
A86: 4001212410 | B86: 처분된종속회사순손익 | C86: 백만원
A87: 4001212420 | B87: 계속영업이익(손실) | C87: 백만원 | D87: 89563.978 | E87: 104926.51 | F87: 151116.18 | G87: 56679.2 | H87: 58529.167 | I87: 68406.742 | J87: 63318.186 | K87: 52997.054
A88: 4001212430 | B88: 중단영업이익(손실) | C88: 백만원
A89: 4001212450 | B89: 당기순이익(손실) | C89: 백만원 | D89: 89563.978 | E89: 104926.51 | F89: 151116.18 | G89: 56679.2 | H89: 58529.167 | I89: 68406.742 | J89: 63318.186 | K89: 52997.054
A90: 4001220000 | B90: 기타포괄손익(*) | C90: 백만원 | D90: 981.12517 | E90: 2419.2193 | F90: -3877.0477 | G90: 2792.6058 | H90: -4853.1975 | I90: 8267.4107 | J90: -201.27209 | K90: -8947.78
A91: 4001220120 | B91: 총포괄손익 | C91: 백만원 | D91: 90545.103 | E91: 107345.73 | F91: 147239.13 | G91: 59471.806 | H91: 53675.97 | I91: 76674.153 | J91: 63116.914 | K91: 44049.274
A92: 4001230000 | B92: (당기순손익귀속)지배기업주주지분 | C92: 백만원 | D92: 89563.978 | E92: 104926.51 | F92: 151116.18 | G92: 56679.2 | H92: 58529.167 | I92: 68406.742 | J92: 63318.186 | K92: 52997.054
A93: 4001230030 | B93: (당기순손익귀속)비지배주주지분 | C93: 백만원
A94: 4001230060 | B94: (총포괄손익귀속)지배기업주주지분 | C94: 백만원 | D94: 90545.103 | E94: 107345.73 | F94: 147239.13 | G94: 59471.806 | H94: 53675.97 | I94: 76674.153 | J94: 63116.914 | K94: 44049.274
A95: 4001230070 | B95: (총포괄손익귀속)비지배주주지분 | C95: 백만원
A96: 4001230080 | B96: 주당계속영업이익 | C96: 원 | F96: 3778 | H96: 1317 | I96: 2879 | J96: 1412
A97: 4001230090 | B97: 주당순손익 | C97: 원 | F97: 3778 | H97: 1317 | I97: 2879 | J97: 1412
A98: 4001230100 | B98: 희석주당계속영업이익 | C98: 원 | F98: 3776 | H98: 1316 | I98: 3959
A99: 4001230110 | B99: 희석주당순손익 | C99: 원 | F99: 3776 | H99: 1316 | I99: 3959
A100: 4001230120 | B100: (지배기업주주지분)주당계속영업이익 | C100: 원 | D100: 2239 | E100: 2623 | F100: 3778 | G100: 1319 | H100: 1317 | I100: 1560 | J100: 1412 | K100: 1182
...

Sheet BS(Quaterly)
A1: Financial Statements
A2: Company | B2: A443060(HD현대마린솔루션) - Fiscal Month:12, 201712부터 IFRS 적용
A3: Type | B3: 연결 | C3: Accounting Std.
A4: Report | B4: 재무상태표 | C4: New
A5: Form | B5: 약식(COMPARE)
A6: Output | B6: 누적분기 | C6: 백만원
A7: Fiscal Year | B7: 2021 | C7: Current
A8: 계정코드 | B8: 계정명 | C8: 단위 | D8: 202112 | E8: 202212 | F8: 202312 | G8: 202406 | H8: 202409 | I8: 202412 | J8: 202503 | K8: 202506
D9: IFRS(연결) | E9: IFRS(연결) | F9: IFRS(연결) | G9: IFRS(연결) | H9: IFRS(연결) | I9: IFRS(연결) | J9: IFRS(연결) | K9: IFRS(연결)
A10: 4001190010 | B10: 자산(*) | C10: 백만원 | D10: 418547.82 | E10: 519815.76 | F10: 656618.15 | G10: 1082506.5 | H10: 1092452.4 | I10: 1152228 | J10: 1233953 | K10: 1120148.3
A11: 4001190240 | B11: 유동자산(*) | C11: 백만원 | D11: 384826.28 | E11: 453230.9 | F11: 597262.32 | G11: 1014908.5 | H11: 1023380.8 | I11: 1075525.9 | J11: 1151124.2 | K11: 1033004.1
A12: 4001190250 | B12: 재고자산(*) | C12: 백만원 | D12: 125525.83 | E12: 159914.31 | F12: 237628.47 | G12: 254656.63 | H12: 248671.94 | I12: 273426.86 | J12: 254700.3 | K12: 261585.98
A13: 4001190260 | B13: 유동생물자산(*) | C13: 백만원
A14: 4001190270 | B14: 유동금융자산(*) | C14: 백만원 | D14: 1169.403 | E14: 6328.31 | G14: 127035.26 | H14: 252000 | I14: 182950 | J14: 117950 | K14: 196293.44
A15: 4001190300 | B15: 매출채권및기타유동채권(*) | C15: 백만원 | D15: 147254.61 | E15: 179692.95 | F15: 210583.35 | G15: 243155.53 | H15: 227269.49 | I15: 262855.9 | J15: 277282.77 | K15: 253016.46
A16: 4001113900 | B16: 당기법인세자산(선급법인세) | C16: 백만원 | E16: 353.5767 | F16: 197.2782 | G16: 1087.1982 | H16: 105.26977 | I16: 747.65082 | J16: 694.2411 | K16: 647.61182
A17: 4001180995 | B17: 계약자산(**) | C17: 백만원 | D17: 9944.81 | E17: 15752.209 | F17: 14031.857 | G17: 10836.09 | H17: 9541.1336 | I17: 16841.284 | J17: 7717.352 | K17: 4832.411
A18: 4001113903 | B18: 반품(환불)자산 | C18: 백만원
A19: 4001113904 | B19: 배출권 | C19: 백만원
A20: 4001190340 | B20: 기타유동자산(*) | C20: 백만원 | D20: 14942.945 | E20: 27638.074 | F20: 39109.339 | G20: 57408.849 | H20: 63787.443 | I20: 40238.149 | J20: 37009.779 | K20: 40850.316
A21: 4001190370 | B21: 현금및현금성자산(*) | C21: 백만원 | D21: 85988.675 | E21: 63551.476 | F21: 95712.021 | G21: 320728.9 | H21: 222005.54 | I21: 298466.07 | J21: 455769.78 | K21: 275777.91
A22: 4001114130 | B22: 매각예정비유동자산및처분자산집단(*) | C22: 백만원
A23: 4001190020 | B23: 비유동자산(*) | C23: 백만원 | D23: 33721.545 | E23: 66584.861 | F23: 59355.83 | G23: 67597.998 | H23: 69071.568 | I23: 76702.051 | J23: 82828.822 | K23: 87144.202
A24: 4001190030 | B24: 유형자산(*) | C24: 백만원 | D24: 12069.328 | E24: 12988.66 | F24: 11181.577 | G24: 13789.954 | H24: 15349.27 | I24: 19580.722 | J24: 20263.564 | K24: 23907.899
A25: 4001190070 | B25: 무형자산(*) | C25: 백만원 | D25: 4136.667 | E25: 4136.667 | F25: 4136.667 | G25: 4136.6665 | H25: 4136.6665 | I25: 4529.714 | J25: 4520.653 | K25: 4486.189
A26: 4001190110 | B26: 비유동생물자산(*) | C26: 백만원
A27: 4001190120 | B27: 투자부동산(*) | C27: 백만원
A28: 4001190130 | B28: 장기금융자산(*) | C28: 백만원 | D28: 215.164 | E28: 56.935 | F28: 2 | G28: 72.71118 | H28: 12.01097 | I28: 220.30888 | J28: 237.19915 | K28: 21.97304
A29: 4001111660 | B29: 관계기업등지분관련투자자산(*) | C29: 백만원 | H29: 2820.8314 | I29: 2761.9779 | J29: 2655.4755 | K29: 2593.4955
A30: 4001190160 | B30: 장기매출채권및기타비유동채권(*) | C30: 백만원 | D30: 1724.932 | E30: 4933.905 | F30: 4855.764 | G30: 4868.6076 | H30: 4857.0072 | I30: 9789.4128 | J30: 9876.5982 | K30: 9229.9447
A31: 4001112490 | B31: 이연법인세자산 | C31: 백만원 | D31: 10895.114 | E31: 17845.452 | F31: 16171.142 | G31: 19048.132 | H31: 18096.613 | I31: 15510.139 | J31: 19445.185 | K31: 24302.742
A32: 4001112500 | B32: 장기당기법인세자산 | C32: 백만원
A33: 4001180575 | B33: 계약자산(**) | C33: 백만원
A34: 4001112503 | B34: 반품(환불)자산 | C34: 백만원
A35: 4001112504 | B35: 배출권 | C35: 백만원
A36: 4001190200 | B36: 기타비유동자산(*) | C36: 백만원 | D36: 4680.34 | E36: 26623.242 | F36: 23008.68 | G36: 25681.927 | H36: 23799.169 | I36: 24309.777 | J36: 25830.146 | K36: 22601.959
A37: 4001112880 | B37: 기타금융업자산 | C37: 백만원
A38: 4001190440 | B38: 부채(*) | C38: 백만원 | D38: 263676.67 | E38: 337598.88 | F38: 416651.3 | G38: 448045.03 | H38: 424204.2 | I38: 378693.41 | J38: 518342.38 | K38: 391868.84
A39: 4001190610 | B39: 유동부채(*) | C39: 백만원 | D39: 221843.98 | E39: 313608.13 | F39: 387790.35 | G39: 410848.05 | H39: 385699.29 | I39: 342617.75 | J39: 476464.19 | K39: 354776.17
A40: 4001181470 | B40: 단기사채(**) | C40: 백만원
A41: 4001121700 | B41: 단기차입금(*) | C41: 백만원 | D41: 21855 | E41: 45346 | F41: 127956.49 | G41: 71969.153 | H41: 46319.6 | K41: 2712.8
A42: 4001190620 | B42: 유동성장기부채(*) | C42: 백만원 | E42: 30000
A43: 4001190630 | B43: 유동금융부채(*) | C43: 백만원 | D43: 2499.1041 | E43: 5779.5403 | F43: 5999.7222 | G43: 7916.3184 | H43: 8024.916 | I43: 8088.0558 | J43: 8466.2816 | K43: 8353.3228
A44: 4001190660 | B44: 매입채무및기타유동채무(*) | C44: 백만원 | D44: 98441.472 | E44: 122068.92 | F44: 146485.82 | G44: 183448.5 | H44: 177611.75 | I44: 183849.01 | J44: 302370.43 | K44: 182483.75
A45: 4001190680 | B45: 유동종업원급여충당부채(*) | C45: 백만원
A46: 4001122460 | B46: 기타단기충당부채(*) | C46: 백만원 | D46: 23735.812 | E46: 9958.2823 | F46: 7800.2728 | G46: 10709.57 | H46: 9597.3408 | I46: 11061.715 | J46: 10708.908 | K46: 10462.455
A47: 4001122560 | B47: 당기법인세부채(미지급법인세) | C47: 백만원 | D47: 20789.983 | E47: 33951.61 | F47: 32500.616 | G47: 40001.024 | H47: 29250.676 | I47: 34604.602 | J47: 45403.041 | K47: 48266.239
A48: 4001122561 | B48: 계약부채 | C48: 백만원 | D48: 50610.483 | E48: 65184.432 | F48: 62793.719 | G48: 95913.921 | H48: 114205.86 | I48: 104218.76 | J48: 108976.81 | K48: 102249.13
A49: 4001122562 | B49: 반품(환불)부채 | C49: 백만원
A50: 4001122563 | B50: 배출부채 | C50: 백만원
A51: 4001190690 | B51: 기타유동부채(*) | C51: 백만원 | D51: 3912.1264 | E51: 1319.3412 | F51: 4253.7029 | G51: 889.56472 | H51: 689.1494 | I51: 795.60471 | J51: 538.719 | K51: 248.48457
A52: 4001122680 | B52: 매각예정으로분류된처분자산집단에포함된부채(*) | C52: 백만원
A53: 4001190450 | B53: 비유동부채(*) | C53: 백만원 | D53: 41832.688 | E53: 23990.752 | F53: 28860.95 | G53: 37196.976 | H53: 38504.907 | I53: 36075.655 | J53: 41878.192 | K53: 37092.662
A54: 4001190460 | B54: 사채(*) | C54: 백만원
A55: 4001190470 | B55: 장기차입금(*) | C55: 백만원 | D55: 30000
A56: 4001190480 | B56: 비유동금융부채(*) | C56: 백만원 | D56: 2305.6862 | E56: 14054.586 | F56: 11835.065 | G56: 14809.127 | H56: 13645.471 | I56: 12682.092 | J56: 14665.055 | K56: 12906.747
A57: 4001190500 | B57: 장기매입채무및기타비유동채무(*) | C57: 백만원 | F57: 331.25909 | G57: 530.179 | H57: 621.98502 | I57: 707.32895 | J57: 784.41617 | K57: 861.40615
A58: 4001190570 | B58: 비유동종업원급여충당부채(*) | C58: 백만원 | D58: 1857.3304 | E58: 588.60317 | F58: 630.05076 | G58: 863.80166 | H58: 996.50074 | I58: 32.93827 | J58: 43.18315 | K58: 47.55397
A59: 4001121280 | B59: 기타장기충당부채(*) | C59: 백만원 | D59: 7669.6711 | E59: 9347.5628 | F59: 4678.2576 | G59: 4858.596 | H59: 4984.6176 | I59: 4234.1894 | J59: 4210.5897 | K59: 3447.4896
A60: 4001121380 | B60: 이연법인세부채 | C60: 백만원
A61: 4001181370 | B61: 장기당기법인세부채(미지급법인세)(**) | C61: 백만원
A62: 4001121401 | B62: 계약부채 | C62: 백만원 | F62: 11386.317 | G62: 16135.272 | H62: 18256.333 | I62: 18419.107 | J62: 22174.948 | K62: 19829.466
A63: 4001121402 | B63: 반품(환불)부채 | C63: 백만원
A64: 4001121403 | B64: 배출부채 | C64: 백만원
A65: 4001190580 | B65: 기타비유동부채(*) | C65: 백만원
A66: 4001121620 | B66: 기타금융업부채 | C66: 백만원
A67: 4001190380 | B67: 자본(*) | C67: 백만원 | D67: 154871.15 | E67: 182216.88 | F67: 239966.85 | G67: 634461.44 | H67: 668248.19 | I67: 773534.56 | J67: 715610.66 | K67: 728279.49
A68: 4001130010 | B68: *수권주식수 | C68: 주 | D68: 20000000 | E68: 200000000 | F68: 200000000 | G68: 200000000 | H68: 200000000 | I68: 200000000 | J68: 200000000 | K68: 200000000
A69: 4001130020 | B69: *주당액면가액 | C69: 원 | D69: 5000 | E69: 500 | F69: 500 | G69: 500 | H69: 500 | I69: 500 | J69: 500 | K69: 500
A70: 4001130030 | B70: *발행한주식총수(*) | C70: 주 | D70: 4000000 | E70: 40000000 | F70: 40000000 | G70: 44450000 | H70: 44450000 | I70: 44450000 | J70: 44829210 | K70: 44829210
A71: 4001130040 | B71: *보통주 | C71: 주 | D71: 4000000 | E71: 40000000 | F71: 40000000 | G71: 44450000 | H71: 44450000 | I71: 44450000 | J71: 44829210 | K71: 44829210
A72: 4001130050 | B72: *우선주 | C72: 주
A73: 4001190390 | B73: 지배기업주주지분(*) | C73: 백만원 | D73: 154871.15 | E73: 182216.88 | F73: 239966.85 | G73: 634461.44 | H73: 668248.19 | I73: 773534.56 | J73: 715610.66 | K73: 728279.49
A74: 4001130070 | B74: 자본금(*) | C74: 백만원 | D74: 20000 | E74: 20000 | F74: 20000 | G74: 22225 | H74: 22225 | I74: 22225 | J74: 22414.605 | K74: 22414.605
A75: 4001130670 | B75: 신종자본증권 | C75: 백만원
A76: 4001190400 | B76: 자본잉여금(*) | C76: 백만원 | D76: 20000 | E76: 20000 | F76: 20000 | G76: 384624.03 | H76: 384624.03 | I76: 384624.03 | J76: 404355.79 | K76: 404355.79
A77: 4001190420 | B77: 기타자본(*) | C77: 백만원 | F77: 510.84298 | G77: 778.17335 | H77: 891.45101 | I77: 29503.673 | J77: 9580.3591 | K77: 9580.3591
A78: 4001130360 | B78: 기타포괄손익누계액(*) | C78: 백만원 | D78: 1585.4048 | E78: 2600.349 | F78: 1097.5643 | G78: 7471.4276 | H78: 2618.2302 | I78: 13654.788 | J78: 13453.516 | K78: 4505.7361
A79: 4001130470 | B79: 이익잉여금(결손금)(*) | C79: 백만원 | D79: 113285.75 | E79: 139616.53 | F79: 198358.44 | G79: 219362.81 | H79: 257889.48 | I79: 323527.07 | J79: 265806.39 | K79: 287423
A80: 4001130640 | B80: 비지배주주지분 | C80: 백만원

Sheet CF(Quaterly)
A1: Financial Statements
A2: Company | B2: A443060(HD현대마린솔루션) - Fiscal Month:12, 201712부터 IFRS 적용
A3: Type | B3: 연결 | C3: Accounting Std. | D3: IFRS
A4: Report | B4: 현금흐름표 | C4: New
A5: Form | B5: 약식(COMPARE)
A6: Output | B6: 결산 | C6: 백만원
A7: Fiscal Year | B7: 2021 | C7: Current
A8: 계정코드 | B8: 계정명 | C8: 단위 | D8: 202112 | E8: 202212 | F8: 202312 | G8: 202406 | H8: 202409 | I8: 202412 | J8: 202503 | K8: 202506
D9: IFRS(연결) | E9: IFRS(연결) | F9: IFRS(연결) | G9: IFRS(연결) | H9: IFRS(연결) | I9: IFRS(연결) | J9: IFRS(연결) | K9: IFRS(연결)
A10: 4001390000 | B10: 영업활동으로인한현금흐름(간접법)(*) | C10: 백만원 | D10: 68373.45 | E10: 51538.089 | F10: 72858.14 | G10: 48975.941 | H10: 80886.639 | I10: 37322.583 | J10: 98176.791 | K10: 57778.409
A11: 4001310010 | B11: *(직접법)총현금유입(*) | C11: 백만원
A12: 4001310100 | B12: *(직접법)총현금유출(*) | C12: 백만원
A13: 4001310190 | B13: 당기순손익 | C13: 백만원 | D13: 89563.978 | E13: 104926.51 | F13: 151116.18 | G13: 56679.2 | H13: 58529.167 | I13: 68406.742 | J13: 63318.186 | K13: 52997.054
A14: 4001310200 | B14: 법인세비용차감전계속사업이익 | C14: 백만원
A15: 4001390010 | B15: 현금유출이없는비용등가산(*) | C15: 백만원 | D15: 46141.026 | E15: 71780.663 | F15: 79369.567 | G15: 28537.202 | H15: 27170.755 | I15: 26272.156 | J15: 29593.827 | K15: 26855.284
A16: 4001390040 | B16: (현금유입이없는수익등차감)(*) | C16: 백만원 | D16: 3413.964 | E16: 4195.705 | F16: 9643.741 | G16: -301.864 | H16: 3242.982 | I16: 13973.221 | J16: 9600.851 | K16: 5345.329
A17: 4001390060 | B17: 영업활동으로인한자산부채변동(운전자본변동)(*) | C17: 백만원 | D17: -24087.659 | E17: -88286.661 | F17: -96512.663 | G17: -9525.5822 | H17: 23386.299 | I17: -45200.475 | J17: 23055.745 | K17: -2744.1655
A18: 4001390070 | B18: 자산의감소(증가)(*) | C18: 백만원 | D18: 430.871 | E18: -98377.209 | F18: -124449.07 | G18: -33628.433 | H18: -1169.176 | I18: -9498.774 | J18: 16346.586 | K18: -10284.579
A19: 4001390110 | B19: 부채의증가(감소)(*) | C19: 백만원 | D19: -24518.53 | E19: 10090.548 | F19: 27936.408 | G19: 24102.851 | H19: 24555.474 | I19: -35701.7 | J19: 6709.159 | K19: 7540.414
A20: 4001312260 | B20: 정부보조금등의변동 | C20: 백만원
A21: 4001312270 | B21: 기타운전자본의변동 | C21: 백만원
A22: 4001312280 | B22: *영업에서창출된현금흐름 | C22: 백만원 | D22: 108203.38 | E22: 84224.805 | F22: 124329.34 | G22: 75992.684 | H22: 105843.24 | I22: 35505.203 | J22: 106366.91 | K22: 71762.843
A23: 4001312290 | B23: 이자수입 | C23: 백만원 | D23: 1029.9497 | E23: 831.3163 | F23: 2452.5653 | G23: 1757.6824 | H23: 2957.2922 | I23: 2880.2907 | J23: 5712.8179 | K23: 3420.9477
A24: 4001312300 | B24: 이자지급(-) | C24: 백만원 | D24: -563.80537 | E24: -2200.2935 | F24: -5106.5212 | G24: -1604.8695 | H24: -357.8728 | I24: -463.10238 | J24: -283.20455 | K24: -287.57596
A25: 4001312310 | B25: 배당금수입 | C25: 백만원 | D25: 145.55232
A26: 4001312320 | B26: 배당금지급(-) | C26: 백만원
A27: 4001312330 | B27: 법인세환입 | C27: 백만원
A28: 4001312340 | B28: 법인세납부(-) | C28: 백만원 | D28: -40441.626 | E28: -31317.738 | F28: -48817.243 | G28: -27169.558 | H28: -27556.019 | I28: -599.81115 | J28: -13619.729 | K28: -17117.806
A29: 4001312350 | B29: 중단영업관련현금흐름 | C29: 백만원
A30: 4001390160 | B30: 투자활동으로인한현금흐름(*) | C30: 백만원 | D30: 64767.534 | E30: -13410.147 | F30: 4737.8244 | G30: -129530.39 | H30: -130593.67 | I30: 66259.986 | J30: 61238.078 | K30: -83764.121
A31: 4001390170 | B31: 투자활동으로인한현금유입액(*) | C31: 백만원 | D31: 81190.709 | E31: 632.21465 | F31: 7918.2017 | G31: 47.17008 | H31: 38.42899 | I31: 61.36455 | J31: 105000 | K31: 17175.438
A32: 4001390270 | B32: (투자활동으로인한현금유출액)(*) | C32: 백만원 | D32: 16423.176 | E32: 14042.362 | F32: 3180.3774 | G32: 129577.56 | H32: 130632.1 | I32: -66198.621 | J32: 43761.922 | K32: 100939.56
A33: 4001321350 | B33: 이자수입 | C33: 백만원
A34: 4001321360 | B34: 이자지급(-) | C34: 백만원
A35: 4001321370 | B35: 배당금수입 | C35: 백만원
A36: 4001321380 | B36: 배당금지급(-) | C36: 백만원
A37: 4001321390 | B37: 법인세환입 | C37: 백만원
A38: 4001321400 | B38: 법인세납부(-) | C38: 백만원
A39: 4001321410 | B39: 중단영업관련현금흐름 | C39: 백만원
A40: 4001390370 | B40: 재무활동으로인한현금흐름(*) | C40: 백만원 | D40: -141539 | E40: -60582.163 | F40: -43910.643 | G40: 222645.97 | H40: -47600.294 | I40: -29541.571 | J40: -2004.3083 | K40: -151633.73
A41: 4001390380 | B41: 재무활동으로인한현금유입액(*) | C41: 백만원 | D41: 81199.12 | E41: 42379.25 | F41: 175222.59 | G41: 372151.23 | H41: 40000 | I41: 19233.296 | K41: 5568.966
A42: 4001390470 | B42: (재무활동으로인한현금유출액)(*) | C42: 백만원 | D42: 32738.124 | E42: 22961.413 | F42: 129133.24 | G42: 69505.263 | H42: 67597.794 | I42: 48774.867 | J42: 2004.3083 | K42: 4783.3868
A43: 4001330680 | B43: 이자수입 | C43: 백만원
A44: 4001330690 | B44: 이자지급(-) | C44: 백만원
A45: 4001330700 | B45: 배당금수입 | C45: 백만원
A46: 4001330710 | B46: 배당금지급(-) | C46: 백만원 | D46: -190000 | E46: -80000 | F46: -90000 | G46: -80000 | H46: -20002.5 | K46: -152419.31
A47: 4001330720 | B47: 법인세환입 | C47: 백만원
A48: 4001330730 | B48: 법인세납부(-) | C48: 백만원
A49: 4001330740 | B49: 중단영업관련현금흐름 | C49: 백만원
A50: 4001340000 | B50: 영업투자재무활동기타현금흐름 | C50: 백만원
A51: 4001340010 | B51: 연결범위변동으로인한현금의증가 | C51: 백만원
A52: 4001340020 | B52: 환율변동효과 | C52: 백만원 | D52: 675.49593 | E52: 17.02282 | F52: -1524.7757 | G52: 948.74136 | H52: -1416.0382 | I52: 2419.5332 | J52: -106.85819 | K52: -2372.4208
A53: 4001340030 | B53: 현금및현금성자산의증가 | C53: 백만원 | D53: -7722.5241 | E53: -22437.199 | F53: 32160.545 | G53: 143040.26 | H53: -98723.361 | I53: 76460.531 | J53: 157303.7 | K53: -179991.87
A54: 4001340040 | B54: 기초현금및현금성자산 | C54: 백만원 | D54: 93711.199 | E54: 85988.675 | F54: 63551.476 | G54: 177688.65 | H54: 320728.9 | I54: 222005.54 | J54: 298466.07 | K54: 455769.77
A55: 4001340050 | B55: 기말현금및현금성자산 | C55: 백만원 | D55: 85988.675 | E55: 63551.476 | F55: 95712.021 | G55: 320728.9 | H55: 222005.54 | I55: 298466.07 | J55: 455769.77 | K55: 275777.91
